Workbook
Name \A: #REF!
Name \B: #REF!
Name \C: #REF!
Name \L: #REF!
Name \M: #REF!
Name \P: #REF!
Name \Y: #REF!
Name _01_30_04: MonthlyOpStats
Name _01_30_04: MonthlyOpStats
Name _1_30_01: MonthlyOpStats
Name _1_30_01: MonthlyOpStats
Name _1_30_02: MonthlyOpStats
Name _1_30_02: MonthlyOpStats
Name _1_31_01: MonthlyOpStats
Name _1_31_01: MonthlyOpStats
Name _1_31_02: MonthlyOpStats
Name _1_31_02: MonthlyOpStats
Name _12_31_05: MonthlyOpStats
Name _12_31_05: MonthlyOpStats
Name _A: #REF!
Name _A___0: #REF!
Name _B: #REF!
Name _B___0: #REF!
Name _C: #REF!
Name _C___0: #REF!
Name _ent1: [1]Inputs!$J$17
Name _ent10: [1]Inputs!$J$476
Name _ent11: [1]Inputs!$J$527
Name _ent12: [1]Inputs!$J$578
Name _ent13: [1]Inputs!$J$629
Name _ent14: [1]Inputs!$J$680
Name _ent15: [1]Inputs!$J$731
Name _ent2: [1]Inputs!$J$68
Name _ent3: [1]Inputs!$J$119
Name _ent4: [1]Inputs!$J$170
Name _ent5: [1]Inputs!$J$221
Name _ent6: [1]Inputs!$J$272
Name _ent7: [1]Inputs!$J$323
Name _ent8: [1]Inputs!$J$374
Name _ent9: [1]Inputs!$J$425
Name _eps1: [1]Inputs!$P$42
Name _eps10: [1]Inputs!$P$501
Name _eps11: [1]Inputs!$P$552
Name _eps12: [1]Inputs!$P$603
Name _eps13: [1]Inputs!$P$654
Name _eps14: [1]Inputs!$P$705
Name _eps15: [1]Inputs!$P$756
Name _eps2: [1]Inputs!$P$93
Name _eps3: [1]Inputs!$P$144
Name _eps4: [1]Inputs!$P$195
Name _eps5: [1]Inputs!$P$246
Name _eps6: [1]Inputs!$P$297
Name _eps7: [1]Inputs!$P$348
Name _eps8: [1]Inputs!$P$399
Name _eps9: [1]Inputs!$P$450
Name _fye1: [1]Inputs!$E$12
Name _fye10: [1]Inputs!$E$471
Name _fye11: [1]Inputs!$E$522
Name _fye12: [1]Inputs!$E$573
Name _fye13: [1]Inputs!$E$624

Sheet Capitalisation
A3: 1Q26 | I3: Exchange rate as at end 1Q26 | J3: =Model!K$204 -> 0.14494854
I4: LTM Average exchange rate 1Q26 | J4: =Model!K$205 -> 0.14097399
B6: Debt Breakdown as on 31-Mar-2026 | C6: RMB millions | D6: Leverage | E6: USD mn | F6: Leverage
B8: Included in non-current liabilities | C8: =SUM(C9:C12) -> 25006.733 | E8: =SUM(E9:E12) -> 3624.6895
B9: Asset-backed securities | C9: 0 | E9: =C9*J3 -> 0
B10: Secured borrowings | C10: 1718.799 | E10: =C10*J3 -> 249.13741
B11: Unsecured borrowings | C11: 18188.172 | E11: =C11*J3 -> 2636.349
B12: Convertible bonds | C12: 5099.762 | E12: =C12*J3 -> 739.20307
B14: Included in current liabilities | C14: =SUM(C15:C18) -> 10360.504 | E14: =SUM(E15:E18) -> 1501.74
B15: Asset-backed securities | C15: 0 | E15: =C15*J3 -> 0
B16: Secured borrowings | C16: 73.134 | E16: =C16*J3 -> 10.600667
B17: Unsecured borrowings | C17: 10287.37 | E17: =C17*J3 -> 1491.1393
B18: Convertible bonds | C18: 0 | E18: =C18*J3 -> 0
B20: Lease Obligations | C20: =SUM(C21:C22) -> 0 | E20: =SUM(E21:E22) -> 0
B21: Short-term | C21: =Model!AK$112 -> 0 | E21: =C21*J3 -> 0
B22: Long-term | C22: =Model!AK$113 -> 0 | E22: =C22*J3 -> 0
B24: Total Loans & Borrowings | C24: =C14+C8+C20 -> 35367.237 | D24: =C24/C29 -> 0.71487752 | E24: =E14+E8+E20 -> 5126.4295 | F24: =E24/E29 -> 0.73503243
B25: Cash and Cash Equivalents | C25: =Model!AK$120 -> 98225.411 | E25: =C25*J3 -> 14237.63
B26: Net debt | C26: =C24-C25 -> -62858.174 | D26: =C26/C29 -> -1.2705515 | E26: =E24-E25 -> -9111.2008 | F26: =E26/E29 -> -1.3063728
B27: Equity | C27: =Model!AK$124 -> 266033.92 | E27: =C27*J3 -> 38561.23
B28: Total Capitalisation | C28: =C26+C27 -> 203175.75 | E28: =E26+E27 -> 29450.029
B29: LTM Adjusted EBITDA | C29: =Model!AK$87 -> 49473.142 | E29: =C29*J4 -> 6974.4263
B30: check | C30: =+C24-Model!AK$119 -> 0
B33: Liquidity at 1Q26 | C33: RMB millions | D33: USD mn
B34: Short-term investments measured at amortized cost | C34: 200 | D34: =C34*J3 -> 28.989709
B35: Short-term investments measured at fair value through profit or loss | C35: 18247.657 | D35: =C35*J3 -> 2644.9713
B36: Term bank deposits | C36: 53443.271 | D36: =C36*J3 -> 7746.5243
B37: Cash and cash equivalents | C37: 26334.483 | D37: =C37*J3 -> 3817.1449
B38: Total liquidity | C38: =SUM(C34:C37) -> 98225.411 | D38: =SUM(D34:D37) -> 14237.63
B39: check | C39: =C38-C25 -> 0
B42: Debt Maturity (from BBG) | C42: RMB mn | D42: USD mn
B43: 2027 | C43: 6419.95 | D43: =C43*J3 -> 930.5624
B44: 2029 | C44: 1000 | D44: =C44*J3 -> 144.94854
B45: 2030 | C45: 4077.19 | D45: =C45*J3 -> 590.98275
B46: 2031+ | C46: =5346.26+2718.13 -> 8064.39 | D46: =C46*J3 -> 1168.9216
B47: Total | C47: =SUM(C43:C46) -> 19561.53 | D47: =SUM(D43:D46) -> 2835.4153
A51: FY25 | I51: Exchange rate as at end | J51: =Model!$K$204 -> 0.14494854
I52: LTM Average exchange rate | J52: =Model!K$205 -> 0.14097399
B54: Debt Breakdown as on 31-Dec-2025 | C54: RMB millions | D54: Leverage (RMB) | E54: USD mn | F54: Leverage (USD)
B56: Included in non-current liabilities | C56: =SUM(C57:C60) -> 22921.433 | E56: =SUM(E57:E60) -> 3322.4283
B57: Asset-backed securities | C57: 0 | E57: =C57*J51 -> 0
B58: Secured borrowings | C58: 1754.255 | E58: =C58*J51 -> 254.27671
B59: Unsecured borrowings | C59: 16046.323 | E59: =C59*J51 -> 2325.8911
B60: Convertible bonds | C60: 5120.855 | E60: =C60*J51 -> 742.26047
B62: Included in current liabilities | C62: =SUM(C63:C66) -> 13202.226 | E62: =SUM(E63:E66) -> 1913.6434
B63: Asset-backed securities | C63: 0 | E63: =C63*J51 -> 0
B64: Secured borrowings | C64: 73.094 | E64: =C64*J51 -> 10.594869
B65: Unsecured borrowings | C65: 13129.132 | E65: =C65*J51 -> 1903.0486
B66: Convertible bonds | C66: 0 | E66: =C66*J51 -> 0
B68: Lease Obligations | C68: =SUM(C69:C70) -> 5714.237 | E68: =SUM(E69:E70) -> 828.27033
B69: Short-term | C69: =Model!AJ$112 -> 2079.368 | E69: =C69*J51 -> 301.40136
B70: Long-term | C70: =Model!AJ$113 -> 3634.869 | E70: =C70*J51 -> 526.86897
B72: Total Loans & Borrowings | C72: =C62+C56+C68 -> 41837.896 | D72: =C72/C77 -> 0.73843309 | E72: =E62+E56+E68 -> 6064.3421 | F72: =E72/E77 -> 0.75925211
B73: Cash and Cash Equivalents | C73: =Model!AJ$120 -> 107696.59 | E73: =C73*J51 -> 15610.464
B74: Net debt | C74: =C72-C73 -> -65858.693 | D74: =C74/C77 -> -1.1623968 | E74: =E72-E73 -> -9546.1216 | F74: =E74/E77 -> -1.1951689
B75: Equity | C75: =Model!AJ$124 -> 266323.27 | E75: =C75*J51 -> 38603.17
B76: Total Capitalisation | C76: =C74+C75 -> 200464.58 | E76: =E74+E75 -> 29057.048
B77: LTM Adjusted EBITDA | C77: =Model!AJ$87 -> 56657.667 | E77: =C77*J52 -> 7987.2575
B78: check | C78: =+C72-Model!AJ$119 -> 0
B81: Liquidity at FY25 | C81: RMB millions | D81: USD mn
B82: Short-term investments measured at amortized cost | C82: 200 | D82: =C82*J51 -> 28.989709
B83: Short-term investments measured at fair value through profit or loss | C83: 29273.546 | D83: =C83*J51 -> 4243.1578
B84: Term bank deposits | C84: 51308.666 | D84: =C84*J51 -> 7437.1164
B85: Cash and cash equivalents | C85: 26914.377 | D85: =C85*J51 -> 3901.1997
B86: Total liquidity | C86: =SUM(C82:C85) -> 107696.59 | D86: =SUM(D82:D85) -> 15610.464
B89: Debt Maturity (from BBG) | C89: RMB mn | D89: USD mn
B90: 2027 | C90: 6506.39 | D90: =C90*J51 -> 943.09175
B91: 2030 | C91: 4142.22 | D91: =C91*J51 -> 600.40875
B92: 2031 | C92: 5522.95 | D92: =C92*J51 -> 800.54356
B93: 2032+ | C93: 2761.48 | D93: =C93*J51 -> 400.2725
B94: Total | C94: =SUM(C90:C93) -> 18933.04 | D94: =SUM(D90:D93) -> 2744.3166
A99: 3Q25 | I99: Exchange rate as at end 3Q25 | J99: =Model!K$204 -> 0.14494854
I100: LTM Average exchange rate 3Q25 | J100: =Model!K$205 -> 0.14097399
B102: Debt Breakdown as on 30-Sep-2025 | C102: RMB millions | D102: Leverage | E102: USD mn | F102: Leverage | I102: Cash Breakdown as on 30-Sep-2025 | J102: RMB millions
I103: Cash and Cash Equivalents | J103: 35547.957
B104: Included in non-current liabilities | C104: =SUM(C105:C108) -> 9588.872 | E104: =SUM(E105:E108) -> 1389.893 | I104: Short-term Investments and bank deposits | J104: =19383.757+55218.606 -> 74602.363
B105: Asset-backed securities | C105: 0 | E105: =C105*J99 -> 0 | I105: Total | J105: =SUM(J103:J104) -> 110150.32
B106: Secured borrowings | C106: 73.095 | E106: =C106*J99 -> 10.595014 | I106: Check | J106: =J105-C121 -> 0
B107: Unsecured borrowings | C107: 4399.164 | E107: =C107*J99 -> 637.65241
B108: Convertible bonds | C108: 5116.613 | E108: =C108*J99 -> 741.6456
B110: Included in current liabilities | C110: =SUM(C111:C114) -> 18000.079 | E110: =SUM(E111:E114) -> 2609.0852
B111: Asset-backed securities | C111: 0 | E111: =C111*J99 -> 0
B112: Secured borrowings | C112: 1754.27 | E112: =C112*J99 -> 254.27888
B113: Unsecured borrowings | C113: 16245.809 | E113: =C113*J99 -> 2354.8063
B114: Convertible bonds | C114: 0 | E114: =C114*J99 -> 0
B116: Lease Obligations | C116: =SUM(C117:C118) -> 0 | E116: =SUM(E117:E118) -> 0
B117: Short-term | C117: =Model!AI$112 -> 0 | E117: =C117*J99 -> 0
B118: Long-term | C118: =Model!AI$113 -> 0 | E118: =C118*J99 -> 0
B120: Total Loans & Borrowings | C120: =C110+C104+C116 -> 27588.951 | D120: =C120/C125 -> 0.47247453 | E120: =E110+E104+E116 -> 3998.9783 | F120: =E120/E125 -> 0.48579525
B121: Cash and Cash Equivalents | C121: =Model!AI$120 -> 110150.32 | E121: =C121*J99 -> 15966.128
B122: Net debt | C122: =C120-C121 -> -82561.369 | D122: =C122/C125 -> -1.4139046 | E122: =E120-E121 -> -11967.15 | F122: =E122/E125 -> -1.4537675
B123: Equity | C123: =Model!AI$124 -> 265563.37 | E123: =C123*J99 -> 38493.023
B124: Total Capitalisation | C124: =C122+C123 -> 183002 | E124: =E122+E123 -> 26525.873
B125: LTM Adjusted EBITDA | C125: =Model!AI$87 -> 58392.462 | E125: =C125*J100 -> 8231.8184
B126: check | C126: =+C120-Model!AI$119 -> 0
B129: Liquidity at 3Q25 | C129: RMB millions | E129: USD mn
B130: Cash and Cash Equivalents | C130: =C121 -> 110150.32 | E130: =E121 -> 15966.128
B131: Total liquidity | C131: =SUM(C130:C130) -> 110150.32 | E131: =SUM(E130:E130) -> 15966.128
B133: Debt Maturity (from BBG) | C133: RMB mn | E133: USD mn
B134: 2027 | C134: 7078.92 | E134: =C134*J99 -> 1026.0791
...

Sheet Model
B2: Xiaomi Corporation | C2: Annual | D2: Annual | E2: Annual | F2: Annual | G2: Annual | H2: Annual | I2: Annual | J2: Annual | K2: LTM | M2: Quarters | N2: Quarters | O2: Quarters | P2: Quarters | Q2: Quarters | R2: Quarters | S2: Quarters | T2: Quarters | U2: Quarters | V2: Quarters | W2: Quarters | X2: Quarters | Y2: Quarters | Z2: Quarters | AA2: Quarters | AB2: Quarters | AC2: Quarters | AD2: Quarters | AE2: Quarters | AF2: Quarters | AG2: Quarters | AH2: Quarters | AI2: Quarters | AJ2: Quarters | AK2: Quarters
B3: (RMB millions) | C3: 43465 | D3: 43830 | E3: 44196 | F3: 44561 | G3: 44926 | H3: 45291 | I3: 45657 | J3: 46022 | K3: =AK3 -> 46112 | M3: 43921 | N3: 44012 | O3: 44104 | P3: 44196 | Q3: 44286 | R3: 44377 | S3: 44469 | T3: 44561 | U3: 44651 | V3: 44742 | W3: 44834 | X3: 44926 | Y3: 45016 | Z3: 45107 | AA3: 45199 | AB3: 45291 | AC3: 45382 | AD3: 45473 | AE3: 45565 | AF3: 45657 | AG3: 45747 | AH3: 45838 | AI3: 45930 | AJ3: 46022 | AK3: 46112
C4: Act | D4: Act | E4: Act | F4: Act | G4: Act | H4: Act | I4: Act | J4: Act | K4: Act | M4: Act | N4: Act | O4: Act | P4: Act | Q4: Act | R4: Act | S4: Act | T4: Act | U4: Act | V4: Act | W4: Act | X4: Act | Y4: Act | Z4: Act | AA4: Act | AB4: Act | AC4: Act | AD4: Act | AE4: Act | AF4: Act | AG4: Act | AH4: Act | AI4: Act | AJ4: Act | AK4: Act
C5: FY | D5: FY | E5: FY | F5: FY | G5: FY | H5: FY | I5: FY | J5: FY | K5: LTM | M5: 1Q | N5: 2Q | O5: 3Q | P5: 4Q | Q5: 1Q | R5: 2Q | S5: 3Q | T5: 4Q | U5: 1Q | V5: 2Q | W5: 3Q | X5: 4Q | Y5: 1Q | Z5: 2Q | AA5: 3Q | AB5: 4Q | AC5: 1Q | AD5: 2Q | AE5: 3Q | AF5: 4Q | AG5: 1Q | AH5: 2Q | AI5: 3Q | AJ5: 4Q | AK5: 1Q
B6: INCOME STATEMENT
B7: Revenue | C7: 174915.42 | D7: 205838.68 | E7: 245865.63 | F7: 328309.15 | G7: 280044.02 | H7: 270970.1 | I7: 365906.35 | J7: 457286.69 | K7: =SUM(AH7:AK7) -> 445134.97 | M7: 49702.167 | N7: 53537.805 | O7: 72162.777 | P7: =E7-SUM(M7:O7) -> 70462.884 | Q7: 76882.163 | R7: 87788.96 | S7: 78062.855 | T7: =F7-SUM(Q7:S7) -> 85575.167 | U7: 73351.502 | V7: 70170.877 | W7: 70474.269 | X7: =G7-SUM(U7:W7) -> 66047.368 | Y7: 59477.134 | Z7: 67354.908 | AA7: 70894.412 | AB7: =H7-SUM(Y7:AA7) -> 73243.646 | AC7: 75506.822 | AD7: 88887.828 | AE7: 92506.541 | AF7: =I7-SUM(AC7:AE7) -> 109005.16 | AG7: 111293.34 | AH7: 115956.09 | AI7: 113120.73 | AJ7: =J7-SUM(AG7:AI7) -> 116916.52 | AK7: 99141.618
B8: % of growth | D8: =(D7/C7)-1 -> 0.17678977 | E8: =(E7/D7)-1 -> 0.19445787 | F8: =(F7/E7)-1 -> 0.33531938 | G8: =(G7/F7)-1 -> -0.14701122 | H8: =(H7/G7)-1 -> -0.032401749 | I8: =(I7/H7)-1 -> 0.35035692 | J8: =(J7/I7)-1 -> 0.24973695 | Q8: =(Q7/M7)-1 -> 0.54685736 | R8: =(R7/N7)-1 -> 0.63975643 | S8: =(S7/O7)-1 -> 0.081760684 | T8: =(T7/P7)-1 -> 0.21447154 | U8: =(U7/Q7)-1 -> -0.045923019 | V8: =(V7/R7)-1 -> -0.20068677 | W8: =(W7/S7)-1 -> -0.097211228 | X8: =(X7/T7)-1 -> -0.22819469 | ... AK8: =(AK7/AG7)-1 -> -0.1091864
B9: Cost of revenues | C9: -152723.49 | D9: -177284.65 | E9: -209113.77 | F9: -270048.2 | G9: -232466.83 | H9: -213493.9 | I9: -289346.16 | J9: -355480.84 | K9: =SUM(AH9:AK9) -> -346924.91 | M9: -42143.71 | N9: -45836.359 | O9: -61997.121 | P9: =E9-SUM(M9:O9) -> -59136.581 | Q9: -62720.932 | R9: -72640.918 | S9: -63770.634 | T9: =F9-SUM(Q9:S9) -> -70915.72 | U9: -60641.756 | V9: -58402.842 | W9: -58752.36 | X9: =G9-SUM(U9:W9) -> -54669.868 | Y9: -47885.567 | Z9: -53193.892 | AA9: -54784.701 | AB9: =H9-SUM(Y9:AA9) -> -57629.74 | AC9: -58677.105 | AD9: -70493.651 | AE9: -73625.131 | AF9: =I9-SUM(AC9:AE9) -> -86550.269 | AG9: -85887.427 | AH9: -89855.133 | AI9: -87184.568 | AJ9: =J9-SUM(AG9:AI9) -> -92553.712 | AK9: -77331.498
B10: Gross Profit | C10: =C7+C9 -> 22191.939 | D10: =D7+D9 -> 28554.033 | E10: =E7+E9 -> 36751.862 | F10: =F7+F9 -> 58260.941 | G10: =G7+G9 -> 47577.19 | H10: =H7+H9 -> 57476.2 | I10: =I7+I9 -> 76560.194 | J10: =J7+J9 -> 101805.85 | K10: =K7+K9 -> 98210.057 | M10: =M7+M9 -> 7558.457 | N10: =N7+N9 -> 7701.446 | O10: =O7+O9 -> 10165.656 | P10: =P7+P9 -> 11326.303 | Q10: =Q7+Q9 -> 14161.231 | R10: =R7+R9 -> 15148.042 | S10: =S7+S9 -> 14292.221 | T10: =T7+T9 -> 14659.447 | ... AK10: =AK7+AK9 -> 21810.12
B11: Gross Profit margin | C11: =C10/C7 -> 0.1268724 | D11: =D10/D7 -> 0.13872044 | E11: =E10/E7 -> 0.14947946 | F11: =F10/F7 -> 0.17745756 | G11: =G10/G7 -> 0.16989183 | H11: =H10/H7 -> 0.2121127 | I11: =I10/I7 -> 0.2092344 | J11: =J10/J7 -> 0.22263024 | K11: =K10/K7 -> 0.22062984 | M11: =M10/M7 -> 0.152075 | N11: =N10/N7 -> 0.14385061 | O11: =O10/O7 -> 0.14087119 | P11: =P10/P7 -> 0.16074141 | Q11: =Q10/Q7 -> 0.18419397 | R11: =R10/R7 -> 0.17255065 | S11: =S10/S7 -> 0.18308607 | T11: =T10/T7 -> 0.17130492 | ... AK11: =AK10/AK7 -> 0.21998955
B12: Operating expenses:
B13: Selling and marketing expenses | C13: -7993.072 | D13: -10378.073 | E13: -14539.4 | F13: -20980.765 | G13: -21323.323 | H13: -19226.5 | I13: -25389.628 | J13: -33214.338 | K13: =SUM(AH13:AK13) -> -34291.004 | M13: -2624.873 | N13: -3223.676 | O13: -3600.582 | P13: =E13-SUM(M13:O13) -> -5090.269 | Q13: -4163.475 | R13: -5680.659 | S13: -4882.314 | T13: =F13-SUM(Q13:S13) -> -6254.317 | U13: -5256.184 | V13: -5332.208 | W13: -4882.576 | X13: =G13-SUM(U13:W13) -> -5852.355 | Y13: -4103.864 | Z13: -4476.758 | AA13: -4736.265 | AB13: =H13-SUM(Y13:AA13) -> -5909.613 | AC13: -5481.047 | AD13: -5899.052 | AE13: -6280.146 | AF13: =I13-SUM(AC13:AE13) -> -7729.383 | AG13: -7199.817 | AH13: -7777.971 | AI13: -8309.653 | AJ13: =J13-SUM(AG13:AI13) -> -9926.897 | AK13: -8276.483
B14: Administrative expenses | C14: -12099.078 | D14: -3103.901 | E14: -3746.449 | F14: -4738.919 | G14: -5113.877 | H14: -5126.8 | I14: -5601.248 | J14: -6653.026 | K14: =SUM(AH14:AK14) -> -6753.317 | M14: -781.533 | N14: -836.426 | O14: -852.715 | P14: =E14-SUM(M14:O14) -> -1275.775 | Q14: -987.652 | R14: -1150.336 | S14: -1274.603 | T14: =F14-SUM(Q14:S14) -> -1326.328 | U14: -1244.573 | V14: -1315.404 | W14: -1255.393 | X14: =G14-SUM(U14:W14) -> -1298.507 | Y14: -1135.173 | Z14: -1143.19 | AA14: -1365.291 | AB14: =H14-SUM(Y14:AA14) -> -1483.146 | AC14: -1523.007 | AD14: -1182.524 | AE14: -1415.369 | AF14: =I14-SUM(AC14:AE14) -> -1480.348 | AG14: -1530.094 | AH14: -1627.144 | AI14: -1848.197 | AJ14: =J14-SUM(AG14:AI14) -> -1647.591 | AK14: -1630.385
B15: Research and development expenses | C15: -5776.826 | D15: -7492.554 | E15: -9256.139 | F15: -13167.088 | G15: -16028.132 | H15: -19097.7 | I15: -24050.484 | J15: -33132.201 | K15: =SUM(AH15:AK15) -> -35374.874 | M15: -1870.984 | N15: -1958.272 | O15: -2321.264 | P15: =E15-SUM(M15:O15) -> -3105.619 | Q15: -3011.991 | R15: -3064.176 | S15: -3237.695 | T15: =F15-SUM(Q15:S15) -> -3853.226 | U15: -3494.539 | V15: -3763.374 | W15: -4069.789 | X15: =G15-SUM(U15:W15) -> -4700.43 | Y15: -4113.36 | Z15: -4554.803 | AA15: -4966.22 | AB15: =H15-SUM(Y15:AA15) -> -5463.317 | AC15: -5159.387 | AD15: -5497.729 | AE15: -5956.784 | AF15: =I15-SUM(AC15:AE15) -> -7436.584 | AG15: -6711.708 | AH15: -7763.377 | AI15: -9059.373 | AJ15: =J15-SUM(AG15:AI15) -> -9597.743 | AK15: -8954.381
B16: Fair value changes on investments | C16: 4430.359 | D16: 3813.012 | E16: 13173.479 | F16: 8132.133 | G16: -1662.01 | H16: 3501.1 | I16: 1050.772 | J16: 13311.733 | K16: =SUM(AH16:AK16) -> 11333.228 | M16: 347.846 | N16: 2366.188 | O16: 3417.924 | P16: =E16-SUM(M16:O16) -> 7041.521 | Q16: 2063.207 | R16: 4165.419 | S16: -1975.634 | T16: =F16-SUM(Q16:S16) -> 3879.141 | U16: -3550.255 | V16: 513.577 | W16: -2390.854 | X16: =G16-SUM(U16:W16) -> 3765.522 | Y16: 3453.259 | Z16: -275.784 | AA16: -299.895 | AB16: =H16-SUM(Y16:AA16) -> 623.52 | AC16: -1226.492 | AD16: -849.41 | AE16: 548.514 | AF16: =I16-SUM(AC16:AE16) -> 2578.16 | AG16: 2827.022 | AH16: 3363.497 | AI16: 5483.157 | AJ16: =J16-SUM(AG16:AI16) -> 1638.057 | AK16: 848.517
B17: Share of net profit /(loss) of investments | C17: -614.92 | D17: -671.822 | E17: 1380.904 | F17: 275.013 | G17: -400.1 | H17: 45.6 | I17: 276.845 | J17: 326.127 | K17: =SUM(AH17:AK17) -> 306.363 | M17: 130.738 | N17: 892.645 | O17: -10.696 | P17: =E17-SUM(M17:O17) -> 368.217 | Q17: 8.989 | R17: -26.193 | S17: 45.116 | T17: =F17-SUM(Q17:S17) -> 247.101 | U17: -201.332 | V17: 62.672 | W17: -264.996 | X17: =G17-SUM(U17:W17) -> 3.556 | Y17: -133.081 | Z17: 74.046 | AA17: 20.633 | AB17: =H17-SUM(Y17:AA17) -> 84.002 | AC17: 155.391 | AD17: 86.385 | AE17: 37.739 | AF17: =I17-SUM(AC17:AE17) -> -2.67 | AG17: 63.531 | AH17: 86.864 | AI17: 25.144 | AJ17: =J17-SUM(AG17:AI17) -> 150.588 | AK17: 43.767
B18: Other operating income/(loss), net | C18: =844.789+213.281 -> 1058.07 | D18: =1265.921-226.399 -> 1039.522 | E18: =642.93-372.458 -> 270.472 | F18: =826.856-2579.507 -> -1752.651 | G18: =1135.56-1368.81 -> -233.25 | H18: =740.1+1696.7 -> 2436.8 | I18: =1666.779-10.334 -> 1656.445 | J18: =2736.94+2719.838 -> 5456.778 | K18: =SUM(AH18:AK18) -> 6657.705 | M18: =73.727-510.19 -> -436.463 | N18: =183.051+288.071 -> 471.122 | O18: =139.291-240.995 -> -101.704 | P18: =E18-SUM(M18:O18) -> 337.517 | Q18: =152.053-64.699 -> 87.354 | R18: =234.612+1099.047 -> 1333.659 | S18: =234.886-472.296 -> -237.41 | T18: =F18-SUM(Q18:S18) -> -2936.254 | U18: =164.927-39.053 -> 125.874 | V18: =186.177-386.447 -> -200.27 | W18: =195.671-414.983 -> -219.312 | X18: =G18-SUM(U18:W18) -> 60.458 | Y18: =164.834+176.027 -> 340.861 | Z18: =184.776+71.223 -> 255.999 | AA18: =128.734+119.806 -> 248.54 | AB18: =H18-SUM(Y18:AA18) -> 1591.4 | AC18: =157.407-69.544 -> 87.863 | AD18: =287.246+549.628 -> 836.874 | AE18: =275.902-50.003 -> 225.899 | AF18: =I18-SUM(AC18:AE18) -> 505.809 | AG18: =(161766+108797)/1000 -> 270.563 | AH18: =299.446+754.446 -> 1053.892 | AI18: =(1686642+1196243)/1000 -> 2882.885 | AJ18: =J18-SUM(AG18:AI18) -> 1249.438 | AK18: =1085.385+386.105 -> 1471.49
B19: Operating profit | C19: =C10+SUM(C13:C18) -> 1196.472 | D19: =D10+SUM(D13:D18) -> 11760.217 | E19: =E10+SUM(E13:E18) -> 24034.729 | F19: =F10+SUM(F13:F18) -> 26028.664 | G19: =G10+SUM(G13:G18) -> 2816.498 | H19: =H10+SUM(H13:H18) -> 20008.7 | I19: =I10+SUM(I13:I18) -> 24502.896 | J19: =J10+SUM(J13:J18) -> 47900.92 | K19: =K10+SUM(K13:K18) -> 40088.158 | M19: =M10+SUM(M13:M18) -> 2323.188 | N19: =N10+SUM(N13:N18) -> 5413.027 | O19: =O10+SUM(O13:O18) -> 6696.619 | P19: =P10+SUM(P13:P18) -> 9601.895 | Q19: =Q10+SUM(Q13:Q18) -> 8157.663 | R19: =R10+SUM(R13:R18) -> 10725.756 | S19: =S10+SUM(S13:S18) -> 2729.681 | T19: =T10+SUM(T13:T18) -> 4415.564 | ... AK19: =AK10+SUM(AK13:AK18) -> 5312.645
B20: Finance exps | C20: 0 | D20: -528.46 | E20: -3364.852 | F20: -2841.457 | G20: -546.483 | H20: -1555.97 | I20: -212.447 | J20: -3634.735 | K20: =SUM(AH20:AK20) -> -3360.646 | M20: -161.045 | N20: -767.025 | O20: -1465.628 | P20: =E20-SUM(M20:O20) -> -971.154 | Q20: 634.009 | R20: -1369.865 | S20: -1260.559 | T20: =F20-SUM(Q20:S20) -> -845.042 | U20: 229.631 | V20: -376.18 | W20: -284.812 | X20: =G20-SUM(U20:W20) -> -115.122 | Y20: -1107.646 | Z20: 63.882 | AA20: -95.602 | AB20: =H20-SUM(Y20:AA20) -> -416.604 | AC20: 519.905 | AD20: -86.211 | AE20: -157.188 | AF20: =I20-SUM(AC20:AE20) -> -488.953 | AG20: 1003.965 | AH20: -512.462 | AI20: -1644.26 | AJ20: =J20-SUM(AG20:AI20) -> -2481.978 | AK20: 1278.054
B21: Finance income | C21: =216.373+12514.279 -> 12730.652 | D21: 930.889 | E21: 963.555 | F21: 1229.826 | G21: 1663.941 | H21: =3558.347 -> 3558.347 | I21: 3836.204 | J21: 5380.68 | K21: =SUM(AH21:AK21) -> 5480.092 | M21: 291.946 | N21: 221.794 | O21: 219.69 | P21: =E21-SUM(M21:O21) -> 230.125 | Q21: 275.208 | R21: 322.651 | S21: 317.991 | T21: =F21-SUM(Q21:S21) -> 313.976 | U21: 265.702 | V21: 379.991 | W21: 455.128 | X21: =G21-SUM(U21:W21) -> 563.12 | Y21: 678.15 | Z21: 851.273 | AA21: 971.589 | AB21: =H21-SUM(Y21:AA21) -> 1057.335 | AC21: 1019.435 | AD21: 876.875 | AE21: 933.119 | AF21: =I21-SUM(AC21:AE21) -> 1006.775 | AG21: -961.404 | AH21: 1478.526 | AI21: 1489.776 | AJ21: =J21-SUM(AG21:AI21) -> 3373.782 | AK21: -861.992
B22: Finance (costs)/income, net | C22: =SUM(C20:C21) -> 12730.652 | D22: =SUM(D20:D21) -> 402.429 | E22: =SUM(E20:E21) -> -2401.297 | F22: =SUM(F20:F21) -> -1611.631 | G22: =SUM(G20:G21) -> 1117.458 | H22: =SUM(H20:H21) -> 2002.377 | I22: =SUM(I20:I21) -> 3623.757 | J22: =SUM(J20:J21) -> 1745.945 | K22: =SUM(K20:K21) -> 2119.446 | M22: =SUM(M20:M21) -> 130.901 | N22: =SUM(N20:N21) -> -545.231 | O22: =SUM(O20:O21) -> -1245.938 | P22: =SUM(P20:P21) -> -741.029 | Q22: =SUM(Q20:Q21) -> 909.217 | R22: =SUM(R20:R21) -> -1047.214 | S22: =SUM(S20:S21) -> -942.568 | T22: =SUM(T20:T21) -> -531.066 | ... AK22: =SUM(AK20:AK21) -> 416.062
B23: Profit before tax | C23: =C19+SUM(C22) -> 13927.124 | D23: =D19+SUM(D22) -> 12162.646 | E23: =E19+SUM(E22) -> 21633.432 | F23: =F19+SUM(F22) -> 24417.033 | G23: =G19+SUM(G22) -> 3933.956 | H23: =H19+SUM(H22) -> 22011.077 | I23: =I19+SUM(I22) -> 28126.653 | J23: =J19+SUM(J22) -> 49646.865 | K23: =K19+SUM(K22) -> 42207.604 | M23: =M19+SUM(M22) -> 2454.089 | N23: =N19+SUM(N22) -> 4867.796 | O23: =O19+SUM(O22) -> 5450.681 | P23: =P19+SUM(P22) -> 8860.866 | Q23: =Q19+SUM(Q22) -> 9066.88 | R23: =R19+SUM(R22) -> 9678.542 | S23: =S19+SUM(S22) -> 1787.113 | T23: =T19+SUM(T22) -> 3884.498 | ... AK23: =AK19+SUM(AK22) -> 5728.707
B24: Current and deferred income tax and social contribution | C24: -449.377 | D24: -2059.696 | E24: -1320.722 | F24: -5133.798 | G24: -1431.388 | H24: -4536.851 | I24: -4548.204 | J24: -8080.426 | K24: =SUM(AH24:AK24) -> -6799.334 | M24: -294.195 | N24: -374.323 | O24: -586.333 | P24: =E24-SUM(M24:O24) -> -65.871 | Q24: -1277.973 | R24: -1415.234 | S24: -998.596 | T24: =F24-SUM(Q24:S24) -> -1441.995 | U24: -114.624 | V24: -371.462 | W24: -283.227 | X24: =G24-SUM(U24:W24) -> -662.075 | Y24: -1254.575 | Z24: -1290.157 | AA24: -1018.128 | AB24: =H24-SUM(Y24:AA24) -> -973.991 | AC24: -1049.166 | AD24: -1609.716 | AE24: -1476.902 | AF24: =I24-SUM(AC24:AE24) -> -412.42 | AG24: -2275.222 | AH24: -2529.62 | AI24: -2698.904 | AJ24: =J24-SUM(AG24:AI24) -> -576.68 | AK24: -994.13
B25: Net profit/loss | C25: =+C23+C24 -> 13477.747 | D25: =+D23+D24 -> 10102.95 | E25: =+E23+E24 -> 20312.71 | F25: =+F23+F24 -> 19283.235 | G25: =+G23+G24 -> 2502.568 | H25: =+H23+H24 -> 17474.226 | I25: =+I23+I24 -> 23578.449 | J25: =+J23+J24 -> 41566.439 | K25: =+K23+K24 -> 35408.27 | M25: =+M23+M24 -> 2159.894 | N25: =+N23+N24 -> 4493.473 | O25: =+O23+O24 -> 4864.348 | P25: =+P23+P24 -> 8794.995 | Q25: =+Q23+Q24 -> 7788.907 | R25: =+R23+R24 -> 8263.308 | S25: =+S23+S24 -> 788.517 | T25: =+T23+T24 -> 2442.503 | ... AK25: =+AK23+AK24 -> 4734.577
B26: % margin | C26: =+C25/C7 -> 0.077052936 | D26: =+D25/D7 -> 0.049081882 | E26: =+E25/E7 -> 0.082617118 | F26: =+F25/F7 -> 0.058734992 | G26: =+G25/G7 -> 0.0089363381 | H26: =+H25/H7 -> 0.064487654 | I26: =+I25/I7 -> 0.06443848 | J26: =+J25/J7 -> 0.090897986 | K26: =+K25/K7 -> 0.07954502 | M26: =+M25/M7 -> 0.043456737 | N26: =+N25/N7 -> 0.083930841 | O26: =+O25/O7 -> 0.067407993 | P26: =+P25/P7 -> 0.12481741 | Q26: =+Q25/Q7 -> 0.10130968 | R26: =+R25/R7 -> 0.094126961 | S26: =+S25/S7 -> 0.010101053 | T26: =+T25/T7 -> 0.028542194 | ... AK26: =+AK25/AK7 -> 0.047755696
B27: Non-controlling interest | C27: 76.139 | D27: -58.786 | E27: 42.794 | F27: 56.086 | G27: -28.538 | H27: 0.977 | I27: 79.677 | J27: 76.95 | K27: =SUM(AH27:AK27) -> 33.918 | M27: 3.621 | N27: 4.655 | O27: 16.248 | P27: =E27-SUM(M27:O27) -> 18.27 | Q27: 3.982 | R27: 5.169 | S27: 3.739 | T27: =F27-SUM(Q27:S27) -> 43.196 | U27: -57.046 | V27: 21.023 | W27: -2.128 | X27: =G27-SUM(U27:W27) -> 9.613 | Y27: -12.299 | Z27: 4.451 | AA27: 4.789 | AB27: =H27-SUM(Y27:AA27) -> 4.036 | AC27: 8.849 | AD27: 28.333 | AE27: 12.112 | AF27: =I27-SUM(AC27:AE27) -> 30.383 | AG27: 31.575 | AH27: 31.242 | AI27: 14.133 | AJ27: =J27-SUM(AG27:AI27) -> 0 | AK27: -11.457
B28: Net profit/loss | C28: =+C25+C27 -> 13553.886 | D28: =+D25+D27 -> 10044.164 | E28: =+E25+E27 -> 20355.504 | F28: =+F25+F27 -> 19339.321 | G28: =+G25+G27 -> 2474.03 | H28: =+H25+H27 -> 17475.203 | I28: =+I25+I27 -> 23658.126 | J28: =+J25+J27 -> 41643.389 | K28: =+K25+K27 -> 35442.188 | M28: =+M25+M27 -> 2163.515 | N28: =+N25+N27 -> 4498.128 | O28: =+O25+O27 -> 4880.596 | P28: =+P25+P27 -> 8813.265 | Q28: =+Q25+Q27 -> 7792.889 | R28: =+R25+R27 -> 8268.477 | S28: =+S25+S27 -> 792.256 | T28: =+T25+T27 -> 2485.699 | ... AK28: =+AK25+AK27 -> 4723.12
B30: % of sales or stated otherwise
B31: =B13 -> Selling and marketing expenses | C31: =-C13/C7 -> 0.045696782 | D31: =-D13/D7 -> 0.050418478 | E31: =-E13/E7 -> 0.059135552 | F31: =-F13/F7 -> 0.063905515 | G31: =-G13/G7 -> 0.076142755 | H31: =-H13/H7 -> 0.070954323 | I31: =-I13/I7 -> 0.069388323 | J31: =-J13/J7 -> 0.072633512 | K31: =-K13/K7 -> 0.077035071 | M31: =-M13/M7 -> 0.052812043 | N31: =-N13/N7 -> 0.060213077 | O31: =-O13/O7 -> 0.04989528 | P31: =-P13/P7 -> 0.072240429 | Q31: =-Q13/Q7 -> 0.054153978 | R31: =-R13/R7 -> 0.064708125 | S31: =-S13/S7 -> 0.06254337 | T31: =-T13/T7 -> 0.073085653 | ... AK31: =-AK13/AK7 -> 0.083481419
B32: =B14 -> Administrative expenses | C32: =-C14/C7 -> 0.069171018 | D32: =-D14/D7 -> 0.015079289 | E32: =-E14/E7 -> 0.01523779 | F32: =-F14/F7 -> 0.014434319 | G32: =-G14/G7 -> 0.018260976 | H32: =-H14/H7 -> 0.018920169 | I32: =-I14/I7 -> 0.015307873 | J32: =-J14/J7 -> 0.014548917 | K32: =-K14/K7 -> 0.015171392 | M32: =-M14/M7 -> 0.015724324 | N32: =-N14/N7 -> 0.015623091 | O32: =-O14/O7 -> 0.011816549 | P32: =-P14/P7 -> 0.018105631 | Q32: =-Q14/Q7 -> 0.012846309 | R32: =-R14/R7 -> 0.013103424 | S32: =-S14/S7 -> 0.016327907 | T32: =-T14/T7 -> 0.015498982 | ... AK32: =-AK14/AK7 -> 0.016445011
B33: =B15 -> Research and development expenses | C33: =-C15/C7 -> 0.033026395 | D33: =-D15/D7 -> 0.036400126 | E33: =-E15/E7 -> 0.037647144 | F33: =-F15/F7 -> 0.040105761 | G33: =-G15/G7 -> 0.057234331 | H33: =-H15/H7 -> 0.070478994 | I33: =-I15/I7 -> 0.065728523 | J33: =-J15/J7 -> 0.072453894 | K33: =-K15/K7 -> 0.079469996 | M33: =-M15/M7 -> 0.037643912 | N33: =-N15/N7 -> 0.036577368 | O33: =-O15/O7 -> 0.032167055 | P33: =-P15/P7 -> 0.044074537 | Q33: =-Q15/Q7 -> 0.03917672 | R33: =-R15/R7 -> 0.034903888 | S33: =-S15/S7 -> 0.041475488 | T33: =-T15/T7 -> 0.045027385 | ... AK33: =-AK15/AK7 -> 0.090319093
B34: =B16 -> Fair value changes on investments | C34: =-C16/C$7 -> -0.025328578 | D34: =-D16/D$7 -> -0.018524273 | E34: =-E16/E$7 -> -0.053579993 | F34: =-F16/F$7 -> -0.024769743 | G34: =-G16/G$7 -> 0.005934817 | H34: =-H16/H$7 -> -0.012920614 | I34: =-I16/I$7 -> -0.0028716965 | J34: =-J16/J$7 -> -0.029110257 | K34: =-K16/K$7 -> -0.025460206 | M34: =-M16/M$7 -> -0.0069986083 | N34: =-N16/N$7 -> -0.044196582 | O34: =-O16/O$7 -> -0.047364086 | P34: =-P16/P$7 -> -0.099932342 | Q34: =-Q16/Q$7 -> -0.026835965 | R34: =-R16/R$7 -> -0.047448096 | S34: =-S16/S$7 -> 0.025308247 | T34: =-T16/T$7 -> -0.045330218 | ... AK34: =-AK16/AK$7 -> -0.0085586358
B35: =B17 -> Share of net profit /(loss) of investments | C35: =-C17/C$7 -> 0.0035155276 | D35: =-D17/D$7 -> 0.0032638277 | E35: =-E17/E$7 -> -0.0056164987 | F35: =-F17/F$7 -> -0.00083766476 | G35: =-G17/G$7 -> 0.001428704 | H35: =-H17/H$7 -> -0.00016828425 | I35: =-I17/I$7 -> -0.0007566007 | J35: =-J17/J$7 -> -0.00071317843 | K35: =-K17/K$7 -> -0.00068824744 | M35: =-M17/M$7 -> -0.0026304286 | N35: =-N17/N$7 -> -0.016673171 | O35: =-O17/O$7 -> 0.00014822046 | P35: =-P17/P$7 -> -0.0052256873 | Q35: =-Q17/Q$7 -> -0.00011691919 | R35: =-R17/R$7 -> 0.00029836326 | S35: =-S17/S$7 -> -0.00057794453 | T35: =-T17/T$7 -> -0.0028875316 | ... AK35: =-AK17/AK$7 -> -0.00044145941
B36: Finance exps as% of debt | C36: =-C20/C109 -> 0 | D36: =-D20/D109 -> 0.02998625 | E36: =-E20/E109 -> 0.19122016 | F36: =-F20/F109 -> 0.10825901 | G36: =-G20/G109 -> 0.023112965 | H36: =-H20/H109 -> 0.055854928 | I36: =-I20/I109 -> 0.0069420277 | J36: =-J20/J109 -> 0.10061924 | K36: =-K20/K109 -> 0.095021446 | P36: =-SUM(M20:P20)/P109 -> 0.19122016 | Q36: =-SUM(N20:Q20)/Q109 -> 0.12234287 | R36: =-SUM(O20:R20)/R109 -> 0.16426855 | S36: =-SUM(P20:S20)/S109 -> 0.11458525 | T36: =-SUM(Q20:T20)/T109 -> 0.10825901 | U36: =-SUM(R20:U20)/U109 -> 0.10923614 | V36: =-SUM(S20:V20)/V109 -> 0.069149912 | W36: =-SUM(T20:W20)/W109 -> 0.049546538 | ... AK36: =-SUM(AH20:AK20)/AK109 -> 0.095021446
B37: Finance income as% of cash and cash equivalents | C37: =C21/C120 -> 0.33287394 | D37: =D21/D120 -> 0.014566468 | E37: =E21/E120 -> 0.010086916 | F37: =F21/F120 -> 0.014271537 | G37: =G21/G120 -> 0.024550236 | H37: =H21/H120 -> 0.033037047 | I37: =I21/I120 -> 0.038164837 | J37: =J21/J120 -> 0.049961471 | K37: =K21/K120 -> 0.055790981 | P37: =SUM(M21:P21)/P120 -> 0.010086916 | Q37: =SUM(N21:Q21)/Q120 -> 0.010018296 | R37: =SUM(O21:R21)/R120 -> 0.011190031 | S37: =SUM(P21:S21)/S120 -> 0.013995212 | T37: =SUM(Q21:T21)/T120 -> 0.014271537 | U37: =SUM(R21:U21)/U120 -> 0.016006616 | V37: =SUM(S21:V21)/V120 -> 0.017058734 | W37: =SUM(T21:W21)/W120 -> 0.021286842 | ... AK37: =SUM(AH21:AK21)/AK120 -> 0.055790981
B38: Tax % of PBT | C38: =-C24/C23 -> 0.032266317 | D38: =-D24/D23 -> 0.16934605 | E38: =-E24/E23 -> 0.061050045 | F38: =-F24/F23 -> 0.21025478 | G38: =-G24/G23 -> 0.3638546 | H38: =-H24/H23 -> 0.20611672 | I38: =-I24/I23 -> 0.16170442 | J38: =-J24/J23 -> 0.16275803 | K38: =-K24/K23 -> 0.16109263 | M38: =-M24/M23 -> 0.11987952 | N38: =-N24/N23 -> 0.07689784 | O38: =-O24/O23 -> 0.1075706 | P38: =-P24/P23 -> 0.0074339235 | Q38: =-Q24/Q23 -> 0.14094959 | R38: =-R24/R23 -> 0.14622388 | S38: =-S24/S23 -> 0.55877608 | T38: =-T24/T23 -> 0.37121785 | ... AK38: =-AK24/AK23 -> 0.1735348
B40: Working capital /sales | C40: =C61/C7 -> -0.02045899 | D40: =D61/D7 -> 0.025716415 | E40: =E61/E7 -> -0.022507562 | F40: =F61/F7 -> -0.057381777 | G40: =G61/G7 -> -0.077189305 | H40: =H61/H7 -> -0.03921691 | I40: =I61/I7 -> 0.14166828 | J40: =J61/J7 -> -0.030358207 | K40: =K61/K7 -> 0 | M40: =M61/M7 -> 0 | N40: =N61/N7 -> 0 | O40: =O61/O7 -> 0 | P40: =P61/P7 -> -0.078535474 | Q40: =Q61/Q7 -> 0 | R40: =R61/R7 -> 0 | S40: =S61/S7 -> 0 | T40: =T61/T7 -> -0.2201452 | ... AK40: =AK61/AK7 -> 0
B41: Capex/sales | C41: =-C65/C7 -> 0.0013504927 | D41: =-D65/D7 -> 0.016213804 | E41: =-E65/E7 -> 0.012049 | F41: =-F65/F7 -> 0.021729361 | G41: =-G65/G7 -> 0.020647597 | H41: =-H65/H7 -> 0.022866239 | I41: =-I65/I7 -> 0.018963374 | J41: =-J65/J7 -> 0.027895802 | K41: =-K65/K7 -> 0 | M41: =-M65/M7 -> 0 | N41: =-N65/N7 -> 0.021010761 | O41: =-O65/O7 -> 0 | P41: =-P65/P7 -> 0.026078481 | Q41: =-Q65/Q7 -> 0 | R41: =-R65/R7 -> 0.020749921 | S41: =-S65/S7 -> 0 | T41: =-T65/T7 -> 0.062077986 | ... AK41: =-AK65/AK7 -> 0
B43: EBITDA | C43: =C3 -> 43465 | D43: =D3 -> 43830 | E43: =E3 -> 44196 | F43: =F3 -> 44561 | G43: =G3 -> 44926 | H43: =H3 -> 45291 | I43: =I3 -> 45657 | J43: =J3 -> 46022 | K43: =K2 -> LTM | M43: =M3 -> 43921 | N43: =N3 -> 44012 | O43: =O3 -> 44104 | P43: =P3 -> 44196 | Q43: =Q3 -> 44286 | R43: =R3 -> 44377 | S43: =S3 -> 44469 | T43: =T3 -> 44561 | ... AK43: =AK3 -> 46112
B44: Operating profit | C44: =C19 -> 1196.472 | D44: =D19 -> 11760.217 | E44: =E19 -> 24034.729 | F44: =F19 -> 26028.664 | G44: =G19 -> 2816.498 | H44: =H19 -> 20008.7 | I44: =I19 -> 24502.896 | J44: =J19 -> 47900.92 | K44: =K19 -> 40088.158 | M44: =M19 -> 2323.188 | N44: =N19 -> 5413.027 | O44: =O19 -> 6696.619 | P44: =P19 -> 9601.895 | Q44: =Q19 -> 8157.663 | R44: =R19 -> 10725.756 | S44: =S19 -> 2729.681 | T44: =T19 -> 4415.564 | ... AK44: =AK19 -> 5312.645
B45: Depreciation, depletion & amortization | C45: =219.523+528.693 -> 748.216 | D45: =895.273+485.786 -> 1381.059 | E45: =1042.895+665.566 -> 1708.461 | F45: =1804.312+1257.334 -> 3061.646 | G45: =2310.951+1396.442 -> 3707.393 | H45: =2401.979+2434.308 -> 4836.287 | I45: =3626.279+2691.99 -> 6318.269 | J45: =5256.031+3500.716 -> 8756.747 | K45: =SUM(AH45:AK45) -> 9384.984 | M45: =229.692+122.228 -> 351.92 | N45: =250.86+122.256 -> 373.116 | O45: =270.577+123.135 -> 393.712 | P45: =E45-SUM(M45:O45) -> 589.713 | Q45: =359.695+297.635 -> 657.33 | R45: =431.658+296.382 -> 728.04 | S45: =469.752+330.434 -> 800.186 | T45: =F45-SUM(Q45:S45) -> 876.09 | U45: =544.464+333.969 -> 878.433 | V45: =603.272+344.14 -> 947.412 | W45: =573.859+357.152 -> 931.011 | X45: =G45-SUM(U45:W45) -> 950.537 | Y45: =563.606+361.473 -> 925.079 | Z45: =598.701+426.732 -> 1025.433 | AA45: =584.48+1057.314 -> 1641.794 | AB45: =H45-SUM(Y45:AA45) -> 1243.981 | AC45: =803.713+590.61 -> 1394.323 | AD45: =816.293+596.037 -> 1412.33 | AE45: =916.859+780.324 -> 1697.183 | AF45: =I45-SUM(AC45:AE45) -> 1814.433 | AG45: =1059.92+722.942 -> 1782.862 | AH45: =1222.019+787.574 -> 2009.593 | AI45: =1323.542+899.903 -> 2223.445 | AJ45: =J45-SUM(AG45:AI45) -> 2740.847 | AK45: =1457.375+953.724 -> 2411.099
B46: EBITDA | C46: =SUM(C44:C45) -> 1944.688 | D46: =SUM(D44:D45) -> 13141.276 | E46: =SUM(E44:E45) -> 25743.19 | F46: =SUM(F44:F45) -> 29090.31 | G46: =SUM(G44:G45) -> 6523.891 | H46: =SUM(H44:H45) -> 24844.987 | I46: =SUM(I44:I45) -> 30821.165 | J46: =SUM(J44:J45) -> 56657.667 | K46: =SUM(K44:K45) -> 49473.142 | M46: =SUM(M44:M45) -> 2675.108 | N46: =SUM(N44:N45) -> 5786.143 | O46: =SUM(O44:O45) -> 7090.331 | P46: =SUM(P44:P45) -> 10191.608 | Q46: =SUM(Q44:Q45) -> 8814.993 | R46: =SUM(R44:R45) -> 11453.796 | S46: =SUM(S44:S45) -> 3529.867 | T46: =SUM(T44:T45) -> 5291.654 | ... AK46: =SUM(AK44:AK45) -> 7723.744
B47: % growth | D47: =+D46/C46-1 -> 5.7575241 | E47: =+E46/D46-1 -> 0.95895665 | F47: =+F46/E46-1 -> 0.13001963 | G47: =+G46/F46-1 -> -0.77573663 | H47: =+H46/G46-1 -> 2.8083081 | I47: =+I46/H46-1 -> 0.24053858 | J47: =+J46/I46-1 -> 0.83827143 | Q47: =Q46/M46-1 -> 2.2951914 | R47: =R46/N46-1 -> 0.97952176 | S47: =S46/O46-1 -> -0.50215766 | T47: =T46/P46-1 -> -0.48078321 | U47: =U46/Q46-1 -> -1.0037243 | V47: =V46/R46-1 -> -0.76597802 | W47: =W46/S46-1 -> -1.1218176 | X47: =X46/T46-1 -> -0.18621267 | ... AK47: =AK46/AG46-1 -> -0.48191544
B48: % margin | C48: =+C46/C7 -> 0.011117876 | D48: =+D46/D7 -> 0.063842597 | E48: =+E46/E7 -> 0.1047043 | F48: =+F46/F7 -> 0.088606457 | G48: =+G46/G7 -> 0.023295949 | H48: =+H46/H7 -> 0.091689035 | I48: =+I46/I7 -> 0.084232386 | J48: =+J46/J7 -> 0.12389966 | K48: =+K46/K7 -> 0.11114189 | M48: =+M46/M7 -> 0.053822764 | N48: =+N46/N7 -> 0.10807584 | O48: =+O46/O7 -> 0.098254686 | P48: =+P46/P7 -> 0.14463796 | Q48: =+Q46/Q7 -> 0.11465589 | R48: =+R46/R7 -> 0.13046966 | S48: =+S46/S7 -> 0.045218267 | T48: =+T46/T7 -> 0.061836327 | ... AK48: =+AK46/AK7 -> 0.077906173
B50: Adjustment | C50: =C51-C46 -> 0 | D50: =D51-D46 -> 0 | E50: =E51-E46 -> 0 | F50: =F51-F46 -> 0 | G50: =G51-G46 -> 0 | H50: =H51-H46 -> 0 | I50: =I51-I46 -> 0 | J50: =J51-J46 -> 0 | K50: =K51-K46 -> 0 | M50: =M51-M46 -> 0 | N50: =N51-N46 -> 0 | O50: =O51-O46 -> 0 | P50: =A50-SUM(M50:O50) -> 0 | Q50: =Q51-Q46 -> 0 | R50: =R51-R46 -> 0 | S50: =S51-S46 -> 0 | T50: =E50-SUM(Q50:S50) -> 0 | U50: =U51-U46 -> 0 | V50: =V51-V46 -> 0 | W50: =W51-W46 -> 0 | X50: =L50-SUM(U50:W50) -> 0 | Y50: =Y51-Y46 -> 0 | Z50: =Z51-Z46 -> 0 | AA50: =AA51-AA46 -> 0 | AB50: =P50-SUM(Y50:AA50) -> 0 | AC50: =AC51-AC46 -> 0 | AD50: =AD51-AD46 -> 0 | AE50: =AE51-AE46 -> 0 | AF50: =T50-SUM(AC50:AE50) -> 0 | AG50: =AG51-AG46 -> 0 | AH50: =AH51-AH46 -> 0 | AI50: =AI51-AI46 -> 0 | AJ50: =X50-SUM(AG50:AI50) -> 0 | AK50: =AK51-AK46 -> 0
B51: Adj. EBITDA | C51: =C46 -> 1944.688 | D51: =D46 -> 13141.276 | E51: =E46 -> 25743.19 | F51: =F46 -> 29090.31 | G51: =G46 -> 6523.891 | H51: =H46 -> 24844.987 | I51: =I46 -> 30821.165 | J51: =J46 -> 56657.667 | K51: =SUM(AH51:AK51) -> 49473.142 | M51: =M46 -> 2675.108 | N51: =N46 -> 5786.143 | O51: =O46 -> 7090.331 | P51: =P46 -> 10191.608 | Q51: =Q46 -> 8814.993 | R51: =R46 -> 11453.796 | S51: =S46 -> 3529.867 | T51: =T46 -> 5291.654 | ... AK51: =AK46 -> 7723.744
B52: % growth | D52: =+D51/C51-1 -> 5.7575241 | E52: =+E51/D51-1 -> 0.95895665 | F52: =+F51/E51-1 -> 0.13001963 | G52: =+G51/F51-1 -> -0.77573663 | H52: =+H51/G51-1 -> 2.8083081 | I52: =+I51/H51-1 -> 0.24053858 | J52: =+J51/I51-1 -> 0.83827143 | Q52: =Q51/M51-1 -> 2.2951914 | R52: =R51/N51-1 -> 0.97952176 | S52: =S51/O51-1 -> -0.50215766 | U52: =U51/Q51-1 -> -1.0037243 | V52: =V51/R51-1 -> -0.76597802 | W52: =W51/S51-1 -> -1.1218176 | X52: =X51/T51-1 -> -0.18621267 | Y52: =Y51/U51-1 -> -208.8979 | Z52: =Z51/V51-1 -> 0.88997291 | AA52: =AA51/W51-1 -> -16.472109 | AB52: =AB51/X51-1 -> 0.46314953 | ... AK52: =AK51/AG51-1 -> -0.48191544
B53: % margin | C53: =+C51/C7 -> 0.011117876 | D53: =+D51/D7 -> 0.063842597 | E53: =+E51/E7 -> 0.1047043 | F53: =+F51/F7 -> 0.088606457 | G53: =+G51/G7 -> 0.023295949 | H53: =+H51/H7 -> 0.091689035 | I53: =+I51/I7 -> 0.084232386 | J53: =+J51/J7 -> 0.12389966 | K53: =+K51/K7 -> 0.11114189 | M53: =+M51/M7 -> 0.053822764 | N53: =+N51/N7 -> 0.10807584 | O53: =+O51/O7 -> 0.098254686 | P53: =+P51/P7 -> 0.14463796 | Q53: =+Q51/Q7 -> 0.11465589 | R53: =+R51/R7 -> 0.13046966 | S53: =+S51/S7 -> 0.045218267 | T53: =+T51/T7 -> 0.061836327 | ... AK53: =+AK51/AK7 -> 0.077906173
B55: Capex sales | C55: =-C65/C7 -> 0.0013504927 | D55: =-D65/D7 -> 0.016213804 | E55: =-E65/E7 -> 0.012049 | F55: =-F65/F7 -> 0.021729361 | G55: =-G65/G7 -> 0.020647597 | H55: =-H65/H7 -> 0.022866239 | I55: =-I65/I7 -> 0.018963374 | J55: =-J65/J7 -> 0.027895802 | K55: =-K65/K7 -> 0 | N55: =-N65/N7 -> 0.021010761 | P55: =-P65/P7 -> 0.026078481 | R55: =-R65/R7 -> 0.020749921 | T55: =-T65/T7 -> 0.062077986 | V55: =-V65/V7 -> 0.03851558 | Z55: =-Z65/Z7 -> 0.054354242 | AB55: =-AB65/AB7 -> 0.034611084 | AD55: =-AD65/AD7 -> 0.022653237 | AF55: =-AF65/AF7 -> 0.045183384 | AH55: =-AH65/AH7 -> 0.043795078 | AJ55: =-AJ65/AJ7 -> 0.06567141
B56: WC SALES | C56: =C61/C7 -> -0.02045899 | D56: =D61/D7 -> 0.025716415 | E56: =E61/E7 -> -0.022507562 | F56: =F61/F7 -> -0.057381777 | G56: =G61/G7 -> -0.077189305 | H56: =H61/H7 -> -0.03921691 | I56: =I61/I7 -> 0.14166828 | J56: =J61/J7 -> -0.030358207 | K56: =K61/K7 -> 0 | N56: =N61/N7 -> 0 | P56: =P61/P7 -> -0.078535474 | R56: =R61/R7 -> 0 | T56: =T61/T7 -> -0.2201452 | V56: =V61/V7 -> 0 | Z56: =Z61/Z7 -> 0 | AB56: =AB61/AB7 -> -0.14508576 | AD56: =AD61/AD7 -> 0 | AF56: =AF61/AF7 -> 0.47554927 | AH56: =AH61/AH7 -> 0 | AJ56: =AJ61/AJ7 -> -0.11873774
N58: 1H | P58: 2H | R58: 1H | T58: 2H | V58: 1H | X58: 2H | Z58: 1H | AB58: 2H | AD58: 1H | AF58: 2H | AH58: 1H | AJ58: 2H
B59: CASH FLOW | C59: =C3 -> 43465 | D59: =D3 -> 43830 | E59: =E3 -> 44196 | F59: =F3 -> 44561 | G59: =G3 -> 44926 | H59: =H3 -> 45291 | I59: =I3 -> 45657 | J59: =J3 -> 46022 | K59: =K2 -> LTM | M59: =M3 -> 43921 | N59: =N3 -> 44012 | O59: =O3 -> 44104 | P59: =P3 -> 44196 | Q59: =Q3 -> 44286 | R59: =R3 -> 44377 | S59: =S3 -> 44469 | T59: =T3 -> 44561 | ... AK59: =AK3 -> 46112
B60: Adj. EBITDA | C60: =C51 -> 1944.688 | D60: =D51 -> 13141.276 | E60: =E51 -> 25743.19 | F60: =F51 -> 29090.31 | G60: =G51 -> 6523.891 | H60: =H51 -> 24844.987 | I60: =I51 -> 30821.165 | J60: =J51 -> 56657.667 | K60: =K51 -> 49473.142 | N60: =N46+M46 -> 8461.251 | P60: =E60-SUM(M60:O60) -> 17281.939 | R60: =R46+Q46 -> 20268.789 | T60: =F60-SUM(Q60:S60) -> 8821.521 | V60: =V46+U46 -> 2647.61 | X60: =G60-SUM(U60:W60) -> 3876.281 | Z60: =Z46+Y46 -> 11891.247 | AB60: =H60-SUM(Y60:AA60) -> 12953.74 | AD60: =AD46+AC46 -> 12378.412 | AF60: =AF46+AE46 -> 18442.753 | AH60: =AH46+AG46 -> 30354.581 | AJ60: =AJ46+AI46 -> 26303.086
B61: Working Capital | C61: =-16114.975-91.003+12627.385 -> -3578.593 | D61: =-6964.428-1276.714+13534.575 -> 5293.433 | E61: =-11602.421-4272.814+10341.399 -> -5533.836 | F61: =-13746.697-7548.686+2456.421 -> -18838.962 | G61: =-5448.99+4346.873-20514.286 -> -21616.403 | H61: =2173.795-1652.782-11147.623 -> -10626.61 | I61: =(24131971-8387158+36092511)/1000 -> 51837.324 | J61: =-26065.762+257.988+11925.37 -> -13882.404 | P61: =E61-SUM(M61:O61) -> -5533.836 | T61: =F61-SUM(Q61:S61) -> -18838.962 | X61: =G61-SUM(U61:W61) -> -21616.403 | AB61: =H61-SUM(Y61:AA61) -> -10626.61 | AF61: =I61-SUM(AC61:AE61) -> 51837.324 | AJ61: =J61-SUM(AG61:AI61) -> -13882.404
B62: Taxes | C62: -1536.742 | D62: -2141.885 | E62: -1953.302 | F62: -2442.495 | G62: -3420.277 | H62: -3011.748 | I62: -3467.218 | J62: -4671.588 | N62: -1333.394 | P62: =E62-SUM(M62:O62) -> -619.908 | R62: -1249.124 | T62: =F62-SUM(Q62:S62) -> -1193.371 | V62: =-1913.099 -> -1913.099 | X62: =G62-SUM(U62:W62) -> -1507.178 | Z62: -1268.523 | AB62: =H62-SUM(Y62:AA62) -> -1743.225 | AD62: -2491.299 | AF62: =I62-SUM(AC62:AE62) -> -975.919 | AH62: -3953.773 | AJ62: =J62-SUM(AG62:AI62) -> -717.815
B63: Cash interest paid | C63: -243.966 | D63: -218.994 | E63: -499.711 | F63: -659.987 | G63: -1020.229 | H63: -758.137 | I63: -717.223 | J63: -774.76 | N63: -164.006 | P63: =E63-SUM(M63:O63) -> -335.705 | R63: -282.834 | T63: =F63-SUM(Q63:S63) -> -377.153 | V63: -458.192 | X63: =G63-SUM(U63:W63) -> -562.037 | Z63: -321.856 | AB63: =H63-SUM(Y63:AA63) -> -436.281 | AD63: -348.935 | AF63: =I63-SUM(AC63:AE63) -> -368.288 | AH63: -387.82 | AJ63: =J63-SUM(AG63:AI63) -> -386.94
B64: Net cash from operations | C64: =SUM(C60:C63) -> -3414.613 | D64: =SUM(D60:D63) -> 16073.83 | E64: =SUM(E60:E63) -> 17756.341 | F64: =SUM(F60:F63) -> 7148.866 | G64: =SUM(G60:G63) -> -19533.018 | H64: =SUM(H60:H63) -> 10448.492 | I64: =SUM(I60:I63) -> 78474.048 | J64: =SUM(J60:J63) -> 37328.915 | N64: =SUM(N60:N63) -> 6963.851 | P64: =SUM(P60:P63) -> 10792.49 | R64: =SUM(R60:R63) -> 18736.831 | T64: =SUM(T60:T63) -> -11587.965 | V64: =SUM(V60:V63) -> 276.319 | X64: =SUM(X60:X63) -> -19809.337 | Z64: =SUM(Z60:Z63) -> 10300.868 | AB64: =SUM(AB60:AB63) -> 147.624 | AD64: =SUM(AD60:AD63) -> 9538.178 | AF64: =SUM(AF60:AF63) -> 68935.87 | AH64: =SUM(AH60:AH63) -> 26012.988 | AJ64: =SUM(AJ60:AJ63) -> 11315.927
B65: Net Capex | C65: =10269.415-10505.637 -> -236.222 | D65: =-3405.163+67.735 -> -3337.428 | E65: =-3025.523+63.088 -> -2962.435 | F65: =-7169.313+35.365 -> -7133.948 | G65: =-5799.57+17.334 -> -5782.236 | H65: =-6268.9+72.833 -> -6196.067 | I65: =(-7297307+358488)/1000 -> -6938.819 | J65: =-12769.155+12.776 -> -12756.379 | N65: =-1129.238+4.368 -> -1124.87 | P65: =E65-SUM(M65:O65) -> -1837.565 | R65: =-1828.851+7.237 -> -1821.614 | T65: =F65-SUM(Q65:S65) -> -5312.334 | V65: =-2717.28+14.608 -> -2702.672 | X65: =G65-SUM(U65:W65) -> -3079.564 | Z65: =-3722.137+61.112 -> -3661.025 | AB65: =H65-SUM(Y65:AA65) -> -2535.042 | AD65: =(-2267908+254311)/1000 -> -2013.597 | AF65: =I65-SUM(AC65:AE65) -> -4925.222 | AH65: =-5085.94+7.634 -> -5078.306 | AJ65: =J65-SUM(AG65:AI65) -> -7678.073
B66: Purchase of intangible assets | C66: 0 | D66: 0 | E66: 0 | F66: 0 | G66: 0 | H66: 0 | I66: 0 | J66: 0 | N66: 0 | P66: =E66-SUM(M66:O66) -> 0 | R66: 0 | T66: =F66-SUM(Q66:S66) -> 0 | V66: 0 | X66: =G66-SUM(U66:W66) -> 0 | Z66: 0 | AB66: =H66-SUM(Y66:AA66) -> 0 | AD66: 0 | AF66: =I66-SUM(AC66:AE66) -> 0 | AH66: 0 | AJ66: =J66-SUM(AG66:AI66) -> 0
B67: Disposals/ Acquistion, of subsidiaries, businesses | C67: -34.936 | D67: 0 | E67: 38.517 | F67: -1086.477 | G67: -25.106 | H67: =-18.144+101.294 -> 83.15 | I67: =(-3784)/1000 -> -3.784 | J67: =-12.117 -> -12.117 | N67: 0 | P67: =E67-SUM(M67:O67) -> 38.517 | R67: 0 | T67: =F67-SUM(Q67:S67) -> -1086.477 | V67: 0 | X67: =G67-SUM(U67:W67) -> -25.106 | Z67: 0 | AB67: =H67-SUM(Y67:AA67) -> 83.15 | AD67: 0 | AF67: =I67-SUM(AC67:AE67) -> -3.784 | AH67: 0 | AJ67: =J67-SUM(AG67:AI67) -> -12.117
B68: Free cash flow | C68: =SUM(C64:C67) -> -3685.771 | D68: =SUM(D64:D67) -> 12736.402 | E68: =SUM(E64:E67) -> 14832.423 | F68: =SUM(F64:F67) -> -1071.559 | G68: =SUM(G64:G67) -> -25340.36 | H68: =SUM(H64:H67) -> 4335.575 | I68: =SUM(I64:I67) -> 71531.445 | J68: =SUM(J64:J67) -> 24560.419 | N68: =SUM(N64:N67) -> 5838.981 | P68: =SUM(P64:P67) -> 8993.442 | R68: =SUM(R64:R67) -> 16915.217 | T68: =SUM(T64:T67) -> -17986.776 | V68: =SUM(V64:V67) -> -2426.353 | X68: =SUM(X64:X67) -> -22914.007 | Z68: =SUM(Z64:Z67) -> 6639.843 | AB68: =SUM(AB64:AB67) -> -2304.268 | AD68: =SUM(AD64:AD67) -> 7524.581 | AF68: =SUM(AF64:AF67) -> 64006.864 | AH68: =SUM(AH64:AH67) -> 20934.682 | AJ68: =SUM(AJ64:AJ67) -> 3625.737
B69: Other Investing | C69: =-7508.04-C65-C66-C67 -> -7236.882 | D69: =-31570.136-D65-D66-D67 -> -28232.708 | E69: =-17678.852-E65-E66-E67 -> -14754.934 | F69: =-45007.945-F65-F66-F67 -> -36787.52 | G69: =15548.773-G65-G66-G67 -> 21356.115 | H69: =-35169.054-H65-H66-H67 -> -29056.137 | I69: =-35386.391-I65-I66-I67 -> -28443.788 | J69: =-119200.696+71259.333-58562.541+59828.588-3598.541+3477.296-10246.805-200+700+3276.391+301.171-20230.812+13734.318-363.724+545.159+370.632 -> -58910.231 | N69: =-4211.76-N65-N66-N67 -> -3086.89 | P69: =E69-SUM(M69:O69) -> -11668.044 | R69: =-31987.329-R65-R66-R67 -> -30165.715 | T69: =F69-SUM(Q69:S69) -> -6621.805 | V69: =7627.358-V65-V66-V67 -> 10330.03 | X69: =G69-SUM(U69:W69) -> 11026.085 | Z69: =-14492.197-Z65-Z66-Z67 -> -10831.172 | AB69: =H69-SUM(Y69:AA69) -> -18224.965 | AD69: =2709.078-AD65-AD66-AD67 -> 4722.675 | AF69: =I69-SUM(AC69:AE69) -> -33166.463 | AH69: =-60128.639-AH65-AH66-AH67 -> -55050.333 | AJ69: =J69-SUM(AG69:AI69) -> -3859.898
B70: Equity Issuance | C70: 0 | D70: 186.838 | E70: =19907.936+254.476 -> 20162.412 | F70: 83.014 | G70: 83.925 | H70: 69.919 | I70: 83.88 | J70: =170.934+39225.991 -> 39396.925 | N70: 0 | P70: =E70-SUM(M70:O70) -> 20162.412 | R70: 0 | T70: =F70-SUM(Q70:S70) -> 83.014 | V70: 0 | X70: =G70-SUM(U70:W70) -> 83.925 | Z70: 0 | AB70: =H70-SUM(Y70:AA70) -> 69.919 | AD70: 0 | AF70: =I70-SUM(AC70:AE70) -> 83.88 | AH70: 39225.991 | AJ70: =J70-SUM(AG70:AI70) -> 170.934
B71: Dividends | C71: 0 | D71: 0 | E71: 0 | F71: 0 | G71: 0 | H71: 0 | I71: -23.286 | J71: -1.964 | N71: 0 | P71: =E71-SUM(M71:O71) -> 0 | R71: 0 | T71: =F71-SUM(Q71:S71) -> 0 | V71: 0 | X71: =G71-SUM(U71:W71) -> 0 | Z71: 0 | AB71: =H71-SUM(Y71:AA71) -> 0 | AD71: 0 | AF71: =I71-SUM(AC71:AE71) -> -23.286 | AH71: 0 | AJ71: =J71-SUM(AG71:AI71) -> -1.964
B72: Net Change in debt | C72: =10269.415-10505.637 -> -236.222 | D72: =17036.724-10417.425 -> 6619.299 | E72: =30582.175-32586.382 -> -2004.207 | F72: =22528.578-13301.236 -> 9227.342 | G72: =19857.851-22649.189 -> -2791.338 | H72: =8866.088-4022.423 -> 4843.665 | I72: =(25998066-19265488-2476524)/1000 -> 4256.054 | J72: =30378.289-25080.95-2902.504 -> 2394.835 | N72: =17582.749-12245.76 -> 5336.989 | P72: =E72-SUM(M72:O72) -> -7341.196 | R72: =7460.26-5447.71 -> 2012.55 | T72: =F72-SUM(Q72:S72) -> 7214.792 | V72: =15425.36-10202.349 -> 5223.011 | X72: =G72-SUM(U72:W72) -> -8014.349 | Z72: =898.693-1402.063 -> -503.37 | AB72: =H72-SUM(Y72:AA72) -> 5347.035 | AD72: =(12436649-7759247)/1000 -> 4677.402 | AF72: =I72-SUM(AC72:AE72) -> -421.348 | AH72: =11721.938-12920.591-1254.754 -> -2453.407 | AJ72: =J72-SUM(AG72:AI72) -> 4848.242
B73: Other financing activities | C73: =26574.172-C72-C71-C70-C63 -> 27054.36 | D73: =3121.238-D72-D71-D70-D63 -> -3465.905 | E73: =26215.568-E72-E71-E70-E63 -> 8557.074 | F73: =4498.686-F72-F71-F70-F63 -> -4151.683 | G73: =-7854.799-G72-G71-G70-G63 -> -4127.157 | H73: =-504.972-H72-H71-H70-H63 -> -4660.419 | I73: =(-3998.976-I72-I71-I70-I63) -> -7598.401 | J73: =2393.914-3836.543-6172.545+367.84-501.925-2499.913 -> -10249.172 | N73: =4793.374-N72-N71-N70-N63 -> -379.609 | P73: =E73-SUM(M73:O73) -> 8936.683 | R73: =1070.09-R72-R71-R70-R63 -> -659.626 | T73: =F73-SUM(Q73:S73) -> -3492.057 | V73: =3633.776-V72-V71-V70-V63 -> -1131.043 | X73: =G73-SUM(U73:W73) -> -2996.114 | Z73: =2286.696-Z72-Z71-Z70-Z63 -> 3111.922 | AB73: =H73-SUM(Y73:AA73) -> -7772.341 | AD73: =455.3-AD72-AD71-AD70-AD63 -> -3873.167 | AF73: =I73-SUM(AC73:AE73) -> -3725.234 | AH73: =34434.304-AH72-AH71-AH70-AH63 -> -1950.46 | AJ73: =J73-SUM(AG73:AI73) -> -8298.712
B74: Cash flow after financing activities | C74: =SUM(C68:C73) -> 15895.485 | D74: =SUM(D68:D73) -> -12156.074 | E74: =SUM(E68:E73) -> 26792.768 | F74: =SUM(F68:F73) -> -32700.406 | G74: =SUM(G68:G73) -> -10818.815 | H74: =SUM(H68:H73) -> -24467.397 | I74: =SUM(I68:I73) -> 39805.904 | J74: =SUM(J68:J73) -> -2809.188 | N74: =SUM(N68:N73) -> 7709.471 | P74: =SUM(P68:P73) -> 19083.297 | R74: =SUM(R68:R73) -> -11897.574 | T74: =SUM(T68:T73) -> -20802.832 | V74: =SUM(V68:V73) -> 11995.645 | X74: =SUM(X68:X73) -> -22814.46 | Z74: =SUM(Z68:Z73) -> -1582.777 | AB74: =SUM(AB68:AB73) -> -22884.62 | AD74: =SUM(AD68:AD73) -> 13051.491 | AF74: =SUM(AF68:AF73) -> 26754.413 | AH74: =SUM(AH68:AH73) -> 706.473 | AJ74: =SUM(AJ68:AJ73) -> -3515.661
B75: Balancing figure | C75: =17651.561-C74 -> 1756.076 | D75: =-4638.544-D74 -> 7517.53 | E75: =30415.216-E74 -> 3622.448 | F75: =-30723.971-F74 -> 1976.435 | G75: =3304.244-G74 -> 14123.059 | H75: =5626.469-H74 -> 30093.866 | I75: =-89.868-I74 -> -39895.772 | J75: =-6770.486-J74 -> -3961.298 | N75: =-3344.633-N74 -> -11054.104 | P75: =E75-SUM(M75:O75) -> 14676.552 | R75: =-22632.915-R74 -> -10735.341 | T75: =F75-SUM(Q75:S75) -> 12711.776 | V75: =4229.71-V74 -> -7765.935 | X75: =G75-SUM(U75:W75) -> 21888.994 | Z75: =3383.118-Z74 -> 4965.895 | AB75: =H75-SUM(Y75:AA75) -> 25127.971 | AD75: =5694.953-AD74 -> -7356.538 | AF75: =I75-SUM(AC75:AE75) -> -32539.234 | AH75: =2360.405-AH74 -> 1653.932 | AJ75: =J75-SUM(AG75:AI75) -> -5615.23
B76: FX | C76: 1015.304 | D76: 328.258 | E76: -1582.634 | F76: -516.893 | G76: 791.438 | H76: 397.583 | I76: 119.997 | J76: 23.421 | N76: 268.088 | P76: =E76-SUM(M76:O76) -> -1850.722 | R76: -238.488 | T76: =F76-SUM(Q76:S76) -> -278.405 | V76: 441.812 | X76: =G76-SUM(U76:W76) -> 349.626 | Z76: 468.573 | AB76: =H76-SUM(Y76:AA76) -> -70.99 | AD76: 9.554 | AF76: =I76-SUM(AC76:AE76) -> 110.443 | AH76: -13.817 | AJ76: =J76-SUM(AG76:AI76) -> 37.238
B77: Net change in cash | C77: =SUM(C74:C76) -> 18666.865 | D77: =SUM(D74:D76) -> -4310.286 | E77: =SUM(E74:E76) -> 28832.582 | F77: =SUM(F74:F76) -> -31240.864 | G77: =SUM(G74:G76) -> 4095.682 | H77: =SUM(H74:H76) -> 6024.052 | I77: =SUM(I74:I76) -> 30.129 | J77: =SUM(J74:J76) -> -6747.065 | N77: =SUM(N74:N76) -> -3076.545 | P77: =SUM(P74:P76) -> 31909.127 | R77: =SUM(R74:R76) -> -22871.403 | T77: =SUM(T74:T76) -> -8369.461 | V77: =SUM(V74:V76) -> 4671.522 | X77: =SUM(X74:X76) -> -575.84 | Z77: =SUM(Z74:Z76) -> 3851.691 | AB77: =SUM(AB74:AB76) -> 2172.361 | AD77: =SUM(AD74:AD76) -> 5704.507 | AF77: =SUM(AF74:AF76) -> -5674.378 | AH77: =SUM(AH74:AH76) -> 2346.588 | AJ77: =SUM(AJ74:AJ76) -> -9093.653
B78: Cash and cash equivalents | C78: =11563.282+C77 -> 30230.147 | D78: =C78+D77 -> 25919.861 | E78: =D78+E77 -> 54752.443 | F78: =E78+F77 -> 23511.579 | G78: =F78+G77 -> 27607.261 | H78: =G78+H77 -> 33631.313 | I78: =H78+I77 -> 33661.442 | J78: =I78+J77 -> 26914.377 | N78: =D78+N77 -> 22843.316 | P78: =N78+P77 -> 54752.443 | R78: =E78+R77 -> 31881.04 | T78: =R78+T77 -> 23511.579 | V78: =F78+V77 -> 28183.101 | X78: =V78+X77 -> 27607.261 | Z78: =X78+Z77 -> 31458.952 | AB78: =Z78+AB77 -> 33631.313 | AD78: =AB78+AD77 -> 39335.82 | AF78: =AD78+AF77 -> 33661.442 | AH78: =AF78+AH77 -> 36008.03 | AJ78: =AH78+AJ77 -> 26914.377
B80: check | C80: =+C78-C120 -> -8014.517 | D80: =+D78-D120 -> -37986.433 | E80: =+E78-E120 -> -40772.789 | F80: =+F78-F120 -> -62661.761 | G80: =+G78-G120 -> -40169.726 | H80: =+H78-H120 -> -74076.466 | I80: =+I78-I120 -> -66855.273 | J80: =+J78-J120 -> -80782.212 | N80: =+N78-N120 -> -37500.128 | P80: =+P78-P120 -> -40772.789 | R80: =+R78-R120 -> -61744.62 | T80: =+T78-T120 -> -62661.761 | V80: =+V78-V120 -> -46714.601 | X80: =+X78-X120 -> -40169.726 | Z80: =+Z78-Z120 -> -57811.041 | AB80: =+AB78-AB120 -> -74076.466 | AD80: =+AD78-AD120 -> -58494.579 | AF80: =+AF78-AF120 -> -66855.273 | AH80: =+AH78-AH120 -> -75926.925 | AJ80: =+AJ78-AJ120 -> -80782.212
C81: =-1414.571-(C64+C75)+C63 -> 0 | D81: =23810.354-(D64+D75)+D63 -> -1.2221335e-12 | E81: =21878.5-(E64+E75)+E63 -> -6.8212103e-13 | F81: =9785.288-(F64+F75)+F63 -> 1.0231815e-12 | G81: =-4389.73-(G64+G75)+G63 -> -2.5011104e-12 | H81: =41300.495-(H64+H75)+H63 -> 9.777068e-12 | I81: =39295.499-(I64+I75)+I63 -> 5.4569682e-12 | J81: =34142.377-(J64+J75)+J63 -> 1.6598278e-11 | N81: =-3926.247-(N64+N75)+N63 -> 0 | R81: =8284.324-(R64+R75)+R63 -> -1.080025e-12
B83: LTM | C83: =C3 -> 43465 | D83: =D3 -> 43830 | E83: =E3 -> 44196 | F83: =F3 -> 44561 | G83: =G3 -> 44926 | H83: =H3 -> 45291 | I83: =I3 -> 45657 | J83: =J3 -> 46022 | K83: =K2 -> LTM | M83: =M3 -> 43921 | N83: =N3 -> 44012 | O83: =O3 -> 44104 | P83: =P3 -> 44196 | Q83: =Q3 -> 44286 | R83: =R3 -> 44377 | S83: =S3 -> 44469 | T83: =T3 -> 44561 | ... AK83: =AK3 -> 46112
B84: =B7 -> Revenue | C84: =C7 -> 174915.42 | D84: =D7 -> 205838.68 | E84: =E7 -> 245865.63 | F84: =F7 -> 328309.15 | G84: =G7 -> 280044.02 | H84: =H7 -> 270970.1 | I84: =I7 -> 365906.35 | ... K84: =K7 -> 445134.97 | P84: =SUM(M7:P7) -> 245865.63 | Q84: =SUM(N7:Q7) -> 273045.63 | R84: =SUM(O7:R7) -> 307296.78 | S84: =SUM(P7:S7) -> 313196.86 | T84: =SUM(Q7:T7) -> 328309.15 | U84: =SUM(R7:U7) -> 324778.48 | V84: =SUM(S7:V7) -> 307160.4 | W84: =SUM(T7:W7) -> 299571.81 | ... AK84: =SUM(AH7:AK7) -> 445134.97
B85: Operating profit | C85: =C19 -> 1196.472 | D85: =D19 -> 11760.217 | E85: =E19 -> 24034.729 | F85: =F19 -> 26028.664 | G85: =G19 -> 2816.498 | H85: =H19 -> 20008.7 | I85: =I19 -> 24502.896 | J85: =J19 -> 47900.92 | K85: =K19 -> 40088.158 | P85: =SUM(M19:P19) -> 24034.729 | Q85: =SUM(N19:Q19) -> 29869.204 | R85: =SUM(O19:R19) -> 35181.933 | S85: =SUM(P19:S19) -> 31214.995 | T85: =SUM(Q19:T19) -> 26028.664 | U85: =SUM(R19:U19) -> 16959.738 | V85: =SUM(S19:V19) -> 7967.01 | W85: =SUM(T19:W19) -> 3876.318 | ... AK85: =SUM(AH19:AK19) -> 40088.158
B86: EBITDA | C86: =+C46 -> 1944.688 | D86: =+D46 -> 13141.276 | E86: =+E46 -> 25743.19 | F86: =+F46 -> 29090.31 | G86: =+G46 -> 6523.891 | H86: =+H46 -> 24844.987 | I86: =+I46 -> 30821.165 | J86: =+J46 -> 56657.667 | K86: =+K46 -> 49473.142 | P86: =SUM(M46:P46) -> 25743.19 | Q86: =SUM(N46:Q46) -> 31883.075 | R86: =SUM(O46:R46) -> 37550.728 | S86: =SUM(P46:S46) -> 33990.264 | T86: =SUM(Q46:T46) -> 29090.31 | U86: =SUM(R46:U46) -> 20242.487 | V86: =SUM(S46:V46) -> 11469.131 | W86: =SUM(T46:W46) -> 7509.264 | ... AK86: =SUM(AH46:AK46) -> 49473.142
B87: Adjusted EBITDA | C87: =+C51 -> 1944.688 | D87: =+D51 -> 13141.276 | E87: =+E51 -> 25743.19 | F87: =+F51 -> 29090.31 | G87: =+G51 -> 6523.891 | H87: =+H51 -> 24844.987 | I87: =+I51 -> 30821.165 | J87: =+J51 -> 56657.667 | K87: =+K51 -> 49473.142 | P87: =SUM(M51:P51) -> 25743.19 | Q87: =SUM(N51:Q51) -> 31883.075 | R87: =SUM(O51:R51) -> 37550.728 | S87: =SUM(P51:S51) -> 33990.264 | T87: =SUM(Q51:T51) -> 29090.31 | U87: =SUM(R51:U51) -> 20242.487 | V87: =SUM(S51:V51) -> 11469.131 | W87: =SUM(T51:W51) -> 7509.264 | ... AK87: =SUM(AH51:AK51) -> 49473.142
B88: Cash interest paid | C88: =-C63 -> 243.966 | D88: =-D63 -> 218.994 | E88: =-E63 -> 499.711 | F88: =-F63 -> 659.987 | G88: =-G63 -> 1020.229 | H88: =-H63 -> 758.137 | I88: =-I63 -> 717.223 | J88: =-J63 -> 774.76 | P88: =-SUM(M63:P63) -> 499.711 | R88: =-SUM(O63:R63) -> 618.539 | T88: =-SUM(Q63:T63) -> 659.987 | V88: =-SUM(S63:V63) -> 835.345 | X88: =-SUM(U63:X63) -> 1020.229 | Z88: =-SUM(W63:Z63) -> 883.893 | AB88: =-SUM(Y63:AB63) -> 758.137 | AD88: =-SUM(AA63:AD63) -> 785.216 | AF88: =-SUM(AC63:AF63) -> 717.223 | AH88: =-SUM(AE63:AH63) -> 756.108 | AJ88: =-SUM(AG63:AJ63) -> 774.76
B89: Net Income | C89: =+C25 -> 13477.747 | D89: =+D25 -> 10102.95 | E89: =+E25 -> 20312.71 | F89: =+F25 -> 19283.235 | G89: =+G25 -> 2502.568 | H89: =+H25 -> 17474.226 | I89: =+I25 -> 23578.449 | J89: =+J25 -> 41566.439 | K89: =+K25 -> 35408.27 | P89: =SUM(M25:P25) -> 20312.71 | Q89: =SUM(N25:Q25) -> 25941.723 | R89: =SUM(O25:R25) -> 29711.558 | S89: =SUM(P25:S25) -> 25635.727 | T89: =SUM(Q25:T25) -> 19283.235 | U89: =SUM(R25:U25) -> 10963.774 | V89: =SUM(S25:V25) -> 4065.843 | W89: =SUM(T25:W25) -> 1803.404 | ... AK89: =SUM(AH25:AK25) -> 35408.27
B90: Capex | C90: =-C65 -> 236.222 | D90: =-D65 -> 3337.428 | E90: =-E65 -> 2962.435 | F90: =-F65 -> 7133.948 | G90: =-G65 -> 5782.236 | H90: =-H65 -> 6196.067 | I90: =-I65 -> 6938.819 | J90: =-J65 -> 12756.379 | P90: =-SUM(M65:P65) -> 2962.435 | R90: =-SUM(O65:R65) -> 3659.179 | T90: =-SUM(Q65:T65) -> 7133.948 | V90: =-SUM(S65:V65) -> 8015.006 | X90: =-SUM(U65:X65) -> 5782.236 | Z90: =-SUM(W65:Z65) -> 6740.589 | AB90: =-SUM(Y65:AB65) -> 6196.067 | AD90: =-SUM(AA65:AD65) -> 4548.639 | AF90: =-SUM(AC65:AF65) -> 6938.819 | AH90: =-SUM(AE65:AH65) -> 10003.528 | AJ90: =-SUM(AG65:AJ65) -> 12756.379
B91: Free cash flow | C91: =+C68 -> -3685.771 | D91: =+D68 -> 12736.402 | E91: =+E68 -> 14832.423 | F91: =+F68 -> -1071.559 | G91: =+G68 -> -25340.36 | H91: =+H68 -> 4335.575 | I91: =+I68 -> 71531.445 | J91: =+J68 -> 24560.419 | P91: =SUM(M68:P68) -> 14832.423 | R91: =SUM(O68:R68) -> 25908.659 | T91: =SUM(Q68:T68) -> -1071.559 | V91: =SUM(S68:V68) -> -20413.129 | X91: =SUM(U68:X68) -> -25340.36 | Z91: =SUM(W68:Z68) -> -16274.164 | AB91: =SUM(Y68:AB68) -> 4335.575 | AD91: =SUM(AA68:AD68) -> 5220.313 | AF91: =SUM(AC68:AF68) -> 71531.445 | AH91: =SUM(AE68:AH68) -> 84941.546 | AJ91: =SUM(AG68:AJ68) -> 24560.419
B93: BALANCE SHEET | C93: =C3 -> 43465 | D93: =D3 -> 43830 | E93: =E3 -> 44196 | F93: =F3 -> 44561 | G93: =G3 -> 44926 | H93: =H3 -> 45291 | I93: =I3 -> 45657 | J93: =J3 -> 46022 | K93: =K2 -> LTM | M93: =M3 -> 43921 | N93: =N3 -> 44012 | O93: =O3 -> 44104 | P93: =P3 -> 44196 | Q93: =Q3 -> 44286 | R93: =R3 -> 44377 | S93: =S3 -> 44469 | T93: =T3 -> 44561 | ... AK93: =AK3 -> 46112
B95: Tangible fixed assets | C95: =3402.968+5068.053 -> 8471.021 | D95: 6992.331 | E95: 6305.657 | F95: 6964.621 | G95: 9138.221 | H95: 13720.825 | I95: 18087.583 | J95: 27950.293 | K95: =AK95 -> 28746.276 | M95: 7237.359 | N95: 8001.825 | O95: 6990.443 | P95: =E95 -> 6305.657 | Q95: 6652.138 | R95: 6987.166 | S95: 7135.251 | T95: =F95 -> 6964.621 | U95: 7223.932 | V95: 7674.223 | W95: 8466.094 | X95: =G95 -> 9138.221 | Y95: 9722.141 | Z95: 12019.697 | AA95: 12707.66 | AB95: =H95 -> 13720.825 | AC95: 14324.16 | AD95: 15779.911 | AE95: 16154.692 | AF95: =I95 -> 18087.583 | AG95: 19585.867 | AH95: 22212.155 | AI95: 25069.729 | AJ95: =J95 -> 27950.293 | AK95: 28746.276
B96: Inventory | C96: 29480.685 | D96: 32585.438 | E96: 41670.719 | F96: 52397.946 | G96: 50437.891 | H96: 44422.837 | I96: 62509.682 | J96: 80989.452 | K96: =AK96 -> 78186.312 | M96: 34111.461 | N96: 38856.939 | O96: 34996.234 | P96: =E96 -> 41670.719 | Q96: 49537.348 | R96: 56801.934 | S96: 58181.844 | T96: =F96 -> 52397.946 | U96: 56144.7 | V96: 57798.719 | W96: 52997.434 | X96: =G96 -> 50437.891 | Y96: 42595.212 | Z96: 38454.691 | AA96: 36842.283 | AB96: =H96 -> 44422.837 | AC96: 51918.525 | AD96: 51524.154 | AE96: 49313.196 | AF96: =I96 -> 62509.682 | AG96: 61416.913 | AH96: 65825.475 | AI96: 73995.731 | AJ96: =J96 -> 80989.452 | AK96: 78186.312
B97: Trade accounts receivable | C97: 5598.443 | D97: 6948.567 | E97: 10161.019 | F97: 17985.503 | G97: 11795.074 | H97: 12150.928 | I97: 14588.579 | J97: 15239.877 | K97: =AK97 -> 17782.583 | M97: 7819.38 | N97: 8472.074 | O97: 13482.432 | P97: =E97 -> 10161.019 | Q97: 12638.874 | R97: 14621.462 | S97: 14107.616 | T97: =F97 -> 17985.503 | U97: 17239.735 | V97: 15196.628 | W97: 14531.181 | X97: =G97 -> 11795.074 | Y97: 11140.264 | Z97: 12541.275 | AA97: 13677.498 | AB97: =H97 -> 12150.928 | AC97: 11213.539 | AD97: 13648.816 | AE97: 14372.495 | AF97: =I97 -> 14588.579 | AG97: 17285.786 | AH97: 18845.26 | AI97: 22637.428 | AJ97: =J97 -> 15239.877 | AK97: 17782.583
B98: Trade accounts payable | C98: 46287.271 | D98: 59527.94 | E98: 72198.856 | F98: 74643.005 | G98: 53093.543 | H98: 62098.5 | I98: 98280.585 | J98: 110699.47 | K98: =AK98 -> 104936.29 | M98: 53910.21 | N98: 60433.835 | O98: 63256.578 | P98: =E98 -> 72198.856 | Q98: 82306.095 | R98: 91373.987 | S98: 73355.847 | T98: =F98 -> 74643.005 | U98: 74874.543 | V98: 69680.442 | W98: 58946.062 | X98: =G98 -> 53093.543 | Y98: 41584.877 | Z98: 55106.248 | AA98: 54682.769 | AB98: =H98 -> 62098.5 | AC98: 60547.077 | AD98: 66772.473 | AE98: 68688.815 | AF98: =I98 -> 98280.585 | AG98: 93753.96 | AH98: 108393.32 | AI98: 116808.74 | AJ98: =J98 -> 110699.47 | AK98: 104936.29
B99: Net working capital | C99: =+C96+C97-C98 -> -11208.143 | D99: =+D96+D97-D98 -> -19993.935 | E99: =+E96+E97-E98 -> -20367.118 | F99: =+F96+F97-F98 -> -4259.556 | G99: =+G96+G97-G98 -> 9139.422 | H99: =+H96+H97-H98 -> -5524.735 | I99: =+I96+I97-I98 -> -21182.324 | J99: =+J96+J97-J98 -> -14470.143 | K99: =+K96+K97-K98 -> -8967.394 | M99: =+M96+M97-M98 -> -11979.369 | N99: =+N96+N97-N98 -> -13104.822 | O99: =+O96+O97-O98 -> -14777.912 | P99: =+P96+P97-P98 -> -20367.118 | Q99: =+Q96+Q97-Q98 -> -20129.873 | R99: =+R96+R97-R98 -> -19950.591 | S99: =+S96+S97-S98 -> -1066.387 | T99: =+T96+T97-T98 -> -4259.556 | ... AK99: =+AK96+AK97-AK98 -> -8967.394
B100: % of revenues | C100: =+C99/C84 -> -0.064077499 | D100: =+D99/D84 -> -0.097134002 | E100: =+E99/E84 -> -0.08283841 | F100: =+F99/F84 -> -0.012974223 | G100: =+G99/G84 -> 0.032635663 | H100: =+H99/H84 -> -0.020388726 | I100: =+I99/I84 -> -0.057890015 | J100: =+J99/J84 -> -0.031643482 | K100: =+K99/K84 -> -0.020145337 | P100: =+P99/P84 -> -0.08283841 | Q100: =+Q99/Q84 -> -0.073723476 | R100: =+R99/R84 -> -0.064922876 | S100: =+S99/S84 -> -0.0034048457 | T100: =+T99/T84 -> -0.012974223 | U100: =+U99/U84 -> -0.0045880749 | V100: =+V99/V84 -> 0.010792098 | W100: =+W99/W84 -> 0.028649401 | ... AK100: =+AK99/AK84 -> -0.020145337
B102: Inventory Days | C102: =IFERROR((C96/-C9)*365,"-") -> 70.457074 | D102: =IFERROR((D96/-D9)*365,"-") -> 67.08807 | E102: =IFERROR((E96/-E9)*365,"-") -> 72.734628 | F102: =IFERROR((F96/-F9)*365,"-") -> 70.821616 | G102: =IFERROR((G96/-G9)*365,"-") -> 79.193365 | H102: =IFERROR((H96/-H9)*365,"-") -> 75.947535 | I102: =IFERROR((I96/-I9)*365,"-") -> 78.853765 | J102: =IFERROR((J96/-J9)*365,"-") -> 83.158209 | K102: =IFERROR((K96/-K9)*365,"-") -> 82.259887 | M102: =IFERROR((M96/-M9)*(365/4),"-") -> 73.858491 | N102: =IFERROR((N96/-N9)*(365/4),"-") -> 77.355527 | O102: =IFERROR((O96/-O9)*(365/4),"-") -> 51.508946 | P102: =IFERROR((P96/-P9)*(365/4),"-") -> 64.299509 | Q102: =IFERROR((Q96/-Q9)*(365/4),"-") -> 72.069768 | R102: =IFERROR((R96/-R9)*(365/4),"-") -> 71.3534 | S102: =IFERROR((S96/-S9)*(365/4),"-") -> 83.252948 | T102: =IFERROR((T96/-T9)*(365/4),"-") -> 67.422464 | ... AK102: =IFERROR((AK96/-AK9)*(365/4),"-") -> 92.258668
B103: Receivable Days | C103: =IFERROR((C97/C7)*365,"-") -> 11.682398 | D103: =IFERROR((D97/D7)*365,"-") -> 12.32143 | E103: =IFERROR((E97/E7)*365,"-") -> 15.084548 | F103: =IFERROR((F97/F7)*365,"-") -> 19.995509 | G103: =IFERROR((G97/G7)*365,"-") -> 15.373305 | H103: =IFERROR((H97/H7)*365,"-") -> 16.367447 | I103: =IFERROR((I97/I7)*365,"-") -> 14.552443 | J103: =IFERROR((J97/J7)*365,"-") -> 12.164262 | K103: =IFERROR((K97/K7)*365,"-") -> 14.581292 | M103: =IFERROR((M97/M7)*(365/4),"-") -> 14.355882 | N103: =IFERROR((N97/N7)*(365/4),"-") -> 14.439829 | O103: =IFERROR((O97/O7)*(365/4),"-") -> 17.048567 | P103: =IFERROR((P97/P7)*(365/4),"-") -> 13.158601 | Q103: =IFERROR((Q97/Q7)*(365/4),"-") -> 15.000843 | R103: =IFERROR((R97/R7)*(365/4),"-") -> 15.197907 | S103: =IFERROR((S97/S7)*(365/4),"-") -> 16.490813 | T103: =IFERROR((T97/T7)*(365/4),"-") -> 19.178194 | ... AK103: =IFERROR((AK97/AK7)*(365/4),"-") -> 16.367099
B104: Payable Days | C104: =IFERROR((C98/-C9)*365,"-") -> 110.62381 | D104: =IFERROR((D98/-D9)*365,"-") -> 122.55826 | E104: =IFERROR((E98/-E9)*365,"-") -> 126.02031 | F104: =IFERROR((F98/-F9)*365,"-") -> 100.88827 | G104: =IFERROR((G98/-G9)*365,"-") -> 83.363048 | H104: =IFERROR((H98/-H9)*365,"-") -> 106.16675 | I104: =IFERROR((I98/-I9)*365,"-") -> 123.9775 | J104: =IFERROR((J98/-J9)*365,"-") -> 113.66381 | K104: =IFERROR((K98/-K9)*365,"-") -> 110.40356 | M104: =IFERROR((M98/-M9)*(365/4),"-") -> 116.72695 | N104: =IFERROR((N98/-N9)*(365/4),"-") -> 120.31033 | O104: =IFERROR((O98/-O9)*(365/4),"-") -> 93.103722 | P104: =IFERROR((P98/-P9)*(365/4),"-") -> 111.40559 | Q104: =IFERROR((Q98/-Q9)*(365/4),"-") -> 119.74362 | R104: =IFERROR((R98/-R9)*(365/4),"-") -> 114.78209 | S104: =IFERROR((S98/-S9)*(365/4),"-") -> 104.96557 | T104: =IFERROR((T98/-T9)*(365/4),"-") -> 96.046042 | ... AK104: =IFERROR((AK98/-AK9)*(365/4),"-") -> 123.82324
B106: Debt Breakdown
B107: Short-term debt | C107: 3075.194 | D107: 12836.555 | E107: 6961.937 | F107: 5527.05 | G107: 2150.741 | H107: 6183.376 | I107: 13327.297 | J107: 13202.226 | K107: =AK107 -> 10360.504 | M107: 11129.841 | N107: 13408.668 | O107: 11385.21 | P107: =E107 -> 6961.937 | Q107: 7392.181 | R107: 6051.582 | S107: 4891.758 | T107: =F107 -> 5527.05 | U107: 9221.716 | V107: 7094.778 | W107: 2517.215 | X107: =G107 -> 2150.741 | Y107: 1583.363 | Z107: 1122.048 | AA107: 2060.828 | AB107: =H107 -> 6183.376 | AC107: 5034.168 | AD107: 8943.685 | AE107: 4944.089 | AF107: =I107 -> 13327.297 | AG107: 12713.769 | AH107: 10640.895 | AI107: 9588.872 | AJ107: =J107 -> 13202.226 | AK107: 10360.504
B108: Long-term debt | C108: 7856.143 | D108: 4786.856 | E108: 10634.806 | F108: 20719.79 | G108: 21493.261 | H108: 21673.969 | I108: 17275.721 | J108: 22921.433 | K108: =AK108 -> 25006.733 | M108: 5351.211 | N108: 9995.908 | O108: 7183.648 | P108: =E108 -> 10634.806 | Q108: 13612.704 | R108: 13262.146 | S108: 21006.592 | T108: =F108 -> 20719.79 | U108: 20492.213 | V108: 25474.316 | W108: 23244.484 | X108: =G108 -> 21493.261 | Y108: 20880.846 | Z108: 21763.554 | AA108: 22774.352 | AB108: =H108 -> 21673.969 | AC108: 22671.729 | AD108: 21037.527 | AE108: 22416.058 | AF108: =I108 -> 17275.721 | AG108: 18230.916 | AH108: 18271.941 | AI108: 18000.079 | AJ108: =J108 -> 22921.433 | AK108: 25006.733
B109: Total Debt | C109: =SUM(C107:C108) -> 10931.337 | D109: =SUM(D107:D108) -> 17623.411 | E109: =SUM(E107:E108) -> 17596.743 | F109: =SUM(F107:F108) -> 26246.84 | G109: =SUM(G107:G108) -> 23644.002 | H109: =SUM(H107:H108) -> 27857.345 | I109: =SUM(I107:I108) -> 30603.018 | J109: =SUM(J107:J108) -> 36123.659 | K109: =SUM(K107:K108) -> 35367.237 | M109: =SUM(M107:M108) -> 16481.052 | N109: =SUM(N107:N108) -> 23404.576 | O109: =SUM(O107:O108) -> 18568.858 | P109: =SUM(P107:P108) -> 17596.743 | Q109: =SUM(Q107:Q108) -> 21004.885 | R109: =SUM(R107:R108) -> 19313.728 | S109: =SUM(S107:S108) -> 25898.35 | T109: =SUM(T107:T108) -> 26246.84 | ... AK109: =SUM(AK107:AK108) -> 35367.237
B111: Lease Obligations
B112: Short-term | C112: 285.402 | D112: 399.444 | E112: 363.397 | F112: 1532.625 | G112: 947.392 | H112: 712.011 | I112: 2238.842 | J112: 2079.368 | K112: =AK112 -> 0 | P112: =E112 -> 363.397 | T112: =F112 -> 1532.625 | V112: 962.826 | X112: =G112 -> 947.392 | Z112: 771.015 | AB112: =H112 -> 712.011 | AD112: 1802.622 | AF112: =I112 -> 2238.842 | AJ112: =J112 -> 2079.368
B113: Long-term | C113: 573.431 | D113: 560.804 | E113: 516.482 | F113: 1748.529 | G113: 1464.736 | H113: 1256.155 | I113: 3169.514 | J113: 3634.869 | K113: =AK113 -> 0 | P113: =E113 -> 516.482 | T113: =F113 -> 1748.529 | V113: 1997.489 | X113: =G113 -> 1464.736 | Z113: 1287.867 | AB113: =H113 -> 1256.155 | AD113: 2564.811 | AF113: =I113 -> 3169.514 | AJ113: =J113 -> 3634.869
B114: Total Lease | C114: =SUM(C112:C113) -> 858.833 | D114: =SUM(D112:D113) -> 960.248 | E114: =SUM(E112:E113) -> 879.879 | F114: =SUM(F112:F113) -> 3281.154 | G114: =SUM(G112:G113) -> 2412.128 | H114: =SUM(H112:H113) -> 1968.166 | I114: =SUM(I112:I113) -> 5408.356 | J114: =SUM(J112:J113) -> 5714.237 | K114: =SUM(K112:K113) -> 0 | M114: =SUM(M112:M113) -> 0 | N114: =SUM(N112:N113) -> 0 | O114: =SUM(O112:O113) -> 0 | P114: =SUM(P112:P113) -> 879.879 | Q114: =SUM(Q112:Q113) -> 0 | R114: =SUM(R112:R113) -> 0 | S114: =SUM(S112:S113) -> 0 | T114: =SUM(T112:T113) -> 3281.154 | ... AK114: =SUM(AK112:AK113) -> 0
...

Sheet KPIs
B2: Xiaomi Corporation | C2: Annual | D2: Annual | E2: Annual | F2: Annual | G2: Annual | H2: Annual | I2: Annual | J2: Annual | K2: LTM | M2: Quarters | N2: Quarters | O2: Quarters | P2: Quarters | Q2: Quarters | R2: Quarters | S2: Quarters | T2: Quarters | U2: Quarters | V2: Quarters | W2: Quarters | X2: Quarters | Y2: Quarters | Z2: Quarters | AA2: Quarters | AB2: Quarters | AC2: Quarters | AD2: Quarters | AE2: Quarters | AF2: Quarters | AG2: Quarters | AH2: Quarters | AI2: Quarters | AJ2: Quarters | AK2: Quarters
B3: (RMB millions) | C3: 43465 | D3: 43830 | E3: 44196 | F3: 44561 | G3: 44926 | H3: 45291 | I3: 45657 | J3: 46022 | K3: =AK3 -> 46112 | M3: 43921 | N3: 44012 | O3: 44104 | P3: 44196 | Q3: 44286 | R3: 44377 | S3: 44469 | T3: 44561 | U3: 44651 | V3: 44742 | W3: 44834 | X3: 44926 | Y3: 45016 | Z3: 45107 | AA3: 45199 | AB3: 45291 | AC3: 45382 | AD3: 45473 | AE3: 45565 | AF3: 45657 | AG3: 45747 | AH3: 45838 | AI3: 45930 | AJ3: 46022 | AK3: 46112
C4: Act | D4: Act | E4: Act | F4: Act | G4: Act | H4: Act | I4: Act | J4: Act | K4: Act | M4: Act | N4: Act | O4: Act | P4: Act | Q4: Act | R4: Act | S4: Act | T4: Act | U4: Act | V4: Act | W4: Act | X4: Act | Y4: Act | Z4: Act | AA4: Act | AB4: Act | AC4: Act | AD4: Act | AE4: Act | AF4: Act | AG4: Act | AH4: Act | AI4: Act | AJ4: Act | AK4: Act
C5: FY | D5: FY | E5: FY | F5: FY | G5: FY | H5: FY | I5: FY | J5: FY | K5: LTM | M5: 1Q | N5: 2Q | O5: 3Q | P5: 4Q | Q5: 1Q | R5: 2Q | S5: 3Q | T5: 4Q | U5: 1Q | V5: 2Q | W5: 3Q | X5: 4Q | Y5: 1Q | Z5: 2Q | AA5: 3Q | AB5: 4Q | AC5: 1Q | AD5: 2Q | AE5: 3Q | AF5: 4Q | AG5: 1Q | AH5: 2Q | AI5: 3Q | AJ5: 4Q | AK5: 1Q
B8: Revenue by segment
B9: Smartphones | C9: 113800.39 | D9: 122094.9 | E9: 152190.89 | F9: 208868.94 | G9: 167217.18 | H9: 157461.3 | I9: 191759.3 | J9: 186439.78 | K9: =SUM(AH9:AK9) -> 180101.16 | M9: 30324.723 | N9: 31627.549 | O9: 47604.133 | P9: =E9-SUM(M9:O9) -> 42634.486 | Q9: 51490.983 | R9: 59088.963 | S9: 47824.932 | T9: =F9-SUM(Q9:S9) -> 50464.066 | U9: 45762.689 | V9: 42268.105 | W9: 42514.239 | X9: =G9-SUM(U9:W9) -> 36672.144 | Y9: 34984.746 | Z9: 36595.461 | AA9: 41648.925 | AB9: =H9-SUM(Y9:AA9) -> 44232.168 | AC9: 46479.748 | AD9: 46516.4 | AE9: 47452.324 | AF9: =I9-SUM(AC9:AE9) -> 51310.828 | AG9: 50611.952 | AH9: 45520.009 | AI9: 45969.027 | AJ9: =J9-SUM(AG9:AI9) -> 44338.789 | AK9: 44273.331
B10: IoT and lifestyle products | C10: 43816.885 | D10: 62087.998 | E10: 67410.453 | F10: 84980.097 | G10: 79794.877 | H10: 80107.7 | I10: 104103.9 | J10: 123200.19 | K10: =SUM(AH10:AK10) -> 115542.11 | M10: 12984.208 | N10: 15252.868 | O10: 18119.021 | P10: =E10-SUM(M10:O10) -> 21054.356 | Q10: 18243.267 | R10: 20734.693 | S10: 20935.557 | T10: =F10-SUM(Q10:S10) -> 25066.58 | U10: 19477.357 | V10: 19811.608 | W10: 19058.648 | X10: =G10-SUM(U10:W10) -> 21447.264 | Y10: 16833.782 | Z10: 22253.866 | AA10: 20673.297 | AB10: =H10-SUM(Y10:AA10) -> 20346.755 | AC10: 20373.489 | AD10: 26760.3 | AE10: 26102.162 | AF10: =I10-SUM(AC10:AE10) -> 30867.949 | AG10: 32339.234 | AH10: 38712.153 | AI10: 27552.155 | AJ10: =J10-SUM(AG10:AI10) -> 24596.649 | AK10: 24681.157
B11: Internet services | C11: 15955.558 | D11: 19841.569 | E11: 23755.285 | F11: 28211.739 | G11: 28321.444 | H11: 30107.5 | I11: 34115.4 | J11: 37440.346 | K11: =SUM(AH11:AK11) -> 37832.595 | M11: 5900.696 | N11: 5907.621 | O11: 5771.89 | P11: =E11-SUM(M11:O11) -> 6175.078 | Q11: 6570.848 | R11: 7033.487 | S11: 7337.857 | T11: =F11-SUM(Q11:S11) -> 7269.547 | U11: 7112.481 | V11: 6971.121 | W11: 7066.591 | X11: =G11-SUM(U11:W11) -> 7171.251 | Y11: 7028.148 | Z11: 7444.079 | AA11: 7755.534 | AB11: =H11-SUM(Y11:AA11) -> 7879.739 | AC11: 8048.383 | AD11: 8265.6 | AE11: 8462.807 | AF11: =I11-SUM(AC11:AE11) -> 9338.61 | AG11: 9076.097 | AH11: 9097.747 | AI11: 9380.464 | AJ11: =J11-SUM(AG11:AI11) -> 9886.038 | AK11: 9468.346
B12: Smart EV and other new initiatives | I12: 32753.6 | J12: 106069.51 | K12: =SUM(AH12:AK12) -> 107353.87 | AC12: 26.032 | AD12: 6368.8 | AE12: 9697.134 | AF12: =I12-SUM(AC12:AE12) -> 16661.634 | AG12: 18580.065 | AH12: 21263.264 | AI12: 29010.088 | AJ12: =J12-SUM(AG12:AI12) -> 37216.096 | AK12: 19864.417
B13: Others | C13: 1342.596 | D13: 1814.218 | E13: 2509.004 | F13: 6248.365 | G13: 4710.518 | H13: 3293.6 | I13: 3174.2 | J13: 4136.86 | K13: =SUM(AH13:AK13) -> 4305.238 | M13: 492.54 | N13: 749.767 | O13: 667.733 | P13: =E13-SUM(M13:O13) -> 598.964 | Q13: 577.065 | R13: 931.817 | S13: 1964.509 | T13: =F13-SUM(Q13:S13) -> 2774.974 | U13: 998.975 | V13: 1120.043 | W13: 1834.791 | X13: =G13-SUM(U13:W13) -> 756.709 | Y13: 630.458 | Z13: 1061.502 | AA13: 816.656 | AB13: =H13-SUM(Y13:AA13) -> 784.984 | AC13: 579.17 | AD13: =976.7 -> 976.7 | AE13: =792.114 -> 792.114 | AF13: =I13-SUM(AC13:AE13) -> 826.216 | AG13: 685.989 | AH13: =1362.918 -> 1362.918 | AI13: =(1209000)/1000 -> 1209 | AJ13: =J13-SUM(AG13:AI13) -> 878.953 | AK13: 854.367
B14: Net Revenue | C14: =SUM(C9:C13) -> 174915.42 | D14: =SUM(D9:D13) -> 205838.68 | E14: =SUM(E9:E13) -> 245865.63 | F14: =SUM(F9:F13) -> 328309.14 | G14: =SUM(G9:G13) -> 280044.02 | H14: =SUM(H9:H13) -> 270970.1 | I14: =SUM(I9:I13) -> 365906.4 | J14: =SUM(J9:J13) -> 457286.69 | K14: =SUM(K9:K13) -> 445134.97 | M14: =SUM(M9:M13) -> 49702.167 | N14: =SUM(N9:N13) -> 53537.805 | O14: =SUM(O9:O13) -> 72162.777 | P14: =SUM(P9:P13) -> 70462.884 | Q14: =SUM(Q9:Q13) -> 76882.163 | R14: =SUM(R9:R13) -> 87788.96 | S14: =SUM(S9:S13) -> 78062.855 | T14: =SUM(T9:T13) -> 85575.167 | ... AK14: =SUM(AK9:AK13) -> 99141.618
B15: check | C15: =C14-Model!C7 -> 0 | D15: =D14-Model!D7 -> 0 | E15: =E14-Model!E7 -> 0 | F15: =F14-Model!F7 -> 0 | G15: =G14-Model!G7 -> 0 | H15: =H14-Model!H7 -> 0 | I15: =I14-Model!I7 -> 0.05 | J15: =J14-Model!J7 -> 0 | K15: =K14-Model!K7 -> 0 | M15: =M14-Model!M7 -> 0 | N15: =N14-Model!N7 -> 0 | O15: =O14-Model!O7 -> 0 | P15: =P14-Model!P7 -> 0 | Q15: =Q14-Model!Q7 -> 0 | R15: =R14-Model!R7 -> 0 | S15: =S14-Model!S7 -> 0 | T15: =T14-Model!T7 -> 0 | ... AK15: =AK14-Model!AK7 -> 0
B17: Revenue by segment (% Share)
B18: Smartphones | C18: =C9/C$14 -> 0.65060235 | D18: =D9/D$14 -> 0.59315818 | E18: =E9/E$14 -> 0.61900026 | F18: =F9/F$14 -> 0.63619594 | G18: =G9/G$14 -> 0.59711034 | H18: =H9/H$14 -> 0.58110212 | I18: =I9/I$14 -> 0.52406654 | J18: =J9/J$14 -> 0.40770874 | K18: =K9/K$14 -> 0.40459898 | M18: =M9/M$14 -> 0.61012879 | N18: =N9/N$14 -> 0.59075169 | O18: =O9/O$14 -> 0.65967712 | P18: =P9/P$14 -> 0.60506303 | Q18: =Q9/Q$14 -> 0.669739 | R18: =R9/R$14 -> 0.67307966 | S18: =S9/S$14 -> 0.61264646 | T18: =T9/T$14 -> 0.58970456 | ... AK18: =AK9/AK$14 -> 0.44656656
B19: IoT and lifestyle products | C19: =C10/C$14 -> 0.25050326 | D19: =D10/D$14 -> 0.30163426 | E19: =E10/E$14 -> 0.27417599 | F19: =F10/F$14 -> 0.2588417 | G19: =G10/G$14 -> 0.28493691 | H19: =H10/H$14 -> 0.29563299 | I19: =I10/I$14 -> 0.28450965 | J19: =J10/J$14 -> 0.26941565 | K19: =K10/K$14 -> 0.25956647 | M19: =M10/M$14 -> 0.26124028 | N19: =N10/N$14 -> 0.28489902 | O19: =O10/O$14 -> 0.25108542 | P19: =P10/P$14 -> 0.29880066 | Q19: =Q10/Q$14 -> 0.23728868 | R19: =R10/R$14 -> 0.23618793 | S19: =S10/S$14 -> 0.26818846 | T19: =T10/T$14 -> 0.29291886 | ... AK19: =AK10/AK$14 -> 0.2489485
B20: Internet services | C20: =C11/C$14 -> 0.091218702 | D20: =D11/D$14 -> 0.096393782 | E20: =E11/E$14 -> 0.096618973 | F20: =F11/F$14 -> 0.085930409 | G20: =G11/G$14 -> 0.10113212 | H20: =H11/H$14 -> 0.11111004 | I20: =I11/I$14 -> 0.093235319 | J20: =J11/J$14 -> 0.081874997 | K20: =K11/K$14 -> 0.08499129 | M20: =M11/M$14 -> 0.1187211 | N20: =N11/N$14 -> 0.11034485 | O20: =O11/O$14 -> 0.079984311 | P20: =P11/P$14 -> 0.087635896 | Q20: =Q11/Q$14 -> 0.085466482 | R20: =R11/R$14 -> 0.080118126 | S20: =S11/S$14 -> 0.093999342 | T20: =T11/T$14 -> 0.084949259 | ... AK20: =AK11/AK$14 -> 0.095503243
B21: Smart EV and other new initiatives | C21: =C12/C$14 -> 0 | D21: =D12/D$14 -> 0 | E21: =E12/E$14 -> 0 | F21: =F12/F$14 -> 0 | G21: =G12/G$14 -> 0 | H21: =H12/H$14 -> 0 | I21: =I12/I$14 -> 0.089513602 | J21: =J12/J$14 -> 0.23195408 | K21: =K12/K$14 -> 0.24117149 | M21: =M12/M$14 -> 0 | N21: =N12/N$14 -> 0 | O21: =O12/O$14 -> 0 | P21: =P12/P$14 -> 0 | Q21: =Q12/Q$14 -> 0 | R21: =R12/R$14 -> 0 | S21: =S12/S$14 -> 0 | T21: =T12/T$14 -> 0 | ... AK21: =AK12/AK$14 -> 0.20036406
B22: Others | C22: =C13/C$14 -> 0.0076756867 | D22: =D13/D$14 -> 0.0088137855 | E22: =E13/E$14 -> 0.010204777 | F22: =F13/F$14 -> 0.019031955 | G22: =G13/G$14 -> 0.016820634 | H22: =H13/H$14 -> 0.012154847 | I22: =I13/I$14 -> 0.0086748961 | J22: =J13/J$14 -> 0.009046535 | K22: =K13/K$14 -> 0.0096717587 | M22: =M13/M$14 -> 0.0099098295 | N22: =N13/N$14 -> 0.01400444 | O22: =O13/O$14 -> 0.00925315 | P22: =P13/P$14 -> 0.0085004185 | Q22: =Q13/Q$14 -> 0.0075058372 | R22: =R13/R$14 -> 0.010614285 | S22: =S13/S$14 -> 0.025165733 | T22: =T13/T$14 -> 0.032427328 | ... AK22: =AK13/AK$14 -> 0.0086176423
B23: Net Revenue | C23: =SUM(C18:C22) -> 1 | D23: =SUM(D18:D22) -> 1 | E23: =SUM(E18:E22) -> 1 | F23: =SUM(F18:F22) -> 1 | G23: =SUM(G18:G22) -> 1 | H23: =SUM(H18:H22) -> 1 | I23: =SUM(I18:I22) -> 1 | J23: =SUM(J18:J22) -> 1 | K23: =SUM(K18:K22) -> 1 | M23: =SUM(M18:M22) -> 1 | N23: =SUM(N18:N22) -> 1 | O23: =SUM(O18:O22) -> 1 | P23: =SUM(P18:P22) -> 1 | Q23: =SUM(Q18:Q22) -> 1 | R23: =SUM(R18:R22) -> 1 | S23: =SUM(S18:S22) -> 1 | T23: =SUM(T18:T22) -> 1 | ... AK23: =SUM(AK18:AK22) -> 1
B25: Revenue by segment (YoY % Growth)
B26: Smartphones | D26: =D9/C9-1 -> 0.072886493 | E26: =E9/D9-1 -> 0.24649674 | F26: =F9/E9-1 -> 0.37241423 | G26: =G9/F9-1 -> -0.1994158 | H26: =H9/G9-1 -> -0.058342553 | I26: =I9/H9-1 -> 0.2178186 | J26: =J9/I9-1 -> -0.027740626 | Q26: =Q9/M9-1 -> 0.69798692 | R26: =R9/N9-1 -> 0.86827512 | S26: =S9/O9-1 -> 0.0046382317 | T26: =T9/P9-1 -> 0.18364429 | U26: =U9/Q9-1 -> -0.11124849 | V26: =V9/R9-1 -> -0.28467005 | W26: =W9/S9-1 -> -0.11104444 | X26: =X9/T9-1 -> -0.27330184 | ... AK26: =AK9/AG9-1 -> -0.12523961
B27: IoT and lifestyle products | D27: =D10/C10-1 -> 0.41698795 | E27: =E10/D10-1 -> 0.085724378 | F27: =F10/E10-1 -> 0.26063679 | G27: =G10/F10-1 -> -0.061016876 | H27: =H10/G10-1 -> 0.0039203394 | I27: =I10/H10-1 -> 0.29954923 | J27: =J10/I10-1 -> 0.18343492 | Q27: =Q10/M10-1 -> 0.40503502 | R27: =R10/N10-1 -> 0.35939634 | S27: =S10/O10-1 -> 0.15544637 | T27: =T10/P10-1 -> 0.19056503 | U27: =U10/Q10-1 -> 0.067646327 | V27: =V10/R10-1 -> -0.044518865 | W27: =W10/S10-1 -> -0.089651735 | X27: =X10/T10-1 -> -0.14438811 | ... AK27: =AK10/AG10-1 -> -0.23680453
B28: Internet services | D28: =D11/C11-1 -> 0.24355218 | E28: =E11/D11-1 -> 0.19724831 | F28: =F11/E11-1 -> 0.18759842 | G28: =G11/F11-1 -> 0.0038886295 | H28: =H11/G11-1 -> 0.063063734 | I28: =I11/H11-1 -> 0.13311965 | J28: =J11/I11-1 -> 0.097461733 | Q28: =Q11/M11-1 -> 0.11357169 | R28: =R11/N11-1 -> 0.19057858 | S28: =S11/O11-1 -> 0.27130922 | T28: =T11/P11-1 -> 0.1772397 | U28: =U11/Q11-1 -> 0.082429696 | V28: =V11/R11-1 -> -0.0088670101 | W28: =W11/S11-1 -> -0.036968014 | X28: =X11/T11-1 -> -0.013521613 | ... AK28: =AK11/AG11-1 -> 0.043217806
B29: Smart EV and other new initiatives | D29: =D12/C12-1 -> #DIV/0! | E29: =E12/D12-1 -> #DIV/0! | F29: =F12/E12-1 -> #DIV/0! | G29: =G12/F12-1 -> #DIV/0! | H29: =H12/G12-1 -> #DIV/0! | I29: =I12/H12-1 -> #DIV/0! | J29: =J12/I12-1 -> 2.2384078 | Q29: =Q12/M12-1 -> #DIV/0! | R29: =R12/N12-1 -> #DIV/0! | S29: =S12/O12-1 -> #DIV/0! | T29: =T12/P12-1 -> #DIV/0! | U29: =U12/Q12-1 -> #DIV/0! | V29: =V12/R12-1 -> #DIV/0! | W29: =W12/S12-1 -> #DIV/0! | X29: =X12/T12-1 -> #DIV/0! | ... AK29: =AK12/AG12-1 -> 0.069125269
B30: Others | D30: =D13/C13-1 -> 0.35127618 | E30: =E13/D13-1 -> 0.38296721 | F30: =F13/E13-1 -> 1.4903767 | G30: =G13/F13-1 -> -0.2461199 | H30: =H13/G13-1 -> -0.30079877 | I30: =I13/H13-1 -> -0.036252125 | J30: =J13/I13-1 -> 0.30327642 | Q30: =Q13/M13-1 -> 0.17161043 | R30: =R13/N13-1 -> 0.24280877 | S30: =S13/O13-1 -> 1.9420577 | T30: =T13/P13-1 -> 3.6329562 | U30: =U13/Q13-1 -> 0.73113081 | V30: =V13/R13-1 -> 0.20199889 | W30: =W13/S13-1 -> -0.066030749 | X30: =X13/T13-1 -> -0.72730952 | ... AK30: =AK13/AG13-1 -> 0.24545292
B31: Net Revenue | D31: =D14/C14-1 -> 0.17678977 | E31: =E14/D14-1 -> 0.19445787 | F31: =F14/E14-1 -> 0.33531938 | G31: =G14/F14-1 -> -0.14701122 | H31: =H14/G14-1 -> -0.032401749 | I31: =I14/H14-1 -> 0.35035711 | J31: =J14/I14-1 -> 0.24973678 | Q31: =Q14/M14-1 -> 0.54685736 | R31: =R14/N14-1 -> 0.63975643 | S31: =S14/O14-1 -> 0.081760684 | T31: =T14/P14-1 -> 0.21447154 | U31: =U14/Q14-1 -> -0.045923019 | V31: =V14/R14-1 -> -0.20068677 | W31: =W14/S14-1 -> -0.097211228 | X31: =X14/T14-1 -> -0.22819469 | ... AK31: =AK14/AG14-1 -> -0.1091864
B35: Revenue by geography
B36: Mainland China | C36: 104944.8 | D36: 114608.63 | E36: 123484.25 | F36: 164717.7 | G36: 142258.42 | H36: 149189.72 | I36: 212562.45 | J36: 306223.14 | K36: =SUM(AH36:AK36) -> 292725.42 | M36: 24870.044 | N36: 29509.195 | O36: 32393.887 | P36: =E36-SUM(M36:O36) -> 36711.125 | Q36: 39473.714 | R36: 44150.041 | S36: 37161.472 | T36: =F36-SUM(Q36:S36) -> 43932.477 | U36: 35889.645 | V36: 36201.979 | W36: 34904.227 | X36: =G36-SUM(U36:W36) -> 35262.566 | Y36: 32491.984 | Z36: 39585.96 | AA36: 36213.944 | AB36: =H36-SUM(Y36:AA36) -> 40897.832 | AC36: 37634.073 | AD36: 50812.668 | AE36: 52347.842 | AF36: =I36-SUM(AC36:AE36) -> 71767.866 | AG36: 73068.671 | AH36: 79265.167 | AI36: 73058.359 | AJ36: =J36-SUM(AG36:AI36) -> 80830.944 | AK36: 59570.951
B37: Rest of the world | C37: 69970.622 | D37: 91230.049 | E37: 122381.38 | F37: 163591.44 | G37: 137785.6 | H37: 121780.42 | I37: 153343.9 | J37: 151063.55 | K37: =SUM(AH37:AK37) -> 152409.55 | M37: 24832.123 | N37: 24028.61 | O37: 39768.89 | P37: =E37-SUM(M37:O37) -> 33751.759 | Q37: 37408.449 | R37: 43638.919 | S37: 40901.383 | T37: =F37-SUM(Q37:S37) -> 41642.69 | U37: 37461.857 | V37: 33968.898 | W37: 35570.042 | X37: =G37-SUM(U37:W37) -> 30784.802 | Y37: 26985.15 | Z37: 27768.948 | AA37: 34680.468 | AB37: =H37-SUM(Y37:AA37) -> 32345.855 | AC37: 37872.749 | AD37: 38075.16 | AE37: 40158.699 | AF37: =I37-SUM(AC37:AE37) -> 37237.293 | AG37: 38224.666 | AH37: 36690.924 | AI37: 40062.375 | AJ37: =J37-SUM(AG37:AI37) -> 36085.581 | AK37: 39570.667
B38: Net Revenue | C38: =SUM(C36:C37) -> 174915.42 | D38: =SUM(D36:D37) -> 205838.68 | E38: =SUM(E36:E37) -> 245865.63 | F38: =SUM(F36:F37) -> 328309.15 | G38: =SUM(G36:G37) -> 280044.02 | H38: =SUM(H36:H37) -> 270970.14 | I38: =SUM(I36:I37) -> 365906.35 | J38: =SUM(J36:J37) -> 457286.69 | K38: =SUM(K36:K37) -> 445134.97 | M38: =SUM(M36:M37) -> 49702.167 | N38: =SUM(N36:N37) -> 53537.805 | O38: =SUM(O36:O37) -> 72162.777 | P38: =SUM(P36:P37) -> 70462.884 | Q38: =SUM(Q36:Q37) -> 76882.163 | R38: =SUM(R36:R37) -> 87788.96 | S38: =SUM(S36:S37) -> 78062.855 | T38: =SUM(T36:T37) -> 85575.167 | ... AK38: =SUM(AK36:AK37) -> 99141.618
B39: check | C39: =C38-Model!C7 -> 0 | D39: =D38-Model!D7 -> 0 | E39: =E38-Model!E7 -> 0 | F39: =F38-Model!F7 -> 0 | G39: =G38-Model!G7 -> 0 | H39: =H38-Model!H7 -> 0.041 | I39: =I38-Model!I7 -> 0 | J39: =J38-Model!J7 -> 0 | K39: =K38-Model!K7 -> 0 | M39: =M38-Model!M7 -> 0 | N39: =N38-Model!N7 -> 0 | O39: =O38-Model!O7 -> 0 | P39: =P38-Model!P7 -> 0 | Q39: =Q38-Model!Q7 -> 0 | R39: =R38-Model!R7 -> 0 | S39: =S38-Model!S7 -> 0 | T39: =T38-Model!T7 -> 0 | ... AK39: =AK38-Model!AK7 -> 0
B41: Revenue by geography (% Share)
B42: Mainland China | C42: =C36/C$38 -> 0.59997455 | D42: =D36/D$38 -> 0.55678861 | E42: =E36/E$38 -> 0.50224283 | F42: =F36/F$38 -> 0.50171525 | G42: =G36/G$38 -> 0.50798592 | H42: =H36/H$38 -> 0.55057623 | I42: =I36/I$38 -> 0.58092036 | J42: =J36/J$38 -> 0.66965243 | K42: =K36/K$38 -> 0.65761048 | M42: =M36/M$38 -> 0.50038148 | N42: =N36/N$38 -> 0.55118425 | O42: =O36/O$38 -> 0.44890023 | P42: =P36/P$38 -> 0.52099947 | Q42: =Q36/Q$38 -> 0.51343137 | R42: =R36/R$38 -> 0.50291108 | S42: =S36/S$38 -> 0.47604551 | T42: =T36/T$38 -> 0.51337881 | ... AK42: =AK36/AK$38 -> 0.60086725
B43: Rest of the world | C43: =C37/C$38 -> 0.40002545 | D43: =D37/D$38 -> 0.44321139 | E43: =E37/E$38 -> 0.49775717 | F43: =F37/F$38 -> 0.49828475 | G43: =G37/G$38 -> 0.49201408 | H43: =H37/H$38 -> 0.44942377 | I43: =I37/I$38 -> 0.41907964 | J43: =J37/J$38 -> 0.33034757 | K43: =K37/K$38 -> 0.34238952 | M43: =M37/M$38 -> 0.49961852 | N43: =N37/N$38 -> 0.44881575 | O43: =O37/O$38 -> 0.55109977 | P43: =P37/P$38 -> 0.47900053 | Q43: =Q37/Q$38 -> 0.48656863 | R43: =R37/R$38 -> 0.49708892 | S43: =S37/S$38 -> 0.52395449 | T43: =T37/T$38 -> 0.48662119 | ... AK43: =AK37/AK$38 -> 0.39913275
B44: Net Revenue | C44: =SUM(C42:C43) -> 1 | D44: =SUM(D42:D43) -> 1 | E44: =SUM(E42:E43) -> 1 | F44: =SUM(F42:F43) -> 1 | G44: =SUM(G42:G43) -> 1 | H44: =SUM(H42:H43) -> 1 | I44: =SUM(I42:I43) -> 1 | J44: =SUM(J42:J43) -> 1 | K44: =SUM(K42:K43) -> 1 | M44: =SUM(M42:M43) -> 1 | N44: =SUM(N42:N43) -> 1 | O44: =SUM(O42:O43) -> 1 | P44: =SUM(P42:P43) -> 1 | Q44: =SUM(Q42:Q43) -> 1 | R44: =SUM(R42:R43) -> 1 | S44: =SUM(S42:S43) -> 1 | T44: =SUM(T42:T43) -> 1 | ... AK44: =SUM(AK42:AK43) -> 1
B46: Revenue by geography (YoY % Growth)
B47: Mainland China | D47: =D36/C36-1 -> 0.092084884 | E47: =E36/D36-1 -> 0.07744284 | F47: =F36/E36-1 -> 0.3339167 | G47: =G36/F36-1 -> -0.13635017 | H47: =H36/G36-1 -> 0.048723324 | I47: =I36/H36-1 -> 0.42477946 | J47: =J36/I36-1 -> 0.44062671 | Q47: =Q36/M36-1 -> 0.5871992 | R47: =R36/N36-1 -> 0.49614522 | S47: =S36/O36-1 -> 0.14717545 | T47: =T36/P36-1 -> 0.19670746 | U47: =U36/Q36-1 -> -0.090796346 | V47: =V36/R36-1 -> -0.18002389 | W47: =W36/S36-1 -> -0.060741539 | X47: =X36/T36-1 -> -0.19734628 | ... AK47: =AK36/AG36-1 -> -0.1847265
B48: Rest of the world | D48: =D37/C37-1 -> 0.30383361 | E48: =E37/D37-1 -> 0.34145913 | F48: =F37/E37-1 -> 0.33673471 | G48: =G37/F37-1 -> -0.15774567 | H48: =H37/G37-1 -> -0.11616002 | I48: =I37/H37-1 -> 0.25918353 | J48: =J37/I37-1 -> -0.014870856 | Q48: =Q37/M37-1 -> 0.50645392 | R48: =R37/N37-1 -> 0.81612332 | S48: =S37/O37-1 -> 0.028476857 | T48: =T37/P37-1 -> 0.23379318 | U48: =U37/Q37-1 -> 0.0014276989 | V48: =V37/R37-1 -> -0.22159167 | W48: =W37/S37-1 -> -0.13034623 | X48: =X37/T37-1 -> -0.26073935 | ... AK48: =AK37/AG37-1 -> 0.035212891
B49: Net Revenue | D49: =D38/C38-1 -> 0.17678977 | E49: =E38/D38-1 -> 0.19445787 | F49: =F38/E38-1 -> 0.33531938 | G49: =G38/F38-1 -> -0.14701122 | H49: =H38/G38-1 -> -0.032401603 | I49: =I38/H38-1 -> 0.35035672 | J49: =J38/I38-1 -> 0.24973695 | Q49: =Q38/M38-1 -> 0.54685736 | R49: =R38/N38-1 -> 0.63975643 | S49: =S38/O38-1 -> 0.081760684 | T49: =T38/P38-1 -> 0.21447154 | U49: =U38/Q38-1 -> -0.045923019 | V49: =V38/R38-1 -> -0.20068677 | W49: =W38/S38-1 -> -0.097211228 | X49: =X38/T38-1 -> -0.22819469 | ... AK49: =AK38/AG38-1 -> -0.1091864
B52: Cost of revenues by segment
B53: Smartphones | C53: -106757.13 | D53: -113335.55 | E53: -138986.94 | F53: -184007.86 | G53: -152248.42 | H53: -134480.7 | I53: -167505.5 | J53: -166173.62 | K53: =SUM(AH53:AK53) -> -161641 | M53: -27872.334 | N53: -29336.59 | O53: -43615.083 | P53: =E53-SUM(M53:O53) -> -38162.937 | Q53: -44857.384 | R53: -52095.546 | S53: -41708.84 | T53: =F53-SUM(Q53:S53) -> -45346.086 | U53: -41240.598 | V53: -38605.297 | W53: -38730.351 | X53: =G53-SUM(U53:W53) -> -33672.169 | Y53: -31051.729 | Z53: -31720.488 | AA53: -34718.945 | AB53: =H53-SUM(Y53:AA53) -> -36989.538 | AC53: -39600.525 | AD53: -40867 | AE53: -41904.746 | AF53: =I53-SUM(AC53:AE53) -> -45133.229 | AG53: -44329.301 | AH53: -40299.755 | AI53: -40873.54 | AJ53: =J53-SUM(AG53:AI53) -> -40671.025 | AK53: -39796.684
B54: IoT and lifestyle products | C54: -39306.134 | D54: -55134.299 | E54: -58804.839 | F54: -73888.603 | G54: -68296.397 | H54: -67029.1 | I54: -83011.8 | J54: -94776.809 | K54: =SUM(AH54:AK54) -> -89057.864 | M54: -11242.932 | N54: -13515.173 | O54: -15538.63 | P54: =E54-SUM(M54:O54) -> -18508.104 | Q54: -15590.732 | R54: -17992.268 | S54: -18509.697 | T54: =F54-SUM(Q54:S54) -> -21795.906 | U54: -16435.379 | V54: -16983.584 | W54: -16488.422 | X54: =G54-SUM(U54:W54) -> -18389.012 | Y54: -14187.118 | Z54: -18343.767 | AA54: -16987.91 | AB54: =H54-SUM(Y54:AA54) -> -17510.305 | AC54: -16326.052 | AD54: -21476.7 | AE54: -20684.052 | AF54: =I54-SUM(AC54:AE54) -> -24524.996 | AG54: -24184.366 | AH54: -29990.611 | AI54: -20957.026 | AJ54: =J54-SUM(AG54:AI54) -> -19644.806 | AK54: -18465.421
B55: Internet services | C55: -5683.856 | D55: -6998.096 | E55: -9111.002 | F55: -7316.598 | G55: -7974.356 | H55: -7773.5 | I55: -7968.6 | J55: -8800.069 | K55: =SUM(AH55:AK55) -> -8968.054 | M55: -2529.144 | N55: -2347.499 | O55: -2283.348 | P55: =E55-SUM(M55:O55) -> -1951.011 | Q55: -1816.119 | R55: -1819.718 | S55: -1940.606 | T55: =F55-SUM(Q55:S55) -> -1740.155 | U55: -2078.351 | V55: -1880.97 | W55: -1974.706 | X55: =G55-SUM(U55:W55) -> -2040.329 | Y55: -1948.401 | Z55: -1926.198 | AA55: -1984.342 | AB55: =H55-SUM(Y55:AA55) -> -1914.559 | AC55: -2073.018 | AD55: -1792.9 | AE55: -1908.226 | AF55: =I55-SUM(AC55:AE55) -> -2194.456 | AG55: -2094.257 | AH55: -2241.978 | AI55: -2169.832 | AJ55: =J55-SUM(AG55:AI55) -> -2294.002 | AK55: -2262.242
B56: Smart EV and other new initiatives | I56: -26703.256 | J56: -80306.052 | K56: =SUM(AH56:AK56) -> -81901.862 | AC56: -22.757 | AD56: -5389 | AE56: -8036.705 | AF56: =I56-SUM(AC56:AE56) -> -13254.794 | AG56: -14274.732 | AH56: -15642.425 | AI56: -21626.082 | AJ56: =J56-SUM(AG56:AI56) -> -28762.813 | AK56: -15870.542
B57: Others | C57: -976.369 | D57: -1816.708 | E57: -2210.986 | F57: -4835.147 | G57: -3947.658 | H57: -4210.6 | I57: -4157 | J57: -5424.289 | K57: =SUM(AH57:AK57) -> -5356.127 | M57: -499.3 | N57: -637.097 | O57: -560.06 | P57: =E57-SUM(M57:O57) -> -514.529 | Q57: -456.697 | R57: -733.386 | S57: -1611.491 | T57: =F57-SUM(Q57:S57) -> -2033.573 | U57: -887.428 | V57: -932.991 | W57: -1558.881 | X57: =G57-SUM(U57:W57) -> -568.358 | Y57: -698.319 | Z57: -1203.439 | AA57: -1093.504 | AB57: =H57-SUM(Y57:AA57) -> -1215.338 | AC57: -654.753 | AD57: =-968 -> -968 | AE57: =(-1091402)/1000 -> -1091.402 | AF57: =I57-SUM(AC57:AE57) -> -1442.845 | AG57: -1004.771 | AH57: =-1680.364 -> -1680.364 | AI57: =-(1558088)/1000 -> -1558.088 | AJ57: =J57-SUM(AG57:AI57) -> -1181.066 | AK57: -936.609
B58: Net cost of revenues | C58: =SUM(C53:C57) -> -152723.49 | D58: =SUM(D53:D57) -> -177284.65 | E58: =SUM(E53:E57) -> -209113.77 | F58: =SUM(F53:F57) -> -270048.2 | G58: =SUM(G53:G57) -> -232466.83 | H58: =SUM(H53:H57) -> -213493.9 | I58: =SUM(I53:I57) -> -289346.16 | J58: =SUM(J53:J57) -> -355480.84 | K58: =SUM(K53:K57) -> -346924.91 | M58: =SUM(M53:M57) -> -42143.71 | N58: =SUM(N53:N57) -> -45836.359 | O58: =SUM(O53:O57) -> -61997.121 | P58: =SUM(P53:P57) -> -59136.581 | Q58: =SUM(Q53:Q57) -> -62720.932 | R58: =SUM(R53:R57) -> -72640.918 | S58: =SUM(S53:S57) -> -63770.634 | T58: =SUM(T53:T57) -> -70915.72 | ... AK58: =SUM(AK53:AK57) -> -77331.498
B59: check | C59: =C58-Model!C9 -> 0 | D59: =D58-Model!D9 -> 0 | E59: =E58-Model!E9 -> 0 | F59: =F58-Model!F9 -> 0 | G59: =G58-Model!G9 -> 0 | H59: =H58-Model!H9 -> 0 | I59: =I58-Model!I9 -> 0 | J59: =J58-Model!J9 -> 0 | K59: =K58-Model!K9 -> 0 | M59: =M58-Model!M9 -> 0 | N59: =N58-Model!N9 -> 0 | O59: =O58-Model!O9 -> 0 | P59: =P58-Model!P9 -> 0 | Q59: =Q58-Model!Q9 -> 0 | R59: =R58-Model!R9 -> 0 | S59: =S58-Model!S9 -> 0 | T59: =T58-Model!T9 -> 0 | ... AK59: =AK58-Model!AK9 -> 0
B61: Gross profit by segment
B62: Smartphones | C62: 7043.259 | D62: 8759.351 | E62: 13203.947 | F62: 24861.088 | G62: 14968.762 | H62: 22980.587 | I62: 24253.8 | J62: 20266.156 | K62: =SUM(AH62:AK62) -> 18460.152 | M62: 2452.389 | N62: 2290.959 | O62: 3989.05 | P62: =E62-SUM(M62:O62) -> 4471.549 | Q62: 6633.599 | R62: 6993.417 | S62: 6116.092 | T62: =F62-SUM(Q62:S62) -> 5117.98 | U62: 4522.091 | V62: 3662.808 | W62: =W9+W53 -> 3783.888 | X62: =G62-SUM(U62:W62) -> 2999.975 | Y62: 3933.017 | Z62: 4874.973 | AA62: =AA9+AA53 -> 6929.98 | AB62: =H62-SUM(Y62:AA62) -> 7242.617 | AC62: 6879.223 | AD62: 5649.46 | AE62: 5547.578 | AF62: =I62-SUM(AC62:AE62) -> 6177.539 | AG62: 6282.651 | AH62: 5220.254 | AI62: 5095.487 | AJ62: =J62-SUM(AG62:AI62) -> 3667.764 | AK62: 4476.647
B63: IoT and lifestyle products | C63: 4510.751 | D63: 6953.699 | E63: 8605.614 | F63: 11091.494 | G63: 11498.48 | H63: 13078.596 | I63: 21092.1 | J63: 28423.382 | K63: =SUM(AH63:AK63) -> 26484.25 | M63: 1741.276 | N63: 1737.695 | O63: 2580.391 | P63: =E63-SUM(M63:O63) -> 2546.252 | Q63: 2652.535 | R63: 2742.425 | S63: 2425.86 | T63: =F63-SUM(Q63:S63) -> 3270.674 | U63: 3041.978 | V63: 2828.024 | W63: =W10+W54 -> 2570.226 | X63: =G63-SUM(U63:W63) -> 3058.252 | Y63: 2646.664 | Z63: 3910.099 | AA63: =AA10+AA54 -> 3685.387 | AB63: =H63-SUM(Y63:AA63) -> 2836.446 | AC63: 4047.437 | AD63: 5283.597 | AE63: 5418.11 | AF63: =I63-SUM(AC63:AE63) -> 6342.956 | AG63: 8154.868 | AH63: 8721.542 | AI63: 6595.129 | AJ63: =J63-SUM(AG63:AI63) -> 4951.843 | AK63: 6215.736
B64: Internet services | C64: 10271.702 | D64: 12843.473 | E64: 14644.283 | F64: 20895.141 | G64: 20347.088 | H64: 22333.95 | I64: 26146.8 | J64: 28640.277 | K64: =SUM(AH64:AK64) -> 28864.541 | M64: 3371.552 | N64: 3560.122 | O64: 3488.542 | P64: =E64-SUM(M64:O64) -> 4224.067 | Q64: 4754.729 | R64: 5213.769 | S64: 5397.251 | T64: =F64-SUM(Q64:S64) -> 5529.392 | U64: 5034.13 | V64: 5090.151 | W64: =W11+W55 -> 5091.885 | X64: =G64-SUM(U64:W64) -> 5130.922 | Y64: 5079.747 | Z64: 5517.881 | AA64: =AA11+AA55 -> 5771.192 | AB64: =H64-SUM(Y64:AA64) -> 5965.13 | AC64: 5975.365 | AD64: 6472.687 | AE64: 6554.581 | AF64: =I64-SUM(AC64:AE64) -> 7144.167 | AG64: 6981.84 | AH64: 6855.769 | AI64: 7210.632 | AJ64: =J64-SUM(AG64:AI64) -> 7592.036 | AK64: 7206.104
B65: Smart EV and other new initiatives | I65: 6050.3 | J65: 25763.461 | K65: =SUM(AH65:AK65) -> 25452.003 | AC65: 3.275 | AD65: 979.785 | AE65: 1660.429 | AF65: =I65-SUM(AC65:AE65) -> 3406.811 | AG65: 4305.333 | AH65: 5620.839 | AI65: 7384.006 | AJ65: =J65-SUM(AG65:AI65) -> 8453.283 | AK65: 3993.875
B66: Others | C66: 366.227 | D66: -2.49 | E66: 298.018 | F66: 1413.218 | G66: 762.86 | H66: -916.894 | I66: -982.8 | J66: -1287.429 | K66: =SUM(AH66:AK66) -> -1050.889 | M66: -6.76 | N66: 112.67 | O66: 107.673 | P66: =E66-SUM(M66:O66) -> 84.435 | Q66: 120.368 | R66: 198.431 | S66: 353.018 | T66: =F66-SUM(Q66:S66) -> 741.401 | U66: 111.547 | V66: 187.052 | W66: =W13+W57 -> 275.91 | X66: =G66-SUM(U66:W66) -> 188.351 | Y66: -67.861 | Z66: -141.937 | AA66: =AA13+AA57 -> -276.848 | AB66: =H66-SUM(Y66:AA66) -> -430.248 | AC66: -75.583 | AD66: =8.648 -> 8.648 | AE66: =(-299.288) -> -299.288 | AF66: =I66-SUM(AC66:AE66) -> -616.577 | AG66: -318.782 | AH66: =-317.446 -> -317.446 | AI66: =(-349088)/1000 -> -349.088 | AJ66: =J66-SUM(AG66:AI66) -> -302.113 | AK66: -82.242
B67: Net cost of revenues | C67: =SUM(C62:C66) -> 22191.939 | D67: =SUM(D62:D66) -> 28554.033 | E67: =SUM(E62:E66) -> 36751.862 | F67: =SUM(F62:F66) -> 58260.941 | G67: =SUM(G62:G66) -> 47577.19 | H67: =SUM(H62:H66) -> 57476.239 | I67: =SUM(I62:I66) -> 76560.2 | J67: =SUM(J62:J66) -> 101805.85 | K67: =SUM(K62:K66) -> 98210.057 | M67: =SUM(M62:M66) -> 7558.457 | N67: =SUM(N62:N66) -> 7701.446 | O67: =SUM(O62:O66) -> 10165.656 | P67: =SUM(P62:P66) -> 11326.303 | Q67: =SUM(Q62:Q66) -> 14161.231 | R67: =SUM(R62:R66) -> 15148.042 | S67: =SUM(S62:S66) -> 14292.221 | T67: =SUM(T62:T66) -> 14659.447 | ... AK67: =SUM(AK62:AK66) -> 21810.12
B68: check | C68: =C67-Model!C10 -> 0 | D68: =D67-Model!D10 -> 0 | E68: =E67-Model!E10 -> 0 | F68: =F67-Model!F10 -> 0 | G68: =G67-Model!G10 -> 0 | H68: =H67-Model!H10 -> 0.039 | I68: =I67-Model!I10 -> 0.006 | J68: =J67-Model!J10 -> 0 | K68: =K67-Model!K10 -> 0 | M68: =M67-Model!M10 -> 0 | N68: =N67-Model!N10 -> 0 | O68: =O67-Model!O10 -> 0 | P68: =P67-Model!P10 -> 0 | Q68: =Q67-Model!Q10 -> 0 | R68: =R67-Model!R10 -> 0 | S68: =S67-Model!S10 -> 0 | T68: =T67-Model!T10 -> 1.4551915e-11 | ... AK68: =AK67-Model!AK10 -> 0
B70: Gross profit margin by segment
B71: Smartphones | C71: =C62/C9 -> 0.061891345 | D71: =D62/D9 -> 0.071742155 | E71: =E62/E9 -> 0.086759115 | F71: =F62/F9 -> 0.11902721 | G71: =G62/G9 -> 0.089516892 | H71: =H62/H9 -> 0.14594435 | I71: =I62/I9 -> 0.12648044 | J71: =J62/J9 -> 0.10870082 | K71: =K62/K9 -> 0.1024988 | M71: =M62/M9 -> 0.080870945 | N71: =N62/N9 -> 0.072435553 | O71: =O62/O9 -> 0.083796296 | P71: =P62/P9 -> 0.10488103 | Q71: =Q62/Q9 -> 0.1288303 | R71: =R62/R9 -> 0.11835403 | S71: =S62/S9 -> 0.12788501 | T71: =T62/T9 -> 0.1014183 | ... AK71: =AK62/AK9 -> 0.10111385
B72: IoT and lifestyle products | C72: =C63/C10 -> 0.1029455 | D72: =D63/D10 -> 0.11199747 | E72: =E63/E10 -> 0.12765993 | F72: =F63/F10 -> 0.13051873 | G72: =G63/G10 -> 0.14410048 | H72: =H63/H10 -> 0.16326266 | I72: =I63/I10 -> 0.20260624 | J72: =J63/J10 -> 0.23070891 | K72: =K63/K10 -> 0.22921729 | M72: =M63/M10 -> 0.13410722 | N72: =N63/N10 -> 0.11392579 | O72: =O63/O10 -> 0.14241338 | P72: =P63/P10 -> 0.12093706 | Q72: =Q63/Q10 -> 0.14539803 | R72: =R63/R10 -> 0.13226263 | S72: =S63/S10 -> 0.11587272 | T72: =T63/T10 -> 0.13047947 | ... AK72: =AK63/AK10 -> 0.25184135
B73: Internet services | C73: =C64/C11 -> 0.64376953 | D73: =D64/D11 -> 0.64730128 | E73: =E64/E11 -> 0.61646421 | F73: =F64/F11 -> 0.74065413 | G73: =G64/G11 -> 0.71843399 | H73: =H64/H11 -> 0.74180686 | I73: =I64/I11 -> 0.7664222 | J73: =J64/J11 -> 0.76495759 | K73: =K64/K11 -> 0.7629543 | M73: =M64/M11 -> 0.57138209 | N73: =N64/N11 -> 0.60263209 | O73: =O64/O11 -> 0.60440202 | P73: =P64/P11 -> 0.68405079 | Q73: =Q64/Q11 -> 0.72360965 | R73: =R64/R11 -> 0.74127797 | S73: =S64/S11 -> 0.73553505 | T73: =T64/T11 -> 0.76062401 | ... AK73: =AK64/AK11 -> 0.76107316
B74: Smart EV and other new initiatives | C74: =C65/C12 -> #DIV/0! | D74: =D65/D12 -> #DIV/0! | E74: =E65/E12 -> #DIV/0! | F74: =F65/F12 -> #DIV/0! | G74: =G65/G12 -> #DIV/0! | H74: =H65/H12 -> #DIV/0! | I74: =I65/I12 -> 0.18472168 | J74: =J65/J12 -> 0.24289223 | K74: =K65/K12 -> 0.23708511 | M74: =M65/M12 -> #DIV/0! | N74: =N65/N12 -> #DIV/0! | O74: =O65/O12 -> #DIV/0! | P74: =P65/P12 -> #DIV/0! | Q74: =Q65/Q12 -> #DIV/0! | R74: =R65/R12 -> #DIV/0! | S74: =S65/S12 -> #DIV/0! | T74: =T65/T12 -> #DIV/0! | ... AK74: =AK65/AK12 -> 0.20105674
B75: Others | C75: =C66/C13 -> 0.27277528 | D75: =D66/D13 -> -0.0013724922 | E75: =E66/E13 -> 0.1187794 | F75: =F66/F13 -> 0.22617405 | G75: =G66/G13 -> 0.16194822 | H75: =H66/H13 -> -0.27838657 | I75: =I66/I13 -> -0.30962132 | J75: =J66/J13 -> -0.31120923 | K75: =K66/K13 -> -0.24409545 | M75: =M66/M13 -> -0.013724774 | N75: =N66/N13 -> 0.15027335 | O75: =O66/O13 -> 0.16125158 | P75: =P66/P13 -> 0.14096841 | Q75: =Q66/Q13 -> 0.20858655 | R75: =R66/R13 -> 0.21295061 | S75: =S66/S13 -> 0.17969783 | T75: =T66/T13 -> 0.26717403 | ... AK75: =AK66/AK13 -> -0.09626074
B76: Net cost of revenues | C76: =C67/C14 -> 0.1268724 | D76: =D67/D14 -> 0.13872044 | E76: =E67/E14 -> 0.14947946 | F76: =F67/F14 -> 0.17745756 | G76: =G67/G14 -> 0.16989183 | H76: =H67/H14 -> 0.21211285 | I76: =I67/I14 -> 0.20923438 | J76: =J67/J14 -> 0.22263024 | K76: =K67/K14 -> 0.22062984 | M76: =M67/M14 -> 0.152075 | N76: =N67/N14 -> 0.14385061 | O76: =O67/O14 -> 0.14087119 | P76: =P67/P14 -> 0.16074141 | Q76: =Q67/Q14 -> 0.18419397 | R76: =R67/R14 -> 0.17255065 | S76: =S67/S14 -> 0.18308607 | T76: =T67/T14 -> 0.17130492 | ... AK76: =AK67/AK14 -> 0.21998955
