Workbook
Name \A: #REF!
Name \B: #REF!
Name \C: #REF!
Name \L: #REF!
Name \M: #REF!
Name \P: #REF!
Name \Y: #REF!
Name _01_30_04: MonthlyOpStats
Name _01_30_04: MonthlyOpStats
Name _01_30_04: MonthlyOpStats
Name _1_30_01: MonthlyOpStats
Name _1_30_01: MonthlyOpStats
Name _1_30_01: MonthlyOpStats
Name _1_30_02: MonthlyOpStats
Name _1_30_02: MonthlyOpStats
Name _1_30_02: MonthlyOpStats
Name _1_31_01: MonthlyOpStats
Name _1_31_01: MonthlyOpStats
Name _1_31_01: MonthlyOpStats
Name _1_31_02: MonthlyOpStats
Name _1_31_02: MonthlyOpStats
Name _1_31_02: MonthlyOpStats
Name _12_31_05: MonthlyOpStats
Name _12_31_05: MonthlyOpStats
Name _12_31_05: MonthlyOpStats
Name _A: #REF!
Name _A___0: #REF!
Name _B: #REF!
Name _B___0: #REF!
Name _C: #REF!
Name _C___0: #REF!
Name _ent1: [1]Inputs!$J$17
Name _ent10: [1]Inputs!$J$476
Name _ent11: [1]Inputs!$J$527
Name _ent12: [1]Inputs!$J$578
Name _ent13: [1]Inputs!$J$629
Name _ent14: [1]Inputs!$J$680
Name _ent15: [1]Inputs!$J$731
Name _ent2: [1]Inputs!$J$68
Name _ent3: [1]Inputs!$J$119
Name _ent4: [1]Inputs!$J$170
Name _ent5: [1]Inputs!$J$221
Name _ent6: [1]Inputs!$J$272
Name _ent7: [1]Inputs!$J$323
Name _ent8: [1]Inputs!$J$374
Name _ent9: [1]Inputs!$J$425
Name _eps1: [1]Inputs!$P$42
Name _eps10: [1]Inputs!$P$501
Name _eps11: [1]Inputs!$P$552
Name _eps12: [1]Inputs!$P$603
Name _eps13: [1]Inputs!$P$654
Name _eps14: [1]Inputs!$P$705
Name _eps15: [1]Inputs!$P$756
Name _eps2: [1]Inputs!$P$93
Name _eps3: [1]Inputs!$P$144
Name _eps4: [1]Inputs!$P$195
Name _eps5: [1]Inputs!$P$246
Name _eps6: [1]Inputs!$P$297
Name _eps7: [1]Inputs!$P$348
Name _eps8: [1]Inputs!$P$399

Sheet Capitalisation
A3: 1Q26 | I3: Exchange rate at the end | J3: =Model!$BF$382 -> 926.27
I4: LTM Average exchange rate | J4: =Model!$BF$381 -> 886.57
B6: As on 31-Mar-2026 | C6: CLP (m) | D6: USD (m) | E6: Leverage (CLP) | F6: Leverage (USD) | I6: Company Reported | J6: =C6 -> CLP (m) | K6: =D6 -> USD (m) | L6: =E6 -> Leverage (CLP) | M6: =F6 -> Leverage (USD)
B7: Bank Loans | C7: 304625.54 | D7: =C7/$J3 -> 328.87337 | I7: Consolidated Financial debt (excluding banking operations) | J7: =+C17-C14-C9-C10-C15 -> 3554283.8 | K7: =J7/$J3 -> 3837.2006 | L7: =J7/J10 -> 2.7550026 | M7: =K7/K10 -> 2.636923
B8: Bonds payable | C8: 64251.817 | D8: =C8/$J3 -> 69.366186 | I8: Cash & Equivalents (including other financial assets) | J8: =Model!$BF$252+24956.527 -> 1853519.8 | K8: =J8/$J3 -> 2001.0578
B9: Financial lease obligations | C9: 133112.24 | D9: =C9/$J3 -> 143.70782 | I9: Net debt | J9: =+J7-J8 -> 1700764 | K9: =J9/$J3 -> 1836.1428 | L9: =J9/J10 -> 1.3182991 | M9: =K9/K10 -> 1.2617967
B10: Other financial debt | C10: 17709.194 | D10: =C10/$J3 -> 19.118825 | I10: LTM Non-Banking Adjusted EBITDA | J10: =C27-230033 -> 1290119.9 | K10: =J10/J4 -> 1455.1811
B11: Total short-term retail business debt | C11: =SUM(C7:C10) -> 519698.79 | D11: =SUM(D7:D10) -> 561.0662
B12: Bank loans | C12: 241709.94 | D12: =C12/$J3 -> 260.94977
B13: Bonds payable | C13: 2943696.5 | D13: =C13/$J3 -> 3178.0113
B14: Financial lease obligations | C14: 1317997 | D14: =C14/$J3 -> 1422.908 | I14: Exlcudes financial leases
B15: Other financial debt | C15: 1331.322 | D15: =C15/$J3 -> 1.4372937
B16: Total long-term retail business debt | C16: =SUM(C12:C15) -> 4504734.7 | D16: =SUM(D12:D15) -> 4863.3063
B17: Total Retail business Debt | C17: =C16+C11 -> 5024433.5 | D17: =D16+D11 -> 5424.3725 | E17: =+C17/C27 -> 3.3052158 | F17: =+D17/D27 -> 3.163554
B18: Cash & Equivalents | C18: =Model!$BF$252 -> 1828563.3 | D18: =C18/$J3 -> 1974.1148
B19: Net debt | C19: =+C17-C18 -> 3195870.2 | D19: =+D17-D18 -> 3450.2577 | E19: =+C19/C27 -> 2.1023347 | F19: =+D19/D27 -> 2.0122284
B21: Obligations with other banks | C21: =Model!$BF$272 -> 206456.31 | D21: =C21/$J3 -> 222.88999
B22: Debt instruments issued | C22: =Model!$BF$273 -> 330432.82 | D22: =C22/$J3 -> 356.73488
B23: Lease liabilities | C23: =Model!$BF$274 -> 29150.929 | D23: =C23/$J3 -> 31.471309
B24: Banking business debt, total | C24: =C21+C22+C23 -> 566040.06 | D24: =D21+D22+D23 -> 611.09618
B25: Equity | C25: =Model!$BF$272 -> 206456.31 | D25: =C25/$J3 -> 222.88999
B26: Total Capitalisation | C26: =C25+C17+C24 -> 5796929.9 | D26: =D25+D17+D24 -> 6258.3587
B27: LTM Non-Banking Adjusted EBITDA | C27: =Model!$BF$204 -> 1520152.9 | D27: =C27/$J4 -> 1714.6451
B29: Debt check | C29: =C17-Model!$BF$260 -> 0
B31: Market cap | C31: =Model!$BF$289 -> 15288900
B32: EV | C32: =C31+Model!$BF$283 -> 19428264
B33: EV/EBITDA | C33: =C32/C34 -> 9.6413544
B34: LTM Total Adjusted EBITDA (Banking + Retail) | C34: =Model!$BF$223 -> 2015097
B38: Liquidity Table | C38: CLP(m) | D38: USD (m)
B39: RCF | C39: 0 | D39: 0
B40: Cash | C40: =C18 -> 1828563.3 | D40: =D18 -> 1974.1148
B41: Total Liquidity | C41: =C39+C40 -> 1828563.3 | D41: =D39+D40 -> 1974.1148
B45: Debt Maturity Profile - BBG | C45: CLP(m) | D45: USD (m)
B46: 2026 | C46: =24042.48+272083.03 -> 296125.51 | D46: =C46/$J3 -> 319.69675
B47: 2027 | C47: 402521.53 | D47: =C47/$J3 -> 434.56177
B48: 2028 | C48: 212845.65 | D48: =C48/$J3 -> 229.78791
B49: 2029 | C49: 454751.53 | D49: =C49/$J3 -> 490.94922
B50: 2030 | C50: 289817.88 | D50: =C50/$J3 -> 312.88704
B51: 2031 & therafter | C51: =3811977.62+272083.03-SUM(C46:C50) -> 2427998.6 | D51: =C51/$J3 -> 2621.2644
B52: Total debt | C52: =SUM(C46:C51) -> 4084060.7 | D52: =SUM(D46:D51) -> 4409.1471
A60: 3Q25 | I60: 3Q25 Exchange rate at end | J60: =Model!$BD$382 -> 961.93
B63: As on 30-Sep-2025 | C63: CLP (m) | D63: USD (m) | E63: Leverage | I63: Company Reported | J63: CLP (m) | K63: USD (m) | L63: Leverage
B64: Bank Loans | C64: 207048.88 | D64: =C64/$J60 -> 215.24319 | I64: Consolidated Financial debt (excluding banking operations) | J64: =+C74-C71-C66-C67-C72 -> 3744349.2 | K64: =J64/$J60 -> 3892.5381 | L64: =J64/J67 -> 3.1409822
B65: Bonds payable | C65: 87747.713 | D65: =C65/$J60 -> 91.220477 | I65: Cash & Equivalents (including other financial assets) | J65: =Model!$BD$252+15227.425 -> 1355757.8 | K65: =J65/$J60 -> 1409.4142
B66: Financial lease obligations | C66: 129100.28 | D66: =C66/$J60 -> 134.20964 | I66: Net debt | J66: =+J64-J65 -> 2388591.4 | K66: =J66/$J60 -> 2483.124 | L66: =J66/J67 -> 2.0036921
B67: Other financial debt | C67: 35224.079 | D67: =C67/$J60 -> 36.618131 | I67: LTM Non-Banking Adjusted EBITDA (Sep 2025) | J67: =C84-218621 -> 1192095
B68: Total short-term retail business debt | C68: =SUM(C64:C67) -> 459120.95 | D68: =SUM(D64:D67) -> 477.29143
B69: Bank loans | C69: 301747.15 | D69: =C69/$J60 -> 313.6893
B70: Bonds payable | C70: 3147805.5 | D70: =C70/$J60 -> 3272.3852
B71: Financial lease obligations | C71: 1280527.3 | D71: =C71/$J60 -> 1331.2063
B72: Other financial debt | C72: 4402.516 | D72: =C72/$J60 -> 4.576753
B73: Total long-term retail business debt | C73: =SUM(C69:C72) -> 4734482.4 | D73: =SUM(D69:D72) -> 4921.8575
B74: Total Retail business Debt | C74: =C73+C68 -> 5193603.4 | D74: =D73+D68 -> 5399.149 | E74: =+C74/C84 -> 3.6815371
B75: Cash & Equivalents | C75: =Model!$BD$252 -> 1340530.3 | D75: =C75/$J60 -> 1393.5841
B76: Net debt | C76: =+C74-C75 -> 3853073 | D76: =+D74-D75 -> 4005.5649 | E76: =+C76/C84 -> 2.7312889
B78: Obligations with other banks | C78: =Model!$BD$272 -> 130737.21 | D78: =C78/$J60 -> 135.91136
B79: Debt instruments issued | C79: =Model!$BD$273 -> 332087.27 | D79: =C79/$J60 -> 345.23018
B80: Lease liabilities | C80: =Model!$BD$274 -> 22299.106 | D80: =C80/$J60 -> 23.181631
B81: Banking business debt, total | C81: =C78+C79+C80 -> 485123.59 | D81: =D78+D79+D80 -> 504.32317
B82: Equity | C82: =Model!$BD$290 -> 9481373.6 | D82: =C82/$J60 -> 9856.6149
B83: Total Capitalisation | C83: =C82+C74+C81 -> 15160101 | D83: =D82+D74+D81 -> 15760.087
B84: LTM Non-Banking Adjusted EBITDA | C84: =Model!$BD$204 -> 1410716
B86: Debt check | C86: =C74-Model!$BD$260 -> 0
B88: Market cap as on 30-Sep-2025 | C88: =Model!$BD$289 -> 16209600
B89: EV | C89: =C88+Model!$BD$283 -> 20478699
B90: EV/EBITDA | C90: =C89/C91 -> 11.025062
B91: LTM Total Adjusted EBITDA (Banking + Retail) | C91: =Model!$BD$223 -> 1857468
B95: Liquidity Table | C95: CLP(m) | D95: USD (m)
B96: RCF | C96: 0 | D96: 0
B97: Cash | C97: =C75 -> 1340530.3 | D97: =D75 -> 1393.5841
B98: Total Liquidity | C98: =C96+C97 -> 1340530.3 | D98: =D96+D97 -> 1393.5841
B102: Debt Maturity Profile (30 Sep 2025) - BBG | C102: CLP(m) | D102: USD (m)
B103: 2026 | C103: 314547.28 | D103: =C103/$J60 -> 326.99602
B104: 2027 | C104: 393683.94 | D104: =C104/$J60 -> 409.26465
B105: 2028 | C105: 210850.44 | D105: =C105/$J60 -> 219.1952
B106: 2028 | C106: 404773.74 | D106: =C106/$J60 -> 420.79334
B107: 2030 | C107: 281903.97 | D107: =C107/$J60 -> 293.06079
B108: 2031 & therafter | C108: =3970208.06-SUM(C103:C107) -> 2364448.7 | D108: =C108/$J60 -> 2458.0257
B109: Total debt | C109: =SUM(C103:C108) -> 3970208.1 | D109: =SUM(D103:D108) -> 4127.3357
A114: 2Q25 | C114: 2Q25 Exchange rate at end | D114: =Model!$BC$382 -> 928.38
I116: Company Reported
B117: As on 30-Jun-2025 | C117: CLP (m) | D117: USD (m) | E117: Leverage | I117: As on 30-Jun-2025 | J117: CLP (m) | K117: USD (m) | L117: Leverage
B118: Bank Loans | C118: 217598.85 | D118: =C118/$D114 -> 234.38554 | I118: Consolidated Financial debt (excluding banking operations) | J118: =+C128-C125-C120-C121-C126 -> 3867228.9 | K118: =J118/$D114 -> 4165.5668 | L118: =J118/J122 -> 3.4140742
B119: Bonds payable | C119: 87864.115 | D119: =C119/$D114 -> 94.642404 | I119: Cash & Equivalents (including other financial assets) | J119: =Model!$BC$252+15715.483 -> 1483577.5 | K119: =J119/$D114 -> 1598.0283
B120: Financial lease obligations | C120: 126889.67 | D120: =C120/$D114 -> 136.67859 | I120: Net debt | J120: =+J118-J119 -> 2383651.4 | K120: =J120/$D114 -> 2567.5385 | L120: =J120/J122 -> 2.1043395
B121: Other financial debt | C121: 36031.443 | D121: =C121/$D114 -> 38.811094
B122: Total short-term retail business debt | C122: =SUM(C118:C121) -> 468384.07 | D122: =SUM(D118:D121) -> 504.51763 | I122: LTM Non-Banking Adjusted EBITDA (Jun 2025) | J122: =C138-214346 -> 1132731.3
B123: Bank loans | C123: 294034.61 | D123: =C123/$D114 -> 316.71795
B124: Bonds payable | C124: 3267731.3 | D124: =C124/$D114 -> 3519.8209
B125: Financial lease obligations | C125: 1311821.9 | D125: =C125/$D114 -> 1413.0226
B126: Other financial debt | C126: 3817.588 | D126: =C126/$D114 -> 4.1120963
B127: Total long-term retail business debt | C127: =SUM(C123:C126) -> 4877405.4 | D127: =SUM(D123:D126) -> 5253.6735
B128: Total Retail business Debt | C128: =C127+C122 -> 5345789.5 | D128: =D127+D122 -> 5758.1911 | E128: =+C128/C138 -> 3.9684355
B129: Cash & Equivalents | C129: =Model!$BC$252 -> 1467862 | D129: =C129/$D114 -> 1581.1005
B130: Net debt | C130: =+C128-C129 -> 3877927.4 | D130: =+D128-D129 -> 4177.0907 | E130: =+C130/C138 -> 2.8787712
B132: Obligations with other banks | C132: =Model!$BC$112 -> 21403.527 | D132: =C132/$D114 -> 23.054705
B133: Debt instruments issued | C133: =Model!$BC$113 -> 368526.48 | D133: =C133/$D114 -> 396.9565
B134: Lease liabilities | C134: =Model!$BC$114 -> 0.007946455 | D134: =C134/$D114 -> 8.5594853e-06
B135: Banking business debt, total | C135: =C132+C133+C134 -> 389930.01 | D135: =D132+D133+D134 -> 420.01122
B136: Equity | C136: =Model!$BC$290 -> 9169210.9 | D136: =C136/$D114 -> 9876.5709
...

Sheet Model
B2: Falabella | C2: Annual | D2: Annual | E2: Annual | F2: Annual | G2: Annual | H2: Annual | I2: Annual | J2: Annual | K2: Annual | L2: Annual | M2: Annual | N2: Annual | O2: Annual | P2: Annual | R2: Quarterly | S2: Quarterly | T2: Quarterly | U2: Quarterly | V2: Quarterly | W2: Quarterly | X2: Quarterly | Y2: Quarterly | Z2: Quarterly | AA2: Quarterly | AB2: Quarterly | AC2: Quarterly | AD2: Quarterly | AE2: Quarterly | AF2: Quarterly | AG2: Quarterly | AH2: Quarterly | AI2: Quarterly | AJ2: Quarterly | AK2: Quarterly | AL2: Quarterly | AM2: Quarterly | AN2: Quarterly | AO2: Quarterly | AP2: Quarterly | AQ2: Quarterly | AR2: Quarterly | AS2: Quarterly | AT2: Quarterly | AU2: Quarterly | AV2: Quarterly | AW2: Quarterly | AX2: Quarterly | AY2: Quarterly | AZ2: Quarterly | BA2: Quarterly | BB2: Quarterly | BC2: Quarterly | BD2: Quarterly | BE2: Quarterly | BF2: Quarterly | BH2: Quarterly | BI2: Quarterly | BJ2: Quarterly | BK2: Quarterly | BL2: Quarterly | BN2: Half year | BO2: Half year | BP2: Half year | BQ2: Half year | BR2: Half year | BS2: Half year | BT2: Half year | BU2: Half year | BV2: Half year | BW2: Half year | BY2: Half year | BZ2: Half year | CC2: Quarterly | CD2: Half year | CE2: Nine Months
B3: (CLP $) | C3: 41975 | D3: 42341 | E3: 42708 | F3: 43073 | G3: 43073 | H3: 43438 | I3: 43438 | J3: 43803 | K3: 44169 | L3: 44534 | M3: 44899 | N3: 45264 | O3: 45630 | P3: 45995 | R3: 42437 | S3: 42527 | T3: 42622 | U3: 42714 | V3: 42801 | W3: 42892 | X3: 42987 | Y3: 43079 | Z3: 43166 | AA3: 43257 | AB3: 43352 | AC3: 43444 | AD3: 43531 | AE3: 43622 | AF3: 43738 | AG3: 43809 | AH3: 43897 | AI3: 43988 | AJ3: 44104 | AK3: 44175 | AL3: 44262 | AM3: 44348 | AN3: 44469 | AO3: 44540 | AP3: 44651 | AQ3: 44713 | AR3: 44834 | AS3: 44905 | AT3: 45016 | AU3: 45078 | AV3: 45199 | AW3: 45270 | AX3: 45382 | AY3: 45444 | AZ3: 45565 | BA3: 45636 | BB3: 45747 | BC3: 45809 | BD3: 45930 | BE3: 46001 | BF3: 46112 | BH3: 43166 | BI3: 43281 | BJ3: 43373 | BK3: 43444 | BL3: 43531 | BN3: 42530 | BO3: 42896 | BP3: 43261 | BQ3: 43646 | BR3: 44012 | BS3: 44377 | BT3: 44742 | BU3: 45107 | BV3: 45473 | BW3: 45838 | BY3: 43281 | BZ3: 43646 | CC3: 42071 | CD3: 42161 | CE3: 42256
C4: Act | D4: Act | E4: Act | F4: Act | G4: Act | H4: Act | I4: Act | J4: Act | K4: Act | L4: Act | M4: Act | N4: Act | O4: Act | P4: Act | R4: Act | S4: Act | T4: Act | U4: Act | V4: Act | W4: Act | X4: Act | Y4: Act | Z4: Act | AA4: Act | AB4: Act | AC4: Act | AD4: Act | AE4: Act | AF4: Act | AG4: Act | AH4: Act | AI4: Act | AJ4: Act | AK4: Act | AL4: Act | AM4: Act | AN4: Act | AO4: Act | AP4: Act | AQ4: Act | AR4: Restated | AS4: Act | AT4: Act | AU4: Act | AV4: Act | AW4: Act | AX4: Act | AY4: Act | AZ4: Act | BA4: Act | BB4: Act | BC4: Act | BD4: Act | BE4: Act | BF4: Act | BH4: Act | BI4: Act | BJ4: Act | BK4: Act | BL4: Act | BN4: Act | BO4: Act | BP4: Act | BQ4: Act | BR4: Act | BS4: Act | BT4: Act | BU4: Act | BV4: Act | BW4: Act | BY4: Act | BZ4: Act | CD4: Act
C5: FY | D5: FY | E5: FY | F5: FY | G5: FY | H5: FY | I5: FY | J5: FY | K5: FY | L5: FY | M5: FY | N5: FY | O5: FY | P5: FY | R5: Q1 | S5: Q2 | T5: Q3 | U5: Q4 | V5: Q1 | W5: Q2 | X5: Q3 | Y5: Q4 | Z5: Q1 | AA5: Q2 | AB5: Q3 | AC5: Q4 | AD5: Q1 | AE5: Q2 | AF5: Q3 | AG5: Q4 | AH5: Q1 | AI5: Q2 | AJ5: Q3 | AK5: Q4 | AL5: Q1 | AM5: Q2 | AN5: Q3 | AO5: Q4 | AP5: Q1 | AQ5: Q2 | AR5: Q3 | AS5: Q4 | AT5: Q1 | AU5: Q2 | AV5: Q3 | AW5: Q4 | AX5: Q1 | AY5: Q2 | AZ5: Q3 | BA5: Q4 | BB5: Q1 | BC5: Q2 | BD5: Q3 | BE5: Q4 | BF5: Q1 | BH5: Q1 | BI5: Q2 | BJ5: Q3 | BK5: Q4 | BL5: Q1 | BN5: H1 2016 | BO5: H1 2017 | BP5: H1 2018 | BQ5: H1 2019 | BR5: H1 2020 | BS5: H1 2021 | BT5: H1 2022 | BU5: H1 2023 | BV5: H1 2024 | BW5: H1 2025 | BY5: H1 2018 | BZ5: H1 2019 | CC5: Q1 | CD5: H12015 | CE5: 9M2015
B6: INCOME STATEMENT | G6: Restated | I6: Restated | BH6: Restated | BI6: Restated | BJ6: Restated | BK6: Restated | BL6: Restated | BY6: Restated | BZ6: Restated
B7: Non-Banking Business
B8: Revenues | C8: 7038379.8 | D8: 7753209.6 | E8: 7898301.8 | F8: 8242645.3 | G8: 8209851.5 | H8: 8483577.3 | I8: 7976898.4 | J8: 8053582.8 | K8: 8281049.9 | L8: 10335384 | M8: 10460666 | N8: 9355114.7 | O8: 10322104 | P8: 11342386 | R8: 1889596.2 | S8: =BN8-R8 -> 1948787.3 | T8: =5707941.211-S8-R8 -> 1869557.7 | U8: =E8-T8-S8-R8 -> 2190360.6 | V8: 1952033.1 | W8: =BO8-V8 -> 2015162.9 | X8: =5909189.615-W8-V8 -> 1941993.6 | Y8: =F8-X8-W8-V8 -> 2333455.6 | Z8: 2010257.7 | AA8: =BP8-Z8 -> 2106536.8 | AB8: =6121405.241-AA8-Z8 -> 2004610.8 | AC8: =H8-AB8-AA8-Z8 -> 2362172.1 | AD8: 1926900.5 | AE8: =BQ8-AD8 -> 1994081 | AF8: =5802437.766-AE8-AD8 -> 1881456.2 | AG8: =J8-AF8-AE8-AD8 -> 2251145.1 | AH8: 1887698.6 | AI8: =BR8-AH8 -> 1458364.1 | AJ8: =5563468.36-AI8-AH8 -> 2217405.7 | AK8: =K8-AJ8-AI8-AH8 -> 2717581.6 | AL8: 2218078.5 | AM8: =BS8-AL8 -> 2390588.7 | AN8: =7229559.641-AM8-AL8 -> 2620892.4 | AO8: =L8-AN8-AM8-AL8 -> 3105824.1 | AP8: 2546146.6 | AQ8: =BT8-AP8 -> 2619187.9 | AR8: =7657493.231-AQ8-AP8 -> 2492158.7 | AS8: =M8-AR8-AQ8-AP8 -> 2803173.2 | AT8: 2274726.3 | AU8: =BU8-AT8 -> 2219917.4 | AV8: =6701080.263-AU8-AT8 -> 2206436.6 | AW8: =N8-AV8-AU8-AT8 -> 2654034.4 | AX8: 2392525.6 | AY8: =BV8-AX8 -> 2445288.2 | AZ8: =7240767.681-AY8-AX8 -> 2402953.9 | BA8: =O8-AZ8-AY8-AX8 -> 3081336.8 | BB8: 2653179.2 | BC8: =BW8-BB8 -> 2693468.6 | BD8: =7976947.918-BC8-BB8 -> 2630300.1 | BE8: =P8-BD8-BC8-BB8 -> 3365438 | BF8: 2766025.9 | BH8: 1887142.6 | BI8: =BY8-BH8 -> 1980615.5 | BJ8: =5745783.56-BI8-BH8 -> 1878025.5 | BK8: =I8-AB8-AA8-Z8 -> 1855493.2 | BL8: 1926900.5 | BN8: 3838383.5 | BO8: 3967196 | BP8: 4116794.5 | BQ8: 3920981.5 | BR8: 3346062.7 | BS8: 4608667.2 | BT8: 5165334.5 | BU8: 4494643.6 | BV8: 4837813.8 | BW8: 5346647.9 | BY8: 3867758.1 | BZ8: 3920981.5 | CC8: 1817584.6 | CD8: 3673268.5 | CE8: 5515070.3
B9: % growth | C9: =C8/6196082.713-1 -> 0.13594026 | D9: =D8/C8-1 -> 0.1015617 | E9: =E8/D8-1 -> 0.018713826 | F9: =F8/E8-1 -> 0.043597154 | H9: =H8/G8-1 -> 0.033341142 | I9: =I8/G8-1 -> -0.028374826 | J9: =J8/I8-1 -> 0.0096133141 | K9: =K8/J8-1 -> 0.028244214 | L9: =L8/K8-1 -> 0.24807649 | M9: =M8/L8-1 -> 0.012121723 | N9: =N8/M8-1 -> -0.10568655 | O9: =O8/N8-1 -> 0.10336483 | P9: =P8/O8-1 -> 0.098844322 | R9: =R8/CC8-1 -> 0.03961939 | S9: =S8/(CD8-CC8)-1 -> 0.050172034 | T9: =T8/(CE8-CD8)-1 -> 0.015069958 | U9: =U8/(D8-CE8)-1 -> -0.021347506 | V9: =V8/R8-1 -> 0.03304245 | W9: =W8/S8-1 -> 0.034059974 | X9: =X8/T8-1 -> 0.038744925 | Y9: =Y8/U8-1 -> 0.065329461 | Z9: =Z8/V8-1 -> 0.029827656 | AA9: =AA8/W8-1 -> 0.045343174 | AB9: =AB8/X8-1 -> 0.032243758 | AC9: =AC8/Y8-1 -> 0.012306402 | AD9: =AD8/BH8-1 -> 0.021067761 | AE9: =AE8/BI8-1 -> 0.006798665 | AF9: =AF8/BJ8-1 -> 0.0018268096 | AG9: =AG8/AC8-1 -> -0.047002089 | AH9: =AH8/AD8-1 -> -0.020344538 | AI9: =AI8/AE8-1 -> -0.26865353 | AJ9: =AJ8/AF8-1 -> 0.17855818 | AK9: =AK8/AG8-1 -> 0.20719967 | AL9: =AL8/AH8-1 -> 0.17501726 | AM9: =AM8/AI8-1 -> 0.63922628 | AN9: =AN8/AJ8-1 -> 0.18196345 | ... BF9: =BF8/BB8-1 -> 0.042532633 | BH9: =BH8/V8-1 -> -0.033242505 | BI9: =BI8/W8-1 -> -0.017143747 | BJ9: =BJ8/X8-1 -> -0.03293942 | BK9: =BK8/Y8-1 -> -0.20483033 | BL9: =BL8/BH8-1 -> 0.021067761 | BN9: =BN8/CD8-1 -> 0.044950438 | BO9: =BO8/BN8-1 -> 0.033559057 | BP9: =BP8/BO8-1 -> 0.037708864 | BQ9: =BQ8/BY8-1 -> 0.013760791 | BR9: =BR8/BZ8-1 -> -0.14662625 | BS9: =(BS8/BR8)-1 -> 0.37734036 | BT9: =(BT8/BS8)-1 -> 0.12078704 | BU9: =(BU8/BT8)-1 -> -0.12984461 | BV9: =(BV8/BU8)-1 -> 0.076350917 | BW9: =(BW8/BV8)-1 -> 0.10517851 | BY9: =BY8/BO8-1 -> -0.025065037 | BZ9: =BZ8/BY8-1 -> 0.013760791
B10: LFL Sales growth
B11: COGS | C11: -4654988.9 | D11: -5098131.6 | E11: -5180719.9 | F11: -5360352 | G11: -5296643 | H11: -5508545.4 | I11: -5255756.4 | J11: -5433070.2 | K11: -5790733.7 | L11: -7047860.2 | M11: -7264723.3 | N11: -6423567.1 | O11: -6844745.1 | P11: -7370628.6 | R11: -1266353.8 | S11: =BN11-R11 -> -1279016.6 | T11: =-3779644.108-S11-R11 -> -1234273.7 | U11: =E11-T11-S11-R11 -> -1401075.8 | V11: -1281071.7 | W11: =BO11-V11 -> -1305217.1 | X11: =-3867346.306-W11-V11 -> -1281057.5 | Y11: =F11-X11-W11-V11 -> -1493005.7 | Z11: -1308674.8 | AA11: =BP11-Z11 -> -1360544.2 | AB11: =-3986411.625-AA11-Z11 -> -1317192.7 | AC11: =H11-AB11-AA11-Z11 -> -1522133.7 | AD11: -1323019.3 | AE11: =BQ11-AD11 -> -1330915.3 | AF11: =-3931139.953-AE11-AD11 -> -1277205.3 | AG11: =J11-AF11-AE11-AD11 -> -1501930.3 | AH11: -1301030.6 | AI11: =BR11-AH11 -> -1063909.1 | AJ11: =-3978350.803-AI11-AH11 -> -1613411.1 | AK11: =K11-AJ11-AI11-AH11 -> -1812382.9 | AL11: -1534201.3 | AM11: =BS11-AL11 -> -1653372.8 | AN11: =-4980184.977-AM11-AL11 -> -1792610.9 | AO11: =L11-AN11-AM11-AL11 -> -2067675.3 | AP11: -1796600.8 | AQ11: =BT11-AP11 -> -1799463.2 | AR11: =-5332866.394-AQ11-AP11 -> -1736802.4 | AS11: =M11-AR11-AQ11-AP11 -> -1931856.9 | AT11: -1614201.7 | AU11: =BU11-AT11 -> -1519467.2 | AV11: =-4656631.536-AU11-AT11 -> -1522962.6 | AW11: =N11-AV11-AU11-AT11 -> -1766935.6 | AX11: -1617669.2 | AY11: =BV11-AX11 -> -1625083.1 | AZ11: =-4835758.418-AY11-AX11 -> -1593006.1 | BA11: =O11-AZ11-AY11-AX11 -> -2008986.7 | BB11: -1737013 | BC11: =BW11-BB11 -> -1749365.6 | BD11: =-5208708.004-BC11-BB11 -> -1722329.4 | BE11: =P11-BD11-BC11-BB11 -> -2161920.6 | BF11: -1802151.5 | BH11: -1253403.4 | BI11: =BY11-BH11 -> -1297192.1 | BJ11: =-3802885.751-BI11-BH11 -> -1252290.2 | BK11: =I11-Z11-AB11-AA11 -> -1269344.7 | BL11: -1323019.3 | BN11: -2545370.4 | BO11: -2586288.9 | BP11: -2669219 | BQ11: -2653934.6 | BR11: -2364939.7 | BS11: -3187574.1 | BT11: -3596064 | BU11: -3133669 | BV11: -3242752.3 | BW11: -3486378.6 | BY11: -2550595.5 | BZ11: -2653934.6
B12: Gross Profit | C12: =C8+C11 -> 2383390.9 | D12: =D8+D11 -> 2655077.9 | E12: =E8+E11 -> 2717581.8 | F12: =F8+F11 -> 2882293.2 | G12: =G8+G11 -> 2913208.5 | H12: =H8+H11 -> 2975032 | I12: =I8+I11 -> 2721142.1 | J12: =J8+J11 -> 2620512.6 | ... P12: =P8+P11 -> 3971757.3 | R12: =R8+R11 -> 623242.44 | S12: =S8+S11 -> 669770.62 | T12: =T8+T11 -> 635284.05 | U12: =U8+U11 -> 789284.74 | V12: =V8+V11 -> 670961.37 | W12: =W8+W11 -> 709945.8 | X12: =X8+X11 -> 660936.14 | Y12: =Y8+Y11 -> 840449.9 | ... BF12: =BF8+BF11 -> 963874.49 | BH12: =BH8+BH11 -> 633739.29 | BI12: =BI8+BI11 -> 683423.31 | BJ12: =BJ8+BJ11 -> 625735.21 | BK12: =BK8+BK11 -> 586148.44 | BL12: =BL8+BL11 -> 603881.25 | BN12: =BN8+BN11 -> 1293013.1 | BO12: =BO8+BO11 -> 1380907.2 | BP12: =BP8+BP11 -> 1447575.5 | BQ12: =BQ8+BQ11 -> 1267046.9 | BR12: =BR8+BR11 -> 981122.98 | BS12: =BS8+BS11 -> 1421093.1 | BT12: =BT8+BT11 -> 1569270.5 | BU12: =BU8+BU11 -> 1360974.7 | ... BW12: =BW8+BW11 -> 1860269.2 | BY12: =BY8+BY11 -> 1317162.6 | BZ12: =BZ8+BZ11 -> 1267046.9
B13: Gross Profit margin | C13: =C12/C8 -> 0.33862777 | D13: =D12/D8 -> 0.34244888 | E13: =E12/E8 -> 0.34407166 | F13: =F12/F8 -> 0.34968061 | G13: =G12/G8 -> 0.35484303 | H13: =H12/H8 -> 0.3506813 | I13: =I12/I8 -> 0.34112783 | J13: =J12/J8 -> 0.32538469 | ... P13: =P12/P8 -> 0.35016947 | R13: =R12/R8 -> 0.32982837 | S13: =S12/S8 -> 0.34368586 | T13: =T12/T8 -> 0.33980446 | U13: =U12/U8 -> 0.36034466 | V13: =V12/V8 -> 0.34372438 | W13: =W12/W8 -> 0.35230194 | X13: =X12/X8 -> 0.34033899 | Y13: =Y12/Y8 -> 0.36017394 | ... BF13: =BF12/BF8 -> 0.34846907 | BH13: =BH12/BH8 -> 0.33581949 | BI13: =BI12/BI8 -> 0.34505603 | BJ13: =BJ12/BJ8 -> 0.33318782 | BK13: =BK12/BK8 -> 0.315899 | BL13: =BL12/BL8 -> 0.31339514 | BN13: =BN12/BN8 -> 0.33686396 | BO13: =BO12/BO8 -> 0.34808141 | BP13: =BP12/BP8 -> 0.35162686 | BQ13: =BQ12/BQ8 -> 0.32314534 | BR13: =BR12/BR8 -> 0.29321715 | BS13: =BS12/BS8 -> 0.3083523 | BT13: =BT12/BT8 -> 0.3038081 | BU13: =BU12/BU8 -> 0.30279924 | ... BW13: =BW12/BW8 -> 0.34793188 | BY13: =BY12/BY8 -> 0.34054937 | BZ13: =BZ12/BZ8 -> 0.32314534
B14: Distribution costs | C14: =-82780.323 -> -82780.323 | D14: =-82294.591 -> -82294.591 | E14: =-89751.825 -> -89751.825 | F14: -84461.522 | G14: -96735.311 | H14: -115829.43 | I14: -115035.38 | J14: -121283.22 | K14: -191796.6 | L14: -220052.79 | M14: -230005.27 | N14: -186697.56 | O14: -172518.14 | P14: -191975.74 | R14: =-20361.824 -> -20361.824 | S14: =BN14-R14 -> -27489.368 | T14: =-68104.112-S14-R14 -> -20252.92 | U14: =E14-T14-S14-R14 -> -21647.713 | V14: =-21251.85 -> -21251.85 | W14: =BO14-V14 -> -20785.146 | X14: =-61890.621-W14-V14 -> -19853.625 | Y14: =F14-X14-W14-V14 -> -22570.901 | Z14: -27799.856 | AA14: =BP14-Z14 -> -28348.288 | AB14: =-82802.048-AA14-Z14 -> -26653.904 | AC14: =H14-AB14-AA14-Z14 -> -33027.383 | AD14: -31929.885 | AE14: =BQ14-AD14 -> -31961.789 | AF14: =-88044.424-AE14-AD14 -> -24152.75 | AG14: =J14-AF14-AE14-AD14 -> -33238.792 | AH14: -30574.627 | AI14: =BR14-AH14 -> -41142.494 | AJ14: =-133280.501-AI14-AH14 -> -61563.38 | AK14: =K14-AJ14-AI14-AH14 -> -58516.1 | AL14: -45456.562 | AM14: =BS14-AL14 -> -55091.847 | AN14: =-153333.855-AM14-AL14 -> -52785.446 | AO14: =L14-AN14-AM14-AL14 -> -66718.931 | AP14: -55163.396 | AQ14: =BT14-AP14 -> -62389.878 | AR14: =-165930.646-AQ14-AP14 -> -48377.372 | AS14: =M14-AR14-AQ14-AP14 -> -64074.629 | AT14: -51562.236 | AU14: =BU14-AT14 -> -47262.47 | AV14: =-138182.98-AU14-AT14 -> -39358.274 | AW14: =N14-AV14-AU14-AT14 -> -48514.58 | AX14: -37683.197 | AY14: =BV14-AX14 -> -42255.766 | AZ14: =-121728.214-AY14-AX14 -> -41789.251 | BA14: =O14-AZ14-AY14-AX14 -> -50789.924 | BB14: -45055.521 | BC14: =BW14-BB14 -> -46540.207 | BD14: =-134372.666-BC14-BB14 -> -42776.938 | BE14: =P14-BD14-BC14-BB14 -> -57603.074 | BF14: -50077.449 | BH14: -27604.65 | BI14: =BY14-BH14 -> -28128.325 | BJ14: =-82212.746-BI14-BH14 -> -26479.771 | BK14: =I14-Z14-AB14-AA14 -> -32233.328 | BL14: -30390.169 | BN14: =-47851.192 -> -47851.192 | BO14: =-42036.996 -> -42036.996 | BP14: -56148.144 | BQ14: -63891.674 | BR14: -71717.121 | BS14: -100548.41 | BT14: -117553.27 | BU14: -98824.706 | BV14: -79938.963 | BW14: -91595.728 | BY14: -55732.975 | BZ14: -60842.881
B15: Administrative expenses | C15: -1457458.8 | D15: -1683851 | E15: -1716574.7 | F15: -1832012.7 | G15: -1847408.4 | H15: -1946931.2 | I15: -1904010.2 | J15: -1966962.4 | K15: -1988674.1 | L15: -2080380.9 | M15: -2441176 | N15: -2357878.6 | O15: -2469130.4 | P15: -2578530.2 | R15: -412196.86 | S15: =BN15-R15 -> -418926.81 | T15: =-1258480.94-S15-R15 -> -427357.26 | U15: =E15-T15-S15-R15 -> -458093.8 | V15: -432963.4 | W15: =BO15-V15 -> -453020.25 | X15: =-1343869.179-W15-V15 -> -457885.54 | Y15: =F15-X15-W15-V15 -> -488143.5 | Z15: -456051.22 | AA15: =BP15-Z15 -> -483628.67 | AB15: =-1417503.229-AA15-Z15 -> -477823.34 | AC15: =H15-AB15-AA15-Z15 -> -529427.95 | AD15: -456016.55 | AE15: =BQ15-AD15 -> -481909.43 | AF15: =-1418658.106-AE15-AD15 -> -480732.12 | AG15: =J15-AF15-AE15-AD15 -> -548304.29 | AH15: -492657.95 | AI15: =BR15-AH15 -> -475280.44 | AJ15: =-1457406.418-AI15-AH15 -> -489468.02 | AK15: =K15-AJ15-AI15-AH15 -> -531267.7 | AL15: -465395.41 | AM15: =BS15-AL15 -> -474591.6 | AN15: =-1467546.165-AM15-AL15 -> -527559.16 | AO15: =L15-AN15-AM15-AL15 -> -612834.75 | AP15: -558138.01 | AQ15: =BT15-AP15 -> -600623.12 | AR15: =-1786267.314-AQ15-AP15 -> -627506.19 | AS15: =M15-AR15-AQ15-AP15 -> -654908.7 | AT15: -569760.36 | AU15: =BU15-AT15 -> -582137.19 | AV15: =-1742316.662-AU15-AT15 -> -590419.11 | AW15: =N15-AV15-AU15-AT15 -> -615561.92 | AX15: -592391.92 | AY15: =BV15-AX15 -> -594271.86 | AZ15: =-1796310.047-AY15-AX15 -> -609646.27 | BA15: =O15-AZ15-AY15-AX15 -> -672820.31 | BB15: -611779.62 | BC15: =BW15-BB15 -> -622738.27 | BD15: =-1876988.159-BC15-BB15 -> -642470.28 | BE15: =P15-BD15-BC15-BB15 -> -701542 | BF15: -627437.98 | BH15: -445572.49 | BI15: =BY15-BH15 -> -472304.59 | BJ15: =-1384656.917-BI15-BH15 -> -466779.83 | BK15: =I15-Z15-AB15-AA15 -> -486507.01 | BL15: -457556.27 | BN15: -831123.68 | BO15: -885983.64 | BP15: -939679.89 | BQ15: -937925.99 | BR15: -967938.4 | BS15: -939987.01 | BT15: -1158761.1 | BU15: -1151897.5 | BV15: -1186663.8 | BW15: -1234517.9 | BY15: -917877.08 | BZ15: -940974.78
B16: Other gains (losses) | C16: 8506.262 | D16: 33749.211 | E16: 160726.38 | F16: 5689.395 | G16: 3289.726 | H16: 24079.804 | I16: 24657.249 | J16: 20796.536 | K16: -45064.092 | L16: -29055.029 | M16: 9378.916 | N16: =226571.067 -> 226571.07 | O16: 195716.95 | P16: 1367762 | R16: 1161.901 | S16: =BN16-R16 -> -648.153 | T16: =137610.958-S16-R16 -> 137097.21 | U16: =E16-T16-S16-R16 -> 23115.419 | V16: -5889.723 | W16: =BO16-V16 -> 8506.923 | X16: =1355.087-W16-V16 -> -1262.113 | Y16: =F16-X16-W16-V16 -> 4334.308 | Z16: -238.956 | AA16: =BP16-Z16 -> -1554.962 | AB16: =-442.73-AA16-Z16 -> 1351.188 | AC16: =H16-AB16-AA16-Z16 -> 24522.534 | AD16: -573.83 | AE16: =BQ16-AD16 -> 9095.729 | AF16: =12274.805-AE16-AD16 -> 3752.906 | AG16: =J16-AF16-AE16-AD16 -> 8521.731 | AH16: 310.265 | AI16: =BR16-AH16 -> 1451.528 | AJ16: =3924.185-AI16-AH16 -> 2162.392 | AK16: =K16-AJ16-AI16-AH16 -> -48988.277 | AL16: -4290.924 | AM16: =BS16-AL16 -> -1470.839 | AN16: =-1446.131-AM16-AL16 -> 4315.632 | AO16: =L16-AN16-AM16-AL16 -> -27608.898 | AP16: 2016.356 | AQ16: =BT16-AP16 -> 83406.528 | AR16: =98690.059 -AQ16-AP16 -> 13267.175 | AS16: =M16-AR16-AQ16-AP16 -> -89311.143 | AT16: 5337 | AU16: =BU16-AT16 -> 170546.43 | AV16: =180918.5-AU16-AT16 -> 5035.073 | AW16: =N16-AV16-AU16-AT16 -> 45652.567 | AX16: 8961.685 | AY16: =BV16-AX16 -> 114692.51 | AZ16: =130389.576-AY16-AX16 -> 6735.379 | BA16: =O16-AZ16-AY16-AX16 -> 65327.378 | BB16: 8023.633 | BC16: =BW16-BB16 -> 432144.41 | BD16: =454570.425-BC16-BB16 -> 14402.383 | BE16: =P16-BD16-BC16-BB16 -> 913191.61 | BF16: 11524.835 | BH16: -306.15 | BI16: =BY16-BH16 -> -1334.111 | BJ16: =120.767-BI16-BH16 -> 1761.028 | BK16: =I16-Z16-AB16-AA16 -> 25099.979 | BL16: -573.83 | BN16: 513.748 | BO16: 2617.2 | BP16: -1793.918 | BQ16: 8521.899 | BR16: 1761.793 | BS16: -5761.763 | BT16: 85422.884 | BU16: 175883.43 | BV16: 123654.2 | BW16: 440168.04 | BY16: -1640.261 | BZ16: 8521.899
B17: Other expenses | C17: -136398.08 | D17: -142275.8 | E17: -135229.38 | F17: -148468.52 | G17: -149314.64 | H17: -142404.86 | I17: -139868.2 | J17: -141899.29 | K17: -111787.54 | L17: -181917.88 | M17: -230886.7 | N17: =-125990.851 -> -125990.85 | O17: -111299.14 | P17: -117786.3 | R17: -29322.073 | S17: =BN17-R17 -> -34087.158 | T17: =-95111.051-S17-R17 -> -31701.82 | U17: =E17-T17-S17-R17 -> -40118.326 | V17: -27598.993 | W17: =BO17-V17 -> -38226.494 | X17: =-102100.525-W17-V17 -> -36275.038 | Y17: =F17-X17-W17-V17 -> -46367.996 | Z17: -27231.974 | AA17: =BP17-Z17 -> -35553.002 | AB17: =-97523.042-AA17-Z17 -> -34738.066 | AC17: =H17-AB17-AA17-Z17 -> -44881.818 | AD17: -28701.599 | AE17: =BQ17-AD17 -> -35788.598 | AF17: =-96458.229-AE17-AD17 -> -31968.032 | AG17: =J17-AF17-AE17-AD17 -> -45441.061 | AH17: -28787.759 | AI17: =BR17-AH17 -> -19880.297 | AJ17: =-72442.206-AI17-AH17 -> -23774.15 | AK17: =K17-AJ17-AI17-AH17 -> -39345.338 | AL17: -29113.605 | AM17: =BS17-AL17 -> -34335.976 | AN17: =-109012.651-AM17-AL17 -> -45563.07 | AO17: =L17-AN17-AM17-AL17 -> -72905.224 | AP17: -41598.689 | AQ17: =BT17-AP17 -> -55961.568 | AR17: =-144595.497-AQ17-AP17 -> -47035.24 | AS17: =M17-AR17-AQ17-AP17 -> -86291.202 | AT17: -35779.462 | AU17: =BU17-AT17 -> -19855.449 | AV17: =-85427.185-AU17-AT17 -> -29792.274 | AW17: =N17-AV17-AU17-AT17 -> -40563.666 | AX17: -22293.91 | AY17: =BV17-AX17 -> -31062.203 | AZ17: =-76560.98-AY17-AX17 -> -23204.867 | BA17: =O17-AZ17-AY17-AX17 -> -34738.157 | BB17: -24655.229 | BC17: =BW17-BB17 -> -30004.953 | BD17: =-78283.815-BC17-BB17 -> -23623.633 | BE17: =P17-BD17-BC17-BB17 -> -39502.485 | BF17: -36726.588 | BH17: -26612.7 | BI17: =BY17-BH17 -> -34952.231 | BJ17: =-95733.611-BI17-BH17 -> -34168.68 | BK17: =I17-Z17-AB17-AA17 -> -42345.161 | BL17: -28701.599 | BN17: -63409.231 | BO17: -65825.487 | BP17: -62784.976 | BQ17: -64490.197 | BR17: -48668.056 | BS17: -63449.581 | BT17: -97560.257 | BU17: -55634.911 | BV17: -53356.113 | BW17: -54660.182 | BY17: -61564.931 | BZ17: -64490.197
B18: Operating Profit | C18: =C12+C15+C16+C17+C14 -> 715259.96 | D18: =D12+D15+D16+D17+D14 -> 780405.77 | E18: =E12+E15+E16+E17+E14 -> 936752.28 | F18: =F12+F15+F16+F17+F14 -> 823039.89 | G18: =G12+G15+G16+G17+G14 -> 823039.89 | H18: =H12+H15+H16+H17+H14 -> 793946.3 | I18: =I12+I15+I16+I17+I14 -> 586885.49 | J18: =J12+J15+J16+J17+J14 -> 411164.22 | ... P18: =P12+P15+P16+P17+P14 -> 2451227.1 | R18: =R12+R15+R16+R17+R14 -> 162523.58 | S18: =S12+S15+S16+S17+S14 -> 188619.13 | T18: =T12+T15+T16+T17+T14 -> 293069.25 | U18: =U12+U15+U16+U17+U14 -> 292540.32 | V18: =V12+V15+V16+V17+V14 -> 183257.41 | W18: =W12+W15+W16+W17+W14 -> 206420.83 | X18: =X12+X15+X16+X17+X14 -> 145659.83 | Y18: =Y12+Y15+Y16+Y17+Y14 -> 287701.82 | ... BF18: =BF12+BF15+BF16+BF17+BF14 -> 261157.31 | BH18: =BH12+BH15+BH16+BH17+BH14 -> 133643.3 | BI18: =BI12+BI15+BI16+BI17+BI14 -> 146704.05 | BJ18: =BJ12+BJ15+BJ16+BJ17+BJ14 -> 100067.95 | BK18: =BK12+BK15+BK16+BK17+BK14 -> 50162.92 | BL18: =BL12+BL15+BL16+BL17+BL14 -> 86659.384 | BN18: =BN12+BN15+BN16+BN17+BN14 -> 351142.71 | BO18: =BO12+BO15+BO16+BO17+BO14 -> 389678.24 | BP18: =BP12+BP15+BP16+BP17+BP14 -> 387168.58 | BQ18: =BQ12+BQ15+BQ16+BQ17+BQ14 -> 209260.95 | BR18: =BR12+BR15+BR16+BR17+BR14 -> -105438.81 | BS18: =BS12+BS15+BS16+BS17+BS14 -> 311346.35 | BT18: =BT12+BT15+BT16+BT17+BT14 -> 280818.67 | BU18: =BU12+BU15+BU16+BU17+BU14 -> 230500.94 | ... BW18: =BW12+BW15+BW16+BW17+BW14 -> 919663.48 | BY18: =BY12+BY15+BY16+BY17+BY14 -> 280347.35 | BZ18: =BZ12+BZ15+BZ16+BZ17+BZ14 -> 209260.95 | CC18: 150597.11 | CD18: 326170.15 | CE18: 478149.54
B19: Finance Income | C19: 19557.464 | D19: 33868.899 | E19: 15268.092 | F19: 16196.997 | G19: 15113.935 | H19: 37280.766 | I19: 36224.345 | J19: 27400.95 | K19: 67907.001 | L19: 124517.24 | M19: 61815.59 | N19: =46977.32 -> 46977.32 | O19: 102808.23 | P19: 78953.013 | R19: 3935.739 | S19: =BN19-R19 -> 3052.026 | T19: =11523.788-S19-R19 -> 4536.023 | U19: =E19-T19-S19-R19 -> 3744.304 | V19: 3775.812 | W19: =BO19-V19 -> 4040.425 | X19: =10472.948-W19-V19 -> 2656.711 | Y19: =F19-X19-W19-V19 -> 5724.049 | Z19: 3756.24 | AA19: =BP19-Z19 -> 11427.085 | AB19: =28555.698-AA19-Z19 -> 13372.373 | AC19: =H19-AB19-AA19-Z19 -> 8725.068 | AD19: 4412.754 | AE19: =BQ19-AD19 -> 4537.166 | AF19: =16074.752-AE19-AD19 -> 7124.832 | AG19: =J19-AF19-AE19-AD19 -> 11326.198 | AH19: 28072.221 | AI19: =BR19-AH19 -> 25324.658 | AJ19: =63585.194-AI19-AH19 -> 10188.315 | AK19: =K19-AJ19-AI19-AH19 -> 4321.807 | AL19: 22714.385 | AM19: =BS19-AL19 -> 20838.483 | AN19: =123969.821-AM19-AL19 -> 80416.953 | AO19: =L19-AN19-AM19-AL19 -> 547.423 | AP19: 5396.444 | AQ19: =BT19-AP19 -> 22294.042 | AR19: =48978.447-AQ19-AP19 -> 21287.961 | AS19: =M19-AR19-AQ19-AP19 -> 12837.143 | AT19: 24115.573 | AU19: =BU19-AT19 -> 11921.398 | AV19: =39428.427-AU19-AT19 -> 3391.456 | AW19: =N19-AV19-AU19-AT19 -> 7548.893 | AX19: 28765.129 | AY19: =BV19-AX19 -> 17531.415 | AZ19: =60808.515-AY19-AX19 -> 14511.971 | BA19: =O19-AZ19-AY19-AX19 -> 41999.711 | BB19: 20760.631 | BC19: =BW19-BB19 -> 18440.342 | BD19: =59813.362 -BC19-BB19 -> 20612.389 | BE19: =P19-BD19-BC19-BB19 -> 19139.651 | BF19: 23509.426 | BH19: 3671.008 | BI19: =BY19-BH19 -> 11168.309 | BJ19: =27823.269-BI19-BH19 -> 12983.952 | BK19: =I19-Z19-AB19-AA19 -> 7668.647 | BL19: 4412.754 | BN19: 6987.765 | BO19: 7816.237 | BP19: 15183.325 | BQ19: 8949.92 | BR19: 53396.879 | BS19: 43552.868 | BT19: 27690.486 | BU19: 36036.971 | BV19: 46296.544 | BW19: 39200.973 | BY19: 14839.317 | BZ19: 8949.92
B20: Finance costs | C20: -139227.17 | D20: -174032.52 | E20: -207568.52 | F20: -196455.24 | G20: -195372.18 | H20: -181505.28 | I20: -181142.09 | J20: -209910.8 | K20: -254510.95 | L20: -234461.9 | M20: -309849.69 | N20: =-350424.957 -> -350424.96 | O20: -350758.04 | P20: -335429.57 | R20: -54381.979 | S20: =BN20-R20 -> -56068.413 | T20: =-159376.326-S20-R20 -> -48925.934 | U20: =E20-T20-S20-R20 -> -48192.192 | V20: -51801.873 | W20: =BO20-V20 -> -43827.315 | X20: =-145347.459-W20-V20 -> -49718.271 | Y20: =F20-X20-W20-V20 -> -51107.784 | Z20: -50233.337 | AA20: =BP20-Z20 -> -44211.044 | AB20: =-139784.912-AA20-Z20 -> -45340.531 | AC20: =H20-AB20-AA20-Z20 -> -41720.368 | AD20: -54309.432 | AE20: =BQ20-AD20 -> -55575.907 | AF20: =-147869.227-AE20-AD20 -> -37983.888 | AG20: =J20-AF20-AE20-AD20 -> -62041.573 | AH20: -53153.389 | AI20: =BR20-AH20 -> -61728.703 | AJ20: =-176938.059-AI20-AH20 -> -62055.967 | AK20: =K20-AJ20-AI20-AH20 -> -77572.89 | AL20: -47771.875 | AM20: =BS20-AL20 -> -53170.201 | AN20: =-166696.133-AM20-AL20 -> -65754.057 | AO20: =L20-AN20-AM20-AL20 -> -67765.772 | AP20: -108657.84 | AQ20: =BT20-AP20 -> -33336.292 | AR20: =-201891.374-AQ20-AP20 -> -59897.246 | AS20: =M20-AR20-AQ20-AP20 -> -107958.32 | AT20: -96805.603 | AU20: =BU20-AT20 -> -91071.717 | AV20: =-255786.52-AU20-AT20 -> -67909.2 | AW20: =N20-AV20-AU20-AT20 -> -94638.437 | AX20: -90388.715 | AY20: =BV20-AX20 -> -88702.059 | AZ20: =-265136.464-AY20-AX20 -> -86045.69 | BA20: =O20-AZ20-AY20-AX20 -> -85621.578 | BB20: -94038.014 | BC20: =BW20-BB20 -> -84255.246 | BD20: =-246995.032-BC20-BB20 -> -68701.772 | BE20: =P20-BD20-BC20-BB20 -> -88434.542 | BF20: -69394.736 | BH20: -50066.245 | BI20: =BY20-BH20 -> -44102.53 | BJ20: =-139455.425-BI20-BH20 -> -45286.65 | BK20: =I20-Z20-AB20-AA20 -> -41357.182 | BL20: -54309.432 | BN20: -110450.39 | BO20: -95629.188 | BP20: -94444.381 | BQ20: -109885.34 | BR20: -114882.09 | BS20: -100942.08 | BT20: -141994.13 | BU20: -187877.32 | BV20: -179090.77 | BW20: -178293.26 | BY20: -94168.775 | BZ20: -109885.34
B21: Gain on net non-monetary position | C21: =26155.945-40226.654-41114.681 -> -55185.39 | D21: =25272.409-18208.873-33455.45 -> -26391.914 | E21: =21247.989+3637.364-26087.89 -> -1202.537 | F21: =15279.304-466.04-17264.195 -> -2450.931 | G21: =(15279304-466040-17264195)/1000 -> -2450.931 | H21: =(7092186-15793359-22494868)/1000 -> -31196.041 | I21: =(7092186-15580747-22494868)/1000 -> -30983.429 | J21: =336.784-22065.192-21944.001 -> -43672.409 | K21: =3579.174-29085.779-28678.051 -> -54184.656 | L21: =22662.137-41110.07-56003.432 -> -74451.365 | M21: =16815.716-7706.67-153721.901 -> -144612.86 | N21: =19044.549+38739.34-66019.02 -> -8235.131 | O21: =24797.081-2548.839-63021.636 -> -40773.394 | P21: =30301.086+44437.584-(52130.972) -> 22607.698 | R21: =5592.977+16.605-6285.019 -> -675.437 | S21: =BN21-R21 -> 3205.373 | T21: =15431.963+3494.044-20794.127-S21-R21 -> -4398.056 | U21: =E21-T21-S21-R21 -> 665.583 | V21: =4371.96+2316.799-4283.507 -> 2405.252 | W21: =BO21-V21 -> -7059.253 | X21: =9730.899+1077.901-10654.905-W21-V21 -> 4807.896 | Y21: =F21-X21-W21-V21 -> -2604.826 | Z21: =(2394134+617271-6344480)/1000 -> -3333.075 | AA21: =BP21-Z21 -> -10102.457 | AB21: =5436.026-16937.342-18114.625-AA21-Z21 -> -16180.409 | AC21: =H21-AB21-AA21-Z21 -> -1580.1 | AD21: =(887202+510869+66641)/1000 -> 1464.712 | AE21: =BQ21-AD21 -> -10659.281 | AF21: =-613.139-19594.921-14045.294-AE21-AD21 -> -25058.785 | AG21: =J21-AF21-AE21-AD21 -> -9419.055 | AH21: =-(2478.993+13188.965+10124.833) -> -25792.791 | AI21: =BR21-AH21 -> -15743.077 | AJ21: =-3763.851-27819.351-15422.249-AI21-AH21 -> -5469.583 | AK21: =K21-AJ21-AI21-AH21 -> -7179.205 | AL21: =5203.08-15240.587-13628.005 -> -23665.512 | AM21: =BS21-AL21 -> -20556.122 | AN21: =14069.113-45488.032-38445.355-AM21-AL21 -> -25642.64 | AO21: =L21-AN21-AM21-AL21 -> -4587.091 | AP21: =6011.224+33227.037-26964.404 -> 12273.857 | AQ21: =BT21-AP21 -> -54114.182 | AR21: =16553.36+1200.253-133092.133-AQ21-AP21 -> -73498.195 | AS21: =M21-AR21-AQ21-AP21 -> -29274.335 | AT21: =3614.252+3036.816-18730.946 -> -12079.878 | AU21: =BU21-AT21 -> 354.884 | AV21: =12331.587+23367.896-45091.23-AU21-AT21 -> 2333.247 | AW21: =N21-AV21-AU21-AT21 -> 1156.616 | AX21: =5606.295-2032.213-15027.684 -> -11453.602 | AY21: =BV21-AX21 -> -21893.353 | AZ21: =16936.959-4432.88-43684.137-AY21-AX21 -> 2166.897 | BA21: =O21-AZ21-AY21-AX21 -> -9593.336 | BB21: =10036.743+12201.239-18860.288 -> 3377.694 | BC21: =BW21-BB21 -> 5351.218 | BD21: =26648.632+30195.877-42516.403-BC21-BB21 -> 5599.194 | BE21: =P21-BD21-BC21-BB21 -> 8279.592 | BF21: =11864.798-10930.868-5036.057 -> -4102.127 | BH21: =(2394134+640584-6344480)/1000 -> -3309.762 | BI21: =BY21-BH21 -> -10040.852 | BJ21: =5436.026-16592.306-18114.625-BI21-BH21 -> -15920.291 | BK21: =I21-Z21-AB21-AA21 -> -1367.488 | BL21: =(887202+510869+66641)/1000 -> 1464.712 | BN21: =11068.964+6441.022-14980.05 -> 2529.936 | BO21: =7103.763-839.968-10917.796 -> -4654.001 | BP21: =4035.861-5826.501-11644.892 -> -13435.532 | BQ21: =78.625+1243.574-10516.768 -> -9194.569 | BR21: =-5074.5-21441.132-15020.236 -> -41535.868 | BS21: =8117.858-27257.443-25082.049 -> -44221.634 | BT21: =11266.09+31772.34-84878.755 -> -41840.325 | BU21: =6532.513+25848.165-44105.672 -> -11724.994 | BV21: =10117.03-13377.011-30086.974 -> -33346.955 | BW21: =18311.75+24710.672-34293.51 -> 8728.912 | BY21: =4035.861-5741.583-11644.892 -> -13350.614 | BZ21: =78.625+1243.574-10516.768 -> -9194.569
B22: Profit before tax | C22: =C18+C19+C20+C21 -> 540404.86 | D22: =D18+D19+D20+D21 -> 613850.24 | E22: =E18+E19+E20+E21 -> 743249.31 | F22: =F18+F19+F20+F21 -> 640330.71 | G22: =G18+G19+G20+G21 -> 640330.71 | H22: =H18+H19+H20+H21 -> 618525.74 | I22: =I18+I19+I20+I21 -> 410984.31 | J22: =J18+J19+J20+J21 -> 184981.96 | ... P22: =P18+P19+P20+P21 -> 2217358.2 | R22: =R18+R19+R20+R21 -> 111401.9 | S22: =S18+S19+S20+S21 -> 138808.12 | T22: =T18+T19+T20+T21 -> 244281.29 | U22: =U18+U19+U20+U21 -> 248758.01 | V22: =V18+V19+V20+V21 -> 137636.6 | W22: =W18+W19+W20+W21 -> 159574.69 | X22: =X18+X19+X20+X21 -> 103406.17 | Y22: =Y18+Y19+Y20+Y21 -> 239713.26 | ... BF22: =BF18+BF19+BF20+BF21 -> 211169.87 | BH22: =BH18+BH19+BH20+BH21 -> 83938.301 | BI22: =BI18+BI19+BI20+BI21 -> 103728.98 | BJ22: =BJ18+BJ19+BJ20+BJ21 -> 51844.96 | BK22: =BK18+BK19+BK20+BK21 -> 15106.897 | BL22: =BL18+BL19+BL20+BL21 -> 38227.418 | BN22: =BN18+BN19+BN20+BN21 -> 250210.01 | BO22: =BO18+BO19+BO20+BO21 -> 297211.29 | BP22: =BP18+BP19+BP20+BP21 -> 294472 | BQ22: =BQ18+BQ19+BQ20+BQ21 -> 99130.963 | BR22: =BR18+BR19+BR20+BR21 -> -208459.89 | BS22: =BS18+BS19+BS20+BS21 -> 209735.51 | BT22: =BT18+BT19+BT20+BT21 -> 124674.71 | BU22: =BU18+BU19+BU20+BU21 -> 66935.594 | ... BW22: =BW18+BW19+BW20+BW21 -> 789300.11 | BY22: =BY18+BY19+BY20+BY21 -> 187667.28 | BZ22: =BZ18+BZ19+BZ20+BZ21 -> 99130.963
B23: Income tax benefit/(expense) | C23: -101425.82 | D23: -134095.69 | E23: -148580.18 | F23: -159920.61 | G23: -159920.61 | H23: -152653.83 | I23: -101167.1 | J23: -62097.989 | K23: -5243.074 | L23: -137325.97 | M23: 80781.84 | N23: -27913.013 | O23: -200897.07 | P23: -535651.53 | R23: -20399.589 | S23: =BN23-R23 -> -30086.647 | T23: =-71778.793-S23-R23 -> -21292.557 | U23: =E23-T23-S23-R23 -> -76801.383 | V23: -29460.29 | W23: =BO23-V23 -> -40121.705 | X23: =-96767.076-W23-V23 -> -27185.081 | Y23: =F23-X23-W23-V23 -> -63153.537 | Z23: -35758.106 | AA23: =BP23-Z23 -> -28281.048 | AB23: =-89312.595-AA23-Z23 -> -25273.441 | AC23: =H23-AB23-AA23-Z23 -> -63341.235 | AD23: -14400.612 | AE23: =BQ23-AD23 -> -14824.508 | AF23: =-38987.134-AE23-AD23 -> -9762.014 | AG23: =J23-AF23-AE23-AD23 -> -23110.855 | AH23: -2182.474 | AI23: =BR23-AH23 -> 49471.331 | AJ23: =47995.639-AI23-AH23 -> 706.782 | AK23: =K23-AJ23-AI23-AH23 -> -53238.713 | AL23: -22309.986 | AM23: =BS23-AL23 -> -34146.64 | AN23: =-106620.197-AM23-AL23 -> -50163.571 | AO23: =L23-AN23-AM23-AL23 -> -30705.77 | AP23: 17397.789 | AQ23: =BT23-AP23 -> -20172.839 | AR23: =27079.479-AQ23-AP23 -> 29854.529 | AS23: =M23-AR23-AQ23-AP23 -> 53702.361 | AT23: 20643.061 | AU23: =BU23-AT23 -> -30881.21 | AV23: =3355.558-AU23-AT23 -> 13593.707 | AW23: =N23-AV23-AU23-AT23 -> -31268.571 | AX23: -23193.99 | AY23: =BV23-AX23 -> -68739.61 | AZ23: =-113714.95-AY23-AX23 -> -21781.35 | BA23: =O23-AZ23-AY23-AX23 -> -87182.119 | BB23: -43348.541 | BC23: =BW23-BB23 -> -158935.54 | BD23: =-246752.197-BC23-BB23 -> -44468.112 | BE23: =P23-BD23-BC23-BB23 -> -288899.33 | BF23: -62303.524 | BH23: -21746.325 | BI23: =BY23-BH23 -> -15952.798 | BJ23: =-50556.535-BI23-BH23 -> -12857.412 | BK23: =I23-Z23-AB23-AA23 -> -11854.5 | BL23: -14400.612 | BN23: -50486.236 | BO23: -69581.995 | BP23: -64039.154 | BQ23: -29225.12 | BR23: 47288.857 | BS23: -56456.626 | BT23: -2775.05 | BU23: -10238.149 | BV23: -91933.6 | BW23: -202284.08 | BY23: -37699.123 | BZ23: -29225.12
B24: Profit/(loss) from continuing operations | C24: =C22+C23 -> 438979.04 | D24: =D22+D23 -> 479754.55 | E24: =E22+E23 -> 594669.14 | F24: =F22+F23 -> 480410.1 | G24: =G22+G23 -> 480410.1 | H24: =H22+H23 -> 465871.91 | I24: =I22+I23 -> 309817.21 | J24: =J22+J23 -> 122883.97 | ... P24: =P22+P23 -> 1681706.7 | R24: =R22+R23 -> 91002.31 | S24: =S22+S23 -> 108721.47 | T24: =T22+T23 -> 222988.73 | U24: =U22+U23 -> 171956.63 | V24: =V22+V23 -> 108176.31 | W24: =W22+W23 -> 119452.99 | X24: =X22+X23 -> 76221.084 | Y24: =Y22+Y23 -> 176559.72 | ... BF24: =BF22+BF23 -> 148866.35 | BH24: =BH22+BH23 -> 62191.976 | BI24: =BI22+BI23 -> 87776.182 | BJ24: =BJ22+BJ23 -> 38987.548 | BK24: =BK22+BK23 -> 3252.397 | BL24: =BL22+BL23 -> 23826.806 | BN24: =BN22+BN23 -> 199723.78 | BO24: =BO22+BO23 -> 227629.3 | BP24: =BP22+BP23 -> 230432.84 | BQ24: =BQ22+BQ23 -> 69905.843 | BR24: =BR22+BR23 -> -161171.03 | BS24: =BS22+BS23 -> 153278.88 | BT24: =BT22+BT23 -> 121899.66 | BU24: =BU22+BU23 -> 56697.445 | ... BW24: =BW22+BW23 -> 587016.02 | BY24: =BY22+BY23 -> 149968.16 | BZ24: =BZ22+BZ23 -> 69905.843 | CC24: 93668.103 | CD24: 196361.11 | CE24: 279718.66
B25: Loss from discontinued Operations | C25: 0 | D25: 0 | E25: 0 | F25: 0 | G25: 0 | H25: 0 | I25: 0 | J25: 0 | K25: 0 | L25: 0 | M25: 0 | N25: 0 | O25: 0 | P25: 0 | R25: 0 | S25: =BN25-R25 -> 0 | T25: =0-S25-R25 -> 0 | U25: =E25-T25-S25-R25 -> 0 | V25: 0 | W25: =BO25-V25 -> 0 | X25: =0-W25-V25 -> 0 | Y25: =F25-X25-W25-V25 -> 0 | Z25: =G25-Y25-X25-W25 -> 0 | AA25: =H25-Z25-Y25-X25 -> 0 | AB25: =I25-AA25-Z25-Y25 -> 0 | AC25: =J25-AB25-AA25-Z25 -> 0 | AD25: =K25-AC25-AB25-AA25 -> 0 | AE25: =L25-AD25-AC25-AB25 -> 0 | AF25: =M25-AE25-AD25-AC25 -> 0 | ... AH25: =O25-AG25-AF25-AE25 -> 0 | AI25: =Q25-AH25-AG25-AF25 -> 0 | AJ25: =R25-AI25-AH25-AG25 -> 0 | AK25: =S25-AJ25-AI25-AH25 -> 0 | AL25: =T25-AK25-AJ25-AI25 -> 0 | AM25: =U25-AL25-AK25-AJ25 -> 0 | AN25: =V25-AM25-AL25-AK25 -> 0 | AO25: =W25-AN25-AM25-AL25 -> 0 | AP25: =X25-AO25-AN25-AM25 -> 0 | ... BD25: =AL25-BC25-BB25-BA25 -> 0 | BE25: =P25-BD25-BC25-BB25 -> 0 | BF25: =AN25-BE25-BD25-BC25 -> 0 | BH25: =(T25-BG25-AD25-AC25)/1000 -> 0 | BI25: =(U25-BH25-AE25-AD25)/1000 -> 0 | BJ25: =(V25-BI25-AF25-AE25)/1000 -> 0 | BK25: =I25-Z25-AB25-AA25 -> 0 | BL25: =(AB25-BK25-BJ25-BI25)/1000 -> 0 | BN25: 0 | BO25: 0 | BP25: 0 | BQ25: 0 | BR25: 0 | BS25: 0 | BT25: 0 | BU25: 0 | BV25: 0 | BW25: 0 | BY25: 0 | BZ25: 0 | CD25: 0 | CE25: 0
B26: Profit for the year (Non-banking businesses) | C26: =C24+C25 -> 438979.04 | D26: =D24+D25 -> 479754.55 | E26: =E24+E25 -> 594669.14 | F26: =F24+F25 -> 480410.1 | G26: =G24+G25 -> 480410.1 | H26: =H24+H25 -> 465871.91 | I26: =I24+I25 -> 309817.21 | J26: =J24+J25 -> 122883.97 | ... P26: =P24+P25 -> 1681706.7 | R26: =R24+R25 -> 91002.31 | S26: =S24+S25 -> 108721.47 | T26: =T24+T25 -> 222988.73 | U26: =U24+U25 -> 171956.63 | V26: =V24+V25 -> 108176.31 | W26: =W24+W25 -> 119452.99 | X26: =X24+X25 -> 76221.084 | Y26: =Y24+Y25 -> 176559.72 | ... BF26: =BF24+BF25 -> 148866.35 | BH26: =BH24+BH25 -> 62191.976 | BI26: =BI24+BI25 -> 87776.182 | BJ26: =BJ24+BJ25 -> 38987.548 | BK26: =BK24+BK25 -> 3252.397 | BL26: =BL24+BL25 -> 23826.806 | BN26: =BN24+BN25 -> 199723.78 | BO26: =BO24+BO25 -> 227629.3 | BP26: =BP24+BP25 -> 230432.84 | BQ26: =BQ24+BQ25 -> 69905.843 | BR26: =BR24+BR25 -> -161171.03 | BS26: =BS24+BS25 -> 153278.88 | BT26: =BT24+BT25 -> 121899.66 | BU26: =BU24+BU25 -> 56697.445 | ... BW26: =BW24+BW25 -> 587016.02 | BY26: =BY24+BY25 -> 149968.16 | BZ26: =BZ24+BZ25 -> 69905.843 | CC26: =CC24 -> 93668.103 | CD26: =CD24 -> 196361.11 | CE26: =CE24 -> 279718.66
B28: Banking Business Income statement | C28: 41975 | D28: 42341 | E28: 42708 | F28: 43073 | G28: =G3 -> 43073 | H28: =H3 -> 43438 | I28: =I3 -> 43438 | J28: =J3 -> 43803 | K28: =K3 -> 44169 | L28: =L3 -> 44534 | M28: =M3 -> 44899 | N28: =N3 -> 45264 | ... P28: =P3 -> 45995 | R28: 42437 | S28: 42527 | T28: 42622 | U28: 42714 | V28: 42801 | W28: 42892 | X28: 42987 | Y28: 43079 | Z28: =Z3 -> 43166 | AA28: =AA3 -> 43257 | AB28: =AB3 -> 43352 | AC28: =AC3 -> 43444 | AD28: =AD3 -> 43531 | AE28: =AE3 -> 43622 | AF28: =AF3 -> 43738 | AG28: =AG3 -> 43809 | ... BF28: =BF3 -> 46112 | BH28: =BH3 -> 43166 | BI28: =BI3 -> 43281 | BJ28: =BJ3 -> 43373 | BK28: =BK3 -> 43444 | BL28: =BL3 -> 43531 | BN28: 42530 | BO28: 42896 | BP28: =BP3 -> 43261 | BQ28: =BQ3 -> 43646 | BR28: =BR3 -> 44012 | BS28: =BS3 -> 44377 | BT28: =BT3 -> 44742 | BU28: =BU3 -> 45107 | BV28: =BV3 -> 45473 | BW28: =BW3 -> 45838 | BY28: =BY3 -> 43281 | BZ28: =BZ3 -> 43646
B29: Interest and indexation income. | C29: 445605.72 | D29: 485319.46 | E29: 526664.49 | F29: 556942.54 | G29: 580503.51 | H29: 598968.12 | I29: 1030424.2 | J29: 1108746 | K29: 978716.65 | L29: 901241.5 | M29: 1483314.9 | N29: =1478556.46+41291.16 -> 1519847.6 | O29: =1387171.214+35532.885 -> 1422704.1 | P29: =1476334.739+30905.664 -> 1507240.4 | R29: 125539.16 | S29: =BN29-R29 -> 131560.53 | T29: =390560.638-S29-R29 -> 133460.95 | U29: =E29-T29-S29-R29 -> 136103.85 | V29: 138497.89 | W29: =BO29-V29 -> 144720.75 | X29: =419434.845-W29-V29 -> 136216.21 | Y29: =F29-X29-W29-V29 -> 137507.69 | Z29: 142435.81 | AA29: =BP29-Z29 -> 147279.5 | AB29: =442891.404-AA29-Z29 -> 153176.1 | AC29: =H29-AB29-AA29-Z29 -> 156076.72 | AD29: 266179.13 | AE29: =BQ29-AD29 -> 279234.26 | AF29: =824896.564-AE29-AD29 -> 279483.17 | AG29: =J29-AF29-AE29-AD29 -> 283849.4 | AH29: 286649.93 | AI29: =BR29-AH29 -> 254568.62 | AJ29: =762024.745-AI29-AH29 -> 220806.2 | AK29: =K29-AJ29-AI29-AH29 -> 216691.91 | AL29: 208676.1 | AM29: =BS29-AL29 -> 207388.6 | AN29: =634820.562-AM29-AL29 -> 218755.86 | AO29: =L29-AN29-AM29-AL29 -> 266420.94 | AP29: 305465.91 | AQ29: =BT29-AP29 -> 372193.5 | AR29: =999056.02+81079.093-AQ29-AP29 -> 402475.7 | AS29: =M29-AR29-AQ29-AP29 -> 403179.79 | AT29: 383759.86 | AU29: =BU29-AT29 -> 380629.49 | AV29: =1119184.417+28238.115-AU29-AT29 -> 383033.18 | AW29: =N29-AV29-AU29-AT29 -> 372425.09 | AX29: =358719.206+6483.274 -> 365202.48 | AY29: =BV29-AX29 -> 360952.21 | AZ29: =1047503.515+24280.81-AY29-AX29 -> 345629.64 | BA29: =O29-AZ29-AY29-AX29 -> 350919.77 | BB29: =351193.012+10724.148 -> 361917.16 | BC29: =BW29-BB29 -> 374252.51 | BD29: =1090336.069+25066.904-BC29-BB29 -> 379233.31 | BE29: =P29-BD29-BC29-BB29 -> 391837.43 | BF29: =398147.131+2757.304 -> 400904.43 | BH29: 248488.89 | BI29: =BY29-BH29 -> 254822.05 | BJ29: =763849.417-BI29-BH29 -> 260538.48 | BK29: =I29-Z29-AB29-AA29 -> 587532.84 | BL29: 266179.13 | BN29: 257099.68 | BO29: 283218.64 | BP29: 289715.31 | BQ29: 545413.39 | BR29: 541218.55 | BS29: 416064.7 | BT29: =625516.904+52142.513 -> 677659.42 | BU29: =741043.845+23345.502 -> 764389.35 | BV29: =709611.982+16542.708 -> 726154.69 | BW29: =716256.99+19912.678 -> 736169.67 | BY29: 503310.94 | BZ29: 545413.39 | CC29: 109942.16 | CD29: 230671.86 | CE29: 358562.77
B30: Interest and indexation expense. | C30: -129938.79 | D30: -133370.24 | E30: -152144.76 | F30: -131370.91 | G30: -131789.24 | H30: -123592.69 | I30: -159244.9 | J30: -183119.74 | K30: -138045.5 | L30: -115989.49 | M30: -381166.57 | N30: =-448056.203-27366.89 -> -475423.09 | O30: =-338960.1-25650.678 -> -364610.78 | P30: =-20885.941-252735.845 -> -273621.79 | R30: -35992.828 | S30: =BN30-R30 -> -39238.813 | T30: =-114157.895-S30-R30 -> -38926.254 | U30: =E30-T30-S30-R30 -> -37986.863 | V30: -38537.457 | W30: =BO30-V30 -> -34274.04 | X30: =-102584.355-W30-V30 -> -29772.858 | Y30: =F30-X30-W30-V30 -> -28786.551 | Z30: -29437.147 | AA30: =BP30-Z30 -> -29591.539 | AB30: =-91225.111-AA30-Z30 -> -32196.425 | AC30: =H30-AB30-AA30-Z30 -> -32367.575 | AD30: -41645.262 | AE30: =BQ30-AD30 -> -48806.062 | AF30: =-136139.206-AE30-AD30 -> -45687.882 | AG30: =J30-AF30-AE30-AD30 -> -46980.537 | AH30: -43648.425 | AI30: =BR30-AH30 -> -39080.329 | AJ30: =-110440.512-AI30-AH30 -> -27711.758 | AK30: =K30-AJ30-AI30-AH30 -> -27604.987 | AL30: -26209.041 | AM30: =BS30-AL30 -> -21899.59 | AN30: =-73211.454-AM30-AL30 -> -25102.823 | AO30: =L30-AN30-AM30-AL30 -> -42778.032 | AP30: -54524.866 | AQ30: =BT30-AP30 -> -90359.362 | AR30: =-203850.272-57800.755-AQ30-AP30 -> -116766.8 | AS30: =M30-AR30-AQ30-AP30 -> -119515.54 | AT30: -118450.79 | AU30: =BU30-AT30 -> -120324.5 | AV30: =-337323.213-17746.916-AU30-AT30 -> -116294.83 | AW30: =N30-AV30-AU30-AT30 -> -120352.96 | AX30: =-105697.939-4777.198 -> -110475.14 | AY30: =BV30-AX30 -> -97265.334 | AZ30: =-272322.142-17665.879-AY30-AX30 -> -82247.55 | BA30: =O30-AZ30-AY30-AX30 -> -74622.757 | BB30: =-61589.132-7410.802 -> -68999.934 | BC30: =BW30-BB30 -> -68739.387 | BD30: =-189705.754-16890.488-BC30-BB30 -> -68856.921 | BE30: =P30-BD30-BC30-BB30 -> -67025.544 | BF30: =-61842.026-1846.825 -> -63688.851 | BH30: -38033.156 | BI30: =BY30-BH30 -> -38365.003 | BJ30: =-117304.963-BI30-BH30 -> -40906.804 | BK30: =I30-Z30-AB30-AA30 -> -68019.786 | BL30: -41645.262 | BN30: -75231.641 | BO30: -72811.497 | BP30: -59028.686 | BQ30: -90451.324 | BR30: -82728.754 | BS30: -48108.631 | BT30: =-107344.703-37539.525 -> -144884.23 | BU30: =-222714.808-16060.487 -> -238775.29 | BV30: =-195383.341-12357.13 -> -207740.47 | BW30: =-124380.291-13359.03 -> -137739.32 | BY30: -76398.159 | BZ30: -90451.324 | CC30: -26594.406 | CD30: -59257.418 | CE30: -96289.736
B31: Net interest and indexation income | C31: =C29+C30 -> 315666.92 | D31: =D29+D30 -> 351949.21 | E31: =E29+E30 -> 374519.73 | F31: =F29+F30 -> 425571.63 | G31: =G29+G30 -> 448714.27 | H31: =H29+H30 -> 475375.44 | I31: =I29+I30 -> 871179.34 | J31: =J29+J30 -> 925626.22 | ... P31: =P29+P30 -> 1233618.6 | R31: =R29+R30 -> 89546.331 | S31: =S29+S30 -> 92321.713 | T31: =T29+T30 -> 94534.699 | U31: =U29+U30 -> 98116.99 | V31: =V29+V30 -> 99960.428 | W31: =W29+W30 -> 110446.71 | X31: =X29+X30 -> 106443.35 | Y31: =Y29+Y30 -> 108721.14 | ... BF31: =BF29+BF30 -> 337215.58 | BH31: =BH29+BH30 -> 210455.73 | BI31: =BI29+BI30 -> 216457.05 | BJ31: =BJ29+BJ30 -> 219631.67 | BK31: =BK29+BK30 -> 519513.05 | BL31: =BL29+BL30 -> 224533.87 | BN31: =BN29+BN30 -> 181868.04 | BO31: =BO29+BO30 -> 210407.14 | BP31: =BP29+BP30 -> 230686.62 | BQ31: =BQ29+BQ30 -> 454962.07 | BR31: =BR29+BR30 -> 458489.79 | BS31: =BS29+BS30 -> 367956.07 | BT31: =BT29+BT30 -> 532775.19 | BU31: =BU29+BU30 -> 525614.05 | ... BW31: =BW29+BW30 -> 598430.35 | BY31: =BY29+BY30 -> 426912.78 | BZ31: =BZ29+BZ30 -> 454962.07 | CC31: =CC29+CC30 -> 83347.751 | CD31: 171414.44 | CE31: 262273.03
B32: Commission income | C32: 106875.47 | D32: 135915.71 | E32: 163483.78 | F32: 168429.49 | G32: 144686.06 | H32: 151585.28 | I32: 222880.45 | J32: 245043.8 | K32: 206908.36 | L32: 231937.09 | M32: 320766.14 | N32: =348379.315 -> 348379.32 | O32: 382301.65 | P32: 454764.15 | R32: 38535.59 | S32: =BN32-R32 -> 39517.887 | T32: =119569.97-S32-R32 -> 41516.493 | U32: =E32-T32-S32-R32 -> 43913.812 | V32: 41599.49 | W32: =BO32-V32 -> 42259.575 | X32: =125549.462-W32-V32 -> 41690.397 | Y32: =F32-X32-W32-V32 -> 42880.028 | Z32: 35276.679 | AA32: =BP32-Z32 -> 36532.645 | AB32: =110971.977-AA32-Z32 -> 39162.653 | AC32: =H32-AB32-AA32-Z32 -> 40613.299 | AD32: 58843.567 | AE32: =BQ32-AD32 -> 59772.075 | AF32: =180549.699-AE32-AD32 -> 61934.057 | AG32: =J32-AF32-AE32-AD32 -> 64494.1 | AH32: 64062.721 | AI32: =BR32-AH32 -> 44187.028 | AJ32: =155852.771-AI32-AH32 -> 47603.022 | AK32: =K32-AJ32-AI32-AH32 -> 51055.584 | AL32: 51602.325 | AM32: =BS32-AL32 -> 49079.947 | AN32: =160892.025-AM32-AL32 -> 60209.753 | AO32: =L32-AN32-AM32-AL32 -> 71045.061 | AP32: 79105.146 | AQ32: =BT32-AP32 -> 78788.126 | AR32: =236279.208-AQ32-AP32 -> 78385.936 | AS32: =M32-AR32-AQ32-AP32 -> 84486.935 | AT32: 86629.691 | AU32: =BU32-AT32 -> 82615.464 | AV32: =262008.23-AU32-AT32 -> 92763.075 | AW32: =N32-AV32-AU32-AT32 -> 86371.085 | AX32: 92675.791 | AY32: =BV32-AX32 -> 93479.841 | AZ32: =281107.347-AY32-AX32 -> 94951.715 | BA32: =O32-AZ32-AY32-AX32 -> 101194.3 | BB32: 105917.9 | BC32: =BW32-BB32 -> 109541.64 | BD32: =329730.835-BC32-BB32 -> 114271.29 | BE32: =P32-BD32-BC32-BB32 -> 125033.32 | BF32: 168025.38 | BH32: 52257.528 | BI32: =BY32-BH32 -> 54405.129 | BJ32: =163658.025-BI32-BH32 -> 56995.368 | BK32: =I32-Z32-AB32-AA32 -> 111908.47 | BL32: 58843.567 | BN32: 78053.477 | BO32: 83859.065 | BP32: 71809.324 | BQ32: 118615.64 | BR32: 108249.75 | BS32: 100682.27 | BT32: 157893.27 | BU32: 169245.15 | BV32: 186155.63 | BW32: 215459.54 | BY32: 106662.66 | BZ32: 118615.64 | CC32: 29504.036 | CD32: 59034.835 | CE32: 94436.261
B33: Commission expense | C33: -29218.656 | D33: -33607.581 | E33: -40135.723 | F33: -42394.224 | G33: -40914.588 | H33: -46909.811 | I33: -117165.21 | J33: -116057.42 | K33: -86761.814 | L33: -88385.525 | M33: -132047.61 | N33: =-102362.057 -> -102362.06 | O33: -129378.53 | P33: -158985.5 | R33: -8911.877 | S33: =BN33-R33 -> -10127.991 | T33: =-28960.018-S33-R33 -> -9920.15 | U33: =E33-T33-S33-R33 -> -11175.705 | V33: -9574.697 | W33: =BO33-V33 -> -10231.821 | X33: =-30689.635-W33-V33 -> -10883.117 | Y33: =F33-X33-W33-V33 -> -11704.589 | Z33: -10621.517 | AA33: =BP33-Z33 -> -11799.311 | AB33: =-34442.139-AA33-Z33 -> -12021.311 | AC33: =H33-AB33-AA33-Z33 -> -12467.672 | AD33: -28654.613 | AE33: =BQ33-AD33 -> -29033.033 | AF33: =-85214.41-AE33-AD33 -> -27526.764 | AG33: =J33-AF33-AE33-AD33 -> -30843.011 | AH33: -28426.914 | AI33: =BR33-AH33 -> -18950.94 | AJ33: =-65069.443-AI33-AH33 -> -17691.589 | AK33: =K33-AJ33-AI33-AH33 -> -21692.371 | AL33: -18941.513 | AM33: =BS33-AL33 -> -18344.135 | AN33: =-60800.287-AM33-AL33 -> -23514.639 | AO33: =L33-AN33-AM33-AL33 -> -27585.238 | AP33: -27733.485 | AQ33: =BT33-AP33 -> -35335.785 | AR33: =-94678.036-AQ33-AP33 -> -31608.766 | AS33: =M33-AR33-AQ33-AP33 -> -37369.578 | AT33: -22959.826 | AU33: =BU33-AT33 -> -25622.216 | AV33: =-69406.125-AU33-AT33 -> -20824.083 | AW33: =N33-AV33-AU33-AT33 -> -32955.932 | AX33: -31024.919 | AY33: =BV33-AX33 -> -31938.397 | AZ33: =-92550.189-AY33-AX33 -> -29586.873 | BA33: =O33-AZ33-AY33-AX33 -> -36828.343 | BB33: -33351.858 | BC33: =BW33-BB33 -> -38622.078 | BD33: =-111531.895-BC33-BB33 -> -39557.959 | BE33: =P33-BD33-BC33-BB33 -> -47453.608 | BF33: -69336.678 | BH33: -28038.482 | BI33: =BY33-BH33 -> -29920.772 | BJ33: =-86921.328-BI33-BH33 -> -28962.074 | BK33: =I33-Z33-AB33-AA33 -> -82723.068 | BL33: -28654.613 | BN33: -19039.868 | BO33: -19806.518 | BP33: -22420.828 | BQ33: -57687.646 | BR33: -47377.854 | BS33: -37285.648 | BT33: -63069.27 | BU33: -48582.042 | BV33: -62963.316 | BW33: -71973.936 | BY33: -57959.254 | BZ33: -57687.646 | CC33: -7788.427 | CD33: -15607.507 | CE33: -24151.703
B34: Net commission income | C34: =C32+C33 -> 77656.818 | D34: =D32+D33 -> 102308.13 | E34: =E32+E33 -> 123348.06 | F34: =F32+F33 -> 126035.27 | G34: =G32+G33 -> 103771.47 | H34: =H32+H33 -> 104675.47 | I34: =I32+I33 -> 105715.24 | J34: =J32+J33 -> 128986.38 | ... P34: =P32+P33 -> 295778.65 | R34: =R32+R33 -> 29623.713 | S34: =S32+S33 -> 29389.896 | T34: =T32+T33 -> 31596.343 | U34: =U32+U33 -> 32738.107 | V34: =V32+V33 -> 32024.793 | W34: =W32+W33 -> 32027.754 | X34: =X32+X33 -> 30807.28 | Y34: =Y32+Y33 -> 31175.439 | ... BF34: =BF32+BF33 -> 98688.697 | BH34: =BH32+BH33 -> 24219.046 | BI34: =BI32+BI33 -> 24484.357 | BJ34: =BJ32+BJ33 -> 28033.294 | BK34: =BK32+BK33 -> 29185.401 | BL34: =BL32+BL33 -> 30188.954 | BN34: =BN32+BN33 -> 59013.609 | BO34: =BO32+BO33 -> 64052.547 | BP34: =BP32+BP33 -> 49388.496 | BQ34: =BQ32+BQ33 -> 60927.996 | BR34: =BR32+BR33 -> 60871.895 | BS34: =BS32+BS33 -> 63396.624 | BT34: =BT32+BT33 -> 94824.002 | BU34: =BU32+BU33 -> 120663.11 | ... BW34: =BW32+BW33 -> 143485.6 | BY34: =BY32+BY33 -> 48703.403 | BZ34: =BZ32+BZ33 -> 60927.996 | CC34: =CC32+CC33 -> 21715.609 | CD34: 43427.328 | CE34: 70284.558
B35: Net income (loss) on financial transactions | C35: -1118.943 | D35: 2341.646 | E35: 17811.714 | F35: 6562.337 | G35: 5013.585 | H35: 20658.479 | I35: 20883.343 | J35: 17187.95 | K35: 26894.489 | L35: 22555.337 | M35: 30629.556 | N35: =41804.83 -> 41804.83 | O35: 54446.125 | P35: 25039.395 | R35: 6021.91 | S35: =BN35-R35 -> 2617.94 | T35: =11652.355-S35-R35 -> 3012.505 | U35: =E35-T35-S35-R35 -> 6159.359 | V35: 4296.759 | W35: =BO35-V35 -> 2686.591 | X35: =8929.982-W35-V35 -> 1946.632 | Y35: =F35-X35-W35-V35 -> -2367.645 | Z35: 5546.555 | AA35: =BP35-Z35 -> 7303.236 | AB35: =14298.612-AA35-Z35 -> 1448.821 | AC35: =H35-AB35-AA35-Z35 -> 6359.867 | AD35: 3698.05 | AE35: =BQ35-AD35 -> 7159.53 | AF35: =15822.252-AE35-AD35 -> 4964.672 | AG35: =J35-AF35-AE35-AD35 -> 1365.698 | AH35: 13408.596 | AI35: =BR35-AH35 -> 6591.714 | AJ35: =25920.888-AI35-AH35 -> 5920.578 | AK35: =K35-AJ35-AI35-AH35 -> 973.601 | AL35: 10009.511 | AM35: =BS35-AL35 -> 4009.919 | AN35: =15618.634-AM35-AL35 -> 1599.204 | AO35: =L35-AN35-AM35-AL35 -> 6936.703 | AP35: -9603.66 | AQ35: =BT35-AP35 -> 28511.429 | AR35: =33166.304-AQ35-AP35 -> 14258.535 | AS35: =M35-AR35-AQ35-AP35 -> -2536.748 | AT35: -8674.342 | AU35: =BU35-AT35 -> 1972.219 | AV35: =22731.424-AU35-AT35 -> 29433.547 | AW35: =N35-AV35-AU35-AT35 -> 19073.406 | AX35: 17189.688 | AY35: =BV35-AX35 -> 10349.004 | AZ35: =38233.284-AY35-AX35 -> 10694.592 | BA35: =O35-AZ35-AY35-AX35 -> 16212.841 | BB35: 9188.611 | BC35: =BW35-BB35 -> 3084.196 | BD35: =29291.921-BC35-BB35 -> 17019.114 | BE35: =P35-BD35-BC35-BB35 -> -4252.526 | BF35: 9624.05 | BH35: 5546.555 | BI35: =BY35-BH35 -> 7371.723 | BJ35: =14495.739-BI35-BH35 -> 1577.461 | BK35: =I35-Z35-AB35-AA35 -> 6584.731 | BL35: 3698.05 | BN35: 8639.85 | BO35: 6983.35 | BP35: 12849.791 | BQ35: 10857.58 | BR35: 20000.31 | BS35: 14019.43 | BT35: 18907.769 | BU35: -6702.123 | BV35: 27538.692 | BW35: 12272.807 | BY35: 12918.278 | BZ35: 10857.58 | CC35: 1289.56 | CD35: 546.766 | CE35: -1267.961
B36: Net income (loss) on currency exchange | C36: 10760.905 | D36: 8854.487 | E36: -5777.584 | F36: 5549.303 | G36: 5549.303 | H36: -8982.788 | I36: -8667.556 | J36: 4289.403 | K36: -3198.974 | L36: -8379.431 | M36: -22050.715 | N36: =-1097.673 -> -1097.673 | O36: 6850.842 | P36: 15727.808 | R36: -2696.743 | S36: =BN36-R36 -> 1123.335 | T36: =-2088.395-S36-R36 -> -514.987 | U36: =E36-T36-S36-R36 -> -3689.189 | V36: -158.082 | W36: =BO36-V36 -> 78.063 | X36: =199.907-W36-V36 -> 279.926 | Y36: =F36-X36-W36-V36 -> 5349.396 | Z36: -3224.654 | AA36: =BP36-Z36 -> -4789.709 | AB36: =-5964.282-AA36-Z36 -> 2050.081 | AC36: =H36-AB36-AA36-Z36 -> -3018.506 | AD36: 793.506 | AE36: =BQ36-AD36 -> 538.648 | AF36: =-133.397-AE36-AD36 -> -1465.551 | AG36: =J36-AF36-AE36-AD36 -> 4422.8 | AH36: -10592.732 | AI36: =BR36-AH36 -> 2910.554 | AJ36: =-6943.082-AI36-AH36 -> 739.096 | AK36: =K36-AJ36-AI36-AH36 -> 3744.108 | AL36: -3061.392 | AM36: =BS36-AL36 -> -983.435 | AN36: =-4732.17-AM36-AL36 -> -687.343 | AO36: =L36-AN36-AM36-AL36 -> -3647.261 | AP36: 12199.547 | AQ36: =BT36-AP36 -> -29086.052 | AR36: =-28093.323-AQ36-AP36 -> -11206.818 | AS36: =M36-AR36-AQ36-AP36 -> 6042.608 | AT36: 11218.594 | AU36: =BU36-AT36 -> 4778.768 | AV36: =-1173.512-AU36-AT36 -> -17170.874 | AW36: =N36-AV36-AU36-AT36 -> 75.839 | AX36: 2935.271 | AY36: =BV36-AX36 -> -607.479 | AZ36: =11230.372-AY36-AX36 -> 8902.58 | BA36: =O36-AZ36-AY36-AX36 -> -4379.53 | BB36: 4685.951 | BC36: =BW36-BB36 -> 3257.521 | BD36: =2124.971 -BC36-BB36 -> -5818.501 | BE36: =P36-BD36-BC36-BB36 -> 13602.837 | BF36: -717.439 | BH36: -3247.33 | BI36: =BY36-BH36 -> -4733.249 | BJ36: =-6044.816-BI36-BH36 -> 1935.763 | BK36: =I36-Z36-AB36-AA36 -> -2703.274 | BL36: 793.506 | BN36: -1573.408 | BO36: -80.019 | BP36: -8014.363 | BQ36: 1332.154 | BR36: -7682.178 | BS36: -4044.827 | BT36: -16886.505 | BU36: 15997.362 | BV36: 2327.792 | BW36: 7943.472 | BY36: -7980.579 | BZ36: 1332.154 | CC36: 2287.591 | CD36: 4888.707 | CE36: 9751.101
B37: Other operating income (expenses) | C37: 827.146 | D37: 2147.794 | E37: -69.539 | F37: -1278.595 | G37: 1377.03 | H37: 2128.723 | I37: 7139.46 | J37: 3402.024 | K37: 2125.477 | L37: 3320.434 | M37: 17219.311 | N37: =22017.939 -> 22017.939 | O37: 26509.757 | P37: 11324.466 | R37: 72.427 | S37: =BN37-R37 -> 178.833 | T37: =-116.098-S37-R37 -> -367.358 | U37: =E37-T37-S37-R37 -> 46.559 | V37: -329.383 | W37: =BO37-V37 -> -145.967 | X37: =-495.601-W37-V37 -> -20.251 | Y37: =F37-X37-W37-V37 -> -782.994 | Z37: 464.659 | AA37: =BP37-Z37 -> 339.022 | AB37: =1450.885-AA37-Z37 -> 647.204 | AC37: =H37-AB37-AA37-Z37 -> 677.838 | AD37: 302.835 | AE37: =BQ37-AD37 -> 1032.999 | AF37: =2383.321-AE37-AD37 -> 1047.487 | AG37: =J37-AF37-AE37-AD37 -> 1018.703 | AH37: 297.166 | AI37: =BR37-AH37 -> 668.773 | AJ37: =1130.286-AI37-AH37 -> 164.347 | AK37: =K37-AJ37-AI37-AH37 -> 995.191 | AL37: 852.088 | AM37: =BS37-AL37 -> 1461.99 | AN37: =2781.522-AM37-AL37 -> 467.444 | AO37: =L37-AN37-AM37-AL37 -> 538.912 | AP37: 2825.333 | AQ37: =BT37-AP37 -> 3357.532 | AR37: =7175.948-AQ37-AP37 -> 993.083 | AS37: =M37-AR37-AQ37-AP37 -> 10043.363 | AT37: 2422.16 | AU37: =BU37-AT37 -> 5259.712 | AV37: =13285.522-AU37-AT37 -> 5603.65 | AW37: =N37-AV37-AU37-AT37 -> 8732.417 | AX37: 12696.023 | AY37: =BV37-AX37 -> 3200.778 | AZ37: =17410.46-AY37-AX37 -> 1513.659 | BA37: =O37-AZ37-AY37-AX37 -> 9099.297 | BB37: 2772.93 | BC37: =BW37-BB37 -> 3476.33 | BD37: =7930.177 -BC37-BB37 -> 1680.917 | BE37: =P37-BD37-BC37-BB37 -> 3394.289 | BF37: 5150.868 | BH37: 942.56 | BI37: =BY37-BH37 -> 1336.017 | BJ37: =4339.327-BI37-BH37 -> 2060.75 | BK37: =I37-Z37-AB37-AA37 -> 5688.575 | BL37: 302.835 | BN37: 251.26 | BO37: -475.35 | BP37: 803.681 | BQ37: 1335.834 | BR37: 965.939 | BS37: 2314.078 | BT37: 6182.865 | BU37: 7681.872 | BV37: 15896.801 | BW37: 6249.26 | BY37: 2278.577 | BZ37: 1335.834 | CC37: 166.479 | CD37: 916.22 | CE37: 956.979
B38: Credit risk provisions | C38: -89422.063 | D38: -114698 | E38: -146481.24 | F38: -179240.27 | G38: -178991.29 | H38: -177873.73 | I38: -291664.73 | J38: -337736.21 | K38: -384783.08 | L38: -130842.04 | M38: -563865.75 | N38: -685758.08 | O38: -448921.5 | P38: -423940.95 | R38: -32512.801 | S38: =BN38-R38 -> -38674.37 | T38: =-103973.812-S38-R38 -> -32786.641 | U38: =E38-T38-S38-R38 -> -42507.43 | V38: -42867.99 | W38: =BO38-V38 -> -50811.616 | X38: =-135250.515-W38-V38 -> -41570.909 | Y38: =F38-X38-W38-V38 -> -43989.757 | Z38: -38784.348 | AA38: =BP38-Z38 -> -40608.225 | AB38: =-133657.173-AA38-Z38 -> -54264.6 | AC38: =H38-AB38-AA38-Z38 -> -44216.561 | AD38: -76382.532 | AE38: =BQ38-AD38 -> -69490.916 | AF38: =-227270.017-AE38-AD38 -> -81396.569 | AG38: =J38-AF38-AE38-AD38 -> -110466.2 | AH38: -106753.41 | AI38: =BR38-AH38 -> -156264.19 | AJ38: =-353437.894-AI38-AH38 -> -90420.294 | AK38: =K38-AJ38-AI38-AH38 -> -31345.186 | AL38: -12166.688 | AM38: =BS38-AL38 -> -30510.797 | AN38: =-75033.997-AM38-AL38 -> -32356.512 | AO38: =L38-AN38-AM38-AL38 -> -55808.042 | AP38: -89008.413 | AQ38: =BT38-AP38 -> -127954.03 | AR38: =-363446.066-AQ38-AP38 -> -146483.62 | AS38: =M38-AR38-AQ38-AP38 -> -200419.68 | AT38: -188311.88 | AU38: =BU38-AT38 -> -184769.27 | AV38: =-523201.631-AU38-AT38 -> -150120.48 | AW38: =N38-AV38-AU38-AT38 -> -162556.45 | AX38: -128754.13 | AY38: =BV38-AX38 -> -124600.24 | AZ38: =-348633.656-AY38-AX38 -> -95279.294 | BA38: =O38-AZ38-AY38-AX38 -> -100287.85 | BB38: -85492.186 | BC38: =BW38-BB38 -> -97083.653 | BD38: =-290005.138-BC38-BB38 -> -107429.3 | BE38: =P38-BD38-BC38-BB38 -> -133935.81 | BF38: -98444.679 | BH38: -60377.683 | BI38: =BY38-BH38 -> -68712.962 | BJ38: =-214147.917-BI38-BH38 -> -85057.272 | BK38: =I38-Z38-AB38-AA38 -> -158007.55 | BL38: -76382.532 | BN38: -71187.171 | BO38: -93679.606 | BP38: -79392.573 | BQ38: -145873.45 | BR38: -263017.6 | BS38: -42677.485 | BT38: -216962.44 | BU38: -373081.15 | BV38: -253354.36 | BW38: -182575.84 | BY38: -129090.65 | BZ38: -145873.45 | CC38: -23438.166 | CD38: -51251.266 | CE38: -80966.414
B39: Total net operating revenue | C39: =C31+C34+SUM(C35:C38) -> 314370.79 | D39: =D31+D34+SUM(D35:D38) -> 352903.27 | E39: =E31+E34+SUM(E35:E38) -> 363351.14 | F39: =F31+F34+SUM(F35:F38) -> 383199.67 | G39: =G31+G34+SUM(G35:G38) -> 385434.37 | H39: =H31+H34+SUM(H35:H38) -> 415981.58 | I39: =I31+I34+SUM(I35:I38) -> 704585.1 | J39: =J31+J34+SUM(J35:J38) -> 741755.76 | ... P39: =P31+P34+SUM(P35:P38) -> 1157548 | R39: =R31+R34+SUM(R35:R38) -> 90054.837 | S39: =S31+S34+SUM(S35:S38) -> 86957.347 | T39: =T31+T34+SUM(T35:T38) -> 95474.561 | U39: =U31+U34+SUM(U35:U38) -> 90864.396 | V39: =V31+V34+SUM(V35:V38) -> 92926.525 | W39: =W31+W34+SUM(W35:W38) -> 94281.538 | X39: =X31+X34+SUM(X35:X38) -> 97886.027 | Y39: =Y31+Y34+SUM(Y35:Y38) -> 98105.581 | ... BF39: =BF31+BF34+SUM(BF35:BF38) -> 351517.08 | BH39: =BH31+BH34+SUM(BH35:BH38) -> 177538.88 | BI39: =BI31+BI34+SUM(BI35:BI38) -> 176202.94 | BJ39: =BJ31+BJ34+SUM(BJ35:BJ38) -> 168181.67 | BK39: =BK31+BK34+SUM(BK35:BK38) -> 400260.93 | BL39: =BL31+BL34+SUM(BL35:BL38) -> 183134.68 | BN39: =BN31+BN34+SUM(BN35:BN38) -> 177012.18 | BO39: =BO31+BO34+SUM(BO35:BO38) -> 187208.06 | BP39: =BP31+BP34+SUM(BP35:BP38) -> 206321.65 | BQ39: =BQ31+BQ34+SUM(BQ35:BQ38) -> 383542.18 | BR39: =BR31+BR34+SUM(BR35:BR38) -> 269628.16 | BS39: =BS31+BS34+SUM(BS35:BS38) -> 400963.89 | BT39: =BT31+BT34+SUM(BT35:BT38) -> 418840.88 | BU39: =BU31+BU34+SUM(BU35:BU38) -> 290173.13 | ... BW39: =BW31+BW34+SUM(BW35:BW38) -> 585805.65 | BY39: =BY31+BY34+SUM(BY35:BY38) -> 353741.81 | BZ39: =BZ31+BZ34+SUM(BZ35:BZ38) -> 383542.18 | CC39: =CC31+CC34+SUM(CC35:CC38) -> 85368.824 | CD39: 169942.2 | CE39: 261031.3
B40: Remuneration and personnel costs | C40: -83551.772 | D40: -90919.63 | E40: -96051.131 | F40: -100447.18 | G40: -100447.18 | H40: -110207.18 | I40: -142834.52 | J40: -149509.71 | K40: -139733.43 | L40: -132165.95 | M40: -143950.62 | N40: -152907.77 | O40: -163384.11 | P40: -174065.14 | R40: -23376.559 | S40: =BN40-R40 -> -23574.508 | T40: =-71784.982-S40-R40 -> -24833.915 | U40: =E40-T40-S40-R40 -> -24266.149 | V40: -25215.548 | W40: =BO40-V40 -> -24916.999 | X40: =-75547.709-W40-V40 -> -25415.162 | Y40: =F40-X40-W40-V40 -> -24899.466 | Z40: -26171.479 | AA40: =BP40-Z40 -> -26387.088 | AB40: =-80980.304-AA40-Z40 -> -28421.737 | AC40: =H40-AB40-AA40-Z40 -> -29226.872 | AD40: -36352.669 | AE40: =BQ40-AD40 -> -35422.811 | AF40: =-110110.72-AE40-AD40 -> -38335.24 | AG40: =J40-AF40-AE40-AD40 -> -39398.99 | AH40: -40737.072 | AI40: =BR40-AH40 -> -32596.63 | AJ40: =-104478.31-AI40-AH40 -> -31144.608 | AK40: =K40-AJ40-AI40-AH40 -> -35255.124 | AL40: -33791.594 | AM40: =BS40-AL40 -> -29930.595 | AN40: =-96168.362-AM40-AL40 -> -32446.173 | AO40: =L40-AN40-AM40-AL40 -> -35997.586 | AP40: -35602.4 | AQ40: =BT40-AP40 -> -36092.123 | AR40: =-110570.141-AQ40-AP40 -> -38875.618 | AS40: =M40-AR40-AQ40-AP40 -> -33380.481 | AT40: -37203.207 | AU40: =BU40-AT40 -> -38398.942 | AV40: =-113117.447-AU40-AT40 -> -37515.298 | AW40: =N40-AV40-AU40-AT40 -> -39790.322 | AX40: -38782.184 | AY40: =BV40-AX40 -> -39071.2 | AZ40: =-119878.256-AY40-AX40 -> -42024.872 | BA40: =O40-AZ40-AY40-AX40 -> -43505.851 | BB40: -39946.26 | BC40: =BW40-BB40 -> -41804.851 | BD40: =-126701.57-BC40-BB40 -> -44950.459 | BE40: =P40-BD40-BC40-BB40 -> -47363.569 | BF40: -44090.776 | BH40: -34889.958 | BI40: =BY40-BH40 -> -35340.347 | BJ40: =-106844.561-BI40-BH40 -> -36614.256 | BK40: =I40-Z40-AB40-AA40 -> -61854.212 | BL40: -36352.669 | BN40: -46951.067 | BO40: -50132.547 | BP40: -52558.567 | BQ40: -71775.48 | BR40: -73333.702 | BS40: -63722.189 | BT40: -71694.523 | BU40: -75602.149 | BV40: -77853.384 | BW40: -81751.111 | BY40: -70230.305 | BZ40: -71775.48 | CC40: -22479.386 | CD40: -43711.89 | CE40: -67145.132
B41: Administrative expenses | C41: -101215.79 | D41: -112366.2 | E41: -125483.99 | F41: -140106.67 | G41: -138010.61 | H41: -154941.6 | I41: -177860.67 | J41: -197819.95 | K41: -206582.61 | L41: -281848.45 | M41: -387437.7 | N41: -405226.49 | O41: -441720.72 | P41: -492031.64 | R41: -29980.278 | S41: =BN41-R41 -> -31361.378 | T41: =-93771.526-S41-R41 -> -32429.87 | U41: =E41-T41-S41-R41 -> -31712.459 | V41: -33447.033 | W41: =BO41-V41 -> -35036.407 | X41: =-103642.155-W41-V41 -> -35158.715 | Y41: =F41-X41-W41-V41 -> -36464.519 | Z41: -36888.668 | AA41: =BP41-Z41 -> -38781.349 | AB41: =-114502.621-AA41-Z41 -> -38832.604 | AC41: =H41-AB41-AA41-Z41 -> -40438.979 | AD41: -43428.451 | AE41: =BQ41-AD41 -> -51472.467 | AF41: =-145550.287-AE41-AD41 -> -50649.369 | AG41: =J41-AF41-AE41-AD41 -> -52269.659 | AH41: -51772.186 | AI41: =BR41-AH41 -> -44262.876 | AJ41: =-145655.218-AI41-AH41 -> -49620.156 | AK41: =K41-AJ41-AI41-AH41 -> -60927.389 | AL41: -56811.942 | AM41: =BS41-AL41 -> -64795.191 | AN41: =-198251.678-AM41-AL41 -> -76644.545 | AO41: =L41-AN41-AM41-AL41 -> -83596.769 | AP41: -83697.561 | AQ41: =BT41-AP41 -> -101499.39 | AR41: =-282108.315-AQ41-AP41 -> -96911.363 | AS41: =M41-AR41-AQ41-AP41 -> -105329.38 | AT41: -92429.861 | AU41: =BU41-AT41 -> -97635.176 | AV41: =-298303.269-AU41-AT41 -> -108238.23 | AW41: =N41-AV41-AU41-AT41 -> -106923.22 | AX41: -100257.19 | AY41: =BV41-AX41 -> -104224.57 | AZ41: =-313579.351-AY41-AX41 -> -109097.59 | BA41: =O41-AZ41-AY41-AX41 -> -128141.37 | BB41: -108089.94 | BC41: =BW41-BB41 -> -109057.08 | BD41: =-341103.012-BC41-BB41 -> -123955.99 | BE41: =P41-BD41-BC41-BB41 -> -150928.63 | BF41: -105139.74 | BH41: -41755.593 | BI41: =BY41-BH41 -> -44478.646 | BJ41: =-130874.488-BI41-BH41 -> -44640.249 | BK41: =I41-Z41-AB41-AA41 -> -63358.049 | BL41: -43428.451 | BN41: -61341.656 | BO41: -68483.44 | BP41: -75670.017 | BQ41: -94900.918 | BR41: -96035.062 | BS41: -121607.13 | BT41: -185196.95 | BU41: -190065.04 | BV41: -204481.77 | BW41: -217147.02 | BY41: -86234.239 | BZ41: -94900.918 | CC41: -26351.184 | CD41: -53544.057 | CE41: -83492.247
B42: Depreciation and amortization | C42: -15489.687 | D42: -15638.353 | E42: -16810.784 | F42: -19762.997 | G42: -19762.997 | H42: -21175.299 | I42: -21175.299 | J42: -34996.501 | K42: -37506.177 | L42: -39291.807 | M42: -42622.992 | N42: -40364.506 | O42: -39942.417 | P42: -38973.918 | R42: -4025.764 | S42: =BN42-R42 -> -4104.233 | T42: =-12426.733-S42-R42 -> -4296.736 | U42: =E42-T42-S42-R42 -> -4384.051 | V42: -4544.656 | W42: =BO42-V42 -> -5082.463 | X42: =-14646.574-W42-V42 -> -5019.455 | Y42: =F42-X42-W42-V42 -> -5116.423 | Z42: -5420.483 | AA42: =BP42-Z42 -> -3881.321 | AB42: =-15415.148-AA42-Z42 -> -6113.344 | AC42: =H42-AB42-AA42-Z42 -> -5760.151 | AD42: -8842.624 | AE42: =BQ42-AD42 -> -7115.821 | AF42: =-25046.097-AE42-AD42 -> -9087.652 | AG42: =J42-AF42-AE42-AD42 -> -9950.404 | AH42: -9963.737 | AI42: =BR42-AH42 -> -9918.458 | AJ42: =-29325.724-AI42-AH42 -> -9443.529 | AK42: =K42-AJ42-AI42-AH42 -> -8180.453 | AL42: -9394.3 | AM42: =BS42-AL42 -> -9402.665 | AN42: =-28364.714-AM42-AL42 -> -9567.749 | AO42: =L42-AN42-AM42-AL42 -> -10927.093 | AP42: -10636.787 | AQ42: =BT42-AP42 -> -10991.736 | AR42: =-32887.432-AQ42-AP42 -> -11258.909 | AS42: =M42-AR42-AQ42-AP42 -> -9735.56 | AT42: -9573.119 | AU42: =BU42-AT42 -> -9855.329 | AV42: =-30167.327-AU42-AT42 -> -10738.879 | AW42: =N42-AV42-AU42-AT42 -> -10197.179 | AX42: -10113.516 | AY42: =BV42-AX42 -> -9504.073 | AZ42: =-28670.043-AY42-AX42 -> -9052.454 | BA42: =O42-AZ42-AY42-AX42 -> -11272.374 | BB42: -8673.006 | BC42: =BW42-BB42 -> -9110.653 | BD42: =-27436.996-BC42-BB42 -> -9653.337 | BE42: =P42-BD42-BC42-BB42 -> -11536.922 | BF42: -10525.775 | BH42: -5420.483 | BI42: =BY42-BH42 -> -3881.321 | BJ42: =-15415.148-BI42-BH42 -> -6113.344 | BK42: =I42-Z42-AB42-AA42 -> -5760.151 | BL42: -8842.624 | BN42: -8129.997 | BO42: -9627.119 | BP42: -9301.804 | BQ42: -15958.445 | BR42: -19882.195 | BS42: -18796.965 | BT42: -21628.523 | BU42: -19428.448 | BV42: -19617.589 | BW42: -17783.659 | BY42: -9301.804 | BZ42: -15958.445 | CC42: -3800.039 | CD42: -7570.785 | CE42: -11336.748
B43: Other operating expenses | C43: -10502.339 | D43: -10548.992 | E43: -11740.051 | F43: -13043.717 | G43: -17374.48 | H43: -20509.182 | I43: -46024.862 | J43: -44322.854 | K43: -49636.946 | L43: -50571.387 | M43: -37351.344 | N43: -46701.967 | O43: -43905.909 | P43: -49427.624 | R43: -2371.372 | S43: =BN43-R43 -> -2589.147 | T43: =-8475.944-S43-R43 -> -3515.425 | U43: =E43-T43-S43-R43 -> -3264.107 | V43: -2843.041 | W43: =BO43-V43 -> -3283.34 | X43: =-9178.291-W43-V43 -> -3051.91 | Y43: =F43-X43-W43-V43 -> -3865.426 | Z43: -4681.995 | AA43: =BP43-Z43 -> -4997.806 | AB43: =-14804.562-AA43-Z43 -> -5124.761 | AC43: =H43-AB43-AA43-Z43 -> -5704.62 | AD43: -11127.227 | AE43: =BQ43-AD43 -> -10413.67 | AF43: =-33927.514-AE43-AD43 -> -12386.617 | AG43: =J43-AF43-AE43-AD43 -> -10395.34 | AH43: -11809.669 | AI43: =BR43-AH43 -> -7913.559 | AJ43: =-33200.258-AI43-AH43 -> -13477.03 | AK43: =K43-AJ43-AI43-AH43 -> -16436.688 | AL43: -12549.788 | AM43: =BS43-AL43 -> -13029.874 | AN43: =-36964.557-AM43-AL43 -> -11384.895 | AO43: =L43-AN43-AM43-AL43 -> -13606.83 | AP43: -11793.877 | AQ43: =BT43-AP43 -> -3094.98 | AR43: =-23370.477-AQ43-AP43 -> -8481.62 | AS43: =M43-AR43-AQ43-AP43 -> -13980.867 | AT43: -7264.223 | AU43: =BU43-AT43 -> -6821.021 | AV43: =-23043.531-AU43-AT43 -> -8958.287 | AW43: =N43-AV43-AU43-AT43 -> -23658.436 | AX43: -13675.971 | AY43: =BV43-AX43 -> -3355.423 | AZ43: =-29932.642-AY43-AX43 -> -12901.248 | BA43: =O43-AZ43-AY43-AX43 -> -13973.267 | BB43: -13933.774 | BC43: =BW43-BB43 -> -12680.1 | BD43: =-37478.296-BC43-BB43 -> -10864.422 | BE43: =P43-BD43-BC43-BB43 -> -11949.328 | BF43: -14697.494 | BH43: -10467.004 | BI43: =BY43-BH43 -> -11592.282 | BJ43: =-33802.578-BI43-BH43 -> -11743.292 | BK43: =I43-Z43-AB43-AA43 -> -31220.3 | BL43: -11127.227 | BN43: -4960.519 | BO43: -6126.381 | BP43: -9679.801 | BQ43: -21540.897 | BR43: -19723.228 | BS43: -25579.662 | BT43: -14888.857 | BU43: -14085.244 | BV43: -17031.394 | BW43: -26613.874 | BY43: -22059.286 | BZ43: -21540.897 | CC43: -2582.257 | CD43: -4968.022 | CE43: -7408.946
B44: Total Operating expenses | C44: =SUM(C40:C43) -> -210759.59 | D44: =SUM(D40:D43) -> -229473.18 | E44: =SUM(E40:E43) -> -250085.95 | F44: =SUM(F40:F43) -> -273360.56 | G44: =SUM(G40:G43) -> -275595.26 | H44: =SUM(H40:H43) -> -306833.26 | I44: =SUM(I40:I43) -> -387895.35 | J44: =SUM(J40:J43) -> -426649.01 | ... P44: =SUM(P40:P43) -> -754498.32 | R44: =SUM(R40:R43) -> -59753.973 | S44: =SUM(S40:S43) -> -61629.266 | T44: =SUM(T40:T43) -> -65075.946 | U44: =SUM(U40:U43) -> -63626.766 | V44: =SUM(V40:V43) -> -66050.278 | W44: =SUM(W40:W43) -> -68319.209 | X44: =SUM(X40:X43) -> -68645.242 | Y44: =SUM(Y40:Y43) -> -70345.834 | ... BF44: =SUM(BF40:BF43) -> -174453.79 | BH44: =SUM(BH40:BH43) -> -92533.038 | BI44: =SUM(BI40:BI43) -> -95292.596 | BJ44: =SUM(BJ40:BJ43) -> -99111.141 | BK44: =SUM(BK40:BK43) -> -162192.71 | BL44: =SUM(BL40:BL43) -> -99750.971 | BN44: =SUM(BN40:BN43) -> -121383.24 | BO44: =SUM(BO40:BO43) -> -134369.49 | BP44: =SUM(BP40:BP43) -> -147210.19 | BQ44: =SUM(BQ40:BQ43) -> -204175.74 | BR44: =SUM(BR40:BR43) -> -208974.19 | BS44: =SUM(BS40:BS43) -> -229705.95 | BT44: =SUM(BT40:BT43) -> -293408.85 | BU44: =SUM(BU40:BU43) -> -299180.88 | ... BW44: =SUM(BW40:BW43) -> -343295.66 | BY44: =SUM(BY40:BY43) -> -187825.63 | BZ44: =SUM(BZ40:BZ43) -> -204175.74 | CC44: =SUM(CC40:CC43) -> -55212.866 | CD44: -109794.75 | CE44: -169383.07
B45: Net operating income | C45: =C39+C44 -> 103611.19 | D45: =D39+D44 -> 123430.09 | E45: =E39+E44 -> 113265.19 | F45: =F39+F44 -> 109839.11 | G45: =G39+G44 -> 109839.11 | H45: =H39+H44 -> 109148.32 | I45: =I39+I44 -> 316689.76 | J45: =J39+J44 -> 315106.75 | ... P45: =P39+P44 -> 403049.66 | R45: =R39+R44 -> 30300.864 | S45: =S39+S44 -> 25328.081 | T45: =T39+T44 -> 30398.615 | U45: =U39+U44 -> 27237.63 | V45: =V39+V44 -> 26876.247 | W45: =W39+W44 -> 25962.329 | X45: =X39+X44 -> 29240.785 | Y45: =Y39+Y44 -> 27759.747 | ... BF45: =BF39+BF44 -> 177063.3 | BH45: =BH39+BH44 -> 85005.84 | BI45: =BI39+BI44 -> 80910.34 | BJ45: =BJ39+BJ44 -> 69070.529 | BK45: =BK39+BK44 -> 238068.22 | BL45: =BL39+BL44 -> 83383.713 | BN45: =BN39+BN44 -> 55628.945 | BO45: =BO39+BO44 -> 52838.576 | BP45: =BP39+BP44 -> 59111.464 | BQ45: =BQ39+BQ44 -> 179366.44 | BR45: =BR39+BR44 -> 60653.971 | BS45: =BS39+BS44 -> 171257.94 | BT45: =BT39+BT44 -> 125432.02 | BU45: =BU39+BU44 -> -9007.749 | ... BW45: =BW39+BW44 -> 242509.99 | BY45: =BY39+BY44 -> 165916.18 | BZ45: =BZ39+BZ44 -> 179366.44 | CC45: =CC39+CC44 -> 30155.958 | CD45: 60147.445 | CE45: 91648.225
B46: Income from investments in companies | C46: 358.358 | D46: 531.214 | E46: 508.395 | F46: 469.655 | G46: 469.655 | H46: 551.214 | I46: 551.214 | J46: 834.977 | K46: 708.89 | L46: 531.673 | M46: 1085.254 | N46: =886.961 -> 886.961 | O46: 890.322 | P46: 1056.927 | R46: 115.348 | S46: =BN46-R46 -> 264.523 | T46: =444.807-S46-R46 -> 64.936 | U46: =E46-T46-S46-R46 -> 63.588 | V46: 63.506 | W46: =BO46-V46 -> 293.462 | X46: =426.119-W46-V46 -> 69.151 | Y46: =F46-X46-W46-V46 -> 43.536 | Z46: 80.886 | AA46: =BP46-Z46 -> 257.363 | AB46: =453.266-AA46-Z46 -> 115.017 | AC46: =H46-AB46-AA46-Z46 -> 97.948 | AD46: 108.358 | AE46: =BQ46-AD46 -> 322.276 | AF46: =696.269-AE46-AD46 -> 265.635 | AG46: =J46-AF46-AE46-AD46 -> 138.708 | AH46: 162.631 | AI46: =BR46-AH46 -> 69.931 | AJ46: =615.337-AI46-AH46 -> 382.775 | AK46: =K46-AJ46-AI46-AH46 -> 93.553 | AL46: 100.282 | AM46: =BS46-AL46 -> 116.133 | AN46: =352.384-AM46-AL46 -> 135.969 | AO46: =L46-AN46-AM46-AL46 -> 179.289 | AP46: 149.268 | AQ46: =BT46-AP46 -> 406.439 | AR46: =806.292-AQ46-AP46 -> 250.585 | AS46: =M46-AR46-AQ46-AP46 -> 278.962 | AT46: 217.751 | AU46: =BU46-AT46 -> 203.963 | AV46: =641.643-AU46-AT46 -> 219.929 | AW46: =N46-AV46-AU46-AT46 -> 245.318 | AX46: 171.756 | AY46: =BV46-AX46 -> 235.721 | AZ46: =644.744-AY46-AX46 -> 237.267 | BA46: =O46-AZ46-AY46-AX46 -> 245.578 | BB46: 240.191 | BC46: =BW46-BB46 -> 292.478 | BD46: =836.148 -BC46-BB46 -> 303.479 | BE46: =P46-BD46-BC46-BB46 -> 220.779 | BF46: 243.441 | BH46: 80.886 | BI46: =BY46-BH46 -> 257.363 | BJ46: =453.266-BI46-BH46 -> 115.017 | BK46: =I46-Z46-AB46-AA46 -> 97.948 | BL46: 108.358 | BN46: 379.871 | BO46: 356.968 | BP46: 338.249 | BQ46: 430.634 | BR46: 232.562 | BS46: 216.415 | BT46: 555.707 | BU46: 421.714 | BV46: 407.477 | BW46: 532.669 | BY46: 338.249 | BZ46: 430.634 | CC46: 102.899 | CD46: 339.975 | CE46: 444.216
B47: Net income before tax | C47: =C45+C46 -> 103969.55 | D47: =D45+D46 -> 123961.3 | E47: =E45+E46 -> 113773.59 | F47: =F45+F46 -> 110308.76 | G47: =G45+G46 -> 110308.76 | H47: =H45+H46 -> 109699.54 | I47: =I45+I46 -> 317240.97 | J47: =J45+J46 -> 315941.73 | ... P47: =P45+P46 -> 404106.59 | R47: =R45+R46 -> 30416.212 | S47: =S45+S46 -> 25592.604 | T47: =T45+T46 -> 30463.551 | U47: =U45+U46 -> 27301.218 | V47: =V45+V46 -> 26939.753 | W47: =W45+W46 -> 26255.791 | X47: =X45+X46 -> 29309.936 | Y47: =Y45+Y46 -> 27803.283 | ... BF47: =BF45+BF46 -> 177306.74 | BH47: =BH45+BH46 -> 85086.726 | BI47: =BI45+BI46 -> 81167.703 | BJ47: =BJ45+BJ46 -> 69185.546 | BK47: =BK45+BK46 -> 238166.17 | BL47: =BL45+BL46 -> 83492.071 | BN47: =BN45+BN46 -> 56008.816 | BO47: =BO45+BO46 -> 53195.544 | BP47: =BP45+BP46 -> 59449.713 | BQ47: =BQ45+BQ46 -> 179797.08 | BR47: =BR45+BR46 -> 60886.533 | BS47: =BS45+BS46 -> 171474.35 | BT47: =BT45+BT46 -> 125987.73 | BU47: =BU45+BU46 -> -8586.035 | ... BW47: =BW45+BW46 -> 243042.66 | BY47: =BY45+BY46 -> 166254.43 | BZ47: =BZ45+BZ46 -> 179797.08 | CC47: =CC45+CC46 -> 30258.857 | CD47: 60487.42 | CE47: 92092.441
B48: Income tax expense | C48: -25843.026 | D48: -33179.362 | E48: -30410.733 | F48: -31814.667 | G48: -31814.667 | H48: -31844.071 | I48: -83330.806 | J48: -82649.229 | K48: -39403.119 | L48: -71485.124 | M48: -1479.651 | N48: 17533.669 | O48: -56942.852 | P48: -101498.27 | R48: -8105.302 | S48: =BN48-R48 -> -6620.686 | T48: =-23091.697-S48-R48 -> -8365.709 | U48: =E48-T48-S48-R48 -> -7319.036 | V48: -7830.935 | W48: =BO48-V48 -> -7036.12 | X48: =-23707.965-W48-V48 -> -8840.91 | Y48: =F48-X48-W48-V48 -> -8106.702 | Z48: -8068.121 | AA48: =BP48-Z48 -> -8958.122 | AB48: =-22953.108-AA48-Z48 -> -5926.865 | AC48: =H48-AB48-AA48-Z48 -> -8890.963 | AD48: -23733.503 | AE48: =BQ48-AD48 -> -25784.688 | AF48: =-72156.783-AE48-AD48 -> -22638.592 | AG48: =J48-AF48-AE48-AD48 -> -10492.446 | AH48: -15287.081 | AI48: =BR48-AH48 -> 2630.854 | AJ48: =-22247.571-AI48-AH48 -> -9591.344 | AK48: =K48-AJ48-AI48-AH48 -> -17155.548 | AL48: -23191.688 | AM48: =BS48-AL48 -> -18810.197 | AN48: =-57527.287-AM48-AL48 -> -15525.402 | AO48: =L48-AN48-AM48-AL48 -> -13957.837 | AP48: -13632.186 | AQ48: =BT48-AP48 -> -775.348 | AR48: =-14979.545-AQ48-AP48 -> -572.011 | AS48: =M48-AR48-AQ48-AP48 -> 13499.894 | AT48: 5840.851 | AU48: =BU48-AT48 -> 10076.495 | AV48: =7265.783-AU48-AT48 -> -8651.563 | AW48: =N48-AV48-AU48-AT48 -> 10267.886 | AX48: -13664.267 | AY48: =BV48-AX48 -> -9996.206 | AZ48: =-43077.548-AY48-AX48 -> -19417.075 | BA48: =O48-AZ48-AY48-AX48 -> -13865.304 | BB48: -29421.836 | BC48: =BW48-BB48 -> -30683.776 | BD48: =-87101.085-BC48-BB48 -> -26995.473 | BE48: =P48-BD48-BC48-BB48 -> -14397.19 | BF48: -50550.192 | BH48: -22079.903 | BI48: =BY48-BH48 -> -21286.371 | BJ48: =-61709.168-BI48-BH48 -> -18342.894 | BK48: =I48-Z48-AB48-AA48 -> -60377.698 | BL48: -23733.503 | BN48: -14725.988 | BO48: -14867.055 | BP48: -17026.243 | BQ48: -49518.191 | BR48: -12656.227 | BS48: -42001.885 | BT48: -14407.534 | BU48: 15917.346 | BV48: -23660.473 | BW48: -60105.612 | BY48: -43366.274 | BZ48: -49518.191 | CC48: -9268.603 | CD48: -16345.888 | CE48: -24821.244
B49: Net income from banking businesses | C49: =C47+C48 -> 78126.524 | D49: =D47+D48 -> 90781.942 | E49: =E47+E48 -> 83362.852 | F49: =F47+F48 -> 78494.096 | G49: =G47+G48 -> 78494.096 | H49: =H47+H48 -> 77855.467 | I49: =I47+I48 -> 233910.16 | J49: =J47+J48 -> 233292.5 | ... P49: =P47+P48 -> 302608.31 | R49: =R47+R48 -> 22310.91 | S49: =S47+S48 -> 18971.918 | T49: =T47+T48 -> 22097.842 | U49: =U47+U48 -> 19982.182 | V49: =V47+V48 -> 19108.818 | W49: =W47+W48 -> 19219.671 | X49: =X47+X48 -> 20469.026 | Y49: =Y47+Y48 -> 19696.581 | ... BF49: =BF47+BF48 -> 126756.54 | BH49: =BH47+BH48 -> 63006.823 | BI49: =BI47+BI48 -> 59881.332 | BJ49: =BJ47+BJ48 -> 50842.652 | BK49: =BK47+BK48 -> 177788.47 | BL49: =BL47+BL48 -> 59758.568 | BN49: =BN47+BN48 -> 41282.828 | BO49: =BO47+BO48 -> 38328.489 | BP49: =BP47+BP48 -> 42423.47 | BQ49: =BQ47+BQ48 -> 130278.88 | BR49: =BR47+BR48 -> 48230.306 | BS49: =BS47+BS48 -> 129472.47 | BT49: =BT47+BT48 -> 111580.19 | BU49: =BU47+BU48 -> 7331.311 | ... BW49: =BW47+BW48 -> 182937.04 | BY49: =BY47+BY48 -> 122888.16 | BZ49: =BZ47+BZ48 -> 130278.88 | CC49: =CC47+CC48 -> 20990.254 | CD49: 44141.532 | CE49: 67271.197
B51: Consolidated Income statement | C51: 41975 | D51: 42341 | E51: 42708 | F51: 43073 | G51: =G3 -> 43073 | H51: =H3 -> 43438 | I51: =I3 -> 43438 | J51: =J3 -> 43803 | K51: =K3 -> 44169 | L51: =L3 -> 44534 | M51: =M3 -> 44899 | N51: =N3 -> 45264 | ... P51: =P3 -> 45995 | R51: 42437 | S51: 42527 | T51: 42622 | U51: 42714 | V51: 42801 | W51: 42892 | X51: 42987 | Y51: 43079 | Z51: =Z3 -> 43166 | AA51: =AA3 -> 43257 | AB51: =AB3 -> 43352 | AC51: =AC3 -> 43444 | AD51: =AD3 -> 43531 | AE51: =AE3 -> 43622 | AF51: =AF3 -> 43738 | AG51: =AG3 -> 43809 | ... BF51: =BF3 -> 46112 | BH51: =BH3 -> 43166 | BI51: =BI3 -> 43281 | BJ51: =BJ3 -> 43373 | BK51: =BK3 -> 43444 | BL51: =BL3 -> 43531 | BN51: 42530 | BO51: 42896 | BP51: =BP3 -> 43261 | BQ51: =BQ3 -> 43646 | BR51: =BR3 -> 44012 | BS51: =BS3 -> 44377 | BT51: =BT3 -> 44742 | BU51: =BU3 -> 45107 | BV51: =BV3 -> 45473 | BW51: =BW3 -> 45838 | BY51: =BY3 -> 43281 | BZ51: =BZ3 -> 43646
B52: Revenues of Non-Banking Operations | C52: =C8 -> 7038379.8 | D52: =D8 -> 7753209.6 | E52: =E8 -> 7898301.8 | F52: =F8 -> 8242645.3 | G52: =G8 -> 8209851.5 | H52: =H8 -> 8483577.3 | I52: =I8 -> 7976898.4 | J52: =J8 -> 8053582.8 | ... P52: =P8 -> 11342386 | R52: =R8 -> 1889596.2 | S52: =BN52-R52 -> 1948787.3 | T52: =T8 -> 1869557.7 | U52: =U8 -> 2190360.6 | V52: =V8 -> 1952033.1 | W52: =BO52-V52 -> 2015162.9 | X52: =X8 -> 1941993.6 | Y52: =Y8 -> 2333455.6 | Z52: =Z8 -> 2010257.7 | AA52: =BP52-Z52 -> 2106536.8 | AB52: =AB8 -> 2004610.8 | AC52: =AC8 -> 2362172.1 | AD52: =AD8 -> 1926900.5 | AE52: =BQ52-AD52 -> 1994081 | AF52: =AF8 -> 1881456.2 | AG52: =AG8 -> 2251145.1 | AH52: =AH8 -> 1887698.6 | AI52: =BR52-AH52 -> 1458364.1 | AJ52: =AJ8 -> 2217405.7 | AK52: =AK8 -> 2717581.6 | AL52: =AL8 -> 2218078.5 | AM52: =BS52-AL52 -> 2390588.7 | AN52: =AN8 -> 2620892.4 | AO52: =AO8 -> 3105824.1 | AP52: =AP8 -> 2546146.6 | AQ52: =BT52-AP52 -> 2619187.9 | AR52: =AR8 -> 2492158.7 | AS52: =AS8 -> 2803173.2 | AT52: =AT8 -> 2274726.3 | AU52: =BU52-AT52 -> 2219917.4 | AV52: =AV8 -> 2206436.6 | AW52: =AW8 -> 2654034.4 | AX52: =AX8 -> 2392525.6 | AY52: =BV52-AX52 -> 2445288.2 | AZ52: =AZ8 -> 2402953.9 | BA52: =BA8 -> 3081336.8 | BB52: =BB8 -> 2653179.2 | BC52: =BW52-BB52 -> 2693468.6 | BD52: =BD8 -> 2630300.1 | BE52: =BE8 -> 3365438 | BF52: =BF8 -> 2766025.9 | BH52: =BH8 -> 1887142.6 | BI52: =BI8 -> 1980615.5 | BJ52: =BJ8 -> 1878025.5 | BK52: =BK8 -> 1855493.2 | BL52: =BL8 -> 1926900.5 | BN52: =BN8 -> 3838383.5 | BO52: =BO8 -> 3967196 | BP52: =BP8 -> 4116794.5 | BQ52: =BQ8 -> 3920981.5 | BR52: =BR8 -> 3346062.7 | BS52: =BS8 -> 4608667.2 | BT52: =BT8 -> 5165334.5 | BU52: =BU8 -> 4494643.6 | ... BW52: =BW8 -> 5346647.9 | BY52: =BY8 -> 3867758.1 | BZ52: =BZ8 -> 3920981.5
B53: Revenues of Banking Operations | C53: =C29+C32+C37 -> 553308.34 | D53: =D29+D32+D37 -> 623382.96 | E53: =E29+E32+E37 -> 690078.73 | F53: =F29+F32+F37 -> 724093.43 | G53: =G29+G32+G37 -> 726566.6 | H53: =H29+H32+H37 -> 752682.12 | I53: =I29+I32+I37 -> 1260444.1 | J53: =J29+J32+J37 -> 1357191.8 | ... P53: =P29+P32+P37 -> 1973329 | R53: =R29+R32+R37 -> 164147.18 | S53: =BN53-R53 -> 171257.25 | T53: =T29+T32+T37 -> 174610.09 | U53: =U29+U32+U37 -> 180064.22 | V53: =V29+V32+V37 -> 179767.99 | W53: =BO53-V53 -> 186834.36 | X53: =X29+X32+X37 -> 177886.35 | Y53: =Y29+Y32+Y37 -> 179604.73 | Z53: =Z29+Z32+Z37 -> 178177.15 | AA53: =BP53-Z53 -> 184151.17 | AB53: =AB29+AB32+AB37 -> 192985.95 | AC53: =AC29+AC32+AC37 -> 197367.85 | AD53: =AD29+AD32+AD37 -> 325325.53 | AE53: =BQ53-AD53 -> 340039.33 | AF53: =AF29+AF32+AF37 -> 342464.72 | AG53: =AG29+AG32+AG37 -> 349362.21 | AH53: =AH29+AH32+AH37 -> 351009.82 | AI53: =BR53-AH53 -> 299424.42 | AJ53: =AJ29+AJ32+AJ37 -> 268573.57 | AK53: =AK29+AK32+AK37 -> 268742.68 | AL53: =AL29+AL32+AL37 -> 261130.52 | AM53: =BS53-AL53 -> 257930.53 | AN53: =AN29+AN32+AN37 -> 279433.06 | AO53: =AO29+AO32+AO37 -> 338004.91 | AP53: =AP29+AP32+AP37 -> 387396.39 | AQ53: =BT53-AP53 -> 454339.16 | AR53: =AR29+AR32+AR37 -> 481854.71 | AS53: =AS29+AS32+AS37 -> 497710.09 | AT53: =AT29+AT32+AT37 -> 472811.71 | AU53: =BU53-AT53 -> 468504.66 | AV53: =AV29+AV32+AV37 -> 481399.91 | AW53: =AW29+AW32+AW37 -> 467528.59 | AX53: =AX29+AX32+AX37 -> 470574.29 | AY53: =BV53-AX53 -> 457632.83 | AZ53: =AZ29+AZ32+AZ37 -> 442095.01 | BA53: =BA29+BA32+BA37 -> 461213.37 | BB53: =BB29+BB32+BB37 -> 470607.99 | BC53: =BW53-BB53 -> 487270.48 | BD53: =BD29+BD32+BD37 -> 495185.52 | BE53: =BE29+BE32+BE37 -> 520265.04 | BF53: =BF29+BF32+BF37 -> 574080.68 | BH53: =BH29+BH32+BH37 -> 301688.97 | BI53: =BI29+BI32+BI37 -> 310563.2 | BJ53: =BJ29+BJ32+BJ37 -> 319594.6 | BK53: =BK29+BK32+BK37 -> 705129.88 | BL53: =BL29+BL32+BL37 -> 325325.53 | BN53: =BN29+BN32+BN37 -> 335404.42 | BO53: =BO29+BO32+BO37 -> 366602.35 | BP53: =BP29+BP32+BP37 -> 362328.31 | BQ53: =BQ29+BQ32+BQ37 -> 665364.87 | BR53: =BR29+BR32+BR37 -> 650434.23 | BS53: =BS29+BS32+BS37 -> 519061.05 | BT53: =BT29+BT32+BT37 -> 841735.55 | BU53: =BU29+BU32+BU37 -> 941316.37 | ... BW53: =BW29+BW32+BW37 -> 957878.47 | BY53: =BY29+BY32+BY37 -> 612252.17 | BZ53: =BZ29+BZ32+BZ37 -> 665364.87
B54: Total Revenues | C54: =SUM(C52:C53) -> 7591688.1 | D54: =SUM(D52:D53) -> 8376592.5 | E54: =SUM(E52:E53) -> 8588380.5 | F54: =SUM(F52:F53) -> 8966738.7 | G54: =SUM(G52:G53) -> 8936418.1 | H54: =SUM(H52:H53) -> 9236259.5 | I54: =SUM(I52:I53) -> 9237342.6 | J54: =SUM(J52:J53) -> 9410774.6 | ... P54: =SUM(P52:P53) -> 13315715 | R54: =SUM(R52:R53) -> 2053743.4 | S54: =SUM(S52:S53) -> 2120044.5 | T54: =SUM(T52:T53) -> 2044167.8 | U54: =SUM(U52:U53) -> 2370424.8 | V54: =SUM(V52:V53) -> 2131801.1 | W54: =SUM(W52:W53) -> 2201997.3 | X54: =SUM(X52:X53) -> 2119880 | Y54: =SUM(Y52:Y53) -> 2513060.4 | ... BF54: =SUM(BF52:BF53) -> 3340106.6 | BH54: =SUM(BH52:BH53) -> 2188831.6 | BI54: =SUM(BI52:BI53) -> 2291178.7 | BJ54: =SUM(BJ52:BJ53) -> 2197620.1 | BK54: =SUM(BK52:BK53) -> 2560623 | BL54: =SUM(BL52:BL53) -> 2252226 | BN54: =SUM(BN52:BN53) -> 4173787.9 | BO54: =SUM(BO52:BO53) -> 4333798.4 | BP54: =SUM(BP52:BP53) -> 4479122.8 | BQ54: =SUM(BQ52:BQ53) -> 4586346.4 | BR54: =SUM(BR52:BR53) -> 3996496.9 | BS54: =SUM(BS52:BS53) -> 5127728.2 | BT54: =SUM(BT52:BT53) -> 6007070 | BU54: =SUM(BU52:BU53) -> 5435960 | ... BW54: =SUM(BW52:BW53) -> 6304526.3 | BY54: =SUM(BY52:BY53) -> 4480010.3 | BZ54: =SUM(BZ52:BZ53) -> 4586346.4
B55: COGS of Non-Banking Operations | C55: =C11 -> -4654988.9 | D55: =D11 -> -5098131.6 | E55: =E11 -> -5180719.9 | F55: =F11 -> -5360352 | G55: =G11 -> -5296643 | H55: =H11 -> -5508545.4 | I55: =I11 -> -5255756.4 | J55: =J11 -> -5433070.2 | ... P55: =P11 -> -7370628.6 | R55: =R11 -> -1266353.8 | S55: =BN55-R55 -> -1279016.6 | T55: =T11 -> -1234273.7 | U55: =U11 -> -1401075.8 | V55: =V11 -> -1281071.7 | W55: =BO55-V55 -> -1305217.1 | X55: =X11 -> -1281057.5 | Y55: =Y11 -> -1493005.7 | Z55: =Z11 -> -1308674.8 | AA55: =BP55-Z55 -> -1360544.2 | AB55: =AB11 -> -1317192.7 | AC55: =AC11 -> -1522133.7 | AD55: =AD11 -> -1323019.3 | AE55: =BQ55-AD55 -> -1330915.3 | AF55: =AF11 -> -1277205.3 | AG55: =AG11 -> -1501930.3 | AH55: =AH11 -> -1301030.6 | AI55: =BR55-AH55 -> -1063909.1 | AJ55: =AJ11 -> -1613411.1 | AK55: =AK11 -> -1812382.9 | AL55: =AL11 -> -1534201.3 | AM55: =BS55-AL55 -> -1653372.8 | AN55: =AN11 -> -1792610.9 | AO55: =AO11 -> -2067675.3 | AP55: =AP11 -> -1796600.8 | AQ55: =BT55-AP55 -> -1799463.2 | AR55: =AR11 -> -1736802.4 | AS55: =AS11 -> -1931856.9 | AT55: =AT11 -> -1614201.7 | AU55: =BU55-AT55 -> -1519467.2 | AV55: =AV11 -> -1522962.6 | AW55: =AW11 -> -1766935.6 | AX55: =AX11 -> -1617669.2 | AY55: =BV55-AX55 -> -1625083.1 | AZ55: =AZ11 -> -1593006.1 | BA55: =BA11 -> -2008986.7 | BB55: =BB11 -> -1737013 | BC55: =BW55-BB55 -> -1749365.6 | BD55: =BD11 -> -1722329.4 | BE55: =BE11 -> -2161920.6 | BF55: =BF11 -> -1802151.5 | BH55: =BH11 -> -1253403.4 | BI55: =BI11 -> -1297192.1 | BJ55: =BJ11 -> -1252290.2 | BK55: =BK11 -> -1269344.7 | BL55: =BL11 -> -1323019.3 | BN55: =BN11 -> -2545370.4 | BO55: =BO11 -> -2586288.9 | BP55: =BP11 -> -2669219 | BQ55: =BQ11 -> -2653934.6 | BR55: =BR11 -> -2364939.7 | BS55: =BS11 -> -3187574.1 | BT55: =BT11 -> -3596064 | BU55: =BU11 -> -3133669 | ... BW55: =BW11 -> -3486378.6 | BY55: =BY11 -> -2550595.5 | BZ55: =BZ11 -> -2653934.6
B56: COGS of Banking Operations | C56: =C30+C33+C35+C38+C36 -> -238937.55 | D56: =D30+D33+D35+D38+D36 -> -270479.69 | E56: =E30+E33+E35+E38+E36 -> -326727.59 | F56: =F30+F33+F35+F38+F36 -> -340893.76 | G56: =G30+G33+G35+G38+G36 -> -341132.24 | H56: =H30+H33+H35+H38+H36 -> -336700.54 | I56: =I30+I33+I35+I38+I36 -> -555859.04 | J56: =J30+J33+J35+J38+J36 -> -615436.02 | ... P56: =P30+P33+P35+P38+P36 -> -815781.04 | R56: =R30+R33+R35+R38+R36 -> -74092.339 | S56: =BN56-R56 -> -84299.899 | T56: =T30+T33+T35+T38+T36 -> -79135.527 | U56: =U30+U33+U35+U38+U36 -> -89199.828 | V56: =V30+V33+V35+V38+V36 -> -86841.467 | W56: =BO56-V56 -> -92552.823 | X56: =X30+X33+X35+X38+X36 -> -80000.326 | Y56: =Y30+Y33+Y35+Y38+Y36 -> -81499.146 | Z56: =Z30+Z33+Z35+Z38+Z36 -> -76521.111 | AA56: =BP56-Z56 -> -79485.548 | AB56: =AB30+AB33+AB35+AB38+AB36 -> -94983.434 | AC56: =AC30+AC33+AC35+AC38+AC36 -> -85710.447 | AD56: =AD30+AD33+AD35+AD38+AD36 -> -142190.85 | AE56: =BQ56-AD56 -> -139631.83 | AF56: =AF30+AF33+AF35+AF38+AF36 -> -151112.09 | AG56: =AG30+AG33+AG35+AG38+AG36 -> -182501.25 | AH56: =AH30+AH33+AH35+AH38+AH36 -> -176012.88 | AI56: =BR56-AH56 -> -204793.19 | AJ56: =AJ30+AJ33+AJ35+AJ38+AJ36 -> -129163.97 | AK56: =AK30+AK33+AK35+AK38+AK36 -> -75924.835 | AL56: =AL30+AL33+AL35+AL38+AL36 -> -50369.123 | AM56: =BS56-AL56 -> -67728.038 | AN56: =AN30+AN33+AN35+AN38+AN36 -> -80062.113 | AO56: =AO30+AO33+AO35+AO38+AO36 -> -122881.87 | AP56: =AP30+AP33+AP35+AP38+AP36 -> -168670.88 | AQ56: =BT56-AP56 -> -254223.8 | AR56: =AR30+AR33+AR35+AR38+AR36 -> -291807.47 | AS56: =AS30+AS33+AS35+AS38+AS36 -> -353798.94 | AT56: =AT30+AT33+AT35+AT38+AT36 -> -327178.24 | AU56: =BU56-AT56 -> -323965 | AV56: =AV30+AV33+AV35+AV38+AV36 -> -274976.73 | AW56: =AW30+AW33+AW35+AW38+AW36 -> -296716.1 | AX56: =AX30+AX33+AX35+AX38+AX36 -> -250129.22 | AY56: =BV56-AX56 -> -244062.44 | AZ56: =AZ30+AZ33+AZ35+AZ38+AZ36 -> -187516.55 | BA56: =BA30+BA33+BA35+BA38+BA36 -> -199905.63 | BB56: =BB30+BB33+BB35+BB38+BB36 -> -173969.42 | BC56: =BW56-BB56 -> -198103.4 | BD56: =BD30+BD33+BD35+BD38+BD36 -> -204643.57 | BE56: =BE30+BE33+BE35+BE38+BE36 -> -239064.65 | BF56: =BF30+BF33+BF35+BF38+BF36 -> -222563.6 | BH56: =BH30+BH33+BH35+BH38+BH36 -> -124150.1 | BI56: =BI30+BI33+BI35+BI38+BI36 -> -134360.26 | BJ56: =BJ30+BJ33+BJ35+BJ38+BJ36 -> -151412.93 | BK56: =BK30+BK33+BK35+BK38+BK36 -> -304868.95 | BL56: =BL30+BL33+BL35+BL38+BL36 -> -142190.85 | BN56: =BN30+BN33+BN35+BN38+BN36 -> -158392.24 | BO56: =BO30+BO33+BO35+BO38+BO36 -> -179394.29 | BP56: =BP30+BP33+BP35+BP38+BP36 -> -156006.66 | BQ56: =BQ30+BQ33+BQ35+BQ38+BQ36 -> -281822.68 | BR56: =BR30+BR33+BR35+BR38+BR36 -> -380806.08 | BS56: =BS30+BS33+BS35+BS38+BS36 -> -118097.16 | BT56: =BT30+BT33+BT35+BT38+BT36 -> -422894.68 | BU56: =BU30+BU33+BU35+BU38+BU36 -> -651143.25 | ... BW56: =BW30+BW33+BW35+BW38+BW36 -> -372072.82 | BY56: =BY30+BY33+BY35+BY38+BY36 -> -258510.36 | BZ56: =BZ30+BZ33+BZ35+BZ38+BZ36 -> -281822.68
B57: Gross Profit | C57: =C54+C55+C56 -> 2697761.6 | D57: =D54+D55+D56 -> 3007981.2 | E57: =E54+E55+E56 -> 3080933 | F57: =F54+F55+F56 -> 3265492.9 | G57: =G54+G55+G56 -> 3298642.9 | H57: =H54+H55+H56 -> 3391013.5 | I57: =I54+I55+I56 -> 3425727.2 | J57: =J54+J55+J56 -> 3362268.4 | ... P57: =P54+P55+P56 -> 5129305.3 | R57: =R54+R55+R56 -> 713297.27 | S57: =S54+S55+S56 -> 756727.97 | T57: =T54+T55+T56 -> 730758.61 | U57: =U54+U55+U56 -> 880149.13 | V57: =V54+V55+V56 -> 763887.9 | W57: =W54+W55+W56 -> 804227.34 | X57: =X54+X55+X56 -> 758822.17 | Y57: =Y54+Y55+Y56 -> 938555.49 | ... BF57: =BF54+BF55+BF56 -> 1315391.6 | BH57: =BH54+BH55+BH56 -> 811278.17 | BI57: =BI54+BI55+BI56 -> 859626.25 | BJ57: =BJ54+BJ55+BJ56 -> 793916.88 | BK57: =BK54+BK55+BK56 -> 986409.37 | BL57: =BL54+BL55+BL56 -> 787015.93 | BN57: =BN54+BN55+BN56 -> 1470025.2 | BO57: =BO54+BO55+BO56 -> 1568115.2 | BP57: =BP54+BP55+BP56 -> 1653897.2 | BQ57: =BQ54+BQ55+BQ56 -> 1650589.1 | BR57: =BR54+BR55+BR56 -> 1250751.1 | BS57: =BS54+BS55+BS56 -> 1822057 | BT57: =BT54+BT55+BT56 -> 1988111.3 | BU57: =BU54+BU55+BU56 -> 1651147.8 | ... BW57: =BW54+BW55+BW56 -> 2446074.9 | BY57: =BY54+BY55+BY56 -> 1670904.4 | BZ57: =BZ54+BZ55+BZ56 -> 1650589.1
B58: SG&A Expenses | C58: =C14+C15+C17+C40+C41+C42+C43 -> -1887396.8 | D58: =D14+D15+D17+D40+D41+D42+D43 -> -2137894.6 | E58: =E14+E15+E17+E40+E41+E42+E43 -> -2191641.9 | F58: =F14+F15+F17+F40+F41+F42+F43 -> -2338303.3 | G58: =G14+G15+G17+G40+G41+G42+G43 -> -2369053.6 | H58: =H14+H15+H17+H40+H41+H42+H43 -> -2511998.7 | I58: =I14+I15+I17+I40+I41+I42+I43 -> -2546809.2 | J58: =J14+J15+J17+J40+J41+J42+J43 -> -2656793.9 | ... M58: =M14+M15+M17+M40+M41+M42+M43 -> -3513430.6 | N58: =N14+N15+N17+N40+N41-N42+N43 -> -3235038.7 | O58: =O14+O15+O17+O40+O41-O42+O43 -> -3362016 | P58: =P14+P15+P17+P40+P41-P42+P43 -> -3564842.7 | R58: =R14+R15+R17+R40+R41+R42+R43 -> -521634.73 | S58: =BN58-R58 -> -542132.6 | T58: =T14+T15+T17+T40+T41+T42+T43 -> -544387.95 | U58: =U14+U15+U17+U40+U41+U42+U43 -> -583486.6 | V58: =V14+V15+V17+V40+V41+V42+V43 -> -547864.52 | W58: =BO58-V58 -> -580351.1 | X58: =X14+X15+X17+X40+X41+X42+X43 -> -582659.44 | Y58: =Y14+Y15+Y17+Y40+Y41+Y42+Y43 -> -627428.23 | Z58: =Z14+Z15+Z17+Z40+Z41+Z42+Z43 -> -584245.68 | AA58: =BP58-Z58 -> -621577.52 | AB58: =AB14+AB15+AB17+AB40+AB41+AB42+AB43 -> -617707.75 | AC58: =AC14+AC15+AC17+AC40+AC41+AC42+AC43 -> -688467.77 | AD58: =AD14+AD15+AD17+AD40+AD41+AD42+AD43 -> -616399.01 | AE58: =BQ58-AD58 -> -654084.59 | AF58: =AF14+AF15+AF17+AF40+AF41+AF42+AF43 -> -647311.78 | AG58: =AG14+AG15+AG17+AG40+AG41+AG42+AG43 -> -738998.54 | AH58: =AH14+AH15+AH17+AH40+AH41+AH42+AH43 -> -666303 | AI58: =BR58-AH58 -> -630994.76 | AJ58: =AJ14+AJ15+AJ17+AJ40+AJ41+AJ42+AJ43 -> -678490.87 | AK58: =AK14+AK15+AK17+AK40+AK41+AK42+AK43 -> -749928.79 | AL58: =AL14+AL15+AL17+AL40+AL41+AL42+AL43 -> -652513.2 | AM58: =BS58-AL58 -> -681177.74 | AN58: =AN14+AN15+AN17+AN40+AN41+AN42+AN43 -> -755951.03 | AO58: =AO14+AO15+AO17+AO40+AO41+AO42+AO43 -> -896587.19 | AP58: =AP14+AP15+AP17+AP40+AP41+AP42+AP43 -> -796630.72 | AQ58: =BT58-AP58 -> -870652.79 | AR58: =AR14+AR15+AR17+AR40+AR41+AR42+AR43 -> -878446.31 | AS58: =AS14+AS15+AS17+AS40+AS41+AS42+AS43 -> -967700.82 | AT58: =AT14+AT15+AT17+AT40+AT41+AT42+AT43 -> -803572.47 | AU58: =BU58-AT58 -> -801965.58 | AV58: =AV14+AV15+AV17+AV40+AV41+AV42+AV43 -> -825020.36 | AW58: =AW14+AW15+AW17+AW40+AW41+AW42+AW43 -> -885209.32 | AX58: =AX14+AX15+AX17+AX40+AX41-AX42+AX43 -> -794970.86 | AY58: =AY14+AY15+AY17+AY40+AY41-AY42+AY43 -> -804736.95 | AZ58: =AZ14+AZ15+AZ17+AZ40+AZ41-AZ42+AZ43 -> -829611.64 | BA58: =BA14+BA15+BA17+BA40+BA41-BA42+BA43 -> -932696.51 | BB58: =BB14+BB15+BB17+BB40+BB41-BB42+BB43 -> -834787.34 | BC58: =BC14+BC15+BC17+BC40+BC41-BC42+BC43 -> -853714.81 | BD58: =BD14+BD15+BD17+BD40+BD41-BD42+BD43 -> -878988.38 | BE58: =BE14+BE15+BE17+BE40+BE41-BE42+BE43 -> -997352.17 | BF58: =BF14+BF15+BF17+BF40+BF41-BF42+BF43 -> -867644.25 | BH58: =BH14+BH15+BH17+BH40+BH41+BH42+BH43 -> -592322.88 | BI58: =BI14+BI15+BI17+BI40+BI41+BI42+BI43 -> -630677.75 | BJ58: =BJ14+BJ15+BJ17+BJ40+BJ41+BJ42+BJ43 -> -626539.43 | BK58: =BK14+BK15+BK17+BK40+BK41+BK42+BK43 -> -723278.21 | BL58: =BL14+BL15+BL17+BL40+BL41+BL42+BL43 -> -616399.01 | BN58: =BN14+BN15+BN17+BN40+BN41+BN42+BN43 -> -1063767.3 | BO58: =BO14+BO15+BO17+BO40+BO41+BO42+BO43 -> -1128215.6 | BP58: =BP14+BP15+BP17+BP40+BP41+BP42+BP43 -> -1205823.2 | BQ58: =BQ14+BQ15+BQ17+BQ40+BQ41+BQ42+BQ43 -> -1270483.6 | BR58: =BR14+BR15+BR17+BR40+BR41+BR42+BR43 -> -1297297.8 | BS58: =BS14+BS15+BS17+BS40+BS41+BS42+BS43 -> -1333690.9 | BT58: =BT14+BT15+BT17+BT40+BT41+BT42+BT43 -> -1667283.5 | BU58: =BU14+BU15+BU17+BU40+BU41+BU42+BU43 -> -1605538 | ... BW58: =BW14+BW15+BW17+BW40+BW41+BW42+BW43 -> -1724069.5 | BY58: =BY14+BY15+BY17+BY40+BY41+BY42+BY43 -> -1223000.6 | BZ58: =BZ14+BZ15+BZ17+BZ40+BZ41+BZ42+BZ43 -> -1270483.6
B59: Operational Income | C59: =C57+C58 -> 810364.89 | D59: =D57+D58 -> 870086.65 | E59: =E57+E58 -> 889291.09 | F59: =F57+F58 -> 927189.6 | G59: =G57+G58 -> 929589.27 | H59: =H57+H58 -> 879014.82 | I59: =I57+I58 -> 878917.99 | J59: =J57+J58 -> 705474.44 | ... P59: =P57+P58 -> 1564462.6 | R59: =R57+R58 -> 191662.54 | S59: =S57+S58 -> 214595.36 | T59: =T57+T58 -> 186370.66 | U59: =U57+U58 -> 296662.53 | V59: =V57+V58 -> 216023.38 | W59: =W57+W58 -> 223876.24 | X59: =X57+X58 -> 176162.73 | Y59: =Y57+Y58 -> 311127.26 | ... BF59: =BF57+BF58 -> 447747.32 | BH59: =BH57+BH58 -> 218955.29 | BI59: =BI57+BI58 -> 228948.5 | BJ59: =BJ57+BJ58 -> 167377.45 | BK59: =BK57+BK58 -> 263131.16 | BL59: =BL57+BL58 -> 170616.93 | BN59: =BN57+BN58 -> 406257.9 | BO59: =BO57+BO58 -> 439899.62 | BP59: =BP57+BP58 -> 448073.97 | BQ59: =BQ57+BQ58 -> 380105.49 | BR59: =BR57+BR58 -> -46546.628 | BS59: =BS57+BS58 -> 488366.05 | BT59: =BT57+BT58 -> 320827.81 | BU59: =BU57+BU58 -> 45609.761 | ... BW59: =BW57+BW58 -> 722005.43 | BY59: =BY57+BY58 -> 447903.79 | BZ59: =BZ57+BZ58 -> 380105.49
B60: Depreciation + Amortization | C60: =-C42+C104 -> 204442.69 | D60: =-D42+D104 -> 243797.35 | E60: =-E42+E104 -> 262189.78 | F60: =-F42+F104 -> 286771 | G60: =-G42+G104 -> 286771 | H60: =-H42+H104 -> 325331 | I60: =-I42+I104 -> 325331 | J60: =-J42+J104 -> 435861 | ... P60: =-P42+P104 -> 497412.92 | R60: =-R42+R104 -> 62543.8 | S60: =BN60-R60 -> 65219.079 | T60: =-T42+T104 -> 66030.92 | U60: =-U42+U104 -> 68395.985 | V60: =-V42+V104 -> 68770.032 | W60: =BO60-V60 -> 70716.638 | X60: =-X42+X104 -> 72071.98 | Y60: =-Y42+Y104 -> 75212.35 | Z60: =-Z42+Z104 -> 76709.131 | AA60: =BP60-Z60 -> 77138.855 | AB60: =-AB42+AB104 -> 82668.989 | AC60: =-AC42+AC104 -> 88814.025 | AD60: =-AD42+AD104 -> 108622 | AE60: =BQ60-AD60 -> 106409 | AF60: =-AF42+AF104 -> 109994 | AG60: =-AG42+AG104 -> 110836 | AH60: =-AH42+AH104 -> 116136 | AI60: =BR60-AH60 -> 116315 | AJ60: =-AJ42+AJ104 -> 114369 | AK60: =-AK42+AK104 -> 115181 | AL60: =-AL42+AL104 -> 110117 | AM60: =BS60-AL60 -> 112753 | AN60: =-AN42+AN104 -> 118242 | AO60: =-AO42+AO104 -> 126371 | AP60: =-AP42+AP104 -> 120513 | AQ60: =BT60-AP60 -> 95398 | AR60: =-AR42+AR104 -> 123114.91 | AS60: =-AS42+AS104 -> 166081.09 | AT60: =-AT42+AT104 -> 124391 | AU60: =BU60-AT60 -> 97691 | AV60: =-AV42+AV104 -> 126891.88 | AW60: =-AW42+AW104 -> 148985.63 | AX60: =-AX42+AX104 -> 126960.52 | AY60: =BV60-AX60 -> 104712.48 | AZ60: =-AZ42+AZ104 -> 122271.45 | BA60: =-BA42+BA104 -> 152197.96 | BB60: =-BB42+BB104 -> 119114.01 | BC60: =BW60-BB60 -> 102740.99 | BD60: =-BD42+BD104 -> 123319.34 | BE60: =-BE42+BE104 -> 152238.58 | BF60: =-BF42+BF104 -> -104034.23 | BH60: =-BH42+BH104 -> 77075 | BI60: =-BI42+BI104 -> 76711 | BJ60: =-BJ42+BJ104 -> 82731 | BK60: =-BK42+BK104 -> 88814.025 | BL60: =-BL42+BL104 -> 108622 | BN60: =-BN42+BN104 -> 127762.88 | BO60: =-BO42+BO104 -> 139486.67 | BP60: =-BP42+BP104 -> 153847.99 | BQ60: =-BQ42+BQ104 -> 215031 | BR60: =-BR42+BR104 -> 232451 | BS60: =-BS42+BS104 -> 222870 | BT60: =-BT42+BT104 -> 215911 | BU60: =-BU42+BU104 -> 222082 | ... BW60: =-BW42+BW104 -> 221855 | BY60: =-BY42+BY104 -> 153786 | BZ60: =-BZ42+BZ104 -> 215031
B61: EBITDA | C61: =C59+C60 -> 1014807.6 | D61: =D59+D60 -> 1113884 | E61: =E59+E60 -> 1151480.9 | F61: =F59+F60 -> 1213960.6 | G61: =G59+G60 -> 1216360.3 | H61: =H59+H60 -> 1204345.8 | I61: =I59+I60 -> 1204249 | J61: =J59+J60 -> 1141335.4 | ... P61: =P59+P60 -> 2061875.5 | R61: =R59+R60 -> 254206.34 | S61: =S59+S60 -> 279814.44 | T61: =T59+T60 -> 252401.58 | U61: =U59+U60 -> 365058.52 | V61: =V59+V60 -> 284793.41 | W61: =W59+W60 -> 294592.88 | X61: =X59+X60 -> 248234.71 | Y61: =Y59+Y60 -> 386339.61 | ... BF61: =BF59+BF60 -> 343713.1 | BH61: =BH59+BH60 -> 296030.29 | BI61: =BI59+BI60 -> 305659.5 | BJ61: =BJ59+BJ60 -> 250108.45 | BK61: =BK59+BK60 -> 351945.18 | BL61: =BL59+BL60 -> 279238.93 | BN61: =BN59+BN60 -> 534020.78 | BO61: =BO59+BO60 -> 579386.29 | BP61: =BP59+BP60 -> 601921.95 | BQ61: =BQ59+BQ60 -> 595136.49 | BR61: =BR59+BR60 -> 185904.37 | BS61: =BS59+BS60 -> 711236.05 | BT61: =BT59+BT60 -> 536738.81 | BU61: =BU59+BU60 -> 267691.76 | ... BW61: =BW59+BW60 -> 943860.43 | BY61: =BY59+BY60 -> 601689.79 | BZ61: =BZ59+BZ60 -> 595136.49
B62: Other Income / (Expenses) | C62: =C16 -> 8506.262 | D62: =D16 -> 33749.211 | E62: =E16 -> 160726.38 | F62: =F16 -> 5689.395 | G62: =G16 -> 3289.726 | H62: =H16 -> 24079.804 | I62: =I16 -> 24657.249 | J62: =J16 -> 20796.536 | ... P62: =P16 -> 1367762 | R62: =R16 -> 1161.901 | S62: =BN62-R62 -> -648.153 | T62: =T16 -> 137097.21 | U62: =U16 -> 23115.419 | V62: =V16 -> -5889.723 | W62: =BO62-V62 -> 8506.923 | X62: =X16 -> -1262.113 | Y62: =Y16 -> 4334.308 | Z62: =Z16 -> -238.956 | AA62: =BP62-Z62 -> -1554.962 | AB62: =AB16 -> 1351.188 | AC62: =AC16 -> 24522.534 | AD62: =AD16 -> -573.83 | AE62: =BQ62-AD62 -> 9095.729 | AF62: =AF16 -> 3752.906 | AG62: =AG16 -> 8521.731 | AH62: =AH16 -> 310.265 | AI62: =BR62-AH62 -> 1451.528 | AJ62: =AJ16 -> 2162.392 | AK62: =AK16 -> -48988.277 | AL62: =AL16 -> -4290.924 | AM62: =BS62-AL62 -> -1470.839 | AN62: =AN16 -> 4315.632 | AO62: =AO16 -> -27608.898 | AP62: =AP16 -> 2016.356 | AQ62: =BT62-AP62 -> 83406.528 | AR62: =AR16 -> 13267.175 | AS62: =AS16 -> -89311.143 | AT62: =AT16 -> 5337 | AU62: =BU62-AT62 -> 170546.43 | AV62: =AV16 -> 5035.073 | AW62: =AW16 -> 45652.567 | AX62: =AX16 -> 8961.685 | AY62: =BV62-AX62 -> 114692.51 | AZ62: =AZ16 -> 6735.379 | BA62: =BA16 -> 65327.378 | BB62: =BB16 -> 8023.633 | BC62: =BW62-BB62 -> 432144.41 | BD62: =BD16 -> 14402.383 | BE62: =BE16 -> 913191.61 | BF62: =BF16 -> 11524.835 | BH62: =BH16 -> -306.15 | BI62: =BI16 -> -1334.111 | BJ62: =BJ16 -> 1761.028 | BK62: =BK16 -> 25099.979 | BL62: =BL16 -> -573.83 | BN62: =BN16 -> 513.748 | BO62: =BO16 -> 2617.2 | BP62: =BP16 -> -1793.918 | BQ62: =BQ16 -> 8521.899 | BR62: =BR16 -> 1761.793 | BS62: =BS16 -> -5761.763 | BT62: =BT16 -> 85422.884 | BU62: =BU16 -> 175883.43 | ... BW62: =BW16 -> 440168.04 | BY62: =BY16 -> -1640.261 | BZ62: =BZ16 -> 8521.899
B63: Net Financial Income / (Cost) | C63: -160784 | D63: -173619 | E63: -218388 | F63: -197522 | G63: -197522 | H63: -166719 | I63: -167413 | J63: -204454 | K63: -215282 | L63: -165948 | M63: -401756 | N63: -369467 | O63: -310972 | P63: -308608 | R63: -56731 | S63: =BN63-R63 -> -61712 | T63: -50204 | U63: =E63-SUM(R63:T63) -> -49741 | V63: -52310 | W63: =BO63-V63 -> -46421 | X63: -46798 | Y63: =F63-X63-W63-V63 -> -51993 | Z63: -52822 | AA63: =BP63-Z63 -> -38084 | AB63: -38439 | AC63: =H63-AB63-AA63-Z63 -> -37374 | AD63: -49829 | AE63: =BQ63-AD63 -> -61623 | AF63: -34388 | AG63: =J63-AF63-AE63-AD63 -> -58614 | AH63: -35206 | AI63: =BR63-AH63 -> -41299 | AJ63: -52270 | AK63: =K63-AJ63-AI63-AH63 -> -86507 | AL63: -38685 | AM63: =BS63-AL63 -> -43786 | AN63: 1299 | AO63: =L63-AN63-AM63-AL63 -> -84776 | AP63: -130226 | AQ63: =BT63-AP63 -> -68957 | AR63: -86822 | AS63: =M63-AR63-AQ63-AP63 -> -115751 | AT63: -91421 | AU63: =BU63-AT63 -> -104525 | AV63: -65503 | AW63: =N63-AV63-AU63-AT63 -> -108018 | AX63: -76652 | AY63: =BV63-AX63 -> -86229 | AZ63: -85130 | BA63: =O63-AZ63-AY63-AX63 -> -62961 | BB63: -92136 | BC63: =BW63-BB63 -> -81249.797 | BD63: -56312 | BE63: =P63-BD63-BC63-BB63 -> -78910.203 | BF63: -50921 | BH63: -52740 | BI63: =BY63-BH63 -> -38234 | BJ63: -38773 | BK63: =I63-Z63-AB63-AA63 -> -38068 | BL63: -49829 | BN63: -118443 | BO63: -98731 | BP63: -90906 | BQ63: -111452 | BR63: -76505 | BS63: -82471 | BT63: -199183 | BU63: -195946 | BV63: -162881 | BW63: -173385.8 | BY63: -90974 | BZ63: -111452
B64: Profit / (Loss) in Associates | C64: 26514 | D64: 25804 | E64: 21756 | F64: 15749 | G64: 15749 | H64: 7643 | I64: 7643 | J64: 1172 | K64: 4288 | L64: 23194 | M64: 17901 | N64: 19932 | O64: 25687 | P64: 31358 | R64: 5708 | S64: =BN64-R64 -> 5741 | T64: 4428 | U64: =E64-SUM(R64:T64) -> 5879 | V64: 4436 | W64: =BO64-V64 -> 3025 | X64: 2696 | Y64: =F64-X64-W64-V64 -> 5592 | Z64: 2475 | AA64: =BP64-Z64 -> 1899 | AB64: 1515 | AC64: =H64-AB64-AA64-Z64 -> 1754 | AD64: 995 | AE64: =BQ64-AD64 -> -486 | AF64: -426 | AG64: =J64-AF64-AE64-AD64 -> 1089 | AH64: -2316 | AI64: =BR64-AH64 -> -2526 | AJ64: 1693 | AK64: =K64-AJ64-AI64-AH64 -> 7437 | AL64: 5303 | AM64: =BS64-AL64 -> 3031 | AN64: 6087 | AO64: =L64-AN64-AM64-AL64 -> 8773 | AP64: 6160 | AQ64: =BT64-AP64 -> 5662 | AR64: 5538 | AS64: =M64-AR64-AQ64-AP64 -> 541 | AT64: 3832 | AU64: =BU64-AT64 -> 3122 | AV64: 6019 | AW64: =N64-AV64-AU64-AT64 -> 6959 | AX64: 5778 | AY64: =BV64-AX64 -> 4747 | AZ64: 7057 | BA64: =O64-AZ64-AY64-AX64 -> 8105 | BB64: 10277 | BC64: =BW64-BB64 -> 8568 | BD64: 8641 | BE64: =P64-BD64-BC64-BB64 -> 3872 | BF64: 12108 | BH64: 2475 | BI64: =BY64-BH64 -> 1899 | BJ64: 1515 | BK64: =I64-Z64-AB64-AA64 -> 1754 | BL64: 995 | BN64: 11449 | BO64: 7461 | BP64: 4374 | BQ64: 509 | BR64: -4842 | BS64: 8334 | BT64: 11822 | BU64: 6954 | BV64: 10525 | BW64: 18845 | BY64: 4374 | BZ64: 509
B65: Exchange Rate Differences | C65: -40227 | D65: -18209 | E65: 3637 | F65: -466 | G65: -466 | H65: -15793 | I65: -15581 | J65: -22065 | K65: -29086 | L65: -41110 | M65: -7707 | N65: =38739 -> 38739 | O65: -2549 | P65: 44438 | R65: 17 | S65: =BN65-R65 -> 6424 | T65: -2947 | U65: =E65-SUM(R65:T65) -> 143 | V65: 2317 | W65: =BO65-V65 -> -3157 | X65: 1918 | Y65: =F65-X65-W65-V65 -> -1544 | Z65: 617 | AA65: =BP65-Z65 -> -6444 | AB65: -11111 | AC65: =H65-AB65-AA65-Z65 -> 1145 | AD65: 511 | AE65: =BQ65-AD65 -> 733 | AF65: -20839 | AG65: =J65-AF65-AE65-AD65 -> -2470 | AH65: -13189 | AI65: =BR65-AH65 -> -8252 | AJ65: -6378 | AK65: =K65-AJ65-AI65-AH65 -> -1267 | AL65: -15241 | AM65: =BS65-AL65 -> -12016 | AN65: -18231 | AO65: =L65-AN65-AM65-AL65 -> 4378 | AP65: 33228 | AQ65: =BT65-AP65 -> -1456 | AR65: -30572 | AS65: =M65-AR65-AQ65-AP65 -> -8907 | AT65: 3037 | AU65: =BU65-AT65 -> 22811 | AV65: -2480 | AW65: =N65-AV65-AU65-AT65 -> 15371 | AX65: -2032 | AY65: =BV65-AX65 -> -11345 | AZ65: 8944 | BA65: =O65-AZ65-AY65-AX65 -> 1884 | BB65: 12201 | BC65: =BW65-BB65 -> 12510 | BD65: 5485 | BE65: =P65-BD65-BC65-BB65 -> 14242 | BF65: -10931 | BH65: 640 | BI65: =BY65-BH65 -> -6382 | BJ65: -10850 | BK65: =I65-Z65-AB65-AA65 -> 1357 | BL65: 511 | BN65: 6441 | BO65: -840 | BP65: -5827 | BQ65: 1244 | BR65: -21441 | BS65: -27257 | BT65: 31772 | BU65: 25848 | BV65: -13377 | BW65: 24711 | BY65: -5742 | BZ65: 1244
B66: Non-Operating Profit | C66: =SUM(C62:C65) -> -165990.74 | D66: =SUM(D62:D65) -> -132274.79 | E66: =SUM(E62:E65) -> -32268.623 | F66: =SUM(F62:F65) -> -176549.61 | G66: =SUM(G62:G65) -> -178949.27 | H66: =SUM(H62:H65) -> -150789.2 | I66: =SUM(I62:I65) -> -150693.75 | J66: =SUM(J62:J65) -> -204550.46 | ... P66: =SUM(P62:P65) -> 1134950 | R66: =SUM(R62:R65) -> -49844.099 | S66: =SUM(S62:S65) -> -50195.153 | T66: =SUM(T62:T65) -> 88374.21 | U66: =SUM(U62:U65) -> -20603.581 | V66: =SUM(V62:V65) -> -51446.723 | W66: =SUM(W62:W65) -> -38046.077 | X66: =SUM(X62:X65) -> -43446.113 | Y66: =SUM(Y62:Y65) -> -43610.692 | ... BF66: =SUM(BF62:BF65) -> -38219.165 | BH66: =SUM(BH62:BH65) -> -49931.15 | BI66: =SUM(BI62:BI65) -> -44051.111 | BJ66: =SUM(BJ62:BJ65) -> -46346.972 | BK66: =SUM(BK62:BK65) -> -9857.021 | BL66: =SUM(BL62:BL65) -> -48896.83 | BN66: =SUM(BN62:BN65) -> -100039.25 | BO66: =SUM(BO62:BO65) -> -89492.8 | BP66: =SUM(BP62:BP65) -> -94152.918 | BQ66: =SUM(BQ62:BQ65) -> -101177.1 | BR66: =SUM(BR62:BR65) -> -101026.21 | BS66: =SUM(BS62:BS65) -> -107155.76 | BT66: =SUM(BT62:BT65) -> -70166.116 | BU66: =SUM(BU62:BU65) -> 12739.427 | ... BW66: =SUM(BW62:BW65) -> 310338.24 | BY66: =SUM(BY62:BY65) -> -93982.261 | BZ66: =SUM(BZ62:BZ65) -> -101177.1
B67: Profit Before Tax Expenses | C67: =C66+C59 -> 644374.15 | D67: =D66+D59 -> 737811.86 | E67: =E66+E59 -> 857022.47 | F67: =F66+F59 -> 750640 | G67: =G66+G59 -> 750640 | H67: =H66+H59 -> 728225.62 | I67: =I66+I59 -> 728224.24 | J67: =J66+J59 -> 500923.97 | ... P67: =P66+P59 -> 2699412.6 | R67: =R66+R59 -> 141818.44 | S67: =S66+S59 -> 164400.21 | T67: =T66+T59 -> 274744.87 | U67: =U66+U59 -> 276058.95 | V67: =V66+V59 -> 164576.66 | W67: =W66+W59 -> 185830.16 | X67: =X66+X59 -> 132716.61 | Y67: =Y66+Y59 -> 267516.56 | ... AU67: =AU66+AU59 -> 134978.67 | AV67: =AV66+AV59-1 -> 7946.949 | AW67: =AW66+AW59 -> 132666.53 | AX67: =AX66+AX59 -> 136386.38 | AY67: =AY66+AY59 -> 250904.01 | AZ67: =AZ66+AZ59 -> 172520.93 | BA67: =BA66+BA59 -> 413316.72 | BB67: =BB66+BB59 -> 316383.08 | BC67: =BC66+BC59 -> 751527.91 | BD67: =BD66+BD59 -> 291740.63 | ... BF67: =BF66+BF59 -> 409528.16 | BH67: =BH66+BH59 -> 169024.14 | BI67: =BI66+BI59 -> 184897.39 | BJ67: =BJ66+BJ59 -> 121030.48 | BK67: =BK66+BK59 -> 253274.14 | BL67: =BL66+BL59 -> 121720.1 | BN67: =BN66+BN59 -> 306218.65 | BO67: =BO66+BO59 -> 350406.82 | BP67: =BP66+BP59 -> 353921.05 | BQ67: =BQ66+BQ59 -> 278928.39 | BR67: =BR66+BR59 -> -147572.84 | BS67: =BS66+BS59 -> 381210.29 | BT67: =BT66+BT59 -> 250661.7 | BU67: =BU66+BU59 -> 58349.188 | ... BW67: =BW66+BW59 -> 1032343.7 | BY67: =BY66+BY59 -> 353921.53 | BZ67: =BZ66+BZ59 -> 278928.39
B68: Income Tax | C68: =C48+C23 -> -127268.85 | D68: =D48+D23 -> -167275.05 | E68: =E48+E23 -> -178990.91 | F68: =F48+F23 -> -191735.28 | G68: =G48+G23 -> -191735.28 | H68: =H48+H23 -> -184497.9 | I68: =I48+I23 -> -184497.9 | J68: =J48+J23 -> -144747.22 | ... P68: =P48+P23 -> -637149.8 | R68: =R48+R23 -> -28504.891 | S68: =BN68-R68 -> -36707.333 | T68: =T48+T23 -> -29658.266 | U68: =E68-SUM(R68:T68) -> -84120.419 | V68: =V48+V23 -> -37291.225 | W68: =BO68-V68 -> -47157.825 | X68: =X48+X23 -> -36025.991 | Y68: =F68-X68-W68-V68 -> -71260.239 | Z68: =Z48+Z23 -> -43826.227 | AA68: =BP68-Z68 -> -37239.17 | AB68: =AB48+AB23 -> -31200.306 | AC68: =H68-AB68-AA68-Z68 -> -72232.198 | AD68: =AD48+AD23 -> -38134.115 | AE68: =BQ68-AD68 -> -40609.196 | AF68: =AF48+AF23 -> -32400.606 | AG68: =J68-AF68-AE68-AD68 -> -33603.301 | AH68: =AH48+AH23 -> -17469.555 | AI68: =BR68-AH68 -> 52102.185 | AJ68: =AJ48+AJ23 -> -8884.562 | AK68: =K68-AJ68-AI68-AH68 -> -70394.261 | AL68: =AL48+AL23 -> -45501.674 | AM68: =BS68-AL68 -> -52956.837 | AN68: =AN48+AN23 -> -65688.973 | AO68: =L68-AN68-AM68-AL68 -> -44663.607 | AP68: =AP48+AP23 -> 3765.603 | AQ68: =BT68-AP68 -> -20948.187 | AR68: =AR48+AR23 -> 29282.518 | AS68: =M68-AR68-AQ68-AP68 -> 67202.255 | AT68: =AT48+AT23 -> 26483.912 | AU68: =BU68-AT68 -> -20804.715 | AV68: =AV48+AV23 -> 4942.144 | AW68: =N68-AV68-AU68-AT68 -> -21000.685 | AX68: =AX48+AX23 -> -36858.257 | AY68: =BV68-AX68 -> -78735.816 | AZ68: =AZ48+AZ23 -> -41198.425 | BA68: =O68-AZ68-AY68-AX68 -> -101047.42 | BB68: =BB48+BB23 -> -72770.377 | BC68: =BW68-BB68 -> -189619.32 | BD68: =BD48+BD23 -> -71463.585 | BE68: =P68-BD68-BC68-BB68 -> -303296.52 | BF68: =BF48+BF23 -> -112853.72 | BH68: =BH48+BH23 -> -43826.228 | BI68: =BI48+BI23 -> -37239.169 | BJ68: =BJ48+BJ23 -> -31200.306 | BK68: =I68-Z68-AB68-AA68 -> -72232.198 | BL68: =BL48+BL23 -> -38134.115 | BN68: =BN48+BN23 -> -65212.224 | BO68: =BO48+BO23 -> -84449.05 | BP68: =BP48+BP23 -> -81065.397 | BQ68: =BQ48+BQ23 -> -78743.311 | BR68: =BR48+BR23 -> 34632.63 | BS68: =BS48+BS23 -> -98458.511 | BT68: =BT48+BT23 -> -17182.584 | BU68: =BU48+BU23 -> 5679.197 | ... BW68: =BW48+BW23 -> -262389.7 | BY68: =BY48+BY23 -> -81065.397 | BZ68: =BZ48+BZ23 -> -78743.311
B69: Net Profit / (Loss) before minority interest | C69: =C67+C68 -> 517105.3 | D69: =D67+D68 -> 570536.81 | E69: =E67+E68 -> 678031.56 | F69: =F67+F68 -> 558904.72 | G69: =G67+G68 -> 558904.72 | H69: =H67+H68 -> 543727.72 | I69: =I67+I68 -> 543726.34 | J69: =J67+J68 -> 356176.76 | ... P69: =P67+P68 -> 2062262.8 | R69: =R67+R68 -> 113313.55 | S69: =S67+S68 -> 127692.88 | T69: =T67+T68 -> 245086.6 | U69: =U67+U68 -> 191938.53 | V69: =V67+V68 -> 127285.43 | W69: =W67+W68 -> 138672.34 | X69: =X67+X68 -> 96690.623 | Y69: =Y67+Y68 -> 196256.33 | ... BF69: =BF67+BF68 -> 296674.44 | BH69: =BH67+BH68 -> 125197.91 | BI69: =BI67+BI68 -> 147658.22 | BJ69: =BJ67+BJ68 -> 89830.172 | BK69: =BK67+BK68 -> 181041.94 | BL69: =BL67+BL68 -> 83585.982 | BN69: =BN67+BN68 -> 241006.43 | BO69: =BO67+BO68 -> 265957.77 | BP69: =BP67+BP68 -> 272855.65 | BQ69: =BQ67+BQ68 -> 200185.08 | BR69: =BR67+BR68 -> -112940.21 | BS69: =BS67+BS68 -> 282751.78 | BT69: =BT67+BT68 -> 233479.11 | BU69: =BU67+BU68 -> 64028.385 | ... BW69: =BW67+BW68 -> 769953.97 | BY69: =BY67+BY68 -> 272856.14 | BZ69: =BZ67+BZ68 -> 200185.08
B70: Minority interest | C70: -52377 | D70: -52602 | E70: -69008 | F70: -49311 | G70: -49311 | H70: -65259 | I70: -65258 | J70: -60704 | K70: -5906 | L70: -42992 | M70: -42241 | N70: -127943 | O70: -154461 | P70: -636838 | R70: -9811 | S70: =BN70-R70 -> -9921 | T70: -34983 | U70: =E70-SUM(R70:T70) -> -14293 | V70: -11621 | W70: =BO70-V70 -> -10720 | X70: -11350 | Y70: =F70-X70-W70-V70 -> -15620 | Z70: -11783 | AA70: =BP70-Z70 -> -20028 | AB70: -13046 | AC70: =H70-AB70-AA70-Z70 -> -20402 | AD70: -13130 | AE70: =BQ70-AD70 -> -18314 | AF70: -16103 | AG70: =J70-AF70-AE70-AD70 -> -13157 | AH70: -10616 | AI70: =BR70-AH70 -> 11624 | AJ70: 3162 | AK70: =K70-AJ70-AI70-AH70 -> -10076 | AL70: -6384 | AM70: =BS70-AL70 -> -4192.645 | AN70: -15873 | AO70: =L70-AN70-AM70-AL70 -> -16542.355 | AP70: -14050 | AQ70: =BT70-AP70 -> -40690 | AR70: -14595 | AS70: =M70-AR70-AQ70-AP70 -> 27094 | AT70: -9963 | AU70: =BU70-AT70 -> -59218 | AV70: -17531 | AW70: =N70-AV70-AU70-AT70 -> -41231 | AX70: -20802 | AY70: =BV70-AX70 -> -38279.721 | AZ70: -25710 | BA70: =O70-AZ70-AY70-AX70 -> -69669.279 | BB70: -34259 | BC70: =BW70-BB70 -> -179414.74 | BD70: -40076 | BE70: =P70-BD70-BC70-BB70 -> -383088.26 | BF70: -40865 | BH70: -11783 | BI70: =BY70-BH70 -> -20028 | BJ70: -13045 | BK70: =I70-Z70-AB70-AA70 -> -20401 | BL70: -13130 | BN70: -19732 | BO70: -22341 | BP70: -31811 | BQ70: -31444 | BR70: 1008 | BS70: -10576.645 | BT70: -54740 | BU70: -69181 | BV70: -59081.721 | BW70: -213673.74 | BY70: -31811 | BZ70: -31444
B71: Net profit/(Loss) | C71: =C69+C70 -> 464728.3 | D71: =D69+D70 -> 517934.81 | E71: =E69+E70 -> 609023.56 | F71: =F69+F70 -> 509593.72 | G71: =G69+G70 -> 509593.72 | H71: =H69+H70 -> 478468.72 | I71: =I69+I70 -> 478468.34 | J71: =J69+J70 -> 295472.76 | ... P71: =P69+P70 -> 1425424.8 | R71: =R69+R70 -> 103502.55 | S71: =S69+S70 -> 117771.88 | T71: =T69+T70 -> 210103.6 | U71: =U69+U70 -> 177645.53 | V71: =V69+V70 -> 115664.43 | W71: =W69+W70 -> 127952.34 | X71: =X69+X70 -> 85340.623 | Y71: =Y69+Y70 -> 180636.33 | ... BF71: =BF69+BF70 -> 255809.44 | BH71: =BH69+BH70 -> 113414.91 | BI71: =BI69+BI70 -> 127630.22 | BJ71: =BJ69+BJ70 -> 76785.172 | BK71: =BK69+BK70 -> 160640.94 | BL71: =BL69+BL70 -> 70455.982 | BN71: =BN69+BN70 -> 221274.43 | BO71: =BO69+BO70 -> 243616.77 | BP71: =BP69+BP70 -> 241044.65 | BQ71: =BQ69+BQ70 -> 168741.08 | BR71: =BR69+BR70 -> -111932.21 | BS71: =BS69+BS70 -> 272175.13 | BT71: =BT69+BT70 -> 178739.11 | BU71: =BU69+BU70 -> -5152.615 | ... BW71: =BW69+BW70 -> 556280.24 | BY71: =BY69+BY70 -> 241045.14 | BZ71: =BZ69+BZ70 -> 168741.08
B73: Total net income (Consolidated) before minority interest | C73: =C49+C26 -> 517105.56 | D73: =D49+D26 -> 570536.49 | E73: =E49+E26 -> 678031.99 | F73: =F49+F26 -> 558904.19 | G73: =G49+G26 -> 558904.19 | H73: =H49+H26 -> 543727.38 | I73: =I49+I26 -> 543727.38 | J73: =J49+J26 -> 356176.47 | ... P73: =P49+P26 -> 1984315 | R73: =R49+R26 -> 113313.22 | S73: =S49+S26 -> 127693.39 | T73: =T49+T26 -> 245086.57 | U73: =U49+U26 -> 191938.81 | V73: =V49+V26 -> 127285.13 | W73: =W49+W26 -> 138672.66 | X73: =X49+X26 -> 96690.11 | Y73: =Y49+Y26 -> 196256.3 | ... BF73: =BF49+BF26 -> 275622.89 | BH73: =BH49+BH26 -> 125198.8 | BI73: =BI49+BI26 -> 147657.51 | BJ73: =BJ49+BJ26 -> 89830.2 | BK73: =BK49+BK26 -> 181040.86 | BL73: =BL49+BL26 -> 83585.374 | BN73: =BN49+BN26 -> 241006.61 | BO73: =BO49+BO26 -> 265957.78 | BP73: =BP49+BP26 -> 272856.31 | BQ73: =BQ49+BQ26 -> 200184.73 | BR73: =BR49+BR26 -> -112940.72 | BS73: =BS49+BS26 -> 282751.35 | BT73: =BT49+BT26 -> 233479.85 | BU73: =BU49+BU26 -> 64028.756 | ... BW73: =BW49+BW26 -> 769953.07 | BY73: =BY49+BY26 -> 272856.31 | BZ73: =BZ49+BZ26 -> 200184.73 | CC73: =CC49+CC26 -> 114658.36 | CD73: =CD49+CD26 -> 240502.65 | CE73: =CE49+CE26 -> 346989.86
B75: % of sales or stated otherwise (Retail Business)
B76: =B11 -> COGS | C76: =C11/C8 -> -0.66137223 | D76: =D11/D8 -> -0.65755112 | E76: =E11/E8 -> -0.65592834 | F76: =F11/F8 -> -0.65031939 | G76: =G11/G8 -> -0.64515697 | H76: =H11/H8 -> -0.6493187 | I76: =I11/I8 -> -0.65887217 | J76: =J11/J8 -> -0.67461531 | ... P76: =P11/P8 -> -0.64983053 | R76: =R11/R8 -> -0.67017163 | S76: =S11/S8 -> -0.65631414 | T76: =T11/T8 -> -0.66019554 | U76: =U11/U8 -> -0.63965534 | V76: =V11/V8 -> -0.65627562 | W76: =W11/W8 -> -0.64769806 | X76: =X11/X8 -> -0.65966101 | Y76: =Y11/Y8 -> -0.63982606 | ... BF76: =BF11/BF8 -> -0.65153093 | BH76: =BH11/BH8 -> -0.66418051 | BI76: =BI11/BI8 -> -0.65494397 | BJ76: =BJ11/BJ8 -> -0.66681218 | BK76: =BK11/BK8 -> -0.684101 | BL76: =BL11/BL8 -> -0.68660486 | BN76: =BN11/BN8 -> -0.66313604 | BO76: =BO11/BO8 -> -0.65191859 | BP76: =BP11/BP8 -> -0.64837314 | BQ76: =BQ11/BQ8 -> -0.67685466 | BR76: =BR11/BR8 -> -0.70678285 | BS76: =BS11/BS8 -> -0.6916477 | BT76: =BT11/BT8 -> -0.6961919 | BU76: =BU11/BU8 -> -0.69720076 | ... BW76: =BW11/BW8 -> -0.65206812 | BY76: =BY11/BY8 -> -0.65945063 | BZ76: =BZ11/BZ8 -> -0.67685466
B77: =B14 -> Distribution costs | C77: =-C14/C8 -> 0.011761275 | D77: =-D14/D8 -> 0.010614261 | E77: =-E14/E8 -> 0.011363433 | F77: =-F14/F8 -> 0.010246895 | G77: =-G14/G8 -> 0.011782833 | H77: =-H14/H8 -> 0.013653371 | I77: =-I14/I8 -> 0.014421066 | J77: =-J14/J8 -> 0.015059535 | ... P77: =-P14/P8 -> 0.016925517 | R77: =-R14/R8 -> 0.010775754 | S77: =-S14/S8 -> 0.014105884 | T77: =-T14/T8 -> 0.010833001 | U77: =-U14/U8 -> 0.0098831732 | V77: =-V14/V8 -> 0.010887034 | W77: =-W14/W8 -> 0.010314375 | X77: =-X14/X8 -> 0.010223322 | Y77: =-Y14/Y8 -> 0.0096727362 | ... BF77: =-BF14/BF8 -> 0.018104476 | BH77: =-BH14/BH8 -> 0.01462775 | BI77: =-BI14/BI8 -> 0.01420181 | BJ77: =-BJ14/BJ8 -> 0.014099793 | BK77: =-BK14/BK8 -> 0.017371839 | BL77: =-BL14/BL8 -> 0.01577153 | BN77: =-BN14/BN8 -> 0.012466496 | BO77: =-BO14/BO8 -> 0.010596148 | BP77: =-BP14/BP8 -> 0.013638802 | BQ77: =-BQ14/BQ8 -> 0.016294816 | BR77: =-BR14/BR8 -> 0.021433287 | BS77: =-BS14/BS8 -> 0.021817242 | BT77: =-BT14/BT8 -> 0.022758115 | BU77: =-BU14/BU8 -> 0.021987217 | ... BW77: =-BW14/BW8 -> 0.017131431 | BY77: =-BY14/BY8 -> 0.014409633 | BZ77: =-BZ14/BZ8 -> 0.015517258
B78: =B15 -> Administrative expenses | C78: =-C15/C8 -> 0.20707305 | D78: =-D15/D8 -> 0.21718115 | E78: =-E15/E8 -> 0.21733466 | F78: =-F15/F8 -> 0.22226028 | G78: =-G15/G8 -> 0.22502337 | H78: =-H15/H8 -> 0.22949413 | I78: =-I15/I8 -> 0.23869055 | J78: =-J15/J8 -> 0.24423445 | ... P78: =-P15/P8 -> 0.22733578 | R78: =-R15/R8 -> 0.21814018 | S78: =-S15/S8 -> 0.21496795 | T78: =-T15/T8 -> 0.22858736 | U78: =-U15/U8 -> 0.20914082 | V78: =-V15/V8 -> 0.22180126 | W78: =-W15/W8 -> 0.22480577 | X78: =-X15/X8 -> 0.23578118 | Y78: =-Y15/Y8 -> 0.20919339 | ... BF78: =-BF15/BF8 -> 0.22683734 | BH78: =-BH15/BH8 -> 0.2361096 | BI78: =-BI15/BI8 -> 0.23846355 | BJ78: =-BJ15/BJ8 -> 0.24854819 | BK78: =-BK15/BK8 -> 0.26219822 | BL78: =-BL15/BL8 -> 0.23745713 | BN78: =-BN15/BN8 -> 0.21652961 | BO78: =-BO15/BO8 -> 0.22332742 | BP78: =-BP15/BP8 -> 0.22825524 | BQ78: =-BQ15/BQ8 -> 0.23920694 | BR78: =-BR15/BR8 -> 0.28927683 | BS78: =-BS15/BS8 -> 0.2039607 | BT78: =-BT15/BT8 -> 0.22433419 | BU78: =-BU15/BU8 -> 0.25628229 | ... BW78: =-BW15/BW8 -> 0.23089568 | BY78: =-BY15/BY8 -> 0.23731502 | BZ78: =-BZ15/BZ8 -> 0.2399845
B79: =B16 -> Other gains (losses) | C79: =C16/C8 -> 0.001208554 | D79: =D16/D8 -> 0.0043529342 | E79: =E16/E8 -> 0.020349485 | F79: =F16/F8 -> 0.00069023897 | G79: =G16/G8 -> 0.00040070469 | H79: =H16/H8 -> 0.0028384021 | I79: =I16/I8 -> 0.0030910822 | J79: =J16/J8 -> 0.0025822713 | ... P79: =P16/P8 -> 0.12058856 | R79: =-R16/R8 -> -0.0006148938 | S79: =-S16/S8 -> 0.000332593 | T79: =-T16/T8 -> -0.07333136 | U79: =-U16/U8 -> -0.010553248 | V79: =-V16/V8 -> 0.0030172249 | W79: =-W16/W8 -> -0.0042214567 | X79: =-X16/X8 -> 0.00064990585 | Y79: =-Y16/Y8 -> -0.0018574632 | ... BF79: =-BF16/BF8 -> -0.0041665679 | BH79: =-BH16/BH8 -> 0.00016222939 | BI79: =-BI16/BI8 -> 0.00067358406 | BJ79: =-BJ16/BJ8 -> -0.00093770188 | BK79: =-BK16/BK8 -> -0.01352739 | BL79: =-BL16/BL8 -> 0.0002977995 | BN79: =BN16/BN8 -> 0.00013384489 | BO79: =BO16/BO8 -> 0.00065971028 | BP79: =-BP16/BP8 -> 0.00043575603 | BQ79: =-BQ16/BQ8 -> -0.0021734096 | BR79: =-BR16/BR8 -> -0.00052652719 | BS79: =-BS16/BS8 -> 0.0012502016 | BT79: =-BT16/BT8 -> -0.016537726 | BU79: =-BU16/BU8 -> -0.039131785 | BV79: =-BV16/BV8 -> -0.025559933 | BW79: =-BW16/BW8 -> -0.082325983 | BY79: =BY16/BY8 -> -0.00042408572 | BZ79: =BZ16/BZ8 -> 0.0021734096
B80: =B17 -> Other expenses | C80: =C17/C8 -> -0.019379188 | D80: =D17/D8 -> -0.018350568 | E80: =E17/E8 -> -0.017121323 | F80: =F17/F8 -> -0.018012242 | G80: =G17/G8 -> -0.018187252 | H80: =H17/H8 -> -0.016785945 | I80: =I17/I8 -> -0.017534159 | J80: =J17/J8 -> -0.017619399 | ... P80: =P17/P8 -> -0.010384614 | R80: =R17/R8 -> -0.015517639 | S80: =S17/S8 -> -0.017491472 | T80: =T17/T8 -> -0.016956855 | U80: =U17/U8 -> -0.018315855 | V80: =V17/V8 -> -0.014138589 | W80: =W17/W8 -> -0.018969431 | X80: =X17/X8 -> -0.018679278 | Y80: =Y17/Y8 -> -0.019870957 | ... BF80: =BF17/BF8 -> -0.013277745 | BH80: =BH17/BH8 -> -0.014102114 | BI80: =BI17/BI8 -> -0.017647156 | BJ80: =BJ17/BJ8 -> -0.018193939 | BK80: =BK17/BK8 -> -0.022821513 | BL80: =BL17/BL8 -> -0.014895216 | BN80: =BN17/BN8 -> -0.016519775 | BO80: =BO17/BO8 -> -0.016592446 | BP80: =BP17/BP8 -> -0.015250938 | BQ80: =BQ17/BQ8 -> -0.016447463 | BR80: =BR17/BR8 -> -0.014544873 | BS80: =BS17/BS8 -> -0.013767447 | BT80: =BT17/BT8 -> -0.0188875 | BU80: =BU17/BU8 -> -0.012378047 | ... BW80: =BW17/BW8 -> -0.010223262 | BY80: =BY17/BY8 -> -0.015917472 | BZ80: =BZ17/BZ8 -> -0.016447463
B81: =B18 -> Operating Profit | C81: =C18/C8 -> 0.10162281 | D81: =D18/D8 -> 0.10065583 | E81: =E18/E8 -> 0.11860173 | F81: =F18/F8 -> 0.099851427 | G81: =G18/G8 -> 0.10025028 | H81: =H18/H8 -> 0.093586263 | I81: =I18/I8 -> 0.073573143 | J81: =J18/J8 -> 0.051053578 | ... P81: =P18/P8 -> 0.21611212 | R81: =R18/R8 -> 0.086009685 | S81: =S18/S8 -> 0.096787953 | T81: =T18/T8 -> 0.1567586 | U81: =U18/U8 -> 0.13355806 | V81: =V18/V8 -> 0.093880277 | W81: =W18/W8 -> 0.10243382 | X81: =X18/X8 -> 0.075005309 | Y81: =Y18/Y8 -> 0.12329432 | ... BF81: =BF18/BF8 -> 0.094416074 | BH81: =BH18/BH8 -> 0.070817805 | BI81: =BI18/BI8 -> 0.074069932 | BJ81: =BJ18/BJ8 -> 0.053283596 | BK81: =BK18/BK8 -> 0.027034818 | BL81: =BL18/BL8 -> 0.04497346 | BN81: =BN18/BN8 -> 0.091481924 | BO81: =BO18/BO8 -> 0.098225104 | BP81: =BP18/BP8 -> 0.094046129 | BQ81: =BQ18/BQ8 -> 0.053369533 | BR81: =BR18/BR8 -> -0.031511306 | BS81: =BS18/BS8 -> 0.067556701 | BT81: =BT18/BT8 -> 0.054366019 | BU81: =BU18/BU8 -> 0.051283473 | ... BW81: =BW18/BW8 -> 0.17200749 | BY81: =BY18/BY8 -> 0.072483166 | BZ81: =BZ18/BZ8 -> 0.053369533
B82: Finance Income as % of cash and cash equivalents | C82: =C19/C154 -> 0.092592918 | D82: =D19/D154 -> 0.1633746 | E82: =E19/E154 -> 0.075840054 | F82: =F19/F154 -> 0.069806463 | G82: =G19/G154 -> 0.065138639 | H82: =H19/H154 -> 0.10588104 | I82: =I19/I154 -> 0.11409552 | J82: =J19/J154 -> 0.09134705 | ... P82: =P19/P154 -> 0.049821389 | U82: =(R19+U19+S19+T19)/U154 -> 0.075840054 | V82: =(S19+V19+T19+U19)/V154 -> 0.077680305 | W82: =(T19+W19+U19+V19)/W154 -> 0.091027814 | X82: =(U19+X19+V19+W19)/X154 -> 0.068045427 | Y82: =(V19+Y19+W19+X19)/Y154 -> 0.069806463 | Z82: =(W19+Z19+X19+Y19)/Z154 -> 0.073964646 | AA82: =(X19+AA19+Y19+Z19)/AA154 -> 0.11044129 | AB82: =(Y19+AB19+Z19+AA19)/AB154 -> 0.16599517 | AC82: =(Z19+AC19+AA19+AB19)/AC154 -> 0.10588104 | AD82: =(H19+AD19-BH19)/AD154 -> 0.12948973 | AE82: =(+AE19+AD19+H19-BH19-BI19)/AE154 -> 0.16269576 | AF82: =(+AF19+AE19+H19-BI19-BJ19+AD19-BH19)/AF154 -> 0.11142772 | AG82: =(AD19+AG19+AE19+AF19)/AG154 -> 0.09134705 | AH82: =SUM(AE19:AH19)/AH154 -> 0.056120335 | AI82: =SUM(AF19:AI19)/AI154 -> 0.050208715 | AJ82: =SUM(AG19:AJ19)/AJ154 -> 0.061725501 | AK82: =(AH19+AK19+AI19+AJ19)/AK154 -> 0.055835669 | AL82: =SUM(AI19:AL19)/AL154 -> 0.061335093 | AM82: =SUM(AJ19:AM19)/AM154 -> 0.071253862 | AN82: =SUM(AK19:AN19)/AN154 -> 0.24316353 | AO82: =(AL19+AO19+AM19+AN19)/AO154 -> 0.23349951 | AP82: =SUM(AM19:AP19)/AP154 -> 0.30390097 | AQ82: =SUM(AN19:AQ19)/AQ154 -> 0.19863096 | AR82: =SUM(AO19:AR19)/AR154 -> 0.075242175 | AS82: =(AP19+AS19+AQ19+AR19)/AS154 -> 0.099051896 | AT82: =SUM(AQ19:AT19)/AT154 -> 0.15351154 | AU82: =SUM(AR19:AU19)/AU154 -> 0.17397131 | AV82: =SUM(AS19:AV19)/AV154 -> 0.080428468 | AW82: =(AT19+AW19+AU19+AV19)/AW154 -> 0.043585531 | AX82: =SUM(AU19:AX19)/AX154 -> 0.054405468 | AY82: =SUM(AV19:AY19)/AY154 -> 0.058234462 | AZ82: =SUM(AW19:AZ19)/AZ154 -> 0.050271787 | BA82: =(AX19+BA19+AY19+AZ19)/BA154 -> 0.062749729 | BB82: =SUM(AY19:BB19)/BB154 -> 0.088195317 | BC82: =SUM(AZ19:BC19)/BC154 -> 0.065205484 | BD82: =SUM(BA19:BD19)/BD154 -> 0.075949846 | BE82: =(BB19+BE19+BC19+BD19)/BE154 -> 0.049821389 | BF82: =SUM(BC19:BF19)/BF154 -> 0.044680875 | BH82: =(W19+BH19+X19+Y19)/Z154 -> 0.073574958 | BI82: =(X19+BI19+Y19+BH19)/AA154 -> 0.10882898 | BJ82: =(Y19+BJ19+Z19+AA19)/AB154 -> 0.16411429 | BK82: =(AA19+BK19+AB19+AC19)/BK154 -> 0.1297458 | BL82: =SUM(BI19:BL19)/BL154 -> 0.12079282 | BN82: =BN19/BN154*2 -> 0.07889762 | BO82: =BO19/BO154*2 -> 0.088403334 | BP82: =BP19/BP154*2 -> 0.14232388 | BQ82: =BQ19/BQ154*2 -> 0.09277162 | BR82: =BR19/BR154*2 -> 0.074629553 | BS82: =BS19/BS154*2 -> 0.1068946 | BT82: =BT19/BT154*2 -> 0.10124145 | BU82: =BU19/BU154*2 -> 0.17871191 | ... BW82: =BW19/BW154*2 -> 0.05341234 | BY82: =BY19/BY154*2 -> 0.13909926 | BZ82: =BZ19/BZ154*2 -> 0.09277162
B83: Finance costs as % of total debt | C83: =-C20/C260 -> 0.045605039 | D83: =-D20/D260 -> 0.050597498 | E83: =-E20/E260 -> 0.055158897 | F83: =-F20/F260 -> 0.051149253 | G83: =-G20/G260 -> 0.050867266 | H83: =-H20/H260 -> 0.047806687 | I83: =-I20/I260 -> 0.053834443 | J83: =-J20/J260 -> 0.04950157 | ... P83: =-P20/P260 -> 0.068835564 | U83: =-(R20+S20+T20+U20)/U260 -> 0.055158897 | V83: =-(S20+T20+U20+V20)/V260 -> 0.055103179 | W83: =-(T20+U20+V20+W20)/W260 -> 0.050486493 | X83: =-(U20+V20+W20+X20)/X260 -> 0.050085161 | Y83: =-(V20+W20+X20+Y20)/Y260 -> 0.051149253 | Z83: =-(W20+X20+Y20+Z20)/Z260 -> 0.051244409 | AA83: =-(X20+Y20+Z20+AA20)/AA260 -> 0.048429678 | AB83: =-(Y20+Z20+AA20+AB20)/AB260 -> 0.045354944 | ... AE83: =-(AB20+AC20+AD20+AE20)/AE260 -> 0.046365357 | AF83: =-(H20+AD20+AE20+AF20-BH20-BI20-BJ20)/AF260 -> 0.043126576 | AG83: =-(AD20+AE20+AF20+AG20)/AG260 -> 0.04950157 | AH83: =-(AE20+AF20+AG20+AH20)/AH260 -> 0.039029494 | AI83: =-(AF20+AG20+AH20+AI20)/AI260 -> 0.037701368 | AJ83: =-(AG20+AH20+AI20+AJ20)/AJ260 -> 0.044679899 | AK83: =-(AH20+AI20+AJ20+AK20)/AK260 -> 0.054219552 | AL83: =-(AI20+AJ20+AK20+AL20)/AL260 -> 0.053484142 | AM83: =-(AJ20+AK20+AL20+AM20)/AM260 -> 0.055284499 | AN83: =-(AK20+AL20+AM20+AN20)/AN260 -> 0.054255192 | ... BF83: =-(BC20+BD20+BE20+BF20)/BF260 -> 0.061854992 | BH83: =-(W20+X20+Y20+BH20)/Z260 -> 0.051200473 | BI83: =-(X20+Y20+Z20+BI20)/AA260 -> 0.048402765 | BJ83: =-(Y20+Z20+AA20+BJ20)/AB260 -> 0.045342142 | BK83: =-(AA20+AB20+Z20+BK20)/AC260 -> 0.047711027 | BL83: =-(BI20+BJ20+BK20+BL20)/BL260 -> 0.043351139 | BN83: =-BN20/BN260*2 -> 0.063677253 | BO83: =-BO20/BO260*2 -> 0.050096494 | BP83: =-(#REF!+BN20+BO20+BP20)/BP260 -> #REF! | BQ83: =-(BO20+BP20+BY20+BQ20)/BQ260 -> 0.092786086 | BR83: =-(J20+BR20-BZ20)/BR260 -> 0.037701368 | BS83: =-(K20+BS20-BR20)/BS260 -> 0.055284499 | BT83: =-(L20+BT20-BS20)/BT260 -> 0.048326839 | BU83: =-(M20+BU20-BT20)/BU260 -> 0.063355281 | BV83: =-(N20+BV20-BU20)/BV260 -> 0.056200916 | BW83: =-(O20+BW20-BV20)/BW260 -> 0.065464704
B84: =B21 -> Gain on net non-monetary position | C84: =C21/C8 -> -0.0078406383 | D84: =D21/D8 -> -0.0034039985 | E84: =E21/E8 -> -0.0001522526 | F84: =F21/F8 -> -0.00029734763 | G84: =G21/G8 -> -0.00029853536 | H84: =H21/H8 -> -0.0036772272 | I84: =I21/I8 -> -0.0038841449 | J84: =J21/J8 -> -0.0054227305 | ... P84: =P21/P8 -> 0.0019932048 | R84: =R21/R8 -> -0.00035745044 | S84: =S21/S8 -> 0.001644804 | T84: =T21/T8 -> -0.002352458 | U84: =U21/U8 -> 0.00030386915 | V84: =V21/V8 -> 0.0012321779 | W84: =W21/W8 -> -0.0035030682 | X84: =X21/X8 -> 0.0024757528 | Y84: =Y21/Y8 -> -0.0011162955 | ... BF84: =BF21/BF8 -> -0.00148304 | BH84: =BH21/BH8 -> -0.0017538483 | BI84: =BI21/BI8 -> -0.0050695616 | BJ84: =BJ21/BJ8 -> -0.0084771434 | BK84: =BK21/BK8 -> -0.00073699436 | BL84: =BL21/BL8 -> 0.00076013888 | BN84: =BN21/BN8 -> 0.00065911497 | BO84: =BO21/BO8 -> -0.001173121 | BP84: =BP21/BP8 -> -0.0032635907 | BQ84: =BQ21/BQ8 -> -0.0023449662 | BR84: =BR21/BR8 -> -0.012413356 | BS84: =BS21/BS8 -> -0.0095953194 | BT84: =BT21/BT8 -> -0.008100216 | BU84: =BU21/BU8 -> -0.0026086593 | ... BW84: =BW21/BW8 -> 0.0016325953 | BY84: =BY21/BY8 -> -0.0034517707 | BZ84: =BZ21/BZ8 -> -0.0023449662
B85: =B22 -> Profit before tax | C85: =C22/C8 -> 0.076779724 | D85: =D22/D8 -> 0.079173693 | E85: =E22/E8 -> 0.09410242 | F85: =F22/F8 -> 0.077685099 | G85: =G22/G8 -> 0.077995407 | H85: =H22/H8 -> 0.072908599 | I85: =I22/I8 -> 0.051521818 | J85: =J22/J8 -> 0.022968903 | ... P85: =P22/P8 -> 0.1954931 | R85: =R22/R8 -> 0.058955399 | S85: =S22/S8 -> 0.071227947 | T85: =T22/T8 -> 0.13066261 | U85: =U22/U8 -> 0.11356944 | V85: =V22/V8 -> 0.070509357 | W85: =W22/W8 -> 0.079186993 | X85: =X22/X8 -> 0.053247428 | Y85: =Y22/Y8 -> 0.10272887 | ... BF85: =BF22/BF8 -> 0.07634414 | BH85: =BH22/BH8 -> 0.044479044 | BI85: =BI22/BI8 -> 0.052372094 | BJ85: =BJ22/BJ8 -> 0.027606101 | BK85: =BK22/BK8 -> 0.0081417153 | BL85: =BL22/BL8 -> 0.019838813 | BN85: =BN22/BN8 -> 0.065186299 | BO85: =BO22/BO8 -> 0.074917218 | BP85: =BP22/BP8 -> 0.071529438 | BQ85: =BQ22/BQ8 -> 0.025282181 | BR85: =BR22/BR8 -> -0.062300054 | BS85: =BS22/BS8 -> 0.045508929 | BT85: =BT22/BT8 -> 0.024136812 | BU85: =BU22/BU8 -> 0.014892303 | ... BW85: =BW22/BW8 -> 0.14762523 | BY85: =BY22/BY8 -> 0.048520946 | BZ85: =BZ22/BZ8 -> 0.025282181
B86: Income tax benefit/(expense) as a % of Profit before tax | C86: =C23/C22 -> -0.18768488 | D86: =D23/D22 -> -0.21845017 | E86: =E23/E22 -> -0.19990624 | F86: =F23/F22 -> -0.2497469 | G86: =G23/G22 -> -0.2497469 | H86: =H23/H22 -> -0.24680271 | I86: =I23/I22 -> -0.24615805 | J86: =J23/J22 -> -0.33569754 | ... P86: =P23/P22 -> -0.24157194 | R86: =R23/R22 -> -0.18311707 | S86: =S23/S22 -> -0.21674991 | T86: =T23/T22 -> -0.087164094 | U86: =U23/U22 -> -0.30873933 | V86: =V23/V22 -> -0.21404401 | W86: =W23/W22 -> -0.251429 | X86: =X23/X22 -> -0.26289613 | Y86: =Y23/Y22 -> -0.2634545 | ... BF86: =BF23/BF22 -> -0.29503983 | BH86: =BH23/BH22 -> -0.25907512 | BI86: =BI23/BI22 -> -0.15379307 | BJ86: =BJ23/BJ22 -> -0.24799734 | BK86: =BK23/BK22 -> -0.78470781 | BL86: =BL23/BL22 -> -0.37670899 | BN86: =BN23/BN22 -> -0.20177544 | BO86: =BO23/BO22 -> -0.23411626 | BP86: =BP23/BP22 -> -0.21747112 | BQ86: =BQ23/BQ22 -> -0.29481324 | BR86: =BR23/BR22 -> -0.22684871 | BS86: =BS23/BS22 -> -0.2691801 | BT86: =BT23/BT22 -> -0.022258324 | BU86: =BU23/BU22 -> -0.15295523 | ... BW86: =BW23/BW22 -> -0.25628286 | BY86: =BY23/BY22 -> -0.20088277 | BZ86: =BZ23/BZ22 -> -0.29481324
B88: capex/sales | C88: =-C139/C8 -> 0.077244069 | D88: =-D139/D8 -> 0.061744155 | E88: =-E139/E8 -> 0.057631987 | F88: =-F139/F8 -> 0.064673364 | G88: =-G139/G8 -> 0.064931698 | H88: =-H139/H8 -> 0.054602002 | I88: =-I139/I8 -> 0.058070228 | J88: =-J139/J8 -> 0.068385653 | ... P88: =-P139/P8 -> 0.026563361 | R88: =-R139/R8 -> 0.045807232 | S88: =-S139/S8 -> 0.050242496 | T88: =-T139/T8 -> 0.06868652 | U88: =-U139/U8 -> 0.064972091 | V88: =-V139/V8 -> 0.058284505 | W88: =-W139/W8 -> 0.062768469 | X88: =-X139/X8 -> 0.070947808 | Y88: =-Y139/Y8 -> 0.066441132 | ... BF88: =-BF139/BF8 -> 0.017344485 | BH88: =-BH139/BH8 -> 0.057511317 | BI88: =-BI139/BI8 -> 0.057680904 | BJ88: =-BJ139/BJ8 -> 0.062020439 | BK88: =-BK139/BK8 -> 0.066811669 | BL88: =-BL139/BL8 -> 0.054912042 | BN88: =-BN139/BN8 -> 0.048059061 | BO88: =-BO139/BO8 -> 0.060562164 | BP88: =-BP139/BP8 -> 0.054113887 | BQ88: =-BQ139/BQ8 -> 0.063663854 | BR88: =-BR139/BR8 -> 0.072945607 | BS88: =-BS139/BS8 -> 0.030424554 | BT88: =-BT139/BT8 -> 0.032051096 | BU88: =-BU139/BU8 -> 0.037376559 | ... BW88: =-BW139/BW8 -> 0.016351295 | BY88: =-BY139/BY8 -> 0.05759816 | BZ88: =-BZ139/BZ8 -> 0.063663854
B89: D/A/sales | C89: =C104/C8 -> 0.026846093 | D89: =D104/D8 -> 0.029427684 | E89: =E104/E8 -> 0.031067311 | F89: =F104/F8 -> 0.032393485 | G89: =G104/G8 -> 0.032522878 | H89: =H104/H8 -> 0.035852293 | I89: =I104/I8 -> 0.038129569 | J89: =J104/J8 -> 0.049774679 | ... P89: =P104/P8 -> 0.040418216 | R89: =R104/R8 -> 0.03096854 | S89: =S104/S8 -> 0.03136045 | T89: =T104/T8 -> 0.033020742 | U89: =U104/U8 -> 0.029224382 | V89: =V104/V8 -> 0.032901786 | W89: =W104/W8 -> 0.032570158 | X89: =X104/X8 -> 0.034527676 | Y89: =Y104/Y8 -> 0.030039537 | ... BF89: =BF104/BF8 -> -0.04141682 | BH89: =BH104/BH8 -> 0.037969847 | BI89: =BI104/BI8 -> 0.036771236 | BJ89: =BJ104/BJ8 -> 0.040796921 | BK89: =BK104/BK8 -> 0.044761078 | BL89: =BL104/BL8 -> 0.051782318 | BN89: =BN104/BN8 -> 0.031167517 | BO89: =BO104/BO8 -> 0.032733334 | BP89: =BP104/BP8 -> 0.035111343 | BQ89: =BQ104/BQ8 -> 0.050771103 | BR89: =BR104/BR8 -> 0.06352804 | BS89: =BS104/BS8 -> 0.044280272 | BT89: =BT104/BT8 -> 0.037612758 | BU89: =BU104/BU8 -> 0.045087791 | ... BW89: =BW104/BW8 -> 0.038168091 | BY89: =BY104/BY8 -> 0.037356058 | BZ89: =BZ104/BZ8 -> 0.050771103
B91: % of income or stated otherwise (Banking Business)
B92: =B76 -> COGS | C92: =C548/(C29+C32+C37) -> -0.43183436 | D92: =D548/(D29+D32+D37) -> -0.4338901 | E92: =E548/(E29+E32+E37) -> -0.47346423 | F92: =F548/(F29+F32+F37) -> -0.47078698 | G92: =G548/(G29+G32+G37) -> -0.46951269 | H92: =H548/(H29+H32+H37) -> -0.44733431 | I92: =I548/(I29+I32+I37) -> -0.44100252 | J92: =J548/(J29+J32+J37) -> -0.45346283 | ... P92: =P548/(P29+P32+P37) -> -0.41340346 | R92: =R548/(R29+R32+R37) -> -0.45137748 | S92: =S548/(S29+S32+S37) -> -0.49224136 | T92: =T548/(T29+T32+T37) -> -0.4532128 | U92: =U548/(U29+U32+U37) -> -0.49537785 | V92: =V548/(V29+V32+V37) -> -0.48307525 | W92: =W548/(W29+W32+W37) -> -0.49537367 | X92: =X548/(X29+X32+X37) -> -0.44972717 | Y92: =Y548/(Y29+Y32+Y37) -> -0.45376949 | ... BF92: =BF548/(BF29+BF32+BF37) -> -0.38768697 | BH92: =BH548/(BH29+BH32+BH37) -> 0 | BI92: =BI548/(BI29+BI32+BI37) -> 0 | BJ92: =BJ548/(BJ29+BJ32+BJ37) -> 0 | BK92: =BK548/(BK29+BK32+BK37) -> 0 | BL92: =BL548/(BL29+BL32+BL37) -> 0 | BN92: =BN548/(BN29+BN32+BN37) -> -0.47224255 | BO92: =BO548/(BO29+BO32+BO37) -> -0.48934299 | BP92: =BP548/(BP29+BP32+BP37) -> -0.43056712 | BQ92: =BQ548/(BQ29+BQ32+BQ37) -> -0.42356111 | BR92: =BR548/(BR29+BR32+BR37) -> -0.58546438 | BS92: =BS548/(BS29+BS32+BS37) -> -0.22752075 | BT92: =BT548/(BT29+BT32+BT37) -> -0.502408 | BU92: =BU548/(BU29+BU32+BU37) -> -0.69173687 | ... BW92: =BW548/(BW29+BW32+BW37) -> -0.38843426 | BY92: =BY548/(BY29+BY32+BY37) -> 0 | BZ92: =BZ548/(BZ29+BZ32+BZ37) -> -0.42356111
B93: =B40 -> Remuneration and personnel costs | C93: =C40/(C29+C32+C37) -> -0.151004 | D93: =D40/(D29+D32+D37) -> -0.14584876 | E93: =E40/(E29+E32+E37) -> -0.13918866 | F93: =F40/(F29+F32+F37) -> -0.13872129 | G93: =G40/(G29+G32+G37) -> -0.13824909 | H93: =H40/(H29+H32+H37) -> -0.14641928 | I93: =I40/(I29+I32+I37) -> -0.11332078 | J93: =J40/(J29+J32+J37) -> -0.11016108 | ... P93: =P40/(P29+P32+P37) -> -0.088208878 | R93: =R40/(R29+R32+R37) -> -0.14241219 | S93: =S40/(S29+S32+S37) -> -0.13765554 | T93: =T40/(T29+T32+T37) -> -0.14222497 | U93: =U40/(U29+U32+U37) -> -0.13476386 | V93: =V40/(V29+V32+V37) -> -0.14026717 | W93: =W40/(W29+W32+W37) -> -0.13336411 | X93: =X40/(X29+X32+X37) -> -0.14287303 | Y93: =Y40/(Y29+Y32+Y37) -> -0.1386348 | ... BF93: =BF40/(BF29+BF32+BF37) -> -0.076802404 | BH93: =BH40/(BH29+BH32+BH37) -> -0.11564877 | BI93: =BI40/(BI29+BI32+BI37) -> -0.11379438 | BJ93: =BJ40/(BJ29+BJ32+BJ37) -> -0.11456469 | BK93: =BK40/(BK29+BK32+BK37) -> -0.08772031 | BL93: =BL40/(BL29+BL32+BL37) -> -0.11174244 | BN93: =BN40/(BN29+BN32+BN37) -> -0.13998345 | BO93: =BO40/(BO29+BO32+BO37) -> -0.13674911 | BP93: =BP40/(BP29+BP32+BP37) -> -0.14505785 | BQ93: =BQ40/(BQ29+BQ32+BQ37) -> -0.10787387 | BR93: =BR40/(BR29+BR32+BR37) -> -0.11274576 | BS93: =BS40/(BS29+BS32+BS37) -> -0.12276434 | BT93: =BT40/(BT29+BT32+BT37) -> -0.08517464 | BU93: =BU40/(BU29+BU32+BU37) -> -0.080315345 | ... BW93: =BW40/(BW29+BW32+BW37) -> -0.085346016 | BY93: =BY40/(BY29+BY32+BY37) -> -0.11470814 | BZ93: =BZ40/(BZ29+BZ32+BZ37) -> -0.10787387
B94: =B41 -> Administrative expenses | C94: =C41/(C$29+C$32+C$37) -> -0.18292838 | D94: =D41/(D$29+D$32+D$37) -> -0.18025228 | E94: =E41/(E$29+E$32+E$37) -> -0.1818401 | F94: =F41/(F$29+F$32+F$37) -> -0.19349254 | G94: =G41/(G$29+G$32+G$37) -> -0.18994901 | H94: =H41/(H$29+H$32+H$37) -> -0.20585264 | I94: =I41/(I$29+I$32+I$37) -> -0.14110952 | J94: =J41/(J$29+J$32+J$37) -> -0.14575681 | ... P94: =P41/(P$29+P$32+P$37) -> -0.2493409 | R94: =R41/(R$29+R$32+R$37) -> -0.18264267 | S94: =S41/(S$29+S$32+S$37) -> -0.18312439 | T94: =T41/(T$29+T$32+T$37) -> -0.18572736 | U94: =U41/(U$29+U$32+U$37) -> -0.17611749 | V94: =V41/(V$29+V$32+V$37) -> -0.18605666 | W94: =W41/(W$29+W$32+W$37) -> -0.18752657 | X94: =X41/(X$29+X$32+X$37) -> -0.19764706 | Y94: =Y41/(Y$29+Y$32+Y$37) -> -0.2030265 | ... BF94: =BF41/(BF$29+BF$32+BF$37) -> -0.18314454 | BH94: =BH41/(BH$29+BH$32+BH$37) -> -0.1384061 | BI94: =BI41/(BI$29+BI$32+BI$37) -> -0.14321931 | BJ94: =BJ41/(BJ$29+BJ$32+BJ$37) -> -0.13967773 | BK94: =BK41/(BK$29+BK$32+BK$37) -> -0.08985302 | BL94: =BL41/(BL$29+BL$32+BL$37) -> -0.13349229 | BN94: =BN41/(BN$29+BN$32+BN$37) -> -0.18288863 | BO94: =BO41/(BO$29+BO$32+BO$37) -> -0.18680578 | BP94: =BP41/(BP$29+BP$32+BP$37) -> -0.20884379 | BQ94: =BQ41/(BQ$29+BQ$32+BQ$37) -> -0.14262989 | BR94: =BR41/(BR$29+BR$32+BR$37) -> -0.14764761 | BS94: =BS41/(BS$29+BS$32+BS$37) -> -0.23428291 | BT94: =BT41/(BT$29+BT$32+BT$37) -> -0.22001797 | BU94: =BU41/(BU$29+BU$32+BU$37) -> -0.20191409 | ... BW94: =BW41/(BW$29+BW$32+BW$37) -> -0.22669579 | BY94: =BY41/(BY$29+BY$32+BY$37) -> -0.14084758 | BZ94: =BZ41/(BZ$29+BZ$32+BZ$37) -> -0.14262989
B95: Credit risk provisions as a % of customer loans and receivables | C95: =C38/C241 -> -0.041012062 | D95: =D38/D241 -> -0.046416383 | E95: =E38/E241 -> -0.05587021 | F95: =F38/F241 -> -0.069185777 | G95: =G38/G241 -> -0.069089673 | H95: =H38/H241 -> -0.062998771 | I95: =I38/I241 -> -0.062971661 | J95: =J38/J241 -> -0.064710134 | ... P95: =P38/P241 -> -0.062258126 | R95: =R38/R241 -> -0.013128486 | S95: =S38/S241 -> -0.015126822 | T95: =T38/T241 -> -0.01292733 | U95: =U38/U241 -> -0.016212991 | V95: =V38/V241 -> -0.016323823 | W95: =W38/W241 -> -0.019406694 | X95: =X38/X241 -> -0.016429488 | Y95: =Y38/Y241 -> -0.016979809 | ... BF95: =BF38/BF241 -> -0.014230656 | BL95: =BL38/BL241 -> -0.016338842 | BN95: =BN38/BN241 -> -0.027843652 | BO95: =BO38/BO241 -> -0.035779445 | BP95: =BP38/BP241 -> -0.029343814 | BQ95: =BQ38/BQ241 -> -0.030515412 | BR95: =BR38/BR241 -> -0.056938195 | BS95: =BS38/BS241 -> -0.0097751634 | BT95: =BT38/BT241 -> -0.033946988 | BU95: =BU38/BU241 -> -0.066361056 | ... BW95: =BW38/BW241 -> -0.030006898
B96: Profit before tax | C96: =C47/(C$29+C$32+C$37) -> 0.18790527 | D96: =D47/(D$29+D$32+D$37) -> 0.19885257 | E96: =E47/(E$29+E$32+E$37) -> 0.16487044 | F96: =F47/(F$29+F$32+F$37) -> 0.15234051 | G96: =G47/(G$29+G$32+G$37) -> 0.15182196 | H96: =H47/(H$29+H$32+H$37) -> 0.14574484 | I96: =I47/(I$29+I$32+I$37) -> 0.25168983 | J96: =J47/(J$29+J$32+J$37) -> 0.23279078 | ... P96: =P47/(P$29+P$32+P$37) -> 0.20478419 | R96: =R47/(R$29+R$32+R$37) -> 0.18529842 | S96: =S47/(S$29+S$32+S$37) -> 0.14943954 | T96: =T47/(T$29+T$32+T$37) -> 0.17446616 | U96: =U47/(U$29+U$32+U$37) -> 0.15161934 | V96: =V47/(V$29+V$32+V$37) -> 0.14985845 | W96: =W47/(W$29+W$32+W$37) -> 0.14052978 | X96: =X47/(X$29+X$32+X$37) -> 0.16476776 | Y96: =Y47/(Y$29+Y$32+Y$37) -> 0.15480262 | ... BF96: =BF47/(BF$29+BF$32+BF$37) -> 0.30885334 | BH96: =BH47/(BH$29+BH$32+BH$37) -> 0.28203459 | BI96: =BI47/(BI$29+BI$32+BI$37) -> 0.26135648 | BJ96: =BJ47/(BJ$29+BJ$32+BJ$37) -> 0.21647909 | BK96: =BK47/(BK$29+BK$32+BK$37) -> 0.33776212 | BL96: =BL47/(BL$29+BL$32+BL$37) -> 0.25664162 | BN96: =BN47/(BN$29+BN$32+BN$37) -> 0.1669889 | BO96: =BO47/(BO$29+BO$32+BO$37) -> 0.14510421 | BP96: =BP47/(BP$29+BP$32+BP$37) -> 0.16407692 | BQ96: =BQ47/(BQ$29+BQ$32+BQ$37) -> 0.27022328 | BR96: =BR47/(BR$29+BR$32+BR$37) -> 0.093609053 | BS96: =BS47/(BS$29+BS$32+BS$37) -> 0.33035489 | BT96: =BT47/(BT$29+BT$32+BT$37) -> 0.14967614 | BU96: =BU47/(BU$29+BU$32+BU$37) -> -0.0091213063 | ... BW96: =BW47/(BW$29+BW$32+BW$37) -> 0.25373016 | BY96: =BY47/(BY$29+BY$32+BY$37) -> 0.27154567 | BZ96: =BZ47/(BZ$29+BZ$32+BZ$37) -> 0.27022328
B97: Income tax benefit/(expense) as a % of Profit before tax | C97: =C48/C47 -> -0.24856341 | D97: =D48/D47 -> -0.26765903 | E97: =E48/E47 -> -0.26729168 | F97: =F48/F47 -> -0.28841468 | G97: =G48/G47 -> -0.28841468 | H97: =H48/H47 -> -0.29028446 | I97: =I48/I47 -> -0.26267353 | J97: =J48/J47 -> -0.26159643 | ... P97: =P48/P47 -> -0.25116709 | R97: =R48/R47 -> -0.26647967 | S97: =S48/S47 -> -0.25869529 | T97: =T48/T47 -> -0.27461372 | U97: =U48/U47 -> -0.2680846 | V97: =V48/V47 -> -0.29068325 | W97: =W48/W47 -> -0.26798355 | X97: =X48/X47 -> -0.30163525 | Y97: =Y48/Y47 -> -0.29157355 | ... BF97: =BF48/BF47 -> -0.28510023 | BH97: =BH48/BH47 -> -0.2594988 | BI97: =BI48/BI47 -> -0.26225174 | BJ97: =BJ48/BJ47 -> -0.2651261 | BK97: =BK48/BK47 -> -0.25351081 | BL97: =BL48/BL47 -> -0.28426056 | BN97: =BN48/BN47 -> -0.26292268 | BO97: =BO48/BO47 -> -0.27947933 | BP97: =BP48/BP47 -> -0.2863974 | BQ97: =BQ48/BQ47 -> -0.27541155 | BR97: =BR48/BR47 -> -0.20786579 | BS97: =BS48/BS47 -> -0.24494558 | BT97: =BT48/BT47 -> -0.11435665 | BU97: =BU48/BU47 -> -1.8538646 | ... BW97: =BW48/BW47 -> -0.24730479 | BY97: =BY48/BY47 -> -0.26084282 | BZ97: =BZ48/BZ47 -> -0.27541155
B99: capex/sales | C99: =-C180/(C29+C32+C37) -> 0.03747572 | D99: =-D180/(D29+D32+D37) -> 0.042339959 | E99: =-E180/(E29+E32+E37) -> 0.04489676 | F99: =-F180/(F29+F32+F37) -> 0.046803511 | G99: =-G180/(G29+G32+G37) -> 0.046644196 | H99: =-H180/(H29+H32+H37) -> 0.043891311 | I99: =-I180/(I29+I32+I37) -> 0.026209971 | J99: =-J180/(J29+J32+J37) -> 0.022528014 | ... P99: =-P180/(P29+P32+P37) -> 0.015483309 | R99: =-R180/(R29+R32+R37) -> 0.031886592 | S99: =-S180/(S29+S32+S37) -> 0.042849101 | T99: =-T180/(T29+T32+T37) -> 0.045278346 | U99: =-U180/(U29+U32+U37) -> 0.058334353 | V99: =-V180/(V29+V32+V37) -> 0.031296339 | W99: =-W180/(W29+W32+W37) -> 0.037476725 | X99: =-X180/(X29+X32+X37) -> 0.045193658 | Y99: =-Y180/(Y29+Y32+Y37) -> 0.073621448 | ... BF99: =-BF180/(BF29+BF32+BF37) -> 0.046570066 | BH99: =-BH180/(BH29+BH32+BH37) -> 0.01640411 | BI99: =-BI180/(BI29+BI32+BI37) -> 0.024523009 | BJ99: =-BJ180/(BJ29+BJ32+BJ37) -> 0.030560473 | BK99: =-BK180/(BK29+BK32+BK37) -> 0.015180693 | BL99: =-BL180/(BL29+BL32+BL37) -> 0.017228509 | BN99: =-BN180/(BN29+BN32+BN37) -> 0.037484041 | BO99: =-BO180/(BO29+BO32+BO37) -> 0.034446096 | BP99: =-BP180/(BP29+BP32+BP37) -> 0.034678171 | BQ99: =-BQ180/(BQ29+BQ32+BQ37) -> 0.02051963 | BR99: =-BR180/(BR29+BR32+BR37) -> 0.030339676 | BS99: =-BS180/(BS29+BS32+BS37) -> 0.023797486 | BT99: =-BT180/(BT29+BT32+BT37) -> 0.018782885 | BU99: =-BU180/(BU29+BU32+BU37) -> 0.011049781 | ... BW99: =-BW180/(BW29+BW32+BW37) -> 0.013758697 | BY99: =-BY180/(BY29+BY32+BY37) -> 0.020522398 | BZ99: =-BZ180/(BZ29+BZ32+BZ37) -> 0.02051963
B100: D/A/sales | C100: =C161/(C29+C32+C37) -> 0.027994675 | D100: =D161/(D29+D32+D37) -> 0.02508627 | E100: =E161/(E29+E32+E37) -> 0.024360675 | F100: =F161/(F29+F32+F37) -> 0.027293435 | G100: =G161/(G29+G32+G37) -> 0.02720053 | H100: =H161/(H29+H32+H37) -> 0.028133123 | I100: =I161/(I29+I32+I37) -> 0.016799871 | J100: =J161/(J29+J32+J37) -> 0.025785966 | ... P100: =P161/(P29+P32+P37) -> 0.019750339 | R100: =R161/(R29+R32+R37) -> 0.024525332 | S100: =S161/(S29+S32+S37) -> 0.02396531 | T100: =T161/(T29+T32+T37) -> 0.024607605 | U100: =U161/(U29+U32+U37) -> 0.024347152 | V100: =V161/(V29+V32+V37) -> 0.025280674 | W100: =W161/(W29+W32+W37) -> 0.027203042 | X100: =X161/(X29+X32+X37) -> 0.028217201 | Y100: =Y161/(Y29+Y32+Y37) -> 0.028487129 | ... BF100: =BF161/(BF29+BF32+BF37) -> 0.01833501 | BH100: =BH161/(BH29+BH32+BH37) -> 0.017967123 | BI100: =BI161/(BI29+BI32+BI37) -> 0.012497685 | BJ100: =BJ161/(BJ29+BJ32+BJ37) -> 0.019128434 | BK100: =BK161/(BK29+BK32+BK37) -> 0.008168922 | BL100: =BL161/(BL29+BL32+BL37) -> 0.027180848 | BN100: =BN161/(BN29+BN32+BN37) -> 0.024239385 | BO100: =BO161/(BO29+BO32+BO37) -> 0.026260385 | BP100: =BP161/(BP29+BP32+BP37) -> 0.025672308 | BQ100: =BQ161/(BQ29+BQ32+BQ37) -> 0.023984502 | BR100: =BR161/(BR29+BR32+BR37) -> 0.030567572 | BS100: =BS161/(BS29+BS32+BS37) -> 0.036213399 | BT100: =BT161/(BT29+BT32+BT37) -> 0.025695152 | BU100: =BU161/(BU29+BU32+BU37) -> 0.020639658 | ... BW100: =BW161/(BW29+BW32+BW37) -> 0.018565674 | BY100: =BY161/(BY29+BY32+BY37) -> 0.015192766 | BZ100: =BZ161/(BZ29+BZ32+BZ37) -> 0.023984502
B102: EBITDA (Non-Banking Business) | C102: 41975 | D102: 42341 | E102: 42708 | F102: 43073 | G102: 43073 | H102: =H3 -> 43438 | I102: =I3 -> 43438 | J102: =J3 -> 43803 | K102: =K3 -> 44169 | L102: =L3 -> 44534 | M102: =M3 -> 44899 | N102: =N3 -> 45264 | O102: =O3 -> 45630 | P102: =P3 -> 45995 | R102: 42437 | S102: 42527 | T102: 42622 | U102: 42714 | V102: 42801 | W102: 42892 | X102: 42987 | Y102: 43079 | Z102: =Z3 -> 43166 | AA102: =AA3 -> 43257 | AB102: =AB3 -> 43352 | AC102: =AC3 -> 43444 | AD102: =AD3 -> 43531 | AE102: =AE3 -> 43622 | AF102: =AF3 -> 43738 | AG102: =AG3 -> 43809 | ... BF102: =BF3 -> 46112 | BH102: =BH3 -> 43166 | BI102: =BI3 -> 43281 | BJ102: =BJ3 -> 43373 | BK102: =BK3 -> 43444 | BL102: =BL3 -> 43531 | BN102: 42530 | BO102: 42896 | BP102: =BP3 -> 43261 | BQ102: =BQ3 -> 43646 | BR102: =BR3 -> 44012 | BS102: =BS3 -> 44377 | BT102: =BT3 -> 44742 | BU102: =BU3 -> 45107 | BV102: =BV3 -> 45473 | BW102: =BW3 -> 45838 | BY102: =BY3 -> 43281 | BZ102: =BZ3 -> 43646 | CC102: 42064 | CD102: 42156 | CE102: 42248
B103: Operating profit | C103: =C18 -> 715259.96 | D103: =D18 -> 780405.77 | E103: =E18 -> 936752.28 | F103: =F18 -> 823039.89 | G103: =G18 -> 823039.89 | H103: =H18 -> 793946.3 | I103: =I18 -> 586885.49 | J103: =J18 -> 411164.22 | ... P103: =P18 -> 2451227.1 | R103: =R18 -> 162523.58 | S103: =S18 -> 188619.13 | T103: =T18 -> 293069.25 | U103: =U18 -> 292540.32 | V103: =V18 -> 183257.41 | W103: =W18 -> 206420.83 | X103: =X18 -> 145659.83 | Y103: =Y18 -> 287701.82 | ... BF103: =BF18 -> 261157.31 | BH103: =BH18 -> 133643.3 | BI103: =BI18 -> 146704.05 | BJ103: =BJ18 -> 100067.95 | BK103: =BK18 -> 50162.92 | BL103: =BL18 -> 86659.384 | BN103: =BN18 -> 351142.71 | BO103: =BO18 -> 389678.24 | BP103: =BP18 -> 387168.58 | BQ103: =BQ18 -> 209260.95 | BR103: =BR18 -> -105438.81 | BS103: =BS18 -> 311346.35 | BT103: =BT18 -> 280818.67 | BU103: =BU18 -> 230500.94 | ... BW103: =BW18 -> 919663.48 | BY103: =BY18 -> 280347.35 | BZ103: =BZ18 -> 209260.95 | CC103: =CC18 -> 150597.11 | CD103: =CD18 -> 326170.15 | CE103: =CE18 -> 478149.54
B104: Depreciation & amortisation | C104: 188953 | D104: 228159 | E104: 245379 | F104: =286771+F42 -> 267008 | G104: =286771+G42 -> 267008 | H104: =325331+H42 -> 304155.7 | I104: =325331+I42 -> 304155.7 | J104: =435861+J42 -> 400864.5 | K104: =462001+K42 -> 424494.82 | L104: =467483+L42 -> 428191.19 | M104: =505107+M42 -> 462484.01 | N104: =457595 -> 457595 | O104: 466200 | P104: 458439 | R104: 58518.036 | S104: =BN104-R104 -> 61114.846 | T104: =181367.066-S104-R104 -> 61734.184 | U104: =E104-T104-S104-R104 -> 64011.934 | V104: 64225.376 | W104: =BO104-V104 -> 65634.175 | X104: =196912.076-W104-V104 -> 67052.525 | Y104: =F104-X104-W104-V104 -> 70095.927 | Z104: 71288.648 | AA104: =BP104-Z104 -> 73257.534 | AB104: =221101.827-AA104-Z104 -> 76555.645 | AC104: =H104-AB104-AA104-Z104 -> 83053.874 | AD104: =108622+AD42 -> 99779.376 | AE104: =BQ104-AD104 -> 99293.179 | AF104: =109994+AF42 -> 100906.35 | AG104: =J104-AF104-AE104-AD104 -> 100885.6 | AH104: =116136+AH42 -> 106172.26 | AI104: =BR104-AH104 -> 106396.54 | AJ104: =114369+AJ42 -> 104925.47 | AK104: =K104-AJ104-AI104-AH104 -> 107000.55 | AL104: =110117+AL42 -> 100722.7 | AM104: =BS104-AL104 -> 103350.34 | AN104: =118242+AN42 -> 108674.25 | AO104: =L104-AN104-AM104-AL104 -> 115443.91 | AP104: =120513+AP42 -> 109876.21 | AQ104: =BT104-AP104 -> 84406.264 | AR104: 111856 | AS104: =M104-AR104-AQ104-AP104 -> 156345.53 | AT104: =124391+AT42 -> 114817.88 | AU104: =BU104-AT104 -> 87835.671 | AV104: 116153 | AW104: =N104-AV104-AU104-AT104 -> 138788.45 | AX104: 116847 | AY104: =BV104-AX104 -> 95208.411 | AZ104: 113219 | BA104: =O104-AZ104-AY104-AX104 -> 140925.59 | BB104: 110441 | BC104: =BW104-BB104 -> 93630.341 | BD104: 113666 | BE104: =P104-BD104-BC104-BB104 -> 140701.66 | BF104: -114560 | BH104: =77075+BH42 -> 71654.517 | BI104: =BY104-BH104 -> 72829.679 | BJ104: =82731+BJ42 -> 76617.656 | BK104: =I104-Z104-AB104-AA104 -> 83053.874 | BL104: =108622+BL42 -> 99779.376 | BN104: 119632.88 | BO104: 129859.55 | BP104: 144546.18 | BQ104: =215031+BQ42 -> 199072.55 | BR104: =232451+BR42 -> 212568.8 | BS104: =222870+BS42 -> 204073.04 | BT104: =215911+BT42 -> 194282.48 | BU104: =222082+BU42 -> 202653.55 | BV104: =231673+BV42 -> 212055.41 | BW104: =221855+BW42 -> 204071.34 | BY104: =153786+BY42 -> 144484.2 | BZ104: =215031+BZ42 -> 199072.55 | CC104: 46925.393 | CD104: 92432.279 | CE104: 139643.04
B105: EBITDA | C105: =SUM(C103+C104) -> 904212.96 | D105: =SUM(D103+D104) -> 1008564.8 | E105: =SUM(E103+E104) -> 1182131.3 | F105: =SUM(F103+F104) -> 1090047.9 | G105: =SUM(G103+G104) -> 1090047.9 | H105: =SUM(H103+H104) -> 1098102 | I105: =SUM(I103+I104) -> 891041.19 | J105: =SUM(J103+J104) -> 812028.72 | ... P105: =SUM(P103+P104) -> 2909666.1 | R105: =SUM(R103+R104) -> 221041.61 | S105: =SUM(S103+S104) -> 249733.98 | T105: =SUM(T103+T104) -> 354803.44 | U105: =SUM(U103+U104) -> 356552.25 | V105: =SUM(V103+V104) -> 247482.78 | W105: =SUM(W103+W104) -> 272055.01 | X105: =SUM(X103+X104) -> 212712.35 | Y105: =SUM(Y103+Y104) -> 357797.74 | ... BF105: =SUM(BF103+BF104) -> 146597.31 | BH105: =SUM(BH103+BH104) -> 205297.82 | BI105: =SUM(BI103+BI104) -> 219533.73 | BJ105: =SUM(BJ103+BJ104) -> 176685.6 | BK105: =SUM(BK103+BK104) -> 133216.79 | BL105: =SUM(BL103+BL104) -> 186438.76 | BN105: =SUM(BN103+BN104) -> 470775.59 | BO105: =SUM(BO103+BO104) -> 519537.79 | BP105: =SUM(BP103+BP104) -> 531714.77 | BQ105: =SUM(BQ103+BQ104) -> 408333.51 | BR105: =SUM(BR103+BR104) -> 107130 | BS105: =SUM(BS103+BS104) -> 515419.39 | BT105: =SUM(BT103+BT104) -> 475101.15 | BU105: =SUM(BU103+BU104) -> 433154.49 | ... BW105: =SUM(BW103+BW104) -> 1123734.8 | BY105: =SUM(BY103+BY104) -> 424831.55 | BZ105: =SUM(BZ103+BZ104) -> 408333.51 | CC105: =SUM(CC103+CC104) -> 197522.51 | CD105: =SUM(CD103+CD104) -> 418602.42 | CE105: =SUM(CE103+CE104) -> 617792.58
B106: % growth | C106: =C105/(2095260.492-79320.118-1241427.742-118483.907+9329.11+134050.782)-1 -> 0.13110234 | D106: =+D105/C105-1 -> 0.11540623 | E106: =+E105/D105-1 -> 0.17209257 | F106: =+F105/E105-1 -> -0.077896074 | G106: =+G105/F105-1 -> -8.8817842e-16 | H106: =+H105/G105-1 -> 0.0073887634 | I106: =+I105/G105-1 -> -0.18256694 | J106: =+J105/I105-1 -> -0.088674317 | K106: =+K105/J105-1 -> -0.28883214 | L106: =+L105/K105-1 -> 1.0854227 | M106: =+M105/L105-1 -> -0.36416764 | N106: =+N105/M105-1 -> 0.23429493 | O106: =+O105/N105-1 -> 0.46678696 | P106: =+P105/O105-1 -> 1.0988285 | R106: =R105/CC105-1 -> 0.1190705 | S106: =S105/(CD105-CC105)-1 -> 0.1296095 | T106: =T105/(CE105-CD105)-1 -> 0.78122975 | U106: =U105/(D105-CE105)-1 -> -0.087570032 | V106: =+V105/R105-1 -> 0.11962079 | W106: =+W105/S105-1 -> 0.08937924 | X106: =+X105/T105-1 -> -0.40047832 | Y106: =+Y105/U105-1 -> 0.0034931514 | Z106: =+Z105/V105-1 -> 0.056839372 | AA106: =+AA105/W105-1 -> -0.0069463599 | AB106: =+AB105/X105-1 -> 0.062983051 | AC106: =+AC105/Y105-1 -> -0.048966606 | AD106: =AD105/BH105-1 -> -0.091861946 | AE106: =+AE105/BI105-1 -> 0.010754675 | AF106: =AF105/BJ105-1 -> -0.026195394 | AG106: =+AG105/AC105-1 -> -0.3192677 | AH106: =AH105/BL105-1 -> -0.24302141 | AI106: =+AI105/AE105-1 -> -1.1532265 | AJ106: =AJ105/AF105-1 -> -0.20795614 | AK106: =+AK105/AG105-1 -> 0.4422586 | AL106: =+AL105/AH105-1 -> 0.70299073 | AM106: =-AM105/AI105-1 -> 7.0904361 | AN106: =AN105/AJ105-1 -> 1.3141396 | AO106: =+AO105/AK105-1 -> 0.11806417 | AP106: =+AP105/AL105-1 -> -0.14065337 | AQ106: =-AQ105/AM105-1 -> -1.9763224 | AR106: =AR105/AN105-1 -> -0.50038405 | AS106: =+AS105/AO105-1 -> -0.64372892 | AT106: =+AT105/AP105-1 -> -0.40167329 | AU106: =-AU105/AQ105-1 -> -2.1527174 | AV106: =AV105/AR105-1 -> -0.079133292 | AW106: =+AW105/AS105-1 -> 1.7570657 | AX106: =+AX105/AT105-1 -> 1.0092368 | AY106: =-AY105/AU105-1 -> -2.1710042 | AZ106: =AZ105/AV105-1 -> 0.75930376 | BA106: =+BA105/AW105-1 -> 0.41797546 | BB106: =+BB105/AX105-1 -> 0.42225519 | BC106: =-BC105/AY105-1 -> -3.1256828 | BD106: =BD105/AZ105-1 -> 0.28169717 | BE106: =+BE105/BA105-1 -> 1.8039403 | BF106: =+BF105/BB105-1 -> -0.58487537 | BH106: =BH105/V105-1 -> -0.17045617 | BI106: =BI105/W105-1 -> -0.19305388 | BJ106: =BJ105/X105-1 -> -0.16936839 | BK106: =+BK105/Y105-1 -> -0.6276757 | BL106: =BL105/BH105-1 -> -0.091861946 | BN106: =BN105/CD105-1 -> 0.12463655 | BO106: =+BO105/BN105-1 -> 0.10357845 | BP106: =+BP105/BO105-1 -> 0.023438091 | BQ106: =+BQ105/BY105-1 -> -0.038834317 | BR106: =+BR105/BZ105-1 -> -0.73764093 | BS106: =(BS105/BR105)-1 -> 3.8111583 | BT106: =(BT105/BS105)-1 -> -0.078224134 | BU106: =(BU105/BT105)-1 -> -0.088289961 | BV106: =(BV105/BU105)-1 -> 0.41014882 | BW106: =(BW105/BV105)-1 -> 0.83973839 | BY106: =+BY105/BO105-1 -> -0.18228942 | BZ106: =+BZ105/BY105-1 -> -0.038834317
B107: % margin | C107: =C105/C8 -> 0.12846891 | D107: =D105/D8 -> 0.13008352 | E107: =E105/E8 -> 0.14966904 | F107: =F105/F8 -> 0.13224491 | G107: =G105/G8 -> 0.13277316 | H107: =H105/H8 -> 0.12943856 | I107: =I105/I8 -> 0.11170271 | J107: =J105/J8 -> 0.10082826 | ... P107: =P105/P8 -> 0.25653034 | R107: =R105/R8 -> 0.11697822 | S107: =S105/S8 -> 0.1281484 | T107: =T105/T8 -> 0.18977934 | U107: =U105/U8 -> 0.16278245 | V107: =V105/V8 -> 0.12678206 | W107: =W105/W8 -> 0.13500398 | X107: =X105/X8 -> 0.10953298 | Y107: =Y105/Y8 -> 0.15333385 | ... BF107: =BF105/BF8 -> 0.052999253 | BH107: =BH105/BH8 -> 0.10878765 | BI107: =BI105/BI8 -> 0.11084117 | BJ107: =BJ105/BJ8 -> 0.094080517 | BK107: =BK105/BK8 -> 0.071795896 | BL107: =BL105/BL8 -> 0.096755779 | BN107: =BN105/BN8 -> 0.12264944 | BO107: =BO105/BO8 -> 0.13095844 | BP107: =BP105/BP8 -> 0.12915747 | BQ107: =BQ105/BQ8 -> 0.10414064 | BR107: =BR105/BR8 -> 0.032016734 | BS107: =BS105/BS8 -> 0.11183697 | BT107: =BT105/BT8 -> 0.091978777 | BU107: =BU105/BU8 -> 0.096371264 | ... BW107: =BW105/BW8 -> 0.21017558 | BY107: =BY105/BY8 -> 0.10983922 | BZ107: =BZ105/BZ8 -> 0.10414064
B108: Adjustment | C108: =C109-C105 -> -8506.959 | D108: =D109-D105 -> -33749.77 | E108: =E109-E105 -> -160726.28 | F108: =F109-F105 -> -5689.996 | G108: =G109-G105 -> -3287.996 | H108: =H109-H105 -> -24080.62 | I108: =I109-I105 -> -24657.243 | J108: =J109-J105 -> -20795.974 | ... P108: =P109-P105 -> -1406736.7 | R108: =R109-R105 -> -1136.24 | S108: =S109-S105 -> 622.711 | T108: =T109-T105 -> -137097.79 | U108: =U109-U105 -> -23114.934 | V108: =V109-V105 -> 5889.312 | W108: =W109-W105 -> -8506.8 | X108: =X109-X105 -> 1261.406 | Y108: =Y109-Y105 -> -4333.914 | ... BF108: =BF109-BF105 -> 207069.62 | BH108: =BH109-BH105 -> 306.86 | BI108: =BI109-BI105 -> 1332.607 | BJ108: =BJ109-BJ105 -> -1760.478 | BK108: =BK109-BK105 -> -25038.163 | BL108: =BL109-BL105 -> 573.903 | BN108: =BN109-BN105 -> -513.587 | BO108: =BO109-BO105 -> -2616.793 | BP108: =BP109-BP105 -> 1730.965 | BQ108: =BQ109-BQ105 -> -8522.393 | BR108: =BR109-BR105 -> -1762.165 | BS108: =BS109-BS105 -> 5761.711 | BT108: =BT109-BT105 -> -85422.696 | BU108: =BU109-BU105 -> -175883.19 | ... BW108: =BW109-BW105 -> -440168.47 | BY108: =BY109-BY105 -> 1639.467 | BZ108: =BZ109-BZ105 -> -8522.393
B109: Adj. EBITDA | C109: 895706 | D109: 974815 | E109: 1021405 | F109: =F129-F125 -> 1084357.9 | G109: =G129-G125 -> 1086759.9 | H109: =H129-H125 -> 1074021.4 | I109: =I129-I125 -> 866383.95 | J109: =J129-J125 -> 791232.75 | K109: =K129-K125 -> 622552.38 | L109: =L129-L125 -> 1233363.9 | M109: =M129-M125 -> 756358.39 | ... P109: =P129-P125 -> 1502929.4 | R109: =R129-R125 -> 219905.37 | S109: =S129-S125 -> 250356.69 | T109: =T129-T125 -> 217705.65 | U109: =U129-U125 -> 333437.32 | V109: =V129-V125 -> 253372.1 | W109: =W129-W125 -> 263548.21 | X109: =X129-X125 -> 213973.76 | Y109: =Y129-Y125 -> 353463.83 | ... BF109: =BF129-BF125 -> 353666.93 | BH109: =BH129-BH125 -> 205604.68 | BI109: =BI129-BI125 -> 220866.34 | BJ109: =BJ129-BJ125 -> 174925.13 | BK109: =BK129-BK125 -> 108178.63 | BL109: =BL129-BL125 -> 187012.66 | BN109: 470262 | BO109: 516921 | BP109: =Z109+AA109 -> 533445.73 | BQ109: =BQ129-BQ125 -> 399811.11 | BR109: =BR129-BR125 -> 105367.83 | BS109: =BS129-BS125 -> 521181.1 | BT109: =BT129-BT125 -> 389678.46 | BU109: =BU129-BU125 -> 257271.3 | BV109: =BV129-BV125 -> 487158.09 | BW109: =BW129-BW125 -> 683566.35 | BY109: =BY129-BY125 -> 426471.02 | BZ109: =BZ129-BZ125 -> 399811.11 | CC109: =CC129-CC125 -> 204798 | CD109: =CD129-CD125 -> 438034.77 | CE109: =CE129-CE125 -> 641521.03
...

Sheet KPIS
BL1: 1H2016 | BM1: 1H2017 | BN1: 1H2018 | BO1: 1H2019 | BP1: 1H2020 | BQ1: 1H2021 | BR1: 1H2022 | BW1: 1H2019
B2: Falabella | D2: Annual | E2: Annual | F2: Annual | G2: Annual | H2: Annual | I2: Annual | J2: Annual | K2: Annual | L2: Annual | M2: Annual | N2: Annual | O2: Annual | P2: Annual | Q2: Annual | S2: Quarterly | T2: Quarterly | U2: Quarterly | V2: Quarterly | W2: Quarterly | X2: Quarterly | Y2: Quarterly | Z2: Quarterly | AA2: Quarterly | AB2: Quarterly | AC2: Quarterly | AD2: Quarterly | AE2: Quarterly | AF2: Quarterly | AG2: Quarterly | AH2: Quarterly | AI2: Quarterly | AJ2: Quarterly | AK2: Quarterly | AL2: Quarterly | AM2: Quarterly | AN2: Quarterly | AO2: Quarterly | AP2: Quarterly | AQ2: Quarterly | AR2: Quarterly | AS2: Quarterly | AT2: Quarterly | AU2: Quarterly | AV2: Quarterly | AW2: Quarterly | AX2: Quarterly | AY2: Quarterly | AZ2: Quarterly | BA2: Quarterly | BB2: Quarterly | BC2: Quarterly | BD2: Quarterly | BE2: Quarterly | BF2: Quarterly | BG2: Quarterly | BH2: Quarterly | BI2: Quarterly | BJ2: Quarterly | BL2: Half year | BM2: Half year | BN2: Half year | BO2: Half year | BP2: Half year | BQ2: Half year | BR2: Half year | BS2: Half year | BT2: Half year | BU2: Half year
D3: 41975 | E3: 42341 | F3: 42708 | G3: 43073 | H3: 43073 | I3: 43438 | J3: 43438 | K3: 43803 | L3: 44169 | M3: 44535 | N3: 44900 | O3: 45265 | P3: 45631 | Q3: 45996 | S3: 42437 | T3: 42527 | U3: 42622 | V3: 42714 | W3: 42801 | X3: 42892 | Y3: 42987 | Z3: 43079 | AA3: 43166 | AB3: 43257 | AC3: 43348 | AD3: 43439 | AE3: 43439 | AF3: 43555 | AG3: 43555 | AH3: 43646 | AI3: 43738 | AJ3: 43830 | AK3: 43921 | AL3: 44012 | AM3: 44104 | AN3: 44104 | AO3: 44196 | AP3: 44286 | AQ3: 44377 | AR3: 44469 | AS3: 44561 | AT3: 44651 | AU3: 44742 | AV3: 44834 | AW3: 44926 | AX3: 45016 | AY3: 45107 | AZ3: 45199 | BA3: 45291 | BB3: 45382 | BC3: 45473 | BD3: 45565 | BE3: 45657 | BF3: 45747 | BG3: 45838 | BH3: 45930 | BI3: 46022 | BJ3: 46112 | BL3: 42530 | BM3: 42896 | BN3: 43261 | BO3: 43646 | BP3: 44012 | BQ3: 44377 | BR3: 44742 | BS3: 45107 | BT3: 45473 | BU3: 45838 | BW3: 43646
D4: Act | E4: Act | F4: Act | G4: Act | H4: Restated | I4: Act | J4: Restated | K4: Act | L4: Act | M4: Act | N4: Act | O4: Act | P4: Act | Q4: Act | S4: Act | T4: Act | U4: Act | V4: Act | W4: Act | X4: Act | Y4: Act | Z4: Act | AA4: Act | AB4: Act | AC4: Act | AD4: Act | AE4: Restated | AF4: Act | AG4: Restated | AH4: Act | AI4: Act | AJ4: Act | AK4: Act | AL4: Act | AM4: Act | AN4: Restated | AO4: Act | AP4: Act | AQ4: Act | AR4: Act | AS4: Act | AT4: Act | AU4: Act | AV4: Act | AW4: Act | AX4: Act | AY4: Act | AZ4: Act | BA4: Act | BB4: Act | BC4: Act | BD4: Act | BE4: Act | BF4: Act | BG4: Act | BH4: Act | BI4: Act | BJ4: Act | BL4: Act | BM4: Act | BN4: Act | BO4: Act | BP4: Act | BQ4: Act | BR4: Act | BS4: Act | BT4: Act | BU4: Act | BW4: Restated
D5: FY | E5: FY | F5: FY | G5: FY | H5: FY | I5: FY | J5: FY | K5: FY | L5: FY | M5: FY | N5: FY | O5: FY | P5: FY | Q5: FY | S5: Q1 | T5: Q2 | U5: Q3 | V5: Q4 | W5: Q1 | X5: Q2 | Y5: Q3 | Z5: Q4 | AA5: Q1 | AB5: Q2 | AC5: Q3 | AD5: Q4 | AE5: Q4 | AF5: Q1 | AG5: Q1 | AH5: Q2 | AI5: Q3 | AJ5: Q4 | AK5: Q1 | AL5: Q2 | AM5: Q3 | AN5: Q3 | AO5: Q4 | AP5: Q1 | AQ5: Q2 | AR5: Q3 | AS5: Q4 | AT5: Q1 | AU5: Q2 | AV5: Q3 | AW5: Q4 | AX5: Q1 | AY5: Q2 | AZ5: Q3 | BA5: Q4 | BB5: Q1 | BC5: Q2 | BD5: Q3 | BE5: Q4 | BF5: Q1 | BG5: Q2 | BH5: Q3 | BI5: Q4 | BJ5: Q1 | BL5: 1H | BM5: 1H | BN5: 1H | BO5: 1H | BP5: 1H | BQ5: 1H | BR5: 1H | BS5: 1H | BT5: 1H | BU5: 1H
B8: Number of stores
B9: Department Stores
B10: Chile | D10: 45 | E10: 45 | F10: 44 | G10: 45 | H10: 45 | I10: 47 | J10: 47 | K10: 47 | L10: 46 | M10: 46 | N10: 47 | O10: 45 | P10: 44 | Q10: 45 | S10: 45 | T10: =BL10 -> 44 | U10: 44 | V10: =F10 -> 44 | W10: 44 | X10: =BM10 -> 44 | Y10: 45 | Z10: =G10 -> 45 | AA10: 45 | AB10: =BN10 -> 46 | AC10: 46 | AD10: =I10 -> 47 | AE10: =J10 -> 47 | AF10: 47 | AG10: 47 | AH10: =BO10 -> 47 | AI10: 47 | AJ10: =K10 -> 47 | AK10: 47 | AL10: =BP10 -> 47 | AM10: 47 | AN10: 47 | AO10: =L10 -> 46 | AP10: 46 | AQ10: =BQ10 -> 46 | AR10: 46 | AS10: =M10 -> 46 | AT10: 46 | AU10: =BR10 -> 46 | AV10: 46 | AW10: =N10 -> 47 | AX10: 47 | AY10: =BS10 -> 46 | AZ10: 46 | BA10: =O10 -> 45 | BB10: 44 | BC10: =BT10 -> 44 | BD10: 44 | BE10: =P10 -> 44 | BF10: 44 | BG10: =BU10 -> 44 | BH10: 44 | BI10: =Q10 -> 45 | BJ10: 45 | BL10: 44 | BM10: 44 | BN10: 46 | BO10: 47 | BP10: 47 | BQ10: 46 | BR10: 46 | BS10: 46 | BT10: 44 | BU10: 44 | BW10: 47
B11: Peru | D11: 25 | E11: 27 | F11: 29 | G11: 29 | H11: 29 | I11: 29 | J11: 29 | K11: 29 | L11: 30 | M11: 31 | N11: 33 | O11: 35 | P11: 35 | Q11: 35 | S11: 28 | T11: =BL11 -> 28 | U11: 28 | V11: =F11 -> 29 | W11: 29 | X11: =BM11 -> 29 | Y11: 29 | Z11: =G11 -> 29 | AA11: 29 | AB11: =BN11 -> 29 | AC11: 29 | AD11: =I11 -> 29 | AE11: =J11 -> 29 | AF11: 29 | AG11: 29 | AH11: =BO11 -> 29 | AI11: 29 | AJ11: =K11 -> 29 | AK11: 29 | AL11: =BP11 -> 29 | AM11: 29 | AN11: 29 | AO11: =L11 -> 30 | AP11: 30 | AQ11: =BQ11 -> 30 | AR11: 31 | AS11: =M11 -> 31 | AT11: 31 | AU11: =BR11 -> 31 | AV11: 33 | AW11: =N11 -> 33 | AX11: 33 | AY11: =BS11 -> 33 | AZ11: 34 | BA11: =O11 -> 35 | BB11: 33 | BC11: =BT11 -> 34 | BD11: 35 | BE11: =P11 -> 35 | BF11: 35 | BG11: =BU11 -> 35 | BH11: 35 | BI11: =Q11 -> 35 | BJ11: 35 | BL11: 28 | BM11: 29 | BN11: 29 | BO11: 29 | BP11: 29 | BQ11: 30 | BR11: 31 | BS11: 33 | BT11: 34 | BU11: 35 | BW11: 29
B12: Argentina | D12: 11 | E12: 11 | F12: 11 | G12: 11 | H12: 11 | I12: 11 | J12: 11 | K12: 10 | L12: 6 | M12: 7 | N12: 0 | O12: 0 | P12: 0 | Q12: 0 | S12: 11 | T12: =BL12 -> 11 | U12: 11 | V12: =F12 -> 11 | W12: 11 | X12: =BM12 -> 11 | Y12: 11 | Z12: =G12 -> 11 | AA12: 11 | AB12: =BN12 -> 11 | AC12: 11 | AD12: =I12 -> 11 | AE12: =J12 -> 11 | AF12: 10 | AG12: 10 | AH12: =BO12 -> 10 | AI12: 10 | AJ12: =K12 -> 10 | AK12: 10 | AL12: =BP12 -> 10 | AM12: 10 | AN12: 10 | AO12: =L12 -> 6 | AP12: 3 | AQ12: =BQ12 -> 0 | AR12: 0 | AS12: =M12 -> 7 | AT12: 0 | AU12: =BR12 -> 0 | AV12: 0 | AW12: =N12 -> 0 | AX12: 0 | AY12: =BS12 -> 0 | AZ12: 0 | BA12: =O12 -> 0 | BB12: 0 | BC12: =BT12 -> 0 | BD12: 0 | BE12: =P12 -> 0 | BF12: 0 | BG12: =BU12 -> 0 | BH12: 0 | BI12: =Q12 -> 0 | BJ12: 0 | BL12: 11 | BM12: 11 | BN12: 11 | BO12: 10 | BP12: 10 | BQ12: 0 | BR12: 0 | BS12: 0 | BT12: 0 | BU12: 0 | BW12: 10
B13: Colombia | D13: 18 | E13: 20 | F13: 25 | G13: 26 | H13: 26 | I13: 27 | J13: 27 | K13: 25 | L13: 26 | M13: 26 | N13: 26 | O13: 26 | P13: 26 | Q13: 25 | S13: 20 | T13: =BL13 -> 21 | U13: 23 | V13: =F13 -> 25 | W13: 25 | X13: =BM13 -> 26 | Y13: 26 | Z13: =G13 -> 26 | AA13: 26 | AB13: =BN13 -> 26 | AC13: 27 | AD13: =I13 -> 27 | AE13: =J13 -> 27 | AF13: 27 | AG13: 27 | AH13: =BO13 -> 25 | AI13: 25 | AJ13: =K13 -> 25 | AK13: 26 | AL13: =BP13 -> 26 | AM13: 26 | AN13: 26 | AO13: =L13 -> 26 | AP13: 26 | AQ13: =BQ13 -> 26 | AR13: 26 | AS13: =M13 -> 26 | AT13: 26 | AU13: =BR13 -> 27 | AV13: 26 | AW13: =N13 -> 26 | AX13: 27 | AY13: =BS13 -> 27 | AZ13: 26 | BA13: =O13 -> 26 | BB13: 26 | BC13: =BT13 -> 26 | BD13: 26 | BE13: =P13 -> 26 | BF13: 25 | BG13: =BU13 -> 25 | BH13: 25 | BI13: =Q13 -> 25 | BJ13: 25 | BL13: 21 | BM13: 26 | BN13: 26 | BO13: 25 | BP13: 26 | BQ13: 26 | BR13: 27 | BS13: 27 | BT13: 26 | BU13: 25 | BW13: 25
B15: Home improvement
B16: Chile | D16: 83 | E16: 86 | F16: 85 | G16: 89 | H16: 89 | I16: 90 | J16: 90 | K16: 89 | L16: 85 | M16: 84 | N16: 85 | O16: 86 | P16: 87 | Q16: 86 | S16: 85 | T16: =BL16 -> 85 | U16: 85 | V16: =F16 -> 85 | W16: 85 | X16: =BM16 -> 85 | Y16: 87 | Z16: =G16 -> 89 | AA16: 89 | AB16: =BN16 -> 90 | AC16: 90 | AD16: =I16 -> 90 | AE16: =J16 -> 90 | AF16: 90 | AG16: 90 | AH16: =BO16 -> 90 | AI16: 89 | AJ16: =K16 -> 89 | AK16: 88 | AL16: =BP16 -> 89 | AM16: 88 | AN16: 88 | AO16: =L16 -> 85 | AP16: 84 | AQ16: =BQ16 -> 84 | AR16: 84 | AS16: =M16 -> 84 | AT16: 85 | AU16: =BR16 -> 85 | AV16: 85 | AW16: =N16 -> 85 | AX16: 86 | AY16: =BS16 -> 86 | AZ16: 86 | BA16: =O16 -> 86 | BB16: 87 | BC16: =BT16 -> 87 | BD16: 87 | BE16: =P16 -> 87 | BF16: 86 | BG16: =BU16 -> 86 | BH16: 86 | BI16: =Q16 -> 86 | BJ16: 86 | BL16: 85 | BM16: 85 | BN16: 90 | BO16: 90 | BP16: 89 | BQ16: 84 | BR16: 85 | BS16: 86 | BT16: 87 | BU16: 86 | BW16: 90
B17: Peru | D17: 56 | E17: 57 | F17: 56 | G17: 56 | H17: 56 | I17: 56 | J17: 56 | K17: 55 | L17: 56 | M17: 56 | N17: 56 | O17: 56 | P17: 55 | Q17: 53 | S17: 56 | T17: =BL17 -> 56 | U17: 56 | V17: =F17 -> 56 | W17: 56 | X17: =BM17 -> 56 | Y17: 56 | Z17: =G17 -> 56 | AA17: 56 | AB17: =BN17 -> 56 | AC17: 56 | AD17: =I17 -> 56 | AE17: =J17 -> 56 | AF17: 56 | AG17: 56 | AH17: =BO17 -> 56 | AI17: 54 | AJ17: =K17 -> 55 | AK17: 55 | AL17: =BP17 -> 55 | AM17: 56 | AN17: 56 | AO17: =L17 -> 56 | AP17: 56 | AQ17: =BQ17 -> 56 | AR17: 56 | AS17: =M17 -> 56 | AT17: 56 | AU17: =BR17 -> 56 | AV17: 56 | AW17: =N17 -> 56 | AX17: 55 | AY17: =BS17 -> 55 | AZ17: 56 | BA17: =O17 -> 56 | BB17: 56 | BC17: =BT17 -> 55 | BD17: 55 | BE17: =P17 -> 55 | BF17: 55 | BG17: =BU17 -> 54 | BH17: 53 | BI17: =Q17 -> 53 | BJ17: 51 | BL17: 56 | BM17: 56 | BN17: 56 | BO17: 56 | BP17: 55 | BQ17: 56 | BR17: 56 | BS17: 55 | BT17: 55 | BU17: 54 | BW17: 56
B18: Argentina | D18: 8 | E18: 8 | F18: 8 | G18: 8 | H18: 8 | I18: 9 | J18: 9 | K18: 9 | L18: 8 | M18: 7 | N18: 7 | O18: 7 | P18: 7 | Q18: 7 | S18: 8 | T18: =BL18 -> 8 | U18: 8 | V18: =F18 -> 8 | W18: 8 | X18: =BM18 -> 8 | Y18: 8 | Z18: =G18 -> 8 | AA18: 8 | AB18: =BN18 -> 8 | AC18: 9 | AD18: =I18 -> 9 | AE18: =J18 -> 9 | AF18: 9 | AG18: 9 | AH18: =BO18 -> 9 | AI18: 9 | AJ18: =K18 -> 9 | AK18: 9 | AL18: =BP18 -> 9 | AM18: 9 | AN18: 9 | AO18: =L18 -> 8 | AP18: 7 | AQ18: =BQ18 -> 7 | AR18: 7 | AS18: =M18 -> 7 | AT18: 7 | AU18: =BR18 -> 7 | AV18: 7 | AW18: =N18 -> 7 | AX18: 7 | AY18: =BS18 -> 7 | AZ18: 7 | BA18: =O18 -> 7 | BB18: 7 | BC18: =BT18 -> 7 | BD18: 7 | BE18: =P18 -> 7 | BF18: 7 | BG18: =BU18 -> 7 | BH18: 7 | BI18: =Q18 -> 7 | BJ18: 7 | BL18: 8 | BM18: 8 | BN18: 8 | BO18: 9 | BP18: 9 | BQ18: 7 | BR18: 7 | BS18: 7 | BT18: 7 | BU18: 7 | BW18: 9
B19: Colombia | D19: 34 | E19: 36 | F19: 38 | G19: 38 | H19: 38 | I19: 40 | J19: 40 | K19: 40 | L19: 40 | M19: 40 | N19: 40 | O19: 41 | P19: 42 | Q19: 42 | S19: 35 | T19: =BL19 -> 35 | U19: 35 | V19: =F19 -> 38 | W19: 38 | X19: =BM19 -> 38 | Y19: 38 | Z19: =G19 -> 38 | AA19: 38 | AB19: =BN19 -> 38 | AC19: 40 | AD19: =I19 -> 40 | AE19: =J19 -> 40 | AF19: 40 | AG19: 40 | AH19: =BO19 -> 40 | AI19: 40 | AJ19: =K19 -> 40 | AK19: 40 | AL19: =BP19 -> 40 | AM19: 40 | AN19: 40 | AO19: =L19 -> 40 | AP19: 40 | AQ19: =BQ19 -> 40 | AR19: 40 | AS19: =M19 -> 40 | AT19: 40 | AU19: =BR19 -> 40 | AV19: 40 | AW19: =N19 -> 40 | AX19: 40 | AY19: =BS19 -> 40 | AZ19: 41 | BA19: =O19 -> 41 | BB19: 42 | BC19: =BT19 -> 42 | BD19: 42 | BE19: =P19 -> 42 | BF19: 42 | BG19: =BU19 -> 42 | BH19: 42 | BI19: =Q19 -> 42 | BJ19: 42 | BL19: 35 | BM19: 38 | BN19: 38 | BO19: 40 | BP19: 40 | BQ19: 40 | BR19: 40 | BS19: 40 | BT19: 42 | BU19: 42 | BW19: 40
B20: Brazil | D20: 57 | E20: 58 | F20: 56 | G20: 57 | H20: 57 | I20: 53 | J20: 53 | K20: 53 | L20: 53 | M20: 52 | N20: 55 | O20: 54 | P20: 52 | Q20: 51 | S20: 57 | T20: =BL20 -> 57 | U20: 57 | V20: =F20 -> 56 | W20: 55 | X20: =BM20 -> 56 | Y20: 56 | Z20: =G20 -> 57 | AA20: 57 | AB20: =BN20 -> 57 | AC20: 53 | AD20: =I20 -> 53 | AE20: =J20 -> 53 | AF20: 53 | AG20: 53 | AH20: =BO20 -> 53 | AI20: 53 | AJ20: =K20 -> 53 | AK20: 53 | AL20: =BP20 -> 53 | AM20: 53 | AN20: 53 | AO20: =L20 -> 53 | AP20: 53 | AQ20: =BQ20 -> 52 | AR20: 53 | AS20: =M20 -> 52 | AT20: 53 | AU20: =BR20 -> 53 | AV20: 53 | AW20: =N20 -> 55 | AX20: 55 | AY20: =BS20 -> 54 | AZ20: 54 | BA20: =O20 -> 54 | BB20: 54 | BC20: =BT20 -> 54 | BD20: 54 | BE20: =P20 -> 52 | BF20: 52 | BG20: =BU20 -> 52 | BH20: 52 | BI20: =Q20 -> 51 | BJ20: 51 | BL20: 57 | BM20: 56 | BN20: 57 | BO20: 53 | BP20: 53 | BQ20: 52 | BR20: 53 | BS20: 54 | BT20: 54 | BU20: 52 | BW20: 53
B21: Uruguay | D21: 0 | E21: 2 | F21: 3 | G21: 3 | H21: 3 | I21: 3 | J21: 3 | K21: 3 | L21: 3 | M21: 4 | N21: 4 | O21: 4 | P21: 4 | Q21: 4 | S21: 2 | T21: =BL21 -> 2 | U21: 2 | V21: =F21 -> 3 | W21: 3 | X21: =BM21 -> 3 | Y21: 3 | Z21: =G21 -> 3 | AA21: 3 | AB21: =BN21 -> 3 | AC21: 3 | AD21: =I21 -> 3 | AE21: =J21 -> 3 | AF21: 3 | AG21: 3 | AH21: =BO21 -> 3 | AI21: 3 | AJ21: =K21 -> 3 | AK21: 3 | AL21: =BP21 -> 3 | AM21: 3 | AN21: 3 | AO21: =L21 -> 3 | AP21: 3 | AQ21: =BQ21 -> 4 | AR21: 4 | AS21: =M21 -> 4 | AT21: 4 | AU21: =BR21 -> 4 | AV21: 4 | AW21: =N21 -> 4 | AX21: 4 | AY21: =BS21 -> 4 | AZ21: 4 | BA21: =O21 -> 4 | BB21: 4 | BC21: =BT21 -> 4 | BD21: 4 | BE21: =P21 -> 4 | BF21: 4 | BG21: =BU21 -> 4 | BH21: 4 | BI21: =Q21 -> 4 | BJ21: 4 | BL21: 2 | BM21: 3 | BN21: 3 | BO21: 3 | BP21: 3 | BQ21: 4 | BR21: 4 | BS21: 4 | BT21: 4 | BU21: 4 | BW21: 3
B22: Mexico | H22: 0 | I22: 3 | J22: 3 | K22: 5 | L22: 6 | M22: 9 | N22: 12 | O22: 13 | P22: 15 | Q22: 15 | AC22: 1 | AD22: =I22 -> 3 | AE22: =J22 -> 3 | AF22: 3 | AG22: 3 | AH22: =BO22 -> 3 | AI22: 3 | AJ22: =K22 -> 5 | AK22: 6 | AL22: =BP22 -> 6 | AM22: 6 | AN22: 6 | AO22: =L22 -> 6 | AP22: 6 | AQ22: =BQ22 -> 7 | AR22: 8 | AS22: =M22 -> 9 | AT22: 9 | AU22: =BR22 -> 10 | AV22: 10 | AW22: =N22 -> 12 | AX22: 12 | AY22: =BS22 -> 12 | AZ22: 13 | BA22: =O22 -> 13 | BB22: 13 | BC22: =BT22 -> 14 | BD22: 14 | BE22: =P22 -> 15 | BF22: 15 | BG22: =BU22 -> 15 | BH22: 15 | BI22: =Q22 -> 15 | BJ22: 15 | BO22: 3 | BP22: 6 | BQ22: 7 | BR22: 10 | BS22: 12 | BT22: 14 | BU22: 15 | BW22: 3
B24: Supermarkets
B25: Chile | D25: 52 | E25: 57 | F25: 61 | G25: 64 | H25: 64 | I25: 67 | J25: 67 | K25: 69 | L25: 67 | M25: 70 | N25: 72 | O25: 72 | P25: 73 | Q25: 71 | S25: 57 | T25: =BL25 -> 59 | U25: 61 | V25: =F25 -> 61 | W25: 61 | X25: =BM25 -> 62 | Y25: 63 | Z25: =G25 -> 64 | AA25: 65 | AB25: =BN25 -> 66 | AC25: 66 | AD25: =I25 -> 67 | AE25: =J25 -> 67 | AF25: 67 | AG25: 67 | AH25: =BO25 -> 68 | AI25: 68 | AJ25: =K25 -> 69 | AK25: 70 | AL25: =BP25 -> 70 | AM25: 70 | AN25: 70 | AO25: =L25 -> 67 | AP25: 67 | AQ25: =BQ25 -> 68 | AR25: 69 | AS25: =M25 -> 70 | AT25: 72 | AU25: =BR25 -> 72 | AV25: 72 | AW25: =N25 -> 72 | AX25: 72 | AY25: =BS25 -> 72 | AZ25: 72 | BA25: =O25 -> 72 | BB25: 72 | BC25: =BT25 -> 72 | BD25: 0 | BE25: =P25 -> 73 | BF25: 71 | BG25: =BU25 -> 71 | BH25: 71 | BI25: =Q25 -> 71 | BJ25: 71 | BL25: 59 | BM25: 62 | BN25: 66 | BO25: 68 | BP25: 70 | BQ25: 68 | BR25: 72 | BS25: 72 | BT25: 72 | BU25: 71 | BW25: 68
B26: Peru | D26: 49 | E26: 52 | F26: 60 | G26: 65 | H26: 65 | I26: 69 | J26: 69 | K26: 77 | L26: 81 | M26: 85 | N26: 88 | O26: 89 | P26: 90 | Q26: 91 | S26: 54 | T26: =BL26 -> 55 | U26: 57 | V26: =F26 -> 60 | W26: 60 | X26: =BM26 -> 61 | Y26: 61 | Z26: =G26 -> 65 | AA26: 67 | AB26: =BN26 -> 66 | AC26: 68 | AD26: =I26 -> 69 | AE26: =J26 -> 69 | AF26: 70 | AG26: 70 | AH26: =BO26 -> 71 | AI26: 73 | AJ26: =K26 -> 77 | AK26: 78 | AL26: =BP26 -> 78 | AM26: 79 | AN26: 79 | AO26: =L26 -> 81 | AP26: 81 | AQ26: =BQ26 -> 83 | AR26: 84 | AS26: =M26 -> 85 | AT26: 85 | AU26: =BR26 -> 87 | AV26: 88 | AW26: =N26 -> 88 | AX26: 88 | AY26: =BS26 -> 88 | AZ26: 89 | BA26: =O26 -> 89 | BB26: 89 | BC26: =BT26 -> 89 | BD26: 0 | BE26: =P26 -> 90 | BF26: 90 | BG26: =BU26 -> 90 | BH26: 90 | BI26: =Q26 -> 91 | BJ26: 91 | BL26: 55 | BM26: 61 | BN26: 66 | BO26: 71 | BP26: 78 | BQ26: 83 | BR26: 87 | BS26: 88 | BT26: 89 | BU26: 90 | BW26: 71
B28: IKEA | L28: 0 | M28: 0 | N28: 0 | O28: 1 | P28: 3 | Q28: =3+2 -> 5 | AP28: 0 | AQ28: =BQ28 -> 0 | AR28: 0 | AS28: =M28 -> 0 | AT28: 0 | AU28: =BR28 -> 0 | AV28: 1 | AW28: =N28 -> 0 | AX28: 0 | AY28: =BS28 -> 2 | AZ28: 2 | BA28: =O28 -> 1 | BB28: 1 | BC28: =BT28 -> 2 | BD28: 2 | BE28: =P28 -> 3 | BF28: 5 | BG28: =BU28 -> 5 | BH28: =2+3 -> 5 | BI28: =Q28 -> 5 | BJ28: 5 | BO28: 0 | BP28: 0 | BQ28: 0 | BR28: 0 | BS28: 2 | BT28: 2 | BU28: 5
B30: Same store sales | D30: 41975 | E30: 42341 | F30: 42708 | G30: =G3 -> 43073 | H30: =H3 -> 43073 | I30: =I3 -> 43438 | J30: =J3 -> 43438 | K30: =K3 -> 43803 | L30: =L3 -> 44169 | M30: 44535 | N30: 44900 | O30: 45265 | P30: =P3 -> 45631 | Q30: =Q3 -> 45996 | S30: 42437 | T30: 42527 | U30: 42622 | V30: 42714 | W30: 42801 | X30: 42892 | Y30: 42987 | Z30: 43079 | AA30: =AA3 -> 43166 | AB30: =AB3 -> 43257 | AC30: =AC3 -> 43348 | AD30: =AD3 -> 43439 | AE30: =AE3 -> 43439 | AF30: =AF3 -> 43555 | AG30: =AG3 -> 43555 | AH30: =AH3 -> 43646 | ... BJ30: =BJ3 -> 46112 | BL30: 42530 | BM30: 42896 | BN30: =BN3 -> 43261 | BO30: =BO3 -> 43646 | BP30: =BP3 -> 44012 | BQ30: =BQ3 -> 44377 | BR30: =BR3 -> 44742 | BS30: =BS3 -> 45107 | BT30: =BT3 -> 45473 | BU30: =BU3 -> 45838 | BW30: =BW3 -> 43646
B32: Department Stores
B33: Chile | D33: 0.015 | E33: 0.061 | F33: 0.101 | G33: 0.048 | H33: 0.048 | I33: -0.036 | J33: -0.036 | K33: -0.028 | S33: 0.131 | T33: 0.096 | U33: 0.133 | V33: 0.066 | W33: 0.081 | X33: 0.06 | Y33: 0.047 | Z33: 0.017 | AA33: -0.049 | AB33: 0.002 | AC33: -0.072 | AD33: -0.033 | AE33: -0.033 | AF33: -0.03 | AG33: -0.03 | AH33: -0.012 | AI33: -0.035 | AJ33: -0.036 | AK33: N/A | AL33: N/A | AM33: -0.05 | AN33: -0.05 | AO33: 0.227 | AP33: 0.301 | AQ33: N/A | AR33: N/A | AS33: 0.155 | AT33: N/A | AU33: N/A | AV33: -0.33 | AW33: -0.198 | AX33: -0.117 | AY33: -0.088 | AZ33: -0.018 | BA33: -0.013 | BB33: 0.064 | BL33: 0.113 | BM33: 0.07 | BN33: 0.002
B34: Peru | D34: -0.007 | E34: -0.012 | F34: -0.016 | G34: 0.003 | H34: 0.003 | I34: 0.054 | J34: 0.054 | K34: -0.009 | S34: 0.014 | T34: 0.014 | U34: -0.02 | V34: -0.05 | W34: -0.059 | X34: 0.05 | Y34: -0.008 | Z34: 0.014 | AA34: 0.121 | AB34: 0.084 | AC34: 0.038 | AD34: 0.003 | AE34: 0.003 | AF34: 0.003 | AG34: 0.003 | AH34: -0.044 | AI34: 0.046 | AJ34: -0.028 | AK34: N/A | AL34: N/A | AM34: -0.262 | AN34: -0.262 | AO34: -0.012 | AP34: N/A | AQ34: N/A | AR34: N/A | AS34: 0.154 | AT34: N/A | AU34: N/A | AV34: 0.016 | AW34: -0.028 | AX34: -0.007 | AY34: -0.11 | AZ34: -0.141 | BA34: -0.083 | BB34: -0.049 | BL34: 0.014 | BM34: 0.002 | BN34: 0.084
B35: Argentina | D35: 0.247 | E35: 0.164 | F35: 0.215 | G35: 0.236 | H35: 0.236 | I35: 0.324 | J35: 0.324 | K35: 0.358 | S35: 0.242 | T35: 0.29 | U35: 0.169 | V35: 0.178 | W35: 0.165 | X35: 0.204 | Y35: 0.254 | Z35: 0.299 | AA35: 0.383 | AB35: 0.367 | AC35: 0.307 | AD35: 0.272 | AE35: 0.272 | AF35: 0.202 | AG35: 0.202 | AH35: 0.234 | AI35: 0.361 | AJ35: 0.562 | AK35: N/A | AL35: N/A | AM35: 0.357 | AN35: 0.357 | AO35: 0.224 | AP35: N/A | AQ35: N/A | AR35: - | AT35: N/A | AU35: N/A | AV35: N/A | AX35: N/A | AY35: N/A | AZ35: N/A | BA35: N/A | BB35: N/A | BL35: 0.269 | BM35: 0.188 | BN35: 0.367
B36: Colombia | D36: 0.078 | E36: -0.01 | F36: 0 | G36: -0.009 | H36: -0.009 | I36: 0.105 | J36: 0.105 | K36: 0.091 | S36: -0.018 | T36: 0 | U36: -0.101 | V36: 0.069 | W36: -0.024 | X36: -0.044 | Y36: 0.004 | Z36: 0.012 | AA36: 0.006 | AB36: 0.119 | AC36: 0.15 | AD36: 0.099 | AE36: 0.099 | AF36: 0.098 | AG36: 0.098 | AH36: 0.09 | AI36: 0.095 | AJ36: 0.086 | AK36: N/A | AL36: N/A | AM36: -0.314 | AN36: -0.314 | AO36: -0.215 | AP36: N/A | AQ36: N/A | AR36: N/A | AS36: 0.293 | AT36: 0.267 | AU36: 0.458 | AV36: 0.091 | AW36: 6,0% | AX36: 0.013 | AY36: -0.093 | AZ36: -0.061 | BA36: -0.036 | BB36: -0.058 | BL36: -0.008 | BM36: -0.035 | BN36: 0.119
B38: Home improvement
B39: Chile | D39: 0.053 | E39: 0.068 | F39: 0.011 | G39: 0.016 | H39: 0.016 | I39: 0.024 | J39: 0.024 | K39: -0.031 | L39: 0.065 | S39: 0.059 | T39: 0.05 | U39: 0.073 | V39: -0.082 | W39: -0.017 | X39: -0.024 | Y39: -0.025 | Z39: 0.139 | AA39: 0.046 | AB39: 0.058 | AC39: 0.019 | AD39: -0.02 | AE39: -0.02 | AF39: -0.017 | AG39: -0.017 | AH39: -0.042 | AI39: -0.007 | AJ39: -0.061 | AK39: -0.051 | AL39: -0.097 | AM39: 0.226 | AN39: 0.226 | AO39: 0.337 | AP39: 0.319 | AQ39: 0.852 | AR39: 0.329 | AS39: 0.229 | AT39: 0.16 | AU39: -0.044 | AV39: -0.21 | AW39: -0.231 | AX39: -0.212 | AY39: -0.233 | AZ39: -0.18 | BA39: -0.132 | BB39: -0.062 | BL39: 0.054 | BM39: -0.021 | BN39: 0.058
B40: Peru | D40: -0.034 | E40: -0.034 | F40: -0.048 | G40: 0.027 | H40: 0.027 | I40: 0.026 | J40: 0.026 | K40: 0.015 | S40: -0.038 | T40: -0.044 | U40: -0.053 | V40: -0.056 | W40: -0.026 | X40: 0.036 | Y40: 0.055 | Z40: 0.045 | AA40: 0.06 | AB40: 0.01 | AC40: 0.029 | AD40: 0.037 | AE40: 0.037 | AF40: 0.017 | AG40: 0.017 | AH40: 0.034 | AI40: 0.021 | AJ40: -0.007 | AK40: N/A | AL40: N/A | AM40: 0.147 | AN40: 0.153 | AO40: 0.118 | AP40: N/A | AQ40: N/A | AR40: N/A | AS40: 0.088 | AT40: 0.096 | AU40: N/A | AV40: -0.135 | AW40: -0.137 | AX40: -0.1 | AY40: -0.153 | AZ40: -0.157 | BA40: -0.159 | BB40: -0.156 | BL40: -0.041 | BM40: 0.003 | BN40: 0.01
B41: Argentina | D41: 0.261 | E41: 0.377 | F41: 0.213 | G41: 0.236 | H41: 0.236 | I41: 0.232 | J41: 0.232 | K41: 0.222 | S41: 0.291 | T41: 0.281 | U41: 0.222 | V41: 0.112 | W41: 0.141 | X41: 0.189 | Y41: 0.23 | Z41: 0.299 | AA41: 0.256 | AB41: 0.234 | AC41: 0.264 | AD41: 0.185 | AE41: 0.185 | AF41: 0.181 | AG41: 0.181 | AH41: 0.135 | AI41: 0.166 | AJ41: 0.368 | AK41: N/A | AL41: N/A | AM41: -0.089 | AN41: -0.089 | AO41: 0.3 | AP41: N/A | AQ41: 1.914 | AR41: 1.22 | AS41: 0.403 | AT41: 0.482 | AU41: 0.575 | AV41: 0.696 | AW41: 0.76 | AX41: 0.971 | AY41: 1.094 | AZ41: 1.123 | BA41: 1.987 | BB41: 1.858 | BL41: 0.279 | BM41: 0.164 | BN41: 0.234
B42: Colombia | D42: 0.06 | E42: 0.116 | F42: 0.046 | G42: -0.048 | H42: -0.048 | I42: 0.039 | J42: 0.039 | K42: 0.081 | S42: 0.085 | T42: 0.085 | U42: 0.01 | V42: 0.015 | W42: -0.027 | X42: -0.071 | Y42: -0.042 | Z42: -0.054 | AA42: -0.009 | AB42: 0.046 | AC42: 0.038 | AD42: 0.077 | AE42: 0.077 | AF42: 0.078 | AG42: 0.078 | AH42: 0.081 | AI42: 0.081 | AJ42: 0.082 | AK42: N/A | AL42: N/A | AM42: 0.012 | AN42: 0.012 | AO42: 0.159 | AP42: N/A | AQ42: N/A | AR42: 0.303 | AS42: 0.143 | AT42: 0.163 | AU42: 0.292 | AV42: 0.077 | AW42: 0.042 | AX42: 0.038 | AY42: -0.052 | AZ42: -0.066 | BA42: -0.063 | BB42: -0.035 | BL42: 0.085 | BM42: -0.049 | BN42: 0.046
B43: Brazil | D43: -0.031 | E43: -0.04 | F43: -0.069 | G43: 0.024 | H43: 0.024 | I43: 0.031 | J43: 0.031 | K43: 0.108 | L43: 0.214 | S43: -0.104 | T43: -0.084 | U43: -0.085 | V43: -0.002 | W43: -0.03 | X43: -0.01 | Y43: 0.106 | Z43: 0.032 | AA43: 0.079 | AB43: -0.013 | AC43: -0.02 | AD43: 0.088 | AE43: 0.088 | AF43: 0.081 | AG43: 0.081 | AH43: 0.182 | AI43: 0.118 | AJ43: 0.066 | AK43: -0.036 | AL43: 0.195 | AM43: 0.369 | AN43: 0.369 | AO43: 0.305 | AP43: 0.353 | AQ43: N/A | AR43: 0.097 | AS43: -0.012 | AT43: 0.081 | AU43: N/A | AV43: -0.11 | AW43: -0.093 | AX43: -0.158 | AY43: -0.196 | AZ43: -0.118 | BA43: 0.016 | BB43: 0.059 | BL43: -0.094 | BM43: -0.02 | BN43: -0.013
B44: Uruguay
B46: Supermarkets
B47: Chile | D47: 0.055 | E47: 0.036 | F47: 0.003 | G47: 0.014 | H47: 0.014 | I47: 0.011 | J47: 0.011 | K47: -0.008 | L47: 0.121 | S47: 0.025 | T47: -0.007 | U47: 0.023 | V47: -0.024 | W47: -0.02 | X47: 0.035 | Y47: 0.015 | Z47: 0.026 | AA47: 0.017 | AB47: 0.019 | AC47: 0.026 | AD47: -0.012 | AE47: -0.012 | AF47: 0.015 | AG47: 0.015 | AH47: -0.024 | AI47: -0.012 | AJ47: -0.009 | AK47: 0.053 | AL47: 0.071 | AM47: 0.133 | AN47: 0.133 | AO47: 0.259 | AP47: 0.1 | AQ47: 0.193 | AR47: 0.078 | AS47: 0.041 | AT47: 0.04 | AU47: -0.057 | AV47: -0.015 | AW47: -0.034 | AX47: 0.002 | AY47: 0 | AZ47: -0.047 | BA47: -0.034 | BB47: -0.017 | BL47: 0.009 | BM47: 0.006 | BN47: 0.019
B48: Peru | D48: 0.051 | E48: 0.007 | F48: -0.015 | G48: 0.003 | H48: 0.003 | I48: 0.06 | J48: 0.06 | K48: 0.022 | S48: 0.003 | T48: -0.029 | U48: -0.017 | V48: -0.014 | W48: -0.01 | X48: 0.006 | Y48: 0.002 | Z48: 0.01 | AA48: 0.048 | AB48: 0.103 | AC48: 0.061 | AD48: 0.035 | AE48: 0.035 | AF48: 0.039 | AG48: 0.039 | AH48: -0.005 | AI48: 0.027 | AJ48: 0.025 | AK48: 0.049 | AL48: N/A | AM48: 0.197 | AN48: 0.197 | AO48: 0.177 | AP48: 0.102 | AQ48: 0.032 | AR48: 0.03 | AS48: -0.02 | AT48: -0.028 | AU48: -0.009 | AV48: -0.065 | AW48: -0.004 | AX48: 0.011 | AY48: -0.028 | AZ48: -0.081 | BA48: -0.004 | BB48: -0.019 | BL48: -0.014 | BM48: -0.002 | BN48: 0.103
B50: Real estate | D50: 41975 | E50: 42341 | F50: 42708 | G50: =G3 -> 43073 | H50: =H3 -> 43073 | I50: =I3 -> 43438 | J50: =J3 -> 43438 | K50: =K3 -> 43803 | L50: =L3 -> 44169 | M50: 44535 | N50: 44900 | O50: 45265 | P50: =P30 -> 45631 | Q50: =Q30 -> 45996 | S50: 42437 | T50: 42527 | U50: 42622 | V50: 42714 | W50: 42801 | X50: 42892 | Y50: 42987 | Z50: 43079 | AA50: =AA3 -> 43166 | AB50: =AB3 -> 43257 | AC50: =AC3 -> 43348 | AD50: =AD3 -> 43439 | AE50: =AE3 -> 43439 | AF50: =AF3 -> 43555 | AG50: =AG3 -> 43555 | AH50: =AH3 -> 43646 | ... BJ50: =BJ3 -> 46112 | BL50: 42530 | BM50: =BM3 -> 42896 | BN50: =BN3 -> 43261 | BO50: =BO3 -> 43646 | BP50: =BP3 -> 44012 | BQ50: =BQ3 -> 44377 | BR50: =BR3 -> 44742 | BS50: =BS3 -> 45107 | BT50: =BT3 -> 45473 | BU50: =BU3 -> 45838 | BW50: =BW3 -> 43646
B52: Number of stores
B54: Mall Plaza – Chile | D54: 15 | E54: 15 | F54: 15 | G54: 17 | H54: 16 | I54: 17 | J54: 17 | K54: 17 | L54: 17 | M54: 17 | N54: 17 | O54: 17 | P54: 17 | Q54: 17 | S54: 15 | T54: =BL54 -> 15 | U54: 15 | V54: =F54 -> 15 | W54: 15 | X54: =BM54 -> 15 | Y54: 16 | Z54: =G54 -> 17 | AA54: 17 | AB54: =BN54 -> 17 | AC54: 17 | AD54: =I54 -> 17 | AE54: =J54 -> 17 | AF54: 17 | AG54: 17 | AH54: =BO54 -> 17 | AI54: 17 | AJ54: =K54 -> 17 | AK54: 17 | AL54: =BP54 -> 17 | AM54: 17 | AN54: 17 | AO54: =L54 -> 17 | AP54: 17 | AQ54: =BQ54 -> 17 | AR54: 17 | AS54: =M54 -> 17 | AT54: 17 | AU54: =BR54 -> 17 | AV54: 17 | AW54: =N54 -> 17 | AX54: 17 | AY54: =BS54 -> 17 | AZ54: 17 | BA54: =O54 -> 17 | BB54: 17 | BC54: =BT54 -> 17 | BD54: 17 | BE54: =P54 -> 17 | BF54: 17 | BG54: =BU54 -> 17 | BH54: 17 | BI54: =Q54 -> 17 | BJ54: 17 | BL54: 15 | BM54: 15 | BN54: 17 | BO54: 17 | BP54: 17 | BQ54: 17 | BR54: 17 | BS54: 17 | BT54: 17 | BU54: 17 | BW54: 17
B55: Open – Chile | D55: 10 | E55: 10 | F55: 10 | G55: 10 | H55: 10 | I55: 10 | J55: 10 | K55: 9 | L55: 9 | M55: 10 | N55: 10 | O55: 10 | P55: 10 | Q55: 9 | S55: 10 | T55: =BL55 -> 10 | U55: 10 | V55: =F55 -> 10 | W55: 10 | X55: =BM55 -> 10 | Y55: 10 | Z55: =G55 -> 10 | AA55: 10 | AB55: =BN55 -> 10 | AC55: 10 | AD55: =I55 -> 10 | AE55: =J55 -> 10 | AF55: 10 | AG55: 10 | AH55: =BO55 -> 9 | AI55: 9 | AJ55: =K55 -> 9 | AK55: 9 | AL55: =BP55 -> 9 | AM55: 9 | AN55: 9 | AO55: =L55 -> 9 | AP55: 10 | AQ55: =BQ55 -> 10 | AR55: 10 | AS55: =M55 -> 10 | AT55: 10 | AU55: =BR55 -> 10 | AV55: 10 | AW55: =N55 -> 10 | AX55: 10 | AY55: =BS55 -> 10 | AZ55: 10 | BA55: =O55 -> 10 | BB55: 10 | BC55: =BT55 -> 10 | BD55: 10 | BE55: =P55 -> 10 | BF55: 10 | BG55: =BU55 -> 9 | BH55: 9 | BI55: =Q55 -> 9 | BJ55: 9 | BL55: 10 | BM55: 10 | BN55: 10 | BO55: 9 | BP55: 9 | BQ55: 10 | BR55: 10 | BS55: 10 | BT55: 10 | BU55: 9 | BW55: 9
B56: Aventura Plaza – Peru | D56: 4 | E56: 4 | F56: 2 | G56: 3 | H56: 3 | I56: 3 | J56: 3 | K56: 3 | L56: 4 | M56: 4 | N56: 4 | O56: 4 | P56: - | Q56: - | S56: 4 | T56: =BL56 -> 4 | U56: 2 | V56: =F56 -> 2 | W56: 2 | X56: =BM56 -> 3 | Y56: 3 | Z56: =G56 -> 3 | AA56: 3 | AB56: =BN56 -> 3 | AC56: 3 | AD56: =I56 -> 3 | AE56: =J56 -> 3 | AF56: 3 | AG56: 3 | AH56: =BO56 -> 3 | AI56: 3 | AJ56: =K56 -> 3 | AK56: 3 | AL56: =BP56 -> 3 | AM56: 4 | AN56: 4 | AO56: =L56 -> 4 | AP56: 4 | AQ56: =BQ56 -> 4 | AR56: 4 | AS56: =M56 -> 4 | AT56: 4 | AU56: =BR56 -> 4 | AV56: 4 | AW56: =N56 -> 4 | AX56: 4 | AY56: =BS56 -> 4 | AZ56: 4 | BA56: =O56 -> 4 | BB56: 4 | BC56: =BT56 -> 4 | BD56: 4 | BE56: =P56 -> - | BG56: =BU56 -> 0 | BH56: 0 | BI56: =Q56 -> - | BL56: 4 | BM56: 3 | BN56: 3 | BO56: 3 | BP56: 3 | BQ56: 4 | BR56: 4 | BS56: 4 | BT56: 4 | BW56: 3
B57: Open Plaza – Peru | D57: 8 | E57: 10 | F57: 11 | G57: 11 | H57: 11 | I57: 11 | J57: 11 | K57: 11 | L57: 11 | M57: 11 | N57: 11 | O57: 11 | P57: - | Q57: - | S57: 10 | T57: =BL57 -> 10 | U57: 10 | V57: =F57 -> 11 | W57: 11 | X57: =BM57 -> 11 | Y57: 11 | Z57: =G57 -> 11 | AA57: 11 | AB57: =BN57 -> 11 | AC57: 11 | AD57: =I57 -> 11 | AE57: =J57 -> 11 | AF57: 11 | AG57: 11 | AH57: =BO57 -> 11 | AI57: 11 | AJ57: =K57 -> 11 | AK57: 11 | AL57: =BP57 -> 11 | AM57: 11 | AN57: 11 | AO57: =L57 -> 11 | AP57: 11 | AQ57: =BQ57 -> 11 | AR57: 11 | AS57: =M57 -> 11 | AT57: 11 | AU57: =BR57 -> 11 | AV57: 11 | AW57: =N57 -> 11 | AX57: 11 | AY57: =BS57 -> 11 | AZ57: 11 | BA57: =O57 -> 11 | BB57: 11 | BC57: =BT57 -> 11 | BD57: 11 | BE57: =P57 -> - | BG57: =BU57 -> 0 | BH57: 0 | BI57: =Q57 -> - | BL57: 10 | BM57: 11 | BN57: 11 | BO57: 11 | BP57: 11 | BQ57: 11 | BR57: 11 | BS57: 11 | BT57: 11 | BW57: 11
B58: Mall Plaza – Peru | P58: 15 | Q58: 15 | BE58: =P58 -> 15 | BF58: 15 | BG58: =BU58 -> 15 | BH58: 15 | BI58: =Q58 -> 15 | BJ58: 15 | BU58: 15
B59: Mall Plaza – Colombia | D59: 1 | E59: 1 | F59: 1 | G59: 1 | H59: 1 | I59: 2 | J59: 2 | K59: 3 | L59: 4 | M59: 4 | N59: 4 | O59: 4 | P59: 5 | Q59: 5 | S59: 1 | T59: =BL59 -> 1 | U59: 1 | V59: =F59 -> 1 | W59: 1 | X59: =BM59 -> 1 | Y59: 1 | Z59: =G59 -> 1 | AA59: 1 | AB59: =BN59 -> 1 | AC59: 2 | AD59: =I59 -> 2 | AE59: =J59 -> 2 | AF59: 2 | AG59: 2 | AH59: =BO59 -> 2 | AI59: 2 | AJ59: =K59 -> 3 | AK59: 3 | AL59: =BP59 -> 3 | AM59: 4 | AN59: 4 | AO59: =L59 -> 4 | AP59: 4 | AQ59: =BQ59 -> 4 | AR59: 4 | AS59: =M59 -> 4 | AT59: 4 | AU59: =BR59 -> 4 | AV59: 4 | AW59: =N59 -> 4 | AX59: 4 | AY59: =BS59 -> 4 | AZ59: 4 | BA59: =O59 -> 4 | BB59: 5 | BC59: =BT59 -> 5 | BD59: 5 | BE59: =P59 -> 5 | BF59: 5 | BG59: =BU59 -> 5 | BH59: 5 | BI59: =Q59 -> 5 | BJ59: 5 | BL59: 1 | BM59: 1 | BN59: 1 | BO59: 2 | BP59: 3 | BQ59: 4 | BR59: 4 | BS59: 4 | BT59: 5 | BU59: 5 | BW59: 2
B60: Total | D60: =SUM(D54:D59) -> 38 | E60: =SUM(E54:E59) -> 40 | F60: =SUM(F54:F59) -> 39 | G60: =SUM(G54:G59) -> 42 | H60: =SUM(H54:H59) -> 41 | I60: =SUM(I54:I59) -> 43 | J60: =SUM(J54:J59) -> 43 | K60: =SUM(K54:K59) -> 43 | ... Q60: =SUM(Q54:Q59) -> 46 | S60: =SUM(S54:S59) -> 40 | T60: =SUM(T54:T59) -> 40 | U60: =SUM(U54:U59) -> 38 | V60: =SUM(V54:V59) -> 39 | W60: =SUM(W54:W59) -> 39 | X60: =SUM(X54:X59) -> 40 | Y60: =SUM(Y54:Y59) -> 41 | Z60: =SUM(Z54:Z59) -> 42 | ... BD60: =SUM(BD54:BD59) -> 47 | BE60: =P60 -> 47 | BF60: =SUM(BF54:BF59) -> 47 | BG60: =SUM(BG54:BG59) -> 46 | BH60: =SUM(BH54:BH59) -> 46 | BI60: =U60 -> 38 | BJ60: =SUM(BJ54:BJ59) -> 46 | BL60: =SUM(BL54:BL59) -> 40 | BM60: =SUM(BM54:BM59) -> 40 | BN60: =SUM(BN54:BN59) -> 42 | BO60: =SUM(BO54:BO59) -> 42 | BP60: =SUM(BP54:BP59) -> 43 | BQ60: =SUM(BQ54:BQ59) -> 46 | BR60: =SUM(BR54:BR59) -> 46 | BS60: =SUM(BS54:BS59) -> 46 | ... BU60: =SUM(BU54:BU59) -> 46 | BW60: =SUM(BW54:BW59) -> 42
B63: Credit Information | D63: 41975 | E63: 42341 | F63: 42708 | G63: =G3 -> 43073 | H63: =H3 -> 43073 | I63: =I3 -> 43438 | J63: =J3 -> 43438 | K63: =K3 -> 43803 | L63: =L3 -> 44169 | M63: 44535 | N63: 44900 | O63: 45265 | P63: 45265 | Q63: 45265 | S63: 42437 | T63: 42527 | U63: 42622 | V63: 42714 | W63: 42801 | X63: 42892 | Y63: 42987 | Z63: 43079 | AA63: =AA3 -> 43166 | AB63: =AB3 -> 43257 | AC63: =AC3 -> 43348 | AD63: =AD3 -> 43439 | AE63: =AE3 -> 43439 | AF63: =AF3 -> 43555 | AG63: =AG3 -> 43555 | AH63: =AH3 -> 43646 | ... BJ63: =BJ3 -> 46112 | BL63: =BL3 -> 42530 | BM63: =BM3 -> 42896 | BN63: =BN3 -> 43261 | BO63: =BO3 -> 43646 | BP63: =BP3 -> 44012 | BQ63: =BQ3 -> 44377 | BR63: =BR3 -> 44742 | BS63: =BS3 -> 45107 | ... BU63: =BU3 -> 45838 | BW63: =BW3 -> 43646
B65: Chile CMR (Card)
B66: Total loans | C66: CLP in millions | D66: 1224623 | E66: 1379680 | F66: 1566161 | G66: 1715531 | H66: 1715531 | I66: 1903551 | J66: 1903551 | K66: 2174219 | S66: 1410244 | T66: =BL66 -> 1440304 | U66: 1438785 | V66: =F66 -> 1566161 | W66: 1583462 | X66: =BM66 -> 1593154 | Y66: 1564757 | Z66: =G66 -> 1715531 | AA66: 1738705 | AB66: =BN66 -> 1786322 | AC66: 1765980 | AD66: =I66 -> 1903551 | AE66: =J66 -> 1903551 | AF66: 1944024 | AG66: 1944024 | AH66: =BO66 -> 2003526 | AI66: 2041069 | AJ66: =K66 -> 2174219 | AL66: =BP66 -> 0 | BL66: 1440304 | BM66: 1593154 | BN66: 1786322 | BO66: 2003526 | BW66: 2003526
B67: Allowances | C67: CLP in millions | D67: -42861 | E67: -47902 | F67: -57943 | G67: -65590 | H67: -65590 | I67: -125451 | J67: -124201 | K67: -143811 | S67: -52826 | T67: =BL67 -> -56900 | U67: -53933 | V67: =F67 -> -57943 | W67: -65211 | X67: =BM67 -> -68561 | Y67: -65707 | Z67: =G67 -> -65590 | AA67: -113547 | AB67: =BN67 -> -121411 | AC67: -122003 | AD67: =I67 -> -125451 | AE67: =J67 -> -124201 | AF67: -119597 | AG67: -119597 | AH67: =BO67 -> -132151 | AI67: -133690 | AJ67: =K67 -> -143811 | AL67: =BP67 -> 0 | BL67: -56900 | BM67: -68561 | BN67: -121411 | BO67: -132151 | BW67: -132151
B68: Active accounts (with outstanding balance) | C68: Number | D68: 2247183 | E68: 2377164 | F68: 2417591 | G68: 2463344 | H68: 2463344 | I68: 2649711 | J68: 2598020 | K68: 2748592 | S68: 2357932 | T68: =BL68 -> 2367794 | U68: 2360481 | V68: =F68 -> 2417591 | W68: 2388008 | X68: =BM68 -> 2387609 | Y68: 2383221 | Z68: =G68 -> 2463344 | AA68: 2494195 | AB68: =BN68 -> 2543845 | AC68: 2570591 | AD68: =I68 -> 2649711 | AE68: =J68 -> 2598020 | AF68: 2694711 | AG68: 2694711 | AH68: =BO68 -> 2721792 | AI68: 2748592 | AJ68: =K68 -> 2748592 | AL68: =BP68 -> 0 | BL68: 2367794 | BM68: 2387609 | BN68: 2543845 | BO68: 2721792 | BW68: 2721792
B69: Average duration | C69: Months | D69: 4.3 | E69: 4 | F69: 3.8 | G69: 6.1 | H69: 6.1 | I69: 5.6 | J69: 5.7 | K69: 5.7 | S69: 5 | T69: =BL69 -> 5 | U69: 5.1 | V69: =F69 -> 3.8 | W69: 5.1 | X69: =BM69 -> 5 | Y69: 5.1 | Z69: =G69 -> 6.1 | AA69: 6.3 | AB69: =BN69 -> 6.2 | AC69: 5.7 | AD69: =I69 -> 5.6 | AE69: =J69 -> 5.7 | AF69: 6 | AG69: 6 | AH69: =BO69 -> 5.7 | AI69: 5.7 | AJ69: =K69 -> 5.7 | AL69: =BP69 -> 0 | BL69: 5 | BM69: 5 | BN69: 6.2 | BO69: 5.7 | BW69: 5.7
B70: Average loan | C70: CLP | D70: 544959 | E70: 580390 | F70: 647819 | G70: 696424 | H70: 696424 | I70: 718399 | J70: 679741 | K70: 791030 | S70: 598085 | T70: =BL70 -> 608289 | U70: 609531 | V70: =F70 -> 647819 | W70: 663089 | X70: =BM70 -> 667259 | Y70: 656572 | Z70: =G70 -> 696424 | AA70: 697101 | AB70: =BN70 -> 702213 | AC70: 686994 | AD70: =I70 -> 718399 | AE70: =J70 -> 679741 | AF70: 721422 | AG70: 721422 | AH70: =BO70 -> 736106 | AI70: 742587 | AJ70: =K70 -> 791030 | AL70: =BP70 -> 0 | BL70: 608289 | BM70: 667259 | BN70: 702213 | BO70: 736106 | BW70: 736106
B72: Banco Falabella Peru (Card)
B73: Total loans | C73: SOL in millions | D73: 3076 | E73: 3911 | F73: 3985 | G73: 3564.146 | H73: 3564.146 | I73: 3101.834 | J73: 3101.834 | K73: 3327.483 | L73: 2694.231 | M73: 2875.133 | N73: 3979.487 | O73: =3808.074 -> 3808.074 | P73: 3526.122 | Q73: 3812.776 | S73: 3901.114 | T73: =BL73 -> 3983 | U73: 3872.767 | V73: =F73 -> 3985 | W73: 3826.32 | X73: =BM73 -> 3829 | Y73: 3511.105 | Z73: =G73 -> 3564.146 | AA73: 3295.6 | AB73: =BN73 -> 3325.172 | AC73: 3036.113 | AD73: =I73 -> 3101.834 | AE73: =J73 -> 3101.834 | AF73: 3029.862 | AG73: 3029.862 | AH73: =BO73 -> 3063.063 | AI73: 3119.346 | AJ73: =K73 -> 3327.483 | AK73: 3044.115 | AL73: =BP73 -> 2784.881 | AM73: 2621.727 | AN73: 2621.727 | AO73: =L73 -> 2694.231 | AP73: 2183.987 | AQ73: =BQ73 -> 2513.764 | AR73: 2491.124 | AS73: =M73 -> 2875.133 | AT73: 3012.537 | AU73: =BR73 -> 3689.447 | AV73: 3775.498 | AW73: =N73 -> 3979.487 | AX73: 3466.2 | AY73: =BS73 -> 3927.195 | AZ73: 3793.198 | BA73: =O73 -> 3808.074 | BB73: 3203.323 | BC73: =BT73 -> 3488.563 | BD73: 3296.255 | BE73: =P73 -> 3526.122 | BF73: 3144.038 | BG73: =BU73 -> 3589.379 | BH73: 3631.116 | BI73: =Q73 -> 3812.776 | BJ73: 3353.963 | BL73: 3983 | BM73: 3829 | BN73: 3325.172 | BO73: 3063.063 | BP73: 2784.881 | BQ73: 2513.764 | BR73: 3689.447 | BS73: 3927.195 | BT73: 3488.563 | BU73: 3589.379 | BW73: 3063.063
