Workbook
Name \A: #REF!
Name \B: #REF!
Name \C: #REF!
Name \L: #REF!
Name \M: #REF!
Name \P: #REF!
Name \Y: #REF!
Name _01_30_04: MonthlyOpStats
Name _01_30_04: MonthlyOpStats
Name _1_30_01: MonthlyOpStats
Name _1_30_01: MonthlyOpStats
Name _1_30_02: MonthlyOpStats
Name _1_30_02: MonthlyOpStats
Name _1_31_01: MonthlyOpStats
Name _1_31_01: MonthlyOpStats
Name _1_31_02: MonthlyOpStats
Name _1_31_02: MonthlyOpStats
Name _12_31_05: MonthlyOpStats
Name _12_31_05: MonthlyOpStats
Name _A: #REF!
Name _A___0: #REF!
Name _B: #REF!
Name _B___0: #REF!
Name _C: #REF!
Name _C___0: #REF!
Name _ent1: [1]Inputs!$J$17
Name _ent10: [1]Inputs!$J$476
Name _ent11: [1]Inputs!$J$527
Name _ent12: [1]Inputs!$J$578
Name _ent13: [1]Inputs!$J$629
Name _ent14: [1]Inputs!$J$680
Name _ent15: [1]Inputs!$J$731
Name _ent2: [1]Inputs!$J$68
Name _ent3: [1]Inputs!$J$119
Name _ent4: [1]Inputs!$J$170
Name _ent5: [1]Inputs!$J$221
Name _ent6: [1]Inputs!$J$272
Name _ent7: [1]Inputs!$J$323
Name _ent8: [1]Inputs!$J$374
Name _ent9: [1]Inputs!$J$425
Name _eps1: [1]Inputs!$P$42
Name _eps10: [1]Inputs!$P$501
Name _eps11: [1]Inputs!$P$552
Name _eps12: [1]Inputs!$P$603
Name _eps13: [1]Inputs!$P$654
Name _eps14: [1]Inputs!$P$705
Name _eps15: [1]Inputs!$P$756
Name _eps2: [1]Inputs!$P$93
Name _eps3: [1]Inputs!$P$144
Name _eps4: [1]Inputs!$P$195
Name _eps5: [1]Inputs!$P$246
Name _eps6: [1]Inputs!$P$297
Name _eps7: [1]Inputs!$P$348
Name _eps8: [1]Inputs!$P$399
Name _eps9: [1]Inputs!$P$450
Name _fye1: [1]Inputs!$E$12
Name _fye10: [1]Inputs!$E$471
Name _fye11: [1]Inputs!$E$522
Name _fye12: [1]Inputs!$E$573
Name _fye13: [1]Inputs!$E$624

Sheet Capitalisation
A2: 1Q26 | I2: Exchange rate as at end 1Q26 | J2: =Model!$K$210 -> 0.14494854
I3: LTM Average exchange rate | J3: =Model!$K$211 -> 0.14097399
B5: Debt Breakdown as on 31-Mar-2026 | C5: RMB mn | D5: Leverage | E5: USD mn | F5: Leverage
B6: current liabilities
B7: RMB bank borrowings – unsecured | E7: =C7*$J$2 -> 0
B8: RMB bank borrowings – secured | E8: =C8*$J$2 -> 0
B9: Total bank borrowings | C9: 5380.92 | E9: =C9*$J$2 -> 779.95652
B11: Current portion of long-term convertible bonds | E11: =C11*$J$2 -> 0
B12: Current portion of long-term senior notes | E12: =C12*$J$2 -> 0
B13: Total bonds and notes | C13: 11334.607 | E13: =C13*$J$2 -> 1642.9348
B15: non-current liabilities:
B16: RMB bank borrowings – unsecured | E16: =C16*$J$2 -> 0
B17: RMB bank borrowings – secured | E17: =C17*$J$2 -> 0
B18: Total bank borrowings | C18: 42686.825 | E18: =C18*$J$2 -> 6187.3931
B20: Non-current portion of long-term convertible bonds | E20: =C20*$J$2 -> 0
B21: Non-current portion of long-term senior notes | E21: =C21*$J$2 -> 0
B22: Total bonds and notes | C22: 46703.421 | E22: =C22*$J$2 -> 6769.5928
B24: lease liabilities:
B25: current lease liabilities | C25: 2829.87 | E25: =C25*$J$2 -> 410.18553
B26: non- current lease liabilities | C26: 3868.242 | E26: =C26*$J$2 -> 560.69604
B28: Total Loans & Borrowings | C28: =SUM(C7:C26) -> 112803.88 | D28: =C28/C36 -> -3.8718558 | E28: =SUM(E7:E26) -> 16350.759 | F28: =E28/E36 -> -3.981017
B29: Cash and Cash Equivalents | C29: =Model!AO$122 -> 117029.37 | E29: =C29*J2 -> 16963.237
B30: Short term Investments | C30: =Model!AO$123 -> 63340.786 | E30: =C30*J2 -> 9181.1547
B31: Net debt | C31: =C28-C29-C30 -> -67566.27 | D31: =IF(C31<0,"net cash",C31/C36) -> net cash | E31: =E28-E29-E30 -> -9793.6324 | F31: =IF(E31<0,"net cash",E31/E36) -> net cash
B32: Restricted cash | C32: =Model!AO$126 -> 19868.723 | E32: =C32*J2 -> 2879.9425
B33: Net debt (including restricted cash) | C33: =C31-C32 -> -87434.993 | D33: =IF(C33<0,"net cash",C33/C36) -> net cash | E33: =E31-E32 -> -12673.575 | F33: =IF(E33<0,"net cash",E33/E36) -> net cash
B34: Equity | C34: =Model!AO$128 -> 149881.76 | E34: =C34*J2 -> 21725.143
B35: Total Capitalisation | C35: =C31+C34 -> 82315.491 | E35: =E31+E34 -> 11931.511
B36: LTM Adjusted EBITDA | C36: =Model!AO$89 -> -29134.32 | E36: =C36*J3 -> -4107.1814
B37: check | C37: =+C28-Model!AO$121 -> 0
B40: Liquidity at end-1Q26 | C40: RMB mn | D40: USD mn
B41: Cash and Cash Equivalents | C41: 117029.37 | D41: =C41*J2 -> 16963.237
B42: Short-term treasury investments | C42: 63340.786 | D42: =C42*J2 -> 9181.1547
B43: Restricted cash | C43: 19868.723 | D43: =C43*J2 -> 2879.9425
B44: Total liquidity | C44: =SUM(C41:C43) -> 200238.88 | D44: =SUM(D41:D43) -> 29024.334
B47: Debt Maturity at end-1Q26 (from BBG) | C47: RMB mn | D47: USD mn
B48: 2027 | C48: 137.38 | D48: =C48*J2 -> 19.913031
B49: 2028 | C49: 8248.87 | D49: =C49*J2 -> 1195.6617
B50: 2029 | C50: 8797.46 | D50: =C50*J2 -> 1275.179
B51: 2030 | C51: 10539.09 | D51: =C51*J2 -> 1527.6257
B52: 2031 | C52: 4060.36 | D52: =C52*J2 -> 588.54327
B53: 2032 | C53: 4060.36 | D53: =C53*J2 -> 588.54327
B54: 2032+ | C54: 10413.82 | D54: =C54*J2 -> 1509.468
B55: Total debt | C55: =SUM(C48:C54) -> 46257.34 | D55: =SUM(D48:D54) -> 6704.934
A60: FY25 | I60: Exchange rate as at end | J60: =Model!$K$210 -> 0.14494854
I61: LTM Average exchange rate | J61: =Model!$K$209 -> 0.14097399
B63: Debt Breakdown as on 31-Dec-2025 | C63: RMB mn | D63: Leverage | E63: USD mn | F63: Leverage
B64: current liabilities
B65: RMB bank borrowings – unsecured | C65: 3461.835 | E65: =C65*$J$60 -> 501.78794
B66: RMB bank borrowings – secured | C66: 6.026 | E66: =C66*$J$60 -> 0.87345992
B68: Current portion of long-term convertible bonds | C68: 10534.893 | E68: =C68*$J$60 -> 1527.0174
B69: Current portion of long-term senior notes | C69: 376.324 | E69: =C69*$J$60 -> 54.547616
B71: non-current liabilities:
B72: RMB bank borrowings – unsecured | C72: 16607.88 | E72: =C72*$J$60 -> 2407.288
B73: RMB bank borrowings – secured | C73: 2181.387 | E73: =C73*$J$60 -> 316.18887
B75: Non-current portion of long-term convertible bonds | C75: 138.22 | E75: =C75*$J$60 -> 20.034788
B76: Non-current portion of long-term senior notes | C76: 46976.534 | E76: =C76*$J$60 -> 6809.1802
B78: lease liabilities:
B79: current lease liabilities | C79: 2737.789 | E79: =C79*$J$60 -> 396.83853
B80: non- current lease liabilities | C80: 3598.218 | E80: =C80*$J$60 -> 521.55646
B82: Total Loans & Borrowings | C82: =SUM(C65:C80) -> 86619.106 | D82: =C82/C90 -> -6.2843951 | E82: =SUM(E65:E80) -> 12555.313 | F82: =E82/E90 -> -6.4615743
B83: Cash and Cash Equivalents | C83: =Model!AN$122 -> 106771.37 | E83: =C83*J60 -> 15476.354
B84: Short term Investments | C84: =Model!AN$123 -> 60062.338 | E84: =C84*J60 -> 8705.9484
B85: Net debt | C85: =C82-C83-C84 -> -80214.598 | D85: =IF(C85<0,"net cash",C85/C90) -> net cash | E85: =E82-E83-E84 -> -11626.989 | F85: =IF(E85<0,"net cash",E85/E90) -> net cash
B86: Restricted cash | C86: =Model!AN$126 -> 21631.575 | E86: =C86*J60 -> 3135.4653
B87: Net debt (including restricted cash) | C87: =C85-C86 -> -101846.17 | D87: =IF(C87<0,"net cash",C87/C90) -> net cash | E87: =E85-E86 -> -14762.454 | F87: =IF(E87<0,"net cash",E87/E90) -> net cash
B88: Equity | C88: =Model!AN$128 -> 150987.85 | E88: =C88*J60 -> 21885.469
B89: Total Capitalisation | C89: =C85+C88 -> 70773.254 | E89: =E85+E88 -> 10258.48
B90: LTM Adjusted EBITDA | C90: =Model!AN$89 -> -13783.205 | E90: =C90*J61 -> -1943.0734
B91: check | C91: =+C82-Model!AN$121 -> 0
B94: Liquidity at end-FY25 | C94: RMB mn | D94: USD mn
B95: Cash and Cash Equivalents | C95: 106771.37 | D95: =C95*J60 -> 15476.354
B96: Short-term treasury investments | C96: 60062.338 | D96: =C96*J60 -> 8705.9484
B97: Restricted cash | C97: 21631.575 | D97: =C97*J60 -> 3135.4653
B98: Total liquidity | C98: =SUM(C95:C97) -> 188465.28 | D98: =SUM(D95:D97) -> 27317.768
B101: Bank borrowings Debt Maturity at end-FY25 | C101: RMB mn | D101: USD mn
B102: Within 1 year | C102: 3467.861 | D102: =C102*J60 -> 502.6614
B103: Between 1 and 2 years | C103: 218.201 | D103: =C103*J60 -> 31.627917
B104: Between 2 and 5 years | C104: 17085.959 | D104: =C104*J60 -> 2476.5849
B105: More than 5 years | C105: 1485.107 | D105: =C105*J60 -> 215.2641
B106: Total debt | C106: =SUM(C102:C105) -> 22257.128 | D106: =SUM(D102:D105) -> 3226.1383
B107: check | C107: =C106-C65-C66-C72-C73 -> 0
B109: Notes payable Debt Maturity at end-FY25 | C109: RMB mn | D109: USD mn
B110: Within 1 year | C110: 10911.217 | D110: =C110*J68 -> 0
B111: Between 1 and 2 years | C111: 138.22 | D111: =C111*J68 -> 0
B112: Between 2 and 5 years | C112: 28125.755 | D112: =C112*J68 -> 0
B113: More than 5 years | C113: 18850.779 | D113: =C113*J68 -> 0
B114: Total debt | C114: =SUM(C110:C113) -> 58025.971 | D114: =SUM(D110:D113) -> 0
B115: check | C115: =C114-C76-C75-C69-C68 -> 0
A121: 3Q25 | I121: Exchange rate as at end 3Q25 | J121: =Model!AM$210 -> 0.14045733
I122: LTM Average exchange rate 3Q25 | J122: =Model!AM$211 -> 0.13874602
B124: Debt Breakdown as on 30-Sep-2025 | C124: RMB mn | D124: Leverage | E124: USD mn | F124: Leverage
B125: Short term debt | C125: =Model!AM$119 -> 19011.274 | E125: =C125*J121 -> 2670.2728
B126: Long term debt | C126: =Model!AM$120 -> 32254.675 | E126: =C126*J121 -> 4530.4055
B127: Total Loans & Borrowings | C127: =C125+C126 -> 51265.949 | D127: =C127/C135 -> 4.3577404 | E127: =E125+E126 -> 7200.6783 | F127: =E127/E135 -> 4.4114893
B128: Cash and Cash Equivalents | C128: =Model!AM$122 -> 99234.19 | E128: =C128*J121 -> 13938.169
B129: Short term Investments | C129: =Model!AM$123 -> 42053.569 | E129: =C129*J121 -> 5906.732
B130: Net debt (compnay reported) | C130: =C127-C128-C129 -> -90021.81 | D130: =C130/C135 -> -7.6520905 | E130: =E127-E128-E129 -> -12644.223 | F130: =E130/E135 -> -7.7464723
B131: Restricted cash | C131: =Model!AM$126 -> 21490.98 | E131: =C131*J121 -> 3018.5656
B132: Net debt (including restricted cash) | C132: =C130-C131 -> -111512.79 | D132: =C132/C135 -> -9.4788803 | E132: =E130-E131 -> -15662.789 | F132: =E132/E135 -> -9.595794
...

Sheet Model
B2: Meituan | C2: Annual | D2: Annual | E2: Annual | F2: Annual | G2: Annual | H2: Annual | I2: Annual | J2: Annual | K2: LTM | M2: Quarters | N2: Quarters | O2: Quarters | P2: Quarters | Q2: Quarters | R2: Quarters | S2: Quarters | T2: Quarters | U2: Quarters | V2: Quarters | W2: Quarters | X2: Quarters | Y2: Quarters | Z2: Quarters | AA2: Quarters | AB2: Quarters | AC2: Quarters | AD2: Quarters | AE2: Quarters | AF2: Quarters | AG2: Quarters | AH2: Quarters | AI2: Quarters | AJ2: Quarters | AK2: Quarters | AL2: Quarters | AM2: Quarters | AN2: Quarters | AO2: Quarters
B3: (RMB million) | C3: 43465 | D3: 43830 | E3: 44196 | F3: 44561 | G3: 44926 | H3: 45291 | I3: 45657 | J3: 46022 | K3: =AO3 -> 46112 | M3: 43555 | N3: 43646 | O3: 43738 | P3: 43830 | Q3: 43921 | R3: 44012 | S3: 44104 | T3: 44196 | U3: 44286 | V3: 44377 | W3: 44469 | X3: 44561 | Y3: 44651 | Z3: 44742 | AA3: 44834 | AB3: 44926 | AC3: 45016 | AD3: 45107 | AE3: 45199 | AF3: 45291 | AG3: 45382 | AH3: 45473 | AI3: 45565 | AJ3: 45657 | AK3: 45747 | AL3: 45838 | AM3: 45930 | AN3: 46022 | AO3: 46112
C4: Act | D4: Act | E4: Act | F4: Act | G4: Act | H4: Act | I4: Act | J4: Act | K4: Act | M4: Act | N4: Act | O4: Act | P4: Act | Q4: Act | R4: Act | S4: Act | T4: Act | U4: Act | V4: Act | W4: Act | X4: Act | Y4: Act | Z4: Act | AA4: Act | AB4: Act | AC4: Act | AD4: Act | AE4: Act | AF4: Act | AG4: Act | AH4: Act | AI4: Act | AJ4: Act | AK4: Act | AL4: Act | AM4: Act | AN4: Act | AO4: Act
C5: FY | D5: FY | E5: FY | F5: FY | G5: FY | H5: FY | I5: FY | J5: FY | K5: LTM | M5: 1Q | N5: 2Q | O5: 3Q | P5: 4Q | Q5: 1Q | R5: 2Q | S5: 3Q | T5: 4Q | U5: 1Q | V5: 2Q | W5: 3Q | X5: 4Q | Y5: 1Q | Z5: 2Q | AA5: 3Q | AB5: 4Q | AC5: 1Q | AD5: 2Q | AE5: 3Q | AF5: 4Q | AG5: 1Q | AH5: 2Q | AI5: 3Q | AJ5: 4Q | AK5: 1Q | AL5: 2Q | AM5: 3Q | AN5: 4Q | AO5: 1Q
B6: INCOME STATEMENT
B7: Revenue | C7: 65227.278 | D7: 97528.531 | E7: 114794.51 | F7: 179128 | G7: 219954.95 | H7: 276744.95 | I7: 337591.58 | J7: 364854.75 | K7: =SUM(AL7:AO7) -> 369687.51 | M7: 19173.512 | N7: 22703.137 | O7: 27493.629 | P7: =D7-SUM(M7:O7) -> 28158.253 | Q7: 16753.887 | R7: 24721.837 | S7: 35401.282 | T7: =E7-SUM(Q7:S7) -> 37917.504 | U7: 37016.262 | V7: 43759.232 | W7: 48829.37 | X7: =F7-SUM(U7:W7) -> 49523.133 | Y7: 46268.754 | Z7: 50938.363 | AA7: 62618.892 | AB7: =G7-SUM(Y7:AA7) -> 60128.939 | AC7: 58617.472 | AD7: 67964.624 | AE7: 76466.907 | AF7: =H7-SUM(AC7:AE7) -> 73695.951 | AG7: 73275.884 | AH7: 82251.077 | AI7: 93577.319 | AJ7: =I7-SUM(AG7:AI7) -> 88487.296 | AK7: 86206.145 | AL7: 91840.48 | AM7: 95488.113 | AN7: =J7-SUM(AK7:AM7) -> 91320.008 | AO7: =91038.906 -> 91038.906
B8: % of growth | D8: =(D7/C7)-1 -> 0.49521081 | E8: =(E7/D7)-1 -> 0.17703516 | F8: =(F7/E7)-1 -> 0.56042303 | G8: =(G7/F7)-1 -> 0.22792055 | H8: =(H7/G7)-1 -> 0.25818926 | I8: =(I7/H7)-1 -> 0.21986533 | J8: =(J7/I7)-1 -> 0.08075785 | Q8: =(Q7/M7)-1 -> -0.12619623 | R8: =(R7/N7)-1 -> 0.088917228 | S8: =(S7/O7)-1 -> 0.28761765 | T8: =(T7/P7)-1 -> 0.34658581 | U8: =(U7/Q7)-1 -> 1.2094134 | V8: =(V7/Q7)-1 -> 1.6118853 | W8: =(W7/S7)-1 -> 0.37931078 | X8: =(X7/T7)-1 -> 0.30607576 | Y8: =(Y7/U7)-1 -> 0.24995749 | Z8: =(Z7/U7)-1 -> 0.3761077 | AA8: =(AA7/W7)-1 -> 0.28240221 | AB8: =(AB7/X7)-1 -> 0.21415862 | AC8: =(AC7/Y7)-1 -> 0.26689109 | AD8: =(AD7/Y7)-1 -> 0.46890975 | AE8: =(AE7/AA7)-1 -> 0.22114756 | AF8: =(AF7/AB7)-1 -> 0.22563199 | AG8: =(AG7/AC7)-1 -> 0.25006899 | AH8: =(AH7/AC7)-1 -> 0.40318363 | AI8: =(AI7/AE7)-1 -> 0.22376231 | AJ8: =(AJ7/AF7)-1 -> 0.2007077 | AK8: =(AK7/AG7)-1 -> 0.17645998 | AL8: =(AL7/AG7)-1 -> 0.25335206 | AM8: =(AM7/AI7)-1 -> 0.020419414 | AN8: =(AN7/AJ7)-1 -> 0.032012641 | AO8: =(AO7/AK7)-1 -> 0.056060516
B9: Cost of revenues | C9: -50122.32 | D9: -65208.143 | E9: -80744.368 | F9: -136653.87 | G9: -158201.97 | H9: -179553.79 | I9: -207806.98 | J9: -253846.12 | K9: =SUM(AL9:AO9) -> -264771.52 | M9: -14104.172 | N9: -14762.502 | O9: -17901.345 | P9: =D9-SUM(M9:O9) -> -18440.124 | Q9: -11557.421 | R9: -16146.879 | S9: -24578.273 | T9: =E9-SUM(Q9:S9) -> -28461.795 | U9: -29816.095 | V9: -31245.861 | W9: -38051.383 | X9: =F9-SUM(U9:W9) -> -37540.53 | Y9: -35528.467 | Z9: -35363.935 | AA9: -44114.024 | AB9: =G9-SUM(Y9:AA9) -> -43195.543 | AC9: -38800.047 | AD9: -42566.619 | AE9: -49484.515 | AF9: =H9-SUM(AC9:AE9) -> -48702.612 | AG9: -47579.144 | AH9: -48361.233 | AI9: -56823.456 | AJ9: =I9-SUM(AG9:AI9) -> -55043.149 | AK9: -54143.437 | AL9: -61426.477 | AM9: -70307.05 | AN9: =J9-SUM(AK9:AM9) -> -67969.156 | AO9: -65068.834
B10: Gross Profit | C10: =C7+C9 -> 15104.958 | D10: =D7+D9 -> 32320.388 | E10: =E7+E9 -> 34050.142 | F10: =F7+F9 -> 42474.128 | G10: =G7+G9 -> 61752.979 | H10: =H7+H9 -> 97191.161 | I10: =I7+I9 -> 129784.59 | J10: =J7+J9 -> 111008.63 | K10: =K7+K9 -> 104915.99 | M10: =M7+M9 -> 5069.34 | N10: =N7+N9 -> 7940.635 | O10: =O7+O9 -> 9592.284 | P10: =P7+P9 -> 9718.129 | Q10: =Q7+Q9 -> 5196.466 | R10: =R7+R9 -> 8574.958 | S10: =S7+S9 -> 10823.009 | T10: =T7+T9 -> 9455.709 | ... AO10: =AO7+AO9 -> 25970.072
B11: Gross Profit margin | C11: =C10/C7 -> 0.23157425 | D11: =D10/D7 -> 0.33139418 | E11: =E10/E7 -> 0.29661821 | F11: =F10/F7 -> 0.23711608 | G11: =G10/G7 -> 0.28075285 | H11: =H10/H7 -> 0.35119398 | I11: =I10/I7 -> 0.38444263 | J11: =J10/J7 -> 0.3042543 | K11: =K10/K7 -> 0.28379642 | M11: =M10/M7 -> 0.26439288 | N11: =N10/N7 -> 0.34975937 | O11: =O10/O7 -> 0.34889116 | P11: =P10/P7 -> 0.34512542 | Q11: =Q10/Q7 -> 0.3101648 | R11: =R10/R7 -> 0.34685764 | S11: =S10/S7 -> 0.30572365 | T11: =T10/T7 -> 0.24937583 | ... AO11: =AO10/AO7 -> 0.28526345
B12: Operating expenses:
B13: Selling and marketing expenses | C13: -15871.901 | D13: -18819.067 | E13: -20882.685 | F13: -40683.166 | G13: -39745.112 | H13: -58616.997 | I13: -63975.235 | J13: -102934.04 | K13: =SUM(AL13:AO13) -> -110703.53 | M13: -3706.112 | N13: -4149.11 | O13: -5614.75 | P13: =D13-SUM(M13:O13) -> -5349.095 | Q13: -3199.439 | R13: -4172.332 | S13: -5835.574 | T13: =E13-SUM(Q13:S13) -> -7675.34 | U13: -7206.408 | V13: -10848.627 | W13: -11388.227 | X13: =F13-SUM(U13:W13) -> -11239.904 | Y13: -9105.728 | Z13: -8986.036 | AA13: -10886.422 | AB13: =G13-SUM(Y13:AA13) -> -10766.926 | AC13: -10433.07 | AD13: -14553.195 | AE13: -16905.422 | AF13: =H13-SUM(AC13:AE13) -> -16725.31 | AG13: -13888.302 | AH13: -14832.448 | AI13: -17953.163 | AJ13: =I13-SUM(AG13:AI13) -> -17301.322 | AK13: -15199.035 | AL13: -22518.913 | AM13: -34266.826 | AN13: =J13-SUM(AK13:AM13) -> -30949.27 | AO13: -22968.519
B14: Research and development expenses | C14: -7071.9 | D14: -8445.664 | E14: -10892.514 | F14: -16675.595 | G14: -20739.865 | H14: -21201.005 | I14: -21053.601 | J14: -25998.265 | K14: =SUM(AL14:AO14) -> -27269.333 | M14: -2036.1 | N14: -2032.33 | O14: -2137.349 | P14: =D14-SUM(M14:O14) -> -2239.885 | Q14: -2296.458 | R14: -2376.737 | S14: -2970.12 | T14: =E14-SUM(Q14:S14) -> -3249.199 | U14: -3477.29 | V14: -3900.794 | W14: -4715.55 | X14: =F14-SUM(U14:W14) -> -4581.961 | Y14: -4879.033 | Z14: -5203.533 | AA14: -5414.371 | AB14: =G14-SUM(Y14:AA14) -> -5242.928 | AC14: -5047.387 | AD14: -5407.176 | AE14: -5321.157 | AF14: =H14-SUM(AC14:AE14) -> -5425.285 | AG14: -5000.153 | AH14: -5339.68 | AI14: -5293.483 | AJ14: =I14-SUM(AG14:AI14) -> -5420.285 | AK14: -5772.03 | AL14: -6260.087 | AM14: -6936.845 | AN14: =J14-SUM(AK14:AM14) -> -7029.303 | AO14: -7043.098
B15: General and administrative expenses | C15: -5546.037 | D15: -4338.954 | E15: -5593.895 | F15: -8612.626 | G15: -9771.81 | H15: -9372.067 | I15: -10729.203 | J15: -11916.432 | K15: =SUM(AL15:AO15) -> -12227.808 | M15: -1012.213 | N15: -1038.298 | O15: -1055.969 | P15: =D15-SUM(M15:O15) -> -1232.474 | Q15: -1069.741 | R15: -1158.092 | S15: -1415.119 | T15: =E15-SUM(Q15:S15) -> -1950.943 | U15: -1737.403 | V15: -2053.024 | W15: -2387.116 | X15: =F15-SUM(U15:W15) -> -2435.083 | Y15: -2312.289 | Z15: -2503.552 | AA15: -2505.272 | AB15: =G15-SUM(Y15:AA15) -> -2450.697 | AC15: -1994.953 | AD15: -2139.048 | AE15: -2537.785 | AF15: =H15-SUM(AC15:AE15) -> -2700.281 | AG15: -2298.323 | AH15: -2694.931 | AI15: -2797.76 | AJ15: =I15-SUM(AG15:AI15) -> -2938.189 | AK15: -2627.017 | AL15: -2678.95 | AM15: -2957.804 | AN15: =J15-SUM(AK15:AM15) -> -3652.661 | AO15: -2938.393
B16: Net provision for impairment losses on financial assets | C16: -285.655 | D16: -645.685 | E16: -467.69 | F16: -259.953 | G16: -468.62 | H16: -1135.405 | I16: -897.505 | J16: -872.035 | K16: =SUM(AL16:AO16) -> -1231.572 | M16: -62.98 | N16: -138.711 | O16: -111.99 | P16: =D16-SUM(M16:O16) -> -332.004 | Q16: -237.542 | R16: -45.676 | S16: -130.285 | T16: =E16-SUM(Q16:S16) -> -54.187 | U16: 33.775 | V16: -104.355 | W16: -136.884 | X16: =F16-SUM(U16:W16) -> -52.489 | Y16: -153.316 | Z16: -50.437 | AA16: -284.035 | AB16: =G16-SUM(Y16:AA16) -> 19.168 | AC16: -255.347 | AD16: -195.264 | AE16: -276.377 | AF16: =H16-SUM(AC16:AE16) -> -408.417 | AG16: -175.386 | AH16: -276.431 | AI16: -275.298 | AJ16: =I16-SUM(AG16:AI16) -> -170.39 | AK16: -121.474 | AL16: -19.219 | AM16: -292.777 | AN16: =J16-SUM(AK16:AM16) -> -438.565 | AO16: -481.011
B17: Fair value changes on other financial investments | C17: 1836.382 | D17: 77.699 | E17: 4955.909 | F17: 815.747 | G17: -1013.057 | H17: 234.227 | I17: 140.921 | J17: 2393.393 | K17: =SUM(AL17:AO17) -> 1981.014 | M17: 165.292 | N17: -323.651 | O17: 163.615 | P17: =D17-SUM(M17:O17) -> 72.443 | Q17: -508.261 | R17: 346.689 | S17: 5779.364 | T17: =E17-SUM(Q17:S17) -> -661.883 | U17: 42.034 | V17: 164.748 | W17: -117.99 | X17: =F17-SUM(U17:W17) -> 726.955 | Y17: -802.894 | Z17: -292.183 | AA17: -105.922 | AB17: =G17-SUM(Y17:AA17) -> 187.942 | AC17: 164.029 | AD17: 103.761 | AE17: 28.089 | AF17: =H17-SUM(AC17:AE17) -> -61.652 | AG17: -517.116 | AH17: -120.037 | AI17: 765.239 | AJ17: =I17-SUM(AG17:AI17) -> 12.835 | AK17: 804.82 | AL17: 481.537 | AM17: -389.928 | AN17: =J17-SUM(AK17:AM17) -> 1496.964 | AO17: 392.441
B18: Other operating income/(loss), net | C18: 748.356 | D18: 2531.143 | E18: 3160.835 | F18: -185.734 | G18: 4165.037 | H18: 6315.473 | I18: 3574.985 | J18: 3277.62 | K18: =SUM(AL18:AO18) -> 2458.179 | M18: 279.131 | N18: 854.043 | O18: 611.223 | P18: =D18-SUM(M18:O18) -> 786.746 | Q18: 399.445 | R18: 1005.835 | S18: 472.408 | T18: =E18-SUM(Q18:S18) -> 1283.147 | U18: 378.118 | V18: 976.976 | W18: -2134.851 | X18: =F18-SUM(U18:W18) -> 594.023 | Y18: 928.731 | Z18: 968.475 | AA18: 1679.376 | AB18: =G18-SUM(Y18:AA18) -> 588.455 | AC18: 1335.024 | AD18: 1505.916 | AE18: 1388.793 | AF18: =H18-SUM(AC18:AE18) -> 2085.74 | AG18: 1391.932 | AH18: 630.572 | AI18: 2485.778 | AJ18: =I18-SUM(AG18:AI18) -> -933.297 | AK18: 1418.138 | AL18: 807.979 | AM18: -96.233 | AN18: =J18-SUM(AK18:AM18) -> 1147.736 | AO18: 598.697
B19: Operating profit | C19: =C10+SUM(C13:C18) -> -11085.797 | D19: =D10+SUM(D13:D18) -> 2679.86 | E19: =E10+SUM(E13:E18) -> 4330.102 | F19: =F10+SUM(F13:F18) -> -23127.199 | G19: =G10+SUM(G13:G18) -> -5820.448 | H19: =H10+SUM(H13:H18) -> 13415.387 | I19: =I10+SUM(I13:I18) -> 36844.956 | J19: =J10+SUM(J13:J18) -> -25041.137 | K19: =K10+SUM(K13:K18) -> -42077.058 | M19: =M10+SUM(M13:M18) -> -1303.642 | N19: =N10+SUM(N13:N18) -> 1112.578 | O19: =O10+SUM(O13:O18) -> 1447.064 | P19: =P10+SUM(P13:P18) -> 1423.86 | Q19: =Q10+SUM(Q13:Q18) -> -1715.53 | R19: =R10+SUM(R13:R18) -> 2174.645 | S19: =S10+SUM(S13:S18) -> 6723.683 | T19: =T10+SUM(T13:T18) -> -2852.696 | ... AO19: =AO10+SUM(AO13:AO18) -> -6469.811
B20: Finance exps | C20: =-44.732 -> -44.732 | D20: -191.042 | E20: -370.016 | F20: -1130.935 | G20: -1628.825 | H20: -1425.157 | I20: -1337.038 | J20: -1886.802 | K20: =SUM(AL20:AO20) -> -2198.659 | M20: -46.821 | N20: -50.115 | O20: -49.011 | P20: =D20-SUM(M20:O20) -> -45.095 | Q20: -48.044 | R20: -60.731 | S20: -111.506 | T20: =E20-SUM(R20:S20) -> -197.779 | U20: -166.052 | V20: -263.269 | W20: -369.942 | X20: =F20-SUM(V20:W20) -> -497.724 | Y20: -330.317 | Z20: -418.612 | AA20: -474.728 | AB20: =G20-SUM(Y20:AA20) -> -405.168 | AC20: -353.479 | AD20: -354.003 | AE20: -350.95 | AF20: =H20-SUM(AC20:AE20) -> -366.725 | AG20: -321.863 | AH20: -285.373 | AI20: -261.651 | AJ20: =I20-SUM(AG20:AI20) -> -468.151 | AK20: -475.12 | AL20: -430.214 | AM20: -413.987 | AN20: =J20-SUM(AK20:AM20) -> -567.481 | AO20: -786.977
B21: Finance income | C21: 294.047 | D21: 166.217 | E21: 213.684 | F21: 546.037 | G21: 657.908 | H21: 818.986 | I21: 1291.807 | J21: 2011.535 | K21: =SUM(AL21:AO21) -> 2002.103 | M21: 52.922 | N21: 21.541 | O21: 38.235 | P21: =D21-SUM(M21:O21) -> 53.519 | Q21: 57.93 | R21: 40.352 | S21: 45.678 | T21: =E21-SUM(Q21:S21) -> 69.724 | U21: 77.855 | V21: 112.118 | W21: 198.89 | X21: =F21-SUM(U21:W21) -> 157.174 | Y21: 110.359 | Z21: 190.412 | AA21: 209.746 | AB21: =G21-SUM(Y21:AA21) -> 147.391 | AC21: 184.419 | AD21: 217.189 | AE21: 201.225 | AF21: =H21-SUM(AC21:AE21) -> 216.153 | AG21: 279.755 | AH21: 344.494 | AI21: 313.088 | AJ21: =I21-SUM(AG21:AI21) -> 354.47 | AK21: 491.358 | AL21: 508.307 | AM21: 513.372 | AN21: =J21-SUM(AK21:AM21) -> 498.498 | AO21: 481.926
B22: Fair value changes of convertible redeemable preferred shares | C22: -104606.06 | H22: 0 | I22: 0 | J22: 0 | K22: =SUM(AL22:AO22) -> 0 | Y22: 0 | Z22: 0 | AA22: 0 | AB22: =G22-SUM(Y22:AA22) -> 0 | AC22: 0 | AD22: 0 | AE22: 0 | AF22: =H22-SUM(AC22:AE22) -> 0 | AG22: 0 | AH22: 0 | AI22: 0 | AJ22: =I22-SUM(AG22:AI22) -> 0 | AK22: 0 | AL22: 0 | AM22: 0 | AN22: =J22-SUM(AK22:AM22) -> 0 | AO22: 0
B23: Share of net profit /(loss) of associates | C23: -48.267 | D23: 107.353 | E23: 264.105 | F23: 145.62 | G23: 35.848 | H23: 1212.652 | I23: 1185.704 | J23: 78.892 | K23: =SUM(AL23:AO23) -> -441.562 | M23: 7.53 | N23: 17.848 | O23: 24.329 | P23: =D23-SUM(M23:O23) -> 57.646 | Q23: 11.128 | R23: 42.881 | S23: 92.698 | T23: =E23-SUM(Q23:S23) -> 117.398 | U23: -2.013 | V23: 38.251 | W23: 273.237 | X23: =F23-SUM(U23:W23) -> -163.855 | Y23: 46.411 | Z23: -400.052 | AA23: 485.362 | AB23: =G23-SUM(Y23:AA23) -> -95.873 | AC23: -49.759 | AD23: 122.406 | AE23: 434.521 | AF23: =H23-SUM(AC23:AE23) -> 705.484 | AG23: 314.197 | AH23: 341.204 | AI23: 213.821 | AJ23: =I23-SUM(AG23:AI23) -> 316.482 | AK23: 18.453 | AL23: 89.223 | AM23: 9.541 | AN23: =J23-SUM(AK23:AM23) -> -38.325 | AO23: -502.001
B24: Profit before tax | C24: =C19+SUM(C20:C23) -> -115490.81 | D24: =D19+SUM(D20:D23) -> 2762.388 | E24: =E19+SUM(E20:E23) -> 4437.875 | F24: =F19+SUM(F20:F23) -> -23566.477 | G24: =G19+SUM(G20:G23) -> -6755.517 | H24: =H19+SUM(H20:H23) -> 14021.868 | I24: =I19+SUM(I20:I23) -> 37985.429 | J24: =J19+SUM(J20:J23) -> -24837.512 | K24: =K19+SUM(K20:K23) -> -42715.176 | M24: =M19+SUM(M20:M23) -> -1290.011 | N24: =N19+SUM(N20:N23) -> 1101.852 | O24: =O19+SUM(O20:O23) -> 1460.617 | P24: =P19+SUM(P20:P23) -> 1489.93 | Q24: =Q19+SUM(Q20:Q23) -> -1694.516 | R24: =R19+SUM(R20:R23) -> 2197.147 | S24: =S19+SUM(S20:S23) -> 6750.553 | T24: =T19+SUM(T20:T23) -> -2863.353 | ... AO24: =AO19+SUM(AO20:AO23) -> -7276.863
B25: Income tax credits/(expenses) / Current and deferred income tax and social contribution | C25: -1.888 | D25: -526.223 | E25: 269.737 | F25: 30.279 | G25: 70.194 | H25: -164.537 | I25: -2177.107 | J25: 1483.318 | K25: =SUM(AL25:AO25) -> 2476.844 | M25: -143.319 | N25: -226.024 | O25: -127.235 | P25: =D25-SUM(M25:O25) -> -29.645 | Q25: 115.238 | R25: 13.034 | S25: -429.552 | T25: =E25-SUM(Q25:S25) -> 571.017 | U25: 10.955 | V25: 8.23 | W25: 6.036 | X25: =F25-SUM(U25:W25) -> 5.058 | Y25: 55.223 | Z25: 5.063 | AA25: 8.209 | AB25: =G25-SUM(Y25:AA25) -> 1.699 | AC25: -8.411 | AD25: -9.972 | AE25: -50.095 | AF25: =H25-SUM(AC25:AE25) -> -96.059 | AG25: -112.502 | AH25: -304.876 | AI25: -1085.48 | AJ25: =I25-SUM(AG25:AI25) -> -674.249 | AK25: -543.921 | AL25: -28.37 | AM25: 1018.336 | AN25: =J25-SUM(AK25:AM25) -> 1037.273 | AO25: 449.605
B26: Net profit/loss | C26: =+C24+C25 -> -115492.7 | D26: =+D24+D25 -> 2236.165 | E26: =+E24+E25 -> 4707.612 | F26: =+F24+F25 -> -23536.198 | G26: =+G24+G25 -> -6685.323 | H26: =+H24+H25 -> 13857.331 | I26: =+I24+I25 -> 35808.322 | J26: =+J24+J25 -> -23354.194 | K26: =+K24+K25 -> -40238.332 | M26: =+M24+M25 -> -1433.33 | N26: =+N24+N25 -> 875.828 | O26: =+O24+O25 -> 1333.382 | P26: =+P24+P25 -> 1460.285 | Q26: =+Q24+Q25 -> -1579.278 | R26: =+R24+R25 -> 2210.181 | S26: =+S24+S25 -> 6321.001 | T26: =+T24+T25 -> -2292.336 | ... AO26: =+AO24+AO25 -> -6827.258
B27: % margin | C27: =+C26/C7 -> -1.7706196 | D27: =+D26/D7 -> 0.022928316 | E27: =+E26/E7 -> 0.041009034 | F27: =+F26/F7 -> -0.13139318 | G27: =+G26/G7 -> -0.030394056 | H27: =+H26/H7 -> 0.05007257 | I27: =+I26/I7 -> 0.10606995 | J27: =+J26/J7 -> -0.064009566 | K27: =+K26/K7 -> -0.10884418 | M27: =+M26/M7 -> -0.074755736 | N27: =+N26/N7 -> 0.0385774 | O27: =+O26/O7 -> 0.048497854 | P27: =+P26/P7 -> 0.051859929 | Q27: =+Q26/Q7 -> -0.094263379 | R27: =+R26/R7 -> 0.089401973 | S27: =+S26/S7 -> 0.17855288 | T27: =+T26/T7 -> -0.060455878 | ... AO27: =+AO26/AO7 -> -0.074992751
B28: Non-controlling interest | C28: 15.524 | D28: 2.604 | E28: 0.701 | F28: -2.181 | G28: -0.787 | H28: -1.503 | I28: -1.143 | J28: -0.821 | K28: =SUM(AL28:AO28) -> -0.924 | M28: 1.553 | N28: 1.587 | O28: 1.82 | P28: =D28-SUM(M28:O28) -> -2.356 | Q28: 0.942 | R28: -0.434 | S28: 0.602 | T28: =E28-SUM(Q28:S28) -> -0.409 | U28: -1.021 | V28: -0.948 | W28: -0.25 | X28: =F28-SUM(U28:W28) -> 0.038 | Y28: 0.077 | Z28: -0.492 | AA28: 0.369 | AB28: =G28-SUM(Y28:AA28) -> -0.741 | AC28: -0.258 | AD28: -0.749 | AE28: -0.211 | AF28: =H28-SUM(AC28:AE28) -> -0.285 | AG28: -0.441 | AH28: =-0.858-AG28 -> -0.417 | AI28: -0.255 | AJ28: =I28-SUM(AG28:AI28) -> -0.03 | AK28: -0.053 | AL28: =-0.532-AK28 -> -0.479 | AM28: -0.366 | AN28: =J28-SUM(AK28:AM28) -> 0.077 | AO28: -0.156
B29: Net profit/loss | C29: =+C26+C28 -> -115477.17 | D29: =+D26+D28 -> 2238.769 | E29: =+E26+E28 -> 4708.313 | F29: =+F26+F28 -> -23538.379 | G29: =+G26+G28 -> -6686.11 | H29: =+H26+H28 -> 13855.828 | I29: =+I26+I28 -> 35807.179 | J29: =+J26+J28 -> -23355.015 | K29: =+K26+K28 -> -40239.256 | M29: =+M26+M28 -> -1431.777 | N29: =+N26+N28 -> 877.415 | O29: =+O26+O28 -> 1335.202 | P29: =+P26+P28 -> 1457.929 | Q29: =+Q26+Q28 -> -1578.336 | R29: =+R26+R28 -> 2209.747 | S29: =+S26+S28 -> 6321.603 | T29: =+T26+T28 -> -2292.745 | ... AO29: =+AO26+AO28 -> -6827.414
B31: As % of sales unless stated otherwise
B32: =B13 -> Selling and marketing expenses | C32: =-C13/C7 -> 0.24333226 | D32: =-D13/D7 -> 0.19295961 | E32: =-E13/E7 -> 0.18191362 | F32: =-F13/F7 -> 0.22711785 | G32: =-G13/G7 -> 0.1806966 | H32: =-H13/H7 -> 0.21180873 | I32: =-I13/I7 -> 0.18950483 | J32: =-J13/J7 -> 0.28212335 | K32: =-K13/K7 -> 0.29945163 | M32: =-M13/M7 -> 0.19329333 | N32: =-N13/N7 -> 0.18275492 | O32: =-O13/O7 -> 0.20422004 | P32: =-P13/P7 -> 0.18996544 | Q32: =-Q13/Q7 -> 0.19096697 | R32: =-R13/R7 -> 0.16877112 | S32: =-S13/S7 -> 0.16484075 | T32: =-T13/T7 -> 0.20242208 | ... AO32: =-AO13/AO7 -> 0.25229344
B33: =B14 -> Research and development expenses | C33: =-C14/C7 -> 0.10841936 | D33: =-D14/D7 -> 0.086596854 | E33: =-E14/E7 -> 0.094887064 | F33: =-F14/F7 -> 0.093093181 | G33: =-G14/G7 -> 0.094291423 | H33: =-H14/H7 -> 0.076608461 | I33: =-I14/I7 -> 0.062364118 | J33: =-J14/J7 -> 0.07125648 | K33: =-K14/K7 -> 0.073763199 | M33: =-M14/M7 -> 0.10619338 | N33: =-N14/N7 -> 0.089517585 | O33: =-O14/O7 -> 0.077739792 | P33: =-P14/P7 -> 0.079546306 | Q33: =-Q14/Q7 -> 0.13707016 | R33: =-R14/R7 -> 0.096139174 | S33: =-S14/S7 -> 0.083898657 | T33: =-T14/T7 -> 0.085691268 | ... AO33: =-AO14/AO7 -> 0.077363605
B34: =B15 -> General and administrative expenses | C34: =-C15/C7 -> 0.085026344 | D34: =-D15/D7 -> 0.044489074 | E34: =-E15/E7 -> 0.048729639 | F34: =-F15/F7 -> 0.048080848 | G34: =-G15/G7 -> 0.044426416 | H34: =-H15/H7 -> 0.033865358 | I34: =-I15/I7 -> 0.031781608 | J34: =-J15/J7 -> 0.032660756 | K34: =-K15/K7 -> 0.033076065 | M34: =-M15/M7 -> 0.052792258 | N34: =-N15/N7 -> 0.04573368 | O34: =-O15/O7 -> 0.038407771 | P34: =-P15/P7 -> 0.043769548 | Q34: =-Q15/Q7 -> 0.063850317 | R34: =-R15/R7 -> 0.046844901 | S34: =-S15/S7 -> 0.039973665 | T34: =-T15/T7 -> 0.051452306 | ... AO34: =-AO15/AO7 -> 0.032276234
B35: =B16 -> Net provision for impairment losses on financial assets | C35: =-C16/C$7 -> 0.0043793794 | D35: =-D16/D$7 -> 0.0066204729 | E35: =-E16/E$7 -> 0.0040741495 | F35: =-F16/F$7 -> 0.0014512137 | G35: =-G16/G$7 -> 0.0021305272 | H35: =-H16/H$7 -> 0.0041027126 | I35: =-I16/I$7 -> 0.0026585527 | J35: =-J16/J$7 -> 0.0023900881 | K35: =-K16/K$7 -> 0.0033313866 | M35: =-M16/M$7 -> 0.0032847399 | N35: =-N16/N$7 -> 0.0061097724 | O35: =-O16/O$7 -> 0.0040733073 | P35: =-P16/P$7 -> 0.011790646 | Q35: =-Q16/Q$7 -> 0.014178322 | R35: =-R16/R$7 -> 0.0018475973 | S35: =-S16/S$7 -> 0.003680234 | T35: =-T16/T$7 -> 0.0014290761 | ... AO35: =-AO16/AO$7 -> 0.0052835762
B36: =B17 -> Fair value changes on other financial investments | C36: =-C17/C$7 -> -0.028153589 | D36: =-D17/D$7 -> -0.00079667969 | E36: =-E17/E$7 -> -0.043172004 | F36: =-F17/F$7 -> -0.0045539894 | G36: =-G17/G$7 -> 0.0046057477 | H36: =-H17/H$7 -> -0.00084636412 | I36: =-I17/I$7 -> -0.00041743044 | J36: =-J17/J$7 -> -0.0065598516 | K36: =-K17/K$7 -> -0.0053586177 | M36: =-M17/M$7 -> -0.0086208515 | N36: =-N17/N$7 -> 0.014255783 | O36: =-O17/O$7 -> -0.0059510151 | P36: =-P17/P$7 -> -0.0025727093 | Q36: =-Q17/Q$7 -> 0.0303369 | R36: =-R17/R$7 -> -0.014023594 | S36: =-S17/S$7 -> -0.16325296 | T36: =-T17/T$7 -> 0.017455869 | ... AO36: =-AO17/AO$7 -> -0.0043106955
B37: =B18 -> Other operating income/(loss), net | C37: =-C18/C7 -> -0.011473053 | D37: =-D18/D7 -> -0.025952847 | E37: =-E18/E7 -> -0.027534723 | F37: =-F18/F7 -> 0.0010368787 | G37: =-G18/G7 -> -0.018935864 | H37: =-H18/H7 -> -0.022820553 | I37: =-I18/I7 -> -0.010589675 | J37: =-J18/J7 -> -0.0089833558 | K37: =-K18/K7 -> -0.0066493429 | M37: =-M18/M7 -> -0.014558157 | N37: =-N18/N7 -> -0.037617841 | O37: =-O18/O7 -> -0.022231441 | P37: =-P18/P7 -> -0.027940157 | Q37: =-Q18/Q7 -> -0.02384193 | R37: =-R18/R7 -> -0.040686095 | S37: =-S18/S7 -> -0.013344375 | T37: =-T18/T7 -> -0.033840492 | ... AO37: =-AO18/AO7 -> -0.0065762763
B38: Finance exps as % of debt | C38: =-C20/C111 -> 0.019705241 | D38: =-D20/D111 -> 0.0475316 | E38: =-E20/E111 -> 0.017306201 | F38: =-F20/F111 -> 0.020854968 | G38: =-G20/G111 -> 0.030896659 | H38: =-H20/H111 -> 0.02612912 | I38: =-I20/I111 -> 0.023981572 | J38: =-J20/J111 -> 0.023501858 | K38: =-K20/K111 -> 0.020721389 | P38: =-SUM(M20:P20)/P111 -> 0.0475316 | Q38: =-SUM(N20:Q20)/Q111 -> 0.047773921 | R38: =-SUM(O20:R20)/R111 -> 0.061040818 | S38: =-SUM(P20:S20)/S111 -> 0.033743085 | T38: =-SUM(Q20:T20)/T111 -> 0.01955329 | U38: =-SUM(R20:U20)/U111 -> 0.059260966 | V38: =-SUM(S20:V20)/V111 -> 0.014846494 | W38: =-SUM(T20:W20)/W111 -> 0.01806914 | ... AO38: =-SUM(AL20:AO20)/AO111 -> 0.020721389
B39: Finance income as% of cash and cash equivalents | C39: =C21/C122 -> 0.017252541 | D39: =D21/D122 -> 0.012407786 | E39: =E21/E122 -> 0.012500849 | F39: =F21/F122 -> 0.0167942 | G39: =G21/G122 -> 0.032636582 | H39: =H21/H122 -> 0.024564848 | I39: =I21/I122 -> 0.018237079 | J39: =J21/J122 -> 0.018839648 | K39: =K21/K122 -> 0.017107697 | P39: =SUM(M21:P21)/P122 -> 0.012407786 | Q39: =SUM(N21:Q21)/Q122 -> 0.012111125 | R39: =SUM(O21:R21)/R122 -> 0.013637261 | S39: =SUM(P21:S21)/S122 -> 0.010029609 | T39: =SUM(Q21:T21)/T122 -> 0.012500849 | U39: =SUM(R21:U21)/U122 -> 0.013129337 | V39: =SUM(S21:V21)/V122 -> 0.0042776876 | W39: =SUM(T21:W21)/W122 -> 0.0090029468 | ... AO39: =SUM(AL21:AO21)/AO122 -> 0.017107697
B40: =B23 -> Share of net profit /(loss) of associates | C40: =-C23/C7 -> 0.00073998182 | D40: =-D23/D7 -> -0.0011007343 | E40: =-E23/E7 -> -0.0023006762 | F40: =-F23/F7 -> -0.00081293825 | G40: =-G23/G7 -> -0.00016297883 | H40: =-H23/H7 -> -0.0043818396 | I40: =-I23/I7 -> -0.003512244 | J40: =-J23/J7 -> -0.00021622852 | K40: =-K23/K7 -> 0.0011944196 | M40: =-M23/M7 -> -0.0003927293 | N40: =-N23/N7 -> -0.00078614687 | O40: =-O23/O7 -> -0.00088489592 | P40: =-P23/P7 -> -0.0020472151 | Q40: =-Q23/Q7 -> -0.00066420407 | R40: =-R23/R7 -> -0.0017345394 | S40: =-S23/S7 -> -0.0026184927 | T40: =-T23/T7 -> -0.0030961426 | ... AO40: =-AO23/AO7 -> 0.005514137
B41: Tax % of PBT | C41: =-C25/C24 -> -1.6347622e-05 | D41: =-D25/D24 -> 0.19049569 | E41: =-E25/E24 -> -0.060780666 | F41: =-F25/F24 -> 0.0012848335 | G41: =-G25/G24 -> 0.010390619 | H41: =-H25/H24 -> 0.011734314 | I41: =-I25/I24 -> 0.057314266 | J41: =-J25/J24 -> 0.059720877 | K41: =-K25/K24 -> 0.057985106 | M41: =-M25/M24 -> -0.11109905 | N41: =-N25/N24 -> 0.205131 | O41: =-O25/O24 -> 0.087110447 | P41: =-P25/P24 -> 0.019896908 | Q41: =-Q25/Q24 -> 0.06800644 | R41: =-R25/R24 -> -0.0059322385 | S41: =-S25/S24 -> 0.06363212 | T41: =-T25/T24 -> 0.1994225 | ... AO41: =-AO25/AO24 -> 0.061785552
B43: Working capital /sales | C43: =C63/C7 -> 0.0004395247 | D43: =D63/D7 -> 0.010377866 | E43: =E63/E7 -> 0.046499262 | F43: =F63/F7 -> 0.022852285 | G43: =G63/G7 -> -0.0036984119 | H43: =H63/H7 -> 0.048692956 | I43: =I63/I7 -> 0.019152045 | J43: =J63/J7 -> -0.0028941079 | K43: =K63/K7 -> 0 | M43: =M63/M7 -> 0 | N43: =N63/N7 -> 0 | O43: =O63/O7 -> 0 | P43: =P63/P7 -> 0.035944631 | Q43: =Q63/Q7 -> 0 | R43: =R63/R7 -> 0 | S43: =S63/S7 -> 0 | T43: =T63/T7 -> 0.14077562 | ... AO43: =AO63/AO7 -> 0
B44: Capex/sales | C44: =-C67/C7 -> 0.033506703 | D44: =-D67/D7 -> 0.029967046 | E44: =-E67/E7 -> 0.13521296 | F44: =-F67/F7 -> 0.04970879 | G44: =-G67/G7 -> 0.024203597 | H44: =-H67/H7 -> 0.023770905 | I44: =-I67/I7 -> 0.029924574 | J44: =-J67/J7 -> 0.035166811 | K44: =-K67/K7 -> 0 | M44: =-M67/M7 -> 0 | N44: =-N67/N7 -> 0.063851925 | O44: =-O67/O7 -> 0 | P44: =-P67/P7 -> 0.05231159 | Q44: =-Q67/Q7 -> 0 | R44: =-R67/R7 -> 0.11499728 | S44: =-S67/S7 -> 0 | T44: =-T67/T7 -> 0.33437755 | ... AO44: =-AO67/AO7 -> 0
B46: EBITDA | C46: =C3 -> 43465 | D46: =D3 -> 43830 | E46: =E3 -> 44196 | F46: =F3 -> 44561 | G46: =G3 -> 44926 | H46: =H3 -> 45291 | I46: =I3 -> 45657 | J46: =J3 -> 46022 | K46: =K3 -> 46112 | M46: =M3 -> 43555 | N46: =N3 -> 43646 | O46: =O3 -> 43738 | P46: =P3 -> 43830 | Q46: =Q3 -> 43921 | R46: =R3 -> 44012 | S46: =S3 -> 44104 | T46: =T3 -> 44196 | ... AO46: =AO3 -> 46112
B47: Operating profit | C47: =C19 -> -11085.797 | D47: =D19 -> 2679.86 | E47: =E19 -> 4330.102 | F47: =F19 -> -23127.199 | G47: =G19 -> -5820.448 | H47: =H19 -> 13415.387 | I47: =I19 -> 36844.956 | J47: =J19 -> -25041.137 | K47: =K19 -> -42077.058 | M47: =M19 -> -1303.642 | N47: =N19 -> 1112.578 | O47: =O19 -> 1447.064 | P47: =P19 -> 1423.86 | Q47: =Q19 -> -1715.53 | R47: =R19 -> 2174.645 | S47: =S19 -> 6723.683 | T47: =T19 -> -2852.696 | ... AO47: =AO19 -> -6469.811
B48: Depreciation, depletion & amortization | C48: =451.241+4252.292 -> 4703.533 | D48: =3654.793+528.817 -> 4183.61 | E48: =4202.623+375.908 -> 4578.531 | F48: =321.09+8110.975 -> 8432.065 | G48: =64.362+9194.58 -> 9258.942 | H48: =62.744+7687.823 -> 7750.567 | I48: =68.522+8181.701 -> 8250.223 | J48: 10199.039 | K48: =SUM(AL48:AO48) -> 10820.228 | M48: =130.911+1472.412 -> 1603.323 | N48: =941.605+131.093 -> 1072.698 | O48: =693.563+131.037 -> 824.6 | P48: =D48-SUM(M48:O48) -> 682.989 | Q48: =664.094+131.636 -> 795.73 | R48: =831.195+93.615 -> 924.81 | S48: =1073.515+75.06 -> 1148.575 | T48: =E48-SUM(Q48:S48) -> 1709.416 | U48: =1721.069+76.603 -> 1797.672 | V48: =1811.03+76.215 -> 1887.245 | W48: =2105.868+78.383 -> 2184.251 | X48: =F48-SUM(U48:W48) -> 2562.897 | Y48: =2118.94+14.354 -> 2133.294 | Z48: =2239.674+16.92 -> 2256.594 | AA48: =17.05+2484.21 -> 2501.26 | AB48: =G48-SUM(Y48:AA48) -> 2367.794 | AC48: =1923.051+13.846 -> 1936.897 | AD48: =1917.587+17.062 -> 1934.649 | AE48: =15.799+1995.332 -> 2011.131 | AF48: =H48-SUM(AC48:AE48) -> 1867.89 | AG48: =1827.531+14.384 -> 1841.915 | AH48: =1991.201+18.392 -> 2009.593 | AI48: =2144.553+17.622 -> 2162.175 | AJ48: =I48-SUM(AG48:AI48) -> 2236.54 | AK48: =2169.265+14.047 -> 2183.312 | AL48: =2367.391+15.721 -> 2383.112 | AM48: =2614.462+16.116 -> 2630.578 | AN48: =J48-SUM(AK48:AM48) -> 3002.037 | AO48: =2786.713+17.788 -> 2804.501
B49: EBITDA | C49: =SUM(C47:C48) -> -6382.264 | D49: =SUM(D47:D48) -> 6863.47 | E49: =SUM(E47:E48) -> 8908.633 | F49: =SUM(F47:F48) -> -14695.134 | G49: =SUM(G47:G48) -> 3438.494 | H49: =SUM(H47:H48) -> 21165.954 | I49: =SUM(I47:I48) -> 45095.179 | J49: =SUM(J47:J48) -> -14842.098 | K49: =SUM(K47:K48) -> -31256.83 | M49: =SUM(M47:M48) -> 299.681 | N49: =SUM(N47:N48) -> 2185.276 | O49: =SUM(O47:O48) -> 2271.664 | P49: =SUM(P47:P48) -> 2106.849 | Q49: =SUM(Q47:Q48) -> -919.8 | R49: =SUM(R47:R48) -> 3099.455 | S49: =SUM(S47:S48) -> 7872.258 | T49: =SUM(T47:T48) -> -1143.28 | ... AO49: =SUM(AO47:AO48) -> -3665.31
B50: % growth | D50: =+D49/C49-1 -> -2.0753974 | E50: =+E49/D49-1 -> 0.29797799 | F50: =+F49/E49-1 -> -2.6495386 | G50: =+G49/F49-1 -> -1.2339886 | H50: =+H49/G49-1 -> 5.1555885 | I50: =+I49/H49-1 -> 1.1305526 | J50: =+J49/I49-1 -> -1.3291283 | Q50: =Q49/M49-1 -> -4.0692637 | R50: =R49/N49-1 -> 0.41833572 | S50: =S49/O49-1 -> 2.4654148 | U50: =U49/Q49-1 -> 2.2282398 | V50: =V49/R49-1 -> -1.4402258 | W50: =W49/S49-1 -> -2.0058588 | X50: =X49/T49-1 -> 1.1367985 | Y50: =Y49/U49-1 -> 0.16219558 | Z50: =Z49/V49-1 -> -2.2926403 | AA50: =AA49/W49-1 -> -1.4406813 | AB50: =AB49/X49-1 -> -1.6697632 | ... AO50: =AO49/AK49-1 -> -1.2874883
B51: % margin | C51: =+C49/C7 -> -0.097846548 | D51: =+D49/D7 -> 0.070373971 | E51: =+E49/E7 -> 0.077605044 | F51: =+F49/F7 -> -0.082037059 | G51: =+G49/G7 -> 0.015632719 | H51: =+H49/H7 -> 0.076481806 | I51: =+I49/I7 -> 0.1335791 | J51: =+J49/J7 -> -0.040679471 | K51: =+K49/K7 -> -0.084549327 | M51: =+M49/M7 -> 0.015629948 | N51: =+N49/N7 -> 0.096254363 | O51: =+O49/O7 -> 0.082625106 | P51: =+P49/P7 -> 0.074821723 | Q51: =+Q49/Q7 -> -0.054900693 | R51: =+R49/R7 -> 0.12537317 | S51: =+S49/S7 -> 0.22237212 | T51: =+T49/T7 -> -0.030151774 | ... AO51: =+AO49/AO7 -> -0.040260919
B53: Adjustment | C53: =C54-C49 -> 1648.433 | D53: =D54-D49 -> 390.164 | E53: =E54-E49 -> -4170.796 | F53: =F54-F49 -> 5001.058 | G53: =G54-G49 -> 6286.095 | H53: =H54-H49 -> 2712.064 | I53: =I54-I49 -> 4024.221 | J53: =J54-J49 -> 1058.893 | K53: =K54-K49 -> 2122.51 | M53: =M54-M49 -> 159.193 | N53: =N54-N49 -> 145.533 | O53: =O54-O49 -> 13.637 | P53: =P54-P49 -> 71.801 | Q53: =Q54-Q49 -> 961.111 | R53: =R54-R49 -> -489.2 | S53: =S54-S49 -> -5196.859 | T53: =T54-T49 -> 554.152 | ... AO53: =AO54-AO49 -> 615.881
B54: Adj. EBITDA | C54: -4733.831 | D54: 7253.634 | E54: 4737.837 | F54: -9694.076 | G54: 9724.589 | H54: 23878.018 | I54: 49119.4 | J54: -13783.205 | K54: =SUM(AL54:AO54) -> -29134.32 | M54: 458.874 | N54: 2330.809 | O54: 2285.301 | P54: =D54-SUM(M54:O54) -> 2178.65 | Q54: 41.311 | R54: 2610.255 | S54: 2675.399 | T54: =E54-SUM(Q54:S54) -> -589.128 | U54: -2382.683 | V54: -1239.986 | W54: -4061.659 | X54: =F54-SUM(U54:W54) -> -2009.748 | Y54: -1840.771 | Z54: 3802.741 | AA54: 4801.736 | AB54: =G54-SUM(Y54:AA54) -> 2960.883 | AC54: 6262.06 | AD54: 7682.351 | AE54: 6189.201 | AF54: =H54-SUM(AC54:AE54) -> 3744.406 | AG54: 8070.343 | AH54: 14997.268 | AI54: 14529.197 | AJ54: =I54-SUM(AG54:AI54) -> 11522.592 | AK54: 12301.686 | AL54: 2781.961 | AM54: -14841.897 | AN54: =J54-SUM(AK54:AM54) -> -14024.955 | AO54: -3049.429
B55: % growth | D55: =+D54/C54-1 -> -2.5322968 | E55: =+E54/D54-1 -> -0.34683264 | F55: =+F54/E54-1 -> -3.0460974 | G55: =+G54/F54-1 -> -2.0031476 | H55: =+H54/G54-1 -> 1.455427 | I55: =+I54/H54-1 -> 1.057097 | J55: =+J54/I54-1 -> -1.2806061 | Q55: =Q54/M54-1 -> -0.90997311 | R55: =R54/N54-1 -> 0.11989228 | S55: =S54/O54-1 -> 0.17069874 | T55: =T54/P54-1 -> -1.2704097 | U55: =U54/Q54-1 -> -58.67672 | V55: =V54/R54-1 -> -1.475044 | W55: =W54/S54-1 -> -2.5181508 | X55: =X54/T54-1 -> 2.4113945 | ... AO55: =AO54/AK54-1 -> -1.2478871
B56: % margin | C56: =+C54/C7 -> -0.072574407 | D56: =+D54/D7 -> 0.074374482 | E56: =+E54/E7 -> 0.041272331 | F56: =+F54/F7 -> -0.054118151 | G56: =+G54/G7 -> 0.044211731 | H56: =+H54/H7 -> 0.086281674 | I56: =+I54/I7 -> 0.14549948 | J56: =+J54/J7 -> -0.037777239 | K56: =+K54/K7 -> -0.078807965 | M56: =+M54/M7 -> 0.023932705 | N56: =+N54/N7 -> 0.10266462 | O56: =+O54/O7 -> 0.083121111 | P56: =+P54/P7 -> 0.077371632 | Q56: =+Q54/Q7 -> 0.0024657562 | R56: =+R54/R7 -> 0.10558499 | S56: =+S54/S7 -> 0.075573506 | T56: =+T54/T7 -> -0.015537099 | ... AO56: =+AO54/AO7 -> -0.033495888
B58: Capex sales | C58: =-C67/C7 -> 0.033506703 | D58: =-D67/D7 -> 0.029967046 | E58: =-E67/E7 -> 0.13521296 | F58: =-F67/F7 -> 0.04970879 | G58: =-G67/G7 -> 0.024203597 | H58: =-H67/H7 -> 0.023770905 | I58: =-I67/I7 -> 0.029924574 | J58: =-J67/J7 -> 0.035166811 | K58: =-K67/K7 -> 0 | M58: =-M67/M7 -> 0 | N58: =-N67/N7 -> 0.063851925 | O58: =-O67/O7 -> 0 | P58: =-P67/P7 -> 0.05231159 | Q58: =-Q67/Q7 -> 0 | R58: =-R67/R7 -> 0.11499728 | S58: =-S67/S7 -> 0 | T58: =-T67/T7 -> 0.33437755 | ... V58: =-V67/V7 -> 0.1251713 | X58: =-X67/X7 -> 0.069196672 | Z58: =-Z67/Z7 -> 0.060898227 | AB58: =-AB67/AB7 -> 0.036948016 | AF58: =-AF67/AF7 -> 0.064608407
B59: WC SALES | C59: =C63/C7 -> 0.0004395247 | D59: =D63/D7 -> 0.010377866 | E59: =E63/E7 -> 0.046499262 | F59: =F63/F7 -> 0.022852285 | G59: =G63/G7 -> -0.0036984119 | H59: =H63/H7 -> 0.048692956 | I59: =I63/I7 -> 0.019152045 | J59: =J63/J7 -> -0.0028941079 | K59: =K63/K7 -> 0 | M59: =M63/M7 -> 0 | N59: =N63/N7 -> 0 | O59: =O63/O7 -> 0 | P59: =P63/P7 -> 0.035944631 | Q59: =Q63/Q7 -> 0 | R59: =R63/R7 -> 0 | S59: =S63/S7 -> 0 | T59: =T63/T7 -> 0.14077562 | ... V59: =V63/V7 -> 0 | X59: =X63/X7 -> 0.082658018 | Z59: =Z63/Z7 -> 0 | AB59: =AB63/AB7 -> -0.013528993 | AF59: =AF63/AF7 -> 0.18285306
B61: CASH FLOW | C61: =C3 -> 43465 | D61: =D3 -> 43830 | E61: =E3 -> 44196 | F61: =F3 -> 44561 | G61: =G3 -> 44926 | H61: =H3 -> 45291 | I61: =I3 -> 45657 | J61: =J3 -> 46022 | K61: =K3 -> 46112 | M61: =M3 -> 43555 | N61: =N3 -> 43646 | O61: =O3 -> 43738 | P61: =P3 -> 43830 | Q61: =Q3 -> 43921 | R61: =R3 -> 44012 | S61: =S3 -> 44104 | T61: =T3 -> 44196 | ... AO61: =AO3 -> 46112
B62: Adj. EBITDA | C62: =C54 -> -4733.831 | D62: =D54 -> 7253.634 | E62: =E54 -> 4737.837 | F62: =F54 -> -9694.076 | G62: =G54 -> 9724.589 | H62: =H54 -> 23878.018 | I62: =I54 -> 49119.4 | J62: =J54 -> -13783.205 | N62: =N54 -> 2330.809 | P62: =D62-SUM(M62:O62) -> 4922.825 | R62: =R54 -> 2610.255 | T62: =E62-SUM(Q62:S62) -> 2127.582 | V62: =V54 -> -1239.986 | X62: =F62-SUM(U62:W62) -> -8454.09 | Z62: =Z54 -> 3802.741 | AB62: =G62-SUM(Y62:AA62) -> 5921.848 | AD62: =AD54 -> 7682.351 | AF62: =H62-SUM(AC62:AE62) -> 16195.667 | AH62: =AH54 -> 14997.268
B63: Working Capital | C63: =-135.879-168.664+2100.697-1767.485 -> 28.669 | D63: =-272.974+94.966+1291.272-101.126 -> 1012.138 | E63: =-381.667-191.265+3991.118+1919.674 -> 5337.86 | F63: =-746.561-40.579+3345.963+1534.661 -> 4093.484 | G63: =(-1327089-377239-150117-481072+2357980+1483065-87112-425105-1784268-22527)/1000 -> -813.484 | H63: =(-4760593-727944-1984534-141830+4381206+11368449+3467173+544757+1335720-6874)/1000 -> 13475.53 | I63: =(-185863-180257-3014154-428955+2992838+1328603+2599432+126556+3244784-17415)/1000 -> 6465.569 | J63: =(-2092785-735460-12918860-1281606+7767830+4098259+863304+598915+2642676+1798)/1000 -> -1055.929 | P63: =D63-SUM(M63:O63) -> 1012.138 | R63: 0 | T63: =E63-SUM(Q63:S63) -> 5337.86 | V63: 0 | X63: =F63-SUM(U63:W63) -> 4093.484 | Z63: 0 | AB63: =G63-SUM(Y63:AA63) -> -813.484 | AD63: 0 | AF63: =H63-SUM(AC63:AE63) -> 13475.53 | AH63: 0
B64: Taxes | C64: -198.629 | D64: -463.304 | E64: -86.311 | F64: -254.73 | G64: -247.258 | H64: -222.849 | I64: -789.636 | J64: -695.348 | N64: -127.598 | P64: =D64-SUM(M64:O64) -> -335.706 | R64: -90.714 | T64: =E64-SUM(Q64:S64) -> 4.403 | V64: -169.679 | X64: =F64-SUM(U64:W64) -> -85.051 | Z64: -115.143 | AB64: =G64-SUM(Y64:AA64) -> -132.115 | AD64: -143.608 | AF64: =H64-SUM(AC64:AE64) -> -79.241 | AH64: -254.609
B65: Cash interest paid | C65: -62.043 | D65: -218.692 | E65: -218.611 | F65: -620.127 | G65: -1162.162 | H65: -578.058 | I65: -427.053 | J65: -1281.447 | N65: -100.424 | P65: =D65-SUM(M65:O65) -> -118.268 | R65: -101.092 | T65: =E65-SUM(Q65:S65) -> -117.519 | V65: -249.748 | X65: =F65-SUM(U65:W65) -> -370.379 | Z65: -393.617 | AB65: =G65-SUM(Y65:AA65) -> -768.545 | AD65: -220.563 | AF65: =H65-SUM(AC65:AE65) -> -357.495 | AH65: -219.468
B66: Net cash from operations | C66: =SUM(C62:C65) -> -4965.834 | D66: =SUM(D62:D65) -> 7583.776 | E66: =SUM(E62:E65) -> 9770.775 | F66: =SUM(F62:F65) -> -6475.449 | G66: =SUM(G62:G65) -> 7501.685 | H66: =SUM(H62:H65) -> 36552.641 | I66: =SUM(I62:I65) -> 54368.28 | J66: =SUM(J62:J65) -> -16815.929 | N66: =SUM(N62:N65) -> 2102.787 | P66: =SUM(P62:P65) -> 5480.989 | R66: =SUM(R62:R65) -> 2418.449 | T66: =SUM(T62:T65) -> 7352.326 | V66: =SUM(V62:V65) -> -1659.413 | X66: =SUM(X62:X65) -> -4816.036 | Z66: =SUM(Z62:Z65) -> 3293.981 | AB66: =SUM(AB62:AB65) -> 4207.704 | AD66: =SUM(AD62:AD65) -> 7318.18 | AF66: =SUM(AF62:AF65) -> 29234.461 | AH66: =SUM(AH62:AH65) -> 14523.191
B67: Net Capex | C67: =-2210.249+24.698 -> -2185.551 | D67: =-2984.976+62.334-0 -> -2922.642 | E67: =-11222.56+279.764-4578.91 -> -15521.706 | F67: =-9010.455+106.219 -> -8904.236 | G67: =-5731.304+407.603 -> -5323.701 | H67: =-6879.551+301.073 -> -6578.478 | I67: =(-10999490+897206)/1000 -> -10102.284 | J67: =-13270.708+439.93 -> -12830.778 | N67: =-1463.481+13.842 -> -1449.639 | P67: =D67-SUM(M67:O67) -> -1473.003 | R67: =-2984.545+141.601 -> -2842.944 | T67: =E67-SUM(Q67:S67) -> -12678.762 | V67: =-3358.165+39.394-2158.629 -> -5477.4 | X67: =F67-SUM(U67:W67) -> -3426.836 | Z67: =-3222.881+120.825 -> -3102.056 | AB67: =G67-SUM(Y67:AA67) -> -2221.645 | AD67: =-1942.244+125.144 -> -1817.1 | AF67: =H67-SUM(AC67:AE67) -> -4761.378 | AH67: =-5770.528+286.851 -> -5483.677
B68: Purchase of intangible assets | C68: =-69.712+3.897 -> -65.815 | D68: =-16.76+1.938 -> -14.822 | E68: -22.966 | F68: 0 | G68: 0 | H68: 0 | I68: 0 | J68: 0 | N68: =-7.662+1.938 -> -5.724 | P68: =D68-SUM(M68:O68) -> -9.098 | R68: -8.447 | T68: =E68-SUM(Q68:S68) -> -14.519 | V68: -27.982 | X68: =F68-SUM(U68:W68) -> 27.982 | Z68: 0 | AB68: =G68-SUM(Y68:AA68) -> 0 | AD68: 0 | AF68: =H68-SUM(AC68:AE68) -> 0 | AH68: 0
B69: Disposals/ Acquistion, of subsidiaries, businesses | C69: -7260.087 | D69: -1365.975 | E69: -26.849 | F69: -13.786 | G69: -89.237 | H69: 365.114 | I69: -36.158 | J69: =-96.246+1.622 -> -94.624 | N69: =-449.764-1.025 -> -450.789 | P69: =D69-SUM(M69:O69) -> -915.186 | R69: 0 | T69: =E69-SUM(Q69:S69) -> -26.849 | V69: -867.327 | X69: =F69-SUM(U69:W69) -> 853.541 | Z69: -88.529 | AB69: =G69-SUM(Y69:AA69) -> -0.708 | AD69: -8.903 | AF69: =H69-SUM(AC69:AE69) -> 374.017 | AH69: -36.158
B70: Free cash flow | C70: =SUM(C66:C69) -> -14477.287 | D70: =SUM(D66:D69) -> 3280.337 | E70: =SUM(E66:E69) -> -5800.746 | F70: =SUM(F66:F69) -> -15393.471 | G70: =SUM(G66:G69) -> 2088.747 | H70: =SUM(H66:H69) -> 30339.277 | I70: =SUM(I66:I69) -> 44229.838 | J70: =SUM(J66:J69) -> -29741.331 | N70: =SUM(N66:N69) -> 196.635 | P70: =SUM(P66:P69) -> 3083.702 | R70: =SUM(R66:R69) -> -432.942 | T70: =SUM(T66:T69) -> -5367.804 | V70: =SUM(V66:V69) -> -8032.122 | X70: =SUM(X66:X69) -> -7361.349 | Z70: =SUM(Z66:Z69) -> 103.396 | AB70: =SUM(AB66:AB69) -> 1985.351 | AD70: =SUM(AD66:AD69) -> 5492.177 | AF70: =SUM(AF66:AF69) -> 24847.1 | AH70: =SUM(AH66:AH69) -> 9003.356
B71: Other Investing | C71: =-91205.155+75235.65-163.675+3453.916-1599.549+0.231+533.068+0-247.673 -> -13993.187 | D71: =-177154.553+170248.473-141.025+323.377-455.987+35.808+1315.886-35.365-20.954 -> -5884.34 | E71: =-196817.451+199496.075-2367.376+601.37-7326.69+1629.777-875.919-19.181 -> -5679.395 | F71: =-409062.234+364318.074+70.806-5040.733-867.327+996.319-1205.221+1234.179-42 -> -49598.137 | G71: =-187401.376+179619.759-40+1.63-3240.76+72.748+1438.076-736.914+874.424+42 -> -9370.413 | H71: =-24663.844-SUM(H67:H69) -> -18450.48 | I71: =10205.252-SUM(I67,I68,I69) -> 20343.694 | J71: =-84812.835+127476.188+3143.852+956.884-4011.142+164.484-230+10.839 -> 42698.27 | N71: =-93727.052+87301.456+323.377-338.893+566.346-14.607 -> -5889.373 | P71: =D71-SUM(M71:O71) -> 5.033 | R71: =-89623.882+93389.672+295.137-1190.123+821.471+37.081-96.385 -> 3632.971 | T71: =E71-SUM(Q71:S71) -> -9312.366 | V71: =-254715.588+246137.75+67.4-1691.595+599.022-470.483 -> -10073.494 | X71: =F71-SUM(U71:W71) -> -39524.643 | Z71: =-7446.679-Z69-Z68-Z67 -> -4256.094 | AB71: =G71-SUM(Y71:AA71) -> -5114.319 | AD71: =-10548.255-AD69-AD68-AD67 -> -8722.252 | AF71: =H71-SUM(AC71:AE71) -> -9728.228 | AH71: =28571.875-AH69-AH68-AH67 -> 34091.71
B72: Equity Issuance | C72: =28516.174-854.63 -> 27661.544 | D72: 0 | E72: 0 | F72: =45286.099 -> 45286.099 | G72: 170.341 | H72: 193.492 | I72: =(152038-26089621)/1000 -> -25937.583 | J72: =55.496-364.843 -> -309.347 | N72: 0 | P72: =D72-SUM(M72:O72) -> 0 | R72: =0.09 -> 0.09 | T72: =E72-SUM(Q72:S72) -> -0.09 | V72: =42694.27 -> 42694.27 | X72: =F72-SUM(U72:W72) -> 2591.829 | Z72: 90.827 | AB72: =G72-SUM(Y72:AA72) -> 79.514 | AD72: 116.877 | AF72: =H72-SUM(AC72:AE72) -> 76.615 | AH72: =24.644-12452.616 -> -12427.972
B73: Dividends | C73: =65.954-4 -> 61.954 | D73: 13.761 | E73: 18.912 | F73: 24.325 | G73: 69.782 | H73: =-2.45 -> -2.45 | I73: -3.185 | J73: 0 | N73: 9.701 | P73: =D73-SUM(M73:O73) -> 4.06 | R73: 17.197 | T73: =E73-SUM(Q73:S73) -> 1.715 | V73: 16.972 | X73: =F73-SUM(U73:W73) -> 7.353 | Z73: 0 | AB73: =G73-SUM(Y73:AA73) -> 69.782 | AD73: 0 | AF73: =H73-SUM(AC73:AE73) -> -2.45 | AH73: 0
B74: Net Change in debt | C74: =2305-1057 -> 1248 | D74: =3640-2250-785.825 -> 604.175 | E74: =10900.292-5448.702+13337.825-936.38 -> 17853.035 | F74: =25346.479-9578.283+19288.691-2191.299 -> 32865.588 | G74: =25844.975-32704.167-2619.636 -> -9478.828 | H74: =42809.865-42146.859-2969.089 -> -2306.083 | I74: =(20262380-21491985-3097904)/1000 -> -4327.509 | J74: =42232.27-5344.353-10719.867-3334.579 -> 22833.471 | N74: =1800-600 -> 1200 | P74: =D74-SUM(M74:O74) -> -595.825 | R74: =2467-2540 -> -73 | T74: =E74-SUM(Q74:S74) -> 17926.035 | V74: =13630.748-2791.956+19304.945 -> 30143.737 | X74: =F74-SUM(U74:W74) -> 2721.851 | Z74: =7163.269-3820.001-1362.87 -> 1980.398 | AB74: =G74-SUM(Y74:AA74) -> -11459.226 | AD74: =8357.508-8749.119-1480.645 -> -1872.256 | AF74: =H74-SUM(AC74:AE74) -> -433.827 | AH74: =2306.776-20791.985-1559.332 -> -20044.541
B75: Other financing activities | C75: =470+0-176.261+158.054 -> 451.793 | D75: =-107.969+467-75.162+444.915 -> 728.784 | E75: =-830.031+114.6+499.088 -> -216.343 | F75: =275.371+791.4 -> 1066.771 | G75: =480.448 -> 480.448 | H75: =278.72-366.924 -> -88.204 | I75: =(280670)/1000 -> 280.67 | J75: 0 | N75: =467-398.845+131.499 -> 199.654 | P75: =D75-SUM(M75:O75) -> 529.13 | R75: =-377.074+40.95-623.138+220.44 -> -738.822 | T75: =E75-SUM(Q75:S75) -> 522.479 | V75: =-878.633+791.4+89.319 -> 2.086 | X75: =F75-SUM(U75:W75) -> 1064.685 | Z75: =380.448 -> 380.448 | AB75: =G75-SUM(Y75:AA75) -> 100 | AD75: =278.72 -> 278.72 | AF75: =H75-SUM(AC75:AE75) -> -366.924 | AH75: =278.29 -> 278.29
B76: Cash flow after financing activities | C76: =SUM(C70:C75) -> 952.817 | D76: =SUM(D70:D75) -> -1257.283 | E76: =SUM(E70:E75) -> 6175.463 | F76: =SUM(F70:F75) -> 14251.175 | G76: =SUM(G70:G75) -> -16039.923 | H76: =SUM(H70:H75) -> 9685.552 | I76: =SUM(I70:I75) -> 34585.925 | J76: =SUM(J70:J75) -> 35481.063 | N76: =SUM(N70:N75) -> -4283.383 | P76: =SUM(P70:P75) -> 3026.1 | R76: =SUM(R70:R75) -> 2405.494 | T76: =SUM(T70:T75) -> 3769.969 | V76: =SUM(V70:V75) -> 54751.449 | X76: =SUM(X70:X75) -> -40500.274 | Z76: =SUM(Z70:Z75) -> -1701.025 | AB76: =SUM(AB70:AB75) -> -14338.898 | AD76: =SUM(AD70:AD75) -> -4706.734 | AF76: =SUM(AF70:AF75) -> 14392.286 | AH76: =SUM(AH70:AH75) -> 10900.843
B77: Balancing figure | C77: =-3323.21-C76 -> -4276.027 | D77: =-3485.531-D76 -> -2228.248 | E77: =4661.09-E76 -> -1514.373 | F77: =16095.04-F76 -> 1843.865 | G77: =-13292.322-G76 -> 2747.601 | H77: =13076.703-H76 -> 3391.151 | I77: =36937.376-I76 -> 2351.451 | J77: =37200.544-J76 -> 1719.481 | N77: =-6636.371-M76-M77-N76 -> -2352.988 | P77: =D77-SUM(M77:O77) -> 124.74 | R77: =431.111-R76-Q76-Q77 -> -1974.383 | T77: =E77-SUM(Q77:S77) -> 460.01 | V77: =54611.414-V76-U76-U77 -> -140.035 | X77: =F77-SUM(U77:W77) -> 1983.9 | Z77: =-7433.488-Z76-Y76-Y77 -> -5732.463 | AB77: =G77-SUM(Y77:AA77) -> 8480.064 | AD77: =6670.946-AD76-AC76-AC77 -> 11377.68 | AF77: =H77-SUM(AC77:AE77) -> -7986.529 | AH77: =21196.521-AH76-AG76-AG77 -> 10295.678
B78: FX | C78: 1009.587 | D78: -173.442 | E78: -963.716 | F78: -675.171 | G78: 937.5 | H78: 104.445 | I78: 556.967 | J78: -1263.275 | N78: -198.448 | P78: =D78-SUM(M78:O78) -> 25.006 | R78: 107.76 | T78: =E78-SUM(Q78:S78) -> -1071.476 | V78: -317.104 | X78: =F78-SUM(U78:W78) -> -358.067 | Z78: 457.066 | AB78: =G78-SUM(Y78:AA78) -> 480.434 | AD78: 173.486 | AF78: =H78-SUM(AC78:AE78) -> -69.041 | AH78: 167.893
B79: Net change in cash | C79: =SUM(C76:C78) -> -2313.623 | D79: =SUM(D76:D78) -> -3658.973 | E79: =SUM(E76:E78) -> 3697.374 | F79: =SUM(F76:F78) -> 15419.869 | G79: =SUM(G76:G78) -> -12354.822 | H79: =SUM(H76:H78) -> 13181.148 | I79: =SUM(I76:I78) -> 37494.343 | J79: =SUM(J76:J78) -> 35937.269 | N79: =SUM(N76:N78) -> -6834.819 | P79: =SUM(P76:P78) -> 3175.846 | R79: =SUM(R76:R78) -> 538.871 | T79: =SUM(T76:T78) -> 3158.503 | V79: =SUM(V76:V78) -> 54294.31 | X79: =SUM(X76:X78) -> -38874.441 | Z79: =SUM(Z76:Z78) -> -6976.422 | AB79: =SUM(AB76:AB78) -> -5378.4 | AD79: =SUM(AD76:AD78) -> 6844.432 | AF79: =SUM(AF76:AF78) -> 6336.716 | AH79: =SUM(AH76:AH78) -> 21364.414
B80: Cash and cash equivalents | C80: =19408.839+C79-51.524 -> 17043.692 | D80: =C80+D79+11.466 -> 13396.185 | E80: =D80+E79 -> 17093.559 | F80: =E80+F79 -> 32513.428 | G80: =F80+G79 -> 20158.606 | H80: =G80+H79 -> 33339.754 | I80: =H80+I79 -> 70834.097 | J80: =I80+J79 -> 106771.37 | N80: =C80+N79+28.377 -> 10237.25 | P80: =N80+P79+11.466-28.377 -> 13396.185 | R80: =D80+R79 -> 13935.056 | T80: =R80+T79 -> 17093.559 | V80: =E80+V79 -> 71387.869 | X80: =V80+X79 -> 32513.428 | Z80: =X80+Z79 -> 25537.006 | AB80: =Z80+AB79 -> 20158.606 | AD80: =AB80+AD79 -> 27003.038 | AF80: =AD80+AF79 -> 33339.754 | AH80: =AF80+AH79 -> 54704.168
B82: check 1 | C82: =+C80-C122 -> 0 | D82: =+D80-D122 -> 0 | E82: =+E80-E122 -> 0 | F82: =+F80-F122 -> 0 | G82: =+G80-G122 -> 0 | H82: =+H80-H122 -> 0 | I82: =+I80-I122 -> 0 | J82: =+J80-J122 -> 0 | N82: =+N80-N122 -> 0 | P82: =+P80-P122+49435.599 -> 49435.599 | R82: =+R80-R122+44522.946 -> 44522.946 | T82: =+T80-T122+43999.364 -> 43999.364 | V82: =+V80-V122 -> 0 | X82: =+X80-X122 -> 0 | Z82: =+Z80-Z122 -> 0 | AB82: =+AB80-AB122 -> 0 | AD82: =+AD80-AD122 -> 0 | AF82: =+AF80-AF122 -> 0 | AH82: =+AH80-AH122 -> 0
B83: check 2 | C83: =-9179.818-(C66+C77)+C65 -> -2.1529445e-12 | D83: =5574.22 -(D66+D77)+D65 -> -1.546141e-11 | E83: =8475.013-(E66+E77)+E65 -> 1.3528734e-11 | F83: =-4011.457-(F66+F77)+F65 -> 3.3651304e-11 | G83: =11411.448-(G66+G77)+G65 -> 0 | H83: =40521.85-(H66+H77)+H65 -> 4.5474735e-12 | I83: =57146.784-(I66+I77)+I65 -> 7.1622708e-12 | J83: =-13815.001-(J66+J77)+J65 -> -2.8876457e-11 | N83: =-149.777-(N66+N77)+N65 -> 9.1233687e-12 | R83: =545.338-(R66+R77)+R65 -> 0.18 | V83: =-1549.7-(V66+V77)+V65 -> 1.8246737e-11 | Z83: =-2044.865-(Z66+Z77)+Z65 -> 1.762146e-12 | AD83: =18916.423-(AD66+AD77)+AD65 -> -1.7053026e-12 | AH83: =25038.337-(AH66+AH77)+AH65 -> -2.8705927e-12
B85: LTM | C85: =C3 -> 43465 | D85: =D3 -> 43830 | E85: =E3 -> 44196 | F85: =F3 -> 44561 | G85: =G3 -> 44926 | H85: =H3 -> 45291 | I85: =I3 -> 45657 | J85: =J3 -> 46022 | K85: =K3 -> 46112 | M85: =M3 -> 43555 | N85: =N3 -> 43646 | O85: =O3 -> 43738 | P85: =P3 -> 43830 | Q85: =Q3 -> 43921 | R85: =R3 -> 44012 | S85: =S3 -> 44104 | T85: =T3 -> 44196 | ... AO85: =AO3 -> 46112
B86: =B7 -> Revenue | C86: =C7 -> 65227.278 | D86: =D7 -> 97528.531 | E86: =E7 -> 114794.51 | F86: =F7 -> 179128 | G86: =G7 -> 219954.95 | H86: =H7 -> 276744.95 | I86: =I7 -> 337591.58 | ... K86: =K7 -> 369687.51 | P86: =SUM(M7:P7) -> 97528.531 | Q86: =SUM(N7:Q7) -> 95108.906 | R86: =SUM(O7:R7) -> 97127.606 | S86: =SUM(P7:S7) -> 105035.26 | T86: =SUM(Q7:T7) -> 114794.51 | U86: =SUM(R7:U7) -> 135056.89 | V86: =SUM(S7:V7) -> 154094.28 | W86: =SUM(T7:W7) -> 167522.37 | ... AO86: =SUM(AL7:AO7) -> 369687.51
B87: Operating profit | C87: =C19 -> -11085.797 | D87: =D19 -> 2679.86 | E87: =E19 -> 4330.102 | F87: =F19 -> -23127.199 | G87: =G19 -> -5820.448 | H87: =H19 -> 13415.387 | I87: =I19 -> 36844.956 | J87: =J19 -> -25041.137 | K87: =K19 -> -42077.058 | P87: =SUM(M19:P19) -> 2679.86 | Q87: =SUM(N19:Q19) -> 2267.972 | R87: =SUM(O19:R19) -> 3330.039 | S87: =SUM(P19:S19) -> 8606.658 | T87: =SUM(Q19:T19) -> 4330.102 | U87: =SUM(R19:U19) -> 1278.625 | V87: =SUM(S19:V19) -> -4147.725 | W87: =SUM(T19:W19) -> -20974.039 | ... AO87: =SUM(AL19:AO19) -> -42077.058
B88: EBITDA | C88: =+C49 -> -6382.264 | D88: =+D49 -> 6863.47 | E88: =+E49 -> 8908.633 | F88: =+F49 -> -14695.134 | G88: =+G49 -> 3438.494 | H88: =+H49 -> 21165.954 | I88: =+I49 -> 45095.179 | J88: =+J49 -> -14842.098 | K88: =+K49 -> -31256.83 | P88: =SUM(M49:P49) -> 6863.47 | Q88: =SUM(N49:Q49) -> 5643.989 | R88: =SUM(O49:R49) -> 6558.168 | S88: =SUM(P49:S49) -> 12158.762 | T88: =SUM(Q49:T49) -> 8908.633 | U88: =SUM(R49:U49) -> 6859.098 | V88: =SUM(S49:V49) -> 2395.183 | W88: =SUM(T49:W49) -> -13395.455 | ... AO88: =SUM(AL49:AO49) -> -31256.83
B89: Adjusted EBITDA | C89: =+C54 -> -4733.831 | D89: =+D54 -> 7253.634 | E89: =+E54 -> 4737.837 | F89: =+F54 -> -9694.076 | G89: =+G54 -> 9724.589 | H89: =+H54 -> 23878.018 | I89: =+I54 -> 49119.4 | J89: =+J54 -> -13783.205 | K89: =+K54 -> -29134.32 | P89: =SUM(M54:P54) -> 7253.634 | Q89: =SUM(N54:Q54) -> 6836.071 | R89: =SUM(O54:R54) -> 7115.517 | S89: =SUM(P54:S54) -> 7505.615 | T89: =SUM(Q54:T54) -> 4737.837 | U89: =SUM(R54:U54) -> 2313.843 | V89: =SUM(S54:V54) -> -1536.398 | W89: =SUM(T54:W54) -> -8273.456 | ... AO89: =SUM(AL54:AO54) -> -29134.32
B90: Cash interest paid | C90: =-C65 -> 62.043 | D90: =-D65 -> 218.692 | E90: =-E65 -> 218.611 | F90: =-F65 -> 620.127 | G90: =-G65 -> 1162.162 | H90: =-H65 -> 578.058 | I90: =-I65 -> 427.053 | J90: =-J65 -> 1281.447 | P90: =-SUM(M65:P65) -> 218.692 | R90: =-SUM(O65:R65) -> 219.36 | T90: =-SUM(Q65:T65) -> 218.611 | V90: =-SUM(S65:V65) -> 367.267 | X90: =-SUM(U65:X65) -> 620.127 | Z90: =-SUM(W65:Z65) -> 763.996 | AB90: =-SUM(Y65:AB65) -> 1162.162 | AD90: =-SUM(AA65:AD65) -> 989.108 | AF90: =-SUM(AC65:AF65) -> 578.058 | AH90: =-SUM(AE65:AH65) -> 576.963 | AJ90: =-SUM(AG65:AJ65) -> 219.468
B91: Net Income | C91: =+C26 -> -115492.7 | D91: =+D26 -> 2236.165 | E91: =+E26 -> 4707.612 | F91: =+F26 -> -23536.198 | G91: =+G26 -> -6685.323 | H91: =+H26 -> 13857.331 | I91: =+I26 -> 35808.322 | J91: =+J26 -> -23354.194 | K91: =+K26 -> -40238.332 | P91: =SUM(M26:P26) -> 2236.165 | Q91: =SUM(N26:Q26) -> 2090.217 | R91: =SUM(O26:R26) -> 3424.57 | S91: =SUM(P26:S26) -> 8412.189 | T91: =SUM(Q26:T26) -> 4659.568 | U91: =SUM(R26:U26) -> 1392.584 | V91: =SUM(S26:V26) -> -4173.972 | W91: =SUM(T26:W26) -> -20489.383 | ... AO91: =SUM(AL26:AO26) -> -40238.332
B92: Capex | C92: =-C67 -> 2185.551 | D92: =-D67 -> 2922.642 | E92: =-E67 -> 15521.706 | F92: =-F67 -> 8904.236 | G92: =-G67 -> 5323.701 | H92: =-H67 -> 6578.478 | I92: =-I67 -> 10102.284 | J92: =-J67 -> 12830.778 | P92: =-SUM(M67:P67) -> 2922.642 | R92: =-SUM(O67:R67) -> 4315.947 | T92: =-SUM(Q67:T67) -> 15521.706 | V92: =-SUM(S67:V67) -> 18156.162 | X92: =-SUM(U67:X67) -> 8904.236 | Z92: =-SUM(W67:Z67) -> 6528.892 | AB92: =-SUM(Y67:AB67) -> 5323.701 | AD92: =-SUM(AA67:AD67) -> 4038.745 | AF92: =-SUM(AC67:AF67) -> 6578.478 | AH92: =-SUM(AE67:AH67) -> 10245.055 | AJ92: =-SUM(AG67:AJ67) -> 5483.677
B93: Free cash flow | C93: =+C70 -> -14477.287 | D93: =+D70 -> 3280.337 | E93: =+E70 -> -5800.746 | F93: =+F70 -> -15393.471 | G93: =+G70 -> 2088.747 | H93: =+H70 -> 30339.277 | I93: =+I70 -> 44229.838 | J93: =+J70 -> -29741.331 | P93: =SUM(M70:P70) -> 3280.337 | R93: =SUM(O70:R70) -> 2650.76 | T93: =SUM(Q70:T70) -> -5800.746 | V93: =SUM(S70:V70) -> -13399.926 | X93: =SUM(U70:X70) -> -15393.471 | Z93: =SUM(W70:Z70) -> -7257.953 | AB93: =SUM(Y70:AB70) -> 2088.747 | AD93: =SUM(AA70:AD70) -> 7477.528 | AF93: =SUM(AC70:AF70) -> 30339.277 | AH93: =SUM(AE70:AH70) -> 33850.456 | AJ93: =SUM(AG70:AJ70) -> 9003.356
B95: BALANCE SHEET | C95: =C3 -> 43465 | D95: =D3 -> 43830 | E95: =E3 -> 44196 | F95: =F3 -> 44561 | G95: =G3 -> 44926 | H95: =H3 -> 45291 | I95: =I3 -> 45657 | J95: =J3 -> 46022 | K95: =K3 -> 46112 | M95: =M3 -> 43555 | N95: =N3 -> 43646 | O95: =O3 -> 43738 | P95: =P3 -> 43830 | Q95: =Q3 -> 43921 | R95: =R3 -> 44012 | S95: =S3 -> 44104 | T95: =T3 -> 44196 | ... AO95: =AO3 -> 46112
B97: Tangible fixed assets | C97: 3978.815 | D97: 5376.217 | E97: 13917.165 | F97: 22814.246 | G97: 22201.259 | H97: 25977.845 | I97: 30238.782 | J97: 38705.474 | K97: =AO97 -> 40260.115 | M97: 5298.343 | N97: 4794.748 | O97: 4900.374 | P97: =D97 -> 5376.217 | Q97: 5270.297 | R97: 7445.625 | S97: 12923.529 | T97: =E97 -> 13917.165 | U97: 13696.617 | V97: 14609.59 | W97: 22493.671 | X97: =F97 -> 22814.246 | Y97: 23077.99 | Z97: 23192.26 | AA97: 22820.527 | AB97: =G97 -> 22201.259 | AC97: 21719.181 | AD97: 21918.108 | AE97: 24288.933 | AF97: =H97 -> 25977.845 | AG97: 26734.801 | AH97: 29493.278 | AI97: 30386.798 | AJ97: =I97 -> 30238.782 | AK97: 32134.464 | AL97: 34026.066 | AM97: 38272.328 | AN97: =J97 -> 38705.474 | AO97: 40260.115
B98: Inventory | C98: 400.244 | D98: 275.227 | E98: 466.492 | F98: 681.693 | G98: 1162.765 | H98: 1304.595 | I98: 1734.124 | J98: 3012.552 | K98: =AO98 -> 3530.738 | M98: 286.976 | N98: 286.387 | O98: 302.425 | P98: =D98 -> 275.227 | Q98: 261.197 | R98: 284.411 | S98: 388.059 | T98: =E98 -> 466.492 | U98: 477.874 | V98: 504.035 | W98: 658.066 | X98: =F98 -> 681.693 | Y98: 733.173 | Z98: 885.678 | AA98: 1018.39 | AB98: =G98 -> 1162.765 | AC98: 1034.947 | AD98: 1231.329 | AE98: 1363.506 | AF98: =H98 -> 1304.595 | AG98: 1340.367 | AH98: 1421.295 | AI98: 1774.941 | AJ98: =I98 -> 1734.124 | AK98: 1901.133 | AL98: 2483.059 | AM98: 3108.807 | AN98: =J98 -> 3012.552 | AO98: 3530.738
B99: Trade accounts receivable | C99: 466.34 | D99: 676.762 | E99: 1030.948 | F99: 1793.035 | G99: 2052.731 | H99: 2742.999 | I99: 2653.046 | J99: 3322.73 | K99: =AO99 -> 3769.352 | M99: 481.863 | N99: 590.787 | O99: 783.566 | P99: =D99 -> 676.762 | Q99: 921.268 | R99: 859.73 | S99: 928.258 | T99: =E99 -> 1030.948 | U99: 1226.481 | V99: 1445.305 | W99: 1656.826 | X99: =F99 -> 1793.035 | Y99: 1871.786 | Z99: 2264.161 | AA99: 2007.97 | AB99: =G99 -> 2052.731 | AC99: 2304.572 | AD99: 2432.368 | AE99: 2932.592 | AF99: =H99 -> 2742.999 | AG99: 3004.572 | AH99: 2934.479 | AI99: 3251.772 | AJ99: =I99 -> 2653.046 | AK99: 2898.096 | AL99: 3141.262 | AM99: 3464.068 | AN99: =J99 -> 3322.73 | AO99: 3769.352
B100: Trade accounts payable | C100: =5340.963+7596.388 -> 12937.351 | D100: =6766.253+7495.262 -> 14261.515 | E100: =11967.026+9414.936 -> 21381.962 | F100: =15165.619+10950.92 -> 26116.539 | G100: =17379.302+12432.342 -> 29811.644 | H100: =22980.506+23798.004 -> 46778.51 | I100: =25193.149+25131.85 -> 50324.999 | J100: =34571.567+29197.5 -> 63769.067 | K100: =AO100 -> 57594.739 | M100: =4661.595+6433.197 -> 11094.792 | N100: =4669.865+7403.989 -> 12073.854 | O100: =5434.038+6116.131 -> 11550.169 | P100: =D100 -> 14261.515 | Q100: =4612.501+4073.672 -> 8686.173 | R100: =7332.014+6366.529 -> 13698.543 | S100: =9649.311+7586.545 -> 17235.856 | T100: =E100 -> 21381.962 | U100: =10188.187+8704.278 -> 18892.465 | V100: =12114.001+10198.454 -> 22312.455 | W100: =13345.537+9746.092 -> 23091.629 | X100: =F100 -> 26116.539 | Y100: =13723.083+7849.488 -> 21572.571 | Z100: =13862.818+10886.742 -> 24749.56 | AA100: =(14698861+10603688)/1000 -> 25302.549 | AB100: =G100 -> 29811.644 | AC100: =15238.051+13295.238 -> 28533.289 | AD100: =18455.867+16826.275 -> 35282.142 | AE100: =(21339403+20169408)/1000 -> 41508.811 | AF100: =H100 -> 46778.51 | AG100: =20296.212+21219.259 -> 41515.471 | AH100: =23021.223+24753.978 -> 47775.201 | AI100: =23827.495+21975.777 -> 45803.272 | AJ100: =I100 -> 50324.999 | AK100: =25372.957+24794.04 -> 50166.997 | AL100: =29253.286+27147.069 -> 56400.355 | AM100: =30682.686+25645.751 -> 56328.437 | AN100: =J100 -> 63769.067 | AO100: =31613.146+25981.593 -> 57594.739
B101: Net working capital | C101: =+C98+C99-C100 -> -12070.767 | D101: =+D98+D99-D100 -> -13309.526 | E101: =+E98+E99-E100 -> -19884.522 | F101: =+F98+F99-F100 -> -23641.811 | G101: =+G98+G99-G100 -> -26596.148 | H101: =+H98+H99-H100 -> -42730.916 | I101: =+I98+I99-I100 -> -45937.829 | J101: =+J98+J99-J100 -> -57433.785 | K101: =+K98+K99-K100 -> -50294.649 | M101: =+M98+M99-M100 -> -10325.953 | N101: =+N98+N99-N100 -> -11196.68 | O101: =+O98+O99-O100 -> -10464.178 | P101: =+P98+P99-P100 -> -13309.526 | Q101: =+Q98+Q99-Q100 -> -7503.708 | R101: =+R98+R99-R100 -> -12554.402 | S101: =+S98+S99-S100 -> -15919.539 | T101: =+T98+T99-T100 -> -19884.522 | ... AO101: =+AO98+AO99-AO100 -> -50294.649
B102: % of revenues | C102: =+C101/C86 -> -0.18505704 | D102: =+D101/D86 -> -0.13646802 | E102: =+E101/E86 -> -0.17321841 | F102: =+F101/F86 -> -0.13198278 | G102: =+G101/G86 -> -0.12091634 | H102: =+H101/H86 -> -0.1544054 | I102: =+I101/I86 -> -0.13607516 | J102: =+J101/J86 -> -0.15741548 | K102: =+K101/K86 -> -0.13604639 | P102: =+P101/P86 -> -0.13646802 | Q102: =+Q101/Q86 -> -0.078895955 | R102: =+R101/R86 -> -0.12925678 | S102: =+S101/S86 -> -0.15156376 | T102: =+T101/T86 -> -0.17321841 | U102: =+U101/U86 -> -0.12726571 | V102: =+V101/V86 -> -0.13214712 | W102: =+W101/W86 -> -0.12402366 | ... AO102: =+AO101/AO86 -> -0.13604639
B104: Inventory Days | C104: =IFERROR((C98/-C9)*365,"-") -> 2.9146508 | D104: =IFERROR((D98/-D9)*365,"-") -> 1.5405722 | E104: =IFERROR((E98/-E9)*365,"-") -> 2.1087487 | F104: =IFERROR((F98/-F9)*365,"-") -> 1.8207896 | G104: =IFERROR((G98/-G9)*365,"-") -> 2.6827051 | H104: =IFERROR((H98/-H9)*365,"-") -> 2.6520029 | I104: =IFERROR((I98/-I9)*365,"-") -> 3.0458806 | J104: =IFERROR((J98/-J9)*365,"-") -> 4.3316852 | K104: =IFERROR((K98/-K9)*365,"-") -> 4.8672885 | M104: =IFERROR((M98/-M9)*(365/4),"-") -> 1.8566535 | N104: =IFERROR((N98/-N9)*(365/4),"-") -> 1.7702158 | O104: =IFERROR((O98/-O9)*(365/4),"-") -> 1.5415759 | P104: =IFERROR((P98/-P9)*(365/4),"-") -> 1.3619466 | Q104: =IFERROR((Q98/-Q9)*(365/4),"-") -> 2.0622444 | R104: =IFERROR((R98/-R9)*(365/4),"-") -> 1.6072768 | S104: =IFERROR((S98/-S9)*(365/4),"-") -> 1.440719 | T104: =IFERROR((T98/-T9)*(365/4),"-") -> 1.4955977 | ... AO104: =IFERROR((AO98/-AO9)*(365/4),"-") -> 4.9513695
B105: Receivable Days | C105: =IFERROR((C99/C7)*365,"-") -> 2.6095539 | D105: =IFERROR((D99/D7)*365,"-") -> 2.5327781 | E105: =IFERROR((E99/E7)*365,"-") -> 3.2779967 | F105: =IFERROR((F99/F7)*365,"-") -> 3.6535761 | G105: =IFERROR((G99/G7)*365,"-") -> 3.4063649 | H105: =IFERROR((H99/H7)*365,"-") -> 3.6177521 | I105: =IFERROR((I99/I7)*365,"-") -> 2.8684418 | J105: =IFERROR((J99/J7)*365,"-") -> 3.3240528 | K105: =IFERROR((K99/K7)*365,"-") -> 3.7215579 | M105: =IFERROR((M99/M7)*(365/4),"-") -> 2.2932679 | N105: =IFERROR((N99/N7)*(365/4),"-") -> 2.3745315 | O105: =IFERROR((O99/O7)*(365/4),"-") -> 2.6006169 | P105: =IFERROR((P99/P7)*(365/4),"-") -> 2.1931237 | Q105: =IFERROR((Q99/Q7)*(365/4),"-") -> 5.0176837 | R105: =IFERROR((R99/R7)*(365/4),"-") -> 3.1733225 | S105: =IFERROR((S99/S7)*(365/4),"-") -> 2.3926688 | T105: =IFERROR((T99/T7)*(365/4),"-") -> 2.4810179 | ... AO105: =IFERROR((AO99/AO7)*(365/4),"-") -> 3.7780921
B106: Payable Days | C106: =IFERROR((C100/-C9)*365,"-") -> 94.212182 | D106: =IFERROR((D100/-D9)*365,"-") -> 79.828266 | E106: =IFERROR((E100/-E9)*365,"-") -> 96.655858 | F106: =IFERROR((F100/-F9)*365,"-") -> 69.756801 | G106: =IFERROR((G100/-G9)*365,"-") -> 68.78075 | H106: =IFERROR((H100/-H9)*365,"-") -> 95.09215 | I106: =IFERROR((I100/-I9)*365,"-") -> 88.392721 | J106: =IFERROR((J100/-J9)*365,"-") -> 91.692201 | K106: =IFERROR((K100/-K9)*365,"-") -> 79.397059 | M106: =IFERROR((M100/-M9)*(365/4),"-") -> 71.780163 | N106: =IFERROR((N100/-N9)*(365/4),"-") -> 74.630925 | O106: =IFERROR((O100/-O9)*(365/4),"-") -> 58.875628 | P106: =IFERROR((P100/-P9)*(365/4),"-") -> 70.572369 | Q106: =IFERROR((Q100/-Q9)*(365/4),"-") -> 68.580463 | R106: =IFERROR((R100/-R9)*(365/4),"-") -> 77.413849 | S106: =IFERROR((S100/-S9)*(365/4),"-") -> 63.990332 | T106: =IFERROR((T100/-T9)*(365/4),"-") -> 68.551686 | ... AO106: =IFERROR((AO100/-AO9)*(365/4),"-") -> 80.76862
B108: Debt Breakdown
B109: Short-term debt | C109: 1800 | D109: 3552.587 | E109: =6395.002+61.732 -> 6456.734 | F109: =11565.2+60.32 -> 11625.52 | G109: =17562.145 -> 17562.145 | H109: =19321.793 -> 19321.793 | I109: =1.079+16567.532 -> 16568.611 | J109: =3467.861+10911.217 -> 14379.078 | K109: =AO109 -> 16715.527 | M109: 2100 | N109: 3000 | O109: 3140 | P109: =D109 -> 3552.587 | Q109: 3557.738 | R109: 3323.694 | S109: 7864.604 | T109: =E109 -> 6456.734 | U109: 7074.497 | V109: =11562.939 -> 11562.939 | W109: 13733.389 | X109: =F109 -> 11625.52 | Y109: 11716.262 | Z109: 11010.575 | AA109: 16326.875 | AB109: =G109 -> 17562.145 | AC109: 17638.409 | AD109: 18591.787 | AE109: =(19758266+2002521)/1000 -> 21760.787 | AF109: =H109 -> 19321.793 | AG109: =11077.508 -> 11077.508 | AH109: 698.79 | AI109: =0.843+10462.767 -> 10463.61 | AJ109: =I109 -> 16568.611 | AK109: =1.322+16806.301 -> 16807.623 | AL109: =1.342+16319.467 -> 16320.809 | AM109: =1.436+16203.785 -> 16205.221 | AN109: =J109 -> 14379.078 | AO109: =11334.607+5380.92 -> 16715.527
B110: Long-term debt | C110: 470.056 | D110: 466.676 | E110: =1957.47+12966.341 -> 14923.811 | F110: =12219.667+30383.378 -> 42603.045 | G110: =1548.967+33607.372 -> 35156.339 | H110: =610.103+34610.966 -> 35221.069 | I110: =1175.045+38009.069 -> 39184.114 | J110: =18789.267+47114.754 -> 65904.021 | K110: =AO110 -> 89390.246 | M110: 470.179 | N110: 936.854 | O110: 937.043 | P110: =D110 -> 466.676 | Q110: 466.738 | R110: 0 | S110: 0 | T110: =E110 -> 14923.811 | U110: 1971.39 | V110: =7591.91+30594.676 -> 38186.586 | W110: =10635.57+30810.312 -> 41445.882 | X110: =F110 -> 42603.045 | Y110: =15338.68+30346.15 -> 45684.83 | Z110: =17472.962+32183.012 -> 49655.974 | AA110: =(10439365+34152622)/1000 -> 44591.987 | AB110: =G110 -> 35156.339 | AC110: =1625.178+33262.808 -> 34887.986 | AD110: =35087.533+275.45 -> 35362.983 | AE110: =(34974799+418050)/1000 -> 35392.849 | AF110: =H110 -> 35221.069 | AG110: =736.522+35541.738 -> 36278.26 | AH110: =816.894+25190.723 -> 26007.617 | AI110: =24206.21+999.622 -> 25205.832 | AJ110: =I110 -> 39184.114 | AK110: =1456.088+37803.914 -> 39260.002 | AL110: =1657.023+26835.731 -> 28492.754 | AM110: =1981.875+26730.917 -> 28712.792 | AN110: =J110 -> 65904.021 | AO110: =42686.825+46703.421 -> 89390.246
B111: Total Debt | C111: =SUM(C109:C110) -> 2270.056 | D111: =SUM(D109:D110) -> 4019.263 | E111: =SUM(E109:E110) -> 21380.545 | F111: =SUM(F109:F110) -> 54228.565 | G111: =SUM(G109:G110) -> 52718.484 | H111: =SUM(H109:H110) -> 54542.862 | I111: =SUM(I109:I110) -> 55752.725 | J111: =SUM(J109:J110) -> 80283.099 | K111: =SUM(K109:K110) -> 106105.77 | M111: =SUM(M109:M110) -> 2570.179 | N111: =SUM(N109:N110) -> 3936.854 | O111: =SUM(O109:O110) -> 4077.043 | P111: =SUM(P109:P110) -> 4019.263 | Q111: =SUM(Q109:Q110) -> 4024.476 | R111: =SUM(R109:R110) -> 3323.694 | S111: =SUM(S109:S110) -> 7864.604 | T111: =SUM(T109:T110) -> 21380.545 | ... AO111: =SUM(AO109:AO110) -> 106105.77
B113: Lease Obligations
B114: Short-term | C114: 0 | D114: 534.566 | E114: 1089.847 | F114: 1756.559 | G114: 2165.978 | H114: 2479.785 | I114: 2622.066 | J114: 2737.789 | K114: =AO114 -> 2829.87 | M114: =544.931+58.492 -> 603.423 | N114: =472.73+10.744 -> 483.474 | O114: 538.787 | P114: =D114 -> 534.566 | Q114: 545.563 | R114: 628.976 | S114: 817.605 | T114: =E114 -> 1089.847 | U114: 1301.337 | V114: 1424.446 | W114: 1480.017 | X114: =F114 -> 1756.559 | Y114: 1801.067 | Z114: 1899.831 | AA114: 2011.043 | AB114: =G114 -> 2165.978 | AC114: 2077.899 | AD114: 2102.205 | AE114: 2306.424 | AF114: =H114 -> 2479.785 | AG114: 2362.936 | AH114: 2398.698 | AI114: 2544.12 | AJ114: =I114 -> 2622.066 | AK114: 2686.634 | AL114: 2838.077 | AM114: 2806.053 | AN114: =J114 -> 2737.789 | AO114: 2829.87
...

Sheet EBITDA
B2: Meituan | C2: Annual | D2: Annual | E2: Annual | G2: Quarters | H2: Quarters | I2: Quarters | J2: Quarters | K2: Quarters | L2: Quarters | M2: Quarters | N2: Quarters | O2: Quarters
B3: (RMB million) | C3: 45291 | D3: 45657 | E3: 46022 | G3: 45382 | H3: 45473 | I3: 45565 | J3: 45657 | K3: 45747 | L3: 45838 | M3: 45930 | N3: 46022 | O3: 46112
C4: Act | D4: Act | E4: Act | G4: Act | H4: Act | I4: Act | J4: Act | K4: Act | L4: Act | M4: Act | N4: Act | O4: Act
C5: FY | D5: FY | E5: FY | G5: 1Q | H5: 2Q | I5: 3Q | J5: 4Q | K5: 1Q | L5: 2Q | M5: 3Q | N5: 4Q | O5: 1Q
B9: Profit for the period | C9: 13857.331 | D9: 35808.322 | E9: -23354.194 | G9: 5368.979 | H9: 11352.338 | I9: 12864.954 | J9: 6222.051 | K9: 10056.88 | L9: 365.296 | M9: -18632.088 | N9: -15144.282 | O9: -6827.258
B10: Adjusted for:
B11: Share-based compensation expenses | C11: 8383.353 | D11: 7582.693 | E11: 6001.867 | G11: 1851.012 | H11: 2069.327 | I11: 1890.022 | J11: 1772.332 | K11: 1707.846 | L11: 1387.416 | M11: 1558.306 | N11: 1348.299 | O11: 1383.006
B12: Foreign exchange (gains)/losses from intercompany balances | C12: 0 | D12: 119.455 | E12: -1512.297 | G12: 0 | H12: 0 | I12: -1548.588 | J12: 1668.043 | K12: -265.904 | L12: -464.206 | M12: -153.975 | N12: -628.212 | O12: -312.006
B13: Net (gains)/losses from investments | C13: 12.486 | D13: -192.795 | E13: -2334.922 | G13: 359.322 | H13: -62.507 | I13: -567.679 | J13: 78.069 | K13: -777.438 | L13: -355.455 | M13: 335.243 | N13: -1537.272 | O13: -389.746
B14: Impairment and expense provision | C14: 817.785 | D14: 202.48 | E14: 2060.775 | G14: 0 | H14: 129.153 | I14: 0 | J14: 73.327 | K14: 0 | L14: 428.137 | M14: 1017.919 | N14: 614.719 | O14: 1094.032
B15: Amortisation of intangible assets resulting from acquisitions | C15: 246.19 | D15: 171.127 | E15: 199.888 | G15: 42.84 | H15: 42.841 | I15: 42.841 | J15: 42.605 | K15: 45.187 | L15: 51.504 | M15: 51.504 | N15: 51.693 | O15: 51.694
B16: Tax effects | C16: -63.727 | D16: 81.167 | E16: 290.882 | G16: -133.759 | H16: 75.104 | I16: 147.711 | J16: -7.889 | K16: 181.933 | L16: 80.343 | M16: -186.543 | N16: 215.149 | O16: 32.375
B17: Adjusted net profit | C17: =SUM(C9:C16) -> 23253.418 | D17: =SUM(D9:D16) -> 43772.449 | E17: =SUM(E9:E16) -> -18648.001 | G17: =SUM(G9:G16) -> 7488.394 | H17: =SUM(H9:H16) -> 13606.256 | I17: =SUM(I9:I16) -> 12829.261 | J17: =SUM(J9:J16) -> 9848.538 | K17: =SUM(K9:K16) -> 10948.504 | L17: =SUM(L9:L16) -> 1493.035 | M17: =SUM(M9:M16) -> -16009.634 | N17: =SUM(N9:N16) -> -15079.906 | O17: =SUM(O9:O16) -> -4967.903
B19: Adjusted for:
B20: Income tax expenses not adjusted for adjusted net profit | C20: 228.264 | D20: 2095.94 | E20: -1774.2 | G20: 246.261 | H20: 229.772 | I20: 937.769 | J20: 682.138 | K20: 361.988 | L20: -51.973 | M20: -831.793 | N20: -1252.422 | O20: -481.98
B21: Share of profits of investments accounted for using the equity method not adjusted for adjusted net profit | C21: -1554.673 | D21: -934.361 | E21: 13.07 | G21: -143.376 | H21: -93.96 | I21: -385.3 | J21: -311.725 | K21: -30.765 | L21: -141.766 | M21: 45.935 | N21: 139.666 | O21: 503.603
B22: Finance income | C22: -818.986 | D22: -1291.807 | E22: -2011.535 | G22: -279.755 | H22: -344.494 | I22: -313.088 | J22: -354.47 | K22: -491.358 | L22: -508.307 | M22: -513.372 | N22: -498.498 | O22: -481.926
B23: Finance costs | C23: 1425.157 | D23: 1337.038 | E23: 1886.802 | G23: 321.863 | H23: 285.373 | I23: 261.651 | J23: 468.151 | K23: 475.12 | L23: 430.214 | M23: 413.987 | N23: 567.481 | O23: 786.977
B24: Certain items in other gains, net | C24: -6405.729 | D24: -4110.082 | E24: -3248.492 | G24: -1404.959 | H24: -695.272 | I24: -963.271 | J24: -1046.58 | K24: -1145.115 | L24: -822.354 | M24: -577.598 | N24: -703.425 | O24: -1212.618
B25: Amortisation of software and others | C25: 62.744 | D25: 68.522 | E25: 62.52 | G25: 14.384 | H25: 18.392 | I25: 17.622 | J25: 18.124 | K25: 14.047 | L25: 15.721 | M25: 16.116 | N25: 16.636 | O25: 17.788
B26: Depreciation of property, plant and equipment | C26: 7687.823 | D26: 8181.701 | E26: 9936.631 | G26: 1827.531 | H26: 1991.201 | I26: 2144.553 | J26: 2218.416 | K26: 2169.265 | L26: 2367.391 | M26: 2614.462 | N26: 2785.513 | O26: 2786.713
B27: Adjusted EBITDA | C27: =SUM(C20:C26,C17) -> 23878.018 | D27: =SUM(D20:D26,D17) -> 49119.4 | E27: =SUM(E20:E26,E17) -> -13783.205 | G27: =SUM(G20:G26,G17) -> 8070.343 | H27: =SUM(H20:H26,H17) -> 14997.268 | I27: =SUM(I20:I26,I17) -> 14529.197 | J27: =SUM(J20:J26,J17) -> 11522.592 | K27: =SUM(K20:K26,K17) -> 12301.686 | L27: =SUM(L20:L26,L17) -> 2781.961 | M27: =SUM(M20:M26,M17) -> -14841.897 | N27: =SUM(N20:N26,N17) -> -14024.955 | O27: =SUM(O20:O26,O17) -> -3049.346

Sheet KPIs
B2: Meituan | C2: Annual | D2: Annual | E2: Annual | F2: Annual | G2: Annual | H2: Annual | I2: Annual | J2: Annual | K2: LTM | M2: Quarters | N2: Quarters | O2: Quarters | P2: Quarters | Q2: Quarters | R2: Quarters | S2: Quarters | T2: Quarters | U2: Quarters | V2: Quarters | W2: Quarters | X2: Quarters | Y2: Quarters | Z2: Quarters | AA2: Quarters | AB2: Quarters | AC2: Quarters | AD2: Quarters | AE2: Quarters | AF2: Quarters | AG2: Quarters | AH2: Quarters | AI2: Quarters | AJ2: Quarters | AK2: Quarters | AL2: Quarters | AM2: Quarters | AN2: Quarters | AO2: Quarters
B3: (RMB million) | C3: 43465 | D3: 43830 | E3: 44196 | F3: 44561 | G3: 44926 | H3: 45291 | I3: 45657 | J3: 46022 | K3: =AO3 -> 46112 | M3: 43555 | N3: 43646 | O3: 43738 | P3: 43830 | Q3: 43921 | R3: 44012 | S3: 44104 | T3: 44196 | U3: 44286 | V3: 44377 | W3: 44469 | X3: 44561 | Y3: 44651 | Z3: 44742 | AA3: 44834 | AB3: 44926 | AC3: 45016 | AD3: 45107 | AE3: 45199 | AF3: 45291 | AG3: 45382 | AH3: 45473 | AI3: 45565 | AJ3: 45657 | AK3: 45747 | AL3: 45838 | AM3: 45930 | AN3: 46022 | AO3: 46112
C4: Act | D4: Act | E4: Act | F4: Act | G4: Act | H4: Act | I4: Act | J4: Act | K4: Act | M4: Act | N4: Act | O4: Act | P4: Act | Q4: Act | R4: Act | S4: Act | T4: Act | U4: Act | V4: Act | W4: Act | X4: Act | Y4: Act | Z4: Act | AA4: Act | AB4: Act | AC4: Act | AD4: Act | AE4: Act | AF4: Act | AG4: Act | AH4: Act | AI4: Act | AJ4: Act | AK4: Act | AL4: Act | AM4: Act | AN4: Act | AO4: Act
C5: FY | D5: FY | E5: FY | F5: FY | G5: FY | H5: FY | I5: FY | J5: FY | K5: LTM | M5: 1Q | N5: 2Q | O5: 3Q | P5: 4Q | Q5: 1Q | R5: 2Q | S5: 3Q | T5: 4Q | U5: 1Q | V5: 2Q | W5: 3Q | X5: 4Q | Y5: 1Q | Z5: 2Q | AA5: 3Q | AB5: 4Q | AC5: 1Q | AD5: 2Q | AE5: 3Q | AF5: 4Q | AG5: 1Q | AH5: 2Q | AI5: 3Q | AJ5: 4Q | AK5: 1Q | AL5: 2Q | AM5: 3Q | AN5: 4Q | AO5: 1Q
B7: Revenue by segment
B8: Food delivery / Core local commerce | C8: 38143.083 | D8: 54843.205 | E8: 66265.319 | F8: 96311.778 | G8: 160759.02 | H8: 206906.93 | I8: 250247.5 | J8: 260826.09 | K8: =SUM(AL8:AO8) -> 260915.65 | M8: 10705.803 | N8: 12844.72 | O8: 15576.972 | P8: 15715.71 | Q8: 9490.423 | R8: 14544.095 | S8: 20692.816 | T8: 21537.985 | U8: 20575.41 | V8: 23125.084 | W8: 26484.643 | X8: 26126.641 | Y8: 24156.722 | Z8: 36779.243 | AA8: 46327.529 | AB8: 43472.664 | AC8: 42885.336 | AD8: 51199.946 | AE8: 57691.008 | AF8: =H8-AC8-AD8-AE8 -> 55130.642 | AG8: 54625.707 | AH8: 60681.858 | AI8: 69373.099 | AJ8: =I8-AG8-AH8-AI8 -> 65566.832 | AK8: 63973.733 | AL8: 65347.283 | AM8: 67446.866 | AN8: =J8-AK8-AL8-AM8 -> 64058.212 | AO8: 64063.286
B9: In-store, hotel & travel | C9: 15840.361 | D9: 22275.472 | E9: 21252.398 | F9: 32530.325 | M9: 4492.102 | N9: 5245.308 | O9: 6181.117 | P9: 6356.945 | Q9: 3094.978 | R9: 4543.982 | S9: 6478.078 | T9: 7135.36 | U9: 6584.391 | V9: 8602.179 | W9: 8621.328 | X9: 8722.427 | Y9: 7621.509 | Z9: 0 | AA9: 0 | AB9: 0 | AC9: 0 | AD9: 0 | AE9: 0 | AF9: =H9-AC9-AD9-AE9 -> 0 | AG9: 0 | AH9: 0 | AI9: 0 | AJ9: =I9-AG9-AH9-AI9 -> 0 | AK9: 0 | AL9: 0 | AM9: 0 | AN9: =J9-AK9-AL9-AM9 -> 0 | AO9: 0
B10: New initiatives and others | C10: 11243.834 | D10: 20409.854 | E10: 27276.793 | F10: 50285.894 | G10: 59195.926 | H10: 69838.022 | I10: 87344.08 | J10: 104028.65 | K10: =SUM(AL10:AO10) -> 108771.86 | M10: 3975.607 | N10: 4613.109 | O10: 5735.54 | P10: 6085.598 | Q10: 4168.486 | R10: 5633.76 | S10: 8230.388 | T10: 9244.159 | U10: 9856.461 | V10: 12031.969 | W10: 13723.399 | X10: 14674.065 | Y10: 14490.523 | Z10: 14159.12 | AA10: 16291.363 | AB10: 16656.275 | AC10: 15732.136 | AD10: 16764.678 | AE10: 18775.899 | AF10: =H10-AC10-AD10-AE10 -> 18565.309 | AG10: 18650.177 | AH10: 21569.219 | AI10: 24204.22 | AJ10: =I10-AG10-AH10-AI10 -> 22920.464 | AK10: 22232.412 | AL10: 26493.197 | AM10: 28041.247 | AN10: =J10-AK10-AL10-AM10 -> 27261.796 | AO10: 26975.62
B11: Total | C11: =SUM(C8:C10) -> 65227.278 | D11: =SUM(D8:D10) -> 97528.531 | E11: =SUM(E8:E10) -> 114794.51 | F11: =SUM(F8:F10) -> 179128 | G11: =SUM(G8:G10) -> 219954.95 | H11: =SUM(H8:H10) -> 276744.95 | I11: =SUM(I8:I10) -> 337591.58 | J11: =SUM(J8:J10) -> 364854.75 | K11: =SUM(K8:K10) -> 369687.51 | M11: =SUM(M8:M10) -> 19173.512 | N11: =SUM(N8:N10) -> 22703.137 | O11: =SUM(O8:O10) -> 27493.629 | P11: =SUM(P8:P10) -> 28158.253 | Q11: =SUM(Q8:Q10) -> 16753.887 | R11: =SUM(R8:R10) -> 24721.837 | S11: =SUM(S8:S10) -> 35401.282 | T11: =SUM(T8:T10) -> 37917.504 | ... AO11: =SUM(AO8:AO10) -> 91038.906
B12: Check | C12: =C11-Model!C7 -> 0 | D12: =D11-Model!D7 -> 0 | E12: =E11-Model!E7 -> 0 | F12: =F11-Model!F7 -> 0 | G12: =G11-Model!G7 -> 0 | H12: =H11-Model!H7 -> 0 | I12: =I11-Model!I7 -> 0 | J12: =J11-Model!J7 -> 0 | K12: =K11-Model!K7 -> 0 | M12: =M11-Model!M7 -> 0 | N12: =N11-Model!N7 -> 0 | O12: =O11-Model!O7 -> 0 | P12: =P11-Model!P7 -> 0 | Q12: =Q11-Model!Q7 -> 0 | R12: =R11-Model!R7 -> 0 | S12: =S11-Model!S7 -> 0 | T12: =T11-Model!T7 -> 0 | ... AO12: =AO11-Model!AO7 -> 0
B14: Operating profit by segment
B15: Food delivery / Core local commerce | D15: 1415.88 | E15: 2833.369 | F15: 6174.641 | G15: 29502.669 | H15: 38698.847 | I15: 52415.162 | J15: -6904.083 | K15: =SUM(AL15:AO15) -> -22425.505 | M15: -154.203 | N15: 756.347 | O15: 330.907 | P15: 482.829 | Q15: -70.881 | R15: 1253.421 | S15: 768.477 | T15: 882.352 | U15: 1115.885 | V15: 2447.076 | W15: 876.103 | X15: 1735.577 | Y15: 1577.143 | Z15: 8260.993 | AA15: 9321.293 | AB15: 7215.242 | AC15: 9445.07 | AD15: 11138.521 | AE15: 10095.831 | AF15: =H15-AC15-AD15-AE15 -> 8019.425 | AG15: 9698.847 | AH15: 15233.585 | AI15: 14582.403 | AJ15: =I15-AG15-AH15-AI15 -> 12900.327 | AK15: 13491.48 | AL15: 3721.13 | AM15: -14071.01 | AN15: =J15-AK15-AL15-AM15 -> -10045.683 | AO15: -2029.942
B16: In-store, hotel & travel | D16: 8403.293 | E16: 8180.933 | F16: 14093.113 | M16: 1592.878 | N16: 2147.499 | O16: 2331.639 | P16: 2331.277 | Q16: 680.179 | R16: 1891.563 | S16: 2787.256 | T16: 2821.935 | U16: 2748.205 | V16: 3663.818 | W16: 3784.074 | X16: 3897.016 | Y16: 3473.546 | Z16: 0 | AA16: 0 | AB16: 0 | AC16: 0 | AD16: 0 | AE16: 0 | AF16: =H16-AC16-AD16-AE16 -> 0 | AG16: 0 | AH16: 0 | AI16: 0 | AJ16: =I16-AG16-AH16-AI16 -> 0 | AK16: 0 | AL16: 0 | AM16: 0 | AN16: =J16-AK16-AL16-AM16 -> 0 | AO16: 0
B17: New initiatives and others | D17: -6749.149 | E17: -10854.996 | F17: -38393.895 | G17: -28379.21 | H17: -20166.484 | I17: -7273.314 | J17: -10082.34 | K17: =SUM(AL17:AO17) -> -9924.888 | M17: -2583.124 | N17: -1645.735 | O17: -1201.845 | P17: -1318.445 | Q17: -1363.717 | R17: -1459.539 | S17: -2028.909 | T17: -6002.831 | U17: -8044.445 | V17: -9238.125 | W17: -10906.087 | X17: -10205.238 | Y17: -9024.754 | Z17: -6789.546 | AA17: -6771.36 | AB17: -6365.02 | AC17: -5028.894 | AD17: -5192.922 | AE17: -5111.976 | AF17: =H17-AC17-AD17-AE17 -> -4832.692 | AG17: -2756.899 | AH17: -1314.359 | AI17: -1026.042 | AJ17: =I17-AG17-AH17-AI17 -> -2176.014 | AK17: -2273.267 | AL17: -1881.318 | AM17: -1277.909 | AN17: =J17-AK17-AL17-AM17 -> -4649.846 | AO17: -2115.815
B18: Unallocated items | D18: -390.164 | E18: 4170.796 | F18: -5001.058 | G18: -6943.907 | H18: -5116.976 | I18: -8296.892 | J18: -8054.714 | K18: =SUM(AL18:AO18) -> -9726.665 | M18: -159.193 | N18: -145.533 | O18: -13.637 | P18: -71.801 | Q18: -961.111 | R18: 489.2 | S18: 5196.859 | T18: -554.152 | U18: -586.652 | V18: -124.474 | W18: -3856.721 | X18: -433.211 | Y18: -1610.177 | Z18: -1964.285 | AA18: -1561.711 | AB18: -1581.812 | AC18: -830.455 | AD18: -1232.6 | AE18: -1625.322 | AF18: =H18-AC18-AD18-AE18 -> -1428.599 | AG18: -1732.556 | AH18: -2662.337 | AI18: 128.815 | AJ18: =I18-AG18-AH18-AI18 -> -4030.814 | AK18: -652.103 | AL18: -1613.462 | AM18: -4410.431 | AN18: =J18-AK18-AL18-AM18 -> -1378.718 | AO18: -2324.054
B19: Total | D19: =SUM(D15:D18) -> 2679.86 | E19: =SUM(E15:E18) -> 4330.102 | F19: =SUM(F15:F18) -> -23127.199 | G19: =SUM(G15:G18) -> -5820.448 | H19: =SUM(H15:H18) -> 13415.387 | I19: =SUM(I15:I18) -> 36844.956 | J19: =SUM(J15:J18) -> -25041.137 | K19: =SUM(K15:K18) -> -42077.058 | M19: =SUM(M15:M18) -> -1303.642 | N19: =SUM(N15:N18) -> 1112.578 | O19: =SUM(O15:O18) -> 1447.064 | P19: =SUM(P15:P18) -> 1423.86 | Q19: =SUM(Q15:Q18) -> -1715.53 | R19: =SUM(R15:R18) -> 2174.645 | S19: =SUM(S15:S18) -> 6723.683 | T19: =SUM(T15:T18) -> -2852.696 | ... AO19: =SUM(AO15:AO18) -> -6469.811
B20: Check | D20: =D19-Model!D19 -> -9.094947e-12 | E20: =E19-Model!E19 -> 9.094947e-12 | F20: =F19-Model!F19 -> 0 | G20: =G19-Model!G19 -> 0 | H20: =H19-Model!H19 -> -1.4551915e-11 | I20: =I19-Model!I19 -> 0 | J20: =J19-Model!J19 -> 0 | K20: =K19-Model!K19 -> 0 | M20: =M19-Model!M19 -> 0 | N20: =N19-Model!N19 -> 0 | O20: =O19-Model!O19 -> 0 | P20: =P19-Model!P19 -> -1.4779289e-11 | Q20: =Q19-Model!Q19 -> 2.2737368e-12 | R20: =R19-Model!R19 -> 0 | S20: =S19-Model!S19 -> 0 | T20: =T19-Model!T19 -> -4.0927262e-12 | ... AO20: =AO19-Model!AO19 -> 0
B22: Revenues:
B23: Delivery services | H23: 82190.98 | I23: 98065.26 | J23: 96067.515 | AG23: 21065.057 | AH23: 23021.272 | AI23: 27784.111 | AJ23: 26194.82 | AK23: 25751.44 | AL23: 23655.555 | AM23: 23021.931 | AN23: =J23-AK23-AL23-AM23 -> 23638.589 | AO23: 25005.93
B24: Commission | H24: 76688.543 | I24: 95340.956 | J24: 105476.79 | AG24: 20657.273 | AH24: 22825.278 | AI24: 26889.908 | AJ24: 24968.497 | AL24: 26471.515 | AM24: 28002.842 | AN24: =J24-AK24-AL24-AM24 -> 51002.43
B25: Online marketing services | H25: 40513.216 | I25: 49240.392 | J25: 51920.379 | AG25: 10390.898 | AH25: 12359.848 | AI25: 13539.14 | AJ25: 12950.506 | AL25: 13649.757 | AM25: 14326.536 | AN25: =J25-AK25-AL25-AM25 -> 23944.086
B26: Merchant services | AK26: 36774.287 | AN26: =J26-AK26-AL26-AM26 -> -36774.287 | AO26: 38058.92
B27: Product sales | AK27: 14308.694 | AN27: =J27-AK27-AL27-AM27 -> -14308.694 | AO27: 20972.102
B28: Other services and sales ((including interest revenue) | H28: 77352.215 | I28: 94944.968 | J28: 111390.07 | AG28: 21162.656 | AH28: 24044.679 | AI28: 25364.16 | AJ28: 24373.473 | AK28: 9371.724 | AL28: 28063.653 | AM28: 30136.804 | AN28: =J28-AK28-AL28-AM28 -> 43817.884 | AO28: 7001.954
B29: Total | H29: =SUM(H23:H28) -> 276744.95 | I29: =SUM(I23:I28) -> 337591.58 | J29: =SUM(J23:J28) -> 364854.75 | AG29: =SUM(AG23:AG28) -> 73275.884 | AH29: =SUM(AH23:AH28) -> 82251.077 | AI29: =SUM(AI23:AI28) -> 93577.319 | AJ29: =SUM(AJ23:AJ28) -> 88487.296 | AK29: =SUM(AK23:AK28) -> 86206.145 | AL29: =SUM(AL23:AL28) -> 91840.48 | AM29: =SUM(AM23:AM28) -> 95488.113 | AN29: =SUM(AN23:AN28) -> 91320.008 | AO29: =SUM(AO23:AO28) -> 91038.906
B30: Check | H30: =H29-Model!H7 -> 0 | I30: =I29-Model!I7 -> 0 | J30: =J29-Model!J7 -> 0 | AG30: =AG29-Model!AG7 -> 0 | AH30: =AH29-Model!AH7 -> 0 | AI30: =AI29-Model!AI7 -> 0 | AJ30: =AJ29-Model!AJ7 -> 0 | AK30: =AK29-Model!AK7 -> 0 | AL30: =AL29-Model!AL7 -> 0 | AM30: =AM29-Model!AM7 -> 0 | AN30: =AN29-Model!AN7 -> 0 | AO30: =AO29-Model!AO7 -> 0
B32: Revenues (% Share)
B33: Delivery services | H33: =H23/H$29 -> 0.29699179 | I33: =I23/I$29 -> 0.29048491 | J33: =J23/J$29 -> 0.26330345 | AG33: =AG23/AG$29 -> 0.28747599 | AH33: =AH23/AH$29 -> 0.27989022 | AI33: =AI23/AI$29 -> 0.29691074 | AJ33: =AJ23/AJ$29 -> 0.29602916 | AK33: =AK23/AK$29 -> 0.29871931 | AL33: =AL23/AL$29 -> 0.25757221 | AM33: =AM23/AM$29 -> 0.24109735 | AN33: =AN23/AN$29 -> 0.25885443 | AO33: =AO23/AO$29 -> 0.27467301
B34: Commission | H34: =H24/H$29 -> 0.27710909 | I34: =I24/I$29 -> 0.28241509 | J34: =J24/J$29 -> 0.28909254 | AG34: =AG24/AG$29 -> 0.28191094 | AH34: =AH24/AH$29 -> 0.27750734 | AI34: =AI24/AI$29 -> 0.28735497 | AJ34: =AJ24/AJ$29 -> 0.28217041 | AL34: =AL24/AL$29 -> 0.28823363 | AM34: =AM24/AM$29 -> 0.29325998 | AN34: =AN24/AN$29 -> 0.55850225
B35: Online marketing services | H35: =H25/H$29 -> 0.14639189 | I35: =I25/I$29 -> 0.14585788 | J35: =J25/J$29 -> 0.14230424 | AG35: =AG25/AG$29 -> 0.14180515 | AH35: =AH25/AH$29 -> 0.15026974 | AI35: =AI25/AI$29 -> 0.14468399 | AJ35: =AJ25/AJ$29 -> 0.14635441 | AL35: =AL25/AL$29 -> 0.14862463 | AM35: =AM25/AM$29 -> 0.15003476 | AN35: =AN25/AN$29 -> 0.26219978
B36: Merchant services | AK36: =AK26/AK$29 -> 0.42658545 | AO36: =AO26/AO$29 -> 0.41805116
B37: Productt sales | AK37: =AK27/AK$29 -> 0.1659823 | AO37: =AO27/AO$29 -> 0.23036417
B38: Other services and sales ((including interest revenue) | H38: =H28/H$29 -> 0.27950723 | I38: =I28/I$29 -> 0.28124211 | J38: =J28/J$29 -> 0.30529976 | AG38: =AG28/AG$29 -> 0.28880792 | AH38: =AH28/AH$29 -> 0.29233269 | AI38: =AI28/AI$29 -> 0.2710503 | AJ38: =AJ28/AJ$29 -> 0.27544601 | AK38: =AK28/AK$29 -> 0.10871295 | AL38: =AL28/AL$29 -> 0.30556954 | AM38: =AM28/AM$29 -> 0.31560791 | AN38: =AN28/AN$29 -> 0.47982786 | AO38: =AO28/AO$29 -> 0.076911667
B39: Total | H39: =SUM(H33:H38) -> 1 | I39: =SUM(I33:I38) -> 1 | J39: =SUM(J33:J38) -> 1 | AG39: =SUM(AG33:AG38) -> 1 | AH39: =SUM(AH33:AH38) -> 1 | AI39: =SUM(AI33:AI38) -> 1 | AJ39: =SUM(AJ33:AJ38) -> 1 | AK39: =SUM(AK33:AK38) -> 1 | AL39: =SUM(AL33:AL38) -> 1 | AM39: =SUM(AM33:AM38) -> 1 | AN39: =SUM(AN33:AN38) -> 1.5593843 | AO39: =SUM(AO33:AO38) -> 1
B41: Revenues (% YoY Growth)
B42: Delivery services | I42: =I23/H23-1 -> 0.19313896 | J42: =J23/I23-1 -> -0.020371587 | AK42: =AK23/AG23-1 -> 0.22247189 | AL42: =AL23/AH23-1 -> 0.02755204 | AM42: =AM23/AI23-1 -> -0.1713994 | AN42: =AN23/AJ23-1 -> -0.097585362 | AO42: =AO23/AK23-1 -> -0.028950226
B43: Commission | I43: =I24/H24-1 -> 0.24322294 | J43: =J24/I24-1 -> 0.10631141 | AK43: =AK24/AG24-1 -> -1 | AL43: =AL24/AH24-1 -> 0.15974557 | AM43: =AM24/AI24-1 -> 0.041388539 | AN43: =AN24/AJ24-1 -> 1.0426712
B44: Online marketing services | I44: =I25/H25-1 -> 0.21541553 | J44: =J25/I25-1 -> 0.054426598 | AK44: =AK25/AG25-1 -> -1 | AL44: =AL25/AH25-1 -> 0.10436285 | AM44: =AM25/AI25-1 -> 0.058157017 | AN44: =AN25/AJ25-1 -> 0.84889193
B45: Merchant services | I45: =IFERROR(I26/H26-1,"NM") -> NM | J45: =IFERROR(J26/I26-1,"NM") -> NM | AO45: =AO26/AK26-1 -> 0.034932914
B46: Productt sales | I46: =IFERROR(I27/H27-1,"NM") -> NM | J46: =IFERROR(J27/I27-1,"NM") -> NM | AO46: =AO27/AK27-1 -> 0.46568946
B47: Other services and sales ((including interest revenue) | I47: =I28/H28-1 -> 0.22743696 | J47: =J28/I28-1 -> 0.17320662 | AK47: =AK28/AG28-1 -> -0.55715748 | AL47: =AL28/AH28-1 -> 0.16714609 | AM47: =AM28/AI28-1 -> 0.18816488 | AN47: =AN28/AJ28-1 -> 0.7977694 | AO47: =AO28/AK28-1 -> -0.25286383
B48: Total | I48: =I29/H29-1 -> 0.21986533 | J48: =J29/I29-1 -> 0.08075785 | AK48: =AK29/AG29-1 -> 0.17645998 | AL48: =AL29/AH29-1 -> 0.11658696 | AM48: =AM29/AI29-1 -> 0.020419414 | AN48: =AN29/AJ29-1 -> 0.032012641 | AO48: =AO29/AK29-1 -> 0.056060516
B51: Operating Metrics
B52: Gross Transaction Volume of food delivery | C52: 282800 | D52: 392722.5 | E52: 488851.2 | F52: 702057.4 | M52: 75575.2 | N52: 93082.3 | O52: 111926.9 | P52: 112138.1 | Q52: 71504.2 | R52: 108827.1 | S52: 152232.5 | T52: 156287.3 | U52: 142735.4 | V52: 173603.3 | W52: 197098 | X52: 188620.8
B53: Number of food delivery transactions | D53: 8722.1 | E53: 10147.4 | F53: 14367.6 | G53: 17670.2 | H53: 21893.2 | M53: 1662.6 | N53: 2085.1 | O53: 2469.1 | P53: 2505.3 | Q53: 1374.5 | R53: 2228.9 | S53: 3212.7 | T53: 3331.3 | U53: 2902.7 | V53: 3541.4 | W53: 4013 | X53: 3910.6 | Y53: =G53-SUM(Z53:AB53) -> 3712.5 | Z53: 4102.4 | AA53: 5025.1 | AB53: 4830.2 | AC53: 4267.4 | AD53: 5400.4 | AE53: 6179.4 | AF53: =H53-AC53-AD53-AE53 -> 6046 | AG53: 5464.5 | AH53: 6167.1 | AI53: 7077.7
B54: Number of domestic hotel room nights | D54: 392.5 | E54: 354.5 | F54: 476.9 | M54: 78.6 | N54: 94 | O54: 109.8 | P54: 110 | Q54: 42.8 | R54: 78 | S54: 113.9 | T54: 119.7 | U54: 101 | V54: 140.8 | W54: 1198 | X54: 115.3
B56: Operating Metrics (LTM)
B58: Number of Transacting Users | C58: 400.4 | D58: 450.5 | E58: 510.6 | F58: 690.5 | G58: 677.9 | M58: 411.8 | N58: 422.6 | O58: 435.8 | P58: 450.5 | Q58: 448.6 | R58: 457.3 | S58: 476.5 | T58: 510.6 | U58: 569.3 | V58: 628.4 | W58: 667.5 | X58: 690.5 | Y58: 692.9 | Z58: 684.7 | AA58: 687.1 | AB58: 677.9
B59: Number of Active Merchants | C59: 5.8 | D59: 6.2 | E59: 6.8 | F59: 8.8 | G59: 9.3 | M59: 5.8 | N59: 5.9 | O59: 5.9 | P59: 6.2 | Q59: 6.1 | R59: 6.3 | S59: 6.5 | T59: 6.8 | U59: 7.1 | V59: 7.7 | W59: 8.3 | X59: 8.8 | Y59: 9 | Z59: 9.2 | AA59: 9.3 | AB59: 9.3
B60: Average number of transactions per annual Transacting User | C60: 23.8 | D60: 27.4 | E60: 28.1 | F60: 35.8 | G60: 40.8 | M60: 24.8 | N60: 25.5 | O60: 26.5 | P60: 27.4 | Q60: 26.2 | R60: 25.7 | S60: 26.8 | T60: 28.1 | U60: 30.5 | V60: 32.8 | W60: 34.4 | X60: 35.8 | Y60: 37.2 | Z60: 38.1 | AA60: 39.5 | AB60: 40.8
