Workbook
Name IQ_CH: 110000
Name IQ_CQ: 5000
Name IQ_CY: 10000
Name IQ_DAILY: 500000
Name IQ_FH: 100000
Name IQ_FQ: 500
Name IQ_FY: 1000
Name IQ_LTM: 2000
Name IQ_MONTH: 15000
Name IQ_NTM: 6000
Name IQ_WEEK: 50000
Name IQ_YTD: 3000

Sheet Capitalisation
A2: 1Q26 | I2: Exchange rate as at end | J2: =Model!$P$215 -> 0.022495315
I3: LTM Average exchange rate | J3: =Model!$P$216 -> 0.024213722
B5: Debt Breakdown as on 31-Mar-2026 | C5: TRY mn | D5: USD mn | E5: Leverage (TRY) | F5: Leverage (USD) | I5: Company reported | J5: Leverage
B6: Short-term debt | C6: =SUM(C7:C8) -> 17384.16 | D6: =SUM(D7:D8) -> 391.06216 | I6: Net Debt/Ebitda | J6: 1.33
B7: Loans | C7: =Model!BC$111-C8 -> 17384.16 | D7: =C7*$J2 -> 391.06216
B8: Lease Liabilities | C8: =Model!BB$116 -> 0 | D8: =C8*$J2 -> 0
B10: Long-term debt | C10: =SUM(C11:C12) -> 40868.248 | D10: =SUM(D11:D12) -> 919.34413
B11: Loans | C11: =Model!BC$112 -> 40868.248 | D11: =C11*$J2 -> 919.34413
B12: Lease Liabilities | C12: =Model!BB$117 -> 0 | D12: =C12*$J2 -> 0
B13: Total Loans & Borrowings | C13: =C6+C10 -> 58252.408 | D13: =D6+D10 -> 1310.4063 | E13: =C13/C20 -> 3.2252547 | F13: =D13/D20 -> 2.9963638
B14: Cash | C14: =Model!BC$125 -> 17161.084 | D14: =C14*$J2 -> 386.044
B15: Net debt exc investments | C15: =C13-C14 -> 41091.324 | D15: =D13-D14 -> 924.36229 | E15: =C15/C20 -> 2.2750988 | F15: =D15/D20 -> 2.1136389
B16: Short term financial investments | C16: =Model!BC$126 -> 6.614 | D16: =C16*$J2 -> 0.14878402
B17: Net debt | C17: =C15-C16 -> 41084.71 | D17: =D15-D16 -> 924.21351 | E17: =C17/C20 -> 2.2747326 | F17: =D17/D20 -> 2.1132987
B18: Equity | C18: =Model!BC$133 -> 51814.711 | D18: =C18*J2 -> 1165.5883
B19: Total Capitalisation | C19: =C18+C17 -> 92899.421 | D19: =D18+D17 -> 2089.8018
B20: LTM Adjusted EBITDA | C20: =Model!BC$90 -> 18061.336 | D20: =C20*$J3 -> 437.33217
B21: check | C21: =+C13-Model!BC$123 -> 0
B24: Cash and cash equivalents | C24: TL mn | D24: USD mn
B25: Cash on hand | C25: 7.281 | D25: =C25*$J2 -> 0.16378839
B26: Demand deposits | C26: 1646.969 | D26: =C26*$J2 -> 37.049087
B27: Time deposits | C27: 15532.459 | D27: =C27*$J2 -> 349.40756
B28: Impairment provision | C28: -25.625 | D28: =C28*$J2 -> -0.57644246
B29: Total Cash and cash equivalents | C29: =SUM(C25:C28) -> 17161.084 | D29: =SUM(D25:D28) -> 386.044
B30: check | C30: =C29-C14 -> 0
B33: Debt Breakup by currency (including lease liabilities) | C33: =C5 -> TRY mn | D33: =D5 -> USD mn | E33: %age
B34: Local currency | C34: =SUM(C35:C36) -> 0 | D34: =SUM(D35:D36) -> 0 | E34: =C34/$C$98 -> 0
B35: short term | C35: 0 | D35: =C35*$J2 -> 0
B36: long term | C36: 0 | D36: =C36*$J2 -> 0
B37: Foreign currency | C37: =SUM(C38:C39) -> 58252.408 | D37: =SUM(D38:D39) -> 1310.4063 | E37: =C37/$C$40 -> 1
B38: short term | C38: =2493.451+14769.609+31.412+89.688 -> 17384.16 | D38: =C38*$J2 -> 391.06216
B39: long term | C39: =32091.538+8649.593+127.117 -> 40868.248 | D39: =C39*$J2 -> 919.34413
B40: Total Debt | C40: =SUM(C34+C37) -> 58252.408 | D40: =SUM(D34+D37) -> 1310.4063 | E40: =SUM(E34+E37) -> 1
B41: check | C41: =C40-C13-C8 -> 0
B44: Debt Maturity (includes bank loans and issued debt instruments) | C44: =C5 -> TRY mn | D44: =D5 -> USD mn
B45: Short term borrowings | C45: 12203.996 | D45: =C45*J2 -> 274.53274
B47: within 1 year | C47: 5180.164 | D47: =C47*$J2 -> 116.52942
B48: within 1-2 years | C48: 2873.517 | D48: =C48*$J2 -> 64.640671
B49: within 2-3 years | C49: 2604.161 | D49: =C49*$J2 -> 58.581423
B50: within 3-4 years | C50: 2366.548 | D50: =C50*$J2 -> 53.236244
B51: within 4-5 years | C51: 16264.409 | D51: =C51*$J2 -> 365.87301
B52: Above 5 years | C52: 16759.613 | D52: =C52*$J2 -> 377.01278
B53: Total | C53: =SUM(C45:C52) -> 58252.408 | D53: =SUM(D45:D52) -> 1310.4063
B54: check | C54: =C53-C40+C8+C12 -> 0
A60: FY25 | I60: Exchange rate as at end | J60: =Model!$P$215 -> 0.022495315
I61: LTM Average exchange rate | J61: =Model!$P$216 -> 0.024213722
B63: Debt Breakdown as on 31-Dec-2025 | C63: TRY mn | D63: USD mn | E63: Leverage (TRY) | F63: Leverage (USD) | I63: Company reported | J63: Leverage
B64: Short-term debt | C64: =SUM(C65:C66) -> 17537.603 | D64: =SUM(D65:D66) -> 394.51391 | I64: Total financial liabilities and non-trade related parties payables/(receivab | J64: 55551.15
B65: Loans | C65: =Model!BB$111-C66 -> 17537.603 | D65: =C65*$J60 -> 394.51391 | I65: Less: Cash and cash equivalents | J65: -23318.683
B66: Lease Liabilities | C66: =Model!BB$116 -> 0 | D66: =C66*$J60 -> 0 | I66: Less: Derivatives instruments | J66: -2950.73
I67: Net debt | J67: =SUM(J64:J66) -> 29281.737
B68: Long-term debt | C68: =SUM(C69:C70) -> 39807.777 | D68: =SUM(D69:D70) -> 895.4885 | I68: Net Debt/Ebitda | J68: =J67/C78 -> 1.5900129
B69: Loans | C69: =Model!BB$112 -> 39807.777 | D69: =C69*$J60 -> 895.4885
B70: Lease Liabilities | C70: =Model!BB$117 -> 0 | D70: =C70*$J60 -> 0
B71: Total Loans & Borrowings | C71: =C64+C68 -> 57345.38 | D71: =D64+D68 -> 1290.0024 | E71: =C71/C78 -> 3.1138828 | F71: =D71/D78 -> 2.8928958
B72: Cash | C72: =Model!BB$125 -> 23318.683 | D72: =C72*$J60 -> 524.56113
B73: Net debt exc investments | C73: =C71-C72 -> 34026.697 | D73: =D71-D72 -> 765.44128 | E73: =C73/C78 -> 1.8476666 | F73: =D73/D78 -> 1.7165409
B74: Short term financial investments | C74: =Model!BB$126 -> 6.42 | D74: =C74*$J60 -> 0.14441992
B75: Net debt | C75: =C73-C74 -> 34020.277 | D75: =D73-D74 -> 765.29686 | E75: =C75/C78 -> 1.847318 | F75: =D75/D78 -> 1.716217
B76: Equity | C76: =Model!BB$133 -> 43301.842 | D76: =C76*J60 -> 974.08859
B77: Total Capitalisation | C77: =C76+C75 -> 77322.119 | D77: =D76+D75 -> 1739.3855
B78: LTM Adjusted EBITDA | C78: =Model!BB$90 -> 18416.037 | D78: =C78*$J61 -> 445.92081
B79: check | C79: =+C71-Model!BB$123 -> 0
B82: Cash and cash equivalents | C82: TL mn | D82: USD mn
B83: Cash on hand | C83: 3.451 | D83: =C83*$J60 -> 0.077631333
B84: Demand deposits | C84: 2613.59 | D84: =C84*$J60 -> 58.793531
B85: Time deposits | C85: 20734.734 | D85: =C85*$J60 -> 466.43438
B86: Impairment provision | C86: -33.092 | D86: =C86*$J60 -> -0.74441498
B87: Total Cash and cash equivalents | C87: =SUM(C83:C86) -> 23318.683 | D87: =SUM(D83:D86) -> 524.56113
B88: check | C88: =C87-C72 -> 0
B91: Debt Breakup by currency (including lease liabilities) | C91: =C63 -> TRY mn | D91: =D63 -> USD mn | E91: %age
B92: Local currency | C92: =SUM(C93:C94) -> 0 | D92: =SUM(D93:D94) -> 0 | E92: =C92/$C$98 -> 0
B93: short term | C93: 0 | D93: =C93*$J60 -> 0
B94: long term | C94: 0 | D94: =C94*$J60 -> 0
B95: Foreign currency | C95: =SUM(C96:C97) -> 57345.38 | D95: =SUM(D96:D97) -> 1290.0024 | E95: =C95/$C$98 -> 1
B96: short term | C96: =2431.623+14981.209+124.771 -> 17537.603 | D96: =C96*$J60 -> 394.51391
B97: long term | C97: =31252.294+8426.04+129.443 -> 39807.777 | D97: =C97*$J60 -> 895.4885
B98: Total Debt | C98: =SUM(C92+C95) -> 57345.38 | D98: =SUM(D92+D95) -> 1290.0024 | E98: =SUM(E92+E95) -> 1
B99: check | C99: =C98-C71-C66 -> 0
B102: Debt Maturity (includes bank loans and issued debt instruments) | C102: =C63 -> TRY mn | D102: =D63 -> USD mn
B103: Short terrm borrowings | C103: 12491.954 | D103: =C103*J60 -> 281.01044
B105: within 1 year | C105: 5045.649 | D105: =C105*$J60 -> 113.50347
B106: within 1-2 years | C106: 2786.572 | D106: =C106*$J60 -> 62.684816
B107: within 2-3 years | C107: 2530.485 | D107: =C107*$J60 -> 56.924058
B108: within 3-4 years | C108: 2308.916 | D108: =C108*$J60 -> 51.939794
B109: within 4-5 years | C109: 15682.324 | D109: =C109*$J60 -> 352.77882
B110: Above 5 years | C110: 16499.48 | D110: =C110*$J60 -> 371.16101
B111: Total | C111: =SUM(C103:C110) -> 57345.38 | D111: =SUM(D103:D110) -> 1290.0024
B112: check | C112: =C111-C98+C66+C70 -> 0
A117: 3Q25 | I117: Exchange rate as at end 3Q25 | J117: =Model!BA$215 -> 0.024047017
I118: Average exchange rate for LTM 3Q25 | J118: =Model!BA$216 -> 0.026656758
B120: Debt Breakdown as on 30-Sep-2025 | C120: TL mn | D120: USD mn | E120: Leverage | F120: Leverage (USD) | I120: Company reported | J120: Leverage
B121: Short-term debt | C121: =SUM(C122:C123) -> 46959.271 | D121: =SUM(D122:D123) -> 1129.2304 | I121: Net Debt/Ebitda | J121: 1.76
B122: Loans | C122: =Model!BA$111-C123 -> 46959.215 | D122: =C122*$J117 -> 1129.229
B123: Lease Liabilities | C123: =Model!BA$116 -> 0.056 | D123: =C123*$J117 -> 0.0013466329
B124: Long-term debt | C124: =SUM(C125:C126) -> 21513.932 | D124: =SUM(D125:D126) -> 517.34588
B125: Loans | C125: =Model!BA$112 -> 21513.932 | D125: =C125*$J117 -> 517.34588
B126: Lease Liabilities | C126: =Model!BA$117 -> 0 | D126: =C126*$J117 -> 0
B127: Total Loans & Borrowings | C127: =C121+C124 -> 68473.203 | D127: =D121+D124 -> 1646.5763 | E127: =C127/C134 -> 3.5837253 | F127: =D127/D134 -> 3.2328725
B128: Cash | C128: =Model!BA$125 -> 29570.256 | D128: =C128*$J117 -> 711.07644
...

Sheet Model
B2: ÜLKER BÝSKÜVÝ SANAYÝ A.Þ. | C2: Annual | D2: Annual | E2: Annual | F2: Annual | G2: Annual | H2: Annual | I2: Annual | J2: Annual | K2: Annual | L2: Annual | M2: Annual | N2: Annual | O2: Annual | P2: LTM | R2: Quarters | S2: Quarters | T2: Quarters | U2: Quarters | V2: Quarters | W2: Quarters | X2: Quarters | Y2: Quarters | Z2: Quarters | AA2: Quarters | AB2: Quarters | AC2: Quarters | AD2: Quarters | AE2: Quarters | AF2: Quarters | AG2: Quarters | AH2: Quarters | AI2: Quarters | AJ2: Quarters | AK2: Quarters | AL2: Quarters | AM2: Quarters | AN2: Quarters | AO2: Quarters | AP2: Quarters | AQ2: Quarters | AR2: Quarters | AS2: Quarters | AT2: Quarters | AU2: Quarters | AV2: Quarters | AW2: Quarters | AX2: Quarters | AY2: Quarters | AZ2: Quarters | BA2: Quarters | BB2: Quarters | BC2: Quarters | BE2: Quarters | BF2: Quarters | BG2: Quarters | BH2: Quarters | BI2: Quarters | BK2: 6M | BL2: 6M | BN2: 9M | BO2: 9M | BQ2: Quarters | BR2: Quarters | BS2: Quarters
B3: (TRY million) | C3: 42735 | D3: 43100 | E3: 43465 | F3: 43830 | G3: 44196 | H3: 44561 | I3: 44926 | J3: 44926 | K3: 45291 | L3: 45291 | M3: 45657 | N3: 45657 | O3: 46022 | P3: =BC3 -> 46112 | R3: 43190 | S3: 43281 | T3: 43373 | U3: 43465 | V3: 43555 | W3: 43646 | X3: 43738 | Y3: 43830 | Z3: 43921 | AA3: 44012 | AB3: 44104 | AC3: 44196 | AD3: 44286 | AE3: 44377 | AF3: 44469 | AG3: 44561 | AH3: 44651 | AI3: 44742 | AJ3: 44834 | AK3: 44926 | AL3: 44926 | AM3: 45016 | AN3: 45016 | AO3: 45107 | AP3: 45107 | AQ3: 45199 | AR3: 45199 | AS3: 45291 | AT3: 45291 | AU3: 45382 | AV3: 45473 | AW3: 45565 | AX3: 45657 | AY3: 45747 | AZ3: 45838 | BA3: 45930 | BB3: 46022 | BC3: 46112 | BE3: 45382 | BF3: 45473 | BG3: 45565 | BH3: 45656 | BI3: 45747 | BK3: 45473 | BL3: 45838 | BN3: 45565 | BO3: 45930 | BQ3: 44104 | BR3: 44286 | BS3: 44377
C4: Act | D4: Act | E4: Act | F4: Act | G4: Act | H4: Act | I4: Act | J4: Restated | K4: Act | L4: Restated | M4: Act | N4: Restated | O4: Act | P4: Act | R4: Act | S4: Act | T4: Act | U4: Act | V4: Act | W4: Act | X4: Act | Y4: Act | Z4: Act | AA4: Act | AB4: Act | AC4: Act | AD4: Act | AE4: Act | AF4: Act | AG4: Act | AH4: Act | AI4: Act | AJ4: Act | AK4: Act | AL4: Restated | AM4: Act | AN4: Restated | AO4: Act | AP4: Restated | AQ4: Act | AR4: Restated | AS4: Act | AT4: Restated | AU4: Act | AV4: Act | AW4: Act | AX4: Act | AY4: Act | AZ4: Act | BA4: Act | BB4: Act | BC4: Act | BE4: Restated | BF4: Restated | BG4: Restated | BH4: Restated | BI4: Restated | BK4: Act | BL4: Act | BN4: Act | BO4: Act | BQ4: Restated | BR4: Restated | BS4: Restated
C5: FY | D5: FY | E5: FY | F5: FY | G5: FY | H5: FY | I5: FY | J5: FY | K5: FY | L5: FY | M5: FY | N5: FY | O5: FY | P5: LTM | R5: 1Q | S5: 2Q | T5: 3Q | U5: 4Q | V5: 1Q | W5: 2Q | X5: 3Q | Y5: 4Q | Z5: 1Q | AA5: 2Q | AB5: 3Q | AC5: 4Q | AD5: 1Q | AE5: 2Q | AF5: 3Q | AG5: 4Q | AH5: 1Q | AI5: 2Q | AJ5: 3Q | AK5: 4Q | AL5: 4Q | AM5: 1Q | AN5: 1Q | AO5: 2Q | AP5: 2Q | AQ5: 3Q | AR5: 3Q | AS5: 4Q | AT5: 4Q | AU5: 1Q | AV5: 2Q | AW5: 3Q | AX5: 4Q | AY5: 1Q | AZ5: 2Q | BA5: 3Q | BB5: 4Q | BC5: 1Q | BE5: 1Q | BF5: 2Q | BG5: 3Q | BH5: 4Q | BI5: 1Q | BK5: 6M | BL5: 6M | BN5: 9M | BO5: 9M | BQ5: 3Q | BR5: 1Q | BS5: 2Q
B6: INCOME STATEMENT
B7: Revenue | C7: 4193.7747 | D7: 4825.648 | E7: 5955.508 | F7: 7803.12 | G7: 9400.861 | H7: 12537.08 | I7: 28196.847 | J7: 51981.208 | K7: 55836.141 | L7: 80615.534 | M7: 84097.908 | N7: 110077.71 | O7: 111904.6 | P7: =SUM(BB7,BC7,AZ7,BA7) -> 118848.7 | R7: 1407.69 | S7: 1312.269 | T7: 1437.674 | U7: =E7-SUM(R7:T7) -> 1797.875 | V7: 1942.36 | W7: 1820.498 | X7: 1893.109 | Y7: =F7-SUM(V7:X7) -> 2147.153 | Z7: 2376.126 | AA7: 2144.641 | AB7: 2228.799 | AC7: =G7-SUM(Z7:AB7) -> 2651.295 | AD7: 2689.678 | AE7: 2542.416 | AF7: 2976.133 | AG7: =H7-SUM(AD7:AF7) -> 4328.853 | AH7: 5886.018 | AI7: 5991.042 | AJ7: 7301.82 | AK7: =I7-SUM(AH7:AJ7) -> 9017.967 | AL7: =J7-SUM(AH7:AJ7) -> 32802.328 | AM7: 10111.756 | AN7: 17346.855 | AO7: 9511.854 | AP7: 16395.693 | AQ7: 12408.578 | AR7: 17809.406 | AS7: =K7-SUM(AM7,AO7,AQ7) -> 23803.953 | AT7: =L7-SUM(AN7,AP7,AR7) -> 29063.58 | AU7: 19600.936 | AV7: 15309.329 | AW7: 18196.405 | AX7: =M7-SUM(AU7,AV7,AW7) -> 30991.238 | AY7: 26962.317 | AZ7: 23057.685 | BA7: 25411.133 | BB7: =O7-SUM(AY7,AZ7,BA7) -> 36473.466 | BC7: 33906.421 | BE7: 27069.643 | BF7: 20675.043 | BG7: 24254.718 | BH7: =N7-SUM(BE7,BF7,BG7) -> 38078.306 | BI7: 35285.011 | BK7: 49370.684 | BL7: 51639.553 | BN7: 77330.367 | BO7: 80925.915 | BQ7: 2291.16 | BR7: 2783.757 | BS7: 2659.067
B8: % growth | D8: =+D7/C7-1 -> 0.15066934 | E8: =+E7/D7-1 -> 0.23413643 | F8: =+F7/E7-1 -> 0.31023584 | G8: =+G7/F7-1 -> 0.20475669 | H8: =+H7/G7-1 -> 0.33360976 | I8: =+I7/H7-1 -> 1.2490761 | J8: =+J7/I7-1 -> 0.84351137 | K8: =+K7/J7-1 -> 0.074160127 | ... M8: =+M7/L7-1 -> 0.043197307 | N8: =+N7/L7-1 -> 0.36546525 | O8: =+O7/N7-1 -> 0.016596375 | V8: =V7/R7-1 -> 0.37982084 | W8: =W7/S7-1 -> 0.38729026 | X8: =X7/T7-1 -> 0.316786 | Y8: =Y7/U7-1 -> 0.19427268 | Z8: =Z7/V7-1 -> 0.22331906 | AA8: =AA7/W7-1 -> 0.17805183 | AB8: =AB7/X7-1 -> 0.17732207 | AC8: =AC7/Y7-1 -> 0.23479556 | ... AK8: =AK7/AG7-1 -> 1.0832232 | AL8: =AL7/AG7-1 -> 6.5776027 | AM8: =AM7/AH7-1 -> 0.71792815 | AN8: =AN7/AI7-1 -> 1.8954654 | AO8: =AO7/AI7-1 -> 0.58767941 | AP8: =AP7/AI7-1 -> 1.7367014 | AQ8: =AQ7/AJ7-1 -> 0.69938152 | AR8: =AR7/AJ7-1 -> 1.4390366 | AS8: =AS7/AK7-1 -> 1.6396141 | AT8: =AT7/AL7-1 -> -0.11397813 | AU8: =AU7/AN7-1 -> 0.12994177 | AV8: =AV7/AP7-1 -> -0.066259108 | AW8: =AW7/AR7-1 -> 0.021730034 | AX8: =AX7/AT7-1 -> 0.066325552 | AY8: =AY7/BE7-1 -> -0.0039648103 | AZ8: =AZ7/BF7-1 -> 0.11524242 | BA8: =BA7/BG7-1 -> 0.04767794 | BB8: =BB7/BH7-1 -> -0.042145782 | BC8: =BC7/BI7-1 -> -0.039070131 | BE8: =BE7/AN7-1 -> 0.56049284 | BF8: =BF7/AP7-1 -> 0.26100452 | BG8: =BG7/AR7-1 -> 0.36190494 | BH8: =BH7/AT7-1 -> 0.31017259 | BI8: =BI7/BE7-1 -> 0.30349008 | BL8: =BL7/BK7-1 -> 0.045955794 | BO8: =BO7/BN7-1 -> 0.046495939 | BQ8: =BQ7/X7-1 -> 0.21026312 | BR8: =BR7/Z7-1 -> 0.17155277 | BS8: =BS7/AA7-1 -> 0.23986579
B9: Cost of sales | C9: -3119.7251 | D9: -3573.677 | E9: -4395.223 | F9: -5663.928 | G9: -6757.398 | H9: -8924.665 | I9: -19788.33 | J9: -40653.018 | K9: -39659.581 | L9: -57260.016 | M9: -59031.548 | N9: -77267.768 | O9: -79559.084 | P9: =SUM(BB9,BC9,AZ9,BA9) -> -86066.846 | R9: -1026.471 | S9: -985.004 | T9: -1052.597 | U9: =E9-SUM(R9:T9) -> -1331.151 | V9: -1404.188 | W9: -1311.332 | X9: -1394.946 | Y9: =F9-SUM(V9:X9) -> -1553.462 | Z9: -1659.845 | AA9: -1557.506 | AB9: -1606.655 | AC9: =G9-SUM(Z9:AB9) -> -1933.392 | AD9: -1916.097 | AE9: -1924.697 | AF9: -2171.949 | AG9: =H9-SUM(AD9:AF9) -> -2911.922 | AH9: -4036.928 | AI9: -4293.332 | AJ9: -5280.918 | AK9: =I9-SUM(AH9:AJ9) -> -6177.152 | AL9: =J9-SUM(AH9:AJ9) -> -27041.84 | AM9: -6640.8 | AN9: -12015.237 | AO9: -6514.881 | AP9: -11910.824 | AQ9: -8222.343 | AR9: -12408.692 | AS9: =K9-SUM(AM9,AO9,AQ9) -> -18281.557 | AT9: =L9-SUM(AN9,AP9,AR9) -> -20925.263 | AU9: -13335.894 | AV9: -10632.082 | AW9: -13265.473 | AX9: =M9-SUM(AU9,AV9,AW9) -> -21798.099 | AY9: -17946.855 | AZ9: -16776.285 | BA9: -17981.12 | BB9: =O9-SUM(AY9,AZ9,BA9) -> -26854.824 | BC9: -24454.617 | BE9: -18417.38 | BF9: -14358.485 | BG9: -17682.081 | BH9: =N9-SUM(BE9,BF9,BG9) -> -26809.822 | BI9: -23486.668 | BK9: -33882.146 | BL9: -35801.158 | BN9: -54106.872 | BO9: -56468.934 | BQ9: -1606.082 | BR9: -1921.419 | BS9: -1947.709
B10: Gross Profit | C10: =C7+C9 -> 1074.0496 | D10: =D7+D9 -> 1251.971 | E10: =E7+E9 -> 1560.285 | F10: =F7+F9 -> 2139.192 | G10: =G7+G9 -> 2643.463 | H10: =H7+H9 -> 3612.415 | I10: =I7+I9 -> 8408.517 | J10: =J7+J9 -> 11328.19 | ... P10: =P7+P9 -> 32781.859 | R10: =R7+R9 -> 381.219 | S10: =S7+S9 -> 327.265 | T10: =T7+T9 -> 385.077 | U10: =U7+U9 -> 466.724 | V10: =V7+V9 -> 538.172 | W10: =W7+W9 -> 509.166 | X10: =X7+X9 -> 498.163 | Y10: =Y7+Y9 -> 593.691 | ... BC10: =BC7+BC9 -> 9451.804 | BE10: =BE7+BE9 -> 8652.263 | BF10: =BF7+BF9 -> 6316.558 | BG10: =BG7+BG9 -> 6572.637 | BH10: =BH7+BH9 -> 11268.484 | BI10: =BI7+BI9 -> 11798.343 | BK10: =BK7+BK9 -> 15488.538 | BL10: =BL7+BL9 -> 15838.395 | BN10: =BN7+BN9 -> 23223.495 | BO10: =BO7+BO9 -> 24456.981 | BQ10: 675.078 | BR10: 862.338 | BS10: 711.358
B11: Gross Profit margin | C11: =C10/C7 -> 0.25610571 | D11: =D10/D7 -> 0.25944101 | E11: =E10/E7 -> 0.26199024 | F11: =F10/F7 -> 0.27414573 | G11: =G10/G7 -> 0.28119371 | H11: =H10/H7 -> 0.28813847 | I11: =I10/I7 -> 0.2982077 | J11: =J10/J7 -> 0.21792856 | ... P11: =P10/P7 -> 0.27582849 | R11: =R10/R7 -> 0.27081176 | S11: =S10/S7 -> 0.24938865 | T11: =T10/T7 -> 0.26784723 | U11: =U10/U7 -> 0.25959758 | V11: =V10/V7 -> 0.27707119 | W11: =W10/W7 -> 0.27968501 | X11: =X10/X7 -> 0.26314544 | Y11: =Y10/Y7 -> 0.27650149 | ... BC11: =BC10/BC7 -> 0.27876148 | BE11: =BE10/BE7 -> 0.31962974 | BF11: =BF10/BF7 -> 0.30551608 | BG11: =BG10/BG7 -> 0.27098386 | BH11: =BH10/BH7 -> 0.29592924 | BI11: =BI10/BI7 -> 0.33437266 | BK11: =BK10/BK7 -> 0.31371933 | BL11: =BL10/BL7 -> 0.30671054 | BN11: =BN10/BN7 -> 0.30031533 | BO11: =BO10/BO7 -> 0.30221445 | BQ11: =BQ10/BQ7 -> 0.29464463 | BR11: =BR10/BR7 -> 0.30977488 | BS11: =BS10/BS7 -> 0.26752165
B12: General Administrative Expenses | C12: -128.28261 | D12: -142.567 | E12: -159.664 | F12: -234.744 | G12: -263.248 | H12: -353.681 | I12: -715.407 | J12: -1238.763 | K12: -1388.277 | L12: -2004.377 | M12: -2275.527 | N12: -2978.49 | O12: -2990.173 | P12: =SUM(BB12,BC12,AZ12,BA12) -> -3258.626 | R12: -34.708 | S12: -39.869 | T12: -39.6 | U12: =E12-SUM(R12:T12) -> -45.487 | V12: -38.613 | W12: -55.972 | X12: -66.617 | Y12: =F12-SUM(V12:X12) -> -73.542 | Z12: -63.816 | AA12: -63.808 | AB12: -66.481 | AC12: =G12-SUM(Z12:AB12) -> -69.143 | AD12: -76.769 | AE12: -80.799 | AF12: -82.105 | AG12: =H12-SUM(AD12:AF12) -> -114.008 | AH12: -132.796 | AI12: -145.579 | AJ12: -194.805 | AK12: =I12-SUM(AH12:AJ12) -> -242.227 | AL12: =J12-SUM(AH12:AJ12) -> -765.583 | AM12: -210.988 | AN12: -358.757 | AO12: -247.964 | AP12: -409.739 | AQ12: -403.85 | AR12: -543.018 | AS12: =K12-SUM(AM12,AO12,AQ12) -> -525.475 | AT12: =L12-SUM(AN12,AP12,AR12) -> -692.863 | AU12: -481.297 | AV12: -400.86 | AW12: -570.708 | AX12: =M12-SUM(AU12,AV12,AW12) -> -822.662 | AY12: -660.35 | AZ12: -644.656 | BA12: -699.259 | BB12: =O12-SUM(AY12,AZ12,BA12) -> -985.908 | BC12: -928.803 | BE12: -664.69 | BF12: -541.355 | BG12: -760.72 | BH12: =N12-SUM(BE12,BF12,BG12) -> -1011.725 | BI12: -864.186 | BK12: -1245.971 | BL12: -1344.671 | BN12: -2100.192 | BO12: -2144.839 | BQ12: -66.977 | BR12: -78.118 | BS12: -82.745
B13: Marketing, Sales and Distribution Expenses | C13: -449.07643 | D13: -478.147 | E13: -598.206 | F13: -752.076 | G13: -921.325 | H13: -1120.598 | I13: -2486.22 | J13: -4389.641 | K13: -5133.098 | L13: -7411.104 | M13: -8600.376 | N13: -11257.232 | O13: -12762.944 | P13: =SUM(BB13,BC13,AZ13,BA13) -> -13621.089 | R13: -152.376 | S13: -118.292 | T13: -145.685 | U13: =E13-SUM(R13:T13) -> -181.853 | V13: -206.804 | W13: -172.846 | X13: -153.876 | Y13: =F13-SUM(V13:X13) -> -218.55 | Z13: -275.631 | AA13: -183.824 | AB13: -210.326 | AC13: =G13-SUM(Z13:AB13) -> -251.544 | AD13: -279.916 | AE13: -227.249 | AF13: -270.405 | AG13: =H13-SUM(AD13:AF13) -> -343.028 | AH13: -537.25 | AI13: -484.019 | AJ13: -640.371 | AK13: =I13-SUM(AH13:AJ13) -> -824.58 | AL13: =J13-SUM(AH13:AJ13) -> -2728.001 | AM13: -991.948 | AN13: -1692.145 | AO13: -906.496 | AP13: -1530.049 | AQ13: -1190.363 | AR13: -1493.086 | AS13: =K13-SUM(AM13,AO13,AQ13) -> -2044.291 | AT13: =L13-SUM(AN13,AP13,AR13) -> -2695.824 | AU13: -2040.865 | AV13: -1639.326 | AW13: -1758.599 | AX13: =M13-SUM(AU13,AV13,AW13) -> -3161.586 | AY13: -3251.343 | AZ13: -2644.952 | BA13: -2699.03 | BB13: =O13-SUM(AY13,AZ13,BA13) -> -4167.619 | BC13: -4109.488 | BE13: -2818.513 | BF13: -2213.887 | BG13: -2344.107 | BH13: =N13-SUM(BE13,BF13,BG13) -> -3880.725 | BI13: -4254.963 | BK13: -5201.7 | BL13: -6091.594 | BN13: -7936.163 | BO13: -9247.76 | BQ13: -211.264 | BR13: -281.943 | BS13: -228.232
B14: Research and Development Expenses | C14: -8.733516 | D14: -13.525 | E14: -12.551 | F14: -19.956 | G14: -24.209 | H14: -39.786 | I14: -88.643 | J14: -164.649 | K14: -238.705 | L14: -344.639 | M14: -415.128 | N14: -543.371 | O14: -628.46 | P14: =SUM(BB14,BC14,AZ14,BA14) -> -655.452 | R14: -3.645 | S14: -3.13 | T14: -3.093 | U14: =E14-SUM(R14:T14) -> -2.683 | V14: -3.836 | W14: -5.253 | X14: -4.451 | Y14: =F14-SUM(V14:X14) -> -6.416 | Z14: -5.682 | AA14: -5.494 | AB14: -5.577 | AC14: =G14-SUM(Z14:AB14) -> -7.456 | AD14: -8.865 | AE14: -9.745 | AF14: -8.31 | AG14: =H14-SUM(AD14:AF14) -> -12.866 | AH14: -12.484 | AI14: -17.23 | AJ14: -20.831 | AK14: =I14-SUM(AH14:AJ14) -> -38.098 | AL14: =J14-SUM(AH14:AJ14) -> -114.104 | AM14: -39.884 | AN14: -69.459 | AO14: -39.268 | AP14: -68.888 | AQ14: -53.429 | AR14: -81.514 | AS14: =K14-SUM(AM14,AO14,AQ14) -> -106.124 | AT14: =L14-SUM(AN14,AP14,AR14) -> -124.778 | AU14: -77.614 | AV14: -68.641 | AW14: -79.388 | AX14: =M14-SUM(AU14,AV14,AW14) -> -189.485 | AY14: -140.298 | AZ14: -133.675 | BA14: -149.267 | BB14: =O14-SUM(AY14,AZ14,BA14) -> -205.22 | BC14: -167.29 | BE14: -107.188 | BF14: -92.699 | BG14: -105.819 | BH14: =N14-SUM(BE14,BF14,BG14) -> -237.665 | BI14: -183.605 | BK14: -206.325 | BL14: -282.4 | BN14: -327.627 | BO14: -452.859 | BQ14: -5.586 | BR14: -8.865 | BS14: -9.895
B15: Other Operating Income | C15: 37.216977 | D15: 58.773 | E15: 114.557 | F15: 87.331 | G15: 229.896 | H15: 895.987 | I15: 1118.931 | J15: 2401.751 | K15: 2745.639 | L15: 3964.12 | M15: 2078.007 | N15: 2719.952 | O15: 3025.401 | P15: =SUM(BB15,BC15,AZ15,BA15) -> 2731.399 | R15: 22.558 | S15: 26.499 | T15: 71.551 | U15: =E15-SUM(R15:T15) -> -6.051 | V15: 31.776 | W15: 16.379 | X15: 9.607 | Y15: =F15-SUM(V15:X15) -> 29.569 | Z15: 54.783 | AA15: 42.459 | AB15: 74.744 | AC15: =G15-SUM(Z15:AB15) -> 57.91 | AD15: 102.224 | AE15: 44.229 | AF15: 13.302 | AG15: =H15-SUM(AD15:AF15) -> 736.232 | AH15: 422.51 | AI15: 257.552 | AJ15: 365.348 | AK15: =I15-SUM(AH15:AJ15) -> 73.521 | AL15: =J15-SUM(AH15:AJ15) -> 1356.341 | AM15: 228.209 | AN15: 403.661 | AO15: 1094.885 | AP15: 1890.503 | AQ15: 359.176 | AR15: 587.727 | AS15: =K15-SUM(AM15,AO15,AQ15) -> 1063.369 | AT15: =L15-SUM(AN15,AP15,AR15) -> 1082.229 | AU15: 1351.312 | AV15: 3.224 | AW15: 134.745 | AX15: =M15-SUM(AU15,AV15,AW15) -> 588.726 | AY15: 1131.685 | AZ15: 427.797 | BA15: 670.322 | BB15: =O15-SUM(AY15,AZ15,BA15) -> 795.597 | BC15: 837.683 | BE15: 1866.214 | BF15: 4.354 | BG15: 179.607 | BH15: =N15-SUM(BE15,BF15,BG15) -> 669.777 | BI15: 1481.012 | BK15: 1982.666 | BL15: 1627.459 | BN15: 2311.06 | BO15: 2419.912 | BQ15: 96.87 | BR15: 126.614 | BS15: 60.538
B16: Other Operating Expenses | C16: -16.492653 | D16: -60.193 | E16: -125.337 | F16: -66.029 | G16: -171.839 | H16: -564.347 | I16: -378.281 | J16: -878.881 | K16: -1169.204 | L16: -1688.082 | M16: -1575.129 | N16: -2061.723 | O16: -2253.736 | P16: =SUM(BB16,BC16,AZ16,BA16) -> -2019.794 | R16: -24.283 | S16: -23.9 | T16: -46.863 | U16: =E16-SUM(R16:T16) -> -30.291 | V16: -24.314 | W16: -13.374 | X16: -22.614 | Y16: =F16-SUM(V16:X16) -> -5.727 | Z16: -28.728 | AA16: -33.077 | AB16: -26.978 | AC16: =G16-SUM(Z16:AB16) -> -83.056 | AD16: -44.882 | AE16: -46.506 | AF16: -7.361 | AG16: =H16-SUM(AD16:AF16) -> -465.598 | AH16: -254.476 | AI16: -23.315 | AJ16: 15.629 | AK16: =I16-SUM(AH16:AJ16) -> -116.119 | AL16: =J16-SUM(AH16:AJ16) -> -616.719 | AM16: -207.595 | AN16: -360.722 | AO16: -71.401 | AP16: -120.225 | AQ16: -441.924 | AR16: -692.11 | AS16: =K16-SUM(AM16,AO16,AQ16) -> -448.284 | AT16: =L16-SUM(AN16,AP16,AR16) -> -515.025 | AU16: -827.271 | AV16: -1.957 | AW16: -215.61 | AX16: =M16-SUM(AU16,AV16,AW16) -> -530.291 | AY16: -720.551 | AZ16: -365.573 | BA16: -465.097 | BB16: =O16-SUM(AY16,AZ16,BA16) -> -702.515 | BC16: -486.609 | BE16: -1142.493 | BF16: -2.644 | BG16: -287.395 | BH16: =N16-SUM(BE16,BF16,BG16) -> -629.191 | BI16: -942.97 | BK16: -1213.763 | BL16: -1129.405 | BN16: -1592.246 | BO16: -1679.257 | BQ16: -55.232 | BR16: -122.723 | BS16: -97.753
B17: Income from Investment Activities | C17: 444.15896 | D17: 680.495 | E17: 1709.158 | F17: 1131.907 | G17: 2503.149 | H17: 6096.145 | I17: 3880.982 | J17: 7811.62 | K17: 7623.622 | L17: 11006.892 | M17: 6108.366 | N17: 7995.382 | O17: 11057.857 | P17: =SUM(BB17,BC17,AZ17,BA17) -> 9274.288 | R17: 315.845 | S17: 646.472 | T17: 1603.173 | U17: =E17-SUM(R17:T17) -> -856.332 | V17: 553.322 | W17: 143.209 | X17: 264.157 | Y17: =F17-SUM(V17:X17) -> 171.219 | Z17: 725.238 | AA17: 319.477 | AB17: 1205.45 | AC17: =G17-SUM(Z17:AB17) -> 252.984 | AD17: 1448.855 | AE17: 782.121 | AF17: -105.996 | AG17: =H17-SUM(AD17:AF17) -> 3971.165 | AH17: 1082.949 | AI17: 1304.375 | AJ17: 1307.218 | AK17: =I17-SUM(AH17:AJ17) -> 186.44 | AL17: =J17-SUM(AH17:AJ17) -> 4117.078 | AM17: 524.086 | AN17: 894.346 | AO17: 3165.844 | AP17: 5580.905 | AQ17: 987.608 | AR17: 1503.336 | AS17: =K17-SUM(AM17,AO17,AQ17) -> 2946.084 | AT17: =L17-SUM(AN17,AP17,AR17) -> 3028.305 | AU17: 1328.192 | AV17: 628.042 | AW17: 2095.632 | AX17: =M17-SUM(AU17,AV17,AW17) -> 2056.5 | AY17: 3389.556 | AZ17: 3099.07 | BA17: 2660.832 | BB17: =O17-SUM(AY17,AZ17,BA17) -> 1908.399 | BC17: 1605.987 | BE17: 1834.284 | BF17: 848.163 | BG17: 2793.352 | BH17: =N17-SUM(BE17,BF17,BG17) -> 2519.583 | BI17: 4435.84 | BK17: 2792.627 | BL17: 6692.227 | BN17: 5795.548 | BO17: 9855.269 | BQ17: 1219.779 | BR17: 1480.763 | BS17: 852.646
B18: Expenses from Investment Activities | C18: -113.22476 | D18: -97.632 | E18: -13.599 | F18: -11.246 | G18: -683.929 | H18: -130.934 | I18: -1607.231 | J18: -3247.512 | K18: -418.788 | L18: -604.641 | M18: -263.15 | N18: -344.443 | O18: -679.996 | P18: =SUM(BB18,BC18,AZ18,BA18) -> -379.206 | R18: -8.281 | S18: 0.197 | T18: -282.82 | U18: =E18-SUM(R18:T18) -> 277.305 | V18: -25.055 | W18: 14.794 | X18: -293.818 | Y18: =F18-SUM(V18:X18) -> 292.833 | Z18: -672.328 | AA18: 429.124 | AB18: 128.596 | AC18: =G18-SUM(Z18:AB18) -> -569.321 | AD18: -0.209 | AE18: -0.026 | AF18: -15.004 | AG18: =H18-SUM(AD18:AF18) -> -115.695 | AH18: -739.621 | AI18: -758.821 | AJ18: -404.992 | AK18: =I18-SUM(AH18:AJ18) -> 296.203 | AL18: =J18-SUM(AH18:AJ18) -> -1344.078 | AM18: -35.677 | AN18: -61.499 | AO18: -140.029 | AP18: -247.106 | AQ18: -126.715 | AR18: -235.781 | AS18: =K18-SUM(AM18,AO18,AQ18) -> -116.367 | AT18: =L18-SUM(AN18,AP18,AR18) -> -60.255 | AU18: -3.78 | AV18: -5.44 | AW18: -111.09 | AX18: =M18-SUM(AU18,AV18,AW18) -> -142.84 | AY18: -575.094 | AZ18: -7.31 | BA18: -75.809 | BB18: =O18-SUM(AY18,AZ18,BA18) -> -21.783 | BC18: -274.304 | BE18: -5.22 | BF18: -7.347 | BG18: -148.076 | BH18: =N18-SUM(BE18,BF18,BG18) -> -183.8 | BI18: -752.613 | BK18: -12.881 | BL18: -616.948 | BN18: -161.924 | BO18: -739.055 | BQ18: 129.387 | BR18: -1.36 | BS18: -0.411
B19: Operating profit | C19: =C10+SUM(C12:C18) -> 839.61561 | D19: =D10+SUM(D12:D18) -> 1199.175 | E19: =E10+SUM(E12:E18) -> 2474.643 | F19: =F10+SUM(F12:F18) -> 2274.379 | G19: =G10+SUM(G12:G18) -> 3311.958 | H19: =H10+SUM(H12:H18) -> 8395.201 | I19: =I10+SUM(I12:I18) -> 8132.648 | J19: =J10+SUM(J12:J18) -> 11622.115 | ... P19: =P10+SUM(P12:P18) -> 24853.379 | R19: =R10+SUM(R12:R18) -> 496.329 | S19: =S10+SUM(S12:S18) -> 815.242 | T19: =T10+SUM(T12:T18) -> 1541.74 | U19: =U10+SUM(U12:U18) -> -378.668 | V19: =V10+SUM(V12:V18) -> 824.648 | W19: =W10+SUM(W12:W18) -> 436.103 | X19: =X10+SUM(X12:X18) -> 230.551 | Y19: =Y10+SUM(Y12:Y18) -> 783.077 | ... BC19: =BC10+SUM(BC12:BC18) -> 5928.98 | BE19: =BE10+SUM(BE12:BE18) -> 7614.657 | BF19: =BF10+SUM(BF12:BF18) -> 4311.143 | BG19: =BG10+SUM(BG12:BG18) -> 5899.479 | BH19: =BH10+SUM(BH12:BH18) -> 8514.738 | BI19: =BI10+SUM(BI12:BI18) -> 10716.858 | BK19: =BK10+SUM(BK12:BK18) -> 12383.191 | BL19: =BL10+SUM(BL12:BL18) -> 14693.063 | BN19: =BN10+SUM(BN12:BN18) -> 19211.951 | BO19: =BO10+SUM(BO12:BO18) -> 22468.392 | BQ19: =BQ10+SUM(BQ12:BQ18) -> 1782.055 | BR19: =BR10+SUM(BR12:BR18) -> 1976.706 | BS19: =BS10+SUM(BS12:BS18) -> 1205.506
B20: % margin | C20: =+C19/C7 -> 0.20020522 | D20: =+D19/D7 -> 0.24850031 | E20: =+E19/E7 -> 0.41552173 | F20: =+F19/F7 -> 0.29147046 | G20: =+G19/G7 -> 0.35230369 | H20: =+H19/H7 -> 0.66962969 | I20: =+I19/I7 -> 0.28842402 | J20: =+J19/J7 -> 0.22358301 | ... P20: =+P19/P7 -> 0.20911779 | R20: =+R19/R7 -> 0.35258402 | S20: =+S19/S7 -> 0.6212461 | T20: =+T19/T7 -> 1.072385 | U20: =+U19/U7 -> -0.21061976 | V20: =+V19/V7 -> 0.42455981 | W20: =+W19/W7 -> 0.23955149 | X20: =+X19/X7 -> 0.12178432 | Y20: =+Y19/Y7 -> 0.3647048 | ... BC20: =+BC19/BC7 -> 0.17486304 | BE20: =+BE19/BE7 -> 0.28129876 | BF20: =+BF19/BF7 -> 0.20851918 | BG20: =+BG19/BG7 -> 0.24323016 | BH20: =+BH19/BH7 -> 0.22361126 | BI20: =+BI19/BI7 -> 0.30372268 | BK20: =+BK19/BK7 -> 0.25082073 | BL20: =+BL19/BL7 -> 0.28453118 | BN20: =+BN19/BN7 -> 0.24843993 | BO20: =+BO19/BO7 -> 0.27764149 | BQ20: =+BQ19/BQ7 -> 0.77779596 | BR20: =+BR19/BR7 -> 0.71008569 | BS20: =+BS19/BS7 -> 0.45335676
B22: Financial expenses | C22: -638.08148 | D22: -703.282 | E22: -2786.405 | F22: -1466.132 | G22: -2372.753 | H22: -8910.373 | I22: -8244.096 | J22: -16430.234 | K22: -18214.12 | L22: -26297.323 | M22: -13130.716 | N22: -17187.1 | O22: -23361.989 | P22: =SUM(BB22,BC22,AZ22,BA22) -> -21862.787 | R22: -305.709 | S22: -524.765 | T22: -1648.729 | U22: =E22-SUM(R22:T22) -> -307.202 | V22: -322.38 | W22: -357.923 | X22: -327.458 | Y22: =F22-SUM(V22:X22) -> -458.371 | Z22: -528.393 | AA22: -592.053 | AB22: -1293.026 | AC22: =G22-SUM(Z22:AB22) -> 40.719 | AD22: -1250.912 | AE22: -703.441 | AF22: -737.17 | AG22: =H22-SUM(AD22:AF22) -> -6218.85 | AH22: -2025.085 | AI22: -2412.951 | AJ22: -2581.142 | AK22: =I22-SUM(AH22:AJ22) -> -1224.918 | AL22: =J22-SUM(AH22:AJ22) -> -9411.056 | AM22: -1465.264 | AN22: -2516.935 | AO22: -7679.675 | AP22: -13292.655 | AQ22: -1709.954 | AR22: -2913.875 | AS22: =K22-SUM(AM22,AO22,AQ22) -> -7359.227 | AT22: =L22-SUM(AN22,AP22,AR22) -> -7573.858 | AU22: -3215.358 | AV22: -2349.95 | AW22: -3822.647 | AX22: =M22-SUM(AU22,AV22,AW22) -> -3742.761 | AY22: -5439.054 | AZ22: -5874.143 | BA22: -5540.338 | BB22: =O22-SUM(AY22,AZ22,BA22) -> -6508.454 | BC22: -3939.852 | BE22: -4440.533 | BF22: -3173.576 | BG22: -5095.36 | BH22: =N22-SUM(BE22,BF22,BG22) -> -4477.631 | BI22: -7117.974 | BK22: -7880.839 | BL22: -11639.906 | BN22: -13567.607 | BO22: -18053.747 | BQ22: -1444.391 | BR22: -1387.968 | BS22: -795.49
B23: Financial income | C23: 135.02642 | D23: 27.859 | E23: 1285.301 | F23: 554.695 | G23: 555.442 | H23: 444.638 | I23: 193.054 | J23: =339.665 -> 339.665 | K23: =318.356 -> 318.356 | L23: 459.638 | M23: 260.297 | N23: 340.709 | O23: 5.6 | P23: =SUM(BB23,BC23,AZ23,BA23) -> 7.022 | R23: 5.318 | S23: 12.531 | T23: 420.94 | U23: =E23-SUM(R23:T23) -> 846.512 | V23: 2.005 | W23: 82.614 | X23: 438.376 | Y23: =F23-SUM(V23:X23) -> 31.7 | Z23: 7.697 | AA23: 182.141 | AB23: 37.439 | AC23: =G23-SUM(Z23:AB23) -> 328.165 | AD23: 1.711 | AE23: 0.733 | AF23: 448.195 | AG23: =H23-SUM(AD23:AF23) -> -6.001 | AH23: 28.219 | AI23: -21.663 | AJ23: 102.225 | AK23: =I23-SUM(AH23:AJ23) -> 84.273 | AL23: =J23-SUM(AH23:AJ23) -> 230.884 | AM23: 129.071 | AN23: 226.139 | AO23: 17.357 | AP23: 12.768 | AQ23: -24.31 | AR23: -59.976 | AS23: =K23-SUM(AM23,AO23,AQ23) -> 196.238 | AT23: =L23-SUM(AN23,AP23,AR23) -> 280.707 | AU23: 13.946 | AV23: 35.637 | AW23: 19.397 | AX23: =M23-SUM(AU23,AV23,AW23) -> 191.317 | AY23: 1.204 | AZ23: 1.255 | BA23: 1.335 | BB23: =O23-SUM(AY23,AZ23,BA23) -> 1.806 | BC23: 2.626 | BE23: 19.26 | BF23: 48.127 | BG23: 25.855 | BH23: =N23-SUM(BE23,BF23,BG23) -> 247.467 | BI23: 1.576 | BK23: 68.544 | BL23: 2.531 | BN23: 99.543 | BO23: 4.056 | BQ23: 34.263 | BR23: 18.892 | BS23: -13.61
B24: Net monetary gain | C24: 0 | D24: 0 | E24: 0 | F24: 0 | G24: 0 | H24: 0 | I24: 0 | J24: 5841.449 | K24: 4475.153 | L24: 6461.171 | M24: 3712.173 | N24: 4858.948 | O24: 2922.25 | P24: =SUM(BB24,BC24,AZ24,BA24) -> 3310.261 | AH24: 0 | AI24: 0 | AJ24: 0 | AK24: =I24-SUM(AH24:AJ24) -> 0 | AL24: =J24-SUM(AH24:AJ24) -> 5841.449 | AM24: 0 | AN24: 1427.8 | AO24: 0 | AP24: 1058.281 | AQ24: 0 | AR24: 3265.006 | AS24: =K24-SUM(AM24,AO24,AQ24) -> 4475.153 | AT24: =L24-SUM(AN24,AP24,AR24) -> 710.084 | AU24: 1316.188 | AV24: 853.582 | AW24: 630.206 | AX24: =M24-SUM(AU24,AV24,AW24) -> 912.197 | AY24: 706.992 | AZ24: 819.253 | BA24: 765.224 | BB24: =O24-SUM(AY24,AZ24,BA24) -> 630.781 | BC24: 1095.003 | BE24: 1817.706 | BF24: 1152.751 | BG24: 840.027 | BH24: =N24-SUM(BE24,BF24,BG24) -> 1048.464 | BI24: 925.225 | BK24: 3079.642 | BL24: 1568.712 | BN24: 4150.778 | BO24: 2451.658
U25: =E25-SUM(R25:T25) -> 0 | Y25: =F25-SUM(V25:X25) -> 0 | AC25: =R25-SUM(Z25:AB25) -> 0 | AG25: =V25-SUM(AD25:AF25) -> 0
B26: Profit before tax | C26: =+C19+C22+C23+C24 -> 336.56055 | D26: =+D19+D22+D23+D24 -> 523.752 | E26: =+E19+E22+E23+E24 -> 973.539 | F26: =+F19+F22+F23+F24 -> 1362.942 | G26: =+G19+G22+G23+G24 -> 1494.647 | H26: =+H19+H22+H23+H24 -> -70.534 | I26: =+I19+I22+I23+I24 -> 81.606 | J26: =+J19+J22+J23+J24 -> 1372.995 | ... P26: =+P19+P22+P23+P24 -> 6307.875 | R26: =+R19+R22+R23 -> 195.938 | S26: =+S19+S22+S23 -> 303.008 | T26: =+T19+T22+T23 -> 313.951 | U26: =+U19+U22+U23 -> 160.642 | V26: =+V19+V22+V23 -> 504.273 | W26: =+W19+W22+W23 -> 160.794 | X26: =+X19+X22+X23 -> 341.469 | Y26: =+Y19+Y22+Y23 -> 356.406 | Z26: =+Z19+Z22+Z23+Z24 -> -70.579 | AA26: =+AA19+AA22+AA23+AA24 -> 682.08 | AB26: =+AB19+AB22+AB23+AB24 -> 465.985 | AC26: =+AC19+AC22+AC23+AC24 -> 417.161 | AD26: =+AD19+AD22+AD23+AD24 -> 664.818 | AE26: =+AE19+AE22+AE23+AE24 -> 377.036 | AF26: =+AF19+AF22+AF23+AF24 -> 39.33 | AG26: =+AG19+AG22+AG23+AG24 -> -1151.718 | ... BC26: =+BC19+BC22+BC23+BC24 -> 3086.757 | BE26: =+BE19+BE22+BE23+BE24 -> 5011.09 | BF26: =+BF19+BF22+BF23+BF24 -> 2338.445 | BG26: =+BG19+BG22+BG23+BG24 -> 1670.001 | BH26: =+BH19+BH22+BH23+BH24 -> 5333.038 | BI26: =+BI19+BI22+BI23+BI24 -> 4525.685 | BK26: =+BK19+BK22+BK23+BK24 -> 7650.538 | BL26: =+BL19+BL22+BL23+BL24 -> 4624.4 | BN26: =+BN19+BN22+BN23+BN24 -> 9894.665 | BO26: =+BO19+BO22+BO23+BO24 -> 6870.359 | BQ26: =+BQ19+BQ22+BQ23 -> 371.927 | BR26: =+BR19+BR22+BR23 -> 607.63 | BS26: =+BS19+BS22+BS23 -> 396.406
B27: Current Tax (Expense)/Income | C27: -59.825029 | D27: -68.079 | E27: -118.197 | F27: -232.123 | G27: -349.929 | H27: -450.711 | I27: -680.294 | J27: -1300.719 | K27: -1297.001 | L27: -1872.594 | M27: -628.228 | N27: -822.302 | O27: -1092.526 | P27: =SUM(BB27,BC27,AZ27,BA27) -> -1936.424 | R27: -33.208 | S27: -38.206 | T27: -52.428 | U27: =E27-SUM(R27:T27) -> 5.645 | V27: -108.769 | W27: -6.824 | X27: -82.959 | Y27: =F27-SUM(V27:X27) -> -33.571 | Z27: -67.338 | AA27: -134.062 | AB27: -97.953 | AC27: =G27-SUM(Z27:AB27) -> -50.576 | AD27: -133.122 | AE27: -147.481 | AF27: -16.48 | AG27: =H27-SUM(AD27:AF27) -> -153.628 | AH27: -190.297 | AI27: -173.977 | AJ27: -203.894 | AK27: =I27-SUM(AH27:AJ27) -> -112.126 | AL27: =J27-SUM(AH27:AJ27) -> -732.551 | AM27: -283.647 | AN27: -489.114 | AO27: -243.223 | AP27: -417.827 | AQ27: -317.871 | AR27: -484.03 | AS27: =K27-SUM(AM27,AO27,AQ27) -> -452.26 | AT27: =L27-SUM(AN27,AP27,AR27) -> -481.623 | AU27: -204.028 | AV27: -236.149 | AW27: 25.373 | AX27: =M27-SUM(AU27,AV27,AW27) -> -213.424 | AY27: -287.036 | AZ27: -23.193 | BA27: -664.908 | BB27: =O27-SUM(AY27,AZ27,BA27) -> -117.389 | BC27: -1130.934 | BE27: -281.77 | BF27: -318.915 | BG27: 33.821 | BH27: =N27-SUM(BE27,BF27,BG27) -> -255.438 | BI27: -375.638 | BK27: -617.611 | BL27: -327.47 | BN27: -630.138 | BO27: -1016.953 | BQ27: -96.689 | BR27: -133.122 | BS27: -159.466
B28: Deferred Tax Income/(Expenses) | C28: 7.560895 | D28: -10.676 | E28: -67.721 | F28: -28.394 | G28: 58.867 | H28: 358.826 | I28: 798.208 | J28: 1357.23 | K28: 742.627 | L28: 1072.196 | M28: -2320.843 | N28: -3037.805 | O28: -380.589 | P28: =SUM(BB28,BC28,AZ28,BA28) -> 90.843 | R28: -10.453 | S28: -29.118 | T28: -4.828 | U28: =E28-SUM(R28:T28) -> -23.322 | V28: 3.942 | W28: -8.036 | X28: 14.256 | Y28: =F28-SUM(V28:X28) -> -38.556 | Z28: 93.774 | AA28: -8.544 | AB28: 5.45 | AC28: =G28-SUM(Z28:AB28) -> -31.813 | AD28: 9.428 | AE28: 3.041 | AF28: 10.354 | AG28: =H28-SUM(AD28:AF28) -> 336.003 | AH28: 178.185 | AI28: 223.283 | AJ28: 134.611 | AK28: =I28-SUM(AH28:AJ28) -> 262.129 | AL28: =J28-SUM(AH28:AJ28) -> 821.151 | AM28: 36.124 | AN28: -244.719 | AO28: 662.195 | AP28: 983.963 | AQ28: 371.466 | AR28: -863.989 | AS28: =K28-SUM(AM28,AO28,AQ28) -> -327.158 | AT28: =L28-SUM(AN28,AP28,AR28) -> 1196.941 | AU28: -943.384 | AV28: -160.934 | AW28: -769.271 | AX28: =M28-SUM(AU28,AV28,AW28) -> -447.254 | AY28: -592.128 | AZ28: -179.097 | BA28: -131.037 | BB28: =O28-SUM(AY28,AZ28,BA28) -> 521.673 | BC28: -120.696 | BE28: -1302.849 | BF28: -217.339 | BG28: -1025.392 | BH28: =N28-SUM(BE28,BF28,BG28) -> -492.225 | BI28: -774.905 | BK28: -1598.447 | BL28: -806.792 | BN28: -2743.792 | BO28: -998.374 | BQ28: 23.104 | BR28: 18.468 | BS28: 10.123
B29: Net profit/loss | C29: =+C26+C27+C28 -> 284.29642 | D29: =+D26+D27+D28 -> 444.997 | E29: =+E26+E27+E28 -> 787.621 | F29: =+F26+F27+F28 -> 1102.425 | G29: =+G26+G27+G28 -> 1203.585 | H29: =+H26+H27+H28 -> -162.419 | I29: =+I26+I27+I28 -> 199.52 | J29: =+J26+J27+J28 -> 1429.506 | ... P29: =+P26+P27+P28 -> 4462.294 | R29: =+R26+R27+R28 -> 152.277 | S29: =+S26+S27+S28 -> 235.684 | T29: =+T26+T27+T28 -> 256.695 | U29: =+U26+U27+U28 -> 142.965 | V29: =+V26+V27+V28 -> 399.446 | W29: =+W26+W27+W28 -> 145.934 | X29: =+X26+X27+X28 -> 272.766 | Y29: =+Y26+Y27+Y28 -> 284.279 | ... BC29: =+BC26+BC27+BC28 -> 1835.127 | BE29: =+BE26+BE27+BE28 -> 3426.471 | BF29: =+BF26+BF27+BF28 -> 1802.191 | BG29: =+BG26+BG27+BG28 -> 678.43 | BH29: =+BH26+BH27+BH28 -> 4585.375 | BI29: =+BI26+BI27+BI28 -> 3375.142 | BK29: =+BK26+BK27+BK28 -> 5434.48 | BL29: =+BL26+BL27+BL28 -> 3490.138 | BN29: =+BN26+BN27+BN28 -> 6520.735 | BO29: =+BO26+BO27+BO28 -> 4855.032 | BQ29: =+BQ26+BQ27+BQ28 -> 298.342 | BR29: =+BR26+BR27+BR28 -> 492.976 | BS29: =+BS26+BS27+BS28 -> 247.063
B30: % margin | C30: =+C29/C7 -> 0.067790102 | D30: =+D29/D7 -> 0.092214973 | E30: =+E29/E7 -> 0.13225085 | F30: =+F29/F7 -> 0.14128003 | G30: =+G29/G7 -> 0.12802923 | H30: =+H29/H7 -> -0.01295509 | I30: =+I29/I7 -> 0.0070759685 | J30: =+J29/J7 -> 0.027500438 | ... P30: =+P29/P7 -> 0.037546004 | R30: =+R29/R7 -> 0.1081751 | S30: =+S29/S7 -> 0.17960037 | T30: =+T29/T7 -> 0.17854882 | U30: =+U29/U7 -> 0.079518876 | V30: =+V29/V7 -> 0.20564983 | W30: =+W29/W7 -> 0.080161582 | X30: =+X29/X7 -> 0.14408362 | Y30: =+Y29/Y7 -> 0.13239811 | ... BC30: =+BC29/BC7 -> 0.054123288 | BE30: =+BE29/BE7 -> 0.12657984 | BF30: =+BF29/BF7 -> 0.087167461 | BG30: =+BG29/BG7 -> 0.027971053 | BH30: =+BH29/BH7 -> 0.12041962 | BI30: =+BI29/BI7 -> 0.095653704 | BK30: =+BK29/BK7 -> 0.11007504 | BL30: =+BL29/BL7 -> 0.067586526 | BN30: =+BN29/BN7 -> 0.084323084 | BO30: =+BO29/BO7 -> 0.059993539 | BQ30: =+BQ29/BQ7 -> 0.13021439 | BR30: =+BR29/BR7 -> 0.17709017 | BS30: =+BS29/BS7 -> 0.092913417
B31: Attributable to:
B32: Controlling interests | C32: 272.66325 | D32: 397.259 | E32: 700.779 | F32: 996.503 | G32: 1016.415 | H32: -464.332 | I32: -353.101 | J32: =J29-J33 -> 984.793 | K32: =K29-K33 -> 3378.878 | L32: =L29-L33 -> 4878.383 | M32: =M29-M33 -> 7400.518 | N32: 9686.71 | O32: 4874.523 | P32: =SUM(BB32,BC32,AZ32,BA32) -> 4046.843 | R32: 133.177 | S32: 218.046 | T32: 220.839 | U32: =E32-SUM(R32:T32) -> 128.717 | V32: 365.476 | W32: 121.733 | X32: 253.514 | Y32: =F32-SUM(V32:X32) -> 255.78 | Z32: -98.292 | AA32: 35.031 | AB32: 323.224 | AC32: =G32-SUM(Z32:AB32) -> 756.452 | AD32: 479.294 | AE32: 26.012 | AF32: 2.457 | AG32: =H32-SUM(AD32:AF32) -> -972.095 | AH32: -470.705 | AI32: -648.635 | AJ32: -217.078 | AK32: =I32-SUM(AH32:AJ32) -> 983.317 | AL32: =J32-SUM(AH32:AJ32) -> 2321.211 | AM32: 895.647 | AN32: 2225.853 | AO32: -1692.398 | AP32: -2471.381 | AQ32: 1456.056 | AR32: 3052.403 | AS32: =K32-SUM(AM32,AO32,AQ32) -> 2719.573 | AT32: =L32-SUM(AN32,AP32,AR32) -> 2071.508 | AU32: 2167.307 | AV32: 1260.349 | AW32: 470.48 | AX32: =M32-SUM(AU32,AV32,AW32) -> 3502.382 | AY32: 2413.368 | AZ32: 721.581 | BA32: 1067.466 | BB32: =O32-SUM(AY32,AZ32,BA32) -> 672.108 | BC32: 1585.688 | BE32: 2993.134 | BF32: 1702.084 | BG32: 627.122 | BH32: =N32-SUM(BE32,BF32,BG32) -> 4364.37 | BI32: 3158.323 | BK32: 4875.008 | BL32: 3279.913 | BN32: 5867.97 | BO32: 4593.516 | BQ32: 248.084 | BR32: 431.148 | BS32: 221.05
B33: Non-controlling interests | C33: 11.633166 | D33: 47.738 | E33: 86.842 | F33: 105.922 | G33: 187.17 | H33: 301.913 | I33: 552.621 | J33: 444.713 | K33: 843.886 | L33: 1218.392 | M33: 615.588 | N33: 805.757 | O33: 331.689 | P33: =SUM(BB33,BC33,AZ33,BA33) -> 415.451 | R33: 19.1 | S33: 17.638 | T33: 35.856 | U33: =E33-SUM(R33:T33) -> 14.248 | V33: 33.97 | W33: 24.201 | X33: 19.252 | Y33: =F33-SUM(V33:X33) -> 28.499 | Z33: 54.149 | AA33: 504.443 | AB33: 50.258 | AC33: =G33-SUM(Z33:AB33) -> -421.68 | AD33: 61.83 | AE33: 206.584 | AF33: 30.747 | AG33: =H33-SUM(AD33:AF33) -> 2.752 | AH33: 139.649 | AI33: 94 | AJ33: 116.976 | AK33: =I33-SUM(AH33:AJ33) -> 201.996 | AL33: =J33-SUM(AH33:AJ33) -> 94.088 | AM33: 257.796 | AN33: 264.361 | AO33: 301.596 | AP33: 396.181 | AQ33: 180.013 | AR33: 337.001 | AS33: =K33-SUM(AM33,AO33,AQ33) -> 104.481 | AT33: =L33-SUM(AN33,AP33,AR33) -> 220.849 | AU33: 313.776 | AV33: 74.126 | AW33: 38.492 | AX33: =M33-SUM(AU33,AV33,AW33) -> 189.194 | AY33: 165.677 | AZ33: 34.595 | BA33: 35.515 | BB33: =O33-SUM(AY33,AZ33,BA33) -> 95.902 | BC33: 249.439 | BE33: 433.337 | BF33: 100.107 | BG33: 51.308 | BH33: =N33-SUM(BE33,BF33,BG33) -> 221.005 | BI33: 216.819 | BK33: 559.472 | BL33: 210.225 | BN33: 652.765 | BO33: 261.516 | BQ33: 50.258 | BR33: 61.828 | BS33: 26.013
B35: Check | C35: =+C29-C32-C33 -> -2.6645353e-13 | D35: =+D29-D32-D33 -> 1.7053026e-13 | E35: =+E29-E32-E33 -> -6.9633188e-13 | F35: =+F29-F32-F33 -> 0 | G35: =+G29-G32-G33 -> 3.126388e-13 | H35: =+H29-H32-H33 -> -5.6843419e-13 | I35: =+I29-I32-I33 -> 0 | J35: =+J29-J32-J33 -> 0 | ... P35: =+P29-P32-P33 -> -2.228262e-11 | R35: =+R29-R32-R33 -> 7.8159701e-14 | S35: =+S29-S32-S33 -> 0 | T35: =+T29-T32-T33 -> 0 | U35: =+U29-U32-U33 -> -7.1054274e-14 | V35: =+V29-V32-V33 -> -1.9895197e-13 | W35: =+W29-W32-W33 -> -1.2079227e-13 | X35: =+X29-X32-X33 -> -4.6185278e-14 | Y35: =+Y29-Y32-Y33 -> -3.126388e-13 | ... BC35: =+BC29-BC32-BC33 -> 3.2684966e-12 | BE35: =+BE29-BE32-BE33 -> -4.5474735e-13 | BF35: =+BF29-BF32-BF33 -> 6.5369932e-13 | BG35: =+BG29-BG32-BG33 -> 2.3803182e-12 | BH35: =+BH29-BH32-BH33 -> 8.2991392e-12 | BI35: =+BI29-BI32-BI33 -> -9.3791641e-13 | BK35: =+BK29-BK32-BK33 -> 0 | BL35: =+BL29-BL32-BL33 -> -4.1779913e-12 | BN35: =+BN29-BN32-BN33 -> -6.9348971e-12 | BO35: =+BO29-BO32-BO33 -> -5.8548721e-12 | BQ35: =+BQ29-BQ32-BQ33 -> -7.8159701e-14 | BR35: =+BR29-BR32-BR33 -> 8.5265128e-14 | BS35: =+BS29-BS32-BS33 -> -1.9539925e-13
B37: As % of sales unless stated otherwise
B38: =B9 -> Cost of sales | C38: =-C9/C7 -> 0.74389429 | D38: =-D9/D7 -> 0.74055899 | E38: =-E9/E7 -> 0.73800976 | F38: =-F9/F7 -> 0.72585427 | G38: =-G9/G7 -> 0.71880629 | H38: =-H9/H7 -> 0.71186153 | I38: =-I9/I7 -> 0.7017923 | J38: =-J9/J7 -> 0.78207144 | ... P38: =-P9/P7 -> 0.72417151 | R38: =-R9/R7 -> 0.72918824 | S38: =-S9/S7 -> 0.75061135 | T38: =-T9/T7 -> 0.73215277 | U38: =-U9/U7 -> 0.74040242 | V38: =-V9/V7 -> 0.72292881 | W38: =-W9/W7 -> 0.72031499 | X38: =-X9/X7 -> 0.73685456 | Y38: =-Y9/Y7 -> 0.72349851 | ... BC38: =-BC9/BC7 -> 0.72123852 | BE38: =-BE9/BE7 -> 0.68037026 | BF38: =-BF9/BF7 -> 0.69448392 | BG38: =-BG9/BG7 -> 0.72901614 | BH38: =-BH9/BH7 -> 0.70407076 | BI38: =-BI9/BI7 -> 0.66562734 | BK38: =-BK9/BK7 -> 0.68628067 | BL38: =-BL9/BL7 -> 0.69328946 | BN38: =-BN9/BN7 -> 0.69968467 | BO38: =-BO9/BO7 -> 0.69778555
B39: =B12 -> General Administrative Expenses | C39: =-C12/C7 -> 0.030588817 | D39: =-D12/D7 -> 0.029543597 | E39: =-E12/E7 -> 0.026809468 | F39: =-F12/F7 -> 0.030083351 | G39: =-G12/G7 -> 0.028002541 | H39: =-H12/H7 -> 0.028210795 | I39: =-I12/I7 -> 0.025371879 | J39: =-J12/J7 -> 0.023830978 | ... P39: =-P12/P7 -> 0.027418271 | R39: =-R12/R7 -> 0.024655997 | S39: =-S12/S7 -> 0.030381728 | T39: =-T12/T7 -> 0.027544492 | U39: =-U12/U7 -> 0.025300424 | V39: =-V12/V7 -> 0.019879425 | W39: =-W12/W7 -> 0.030745433 | X39: =-X12/X7 -> 0.035189205 | Y39: =-Y12/Y7 -> 0.034250936 | ... BC39: =-BC12/BC7 -> 0.02739313 | BE39: =-BE12/BE7 -> 0.024554812 | BF39: =-BF12/BF7 -> 0.026183984 | BG39: =-BG12/BG7 -> 0.031363795 | BH39: =-BH12/BH7 -> 0.026569591 | BI39: =-BI12/BI7 -> 0.024491589 | BK39: =-BK12/BK7 -> 0.025237062 | BL39: =-BL12/BL7 -> 0.026039555 | BN39: =-BN12/BN7 -> 0.027158697 | BO39: =-BO12/BO7 -> 0.026503735
B40: =B13 -> Marketing, Sales and Distribution Expenses | C40: =-C13/C7 -> 0.10708168 | D40: =-D13/D7 -> 0.099084517 | E40: =-E13/E7 -> 0.10044584 | F40: =-F13/F7 -> 0.096381447 | G40: =-G13/G7 -> 0.098004321 | H40: =-H13/H7 -> 0.089382695 | I40: =-I13/I7 -> 0.088173688 | J40: =-J13/J7 -> 0.084446691 | ... P40: =-P13/P7 -> 0.11460864 | R40: =-R13/R7 -> 0.10824542 | S40: =-S13/S7 -> 0.090143103 | T40: =-T13/T7 -> 0.10133382 | U40: =-U13/U7 -> 0.10114886 | V40: =-V13/V7 -> 0.10647048 | W40: =-W13/W7 -> 0.09494435 | X40: =-X13/X7 -> 0.081282166 | Y40: =-Y13/Y7 -> 0.10178595 | ... BC40: =-BC13/BC7 -> 0.12120088 | BE40: =-BE13/BE7 -> 0.1041208 | BF40: =-BF13/BF7 -> 0.10708016 | BG40: =-BG13/BG7 -> 0.096645403 | BH40: =-BH13/BH7 -> 0.10191433 | BI40: =-BI13/BI7 -> 0.1205884 | BK40: =-BK13/BK7 -> 0.1053601 | BL40: =-BL13/BL7 -> 0.11796372 | BN40: =-BN13/BN7 -> 0.10262673 | BO40: =-BO13/BO7 -> 0.1142744
B41: =+B14 -> Research and Development Expenses | C41: =C14/C7 -> -0.0020824953 | D41: =D14/D7 -> -0.0028027324 | E41: =E14/E7 -> -0.0021074609 | F41: =F14/F7 -> -0.0025574386 | G41: =G14/G7 -> -0.0025751897 | H41: =H14/H7 -> -0.0031734662 | I41: =I14/I7 -> -0.0031437203 | J41: =J14/J7 -> -0.0031674716 | ... P41: =P14/P7 -> -0.0055150117 | R41: =R14/R7 -> -0.0025893485 | S41: =S14/S7 -> -0.0023851817 | T41: =T14/T7 -> -0.0021513918 | U41: =U14/U7 -> -0.0014923173 | V41: =V14/V7 -> -0.0019749171 | W41: =W14/W7 -> -0.0028854742 | X41: =X14/X7 -> -0.0023511589 | Y41: =Y14/Y7 -> -0.0029881429 | ... BC41: =BC14/BC7 -> -0.0049338737 | BE41: =BE14/BE7 -> -0.0039597124 | BF41: =BF14/BF7 -> -0.0044836182 | BG41: =BG14/BG7 -> -0.0043628213 | BH41: =BH14/BH7 -> -0.0062414804 | BI41: =BI14/BI7 -> -0.0052034843 | BK41: =BK14/BK7 -> -0.0041790995 | BL41: =BL14/BL7 -> -0.0054686763 | BN41: =BN14/BN7 -> -0.0042367185 | BO41: =BO14/BO7 -> -0.0055959701
B42: Financial income as a % of cash | C42: =C23/C127 -> 0.058986839 | D42: =D23/D127 -> 0.008731904 | E42: =E23/E127 -> 0.38032699 | F42: =F23/F127 -> 0.10908332 | G42: =G23/G127 -> 0.074418185 | H42: =H23/H127 -> 0.047202974 | I42: =I23/I127 -> 0.020395906 | J42: =J23/J127 -> 0.02177856 | ... P42: =P23/P127 -> 0.00040902397 | R42: =(SUM(F23:R23)/R127) -> 1.0002644 | S42: =(SUM(P23:S23)/S127) -> 0.0080442698 | T42: =(SUM(P23:T23)/T127) -> 0.1104332 | U42: =(SUM(R23:U23)/U127) -> 0.38032699 | V42: =(SUM(S23:V23)/V127) -> 0.33465657 | W42: =(SUM(T23:W23)/W127) -> 0.32824475 | X42: =(SUM(U23:X23)/X127) -> 0.3588269 | Y42: =(SUM(V23:Y23)/Y127) -> 0.10908332 | Z42: =(SUM(W23:Z23)/Z127) -> 0.11119705 | AA42: =(SUM(X23:AA23)/AA127) -> 0.10057015 | AB42: =(SUM(Y23:AB23)/AB127) -> 0.043842324 | ... AK42: =(SUM(AH23:AK23)/AK127) -> 0.020395906 | AL42: =(SUM(AH23:AJ23,AL23)/AL127) -> 0.02177856 | AM42: =(SUM(AI23:AM23)/AM127) -> 0.053198823 | AN42: =(SUM(AJ23:AN23)/AN127) -> 0.046487476 | AO42: =(SUM(AO23,AM23,AK23,AJ23)/AO127) -> 0.037996702 | AP42: =(SUM(AP23,AN23,AL23,AJ23)/AP127) -> 0.065283941 | AQ42: =(SUM(AQ23,AO23,AM23,AK23)/AQ127) -> 0.021307044 | AR42: =(SUM(AR23,AP23,AN23,AL23)/AR127) -> 0.042307786 | AS42: =(SUM(AS23,AQ23,AO23,AM23)/AS127) -> 0.027299859 | AT42: =(SUM(AT23,AR23,AP23,AN23)/AT127) -> 0.03941516 | AU42: =(SUM(AT23:AU23,AR23,AP23)/AU127) -> 0.019534483 | AV42: =(SUM(AT23:AV23,AR23)/AV127) -> 0.016157916 | AW42: =(SUM(AT23:AW23)/AW127) -> 0.014986057 | AX42: =(SUM(AX23,AV23,AW23,AU23)/AX127) -> 0.0098921139 | AY42: =(SUM(AX23,AY23,AV23,AW23)/AY127) -> 0.010339479 | AZ42: =(SUM(AX23,AY23,AZ23,AW23)/AZ127) -> 0.0077807723 | BA42: =(SUM(AX23:BA23)/BA127) -> 0.006596825 | BB42: =(SUM(BB23,AZ23,BA23,AY23)/BB127) -> 0.00024008468 | BC42: =(SUM(BB23,BC23,AZ23,BA23)/BC127) -> 0.00040902397 | BH42: =(SUM(BH23,BF23,BG23,BE23)/BH127) -> 0.0098921198 | BI42: =(SUM(BI23,BG23,BH23,BF23)/BI127) -> 0.013491588
B43: Financial expenses as a % of debt | C43: =C22/C123 -> -0.21608975 | D43: =D22/D123 -> -0.16315922 | E43: =E22/E123 -> -0.5311735 | F43: =F22/F123 -> -0.2494411 | G43: =G22/G123 -> -0.25408966 | H43: =H22/H123 -> -0.49105209 | I43: =I22/I123 -> -0.34726508 | J43: =J22/J123 -> -0.42002583 | ... P43: =P22/P123 -> -0.3753113 | R43: =(SUM(F22:R22)/R123) -> -33.523896 | S43: =(SUM(P22:S22)/S123) -> -4.7287016 | T43: =(SUM(P22:T22)/T123) -> -3.9421733 | U43: =(SUM(R22:U22)/U123) -> -0.5311735 | V43: =(SUM(S22:V22)/V123) -> -0.50439512 | W43: =(SUM(T22:W22)/W123) -> -0.44808116 | X43: =(SUM(U22:X22)/X123) -> -0.22852813 | Y43: =(SUM(V22:Y22)/Y123) -> -0.2494411 | Z43: =(SUM(W22:Z22)/Z123) -> -0.26259544 | AA43: =(SUM(X22:AA22)/AA123) -> -0.26565083 | AB43: =(SUM(Y22:AB22)/AB123) -> -0.34162717 | ... AK43: =(SUM(AH22:AK22)/AK123) -> -0.34726508 | AL43: =(SUM(AH22:AJ22,AL22)/AL123) -> -0.42002583 | AM43: =(SUM(AI22:AM22)/AM123) -> -0.67837772 | AN43: =(SUM(AJ22:AN22)/AN123) -> -0.68250402 | AO43: =(SUM(AO22,AM22,AK22,AJ22)/AO123) -> -0.45278249 | AP43: =(SUM(AP22,AN22,AL22,AJ22)/AP123) -> -0.97198391 | AQ43: =(SUM(AQ22,AO22,AM22,AK22)/AQ123) -> -0.42279153 | AR43: =(SUM(AR22,AP22,AN22,AL22)/AR123) -> -0.98470391 | AS43: =(SUM(AS22,AQ22,AO22,AM22)/AS123) -> -0.59599955 | AT43: =(SUM(AT22,AR22,AP22,AN22)/AT123) -> -0.86049684 | AU43: =(SUM(AT22:AU22,AR22,AP22)/AU123) -> -0.78677202 | AV43: =(SUM(AT22:AV22,AR22)/AV123) -> -0.42531193 | AW43: =(SUM(AT22:AW22)/AW123) -> -0.35680647 | AX43: =(SUM(AX22,AV22,AW22,AU22)/AX123) -> -0.27350322 | AY43: =(SUM(AX22:AY22,AV22,AW22)/AY123) -> -0.27705461 | AZ43: =(SUM(AX22:AZ22,AW22)/AZ123) -> -0.28916335 | BA43: =(SUM(AX22:BA22)/BA123) -> -0.30079352 | BB43: =(SUM(BB22,AZ22,BA22,AY22)/BB123) -> -0.40739095 | BC43: =(SUM(BB22:BC22,AZ22,BA22)/BC123) -> -0.3753113 | BH43: =(SUM(BH22,BF22,BG22,BE22)/BH123) -> -0.27350322 | BI43: =(SUM(BI22,BG22,BH22,BF22)/BI123) -> -0.35843526
B44: Tax % of PBT | C44: =-(C28+C27)/C26 -> 0.15528895 | D44: =-(D28+D27)/D26 -> 0.15036697 | E44: =-(E28+E27)/E26 -> 0.19097129 | F44: =-(F28+F27)/F26 -> 0.19114313 | G44: =-(G28+G27)/G26 -> 0.19473628 | H44: =-(H28+H27)/H26 -> -1.3027051 | I44: =-(I28+I27)/I26 -> -1.4449183 | J44: =-(J28+J27)/J26 -> -0.041158926 | ... P44: =-(P28+P27)/P26 -> 0.29258364 | R44: =-(R28+R27)/R26 -> 0.22283069 | S44: =-(S28+S27)/S26 -> 0.22218555 | T44: =-(T28+T27)/T26 -> 0.18237241 | U44: =-(U28+U27)/U26 -> 0.11003972 | V44: =-(V28+V27)/V26 -> 0.20787748 | W44: =-(W28+W27)/W26 -> 0.092416384 | X44: =-(X28+X27)/X26 -> 0.20119835 | Y44: =-(Y28+Y27)/Y26 -> 0.20237314 | ... BC44: =-(BC28+BC27)/BC26 -> 0.40548381 | BE44: =-(BE28+BE27)/BE26 -> 0.31622242 | BF44: =-(BF28+BF27)/BF26 -> 0.22932077 | BG44: =-(BG28+BG27)/BG26 -> 0.59375473 | BH44: =-(BH28+BH27)/BH26 -> 0.14019458 | BI44: =-(BI28+BI27)/BI26 -> 0.25422516 | BK44: =-(BK28+BK27)/BK26 -> 0.28966041 | BL44: =-(BL28+BL27)/BL26 -> 0.24527766 | BN44: =-(BN28+BN27)/BN26 -> 0.34098476 | BO44: =-(BO28+BO27)/BO26 -> 0.29333649
B46: Working capital /sales | C46: =C63/C7 -> 0.015777208 | D46: =D63/D7 -> 0.012900651 | E46: =E63/E7 -> -0.14559178 | F46: =F63/F7 -> -0.055149479 | G46: =G63/G7 -> -0.096938568 | H46: =H63/H7 -> -0.19345884 | I46: =I63/I7 -> -0.11367959 | J46: =J63/J7 -> -0.096091322 | ... P46: =P63/P7 -> -0.11643188 | R46: =R63/R7 -> -0.24838352 | S46: =S63/S7 -> -0.25387935 | T46: =T63/T7 -> -0.18656316 | U46: =U63/U7 -> 0.046693458 | V46: =V63/V7 -> -0.21248224 | W46: =W63/W7 -> -0.061126131 | X46: =X63/X7 -> -0.10982569 | Y46: =Y63/Y7 -> 0.14045157 | ... BC46: =BC63/BC7 -> -0.3493177 | BE46: =BE63/BE7 -> -0.31228886 | BF46: =BF63/BF7 -> 0.044963631 | BG46: =BG63/BG7 -> -0.24973529 | BH46: =BH63/BH7 -> -0.0091208889 | BI46: =BI63/BI7 -> -0.47290007 | BK46: =BK63/BK7 -> -0.15239657 | BL46: =BL63/BL7 -> -0.29932463 | BN46: =BN63/BN7 -> -0.17562547 | BO46: =BO63/BO7 -> -0.22964447
B47: Capex/sales | C47: =-C67/C7 -> 0.062923626 | D47: =-D67/D7 -> 0.065941403 | E47: =-E67/E7 -> 0.031087021 | F47: =-F67/F7 -> 0.016407283 | G47: =-G67/G7 -> 0.020112519 | H47: =-H67/H7 -> 0.034892734 | I47: =-I67/I7 -> 0.023793121 | J47: =-J67/J7 -> 0.021841605 | ... P47: =-P67/P7 -> 0.01324685 | R47: =-R67/R7 -> 0.029691196 | S47: =-S67/S7 -> 0.041538739 | T47: =-T67/T7 -> 0.047485035 | U47: =-U67/U7 -> 0.011438504 | V47: =-V67/V7 -> 0.0097227085 | W47: =-W67/W7 -> 0.012267522 | X47: =-X67/X7 -> 0.015146513 | Y47: =-Y67/Y7 -> 0.027075853 | ... BC47: =-BC67/BC7 -> 0.0057703525 | BE47: =-BE67/BE7 -> 0.013571032 | BF47: =-BF67/BF7 -> 0.02200779 | BG47: =-BG67/BG7 -> 0.035842759 | BH47: =-BH67/BH7 -> 0.042906426 | BI47: =-BI67/BI7 -> 0.0065120286 | BK47: =-BK67/BK7 -> 0.016657152 | BL47: =-BL67/BL7 -> 0.0087284644 | BN47: =-BN67/BN7 -> 0.021876671 | BO47: =-BO67/BO7 -> 0.013268383
B49: EBITDA | C49: =C3 -> 42735 | D49: =D3 -> 43100 | E49: =E3 -> 43465 | F49: =F3 -> 43830 | G49: =G3 -> 44196 | H49: =H3 -> 44561 | I49: =I3 -> 44926 | J49: =J3 -> 44926 | ... O49: =O3 -> 46022 | P49: =P2 -> LTM | R49: =R3 -> 43190 | S49: =S3 -> 43281 | T49: =T3 -> 43373 | U49: =U3 -> 43465 | V49: =V3 -> 43555 | W49: =W3 -> 43646 | X49: =X3 -> 43738 | Y49: =Y3 -> 43830 | ... BC49: =BC3 -> 46112 | BE49: =BE3 -> 45382 | BF49: =BF3 -> 45473 | BG49: =BG3 -> 45565 | BH49: =BH3 -> 45656 | BI49: =BI3 -> 45747 | BK49: =BK3 -> 45473 | BL49: =BL3 -> 45838 | BN49: =BN3 -> 45565 | BO49: =BO3 -> 45930 | BQ49: =BQ3 -> 44104 | BR49: =BR3 -> 44286 | BS49: =BS3 -> 44377
B50: Operating profit | C50: =+C19-C17-C18 -> 508.68142 | D50: =+D19-D17-D18 -> 616.312 | E50: =+E19-E17-E18 -> 779.084 | F50: =+F19-F17-F18 -> 1153.718 | G50: =+G19-G17-G18 -> 1492.738 | H50: =+H19-H17-H18 -> 2429.99 | I50: =+I19-I17-I18 -> 5858.897 | J50: =+J19-J17-J18 -> 7058.007 | ... P50: =+P19-P17-P18 -> 15958.297 | R50: =+R19-R17-R18 -> 188.765 | S50: =+S19-S17-S18 -> 168.573 | T50: =+T19-T17-T18 -> 221.387 | U50: =+U19-U17-U18 -> 200.359 | V50: =+V19-V17-V18 -> 296.381 | W50: =+W19-W17-W18 -> 278.1 | X50: =+X19-X17-X18 -> 260.212 | Y50: =+Y19-Y17-Y18 -> 319.025 | ... BC50: =+BC19-BC17-BC18 -> 4597.297 | BE50: =+BE19-BE17-BE18 -> 5785.593 | BF50: =+BF19-BF17-BF18 -> 3470.327 | BG50: =+BG19-BG17-BG18 -> 3254.203 | BH50: =+BH19-BH17-BH18 -> 6178.955 | BI50: =+BI19-BI17-BI18 -> 7033.631 | BK50: =+BK19-BK17-BK18 -> 9603.445 | BL50: =+BL19-BL17-BL18 -> 8617.784 | BN50: =+BN19-BN17-BN18 -> 13578.327 | BO50: =+BO19-BO17-BO18 -> 13352.178 | BQ50: =+BQ19 -> 1782.055 | BR50: =+BR19 -> 1976.706 | BS50: =+BS19 -> 1205.506
B51: Depreciation, depletion & amortization | C51: =86.519348+0.851524 -> 87.370872 | D51: =115.062+0.798 -> 115.86 | E51: =145.905+3.399 -> 149.304 | F51: =165.471+5.639 -> 171.11 | G51: =183.867+2.604 -> 186.471 | H51: =225.794+4.215 -> 230.009 | I51: =342.489+6.285 -> 348.774 | J51: =1154.835+12.932 -> 1167.767 | K51: =1174.464+9.644 -> 1184.108 | L51: =1695.678+13.923 -> 1709.601 | M51: =1808.041+12.585 -> 1820.626 | N51: =2366.588+16.472 -> 2383.06 | O51: =2437.961+14.136 -> 2452.097 | P51: =SUM(BB51,BC51,AZ51,BA51) -> 2814.644 | R51: =33.732+0.775 -> 34.507 | S51: =67.189+1.633-R51 -> 34.315 | T51: =104.98+2.537-S51-R51 -> 38.695 | U51: =+E51-SUM(R51:T51) -> 41.787 | V51: =40.052+1.237 -> 41.289 | W51: =82.148+2.616-V51 -> 43.475 | X51: =121.942+4.172-V51-W51 -> 41.35 | Y51: =+F51-SUM(V51:X51) -> 44.996 | Z51: =43.455+0.56 -> 44.015 | AA51: =88.657+1.128-Z51 -> 45.77 | AB51: =134.501+1.896-AA51-Z51 -> 46.612 | AC51: =G51-SUM(Z51:AB51) -> 50.074 | AD51: =48.785+0.686 -> 49.471 | AE51: =99.751+1.432-AD51 -> 51.712 | AF51: =164.189+4.3-AE51-AD51 -> 67.306 | AG51: =H51-SUM(AD51:AF51) -> 61.52 | AH51: =76.783+1.282 -> 78.065 | AI51: =159.031+2.523-AH51 -> 83.489 | AJ51: =246.29+4.119-AI51-AH51 -> 88.855 | AK51: =I51-SUM(AH51:AJ51) -> 98.365 | AL51: =J51-SUM(AI51:AK51) -> 897.058 | AM51: =113.611+1.267 -> 114.878 | AN51: =358.327+2.509 -> 360.836 | AO51: =223.576+3.127-AM51 -> 111.825 | AP51: =770.005+6.511-AH51 -> 698.451 | AQ51: =351.41+5.87-AO51-AM51 -> 130.577 | AR51: =1220.177+10.057-AP51-AN51 -> 170.947 | AS51: =K51-SUM(AM51,AO51,AQ51) -> 826.828 | AT51: =L51-SUM(AN51,AP51,AR51) -> 479.367 | AU51: =371.116+5.886 -> 377.002 | AV51: =769.522+5.821-AU51 -> 398.341 | AW51: =1214.324+9.947-AU51-AV51 -> 448.928 | AX51: =M51-SUM(AU51,AV51,AW51) -> 596.355 | AY51: =517.634+3.355 -> 520.989 | AZ51: =1059.741+6.254-AY51 -> 545.006 | BA51: =BO51-AZ51-AY51 -> 704.989 | BB51: =O51-SUM(AY51,AZ51,BA51) -> 681.113 | BC51: =868.997+14.539 -> 883.536 | BE51: =512.525+8.129 -> 520.654 | BF51: =1039.228+7.862-BE51 -> 526.436 | BG51: =BN51-BF51-BE51 -> 584.79 | BH51: =N51-SUM(BE51,BF51,BG51) -> 751.18 | BI51: =677.416+4.391 -> 681.807 | BK51: =1039.228+7.862 -> 1047.09 | BL51: =1059.741+6.254 -> 1065.995 | BN51: =1618.621+13.259 -> 1631.88 | BO51: =1760.946+10.038 -> 1770.984 | BQ51: =143.816+1.997-Z51-AA51 -> 56.028 | BR51: =52.202+0.77 -> 52.972 | BS51: =107.55+1.56-BR51 -> 56.138
B52: EBITDA | C52: =SUM(C50:C51) -> 596.05229 | D52: =SUM(D50:D51) -> 732.172 | E52: =SUM(E50:E51) -> 928.388 | F52: =SUM(F50:F51) -> 1324.828 | G52: =SUM(G50:G51) -> 1679.209 | H52: =SUM(H50:H51) -> 2659.999 | I52: =SUM(I50:I51) -> 6207.671 | J52: =SUM(J50:J51) -> 8225.774 | ... P52: =SUM(P50:P51) -> 18772.941 | R52: =SUM(R50:R51) -> 223.272 | S52: =SUM(S50:S51) -> 202.888 | T52: =SUM(T50:T51) -> 260.082 | U52: =SUM(U50:U51) -> 242.146 | V52: =SUM(V50:V51) -> 337.67 | W52: =SUM(W50:W51) -> 321.575 | X52: =SUM(X50:X51) -> 301.562 | Y52: =SUM(Y50:Y51) -> 364.021 | ... BC52: =SUM(BC50:BC51) -> 5480.833 | BE52: =SUM(BE50:BE51) -> 6306.247 | BF52: =SUM(BF50:BF51) -> 3996.763 | BG52: =SUM(BG50:BG51) -> 3838.993 | BH52: =SUM(BH50:BH51) -> 6930.135 | BI52: =SUM(BI50:BI51) -> 7715.438 | BK52: =SUM(BK50:BK51) -> 10650.535 | BL52: =SUM(BL50:BL51) -> 9683.779 | BN52: =SUM(BN50:BN51) -> 15210.207 | BO52: =SUM(BO50:BO51) -> 15123.162 | BQ52: =SUM(BQ50:BQ51) -> 1838.083 | BR52: =SUM(BR50:BR51) -> 2029.678 | BS52: =SUM(BS50:BS51) -> 1261.644
B53: % growth | D53: =+D52/C52-1 -> 0.22836874 | E53: =+E52/D52-1 -> 0.26799167 | F53: =+F52/E52-1 -> 0.42701974 | G53: =+G52/F52-1 -> 0.26749208 | H53: =+H52/G52-1 -> 0.58407858 | I53: =+I52/H52-1 -> 1.3337118 | J53: =+J52/I52-1 -> 0.32509825 | K53: =+K52/J52-1 -> 0.48034981 | ... O53: =+O52/N52-1 -> -0.08942785 | V53: =V52/R52-1 -> 0.51237056 | W53: =W52/S52-1 -> 0.58498778 | X53: =X52/T52-1 -> 0.15948816 | Y53: =Y52/U52-1 -> 0.50331205 | Z53: =Z52/V52-1 -> 0.30666627 | AA53: =AA52/W52-1 -> 0.21017181 | AB53: =AB52/X52-1 -> 0.43963099 | AC53: =AC52/Y52-1 -> 0.13918702 | ... AL53: =AL52/AH52-1 -> 1.6825157 | AM53: =AM52/AH52-1 -> 0.67317661 | AN53: =AN52/AI52-1 -> 1.6413933 | AO53: =AO52/AI52-1 -> 1.1471115 | AP53: =AP52/AI52-1 -> 2.6131032 | AQ53: =AQ52/AJ52-1 -> 0.58217366 | AR53: =AR52/AJ52-1 -> 1.0490638 | AS53: =AS52/AK52-1 -> 1.3935224 | AT53: =AT52/AL52-1 -> 0.49662302 | AU53: =AU52/AN52-1 -> 0.26314484 | AV53: =AV52/AP52-1 -> -0.39978265 | AW53: =AW52/AR52-1 -> -0.13713631 | AX53: =AX52/AT52-1 -> 0.00048894255 | AY53: =AY52/BE52-1 -> -0.065118445 | AZ53: =AZ52/BF52-1 -> -0.1329616 | BA53: =BA52/BG52-1 -> 0.24841879 | BB53: =BB52/AX52-1 -> -0.11280999 | BC53: =BC52/BI52-1 -> -0.28962776 | BE53: =BE52/AN52-1 -> 0.74445122 | BF53: =BF52/AP52-1 -> -0.19174397 | BG53: =BG52/AR52-1 -> 0.14608438 | BH53: =BH52/AS52-1 -> 0.61601164 | BI53: =BI52/BE52-1 -> 0.22345953 | BL53: =BL52/BK52-1 -> -0.090770651 | BO53: =BO52/BN52-1 -> -0.0057228018 | BQ53: =BQ52/X52-1 -> 5.0952076 | BR53: =BR52/Z52-1 -> 3.6001287 | BS53: =BS52/AA52-1 -> 2.241959
B54: % margin | C54: =+C52/C7 -> 0.14212787 | D54: =+D52/D7 -> 0.15172512 | E54: =+E52/E7 -> 0.15588729 | F54: =+F52/F7 -> 0.16978183 | G54: =+G52/G7 -> 0.17862289 | H54: =+H52/H7 -> 0.21217054 | I54: =+I52/I7 -> 0.22015479 | J54: =+J52/J7 -> 0.15824515 | ... P54: =+P52/P7 -> 0.15795663 | R54: =+R52/R7 -> 0.15860878 | S54: =+S52/S7 -> 0.15460854 | T54: =+T52/T7 -> 0.18090471 | U54: =+U52/U7 -> 0.13468456 | V54: =+V52/V7 -> 0.17384522 | W54: =+W52/W7 -> 0.17664123 | X54: =+X52/X7 -> 0.15929458 | Y54: =+Y52/Y7 -> 0.16953659 | ... BC54: =+BC52/BC7 -> 0.16164587 | BE54: =+BE52/BE7 -> 0.2329638 | BF54: =+BF52/BF7 -> 0.19331341 | BG54: =+BG52/BG7 -> 0.1582782 | BH54: =+BH52/BH7 -> 0.18199694 | BI54: =+BI52/BI7 -> 0.2186605 | BK54: =+BK52/BK7 -> 0.2157259 | BL54: =+BL52/BL7 -> 0.18752639 | BN54: =+BN52/BN7 -> 0.19669126 | BO54: =+BO52/BO7 -> 0.18687663 | BQ54: =+BQ52/BQ7 -> 0.80224995 | BR54: =+BR52/BR7 -> 0.72911465 | BS54: =+BS52/BS7 -> 0.47446868
B56: Adjustment | C56: =C57-C52 -> -20.752288 | D56: =D57-D52 -> 1.42 | E56: =E57-E52 -> 10.78 | F56: =F57-F52 -> -21.302 | G56: =G57-G52 -> -58.057 | H56: =H57-H52 -> -331.64 | I56: =I57-I52 -> -740.65 | J56: =J57-J52 -> -1522.869 | ... P56: =P57-P52 -> -711.605 | R56: =R57-R52 -> 1.726 | S56: =S57-S52 -> -2.57 | T56: =T57-T52 -> -24.718 | U56: =U57-U52 -> 36.342 | V56: =V57-V52 -> -7.462 | W56: =W57-W52 -> -3.005 | X56: =X57-X52 -> 13.007 | Y56: =Y57-Y52 -> -23.842 | ... BC56: =BC57-BC52 -> -351.074 | BE56: =BE57-BE52 -> -723.721 | BF56: =BF57-BF52 -> 302.343 | BG56: =BG57-BG52 -> 770.768 | BH56: =BH57-BH52 -> -1007.619 | BI56: =BI57-BI52 -> -538.042 | BK56: =BK57-BK52 -> -768.903 | BL56: =BL57-BL52 -> -498.054 | BN56: =BN57-BN52 -> -718.814 | BO56: =BO57-BO52 -> -740.655 | BQ56: =BQ57-BQ52 -> -1258.518 | BR56: =BR57-BR52 -> -1483.294 | BS56: =BS57-BS52 -> -815.02
B57: Adj. EBITDA | C57: 575.3 | D57: 733.592 | E57: 939.168 | F57: 1303.526 | G57: 1621.152 | H57: 2328.359 | I57: 5467.021 | J57: 6702.905 | K57: 10600.588 | L57: 15304.999 | M57: 15595.955 | N57: 20413.909 | O57: 18416.037 | P57: =SUM(BB57,BC57,AZ57,BA57) -> 18061.336 | R57: 224.998 | S57: =425.316-R57 -> 200.318 | T57: =660.68-R57-S57 -> 235.364 | U57: =+E57-SUM(R57:T57) -> 278.488 | V57: 330.208 | W57: =648.778-V57 -> 318.57 | X57: =963.347-V57-W57 -> 314.569 | Y57: =+F57-SUM(V57:X57) -> 340.179 | Z57: 415.167 | AA57: =794.946-Z57 -> 379.779 | AB57: =1181.318-Z57-AA57 -> 386.372 | AC57: =G57-SUM(Z57:AB57) -> 439.834 | AD57: 457.502 | AE57: =809.14-AD57 -> 351.638 | AF57: =1495.751-AD57-AE57 -> 686.611 | AG57: =H57-SUM(AD57:AF57) -> 832.608 | AH57: 1244.625 | AI57: =2378.996-AH57 -> 1134.371 | AJ57: =3632.747-AH57-AI57 -> 1253.751 | AK57: =I57-SUM(AH57:AJ57) -> 1834.274 | AL57: =J57-SUM(AI57:AK57) -> 2480.509 | AM57: 2343.014 | AN57: 3572.093 | AO57: =4258.083-AM57 -> 1915.069 | AP57: =6733.87-AN57 -> 3161.777 | AQ57: =6927.254-AM57-AO57 -> 2669.171 | AR57: =11002.053-AN57-AP57 -> 4268.183 | AS57: =K57-SUM(AM57,AO57,AQ57) -> 3673.334 | AT57: =L57-SUM(AN57,AP57,AR57) -> 4302.946 | AU57: 4042.268 | AV57: =7317.091-AU57 -> 3274.823 | AW57: =10871.751-AV57-AU57 -> 3554.66 | AX57: =M57-SUM(AU57,AV57,AW57) -> 4724.204 | AY57: 5484.46 | AZ57: =BL57-AY57 -> 3701.265 | BA57: =BO57-AZ57-AY57 -> 5196.782 | BB57: =O57-SUM(AY57,AZ57,BA57) -> 4033.53 | BC57: 5129.759 | BE57: 5582.526 | BF57: =BK57-BE57 -> 4299.106 | BG57: =BN57-BF57-BE57 -> 4609.761 | BH57: =N57-SUM(BE57,BF57,BG57) -> 5922.516 | BI57: 7177.396 | BK57: 9881.632 | BL57: 9185.725 | BN57: 14491.393 | BO57: 14382.507 | BQ57: =1374.511-Z57-AA57 -> 579.565 | BR57: 546.384 | BS57: =993.008-BR57 -> 446.624
B58: % growth | D58: =+D57/C57-1 -> 0.27514688 | E58: =+E57/D57-1 -> 0.28023206 | F58: =+F57/E57-1 -> 0.38795828 | G58: =+G57/F57-1 -> 0.24366679 | H58: =+H57/G57-1 -> 0.43623732 | I58: =+I57/H57-1 -> 1.3480146 | J58: =+J57/I57-1 -> 0.22606169 | K58: =+K57/J57-1 -> 0.58149161 | ... O58: =+O57/N57-1 -> -0.097868174 | V58: =V57/R57-1 -> 0.46760416 | W58: =W57/S57-1 -> 0.59032139 | X58: =X57/T57-1 -> 0.3365213 | Y58: =Y57/U57-1 -> 0.22152121 | Z58: =Z57/V57-1 -> 0.25728934 | AA58: =AA57/W57-1 -> 0.19213674 | AB58: =AB57/X57-1 -> 0.22825835 | AC58: =AC57/Y57-1 -> 0.29294871 | ... AL58: =AL57/AH57-1 -> 0.992977 | AM58: =AM57/AH57-1 -> 0.88250598 | AN58: =AN57/AI57-1 -> 2.1489636 | AO58: =AO57/AI57-1 -> 0.68822105 | AP58: =AP57/AI57-1 -> 1.7872513 | AQ58: =AQ57/AJ57-1 -> 1.1289483 | AR58: =AR57/AJ57-1 -> 2.4043307 | AS58: =AS57/AK57-1 -> 1.0026092 | AT58: =AT57/AL57-1 -> 0.73470284 | AU58: =AU57/AN57-1 -> 0.13162451 | AV58: =AV57/AP57-1 -> 0.035753945 | AW58: =AW57/AR57-1 -> -0.16717254 | AX58: =AX57/AT57-1 -> 0.097899904 | AY58: =AY57/BE57-1 -> -0.0175666 | AZ58: =AZ57/BF57-1 -> -0.1390617 | BA58: =BA57/BG57-1 -> 0.12734304 | BB58: =BB57/AX57-1 -> -0.14619902 | BC58: =BC57/BI57-1 -> -0.28528968 | BE58: =BE57/AN57-1 -> 0.56281653 | BF58: =BF57/AP57-1 -> 0.35971196 | BG58: =BG57/AR57-1 -> 0.080028902 | BH58: =BH57/AS57-1 -> 0.61229989 | BI58: =BI57/BE57-1 -> 0.28568967 | BL58: =BL57/BK57-1 -> -0.070424298 | BO58: =BO57/BN57-1 -> -0.0075138394 | BQ58: =BQ57/X57-1 -> 0.84240977 | BR58: =BR57/Z57-1 -> 0.31605836 | BS58: =BS57/AA57-1 -> 0.17601026
B59: % margin | C59: =+C57/C7 -> 0.13717952 | D59: =+D57/D7 -> 0.15201938 | E59: =+E57/E7 -> 0.15769738 | F59: =+F57/F7 -> 0.1670519 | G59: =+G57/G7 -> 0.17244718 | H59: =+H57/H7 -> 0.18571781 | I59: =+I57/I7 -> 0.19388767 | J59: =+J57/J7 -> 0.12894862 | ... P59: =+P57/P7 -> 0.15196914 | R59: =+R57/R7 -> 0.15983491 | S59: =+S57/S7 -> 0.1526501 | T59: =+T57/T7 -> 0.16371166 | U59: =+U57/U7 -> 0.15489842 | V59: =+V57/V7 -> 0.1700035 | W59: =+W57/W7 -> 0.17499058 | X59: =+X57/X7 -> 0.16616529 | Y59: =+Y57/Y7 -> 0.15843258 | ... BC59: =+BC57/BC7 -> 0.15129167 | BE59: =+BE57/BE7 -> 0.20622828 | BF59: =+BF57/BF7 -> 0.20793698 | BG59: =+BG57/BG7 -> 0.19005626 | BH59: =+BH57/BH7 -> 0.15553518 | BI59: =+BI57/BI7 -> 0.20341204 | BK59: =+BK57/BK7 -> 0.20015181 | BL59: =+BL57/BL7 -> 0.17788157 | BN59: =+BN57/BN7 -> 0.18739589 | BO59: =+BO57/BO7 -> 0.17772437 | BQ59: =+BQ57/BQ7 -> 0.25295702 | BR59: =+BR57/BR7 -> 0.19627575 | BS59: =+BS57/BS7 -> 0.16796267
B61: CASH FLOW | C61: =C3 -> 42735 | D61: =D3 -> 43100 | E61: =E3 -> 43465 | F61: =F3 -> 43830 | G61: =G3 -> 44196 | H61: =H3 -> 44561 | I61: =I3 -> 44926 | J61: =J3 -> 44926 | ... O61: =O3 -> 46022 | P61: =P2 -> LTM | R61: =R3 -> 43190 | S61: =S3 -> 43281 | T61: =T3 -> 43373 | U61: =U3 -> 43465 | V61: =V3 -> 43555 | W61: =W3 -> 43646 | X61: =X3 -> 43738 | Y61: =Y3 -> 43830 | ... BC61: =BC3 -> 46112 | BE61: =BE3 -> 45382 | BF61: =BF3 -> 45473 | BG61: =BG3 -> 45565 | BH61: =BH3 -> 45656 | BI61: =BI3 -> 45747 | BK61: =BK3 -> 45473 | BL61: =BL3 -> 45838 | BN61: =BN3 -> 45565 | BO61: =BO3 -> 45930 | BQ61: =BQ3 -> 44104 | BR61: =BR3 -> 44286 | BS61: =BS3 -> 44377
B62: Adj. EBITDA | C62: =C57 -> 575.3 | D62: =D57 -> 733.592 | E62: =E57 -> 939.168 | F62: =F57 -> 1303.526 | G62: =G57 -> 1621.152 | H62: =H57 -> 2328.359 | I62: =I57 -> 5467.021 | J62: =J57 -> 6702.905 | ... P62: =P57 -> 18061.336 | R62: =R57 -> 224.998 | S62: =S57 -> 200.318 | T62: =T57 -> 235.364 | U62: =U57 -> 278.488 | V62: =V57 -> 330.208 | W62: =W57 -> 318.57 | X62: =X57 -> 314.569 | Y62: =Y57 -> 340.179 | ... BC62: =BC57 -> 5129.759 | BE62: =BE57 -> 5582.526 | BF62: =BF57 -> 4299.106 | BG62: =BG57 -> 4609.761 | BH62: =BH57 -> 5922.516 | BI62: =BI57 -> 7177.396 | BK62: =BK57 -> 9881.632 | BL62: =BL57 -> 9185.725 | BN62: =BN57 -> 14491.393 | BO62: =BO57 -> 14382.507 | BQ62: =BQ57 -> 579.565 | BR62: =BR57 -> 546.384 | BS62: =BS57 -> 446.624
B63: Working Capital | C63: =21.875657-25.086496-63.836647+80.487471+18.879745+25.637213+8.209115 -> 66.166058 | D63: =-66.505+56.637-182.015-25.004+272.227+10.658-3.744 -> 62.254 | E63: =-17.834-1029.696+26.665+63.864-88.681+166.843+11.766 -> -867.073 | F63: =1038.478-1468.816 -> -430.338 | G63: =966.215-1877.521 -> -911.306 | H63: =557.41-2982.819 -> -2425.409 | I63: =3429.49-6634.896 -> -3205.406 | J63: =5597.158-10592.101 -> -4994.943 | K63: =9404.93-13686.187 -> -4281.257 | L63: =13578.722-19759.949 -> -6181.227 | M63: =7585.577-18226.759 -> -10641.182 | N63: =9928.937-23857.427 -> -13928.49 | O63: =8138.617-22882.764 -> -14744.147 | P63: =SUM(AZ63:BC63) -> -13837.778 | R63: =-65.299-322.49+27.467-35.388-30.243+71.894+4.412 -> -349.647 | S63: =-59.741-557.703+73.957-4.235-150.033-4.207+19.157-R63 -> -333.158 | T63: =-915.104-33.776-16.978+76.079-191.485+136.809-6.567-R63-S63 -> -268.217 | U63: =E63-SUM(R63:T63) -> 83.949 | V63: =-68.88-300.258+18.897+3.797-55.468+3.853-14.658 -> -412.717 | W63: =-60.857-321.682-42.648-5.731-115.881+45.652-22.85-V63 -> -111.28 | X63: =-49.691-591.357-67.738-6.608-72.214+69.936-14.237-V63-W63 -> -207.912 | Y63: =F63-SUM(V63:X63) -> 301.571 | Z63: =-27.784-283.874-70.117-26.175-10.255-73.237-0.936 -> -492.378 | AA63: =28.051-189.951-189.483-35.315-104.19-208.736-10.281-Z63 -> -217.527 | AB63: =-194.63-229.423-252.08-188.839-43.149-270.517-32.009-Z63-AA63 -> -500.742 | AC63: =G63-SUM(Z63:AB63) -> 299.341 | AD63: =-203.667-110.335-11.123+59.028-47.922+204.164-50.467 -> -160.322 | AE63: =-177.419-155.893-27.444+56.292-82.197+216.866-102.736-AD63 -> -112.209 | AF63: =-148.411-317.06-263.792-159.525-41.605+45.531-86.68-AD63-AE63 -> -699.011 | AG63: =H63-SUM(AD63:AF63) -> -1453.867 | AH63: =-438.138-665.839-424.134-256.004+353.235+278.389+3.204 -> -1149.287 | AI63: =-664.519-269.263-990.301-856.494+382.138+440.665-59.022-AH63 -> -867.509 | AJ63: =-936.768-1151.029-2013.918-926.239+760.923+479.052-93.68-AH63-AI63 -> -1864.863 | AK63: =I63-SUM(AH63:AJ63) -> 676.253 | AL63: =J63-SUM(AH63:AJ63) -> -1113.284 | AM63: =-626.086-1501.796-526.476-222.599-141.051-160.471+271.514 -> -2906.965 | AN63: =-1054.901-2530.457-918.05-378.4-237.664-270.386+527.285 -> -4862.573 | AO63: =2471.342-6153.861-AM63 -> -775.554 | AP63: =4458.821-11159.659-AN63 -> -1838.265 | AQ63: =-1325.478-1837.351-1264.839-308.573+598.792+182.817+158.595-AM63-AO63 -> -113.518 | AR63: =8458.87-15513.81-AN63-AP63 -> -354.102 | AS63: =K63-SUM(AM63,AO63,AQ63) -> -485.22 | AT63: =L63-SUM(AN63,AP63,AR63) -> 873.713 | AU63: =-795.447-3492.719-600.478-336.835-757.151-490.259+351.735 -> -6121.154 | AV63: =3305.887-8877.155-AU63 -> 549.886 | AW63: =2698.789-12887.68-AV63-AU63 -> -4617.623 | AX63: =M63-SUM(AU63,AV63,AW63) -> -452.291 | AY63: =-1169.292-4113.015-6448.932-359.451-660.296-67.779+68.283 -> -12750.482 | AZ63: =BL63-AY63 -> -2706.508 | BA63: =BO63-AZ63-AY63 -> -3127.199 | BB63: =O63-SUM(AY63,AZ63,BA63) -> 3840.042 | BC63: =-1140.822-4141.876-4015.975-832.535-291.977-1988.478+567.55 -> -11844.113 | BE63: =-1098.543-4823.579-829.283-465.182-1045.655-677.066+485.76 -> -8453.548 | BF63: =BK63-BE63 -> 929.625 | BG63: =BN63-BF63-BE63 -> -6057.259 | BH63: =N63-BG63-BF63-BE63 -> -347.308 | BI63: =-1530.228-5382.615-8439.58-470.406-864.115-88.701+89.361 -> -16686.284 | BK63: =4464.556-11988.479 -> -7523.923 | BL63: =-3422.139-12034.851 -> -15456.99 | BN63: =(3597325-17178507)/1000 -> -13581.182 | BO63: =(-824217-17759972)/1000 -> -18584.189 | BQ63: =-239.197-164.333-761.881+145.044-94.439+48.333-29.85-AA63-Z63 -> -386.418 | BR63: =-83.101-137.6-471.891-76.158-51.404+43.721-18.845 -> -795.278 | BS63: =-39.38-166.42-280.763-95.621-134.118+27.897-148.506-BR63 -> -41.633
B64: Taxes | C64: -53.695588 | D64: -50.8 | E64: -141.359 | F64: -171.654 | G64: -338.022 | H64: -393.369 | I64: -566.722 | J64: -1256.415 | K64: -1356.03 | L64: -1957.819 | M64: -992.386 | N64: -1298.957 | O64: -1123.441 | P64: =SUM(AZ64:BC64) -> -1237.611 | R64: -14.544 | S64: =-51.328-R64 -> -36.784 | T64: =-75.704-S64-R64 -> -24.376 | U64: =E64-SUM(R64:T64) -> -65.655 | V64: -0.78 | W64: =-67.739-V64 -> -66.959 | X64: =-108.546-V64-W64 -> -40.807 | Y64: =F64-SUM(V64:X64) -> -63.108 | Z64: -34.288 | AA64: =-122.077-Z64 -> -87.789 | AB64: =-244.022-Z64-AA64 -> -121.945 | AC64: =G64-SUM(Z64:AB64) -> -94 | AD64: -24.087 | AE64: =-204.437-AD64 -> -180.35 | AF64: =-346.211-AD64-AE64 -> -141.774 | AG64: =H64-SUM(AD64:AF64) -> -47.158 | AH64: -224.088 | AI64: =-311.641-AH64 -> -87.553 | AJ64: =-431.037-AH64-AI64 -> -119.396 | AK64: =I64-SUM(AH64:AJ64) -> -135.685 | AL64: =J64-SUM(AH64:AJ64) -> -825.378 | AM64: -66.684 | AN64: -3.262 | AO64: =-422.02-AM64 -> -355.336 | AP64: =-852.429-AN64 -> -849.167 | AQ64: =-853.827-AM64-AO64 -> -431.807 | AR64: =-1715.247-AN64-AP64 -> -862.818 | AS64: =K64-SUM(AM64,AO64,AQ64) -> -502.203 | AT64: =L64-SUM(AN64,AP64,AR64) -> -242.572 | AU64: -97.199 | AV64: =-597.089-AU64 -> -499.89 | AW64: =-828.744-AV64-AU64 -> -231.655 | AX64: =M64-SUM(AU64,AV64,AW64) -> -163.642 | AY64: -66.67 | AZ64: =BL64-AY64 -> -297.673 | BA64: =BO64-AZ64-AY64 -> -216.342 | BB64: =O64-SUM(AY64,AZ64,BA64) -> -542.756 | BC64: -180.84 | BE64: -134.236 | BF64: =BK64-BE64 -> -672.125 | BG64: =BN64-BF64-BE64 -> -298.305 | BH64: =N64-BG64-BF64-BE64 -> -194.291 | BI64: -87.25 | BK64: -806.361 | BL64: -364.343 | BN64: -1104.666 | BO64: -580.685 | BQ64: =-249.49-AA64-Z64 -> -127.413 | BR64: -24.953 | BS64: =-205.727-BR64 -> -180.774
B65: Cash interest paid | C65: -75.880255 | D65: -173.43 | E65: -337.13 | F65: -414.644 | G65: -364.133 | H65: -756.749 | I65: -2014.244 | J65: -3851.84 | K65: -3670.666 | L65: -5299.662 | M65: -4132.167 | N65: -5408.69 | O65: -5224.851 | P65: =SUM(AZ65:BC65) -> -5651.265 | R65: -16.986 | S65: =-160.165-R65 -> -143.179 | T65: =-182.187-S65-R65 -> -22.022 | U65: =E65-SUM(R65:T65) -> -154.943 | V65: -33.311 | W65: =-194.884-V65 -> -161.573 | X65: =-260.868-V65-W65 -> -65.984 | Y65: =F65-SUM(V65:X65) -> -153.776 | Z65: -37.928 | AA65: =-175.205-Z65 -> -137.277 | AB65: =-190.301-Z65-AA65 -> -15.096 | AC65: =G65-SUM(Z65:AB65) -> -173.832 | AD65: -38.099 | AE65: =-341.606-AD65 -> -303.507 | AF65: =-486.687-AD65-AE65 -> -145.081 | AG65: =H65-SUM(AD65:AF65) -> -270.062 | AH65: -56.107 | AI65: =-778.768-AH65 -> -722.661 | AJ65: =-798.495-AH65-AI65 -> -19.727 | AK65: =I65-SUM(AH65:AJ65) -> -1215.749 | AL65: =J65-SUM(AH65:AJ65) -> -3053.345 | AM65: -55.542 | AN65: -105.284 | AO65: =-996.485-AM65 -> -940.943 | AP65: =-1811.17-AN65 -> -1705.886 | AQ65: =-1016.535-AM65-AO65 -> -20.05 | AR65: =-1879.888-AN65-AP65 -> -68.718 | AS65: =K65-SUM(AM65,AO65,AQ65) -> -2654.131 | AT65: =L65-SUM(AN65,AP65,AR65) -> -3419.774 | AU65: -72.482 | AV65: =-1718.437-AU65 -> -1645.955 | AW65: =-2459.319-AV65-AU65 -> -740.882 | AX65: =M65-SUM(AU65,AV65,AW65) -> -1672.848 | AY65: -788.277 | AZ65: =BL65-AY65 -> -1719.606 | BA65: =BO65-AZ65-AY65 -> -1285.58 | BB65: =O65-SUM(AY65,AZ65,BA65) -> -1431.388 | BC65: -1214.691 | BE65: -100.1 | BF65: =BK65-BE65 -> -2220.626 | BG65: =BN65-BF65-BE65 -> -957.399 | BH65: =N65-BG65-BF65-BE65 -> -2130.565 | BI65: -1031.601 | BK65: -2320.726 | BL65: -2507.883 | BN65: -3278.125 | BO65: -3793.463 | BQ65: =-205.039-AA65-Z65 -> -29.834 | BR65: -38.099 | BS65: =-391.271-BR65 -> -353.172
B66: Net cash from operations | C66: =SUM(C62:C65) -> 511.89021 | D66: =SUM(D62:D65) -> 571.616 | E66: =SUM(E62:E65) -> -406.394 | F66: =SUM(F62:F65) -> 286.89 | G66: =SUM(G62:G65) -> 7.691 | H66: =SUM(H62:H65) -> -1247.168 | I66: =SUM(I62:I65) -> -319.351 | J66: =SUM(J62:J65) -> -3400.293 | ... P66: =SUM(P62:P65) -> -2665.318 | R66: =SUM(R62:R65) -> -156.179 | S66: =SUM(S62:S65) -> -312.803 | T66: =SUM(T62:T65) -> -79.251 | U66: =SUM(U62:U65) -> 141.839 | V66: =SUM(V62:V65) -> -116.6 | W66: =SUM(W62:W65) -> -21.242 | X66: =SUM(X62:X65) -> -0.134 | Y66: =SUM(Y62:Y65) -> 424.866 | ... BC66: =SUM(BC62:BC65) -> -8109.885 | BE66: =SUM(BE62:BE65) -> -3105.358 | BF66: =SUM(BF62:BF65) -> 2335.98 | BG66: =SUM(BG62:BG65) -> -2703.202 | BH66: =SUM(BH62:BH65) -> 3250.352 | BI66: =SUM(BI62:BI65) -> -10627.739 | BK66: =SUM(BK62:BK65) -> -769.378 | BL66: =SUM(BL62:BL65) -> -9143.491 | BN66: =SUM(BN62:BN65) -> -3472.58 | BO66: =SUM(BO62:BO65) -> -8575.83 | BQ66: =SUM(BQ62:BQ65) -> 35.9 | BR66: =SUM(BR62:BR65) -> -311.946 | BS66: =SUM(BS62:BS65) -> -128.955
B67: Net Capex | C67: =4.161003-268.048518 -> -263.88752 | D67: =-326.139+7.929 -> -318.21 | E67: =-225.281+40.142 -> -185.139 | F67: =-135.572+7.544 -> -128.028 | G67: =-193.143+4.068 -> -189.075 | H67: =-558.319+94.721+26.145 -> -437.453 | I67: =-740.762+69.871+0 -> -670.891 | J67: =190.337-1325.69 -> -1135.353 | K67: =90.426-1198.117 -> -1107.691 | L67: =130.556-1729.827 -> -1599.271 | M67: =-2552.177+11.512 -> -2540.665 | N67: =15.069-3340.604 -> -3325.535 | O67: =161.546-1715.843 -> -1554.297 | P67: =SUM(AZ67:BC67) -> -1574.371 | R67: =-66.289+24.493 -> -41.796 | S67: =-124.212+27.906-R67 -> -54.51 | T67: =-193.822+29.248-R67-S67 -> -68.268 | U67: =E67-SUM(R67:T67) -> -20.565 | V67: =-21.104+2.219 -> -18.885 | W67: =-47.911+6.693-V67 -> -22.333 | X67: =-75.41+5.518-V67-W67 -> -28.674 | Y67: =F67-SUM(V67:X67) -> -58.136 | Z67: =-23.821+2.515 -> -21.306 | AA67: =-49.924+2.637-Z67 -> -25.981 | AB67: =-86.606+3.445-Z67-AA67 -> -35.874 | AC67: =G67-SUM(Z67:AB67) -> -105.914 | AD67: =-23.623+2.719+26.145 -> 5.241 | AE67: =-84.363+3.454+26.145-AD67 -> -60.005 | AF67: =91.898+26.145-216.142-AD67-AE67 -> -43.335 | AG67: =H67-SUM(AD67:AF67) -> -339.354 | AH67: =-80.625+6.117+0 -> -74.508 | AI67: =-193.304+13.713+0-AH67 -> -105.083 | AJ67: =40.579+0-364.429-AH67-AI67 -> -144.259 | AK67: =I67-SUM(AH67:AJ67) -> -347.041 | AL67: =J67-SUM(AH67:AJ67) -> -811.503 | AM67: =-171.29+18.683 -> -152.607 | AN67: =33.074-286.858 -> -253.784 | AO67: =-325.922+22.4-AM67 -> -150.915 | AP67: =-557.49+46.378-AN67 -> -257.328 | AQ67: =26.92+0-607.853-AM67-AO67 -> -277.411 | AR67: =48.59-1023.153-AN67-AP67 -> -463.451 | AS67: =K67-SUM(AM67,AO67:AQ67) -> -269.43 | AT67: =L67-SUM(AN67,AP67,AR67) -> -624.708 | AU67: =2.093-268.098 -> -266.005 | AV67: =-631.424+22.478-AU67 -> -342.941 | AW67: =29.878-1299.05-AV67-AU67 -> -660.226 | AX67: =M67-SUM(AU67,AV67,AW67) -> -1271.493 | AY67: =1.093-176.671 -> -175.578 | AZ67: =BL67-AY67 -> -275.156 | BA67: =BO67-AZ67-AY67 -> -623.022 | BB67: =O67-SUM(AY67,AZ67,BA67) -> -480.541 | BC67: =0.799-196.451 -> -195.652 | BE67: =2.891-370.254 -> -367.363 | BF67: =BK67-BE67 -> -455.012 | BG67: =BN67-BF67-BE67 -> -869.356 | BH67: =N67-BG67-BF67-BE67 -> -1633.804 | BI67: =1.429-231.206 -> -229.777 | BK67: =30.355-852.73 -> -822.375 | BL67: =51.144-501.878 -> -450.734 | BN67: =(-1731556+39825)/1000 -> -1691.731 | BO67: =(-1131254+57498)/1000 -> -1073.756 | BQ67: =3.559-101.35-AA67-Z67 -> -50.504 | BR67: =-31.031+26.145+2.929 -> -1.957 | BS67: =-100.532+2.972+26.145-BR67 -> -69.458
B68: Purchase of intangible assets | C68: -0.448564 | D68: -1.327 | E68: -6.862 | F68: -5.178 | G68: -2.728 | H68: -1.389 | I68: -6.473 | J68: -11.081 | K68: -3.518 | L68: -5.08 | M68: -8.647 | N68: -11.318 | O68: -23.043 | P68: =SUM(AZ68:BC68) -> -59.58 | R68: -2.784 | S68: =-3.384-R68 -> -0.6 | T68: =-4.359-S68-R68 -> -0.975 | U68: =E68-SUM(R68:T68) -> -2.503 | V68: -1.483 | W68: =-1.67-V68 -> -0.187 | X68: =-2.157-V68-W68 -> -0.487 | Y68: =F68-SUM(V68:X68) -> -3.021 | Z68: -1.74 | AA68: =-2.099-Z68 -> -0.359 | AB68: =-2.17-Z68-AA68 -> -0.071 | AC68: =G68-SUM(Z68:AB68) -> -0.558 | AD68: -0.076 | AE68: =-0.116-AD68 -> -0.04 | AF68: =-0.536-AD68-AE68 -> -0.42 | AG68: =H68-SUM(AD68:AF68) -> -0.853 | AH68: -0.382 | AI68: =-0.585-AH68 -> -0.203 | AJ68: =-0.833-AH68-AI68 -> -0.248 | AK68: =I68-SUM(AH68:AJ68) -> -5.64 | AL68: =J68-SUM(AH68:AJ68) -> -10.248 | AM68: -0.719 | AN68: -1.318 | AO68: =-2.426-AM68 -> -1.707 | AP68: =-3.624-AN68 -> -2.306 | AQ68: =-2.754-AM68-AO68 -> -0.328 | AR68: =-3.576-AN68-AP68 -> 0.048 | AS68: =K68-SUM(AM68,AO68:AQ68) -> 1.542 | AT68: =L68-SUM(AN68,AP68,AR68) -> -1.504 | AU68: -4.004 | AV68: =-4.537-AU68 -> -0.533 | AW68: =-9.852-AV68-AU68 -> -5.315 | AX68: =M68-SUM(AU68,AV68,AW68) -> 1.205 | AY68: -0.264 | AZ68: =BL68-AY68 -> -4.325 | BA68: =BO68-AZ68-AY68 -> -7.723 | BB68: =O68-SUM(AY68,AZ68,BA68) -> -10.731 | BC68: -36.801 | BE68: -5.53 | BF68: =BK68-BE68 -> -0.597 | BG68: =BN68-BF68-BE68 -> -7.004 | BH68: =N68-BG68-BF68-BE68 -> 1.813 | BI68: -0.345 | BK68: -6.127 | BL68: -4.589 | BN68: -13.131 | BO68: -12.312 | BQ68: =-2.308-AA68-Z68 -> -0.209 | BR68: -0.12 | BS68: =-0.148-BR68 -> -0.028
B69: Disposals/ Acquistion, of subsidiaries, businesses | C69: -20.517153 | D69: 40.747 | E69: 40.747 | F69: 0 | G69: 0 | H69: -3736.314 | I69: 0 | J69: 0 | K69: 0 | L69: 0 | M69: 0 | N69: 0 | O69: 0 | P69: =SUM(AZ69:BC69) -> 0 | R69: 0 | S69: =40.746-R69 -> 40.746 | T69: =40.746-S69-R69 -> 0 | U69: =E69-SUM(R69:T69) -> 0.001 | V69: 0 | W69: 0 | X69: 0 | Y69: =F69-SUM(V69:X69) -> 0 | Z69: -943.351 | AA69: =0-105.796-Z69 -> 837.555 | AB69: =1667.334-AA69-Z69 -> 1773.13 | AC69: =G69-SUM(Z69:AB69) -> -1667.334 | AD69: -1192.808 | AE69: =-1199.589-AD69 -> -6.781 | AF69: =-3736.314+423.664-AE69-AD69 -> -2113.061 | AG69: =H69-SUM(AD69:AF69) -> -423.664 | AH69: -10.026 | AI69: =-18.637-AH69 -> -8.611 | AJ69: =0+1051.37-AI69-AH69 -> 1070.007 | AK69: =I69-SUM(AH69:AJ69) -> -1051.37 | AL69: =J69-SUM(AH69:AJ69) -> -1051.37 | AM69: 207.844 | AN69: -19.586 | AO69: =207.843-AM69 -> -0.001 | AP69: =436.749-11.001-AN69 -> 445.334 | AQ69: =0+203.68-AO69-AM69 -> -4.163 | AR69: =-9.577+475.705-AP69-AN69 -> 40.38 | AS69: =K69-SUM(AM69,AO69:AQ69) -> -649.014 | AT69: =L69-SUM(AN69,AP69,AR69) -> -466.128 | AU69: -11.326 | AV69: =-12.279-AU69 -> -0.953 | AW69: =-18.208-AU69-AV69 -> -5.929 | AX69: =M69-SUM(AU69,AV69,AW69) -> 18.208 | AY69: 0 | AZ69: =BL69-AY69 -> 0 | BA69: =BO69-AZ69-AY69 -> 0 | BB69: =O69-SUM(AY69,AZ69,BA69) -> 0 | BC69: 0 | BE69: 0 | BF69: =BK69-BE69 -> 0 | BG69: =BN69-BF69-BE69 -> 0 | BH69: =N69-BG69-BF69-BE69 -> 0 | BI69: 0 | BK69: 0 | BL69: 0 | BN69: 0 | BO69: 0 | BQ69: =1667.334-AA69-Z69 -> 1773.13 | BR69: -1192.808 | BS69: =-1199.589-BR69 -> -6.781
B70: Free cash flow | C70: =SUM(C66:C69) -> 227.03698 | D70: =SUM(D66:D69) -> 292.826 | E70: =SUM(E66:E69) -> -557.648 | F70: =SUM(F66:F69) -> 153.684 | G70: =SUM(G66:G69) -> -184.112 | H70: =SUM(H66:H69) -> -5422.324 | I70: =SUM(I66:I69) -> -996.715 | J70: =SUM(J66:J69) -> -4546.727 | ... P70: =SUM(P66:P69) -> -4299.269 | R70: =SUM(R66:R69) -> -200.759 | S70: =SUM(S66:S69) -> -327.167 | T70: =SUM(T66:T69) -> -148.494 | U70: =SUM(U66:U69) -> 118.772 | V70: =SUM(V66:V69) -> -136.968 | W70: =SUM(W66:W69) -> -43.762 | X70: =SUM(X66:X69) -> -29.295 | Y70: =SUM(Y66:Y69) -> 363.709 | ... BC70: =SUM(BC66:BC69) -> -8342.338 | BE70: =SUM(BE66:BE69) -> -3478.251 | BF70: =SUM(BF66:BF69) -> 1880.371 | BG70: =SUM(BG66:BG69) -> -3579.562 | BH70: =SUM(BH66:BH69) -> 1618.361 | BI70: =SUM(BI66:BI69) -> -10857.861 | BK70: =SUM(BK66:BK69) -> -1597.88 | BL70: =SUM(BL66:BL69) -> -9598.814 | BN70: =SUM(BN66:BN69) -> -5177.442 | BO70: =SUM(BO66:BO69) -> -9661.898 | BQ70: =SUM(BQ66:BQ69) -> 1758.317 | BR70: =SUM(BR66:BR69) -> -1506.831 | BS70: =SUM(BS66:BS69) -> -205.222
B71: Other Investing | C71: =802.828779+0.683686+76.906418+14.450374+7.679254 -> 902.54851 | D71: =5.417+0.916+125.519-47.469+7.948 -> 92.331 | E71: =-0.199+0.231+190.732+52.001+8.576 -> 251.341 | F71: =0.758+817.961+233.928+801.458-17.63-336.41+10.444+2.026 -> 1512.535 | G71: =-1441.584+0.064+491.169+11.919-40.837+174.989 -> -804.28 | H71: =1837.753+0.045+392.815+423.471-34.969+12.217 -> 2631.332 | I71: =-649.135+374.246+6845.914-44.999+11.062-15.897 -> 6521.191 | J71: =-1069.599+718.621-75.627+11888.145-0.008+21.592 -> 11483.124 | K71: =-800.523+1209.731-93.201+350.625-8.82+24.53 -> 682.342 | L71: =-1155.785+1746.595-134.562+506.228-12.734+35.416 -> 985.158 | M71: =6.898+2650.994+212.636-15.337+37.345 -> 2892.536 | N71: =9.029+3469.948+278.324-20.075+48.882 -> 3786.108 | O71: =194.2+4358.784-63.803-7.947+56.966 -> 4538.2 | P71: =SUM(AZ71:BC71) -> 4670.025 | R71: =-0.802+58.295+35.625+2.435 -> 95.553 | S71: =-64.609+0.102+84.037+52.115+4.738-R71 -> -19.17 | T71: =-68.193+0.102+151.225+59.483+6.702-R71-S71 -> 72.936 | U71: =E71-SUM(R71:T71) -> 102.022 | V71: =-0.059+52.757-4.557+2.563+2.404 -> 53.108 | W71: =-0.087+0.083+123.358+0.784+5.143+ 703.819-V71 -> 779.992 | X71: =-336.478+0.083+331.352+2.406+7.934-V71-W71 -> -827.803 | Y71: =F71-SUM(V71:X71) -> 1507.238 | Z71: =-0.077+31.291+2.478+3.009 -> 36.701 | AA71: =-0.129+0.064+61.565-3.76+0+5.975-Z71 -> 27.014 | AB71: =-1514.904+0.064+106.478-9.499+8.919-AA71-Z71 -> -1472.657 | AC71: =G71-SUM(Z71:AB71) -> 604.662 | AD71: =-4.196+75.145+0+3.334-17.002+0.045 -> 57.326 | AE71: =-93.627+0.045+167.486-9.902+6.547-AD71 -> 13.223 | AF71: =1818.442+0.045+352.973+6.448+9.252-AE71-AD71 -> 2116.611 | AG71: =H71-SUM(AD71:AF71) -> 444.172 | AH71: =-323.235+0+83.769+4.379+2.766 -> -232.321 | AI71: =-369.455+165.105-9.196+5.472-AH71 -> 24.247 | AJ71: =-666.465+0+275.96+0+8.251-AI71-AH71 -> -174.18 | AK71: =I71-SUM(AH71:AJ71) -> 6903.445 | AL71: =J71-SUM(AH71:AJ71) -> 11865.378 | AM71: =-168.002+227.418+94.597+4.646 -> 158.659 | AN71: =-283.076+392.406+186.587+402.81+8.039 -> 706.766 | AO71: =-635.763+413.199+7.627+9.286-AM71 -> -364.31 | AP71: =-1090.951+768.385+56.826+16.887-AN71 -> -955.619 | AQ71: =-652.511+0+669.402-2.521+14.044-AO71-AM71 -> 234.065 | AR71: =-974.754+1247.66+92.233+25.936-AP71-AN71 -> 639.928 | AS71: =K71-SUM(AM71,AO71:AQ71) -> 1609.547 | AT71: =L71-SUM(AN71,AP71,AR71) -> 594.083 | AU71: =-147.677+213.588+26.161+8.366 -> 100.438 | AV71: =98.473+606.569-30.982+17.258-AU71 -> 590.88 | AW71: =-202.359+1603.796+89.806+27.39-AU71-AV71 -> 827.315 | AX71: =M71-SUM(AU71,AV71,AW71) -> 1373.903 | AY71: =-201.654+941.737-26.995+13.093 -> 726.181 | AZ71: =BL71-AY71 -> 1433.148 | BA71: =BO71-AZ71-AY71 -> 1666.237 | BB71: =O71-SUM(AY71,AZ71,BA71) -> 712.634 | BC71: =143.39+734.813-35.282-2.504+17.589 -> 858.006 | BE71: =-203.948+294.973+36.129+11.555-15.642 -> 123.067 | BF71: =BK71-BE71 -> 793.967 | BG71: =BN71-BF71-BE71 -> 1082.943 | BH71: =N71-BG71-BF71-BE71 -> 1786.131 | BI71: =-263.9+1232.431-35.328+17.135 -> 950.338 | BK71: =(132986+819163-41841-16581+23307)/1000 -> 917.034 | BL71: =(-225506+2385725-20787-7014+26911)/1000 -> 2159.329 | BN71: =(-269732+2137764+119706-24270+36509)/1000 -> 1999.977 | BO71: =(-208625+3993797+5851-7615+42158)/1000 -> 3825.566 | BQ71: =-1679.474+0.064+157.64-9.721+6.598-AA71-Z71 -> -1588.608 | BR71: =6.71+0.045+102.161-17.245+3.054 -> 94.725 | BS71: =-111.172+0.045+262.786-10.636+6.477-BR71 -> 52.775
B72: Equity Issuance | C72: 0 | D72: 0 | E72: 0 | F72: 0 | G72: 0 | H72: 0 | I72: 0 | J72: 0 | K72: 0 | L72: 0 | M72: 0 | N72: 0 | O72: 0 | P72: =SUM(AZ72:BC72) -> 0 | R72: 0 | S72: 0 | T72: 0 | U72: =E72-SUM(R72:T72) -> 0 | V72: 0 | W72: 0 | X72: 0 | Y72: =F72-SUM(V72:X72) -> 0 | Z72: 0 | AA72: =0-Z72 -> 0 | AB72: =0-AA72-Z72 -> 0 | AC72: =G72-SUM(Z72:AB72) -> 0 | AD72: 0 | AE72: =0-AD72 -> 0 | AF72: =0-AE72-AD72 -> 0 | AG72: =H72-SUM(AD72:AF72) -> 0 | AH72: 0 | AI72: 0 | AJ72: =-27.771-AI72-AH72 -> -27.771 | AK72: =I72-SUM(AH72:AJ72) -> 27.771 | AL72: =J72-SUM(AH72:AJ72) -> 27.771 | AM72: 0 | AN72: 0 | AO72: 0 | AP72: 0 | AQ72: =0-AO72-AM72 -> 0 | AR72: =0-AP72-AN72 -> 0 | AS72: =K72-SUM(AM72,AO72:AQ72) -> 0 | AT72: =L72-SUM(AN72,AP72,AR72) -> 0 | AU72: 0 | AV72: =0-AU72 -> 0 | AW72: =0-AU72-AV72 -> 0 | AX72: =M72-SUM(AU72,AV72,AW72) -> 0 | AY72: 0 | AZ72: =BL72-AY72 -> 0 | BA72: =BO72-AZ72-AY72 -> 0 | BB72: =O72-SUM(AY72,AZ72,BA72) -> 0 | BC72: 0 | BE72: 0 | BF72: =BK72-BE72 -> 0 | BG72: =BN72-BF72-BE72 -> 0 | BH72: =N72-BG72-BF72-BE72 -> 0 | BI72: 0 | BK72: 0 | BL72: 0 | BN72: 0 | BO72: 0 | BQ72: =0-AA72-Z72 -> 0 | BR72: 0 | BS72: 0
B73: Dividends | C73: -114.82533 | D73: -71.917 | E73: -101.877 | F73: 0 | G73: -6.686 | H73: -373.341 | I73: -120.632 | J73: -198.768 | K73: -199.811 | L73: -288.485 | M73: -364.771 | N73: -477.457 | O73: =-3835.15 -> -3835.15 | P73: =SUM(AZ73:BC73) -> -3835.15 | R73: 0 | S73: 0 | T73: 0 | U73: =E73-SUM(R73:T73) -> -101.877 | V73: 0 | W73: 0 | X73: 0 | Y73: =F73-SUM(V73:X73) -> 0 | Z73: 0 | AA73: =0-Z73 -> 0 | AB73: =0-AA73-Z73 -> 0 | AC73: =G73-SUM(Z73:AB73) -> -6.686 | AD73: -66.025 | AE73: =-349.292-AD73 -> -283.267 | AF73: =-349.291-AE73-AD73 -> 0.001 | AG73: =H73-SUM(AD73:AF73) -> -24.05 | AH73: 0 | AI73: =0-AH73 -> 0 | AJ73: =-119.59-AI73-AH73 -> -119.59 | AK73: =I73-SUM(AH73:AJ73) -> -1.042 | AL73: =J73-SUM(AH73:AJ73) -> -79.178 | AM73: 0 | AN73: 0 | AO73: =-199.811-AM73 -> -199.811 | AP73: =-342.871-AN73 -> -342.871 | AQ73: =-199.811-AO73-AM73 -> 0 | AR73: =-298.488-AP73-AN73 -> 44.383 | AS73: =K73-SUM(AM73,AO73:AQ73) -> 342.871 | AT73: =L73-SUM(AN73,AP73,AR73) -> 10.003 | AU73: 0 | AV73: =-341.779-AU73 -> -341.779 | AW73: =-341.779-AU73-AV73 -> 0 | AX73: =M73-SUM(AU73,AV73,AW73) -> -22.992 | AY73: 0 | AZ73: =BL73-AY73 -> -3436.324 | BA73: =BO73-AZ73-AY73 -> -243.925 | BB73: =O73-SUM(AY73,AZ73,BA73) -> -154.901 | BC73: 0 | BE73: 0 | BF73: =BK73-BE73 -> -461.568 | BG73: =BN73-BF73-BE73 -> 5.997 | BH73: =N73-BG73-BF73-BE73 -> -21.886 | BI73: 0 | BK73: -461.568 | BL73: -3436.324 | BN73: -455.571 | BO73: -3680.249 | BQ73: =0-AA73-Z73 -> 0 | BR73: -66.025 | BS73: =-349.292-BR73 -> -283.267
B74: Net Change in debt | C74: =952.561529-1219.19359 -> -266.63206 | D74: =3599.63-2783.124 -> 816.506 | E74: =389.808-861.537 -> -471.729 | F74: =317.922-345.444 -> -27.522 | G74: =8446.445-6634.184 -> 1812.261 | H74: =1588.167-1705.798 -> -117.631 | I74: =2022.496-3047.8 -> -1025.304 | J74: =3945.711-5945.987 -> -2000.276 | K74: =1168.555-8067.427 -> -6898.872 | L74: =1687.145-11647.652 -> -9960.507 | M74: =27721.943-16717.555 -> 11004.388 | N74: =36285.897-21881.997 -> 14403.9 | O74: =28925.964-33560.771 -> -4634.807 | P74: =SUM(AZ74:BC74) -> -8320.894 | R74: =+-147.002+225.101 -> 78.099 | S74: =246.58-645.388-R74 -> -476.907 | T74: =-729.707+309.462-R74-S74 -> -21.437 | U74: =E74-SUM(R74:T74) -> -51.484 | V74: =-21.104 -> -21.104 | W74: =206.719-57.102-V74 -> 170.721 | X74: =320.342-78.258-V74-W74 -> 92.467 | Y74: =F74-SUM(V74:X74) -> -269.606 | Z74: =17.215-73.016 -> -55.801 | AA74: =3123.611-2733.053-Z74 -> 446.359 | AB74: =3191.759-2827.304-AA74-Z74 -> -26.103 | AC74: =G74-SUM(Z74:AB74) -> 1447.806 | AD74: =1.073-26.169 -> -25.096 | AE74: =2.279-174.017-AD74 -> -146.642 | AF74: =1183.493-937.099-AE74-AD74 -> 418.132 | AG74: =H74-SUM(AD74:AF74) -> -364.025 | AH74: =62.847-291.963 -> -229.116 | AI74: =1639.011-1469.462-AH74 -> 398.665 | AJ74: =1678.74-1747.701-AI74-AH74 -> -238.51 | AK74: =I74-SUM(AH74:AJ74) -> -956.343 | AL74: =J74-SUM(AH74:AJ74) -> -1931.315 | AM74: =757.967-514.048 -> 243.919 | AN74: =1163.274-886.655 -> 276.619 | AO74: =93.946-3927.859-AM74 -> -4077.832 | AP74: =1605.825-8480.726-AN74 -> -7151.52 | AQ74: =93.946-5592.763-AO74-AM74 -> -1664.904 | AR74: =1778.104-11531.601-AP74-AN74 -> -2878.596 | AS74: =K74-SUM(AM74,AO74:AQ74) -> 5751.465 | AT74: =L74-SUM(AN74,AP74,AR74) -> -207.01 | AU74: =1385.227-970.447 -> 414.78 | AV74: =7564.245-3501.194-AU74 -> 3648.271 | AW74: =26845.727-15740.082-AU74-AV74 -> 7042.594 | AX74: =M74-SUM(AU74,AV74,AW74) -> -101.257 | AY74: =5918.984-2733.493 -> 3185.491 | AZ74: =BL74-AY74 -> 4854.68 | BA74: =BO74-AZ74-AY74 -> 2.477 | BB74: =O74-SUM(AY74,AZ74,BA74) -> -12677.455 | BC74: =8605.397-9105.993 -> -500.596 | BE74: =1913.05-1340.224 -> 572.826 | BF74: =BK74-BE74 -> 4914.27 | BG74: =BN74-BF74-BE74 -> 9316.063 | BH74: =N74-BG74-BF74-BE74 -> -399.259 | BI74: =7746.049-3577.264 -> 4168.785 | BK74: =10215.411-4728.315 -> 5487.096 | BL74: =11929.882-3889.711 -> 8040.171 | BN74: =(35783746-20980587)/1000 -> 14803.159 | BO74: =(13261465-5218817)/1000 -> 8042.648 | BQ74: =3549.816-3357.035-AA74-Z74 -> -197.777 | BR74: =736.887-112.134 -> 624.753 | BS74: =1204.337-668.154-BR74 -> -88.57
B75: Other financing activities | C75: =-0.357129-2.502818-78.764095 -> -81.624042 | D75: =-0.072+4.81-6.534-637.265 -> -639.061 | E75: =1.901-43.664-239.632 -> -281.395 | F75: =-23.795-1.064 -> -24.859 | G75: =-33.849+0.02+500.271 -> 466.442 | H75: =47.165-54.699-0.12 -> -7.654 | I75: =2.648-87.282 -> -84.634 | J75: =4.576-185.979 -> -181.403 | K75: =695.576-287.904 -> 407.672 | L75: =1004.264-415.672 -> 588.592 | M75: -630.194 | N75: -824.876 | O75: =-3032.387-1111.953 -> -4144.34 | P75: =SUM(AZ75:BC75) -> -3611.254 | R75: =-4.194+6.929+1.901 -> 4.636 | S75: =-7.279+1.901-238.511-R75 -> -248.525 | T75: =1.901-19.49-239.907-S75-R75 -> -13.607 | U75: =E75-SUM(R75:T75) -> -23.899 | V75: =-15.929+1.522 -> -14.407 | W75: =-13.602-0.821-V75 -> -0.016 | X75: =-20.184+0.017-V75-W75 -> -5.744 | Y75: =F75-SUM(V75:X75) -> -4.692 | Z75: =-6.044+2.987 -> -3.057 | AA75: =500.271-18.011+1.41-Z75 -> 486.727 | AB75: =500.271-25.15+0.586-AA75-Z75 -> -7.963 | AC75: =G75-SUM(Z75:AB75) -> -9.265 | AD75: =-6.865-0.094 -> -6.959 | AE75: =0-13.448-0.133-AD75 -> -6.622 | AF75: =47.165-29.96+0.437-AE75-AD75 -> 31.223 | AG75: =H75-SUM(AD75:AF75) -> -25.296 | AH75: =-18.173+0 -> -18.173 | AI75: =-31.223-AH75 -> -13.05 | AJ75: =0-59.363+0-AI75-AH75 -> -28.14 | AK75: =I75-SUM(AH75:AJ75) -> -25.271 | AL75: =J75-SUM(AH75:AJ75) -> -122.04 | AM75: -41.98 | AN75: -44.028 | AO75: =-95.341+454.161-AM75 -> 400.8 | AP75: =-171.168+810.23-AN75 -> 683.09 | AQ75: =540.991-160.26+0-AO75-AM75 -> 21.911 | AR75: =840.205-290.384-AP75-AN75 -> -89.241 | AS75: =K75-SUM(AM75,AO75:AQ75) -> -656.149 | AT75: =L75-SUM(AN75,AP75,AR75) -> 38.771 | AU75: -75.434 | AV75: =-276.097-AU75 -> -200.663 | AW75: =-277.049-AU75-AV75 -> -0.952 | AX75: =M75-SUM(AU75,AV75,AW75) -> -353.145 | AY75: =-1136.431-337.525 -> -1473.956 | AZ75: =BL75-AY75 -> -428.959 | BA75: =BO75-AZ75-AY75 -> -849.226 | BB75: =O75-SUM(AY75,AZ75,BA75) -> -1392.199 | BC75: =-543.784-397.086 -> -940.87 | BE75: =-104.177 -> -104.177 | BF75: =BK75-BE75 -> -268.688 | BG75: =BN75-BF75-BE75 -> 3.575 | BH75: =N75-BG75-BF75-BE75 -> -455.586 | BI75: =-1487.223-441.712 -> -1928.935 | BK75: =-372.865 -> -372.865 | BL75: =-1384.824-518.091 -> -1902.915 | BN75: -369.29 | BO75: =(-2029006-723135)/1000 -> -2752.141 | BQ75: =500.271-29.543+0.566-AA75-Z75 -> -12.376 | BR75: =-9.095-0.12 -> -9.215 | BS75: =-30.559-0.12-BR75 -> -21.464
B76: Cash flow after financing activities | C76: =SUM(C70:C75) -> 666.50406 | D76: =SUM(D70:D75) -> 490.685 | E76: =SUM(E70:E75) -> -1161.308 | F76: =SUM(F70:F75) -> 1613.838 | G76: =SUM(G70:G75) -> 1283.625 | H76: =SUM(H70:H75) -> -3289.618 | I76: =SUM(I70:I75) -> 4293.906 | J76: =SUM(J70:J75) -> 4555.95 | ... P76: =SUM(P70:P75) -> -15396.542 | R76: =SUM(R70:R75) -> -22.471 | S76: =SUM(S70:S75) -> -1071.769 | T76: =SUM(T70:T75) -> -110.602 | U76: =SUM(U70:U75) -> 43.534 | V76: =SUM(V70:V75) -> -119.371 | W76: =SUM(W70:W75) -> 906.935 | X76: =SUM(X70:X75) -> -770.375 | Y76: =SUM(Y70:Y75) -> 1596.649 | ... BC76: =SUM(BC70:BC75) -> -8925.798 | BE76: =SUM(BE70:BE75) -> -2886.535 | BF76: =SUM(BF70:BF75) -> 6858.352 | BG76: =SUM(BG70:BG75) -> 6829.016 | BH76: =SUM(BH70:BH75) -> 2527.761 | BI76: =SUM(BI70:BI75) -> -7667.673 | BK76: =SUM(BK70:BK75) -> 3971.817 | BL76: =SUM(BL70:BL75) -> -4738.553 | BN76: =SUM(BN70:BN75) -> 10800.833 | BO76: =SUM(BO70:BO75) -> -4226.074 | BQ76: =SUM(BQ70:BQ75) -> -40.444 | BR76: =SUM(BR70:BR75) -> -862.593 | BS76: =SUM(BS70:BS75) -> -545.748
B77: Inflation effect on cash and cash equivalents | C77: 0 | D77: 0 | E77: 0 | F77: 0 | G77: 0 | H77: 0 | I77: 0 | J77: -3182.079 | K77: -5994.627 | L77: -8654.969 | M77: -5173.332 | N77: -6771.495 | O77: -8127.198 | P77: =SUM(AZ77:BC77) -> -7821.581 | AH77: 0 | AI77: 0 | AJ77: 0 | AK77: =I77-SUM(AH77:AJ77) -> 0 | AL77: =J77-SUM(AH77:AJ77) -> -3182.079 | AM77: 0 | AN77: -1952.614 | AO77: 0 | AP77: =-3140.319-AN77 -> -1187.705 | AQ77: 0 | AR77: =-6892.636-AP77-AN77 -> -3752.317 | AS77: =K77-SUM(AM77,AO77:AQ77) -> -4806.922 | AT77: =L77-SUM(AN77,AP77,AR77) -> -1762.333 | AU77: -1756 | AV77: =-2883.366-AU77 -> -1127.366 | AW77: =-4180.32-AV77-AU77 -> -1296.954 | AX77: =M77-SUM(AU77,AV77,AW77) -> -993.012 | AY77: -2647.327 | AZ77: =BL77-AY77 -> -1739.275 | BA77: =BO77-AZ77-AY77 -> -2303.451 | BB77: =O77-SUM(AY77,AZ77,BA77) -> -1437.145 | BC77: -2341.71 | BE77: -2425.103 | BF77: =BK77-BE77 -> -1468.844 | BG77: =BN77-BF77-BE77 -> -1678.171 | BH77: =N77-BG77-BF77-BE77 -> -1199.377 | BI77: -3464.501 | BK77: -3893.947 | BL77: -4386.602 | BN77: -5572.118 | BO77: -6690.053
B78: Balancing figure | C78: =666.993424-C76 -> 0.489366 | D78: =454.283-D76 -> -36.402 | E78: =-1088.666-E76 -> 72.642 | F78: =1707.987-F76 -> 94.149 | G78: =1448.005-G76 -> 164.38 | H78: =-2771.86-H76 -> 517.758 | I78: =5298.289-I76 -> 1004.383 | J78: =7116.221-J76-J77-J79 -> 3570.238 | K78: =-3592.238-K76-K77-K79 -> 2387.743 | L78: =-5186.429-L76-L77-L79 -> 3447.394 | M78: =9477.59-M76-M77-M79 -> 1825.668 | N78: =12405.438-N76-N77-N79 -> 2389.657 | O78: =-11116.659-O76-O77-O79 -> 3354.94 | P78: =SUM(AZ78:BC78) -> 4126.868 | R78: =60.879-R76 -> 83.35 | S78: =-967.008-S76-R76-R78 -> 43.882 | T78: =-967.358-T76-S76-R76-R78-S78 -> 110.252 | U78: =E78-SUM(R78:T78) -> -164.842 | V78: =15.574-V76 -> 134.945 | W78: =941.995-W76-V76-V78 -> 19.486 | X78: =162.757-X76-W76-V76-V78-W78 -> -8.863 | Y78: =F78-SUM(V78:X78) -> -51.419 | Z78: =-948.983-Z76 -> 188.998 | AA78: =724.622-AA76-Z76-Z78 -> -34.896 | AB78: =811.624-AB76-AA76-Z76-Z78-AA78 -> 107.951 | AC78: =G78-SUM(Z78:AB78) -> -97.673 | AD78: =-798.884-AD76 -> 194.519 | AE78: =-1557.391-AE76-AD76-AD78 -> -23.945 | AF78: =-1486.759-AF76-AE76-AD76-AD78-AE78 -> -39.264 | AG78: =H78-SUM(AD78:AF78) -> 386.448 | AH78: =-260.228-AH76 -> 489.155 | AI78: =-307.978-AI76-AH76-AH78 -> 199.637 | AJ78: =-166.908-AJ76-AI76-AH76-AH78-AI78 -> 553.996 | AK78: =I78-SUM(AH78:AJ78) -> -238.405 | AL78: =J78-SUM(AH78:AJ78) -> 2327.45 | AM78: =446.598-AM76 -> 717.659 | AN78: =-930.423-AN76-AN77-AN79 -> 1482.441 | AO78: =-3327.869-AO76-AM76-AM78 -> 776.073 | AP78: =-3992.848-AP76-AP77-AP79 -> 1282.184 | AQ78: =-2914.008-AQ76-AO76-AM76-AM78-AO78 -> 0.895 | AR78: =-6253.094-AR76-AR77-AR79 -> -4060.909 | AS78: =K78-SUM(AM78,AO78:AQ78) -> -389.068 | AT78: =L78-SUM(AN78,AP78,AR78) -> 4743.678 | AU78: =-750.729-AU76-AU77-AU79 -> 1262.671 | AV78: =2184.257-AV76-AV77-AV79 -> -938.075 | AW78: =7491.789-AW76-AW77-AW79 -> 2504.813 | AX78: =M78-SUM(AU78,AV78,AW78) -> -1003.741 | AY78: =-5018.543-AY76-AY77-AY79 -> 1591.374 | AZ78: =-3303.358-AZ76-AZ77-AZ79-AY76-AY77-AY79-AY78 -> 563.592 | BA78: =BO78-AZ78-AY78 -> 261.55 | BB78: =O78-SUM(AY78,AZ78,BA78) -> 938.424 | BC78: =-8499.309-BC76-BC77-BC79 -> 2363.302 | BE78: =-1036.785-BE76-BE77-BE79 -> 1743.798 | BF78: =2949.81-BF76-BF77-BF79-BE76-BE77-BE79-BE78 -> -291.584 | BG78: =BN78-BF78-BE78 -> 408.414 | BH78: =N78-BG78-BF78-BE78 -> 529.029 | BI78: =-6567.66-BI76-BI77-BI79 -> 2082.6 | BK78: =2949.81-BK76-BK77-BK79 -> 1452.214 | BL78: =-3303.358-BL76-BL77-BL79 -> 2154.966 | BN78: =9986.106-BN76-BN77-BN79 -> 1860.628 | BO78: =-3427.941-BO76-BO77-BO79 -> 2416.516 | BQ78: =794.036-BQ76-AA76-Z76-Z78-AA78 -> 109.858 | BR78: =-786.442-BR76 -> 76.151 | BS78: =-1287.454-BS76-BR76-BR78 -> 44.736
B79: FX | C79: 245.57457 | D79: 447.243 | E79: 1277.562 | F79: -679.85 | G79: 348.716 | H79: 1941.174 | I79: 951.711 | J79: 2172.112 | K79: 5841.889 | L79: 8434.448 | M79: 2642.387 | N79: 3458.682 | O79: 5985.438 | P79: =SUM(AZ79:BC79) -> 4493.83 | R79: 247.21 | S79: =866.427-R79 -> 619.217 | T79: =1811.772-S79-R79 -> 945.345 | U79: =E79-SUM(R79:T79) -> -534.21 | V79: 90.549 | W79: =90.985-V79 -> 0.436 | X79: =274.384-V79-W79 -> 183.399 | Y79: =F79-SUM(V79:X79) -> -954.234 | Z79: 140.739 | AA79: =203.779-Z79 -> 63.04 | AB79: =693.145-Z79-AA79 -> 489.366 | AC79: =G79-SUM(Z79:AB79) -> -344.429 | AD79: 342.198 | AE79: =495.207-AD79 -> 153.009 | AF79: =513.848-AD79-AE79 -> 18.641 | AG79: =H79-SUM(AD79:AF79) -> 1427.326 | AH79: 240.507 | AI79: =627.196-AH79 -> 386.689 | AJ79: =927.485-AH79-AI79 -> 300.289 | AK79: =I79-SUM(AH79:AJ79) -> 24.226 | AL79: =J79-SUM(AH79:AJ79) -> 1244.627 | AM79: 160.06 | AN79: 274.107 | AO79: =2831.049-AM79 -> 2670.989 | AP79: =4999.541-AN79 -> 4725.434 | AQ79: =3342.124-AM79-AO79 -> 511.075 | AR79: =6283.677-AN79-AP79 -> 1284.136 | AS79: =K79-SUM(AM79,AO79:AQ79) -> -2225.669 | AT79: =L79-SUM(AN79,AP79,AR79) -> 2150.771 | AU79: 1832.718 | AV79: =1051.27-AU79 -> -781.448 | AW79: =2173.213-AV79-AU79 -> 1121.943 | AX79: =M79-SUM(AU79,AV79,AW79) -> 469.174 | AY79: 1896.505 | AZ79: =BL79-AY79 -> 1770.326 | BA79: =BO79-AZ79-AY79 -> 1404.839 | BB79: =O79-SUM(AY79,AZ79,BA79) -> 913.768 | BC79: 404.897 | BE79: 2531.055 | BF79: =BK79-BE79 -> -1111.329 | BG79: =BN79-BF79-BE79 -> 1477.037 | BH79: =N79-BG79-BF79-BE79 -> 561.919 | BI79: 2481.914 | BK79: 1419.726 | BL79: 3666.831 | BN79: 2896.763 | BO79: 5071.67 | BQ79: =698.916-AA79-Z79 -> 495.137 | BR79: 345.477 | BS79: =501.871-BR79 -> 156.394
B80: Net change in cash | C80: =SUM(C76:C79) -> 912.56799 | D80: =SUM(D76:D79) -> 901.526 | E80: =SUM(E76:E79) -> 188.896 | F80: =SUM(F76:F79) -> 1028.137 | G80: =SUM(G76:G79) -> 1796.721 | H80: =SUM(H76:H79) -> -830.686 | I80: =SUM(I76:I79) -> 6250 | J80: =SUM(J76:J79) -> 7116.221 | ... P80: =SUM(P76:P79) -> -14597.425 | R80: =SUM(R76:R79) -> 308.089 | S80: =SUM(S76:S79) -> -408.67 | T80: =SUM(T76:T79) -> 944.995 | U80: =SUM(U76:U79) -> -655.518 | V80: =SUM(V76:V79) -> 106.123 | W80: =SUM(W76:W79) -> 926.857 | X80: =SUM(X76:X79) -> -595.839 | Y80: =SUM(Y76:Y79) -> 590.996 | ... AB80: =SUM(AB76:AB79) -> 576.368 | AC80: =G80-SUM(Z80:AB80) -> 291.952 | AD80: =SUM(AD76:AD79) -> -456.686 | AE80: =SUM(AE76:AE79) -> -605.498 | AF80: =SUM(AF76:AF79) -> 89.273 | AG80: =H80-SUM(AD80:AF80) -> 142.225 | AH80: =SUM(AH76:AH79) -> -19.721 | AI80: =SUM(AI76:AI79) -> 338.939 | AJ80: =SUM(AJ76:AJ79) -> 441.359 | AK80: =I80-SUM(AH80:AJ80) -> 5489.423 | AL80: =J80-SUM(AH80:AJ80) -> 6355.644 | AM80: =SUM(AM76:AM79) -> 606.658 | AN80: =SUM(AN76:AN79) -> -930.423 | AO80: =SUM(AO76:AO79) -> -1103.478 | AP80: =SUM(AP76:AP79) -> -3992.848 | AQ80: =SUM(AQ76:AQ79) -> 924.936 | AR80: =SUM(AR76:AR79) -> -6253.094 | AS80: =K80-SUM(AM80,AO80:AQ80) -> -27.506 | AT80: =SUM(AT76:AT79) -> 5989.936 | AU80: =SUM(AU76:AU79) -> -750.729 | AV80: =SUM(AV76:AV79) -> 2184.257 | AW80: =SUM(AW76:AW79) -> 7491.789 | AX80: =SUM(AX76:AX79) -> 552.273 | AY80: =SUM(AY76:AY79) -> -5018.543 | AZ80: =SUM(AZ76:AZ79) -> 1715.185 | BA80: =SUM(BA76:BA79) -> -124.583 | ... BC80: =SUM(BC76:BC79) -> -8499.309 | BE80: =SUM(BE76:BE79) -> -1036.785 | BF80: =SUM(BF76:BF79) -> 3986.595 | BG80: =SUM(BG76:BG79) -> 7036.296 | BH80: =SUM(BH76:BH79) -> 2419.332 | BI80: =SUM(BI76:BI79) -> -6567.66 | BK80: =SUM(BK76:BK79) -> 2949.81 | BL80: =SUM(BL76:BL79) -> -3303.358 | BN80: =SUM(BN76:BN79) -> 9986.106 | BO80: =SUM(BO76:BO79) -> -3427.941 | BQ80: =SUM(BQ76:BQ79) -> 564.551 | BR80: =SUM(BR76:BR79) -> -440.965 | BS80: =SUM(BS76:BS79) -> -344.618
B81: Cash and cash equivalents | C81: =1360.002831+C80 -> 2272.5708 | D81: =2288.339+D80 -> 3189.865 | E81: =D81+E80 -> 3378.761 | F81: =999.462+F80 -> 2027.599 | G81: =F81+G80 -> 3824.32 | H81: =3835.52+H80 -> 3004.834 | I81: =H81+I80 -> 9254.834 | J81: =8133.239+J80 -> 15249.46 | K81: =J81+K80 -> 11657.222 | L81: =K81+L80+(22016.983-11657.222) -> 16830.554 | M81: =L81+M80 -> 26308.144 | N81: =22029.904+N80 -> 34435.342 | O81: =N81+O80 -> 23318.683 | P81: =BC81 -> 17161.084 | R81: =3189.865+R80 -> 3497.954 | S81: =R81+S80 -> 3089.284 | T81: =S81+T80 -> 4034.279 | U81: =T81+U80 -> 3378.761 | V81: =999.462+V80 -> 1105.585 | W81: =V81+W80 -> 2032.442 | X81: =W81+X80 -> 1436.603 | Y81: =X81+Y80 -> 2027.599 | Z81: =Y81+Z80 -> 1219.355 | AA81: =+Z81+AA80 -> 2956 | AB81: =+AA81+AB80 -> 3532.368 | AC81: =+AB81+AC80 -> 3824.32 | AD81: =AC81+AD80 -> 3367.634 | AE81: =+AD81+AE80 -> 2762.136 | AF81: =+AE81+AF80 -> 2851.409 | AG81: =+AF81+AG80 -> 2993.634 | AH81: =3004.834+AH80 -> 2985.113 | AI81: =AH81+AI80 -> 3324.052 | AJ81: =+AI81+AJ80 -> 3765.411 | AK81: =+AJ81+AK80 -> 9254.834 | AL81: =+AK81+AL80 -> 15610.478 | AM81: =9254.834+AM80 -> 9861.492 | AN81: =17546.581+AN80 -> 16616.158 | AO81: =AM81+AO80 -> 8758.014 | AP81: =19021.351+AP80 -> 15028.503 | AQ81: =+AO81+AQ80 -> 9682.95 | AR81: =20717.968+AR80 -> 14464.874 | AS81: =+AQ81+AS80+(15249.46-9254.834) -> 15650.07 | AT81: =L81 -> 16830.554 | AU81: =13413.222+AU80 -> 12662.493 | AV81: =14540.588+AV80 -> 16724.845 | AW81: =15837.542+AW80 -> 23329.331 | AX81: =AW81+AX80+2426.54 -> 26308.144 | AY81: =28955.471+AY80 -> 23936.928 | AZ81: =30694.746+AZ80+AY80 -> 27391.388 | BA81: =32998.197+BA80+AZ80+AY80 -> 29570.256 | BB81: =34435.342+BB80+BA80+AZ80+AY80 -> 23318.683 | BC81: =25660.393+BC80 -> 17161.084 | BE81: =18524.173+BE80 -> 17487.388 | BF81: =19636.869+BF80+BE80 -> 22586.679 | BG81: =21110.495+BG80+BF80+BE80 -> 31096.601 | BH81: =22029.904+BH80+BG80+BF80+BE80 -> 34435.342 | BI81: =37893.409+BI80 -> 31325.749 | BK81: =19636.869+BK80 -> 22586.679 | BL81: =30694.746+BL80 -> 27391.388 | BN81: =21110.495+BN80 -> 31096.601 | BO81: =32998.197+BO80 -> 29570.256 | BQ81: =+AA81+BQ80 -> 3520.551 | BR81: =3835.52+BR80 -> 3394.555 | BS81: =+AD81+BS80 -> 3023.016
AU82: =AT81-L81 -> 0
B83: check1 | E83: =3.378-(E66+E78-E65) -> -1.563194e-13 | F83: =795.579-(F66+F78-F65) -> -0.104 | G83: =536.204-(G66+G78-G65) -> 0 | H83: =27.339-(H66+H78-H65) -> 2.8421709e-13 | I83: =2699.276-(I66+I78-I65) -> 0 | J83: =4021.785-(J66+J78-J65) -> 0 | K83: =7351.044-(K66+K78-K65) -> 0 | L83: =10613.347-(L66+L78-L65) -> 0 | M83: =5788.055-(M66+M78-M65) -> 0 | N83: =7576.119-(N66+N78-N65) -> 0 | O83: =5903.389-(O66+O78-O65) -> 0 | V83: =51.656-(V66+V78-V65) -> 0 | W83: =211.473-51.656-(W66+W78-W65) -> 0 | X83: =268.46-211.473-(X66+X78-X65) -> -7.1054274e-14 | Z83: =77.499-(Z66+Z78-Z65) -> 0 | AA83: =117.066-77.499-(AA66+AA78-AA65) -> 2.4158453e-13 | AB83: =-11.298-117.066-(AB66+AB78-AB65) -> 3.126388e-13 | AD83: =467.612-(AD66+AD78-AD65) -> 0 | AE83: =502.746-467.612-(AE66+AE78-AE65) -> 1.1368684e-13 | AF83: =309.308-502.746-(AF66+AF78-AF65) -> 0 | AH83: =360.405-(AH66+AH78-AH65) -> 0 | AI83: =739.351-360.405-(AI66+AI78-AI65) -> 0 | AJ83: =562.839-739.351-(AJ66+AJ78-AJ65) -> 0 | AM83: =87.024-(AM66+AM78-AM65) -> 0 | AN83: =188.699-(AN66+AN78-AN65) -> 0 | AO83: =1647.276-87.024-(AO66+AO78-AO65) -> 0 | AP83: =2875.651-188.699-(AP66+AP78-AP65) -> 930.423 | AQ83: =3772.017-1647.276-(AQ66+AQ78-AQ65) -> 0 | AR83: =5858.853-2875.651-(AR66+AR78-AR65) -> 3992.848 | AU83: =-913.414-(AU66+AU78-AU65) -> 0 | AV83: =2224.059+913.414-(AV66+AV78-AV65) -> 750.729 | AW83: =1249.997-2224.059-(AW66+AW78-AW65) -> -2184.257 | AY83: =-5741.318-(AY66+AY78-AY65) -> 0 | AZ83: =-4480.642+5741.318-(AZ66+AZ78-AZ65) -> 2.0463631e-12 | BA83: =-2365.851+4480.642-(BA66+BA78-BA65) -> 0 | BC83: =-4531.892-(BC66+BC78-BC65) -> 0 | BE83: =-1261.46-(BE66+BE78-BE65) -> 0 | BF83: =3003.562+1261.46-(BF66+BF78-BF65) -> 0 | BG83: =1666.173-(BG66+BG78-BG65)-3003.562 -> 0 | BH83: =7576.119-(BH66+BH78-BH65)-1666.173 -> -2.0463631e-12 | BI83: =-7513.538-(BI66+BI78-BI65) -> 0 | BK83: =3003.562-(BK66+BK78-BK65) -> 0 | BL83: =-4480.642-(BL66+BL78-BL65) -> 0 | BN83: =1666.173-(BN66+BN78-BN65) -> 0 | BO83: =-2365.851-(BO66+BO78-BO65) -> 0 | BQ83: =292.658-117.066-(BQ66+BQ78-BQ65) -> 0 | BR83: =-197.696-(BR66+BR78-BR65) -> 0 | BS83: =71.257+197.696-(BS66+BS78-BS65) -> 0
B84: check2 | C84: =C81-C127 -> -16.523174 | D84: =D81-D127 -> -0.619 | E84: =E81-E127 -> -0.702 | F84: =F81-F125 -> 0 | G84: =G81-G125 -> 0 | H84: =H81-H125 -> 0 | I84: =I81-I125 -> 0 | J84: =J81-J125 -> 0 | K84: =K81-K125 -> 0 | L84: =L81-L125 -> 0 | M84: =M81-M125 -> 0 | ... P84: =P81-P125 -> 0 | R84: =R81-R125 -> 15.021 | S84: =S81-S125 -> -1.883 | T84: =T81-T125 -> -1.916 | U84: =U81-U125 -> 0 | V84: =V81-V125 -> -2724.421 | W84: =W81-W125 -> -2085.833 | X84: =X81-X125 -> -2379.299 | Y84: =Y81-Y125 -> 0 | ... AE84: =AE81-AE125 -> 0 | AF84: =AF81-AF125+(3835.52-AC81) -> 0 | AG84: =AG81-AG125 -> -11.2 | AH84: =AH81-AH125 -> 0 | AI84: =AI81-AI125 -> 0 | AJ84: =AJ81-AJ125+(3004.834-AG81-11.2) -> 2.7355895e-13 | AK84: =AK81-AK125 -> 0 | AL84: =AL81-AL125 -> 361.018 | AM84: =AM81-AM125 -> 0 | AN84: =AN81-AN125 -> 0 | AO84: =AO81-AO125 -> 0 | AQ84: =AQ81-AQ125 -> 0 | AS84: =AS81-AS125 -> 3992.848 | AU84: =AU81-AU125 -> 0 | AV84: =AV81-AV125 -> 0 | AW84: =AW81-AW125 -> 0 | AX84: =AX81-AX125 -> 0 | AY84: =AY81-AY125 -> 0 | AZ84: =AZ81-AZ125 -> 0 | BA84: =BA81-BA125 -> 0 | BB84: =BB81-BB125 -> 0 | BC84: =BC81-BC125 -> 0
B86: LTM | C86: =C3 -> 42735 | D86: =D3 -> 43100 | E86: =E3 -> 43465 | F86: =F3 -> 43830 | G86: =G3 -> 44196 | H86: =H3 -> 44561 | I86: =I3 -> 44926 | J86: =J3 -> 44926 | ... O86: =O3 -> 46022 | P86: =P2 -> LTM | R86: =R3 -> 43190 | S86: =S3 -> 43281 | T86: =T3 -> 43373 | U86: =U3 -> 43465 | V86: =V3 -> 43555 | W86: =W3 -> 43646 | X86: =X3 -> 43738 | Y86: =Y3 -> 43830 | ... BC86: =BC3 -> 46112 | BE86: =BE3 -> 45382 | BF86: =BF3 -> 45473 | BG86: =BG3 -> 45565 | BH86: =BH3 -> 45656 | BI86: =BI3 -> 45747
B87: =+B7 -> Revenue | C87: =+C7 -> 4193.7747 | D87: =+D7 -> 4825.648 | E87: =+E7 -> 5955.508 | F87: =+F7 -> 7803.12 | G87: =+G7 -> 9400.861 | H87: =+H7 -> 12537.08 | I87: =+I7 -> 28196.847 | ... P87: =+P7 -> 118848.7 | U87: =SUM(R7:U7) -> 5955.508 | V87: =SUM(S7:V7) -> 6490.178 | W87: =SUM(T7:W7) -> 6998.407 | X87: =SUM(U7:X7) -> 7453.842 | Y87: =SUM(V7:Y7) -> 7803.12 | Z87: =SUM(W7:Z7) -> 8236.886 | AA87: =SUM(X7:AA7) -> 8561.029 | AB87: =SUM(Y7:AB7) -> 8896.719 | ... AK87: =SUM(AH7:AK7) -> 28196.847 | AL87: =SUM(AH7:AJ7,AL7) -> 51981.208 | AM87: =SUM(AI7:AK7,AM7) -> 32422.585 | AN87: =SUM(AI7:AJ7,AL7,AN7) -> 63442.045 | AO87: =SUM(AJ7,AL7,AN7:AO7) -> 66962.857 | AP87: =SUM(AK7,AM7,AO7:AP7) -> 45037.27 | AQ87: =SUM(AQ7,AO7,AM7,AK7) -> 41050.155 | AR87: =SUM(AL7,AN7,AP7,AR7) -> 84354.282 | AS87: =SUM(AM7,AO7,AQ7,AS7) -> 55836.141 | AT87: =SUM(AN7,AP7,AR7,AT7) -> 80615.534 | AU87: =SUM(AP7:AU7)-AS7-AQ7 -> 82869.615 | AV87: =SUM(AR7,AT7,AU7:AV7)-AU7 -> 62182.315 | AW87: =SUM(AT7:AW7)-AU7 -> 62569.314 | AX87: =SUM(AU7,AV7,AW7,AX7) -> 84097.908 | AY87: =SUM(AV7,AW7,AX7,AY7) -> 91459.289 | AZ87: =SUM(AW7,AX7,AY7:AZ7) -> 99207.645 | BA87: =SUM(AX7:BA7) -> 106422.37 | BB87: =SUM(AY7,AZ7,BA7,BB7) -> 111904.6 | BC87: =SUM(AZ7,BA7,BB7,BC7) -> 118848.7 | BE87: =SUM(AP7,AT7,AR7,BE7) -> 90338.322 | BF87: =SUM(AR7,BE7,AT7,BF7) -> 94617.672 | BG87: =BG7+BF7+BE7+AT7 -> 101062.98 | BH87: =SUM(BE7:BH7) -> 110077.71 | BI87: =SUM(BF7:BI7) -> 118293.08
B88: Operating profit | C88: =+C19 -> 839.61561 | D88: =+D19 -> 1199.175 | E88: =+E19 -> 2474.643 | F88: =+F19 -> 2274.379 | G88: =+G19 -> 3311.958 | H88: =+H19 -> 8395.201 | I88: =+I19 -> 8132.648 | J88: =+J19 -> 11622.115 | ... P88: =+P19 -> 24853.379 | U88: =SUM(R19:U19) -> 2474.643 | V88: =SUM(S19:V19) -> 2802.962 | W88: =SUM(T19:W19) -> 2423.823 | X88: =SUM(U19:X19) -> 1112.634 | Y88: =SUM(V19:Y19) -> 2274.379 | Z88: =SUM(W19:Z19) -> 1899.848 | AA88: =SUM(X19:AA19) -> 2555.737 | AB88: =SUM(Y19:AB19) -> 4046.758 | ... AK88: =SUM(AH19:AK19) -> 8132.648 | AL88: =SUM(AH19:AJ19,AL19) -> 11622.115 | AM88: =SUM(AI19:AK19,AM19) -> 9191.885 | AN88: =SUM(AI19:AJ19,AL19,AN19) -> 14031.236 | AO88: =SUM(AJ19,AL19,AN19:AO19) -> 18053.107 | AP88: =SUM(AK19,AM19,AO19:AP19) -> 20345.928 | AQ88: =SUM(AQ19,AO19,AM19,AK19) -> 14082.396 | AR88: =SUM(AL19,AN19,AP19,AR19) -> 23779.003 | AS88: =SUM(AM19,AO19,AQ19,AS19) -> 18197.749 | AT88: =SUM(AN19,AP19,AR19,AT19) -> 26273.687 | AU88: =SUM(AP19:AU19)-AS19-AQ19 -> 27700.363 | AV88: =SUM(AR19,AT19,AU19:AV19)-AU19 -> 15798.663 | AW88: =SUM(AT19:AW19)-AU19 -> 15778.309 | AX88: =SUM(AU19,AV19,AW19,AX19) -> 20123.423 | AY88: =SUM(AV19,AW19,AX19,AY19) -> 22798.771 | AZ88: =SUM(AW19,AX19,AY19:AZ19) -> 25618.583 | BA88: =SUM(AX19:BA19) -> 27865.374 | BB88: =SUM(AY19,AZ19,BA19,BB19) -> 27113.466 | BC88: =SUM(AZ19,BA19,BB19,BC19) -> 24853.379 | BE88: =SUM(AP19,AT19,AR19,BE19) -> 29801.301 | BF88: =SUM(AR19,BE19,AT19,BF19) -> 24532.174 | BG88: =BG19+BF19+BE19+AT19 -> 25985.385 | BH88: =SUM(BE19:BH19) -> 26340.017 | BI88: =SUM(BF19:BI19) -> 29442.218
B89: EBITDA | C89: =+C52 -> 596.05229 | D89: =+D52 -> 732.172 | E89: =+E52 -> 928.388 | F89: =+F52 -> 1324.828 | G89: =+G52 -> 1679.209 | H89: =+H52 -> 2659.999 | I89: =+I52 -> 6207.671 | J89: =+J52 -> 8225.774 | ... P89: =+P52 -> 18772.941 | U89: =SUM(R52:U52) -> 928.388 | V89: =SUM(S52:V52) -> 1042.786 | W89: =SUM(T52:W52) -> 1161.473 | X89: =SUM(U52:X52) -> 1202.953 | Y89: =SUM(V52:Y52) -> 1324.828 | Z89: =SUM(W52:Z52) -> 1428.38 | AA89: =SUM(X52:AA52) -> 1495.966 | AB89: =SUM(Y52:AB52) -> 1628.542 | ... AK89: =SUM(AH52:AK52) -> 6207.671 | AL89: =SUM(AH52:AJ52,AL52) -> 8205.474 | AM89: =SUM(AI52:AK52,AM52) -> 7158.64 | AN89: =SUM(AI52:AJ52,AL52,AN52) -> 10407.847 | AO89: =SUM(AJ52,AL52,AN52:AO52) -> 11977.793 | AP89: =SUM(AK52,AM52,AO52:AP52) -> 12038.781 | AQ89: =SUM(AQ52,AO52,AM52,AK52) -> 9680.281 | AR89: =SUM(AL52,AN52,AP52,AR52) -> 15699.094 | AS89: =SUM(AM52,AO52,AQ52,AS52) -> 12177.023 | AT89: =SUM(AN52,AP52,AR52,AT52) -> 17581.037 | AU89: =SUM(AP52:AU52)-AS52-AQ52 -> 18532.314 | AV89: =SUM(AR52,AT52,AU52:AV52)-AU52 -> 11989.111 | AW89: =SUM(AT52:AW52)-AU52 -> 11529.751 | AX89: =SUM(AU52,AV52,AW52,AX52) -> 16098.833 | AY89: =SUM(AV52,AW52,AX52,AY52) -> 17428.118 | AZ89: =SUM(AW52,AX52,AY52:AZ52) -> 17925.437 | BA89: =SUM(AX52:BA52) -> 19827.808 | BB89: =SUM(AY52,AZ52,BA52,BB52) -> 19187.702 | BC89: =SUM(AZ52,BA52,BB52,BC52) -> 18772.941 | BE89: =SUM(AP52,AT52,AR52,BE52) -> 20272.252 | BF89: =SUM(AR52,BE52,AT52,BF52) -> 19324.093 | BG89: =BG52+BF52+BE52+AT52 -> 19813.426 | BH89: =SUM(BE52:BH52) -> 21072.138 | BI89: =SUM(BF52:BI52) -> 22481.329
B90: Adjusted EBITDA | C90: =+C57 -> 575.3 | D90: =+D57 -> 733.592 | E90: =+E57 -> 939.168 | F90: =+F57 -> 1303.526 | G90: =+G57 -> 1621.152 | H90: =+H57 -> 2328.359 | I90: =+I57 -> 5467.021 | J90: =+J57 -> 6702.905 | ... P90: =+P57 -> 18061.336 | U90: =SUM(R57:U57) -> 939.168 | V90: =SUM(S57:V57) -> 1044.378 | W90: =SUM(T57:W57) -> 1162.63 | X90: =SUM(U57:X57) -> 1241.835 | Y90: =SUM(V57:Y57) -> 1303.526 | Z90: =SUM(W57:Z57) -> 1388.485 | AA90: =SUM(X57:AA57) -> 1449.694 | AB90: =SUM(Y57:AB57) -> 1521.497 | ... AK90: =SUM(AH57:AK57) -> 5467.021 | AL90: =SUM(AH57:AJ57,AL57) -> 6113.256 | AM90: =SUM(AI57:AK57,AM57) -> 6565.41 | AN90: =SUM(AI57:AJ57,AL57,AN57) -> 8440.724 | AO90: =SUM(AJ57,AL57,AN57:AO57) -> 9221.422 | AP90: =SUM(AK57,AM57,AO57:AP57) -> 9254.134 | AQ90: =SUM(AQ57,AO57,AM57,AK57) -> 8761.528 | AR90: =SUM(AL57,AN57,AP57,AR57) -> 13482.562 | AS90: =SUM(AM57,AO57,AQ57,AS57) -> 10600.588 | AT90: =SUM(AN57,AP57,AR57,AT57) -> 15304.999 | AU90: =SUM(AP57:AU57)-AS57-AQ57 -> 15775.174 | AV90: =SUM(AR57,AT57,AU57:AV57)-AU57 -> 11845.952 | AW90: =SUM(AT57:AW57)-AU57 -> 11132.429 | AX90: =SUM(AU57,AV57,AW57,AX57) -> 15595.955 | AY90: =SUM(AV57,AW57,AX57,AY57) -> 17038.147 | AZ90: =SUM(AW57,AX57,AY57:AZ57) -> 17464.589 | BA90: =SUM(AX57:BA57) -> 19106.711 | BB90: =SUM(AY57,AZ57,BA57,BB57) -> 18416.037 | BC90: =SUM(AZ57,BA57,BB57,BC57) -> 18061.336 | BE90: =SUM(AP57,AT57,AR57,BE57) -> 17315.432 | BF90: =SUM(AR57,BE57,AT57,BF57) -> 18452.761 | BG90: =BG57+BF57+BE57+AT57 -> 18794.339 | BH90: =BH57+BG57+BF57+BE57 -> 20413.909 | BI90: =BI57+BH57+BG57+BF57 -> 22008.779
B91: Cash interest paid | C91: =-C65 -> 75.880255 | D91: =-D65 -> 173.43 | E91: =-E65 -> 337.13 | F91: =-F65 -> 414.644 | G91: =-G65 -> 364.133 | H91: =-H65 -> 756.749 | I91: =-I65 -> 2014.244 | J91: =-J65 -> 3851.84 | ... P91: =-P65 -> 5651.265 | U91: =-SUM(R65:U65) -> 337.13 | V91: =-SUM(S65:V65) -> 353.455 | W91: =-SUM(T65:W65) -> 371.849 | X91: =-SUM(U65:X65) -> 415.811 | Y91: =-SUM(V65:Y65) -> 414.644 | Z91: =-SUM(W65:Z65) -> 419.261 | AA91: =-SUM(X65:AA65) -> 394.965 | AB91: =-SUM(Y65:AB65) -> 344.077 | ... AK91: =-SUM(AH65:AK65) -> 2014.244 | AL91: =-SUM(AH65:AJ65,AL65) -> 3851.84 | AM91: =-SUM(AI65:AK65,AM65) -> 2013.679 | AN91: =-SUM(AI65:AJ65,AL65,AN65) -> 3901.017 | AO91: =-SUM(AJ65,AL65,AN65:AO65) -> 4119.299 | AP91: =-SUM(AK65,AM65,AO65:AP65) -> 3918.12 | AQ91: =-SUM(AQ65,AO65,AM65,AK65) -> 2232.284 | AR91: =-SUM(AL65,AN65,AP65,AR65) -> 4933.233 | AS91: =-SUM(AM65,AO65,AQ65,AS65) -> 3670.666 | AT91: =-SUM(AN65,AP65,AR65,AT65) -> 5299.662 | AU91: =-SUM(AP65:AU65)+AS65+AQ65 -> 5266.86 | AV91: =-SUM(AR65,AT65,AU65:AV65)+AU65 -> 5134.447 | AW91: =-SUM(AT65:AW65)-AU65 -> 5951.575 | AX91: =-SUM(AU65,AV65,AW65,AX65) -> 4132.167 | AY91: =-SUM(AV65,AW65,AX65,AY65) -> 4847.962 | AZ91: =-SUM(AW65,AX65,AY65:AZ65) -> 4921.613 | BA91: =-SUM(AX65:BA65) -> 5466.311 | BB91: =-SUM(AY65,AZ65,BA65,BB65) -> 5224.851 | BC91: =-SUM(AZ65,BA65,BB65,BC65) -> 5651.265 | BE91: =-SUM(AP65,AT65,AR65,BE65) -> 5294.478 | BF91: =-SUM(AR65,BE65,AT65,BF65) -> 5809.218 | BG91: =-(BG65+BF65+BE65+AT65) -> 6697.899 | BH91: =-(BH65+BG65+BF65+BE65) -> 5408.69 | BI91: =-(BI65+BH65+BG65+BF65) -> 6340.191
B92: Net Income | C92: =+C29 -> 284.29642 | D92: =+D29 -> 444.997 | E92: =+E29 -> 787.621 | F92: =+F29 -> 1102.425 | G92: =+G29 -> 1203.585 | H92: =+H29 -> -162.419 | I92: =+I29 -> 199.52 | J92: =+J29 -> 1429.506 | ... P92: =+P29 -> 4462.294 | U92: =SUM(R29:U29) -> 787.621 | V92: =SUM(S29:V29) -> 1034.79 | W92: =SUM(T29:W29) -> 945.04 | X92: =SUM(U29:X29) -> 961.111 | Y92: =SUM(V29:Y29) -> 1102.425 | Z92: =SUM(W29:Z29) -> 658.836 | AA92: =SUM(X29:AA29) -> 1052.376 | AB92: =SUM(Y29:AB29) -> 1153.092 | ... AK92: =SUM(AH29:AK29) -> 199.52 | AL92: =SUM(AH29:AJ29,AL29) -> 1429.506 | AM92: =SUM(AI29:AK29,AM29) -> 1684.019 | AN92: =SUM(AI29:AJ29,AL29,AN29) -> 4250.776 | AO92: =SUM(AJ29,AL29,AN29:AO29) -> 3414.609 | AP92: =SUM(AK29,AM29,AO29:AP29) -> -1127.246 | AQ92: =SUM(AQ29,AO29,AM29,AK29) -> 2584.023 | AR92: =SUM(AL29,AN29,AP29,AR29) -> 6219.717 | AS92: =SUM(AM29,AO29,AQ29,AS29) -> 4222.764 | AT92: =SUM(AN29,AP29,AR29,AT29) -> 6096.775 | AU92: =SUM(AP29:AU29)-AS29-AQ29 -> 6087.644 | AV92: =SUM(AR29,AT29,AU29:AV29)-AU29 -> 7016.236 | AW92: =SUM(AT29:AW29)-AU29 -> 4135.804 | AX92: =SUM(AU29,AV29,AW29,AX29) -> 8016.106 | AY92: =SUM(AV29,AW29,AX29,AY29) -> 8114.068 | AZ92: =SUM(AW29,AX29,AY29:AZ29) -> 7535.769 | BA92: =SUM(AX29:BA29) -> 8129.778 | BB92: =SUM(AY29,AZ29,BA29,BB29) -> 5206.212 | BC92: =SUM(AZ29,BA29,BB29,BC29) -> 4462.294 | BE92: =SUM(AP29,AT29,AR29,BE29) -> 7033.032 | BF92: =SUM(AR29,BE29,AT29,BF29) -> 10910.423 | BG92: =BG29+BF29+BE29+AT29 -> 8199.449 | BH92: =BH29+BG29+BF29+BE29 -> 10492.467 | BI92: =BI29+BH29+BG29+BF29 -> 10441.138
B93: Capex | C93: =-C67 -> 263.88752 | D93: =-D67 -> 318.21 | E93: =-E67 -> 185.139 | F93: =-F67 -> 128.028 | G93: =-G67 -> 189.075 | H93: =-H67 -> 437.453 | I93: =-I67 -> 670.891 | J93: =-J67 -> 1135.353 | ... P93: =-P67 -> 1574.371 | U93: =-SUM(R67:U67) -> 185.139 | V93: =-SUM(S67:V67) -> 162.228 | W93: =-SUM(T67:W67) -> 130.051 | X93: =-SUM(U67:X67) -> 90.457 | Y93: =-SUM(V67:Y67) -> 128.028 | Z93: =-SUM(W67:Z67) -> 130.449 | AA93: =-SUM(X67:AA67) -> 134.097 | AB93: =-SUM(Y67:AB67) -> 141.297 | ... AK93: =-SUM(AH67:AK67) -> 670.891 | AL93: =-SUM(AH67:AJ67,AL67) -> 1135.353 | AM93: =-SUM(AI67:AK67,AM67) -> 748.99 | AN93: =-SUM(AI67:AJ67,AL67,AN67) -> 1314.629 | AO93: =-SUM(AJ67,AL67,AN67:AO67) -> 1360.461 | AP93: =-SUM(AK67,AM67,AO67:AP67) -> 907.891 | AQ93: =-SUM(AQ67,AO67,AM67,AK67) -> 927.974 | AR93: =-SUM(AL67,AN67,AP67,AR67) -> 1786.066 | AS93: =-SUM(AM67,AO67,AQ67,AS67) -> 850.363 | AT93: =-SUM(AN67,AP67,AR67,AT67) -> 1599.271 | AU93: =-SUM(AP67:AU67)+AS67+AQ67 -> 1611.492 | AV93: =-SUM(AR67,AT67,AU67:AV67)+AU67 -> 1431.1 | AW93: =-SUM(AT67:AW67)-AU67 -> 2159.885 | AX93: =-SUM(AU67,AV67,AW67,AX67) -> 2540.665 | AY93: =-SUM(AV67,AW67,AX67,AY67) -> 2450.238 | AZ93: =-SUM(AW67,AX67,AY67:AZ67) -> 2382.453 | BA93: =-SUM(AX67:BA67) -> 2345.249 | BB93: =-SUM(AY67,AZ67,BA67,BB67) -> 1554.297 | BC93: =-SUM(AZ67,BA67,BB67,BC67) -> 1574.371 | BE93: =-SUM(AP67,AT67,AR67,BE67) -> 1712.85 | BF93: =-SUM(AR67,BE67,AT67,BF67) -> 1910.534 | BG93: =-(BG67+BF67+BE67+AT67) -> 2316.439 | BH93: =-(BH67+BG67+BF67+BE67) -> 3325.535 | BI93: =-(BI67+BH67+BG67+BF67) -> 3187.949
B94: Free cash flow | C94: =+C70 -> 227.03698 | D94: =+D70 -> 292.826 | E94: =+E70 -> -557.648 | F94: =+F70 -> 153.684 | G94: =+G70 -> -184.112 | H94: =+H70 -> -5422.324 | I94: =+I70 -> -996.715 | J94: =+J70 -> -4546.727 | ... P94: =+P70 -> -4299.269 | U94: =SUM(R70:U70) -> -557.648 | V94: =SUM(S70:V70) -> -493.857 | W94: =SUM(T70:W70) -> -210.452 | X94: =SUM(U70:X70) -> -91.253 | Y94: =SUM(V70:Y70) -> 153.684 | Z94: =SUM(W70:Z70) -> -825.172 | AA94: =SUM(X70:AA70) -> -33.009 | AB94: =SUM(Y70:AB70) -> 1482.06 | ... AK94: =SUM(AH70:AK70) -> -996.715 | AL94: =SUM(AH70:AJ70,AL70) -> -5136.376 | AM94: =SUM(AI70:AK70,AM70) -> -1358.601 | AN94: =SUM(AI70:AJ70,AL70,AN70) -> -6540.317 | AO94: =SUM(AJ70,AL70,AN70:AO70) -> -6192.455 | AP94: =SUM(AK70,AM70,AO70:AP70) -> -2231.845 | AQ94: =SUM(AQ70,AO70,AM70,AK70) -> 635.89 | AR94: =SUM(AL70,AN70,AP70,AR70) -> -4544.652 | AS94: =SUM(AM70,AO70,AQ70,AS70) -> -4.274 | AT94: =SUM(AN70,AP70,AR70,AT70) -> 261.94 | AU94: =SUM(AP70:AU70)-AS70-AQ70 -> -594.248 | AV94: =SUM(AR70,AT70,AU70:AV70)-AU70 -> 4315.932 | AW94: =SUM(AT70:AW70)-AU70 -> -950.56 | AX94: =SUM(AU70,AV70,AW70,AX70) -> -2719.092 | AY94: =SUM(AV70,AW70,AX70,AY70) -> -8486.001 | AZ94: =SUM(AW70,AX70,AY70:AZ70) -> -11122.441 | BA94: =SUM(AX70:BA70) -> -8478.555 | BB94: =SUM(AY70,AZ70,BA70,BB70) -> -4253.742 | BC94: =SUM(AZ70,BA70,BB70,BC70) -> -4299.269 | BE94: =SUM(AP70,AT70,AR70,BE70) -> -1542.597 | BF94: =SUM(AR70,BE70,AT70,BF70) -> 1383.615 | BG94: =(BG70+BF70+BE70+AT70) -> -4755.469 | BH94: =(BH70+BG70+BF70+BE70) -> -3559.081 | BI94: =(BI70+BH70+BG70+BF70) -> -10938.691
B96: BALANCE SHEET | C96: =C3 -> 42735 | D96: =D3 -> 43100 | E96: =E3 -> 43465 | F96: =F3 -> 43830 | G96: =G3 -> 44196 | H96: =H3 -> 44561 | I96: =I3 -> 44926 | J96: =J3 -> 44926 | ... O96: =O3 -> 46022 | P96: =P2 -> LTM | R96: =R3 -> 43190 | S96: =S3 -> 43281 | T96: =T3 -> 43373 | U96: =U3 -> 43465 | V96: =V3 -> 43555 | W96: =W3 -> 43646 | X96: =X3 -> 43738 | Y96: =Y3 -> 43830 | ... BC96: =BC3 -> 46112 | BE96: =BE3 -> 45382 | BF96: =BF3 -> 45473 | BG96: =BG3 -> 45565 | BH96: =BH3 -> 45656 | BI96: =BI3 -> 45747
B98: Tangible fixed assets | C98: 1118.765 | D98: 2098.78 | E98: 2276.366 | F98: =2383.177+21.155 -> 2404.332 | G98: =2687.913+26.145 -> 2714.058 | H98: 3640.893 | I98: 6817.011 | J98: 14702.973 | K98: 16274.328 | L98: 23496.675 | M98: 23257.108 | N98: 30441.77 | O98: 31331.326 | P98: =BC98 -> 33521.791 | R98: =2053.211+16.192 -> 2069.403 | S98: =16.185+2196.005 -> 2212.19 | T98: =2355.854+16.196 -> 2372.05 | U98: =E98 -> 2276.366 | V98: =2297.472+21.036 -> 2318.508 | W98: =2363.467+21.036 -> 2384.503 | X98: =2337.141+21.036 -> 2358.177 | Y98: =F98 -> 2404.332 | Z98: =2394.753+21.155 -> 2415.908 | AA98: =2418.095+21.155 -> 2439.25 | AB98: =2491.983+21.155 -> 2513.138 | AC98: =G98 -> 2714.058 | AD98: =2747.508 -> 2747.508 | AE98: =2791.451+0 -> 2791.451 | AF98: 2943.696 | AG98: =H98 -> 3640.893 | AH98: 3680.546 | AI98: 3869.1 | AJ98: 4084.893 | AK98: =I98 -> 6817.011 | AL98: =J98 -> 14702.973 | AM98: 6823.652 | AN98: 6823.652 | AO98: 7446.514 | AP98: 7446.514 | AQ98: 7676.919 | AR98: 7676.919 | AS98: =K98 -> 16274.328 | AT98: =K98 -> 16274.328 | AU98: 18307.403 | AV98: 19590.032 | AW98: 21438.911 | AX98: =M98 -> 23257.108 | AY98: 25199.949 | AZ98: 26432.007 | BA98: 28267.63 | BB98: =O98 -> 31331.326 | BC98: 33521.791 | BE98: =AU98 -> 18307.403 | BF98: =AV98 -> 19590.032 | BG98: =AW98 -> 21438.911 | BH98: =N98 -> 30441.77 | BI98: =AY98 -> 25199.949
B99: Employee benefit plans | C99: 31.676 | D99: 28.577 | E99: 33.332 | F99: 44.822 | G99: 49.874 | H99: 76.957 | I99: 132.371 | J99: 218.112 | K99: 284.938 | L99: 411.39 | M99: 523.81 | N99: 1124.353 | O99: 908.887 | P99: =BC99 -> 1064.666 | R99: 44.729 | S99: 38.7 | T99: 39.765 | U99: =E99 -> 33.332 | V99: 50.087 | W99: 51.368 | X99: 42.525 | Y99: =F99 -> 44.822 | Z99: 55.926 | AA99: 53.185 | AB99: 49.441 | AC99: =G99 -> 49.874 | AD99: 76.123 | AE99: 66.386 | AF99: 67.553 | AG99: =H99 -> 76.957 | AH99: 101.646 | AI99: 101.208 | AJ99: 137.202 | AK99: =I99 -> 132.371 | AL99: =J99 -> 218.112 | AM99: 344.154 | AN99: 344.154 | AO99: 226.615 | AP99: 226.615 | AQ99: 286.668 | AR99: 286.668 | AS99: =K99 -> 284.938 | AT99: =K99 -> 284.938 | AU99: 665.329 | AV99: 408.857 | AW99: 505.471 | AX99: =M99 -> 523.81 | AY99: 687.281 | AZ99: 616.152 | BA99: 927.785 | BB99: =O99 -> 908.887 | BC99: 1064.666 | BE99: =AU99 -> 665.329 | BF99: =AV99 -> 408.857 | BG99: =AW99 -> 505.471 | BH99: =N99 -> 1124.353 | BI99: =AY99 -> 687.281
B100: Inventory | C100: 406.274 | D100: 583.581 | E100: 604.554 | F100: 592.698 | G100: 871.48 | H100: 3218.231 | I100: 4996.35 | J100: 8516.384 | K100: 8391.268 | L100: 12115.21 | M100: 11830.655 | N100: 15485.42 | O100: 23671.382 | P100: =BC100 -> 28469.837 | R100: 534.614 | S100: 506.807 | T100: 584.473 | U100: =E100 -> 604.554 | V100: 596.242 | W100: 661.139 | X100: 681.432 | Y100: =F100 -> 592.698 | Z100: 671.929 | AA100: 804.703 | AB100: 897.909 | AC100: =G100 -> 871.48 | AD100: 928.95 | AE100: 961.339 | AF100: 2028.702 | AG100: =H100 -> 3218.231 | AH100: 3744.893 | AI100: 4279.769 | AJ100: 5402.135 | AK100: =I100 -> 4996.35 | AL100: =J100 -> 8516.384 | AM100: 5520.627 | AN100: 5520.627 | AO100: 6555.159 | AP100: 6555.159 | AQ100: 6664.345 | AR100: 6664.345 | AS100: =K100 -> 8391.268 | AT100: =K100 -> 8391.268 | AU100: 8999.055 | AV100: 10414.885 | AW100: 10998.733 | AX100: =M100 -> 11830.655 | AY100: 19099.042 | AZ100: 23571.112 | BA100: 23046.205 | BB100: =O100 -> 23671.382 | BC100: 28469.837 | BE100: =AU100 -> 8999.055 | BF100: =AV100 -> 10414.885 | BG100: =AW100 -> 10998.733 | BH100: =N100 -> 15485.42 | BI100: =AY100 -> 19099.042
B101: Trade accounts receivable | C101: =587.415+175.851 -> 763.266 | D101: =534.993+241.929 -> 776.922 | E101: =1564.689+334.397 -> 1899.086 | F101: =2106.741+259.061 -> 2365.802 | G101: =2031.627+848.06 -> 2879.687 | H101: =2522.152+2165.759 -> 4687.911 | I101: =4100.552+3287.788 -> 7388.34 | J101: =6756.599+5417.384 -> 12173.983 | K101: =6733.195+5333.616 -> 12066.811 | L101: =9721.304+7700.609 -> 17421.913 | M101: =14521.162+7378.523 -> 21899.685 | N101: =19007.087+9657.921 -> 28665.008 | O101: =18882.923+10436.987 -> 29319.91 | P101: =BC101 -> 34687.717 | R101: =856.115+300.229 -> 1156.344 | S101: =1092.696+299.443 -> 1392.139 | T101: =1450.097+399.967 -> 1850.064 | U101: =E101 -> 1899.086 | V101: =1864.947+426.447 -> 2291.394 | W101: =1886.371+426.607 -> 2312.978 | X101: =2156.046+410.204 -> 2566.25 | Y101: =F101 -> 2365.802 | Z101: =2390.615+336.284 -> 2726.899 | AA101: =2296.692+280.55 -> 2577.242 | AB101: =2000.771+888.787 -> 2889.558 | AC101: =G101 -> 2879.687 | AD101: =2141.962+1114.735 -> 3256.697 | AE101: =2187.52+1097.4 -> 3284.92 | AF101: =2357.206+1284.907 -> 3642.113 | AG101: =H101 -> 4687.911 | AH101: =3187.991+2668.082 -> 5856.073 | AI101: =2791.415+2998.206 -> 5789.621 | AJ101: =3673.181+3369.507 -> 7042.688 | AK101: =I101 -> 7388.34 | AL101: =J101 -> 12173.983 | AM101: =5602.348+3922.531 -> 9524.879 | AN101: =5602.348+3922.531 -> 9524.879 | AO101: =5246.057+4646.703 -> 9892.76 | AP101: =5246.057+4646.703 -> 9892.76 | AQ101: =5937.903+4955.254 -> 10893.157 | AR101: =5937.903+4955.254 -> 10893.157 | AS101: =K101 -> 12066.811 | AT101: =K101 -> 12066.811 | AU101: =10225.914+6130.93 -> 16356.844 | AV101: =8675.247+6455.954 -> 15131.201 | AW101: =11670.631+6770.726 -> 18441.357 | AX101: =M101 -> 21899.685 | AY101: =18634.177+8744.771 -> 27378.948 | AZ101: =17455.651+9066.372 -> 26522.023 | BA101: =20079.94+9538.39 -> 29618.33 | BB101: =O101 -> 29319.91 | BC101: =23024.799+11662.918 -> 34687.717 | BE101: =AU101 -> 16356.844 | BF101: =AV101 -> 15131.201 | BG101: =AW101 -> 18441.357 | BH101: =N101 -> 28665.008 | BI101: =AY101 -> 27378.948
B102: Trade accounts payable | C102: =341.189+328.31 -> 669.499 | D102: =353.465+591.861 -> 945.326 | E102: =520.308+593.789 -> 1114.097 | F102: =607.365+617.233 -> 1224.598 | G102: =374.544+827.715 -> 1202.259 | H102: =475.461+1794.96 -> 2270.421 | I102: =1079.457+3081.81 -> 4161.267 | J102: =1778.653+5077.988 -> 6856.641 | K102: =2290.127+5344.931 -> 7635.058 | L102: =3306.457+7716.946 -> 11023.403 | M102: =3111.05+7157.284 -> 10268.334 | N102: =4072.329+9368.336 -> 13440.665 | O102: =5036.055+9170.668 -> 14206.723 | P102: =BC102 -> 12112.004 | R102: =425.114+570.86 -> 995.974 | S102: =349.258+450.522 -> 799.78 | T102: =490.274+537.218 -> 1027.492 | U102: =E102 -> 1114.097 | V102: =524.161+564.839 -> 1089 | W102: =565.96+515.941 -> 1081.901 | X102: =590.244+552.512 -> 1142.756 | Y102: =F102 -> 1224.598 | Z102: =534.128+628.886 -> 1163.014 | AA102: =398.629+555.87 -> 954.499 | AB102: =263.79+738.068 -> 1001.858 | AC102: =G102 -> 1202.259 | AD102: =578.708+838.498 -> 1417.206 | AE102: =591.41+825.489 -> 1416.899 | AF102: =321.535+1049.637 -> 1371.172 | AG102: =H102 -> 2270.421 | AH102: =753.85+2195.744 -> 2949.594 | AI102: =916.126+2353.913 -> 3270.039 | AJ102: =954.513+2843.544 -> 3798.057 | AK102: =I102 -> 4161.267 | AL102: =J102 -> 6856.641 | AM102: =918.986+2951.694 -> 3870.68 | AN102: =918.986+2951.694 -> 3870.68 | AO102: =1142.045+1142.045 -> 2284.09 | AP102: =1142.045+1142.045 -> 2284.09 | AQ102: =1262.274+4216.418 -> 5478.692 | AR102: =1262.274+4216.418 -> 5478.692 | AS102: =K102 -> 7635.058 | AT102: =K102 -> 7635.058 | AU102: =1799.868+5146.613 -> 6946.481 | AV102: =2102.413+5150.492 -> 7252.905 | AW102: =2018.521+5013.602 -> 7032.123 | AX102: =M102 -> 10268.334 | AY102: =3043.426+6817.662 -> 9861.088 | AZ102: =3224.387+6805.318 -> 10029.705 | BA102: =2754.053+6972.186 -> 9726.239 | BB102: =O102 -> 14206.723 | BC102: =3047.577+9064.427 -> 12112.004 | BE102: =AU102 -> 6946.481 | BF102: =AV102 -> 7252.905 | BG102: =AW102 -> 7032.123 | BH102: =N102 -> 13440.665 | BI102: =AY102 -> 9861.088
B103: Net working capital | C103: =+C100+C101-C102 -> 500.041 | D103: =+D100+D101-D102 -> 415.177 | E103: =+E100+E101-E102 -> 1389.543 | F103: =+F100+F101-F102 -> 1733.902 | G103: =+G100+G101-G102 -> 2548.908 | H103: =+H100+H101-H102 -> 5635.721 | I103: =+I100+I101-I102 -> 8223.423 | J103: =+J100+J101-J102 -> 13833.726 | ... P103: =+P100+P101-P102 -> 51045.55 | R103: =+R100+R101-R102 -> 694.984 | S103: =+S100+S101-S102 -> 1099.166 | T103: =+T100+T101-T102 -> 1407.045 | U103: =+U100+U101-U102 -> 1389.543 | V103: =+V100+V101-V102 -> 1798.636 | W103: =+W100+W101-W102 -> 1892.216 | X103: =+X100+X101-X102 -> 2104.926 | Y103: =+Y100+Y101-Y102 -> 1733.902 | ... BC103: =+BC100+BC101-BC102 -> 51045.55 | BE103: =+BE100+BE101-BE102 -> 18409.418 | BF103: =+BF100+BF101-BF102 -> 18293.181 | BG103: =+BG100+BG101-BG102 -> 22407.967 | BH103: =+BH100+BH101-BH102 -> 30709.763 | BI103: =+BI100+BI101-BI102 -> 36616.902
B104: % of revenues | C104: =+C103/C87 -> 0.11923411 | D104: =+D103/D87 -> 0.086035492 | E104: =+E103/E87 -> 0.23332065 | F104: =+F103/F87 -> 0.22220625 | G104: =+G103/G87 -> 0.27113559 | H104: =+H103/H87 -> 0.44952421 | I104: =+I103/I87 -> 0.29164335 | J104: =+J103/J87 -> 0.26612937 | ... P104: =+P103/P87 -> 0.42950026 | U104: =+U103/U87 -> 0.23332065 | V104: =+V103/V87 -> 0.277132 | W104: =+W103/W87 -> 0.2703781 | X104: =+X103/X87 -> 0.28239477 | Y104: =+Y103/Y87 -> 0.22220625 | Z104: =+Z103/Z87 -> 0.27143923 | AA104: =+AA103/AA87 -> 0.28354606 | AB104: =+AB103/AB87 -> 0.3131052 | ... BC104: =+BC103/BC87 -> 0.42950026 | BE104: =+BE103/BE87 -> 0.20378304 | BF104: =+BF103/BF87 -> 0.19333789 | BG104: =+BG103/BG87 -> 0.22172279 | BH104: =+BH103/BH87 -> 0.27898258 | BI104: =+BI103/BI87 -> 0.30954391
B106: Inventory Days | C106: =IFERROR((C100/-C9)*365,"-") -> 47.533037 | D106: =IFERROR((D100/-D9)*365,"-") -> 59.604454 | E106: =IFERROR((E100/-E9)*365,"-") -> 50.205009 | F106: =IFERROR((F100/-F9)*365,"-") -> 38.195184 | G106: =IFERROR((G100/-G9)*365,"-") -> 47.072882 | H106: =IFERROR((H100/-H9)*365,"-") -> 131.61887 | I106: =IFERROR((I100/-I9)*365,"-") -> 92.15875 | J106: =IFERROR((J100/-J9)*365,"-") -> 76.4637 | ... P106: =IFERROR((P100/-P9)*365,"-") -> 120.73744 | Z106: =IFERROR((Z100/-Z9)*(365/4),"-") -> 36.939305 | AA106: =IFERROR((AA100/-AA9)*(365/4),"-") -> 47.145339 | AB106: =IFERROR((AB100/-AB9)*(365/4),"-") -> 50.996758 | AC106: =IFERROR((AC100/-AC9)*(365/4),"-") -> 41.131105 | AD106: =IFERROR((AD100/-AD9)*(365/4),"-") -> 44.239246 | AE106: =IFERROR((AE100/-AE9)*(365/4),"-") -> 45.57714 | AF106: =IFERROR((AF100/-AF9)*(365/4),"-") -> 85.23177 | AG106: =IFERROR((AG100/-AG9)*(365/4),"-") -> 100.84871 | ... BC106: =IFERROR((BC100/-BC9)*(365/4),"-") -> 106.2324 | BE106: =IFERROR((BE100/-BE9)*(365/4),"-") -> 44.586351 | BF106: =IFERROR((BF100/-BF9)*(365/4),"-") -> 66.18792 | BG106: =IFERROR((BG100/-BG9)*(365/4),"-") -> 56.75997 | BH106: =IFERROR((BH100/-BH9)*(365/4),"-") -> 52.706227 | BI106: =IFERROR((BI100/-BI9)*(365/4),"-") -> 74.203271
B107: Receivable Days | C107: =IFERROR((C101/C7)*365,"-") -> 66.429913 | D107: =IFERROR((D101/D7)*365,"-") -> 58.764446 | E107: =IFERROR((E101/E7)*365,"-") -> 116.39081 | F107: =IFERROR((F101/F7)*365,"-") -> 110.66314 | G107: =IFERROR((G101/G7)*365,"-") -> 111.80739 | H107: =IFERROR((H101/H7)*365,"-") -> 136.48214 | I107: =IFERROR((I101/I7)*365,"-") -> 95.639917 | J107: =IFERROR((J101/J7)*365,"-") -> 85.482888 | ... P107: =IFERROR((P101/P7)*365,"-") -> 106.53054 | Z107: =IFERROR((Z101/Z7)*(365/4),"-") -> 104.72068 | AA107: =IFERROR((AA101/AA7)*(365/4),"-") -> 109.65627 | AB107: =IFERROR((AB101/AB7)*(365/4),"-") -> 118.30235 | AC107: =IFERROR((AC101/AC7)*(365/4),"-") -> 99.1106 | AD107: =IFERROR((AD101/AD7)*(365/4),"-") -> 110.48668 | AE107: =IFERROR((AE101/AE7)*(365/4),"-") -> 117.89925 | AF107: =IFERROR((AF101/AF7)*(365/4),"-") -> 111.66934 | AG107: =IFERROR((AG101/AG7)*(365/4),"-") -> 98.818758 | ... BC107: =IFERROR((BC101/BC7)*(365/4),"-") -> 93.352648 | BE107: =IFERROR((BE101/BE7)*(365/4),"-") -> 55.137854 | BF107: =IFERROR((BF101/BF7)*(365/4),"-") -> 66.782066 | BG107: =IFERROR((BG101/BG7)*(365/4),"-") -> 69.379237 | BH107: =IFERROR((BH101/BH7)*(365/4),"-") -> 68.692183 | BI107: =IFERROR((BI101/BI7)*(365/4),"-") -> 70.804258
B108: Payable Days | C108: =IFERROR((C102/-C9)*365,"-") -> 78.329701 | D108: =IFERROR((D102/-D9)*365,"-") -> 96.551532 | E108: =IFERROR((E102/-E9)*365,"-") -> 92.519857 | F108: =IFERROR((F102/-F9)*365,"-") -> 78.916658 | G108: =IFERROR((G102/-G9)*365,"-") -> 64.939868 | H108: =IFERROR((H102/-H9)*365,"-") -> 92.855437 | I108: =IFERROR((I102/-I9)*365,"-") -> 76.755464 | J108: =IFERROR((J102/-J9)*365,"-") -> 61.561825 | ... P108: =IFERROR((P102/-P9)*365,"-") -> 51.365673 | Z108: =IFERROR((Z102/-Z9)*(365/4),"-") -> 63.936709 | AA108: =IFERROR((AA102/-AA9)*(365/4),"-") -> 55.921476 | AB108: =IFERROR((AB102/-AB9)*(365/4),"-") -> 56.900543 | AC108: =IFERROR((AC102/-AC9)*(365/4),"-") -> 56.74283 | AD108: =IFERROR((AD102/-AD9)*(365/4),"-") -> 67.491389 | AE108: =IFERROR((AE102/-AE9)*(365/4),"-") -> 67.175266 | AF108: =IFERROR((AF102/-AF9)*(365/4),"-") -> 57.60699 | AG108: =IFERROR((AG102/-AG9)*(365/4),"-") -> 71.147481 | ... BC108: =IFERROR((BC102/-BC9)*(365/4),"-") -> 45.194753 | BE108: =IFERROR((BE102/-BE9)*(365/4),"-") -> 34.416752 | BF108: =IFERROR((BF102/-BF9)*(365/4),"-") -> 46.093135 | BG108: =IFERROR((BG102/-BG9)*(365/4),"-") -> 36.289915 | BH108: =IFERROR((BH102/-BH9)*(365/4),"-") -> 45.746692 | BI108: =IFERROR((BI102/-BI9)*(365/4),"-") -> 38.31213
B110: Debt Breakdown
B111: Short-term debt | C111: =544.791+1821.631 -> 2366.422 | D111: =433.371+457.356 -> 890.727 | E111: =85.519+369.129 -> 454.648 | F111: =150.764+5074.414 -> 5225.178 | G111: =11.408+431.144+318.467 -> 761.019 | H111: =1499.536+579.253+759.909 -> 2838.698 | I111: =9655.778+812.749+925.081 -> 11393.608 | J111: =1524.283+15910.107+1339.19 -> 18773.58 | K111: =1140.185+3046.205+1273.041 -> 5459.431 | L111: =1646.185+6237.833 -> 7884.018 | M111: =4204.001+11070.42 -> 15274.421 | N111: =5502.715+2130.884+12357.619+1.827 -> 19993.045 | O111: =12491.954+3225.238+1820.411 -> 17537.603 | P111: =BC111 -> 17384.16 | R111: =320.021+479.879 -> 799.9 | S111: =170.622+246.773 -> 417.395 | T111: =192.618+219.539 -> 412.157 | U111: =E111 -> 454.648 | V111: =77.245+392.56 -> 469.805 | W111: =263.751+2608.307 -> 2872.058 | X111: =355.486+2518.239 -> 2873.725 | Y111: =+F111 -> 5225.178 | Z111: =140.003+5560.634 -> 5700.637 | AA111: =115.995+3347.15 -> 3463.145 | AB111: =69.362+3980.636 -> 4049.998 | AC111: =G111 -> 761.019 | AD111: =470.663+368.139 -> 838.802 | AE111: =1.319+494.091+377.089 -> 872.499 | AF111: =33.25+690.318+1037.494+392.536 -> 2153.598 | AG111: =H111 -> 2838.698 | AH111: =1624.323+647.136+707.289 -> 2978.748 | AI111: =8656.566+723.935+1277.648 -> 10658.149 | AJ111: =9136.15+818.905+1463.691 -> 11418.746 | AK111: =I111 -> 11393.608 | AL111: =J111 -> 18773.58 | AM111: =10256.886+846.966+1268.448 -> 12372.3 | AN111: =10256.886+846.966+1268.448 -> 12372.3 | AO111: =1598.56+2567.485+1122.118 -> 5288.163 | AP111: =1598.56+2567.485+1122.118 -> 5288.163 | AQ111: =2679.303+1207.277+1094.307 -> 4980.887 | AR111: =2679.303+1207.277+1094.307 -> 4980.887 | AS111: =K111 -> 5459.431 | AT111: =K111 -> 5459.431 | AU111: =3345.172+1423.746+1668.098 -> 6437.016 | AV111: =3108.267+1738.118+1419.399 -> 6265.784 | AW111: =3966.044+3687.592-1.697 -> 7651.939 | AX111: =M111 -> 15274.421 | AY111: =7796.383+1835.185+10267.035 -> 19898.603 | AZ111: =14005.143+19689.936+10712.631 -> 44407.71 | BA111: =14520.268+21085.424+11353.579 -> 46959.271 | BB111: =O111 -> 17537.603 | BC111: =12235.408+5148.752 -> 17384.16 | BE111: =AU111 -> 6437.016 | BF111: =AV111 -> 6265.784 | BG111: =AW111 -> 7651.939 | BH111: =N111 -> 19993.045 | BI111: =AY111 -> 19898.603
B112: Long-term debt | C112: 586.432 | D112: 3419.676 | E112: 4791.105 | F112: 652.49 | G112: =4097.309+4479.923 -> 8577.232 | H112: =7148.942+8157.834 -> 15306.776 | I112: =1315.059+11031.399 -> 12346.458 | J112: =2166.861+18176.758 -> 20343.619 | K112: =9188.165+15913.031 -> 25101.196 | L112: 36242.814 | M112: 32734.945 | N112: =18628.989+24218.543 -> 42847.532 | O112: =17280.429+22527.348 -> 39807.777 | P112: =BC112 -> 40868.248 | R112: 3906.693 | S112: 4381.652 | T112: 5762.607 | U112: =E112 -> 4791.105 | V112: 5087.497 | W112: 3011.327 | X112: 2880.328 | Y112: =+F112 -> 652.49 | Z112: =667.124 -> 667.124 | AA112: 3712.722 | AB112: 4356.368 | AC112: =G112 -> 8577.232 | AD112: =4525.666+5178.668 -> 9704.334 | AE112: =4582.72+5308.538 -> 9891.258 | AF112: =5019.26+5525.557 -> 10544.817 | AG112: =G112 -> 8577.232 | AH112: =7751.662+9113.845 -> 16865.507 | AI112: =1211.906+10200.526 -> 11412.432 | AJ112: =1258.034+11538.698 -> 12796.732 | AK112: =I112 -> 12346.458 | AL112: =J112 -> 20343.619 | AM112: =1332.721+11495.292 -> 12828.013 | AN112: =1332.721+11495.292 -> 12828.013 | AO112: =23317.042-2.069 -> 23314.973 | AP112: =23317.042-2.069 -> 23314.973 | AQ112: =8512.677+15077.99 -> 23590.667 | AR112: =8512.677+15077.99 -> 23590.667 | AS112: =K112 -> 25101.196 | AT112: =K112 -> 25101.196 | AU112: =10078.163+17796.852 -> 27875.015 | AV112: =31478.927-0.552 -> 31478.375 | AW112: =39885.968-0.055 -> 39885.913 | AX112: =M112 -> 32734.945 | AY112: =16065.955+19455.607 -> 35521.562 | AZ112: 20879.282 | BA112: =118.717+21395.215 -> 21513.932 | BB112: =O112 -> 39807.777 | BC112: 40868.248 | BE112: =AU112 -> 27875.015 | BF112: =AV112 -> 31478.375 | BG112: =AW112 -> 39885.913 | BH112: =N112 -> 42847.532 | BI112: =AY112 -> 35521.562
B113: Total Debt | C113: =SUM(C111:C112) -> 2952.854 | D113: =SUM(D111:D112) -> 4310.403 | E113: =SUM(E111:E112) -> 5245.753 | F113: =SUM(F111:F112) -> 5877.668 | G113: =SUM(G111:G112) -> 9338.251 | H113: =SUM(H111:H112) -> 18145.474 | I113: =SUM(I111:I112) -> 23740.066 | J113: =SUM(J111:J112) -> 39117.199 | ... P113: =SUM(P111:P112) -> 58252.408 | R113: =SUM(R111:R112) -> 4706.593 | S113: =SUM(S111:S112) -> 4799.047 | T113: =SUM(T111:T112) -> 6174.764 | U113: =SUM(U111:U112) -> 5245.753 | V113: =SUM(V111:V112) -> 5557.302 | W113: =SUM(W111:W112) -> 5883.385 | X113: =SUM(X111:X112) -> 5754.053 | Y113: =SUM(Y111:Y112) -> 5877.668 | ... BC113: =SUM(BC111:BC112) -> 58252.408 | BE113: =SUM(BE111:BE112) -> 34312.031 | BF113: =SUM(BF111:BF112) -> 37744.159 | BG113: =SUM(BG111:BG112) -> 47537.852 | BH113: =SUM(BH111:BH112) -> 62840.577 | BI113: =SUM(BI111:BI112) -> 55420.165
...

Sheet KPIs
B2: ÜLKER BÝSKÜVÝ SANAYÝ A.Þ. | C2: Annual | D2: Annual | E2: Annual | F2: Annual | G2: Annual | H2: Annual | I2: Annual | J2: Annual | K2: Annual | L2: Annual | M2: Annual | N2: Annual | O2: Annual | P2: LTM | R2: Quarters | S2: Quarters | T2: Quarters | U2: Quarters | V2: Quarters | W2: Quarters | X2: Quarters | Y2: Quarters | Z2: Quarters | AA2: Quarters | AB2: Quarters | AC2: Quarters | AD2: Quarters | AE2: Quarters | AF2: Quarters | AG2: Quarters | AH2: Quarters | AI2: Quarters | AJ2: Quarters | AK2: Quarters | AL2: Quarters | AM2: Quarters | AN2: Quarters | AO2: Quarters | AP2: Quarters | AQ2: Quarters | AR2: Quarters | AS2: Quarters | AT2: Quarters | AU2: Quarters | AV2: Quarters | AW2: Quarters | AX2: Quarters | AY2: Quarters | BA2: Quarters | BB2: Quarters | BC2: Quarters | BD2: Quarters | BE2: Quarters | BG2: Semi - Annually | BH2: Semi - Annually | BJ2: 9M | BK2: 9M
B3: (TL million) | C3: 42735 | D3: 43100 | E3: 43465 | F3: 43830 | G3: 44196 | H3: 44561 | I3: 44926 | J3: 44926 | K3: 45291 | L3: 45291 | M3: 45657 | N3: 45657 | O3: 46022 | P3: =AY3 -> 46112 | R3: 43190 | S3: 43281 | T3: 43373 | U3: 43465 | V3: 43555 | W3: 43646 | X3: 43738 | Y3: 43830 | Z3: 43921 | AA3: 44012 | AB3: 44104 | AC3: 44196 | AD3: 44286 | AE3: 44377 | AF3: 44469 | AG3: 44561 | AH3: 44651 | AI3: 44742 | AJ3: 44834 | AK3: 44926 | AL3: 45016 | AM3: 45016 | AN3: 45107 | AO3: 45199 | AP3: 45291 | AQ3: 45382 | AR3: 45473 | AS3: 45565 | AT3: 45657 | AU3: 45747 | AV3: 45838 | AW3: 45930 | AX3: 46021 | AY3: 46112 | BA3: 45382 | BB3: 45473 | BC3: 45565 | BD3: 45656 | BE3: 45747 | BG3: 45473 | BH3: 45838 | BJ3: 45565 | BK3: 45930
C4: Act | D4: Act | E4: Act | F4: Act | G4: Act | H4: Act | I4: Act | J4: Restated | K4: Act | L4: Restated | M4: Act | N4: Restated | O4: Act | P4: Act | R4: Act | S4: Act | T4: Act | U4: Act | V4: Act | W4: Act | X4: Act | Y4: Act | Z4: Act | AA4: Act | AB4: Act | AC4: Act | AD4: Act | AE4: Act | AF4: Act | AG4: Act | AH4: Act | AI4: Act | AJ4: Act | AK4: Act | AL4: Act | AM4: Restated | AN4: Act | AO4: Act | AP4: Act | AQ4: Act | AR4: Act | AS4: Act | AT4: Act | AU4: Act | AV4: Act | AW4: Act | AX4: Act | AY4: Act | BA4: Restated | BB4: Restated | BC4: Restated | BD4: Restated | BE4: Restated | BG4: Act | BH4: Act | BJ4: Act | BK4: Act
C5: FY | D5: FY | E5: FY | F5: FY | G5: FY | H5: FY | I5: FY | J5: FY | K5: FY | L5: FY | M5: FY | N5: FY | O5: FY | P5: LTM | R5: 1Q | S5: 2Q | T5: 3Q | U5: 4Q | V5: 1Q | W5: 2Q | X5: 3Q | Y5: 4Q | Z5: 1Q | AA5: 2Q | AB5: 3Q | AC5: 4Q | AD5: 1Q | AE5: 2Q | AF5: 3Q | AG5: 4Q | AH5: 1Q | AI5: 2Q | AJ5: 3Q | AK5: 4Q | AL5: 1Q | AM5: 1Q | AN5: 2Q | AO5: 3Q | AP5: 4Q | AQ5: 1Q | AR5: 2Q | AS5: 3Q | AT5: 4Q | AU5: 1Q | AV5: 2Q | AW5: 3Q | AX5: 4Q | AY5: 1Q | BA5: 1Q | BB5: 2Q | BC5: 3Q | BD5: 4Q | BE5: 1Q | BG5: 1H | BH5: 1H | BJ5: 9M | BK5: 9M
B8: Revenue by business segment
B9: Domestic | D9: 3173.193 | E9: 3709.288 | F9: 4728.447 | G9: 5606.929 | H9: 7386.841 | I9: 17482.255 | J9: =33287.39 -> 33287.39 | K9: 38076.576 | L9: 92193.212 | M9: 76189.509 | N9: 99726.223 | O9: 103118.66 | P9: =SUM(AV9:AY9) -> 110717 | R9: 930.381 | S9: =1807.14-R9 -> 876.759 | T9: =2700.129-S9-R9 -> 892.989 | U9: =+E9-SUM(R9:T9) -> 1009.159 | V9: 1202.223 | W9: =2320.967-V9 -> 1118.744 | X9: =3499.827-V9-W9 -> 1178.86 | Y9: =+F9-SUM(V9:X9) -> 1228.62 | Z9: 1474.956 | AA9: =2736.219-Z9 -> 1261.263 | AB9: =4047.242-Z9-AA9 -> 1311.023 | AC9: =+G9-SUM(Z9:AB9) -> 1559.687 | AD9: 1681.246 | AE9: =3169.435-AD9 -> 1488.189 | AF9: =5148.731-AD9-AE9 -> 1979.296 | AG9: =+H9-SUM(AD9:AF9) -> 2238.11 | AH9: 3506.874 | AI9: =7089.243-AH9 -> 3582.369 | AJ9: =11813.999-AH9-AI9 -> 4724.756 | AK9: =+I9-SUM(AH9:AJ9) -> 5668.256 | AL9: 6659.227 | AM9: 11477.348 | AN9: =12859.019-AL9 -> 6199.792 | AO9: =20920.052-AL9-AN9 -> 8061.033 | AP9: =+K9-SUM(AL9:AO9) -> 5679.176 | AQ9: 13416.966 | AR9: =25336.366-AQ9 -> 11919.4 | AS9: =40904.033-AQ9-AR9 -> 15567.667 | AU9: 25559.447 | AV9: 21132.488 | AW9: 23096.503 | AX9: =O9-SUM(AU9:AW9) -> 33330.223 | AY9: 33157.781 | BA9: 25188.647 | BB9: 18884.78 | BC9: 22027.66 | BD9: =N9-SUM(BA9:BC9) -> 33625.136 | BE9: 33449.106 | BG9: 45586.436 | BH9: 48227.219 | BJ9: 71035.079 | BK9: 74942.876
B10: Foreign | D10: 1652.455 | E10: 2246.22 | F10: 3074.673 | G10: 3793.932 | H10: 5150.239 | I10: 10714.592 | J10: 18693.818 | K10: 17759.565 | L10: 15975.816 | M10: 15607.316 | N10: 20428.779 | O10: 21326.493 | P10: =SUM(AV10:AY10) -> 22652.167 | R10: 477.309 | S10: =912.819-R10 -> 435.51 | T10: =1457.504-S10-R10 -> 544.685 | U10: =+E10-SUM(R10:T10) -> 788.716 | V10: 740.137 | W10: =1441.891-V10 -> 701.754 | X10: =2156.14-V10-W10 -> 714.249 | Y10: =+F10-SUM(V10:X10) -> 918.533 | Z10: 901.17 | AA10: =1784.548-Z10 -> 883.378 | AB10: =2702.324-Z10-AA10 -> 917.776 | AC10: =+G10-SUM(Z10:AB10) -> 1091.608 | AD10: 1102.511 | AE10: =2062.659-AD10 -> 960.148 | AF10: =3270.226-AD10-AE10 -> 1207.567 | AG10: =+H10-SUM(AD10:AF10) -> 1880.013 | AH10: 2379.144 | AI10: =4787.817-AH10 -> 2408.673 | AJ10: =7364.881-AH10-AI10 -> 2577.064 | AK10: =+I10-SUM(AH10:AJ10) -> 3349.711 | AL10: 3452.529 | AM10: 5869.507 | AN10: =6764.591-AL10 -> 3312.062 | AO10: =11112.136-AL10-AN10 -> 4347.545 | AP10: =+K10-SUM(AL10:AO10) -> 777.922 | AQ10: 6183.97 | AR10: =11221.335-AQ10 -> 5037.365 | AS10: =17110.852-AQ10-AR10 -> 5889.517 | AU10: 3920.202 | AV10: 4460.924 | AW10: 5405.227 | AX10: =O10-SUM(AU10:AW10) -> 7540.14 | AY10: 5245.876 | BA10: 4563.131 | BB10: 3856.679 | BC10: 4391.578 | BD10: =N10-SUM(BA10:BC10) -> 7617.391 | BE10: 5130.285 | BG10: 8693.905 | BH10: 8616.602 | BJ10: 13737.906 | BK10: 14668.452
B11: Sales returns and discounts (-) | L11: -27553.494 | M11: -7698.917 | N11: -10077.292 | O11: -12540.553 | P11: =SUM(AV11:AY11) -> -14520.457 | AU11: -2517.332 | AV11: -2535.727 | AW11: -3090.597 | AX11: =O11-SUM(AU11:AW11) -> -4396.897 | AY11: -4497.236 | BA11: -2682.135 | BB11: -2066.416 | BC11: -2164.52 | BD11: =N11-SUM(BA11:BC11) -> -3164.221 | BE11: -3294.38 | BG11: -4909.657 | BH11: -5204.268 | BJ11: -7442.618 | BK11: -8685.413
B12: Total | D12: =SUM(D9:D11) -> 4825.648 | E12: =SUM(E9:E11) -> 5955.508 | F12: =SUM(F9:F11) -> 7803.12 | G12: =SUM(G9:G11) -> 9400.861 | H12: =SUM(H9:H11) -> 12537.08 | I12: =SUM(I9:I11) -> 28196.847 | J12: =SUM(J9:J11) -> 51981.208 | K12: =SUM(K9:K11) -> 55836.141 | ... P12: =SUM(P9:P11) -> 118848.71 | R12: =SUM(R9:R10) -> 1407.69 | S12: =SUM(S9:S10) -> 1312.269 | T12: =SUM(T9:T10) -> 1437.674 | U12: =SUM(U9:U10) -> 1797.875 | V12: =SUM(V9:V10) -> 1942.36 | W12: =SUM(W9:W10) -> 1820.498 | X12: =SUM(X9:X10) -> 1893.109 | Y12: =SUM(Y9:Y10) -> 2147.153 | Z12: =SUM(Z9:Z10) -> 2376.126 | AA12: =SUM(AA9:AA11) -> 2144.641 | AB12: =SUM(AB9:AB11) -> 2228.799 | AC12: =SUM(AC9:AC11) -> 2651.295 | AD12: =SUM(AD9:AD11) -> 2783.757 | AE12: =SUM(AE9:AE11) -> 2448.337 | AF12: =SUM(AF9:AF11) -> 3186.863 | AG12: =SUM(AG9:AG11) -> 4118.123 | AH12: =SUM(AH9:AH11) -> 5886.018 | ... AY12: =SUM(AY9:AY11) -> 33906.421 | BA12: =SUM(BA9:BA11) -> 27069.643 | BB12: =SUM(BB9:BB11) -> 20675.043 | BC12: =SUM(BC9:BC11) -> 24254.718 | BD12: =SUM(BD9:BD11) -> 38078.306 | BE12: =SUM(BE9:BE11) -> 35285.011 | BG12: =SUM(BG9:BG11) -> 49370.684 | BH12: =SUM(BH9:BH11) -> 51639.553 | BJ12: =SUM(BJ9:BJ11) -> 77330.367 | BK12: =SUM(BK9:BK11) -> 80925.915
B13: Check | D13: =+D12-Model!D7 -> 0 | E13: =+E12-Model!E7 -> 0 | F13: =+F12-Model!F7 -> 0 | G13: =+G12-Model!G7 -> 0 | H13: =+H12-Model!H7 -> 0 | I13: =+I12-Model!I7 -> 0 | J13: =+J12-Model!J7 -> 0 | K13: =+K12-Model!K7 -> 0 | ... P13: =+P12-Model!P7 -> 0 | R13: =+R12-Model!R7 -> 0 | S13: =+S12-Model!S7 -> 0 | T13: =+T12-Model!T7 -> 0 | U13: =+U12-Model!U7 -> 0 | V13: =+V12-Model!V7 -> 0 | W13: =+W12-Model!W7 -> 0 | X13: =+X12-Model!X7 -> 0 | Y13: =+Y12-Model!Y7 -> 0 | ... AC13: =+AC12-Model!AC7 -> 0 | AD13: =+AD12-Model!BR7 -> 0 | AE13: =+AE12-Model!AE7 -> -94.079 | AF13: =((+AF12-Model!AF7)-(8418.957-SUM(Model!AD7:AF7))) -> -1.3642421e-12 | AG13: =((+AG12-Model!AG7))+(8418.957-SUM(Model!AD7:AF7)) -> 0 | AH13: =+AH12-Model!AH7 -> 0 | AI13: =+AI12-Model!AI7 -> 0 | AJ13: =((+AJ12-Model!AJ7)-(19178.88-SUM(Model!AH7:AJ7))) -> 0 | AK13: =+AK12-Model!AK7 -> 0 | AL13: =+AL12-Model!AM7 -> 0 | AM13: =+AM12-Model!AN7 -> 0 | AN13: =+AN12-Model!AO7 -> 0 | AO13: =+AO12-Model!AQ7 -> 0 | AP13: =+AP12-Model!AS7 -> -17346.855 | AQ13: =+AQ12-Model!AU7 -> 0 | AR13: =+AR12-Model!AV7 -> 1647.436 | AS13: =+AS12-Model!AW7 -> 3260.779 | AU13: =+AU12-Model!AY7 -> 0 | AV13: =+AV12-Model!AZ7 -> 0 | AW13: =+AW12-Model!BA7 -> 0 | AX13: =+AX12-Model!BB7 -> 0 | AY13: =+AY12-Model!BC7 -> 0 | BA13: =BA12-Model!BE7 -> 0 | BB13: =BB12-Model!BF7 -> 0 | BC13: =BC12-Model!BG7 -> 0 | BD13: =BD12-Model!BH7 -> 0 | BE13: =BE12-Model!BI7 -> 0 | BG13: =BG12-Model!BK7 -> 0 | BH13: =BH12-Model!BL7 -> 0 | BJ13: =BJ12-Model!BN7 -> 0 | BK13: =BK12-Model!BO7 -> 0
B15: % of Revenue by business segment
B16: =+B9 -> Domestic | D16: =+D9/D$12 -> 0.65756827 | E16: =+E9/E$12 -> 0.62283318 | F16: =+F9/F$12 -> 0.60596877 | G16: =+G9/G$12 -> 0.59642718 | H16: =+H9/H$12 -> 0.58919948 | I16: =+I9/I$12 -> 0.62000744 | J16: =+J9/J$12 -> 0.64037354 | K16: =+K9/K$12 -> 0.68193423 | ... P16: =+P9/P$12 -> 0.93157931 | R16: =+R9/R$12 -> 0.66092748 | S16: =+S9/S$12 -> 0.66812445 | T16: =+T9/T$12 -> 0.62113455 | U16: =+U9/U$12 -> 0.56130654 | V16: =+V9/V$12 -> 0.61894963 | W16: =+W9/W$12 -> 0.61452635 | X16: =+X9/X$12 -> 0.62271111 | Y16: =+Y9/Y$12 -> 0.57220887 | ... AY16: =+AY9/AY$12 -> 0.97792041 | BA16: =+BA9/BA$12 -> 0.93051271 | BB16: =+BB9/BB$12 -> 0.91340947 | BC16: =+BC9/BC$12 -> 0.90818042 | BD16: =+BD9/BD$12 -> 0.88305231 | BE16: =+BE9/BE$12 -> 0.94796927 | BG16: =+BG9/BG$12 -> 0.9233503 | BH16: =+BH9/BH$12 -> 0.93392015 | BJ16: =+BJ9/BJ$12 -> 0.91859229 | BK16: =+BK9/BK$12 -> 0.9260677
B17: =+B10 -> Foreign | D17: =+D10/D$12 -> 0.34243173 | E17: =+E10/E$12 -> 0.37716682 | F17: =+F10/F$12 -> 0.39403123 | G17: =+G10/G$12 -> 0.40357282 | H17: =+H10/H$12 -> 0.41080052 | I17: =+I10/I$12 -> 0.37999256 | J17: =+J10/J$12 -> 0.35962646 | K17: =+K10/K$12 -> 0.31806577 | ... P17: =+P10/P$12 -> 0.19059667 | R17: =+R10/R$12 -> 0.33907252 | S17: =+S10/S$12 -> 0.33187555 | T17: =+T10/T$12 -> 0.37886545 | U17: =+U10/U$12 -> 0.43869346 | V17: =+V10/V$12 -> 0.38105037 | W17: =+W10/W$12 -> 0.38547365 | X17: =+X10/X$12 -> 0.37728889 | Y17: =+Y10/Y$12 -> 0.42779113 | ... AY17: =+AY10/AY$12 -> 0.1547163 | BA17: =+BA10/BA$12 -> 0.16857005 | BB17: =+BB10/BB$12 -> 0.18653789 | BC17: =+BC10/BC$12 -> 0.18106077 | BD17: =+BD10/BD$12 -> 0.20004543 | BE17: =+BE10/BE$12 -> 0.14539559 | BG17: =+BG10/BG$12 -> 0.17609448 | BH17: =+BH10/BH$12 -> 0.16686051 | BJ17: =+BJ10/BJ$12 -> 0.17765215 | BK17: =+BK10/BK$12 -> 0.18125778
B18: Sales returns and discounts (-) | D18: =+D11/D$12 -> 0 | E18: =+E11/E$12 -> 0 | F18: =+F11/F$12 -> 0 | G18: =+G11/G$12 -> 0 | H18: =+H11/H$12 -> 0 | I18: =+I11/I$12 -> 0 | J18: =+J11/J$12 -> 0 | K18: =+K11/K$12 -> 0 | ... P18: =+P11/P$12 -> -0.12217598 | R18: =+R11/R$12 -> 0 | S18: =+S11/S$12 -> 0 | T18: =+T11/T$12 -> 0 | U18: =+U11/U$12 -> 0 | V18: =+V11/V$12 -> 0 | W18: =+W11/W$12 -> 0 | X18: =+X11/X$12 -> 0 | Y18: =+Y11/Y$12 -> 0 | ... AY18: =+AY11/AY$12 -> -0.13263671 | BA18: =+BA11/BA$12 -> -0.099082762 | BB18: =+BB11/BB$12 -> -0.099947362 | BC18: =+BC11/BC$12 -> -0.089241194 | BD18: =+BD11/BD$12 -> -0.083097735 | BE18: =+BE11/BE$12 -> -0.093364857 | BG18: =+BG11/BG$12 -> -0.099444784 | BH18: =+BH11/BH$12 -> -0.10078066 | BJ18: =+BJ11/BJ$12 -> -0.096244442 | BK18: =+BK11/BK$12 -> -0.10732548
B19: Total | D19: =SUM(D16:D18) -> 1 | E19: =SUM(E16:E18) -> 1 | F19: =SUM(F16:F18) -> 1 | G19: =SUM(G16:G18) -> 1 | H19: =SUM(H16:H18) -> 1 | I19: =SUM(I16:I18) -> 1 | J19: =SUM(J16:J18) -> 1 | K19: =SUM(K16:K18) -> 1 | ... P19: =SUM(P16:P18) -> 1 | R19: =SUM(R16:R18) -> 1 | S19: =SUM(S16:S18) -> 1 | T19: =SUM(T16:T18) -> 1 | U19: =SUM(U16:U18) -> 1 | V19: =SUM(V16:V18) -> 1 | W19: =SUM(W16:W18) -> 1 | X19: =SUM(X16:X18) -> 1 | Y19: =SUM(Y16:Y18) -> 1 | ... AY19: =SUM(AY16:AY18) -> 1 | BA19: =SUM(BA16:BA18) -> 1 | BB19: =SUM(BB16:BB18) -> 1 | BC19: =SUM(BC16:BC18) -> 1 | BD19: =SUM(BD16:BD18) -> 1 | BE19: =SUM(BE16:BE18) -> 1 | BG19: =SUM(BG16:BG18) -> 1 | BH19: =SUM(BH16:BH18) -> 1 | BJ19: =SUM(BJ16:BJ18) -> 1 | BK19: =SUM(BK16:BK18) -> 1
B21: EBITDA by business segment
B22: =B16 -> Domestic | D22: 429.643 | E22: 497.507 | F22: 676.098 | G22: 809.63 | H22: 1250.882 | I22: 3217.757 | J22: 3464.503 | K22: 6602.587 | L22: 9532.734 | M22: 10799.323 | N22: 14135.486 | O22: 13594.98 | P22: =SUM(AV22:AY22) -> 13383.96 | R22: 132.262 | S22: =252.088-R22 -> 119.826 | T22: =369.64-S22-R22 -> 117.552 | U22: =+E22-SUM(R22:T22) -> 127.867 | V22: 174.773 | W22: =348.102-V22 -> 173.329 | X22: =512.561-V22-W22 -> 164.459 | Y22: =+F22-SUM(V22:X22) -> 163.537 | Z22: 221.672 | AA22: =417.938-Z22 -> 196.266 | AB22: =602.601-Z22-AA22 -> 184.663 | AC22: =+G22-SUM(Z22:AB22) -> 207.029 | AD22: 300.844 | AE22: =412.894-AD22 -> 112.05 | AF22: =855.013-AD22-AE22 -> 442.119 | AG22: =+H22-SUM(AD22:AF22) -> 395.869 | AH22: 691.594 | AI22: =1308.551-AH22 -> 616.957 | AJ22: =2070.402-AH22-AI22 -> 761.851 | AK22: =+I22-SUM(AH22:AJ22) -> 1147.355 | AL22: 1533.295 | AM22: 2259.992 | AN22: =2733.404-AL22 -> 1200.109 | AO22: =4404.468-AL22-AN22 -> 1671.064 | AP22: =+K22-SUM(AL22:AO22) -> -61.873 | AQ22: 2581.608 | AR22: =4860.935-AQ22 -> 2279.327 | AS22: =7438.392-AQ22-AR22 -> 2577.457 | AT22: =M22-SUM(AQ22:AS22) -> 3360.931 | AU22: 3960.616 | AV22: =BH22-AU22 -> 2843.132 | AW22: =BK22-AU22-AV22 -> 3889.863 | AX22: =O22-SUM(AU22:AW22) -> 2901.369 | AY22: 3749.596 | BA22: 3565.3 | BB22: =BG22-BA22 -> 2999.327 | BC22: =BJ22-BB22-BA22 -> 3350.304 | BD22: =N22-SUM(BA22:BC22) -> 4220.555 | BE22: 5183.174 | BG22: 6564.627 | BH22: =6803.748 -> 6803.748 | BJ22: 9914.931 | BK22: 10693.611
B23: =B17 -> Foreign | D23: 303.949 | E23: 441.661 | F23: 627.428 | G23: 811.522 | H23: 1077.477 | I23: 2249.264 | J23: 3238.402 | K23: 3998.001 | L23: 5772.265 | M23: 4796.632 | N23: 6278.423 | O23: 4821.057 | P23: =SUM(AV23:AY23) -> 4677.376 | R23: 92.736 | S23: =173.228-R23 -> 80.492 | T23: =291.04-S23-R23 -> 117.812 | U23: =+E23-SUM(R23:T23) -> 150.621 | V23: 155.435 | W23: =300.676-V23 -> 145.241 | X23: =450.786-V23-W23 -> 150.11 | Y23: =+F23-SUM(V23:X23) -> 176.642 | Z23: 193.495 | AA23: =377.008-Z23 -> 183.513 | AB23: =578.717-Z23-AA23 -> 201.709 | AC23: =+G23-SUM(Z23:AB23) -> 232.805 | AD23: 245.54 | AE23: =396.246-AD23 -> 150.706 | AF23: =640.738-AD23-AE23 -> 244.492 | AG23: =+H23-SUM(AD23:AF23) -> 436.739 | AH23: 553.031 | AI23: =1070.445-AH23 -> 517.414 | AJ23: =1562.345-AH23-AI23 -> 491.9 | AK23: =+I23-SUM(AH23:AJ23) -> 686.919 | AL23: 809.719 | AM23: 1312.101 | AN23: =1524.68-AL23 -> 714.961 | AO23: =2522.786-AL23-AN23 -> 998.106 | AP23: =+K23-SUM(AL23:AO23) -> 163.114 | AQ23: 1460.66 | AR23: =2456.156-AQ23 -> 995.496 | AS23: =3433.359-AQ23-AR23 -> 977.203 | AT23: =M23-SUM(AQ23:AS23) -> 1363.273 | AU23: 1523.844 | AV23: =BH23-AU23 -> 858.133 | AW23: =BK23-AU23-AV23 -> 1306.919 | AX23: =O23-SUM(AU23:AW23) -> 1132.161 | AY23: 1380.163 | BA23: 2017.226 | BB23: =BG23-BA23 -> 1299.779 | BC23: =BJ23-BB23-BA23 -> 1259.457 | BD23: =N23-SUM(BA23:BC23) -> 1701.961 | BE23: 1994.222 | BG23: 3317.005 | BH23: 2381.977 | BJ23: 4576.462 | BK23: 3688.896
B24: Total | D24: =SUM(D22:D23) -> 733.592 | E24: =SUM(E22:E23) -> 939.168 | F24: =SUM(F22:F23) -> 1303.526 | G24: =SUM(G22:G23) -> 1621.152 | H24: =SUM(H22:H23) -> 2328.359 | I24: =SUM(I22:I23) -> 5467.021 | J24: =SUM(J22:J23) -> 6702.905 | K24: =SUM(K22:K23) -> 10600.588 | ... P24: =SUM(P22:P23) -> 18061.336 | R24: =SUM(R22:R23) -> 224.998 | S24: =SUM(S22:S23) -> 200.318 | T24: =SUM(T22:T23) -> 235.364 | U24: =SUM(U22:U23) -> 278.488 | V24: =SUM(V22:V23) -> 330.208 | W24: =SUM(W22:W23) -> 318.57 | X24: =SUM(X22:X23) -> 314.569 | Y24: =SUM(Y22:Y23) -> 340.179 | ... AY24: =SUM(AY22:AY23) -> 5129.759 | BA24: =SUM(BA22:BA23) -> 5582.526 | BB24: =SUM(BB22:BB23) -> 4299.106 | BC24: =SUM(BC22:BC23) -> 4609.761 | BD24: =SUM(BD22:BD23) -> 5922.516 | BE24: =SUM(BE22:BE23) -> 7177.396 | BG24: =SUM(BG22:BG23) -> 9881.632 | BH24: =SUM(BH22:BH23) -> 9185.725 | BJ24: =SUM(BJ22:BJ23) -> 14491.393 | BK24: =SUM(BK22:BK23) -> 14382.507
B25: Check | D25: =D24-Model!D57 -> 0 | E25: =E24-Model!E57 -> 0 | F25: =F24-Model!F57 -> 0 | G25: =G24-Model!G57 -> 0 | H25: =H24-Model!H57 -> 0 | I25: =I24-Model!I57 -> 0 | J25: =J24-Model!J57 -> 0 | K25: =K24-Model!K57 -> 0 | ... P25: =P24-Model!P57 -> 0 | R25: =R24-Model!R57 -> 0 | S25: =S24-Model!S57 -> 0 | T25: =T24-Model!T57 -> 0 | U25: =U24-Model!U57 -> 0 | V25: =V24-Model!V57 -> 0 | W25: =W24-Model!W57 -> 0 | X25: =X24-Model!X57 -> 0 | Y25: =Y24-Model!Y57 -> 0 | ... AC25: =AC24-Model!AC57 -> 0 | AD25: =AD24-Model!BR57 -> 0 | AE25: =AE24-Model!AE57 -> -88.882 | AF25: =AF24-Model!AF57 -> 0 | AG25: =AG24-Model!AG57 -> 0 | AH25: =AH24-Model!AH57 -> 0 | AI25: =AI24-Model!AI57 -> 0 | AJ25: =AJ24-Model!AJ57 -> 0 | AK25: =AK24-Model!AK57 -> 0 | AL25: =AL24-Model!AM57 -> 0 | AM25: =AM24-Model!AN57 -> 0 | AN25: =AN24-Model!AO57 -> 0.001 | AO25: =AO24-Model!AQ57 -> -0.001 | AP25: =AP24-Model!AS57 -> -3572.093 | AQ25: =AQ24-Model!AU57 -> 0 | AR25: =AR24-Model!AV57 -> 0 | AS25: =AS24-Model!AW57 -> 0 | AT25: =AT24-Model!AX57 -> 0 | AU25: =AU24-Model!AY57 -> 0 | AV25: =AV24-Model!AZ57 -> 0 | AW25: =AW24-Model!BA57 -> 0 | AX25: =AX24-Model!BB57 -> -4.0927262e-12 | AY25: =AY24-Model!BC57 -> 0 | BA25: =BA24-Model!BE57 -> 0 | BB25: =BB24-Model!BF57 -> 0 | BC25: =BC24-Model!BG57 -> 0 | BD25: =BD24-Model!BH57 -> 0 | BE25: =BE24-Model!BI57 -> 0 | BG25: =BG24-Model!BK57 -> 0 | BH25: =BH24-Model!BL57 -> 0 | BJ25: =BJ24-Model!BN57 -> 0 | BK25: =BK24-Model!BO57 -> 0
B27: % margin
B28: =+B22 -> Domestic | D28: =+D22/D9 -> 0.13539769 | E28: =+E22/E9 -> 0.13412466 | F28: =+F22/F9 -> 0.14298521 | G28: =+G22/G9 -> 0.14439812 | H28: =+H22/H9 -> 0.16933923 | I28: =+I22/I9 -> 0.18405846 | J28: =+J22/J9 -> 0.10407854 | K28: =+K22/K9 -> 0.17340286 | ... P28: =+P22/P9 -> 0.12088442 | R28: =+R22/R9 -> 0.14215896 | S28: =+S22/S9 -> 0.13666926 | T28: =+T22/T9 -> 0.1316388 | U28: =+U22/U9 -> 0.1267065 | V28: =+V22/V9 -> 0.14537486 | W28: =+W22/W9 -> 0.15493178 | X28: =+X22/X9 -> 0.13950681 | Y28: =+Y22/Y9 -> 0.13310625 | ... AS28: =+AS22/AS9 -> 0.16556476 | AU28: =+AU22/AU9 -> 0.15495703 | AV28: =+AV22/AV9 -> 0.13453844 | AW28: =+AW22/AW9 -> 0.16841783 | AX28: =+AX22/AX9 -> 0.087049193 | AY28: =+AY22/AY9 -> 0.11308344 | BA28: =+BA22/BA9 -> 0.14154393 | BB28: =+BB22/BB9 -> 0.15882245 | BC28: =+BC22/BC9 -> 0.15209532 | BD28: =+BD22/BD9 -> 0.12551786 | BE28: =+BE22/BE9 -> 0.15495703 | BG28: =+BG22/BG9 -> 0.14400395 | BH28: =+BH22/BH9 -> 0.14107693 | BJ28: =+BJ22/BJ9 -> 0.13957795 | BK28: =+BK22/BK9 -> 0.14269016
B29: =+B23 -> Foreign | D29: =+D23/D10 -> 0.18393784 | E29: =+E23/E10 -> 0.19662411 | F29: =+F23/F10 -> 0.20406333 | G29: =+G23/G10 -> 0.21389999 | H29: =+H23/H10 -> 0.20920913 | I29: =+I23/I10 -> 0.20992531 | J29: =+J23/J10 -> 0.17323385 | K29: =+K23/K10 -> 0.22511818 | ... P29: =+P23/P10 -> 0.20648691 | R29: =+R23/R10 -> 0.19428923 | S29: =+S23/S10 -> 0.18482239 | T29: =+T23/T10 -> 0.21629382 | U29: =+U23/U10 -> 0.19096988 | V29: =+V23/V10 -> 0.21000842 | W29: =+W23/W10 -> 0.20696854 | X29: =+X23/X10 -> 0.2101648 | Y29: =+Y23/Y10 -> 0.19230882 | ... AS29: =+AS23/AS10 -> 0.16592243 | AU29: =+AU23/AU10 -> 0.38871568 | AV29: =+AV23/AV10 -> 0.19236665 | AW29: =+AW23/AW10 -> 0.241788 | AX29: =+AX23/AX10 -> 0.15015119 | AY29: =+AY23/AY10 -> 0.26309486 | BA29: =+BA23/BA10 -> 0.44207059 | BB29: =+BB23/BB10 -> 0.33702027 | BC29: =+BC23/BC10 -> 0.28678917 | BD29: =+BD23/BD10 -> 0.22343096 | BE29: =+BE23/BE10 -> 0.38871564 | BG29: =+BG23/BG10 -> 0.38153223 | BH29: =+BH23/BH10 -> 0.27644041 | BJ29: =+BJ23/BJ10 -> 0.33312661 | BK29: =+BK23/BK10 -> 0.25148502
B30: Total | D30: =+D24/D12 -> 0.15201938 | E30: =+E24/E12 -> 0.15769738 | F30: =+F24/F12 -> 0.1670519 | G30: =+G24/G12 -> 0.17244718 | H30: =+H24/H12 -> 0.18571781 | I30: =+I24/I12 -> 0.19388767 | J30: =+J24/J12 -> 0.12894862 | K30: =+K24/K12 -> 0.18985173 | ... P30: =+P24/P12 -> 0.15196914 | R30: =+R24/R12 -> 0.15983491 | S30: =+S24/S12 -> 0.1526501 | T30: =+T24/T12 -> 0.16371166 | U30: =+U24/U12 -> 0.15489842 | V30: =+V24/V12 -> 0.1700035 | W30: =+W24/W12 -> 0.17499058 | X30: =+X24/X12 -> 0.16616529 | Y30: =+Y24/Y12 -> 0.15843258 | ... AS30: =+AS24/AS12 -> 0.16566293 | AU30: =+AU24/AU12 -> 0.20341204 | AV30: =+AV24/AV12 -> 0.16052197 | AW30: =+AW24/AW12 -> 0.20450808 | AX30: =+AX24/AX12 -> 0.11058806 | AY30: =+AY24/AY12 -> 0.15129167 | BA30: =+BA24/BA12 -> 0.20622828 | BB30: =+BB24/BB12 -> 0.20793698 | BC30: =+BC24/BC12 -> 0.19005626 | BD30: =+BD24/BD12 -> 0.15553518 | BE30: =+BE24/BE12 -> 0.20341204 | BG30: =+BG24/BG12 -> 0.20015181 | BH30: =+BH24/BH12 -> 0.17788157 | BJ30: =+BJ24/BJ12 -> 0.18739589 | BK30: =+BK24/BK12 -> 0.17772437
B32: Confectionary Volume (Tons) | D32: 545717 | E32: 553664 | F32: 576335 | G32: 595000 | H32: 583000 | I32: 681745 | J32: 594000 | K32: 603000 | L32: 688000 | M32: 705000 | N32: 705000 | O32: 696000 | P32: =SUM(AV32:AY32) -> 696000 | S32: 130129 | T32: 129687 | V32: 154515 | W32: 132415 | X32: 137496 | Y32: =+F32-SUM(V32:X32) -> 151909 | Z32: 162774 | AA32: 137249 | AB32: 137665 | AC32: =+G32-SUM(Z32:AB32) -> 157312 | AD32: 167404 | AE32: 130645 | AF32: 165387 | AG32: =+H32-SUM(AD32:AF32) -> 119564 | AH32: 179138 | AI32: =337447-AH32 -> 158309 | AJ32: 163406 | AK32: =+I32-SUM(AH32:AJ32) -> 180892 | AL32: 173324 | AN32: =324376-AL32 -> 151052 | AO32: 177702 | AP32: =+K32-SUM(AL32:AO32) -> 100922 | AQ32: 200000 | AR32: 153000 | AS32: 172000 | AT32: =M32-SUM(AQ32:AS32) -> 180000 | AU32: 182000 | AV32: 161000 | AW32: =BK32-AU32-AV32 -> 174000 | AX32: =O32-SUM(AU32:AW32) -> 179000 | AY32: 182000 | BA32: 200000 | BB32: 153000 | BC32: =BJ32-BB32-BA32 -> 172000 | BD32: =N32-SUM(BA32:BC32) -> 180000 | BE32: 182000 | BG32: 353000 | BH32: 344000 | BJ32: 525000 | BK32: 517000
B34: Confectionary Sales Volume (KTons)
B35: Biscuits | D35: 307.123 | E35: 313.202 | F35: 328 | G35: 334 | H35: 322 | I35: 323 | J35: 323 | K35: 326 | L35: 326 | M35: 338 | N35: =SUM(BA35:BD35) -> 339.21 | O35: =SUM(AU35:AX35) -> 348.12 | P35: =SUM(AV35:AY35) -> 350.28 | R35: 83.337 | S35: 71.648 | T35: 74 | U35: =+E35-SUM(R35:T35) -> 84.217 | V35: 89.947 | W35: 73.469 | X35: 81 | Y35: =+F35-SUM(V35:X35) -> 83.584 | Z35: 92 | AA35: 76 | AB35: 79 | AC35: =+G35-SUM(Z35:AB35) -> 87 | AD35: 84 | AE35: 70 | AF35: 82 | AG35: =+H35-SUM(AD35:AF35) -> 86 | AH35: 87 | AI35: 73 | AJ35: 80 | AK35: =+I35-SUM(AH35:AJ35) -> 83 | AL35: 83 | AN35: 71 | AO35: 85 | AP35: =+K35-SUM(AL35:AO35) -> 87 | AQ35: =AQ38*51% -> 91.29 | AR35: =AR38*54% -> 72.36 | AS35: 86.07 | AT35: =M35-SUM(AQ35:AS35) -> 88.28 | AU35: =AU38*53% -> 85.86 | AV35: =AV38*57% -> 81.51 | AW35: =AW38*59% -> 90.27 | AX35: =AX38*58% -> 90.48 | AY35: =AY38*54% -> 88.02 | BA35: =BA38*51% -> 91.29 | BB35: =BB38*54% -> 72.36 | BC35: =BC38*57% -> 86.07 | BD35: =BD38*57% -> 89.49 | BE35: =BE38*53% -> 85.86
B36: Chocolate | D36: 179.054 | E36: 187.587 | F36: 199 | G36: 219 | H36: 217 | I36: 222 | J36: 222 | K36: 224 | L36: 224 | M36: 227 | N36: =SUM(BA36:BD36) -> 224.62 | O36: =SUM(AU36:AX36) -> 207.66 | P36: =SUM(AV36:AY36) -> 206.41 | R36: 50.078 | S36: 45.778 | T36: 42 | U36: =+E36-SUM(R36:T36) -> 49.731 | V36: 52.007 | W36: 47.704 | X36: 45 | Y36: =+F36-SUM(V36:X36) -> 54.289 | Z36: 59 | AA36: 53 | AB36: 48 | AC36: =+G36-SUM(Z36:AB36) -> 59 | AD36: 55 | AE36: 51 | AF36: 51 | AG36: =+H36-SUM(AD36:AF36) -> 60 | AH36: 58 | AI36: 53 | AJ36: 51 | AK36: =+I36-SUM(AH36:AJ36) -> 60 | AL36: 58 | AN36: 52 | AO36: 55 | AP36: =+K36-SUM(AL36:AO36) -> 59 | AQ36: =AQ38*40% -> 71.6 | AR36: =AR38*36% -> 48.24 | AS36: 49.83 | AT36: =M36-SUM(AQ36:AS36) -> 57.33 | AU36: =AU38*38% -> 61.56 | AV36: =AV38*33% -> 47.19 | AW36: =AW38*31% -> 47.43 | AX36: =AX38*33% -> 51.48 | AY36: =AY38*37% -> 60.31 | BA36: =BA38*40% -> 71.6 | BB36: =BB38*36% -> 48.24 | BC36: =BC38*33% -> 49.83 | BD36: =BD38*35% -> 54.95 | BE36: =BE38*38% -> 61.56
B37: Cake | D37: 59.54 | E37: 52.875 | F37: 49 | G37: 42 | H37: 44 | I37: 50 | J37: 50 | K37: 53 | L37: 53 | M37: 56 | N37: =SUM(BA37:BD37) -> 55.38 | O37: =SUM(AU37:AX37) -> 58.22 | P37: =SUM(AV37:AY37) -> 58.31 | R37: 14.642 | S37: 12.871 | T37: 13 | U37: =+E37-SUM(R37:T37) -> 12.362 | V37: 12.561 | W37: 11.241 | X37: 12 | Y37: =+F37-SUM(V37:X37) -> 13.198 | Z37: 12 | AA37: 8 | AB37: 11 | AC37: =+G37-SUM(Z37:AB37) -> 11 | AD37: 10 | AE37: 10 | AF37: 12 | AG37: =+H37-SUM(AD37:AF37) -> 12 | AH37: 12 | AI37: 12 | AJ37: 13 | AK37: =+I37-SUM(AH37:AJ37) -> 13 | AL37: 12 | AN37: 11 | AO37: 15 | AP37: =+K37-SUM(AL37:AO37) -> 15 | AQ37: =AQ38*8% -> 14.32 | AR37: =AR38*10% -> 13.4 | AS37: 15.1 | AT37: =M37-SUM(AQ37:AS37) -> 13.18 | AU37: =AU38*9% -> 14.58 | AV37: =AV38*10% -> 14.3 | AW37: =AW38*10% -> 15.3 | AX37: =AX38*9% -> 14.04 | AY37: =AY38*9% -> 14.67 | BA37: =BA38*8% -> 14.32 | BB37: =BB38*10% -> 13.4 | BC37: =BC38*10% -> 15.1 | BD37: =BD38*8% -> 12.56 | BE37: =BE38*9% -> 14.58
B38: Total | D38: =+D35+D36+D37 -> 545.717 | E38: =+E35+E36+E37 -> 553.664 | F38: =+F35+F36+F37 -> 576 | G38: =+G35+G36+G37 -> 595 | H38: =+H35+H36+H37 -> 583 | I38: =+I35+I36+I37 -> 595 | J38: =+J35+J36+J37 -> 595 | K38: =+K35+K36+K37 -> 603 | ... M38: =+M35+M36+M37 -> 621 | N38: =SUM(N35:N36) -> 563.83 | O38: =SUM(O35:O36) -> 555.78 | P38: =+P35+P36+P37 -> 615 | R38: =+R35+R36+R37 -> 148.057 | S38: =+S35+S36+S37 -> 130.297 | T38: =+T35+T36+T37 -> 129 | U38: =+U35+U36+U37 -> 146.31 | V38: =+V35+V36+V37 -> 154.515 | W38: =+W35+W36+W37 -> 132.414 | X38: =+X35+X36+X37 -> 138 | Y38: =+Y35+Y36+Y37 -> 151.071 | ... AL38: =+AL35+AL36+AL37 -> 153 | AN38: =+AN35+AN36+AN37 -> 134 | AO38: =+AO35+AO36+AO37 -> 155 | AP38: =+AP35+AP36+AP37 -> 161 | AQ38: 179 | AR38: 134 | AS38: =+AS35+AS36+AS37 -> 151 | AT38: =+AT35+AT36+AT37 -> 158.79 | AU38: 162 | AV38: 143 | AW38: 153 | AX38: 156 | AY38: 163 | BA38: 179 | BB38: 134 | BC38: 151 | BD38: 157 | BE38: 162
B40: Confectionary Sales Value ( MTL)
B41: Biscuits | D41: 2050 | E41: 2625 | F41: 3395 | G41: 4149 | H41: 5324 | I41: 12123 | J41: 21906 | K41: 22350 | L41: 32263 | M41: 31283 | N41: =SUM(BA41:BD41) -> 34716.16 | O41: =SUM(AU41:AX41) -> 36350.44 | P41: =SUM(AV41:AY41) -> 38902.3 | R41: 618 | S41: 554 | T41: 660 | U41: =+E41-SUM(R41:T41) -> 793 | V41: 874 | W41: 776 | X41: 845 | Y41: =+F41-SUM(V41:X41) -> 900 | Z41: 1050 | AA41: 899 | AB41: 1010 | AC41: =+G41-SUM(Z41:AB41) -> 1190 | AD41: 1191 | AE41: 1055 | AF41: 1312 | AG41: =+H41-SUM(AD41:AF41) -> 1766 | AH41: 2617 | AI41: 2502 | AJ41: 3348 | AK41: =+I41-SUM(AH41:AJ41) -> 3656 | AL41: 4124 | AN41: 3849 | AO41: 5293 | AP41: =+K41-SUM(AL41:AO41) -> 9084 | AQ41: =AQ44*39% -> 7413.9 | AR41: =AR44*39% -> 5656.17 | AS41: 6902.8 | AT41: =M41-SUM(AQ41:AS41) -> 11310.13 | AU41: =AU44*33% -> 8532.48 | AV41: =AV44*38% -> 8227.76 | AW41: =AW44*40% -> 9668.4 | AX41: =AX44*38% -> 9921.8 | AY41: =AY44*34% -> 11084.34 | BA41: =BA44*39% -> 7413.9 | BB41: =BB44*39% -> 7638.54 | BC41: =BC44*40% -> 9200.8 | BD41: =BD44*38% -> 10462.92 | BE41: =BE44*33% -> 11166.21
B42: Chocolate | D42: 2241 | E42: 2808 | F42: 3756 | G42: 4694 | H42: 6028 | I42: 12895 | J42: 24104 | K42: 26890 | L42: 38841 | M42: 42298 | N42: =SUM(BA42:BD42) -> 47324.84 | O42: =SUM(AU42:AX42) -> 53676.87 | P42: =SUM(AV42:AY42) -> 57397.86 | R42: 664 | S42: 643 | T42: 649 | U42: =+E42-SUM(R42:T42) -> 852 | V42: 910 | W42: 897 | X42: 885 | Y42: =+F42-SUM(V42:X42) -> 1064 | Z42: 1178 | AA42: 1143 | AB42: 1079 | AC42: =+G42-SUM(Z42:AB42) -> 1294 | AD42: 1354 | AE42: 1332 | AF42: 1383 | AG42: =+H42-SUM(AD42:AF42) -> 1959 | AH42: 2678 | AI42: 2819 | AJ42: 3164 | AK42: =+I42-SUM(AH42:AJ42) -> 4234 | AL42: 5048 | AN42: 4634 | AO42: 5584 | AP42: =+K42-SUM(AL42:AO42) -> 11624 | AQ42: =AQ44*54% -> 10265.4 | AR42: =AR44*52% -> 7541.56 | AS42: 8801.07 | AT42: =M42-SUM(AQ42:AS42) -> 15689.97 | AU42: =AU44*60% -> 15513.6 | AV42: =AV44*53% -> 11475.56 | AW42: =AW44*51% -> 12327.21 | AX42: =AX44*55% -> 14360.5 | AY42: =AY44*59% -> 19234.59 | BA42: =BA44*54% -> 10265.4 | BB42: =BB44*52% -> 10184.72 | BC42: =BC44*51% -> 11731.02 | BD42: =BD44*55% -> 15143.7 | BE42: =BE44*60% -> 20302.2
B43: Cake | D43: 446 | E43: 489 | F43: 575 | G43: 557 | H43: 771 | I43: 1988 | J43: 3741 | K43: 4264 | L43: 6143 | M43: 6435 | N43: =SUM(BA43:BD43) -> 7091 | O43: =SUM(AU43:AX43) -> 7761.69 | P43: =SUM(AV43:AY43) -> 8233.84 | R43: 120 | S43: 111 | T43: 123 | U43: =+E43-SUM(R43:T43) -> 135 | V43: 146 | W43: 130 | X43: 147 | Y43: =+F43-SUM(V43:X43) -> 152 | Z43: 148 | AA43: 103 | AB43: 140 | AC43: =+G43-SUM(Z43:AB43) -> 166 | AD43: 145 | AE43: 155 | AF43: 204 | AG43: =+H43-SUM(AD43:AF43) -> 267 | AH43: 369 | AI43: 420 | AJ43: 566 | AK43: =+I43-SUM(AH43:AJ43) -> 633 | AL43: 668 | AN43: 660 | AO43: 1005 | AP43: =+K43-SUM(AL43:AO43) -> 1931 | AQ43: =AQ44*7% -> 1330.7 | AR43: =AR44*9% -> 1305.27 | AS43: 1553.13 | AT43: =M43-SUM(AQ43:AS43) -> 2245.9 | AU43: =AU44*7% -> 1809.92 | AV43: =AV44*9% -> 1948.68 | AW43: =AW44*9% -> 2175.39 | AX43: =AX44*7% -> 1827.7 | AY43: =AY44*7% -> 2282.07 | BA43: =BA44*7% -> 1330.7 | BB43: =BB44*9% -> 1762.74 | BC43: =BC44*9% -> 2070.18 | BD43: =BD44*7% -> 1927.38 | BE43: =BE44*7% -> 2368.59
B44: Total | D44: =+D41+D42+D43 -> 4737 | E44: =+E41+E42+E43 -> 5922 | F44: =+F41+F42+F43 -> 7726 | G44: =+G41+G42+G43 -> 9400 | H44: =+H41+H42+H43 -> 12123 | I44: =+I41+I42+I43 -> 27006 | J44: =+J41+J42+J43 -> 49751 | K44: =+K41+K42+K43 -> 53504 | ... P44: =+P41+P42+P43 -> 104534 | R44: =+R41+R42+R43 -> 1402 | S44: =+S41+S42+S43 -> 1308 | T44: =+T41+T42+T43 -> 1432 | U44: =+U41+U42+U43 -> 1780 | V44: =+V41+V42+V43 -> 1930 | W44: =+W41+W42+W43 -> 1803 | X44: =+X41+X42+X43 -> 1877 | Y44: =+Y41+Y42+Y43 -> 2116 | ... AL44: =+AL41+AL42+AL43 -> 9840 | AN44: =+AN41+AN42+AN43 -> 9143 | AO44: =+AO41+AO42+AO43 -> 11882 | AP44: =+AP41+AP42+AP43 -> 22639 | AQ44: 19010 | AR44: 14503 | AS44: =+AS41+AS42+AS43 -> 17257 | AT44: =+AT41+AT42+AT43 -> 29246 | AU44: 25856 | AV44: 21652 | AW44: 24171 | AX44: 26110 | AY44: 32601 | BA44: 19010 | BB44: 19586 | BC44: 23002 | BD44: 27534 | BE44: 33837
B46: Market growth (Volume)
B47: Biscuits | E47: 0.022 | F47: -0.036 | G47: -0.002 | H47: -0.035 | I47: 0.001 | J47: 0.001 | K47: 0.01 | S47: 0.005 | T47: 0.022 | U47: 0.022 | V47: -0.026 | W47: -0.038 | X47: -0.031 | Y47: -0.036 | Z47: 0.015 | AA47: 0.034 | AB47: 0.003 | AC47: -0.002 | AD47: -0.103 | AE47: -0.082 | AF47: -0.051 | AG47: -0.035 | AH47: 0.036 | AI47: 0.052 | AJ47: -0.022 | AK47: -0.054 | AL47: -0.047 | AN47: =AN35/AI35-1 -> -0.02739726 | AO47: =AO35/AJ35-1 -> 0.0625 | AP47: =AP35/AK35-1 -> 0.048192771 | AQ47: =AQ35/AL35-1 -> 0.099879518 | AR47: =AR35/AN35-1 -> 0.01915493 | AT47: =AT35/AP35-1 -> 0.014712644 | AU47: =AU35/AQ35-1 -> -0.059480776 | AV47: =AV35/BB35-1 -> 0.12645108 | AW47: =AW35/BC35-1 -> 0.04879749 | AX47: =AX35/BD35-1 -> 0.011062689 | AY47: =AY35/BE35-1 -> 0.025157233 | BA47: =BA35/AL35-1 -> 0.099879518 | BB47: =BB35/AN35-1 -> 0.01915493 | BC47: =BC35/AO35-1 -> 0.012588235 | BD47: =BD35/AP35-1 -> 0.02862069 | BE47: =BE35/BA35-1 -> -0.059480776
B48: Chocolate | E48: 0.079 | F48: -0.032 | G48: 0.079 | H48: 0.024 | I48: 0.021 | J48: 0.021 | K48: 0.011 | S48: 0.069 | T48: 0.088 | U48: 0.079 | V48: -0.05 | W48: -0.049 | X48: -0.05 | Y48: -0.032 | Z48: 0.097 | AA48: 0.1 | AB48: 0.095 | AC48: 0.079 | AD48: -0.017 | AE48: -0.007 | AF48: 0.007 | AG48: 0.024 | AH48: 0.049 | AI48: 0.03 | AJ48: -0.009 | AK48: 0.014 | AL48: 0.002 | AN48: =AN36/AI36-1 -> -0.018867925 | AO48: =AO36/AJ36-1 -> 0.078431373 | AP48: =AP36/AK36-1 -> -0.016666667 | AQ48: =AQ36/AL36-1 -> 0.23448276 | AR48: =AR36/AN36-1 -> -0.072307692 | AT48: =AT36/AP36-1 -> -0.028305085 | AU48: =AU36/AQ36-1 -> -0.14022346 | AV48: =AV36/BB36-1 -> -0.021766169 | AW48: =AW36/BC36-1 -> -0.048163757 | AX48: =AX36/BD36-1 -> -0.063148317 | AY48: =AY36/BE36-1 -> -0.020305393 | BA48: =BA36/AL36-1 -> 0.23448276 | BB48: =BB36/AN36-1 -> -0.072307692 | BC48: =BC36/AO36-1 -> -0.094 | BD48: =BD36/AP36-1 -> -0.068644068 | BE48: =BE36/BA36-1 -> -0.14022346
B49: Cake | E49: 0.028 | F49: -0.096 | G49: -0.071 | H49: 0.051 | I49: 0.15 | J49: 0.15 | K49: 0.056 | S49: 0.032 | T49: 0.047 | U49: 0.028 | V49: -0.127 | W49: -0.13 | X49: -0.112 | Y49: -0.096 | Z49: 0.015 | AA49: -0.029 | AB49: -0.047 | AC49: -0.071 | AD49: -0.153 | AE49: -0.054 | AF49: -0.007 | AG49: 0.051 | AH49: 0.257 | AI49: 0.233 | AJ49: 0.142 | AK49: 0.015 | AL49: 0.012 | AN49: =AN37/AI37-1 -> -0.083333333 | AO49: =AO37/AJ37-1 -> 0.15384615 | AP49: =AP37/AK37-1 -> 0.15384615 | AQ49: =AQ37/AL37-1 -> 0.19333333 | AR49: =AR37/AN37-1 -> 0.21818182 | AT49: =AT37/AP37-1 -> -0.12133333 | AU49: =AU37/AQ37-1 -> 0.018156425 | AV49: =AV37/BB37-1 -> 0.067164179 | AW49: =AW37/BC37-1 -> 0.013245033 | AX49: =AX37/BD37-1 -> 0.11783439 | AY49: =AY37/BE37-1 -> 0.0061728395 | BA49: =BA37/AL37-1 -> 0.19333333 | BB49: =BB37/AN37-1 -> 0.21818182 | BC49: =BC37/AO37-1 -> 0.0066666667 | BD49: =BD37/AP37-1 -> -0.16266667 | BE49: =BE37/BA37-1 -> 0.018156425
B50: Total Confectionary | E50: 0.043 | F50: -0.035 | G50: 0.018 | H50: -0.004 | I50: 0.019 | J50: 0.019 | K50: 0.014 | S50: 0.032 | T50: 0.048 | U50: 0.043 | V50: -0.042 | W50: -0.044 | X50: -0.04 | Y50: -0.035 | Z50: 0.038 | AA50: 0.052 | AB50: 0.031 | AC50: 0.018 | AD50: -0.067 | AE50: -0.047 | AF50: -0.024 | AG50: -0.004 | AH50: 0.055 | AI50: 0.057 | AJ50: -0.004 | AK50: -0.023 | AL50: -0.025 | AN50: =AN38/AI38-1 -> -0.028985507 | AO50: =AO38/AJ38-1 -> 0.076388889 | AP50: =AP38/AK38-1 -> 0.032051282 | AQ50: =AQ38/AL38-1 -> 0.16993464 | AR50: =AR38/AN38-1 -> 0 | AT50: =AT38/AP38-1 -> -0.013726708 | AU50: =AU38/AQ38-1 -> -0.094972067 | AV50: =AV38/BB38-1 -> 0.067164179 | AW50: =AW38/BC38-1 -> 0.013245033 | AX50: =AX38/BD38-1 -> -0.0063694268 | AY50: =AY38/BE38-1 -> 0.0061728395 | BA50: =BA38/AL38-1 -> 0.16993464 | BB50: =BB38/AN38-1 -> 0 | BC50: =BC38/AO38-1 -> -0.025806452 | BD50: =BD38/AP38-1 -> -0.02484472 | BE50: =BE38/BA38-1 -> -0.094972067
B52: Market growth (Value)
B53: Biscuits | E53: 0.204 | F53: 0.248 | G53: 0.159 | H53: 0.217 | I53: 1.277 | J53: 1.277 | K53: 0.594 | S53: 0.141 | T53: 0.167 | U53: 0.204 | V53: 0.283 | W53: 0.28 | X53: 0.289 | Y53: 0.248 | Z53: 0.202 | AA53: 0.204 | AB53: 0.289 | AC53: 0.159 | AD53: 0.073 | AE53: 0.121 | AF53: 0.166 | AG53: 0.217 | AH53: 1.197 | AI53: 1.371 | AJ53: 1.553 | AK53: 1.07 | AL53: 0.576 | AN53: =AN41/AI41-1 -> 0.5383693 | AO53: =AO41/AJ41-1 -> 0.58094385 | AP53: =AP41/AK41-1 -> 1.4846827 | AQ53: =AQ41/AL41-1 -> 0.79774491 | AR53: =AR41/AN41-1 -> 0.46951676 | AT53: =AT41/AP41-1 -> 0.24506055 | AU53: =AU41/AQ41-1 -> 0.15087606 | AV53: =AV41/BB41-1 -> 0.077137778 | AW53: =AW41/BC41-1 -> 0.050821668 | AX53: =AX41/BD41-1 -> -0.051717876 | AY53: =AY41/BE41-1 -> -0.0073319416 | BA53: =BA41/AL41-1 -> 0.79774491 | BB53: =BB41/AN41-1 -> 0.98455183 | BC53: =BC41/AO41-1 -> 0.73829586 | BD53: =BD41/AP41-1 -> 0.15179657 | BE53: =BE41/BA41-1 -> 0.50611824
B54: Chocolate | E54: 0.221 | F54: 0.209 | G54: 0.268 | H54: 0.274 | I54: 1.139 | J54: 1.139 | K54: 0.717 | S54: 0.187 | T54: 0.217 | U54: 0.221 | V54: 0.21 | W54: 0.218 | X54: 0.217 | Y54: 0.209 | Z54: 0.277 | AA54: 0.281 | AB54: 0.274 | AC54: 0.268 | AD54: 0.209 | AE54: 0.216 | AF54: 0.23 | AG54: 0.274 | AH54: 0.979 | AI54: 1.116 | AJ54: 1.287 | AK54: 1.161 | AL54: 0.885 | AN54: =AN42/AI42-1 -> 0.64384534 | AO54: =AO42/AJ42-1 -> 0.76485461 | AP54: =AP42/AK42-1 -> 1.7453944 | AQ54: =AQ42/AL42-1 -> 1.0335578 | AR54: =AR42/AN42-1 -> 0.62744066 | AT54: =AT42/AP42-1 -> 0.34979095 | AU54: =AU42/AQ42-1 -> 0.51125139 | AV54: =AV42/BB42-1 -> 0.12674281 | AW54: =AW42/BC42-1 -> 0.050821668 | AX54: =AX42/BD42-1 -> -0.051717876 | AY54: =AY42/BE42-1 -> -0.052585927 | BA54: =BA42/AL42-1 -> 1.0335578 | BB54: =BB42/AN42-1 -> 1.1978248 | BC54: =BC42/AO42-1 -> 1.1008274 | BD54: =BD42/AP42-1 -> 0.30279594 | BE54: =BE42/BA42-1 -> 0.97773102
B55: Cake | E55: 0.211 | F55: 0.148 | G55: 0.069 | H55: 0.367 | I55: 1.58 | J55: 1.58 | K55: 0.745 | S55: 0.18 | T55: 0.197 | U55: 0.211 | V55: 0.167 | W55: 0.174 | X55: 0.178 | Y55: 0.148 | Z55: 0.114 | AA55: 0.065 | AB55: 0.061 | AC55: 0.069 | AD55: 0.108 | AE55: 0.226 | AF55: 0.284 | AG55: 0.367 | AH55: 1.54 | AI55: 1.709 | AJ55: 1.769 | AK55: 1.381 | AL55: 0.811 | AN55: =AN43/AI43-1 -> 0.57142857 | AO55: =AO43/AJ43-1 -> 0.77561837 | AP55: =AP43/AK43-1 -> 2.0505529 | AQ55: =AQ43/AL43-1 -> 0.99206587 | AR55: =AR43/AN43-1 -> 0.97768182 | AT55: =AT43/AP43-1 -> 0.16307613 | AU55: =AU43/AQ43-1 -> 0.36012625 | AV55: =AV43/BB43-1 -> 0.10548351 | AW55: =AW43/BC43-1 -> 0.050821668 | AX55: =AX43/BD43-1 -> -0.051717876 | AY55: =AY43/BE43-1 -> -0.036528061 | BA55: =BA43/AL43-1 -> 0.99206587 | BB55: =BB43/AN43-1 -> 1.6708182 | BC55: =BC43/AO43-1 -> 1.0598806 | BD55: =BD43/AP43-1 -> -0.0018746763 | BE55: =BE43/BA43-1 -> 0.77995792
B56: Total Confectionary | E56: 0.218 | F56: 0.205 | G56: 0.196 | H56: 0.265 | I56: 1.228 | J56: 1.228 | K56: 0.664 | S56: 0.167 | T56: 0.19 | U56: 0.218 | V56: 0.22 | W56: 0.223 | X56: 0.227 | Y56: 0.205 | Z56: 0.222 | AA56: 0.222 | AB56: 0.2 | AC56: 0.196 | AD56: 0.169 | AE56: 0.192 | AF56: 0.219 | AG56: 0.265 | AH56: 1.106 | AI56: 1.258 | AJ56: 1.441 | AK56: 1.135 | AL56: 0.737 | AN56: =AN44/AI44-1 -> 0.59257969 | AO56: =AO44/AJ44-1 -> 0.6787228 | AP56: =AP44/AK44-1 -> 1.6562243 | AQ56: =AQ44/AL44-1 -> 0.93191057 | AR56: =AR44/AN44-1 -> 0.58624084 | AT56: =AT44/AP44-1 -> 0.29184151 | AU56: =AU44/AQ44-1 -> 0.36012625 | AV56: =AV44/BB44-1 -> 0.10548351 | AW56: =AW44/BC44-1 -> 0.050821668 | AX56: =AX44/BD44-1 -> -0.051717876 | AY56: =AY44/BE44-1 -> -0.036528061 | BA56: =BA44/AL44-1 -> 0.93191057 | BB56: =BB44/AN44-1 -> 1.1421853 | BC56: =BC44/AO44-1 -> 0.93586938 | BD56: =BD44/AP44-1 -> 0.2162198 | BE56: =BE44/BA44-1 -> 0.77995792
