Workbook
Name IQ_CH: 110000
Name IQ_CQ: 5000
Name IQ_CY: 10000
Name IQ_DAILY: 500000
Name IQ_FH: 100000
Name IQ_FQ: 500
Name IQ_FY: 1000
Name IQ_LTM: 2000
Name IQ_MONTH: 15000
Name IQ_NTM: 6000
Name IQ_WEEK: 50000
Name IQ_YTD: 3000

Sheet Capitalization
A2: 1Q26 | I2: Exchange rate as at end | J2: =Model!$R$216 -> 0.24697456
I3: LTM Average exchange rate | J3: =Model!$R$217 -> 0.2404492
C5: Amount outstanding as on 31-Mar-2026 | D5: MYR (mn) | E5: USD (mn) | F5: Leverage (RM) | G5: Leverage (USD) | I5: Company reported | J5: =F5 -> Leverage (RM)
I6: Group Borrowings | J6: 15098
C7: Short-term debt | I7: Group Cash | J7: 3624
C8: Secured | D8: =Model!$BM$108 -> 91.315 | E8: =+D8*J2 -> 22.552482 | I8: Net debt / EBITDA | J8: 2.51x
C9: Unsecured | D9: =Model!$BM$109 -> 4621.096 | E9: =+D9*J2 -> 1141.2932
C10: Lease liabilities | D10: =Model!$BM$110 -> 325.305 | E10: =+D10*J2 -> 80.34206
C11: Long-term debt
C12: Secured | D12: =Model!$BM$113 -> 3653.265 | E12: =+D12*J2 -> 902.26352
C13: Unsecured | D13: =Model!$BM$114 -> 6732.13 | E13: =+D13*J2 -> 1662.6649
C14: Lease liabilities | D14: =Model!$BM$115 -> 1471.271 | E14: =+D14*J2 -> 363.36651
C15: Total Loans & Borrows | D15: =SUM(D8:D14) -> 16894.382 | E15: =SUM(E8:E14) -> 4172.4826 | F15: =+D15/D20 -> 3.8730008 | G15: =+E15/E20 -> 3.9781072
C16: Cash & Equivalents | D16: =Model!$BM$123 -> 2413.057 | E16: =+D16*J2 -> 595.96369
C17: Net debt | D17: =+D15-D16 -> 14481.325 | E17: =+E15-E16 -> 3576.5189 | F17: =+D17/D20 -> 3.3198127 | G17: =+E17/E20 -> 3.4099065
C18: Equity | D18: =Model!$BM$131 -> 23762.062 | E18: =+D18*J2 -> 5868.6248
C19: Total Capitalisation | D19: =D15+D18 -> 40656.444 | E19: =E15+E18 -> 10041.107 | F19: =D19/D20 -> 9.3204025 | G19: =E19/E20 -> 9.5733416
C20: LTM Adjusted EBITDA | D20: =Model!$BM$90 -> 4362.091 | E20: =D20*J3 -> 1048.8613
C21: check | D21: =+D15-Model!$BM$116 -> 0
C24: Liquidity Table at end-1Q26 | D24: =D5 -> MYR (mn) | E24: USD (mn)
C25: Deposits, cash and bank balances | D25: 3623.942 | E25: =D25*J2 -> 895.02149
C26: Less:
C27: Deposits pledged and restricted cash | D27: -173.115 | E27: =D27*J2 -> -42.755001
C28: Deposits maturing more than three (3) months | D28: -918.252 | E28: =D28*J2 -> -226.78489
C29: Bank overdraft | D29: -119.518 | E29: =D29*J2 -> -29.517906
C30: Total | D30: =SUM(D25:D29) -> 2413.057 | E30: =SUM(E25:E29) -> 595.96369
C33: Foreign currency borrowings and debt securities by currency at end-1Q26 | D33: =D5 -> MYR (mn) | E33: USD (mn)
C34: USD | D34: 6971.698 | E34: =D34*J2 -> 1721.8321
C35: IDR | D35: 1945.09 | E35: =D35*J2 -> 480.38775
C36: BDT | D36: 118.83 | E36: =D36*J2 -> 29.347987
C37: LKR | D37: 748.527 | E37: =D37*J2 -> 184.86713
C38: PHP | D38: 1717.941 | E38: =D38*J2 -> 424.28773
C39: Others | D39: 14.596 | E39: =D39*J2 -> 3.6048407
C40: Total debt | D40: =SUM(D34:D39) -> 11516.682 | E40: =SUM(E34:E39) -> 2844.3275
C43: Debt maturity at end-1Q26 (from BBG) | D43: =D5 -> MYR (mn) | E43: USD (mn)
C44: 2027 | D44: 1531.7 | E44: =D44*J2 -> 378.29094
C45: 2028 | D45: 29.5 | E45: =D45*J2 -> 7.2857496
C46: 2029 | D46: 396.55 | E46: =D46*J2 -> 97.937762
C47: 2030 | D47: 1989.65 | E47: =D47*J2 -> 491.39294
C48: 2031+ | D48: =15056.88-SUM(D44:D47) -> 11109.48 | E48: =D48*J2 -> 2743.759
C49: Total | D49: =SUM(D44:D48) -> 15056.88 | E49: =SUM(E44:E48) -> 3718.6663
A54: 4Q25 | I54: Exchange rate as at end | J54: =Model!$R$216 -> 0.24697456
I55: LTM Average exchange rate | J55: =Model!$R$217 -> 0.2404492
C57: Amount outstanding as on 31-Dec-2025 | D57: MYR (mn) | E57: USD (mn) | F57: Leverage (RM) | G57: Leverage (USD) | I57: Company reported | J57: =F57 -> Leverage (RM)
I58: Group Borrowings | J58: 15052
C59: Short-term debt | I59: Group Cash | J59: 3747
C60: Secured | D60: =Model!$BL$108 -> 1752.382 | E60: =+D60*J54 -> 432.79378 | I60: Net debt | J60: =J58-J59 -> 11305
C61: Unsecured | D61: =Model!$BL$109 -> 4898.263 | E61: =+D61*J54 -> 1209.7464 | I61: Net debt / EBITDA | J61: =J60/D73 -> 2.0703448
C62: Lease liabilities | D62: =Model!$BL$110 -> 330.526 | E62: =+D62*J54 -> 81.631514
C63: Long-term debt
C64: Secured | D64: =Model!$BL$113 -> 2021.459 | E64: =+D64*J54 -> 499.24895
C65: Unsecured | D65: =Model!$BL$114 -> 6380.354 | E65: =+D65*J54 -> 1575.7851
C66: Lease liabilities | D66: =Model!$BL$115 -> 1471.579 | E66: =+D66*J54 -> 363.44258
C67: RCF Drawdown & other | D67: 0
C68: Total Loans & Borrows | D68: =SUM(D60:D67) -> 16854.563 | E68: =SUM(E60:E67) -> 4162.6483 | F68: =+D68/D73 -> 3.0866659 | G68: =+E68/E73 -> 3.1704325
C69: Cash & Equivalents | D69: =Model!$BL$123 -> 3746.781 | E69: =+D69*J54 -> 925.35959
C70: Net debt | D70: =+D68-D69 -> 13107.782 | E70: =+E68-E69 -> 3237.2887 | F70: =+D70/D73 -> 2.4004979 | G70: =+E70/E73 -> 2.4656431
C71: Equity | D71: =Model!$BL$131 -> 24068.415 | E71: =+D71*J54 -> 5944.2862
C72: Total Capitalisation | D72: =D68+D71 -> 40922.978 | E72: =E68+E71 -> 10106.935 | F72: =D72/D73 -> 7.4944429 | G72: =E72/E73 -> 7.6978287
C73: LTM Adjusted EBITDA | D73: =Model!$BL$90 -> 5460.443 | E73: =D73*J55 -> 1312.9591
C74: check | D74: =+D68-Model!$BL$116 -> 0
C76: Liquidity Table at end-FY25 | D76: =D57 -> MYR (mn) | E76: USD (mn)
C77: Cash and cash equivalents | D77: =D69 -> 3746.781 | E77: =D77*J54 -> 925.35959
C78: Total | D78: =SUM(D77:D77) -> 3746.781 | E78: =SUM(E77:E77) -> 925.35959
C81: Foreign currency borrowings and debt securities by currency at end-FY25 | D81: =D57 -> MYR (mn) | E81: USD (mn)
C82: USD | D82: 9046.417 | E82: =D82*J54 -> 2234.2349
C83: IDR | D83: 1723.919 | E83: =D83*J54 -> 425.76414
C84: BDT | D84: 0.665 | E84: =D84*J54 -> 0.16423808
C85: LKR | D85: 939.874 | E85: =D85*J54 -> 232.12497
C86: PHP | D86: 1760.057 | E86: =D86*J54 -> 434.68931
C87: Others | D87: 39.489 | E87: =D87*J54 -> 9.7527785
C88: Total debt | D88: =SUM(D82:D87) -> 13510.421 | E88: =SUM(E82:E87) -> 3336.7303
C91: Debt maturity at end-FY25 (from BBG) | D91: =D57 -> MYR (mn) | E91: USD (mn)
C92: 2026 | D92: 1946.28 | E92: =D92*J54 -> 480.68165
C93: 2027 | D93: 1560.13 | E93: =D93*J54 -> 385.31242
C94: 2028 | D94: 30.45 | E94: =D94*J54 -> 7.5203754
C95: 2029 | D95: 398.85 | E95: =D95*J54 -> 98.505804
C96: 2030 and thereafter | D96: =15172.79-SUM(D92:D95) -> 11237.08 | E96: =D96*J54 -> 2775.2729
C97: Total | D97: =SUM(D92:D96) -> 15172.79 | E97: =SUM(E92:E96) -> 3747.2932
A101: 3Q25 | I101: Exchange rate as at end 3Q25 | J101: =Model!$R$216 -> 0.24697456
I102: LTM Average exchange rate 3Q25 | J102: =Model!$R$217 -> 0.2404492
C104: Amount outstanding as on 30-Sep-2025 | D104: RM (mn) | E104: USD (mn) | F104: Leverage (RM) | G104: Leverage (USD) | I104: Company reported | J104: =F104 -> Leverage (RM)
I105: Group Borrowings | J105: 15762
C106: Short-term debt | I106: Group Cash | J106: 3676
C107: Secured | D107: =Model!$BK$108 -> 1724.973 | E107: =+D107*J101 -> 426.02445 | I107: Net debt | J107: =J105-J106 -> 12086
C108: Unsecured | D108: =Model!$BK$109 -> 3122.402 | E108: =+D108*J101 -> 771.15387 | I108: Net debt / EBITDA | J108: =J107/D120 -> 1.4758915
C109: Lease liabilities | D109: =Model!$BK$110 -> 326.012 | E109: =+D109*J101 -> 80.516671
C110: Long-term debt
C111: Secured | D111: =Model!$BK$113 -> 2238.642 | E111: =+D111*J101 -> 552.88763
C112: Unsecured | D112: =Model!$BK$114 -> 8675.93 | E112: =+D112*J101 -> 2142.734
C113: Lease liabilities | D113: =Model!$BK$115 -> 1391.374 | E113: =+D113*J101 -> 343.63398
C114: RCF Drawdown & other | D114: 0
C115: Total Loans & Borrows | D115: =SUM(D107:D114) -> 17479.333 | E115: =SUM(E107:E114) -> 4316.9506 | F115: =+D115/D120 -> 2.1345026 | G115: =+E115/E120 -> 2.1924292
C116: Cash & Equivalents | D116: =Model!$BK$123 -> 3676.121 | E116: =+D116*J101 -> 907.90837
C117: Net debt | D117: =+D115-D116 -> 13803.212 | E117: =+E115-E116 -> 3409.0422 | F117: =+D117/D120 -> 1.6855902 | G117: =+E117/E120 -> 1.7313341
C118: Equity | D118: =Model!$BK$131 -> 24607.75 | E118: =+D118*J101 -> 6077.4883
C119: Total Capitalisation | D119: =D115+D118 -> 42087.083 | E119: =E115+E118 -> 10394.439 | F119: =D119/D120 -> 5.1394975 | G119: =E119/E120 -> 5.2789743
C120: LTM Adjusted EBITDA | D120: =Model!$BK$90 -> 8188.949 | E120: =D120*J102 -> 1969.0262
C121: check | D121: =+D115-Model!$BK$116 -> 0
C123: Liquidity Table at end-3Q25 | D123: RM (mn) | E123: USD (mn)
...

Sheet Model
B2: Axiata | C2: Annual | D2: Annual | E2: Annual | F2: Annual | G2: Annual | H2: Annual | I2: Annual | J2: Annual | K2: Annual | L2: Annual | M2: Annual | N2: Annual | O2: Annual | P2: Annual | Q2: Annual | R2: LTM | T2: Quarterly | U2: Quarterly | V2: Quarterly | W2: Quarterly | X2: Quarterly | Y2: Quarterly | Z2: Quarterly | AA2: Quarterly | AB2: Quarterly | AC2: Quarterly | AD2: Quarterly | AE2: Quarterly | AF2: Quarterly | AG2: Quarterly | AH2: Quarterly | AI2: Quarterly | AJ2: Quarterly | AK2: Quarterly | AL2: Quarterly | AM2: Quarterly | AN2: Quarterly | AO2: Quarterly | AP2: Quarterly | AQ2: Quarterly | AR2: Quarterly | AS2: Quarterly | AT2: Quarterly | AU2: Quarterly | AV2: Quarterly | AW2: Quarterly | AX2: Quarterly | AY2: Quarterly | AZ2: Quarterly | BA2: Quarterly | BB2: Quarterly | BC2: Quarterly | BD2: Quarterly | BE2: Quarterly | BF2: Quarterly | BG2: Quarterly | BH2: Quarterly | BI2: Quarterly | BJ2: Quarterly | BK2: Quarterly | BL2: Quarterly | BM2: Quarterly | BO2: Quarterly | BP2: Quarterly | BQ2: Quarterly | BR2: Quarterly | BS2: Quarterly | BT2: Quarterly | BV2: 6M | BW2: 6M | BY2: 9M | BZ2: 9M | CB2: Quarterly | CC2: Quarterly
B3: (MYR millions) | C3: 42707 | D3: 43073 | E3: 43438 | F3: 43803 | G3: 44169 | H3: 44561 | I3: 44926 | J3: 44561 | K3: 44926 | L3: 44926 | M3: 45291 | N3: 45291 | O3: 45657 | P3: 45657 | Q3: 46022 | R3: =BM3 -> 46112 | T3: 43190 | U3: 43281 | V3: 43373 | W3: 43465 | X3: 43555 | Y3: 43646 | Z3: 43738 | AA3: 43830 | AB3: 43921 | AC3: 44012 | AD3: 44104 | AE3: 44196 | AF3: 44286 | AG3: 44377 | AH3: 44469 | AI3: 44561 | AJ3: 44286 | AK3: 44377 | AL3: 44469 | AM3: 44561 | AN3: 44651 | AO3: 44742 | AP3: 44834 | AQ3: 44926 | AR3: 44651 | AS3: 44742 | AT3: 44834 | AU3: 44926 | AV3: 44834 | AW3: 44926 | AX3: 45016 | AY3: 45016 | AZ3: 45107 | BA3: 45107 | BB3: 45199 | BC3: 45199 | BD3: 45291 | BE3: 45382 | BF3: 45473 | BG3: 45565 | BH3: 45657 | BI3: 45747 | BJ3: 45838 | BK3: 45930 | BL3: 46022 | BM3: 46112 | BO3: 45291 | BP3: 45382 | BQ3: 45473 | BR3: 45565 | BS3: 45657 | BT3: 45747 | BV3: 45473 | BW3: 45838 | BY3: 45565 | BZ3: 45930 | CB3: 45657 | CC3: 46022
C4: Act | D4: Act | E4: Act | F4: Act | G4: Act | H4: Act | I4: Act | J4: Act | K4: Act | L4: Act | M4: Act | N4: Act | O4: Act | P4: Act | Q4: Act | R4: Act | T4: Act | U4: Act | V4: Act | W4: Act | X4: Act | Y4: Act | Z4: Act | AA4: Act | AB4: Act | AC4: Act | AD4: Act | AE4: Act | AF4: Act | AG4: Act | AH4: Act | AI4: Act | AJ4: restated | AK4: restated | AL4: restated | AM4: restated | AN4: Act | AO4: Act | AP4: Act | AQ4: Act | AR4: Restated | AS4: Restated | AT4: Restated | AU4: Restated | AV4: Restated** | AW4: Restated | AX4: Act | AY4: Restated | AZ4: Act | BA4: Restated | BB4: Act | BC4: Restated | BE4: Act | BF4: Act | BG4: Act | BH4: Act | BI4: Act | BJ4: Act | BK4: Act | BL4: Act | BM4: Act | BO4: Act | BP4: Act | BQ4: Act | BR4: Act | BS4: Act | BT4: Act | BV4: Act | BW4: Act | BY4: Act | BZ4: Act | CB4: Act | CC4: Act
C5: FY | D5: FY | E5: FY | F5: FY | G5: FY | H5: FY | I5: FY | J5: FY | K5: FY | L5: FY | M5: FY | N5: FY | O5: FY | P5: FY | Q5: FY | R5: LTM | T5: Q1 | U5: Q2 | V5: Q3 | W5: Q4 | X5: Q1 | Y5: Q2 | Z5: Q3 | AA5: Q4 | AB5: Q1 | AC5: Q2 | AD5: Q3 | AE5: Q4 | AF5: Q1 | AG5: Q2 | AH5: Q3 | AI5: Q4 | AJ5: Q1 | AK5: Q2 | AL5: Q3 | AM5: Q4 | AN5: Q1 | AO5: Q2 | AP5: Q3 | AQ5: Q4 | AR5: Q1 | AS5: Q2 | AT5: Q3 | AU5: Q4 | AV5: Q3 | AW5: Q4 | AX5: Q1 | AY5: Q1 | AZ5: Q2 | BA5: Q2 | BB5: Q3 | BC5: Q3 | BD5: Q4 | BE5: Q1 | BF5: Q2 | BG5: Q3 | BH5: Q4 | BI5: Q1 | BJ5: Q2 | BK5: Q3 | BL5: Q4 | BM5: Q1 | BO5: Q4 | BP5: Q1 | BQ5: Q2 | BR5: Q3 | BS5: Q4 | BT5: Q1 | BV5: 6M | BW5: 6M | BY5: 9M | BZ5: 9M | CB5: Q4 | CC5: Q4
B6: INCOME STATEMENT | J6: Restated | K6: Restated | L6: Restated** | N6: Restated | P6: Restated | BO6: Restated | BP6: Restated | BQ6: Restated | BR6: Restated | BS6: Restated | BT6: Restated | BV6: Restated | BY6: Restated | CB6: Restated | CC6: Restated
B7: Operating revenue | C7: 21565.392 | D7: 24402.401 | E7: 23885.781 | F7: 24583.312 | G7: 24203.171 | H7: 25900.661 | I7: 27522 | J7: 19994.368 | K7: 21725.735 | L7: 20020.28 | M7: 22002.269 | N7: 22318.326 | O7: 22334.617 | P7: 12541.918 | Q7: 11757.997 | R7: =SUM(BJ7:BM7) -> 9468.961 | T7: 5748.249 | U7: 5867.065 | V7: 6003.472 | W7: =E7-V7-U7-T7 -> 6266.995 | X7: 5949.437 | Y7: 6153.614 | Z7: 6213.254 | AA7: =F7-Z7-Y7-X7 -> 6267.007 | AB7: 6036.584 | AC7: 5792.414 | AD7: 6111.657 | AE7: =G7-AD7-AC7-AB7 -> 6262.516 | AF7: 6064.019 | AG7: 6390.064 | AH7: 6542.963 | AI7: =H7-AH7-AG7-AF7 -> 6903.615 | AM7: 5336.465 | AN7: 6469.951 | AO7: 6704.257 | AP7: 7260.318 | AQ7: =I7-SUM(AN7:AP7) -> 7087.474 | AR7: 4983.89 | AS7: 5197.605 | AT7: 5709 | AU7: 5835 | AV7: 5367.383 | AW7: =L7-AR7-AS7-AV7 -> 4471.402 | AX7: 5378.716 | AY7: 4997.228 | AZ7: 5994.526 | BA7: 5592.159 | BB7: 6010 | BC7: 5695.697 | BD7: =M7-AZ7-AX7-BC7 -> 4933.33 | BE7: 5662.084 | BF7: 5755.766 | BG7: 5321.643 | BH7: =O7-SUM(BE7:BG7) -> 5595.124 | BI7: 5088.897 | BJ7: 2966.419 | BK7: 2920.48 | BL7: =Q7-SUM(BI7:BK7) -> 782.201 | BM7: 2799.861 | BO7: =N7-SUM(AY7,BA7,BC7) -> 6033.242 | BP7: 5739.043 | BQ7: 3319.636 | BR7: 3064.998 | BS7: =P7-SUM(BP7:BR7) -> 418.241 | BT7: 2891.857 | BV7: 6508.744 | BW7: 5858.276 | BY7: 9573.74 | BZ7: 8778.756 | CB7: =P7-BY7 -> 2968.178 | CC7: =Q7-BZ7 -> 2979.241
B8: % y-o-y growth | D8: =D7/C7-1 -> 0.13155379 | E8: =E7/D7-1 -> -0.021170868 | F8: =F7/E7-1 -> 0.029202771 | G8: =G7/E7-1 -> 0.013287822 | H8: =H7/F7-1 -> 0.053587124 | I8: =I7/H7-1 -> 0.062598364 | J8: =J7/G7-1 -> -0.17389469 | K8: =K7/J7-1 -> 0.086592735 | L8: =L7/J7-1 -> 0.0012959649 | M8: =M7/L7-1 -> 0.098999065 | N8: =N7/L7-1 -> 0.11478591 | O8: =O7/N7-1 -> 0.00072993826 | P8: =P7/N7-1 -> -0.43804396 | Q8: =Q7/P7-1 -> -0.062504076 | X8: =X7/T7-1 -> 0.034999876 | Y8: =Y7/U7-1 -> 0.048840263 | Z8: =Z7/V7-1 -> 0.034943446 | AA8: =AA7/W7-1 -> 1.9147933e-06 | AB8: =AB7/X7-1 -> 0.014647941 | AC8: =AC7/Y7-1 -> -0.058697214 | AD8: =AD7/Z7-1 -> -0.016351657 | AE8: =AE7/AA7-1 -> -0.00071661002 | ... AI8: =AI7/AE7-1 -> 0.10237084 | AM8: =AM7/AE7-1 -> -0.14787204 | AN8: =AN7/AF7-1 -> 0.066941083 | AO8: =AO7/AG7-1 -> 0.049168991 | AP8: =AP7/AH7-1 -> 0.10963764 | AQ8: =AQ7/AI7-1 -> 0.026632279 | AR8: =AR7/AF7-1 -> -0.17812098 | AS8: =AS7/AG7-1 -> -0.18661143 | AT8: =AT7/AH7-1 -> -0.12745953 | AU8: =AU7/AM7-1 -> 0.093420457 | AV8: =AV7/AH7-1 -> -0.17967089 | AW8: =AW7/AM7-1 -> -0.16210413 | AX8: =AX7/AR7-1 -> 0.079220448 | AY8: =AY7/AS7-1 -> -0.038551795 | AZ8: =AZ7/AS7-1 -> 0.15332466 | BA8: =BA7/AS7-1 -> 0.075910732 | BB8: =BB7/AT7-1 -> 0.052723769 | BC8: =BC7/AV7-1 -> 0.061168357 | BD8: =BD7/AW7-1 -> 0.1033072 | BE8: =BE7/AW7-1 -> 0.26628829 | BF8: =BF7/AX7-1 -> 0.070100373 | BG8: =BG7/BC7-1 -> -0.065673086 | BH8: =BH7/BO7-1 -> -0.072617342 | BI8: =BI7/BP7-1 -> -0.11328474 | BJ8: =BJ7/BQ7-1 -> -0.10640233 | BK8: =BK7/BR7-1 -> -0.047151091 | BL8: =BL7/BS7-1 -> 0.87021598 | BM8: =BM7/BT7-1 -> -0.031812085 | BO8: =BO7/AW7-1 -> 0.34929537 | BP8: =BP7/AY7-1 -> 0.1484453 | BQ8: =BQ7/BA7-1 -> -0.40637668 | BR8: =BR7/BC7-1 -> -0.46187482 | BS8: =BS7/BO7-1 -> -0.93067724 | BT8: =BT7/BP7-1 -> -0.49610815 | BW8: =BW7/BV7-1 -> -0.099937561 | BZ8: =BZ7/BY7-1 -> -0.083037977 | CC8: =CC7/CB7-1 -> 0.0037272023
B9: Depreciation, impairment and amortisation | C9: -5666.505 | D9: -5986.213 | E9: -7644.816 | F9: -7084.236 | G9: -8484.994 | H9: -8094.868 | I9: -7070.912 | J9: -6317.817 | K9: -7070.912 | L9: -7878.003 | M9: -7199.986 | N9: -8202.382 | O9: -7341.195 | P9: -3752.309 | Q9: -3893.444 | R9: =SUM(BJ9:BM9) -> -3007.488 | T9: -1393.211 | U9: -1489.038 | V9: -1511.446 | W9: =E9-V9-U9-T9 -> -3251.121 | X9: -1643.04 | Y9: -1706.761 | Z9: -1846.046 | AA9: =F9-Z9-Y9-X9 -> -1888.389 | AB9: -1848.469 | AC9: -1842.228 | AD9: -1762.142 | AE9: =G9-AD9-AC9-AB9 -> -3032.155 | AF9: -1974.973 | AG9: -1903.392 | AH9: -1983.974 | AI9: =H9-AH9-AG9-AF9 -> -2232.529 | AM9: -1636.167 | AN9: -1860.543 | AO9: -1879.377 | AP9: -2101.416 | AQ9: =I9-SUM(AN9:AP9) -> -1229.576 | AR9: -1608.352 | AS9: -1626.464 | AT9: -1680.506 | AU9: =K9-AR9-AS9-AT9 -> -2155.59 | AV9: -1680.506 | AW9: =L9-AR9-AS9-AV9 -> -2962.681 | AX9: -1812.906 | AY9: -1636.184 | AZ9: -2697.068 | BA9: -1814.368 | BB9: -1859.536 | BC9: -1859.536 | BD9: =M9-AZ9-AX9-BC9 -> -830.476 | BE9: -1916.817 | BF9: -1879.054 | BG9: -1818.854 | BH9: =O9-SUM(BE9:BG9) -> -1726.47 | BI9: -1658.463 | BJ9: -1133.367 | BK9: -1019.063 | BL9: =Q9-SUM(BI9:BK9) -> -82.551 | BM9: -772.507 | BO9: =N9-SUM(AY9,BA9,BC9) -> -2892.294 | BP9: -1897.248 | BQ9: -972.917 | BR9: -944.656 | BS9: =P9-SUM(BP9:BR9) -> 62.512 | BT9: -825.975 | BV9: -1956.151 | BW9: -1959.341 | BY9: -2900.808 | BZ9: -2978.404 | CB9: =P9-BY9 -> -851.501 | CC9: =Q9-BZ9 -> -915.04
B10: Impairment of goodwill | F10: 0 | G10: 0 | H10: 0 | I10: -4145.544 | J10: -340.029 | K10: -4145.544 | L10: 0 | M10: 0 | N10: 0 | O10: 0 | P10: 0 | Q10: 0 | R10: =SUM(BJ10:BM10) -> 0 | AB10: 0 | AC10: 0 | AD10: 0 | AE10: =G10-AD10-AC10-AB10 -> 0 | AF10: 0 | AG10: 0 | AH10: 0 | AI10: =H10-AH10-AG10-AF10 -> 0 | AM10: -338.44 | AN10: 0 | AO10: 0 | AP10: 0 | AQ10: =I10-SUM(AN10:AP10) -> -4145.544 | AR10: 0 | AS10: 0 | AT10: 0 | AU10: =K10-AR10-AS10-AT10 -> -4145.544 | AV10: 0 | AW10: =L10-AR10-AS10-AV10 -> 0 | AX10: 0 | AY10: 0 | AZ10: 0 | BA10: 0 | BB10: 0 | BC10: 0 | BD10: =M10-AZ10-AX10-BC10 -> 0 | BE10: 0 | BF10: 0 | BG10: 0 | BH10: =O10-SUM(BE10:BG10) -> 0 | BI10: 0 | BJ10: 0 | BK10: 0 | BL10: =Q10-SUM(BI10:BK10) -> 0 | BM10: 0 | BO10: =N10-SUM(AY10,BA10,BC10) -> 0 | BP10: 0 | BQ10: 0 | BR10: 0 | BS10: =P10-SUM(BP10:BR10) -> 0 | BT10: 0 | BV10: 0 | BW10: 0 | BY10: 0 | BZ10: 0 | CB10: =P10-BY10 -> 0 | CC10: =Q10-BZ10 -> 0
B11: Foreign exchange gains / (losses) | C11: -85.342 | D11: -191.563 | E11: 8.389 | F11: 5.421 | G11: -196.083 | H11: 58.239 | I11: -420.48 | J11: 58.05 | K11: -420.48 | L11: -388.816 | M11: 143.947 | N11: 47.984 | O11: -311.622 | P11: -195.976 | Q11: -274.503 | R11: =SUM(BJ11:BM11) -> -272.908 | T11: -106.444 | U11: 87.727 | V11: 38.593 | W11: =E11-V11-U11-T11 -> -11.487 | X11: 14.577 | Y11: 5.728 | Z11: 6.295 | AA11: =F11-Z11-Y11-X11 -> -21.179 | AB11: 65.594 | AC11: -6.237 | AD11: -116.412 | AE11: =G11-AD11-AC11-AB11 -> -139.028 | AF11: 72.199 | AG11: 0.011 | AH11: -4.807 | AI11: =H11-AH11-AG11-AF11 -> -9.164 | AM11: -9.858 | AN11: -241.227 | AO11: -175.399 | AP11: 77.356 | AQ11: =I11-SUM(AN11:AP11) -> -81.21 | AR11: -241.187 | AS11: -175.938 | AT11: 62.868 | AU11: =K11-AR11-AS11-AT11 -> -66.223 | AV11: 62.868 | AW11: =L11-AR11-AS11-AV11 -> -34.559 | AX11: 5.831 | AY11: 7.331 | AZ11: 161.552 | BA11: 193.448 | BB11: -12.171 | BC11: -12.171 | BD11: =M11-AZ11-AX11-BC11 -> -11.265 | BE11: 87.886 | BF11: -53.866 | BG11: -368.639 | BH11: =O11-SUM(BE11:BG11) -> 22.997 | BI11: -22.418 | BJ11: -181.799 | BK11: -0.389 | BL11: =Q11-SUM(BI11:BK11) -> -69.897 | BM11: -20.823 | BO11: =N11-SUM(AY11,BA11,BC11) -> -140.624 | BP11: 58.64 | BQ11: -50.578 | BR11: -378.359 | BS11: =P11-SUM(BP11:BR11) -> 174.321 | BT11: -22.145 | BV11: 41.09 | BW11: -203.944 | BY11: -337.268 | BZ11: -204.332 | CB11: =P11-BY11 -> 141.292 | CC11: =Q11-BZ11 -> -70.171
B12: Domestic interconnect and international outpayment | C12: -2096.123 | D12: -2700.723 | E12: -2408.317 | F12: -1980.257 | G12: -1822.171 | H12: -2199.93 | I12: -2148.369 | J12: -1972.088 | K12: -2148.369 | L12: -2227.676 | M12: -2479.354 | N12: -2497.542 | O12: -1953.594 | P12: -1513.718 | Q12: -1206.774 | R12: =SUM(BJ12:BM12) -> -1112.971 | T12: -602.404 | U12: -611.211 | V12: -600.128 | W12: =E12-V12-U12-T12 -> -594.574 | X12: -530.672 | Y12: -502.143 | Z12: -447.204 | AA12: =F12-Z12-Y12-X12 -> -500.238 | AB12: -416.564 | AC12: -417.555 | AD12: -460.999 | AE12: =G12-AD12-AC12-AB12 -> -527.053 | AF12: -417.174 | AG12: -528.876 | AH12: -573.079 | AI12: =H12-AH12-AG12-AF12 -> -680.801 | AM12: -612.062 | AN12: -525.369 | AO12: -538.513 | AP12: -668.257 | AQ12: =I12-SUM(AN12:AP12) -> -416.23 | AR12: -449.868 | AS12: -460.123 | AT12: -568.587 | AU12: =K12-AR12-AS12-AT12 -> -669.791 | AV12: -568.587 | AW12: =L12-AR12-AS12-AV12 -> -749.098 | AX12: -568.686 | AY12: -550.526 | AZ12: -638.854 | BA12: -624.037 | BB12: -666.2 | BC12: -666.2 | BD12: =M12-AZ12-AX12-BC12 -> -605.614 | BE12: -564.354 | BF12: -531.242 | BG12: -421.033 | BH12: =O12-SUM(BE12:BG12) -> -436.965 | BI12: -385.679 | BJ12: -331.558 | BK12: -300.323 | BL12: =Q12-SUM(BI12:BK12) -> -189.214 | BM12: -291.876 | BO12: =N12-SUM(AY12,BA12,BC12) -> -656.779 | BP12: -571.187 | BQ12: -374.752 | BR12: -357.617 | BS12: =P12-SUM(BP12:BR12) -> -210.162 | BT12: -330.493 | BV12: -808.575 | BW12: -662.051 | BY12: -1166.191 | BZ12: -962.374 | CB12: =P12-BY12 -> -347.527 | CC12: =Q12-BZ12 -> -244.4
B13: Marketing, Advertising and promotion | C13: -1817.599 | D13: -2108.755 | E13: -2147.698 | F13: -2001.47 | G13: -1892.272 | H13: -2192.658 | I13: -1862.175 | J13: -1858.864 | K13: -1862.175 | L13: -1757.81 | M13: -1774.327 | N13: -1774.327 | O13: -1537.456 | P13: -1007.41 | Q13: -866.55 | R13: =SUM(BJ13:BM13) -> -759.666 | T13: -550.88 | U13: -565.847 | V13: -506.784 | W13: =E13-V13-U13-T13 -> -524.187 | X13: -488.979 | Y13: -516.257 | Z13: -475.962 | AA13: =F13-Z13-Y13-X13 -> -520.272 | AB13: -497.362 | AC13: -412.348 | AD13: -440.084 | AE13: =G13-AD13-AC13-AB13 -> -542.478 | AF13: -482.756 | AG13: -567.573 | AH13: -566.023 | AI13: =H13-AH13-AG13-AF13 -> -576.306 | AM13: -503.799 | AN13: -537.348 | AO13: -534.164 | AP13: -529.778 | AQ13: =I13-SUM(AN13:AP13) -> -260.885 | AR13: -476.45 | AS13: -449.12 | AT13: -414.772 | AU13: =K13-AR13-AS13-AT13 -> -521.833 | AV13: -414.772 | AW13: =L13-AR13-AS13-AV13 -> -417.468 | AX13: -426.414 | AY13: -405.831 | AZ13: -471.13 | BA13: -450.452 | BB13: -461.877 | BC13: -461.877 | BD13: =M13-AZ13-AX13-BC13 -> -414.906 | BE13: -431.577 | BF13: -436.283 | BG13: -342.545 | BH13: =O13-SUM(BE13:BG13) -> -327.051 | BI13: -304.204 | BJ13: -215.964 | BK13: -214.027 | BL13: =Q13-SUM(BI13:BK13) -> -132.355 | BM13: -197.32 | BO13: =N13-SUM(AY13,BA13,BC13) -> -456.167 | BP13: -431.577 | BQ13: -294.253 | BR13: -215.615 | BS13: =P13-SUM(BP13:BR13) -> -65.965 | BT13: -213.264 | BV13: -583.817 | BW13: -429.227 | BY13: -799.433 | BZ13: -643.254 | CB13: =P13-BY13 -> -207.977 | CC13: =Q13-BZ13 -> -223.296
B14: Other operating costs | C14: -8074.312 | D14: -8455.866 | E14: -8927.499 | F14: -7406.798 | G14: -7305.59 | H14: -7963.233 | I14: -6328.825 | J14: -5685.331 | K14: -6328.825 | L14: -5747.014 | M14: -6128.716 | N14: -6135.272 | O14: -5958.757 | P14: -2949.727 | Q14: -2885.284 | R14: =SUM(BJ14:BM14) -> -2015.33 | T14: -2143.009 | U14: -2121.201 | V14: -2200.231 | W14: =E14-V14-U14-T14 -> -2463.058 | X14: -2005.522 | Y14: -1832.29 | Z14: -1942.82 | AA14: =F14-Z14-Y14-X14 -> -1626.166 | AB14: -1892.56 | AC14: -1870.242 | AD14: -1846.424 | AE14: =G14-AD14-AC14-AB14 -> -1696.364 | AF14: -1924.25 | AG14: -1930.334 | AH14: -1978.687 | AI14: =H14-AH14-AG14-AF14 -> -2129.962 | AM14: -1552.268 | AN14: -1983.515 | AO14: -2089.265 | AP14: -2223.552 | AQ14: =I14-SUM(AN14:AP14) -> -32.493 | AR14: -1417.339 | AS14: -1548.441 | AT14: -1623.2 | AU14: =K14-AR14-AS14-AT14 -> -1739.845 | AV14: -1623.2 | AW14: =L14-AR14-AS14-AV14 -> -1158.034 | AX14: -1507.643 | AY14: -1419.337 | AZ14: -1647.272 | BA14: -1530.464 | BB14: -1528.728 | BC14: -1528.728 | BD14: =M14-AZ14-AX14-BC14 -> -1445.073 | BE14: -1497.033 | BF14: -1513.985 | BG14: -1507.974 | BH14: =O14-SUM(BE14:BG14) -> -1439.765 | BI14: -1516.152 | BJ14: -638.985 | BK14: -687.212 | BL14: =Q14-SUM(BI14:BK14) -> -42.935 | BM14: -646.198 | BO14: =N14-SUM(AY14,BA14,BC14) -> -1656.743 | BP14: -1498.416 | BQ14: -783.627 | BR14: -746.352 | BS14: =P14-SUM(BP14:BR14) -> 78.668 | BT14: -797.215 | BV14: -1515.986 | BW14: -1436.201 | BY14: -2262.338 | BZ14: -2123.414 | CB14: =P14-BY14 -> -687.389 | CC14: =Q14-BZ14 -> -761.87
B15: Staff costs | C15: -1564.71 | D15: -1906.939 | E15: -2068.133 | F15: -2220.2 | G15: -2227.532 | H15: -2071.006 | I15: -1662.47 | J15: -1536.728 | K15: -1662.47 | L15: -1570.643 | M15: -1719.19 | N15: -1731.332 | O15: -1614.394 | P15: -1280.392 | Q15: -1305.327 | R15: =SUM(BJ15:BM15) -> -1187.499 | T15: -415.546 | U15: -525.638 | V15: -525.312 | W15: =E15-V15-U15-T15 -> -601.637 | X15: -502.496 | Y15: -632.397 | Z15: -545.591 | AA15: =F15-Z15-Y15-X15 -> -539.716 | AB15: -650.213 | AC15: -508.519 | AD15: -524.512 | AE15: =G15-AD15-AC15-AB15 -> -544.288 | AF15: -519.665 | AG15: -520.293 | AH15: -551.819 | AI15: =H15-AH15-AG15-AF15 -> -479.229 | AM15: -341.127 | AN15: -499.448 | AO15: -543.211 | AP15: -608.348 | AQ15: =I15-SUM(AN15:AP15) -> -11.463 | AR15: -374.89 | AS15: -395.351 | AT15: -420.163 | AU15: =K15-AR15-AS15-AT15 -> -472.066 | AV15: -420.163 | AW15: =L15-AR15-AS15-AV15 -> -380.239 | AX15: -432.436 | AY15: -410.339 | AZ15: -474.699 | BA15: -450.56 | BB15: -464.415 | BC15: -464.415 | BD15: =M15-AZ15-AX15-BC15 -> -347.64 | BE15: -409.489 | BF15: -423.423 | BG15: -384.29 | BH15: =O15-SUM(BE15:BG15) -> -397.192 | BI15: -401.625 | BJ15: -335.825 | BK15: -340.352 | BL15: =Q15-SUM(BI15:BK15) -> -227.525 | BM15: -283.797 | BO15: =N15-SUM(AY15,BA15,BC15) -> -406.018 | BP15: -412.804 | BQ15: -337.287 | BR15: -309.464 | BS15: =P15-SUM(BP15:BR15) -> -220.837 | BT15: -313.157 | BV15: -665.861 | BW15: -648.983 | BY15: -975.325 | BZ15: -989.335 | CB15: =P15-BY15 -> -305.067 | CC15: =Q15-BZ15 -> -315.992
B16: Impairment on receivables, net / provision for impairment on financial assets | C16: 0 | D16: 0 | E16: 0 | F16: -355.437 | G16: -298.731 | H16: -69.817 | I16: -127.251 | J16: -39.098 | K16: -127.251 | L16: -97.223 | M16: -271.81 | N16: -270.509 | O16: -141.172 | P16: -102.354 | Q16: -33.619 | R16: =SUM(BJ16:BM16) -> -31.404 | T16: 0 | U16: 0 | V16: 0 | W16: =E16-V16-U16-T16 -> 0 | X16: 0 | Y16: 0 | Z16: 0 | AA16: =F16-Z16-Y16-X16 -> -355.437 | AB16: -75.992 | AC16: 0 | AD16: 0 | AE16: =G16-AD16-AC16-AB16 -> -222.739 | AF16: -28.319 | AG16: -32.12 | AH16: -13.969 | AI16: =H16-AH16-AG16-AF16 -> 4.591 | AM16: -5.354 | AN16: -25.808 | AO16: 11.532 | AP16: -26.776 | AQ16: =I16-SUM(AN16:AP16) -> -86.199 | AR16: -19.064 | AS16: -14.9 | AT16: -32.893 | AU16: =K16-AR16-AS16-AT16 -> -60.394 | AV16: -32.893 | AW16: =L16-AR16-AS16-AV16 -> -30.366 | AX16: -26.806 | AY16: -27.921 | AZ16: -33.798 | BA16: -33.461 | BB16: -36.469 | BC16: -36.469 | BD16: =M16-AZ16-AX16-BC16 -> -174.737 | BE16: -22.762 | BF16: -25.634 | BG16: -31.013 | BH16: =O16-SUM(BE16:BG16) -> -61.763 | BI16: -27.021 | BJ16: -4.039 | BK16: -16.146 | BL16: =Q16-SUM(BI16:BK16) -> 13.587 | BM16: -24.806 | BO16: =N16-SUM(AY16,BA16,BC16) -> -172.658 | BP16: -21.513 | BQ16: -16.706 | BR16: -22.098 | BS16: =P16-SUM(BP16:BR16) -> -42.037 | BT16: -18.559 | BV16: -28.755 | BW16: -22.599 | BY16: -50.853 | BZ16: -38.744 | CB16: =P16-BY16 -> -51.501 | CC16: =Q16-BZ16 -> 5.125
B17: Other gains/(losses) - net | C17: -68.161 | D17: -57.655 | E17: -25.242 | F17: -22.601 | G17: 2.693 | H17: 52.034 | I17: 28.225 | J17: 17.026 | K17: 28.225 | L17: 5.348 | M17: -5.342 | N17: -5.342 | O17: -0.852 | P17: -0.852 | Q17: 6.075 | R17: =SUM(BJ17:BM17) -> 5.252 | T17: 20.262 | U17: 49.509 | V17: 27.674 | W17: =E17-V17-U17-T17 -> -122.687 | X17: -22.709 | Y17: -0.089 | Z17: -0.122 | AA17: =F17-Z17-Y17-X17 -> 0.319 | AB17: 0.566 | AC17: 0.61 | AD17: 0.778 | AE17: =G17-AD17-AC17-AB17 -> 0.739 | AF17: 16.202 | AG17: 6.495 | AH17: 41.723 | AI17: =H17-AH17-AG17-AF17 -> -12.386 | AM17: -12.383 | AN17: 11.509 | AO17: 8.756 | AP17: 5.016 | AQ17: =I17-SUM(AN17:AP17) -> 2.944 | AR17: 11.511 | AS17: 8.756 | AT17: -2.315 | AU17: =K17-AR17-AS17-AT17 -> 10.273 | AV17: -2.315 | AW17: =L17-AR17-AS17-AV17 -> -12.604 | AX17: 6.31 | AY17: -1.247 | AZ17: 6.801 | BA17: 1.58 | BB17: 0.132 | BC17: 0.132 | BD17: =M17-AZ17-AX17-BC17 -> -18.585 | BE17: 2.463 | BF17: -0.829 | BG17: 2.007 | BH17: =O17-SUM(BE17:BG17) -> -4.493 | BI17: 2.525 | BJ17: 1.214 | BK17: 1.862 | BL17: =Q17-SUM(BI17:BK17) -> 0.474 | BM17: 1.702 | BO17: =N17-SUM(AY17,BA17,BC17) -> -5.807 | BP17: 2.463 | BQ17: -0.829 | BR17: 2.007 | BS17: =P17-SUM(BP17:BR17) -> -4.493 | BT17: 2.525 | BV17: 1.634 | BW17: 3.74 | BY17: 3.642 | BZ17: 5.601 | CB17: =P17-BY17 -> -4.494 | CC17: =Q17-BZ17 -> 0.474
B18: Other operating income (expenses)- net | C18: 534.566 | D18: 5.37 | E18: -3057.592 | F18: 714.392 | G18: 516.393 | H18: 398.655 | I18: -33.426 | J18: 107.224 | K18: -33.426 | L18: -0.104 | M18: 91.067 | N18: 96.547 | O18: 80.506 | P18: -6.461 | Q18: -2.545 | R18: =SUM(BJ18:BM18) -> -21.78 | T18: 57.774 | U18: -3273.839 | V18: 103.168 | W18: =E18-V18-U18-T18 -> 55.305 | X18: 460.57 | Y18: 145.435 | Z18: 36.168 | AA18: =F18-Z18-Y18-X18 -> 72.219 | AB18: 414.556 | AC18: 10.989 | AD18: 43.671 | AE18: =G18-AD18-AC18-AB18 -> 47.177 | AF18: 69.565 | AG18: 34.565 | AH18: 135.243 | AI18: =H18-AH18-AG18-AF18 -> 159.282 | AM18: 25.195 | AN18: 46.035 | AO18: 22.599 | AP18: -29.547 | AQ18: =I18-SUM(AN18:AP18) -> -72.513 | AR18: 30.184 | AS18: -2.4 | AT18: -82.776 | AU18: =K18-AR18-AS18-AT18 -> 21.566 | AV18: -82.776 | AW18: =L18-AR18-AS18-AV18 -> 54.888 | AX18: 10.993 | AY18: 10.402 | AZ18: -407.09 | BA18: -9.845 | BB18: 26.571 | BC18: 26.571 | BD18: =M18-AZ18-AX18-BC18 -> 460.593 | BE18: 26.161 | BF18: -6.682 | BG18: 12.569 | BH18: =O18-SUM(BE18:BG18) -> 48.458 | BI18: 14.794 | BJ18: 5.903 | BK18: -45.964 | BL18: =Q18-SUM(BI18:BK18) -> 22.722 | BM18: -4.441 | BO18: =N18-SUM(AY18,BA18,BC18) -> 69.419 | BP18: 29.894 | BQ18: -38.019 | BR18: -9.311 | BS18: =P18-SUM(BP18:BR18) -> 10.975 | BT18: 8.492 | BV18: -49.523 | BW18: 14.394 | BY18: -58.829 | BZ18: -31.569 | CB18: =P18-BY18 -> 52.368 | CC18: =Q18-BZ18 -> 29.024
B19: Operating Profit | C19: =C7+SUM(C9:C18) -> 2727.206 | D19: =D7+SUM(D9:D18) -> 3000.057 | E19: =E7+SUM(E9:E18) -> -2385.127 | F19: =F7+SUM(F9:F18) -> 4232.126 | G19: =G7+SUM(G9:G18) -> 2494.884 | H19: =H7+SUM(H9:H18) -> 3818.077 | I19: =I7+SUM(I9:I18) -> 3750.773 | J19: =J7+SUM(J9:J18) -> 2426.713 | ... R19: =R7+SUM(R9:R18) -> 1065.167 | T19: =T7+SUM(T9:T18) -> 614.791 | U19: =U7+SUM(U9:U18) -> -2582.473 | V19: =V7+SUM(V9:V18) -> 829.006 | W19: =W7+SUM(W9:W18) -> -1246.451 | X19: =X7+SUM(X9:X18) -> 1231.166 | Y19: =Y7+SUM(Y9:Y18) -> 1114.84 | Z19: =Z7+SUM(Z9:Z18) -> 997.972 | AA19: =AA7+SUM(AA9:AA18) -> 888.148 | ... AI19: =AI7+SUM(AI9:AI18) -> 947.111 | AM19: =AM7+SUM(AM9:AM18) -> 350.202 | AN19: =AN7+SUM(AN9:AN18) -> 854.237 | AO19: =AO7+SUM(AO9:AO18) -> 987.215 | AP19: =AP7+SUM(AP9:AP18) -> 1155.016 | AQ19: =AQ7+SUM(AQ9:AQ18) -> 754.305 | AR19: =AR7+SUM(AR9:AR18) -> 438.435 | AS19: =AS7+SUM(AS9:AS18) -> 533.624 | AT19: =AT7+SUM(AT9:AT18) -> 946.656 | ... BM19: =BM7+SUM(BM9:BM18) -> 559.795 | BO19: =BO7+SUM(BO9:BO18) -> -284.429 | BP19: =BP7+SUM(BP9:BP18) -> 997.295 | BQ19: =BQ7+SUM(BQ9:BQ18) -> 450.668 | BR19: =BR7+SUM(BR9:BR18) -> 83.533 | BS19: =BS7+SUM(BS9:BS18) -> 201.223 | BT19: =BT7+SUM(BT9:BT18) -> 382.066 | BV19: =BV7+SUM(BV9:BV18) -> 942.8 | BW19: =BW7+SUM(BW9:BW18) -> 514.064 | BY19: =BY7+SUM(BY9:BY18) -> 1026.337 | BZ19: =BZ7+SUM(BZ9:BZ18) -> 812.931 | CB19: =CB7+SUM(CB9:CB18) -> 706.382 | CC19: =CC7+SUM(CC9:CC18) -> 483.095
B20: Finance Income | C20: 183.394 | D20: 241.807 | E20: 221.459 | F20: 230.468 | G20: 177.183 | H20: 150.982 | I20: 255.274 | J20: 179.684 | K20: 255.274 | L20: 223.805 | M20: 248.363 | N20: 287.17 | O20: 265.646 | P20: 176.326 | Q20: 169.717 | R20: =SUM(BJ20:BM20) -> 138.061 | T20: 61.299 | U20: 53.411 | V20: 50.768 | W20: =E20-V20-U20-T20 -> 55.981 | X20: 56.381 | Y20: 55.022 | Z20: 65.886 | AA20: =F20-Z20-Y20-X20 -> 53.179 | AB20: 42.137 | AC20: 48.1 | AD20: 46.917 | AE20: =G20-AD20-AC20-AB20 -> 40.029 | AF20: 34.469 | AG20: 37.003 | AH20: 39.153 | AI20: =H20-AH20-AG20-AF20 -> 40.357 | AM20: 48.56 | AN20: 36.735 | AO20: 43.721 | AP20: 58.39 | AQ20: =I20-SUM(AN20:AP20) -> 116.428 | AR20: 44.836 | AS20: 51.611 | AT20: 57.349 | AU20: =K20-AR20-AS20-AT20 -> 101.478 | AV20: 57.349 | AW20: =L20-AR20-AS20-AV20 -> 70.009 | AX20: 83.871 | AY20: 69.662 | AZ20: 76.942 | BA20: 62.383 | BB20: 69.595 | BC20: 69.595 | BD20: =M20-AZ20-AX20-BC20 -> 17.955 | BE20: 57.936 | BF20: 41.635 | BG20: 55.01 | BH20: =O20-SUM(BE20:BG20) -> 111.065 | BI20: 66.343 | BJ20: 49.339 | BK20: 43.11 | BL20: =Q20-SUM(BI20:BK20) -> 10.925 | BM20: 34.687 | BO20: =N20-SUM(AY20,BA20,BC20) -> 85.53 | BP20: 72.159 | BQ20: 36.79 | BR20: 47.809 | BS20: =P20-SUM(BP20:BR20) -> 19.568 | BT20: 36.851 | BV20: 89.993 | BW20: 86.191 | BY20: 137.802 | BZ20: 129.302 | CB20: =P20-BY20 -> 38.524 | CC20: =Q20-BZ20 -> 40.415
B21: Finance cost excluding net foreign exchange gains / (losses) on financing activities | C21: -1201.184 | D21: -1253.369 | E21: -1272.385 | F21: -1738.473 | G21: -1693.067 | H21: -1565.069 | I21: -1827.015 | J21: -1411.448 | K21: -1827.015 | L21: -1702.229 | M21: -2287.869 | N21: -2296.617 | O21: -2345.021 | P21: -1419.573 | Q21: -1248.83 | R21: =SUM(BJ21:BM21) -> -985.55 | T21: -302.522 | U21: -314.951 | V21: -323.633 | W21: =E21-V21-U21-T21 -> -331.279 | X21: -408.922 | Y21: -464.566 | Z21: -435.309 | AA21: =F21-Z21-Y21-X21 -> -429.676 | AB21: -426.235 | AC21: -427.087 | AD21: -429.448 | AE21: =G21-AD21-AC21-AB21 -> -410.297 | AF21: -362.309 | AG21: -376.835 | AH21: -379.092 | AI21: =H21-AH21-AG21-AF21 -> -446.833 | AM21: -412.488 | AN21: -403.26 | AO21: -434.955 | AP21: -522.555 | AQ21: =I21-SUM(AN21:AP21) -> -466.245 | AR21: -368.691 | AS21: -400.709 | AT21: -461.635 | AU21: =K21-AR21-AS21-AT21 -> -595.98 | AV21: -461.635 | AW21: =L21-AR21-AS21-AV21 -> -471.194 | AX21: -536.918 | AY21: -509.642 | AZ21: -721.369 | BA21: -623.026 | BB21: -586.882 | BC21: -586.882 | BD21: =M21-AZ21-AX21-BC21 -> -442.7 | BE21: -602.031 | BF21: -602.966 | BG21: -562.216 | BH21: =O21-SUM(BE21:BG21) -> -577.808 | BI21: -526.709 | BJ21: -313.785 | BK21: -313.992 | BL21: =Q21-SUM(BI21:BK21) -> -94.344 | BM21: -263.429 | BO21: =N21-SUM(AY21,BA21,BC21) -> -577.067 | BP21: -604.321 | BQ21: -370.852 | BR21: -342.787 | BS21: =P21-SUM(BP21:BR21) -> -101.613 | BT21: -309.683 | BV21: -739.738 | BW21: -623.468 | BY21: -1082.526 | BZ21: -937.46 | CB21: =P21-BY21 -> -337.047 | CC21: =Q21-BZ21 -> -311.37
B22: Net foreign exchange gains/ (losses) on financing activities | C22: -599.72 | D22: 352 | E22: -208.689 | F22: 59.085 | G22: 173.395 | H22: -234.355 | I22: -564.533 | J22: -234.355 | K22: -564.533 | L22: -622.879 | M22: -357.443 | N22: -357.443 | O22: 330.737 | P22: 330.737 | Q22: 531.033 | R22: =SUM(BJ22:BM22) -> 606.499 | T22: 125.023 | U22: -202.014 | V22: -164.841 | W22: =E22-V22-U22-T22 -> 33.143 | X22: 115.433 | Y22: -48.264 | Z22: -55.538 | AA22: =F22-Z22-Y22-X22 -> 47.454 | AB22: -165.313 | AC22: 35.004 | AD22: 94.321 | AE22: =G22-AD22-AC22-AB22 -> 209.383 | AF22: -186.736 | AG22: -4.752 | AH22: -47.122 | AI22: =H22-AH22-AG22-AF22 -> 4.255 | AM22: 4.256 | AN22: -235.657 | AO22: -300.255 | AP22: -424.006 | AQ22: =I22-SUM(AN22:AP22) -> 395.385 | AR22: -235.657 | AS22: -300.255 | AT22: -424.006 | AU22: =K22-AR22-AS22-AT22 -> 395.385 | AV22: -424.006 | AW22: =L22-AR22-AS22-AV22 -> 337.039 | AX22: -19.402 | AY22: -19.402 | AZ22: -459.478 | BA22: -459.478 | BB22: -75.192 | BC22: -75.192 | BD22: =M22-AZ22-AX22-BC22 -> 196.629 | BE22: -196.601 | BF22: -18.36 | BG22: 1034.989 | BH22: =O22-SUM(BE22:BG22) -> -489.291 | BI22: 50.865 | BJ22: 306.708 | BK22: -5.966 | BL22: =Q22-SUM(BI22:BK22) -> 179.426 | BM22: 126.331 | BO22: =N22-SUM(AY22,BA22,BC22) -> 196.629 | BP22: -196.601 | BQ22: -18.36 | BR22: 1034.989 | BS22: =P22-SUM(BP22:BR22) -> -489.291 | BT22: 50.865 | BV22: -214.961 | BW22: 357.574 | BY22: 820.027 | BZ22: 351.607 | CB22: =P22-BY22 -> -489.29 | CC22: =Q22-BZ22 -> 179.426
B23: Joint ventures - share of tax (net taxes) | C23: -95.842 | D23: -48.989 | E23: 1.678 | F23: -2.819 | G23: -1.039 | H23: -7.706 | I23: -9.709 | J23: -7.706 | K23: -9.709 | L23: -9.709 | M23: 0.903 | N23: 0.903 | O23: 0.066 | P23: 0.066 | Q23: 0.008 | R23: =SUM(BJ23:BM23) -> 0.495 | T23: 0 | U23: 0.17 | V23: 1.082 | W23: =E23-V23-U23-T23 -> 0.426 | X23: -2.236 | Y23: -0.583 | Z23: 0 | AA23: =F23-Z23-Y23-X23 -> 0 | AB23: -1.936 | AC23: -2.037 | AD23: 2.358 | AE23: =G23-AD23-AC23-AB23 -> 0.576 | AF23: -0.188 | AG23: -1.529 | AH23: -4.802 | AI23: =H23-AH23-AG23-AF23 -> -1.187 | AM23: -1.187 | AN23: -1.986 | AO23: -2.334 | AP23: -3.621 | AQ23: =I23-SUM(AN23:AP23) -> -1.768 | AR23: -1.986 | AS23: -2.334 | AT23: -3.621 | AU23: =K23-AR23-AS23-AT23 -> -1.768 | AV23: -3.621 | AW23: =L23-AR23-AS23-AV23 -> -1.768 | AX23: 1.231 | AY23: 1.231 | AZ23: -0.812 | BA23: -0.812 | BB23: -0.57 | BC23: -0.57 | BD23: =M23-AZ23-AX23-BC23 -> 1.054 | BE23: 0.104 | BF23: 0.89 | BG23: -1.223 | BH23: =O23-SUM(BE23:BG23) -> 0.295 | BI23: -0.848 | BJ23: 0.2 | BK23: -0.191 | BL23: =Q23-SUM(BI23:BK23) -> 0.847 | BM23: -0.361 | BO23: =N23-SUM(AY23,BA23,BC23) -> 1.054 | BP23: 0.104 | BQ23: 0.89 | BR23: -1.223 | BS23: =P23-SUM(BP23:BR23) -> 0.295 | BT23: -0.848 | BV23: 0.994 | BW23: -0.648 | BY23: -0.23 | BZ23: -0.839 | CB23: =P23-BY23 -> 0.296 | CC23: =Q23-BZ23 -> 0.847
B24: Associates - share of tax (net of tax) | C24: 131.124 | D24: -352.67 | E24: -26.364 | F24: -0.647 | G24: 19.761 | H24: 11.689 | I24: -56.817 | J24: -1.663 | K24: -56.817 | L24: -56.817 | M24: 530.743 | N24: 530.743 | O24: 450.865 | P24: 454.179 | Q24: 19.342 | R24: =SUM(BJ24:BM24) -> 4.626 | T24: -86.074 | U24: 46.569 | V24: 3.069 | W24: =E24-V24-U24-T24 -> 10.072 | X24: 1.082 | Y24: -2.515 | Z24: 0.778 | AA24: =F24-Z24-Y24-X24 -> 0.008 | AB24: 7.903 | AC24: 4.946 | AD24: 4.792 | AE24: =G24-AD24-AC24-AB24 -> 2.12 | AF24: 1.884 | AG24: 2.161 | AH24: 2.576 | AI24: =H24-AH24-AG24-AF24 -> 5.068 | AM24: -0.336 | AN24: 3.151 | AO24: -6.643 | AP24: 5.36 | AQ24: =I24-SUM(AN24:AP24) -> -58.685 | AR24: -0.799 | AS24: -10.78 | AT24: 0.08 | AU24: =K24-AR24-AS24-AT24 -> -45.318 | AV24: 0.08 | AW24: =L24-AR24-AS24-AV24 -> -45.318 | AX24: 113.294 | AY24: 113.294 | AZ24: 107.114 | BA24: 107.114 | BB24: 143.658 | BC24: 143.658 | BD24: =M24-AZ24-AX24-BC24 -> 166.677 | BE24: 106.25 | BF24: 144.813 | BG24: 138.666 | BH24: =O24-SUM(BE24:BG24) -> 61.136 | BI24: 76.229 | BJ24: 51.363 | BK24: -27.719 | BL24: =Q24-SUM(BI24:BK24) -> -80.531 | BM24: 61.513 | BO24: =N24-SUM(AY24,BA24,BC24) -> 166.677 | BP24: 106.25 | BQ24: 145.109 | BR24: 140.263 | BS24: =P24-SUM(BP24:BR24) -> 62.557 | BT24: 81.242 | BV24: 255.239 | BW24: 132.605 | BY24: 395.502 | BZ24: 104.885 | CB24: =P24-BY24 -> 58.677 | CC24: =Q24-BZ24 -> -85.543
B25: Associates - gain/ (loss) on dilution of equity interest | C25: -5.398 | D25: -2.595 | E25: -403.712 | F25: 0 | G25: 0 | H25: 0 | I25: 0 | J25: 0 | K25: 0 | L25: 0 | M25: 0.11 | N25: 0.11 | O25: 0 | P25: 0 | Q25: 53.178 | R25: =SUM(BJ25:BM25) -> 53.178 | T25: -357.604 | U25: -45.384 | V25: 0 | W25: =E25-V25-U25-T25 -> -0.724 | X25: 0 | Y25: 0 | Z25: 0 | AA25: =F25-Z25-Y25-X25 -> 0 | AB25: 0 | AC25: 0 | AD25: 0 | AE25: =G25-AD25-AC25-AB25 -> 0 | AF25: 0 | AG25: 0 | AH25: 0 | AI25: =H25-AH25-AG25-AF25 -> 0 | AM25: 0 | AN25: 0 | AO25: 0 | AP25: 0 | AQ25: =I25-SUM(AN25:AP25) -> 0 | AR25: 0 | AS25: 0 | AT25: 0 | AU25: =K25-AR25-AS25-AT25 -> 0 | AV25: 0 | AW25: =L25-AR25-AS25-AV25 -> 0 | AX25: 0 | AY25: 0 | AZ25: 0 | BA25: 0 | BB25: 0 | BC25: 0 | BD25: =M25-AZ25-AX25-BC25 -> 0.11 | BE25: 0 | BF25: 0 | BG25: 0 | BH25: =O25-SUM(BE25:BG25) -> 0 | BI25: 0 | BJ25: 0 | BK25: 0 | BL25: =Q25-SUM(BI25:BK25) -> 53.178 | BM25: 0 | BO25: =N25-SUM(AY25,BA25,BC25) -> 0.11 | BP25: 0 | BQ25: 0 | BR25: 0 | BS25: =P25-SUM(BP25:BR25) -> 0 | BT25: 0 | BV25: 0 | BW25: 0 | BY25: 0 | BZ25: 0 | CB25: =P25-BY25 -> 0 | CC25: =Q25-BZ25 -> 53.178
B26: Gain on early redemption of debt | N26: 0 | O26: 306.101 | P26: 306.101 | Q26: 175.129 | R26: =SUM(BJ26:BM26) -> 175.129 | BE26: 0 | BF26: 0 | BG26: 306.101 | BH26: =O26-SUM(BE26:BG26) -> 0 | BI26: 0 | BJ26: 0 | BK26: 175.129 | BL26: =Q26-SUM(BI26:BK26) -> 0 | BM26: 0 | BO26: =N26-SUM(AY26,BA26,BC26) -> 0 | BP26: 0 | BQ26: 0 | BR26: 306.101 | BS26: =P26-SUM(BP26:BR26) -> 0 | BT26: 0 | BV26: 0 | BW26: 0 | BY26: 306.101 | BZ26: 175.129 | CB26: =P26-BY26 -> 0 | CC26: =Q26-BZ26 -> 0
B27: Profit before tax | C27: =SUM(C19,C20,C21,C22,C23,C24,C25,C26) -> 1139.58 | D27: =SUM(D19,D20,D21,D22,D23,D24,D25,D26) -> 1936.241 | E27: =SUM(E19,E20,E21,E22,E23,E24,E25,E26) -> -4073.14 | F27: =SUM(F19,F20,F21,F22,F23,F24,F25,F26) -> 2779.74 | G27: =SUM(G19,G20,G21,G22,G23,G24,G25,G26) -> 1171.117 | H27: =SUM(H19,H20,H21,H22,H23,H24,H25,H26) -> 2173.618 | I27: =SUM(I19,I20,I21,I22,I23,I24,I25,I26) -> 1547.973 | J27: =SUM(J19,J20,J21,J22,J23,J24,J25,J26) -> 951.225 | ... R27: =SUM(R19,R20,R21,R22,R23,R24,R25,R26) -> 1057.605 | T27: =SUM(T19,T20,T21,T22,T23,T24,T25) -> 54.913 | U27: =SUM(U19,U20,U21,U22,U23,U24,U25) -> -3044.672 | V27: =SUM(V19,V20,V21,V22,V23,V24,V25) -> 395.451 | W27: =SUM(W19,W20,W21,W22,W23,W24,W25) -> -1478.832 | X27: =SUM(X19,X20,X21,X22,X23,X24,X25) -> 992.904 | Y27: =SUM(Y19,Y20,Y21,Y22,Y23,Y24,Y25) -> 653.934 | Z27: =SUM(Z19,Z20,Z21,Z22,Z23,Z24,Z25) -> 573.789 | AA27: =SUM(AA19,AA20,AA21,AA22,AA23,AA24,AA25) -> 559.113 | ... AI27: =SUM(AI19,AI20,AI21,AI22,AI23,AI24,AI25) -> 548.771 | AM27: =SUM(AM19,AM20,AM21,AM22,AM23,AM24,AM25) -> -10.993 | AN27: =SUM(AN19,AN20,AN21,AN22,AN23,AN24,AN25) -> 253.22 | AO27: =SUM(AO19,AO20,AO21,AO22,AO23,AO24,AO25) -> 286.749 | AP27: =SUM(AP19,AP20,AP21,AP22,AP23,AP24,AP25) -> 268.584 | AQ27: =SUM(AQ19,AQ20,AQ21,AQ22,AQ23,AQ24,AQ25) -> 739.42 | AR27: =SUM(AR19,AR20,AR21,AR22,AR23,AR24,AR25) -> -123.862 | AS27: =SUM(AS19,AS20,AS21,AS22,AS23,AS24,AS25) -> -128.843 | AT27: =SUM(AT19,AT20,AT21,AT22,AT23,AT24,AT25) -> 114.823 | ... AW27: =SUM(AW19,AW20,AW21,AW22,AW23,AW24,AW25) -> -1329.991 | AX27: =SUM(AX19,AX20,AX21,AX22,AX23,AX24,AX25,AX26) -> 269.035 | AY27: =SUM(AY19,AY20,AY21,AY22,AY23,AY24,AY25,AY26) -> 218.719 | AZ27: =SUM(AZ19,AZ20,AZ21,AZ22,AZ23,AZ24,AZ25,AZ26) -> -1204.635 | BA27: =SUM(BA19,BA20,BA21,BA22,BA23,BA24,BA25,BA26) -> -39.819 | BB27: =SUM(BB19,BB20,BB21,BB22,BB23,BB24,BB25,BB26) -> 557.916 | BC27: =SUM(BC19,BC20,BC21,BC22,BC23,BC24,BC25,BC26) -> 243.613 | BD27: =SUM(BD19,BD20,BD21,BD22,BD23,BD24,BD25,BD26) -> 1485.352 | BE27: =SUM(BE19,BE20,BE21,BE22,BE23,BE24,BE25,BE26) -> 302.22 | ... BM27: =SUM(BM19,BM20,BM21,BM22,BM23,BM24,BM25,BM26) -> 518.536 | BO27: =SUM(BO19,BO20,BO21,BO22,BO23,BO24,BO25,BO26) -> -411.496 | BP27: =SUM(BP19,BP20,BP21,BP22,BP23,BP24,BP25,BP26) -> 374.886 | BQ27: =SUM(BQ19,BQ20,BQ21,BQ22,BQ23,BQ24,BQ25,BQ26) -> 244.245 | BR27: =SUM(BR19,BR20,BR21,BR22,BR23,BR24,BR25,BR26) -> 1268.685 | BS27: =SUM(BS19,BS20,BS21,BS22,BS23,BS24,BS25,BS26) -> -307.261 | BT27: =SUM(BT19,BT20,BT21,BT22,BT23,BT24,BT25,BT26) -> 240.493 | BV27: =SUM(BV19,BV20,BV21,BV22,BV23,BV24,BV25,BV26) -> 334.327 | BW27: =SUM(BW19,BW20,BW21,BW22,BW23,BW24,BW25,BW26) -> 466.318 | BY27: =SUM(BY19,BY20,BY21,BY22,BY23,BY24,BY25,BY26) -> 1603.013 | BZ27: =SUM(BZ19,BZ20,BZ21,BZ22,BZ23,BZ24,BZ25,BZ26) -> 635.555 | CB27: =SUM(CB19,CB20,CB21,CB22,CB23,CB24,CB25,CB26) -> -22.458 | CC27: =SUM(CC19,CC20,CC21,CC22,CC23,CC24,CC25,CC26) -> 360.048
B28: Income tax benefit/(expense) | C28: -482.422 | D28: -773.749 | E28: -901.552 | F28: -964.644 | G28: -547.072 | H28: -896.737 | I28: -614.666 | J28: -643.69 | K28: -614.666 | L28: -604.86 | M28: -651.168 | N28: -665.744 | O28: -965.616 | P28: -775.566 | Q28: -656.33 | R28: =SUM(BJ28:BM28) -> -639.04 | T28: -136.032 | U28: -259.477 | V28: -196.104 | W28: =E28-V28-U28-T28 -> -309.939 | X28: -193.078 | Y28: -349.972 | Z28: -266.624 | AA28: =F28-Z28-Y28-X28 -> -154.97 | AB28: -194.396 | AC28: -249.326 | AD28: -256.804 | AE28: =G28-AD28-AC28-AB28 -> 153.454 | AF28: -174.578 | AG28: -189.727 | AH28: -195.162 | AI28: =H28-AH28-AG28-AF28 -> -337.27 | AM28: -223.538 | AN28: -262.511 | AO28: -300.1 | AP28: -274.964 | AQ28: =I28-SUM(AN28:AP28) -> 222.909 | AR28: -146.152 | AS28: -178.311 | AT28: -145.071 | AU28: =K28-AR28-AS28-AT28 -> -145.132 | AV28: -145.071 | AW28: =L28-AR28-AS28-AV28 -> -135.326 | AX28: -127.101 | AY28: -116.358 | AZ28: 80.818 | BA28: -153.766 | BB28: -135.622 | BC28: -135.622 | BD28: =M28-AZ28-AX28-BC28 -> -469.263 | BE28: -167.262 | BF28: -249.265 | BG28: -289.505 | BH28: =O28-SUM(BE28:BG28) -> -259.584 | BI28: -148.042 | BJ28: -260.396 | BK28: -155.687 | BL28: =Q28-SUM(BI28:BK28) -> -92.205 | BM28: -130.752 | BO28: =N28-SUM(AY28,BA28,BC28) -> -259.998 | BP28: -173.207 | BQ28: -195.61 | BR28: -253.157 | BS28: =P28-SUM(BP28:BR28) -> -153.592 | BT28: -123.277 | BV28: -325.701 | BW28: -383.673 | BY28: -578.859 | BZ28: -539.36 | CB28: =P28-BY28 -> -196.707 | CC28: =Q28-BZ28 -> -116.97
B29: Profit / (Loss) for the financial period from continuing operations | C29: =+C27+C28 -> 657.158 | D29: =+D27+D28 -> 1162.492 | E29: =+E27+E28 -> -4974.692 | F29: =+F27+F28 -> 1815.096 | G29: =+G27+G28 -> 624.045 | H29: =+H27+H28 -> 1276.881 | I29: =+I27+I28 -> 933.307 | J29: =+J27+J28 -> 307.535 | ... R29: =+R27+R28 -> 418.565 | T29: =+T27+T28 -> -81.119 | U29: =+U27+U28 -> -3304.149 | V29: =+V27+V28 -> 199.347 | W29: =+W27+W28 -> -1788.771 | X29: =+X27+X28 -> 799.826 | Y29: =+Y27+Y28 -> 303.962 | Z29: =+Z27+Z28 -> 307.165 | AA29: =+AA27+AA28 -> 404.143 | ... AI29: =+AI27+AI28 -> 211.501 | AM29: =+AM27+AM28 -> -234.531 | AN29: =+AN27+AN28 -> -9.291 | AO29: =+AO27+AO28 -> -13.351 | AP29: =+AP27+AP28 -> -6.38 | AQ29: =+AQ27+AQ28 -> 962.329 | AR29: =+AR27+AR28 -> -270.014 | AS29: =+AS27+AS28 -> -307.154 | AT29: =+AT27+AT28 -> -30.248 | ... BM29: =+BM27+BM28 -> 387.784 | BO29: =+BO27+BO28 -> -671.494 | BP29: =+BP27+BP28 -> 201.679 | BQ29: =+BQ27+BQ28 -> 48.635 | BR29: =+BR27+BR28 -> 1015.528 | BS29: =+BS27+BS28 -> -460.853 | BT29: =+BT27+BT28 -> 117.216 | BV29: =+BV27+BV28 -> 8.626 | BW29: =+BW27+BW28 -> 82.645 | BY29: =+BY27+BY28 -> 1024.154 | BZ29: =+BZ27+BZ28 -> 96.195 | CB29: =+CB27+CB28 -> -219.165 | CC29: =+CC27+CC28 -> 243.078
B30: Gain on disposal of group of subsidiares - net | K30: 13472.081 | L30: 0 | M30: 0 | N30: 0 | O30: 0 | P30: 0 | Q30: 0 | R30: =SUM(BJ30:BM30) -> 0 | AP30: 0 | AQ30: =I30-SUM(AN30:AP30) -> 0 | AR30: 0 | AS30: 0 | AT30: 0 | AU30: =K30-AR30-AS30-AT30 -> 13472.081 | AV30: 0 | AW30: =L30-AR30-AS30-AV30 -> 0 | AZ30: 402 | BA30: 0 | BB30: 0 | BC30: 0 | BD30: =M30-AZ30-AX30-BC30 -> -402 | BF30: 0 | BG30: 0 | BH30: =O30-SUM(BE30:BG30) -> 0 | BI30: 0 | BJ30: 0 | BK30: 0 | BL30: =Q30-SUM(BI30:BK30) -> 0 | BM30: 0 | BO30: =N30-SUM(AY30,BA30,BC30) -> 0 | BP30: 0 | BQ30: 0 | BR30: 0 | BS30: =P30-SUM(BP30:BR30) -> 0 | BT30: 0 | BV30: 0 | BW30: 0 | BY30: 0 | BZ30: 0 | CB30: =P30-BY30 -> 0 | CC30: =Q30-BZ30 -> 0
B31: Profit for the financial period from discontinued operations | J31: 969.346 | K31: 1424.208 | L31: 12433.764 | M31: -2599.355 | N31: -1802.431 | O31: 0 | P31: 793.87 | Q31: 292.335 | R31: =SUM(BJ31:BM31) -> 292.335 | AN31: 0 | AO31: 0 | AP31: 0 | AQ31: =I31-SUM(AN31:AP31) -> 0 | AR31: 260.723 | AS31: 293.803 | AT31: 365.485 | AU31: =K31-AR31-AS31-AT31 -> 504.197 | AV31: 365.485 | AW31: =L31-AR31-AS31-AV31 -> 11513.753 | AX31: 0 | AY31: 39.573 | AZ31: 0 | BA31: -528.232 | BB31: -1022.85 | BC31: -1022.85 | BD31: =M31-AZ31-AX31-BC31 -> -1576.505 | BE31: 66.721 | BF31: 53.949 | BG31: 44.702 | BH31: =O31-SUM(BE31:BG31) -> -165.372 | BI31: 0 | BJ31: 238.467 | BK31: 6.519 | BL31: =Q31-SUM(BI31:BK31) -> 47.349 | BM31: 0 | BO31: =N31-SUM(AY31,BA31,BC31) -> -290.922 | BP31: 0 | BQ31: 206.829 | BR31: 172.867 | BS31: =P31-SUM(BP31:BR31) -> 414.174 | BT31: 191.276 | BV31: 448.517 | BW31: 429.742 | BY31: 621.384 | BZ31: 436.261 | CB31: =P31-BY31 -> 172.486 | CC31: =Q31-BZ31 -> -143.926
B32: Profit / (Loss) for the financial period | C32: =+C29+C31+C30 -> 657.158 | D32: =+D29+D31+D30 -> 1162.492 | E32: =+E29+E31+E30 -> -4974.692 | F32: =+F29+F31+F30 -> 1815.096 | G32: =+G29+G31+G30 -> 624.045 | H32: =+H29+H31+H30 -> 1276.881 | I32: =+I29+I31+I30 -> 933.307 | J32: =+J29+J31+J30 -> 1276.881 | ... R32: =+R29+R31+R30 -> 710.9 | T32: =+T29+T31+T30 -> -81.119 | U32: =+U29+U31+U30 -> -3304.149 | V32: =+V29+V31+V30 -> 199.347 | W32: =+W29+W31+W30 -> -1788.771 | X32: =+X29+X31+X30 -> 799.826 | Y32: =+Y29+Y31+Y30 -> 303.962 | Z32: =+Z29+Z31+Z30 -> 307.165 | AA32: =+AA29+AA31+AA30 -> 404.143 | ... AI32: =+AI29+AI31+AI30 -> 211.501 | AM32: =+AM29+AM31+AM30 -> -234.531 | AN32: =+AN29+AN31+AN30 -> -9.291 | AO32: =+AO29+AO31+AO30 -> -13.351 | AP32: =+AP29+AP31+AP30 -> -6.38 | AQ32: =+AQ29+AQ31+AQ30 -> 962.329 | AR32: =+AR29+AR31+AR30 -> -9.291 | AS32: =+AS29+AS31+AS30 -> -13.351 | AT32: =+AT29+AT31+AT30 -> 335.237 | ... BM32: =+BM29+BM31+BM30 -> 387.784 | BO32: =+BO29+BO31+BO30 -> -962.416 | BP32: =+BP29+BP31+BP30 -> 201.679 | BQ32: =+BQ29+BQ31+BQ30 -> 255.464 | BR32: =+BR29+BR31+BR30 -> 1188.395 | BS32: =+BS29+BS31+BS30 -> -46.679 | BT32: =+BT29+BT31+BT30 -> 308.492 | BV32: =+BV29+BV31+BV30 -> 457.143 | BW32: =+BW29+BW31+BW30 -> 512.387 | BY32: =+BY29+BY31+BY30 -> 1645.538 | BZ32: =+BZ29+BZ31+BZ30 -> 532.456 | CB32: =+CB29+CB31+CB30 -> -46.679 | CC32: =+CC29+CC31+CC30 -> 99.152
B34: % of Net sales unless stated otherwise
B35: =B9 -> Depreciation, impairment and amortisation | C35: =-C9/C7 -> 0.26275919 | D35: =-D9/D7 -> 0.24531246 | E35: =-E9/E7 -> 0.32005719 | F35: =-F9/F7 -> 0.28817256 | G35: =-G9/G7 -> 0.35057365 | H35: =-H9/H7 -> 0.31253519 | I35: =-I9/I7 -> 0.25691854 | J35: =-J9/J7 -> 0.31597983 | ... R35: =-R9/R7 -> 0.31761542 | T35: =-T9/T7 -> 0.24237137 | U35: =-U9/U7 -> 0.25379606 | V35: =-V9/V7 -> 0.25176198 | W35: =-W9/W7 -> 0.51876872 | X35: =-X9/X7 -> 0.27616731 | Y35: =-Y9/Y7 -> 0.27735913 | Z35: =-Z9/Z7 -> 0.2971142 | AA35: =-AA9/AA7 -> 0.30132231 | ... AI35: =-AI9/AI7 -> 0.3233855 | AM35: =-AM9/AM7 -> 0.30660128 | AN35: =-AN9/AN7 -> 0.28756678 | AO35: =-AO9/AO7 -> 0.28032592 | AP35: =-AP9/AP7 -> 0.28943856 | AQ35: =-AQ9/AQ7 -> 0.17348579 | AR35: =-AR9/AR7 -> 0.32271017 | AS35: =-AS9/AS7 -> 0.31292566 | AT35: =-AT9/AT7 -> 0.29436083 | ... BM35: =-BM9/BM7 -> 0.27590905 | BO35: =-BO9/BO7 -> 0.479393 | BP35: =-BP9/BP7 -> 0.33058613 | BQ35: =-BQ9/BQ7 -> 0.29307942 | BR35: =-BR9/BR7 -> 0.30820771 | BS35: =-BS9/BS7 -> -0.14946406 | BT35: =-BT9/BT7 -> 0.28562097 | BV35: =-BV9/BV7 -> 0.30054201 | BW35: =-BW9/BW7 -> 0.33445693 | BY35: =-BY9/BY7 -> 0.30299632 | BZ35: =-BZ9/BZ7 -> 0.33927404
B36: =B13 -> Marketing, Advertising and promotion | C36: =-C13/C7 -> 0.084283142 | D36: =-D13/D7 -> 0.086415882 | E36: =-E13/E7 -> 0.089915335 | F36: =-F13/F7 -> 0.081415799 | G36: =-G13/G7 -> 0.078182813 | H36: =-H13/H7 -> 0.08465645 | I36: =-I13/I7 -> 0.067661325 | J36: =-J13/J7 -> 0.09296938 | ... R36: =-R13/R7 -> 0.080226965 | T36: =-T13/T7 -> 0.095834401 | U36: =-U13/U7 -> 0.096444645 | V36: =-V13/V7 -> 0.084415152 | W36: =-W13/W7 -> 0.083642479 | X36: =-X13/X7 -> 0.082189121 | Y36: =-Y13/Y7 -> 0.083894927 | Z36: =-Z13/Z7 -> 0.076604304 | AA36: =-AA13/AA7 -> 0.083017619 | ... AI36: =-AI13/AI7 -> 0.083478873 | AM36: =-AM13/AM7 -> 0.094406878 | AN36: =-AN13/AN7 -> 0.08305287 | AO36: =-AO13/AO7 -> 0.079675347 | AP36: =-AP13/AP7 -> 0.07296898 | AQ36: =-AQ13/AQ7 -> 0.036809306 | AR36: =-AR13/AR7 -> 0.095598017 | AS36: =-AS13/AS7 -> 0.086409029 | AT36: =-AT13/AT7 -> 0.072652303 | ... BM36: =-BM13/BM7 -> 0.070474927 | BO36: =-BO13/BO7 -> 0.075608935 | BP36: =-BP13/BP7 -> 0.075200168 | BQ36: =-BQ13/BQ7 -> 0.08864014 | BR36: =-BR13/BR7 -> 0.070347517 | BS36: =-BS13/BS7 -> 0.15772007 | BT36: =-BT13/BT7 -> 0.073746385 | BV36: =-BV13/BV7 -> 0.089697336 | BW36: =-BW13/BW7 -> 0.073268484 | BY36: =-BY13/BY7 -> 0.083502685 | BZ36: =-BZ13/BZ7 -> 0.073273935
B37: =B14 -> Other operating costs | C37: =-C14/C7 -> 0.37441063 | D37: =-D14/D7 -> 0.34651779 | E37: =-E14/E7 -> 0.37375789 | F37: =-F14/F7 -> 0.30129374 | G37: =-G14/G7 -> 0.30184433 | H37: =-H14/H7 -> 0.30745289 | I37: =-I14/I7 -> 0.22995513 | J37: =-J14/J7 -> 0.28434662 | ... R37: =-R14/R7 -> 0.21283539 | T37: =-T14/T7 -> 0.37281075 | U37: =-U14/U7 -> 0.3615438 | V37: =-V14/V7 -> 0.36649309 | W37: =-W14/W7 -> 0.39302058 | X37: =-X14/X7 -> 0.33709442 | Y37: =-Y14/Y7 -> 0.29775836 | Z37: =-Z14/Z7 -> 0.31268961 | AA37: =-AA14/AA7 -> 0.25948048 | ... AI37: =-AI14/AI7 -> 0.3085285 | AM37: =-AM14/AM7 -> 0.29087945 | AN37: =-AN14/AN7 -> 0.30657342 | AO37: =-AO14/AO7 -> 0.31163259 | AP37: =-AP14/AP7 -> 0.30626097 | AQ37: =-AQ14/AQ7 -> 0.0045845671 | AR37: =-AR14/AR7 -> 0.28438409 | AS37: =-AS14/AS7 -> 0.29791433 | AT37: =-AT14/AT7 -> 0.284323 | ... BM37: =-BM14/BM7 -> 0.23079646 | BO37: =-BO14/BO7 -> 0.27460244 | BP37: =-BP14/BP7 -> 0.26109161 | BQ37: =-BQ14/BQ7 -> 0.23605811 | BR37: =-BR14/BR7 -> 0.24350815 | BS37: =-BS14/BS7 -> -0.18809251 | BT37: =-BT14/BT7 -> 0.2756758 | BV37: =-BV14/BV7 -> 0.23291529 | BW37: =-BW14/BW7 -> 0.24515762 | BY37: =-BY14/BY7 -> 0.23630661 | BZ37: =-BZ14/BZ7 -> 0.24188097
B38: =B15 -> Staff costs | C38: =-C15/C7 -> 0.072556529 | D38: =-D15/D7 -> 0.078145548 | E38: =-E15/E7 -> 0.086584274 | F38: =-F15/F7 -> 0.090313299 | G38: =-G15/G7 -> 0.092034717 | H38: =-H15/H7 -> 0.079959581 | I38: =-I15/I7 -> 0.06040513 | J38: =-J15/J7 -> 0.076858043 | ... R38: =-R15/R7 -> 0.12540964 | T38: =-T15/T7 -> 0.072290884 | U38: =-U15/U7 -> 0.089591303 | V38: =-V15/V7 -> 0.087501366 | W38: =-W15/W7 -> 0.096000874 | X38: =-X15/X7 -> 0.084461101 | Y38: =-Y15/Y7 -> 0.10276839 | Z38: =-Z15/Z7 -> 0.087810831 | AA38: =-AA15/AA7 -> 0.086120217 | ... AI38: =-AI15/AI7 -> 0.06941711 | AM38: =-AM15/AM7 -> 0.063923777 | AN38: =-AN15/AN7 -> 0.07719502 | AO38: =-AO15/AO7 -> 0.081024788 | AP38: =-AP15/AP7 -> 0.08379082 | AQ38: =-AQ15/AQ7 -> 0.0016173604 | AR38: =-AR15/AR7 -> 0.07522036 | AS38: =-AS15/AS7 -> 0.076064072 | AT38: =-AT15/AT7 -> 0.073596602 | ... BM38: =-BM15/BM7 -> 0.1013611 | BO38: =-BO15/BO7 -> 0.06729682 | BP38: =-BP15/BP7 -> 0.071929066 | BQ38: =-BQ15/BQ7 -> 0.10160361 | BR38: =-BR15/BR7 -> 0.10096711 | BS38: =-BS15/BS7 -> 0.52801375 | BT38: =-BT15/BT7 -> 0.10828924 | BV38: =-BV15/BV7 -> 0.10230253 | BW38: =-BW15/BW7 -> 0.11078054 | BY38: =-BY15/BY7 -> 0.10187502 | BZ38: =-BZ15/BZ7 -> 0.11269649
B39: =B19 -> Operating Profit | C39: =C19/C7 -> 0.12646216 | D39: =D19/D7 -> 0.12294106 | E39: =E19/E7 -> -0.099855517 | F39: =F19/F7 -> 0.17215443 | G39: =G19/G7 -> 0.10308087 | H39: =H19/H7 -> 0.14741234 | I39: =I19/I7 -> 0.13628272 | J39: =J19/J7 -> 0.12136983 | ... R39: =R19/R7 -> 0.11249038 | T39: =T19/T7 -> 0.10695274 | U39: =U19/U7 -> -0.44016438 | V39: =V19/V7 -> 0.13808776 | W39: =W19/W7 -> -0.19889133 | X39: =X19/X7 -> 0.20693824 | Y39: =Y19/Y7 -> 0.18116833 | Z39: =Z19/Z7 -> 0.16061986 | AA39: =AA19/AA7 -> 0.14171805 | ... AI39: =AI19/AI7 -> 0.13719059 | AM39: =AM19/AM7 -> 0.065624341 | AN39: =AN19/AN7 -> 0.13203145 | AO39: =AO19/AO7 -> 0.14725196 | AP39: =AP19/AP7 -> 0.15908614 | AQ39: =AQ19/AQ7 -> 0.1064279 | AR39: =AR19/AR7 -> 0.087970441 | AS39: =AS19/AS7 -> 0.10266729 | AT39: =AT19/AT7 -> 0.16581818 | ... BM39: =BM19/BM7 -> 0.19993671 | BO39: =BO19/BO7 -> -0.047143642 | BP39: =BP19/BP7 -> 0.17377375 | BQ39: =BQ19/BQ7 -> 0.13575826 | BR39: =BR19/BR7 -> 0.027253851 | BS39: =BS19/BS7 -> 0.48111735 | BT39: =BT19/BT7 -> 0.13211787 | BV39: =BV19/BV7 -> 0.1448513 | BW39: =BW19/BW7 -> 0.087750048 | BY39: =BY19/BY7 -> 0.10720335 | BZ39: =BZ19/BZ7 -> 0.092602073
B40: Finance Income as a % of cash at end of period | C40: =C20/C123 -> 0.88719571 | D40: =D20/D123 -> 3.6282842 | E40: =E20/E123 -> 0.043667805 | F40: =F20/F123 -> 0.054470009 | G40: =G20/G123 -> 0.024628405 | H40: =H20/H123 -> 0.021663707 | I40: =I20/I123 -> 0.034254658 | J40: =J20/J123 -> 0.025782024 | ... R40: =R20/R123 -> 0.057214148 | T40: =SUM(T20:T20)/T123 -> 0.010726253 | U40: =SUM(T20:U20)/U123 -> 0.018399493 | V40: =SUM(T20:V20)/V123 -> 0.027494315 | W40: =SUM(T20:W20)/W123 -> 0.043667805 | X40: =SUM(X20:X20)/X123 -> 0.0083525205 | Y40: =SUM(X20:Y20)/Y123 -> 0.020561066 | Z40: =SUM(X20:Z20)/Z123 -> 0.035587638 | AA40: =SUM(X20:AA20)/AA123 -> 0.054470009 | AB40: =SUM(Y20:AB20)/AB123 -> 0.036263691 | AC40: =SUM(Z20:AC20)/AC123 -> 0.035434178 | AD40: =SUM(AA20:AD20)/AD123 -> 0.017243391 | AE40: =SUM(AB20:AE20)/AE123 -> 0.024628405 | AF40: =SUM(AC20:AF20)/AF123 -> 0.025871273 | AG40: =SUM(AD20:AG20)/AG123 -> 0.022625338 | AH40: =SUM(AE20:AH20)/AH123 -> 0.020579076 | AI40: =SUM(AF20:AI20)/AI123 -> 0.021663707 | AM40: =SUM(AJ20:AM20)/AM123 -> 0.0069676492 | AN40: =SUM(AC20:AN20)/AN123 -> 0.064221567 | AO40: =SUM(AD20:AO20)/AO123 -> 0.055713426 | AP40: =SUM(AE20:AP20)/AP123 -> 0.048882648 | AQ40: =SUM(AF20:AQ20)/AQ123 -> 0.061030761 | AR40: =SUM(AG20:AR20)/AR123 -> 0.080454971 | AS40: =SUM(AH20:AS20)/AS123 -> 0.072847084 | AT40: =SUM(AI20:AT20)/AT123 -> 0.064328302 | AU40: =SUM(AR20:AU20)/AU123 -> 0.034254658 | AV40: =SUM(AK20:AV20)/AV123 -> 0.079631862 | AW40: =SUM(AT20:AW20)/AW123 -> 0.038399956 | AX40: =SUM(AS20:AX20)/AX123 -> 0.077294882 | AY40: =SUM(AT20:AY20)/AY123 -> 0.080603772 | AZ40: =SUM(AT20:AZ20)/AZ123 -> 0.082395475 | BA40: =SUM(AU20:BA20)/BA123 -> 0.083198283 | BB40: =SUM(AU20:BB20)/BB123 -> 0.10450888 | BC40: =SUM(AV20:BC20)/BC123 -> 0.098873641 | BD40: =SUM(AZ20:BD20)/BD123 -> 0.064280439 | BE40: =SUM(BC20:BE20,BA20)/BE123 -> 0.047141846 | BF40: =SUM(BC20:BF20)/BF123 -> 0.036142382 | BG40: =SUM(BD20:BG20)/BG123 -> 0.038017366 | BH40: =SUM(BE20:BH20)/BH123 -> 0.054654723 | BI40: =SUM(BG20:BI20,BF20)/BI123 -> 0.055325012 | BJ40: =SUM(BG20:BJ20)/BJ123 -> 0.057902444 | BK40: =SUM(BH20:BK20)/BK123 -> 0.073408084 | BL40: =SUM(BI20:BL20)/BL123 -> 0.045296749 | BM40: =SUM(BK20:BM20,BJ20)/BM123 -> 0.057214148 | BS40: =SUM(BP20:BS20)/BS123 -> 0.036277786
B41: Finance costs as a % of debt at end of period | C41: =-C21/C116 -> 0.053961834 | D41: =-D21/D116 -> 0.065334118 | E41: =-E21/E116 -> 0.066543824 | F41: =-F21/F116 -> 0.067732996 | G41: =-G21/G116 -> 0.061849377 | H41: =-H21/H116 -> 0.053558836 | I41: =-I21/I116 -> 0.050922894 | J41: =-J21/J116 -> 0.048301712 | ... R41: =-R21/R116 -> 0.05833596 | T41: =-SUM(T21:T21)/T116 -> 0.016663456 | U41: =-SUM(T21:U21)/U116 -> 0.033068803 | V41: =-SUM(T21:V21)/V116 -> 0.048336515 | W41: =-SUM(T21:W21)/W116 -> 0.066543824 | X41: =-SUM(X21:X21)/X116 -> 0.015470524 | Y41: =-SUM(X21:Y21)/Y116 -> 0.034107767 | Z41: =-SUM(X21:Z21)/Z116 -> 0.050928559 | AA41: =-SUM(X21:AA21)/AA116 -> 0.067732996 | AB41: =-SUM(Y21:AB21)/AB116 -> 0.066390319 | AC41: =-SUM(Z21:AC21)/AC116 -> 0.064025304 | AD41: =-SUM(AA21:AD21)/AD116 -> 0.05598681 | AE41: =-SUM(AB21:AE21)/AE116 -> 0.061849377 | AF41: =-SUM(AC21:AF21)/AF116 -> 0.060400719 | AG41: =-SUM(AD21:AG21)/AG116 -> 0.057787878 | AH41: =-SUM(AE21:AH21)/AH116 -> 0.055168036 | AI41: =-SUM(AF21:AI21)/AI116 -> 0.053558836 | AM41: =-SUM(AJ21:AM21)/AM116 -> 0.014115913 | AN41: =-SUM(AC21:AN21)/AN116 -> 0.12646823 | AO41: =-SUM(AD21:AO21)/AO116 -> 0.10195929 | AP41: =-SUM(AE21:AP21)/AP116 -> 0.095661442 | AQ41: =-SUM(AF21:AQ21)/AQ116 -> 0.10604172 | AR41: =-SUM(AG21:AR21)/AR116 -> 0.13213021 | AS41: =-SUM(AH21:AS21)/AS116 -> 0.10696062 | AT41: =-SUM(AI21:AT21)/AT116 -> 0.099967711 | AU41: =-SUM(AR21:AU21)/AU116 -> 0.050920827 | AV41: =-SUM(AK21:AV21)/AV116 -> 0.11555431 | AW41: =-SUM(AT21:AW21)/AW116 -> 0.055475765 | AX41: =-SUM(AS21:AX21)/AX116 -> 0.079857174 | AY41: =-SUM(AT21:AY21)/AY116 -> 0.082828099 | AZ41: =-SUM(AT21:AZ21)/AZ116 -> 0.099519752 | BA41: =-SUM(AU21:BA21)/BA116 -> 0.1037933 | BB41: =-SUM(AU21:BB21)/BB116 -> 0.12264685 | BC41: =-SUM(AV21:BC21)/BC116 -> 0.12239925 | BD41: =-SUM(AZ21:BD21)/BD116 -> 0.080144175 | BE41: =-SUM(BC21:BE21,BA21)/BE116 -> 0.060374751 | BF41: =-SUM(BC21:BF21)/BF116 -> 0.060006763 | BG41: =-SUM(BD21:BG21)/BG116 -> 0.067376156 | BH41: =-SUM(BE21:BH21)/BH116 -> 0.068515834 | BI41: =-SUM(BG21:BI21,BF21)/BI116 -> 0.068653311 | BJ41: =-SUM(BG21:BJ21)/BJ116 -> 0.10214488 | BK41: =-SUM(BH21:BK21)/BK116 -> 0.099105269 | BL41: =-SUM(BI21:BL21)/BL116 -> 0.074094475 | BM41: =-SUM(BK21:BM21,BJ21)/BM116 -> 0.05833596 | BS41: =-SUM(BP21:BS21)/BS116 -> 0.041476485
B42: =B27 -> Profit before tax | C42: =C27/C7 -> 0.052843 | D42: =D27/D7 -> 0.079346332 | E42: =E27/E7 -> -0.17052572 | F42: =F27/F7 -> 0.11307427 | G42: =G27/G7 -> 0.048386924 | H42: =H27/H7 -> 0.083921333 | I42: =I27/I7 -> 0.056244931 | J42: =J27/J7 -> 0.047574647 | ... R42: =R27/R7 -> 0.11169177 | T42: =T27/T7 -> 0.0095529961 | U42: =U27/U7 -> -0.51894295 | V42: =V27/V7 -> 0.065870383 | W42: =W27/W7 -> -0.23597147 | X42: =X27/X7 -> 0.16689041 | Y42: =Y27/Y7 -> 0.10626828 | Z42: =Z27/Z7 -> 0.092349194 | AA42: =AA27/AA7 -> 0.089215314 | ... AI42: =AI27/AI7 -> 0.079490383 | AM42: =AM27/AM7 -> -0.0020599779 | AN42: =AN27/AN7 -> 0.039137854 | AO42: =AO27/AO7 -> 0.042771183 | AP42: =AP27/AP7 -> 0.036993421 | AQ42: =AQ27/AQ7 -> 0.10432772 | AR42: =AR27/AR7 -> -0.024852475 | AS42: =AS27/AS7 -> -0.024788917 | AT42: =AT27/AT7 -> 0.020112629 | ... BM42: =BM27/BM7 -> 0.18520062 | BO42: =BO27/BO7 -> -0.068204789 | BP42: =BP27/BP7 -> 0.065322041 | BQ42: =BQ27/BQ7 -> 0.073575838 | BR42: =BR27/BR7 -> 0.41392686 | BS42: =BS27/BS7 -> -0.7346506 | BT42: =BT27/BT7 -> 0.083162134 | BV42: =BV27/BV7 -> 0.051365824 | BW42: =BW27/BW7 -> 0.079599869 | BY42: =BY27/BY7 -> 0.16743853 | BZ42: =BZ27/BZ7 -> 0.072396932
B43: Income tax benefit/(expense) as a % of Profit before tax | C43: =-C28/C27 -> 0.42333316 | D43: =-D28/D27 -> 0.39961399 | E43: =-E28/E27 -> -0.22134078 | F43: =-F28/F27 -> 0.3470267 | G43: =-G28/G27 -> 0.46713693 | H43: =-H28/H27 -> 0.41255501 | I43: =-I28/I27 -> 0.39707799 | J43: =-J28/J27 -> 0.67669584 | ... R43: =-R28/R27 -> 0.60423315 | T43: =-T28/T27 -> 2.4772276 | U43: =-U28/U27 -> -0.085223302 | V43: =-V28/V27 -> 0.49589962 | W43: =-W28/W27 -> -0.20958364 | X43: =-X28/X27 -> 0.19445787 | Y43: =-Y28/Y27 -> 0.53517939 | Z43: =-Z28/Z27 -> 0.46467255 | AA43: =-AA28/AA27 -> 0.27717116 | ... AI43: =-AI28/AI27 -> 0.61459151 | AM43: =-AM28/AM27 -> -20.334577 | AN43: =-AN28/AN27 -> 1.0366914 | AO43: =-AO28/AO27 -> 1.0465599 | AP43: =-AP28/AP27 -> 1.0237542 | AQ43: =-AQ28/AQ27 -> -0.30146466 | AR43: =-AR28/AR27 -> -1.1799583 | AS43: =-AS28/AS27 -> -1.3839401 | AT43: =-AT28/AT27 -> 1.2634315 | ... BM43: =-BM28/BM27 -> 0.25215607 | BO43: =-BO28/BO27 -> -0.63183603 | BP43: =-BP28/BP27 -> 0.46202579 | BQ43: =-BQ28/BQ27 -> 0.80087617 | BR43: =-BR28/BR27 -> 0.19954283 | BS43: =-BS28/BS27 -> -0.4998747 | BT43: =-BT28/BT27 -> 0.5126012 | BV43: =-BV28/BV27 -> 0.97419891 | BW43: =-BW28/BW27 -> 0.82277116 | BY43: =-BY28/BY27 -> 0.36110687 | BZ43: =-BZ28/BZ27 -> 0.8486441
B45: capex/sales | C45: =-C69/C7 -> 0.25425283 | D45: =-D69/D7 -> 0.20018956 | E45: =-E69/E7 -> 0.27786929 | F45: =-F69/F7 -> 0.27542001 | G45: =-G69/G7 -> 0.18670967 | H45: =-H69/H7 -> 0.24590106 | I45: =-I69/I7 -> 0.35070137 | J45: =-J69/J7 -> 0.31249775 | ... R45: =-R69/R7 -> 0.17358187 | T45: =-T69/T7 -> 0.22896625 | U45: =-U69/U7 -> 0.31463619 | V45: =-V69/V7 -> 0.30079944 | W45: =-W69/W7 -> 0.26633785 | X45: =-X69/X7 -> 0.28288946 | Y45: =-Y69/Y7 -> 0.2297211 | Z45: =-Z69/Z7 -> 0.2308383 | AA45: =-AA69/AA7 -> 0.35740043 | ... AI45: =-AI69/AI7 -> 0.23944412 | AM45: =-AM69/AM7 -> 0 | AN45: =-AN69/AN7 -> 0.26457171 | AO45: =-AO69/AO7 -> 0.51441927 | AP45: =-AP69/AP7 -> 0.35986303 | AQ45: =-AQ69/AQ7 -> 0.26507582 | AR45: =-AR69/AR7 -> 0.34345983 | AS45: =-AS69/AS7 -> 0.66353619 | AT45: =-AT69/AT7 -> 0.45764933 | ... BM45: =-BM69/BM7 -> 0.16984343 | BO45: =-BO69/BO7 -> 0.25711367 | BP45: =-BP69/BP7 -> 0.26729439 | BQ45: =-BQ69/BQ7 -> 0.43060956 | BR45: =-BR69/BR7 -> 0.3153157 | BS45: =-BS69/BS7 -> 2.8605302 | BT45: =-BT69/BT7 -> 0.29744036 | BV45: =-BV69/BV7 -> 0.45530766 | BW45: =-BW69/BW7 -> 0.21469166 | BY45: =-BY69/BY7 -> 0.41048984 | BZ45: =-BZ69/BZ7 -> 0.19137928
B46: D/A/sales | C46: =C50/C7 -> 0.26275919 | D46: =D50/D7 -> 0.24531246 | E46: =E50/E7 -> 0.32005719 | F46: =F50/F7 -> 0.28817256 | G46: =G50/G7 -> 0.35057365 | H46: =H50/H7 -> 0.31253519 | I46: =I50/I7 -> 0.25691854 | J46: =J50/J7 -> 0.31597983 | ... R46: =R50/R7 -> 0.31761542 | T46: =T50/T7 -> 0.24237137 | U46: =U50/U7 -> 0.25379606 | V46: =V50/V7 -> 0.25176198 | W46: =W50/W7 -> 0.51876872 | X46: =X50/X7 -> 0.27616731 | Y46: =Y50/Y7 -> 0.27735913 | Z46: =Z50/Z7 -> 0.2971142 | AA46: =AA50/AA7 -> 0.30132231 | ... AI46: =AI50/AI7 -> 0.3233855 | AM46: =AM50/AM7 -> 0.30660128 | AN46: =AN50/AN7 -> 0.28756678 | AO46: =AO50/AO7 -> 0.28032592 | AP46: =AP50/AP7 -> 0.28943856 | AQ46: =AQ50/AQ7 -> 0.17348579 | AR46: =AR50/AR7 -> 0.32271017 | AS46: =AS50/AS7 -> 0.31292566 | AT46: =AT50/AT7 -> 0.29436083 | ... BM46: =BM50/BM7 -> 0.27590905 | BO46: =BO50/BO7 -> 0.479393 | BP46: =BP50/BP7 -> 0.33058613 | BQ46: =BQ50/BQ7 -> 0.29307942 | BR46: =BR50/BR7 -> 0.30820771 | BS46: =BS50/BS7 -> -0.14946406 | BT46: =BT50/BT7 -> 0.28562097 | BV46: =BV50/BV7 -> 0.30054201 | BW46: =BW50/BW7 -> 0.33445693 | BY46: =BY50/BY7 -> 0.30299632 | BZ46: =BZ50/BZ7 -> 0.33927404
B48: EBITDA | C48: =+C3 -> 42707 | D48: =+D3 -> 43073 | E48: =E3 -> 43438 | F48: =F3 -> 43803 | G48: =G3 -> 44169 | H48: =H3 -> 44561 | I48: =I3 -> 44926 | J48: =+J3 -> 44561 | K48: =K3 -> 44926 | L48: =L3 -> 44926 | M48: =M3 -> 45291 | N48: =N3 -> 45291 | O48: =O3 -> 45657 | P48: =P3 -> 45657 | Q48: =Q3 -> 46022 | R48: =+R3 -> 46112 | T48: =+T3 -> 43190 | U48: =+U3 -> 43281 | V48: =+V3 -> 43373 | W48: =+W3 -> 43465 | X48: =+X3 -> 43555 | Y48: =+Y3 -> 43646 | Z48: =+Z3 -> 43738 | AA48: =+AA3 -> 43830 | ... BM48: =+BM3 -> 46112 | BO48: =+BO3 -> 45291 | BP48: =+BP3 -> 45382 | BQ48: =+BQ3 -> 45473 | BR48: =+BR3 -> 45565 | BS48: =+BS3 -> 45657 | BT48: =+BT3 -> 45747 | BV48: =+BV3 -> 45473 | BW48: =+BW3 -> 45838 | BY48: =+BY3 -> 45565 | BZ48: =+BZ3 -> 45930
B49: Operating profit | C49: =C19 -> 2727.206 | D49: =D19 -> 3000.057 | E49: =E19 -> -2385.127 | F49: =F19 -> 4232.126 | G49: =G19 -> 2494.884 | H49: =H19 -> 3818.077 | I49: =I19 -> 3750.773 | J49: =J19 -> 2426.713 | ... R49: =R19 -> 1065.167 | T49: =T19 -> 614.791 | U49: =U19 -> -2582.473 | V49: =V19 -> 829.006 | W49: =W19 -> -1246.451 | X49: =X19 -> 1231.166 | Y49: =Y19 -> 1114.84 | Z49: =Z19 -> 997.972 | AA49: =AA19 -> 888.148 | ... AI49: =AI19 -> 947.111 | AM49: =AM19 -> 350.202 | AN49: =AN19 -> 854.237 | AO49: =AO19 -> 987.215 | AP49: =AP19 -> 1155.016 | AQ49: =AQ19 -> 754.305 | AR49: =AR19 -> 438.435 | AS49: =AS19 -> 533.624 | AT49: =AT19 -> 946.656 | ... BM49: =BM19 -> 559.795 | BO49: =BO19 -> -284.429 | BP49: =BP19 -> 997.295 | BQ49: =BQ19 -> 450.668 | BR49: =BR19 -> 83.533 | BS49: =BS19 -> 201.223 | BT49: =BT19 -> 382.066 | BV49: =BV19 -> 942.8 | BW49: =BW19 -> 514.064 | BY49: =BY19 -> 1026.337 | BZ49: =BZ19 -> 812.931
B50: Depreciation & amortisation | C50: =-C9 -> 5666.505 | D50: =-D9 -> 5986.213 | E50: =-E9 -> 7644.816 | F50: =-F9 -> 7084.236 | G50: =-G9 -> 8484.994 | H50: =-H9 -> 8094.868 | I50: =-I9 -> 7070.912 | J50: =-J9 -> 6317.817 | ... R50: =-R9 -> 3007.488 | T50: =-T9 -> 1393.211 | U50: =-U9 -> 1489.038 | V50: =-V9 -> 1511.446 | W50: =-W9 -> 3251.121 | X50: =-X9 -> 1643.04 | Y50: =-Y9 -> 1706.761 | Z50: =-Z9 -> 1846.046 | AA50: =-AA9 -> 1888.389 | ... AI50: =-AI9 -> 2232.529 | AM50: =-AM9 -> 1636.167 | AN50: =-AN9 -> 1860.543 | AO50: =-AO9 -> 1879.377 | AP50: =-AP9 -> 2101.416 | AQ50: =-AQ9 -> 1229.576 | AR50: =-AR9 -> 1608.352 | AS50: =-AS9 -> 1626.464 | AT50: =-AT9 -> 1680.506 | ... BM50: =-BM9 -> 772.507 | BO50: =-BO9 -> 2892.294 | BP50: =-BP9 -> 1897.248 | BQ50: =-BQ9 -> 972.917 | BR50: =-BR9 -> 944.656 | BS50: =-BS9 -> -62.512 | BT50: =-BT9 -> 825.975 | BV50: =-BV9 -> 1956.151 | BW50: =-BW9 -> 1959.341 | BY50: =-BY9 -> 2900.808 | BZ50: =-BZ9 -> 2978.404
B51: EBITDA | C51: =SUM(C49:C50) -> 8393.711 | D51: =SUM(D49:D50) -> 8986.27 | E51: =SUM(E49:E50) -> 5259.689 | F51: =SUM(F49:F50) -> 11316.362 | G51: =SUM(G49:G50) -> 10979.878 | H51: =SUM(H49:H50) -> 11912.945 | I51: =SUM(I49:I50) -> 10821.685 | J51: =SUM(J49:J50) -> 8744.53 | ... R51: =SUM(R49:R50) -> 4072.655 | T51: =SUM(T49:T50) -> 2008.002 | U51: =SUM(U49:U50) -> -1093.435 | V51: =SUM(V49:V50) -> 2340.452 | W51: =SUM(W49:W50) -> 2004.67 | X51: =SUM(X49:X50) -> 2874.206 | Y51: =SUM(Y49:Y50) -> 2821.601 | Z51: =SUM(Z49:Z50) -> 2844.018 | AA51: =SUM(AA49:AA50) -> 2776.537 | ... AI51: =SUM(AI49:AI50) -> 3179.64 | AM51: =SUM(AM49:AM50) -> 1986.369 | AN51: =SUM(AN49:AN50) -> 2714.78 | AO51: =SUM(AO49:AO50) -> 2866.592 | AP51: =SUM(AP49:AP50) -> 3256.432 | AQ51: =SUM(AQ49:AQ50) -> 1983.881 | AR51: =SUM(AR49:AR50) -> 2046.787 | AS51: =SUM(AS49:AS50) -> 2160.088 | AT51: =SUM(AT49:AT50) -> 2627.162 | ... BM51: =SUM(BM49:BM50) -> 1332.302 | BO51: =SUM(BO49:BO50) -> 2607.865 | BP51: =SUM(BP49:BP50) -> 2894.543 | BQ51: =SUM(BQ49:BQ50) -> 1423.585 | BR51: =SUM(BR49:BR50) -> 1028.189 | BS51: =SUM(BS49:BS50) -> 138.711 | BT51: =SUM(BT49:BT50) -> 1208.041 | BV51: =SUM(BV49:BV50) -> 2898.951 | BW51: =SUM(BW49:BW50) -> 2473.405 | BY51: =SUM(BY49:BY50) -> 3927.145 | BZ51: =SUM(BZ49:BZ50) -> 3791.335
B52: % growth | D52: =+D51/C51-1 -> 0.070595592 | E52: =+E51/D51-1 -> -0.4146972 | F52: =+F51/E51-1 -> 1.1515268 | G52: =+G51/F51-1 -> -0.029734291 | H52: =+H51/G51-1 -> 0.084979724 | I52: =+I51/H51-1 -> -0.091602874 | J52: =+J51/G51-1 -> -0.20358587 | K52: =+K51/J51-1 -> -0.42530702 | L52: =+L51/J51-1 -> -0.058114959 | M52: =+M51/L51-1 -> 0.19695661 | N52: =+N51/L51-1 -> 0.22002377 | O52: =+O51/N51-1 -> 0.084464369 | P52: =+P51/N51-1 -> -0.45414639 | Q52: =+Q51/P51-1 -> -0.053884502 | AB52: =+AB51/X51-1 -> 0.038411652 | AC52: =+AC51/Y51-1 -> -0.082396129 | AD52: =+AD51/Z51-1 -> -0.02684336 | AE52: =+AE51/AA51-1 -> -0.04972201 | AF52: =+AF51/AB51-1 -> -0.045161024 | AG52: =+AG51/AC51-1 -> 0.10151241 | AH52: =+AH51/AD51-1 -> 0.095339951 | AI52: =+AI51/AE51-1 -> 0.20510202 | AM52: =AM51/AE51-1 -> -0.24715461 | AN52: =AN51/AF51-1 -> -0.047385783 | AO52: =AO51/AG51-1 -> 0.0051379079 | AP52: =AP51/AH51-1 -> 0.074182306 | AQ52: =AQ51/AI51-1 -> -0.37606742 | AR52: =AR51/AF51-1 -> -0.28178401 | AS52: =AS51/AG51-1 -> -0.24258969 | AT52: =AT51/AH51-1 -> -0.13339172 | AU52: =AU51/AM51-1 -> -1.9106349 | AV52: =AV51/AH51-1 -> -0.24607914 | AW52: =AW51/AM51-1 -> -0.12205537 | AX52: =AX51/AR51-1 -> 0.19204636 | AY52: =AY51/AS51-1 -> 0.018365918 | AZ52: =AZ51/AS51-1 -> 0.15274748 | BA52: =BA51/AT51-1 -> 0.023297383 | BB52: =BB51/AT51-1 -> 0.091231907 | BC52: =BC51/AV51-1 -> 0.11681896 | BD52: =BD51/AW51-1 -> 0.36250532 | BE52: =BE51/AW51-1 -> 0.63618499 | BF52: =BF51/AZ51-1 -> 0.10995263 | BG52: =BG51/AY51-1 -> 0.036806288 | BH52: =BH51/BO51-1 -> 0.15011705 | BI52: =BI51/BP51-1 -> -0.15388474 | BJ52: =BJ51/BQ51-1 -> -0.11114124 | BK52: =BK51/BR51-1 -> 0.28179644 | BL52: =BL51/BS51-1 -> 0.13226781 | BM52: =BM51/BT51-1 -> 0.10286158 | BO52: =BO51/AW51-1 -> 0.49540232 | BP52: =BP51/AY51-1 -> 0.31584491 | BQ52: =BQ51/BA51-1 -> -0.47046498 | BR52: =BR51/BC51-1 -> -0.59718986 | BS52: =BS51/BO51-1 -> -0.94681051 | BT52: =BT51/BP51-1 -> -0.5826488 | BW52: =BW51/BV51-1 -> -0.1467931 | BZ52: =BZ51/BY51-1 -> -0.034582375
B53: % margin | C53: =C51/C7 -> 0.38922135 | D53: =D51/D7 -> 0.36825352 | E53: =E51/E7 -> 0.22020168 | F53: =F51/F7 -> 0.46032699 | G53: =G51/G7 -> 0.45365452 | H53: =H51/H7 -> 0.45994753 | I53: =I51/I7 -> 0.39320126 | J53: =J51/J7 -> 0.43734966 | ... R53: =R51/R7 -> 0.4301058 | T53: =T51/T7 -> 0.34932412 | U53: =U51/U7 -> -0.18636831 | V53: =V51/V7 -> 0.38984974 | W53: =W51/W7 -> 0.31987739 | X53: =X51/X7 -> 0.48310554 | Y53: =Y51/Y7 -> 0.45852746 | Z53: =Z51/Z7 -> 0.45773406 | AA53: =AA51/AA7 -> 0.44304035 | ... AI53: =AI51/AI7 -> 0.46057609 | AM53: =AM51/AM7 -> 0.37222562 | AN53: =AN51/AN7 -> 0.41959823 | AO53: =AO51/AO7 -> 0.42757788 | AP53: =AP51/AP7 -> 0.44852471 | AQ53: =AQ51/AQ7 -> 0.27991369 | AR53: =AR51/AR7 -> 0.41068061 | AS53: =AS51/AS7 -> 0.41559295 | AT53: =AT51/AT7 -> 0.46017902 | ... BM53: =BM51/BM7 -> 0.47584577 | BO53: =BO51/BO7 -> 0.43224936 | BP53: =BP51/BP7 -> 0.50435987 | BQ53: =BQ51/BQ7 -> 0.42883768 | BR53: =BR51/BR7 -> 0.33546156 | BS53: =BS51/BS7 -> 0.33165328 | BT53: =BT51/BT7 -> 0.41773884 | BV53: =BV51/BV7 -> 0.4453933 | BW53: =BW51/BW7 -> 0.42220698 | BY53: =BY51/BY7 -> 0.41019967 | BZ53: =BZ51/BZ7 -> 0.43187611
B55: Adjustment | C55: =C59-C51 -> -381.063 | D55: =D59-D51 -> 243.848 | E55: =E59-E51 -> 3074.445 | F55: =F59-F51 -> -697.212 | G55: =G59-G51 -> -323.003 | H55: =H59-H51 -> -508.928 | I55: =I59-I51 -> 1612.315 | J55: =J59-J51 -> 157.729 | ... R55: =R59-R51 -> 289.436 | T55: =T59-T51 -> -2008.002 | U55: =U59-U51 -> 1093.435 | V55: =V59-V51 -> -2340.452 | W55: =W59-W51 -> 6329.464 | X55: =X59-X51 -> -452.438 | Y55: =Y59-Y51 -> -151.074 | Z55: =Z59-Z51 -> -42.341 | AA55: =AA59-AA51 -> -51.359 | ... AI55: =AI59-AI51 -> -137.732 | AM55: =AM59-AM51 -> 335.531 | AN55: =AN59-AN51 -> 183.683 | AO55: =AO59-AO51 -> 144.008 | AP55: =AP59-AP51 -> -52.832 | AQ55: =AQ59-AQ51 -> 1337.456 | AR55: =AR59-AR51 -> 199.213 | AS55: =AS59-AS51 -> 169.864 | AT55: =AT59-AT51 -> -155.162 | ... BM55: =BM59-BM51 -> 23.562 | BO55: =BO59-BO51 -> 76.976 | BP55: =BP59-BP51 -> -90.997 | BQ55: =BQ59-BQ51 -> 89.415 | BR55: =BR59-BR51 -> 385.711 | BS55: =BS59-BS51 -> -180.84 | BT55: =BT59-BT51 -> 11.128 | BV55: =BV59-BV51 -> 6.799 | BW55: =BW59-BW51 -> 185.81 | BY55: =BY59-BY51 -> 392.455 | BZ55: =BZ59-BZ51 -> 230.3
B56: Adj. EBITDA (Pre-IFRS) | C56: 8012.648 | D56: 9230.118 | E56: 8334.134 | F56: 9311.3 | G56: 10656.875 | H56: 11404.017 | I56: 9596.645 | J56: 8902.259 | K56: 9596.645 | L56: 8619.914 | M56: 9628.872 | N56: 9909.3 | O56: 11129.2 | P56: 5688.317 | Q56: 5460.443
B57: % growth | D57: =+D56/C56-1 -> 0.15194353 | E57: =+E56/D56-1 -> -0.097071782 | F57: =+F56/E56-1 -> 0.11724865 | G57: =+G56/F56-1 -> 0.1445099 | H57: =+H56/G56-1 -> 0.07010892 | I57: =+I56/H56-1 -> -0.15848556 | J57: =+J56/G56-1 -> -0.16464639 | K57: =+K56/J56-1 -> 0.078001101 | L57: =+L56/J56-1 -> -0.031716107 | M57: =+M56/L56-1 -> 0.11704966 | N57: =+N56/L56-1 -> 0.14958223 | O57: =+O56/N56-1 -> 0.12310658 | P57: =+P56/N56-1 -> -0.42596177 | Q57: =+Q56/P56-1 -> -0.040060004
B58: % margin | C58: =C56/C7 -> 0.37155123 | D58: =D56/D7 -> 0.3782463 | E58: =E56/E7 -> 0.34891612 | F58: =F56/F7 -> 0.37876507 | G58: =G56/G7 -> 0.44030904 | H58: =H56/H7 -> 0.4402983 | I58: =I56/I7 -> 0.34868996 | J58: =J56/J7 -> 0.44523833 | ... Q58: =Q56/Q7 -> 0.46440248 | T58: =T56/T7 -> 0 | U58: =U56/U7 -> 0 | V58: =V56/V7 -> 0 | W58: =W56/W7 -> 0 | X58: =X56/X7 -> 0 | Y58: =Y56/Y7 -> 0 | Z58: =Z56/Z7 -> 0 | AA58: =AA56/AA7 -> 0
B59: Adj. EBITDA | C59: =+C56 -> 8012.648 | D59: =+D56 -> 9230.118 | E59: =+E56 -> 8334.134 | F59: 10619.15 | G59: 10656.875 | H59: 11404.017 | I59: 12434 | J59: 8902.259 | K59: 9596.645 | L59: 8619.914 | M59: 9628.872 | N59: 9909.3 | O59: =O56 -> 11129.2 | P59: =P56 -> 5688.317 | Q59: =Q56 -> 5460.443 | R59: =SUM(BJ59:BM59) -> 4362.091 | T59: =+T56 -> 0 | U59: =+U56 -> 0 | V59: =+V56 -> 0 | W59: =E59-V59-U59-T59 -> 8334.134 | X59: 2421.768 | Y59: =5092.295-X59 -> 2670.527 | Z59: =7893.972-X59-Y59 -> 2801.677 | AA59: =F59-Z59-Y59-X59 -> 2725.178 | AB59: 2503.893 | AC59: =5087.643-AB59 -> 2583.75 | AD59: =7927.281-AB59-AC59 -> 2839.638 | AE59: =G59-AD59-AC59-AB59 -> 2729.594 | AF59: 2691.855 | AG59: =5502.723-AF59 -> 2810.868 | AH59: =8362.109-AF59-AG59 -> 2859.386 | AI59: =H59-AH59-AG59-AF59 -> 3041.908 | AM59: 2321.9 | AN59: 2898.463 | AO59: 3010.6 | AP59: 3203.6 | AQ59: =I59-SUM(AN59:AP59) -> 3321.337 | AR59: 2246 | AS59: =4575.952-AR59 -> 2329.952 | AT59: 2472 | AU59: =K59-SUM(AR59:AT59) -> 2548.693 | AV59: 2307.8 | AW59: =L59-AR59-AS59-AV59 -> 1736.162 | AX59: 2416.731 | AY59: 2183.3 | AZ59: =5145.504-AX59 -> 2728.773 | BA59: =4686.459-AY59 -> 2503.159 | BB59: 2714 | BC59: 2538 | BD59: =M59-SUM(AX59,AZ59,BC59) -> 1945.368 | BE59: 2736.869 | BF59: =5562.067-BE59 -> 2825.198 | BG59: 2634.8 | BH59: =O59-SUM(BE59,BF59,BG59) -> 2932.333 | BI59: 2454.216 | BJ59: 1440 | BK59: 1362.4 | BL59: =Q59-SUM(BI59,BJ59,BK59) -> 203.827 | BM59: 1355.864 | BO59: =N59-SUM(AY59,BA59,BC59) -> 2684.841 | BP59: 2803.546 | BQ59: 1513 | BR59: 1413.9 | BS59: =P59-SUM(BP59:BR59) -> -42.129 | BT59: 1219.169 | BV59: 2905.75 | BW59: 2659.215 | BY59: 4319.6 | BZ59: 4021.635
B60: % growth | D60: =+D59/C59-1 -> 0.15194353 | E60: =+E59/D59-1 -> -0.097071782 | F60: =+F59/E59-1 -> 0.27417558 | G60: =+G59/F59-1 -> 0.0035525442 | H60: =+H59/G59-1 -> 0.07010892 | I60: =+I59/H59-1 -> 0.090317561 | J60: =+J59/G59-1 -> -0.16464639 | K60: =+K59/J59-1 -> 0.078001101 | L60: =+L59/J59-1 -> -0.031716107 | M60: =+M59/L59-1 -> 0.11704966 | N60: =+N59/L59-1 -> 0.14958223 | O60: =+O59/N59-1 -> 0.12310658 | P60: =+P59/N59-1 -> -0.42596177 | Q60: =+Q59/P59-1 -> -0.040060004 | AB60: =+AB59/X59-1 -> 0.033911176 | AC60: =+AC59/Y59-1 -> -0.032494335 | AD60: =+AD59/Z59-1 -> 0.013549385 | AE60: =+AE59/AA59-1 -> 0.0016204446 | AF60: =+AF59/AB59-1 -> 0.075067904 | AG60: =+AG59/AC59-1 -> 0.087902467 | AH60: =+AH59/AD59-1 -> 0.0069544076 | AI60: =+AI59/AE59-1 -> 0.11441775 | AM60: =AM59/AE59-1 -> -0.14936067 | AN60: =AN59/AF59-1 -> 0.07675302 | AO60: =AO59/AG59-1 -> 0.071057054 | AP60: =AP59/AH59-1 -> 0.12038039 | AQ60: =AQ59/AI59-1 -> 0.09185978 | AR60: =AR59/AF59-1 -> -0.16563114 | AS60: =AS59/AG59-1 -> -0.17109163 | AT60: =AT59/AH59-1 -> -0.13547874 | AU60: =AU59/AM59-1 -> 0.09767561 | AV60: =AV59/AH59-1 -> -0.19290365 | AW60: =AW59/AM59-1 -> -0.25226668 | AX60: =AX59/AR59-1 -> 0.076015583 | AY60: =AY59/AS59-1 -> -0.062942069 | AZ60: =AZ59/AS59-1 -> 0.17117134 | BA60: =BA59/AT59-1 -> 0.012604773 | BB60: =BB59/AT59-1 -> 0.09789644 | BC60: =BC59/AV59-1 -> 0.099748678 | BD60: =BD59/AW59-1 -> 0.12049912 | BE60: =BE59/AW59-1 -> 0.57639034 | BF60: =BF59/AZ59-1 -> 0.035336395 | BG60: =BG59/AY59-1 -> 0.20679705 | BH60: =BH59/BO59-1 -> 0.09218125 | BI60: =BI59/BP59-1 -> -0.12460291 | BJ60: =BJ59/BQ59-1 -> -0.048248513 | BK60: =BK59/BR59-1 -> -0.036424075 | BL60: =BL59/BS59-1 -> -5.8381637 | BM60: =BM59/BT59-1 -> 0.11212145 | BO60: =BO59/AW59-1 -> 0.54642309 | BP60: =BP59/AY59-1 -> 0.28408647 | BQ60: =BQ59/BA59-1 -> -0.39556377 | BR60: =BR59/BC59-1 -> -0.4429078 | BS60: =BS59/BO59-1 -> -1.0156914 | BT60: =BT59/BP59-1 -> -0.56513323 | BW60: =BW59/BV59-1 -> -0.084843844 | BZ60: =BZ59/BY59-1 -> -0.068979767
B61: % margin | C61: =C59/C7 -> 0.37155123 | D61: =D59/D7 -> 0.3782463 | E61: =E59/E7 -> 0.34891612 | F61: =F59/F7 -> 0.4319658 | G61: =G59/G7 -> 0.44030904 | H61: =H59/H7 -> 0.4402983 | I61: =I59/I7 -> 0.45178403 | J61: =J59/J7 -> 0.44523833 | ... R61: =R59/R7 -> 0.46067261 | T61: =T59/T7 -> 0 | U61: =U59/U7 -> 0 | V61: =V59/V7 -> 0 | W61: =W59/W7 -> 1.3298453 | X61: =X59/X7 -> 0.40705835 | Y61: =Y59/Y7 -> 0.43397701 | Z61: =Z59/Z7 -> 0.45091944 | AA61: =AA59/AA7 -> 0.43484521 | ... AI61: =AI59/AI7 -> 0.44062538 | AM61: =AM59/AM7 -> 0.43510076 | AN61: =AN59/AN7 -> 0.4479884 | AO61: =AO59/AO7 -> 0.44905796 | AP61: =AP59/AP7 -> 0.44124789 | AQ61: =AQ59/AQ7 -> 0.4686207 | AR61: =AR59/AR7 -> 0.450652 | AS61: =AS59/AS7 -> 0.44827416 | AT61: =AT59/AT7 -> 0.43300053 | ... BM61: =BM59/BM7 -> 0.48426118 | BO61: =BO59/BO7 -> 0.44500801 | BP61: =BP59/BP7 -> 0.48850409 | BQ61: =BQ59/BQ7 -> 0.45577286 | BR61: =BR59/BR7 -> 0.46130536 | BS61: =BS59/BS7 -> -0.10072901 | BT61: =BT59/BT7 -> 0.42158689 | BV61: =BV59/BV7 -> 0.4464379 | BW61: =BW59/BW7 -> 0.4539245 | BY61: =BY59/BY7 -> 0.45119253 | BZ61: =BZ59/BZ7 -> 0.4581099
B63: CASH FLOW | C63: =+C48 -> 42707 | D63: =+D48 -> 43073 | E63: =E3 -> 43438 | F63: =F3 -> 43803 | G63: =G3 -> 44169 | H63: =H3 -> 44561 | I63: =I3 -> 44926 | J63: =+J48 -> 44561 | K63: =K3 -> 44926 | L63: =L3 -> 44926 | M63: =M3 -> 45291 | N63: =N3 -> 45291 | O63: =O3 -> 45657 | P63: =P3 -> 45657 | Q63: =Q3 -> 46022 | R63: =+R48 -> 46112 | T63: =+T48 -> 43190 | U63: =+U48 -> 43281 | V63: =+V48 -> 43373 | W63: =+W48 -> 43465 | X63: =+X48 -> 43555 | Y63: =+Y48 -> 43646 | Z63: =+Z48 -> 43738 | AA63: =+AA48 -> 43830 | ... BM63: =+BM48 -> 46112 | BO63: =+BO48 -> 45291 | BP63: =+BP48 -> 45382 | BQ63: =+BQ48 -> 45473 | BR63: =+BR48 -> 45565 | BS63: =+BS48 -> 45657 | BT63: =+BT48 -> 45747 | BV63: =+BV48 -> 45473 | BW63: =+BW48 -> 45838 | BY63: =+BY48 -> 45565 | BZ63: =+BZ48 -> 45930
B64: Adjusted EBITDA | C64: =C59 -> 8012.648 | D64: =D59 -> 9230.118 | E64: =E59 -> 8334.134 | F64: =F59 -> 10619.15 | G64: =G59 -> 10656.875 | H64: =H59 -> 11404.017 | I64: =I59 -> 12434 | J64: =J59 -> 8902.259 | ... R64: =R59 -> 4362.091 | T64: =T59 -> 0 | U64: =U59 -> 0 | V64: =V59 -> 0 | W64: =W59 -> 8334.134 | X64: =X59 -> 2421.768 | Y64: =Y59 -> 2670.527 | Z64: =Z59 -> 2801.677 | AA64: =AA59 -> 2725.178 | ... AI64: =AI59 -> 3041.908 | AN64: =AN59 -> 2898.463 | AO64: =AO59 -> 3010.6 | AP64: =AP59 -> 3203.6 | AQ64: =AQ59 -> 3321.337 | AR64: =AR59 -> 2246 | AS64: =AS59 -> 2329.952 | AT64: =AT59 -> 2472 | AU64: =AU59 -> 2548.693 | ... BM64: =BM59 -> 1355.864 | BO64: =BO59 -> 2684.841 | BP64: =BP59 -> 2803.546 | BQ64: =BQ59 -> 1513 | BR64: =BR59 -> 1413.9 | BS64: =BS59 -> -42.129 | BT64: =BT59 -> 1219.169 | BV64: =BV59 -> 2905.75 | BW64: =BW59 -> 2659.215 | BY64: =BY59 -> 4319.6 | BZ64: =BZ59 -> 4021.635
B65: Working Capital | C65: =21480.09-12804.218 -> 8675.872 | D65: =23648.914-15884.795 -> 7764.119 | E65: =24430.358-16116.096 -> 8314.262 | F65: =24875.636-13413.645 -> 11461.991 | G65: =24167.782-15053.69 -> 9114.092 | H65: =25321.996-14459.604 -> 10862.392 | I65: =24059.934-12769.56 -> 11290.374 | J65: =25250.051-14438.737 -> 10811.314 | K65: =24059.934-12769.56 -> 11290.374 | L65: =23956.521-12524.399 -> 11432.122 | M65: =21975.889-11319.163 -> 10656.726 | N65: =21978.081-11142.145 -> 10835.936 | O65: =21486.096-9786.369 -> 11699.727 | P65: =21720.526-9879.624 -> 11840.902 | Q65: =12752.577-6840.741 -> 5911.836 | R65: =BJ65+BK65+BL65+BM65 -> 4343.472 | T65: =5831.317-4373.928 -> 1457.389 | U65: =11153.032-6911.632-T65 -> 2784.011 | V65: =16960.672-10418.513-T65-U65 -> 2300.759 | W65: =+E65-T65-U65-V65 -> 1772.103 | X65: =5905.106-3548.173 -> 2356.933 | Y65: =12162.747-7467.935-X65 -> 2337.879 | Z65: =18633.972-10442.32-X65-Y65 -> 3496.84 | AA65: =+F65-X65-Y65-Z65 -> 3270.339 | AB65: =5973.926-3540.341 -> 2433.585 | AC65: =11043.202-5262.221-AB65 -> 3347.396 | AD65: =18092.279-10347.167-AB65-AC65 -> 1964.131 | AE65: =+G65-AB65-AC65-AD65 -> 1368.98 | AF65: =5784.876-3687.727 -> 2097.149 | AG65: =12151.134-6739.762-AF65 -> 3314.223 | AH65: =18615.589-9720.797-AF65-AG65 -> 3483.42 | AI65: =+H65-AF65-AG65-AH65 -> 1967.6 | AN65: =6629.055-3766.079 -> 2862.976 | AO65: =13412.632-7521.492-AN65 -> 3028.164 | AP65: =20501.119-11570.153-AN65-AO65 -> 3039.826 | AQ65: =I65-SUM(AN65:AP65) -> 2359.408 | AR65: =6629.055-3766.079 -> 2862.976 | AS65: =13412.632-7521.492-AR65 -> 3028.164 | AT65: =20501.119-11570.153-AR65-AS65 -> 3039.826 | AU65: =K65-AR65-AS65-AT65 -> 2359.408 | AV65: =20501.119-11570.153-AR65-AS65 -> 3039.826 | AW65: =L65-AR65-AS65-AV65 -> 2501.156 | AX65: =5213.016-3022.465 -> 2190.551 | AY65: =5213.016-3022.465 -> 2190.551 | AZ65: =10862.801-6222.873-AX65 -> 2449.377 | BA65: =10862.801-6222.873-AY65 -> 2449.377 | BB65: =17000.952-9032.179-AX65-AZ65 -> 3328.845 | BC65: =17000.952-9032.179-AX65-AZ65 -> 3328.845 | BD65: =M65-AZ65-AX65-BC65 -> 2687.953 | BE65: =5436.013-2567.969 -> 2868.044 | BF65: =11389.042-5326.859-BE65 -> 3194.139 | BG65: =16943.202-8065.736-BF65-BE65 -> 2815.283 | BH65: =O65-SUM(BE65:BG65) -> 2822.261 | BI65: =(5120244-2629715)/1000 -> 2490.529 | BJ65: =BW65-BI65 -> 776.222 | BK65: =BZ65-BW65 -> 1401.312 | BL65: =Q65-SUM(BI65:BK65) -> 1243.773 | BM65: =2508.788-1586.623 -> 922.165 | BO65: =N65-SUM(AY65,BA65,BC65) -> 2867.163 | BP65: =5436.013-2567.969 -> 2868.044 | BQ65: =BV65-BP65 -> 3194.139 | BR65: =BY65-BV65 -> 2815.283 | BS65: =P65-BR65-BQ65-BP65 -> 2963.436 | BT65: =(5120244-2629715)/1000 -> 2490.529 | BV65: =(11389042-5326859)/1000 -> 6062.183 | BW65: =(6769035-3502284)/1000 -> 3266.751 | BY65: =(16943202-8065736)/1000 -> 8877.466 | BZ65: =(9446520-4778457)/1000 -> 4668.063
B66: Taxes, net | C66: -744.903 | D66: -730.614 | E66: -1107.816 | F66: -1233.788 | G66: -576.986 | H66: -576.24 | I66: -875.464 | J66: -576.24 | K66: -875.464 | L66: -908.219 | M66: -675.481 | N66: -676.56 | O66: -639.607 | P66: -693.651 | Q66: -662.74 | R66: =BJ66+BK66+BL66+BM66 -> -722.991 | T66: -394.527 | U66: =-541.591-T66 -> -147.064 | V66: =-881.492-T66-U66 -> -339.901 | W66: =+E66-T66-U66-V66 -> -226.324 | X66: -289.278 | Y66: =-455.777-X66 -> -166.499 | Z66: =-807.9-X66-Y66 -> -352.123 | AA66: =F66-Z66-Y66-X66 -> -425.888 | AB66: -407.223 | AC66: =-746.768-AB66 -> -339.545 | AD66: =-809.825-AB66-AC66 -> -63.057 | AE66: =+G66-AB66-AC66-AD66 -> 232.839 | AF66: -191.944 | AG66: =-321.681-AF66 -> -129.737 | AH66: =-455.088-AF66-AG66 -> -133.407 | AI66: =+H66-AF66-AG66-AH66 -> -121.152 | AN66: -223.885 | AO66: =-383.481-AN66 -> -159.596 | AP66: =-691.825-AN66-AO66 -> -308.344 | AQ66: =I66-SUM(AN66:AP66) -> -183.639 | AR66: -223.885 | AS66: =-383.481-AR66 -> -159.596 | AT66: =-691.825-AR66-AS66 -> -308.344 | AU66: =K66-AR66-AS66-AT66 -> -183.639 | AV66: =-691.825-AR66-AS66 -> -308.344 | AW66: =L66-AR66-AS66-AV66 -> -216.394 | AX66: -211.656 | AY66: -211.656 | AZ66: =-349.048-AX66 -> -137.392 | BA66: =-349.048-AY66 -> -137.392 | BB66: =-514.829-AX66-AZ66 -> -165.781 | BC66: =-514.829-AX66-AZ66 -> -165.781 | BD66: =M66-AZ66-AX66-BC66 -> -160.652 | BE66: -204.765 | BF66: =-330.513-BE66 -> -125.748 | BG66: =-405.389-BF66-BE66 -> -74.876 | BH66: =O66-SUM(BE66:BG66) -> -234.218 | BI66: -284.532 | BJ66: =BW66-BI66 -> -163.453 | BK66: =BZ66-BW66 -> -88.978 | BL66: =Q66-SUM(BI66:BK66) -> -125.777 | BM66: -344.783 | BO66: =N66-SUM(AY66,BA66,BC66) -> -161.731 | BP66: -204.765 | BQ66: =BV66-BP66 -> -125.748 | BR66: =BY66-BV66 -> -74.876 | BS66: =P66-BR66-BQ66-BP66 -> -288.262 | BT66: -284.752 | BV66: -330.513 | BW66: -447.985 | BY66: -405.389 | BZ66: -536.963
B67: Cash interest paid | C67: -1153.868 | D67: -1297.431 | E67: -1102.214 | F67: -1689.589 | G67: -1400.405 | H67: -1398.06 | I67: -1590.874 | J67: -1398.06 | K67: -1590.874 | L67: -1589.069 | M67: -2303.003 | N67: -2296.339 | O67: -2157.191 | P67: -2157.191 | Q67: -1543.512 | R67: =BJ67+BK67+BL67+BM67 -> -1207.167 | T67: -348.107 | U67: =-612.9-T67 -> -264.793 | V67: =957.485-T67-U67 -> 1570.385 | W67: =+E67-T67-U67-V67 -> -2059.699 | X67: -297.38 | Y67: =-340.578-X67 -> -43.198 | Z67: =-1315.472-X67-Y67 -> -974.894 | AA67: =F67-Z67-Y67-X67 -> -374.117 | AB67: -506.676 | AC67: =-1278.07-AB67 -> -771.394 | AD67: =-1183.179-AB67-AC67 -> 94.891 | AE67: =+G67-AB67-AC67-AD67 -> -217.226 | AF67: -486.561 | AG67: =-738.536-AF67 -> -251.975 | AH67: =-1170.116-AF67-AG67 -> -431.58 | AI67: =+H67-AF67-AG67-AH67 -> -227.944 | AN67: -530.644 | AO67: =-783.551-AN67 -> -252.907 | AP67: =-1252.843-AN67-AO67 -> -469.292 | AQ67: =I67-SUM(AN67:AP67) -> -338.031 | AR67: -530.644 | AS67: =-783.551-AR67 -> -252.907 | AT67: =-1252.843-AR67-AS67 -> -469.292 | AU67: =K67-AR67-AS67-AT67 -> -338.031 | AV67: =-1252.843-AR67-AS67 -> -469.292 | AW67: =L67-AR67-AS67-AV67 -> -336.226 | AX67: -552.784 | AY67: -552.784 | AZ67: =-1215.876-AX67 -> -663.092 | BA67: =-1215.876-AY67 -> -663.092 | BB67: =-1919.34-AX67-AZ67 -> -703.464 | BC67: =-1919.34-AX67-AZ67 -> -703.464 | BD67: =M67-AZ67-AX67-BC67 -> -383.663 | BE67: -766.611 | BF67: =-1235.924-BE67 -> -469.313 | BG67: =-1801.317-BF67-BE67 -> -565.393 | BH67: =O67-SUM(BE67:BG67) -> -355.874 | BI67: -655.176 | BJ67: =BW67-BI67 -> -422.757 | BK67: =BZ67-BW67 -> -345.27 | BL67: =Q67-SUM(BI67:BK67) -> -120.309 | BM67: -318.831 | BO67: =N67-SUM(AY67,BA67,BC67) -> -376.999 | BP67: -766.611 | BQ67: =BV67-BP67 -> -469.313 | BR67: =BY67-BV67 -> -565.393 | BS67: =P67-BR67-BQ67-BP67 -> -355.874 | BT67: -655.176 | BV67: -1235.924 | BW67: -1077.933 | BY67: -1801.317 | BZ67: -1423.203
B68: Net cash from operations | C68: =SUM(C64:C67) -> 14789.749 | D68: =SUM(D64:D67) -> 14966.192 | E68: =SUM(E64:E67) -> 14438.366 | F68: =SUM(F64:F67) -> 19157.764 | G68: =SUM(G64:G67) -> 17793.576 | H68: =SUM(H64:H67) -> 20292.109 | I68: =SUM(I64:I67) -> 21258.036 | J68: =SUM(J64:J67) -> 17739.273 | ... R68: =SUM(R64:R67) -> 6775.405 | T68: =SUM(T64:T67) -> 714.755 | U68: =SUM(U64:U67) -> 2372.154 | V68: =SUM(V64:V67) -> 3531.243 | W68: =SUM(W64:W67) -> 7820.214 | X68: =SUM(X64:X67) -> 4192.043 | Y68: =SUM(Y64:Y67) -> 4798.709 | Z68: =SUM(Z64:Z67) -> 4971.5 | AA68: =SUM(AA64:AA67) -> 5195.512 | ... AI68: =SUM(AI64:AI67) -> 4660.412 | AN68: =SUM(AN64:AN67) -> 5006.91 | AO68: =SUM(AO64:AO67) -> 5626.261 | AP68: =SUM(AP64:AP67) -> 5465.79 | AQ68: =SUM(AQ64:AQ67) -> 5159.075 | AR68: =SUM(AR64:AR67) -> 4354.447 | AS68: =SUM(AS64:AS67) -> 4945.613 | AT68: =SUM(AT64:AT67) -> 4734.19 | AU68: =SUM(AU64:AU67) -> 4386.431 | ... BM68: =SUM(BM64:BM67) -> 1614.415 | BO68: =SUM(BO64:BO67) -> 5013.274 | BP68: =SUM(BP64:BP67) -> 4700.214 | BQ68: =SUM(BQ64:BQ67) -> 4112.078 | BR68: =SUM(BR64:BR67) -> 3588.914 | BS68: =SUM(BS64:BS67) -> 2277.171 | BT68: =SUM(BT64:BT67) -> 2769.77 | BV68: =SUM(BV64:BV67) -> 7401.496 | BW68: =SUM(BW64:BW67) -> 4400.048 | BY68: =SUM(BY64:BY67) -> 10990.36 | BZ68: =SUM(BZ64:BZ67) -> 6729.532
B69: Net Capex | C69: =81.187-5564.249 -> -5483.062 | D69: =28.945-4914.051 -> -4885.106 | E69: =57.412-6694.537 -> -6637.125 | F69: =28.485-6799.221 -> -6770.736 | G69: =64.877-4583.843 -> -4518.966 | H69: =118.545-6487.545 -> -6369 | I69: =30.588-9682.591 -> -9652.003 | J69: =-6366.742+118.547 -> -6248.195 | K69: =30.588-9682.591 -> -9652.003 | L69: =30.713-9760.988 -> -9730.275 | M69: =20.25-6969.664 -> -6949.414 | N69: =20.251-7126.661 -> -7106.41 | O69: =-5055.192+12.015 -> -5043.177 | P69: =14.89-5141.204 -> -5126.314 | Q69: =12.382-2040.639 -> -2028.257 | R69: =BJ69+BK69+BL69+BM69 -> -1643.64 | T69: =0.998-1317.153 -> -1316.155 | U69: =6.89-3169.036-T69 -> -1845.991 | V69: =24.272-4992.259-T69-U69 -> -1805.841 | W69: =+E69-T69-U69-V69 -> -1669.138 | X69: =5.206-1688.239 -> -1683.033 | Y69: =9.866-3106.514-X69 -> -1413.615 | Z69: =16.053-4546.958-X69-Y69 -> -1434.257 | AA69: =F69-Z69-Y69-X69 -> -2239.831 | AB69: =20.134-998.89+248.355 -> -730.401 | AC69: =26.49-2465.631-AB69 -> -1708.74 | AD69: =15.215-3496.469-AB69-AC69 -> -1042.113 | AE69: =+G69-AB69-AC69-AD69 -> -1037.712 | AF69: =52.814-1347.493+0 -> -1294.679 | AG69: =83.018-3265.852-AF69 -> -1888.155 | AH69: =95.498-4811.468-AF69-AG69 -> -1533.136 | AI69: =+H69-AF69-AG69-AH69 -> -1653.03 | AN69: =1.932-1713.698 -> -1711.766 | AO69: =11.371-5171.936-AN69 -> -3448.799 | AP69: =13.488-7786.773-AN69-AO69 -> -2612.72 | AQ69: =I69-SUM(AN69:AP69) -> -1878.718 | AR69: =1.932-1713.698 -> -1711.766 | AS69: =11.371-5171.936-AR69 -> -3448.799 | AT69: =13.488-7786.773-AR69-AS69 -> -2612.72 | AU69: =K69-AR69-AS69-AT69 -> -1878.718 | AV69: =13.488-7786.773-AR69-AS69 -> -2612.72 | AW69: =L69-AR69-AS69-AV69 -> -1956.99 | AX69: =5.215-1842.987 -> -1837.772 | AY69: =5.215-1842.987 -> -1837.772 | AZ69: =10.275-3832.772-AX69 -> -1984.725 | BA69: =10.275-3832.772-AY69 -> -1984.725 | BB69: =15.999-5571.18-AX69-AZ69 -> -1732.684 | BC69: =15.999-5571.18-AX69-AZ69 -> -1732.684 | BD69: =M69-AZ69-AX69-BC69 -> -1394.233 | BE69: =1.882-1535.896 -> -1534.014 | BF69: =3.133-2966.614-BE69 -> -1429.467 | BG69: =-3934.703+4.78-BF69-BE69 -> -966.442 | BH69: =O69-SUM(BE69:BG69) -> -1113.254 | BI69: =(-866011+5856)/1000 -> -860.155 | BJ69: =BW69-BI69 -> -397.568 | BK69: =BZ69-BW69 -> -422.349 | BL69: =Q69-SUM(BI69:BK69) -> -348.185 | BM69: =-477.051+1.513 -> -475.538 | BO69: =N69-SUM(AY69,BA69,BC69) -> -1551.229 | BP69: =1.882-1535.896 -> -1534.014 | BQ69: =BV69-BP69 -> -1429.467 | BR69: =BY69-BV69 -> -966.442 | BS69: =P69-BR69-BQ69-BP69 -> -1196.391 | BT69: =5.856-866.011 -> -860.155 | BV69: =(3133-2966614)/1000 -> -2963.481 | BW69: =(8235-1265958)/1000 -> -1257.723 | BY69: =(4780-3934703)/1000 -> -3929.923 | BZ69: =(8325-1688397)/1000 -> -1680.072
B70: Purchase and development of intangible assets | C70: =-1003.074 -> -1003.074 | D70: -99.372 | E70: -540.64 | F70: -429.628 | G70: -596.723 | H70: =-573.915+3.568 -> -570.347 | I70: =-446.079+1.556 -> -444.523 | J70: =-573.915+3.568 -> -570.347 | K70: =-446.079+1.556 -> -444.523 | L70: =1.556-448.614 -> -447.058 | M70: -732.999 | N70: -732.999 | O70: -799.284 | P70: =-799.485 -> -799.485 | Q70: =-331.672 -> -331.672 | R70: =BJ70+BK70+BL70+BM70 -> -304.219 | T70: -389.556 | U70: =-494.806-T70 -> -105.25 | V70: =-622.209-T70-U70 -> -127.403 | W70: =+E70-T70-U70-V70 -> 81.569 | X70: -0.689 | Y70: =-11.116-X70 -> -10.427 | Z70: =-331.006-X70-Y70 -> -319.89 | AA70: =F70-Z70-Y70-X70 -> -98.622 | AB70: -42.802 | AC70: =-65.49-AB70 -> -22.688 | AD70: =-243.385-AB70-AC70 -> -177.895 | AE70: =+G70-AB70-AC70-AD70 -> -353.338 | AF70: -25.56 | AG70: =-174.804-AF70 -> -149.244 | AH70: =-441.861-AF70-AG70 -> -267.057 | AI70: =+H70-AF70-AG70-AH70 -> -128.486 | AN70: -62.011 | AO70: =-147.477-AN70 -> -85.466 | AP70: =-327.082-AN70-AO70 -> -179.605 | AQ70: =I70-SUM(AN70:AP70) -> -117.441 | AR70: -62.011 | AS70: =-147.477-AR70 -> -85.466 | AT70: =-327.082-AR70-AS70 -> -179.605 | AU70: =K70-AR70-AS70-AT70 -> -117.441 | AV70: =-327.082-AR70-AS70 -> -179.605 | AW70: =L70-AR70-AS70-AV70 -> -119.976 | AX70: -158.654 | AY70: -158.654 | AZ70: =-279.505-AX70 -> -120.851 | BA70: =-279.505-AY70 -> -120.851 | BB70: =-476.577-AX70-AZ70 -> -197.072 | BC70: =-476.577-AX70-AZ70 -> -197.072 | BD70: =M70-AZ70-AX70-BC70 -> -256.422 | BE70: -140.893 | BF70: =-335.924-BE70 -> -195.031 | BG70: =-579.111-BF70-BE70 -> -243.187 | BH70: =O70-SUM(BE70:BG70) -> -220.173 | BI70: -195.498 | BJ70: =BW70-BI70 -> -131.67 | BK70: =BZ70-BW70 -> -64.457 | BL70: =Q70-SUM(BI70:BK70) -> 59.953 | BM70: -168.045 | BO70: =N70-SUM(AY70,BA70,BC70) -> -256.422 | BP70: -140.893 | BQ70: =BV70-BP70 -> -195.031 | BR70: =BY70-BV70 -> -243.187 | BS70: =P70-BR70-BQ70-BP70 -> -220.374 | BT70: -195.498 | BV70: -335.924 | BW70: -327.168 | BY70: =(-579111)/1000 -> -579.111 | BZ70: =(-391625)/1000 -> -391.625
B71: Disposals/ Acquistion of subsidiaries | C71: =-57.421-83.471+118.229 -> -22.663 | D71: =-110.047-20.149+92.587 -> -37.609 | E71: =-18.398-57.003-83.435 -> -158.836 | F71: =1649.256+21.451-8.57-6.094 -> 1656.043 | G71: =-6.054-10.743-11.169-1.953 -> -29.919 | H71: =-2.421-12.672 -> -15.093 | I71: =-4.504-2780.487 -> -2784.991 | J71: =-2.421-12.672 -> -15.093 | K71: =-4.504-2780.487 -> -2784.991 | L71: =-3.773-2780.487-0.731 -> -2784.991 | M71: =-53.691-0.64 -> -54.331 | N71: =-53.691-0.64 -> -54.331 | O71: =-5.908-0.554 -> -6.462 | P71: =-5.908+23.538 -> 17.63 | Q71: =1340.823 -> 1340.823 | R71: =BJ71+BK71+BL71+BM71 -> 1340.823 | T71: -3.731 | U71: =-49.328-T71 -> -45.597 | V71: =-49.328-20.71-T71-U71 -> -20.71 | W71: =+E71-T71-U71-V71 -> -88.798 | X71: =1649.256-2.706-3.233 -> 1643.317 | Y71: =1649.256-6.561-X71 -> -0.622 | Z71: =1649.256-6.69-8.792-X71-Y71 -> -8.921 | AA71: =F71-Z71-Y71-X71 -> 22.269 | AB71: -8.365 | AC71: =0-1.542-1.182-AB71 -> 5.641 | AD71: =0-14.131-5.489-AB71-AC71 -> -16.896 | AE71: =+G71-AB71-AC71-AD71 -> -10.299 | AF71: -0.215 | AG71: =3.027-0-0.381-AF71 -> 2.861 | AH71: =3.591-2.302-AF71-AG71 -> -1.357 | AI71: =+H71-AF71-AG71-AH71 -> -16.382 | AN71: -0.808 | AO71: =-3.921-2784.89-AN71 -> -2788.003 | AP71: =-2788.061-4.015-AN71-AO71 -> -3.265 | AQ71: =I71-SUM(AN71:AP71) -> 7.085 | AR71: -0.808 | AS71: =-3.921-2784.89-AR71 -> -2788.003 | AT71: =-2788.061-4.015-AR71-AS71 -> -3.265 | AU71: =K71-AR71-AS71-AT71 -> 7.085 | AV71: =-2788.061-4.015-AR71-AS71 -> -3.265 | AW71: =L71-AR71-AS71-AV71 -> 7.085 | AX71: -0.46 | AY71: -0.46 | AZ71: =-51.786-0.46-AX71 -> -51.786 | BA71: =-51.786-0.46-AY71 -> -51.786 | BB71: =-51.768-0.46-AX71-AZ71 -> 0.018 | BC71: =-51.768-0.46-AX71-AZ71 -> 0.018 | BD71: =M71-AZ71-AX71-BC71 -> -2.103 | BE71: 0 | BF71: =5.283+0.091-BE71 -> 5.374 | BG71: =2.485-0.554-BF71-BE71 -> -3.443 | BH71: =O71-SUM(BE71:BG71) -> -8.393 | BI71: 0 | BJ71: =BW71-BI71 -> 1352.416 | BK71: =BZ71-BW71 -> -1.121 | BL71: =Q71-SUM(BI71:BK71) -> -10.472 | BM71: 0 | BO71: =N71-SUM(AY71,BA71,BC71) -> -2.103 | BP71: 0 | BQ71: =BV71-BP71 -> 28.821 | BR71: =BY71-BV71 -> -2.798 | BS71: =P71-BR71-BQ71-BP71 -> -8.393 | BT71: 0 | BV71: =(5283+23538)/1000 -> 28.821 | BW71: =(1352416)/1000 -> 1352.416 | BY71: =(2485+23538)/1000 -> 26.023 | BZ71: =(1351295)/1000 -> 1351.295
B72: Free cash flow | C72: =SUM(C68:C71) -> 8280.95 | D72: =SUM(D68:D71) -> 9944.105 | E72: =SUM(E68:E71) -> 7101.765 | F72: =SUM(F68:F71) -> 13613.443 | G72: =SUM(G68:G71) -> 12647.968 | H72: =SUM(H68:H71) -> 13337.669 | I72: =SUM(I68:I71) -> 8376.519 | J72: =SUM(J68:J71) -> 10905.638 | ... R72: =SUM(R68:R71) -> 6168.369 | T72: =SUM(T68:T71) -> -994.687 | U72: =SUM(U68:U71) -> 375.316 | V72: =SUM(V68:V71) -> 1577.289 | W72: =SUM(W68:W71) -> 6143.847 | X72: =SUM(X68:X71) -> 4151.638 | Y72: =SUM(Y68:Y71) -> 3374.045 | Z72: =SUM(Z68:Z71) -> 3208.432 | AA72: =SUM(AA68:AA71) -> 2879.328 | ... AI72: =SUM(AI68:AI71) -> 2862.514 | AN72: =SUM(AN68:AN71) -> 3232.325 | AO72: =SUM(AO68:AO71) -> -696.007 | AP72: =SUM(AP68:AP71) -> 2670.2 | AQ72: =SUM(AQ68:AQ71) -> 3170.001 | AR72: =SUM(AR68:AR71) -> 2579.862 | AS72: =SUM(AS68:AS71) -> -1376.655 | AT72: =SUM(AT68:AT71) -> 1938.6 | AU72: =SUM(AU68:AU71) -> 2397.357 | ... BM72: =SUM(BM68:BM71) -> 970.832 | BO72: =SUM(BO68:BO71) -> 3203.52 | BP72: =SUM(BP68:BP71) -> 3025.307 | BQ72: =SUM(BQ68:BQ71) -> 2516.401 | BR72: =SUM(BR68:BR71) -> 2376.487 | BS72: =SUM(BS68:BS71) -> 852.013 | BT72: =SUM(BT68:BT71) -> 1714.117 | BV72: =SUM(BV68:BV71) -> 4130.912 | BW72: =SUM(BW68:BW71) -> 4167.573 | BY72: =SUM(BY68:BY71) -> 6507.349 | BZ72: =SUM(BZ68:BZ71) -> 6009.13
B73: Other investing activities | C73: =479.338+0-1.622+186.804 -> 664.52 | D73: =140.068-0.649+0.025+239.343 -> 378.787 | E73: =-0.191+90.187-0.397+223.962 -> 313.561 | F73: =133.618-33.03+97.5+96.149+0.241+230.232-41.336-38.712 -> 444.662 | G73: =580.79+601.802+150.582-22.495-0.647+4.884+192.101 -> 1507.017 | H73: =150.263-1400.993+0.559-29.794-0.282+5.262+149.82+5.837 -> -1119.328 | I73: =-569.293-7.556+1753.04-95.703+1.094+16.524+228.644 -> 1326.75 | J73: =80.4-1400.993+0.559-123.866-0.282+5.262+149.82+5.837 -> -1283.263 | K73: =-569.293-7.556+1753.04-95.703+1.094+16.524+228.644 -> 1326.75 | L73: =-11584.996-SUM(L69,L70,L71) -> 1377.328 | M73: =-4700.105-SUM(M69,M70,M71) -> 3036.639 | N73: =-4914.237-SUM(N69,N70,N71) -> 2979.503 | O73: =-5576.479-SUM(O69,O70,O71) -> 272.444 | P73: =-1090.492+845.987-0.554-209.409+23.768-65.454+0.476+547.612+263.341 -> 315.275 | Q73: =-820.665+778.085-0.7+12.35-27.127+1.191+843.557+212.422 -> 999.113 | R73: =BJ73+BK73+BL73+BM73 -> 1893.7583 | T73: =31.252+0.209+65.802 -> 97.263 | U73: =-48.53+49.017+0.057+118.368-T73 -> 21.649 | V73: =36.394+90.187+0.064+168.292-U73-T73 -> 176.025 | W73: =+E73-T73-U73-V73 -> 18.624 | X73: =-4.08-21.933+0-0.522+55.239 -> 28.704 | Y73: =-212.808-27.544+96.149+0.092+107.769-X73 -> -65.046 | Z73: =-96.888-12.45+96.149+0.139+173.529-Y73-X73 -> 196.821 | AA73: =F73-Z73-Y73-X73 -> 284.183 | AB73: =320.872+73.725+0.564+42.985 -> 438.146 | AC73: =310.388-9.235+149.85+0.662+90.247+577.709-AB73 -> 681.475 | AD73: =383.407-2.025+0.027+130.304+580.79-1.899+150.506+6.783-AC73-AB73 -> 128.272 | AE73: =+G73-AB73-AC73-AD73 -> 259.124 | AF73: =-355.748+0.316-7.97+0.564+0.056+33.237 -> -329.545 | AG73: =-366.386-29.511-7.97+0.515-14.822+0.065+5.262+69.329-AF73 -> -13.973 | AH73: =-1.678-42.817+5.262-0.112+107.338-8.012+0.083-22.147-AF73-AG73 -> 381.435 | AI73: =+H73-AF73-AG73-AH73 -> -1157.245 | AN73: =-1798.861-AN71-AN70-AN69 -> -24.276 | AO73: =-46.432-8.165+0.224-87.182+0.935+78.807-AN73 -> -37.537 | AP73: =-4.441-9.796+0.232-98.055+0.171+132.967-AN73-AO73 -> 82.891 | AQ73: =I73-SUM(AN73:AP73) -> 1305.672 | AR73: =-1798.861-AR71-AR70-AR69 -> -24.276 | AS73: =-46.432-8.165+0.224-87.182+0.935+78.807-AR73 -> -37.537 | AT73: =-4.441-9.796+0.232-98.055+0.171+132.967-AR73-AS73 -> 82.891 | AU73: =K73-AR73-AS73-AT73 -> 1305.672 | AV73: =-4.441-9.796+0.232-98.055+0.171+132.967-AR73-AS73 -> 82.891 | AW73: =L73-AR73-AS73-AV73 -> 1356.25 | AX73: =-1332.048-AX71-AX70-AX69 -> 664.838 | AY73: =-1332.048-AY71-AY70-AY69 -> 664.838 | AZ73: =448.015+244.637-0.294+161.805-7.818+2431.867-77.338-AX73 -> 2536.036 | BA73: =448.015+244.637-0.294+161.805-7.818+2431.867-77.338-AY73 -> 2536.036 | BB73: =380.667-7.818+402-109.234+2431.867+0.111+0.443-95.118-0.932+368.897+233.232-AX73-AZ73 -> 403.241 | BC73: =380.667-7.818+402-109.234+2431.867+0.111+0.443-95.118-0.932+368.897+233.232-AX73-AZ73 -> 403.241 | BD73: =M73-AZ73-AX73-BC73 -> -567.476 | BE73: =-1359.606-BE71-BE70-BE69 -> 315.301 | BF73: =55.236+271.819+0.271+134.763-42.393+23.768-14.431-BE73 -> 113.732 | BG73: =-50.729-123.918+23.538-28.925+0.148+23.768+407.821+202.285-BF73-BE73 -> 24.955 | BH73: =O73-SUM(BE73:BG73) -> -181.544 | BI73: =(-891346-BI71-BI70-BI69)/1000 -> -890.29035 | BJ73: =BW73-BI73 -> 1325.2533 | BK73: =BZ73-BW73 -> 12.231 | BL73: =Q73-SUM(BI73:BK73) -> 551.919 | BM73: =-222.367+63.342-7.683-0.8+0.07+139.793+32 -> 4.355 | BO73: =N73-SUM(AY73,BA73,BC73) -> -624.612 | BP73: =-1359.606-BP71-BP70-BP69 -> 315.301 | BQ73: =BV73-BP73 -> 113.823 | BR73: =BY73-BV73 -> 0.772 | BS73: =P73-BR73-BQ73-BP73 -> -114.621 | BT73: =-311.164+230.742-1.254+32.138-22.046+0.394+165.459+70.038 -> 164.307 | BV73: =(55236-42393+23768-14431+271+271910+134763)/1000 -> 429.124 | BW73: =(17063-1208+24306-44814+1188+308105+130323)/1000 -> 434.963 | BY73: =(-50729-554-123918+23768-28925+148+407821+202285)/1000 -> 429.896 | BZ73: =(-182106-1202+41158-32759+1622+455617+164864)/1000 -> 447.194
B74: Equity Issuance/Buyback | C74: =10.477-0.171 -> 10.306 | D74: =7.65+0 -> 7.65 | E74: 10.963 | F74: 16.389 | G74: =-40.469 -> -40.469 | H74: -0.309 | I74: 0 | J74: -0.309 | K74: 0 | L74: 0 | M74: 0 | N74: 0 | O74: 0 | P74: 0 | Q74: 0 | R74: =BJ74+BK74+BL74+BM74 -> 1.828 | T74: 3.306 | U74: =6.497-T74 -> 3.191 | V74: =6.678-T74-U74 -> 0.181 | W74: =+E74-T74-U74-V74 -> 4.285 | X74: 4.158 | Y74: =16.389-X74 -> 12.231 | Z74: =16.389-Y74-X74 -> 0 | AA74: =F74-Z74-Y74-X74 -> 0 | AB74: 0 | AC74: =0-AB74 -> 0 | AD74: =0-40.469-AC74-AB74 -> -40.469 | AE74: =+G74-AB74-AC74-AD74 -> 0 | AF74: 0 | AG74: =0-AF74 -> 0 | AH74: =0-AG74-AF74 -> 0 | AI74: =+H74-AF74-AG74-AH74 -> -0.309 | AN74: 0 | AO74: =0-AN74 -> 0 | AP74: =31.122-AO74-AN74 -> 31.122 | AQ74: =I74-SUM(AN74:AP74) -> -31.122 | AR74: 0 | AS74: =0-AR74 -> 0 | AT74: =31.122-AS74-AR74 -> 31.122 | AU74: =K74-AR74-AS74-AT74 -> -31.122 | AV74: =31.122-AS74-AR74 -> 31.122 | AW74: =L74-AR74-AS74-AV74 -> -31.122 | AX74: 0 | AY74: 0 | AZ74: =0-AX74 -> 0 | BA74: =0-AY74 -> 0 | BB74: =25.764-AZ74-AX74 -> 25.764 | BC74: =25.764-AZ74-AX74 -> 25.764 | BD74: =M74-AZ74-AX74-BC74 -> -25.764 | BE74: 0 | BF74: =0-BE74 -> 0 | BG74: =0-BF74-BE74 -> 0 | BH74: =O74-SUM(BE74:BG74) -> 0 | BI74: 0 | BJ74: =BW74-BI74 -> -0.123 | BK74: =BZ74-BW74 -> 0.123 | BL74: =Q74-SUM(BI74:BK74) -> 0 | BM74: 1.828 | BO74: =N74-SUM(AY74,BA74,BC74) -> -25.764 | BP74: 0 | BQ74: =BV74-BP74 -> 0 | BR74: =BY74-BV74 -> 0 | BS74: =P74-BR74-BQ74-BP74 -> 0 | BT74: 0 | BV74: 0 | BW74: =(-123)/1000 -> -0.123 | BY74: 0 | BZ74: 0
B75: Dividends Paid | C75: =-790.477-112.241 -> -902.718 | D75: =-379.252-115.136 -> -494.388 | E75: =-691.114-164.331 -> -855.445 | F75: =-538.283-75.386 -> -613.669 | G75: =-595.993-256.739 -> -852.732 | H75: =-825.539-204.776 -> -1030.315 | I75: =-504.724-192.565 -> -697.289 | J75: =-825.539-204.776 -> -1030.315 | K75: =-504.724-192.565 -> -697.289 | L75: =-504.724-190.865 -> -695.589 | M75: =-1743.854-304.461 -> -2048.315 | N75: =-1743.854-304.461 -> -2048.315 | O75: =-918.192-343.718 -> -1261.91 | P75: =-918.192-344.389 -> -1262.581 | Q75: =-918.586-427.852 -> -1346.438 | R75: =BJ75+BK75+BL75+BM75 -> -1354.489 | T75: -5.605 | U75: =-21.603-T75 -> -15.998 | V75: =-267.116-237.627-T75-U75 -> -483.14 | W75: =+E75-T75-U75-V75 -> -350.702 | X75: 0 | Y75: =-48.051-218.307-X75 -> -266.358 | Z75: =-74.41-218.307-X75-Y75 -> -26.359 | AA75: =F75-Z75-Y75-X75 -> -320.952 | AB75: -3.78 | AC75: =-78.423-412.603-AB75 -> -487.246 | AD75: =-412.603-144.888-AB75-AC75 -> -66.465 | AE75: =+G75-AB75-AC75-AD75 -> -295.241 | AF75: -44.115 | AG75: =-107.294-458.631-AF75 -> -521.81 | AH75: =-141.672-825.539-AF75-AG75 -> -401.286 | AI75: =+H75-AF75-AG75-AH75 -> -63.104 | AN75: =-504.724-36.683 -> -541.407 | AO75: =-504.724-127.276-AN75 -> -90.593 | AP75: =-504.724-131.014-AN75-AO75 -> -3.738 | AQ75: =I75-SUM(AN75:AP75) -> -61.551 | AR75: =-504.724-36.683 -> -541.407 | AS75: =-504.724-127.276-AR75 -> -90.593 | AT75: =-504.724-131.014-AR75-AS75 -> -3.738 | AU75: =K75-AR75-AS75-AT75 -> -61.551 | AV75: =-504.724-131.014-AR75-AS75 -> -3.738 | AW75: =L75-AR75-AS75-AV75 -> -59.851 | AX75: =-1284.9-54.086 -> -1338.986 | AY75: =-1284.9-54.086 -> -1338.986 | AZ75: =-141.901-1284.9-AX75 -> -87.815 | BA75: =-141.901-1284.9-AY75 -> -87.815 | BB75: =-1284.9-237.5-AX75-AZ75 -> -95.599 | BC75: =-1284.9-237.5-AX75-AZ75 -> -95.599 | BD75: =M75-AZ75-AX75-BC75 -> -525.915 | BE75: -0.019 | BF75: =-155.408-459.096-BE75 -> -614.485 | BG75: =-459.096-279.024-BF75-BE75 -> -123.616 | BH75: =O75-SUM(BE75:BG75) -> -523.79 | BI75: -7.24 | BJ75: =BW75-BI75 -> -721.956 | BK75: =BZ75-BW75 -> -72.698 | BL75: =Q75-SUM(BI75:BK75) -> -544.544 | BM75: -15.291 | BO75: =N75-SUM(AY75,BA75,BC75) -> -525.915 | BP75: -0.019 | BQ75: =BV75-BP75 -> -614.485 | BR75: =BY75-BV75 -> -123.616 | BS75: =P75-BR75-BQ75-BP75 -> -524.461 | BT75: -7.24 | BV75: =(-459096-155408)/1000 -> -614.504 | BW75: =(-459274-269922)/1000 -> -729.196 | BY75: =(-459096-279024)/1000 -> -738.12 | BZ75: =(-459274-342620)/1000 -> -801.894
B76: Change in debt | C76: =6532.358-4672.168+2489.687-164.502-122.145 -> 4063.23 | D76: =5090.384-7250.018+1712.86-1000-153.693 -> -1600.467 | E76: =6779.461-7041.24-334.77 -> -596.549 | F76: =3513.881+188.8-4448.26-1606.684-1207.992 -> -3560.255 | G76: =11295.628+2091.25-8411.387-3582.091-1328.392 -> 65.008 | H76: =5095.669-3760.522-666.907-1522.063 -> -853.823 | I76: =17209.88+1823-11212.645-790.914-1705.311 -> 5324.01 | J76: =4557.752-3222.604-666.907-1522.063 -> -853.822 | K76: =17209.88+1823-11212.645-790.914-1705.311 -> 5324.01 | L76: =17281.03+1823-11319.031-790.914-1705.311 -> 5288.774 | M76: =8874.102-10417.708-37.738-1737.383 -> -3318.727 | N76: =8874.102-10417.708-44.402-1759.069 -> -3347.077 | O76: =4100.067-4436.072-110.246-1715.226 -> -2161.477 | P76: =4100.067-4436.072-1731.173 -> -2067.178 | Q76: =4566.904-6606.241-736.707 -> -2776.044 | R76: =BJ76+BK76+BL76+BM76 -> 40.415 | T76: =2294.018-2692.489-57.63 -> -456.101 | U76: =3564.972-3787.28-87.195-T76 -> 146.598 | V76: =5237.339-4960.409-109.443-T76-U76 -> 476.99 | W76: =+E76-T76-U76-V76 -> -764.036 | X76: =1181.515-736.436+0-561.298 -> -116.219 | Y76: =2025.827-3309.622-823.395-X76 -> -1990.971 | Z76: =3772.259-5692.689-1557.349-X76-Y76 -> -1370.589 | AA76: =F76-Z76-Y76-X76 -> -82.476 | AB76: =1769.347-547.36-106.704-518.262 -> 597.021 | AC76: =3740.531-2897.986-220.47-1030.442-AB76 -> -1005.388 | AD76: =9826.895-5575.704-1113.622-AB76-AC76 -> 3545.936 | AE76: =+G76-AB76-AC76-AD76 -> -3072.561 | AF76: =388.109-735.693-0-494.101 -> -841.685 | AG76: =2097.224-2251.299-944.455-AF76 -> -256.845 | AH76: =2878.56-2845.516-1238.777-AF76-AG76 -> -107.203 | AI76: =+H76-AF76-AG76-AH76 -> 351.91 | AN76: =513.277-588.473-32.23-568.058 -> -675.484 | AO76: =6431.065-1332.422-1007.298-AN76 -> 4766.829 | AP76: =9786.573+1857.5-4146.805-676.86-1404.921-AO76-AN76 -> 1324.142 | AQ76: =I76-SUM(AN76:AP76) -> -91.477 | AR76: =513.277-588.473-32.23-568.058 -> -675.484 | AS76: =6431.065-1332.422-1007.298-AR76 -> 4766.829 | AT76: =9786.573+1857.5-4146.805-676.86-1404.921-AS76-AR76 -> 1324.142 | AU76: =K76-AR76-AS76-AT76 -> -91.477 | AV76: =9786.573+1857.5-4146.805-676.86-1404.921-AS76-AR76 -> 1324.142 | AW76: =L76-AR76-AS76-AV76 -> -126.713 | AX76: =1800.739-1948.202-548.428 -> -695.891 | AY76: =1800.739-1948.202-548.428 -> -695.891 | AZ76: =6663.12-8220.891-1133.873-AX76 -> -1995.753 | BA76: =6663.12-8220.891-1133.873-AY76 -> -1995.753 | BB76: =7791.036+0-9678.936-0-1424.884-AZ76-AX76 -> -621.14 | BC76: =7791.036+0-9678.936-0-1424.884-AZ76-AX76 -> -621.14 | BD76: =M76-AZ76-AX76-BC76 -> -5.943 | BE76: =1032.209-802.088-41.124-750.266 -> -561.269 | BF76: =2914.59-2165.113-114.624+267.57+29.96-1076.887-BE76 -> 416.765 | BG76: =3754.806-3669.098-108.256-1323.438-BF76-BE76 -> -1201.482 | BH76: =O76-SUM(BE76:BG76) -> -815.491 | BI76: =(1394831-1299977-610461)/1000 -> -515.607 | BJ76: =BW76-BI76 -> -485.514 | BK76: =BZ76-BW76 -> -1429.299 | BL76: =Q76-SUM(BI76:BK76) -> -345.624 | BM76: =5015.726-2597.36-117.514 -> 2300.852 | BO76: =N76-SUM(AY76,BA76,BC76) -> -34.293 | BP76: =1032.209-802.088-41.124-750.266 -> -561.269 | BQ76: =BV76-BP76 -> 233.859 | BR76: =BY76-BV76 -> -910.32 | BS76: =P76-BR76-BQ76-BP76 -> -829.448 | BT76: =1394.831-1299.977-610.461 -> -515.607 | BV76: =(2914590-2165113-1076887)/1000 -> -327.41 | BW76: =(2765658-3240353-526426)/1000 -> -1001.121 | BY76: =(3754806-3669098-1323438)/1000 -> -1237.73 | BZ76: =(4397110-6179895-647635)/1000 -> -2430.42
B77: Other financing activities | C77: =667.614+531.235+900-79.835 -> 2019.014 | D77: =2178.986+1162.44-6.555 -> 3334.871 | E77: =367.434-1.289+396.456 -> 762.601 | F77: =82.444-90.704 -> -8.26 | G77: =561.908+9.596+184.092+7.897+294 -> 1057.493 | H77: =247.237+420.667 -> 667.904 | I77: =167.997-1349.081+0.231 -> -1180.853 | J77: =247.237+420.667 -> 667.904 | K77: =167.997-1349.081+0.231 -> -1180.853 | L77: =167.997-1349.081+0.106+0.123 -> -1180.855 | M77: =25.733+74 -> 99.733 | N77: =25.733+74 -> 99.733 | O77: =267.57+44.246 -> 311.816 | P77: =-110.246+267.57+44.246 -> 201.57 | Q77: =-100+35.142 -> -64.858 | R77: =BJ77+BK77+BL77+BM77 -> -2141.129 | T77: 0.62 | U77: =367.433+0.62+0.848-T77 -> 368.281 | V77: =367.434+82.262-T77-U77 -> 80.795 | W77: =+E77-T77-U77-V77 -> 312.905 | X77: =-0.064+0.228-2.016 -> -1.852 | Y77: =80.986-89.167-X77 -> -6.329 | Z77: =-0.112+82.153-90.674-X77-Y77 -> -0.452 | AA77: =F77-Z77-Y77-X77 -> 0.373 | AB77: =264.965+0.222 -> 265.187 | AC77: =3.76-40.468+558.652-AB77 -> 256.757 | AD77: =2056.933-1410.087+561.908+8.864+33.2-AB77-AC77 -> 728.874 | AE77: =+G77-AB77-AC77-AD77 -> -193.325 | AF77: =0+0.136-0.319 -> -0.183 | AG77: =246.591-0.319-AF77 -> 246.455 | AH77: =-400+246.519-0.319-AF77-AG77 -> -400.072 | AI77: =+H77-AF77-AG77-AH77 -> 821.704 | AN77: =-1185.767-AN76-AN75 -> 31.124 | AO77: =-74.592+31.117+0.026-AN77 -> -74.573 | AP77: =0.07-AO77-AN77 -> 43.519 | AQ77: =I77-SUM(AN77:AP77) -> -1180.923 | AR77: =-1185.767-AR76-AR75 -> 31.124 | AS77: =-74.592+31.117+0.026-AR77 -> -74.573 | AT77: =0.07-AS77-AR77 -> 43.519 | AU77: =K77-AR77-AS77-AT77 -> -1180.923 | AV77: =0.07-AS77-AR77 -> 43.519 | AW77: =L77-AR77-AS77-AV77 -> -1180.925 | AX77: =-1994.877-AX76-AX75 -> 40 | AY77: =-1994.877-AY76-AY75 -> 40 | AZ77: =25.764+40-AX77 -> 25.764 | BA77: =25.764+40-AY77 -> 25.764 | BB77: =40-AZ77-AX77 -> -25.764 | BC77: =40-AZ77-AX77 -> -25.764 | BD77: =M77-AZ77-AX77-BC77 -> 59.733 | BE77: =-543.328-BE76-BE75 -> 17.96 | BF77: =0-BD77 -> -59.733 | BG77: =267.57+44.246-BF77-BE77 -> 353.589 | BH77: =O77-SUM(BE77:BG77) -> 0 | BI77: =(30000)/1000 -> 30 | BJ77: =BW77-BI77 -> 0 | BK77: =BZ77-BW77 -> -100.122 | BL77: =Q77-SUM(BI77:BK77) -> 5.264 | BM77: =-2066.271+20 -> -2046.271 | BO77: =N77-SUM(AY77,BA77,BC77) -> 59.733 | BP77: =-543.328-BP76-BP75 -> 17.96 | BQ77: =BV77-BP77 -> 164.946 | BR77: =BY77-BV77 -> 20.654 | BS77: =P77-BR77-BQ77-BP77 -> -1.99 | BT77: =30 -> 30 | BV77: =(-114624+267570+29960)/1000 -> 182.906 | BW77: =(30000)/1000 -> 30 | BY77: =(-108256+267570+44246)/1000 -> 203.56 | BZ77: =(-100000+30000-122)/1000 -> -70.122
B78: Cash flow after financing activities | C78: =SUM(C72:C77) -> 14135.302 | D78: =SUM(D72:D77) -> 11570.558 | E78: =SUM(E72:E77) -> 6736.896 | F78: =SUM(F72:F77) -> 9892.31 | G78: =SUM(G72:G77) -> 14384.285 | H78: =SUM(H72:H77) -> 11001.798 | I78: =SUM(I72:I77) -> 13149.137 | J78: =SUM(J72:J77) -> 8405.833 | ... R78: =SUM(R72:R77) -> 4608.7523 | T78: =SUM(T72:T77) -> -1355.204 | U78: =SUM(U72:U77) -> 899.037 | V78: =SUM(V72:V77) -> 1828.14 | W78: =SUM(W72:W77) -> 5364.923 | X78: =SUM(X72:X77) -> 4066.429 | Y78: =SUM(Y72:Y77) -> 1057.572 | Z78: =SUM(Z72:Z77) -> 2007.853 | AA78: =SUM(AA72:AA77) -> 2760.456 | ... AI78: =SUM(AI72:AI77) -> 2815.47 | AN78: =SUM(AN72:AN77) -> 2022.282 | AO78: =SUM(AO72:AO77) -> 3868.119 | AP78: =SUM(AP72:AP77) -> 4148.136 | AQ78: =SUM(AQ72:AQ77) -> 3110.6 | AR78: =SUM(AR72:AR77) -> 1369.819 | AS78: =SUM(AS72:AS77) -> 3187.471 | AT78: =SUM(AT72:AT77) -> 3416.536 | AU78: =SUM(AU72:AU77) -> 2337.956 | ... BM78: =SUM(BM72:BM77) -> 1216.305 | BO78: =SUM(BO72:BO77) -> 2052.669 | BP78: =SUM(BP72:BP77) -> 2797.28 | BQ78: =SUM(BQ72:BQ77) -> 2414.544 | BR78: =SUM(BR72:BR77) -> 1363.977 | BS78: =SUM(BS72:BS77) -> -618.507 | BT78: =SUM(BT72:BT77) -> 1385.577 | BV78: =SUM(BV72:BV77) -> 3801.028 | BW78: =SUM(BW72:BW77) -> 2902.096 | BY78: =SUM(BY72:BY77) -> 5164.955 | BZ78: =SUM(BZ72:BZ77) -> 3153.888
B79: FX | C79: 98.104 | D79: -216.189 | E79: -162.023 | F79: 49.343 | G79: -66.881 | H79: 92.439 | I79: =-733.245 -> -733.245 | J79: -30.19 | K79: =-733.245 -> -733.245 | L79: =-18.701 -> -18.701 | M79: =-266.718 -> -266.718 | N79: -266.167 | O79: -514.527 | P79: -514.457 | Q79: -470.105 | R79: =BJ79+BK79+BL79+BM79 -> -426.822 | T79: 199.937 | U79: =-167.924-T79 -> -367.861 | V79: =-230.606-T79-U79 -> -62.682 | W79: =+E79-T79-U79-V79 -> 68.583 | X79: 64.148 | Y79: =85.504-X79 -> 21.356 | Z79: =82.179-X79-Y79 -> -3.325 | AA79: =F79-Z79-Y79-X79 -> -32.836 | AB79: -16.869 | AC79: =28.105-AB79 -> 44.974 | AD79: =-36.197-AB79-AC79 -> -64.302 | AE79: =+G79-AB79-AC79-AD79 -> -30.684 | AF79: -2.044 | AG79: =17.972-AF79 -> 20.016 | AH79: =149.8-AF79-AG79 -> 131.828 | AI79: =+H79-AF79-AG79-AH79 -> -57.361 | AN79: -198.019 | AO79: =-265.218-AN79 -> -67.199 | AP79: =-41.229-AN79-AO79 -> 223.989 | AQ79: =I79-SUM(AN79:AP79) -> -692.016 | AR79: -198.019 | AS79: =-265.218-AR79 -> -67.199 | AT79: =-41.229-AR79-AS79 -> 223.989 | AU79: =K79-AR79-AS79-AT79 -> -692.016 | AV79: =-41.229-AR79-AS79 -> 223.989 | AW79: =L79-AR79-AS79-AV79 -> 22.528 | AX79: 133.805 | AY79: 133.805 | AZ79: =790.23-AX79 -> 656.425 | BA79: =790.23-AY79 -> 656.425 | BB79: =516.151-AX79-AZ79 -> -274.079 | BC79: =516.151-AX79-AZ79 -> -274.079 | BD79: =M79-AZ79-AX79-BC79 -> -782.869 | BE79: -74.331 | BF79: =-231.139-BE79 -> -156.808 | BG79: =-829.085-BF79-BE79 -> -597.946 | BH79: =O79-SUM(BE79:BG79) -> 314.558 | BI79: -55.597 | BJ79: =BW79-BI79 -> -101.791 | BK79: =BZ79-BW79 -> -101.886 | BL79: =Q79-SUM(BI79:BK79) -> -210.831 | BM79: -12.314 | BO79: =N79-SUM(AY79,BA79,BC79) -> -782.318 | BP79: -74.331 | BQ79: =BV79-BP79 -> -156.808 | BR79: =BY79-BV79 -> -597.946 | BS79: =P79-BR79-BQ79-BP79 -> 314.628 | BT79: -55.597 | BV79: -231.139 | BW79: -157.388 | BY79: -829.085 | BZ79: -259.274
B80: Balancing figure | C80: =230.796-240.143-C78 -> -14144.649 | D80: =1814.078+224.347-D78 -> -9532.133 | E80: =-2550.819+28.936-E78 -> -9258.779 | F80: =-726.84-95.146-F78 -> -10714.296 | G80: =3727.41+46.528-G78 -> -10610.347 | H80: =-402.219-49.707-H78 -> -11453.724 | I80: =715.137+43.213-I78 -> -12390.787 | J80: =-496.426+116.784-J78 -> -8785.475 | K80: =715.137+43.213-K78 -> -9553.432 | L80: =762.168-729.603-L78 -> -9349.517 | M80: =-2289.172+65.681-390.27-M78 -> -9953.461 | N80: =-2346.859+65.681-390.27-N78 -> -10233.889 | O80: =214.879+11.411+441.327-O78 -> -10676.462 | P80: =268.977+8.3+390.27-P78 -> -5289.747 | Q80: =-501.749+3.615 -Q78 -> -5456.828 | R80: =BJ80+BK80+BL80+BM80 -> -5412.4983 | T80: =-1355.204+62.564-T78 -> 62.564 | U80: =-456.167+34.189+9.12-U78-T80-T78 -> -19.255 | V80: =-542.997+147.971+5.3299-V78-U80-T80-U78-T78 -> -1804.9781 | W80: =+E80-T80-U80-V80 -> -7497.1099 | X80: =1644.661+43.038-X78 -> -2378.73 | Y80: =31.706+39.601-Y78-X80-X78 -> -2673.964 | Z80: =-298.934+39.168-Z78-Y80-Y78-X80-X78 -> -2338.926 | AA80: =F80-Z80-Y80-X80 -> -3322.676 | AB80: =2034.692-27.784-AB78 -> -2531.677 | AC80: =1990.96-25.462-AC78-AB80-AB78 -> -2581.428 | AD80: =7046.17-13.348-AC80-AC78-AB80-AB78-AD78 -> -2827.523 | AE80: =+G80-AB80-AC80-AD80 -> -2669.719 | AF80: =-1125.726+28.173-AF78 -> -2672.07 | AG80: =-765.538-16.126-AG78-AF80-AF78 -> -2846.779 | AH80: =-175.781-21.953-AG80-AG78-AF80-AF78-AH78 -> -2865.213 | AI80: =+H80-AF80-AG80-AH80 -> -3069.662 | AN80: =-876.181+12.947-AN78 -> -2885.516 | AO80: =-18.662+18.904-AO78-AN80-AN78 -> -3004.643 | AP80: =925.874-114.213-AO80-AO78-AN80-AN78-AP78 -> -3336.717 | AQ80: =I80-SUM(AN80:AP80) -> -3163.911 | AR80: =-876.181+12.947-AR78 -> -2233.053 | AS80: =-18.662+18.904-AS78-AR80-AR78 -> -2323.995 | AT80: =925.874-114.213-AS80-AS78-AR80-AR78-AT78 -> -2605.117 | AU80: =K80-AR80-AS80-AT80 -> -2391.267 | AV80: =925.874-114.213-AS80-AS78-AR80-AR78-AV78 -> -2440.917 | AW80: =L80-AR80-AS80-AV80 -> -2351.552 | AX80: =-1900.814-1.845-AX78 -> -2418.576 | AY80: =-1900.814-1.845-AY78 -> -2185.145 | AZ80: =-1931.051-13.34-AZ78-AX80-AX78 -> -2740.268 | BA80: =-1931.051-13.34-BA78-AY80-AY78 -> -2514.654 | BB80: =-1714.705+48.522-AZ80-AZ78-AX80-AX78-BB78-505.725 -> -3157.881 | BC80: =-1714.705+48.522-AX80-AX78-AZ80-AZ78-BC78-505.725 -> -2981.881 | BD80: =M80-AZ80-AX80-BC80 -> -1812.736 | BE80: =-6.266-15.692-BE78 -> -2752.561 | BF80: =895.278-14.561-BF78-BE80-BE78 -> -2758.756 | BG80: =845.355-37.068-BE80-BE78-BF80-BF78-BG78 -> -2722.618 | BH80: =O80-SUM(BE80:BG80) -> -2442.527 | BI80: =166.628-6.92-BI78 -> -1406.5387 | BJ80: =242.881-15.243-BJ78-BI80-BI78 -> -2502.9203 | BK80: =-867.747-3.372-BI80-BI78-BJ80-BJ78-BK78 -> -1350.529 | BL80: =Q80-SUM(BI80:BK80) -> -196.84 | BM80: =-138.585-7.319-BM78 -> -1362.209 | BO80: =N80-SUM(AY80,BA80,BC80) -> -2552.209 | BP80: =-6.266-15.692-BP78 -> -2819.238 | BQ80: =895.278-14.561-BQ78-BP80-BP78 -> -1511.869 | BR80: =845.355-37.068-BR78-BQ80-BQ78-BP78-BP80 -> -1436.407 | BS80: =P80-BR80-BQ80-BP80 -> 477.767 | BT80: =166.628-6.92-BT78 -> -1225.869 | BV80: =895.278-14.561-BV78 -> -2920.311 | BW80: =242.881-15.243-BW78 -> -2674.458 | BY80: =845.355-37.068-BY78 -> -4356.668 | BZ80: =-867.747-3.372-BZ78 -> -4025.007
B81: Net change in cash | C81: =SUM(C78:C80) -> 88.757 | D81: =SUM(D78:D80) -> 1822.236 | E81: =SUM(E78:E80) -> -2683.906 | F81: =SUM(F78:F80) -> -772.643 | G81: =SUM(G78:G80) -> 3707.057 | H81: =SUM(H78:H80) -> -359.487 | I81: =SUM(I78:I80) -> 25.105 | J81: =SUM(J78:J80) -> -409.832 | ... R81: =SUM(R78:R80) -> -1230.568 | T81: =SUM(T78:T80) -> -1092.703 | U81: =SUM(U78:U80) -> 511.921 | V81: =SUM(V78:V80) -> -39.5201 | W81: =SUM(W78:W80) -> -2063.6039 | X81: =SUM(X78:X80) -> 1751.847 | Y81: =SUM(Y78:Y80) -> -1595.036 | Z81: =SUM(Z78:Z80) -> -334.398 | AA81: =SUM(AA78:AA80) -> -595.056 | ... AI81: =SUM(AI78:AI80) -> -311.553 | AN81: =SUM(AN78:AN80) -> -1061.253 | AO81: =SUM(AO78:AO80) -> 796.277 | AP81: =SUM(AP78:AP80) -> 1035.408 | AQ81: =SUM(AQ78:AQ80) -> -745.327 | AR81: =SUM(AR78:AR80) -> -1061.253 | AS81: =SUM(AS78:AS80) -> 796.277 | AT81: =SUM(AT78:AT80) -> 1035.408 | AU81: =SUM(AU78:AU80) -> -745.327 | ... BM81: =SUM(BM78:BM80) -> -158.218 | BO81: =SUM(BO78:BO80) -> -1281.858 | BP81: =SUM(BP78:BP80) -> -96.289 | BQ81: =SUM(BQ78:BQ80) -> 745.867 | BR81: =SUM(BR78:BR80) -> -670.376 | BS81: =SUM(BS78:BS80) -> 173.888 | BT81: =SUM(BT78:BT80) -> 104.111 | BV81: =SUM(BV78:BV80) -> 649.578 | BW81: =SUM(BW78:BW80) -> 70.25 | BY81: =SUM(BY78:BY80) -> -20.798 | BZ81: =SUM(BZ78:BZ80) -> -1130.393
B82: Cash and cash equivalents | C82: 4649.422 | D82: =+C82+D81 -> 6471.658 | E82: =6471.658+E81 -> 3787.752 | F82: =+E82+F81 -> 3015.109 | G82: =+F82+G81 -> 6722.166 | H82: =+G82+H81 -> 6362.679 | I82: =+H82+I81 -> 6387.784 | J82: =G82+J81 -> 6312.334 | K82: =+J82+K81 -> 6337.439 | L82: =+J82+L81 -> 6326.198 | M82: =+L82+M81 -> 3445.719 | N82: =L82+N81 -> 3388.583 | O82: =+N82+O81 -> 3541.673 | P82: =3388.579+P81 -> 3541.669 | Q82: =+P82+Q81 -> 2573.43 | R82: =BM82 -> 2413.057 | T82: =6471.658+T81 -> 5378.955 | U82: =T82+U81 -> 5890.876 | V82: =U82+V81 -> 5851.3559 | W82: =V82+W81 -> 3787.752 | X82: =W82+X81 -> 5539.599 | Y82: =X82+Y81 -> 3944.563 | Z82: =Y82+Z81 -> 3610.165 | AA82: =Z82+AA81 -> 3015.109 | AB82: =3015.105+AB81 -> 5005.144 | AC82: =AB82+AC81 -> 5008.708 | AD82: =AC82+AD81 -> 10011.73 | AE82: =AD82+AE81 -> 6722.162 | AF82: =AF81+6722.163 -> 5622.566 | AG82: =AF82+AG81 -> 5958.471 | AH82: =AG82+AH81 -> 6674.229 | AI82: =AH82+AI81 -> 6362.676 | AN82: =AN81+6312.33 -> 5251.077 | AO82: =AN82+AO81 -> 6047.354 | AP82: =AO82+AP81 -> 7082.762 | AQ82: =AP82+AQ81 -> 6337.435 | AR82: =AR81+6312.33 -> 5251.077 | AS82: =AR82+AS81 -> 6047.354 | AT82: =AS82+AT81 -> 7082.762 | AU82: =AT82+AU81 -> 6337.435 | AV82: =AS82+AV81 -> 7082.762 | AW82: =AV82+AW81 -> 6326.194 | AX82: =AX81+6326.194 -> 4557.34 | AY82: =AY81+6326.194 -> 4557.34 | AZ82: =AX82+AZ81 -> 5172.033 | BA82: =AY82+BA81 -> 5172.033 | BB82: =AZ82+BB81 -> 4670.437 | BC82: =AZ82+BC81 -> 4670.437 | BD82: =BC82+BD81 -> 3445.715 | BE82: =BE81+3388.578 -> 3292.289 | BF82: =BE82+BF81 -> 4038.156 | BG82: =BF82+BG81 -> 3367.78 | BH82: =BG82+BH81 -> 3541.668 | BI82: =BI81+BH82 -> 3645.779 | BJ82: =BI82+BJ81 -> 3611.918 | BK82: =BJ82+BK81 -> 2411.275 | BL82: =BK82+BL81 -> 2573.429 | BM82: =BM81+2571.275 -> 2413.057 | BO82: =BC82+BO81 -> 3388.579 | BP82: =BP81+3388.578 -> 3292.289 | BQ82: =BQ81+BP82 -> 4038.156 | BR82: =BR81+BQ82 -> 3367.78 | BS82: =P82 -> 3541.669 | BT82: =BT81+3541.669 -> 3645.78 | BV82: =BV81+3388.578 -> 4038.156 | BW82: =BW81+BH82 -> 3611.918 | BY82: =BY81+3388.578 -> 3367.78 | BZ82: =BZ81+BH82 -> 2411.275
B84: check | C84: =C82-C118 -> 0 | D84: =D82-D118 -> 0 | E84: =E82-E118 -> 0.004 | F84: =F82-F118 -> 0.004 | G84: =G82-G118 -> 0.004 | H84: =H82-H118 -> 0.004 | I84: =I82-I118-50 -> 0.349 | J84: =J82-J118 -> 0.004 | K84: =K82-K118 -> 0.004 | L84: =L82-L118 -> -0.996 | M84: =M82-M118 -> 0.004 | N84: =N82-N118 -> 0.004 | O84: =O82-O118 -> 0.004 | P84: =P82-P118 -> 0 | Q84: =Q82-Q118 -> 0 | R84: =R82-R123 -> 0 | T84: =T82-T118 -> 0 | U84: =U82-U118 -> 0.001 | V84: =V82-V118 -> 0.0009 | W84: =W82-W118 -> 0.004 | X84: =X82-X118 -> 0.004 | Y84: =Y82-Y118 -> 0.004 | Z84: =Z82-Z118 -> 0.004 | AA84: =AA82-AA118 -> 0.004 | ... AI84: =AI82-AI118 -> 0.001 | AN84: =AN82-AN118 -> 0 | AO84: =AO82-AO118 -> 0 | AP84: =AP82-AP118 -> 0 | AQ84: =AQ82-AQ118 -> 0 | AR84: =AR82-AR118 -> 0 | AS84: =AS82-AS118 -> 0 | AT84: =AT82-AT118 -> 0 | AU84: =AU82-AU118 -> 0 | ... BL84: =BL82-BL118 -> -0.001 | BM84: =BM82-BM123 -> 0 | BO84: =BO82-BO118 -> 0 | BP84: =BP82-BP118 -> 0 | BQ84: =BQ82-BQ118 -> 0 | BR84: =BR82-BR118 -> 0 | BS84: =BS82-BS118 -> 0 | BT84: =BT82-BT118 -> 0
B86: LTM | C86: =+C63 -> 42707 | D86: =+D63 -> 43073 | E86: =E3 -> 43438 | F86: =F3 -> 43803 | G86: =G3 -> 44169 | H86: =H3 -> 44561 | I86: =I3 -> 44926 | J86: =J3 -> 44561 | K86: =K3 -> 44926 | L86: =L3 -> 44926 | ... Q86: =Q3 -> 46022 | R86: =+R63 -> 46112 | T86: =+T63 -> 43190 | U86: =+U63 -> 43281 | V86: =+V63 -> 43373 | W86: =+W63 -> 43465 | X86: =+X63 -> 43555 | Y86: =+Y63 -> 43646 | Z86: =+Z63 -> 43738 | AA86: =+AA63 -> 43830 | ... AI86: =+AI63 -> 44561 | AM86: =+AM63 -> 44561 | AN86: =+AN63 -> 44651 | AO86: =+AO63 -> 44742 | AP86: =+AP63 -> 44834 | AQ86: =+AQ63 -> 44926 | AR86: =+AR63 -> 44651 | AS86: =+AS63 -> 44742 | AT86: =+AT63 -> 44834 | ... BM86: =+BM63 -> 46112 | BO86: =+BO63 -> 45291 | BP86: =+BP63 -> 45382 | BQ86: =+BQ63 -> 45473 | BR86: =+BR63 -> 45565 | BS86: =+BS63 -> 45657 | BT86: =+BT63 -> 45747
B87: =+B7 -> Operating revenue | C87: =+C7 -> 21565.392 | D87: =+D7 -> 24402.401 | E87: =+E7 -> 23885.781 | F87: =+F7 -> 24583.312 | G87: =+G7 -> 24203.171 | H87: =+H7 -> 25900.661 | I87: =+I7 -> 27522 | ... R87: =+R7 -> 9468.961 | W87: =+W7+V7+U7+T7 -> 23885.781 | X87: =+X7+W7+V7+U7 -> 24086.969 | Y87: =+Y7+X7+W7+V7 -> 24373.518 | Z87: =+Z7+Y7+X7+W7 -> 24583.3 | AA87: =+AA7+Z7+Y7+X7 -> 24583.312 | AB87: =+AB7+AA7+Z7+Y7 -> 24670.459 | AC87: =+AC7+AB7+AA7+Z7 -> 24309.259 | AD87: =+AD7+AC7+AB7+AA7 -> 24207.662 | ... AI87: =+AI7+AH7+AG7+AF7 -> 25900.661 | AN87: =+AN7+AM7+AH7+AG7 -> 24739.443 | AO87: =+AO7+AN7+AM7+AH7 -> 25053.636 | AP87: =+AP7+AO7+AN7+AM7 -> 25770.991 | AQ87: =+AQ7+AP7+AO7+AN7 -> 27522 | AR87: =+AR7+AM7+AH7+AG7 -> 23253.382 | AS87: =+AS7+AR7+AM7+AH7 -> 22060.923 | AT87: =+AT7+AS7+AR7+AM7 -> 21226.96 | AU87: =+AU7+AT7+AS7+AR7 -> 21725.495 | AV87: =+AV7+AS7+AR7+AM7 -> 20885.343 | AW87: =+AW7+AV7+AR7+AS7 -> 20020.28 | AX87: =+AX7+AU7+AV7+AS7 -> 21778.704 | AY87: =+AY7+AV7+AW7+AT7 -> 20545.013 | AZ87: =+AZ7+AX7+AU7+AV7 -> 22575.625 | BA87: =+BA7+AY7+AV7+AW7 -> 20428.172 | BB87: =+BB7+AZ7+AX7+AU7 -> 23218.242 | BC87: =+BC7+BA7+AY7+AU7 -> 22120.084 | BD87: =+BD7+BB7+AX7+AZ7 -> 22316.572 | BE87: =+BE7+BD7+BC7+BA7 -> 21883.27 | BF87: =+BF7+BE7+BD7+BC7 -> 22046.877 | BG87: =+BG7+BE7+BF7+BD7 -> 21672.823 | BH87: =+BH7+BF7+BG7+BE7 -> 22334.617 | BI87: =+BI7+BH7+BG7+BF7 -> 21761.43 | BJ87: =+BJ7+BI7+BH7+BG7 -> 18972.083 | BK87: =+BK7+BI7+BJ7+BH7 -> 16570.92 | BL87: =+BL7+BJ7+BK7+BI7 -> 11757.997 | BM87: =+BM7+BL7+BK7+BJ7 -> 9468.961 | BO87: =SUM(AY7,BA7,BC7,BO7) -> 22318.326 | BP87: =+BP7+BO7+BC7+BA7 -> 23060.141 | BQ87: =+BQ7+BP7+BO7+BC7 -> 20787.618 | BR87: =+BR7+BQ7+BP7+BO7 -> 18156.919 | BS87: =+BS7+BR7+BQ7+BP7 -> 12541.918 | BT87: =+BT7+BS7+BR7+BQ7 -> 9694.732
B88: Operating profit | C88: =C19 -> 2727.206 | D88: =D19 -> 3000.057 | E88: =E19 -> -2385.127 | F88: =F19 -> 4232.126 | G88: =G19 -> 2494.884 | H88: =H19 -> 3818.077 | I88: =I19 -> 3750.773 | J88: =J19 -> 2426.713 | ... R88: =R19 -> 1065.167 | W88: =W19+V19+U19+T19 -> -2385.127 | X88: =X19+W19+V19+U19 -> -1768.752 | Y88: =Y19+X19+W19+V19 -> 1928.561 | Z88: =Z19+Y19+X19+W19 -> 2097.527 | AA88: =AA19+Z19+Y19+X19 -> 4232.126 | AB88: =AB19+AA19+Z19+Y19 -> 4137.1 | AC88: =AC19+AB19+AA19+Z19 -> 3769.144 | AD88: =AD19+AC19+AB19+AA19 -> 3776.705 | ... AI88: =AI19+AH19+AG19+AF19 -> 3818.077 | AN88: =AN19+AM19+AH19+AG19 -> 3200.557 | AO88: =AO19+AN19+AM19+AH19 -> 3239.225 | AP88: =AP19+AO19+AN19+AM19 -> 3346.67 | AQ88: =AQ19+AP19+AO19+AN19 -> 3750.773 | AR88: =AR19+AM19+AH19+AG19 -> 2784.755 | AS88: =AS19+AR19+AM19+AH19 -> 2369.832 | AT88: =AT19+AS19+AR19+AM19 -> 2268.917 | AU88: =AU19+AT19+AS19+AR19 -> -2045.732 | AV88: =AV19+AS19+AR19+AM19 -> 1927.3 | AW88: =AW19+AV19+AR19+AS19 -> 358.339 | AX88: =AX19+AU19+AV19+AS19 -> -2198.825 | AY88: =AY19+AV19+AW19+AT19 -> 896.512 | AZ88: =AZ19+AX19+AU19+AV19 -> -2939.481 | BA88: =BA19+AY19+AV19+AW19 -> 823.856 | BB88: =BB19+AZ19+AX19+AU19 -> -2537.213 | BC88: =BC19+AZ19+AX19+AU19 -> -2851.516 | BD88: =BD19+BB19+AX19+AZ19 -> 2972.861 | BE88: =BE19+BD19+BC19+BA19 -> 4049.193 | BF88: =BF19+BE19+BD19+BC19 -> 4059.961 | BG88: =BG19+BE19+BD19+BF19 -> 3828.828 | BH88: =BH19+BF19+BE19+BG19 -> 3556.081 | BI88: =BI19+BH19+BG19+BF19 -> 3410.173 | BJ88: =BJ19+BI19+BH19+BG19 -> 2657.404 | BK88: =BK19+BI19+BH19+BJ19 -> 2494.399 | BL88: =BL19+BJ19+BI19+BK19 -> 1296.026 | BM88: =BM19+BL19+BK19+BJ19 -> 1065.167 | BO88: =SUM(AY19,BA19,BC19,BO19) -> 1846.151 | BP88: =BP19+BO19+BC19+BA19 -> 2279.87 | BQ88: =BQ19+BP19+BO19+BC19 -> 1856.538 | BR88: =BR19+BQ19+BP19+BO19 -> 1247.067 | BS88: =BS19+BR19+BQ19+BP19 -> 1732.719 | BT88: =BT19+BS19+BR19+BQ19 -> 1117.49
B89: EBITDA | C89: =C51 -> 8393.711 | D89: =D51 -> 8986.27 | E89: =E51 -> 5259.689 | F89: =F51 -> 11316.362 | G89: =G51 -> 10979.878 | H89: =H51 -> 11912.945 | I89: =I51 -> 10821.685 | J89: =J51 -> 8744.53 | ... R89: =R51 -> 4072.655 | W89: =W51+V51+U51+T51 -> 5259.689 | X89: =X51+W51+V51+U51 -> 6125.893 | Y89: =Y51+X51+W51+V51 -> 10040.929 | Z89: =Z51+Y51+X51+W51 -> 10544.495 | AA89: =AA51+Z51+Y51+X51 -> 11316.362 | AB89: =AB51+AA51+Z51+Y51 -> 11426.765 | AC89: =AC51+AB51+AA51+Z51 -> 11194.276 | AD89: =AD51+AC51+AB51+AA51 -> 11117.933 | ... AI89: =AI51+AH51+AG51+AF51 -> 11912.945 | AN89: =AN51+AM51+AH51+AG51 -> 10584.633 | AO89: =AO51+AN51+AM51+AH51 -> 10599.286 | AP89: =AP51+AO51+AN51+AM51 -> 10824.173 | AQ89: =AQ51+AP51+AO51+AN51 -> 10821.685 | AR89: =AR51+AM51+AH51+AG51 -> 9916.64 | AS89: =AS51+AR51+AM51+AH51 -> 9224.789 | AT89: =AT51+AS51+AR51+AM51 -> 8820.406 | AU89: =AU51+AT51+AS51+AR51 -> 5025.18 | AV89: =AV51+AS51+AR51+AM51 -> 8478.789 | AW89: =AW51+AV51+AR51+AS51 -> 8236.342 | AX89: =AX51+AU51+AV51+AS51 -> 5076.641 | AY89: =AY51+AV51+AW51+AT51 -> 8856.389 | AZ89: =AZ51+AX51+AU51+AV51 -> 5406.589 | BA89: =BA51+AY51+AV51+AW51 -> 8917.595 | BB89: =BB51+AZ51+AX51+AU51 -> 5987.887 | BC89: =BC51+AZ51+AX51+AU51 -> 5673.584 | BD89: =BD51+BB51+AX51+AZ51 -> 10172.847 | BE89: =BE51+BD51+BC51+BA51 -> 10470.39 | BF89: =BF51+BE51+BD51+BC51 -> 10545.844 | BG89: =BG51+BE51+BF51+BD51 -> 10274.029 | BH89: =BH51+BF51+BG51+BE51 -> 10897.276 | BI89: =BI51+BH51+BG51+BF51 -> 10493.014 | BJ89: =BJ51+BI51+BH51+BG51 -> 8994.558 | BK89: =BK51+BI51+BJ51+BH51 -> 8031.762 | BL89: =BL51+BJ51+BK51+BI51 -> 5189.47 | BM89: =BM51+BL51+BK51+BJ51 -> 4072.655 | BO89: =SUM(AY51,BA51,BC51,BO51) -> 10048.533 | BP89: =BP51+BO51+BC51+BA51 -> 10743.316 | BQ89: =BQ51+BP51+BO51+BC51 -> 9478.533 | BR89: =BR51+BQ51+BP51+BO51 -> 7954.182 | BS89: =BS51+BR51+BQ51+BP51 -> 5485.028 | BT89: =BT51+BS51+BR51+BQ51 -> 3798.526
B90: Adjusted EBITDA | C90: =+C59 -> 8012.648 | D90: =+D59 -> 9230.118 | E90: =+E59 -> 8334.134 | F90: =+F59 -> 10619.15 | G90: =+G59 -> 10656.875 | H90: =+H59 -> 11404.017 | I90: =+I59 -> 12434 | J90: =+J59 -> 8902.259 | ... R90: =+R59 -> 4362.091 | W90: =+W59+V59+U59+T59 -> 8334.134 | X90: =+X59+W59+V59+U59 -> 10755.902 | Y90: =+Y59+X59+W59+V59 -> 13426.429 | Z90: =+Z59+Y59+X59+W59 -> 16228.106 | AA90: =+AA59+Z59+Y59+X59 -> 10619.15 | AB90: =+AB59+AA59+Z59+Y59 -> 10701.275 | AC90: =+AC59+AB59+AA59+Z59 -> 10614.498 | AD90: =+AD59+AC59+AB59+AA59 -> 10652.459 | ... AI90: =+AI59+AH59+AG59+AF59 -> 11404.017 | AN90: =+AN59+AM59+AH59+AG59 -> 10890.617 | AO90: =+AO59+AN59+AM59+AH59 -> 11090.349 | AP90: =+AP59+AO59+AN59+AM59 -> 11434.563 | AQ90: =+AQ59+AP59+AO59+AN59 -> 12434 | AR90: =+AR59+AM59+AH59+AG59 -> 10238.154 | AS90: =+AS59+AR59+AM59+AH59 -> 9757.238 | AT90: =+AT59+AS59+AR59+AM59 -> 9369.852 | AU90: =+AU59+AT59+AS59+AR59 -> 9596.645 | AV90: =AV59+AS59+AR59+AM59 -> 9205.652 | AW90: =+AW59+AV59+AR59+AS59 -> 8619.914 | AX90: =+AX59+AU59+AV59+AS59 -> 9603.176 | AY90: =+AY59+AV59+AW59+AT59 -> 8699.262 | AZ90: =+AZ59+AX59+AU59+AV59 -> 10001.997 | BA90: =+BA59+AY59+AV59+AW59 -> 8730.421 | BB90: =+BB59+AZ59+AX59+AU59 -> 10408.197 | BC90: =+BC59+AZ59+AX59+AU59 -> 10232.197 | BD90: =+BD59+BB59+AX59+AZ59 -> 9804.872 | BE90: =+BE59+BD59+BC59+BA59 -> 9723.396 | BF90: =+BF59+BE59+BD59+BC59 -> 10045.435 | BG90: =+BG59+BE59+BF59+BD59 -> 10142.235 | BH90: =+BH59+BF59+BG59+BE59 -> 11129.2 | BI90: =+BI59+BH59+BG59+BF59 -> 10846.547 | BJ90: =+BJ59+BI59+BH59+BG59 -> 9461.349 | BK90: =+BK59+BI59+BJ59+BH59 -> 8188.949 | BL90: =+BL59+BJ59+BK59+BI59 -> 5460.443 | BM90: =+BM59+BL59+BK59+BJ59 -> 4362.091 | BO90: =SUM(AY59,BA59,BC59,BO59) -> 9909.3 | BP90: =+BP59+BO59+BA59+BC59 -> 10529.546 | BQ90: =+BQ59+BP59+BC59+BO59 -> 9539.387 | BR90: =+BR59+BQ59+BO59+BP59 -> 8415.287 | BS90: =+BS59+BR59+BP59+BQ59 -> 5688.317 | BT90: =+BT59+BS59+BQ59+BR59 -> 4103.94
B91: Cash interest paid | C91: =-C67 -> 1153.868 | D91: =-D67 -> 1297.431 | E91: =-E67 -> 1102.214 | F91: =-F67 -> 1689.589 | G91: =-G67 -> 1400.405 | H91: =-H67 -> 1398.06 | I91: =-I67 -> 1590.874 | J91: =-J67 -> 1398.06 | ... R91: =-R67 -> 1207.167 | W91: =-W67-V67-U67-T67 -> 1102.214 | X91: =-X67-W67-V67-U67 -> 1051.487 | Y91: =-Y67-X67-W67-V67 -> 829.892 | Z91: =-Z67-Y67-X67-W67 -> 3375.171 | AA91: =-AA67-Z67-Y67-X67 -> 1689.589 | AB91: =-AB67-AA67-Z67-Y67 -> 1898.885 | AC91: =-AC67-AB67-AA67-Z67 -> 2627.081 | AD91: =-AD67-AC67-AB67-AA67 -> 1557.296 | ... AI91: =-AI67-AH67-AG67-AF67 -> 1398.06 | AN91: =-AN67-AI67-AH67-AG67 -> 1442.143 | AO91: =-AO67-AN67-AI67-AH67 -> 1443.075 | AP91: =-AP67-AO67-AN67-AI67 -> 1480.787 | AQ91: =-AQ67-AP67-AO67-AN67 -> 1590.874 | AR91: =-AR67-AI67-AH67-AG67 -> 1442.143 | AS91: =-AS67-AR67-AI67-AH67 -> 1443.075 | AT91: =-AT67-AS67-AR67-AI67 -> 1480.787 | AU91: =-AU67-AT67-AS67-AR67 -> 1590.874 | AV91: =-AV67-AS67-AR67-AI67 -> 1480.787 | AW91: =-AW67-AV67-AS67-AR67 -> 1589.069 | AX91: =-AX67-AU67-AV67-AS67 -> 1613.014 | AY91: =-AY67-AV67-AW67-AT67 -> 1827.594 | AZ91: =-AZ67-AX67-AU67-AV67 -> 2023.199 | BA91: =-BA67-AY67-AV67-AW67 -> 2021.394 | BB91: =-BB67-AZ67-AX67-AU67 -> 2257.371 | BC91: =-BC67-AZ67-AX67-AU67 -> 2257.371 | BD91: =-BD67-BB67-AX67-AZ67 -> 2303.003 | BE91: =-BE67-BD67-BC67-BA67 -> 2516.83 | BF91: =-BF67-BE67-BD67-BC67 -> 2323.051 | BG91: =-BG67-BF67-BE67-BD67 -> 2184.98 | BH91: =-BH67-BG67-BF67-BE67 -> 2157.191 | BI91: =-BI67-BH67-BG67-BF67 -> 2045.756 | BJ91: =-BJ67-BI67-BH67-BG67 -> 1999.2 | BK91: =-BK67-BJ67-BI67-BH67 -> 1779.077 | BL91: =-BL67-BK67-BJ67-BI67 -> 1543.512 | BM91: =-BM67-BL67-BK67-BJ67 -> 1207.167 | BO91: =-SUM(AY67,BA67,BC67,BO67) -> 2296.339 | BP91: =-BP67-BO67-BC67-BA67 -> 2510.166 | BQ91: =-BQ67-BP67-BO67-BC67 -> 2316.387 | BR91: =-BR67-BQ67-BP67-BO67 -> 2178.316 | BS91: =-BS67-BR67-BQ67-BP67 -> 2157.191 | BT91: =-BT67-BS67-BR67-BQ67 -> 2045.756
B92: Net Income | C92: =+C29 -> 657.158 | D92: =+D29 -> 1162.492 | E92: =+E29 -> -4974.692 | F92: =+F29 -> 1815.096 | G92: =+G29 -> 624.045 | H92: =+H29 -> 1276.881 | I92: =+I29 -> 933.307 | J92: =+J29 -> 307.535 | ... R92: =+R29 -> 418.565 | W92: =+W29+V29+U29+T29 -> -4974.692 | X92: =+X29+W29+V29+U29 -> -4093.747 | Y92: =+Y29+X29+W29+V29 -> -485.636 | Z92: =+Z29+Y29+X29+W29 -> -377.818 | AA92: =+AA29+Z29+Y29+X29 -> 1815.096 | AB92: =+AB29+AA29+Z29+Y29 -> 1413.57 | AC92: =+AC29+AB29+AA29+Z29 -> 1266.092 | AD92: =+AD29+AC29+AB29+AA29 -> 1426.596 | ... AI92: =+AI29+AH29+AG29+AF29 -> 1276.881 | AN92: =+AN29+AM29+AH29+AG29 -> 634.168 | AO92: =+AO29+AN29+AM29+AH29 -> 205.949 | AP92: =+AP29+AO29+AN29+AM29 -> -263.553 | AQ92: =+AQ29+AP29+AO29+AN29 -> 933.307 | AR92: =+AR29+AM29+AH29+AG29 -> 373.445 | AS92: =+AS29+AR29+AM29+AH29 -> -348.577 | AT92: =+AT29+AS29+AR29+AM29 -> -841.947 | AU92: =+AU29+AT29+AS29+AR29 -> -4863.198 | AV92: =+AV29+AR29+AS29+AM29 -> -1183.564 | AW92: =+AW29+AV29+AR29+AS29 -> -2414.35 | AX92: =+AX29+AU29+AV29+AS29 -> -4792.867 | AY92: =+AY29+AV29+AW29+AT29 -> -1765.069 | AZ92: =+AZ29+AX29+AU29+AV29 -> -5609.53 | BA92: =+BA29+AY29+AV29+AW29 -> -1928.406 | BB92: =+BB29+AZ29+AX29+AU29 -> -4815.371 | BC92: =+BC29+AZ29+AX29+AU29 -> -5129.674 | BD92: =+BD29+BB29+AX29+AZ29 -> 456.5 | BE92: =+BE29+BD29+BC29+BA29 -> 1065.453 | BF92: =+BF29+BE29+BD29+BC29 -> 1460.553 | BG92: =+BG29+BF29+BE29+BD29 -> 2496.255 | BH92: =+BH29+BG29+BF29+BE29 -> 1598.859 | BI92: =+BI29+BH29+BG29+BF29 -> 1772.393 | BJ92: =+BJ29+BI29+BH29+BG29 -> 1536.306 | BK92: =+BK29+BJ29+BI29+BH29 -> 406.163 | BL92: =+BL29+BK29+BJ29+BI29 -> 339.273 | BM92: =+BM29+BL29+BK29+BJ29 -> 418.565 | BO92: =+SUM(AY29,BA29,BC29,BO29) -> -654.727 | BP92: =+BP29+BO29+BA29+BC29 -> -555.409 | BQ92: =+BQ29+BP29+BC29+BO29 -> -313.189 | BR92: =+BR29+BQ29+BO29+BP29 -> 594.348 | BS92: =+BS29+BR29+BP29+BQ29 -> 804.989 | BT92: =+BT29+BS29+BQ29+BR29 -> 720.526
B93: Capex | C93: =-C69 -> 5483.062 | D93: =-D69 -> 4885.106 | E93: =-E69 -> 6637.125 | F93: =-F69 -> 6770.736 | G93: =-G69 -> 4518.966 | H93: =-H69 -> 6369 | I93: =-I69 -> 9652.003 | J93: =-J69 -> 6248.195 | ... R93: =-R69 -> 1643.64 | W93: =-W69-V69-U69-T69 -> 6637.125 | X93: =-X69-W69-V69-U69 -> 7004.003 | Y93: =-Y69-X69-W69-V69 -> 6571.627 | Z93: =-Z69-Y69-X69-W69 -> 6200.043 | AA93: =-AA69-Z69-Y69-X69 -> 6770.736 | AB93: =-AB69-AA69-Z69-Y69 -> 5818.104 | AC93: =-AC69-AB69-AA69-Z69 -> 6113.229 | AD93: =-AD69-AC69-AB69-AA69 -> 5721.085 | ... AI93: =-AI69-AH69-AG69-AF69 -> 6369 | AN93: =-AN69-AI69-AH69-AG69 -> 6786.087 | AO93: =-AO69-AN69-AI69-AH69 -> 8346.731 | AP93: =-AP69-AO69-AN69-AI69 -> 9426.315 | AQ93: =-AQ69-AP69-AO69-AN69 -> 9652.003 | AR93: =-AR69-AI69-AH69-AG69 -> 6786.087 | AS93: =-AS69-AR69-AI69-AH69 -> 8346.731 | AT93: =-AT69-AS69-AR69-AI69 -> 9426.315 | AU93: =-AU69-AT69-AS69-AR69 -> 9652.003 | AV93: =-AV69-AS69-AR69-AI69 -> 9426.315 | AW93: =-AW69-AV69-AS69-AR69 -> 9730.275 | AX93: =-AX69-AU69-AV69-AS69 -> 9778.009 | AY93: =-AY69-AV69-AW69-AT69 -> 9020.202 | AZ93: =-AZ69-AX69-AU69-AV69 -> 8313.935 | BA93: =-BA69-AY69-AV69-AW69 -> 8392.207 | BB93: =-BB69-AZ69-AX69-AU69 -> 7433.899 | BC93: =-BC69-AZ69-AX69-AU69 -> 7433.899 | BD93: =-BD69-BB69-AX69-AZ69 -> 6949.414 | BE93: =-BE69-BD69-BC69-BA69 -> 6645.656 | BF93: =-BF69-BE69-BD69-BC69 -> 6090.398 | BG93: =-BG69-BF69-BE69-BD69 -> 5324.156 | BH93: =-BH69-BG69-BF69-BE69 -> 5043.177 | BI93: =-BI69-BH69-BG69-BF69 -> 4369.318 | BJ93: =-BJ69-BI69-BH69-BG69 -> 3337.419 | BK93: =-BK69-BJ69-BI69-BH69 -> 2793.326 | BL93: =-BL69-BK69-BJ69-BI69 -> 2028.257 | BM93: =-BM69-BL69-BK69-BJ69 -> 1643.64 | BO93: =-SUM(AY69,BA69,BC69,BO69) -> 7106.41 | BP93: =-BP69-BO69-BC69-BA69 -> 6802.652 | BQ93: =-BQ69-BP69-BO69-BC69 -> 6247.394 | BR93: =-BR69-BQ69-BP69-BO69 -> 5481.152 | BS93: =-BS69-BR69-BQ69-BP69 -> 5126.314 | BT93: =-BT69-BS69-BR69-BQ69 -> 4452.455
B94: Free cash flow | C94: =+C72 -> 8280.95 | D94: =+D72 -> 9944.105 | E94: =+E72 -> 7101.765 | F94: =+F72 -> 13613.443 | G94: =+G72 -> 12647.968 | H94: =+H72 -> 13337.669 | I94: =+I72 -> 8376.519 | J94: =+J72 -> 10905.638 | ... R94: =+R72 -> 6168.369 | W94: =+W72+V72+U72+T72 -> 7101.765 | X94: =+X72+W72+V72+U72 -> 12248.09 | Y94: =+Y72+X72+W72+V72 -> 15246.819 | Z94: =+Z72+Y72+X72+W72 -> 16877.962 | AA94: =+AA72+Z72+Y72+X72 -> 13613.443 | AB94: =+AB72+AA72+Z72+Y72 -> 12703.816 | AC94: =+AC72+AB72+AA72+Z72 -> 12424.191 | AD94: =+AD72+AC72+AB72+AA72 -> 12814.458 | ... AI94: =+AI72+AH72+AG72+AF72 -> 13337.669 | AN94: =+AN72+AI72+AH72+AG72 -> 13779.949 | AO94: =+AO72+AN72+AI72+AH72 -> 9375.101 | AP94: =+AP72+AO72+AN72+AI72 -> 8069.032 | AQ94: =+AQ72+AP72+AO72+AN72 -> 8376.519 | AR94: =+AR72+AI72+AH72+AG72 -> 13127.486 | AS94: =+AS72+AR72+AI72+AH72 -> 8041.99 | AT94: =+AT72+AS72+AR72+AI72 -> 6004.321 | AU94: =+AU72+AT72+AS72+AR72 -> 5539.164 | AV94: =+AV72+AS72+AR72+AI72 -> 5840.121 | AW94: =+AW72+AV72+AR72+AS72 -> 4592.424 | AX94: =+AX72+AU72+AV72+AS72 -> 4641.058 | AY94: =+AY72+AV72+AW72+AT72 -> 6940.342 | AZ94: =+AZ72+AX72+AU72+AV72 -> 8238.017 | BA94: =+BA72+AY72+AV72+AW72 -> 6996.432 | BB94: =+BB72+AZ72+AX72+AU72 -> 9707.479 | BC94: =+BC72+AZ72+AX72+AU72 -> 9531.479 | BD94: =+BD72+BB72+AX72+AZ72 -> 9746.37 | BE94: =+BE72+BD72+BC72+BA72 -> 10457.43 | BF94: =+BF72+BE72+BD72+BC72 -> 12267.892 | BG94: =+BG72+BF72+BE72+BD72 -> 12796.772 | BH94: =+BH72+BG72+BF72+BE72 -> 14183.206 | BI94: =+BI72+BH72+BG72+BF72 -> 14173.96 | BJ94: =+BJ72+BI72+BH72+BG72 -> 12821.998 | BK94: =+BK72+BJ72+BI72+BH72 -> 11066.793 | BL94: =+BL72+BK72+BJ72+BI72 -> 8146.921 | BM94: =+BM72+BL72+BK72+BJ72 -> 6168.369 | BO94: =SUM(AY72,BA72,BC72,BO72) -> 9878.597 | BP94: =+BP72+BO72+BA72+BC72 -> 11291.379 | BQ94: =+BQ72+BP72+BC72+BO72 -> 11813.09 | BR94: =+BR72+BQ72+BO72+BP72 -> 11121.715 | BS94: =+BS72+BR72+BP72+BQ72 -> 8770.208 | BT94: =+BT72+BS72+BQ72+BR72 -> 7459.018
B96: BALANCE SHEET | C96: =+C86 -> 42707 | D96: =+D86 -> 43073 | E96: =E3 -> 43438 | F96: =F3 -> 43803 | G96: =G3 -> 44169 | H96: =H3 -> 44561 | I96: =I3 -> 44926 | J96: =J3 -> 44561 | K96: =K3 -> 44926 | L96: =L3 -> 44926 | ... Q96: =Q3 -> 46022 | R96: =+R86 -> 46112 | T96: =+T86 -> 43190 | U96: =+U86 -> 43281 | V96: =+V86 -> 43373 | W96: =+W86 -> 43465 | X96: =+X86 -> 43555 | Y96: =+Y86 -> 43646 | Z96: =+Z86 -> 43738 | AA96: =+AA86 -> 43830 | ... AI96: =+AI86 -> 44561 | AM96: =+AM86 -> 44561 | AN96: =+AN86 -> 44651 | AO96: =+AO86 -> 44742 | AP96: =+AP86 -> 44834 | AQ96: =+AQ86 -> 44926 | AR96: =+AR86 -> 44651 | AS96: =+AS86 -> 44742 | AT96: =+AT86 -> 44834 | ... BM96: =+BM86 -> 46112 | BO96: =+BO86 -> 45291 | BP96: =+BP86 -> 45382 | BQ96: =+BQ86 -> 45473 | BR96: =+BR86 -> 45565 | BS96: =+BS86 -> 45657 | BT96: =+BT86 -> 45747
B98: Tangible fixed assets | C98: =27481.605 -> 27481.605 | D98: 26909.97 | E98: 27290.458 | F98: 25633.223 | G98: =24495.647+8518.895 -> 33014.542 | H98: =26975.288+8983.213 -> 35958.501 | I98: =27201.035+9313.782 -> 36514.817 | J98: =26975.288+8983.213 -> 35958.501 | K98: =27200.975+9313.782 -> 36514.757 | L98: =27200.975+9313.782 -> 36514.757 | M98: =27439.783+10942.472 -> 38382.255 | N98: =27439.783+10942.472 -> 38382.255 | O98: =25521.642+9775.813 -> 35297.455 | P98: =25521.642+9775.813 -> 35297.455 | Q98: =14457.059+1917.208 -> 16374.267 | R98: =BM98 -> 16014.306 | T98: 25841.812 | U98: 26808.567 | V98: 27449.634 | W98: =+E98 -> 27290.458 | X98: 32359.527 | Y98: 33305.025 | Z98: 34279.601 | AA98: =F98 -> 25633.223 | AB98: =25210.673+8188.318 -> 33398.991 | AC98: 26256.254 | AD98: =25390.808+8294.771 -> 33685.579 | AE98: =G98 -> 33014.542 | AF98: =24434.257+8370.734 -> 32804.991 | AG98: =24946.702+8495.423 -> 33442.125 | AH98: =25447.568+8851.014 -> 34298.582 | AI98: =H98 -> 35958.501 | AM98: =J98 -> 35958.501 | AN98: =26060.724+9210.735 -> 35271.459 | AO98: =30940.863+9753.279 -> 40694.142 | AP98: =32606.909+10265.168 -> 42872.077 | AQ98: =I98 -> 36514.817 | AR98: =26060.724+9210.735 -> 35271.459 | AS98: =30940.863+9753.279 -> 40694.142 | AT98: =32606.909+10265.168 -> 42872.077 | AU98: =K98 -> 36514.757 | AV98: =32606.909+10265.168 -> 42872.077 | AW98: =L98 -> 36514.757 | AX98: =27933.612+9760.248 -> 37693.86 | AY98: =27933.612+9760.248 -> 37693.86 | AZ98: =29846.974+10811.667 -> 40658.641 | BA98: =29846.974+10811.667 -> 40658.641 | BB98: =28201.89+10945.909 -> 39147.799 | BC98: =28201.89+10945.909 -> 39147.799 | BD98: =M98 -> 38382.255 | BE98: =27968.329+10987.8 -> 38956.129 | BF98: =27189.215+10507.114 -> 37696.329 | BG98: =(24455.585+9594.449) -> 34050.034 | BH98: =O98 -> 35297.455 | BI98: =24470.524+9232.594 -> 33703.118 | BJ98: =15172.085+1815.685 -> 16987.77 | BK98: =14900.375+1839.849 -> 16740.224 | BL98: =Q98 -> 16374.267 | BM98: =14105.643+1908.663 -> 16014.306 | BO98: =N98 -> 38382.255 | BP98: =BE98 -> 38956.129 | BQ98: =BF98 -> 37696.329 | BR98: =BG98 -> 34050.034 | BS98: =P98 -> 35297.455 | BT98: =BI98 -> 33703.118
B99: Inventory | C99: 174.747 | D99: 174.279 | E99: 219.13 | F99: 154.328 | G99: 141.663 | H99: 222.747 | I99: 221.562 | J99: 222.747 | K99: 216.351 | L99: 216.351 | M99: 218.889 | N99: 218.889 | O99: 122.663 | P99: 122.663 | Q99: 71.841 | R99: =BM99 -> 71.803 | T99: 198.719 | U99: 153.635 | V99: 181.099 | W99: =+E99 -> 219.13 | X99: 208.026 | Y99: 146.893 | Z99: 153.732 | AA99: =F99 -> 154.328 | AB99: 141.491 | AC99: 140.352 | AD99: 151.121 | AE99: =G99 -> 141.663 | AF99: 222.259 | AG99: 227.093 | AH99: 183.715 | AI99: =H99 -> 222.747 | AM99: =J99 -> 222.747 | AN99: 195.628 | AO99: 208.572 | AP99: 258.183 | AQ99: =I99 -> 221.562 | AR99: 195.628 | AS99: 208.572 | AT99: 258.183 | AU99: =K99 -> 216.351 | AV99: 258.183 | AW99: =L99 -> 216.351 | AX99: 206.209 | AY99: 206.209 | AZ99: 237.605 | BA99: 237.605 | BB99: 203.608 | BC99: 203.608 | BD99: =M99 -> 218.889 | BE99: 156.131 | BF99: 127.653 | BG99: 115.299 | BH99: =O99 -> 122.663 | BI99: 125.917 | BJ99: 65.78 | BK99: 74.52 | BL99: =Q99 -> 71.841 | BM99: 71.803 | BO99: =N99 -> 218.889 | BP99: =BE99 -> 156.131 | BQ99: =BF99 -> 127.653 | BR99: =BG99 -> 115.299 | BS99: =P99 -> 122.663 | BT99: =BI99 -> 125.917
B100: Trade accounts receivables, net | C100: 4775.304 | D100: 4496.637 | E100: 5115.23 | F100: 4721.973 | G100: 4362.395 | H100: 5060.933 | I100: 6863.366 | J100: 5060.933 | K100: 6943.592 | L100: 6943.592 | M100: 4808.681 | N100: 4784.46 | O100: 5349.462 | P100: 5349.462 | Q100: 3590.424 | R100: =BM100 -> 4181.64 | T100: 3670.066 | U100: 4079.667 | V100: 4474.542 | W100: =+E100 -> 5115.23 | X100: 4573.377 | Y100: 4640.227 | Z100: 4783.869 | AA100: =F100 -> 4721.973 | AB100: 5509.172 | AC100: 4393.911 | AD100: 3811.239 | AE100: =G100 -> 4362.395 | AF100: 4514.139 | AG100: 4296.281 | AH100: 4295.562 | AI100: =H100 -> 5060.933 | AM100: =J100 -> 5060.933 | AN100: 5046.041 | AO100: 5368.602 | AP100: 5477.927 | AQ100: =I100 -> 6863.366 | AR100: 5046.041 | AS100: 5368.602 | AT100: 5477.927 | AU100: =K100 -> 6943.592 | AV100: 5477.927 | AW100: =L100 -> 6943.592 | AX100: 7066.534 | AY100: 7066.534 | AZ100: 5330.531 | BA100: 5330.531 | BB100: 4440.554 | BC100: 4440.554 | BD100: =M100 -> 4808.681 | BE100: 5061.9 | BF100: 4733.59 | BG100: 4241.548 | BH100: =O100 -> 5349.462 | BI100: 5253.831 | BJ100: 4269.273 | BK100: 4087.096 | BL100: =Q100 -> 3590.424 | BM100: 4181.64 | BO100: =N100 -> 4784.46 | BP100: =BE100 -> 5061.9 | BQ100: =BF100 -> 4733.59 | BR100: =BG100 -> 4241.548 | BS100: =P100 -> 5349.462 | BT100: =BI100 -> 5253.831
B101: Trade creditors /payables | C101: 12282.899 | D101: 12616.963 | E101: 12484.444 | F101: 12178.262 | G101: 12001.948 | H101: 13555.061 | I101: 10534.267 | J101: 13555.061 | K101: 10579.565 | L101: 10579.565 | M101: 9317.385 | N101: 9293.164 | O101: 8979.886 | P101: 8979.886 | Q101: 5905.529 | R101: =BM101 -> 5615.442 | T101: 11524.581 | U101: 11838.221 | V101: 10812.664 | W101: =+E101 -> 12484.444 | X101: 11696.522 | Y101: 11697.698 | Z101: 12382.116 | AA101: =F101 -> 12178.262 | AB101: 12400.392 | AC101: 12642.009 | AD101: 11983.599 | AE101: =G101 -> 12001.948 | AF101: 11384.961 | AG101: 11870.698 | AH101: 12641.238 | AI101: =H101 -> 13555.061 | AM101: =J101 -> 13555.061 | AN101: 12629.671 | AO101: 13213.952 | AP101: 13377.058 | AQ101: =I101 -> 10534.267 | AR101: 12629.671 | AS101: 13213.952 | AT101: 13377.058 | AU101: =K101 -> 10579.565 | AV101: 13377.058 | AW101: =L101 -> 10579.565 | AX101: 10060.58 | AY101: 10060.58 | AZ101: 10436.017 | BA101: 10436.017 | BB101: 9383.292 | BC101: 9383.292 | BD101: =M101 -> 9317.385 | BE101: 8990.86 | BF101: 8960.984 | BG101: 7859.695 | BH101: =O101 -> 8979.886 | BI101: 8659.645 | BJ101: 5915.515 | BK101: 6007.532 | BL101: =Q101 -> 5905.529 | BM101: 5615.442 | BO101: =N101 -> 9293.164 | BP101: =BE101 -> 8990.86 | BQ101: =BF101 -> 8960.984 | BR101: =BG101 -> 7859.695 | BS101: =P101 -> 8979.886 | BT101: =BI101 -> 8659.645
B102: Net working capital | C102: =C99+C100-C101 -> -7332.848 | D102: =D99+D100-D101 -> -7946.047 | E102: =E99+E100-E101 -> -7150.084 | F102: =F99+F100-F101 -> -7301.961 | G102: =G99+G100-G101 -> -7497.89 | H102: =H99+H100-H101 -> -8271.381 | I102: =I99+I100-I101 -> -3449.339 | J102: =J99+J100-J101 -> -8271.381 | ... R102: =R99+R100-R101 -> -1361.999 | T102: =T99+T100-T101 -> -7655.796 | U102: =U99+U100-U101 -> -7604.919 | V102: =V99+V100-V101 -> -6157.023 | W102: =W99+W100-W101 -> -7150.084 | X102: =X99+X100-X101 -> -6915.119 | Y102: =Y99+Y100-Y101 -> -6910.578 | Z102: =Z99+Z100-Z101 -> -7444.515 | AA102: =AA99+AA100-AA101 -> -7301.961 | ... AI102: =AI99+AI100-AI101 -> -8271.381 | AM102: =AM99+AM100-AM101 -> -8271.381 | AN102: =AN99+AN100-AN101 -> -7388.002 | AO102: =AO99+AO100-AO101 -> -7636.778 | AP102: =AP99+AP100-AP101 -> -7640.948 | AQ102: =AQ99+AQ100-AQ101 -> -3449.339 | AR102: =AR99+AR100-AR101 -> -7388.002 | AS102: =AS99+AS100-AS101 -> -7636.778 | AT102: =AT99+AT100-AT101 -> -7640.948 | ... BM102: =BM99+BM100-BM101 -> -1361.999 | BO102: =BO99+BO100-BO101 -> -4289.815 | BP102: =BP99+BP100-BP101 -> -3772.829 | BQ102: =BQ99+BQ100-BQ101 -> -4099.741 | BR102: =BR99+BR100-BR101 -> -3502.848 | BS102: =BS99+BS100-BS101 -> -3507.761 | BT102: =BT99+BT100-BT101 -> -3279.897
B103: % of revenues | C103: =+C102/C87 -> -0.3400285 | D103: =+D102/D87 -> -0.32562562 | E103: =+E102/E87 -> -0.29934479 | F103: =+F102/F87 -> -0.29702918 | G103: =+G102/G87 -> -0.30978957 | H103: =+H102/H87 -> -0.31935019 | I103: =+I102/I87 -> -0.12533024 | J103: =+J102/J87 -> -0.41368554 | ... R103: =+R102/R87 -> -0.14383827 | W103: =+W102/W87 -> -0.29934479 | X103: =+X102/X87 -> -0.28708963 | Y103: =+Y102/Y87 -> -0.28352813 | Z103: =+Z102/Z87 -> -0.30282814 | AA103: =+AA102/AA87 -> -0.29702918 | AB103: =+AB102/AB87 -> -0.2735956 | AC103: =+AC102/AC87 -> -0.33352502 | AD103: =+AD102/AD87 -> -0.33135125 | ... AI103: =+AI102/AI87 -> -0.31935019 | AN103: =+AN102/AN87 -> -0.29863251 | AO103: =+AO102/AO87 -> -0.30481715 | AP103: =+AP102/AP87 -> -0.29649415 | AQ103: =+AQ102/AQ87 -> -0.12533024 | AR103: =+AR102/AR87 -> -0.31771731 | AS103: =+AS102/AS87 -> -0.34616766 | AT103: =+AT102/AT87 -> -0.35996431 | AU103: =+AU102/AU87 -> -0.15740134 | ... BJ103: =+BJ102/BJ87 -> -0.083304611 | BK103: =BK102/BR102-1 -> -0.47302424 | BL103: =+BL102/BL87 -> -0.19078624 | BM103: =+BM102/BM87 -> -0.14383827 | BO103: =BO102/AW102-1 -> 0.25447052 | BP103: =BP102/AY102-1 -> 0.35331764 | BQ103: =BQ102/BA102-1 -> -0.15779761 | BR103: =BR102/BC102-1 -> -0.26086687 | BS103: =BS102/BA102-1 -> -0.27940699 | BT103: =BT102/BC102-1 -> -0.30791158
B105: Debt Breakdown
B106: Short-term debt | C106: =+C107+C110 -> 7124.409 | D106: =+D107+D110 -> 4387.67 | E106: =+E107+E110 -> 4474.455 | F106: =+F107+F110 -> 9074.453 | G106: =+G107+G110 -> 4705.864 | H106: =+H107+H110 -> 5990.262 | I106: =+I107+I110 -> 8935.621 | J106: =+J107+J110 -> 5990.262 | ... R106: =+R107+R110 -> 5037.716 | T106: =+T107+T110 -> 3506.831 | U106: =+U107+U110 -> 3261.264 | V106: =+V107+V110 -> 4966.502 | W106: =+W107+W110 -> 4474.455 | X106: =+X107+X110 -> 5290.303 | Y106: =+Y107+Y110 -> 5058.495 | Z106: =+Z107+Z110 -> 5615.709 | AA106: =+AA107+AA110 -> 9074.453 | ... AI106: =+AI107+AI110 -> 5990.262 | AM106: =+AM107+AM110 -> 5990.262 | AN106: =+AN107+AN110 -> 6148.891 | AO106: =+AO107+AO110 -> 9324.216 | AP106: =+AP107+AP110 -> 9029.526 | AQ106: =+AQ107+AQ110 -> 8935.621 | AR106: =+AR107+AR110 -> 6148.891 | AS106: =+AS107+AS110 -> 9324.216 | AT106: =+AT107+AT110 -> 9029.526 | ... BM106: =+BM107+BM110 -> 5037.716 | BO106: =+BO107+BO110 -> 4756.656 | BP106: =BE106 -> 5325.528 | BQ106: =BF106 -> 5546.999 | BR106: =BG106 -> 6378.328 | BS106: =+BS107+BS110 -> 6515.913 | BT106: =+BT107+BT110 -> 7199.509
B107: Interest bearing borrowings (Loans) | C107: =+C108+C109 -> 7124.409 | D107: =+D108+D109 -> 4387.67 | E107: =+E108+E109 -> 4474.455 | F107: =+F108+F109 -> 7631.753 | G107: =+G108+G109 -> 2971.544 | H107: =+H108+H109 -> 4231.416 | I107: =+I108+I109 -> 7096.004 | J107: =+J108+J109 -> 4231.416 | ... R107: =+R108+R109 -> 4712.411 | T107: =+T108+T109 -> 3506.831 | U107: =+U108+U109 -> 3261.264 | V107: =+V108+V109 -> 4966.502 | W107: =+W108+W109 -> 4474.455 | X107: =+X108+X109 -> 4480.209 | Y107: =+Y108+Y109 -> 3729.968 | Z107: =+Z108+Z109 -> 4069.854 | AA107: =+AA108+AA109 -> 7631.753 | ... AI107: =+AI108+AI109 -> 4231.416 | AM107: =+AM108+AM109 -> 4231.416 | AN107: =+AN108+AN109 -> 4266.935 | AO107: =+AO108+AO109 -> 7310.052 | AP107: =+AP108+AP109 -> 6890.653 | AQ107: =+AQ108+AQ109 -> 7096.004 | AR107: =+AR108+AR109 -> 4266.935 | AS107: =+AS108+AS109 -> 7310.052 | AT107: =+AT108+AT109 -> 6890.653 | ... BM107: =+BM108+BM109 -> 4712.411 | BO107: =+BO108+BO109 -> 2670.161 | BP107: =BE107 -> 3259.873 | BQ107: =BF107 -> 3535.81 | BR107: =BG107 -> 4541.362 | BS107: =+BS108+BS109 -> 4682.743 | BT107: =BI107 -> 5077.276
B108: Secured | C108: 333.788 | D108: 93.502 | E108: 912.254 | F108: 79.204 | G108: 278.391 | H108: 280.124 | I108: 361.942 | J108: 280.123 | K108: 361.942 | L108: 361.942 | M108: 189.863 | N108: 190.049 | O108: 115.036 | P108: 115.204 | Q108: 1752.382 | R108: =BM108 -> 91.315 | T108: 99.419 | U108: 117.684 | V108: 667.139 | W108: =+E108 -> 912.254 | X108: 960.399 | Y108: 87.458 | Z108: 96.682 | AA108: =F108 -> 79.204 | AB108: 105.852 | AC108: 147.122 | AD108: 132.669 | AE108: =G108 -> 278.391 | AF108: 178.772 | AG108: 214.662 | AH108: 169.697 | AI108: =H108 -> 280.124 | AM108: =J108 -> 280.123 | AN108: 280.575 | AO108: 388.73 | AP108: 411.251 | AQ108: =I108 -> 361.942 | AR108: 280.575 | AS108: 388.73 | AT108: 411.251 | AU108: =K108 -> 361.942 | AV108: 411.251 | AW108: =L108 -> 361.942 | AX108: 401.424 | AY108: 401.424 | AZ108: 314.106 | BA108: 314.106 | BB108: 179.128 | BC108: 179.128 | BD108: =M108 -> 189.863 | BE108: 181.097 | BF108: 139.786 | BG108: 131.18 | BH108: =O108 -> 115.036 | BI108: 75.639 | BJ108: 2096.41 | BK108: 1724.973 | BL108: =Q108 -> 1752.382 | BM108: 91.315 | BO108: =N108 -> 190.049 | BP108: =BE108 -> 181.097 | BQ108: =BF108 -> 139.786 | BR108: =BG108 -> 131.18 | BS108: =P108 -> 115.204 | BT108: =BI108 -> 75.639
B109: Unsecured | C109: 6790.621 | D109: 4294.168 | E109: 3562.201 | F109: 7552.549 | G109: 2693.153 | H109: 3951.292 | I109: 6734.062 | J109: 3951.293 | K109: 6726.186 | L109: 6726.186 | M109: 2476.097 | N109: 2480.112 | O109: 4567.707 | P109: 4567.539 | Q109: 4898.263 | R109: =BM109 -> 4621.096 | T109: 3407.412 | U109: 3143.58 | V109: 4299.363 | W109: =+E109 -> 3562.201 | X109: 3519.81 | Y109: 3642.51 | Z109: 3973.172 | AA109: =F109 -> 7552.549 | AB109: 8940.551 | AC109: 7391.918 | AD109: 5083.111 | AE109: =G109 -> 2693.153 | AF109: 2656.935 | AG109: 2353.983 | AH109: 2776.046 | AI109: =H109 -> 3951.292 | AM109: =J109 -> 3951.293 | AN109: 3986.36 | AO109: 6921.322 | AP109: 6479.402 | AQ109: =I109 -> 6734.062 | AR109: 3986.36 | AS109: 6921.322 | AT109: 6479.402 | AU109: =K109 -> 6726.186 | AV109: 6479.402 | AW109: =L109 -> 6726.186 | AX109: 6872.059 | AY109: 6872.059 | AZ109: 3461.101 | BA109: 3461.101 | BB109: 2556.604 | BC109: 2556.604 | BD109: =M109 -> 2476.097 | BE109: 3078.776 | BF109: 3396.024 | BG109: 4410.182 | BH109: =O109 -> 4567.707 | BI109: 5001.637 | BJ109: 5127.587 | BK109: 3122.402 | BL109: =Q109 -> 4898.263 | BM109: 4621.096 | BO109: =N109 -> 2480.112 | BP109: =BE109 -> 3078.776 | BQ109: =BF109 -> 3396.024 | BR109: =BG109 -> 4410.182 | BS109: =P109 -> 4567.539 | BT109: =BI109 -> 5001.637
B110: Lease Liabilities | E110: 0 | F110: 1442.7 | G110: 1734.32 | H110: 1758.846 | I110: 1839.617 | J110: 1758.846 | K110: 1839.617 | L110: 1839.617 | M110: 2086.495 | N110: 2086.495 | O110: 1833.17 | P110: 1833.17 | Q110: 330.526 | R110: =BM110 -> 325.305 | T110: 0 | U110: 0 | V110: 0 | W110: =+E110 -> 0 | X110: 810.094 | Y110: 1328.527 | Z110: 1545.855 | AA110: =F110 -> 1442.7 | AB110: 1582.519 | AC110: 1596.246 | AD110: 1660.852 | AE110: =G110 -> 1734.32 | AF110: 1976.374 | AG110: 1790.875 | AH110: 1782.803 | AI110: =H110 -> 1758.846 | AM110: =J110 -> 1758.846 | AN110: 1881.956 | AO110: 2014.164 | AP110: 2138.873 | AQ110: =I110 -> 1839.617 | AR110: 1881.956 | AS110: 2014.164 | AT110: 2138.873 | AU110: =K110 -> 1839.617 | AV110: 2138.873 | AW110: =L110 -> 1839.617 | AX110: 2358.639 | AY110: 2358.639 | AZ110: 2229.476 | BA110: 2229.476 | BB110: 2143.294 | BC110: 2143.294 | BD110: =M110 -> 2086.495 | BE110: 2065.655 | BF110: 2011.189 | BG110: 1836.966 | BH110: =O110 -> 1833.17 | BI110: 2122.233 | BJ110: 327.369 | BK110: 326.012 | BL110: =Q110 -> 330.526 | BM110: 325.305 | BO110: =N110 -> 2086.495 | BP110: =BE110 -> 2065.655 | BQ110: =BF110 -> 2011.189 | BR110: =BG110 -> 1836.966 | BS110: =P110 -> 1833.17 | BT110: =BI110 -> 2122.233
B111: Long-term debt | C111: =+C112+C115 -> 15135.472 | D111: =+D112+D115 -> 14796.319 | E111: =+E112+E115 -> 14646.553 | F111: =+F112+F115 -> 16592.107 | G111: =+G112+G115 -> 22668.171 | H111: =+H112+H115 -> 23231.228 | I111: =+I112+I115 -> 26942.446 | J111: =+J112+J115 -> 23231.228 | ... R111: =+R112+R115 -> 11856.666 | T111: =+T112+T115 -> 14647.986 | U111: =+U112+U115 -> 15411.108 | V111: =+V112+V115 -> 14503.375 | W111: =+W112+W115 -> 14646.553 | X111: =+X112+X115 -> 21142.028 | Y111: =+Y112+Y115 -> 20551.156 | Z111: =+Z112+Z115 -> 20082.976 | AA111: =+AA112+AA115 -> 16592.107 | ... AI111: =+AI112+AI115 -> 23231.228 | AM111: =+AM112+AM115 -> 23231.228 | AN111: =+AN112+AN115 -> 22693.522 | AO111: =+AO112+AO115 -> 26528.494 | AP111: =+AP112+AP115 -> 30156.837 | AQ111: =+AQ112+AQ115 -> 26942.446 | AR111: =+AR112+AR115 -> 22693.522 | AS111: =+AS112+AS115 -> 26528.494 | AT111: =+AT112+AT115 -> 30156.837 | ... BM111: =+BM112+BM115 -> 11856.666 | BO111: =+BO112+BO115 -> 32187.5 | BP111: =BE111 -> 32018.543 | BQ111: =BF111 -> 31691.787 | BR111: =BG111 -> 26421.302 | BS111: =+BS112+BS115 -> 27710.059 | BT111: =BI111 -> 25860.79
...

Sheet KPI
B2: Axiata | C2: Annual | D2: Annual | E2: Annual | F2: Annual | G2: Annual | H2: Annual | I2: Annual | J2: Annual | K2: Annual | L2: Annual | M2: Annual | N2: Annual | O2: Annual | Q2: Quarterly | R2: Quarterly | S2: Quarterly | T2: Quarterly | U2: Quarterly | V2: Quarterly | W2: Quarterly | X2: Quarterly | Y2: Quarterly | Z2: Quarterly | AA2: Quarterly | AB2: Quarterly | AC2: Quarterly | AD2: Quarterly | AE2: Quarterly | AF2: Quarterly | AG2: Quarterly | AH2: Quarterly | AI2: Quarterly | AJ2: Quarterly | AK2: Quarterly | AL2: Quarterly | AM2: Quarterly | AN2: Quarterly | AO2: Quarterly | AP2: Quarterly | AQ2: Quarterly | AR2: Quarterly | AS2: Quarterly | AT2: Quarterly | AU2: Quarterly | AV2: Quarterly | AW2: Quarterly | AY2: Quarterly | AZ2: Quarterly | BA2: Quarterly | BC2: 6M | BD2: 6M | BF2: 9M | BG2: 9M
B3: (MYR millions) | C3: 42735 | D3: =EDATE(C3,12) -> 43100 | E3: =EDATE(D3,12) -> 43465 | F3: =EDATE(E3,12) -> 43830 | G3: =EDATE(F3,12) -> 44196 | H3: =EDATE(G3,12) -> 44561 | I3: 44561 | J3: =EDATE(H3,12) -> 44926 | K3: 44926 | L3: =EDATE(J3,12) -> 45291 | M3: =EDATE(K3,12) -> 45291 | N3: 45657 | O3: 46022 | Q3: 43160 | R3: 43252 | S3: 43344 | T3: 43435 | U3: 43525 | V3: 43617 | W3: 43709 | X3: 43800 | Y3: 43891 | Z3: 43983 | AA3: 44075 | AB3: 44166 | AC3: 44256 | AD3: 44348 | AE3: 44440 | AF3: 44531 | AG3: 44621 | AH3: 44713 | AI3: 44805 | AJ3: 44896 | AK3: 44986 | AL3: 45078 | AM3: 45199 | AN3: 45261 | AO3: 45352 | AP3: 45444 | AQ3: 45565 | AR3: 45627 | AS3: 45717 | AT3: 45809 | AU3: 45901 | AV3: 45992 | AW3: 46082 | AY3: 45261 | AZ3: 45382 | BA3: 45747 | BC3: 45444 | BD3: 45809 | BF3: 45536 | BG3: 45901
C4: Act | D4: Act | E4: Act | F4: Act | G4: Act | H4: Act | I4: Act | J4: Act | K4: Act | L4: Act | M4: Act | N4: Act | O4: Act | Q4: Act | R4: Act | S4: Act | T4: Act | U4: Act | V4: Act | W4: Act | X4: Act | Y4: Act | Z4: Act | AA4: Act | AB4: Act | AC4: Act | AD4: Act | AE4: Act | AF4: Act | AG4: Act | AH4: Act | AI4: Act | AJ4: Act | AK4: Act | AL4: Act | AM4: Act | AN4: Act | AO4: Act | AP4: Act | AQ4: Act | AR4: Act | AS4: Act | AT4: Act | AU4: Act | AV4: Act | AW4: Act | AY4: Act | AZ4: Act | BA4: Act | BC4: Act | BD4: Act | BF4: Act | BG4: Act
C5: FY | D5: FY | E5: FY | F5: FY | G5: FY | H5: FY | I5: FY | J5: FY | K5: FY | L5: FY | M5: FY | N5: FY | O5: FY | Q5: Q1 | R5: Q2 | S5: Q3 | T5: Q4 | U5: Q1 | V5: Q2 | W5: Q3 | X5: Q4 | Y5: Q1 | Z5: Q2 | AA5: Q3 | AB5: Q4 | AC5: Q1 | AD5: Q2 | AE5: Q3 | AF5: Q4 | AG5: Q1 | AH5: Q2 | AI5: Q3 | AJ5: Q4 | AK5: Q1 | AL5: Q2 | AM5: Q3 | AN5: Q4 | AO5: Q1 | AP5: Q2 | AQ5: Q3 | AR5: Q4 | AS5: Q1 | AT5: Q2 | AU5: Q3 | AV5: Q4 | AW5: Q1 | AY5: Q4 | AZ5: Q1 | BA5: Q1 | BC5: 6M | BD5: 6M | BF5: 9M | BG5: 9M
I6: Restated | K6: Restated | M6: Restated and reclassified | AY6: Restated and reclassified | AZ6: Restated | BA6: Restated | BC6: Restated | BD6: Act | BF6: Restated | BG6: Act
B8: Revenue by segment
B9: Mobile
B10: Malaysia | C10: 6576.648 | D10: 6549.138 | E10: 7284.632 | F10: 6651.37 | G10: 6174.047 | H10: 6603.94 | Q10: 1789.977 | R10: =3588.746-Q10 -> 1798.769 | S10: =5388.829-R10-Q10 -> 1800.083 | T10: =+E10-Q10-R10-S10 -> 1895.803 | U10: 1651.508 | V10: =3303.106-U10 -> 1651.598 | W10: =4924.836-V10-U10 -> 1621.73 | X10: =+F10-U10-V10-W10 -> 1726.534 | Y10: 1538.068 | Z10: =2974.814-Y10 -> 1436.746 | AA10: =4546.506-Z10-Y10 -> 1571.692 | AB10: =+G10-Y10-Z10-AA10 -> 1627.541 | AC10: 1636.484 | AD10: =3260.898-AC10 -> 1624.414 | AE10: =4859.306-AD10-AC10 -> 1598.408 | AF10: =+H10-AC10-AD10-AE10 -> 1744.634
B11: Indonesia | C11: 6604.17 | D11: 7288.351 | E11: 6426.079 | F11: 7261.368 | G11: 7490.193 | H11: 7744.658 | I11: 7755.128 | J11: 8625.766 | K11: 8625.766 | L11: 9574.994 | M11: 9574.994 | N11: 9693.664 | O11: 9693.664 | Q11: 1569.786 | R11: =3124.307-Q11 -> 1554.521 | S11: =4733.535-R11-Q11 -> 1609.228 | T11: =+E11-Q11-R11-S11 -> 1692.544 | U11: 1719.248 | V11: =3505.604-U11 -> 1786.356 | W11: =5392.721-V11-U11 -> 1887.117 | X11: =+F11-U11-V11-W11 -> 1868.647 | Y11: 1878.396 | Z11: =3764.315-Y11 -> 1885.919 | AA11: =5677.409-Z11-Y11 -> 1913.094 | AB11: =+G11-Y11-Z11-AA11 -> 1812.784 | AC11: 1789.554 | AD11: =3715.295-AC11 -> 1925.741 | AE11: =5708.452-AD11-AC11 -> 1993.157 | AF11: =+H11-AC11-AD11-AE11 -> 2036.206 | AG11: 1968.616 | AH11: =4154.08-AG11 -> 2185.464 | AI11: =6413.558-AH11-AG11 -> 2259.478 | AJ11: =K11-AG11-AH11-AI11 -> 2212.208 | AK11: 2172.099 | AL11: =4620.759-AK11 -> 2448.66 | AM11: =7063.574-AL11-AK11 -> 2442.815 | AN11: =L11-AK11-AL11-AM11 -> 2511.42 | AO11: 2503.295 | AP11: =4972.006-AO11 -> 2468.711 | AQ11: =7260.508-AP11-AO11 -> 2288.502 | AR11: =N11-AO11-AP11-AQ11 -> 2433.156 | AV11: =R11-AS11-AT11-AU11 -> 1554.521
B12: Bangladesh | C12: 2783.393 | D12: 3640.633 | E12: 3272.499 | F12: 3652.726 | G12: 3711.903 | H12: 3858.048 | I12: 3858.048 | J12: 3968.059 | K12: 3968.064 | L12: 4112.954 | M12: 4112.954 | N12: 3867.504 | O12: 3867.504 | Q12: 769.011 | R12: =1546.178-Q12 -> 777.167 | S12: =2398.035-R12-Q12 -> 851.857 | T12: =+E12-Q12-R12-S12 -> 874.464 | U12: 892.444 | V12: =1806.804-U12 -> 914.36 | W12: =2732.975-V12-U12 -> 926.171 | X12: =+F12-U12-V12-W12 -> 919.751 | Y12: 952.575 | Z12: =1848.337-Y12 -> 895.762 | AA12: =2795.488-Z12-Y12 -> 947.151 | AB12: =+G12-Y12-Z12-AA12 -> 916.415 | AC12: 942.643 | AD12: =1893.532-AC12 -> 950.889 | AE12: =2888.534-AD12-AC12 -> 995.002 | AF12: =+H12-AC12-AD12-AE12 -> 969.514 | AG12: 957.095 | AH12: =1967.581-AG12 -> 1010.486 | AI12: =2982.608-AH12-AG12 -> 1015.027 | AJ12: =K12-AG12-AH12-AI12 -> 985.456 | AK12: 954.866 | AL12: =2007.02-AK12 -> 1052.154 | AM12: =3064.641-AL12-AK12 -> 1057.621 | AN12: =L12-AK12-AL12-AM12 -> 1048.313 | AO12: 1060.3 | AP12: =2119.615-AO12 -> 1059.315 | AQ12: =3026.902-AP12-AO12 -> 907.287 | AR12: =N12-AO12-AP12-AQ12 -> 840.602 | AV12: =R12-AS12-AT12-AU12 -> 777.167
B13: Sri Lanka | C13: 2415.658 | D13: 2642.009 | E13: 2700.05 | F13: 2676.665 | G13: 2699.746 | H13: 2923.208 | I13: 2923.377 | J13: 2507.468 | K13: 2507.833 | L13: 2622.845 | M13: 2622.845 | N13: 2654.312 | O13: 2654.312 | Q13: 652.212 | R13: =1317.304-Q13 -> 665.092 | S13: =2023.049-R13-Q13 -> 705.745 | T13: =+E13-Q13-R13-S13 -> 677.001 | U13: 660.024 | V13: =1345.576-U13 -> 685.552 | W13: =2010.147-V13-U13 -> 664.571 | X13: =+F13-U13-V13-W13 -> 666.518 | Y13: 651.298 | Z13: =1307.873-Y13 -> 656.575 | AA13: =1996.724-Z13-Y13 -> 688.851 | AB13: =+G13-Y13-Z13-AA13 -> 703.022 | AC13: 677.757 | AD13: =1389.049-AC13 -> 711.292 | AE13: =2159.259-AD13-AC13 -> 770.21 | AF13: =+H13-AC13-AD13-AE13 -> 763.949 | AG13: 728.359 | AH13: =1284.286-AG13 -> 555.927 | AI13: =1859.175-AH13-AG13 -> 574.889 | AJ13: =K13-AG13-AH13-AI13 -> 648.658 | AK13: 621.862 | AL13: =1317.917-AK13 -> 696.055 | AM13: =1992.801-AL13-AK13 -> 674.884 | AN13: =L13-AK13-AL13-AM13 -> 630.044 | AO13: 652.111 | AP13: =1272.001-AO13 -> 619.89 | AQ13: =1964.061-AP13-AO13 -> 692.06 | AR13: =N13-AO13-AP13-AQ13 -> 690.251 | AV13: =R13-AS13-AT13-AU13 -> 665.092
B14: Nepal | C14: 1613.036 | D14: 2352.207 | E14: 2098.039 | F14: 1974.475 | G14: 1476.525 | H14: 1437.759 | I14: 1437.785 | J14: 1387.643 | Q14: 541.004 | R14: =1090.467-Q14 -> 549.463 | S14: =1586.705-R14-Q14 -> 496.238 | T14: =+E14-Q14-R14-S14 -> 511.334 | U14: 497.595 | V14: =1017.926-U14 -> 520.331 | W14: =1506.468-V14-U14 -> 488.542 | X14: =+F14-U14-V14-W14 -> 468.007 | Y14: 442.802 | Z14: =758.239-Y14 -> 315.437 | AA14: =1106.947-Z14-Y14 -> 348.708 | AB14: =+G14-Y14-Z14-AA14 -> 369.578 | AC14: 377.288 | AD14: =722.6-AC14 -> 345.312 | AE14: =1076.261-AD14-AC14 -> 353.661 | AF14: =+H14-AC14-AD14-AE14 -> 361.498 | AG14: 340.12 | AH14: =705.079-AG14 -> 364.959 | AJ14: =K14-AG14-AH14-AI14 -> -705.079 | AK14: 309.862 | AL14: =638.612-AK14 -> 328.75 | AN14: =L14-AK14-AL14-AM14 -> -638.612 | AR14: =N14-AO14-AP14-AQ14 -> 0 | AV14: =R14-AS14-AT14-AU14 -> 549.463
B15: Cambodia | C15: 1078.398 | D15: 1173.882 | E15: 1147.383 | F15: 1282.445 | G15: 1361.84 | H15: 1420.214 | I15: 1420.33 | J15: 1610.741 | K15: 1610.743 | L15: 1687.279 | M15: 1687.279 | N15: 1843.392 | O15: 1843.392 | Q15: 251.225 | R15: =532.584-Q15 -> 281.359 | S15: =828.729-R15-Q15 -> 296.145 | T15: =+E15-Q15-R15-S15 -> 318.654 | U15: 302.132 | V15: =620.517-U15 -> 318.385 | W15: =949.757-V15-U15 -> 329.24 | X15: =+F15-U15-V15-W15 -> 332.688 | Y15: 317.423 | Z15: =627.696-Y15 -> 310.273 | AA15: =953.312-Z15-Y15 -> 325.616 | AB15: =+G15-Y15-Z15-AA15 -> 408.528 | AC15: 337.341 | AD15: =675.664-AC15 -> 338.323 | AE15: =1039.738-AD15-AC15 -> 364.074 | AF15: =+H15-AC15-AD15-AE15 -> 380.476 | AG15: 361.691 | AH15: =746.237-AG15 -> 384.546 | AI15: =1195.041-AH15-AG15 -> 448.804 | AJ15: =K15-AG15-AH15-AI15 -> 415.702 | AK15: 386.975 | AL15: =801.596-AK15 -> 414.621 | AM15: =1230.243-AL15-AK15 -> 428.647 | AN15: =L15-AK15-AL15-AM15 -> 457.036 | AO15: 462.342 | AP15: =941.74-AO15 -> 479.398 | AQ15: =1387.152-AP15-AO15 -> 445.412 | AR15: =N15-AO15-AP15-AQ15 -> 456.24 | AV15: =R15-AS15-AT15-AU15 -> 281.359
B16: Fixed BB | AR16: =N16-AO16-AP16-AQ16 -> 0 | AV16: =R16-AS16-AT16-AU16 -> 0
B17: Indonesia | J17: 669.269 | K17: 669.269 | L17: 1172.017 | M17: 1172.017 | N17: 938.731 | O17: 938.731 | AI17: =320.934-AH17-AG17 -> 320.934 | AJ17: =K17-AG17-AH17-AI17 -> 348.335 | AK17: 281.558 | AL17: =581.286-AK17 -> 299.728 | AM17: =876.511-AK17-AL17 -> 295.225 | AN17: =L17-AK17-AL17-AM17 -> 295.506 | AO17: 272.246 | AP17: =537.474-AO17 -> 265.228 | AQ17: =799.369-AO17-AP17 -> 261.895 | AR17: =N17-AO17-AP17-AQ17 -> 139.362 | AV17: =R17-AS17-AT17-AU17 -> 0
B18: Infrastructure | T18: =+E18-Q18-R18-S18 -> 0 | X18: =+F18-U18-V18-W18 -> 0 | AB18: =+G18-Y18-Z18-AA18 -> 0 | AF18: =+H18-AC18-AD18-AE18 -> 0 | AR18: =N18-AO18-AP18-AQ18 -> 0 | AV18: =R18-AS18-AT18-AU18 -> 0
B19: Malaysia | C19: 231.492 | D19: 429.123 | E19: 576.433 | F19: 663.057 | G19: 761.187 | H19: 793.376 | I19: 1391.518 | J19: 1843.427 | K19: 1537.411 | L19: 1865.257 | M19: 2181.314 | N19: 2227.909 | O19: 2227.909 | Q19: 96.163 | R19: =258.37-Q19 -> 162.207 | S19: =409.119-R19-Q19 -> 150.749 | T19: =+E19-Q19-R19-S19 -> 167.314 | U19: 156.371 | V19: =308.713-U19 -> 152.342 | W19: =482.011-V19-U19 -> 173.298 | X19: =+F19-U19-V19-W19 -> 181.046 | Y19: 180.492 | Z19: =362.958-Y19 -> 182.466 | AA19: =547.219-Z19-Y19 -> 184.261 | AB19: =+G19-Y19-Z19-AA19 -> 213.968 | AC19: 186.9 | AD19: =373.917-AC19 -> 187.017 | AE19: =570.366-AD19-AC19 -> 196.449 | AF19: =+H19-AC19-AD19-AE19 -> 223.01 | AG19: 407.848 | AH19: =861.255-AG19 -> 453.407 | AI19: =1323.197-AH19-AG19 -> 461.942 | AJ19: =K19-AG19-AH19-AI19 -> 214.214 | AK19: 470.1 | AL19: =1026.252-AK19 -> 556.152 | AM19: =1561.921-AL19-AK19 -> 535.669 | AN19: =L19-AK19-AL19-AM19 -> 303.336 | AO19: 443.298 | AP19: =1014.617-AO19 -> 571.319 | AQ19: =1462.852-AP19-AO19 -> 448.235 | AR19: =N19-AO19-AP19-AQ19 -> 765.057 | AV19: =R19-AS19-AT19-AU19 -> 162.207
B20: Others | C20: 262.597 | D20: 327.058 | E20: 380.666 | F20: 421.206 | G20: 527.73 | H20: 1119.458 | I20: 1208.182 | J20: 1113.362 | K20: =87.71+859.778+153.706 -> 1101.194 | L20: =59.403+756.813+150.707 -> 966.923 | M20: =756.813+150.707+59.403 -> 966.923 | N20: =946.707+154.281+8.117 -> 1109.105 | O20: =946.707+154.281+8.117 -> 1109.105 | Q20: 78.871 | R20: =157.358-Q20 -> 78.487 | S20: =250.785-R20-Q20 -> 93.427 | T20: =+E20-Q20-R20-S20 -> 129.881 | U20: 70.115 | V20: =194.805-U20 -> 124.69 | W20: =317.39-V20-U20 -> 122.585 | X20: =+F20-U20-V20-W20 -> 103.816 | Y20: 75.53 | Z20: =184.766-Y20 -> 109.236 | AA20: =317.05-Z20-Y20 -> 132.284 | AB20: =+G20-Y20-Z20-AA20 -> 210.68 | AC20: 116.052 | AD20: =423.128-AC20 -> 307.076 | AE20: =695.13-AD20-AC20 -> 272.002 | AF20: =+H20-AC20-AD20-AE20 -> 424.328 | AG20: =173.988+15.576+30.597 -> 220.161 | AH20: =399.224+26.707+37.027-AG20 -> 242.797 | AI20: =637.671+55.479+56.47-AH20-AG20 -> 286.662 | AJ20: =K20-AG20-AH20-AI20 -> 351.574 | AK20: =140.787+25.229+15.378 -> 181.394 | AL20: =295.053+59.757+24.99-AK20 -> 198.406 | AM20: =510.132+91.425+38.447-AL20-AK20 -> 260.204 | AN20: =L20-AK20-AL20-AM20 -> 326.919 | AO20: =228.75+33.231+6.511 -> 268.492 | AP20: =462.761+64.134+33.504-AO20 -> 291.907 | AQ20: =691.382+99.321+47.947-AP20-AO20 -> 278.251 | AR20: =N20-AO20-AP20-AQ20 -> 270.455 | AV20: =R20-AS20-AT20-AU20 -> 78.487
B21: Eliminations | C21: 0 | D21: 0 | E21: 0 | F21: 0 | G21: 0 | H21: 0 | I21: 0 | J21: 0 | K21: 0 | L21: 0 | M21: 0 | N21: 0 | O21: 0 | Q21: 0 | R21: =0-Q21 -> 0 | S21: =0-R21-Q21 -> 0 | T21: =+E21-Q21-R21-S21 -> 0 | U21: 0 | V21: =0-U21 -> 0 | W21: =0-V21-U21 -> 0 | X21: =+F21-U21-V21-W21 -> 0 | Y21: 0 | Z21: =0-Y21 -> 0 | AA21: =0-Z21-Y21 -> 0 | AB21: =+G21-Y21-Z21-AA21 -> 0 | AC21: 0 | AD21: =0-AC21 -> 0 | AE21: =0-AD21-AC21 -> 0 | AF21: =+H21-AC21-AD21-AE21 -> 0 | AG21: 0 | AH21: =0-AG21 -> 0 | AI21: 0 | AJ21: =K21-AG21-AH21-AI21 -> 0 | AK21: 0 | AL21: =0-AK21 -> 0 | AM21: =0-AL21-AK21 -> 0 | AN21: =L21-AK21-AL21-AM21 -> 0 | AO21: 0 | AP21: =0-AO21 -> 0 | AQ21: =0-AP21-AO21 -> 0 | AR21: =N21-AO21-AP21-AQ21 -> 0 | AV21: =R21-AS21-AT21-AU21 -> 0
B22: Total continuing operations | C22: =+SUM(C10:C21) -> 21565.392 | D22: =+SUM(D10:D21) -> 24402.401 | E22: =+SUM(E10:E21) -> 23885.781 | F22: =+SUM(F10:F21) -> 24583.312 | G22: =+SUM(G10:G21) -> 24203.171 | H22: =+SUM(H10:H21) -> 25900.661 | I22: =+SUM(I10:I21) -> 19994.368 | J22: =+SUM(J10:J21) -> 21725.735 | ... O22: =+SUM(O10:O21) -> 22334.617 | Q22: =+SUM(Q10:Q21) -> 5748.249 | R22: =+SUM(R10:R21) -> 5867.065 | S22: =+SUM(S10:S21) -> 6003.472 | T22: =+SUM(T10:T21) -> 6266.995 | U22: =+SUM(U10:U21) -> 5949.437 | V22: =+SUM(V10:V21) -> 6153.614 | W22: =+SUM(W10:W21) -> 6213.254 | X22: =+SUM(X10:X21) -> 6267.007 | ... AR22: =+SUM(AR10:AR21) -> 5595.123 | AV22: =+SUM(AV10:AV21) -> 4068.296 | AY22: =+SUM(AY10:AY21) -> 0
B23: Discontinued Operation | I23: 5906.293 | J23: 5795.919 | K23: 7475.79 | L23: 1487.21 | AG23: 1486.061 | AH23: =2992.714-AG23 -> 1506.653 | AM23: =953.37-AL23-AK23 -> 953.37 | AN23: =L23-AK23-AL23-AM23 -> 533.84 | AO23: 76.959 | AR23: =N23-AO23-AP23-AQ23 -> -76.959 | AV23: =R23-AS23-AT23-AU23 -> 0
B24: Total | G24: =G22+G23 -> 24203.171 | H24: =H22+H23 -> 25900.661 | I24: =I22+I23 -> 25900.661 | J24: =J22+J23 -> 27521.654 | K24: =K22+K23 -> 27496.07 | L24: =L22+L23 -> 23489.479 | M24: =M22+M23 -> 22318.326 | N24: =N22+N23 -> 22334.617 | O24: =O22+O23 -> 22334.617 | Q24: =Q22+Q23 -> 5748.249 | R24: =R22+R23 -> 5867.065 | S24: =S22+S23 -> 6003.472 | T24: =T22+T23 -> 6266.995 | U24: =U22+U23 -> 5949.437 | V24: =V22+V23 -> 6153.614 | W24: =W22+W23 -> 6213.254 | X24: =X22+X23 -> 6267.007 | ... AR24: =AR22+AR23 -> 5518.164 | AV24: =AV22+AV23 -> 4068.296 | AY24: =AY22+AY23 -> 0
B26: Check | C26: =+C22-Model!C7 -> 0 | D26: =+D22-Model!D7 -> 0 | E26: =+E22-Model!E7 -> 0 | F26: =+F22-Model!F7 -> 0 | G26: =+G22-Model!G7 -> 0 | H26: =+H22-Model!H7 -> 0 | I26: =+I22-Model!J7 -> 0 | J26: =+J22-Model!K7 -> 0 | K26: =+K22-Model!L7 -> 0 | L26: =+L22-Model!M7 -> 0 | M26: =+M22-Model!N7 -> 0 | N26: =+N22-Model!O7 -> 0 | O26: =+O22-Model!P7 -> 9792.699 | Q26: =+Q22-Model!T7 -> 0 | R26: =+R22-Model!U7 -> 0 | S26: =+S22-Model!V7 -> 0 | T26: =+T22-Model!W7 -> 0 | U26: =+U22-Model!X7 -> 0 | V26: =+V22-Model!Y7 -> 0 | W26: =+W22-Model!Z7 -> 0 | X26: =+X22-Model!AA7 -> 0 | ... AF26: =+AF22-Model!AI7 -> 0 | AG26: =+AG22-Model!AR7 -> 0 | AH26: =+AH22-Model!AS7 -> -0.019 | AI26: =+AI22-Model!AV7 -> 0.353 | AJ26: =+AJ22-Model!AW7 -> -0.334 | AK26: =+AK22-Model!AX7 -> 0 | AL26: =+AL22-Model!AZ7 -> 0 | AM26: =+AM22-Model!BC7 -> -0.632 | AN26: =+AN22-Model!BD7 -> 0.632 | AO26: =+AO22-Model!BE7 -> 0 | AP26: =+AP22-Model!BF7 -> 0.002 | AQ26: =+AQ22-Model!BG7 -> -0.001 | AR26: =+AR22-Model!BH7 -> -0.001 | AV26: =+AV22-Model!BL7 -> 3286.095
B28: % of Revenue by segment
B29: =+B9 -> Mobile
B30: =+B10 -> Malaysia | C30: =+C10/C$22 -> 0.30496306 | D30: =+D10/D$22 -> 0.26838089 | E30: =+E10/E$22 -> 0.30497776 | F30: =+F10/F$22 -> 0.27056444 | G30: =+G10/G$22 -> 0.25509248 | H30: =+H10/H$22 -> 0.25497187 | Q30: =+Q10/Q$22 -> 0.31139517 | R30: =+R10/R$22 -> 0.30658754 | S30: =+S10/S$22 -> 0.29984033 | T30: =+T10/T$22 -> 0.30250591 | U30: =+U10/U$22 -> 0.27759064 | V30: =+V10/V$22 -> 0.2683948 | W30: =+W10/W$22 -> 0.26101138 | X30: =+X10/X$22 -> 0.27549578 | ... AF30: =+AF10/AF$22 -> 0.25271311
B31: =+B11 -> Indonesia | C31: =+C11/C$22 -> 0.30623927 | D31: =+D11/D$22 -> 0.29867352 | E31: =+E11/E$22 -> 0.26903366 | F31: =+F11/F$22 -> 0.29537794 | G31: =+G11/G$22 -> 0.30947156 | H31: =+H11/H$22 -> 0.29901391 | I31: =+I11/I$22 -> 0.38786562 | J31: =+J11/J$22 -> 0.39702988 | ... O31: =+O11/O$22 -> 0.43401971 | Q31: =+Q11/Q$22 -> 0.27308942 | R31: =+R11/R$22 -> 0.26495718 | S31: =+S11/S$22 -> 0.26804956 | T31: =+T11/T$22 -> 0.27007266 | U31: =+U11/U$22 -> 0.28897659 | V31: =+V11/V$22 -> 0.2902938 | W31: =+W11/W$22 -> 0.30372443 | X31: =+X11/X$22 -> 0.29817216 | ... AR31: =+AR11/AR$22 -> 0.43487087 | AV31: =+AV11/AV$22 -> 0.38210617
B32: =+B12 -> Bangladesh | C32: =+C12/C$22 -> 0.12906758 | D32: =+D12/D$22 -> 0.14919159 | E32: =+E12/E$22 -> 0.13700615 | F32: =+F12/F$22 -> 0.14858559 | G32: =+G12/G$22 -> 0.15336433 | H32: =+H12/H$22 -> 0.14895558 | I32: =+I12/I$22 -> 0.19295674 | J32: =+J12/J$22 -> 0.18264326 | ... O32: =+O12/O$22 -> 0.17316187 | Q32: =+Q12/Q$22 -> 0.13378178 | R32: =+R12/R$22 -> 0.13246265 | S32: =+S12/S$22 -> 0.14189406 | T32: =+T12/T$22 -> 0.13953482 | U32: =+U12/U$22 -> 0.15000478 | V32: =+V12/V$22 -> 0.14858911 | W32: =+W12/W$22 -> 0.14906376 | X32: =+X12/X$22 -> 0.14676081 | ... AR32: =+AR12/AR$22 -> 0.15023834 | AV32: =+AV12/AV$22 -> 0.1910301
B33: =+B13 -> Sri Lanka | C33: =+C13/C$22 -> 0.11201549 | D33: =+D13/D$22 -> 0.1082684 | E33: =+E13/E$22 -> 0.11304006 | F33: =+F13/F$22 -> 0.10888138 | G33: =+G13/G$22 -> 0.11154514 | H33: =+H13/H$22 -> 0.11286229 | I33: =+I13/I$22 -> 0.14621002 | J33: =+J13/J$22 -> 0.11541465 | ... O33: =+O13/O$22 -> 0.11884296 | Q33: =+Q13/Q$22 -> 0.11346273 | R33: =+R13/R$22 -> 0.11336026 | S33: =+S13/S$22 -> 0.11755614 | T33: =+T13/T$22 -> 0.10802641 | U33: =+U13/U$22 -> 0.1109389 | V33: =+V13/V$22 -> 0.1114064 | W33: =+W13/W$22 -> 0.10696022 | X33: =+X13/X$22 -> 0.10635348 | ... AR33: =+AR13/AR$22 -> 0.12336655 | AV33: =+AV13/AV$22 -> 0.16348171
B34: =+B14 -> Nepal | C34: =+C14/C$22 -> 0.074797435 | D34: =+D14/D$22 -> 0.096392441 | E34: =+E14/E$22 -> 0.087836316 | F34: =+F14/F$22 -> 0.080317697 | G34: =+G14/G$22 -> 0.061005436 | H34: =+H14/H$22 -> 0.055510514 | I34: =+I14/I$22 -> 0.0719095 | J34: =+J14/J$22 -> 0.063870935 | ... O34: =+O14/O$22 -> 0 | Q34: =+Q14/Q$22 -> 0.094116313 | R34: =+R14/R$22 -> 0.093652107 | S34: =+S14/S$22 -> 0.082658502 | T34: =+T14/T$22 -> 0.081591576 | U34: =+U14/U$22 -> 0.083637326 | V34: =+V14/V$22 -> 0.084556977 | W34: =+W14/W$22 -> 0.078629008 | X34: =+X14/X$22 -> 0.074677912 | ... AR34: =+AR14/AR$22 -> 0 | AV34: =+AV14/AV$22 -> 0.13505974
B35: =+B15 -> Cambodia | C35: =+C15/C$22 -> 0.050005954 | D35: =+D15/D$22 -> 0.048105184 | E35: =+E15/E$22 -> 0.048036235 | F35: =+F15/F$22 -> 0.0521673 | G35: =+G15/G$22 -> 0.056267007 | H35: =+H15/H$22 -> 0.054833118 | I35: =+I15/I$22 -> 0.071036504 | J35: =+J15/J$22 -> 0.07413977 | ... O35: =+O15/O$22 -> 0.082535196 | Q35: =+Q15/Q$22 -> 0.043704613 | R35: =+R15/R$22 -> 0.047955664 | S35: =+S15/S$22 -> 0.049328955 | T35: =+T15/T$22 -> 0.050846379 | U35: =+U15/U$22 -> 0.050783293 | V35: =+V15/V$22 -> 0.051739514 | W35: =+W15/W$22 -> 0.052989947 | X35: =+X15/X$22 -> 0.053085628 | ... AR35: =+AR15/AR$22 -> 0.081542443 | AV35: =+AV15/AV$22 -> 0.06915893
B36: =+B16 -> Fixed BB | C36: =+C16/C$22 -> 0 | D36: =+D16/D$22 -> 0 | E36: =+E16/E$22 -> 0
B37: =+B17 -> Indonesia | C37: =+C17/C$22 -> 0 | D37: =+D17/D$22 -> 0 | E37: =+E17/E$22 -> 0 | J37: =+J17/J$22 -> 0.030805356 | K37: =+K17/K$22 -> 0.033429552 | L37: =+L17/L$22 -> 0.053268006 | M37: =+M17/M$22 -> 0.052513661 | N37: =+N17/N$22 -> 0.042030316 | O37: =+O17/O$22 -> 0.042030316 | AI37: =+AI17/AI$22 -> 0.059789453 | AJ37: =+AJ17/AJ$22 -> 0.077908679 | AK37: =+AK17/AK$22 -> 0.052346694 | AL37: =+AL17/AL$22 -> 0.050000284 | AM37: =+AM17/AM$22 -> 0.051838741 | AN37: =+AN17/AN$22 -> 0.059892233 | AO37: =+AO17/AO$22 -> 0.048082296 | AP37: =+AP17/AP$22 -> 0.046080384 | ... AR37: =+AR17/AR$22 -> 0.024907763 | AV37: =+AV17/AV$22 -> 0
B38: =+B18 -> Infrastructure
B39: =+B19 -> Malaysia | C39: =+C19/C$22 -> 0.010734421 | D39: =+D19/D$22 -> 0.017585278 | E39: =+E19/E$22 -> 0.024132893 | F39: =+F19/F$22 -> 0.026971834 | G39: =+G19/G$22 -> 0.031449887 | H39: =+H19/H$22 -> 0.030631496 | I39: =+I19/I$22 -> 0.069595498 | J39: =+J19/J$22 -> 0.084849926 | ... O39: =+O19/O$22 -> 0.099751386 | Q39: =+Q19/Q$22 -> 0.016729094 | R39: =+R19/R$22 -> 0.027647043 | S39: =+S19/S$22 -> 0.025110303 | T39: =+T19/T$22 -> 0.026697644 | U39: =+U19/U$22 -> 0.026283327 | V39: =+V19/V$22 -> 0.024756509 | W39: =+W19/W$22 -> 0.027891665 | X39: =+X19/X$22 -> 0.02888875 | ... AR39: =+AR19/AR$22 -> 0.1367364 | AV39: =+AV19/AV$22 -> 0.039870993
B40: =+B20 -> Others | C40: =+C20/C$22 -> 0.012176778 | D40: =+D20/D$22 -> 0.013402698 | E40: =+E20/E$22 -> 0.015936929 | F40: =+F20/F$22 -> 0.017133818 | G40: =+G20/G$22 -> 0.021804168 | H40: =+H20/H$22 -> 0.043221214 | I40: =+I20/I$22 -> 0.060426116 | J40: =+J20/J$22 -> 0.051246229 | ... O40: =+O20/O$22 -> 0.049658564 | Q40: =+Q20/Q$22 -> 0.013720874 | R40: =+R20/R$22 -> 0.013377558 | S40: =+S20/S$22 -> 0.015562161 | T40: =+T20/T$22 -> 0.020724606 | U40: =+U20/U$22 -> 0.011785149 | V40: =+V20/V$22 -> 0.020262889 | W40: =+W20/W$22 -> 0.019729597 | X40: =+X20/X$22 -> 0.016565483 | ... AR40: =+AR20/AR$22 -> 0.048337633 | AV40: =+AV20/AV$22 -> 0.019292352
B41: =+B21 -> Eliminations | C41: =+C21/C$22 -> 0 | D41: =+D21/D$22 -> 0 | E41: =+E21/E$22 -> 0 | F41: =+F21/F$22 -> 0 | G41: =+G21/G$22 -> 0 | H41: =+H21/H$22 -> 0 | I41: =+I21/I$22 -> 0 | J41: =+J21/J$22 -> 0 | ... O41: =+O21/O$22 -> 0 | Q41: =+Q21/Q$22 -> 0 | R41: =+R21/R$22 -> 0 | S41: =+S21/S$22 -> 0 | T41: =+T21/T$22 -> 0 | U41: =+U21/U$22 -> 0 | V41: =+V21/V$22 -> 0 | W41: =+W21/W$22 -> 0 | X41: =+X21/X$22 -> 0 | ... AR41: =+AR21/AR$22 -> 0 | AV41: =+AV21/AV$22 -> 0
B42: Total | C42: =+SUM(C30:C41) -> 1 | D42: =+SUM(D30:D41) -> 1 | E42: =+SUM(E30:E41) -> 1 | F42: =+SUM(F30:F41) -> 1 | G42: =+SUM(G30:G41) -> 1 | H42: =+SUM(H30:H41) -> 1 | I42: =+SUM(I30:I41) -> 1 | J42: =+SUM(J30:J41) -> 1 | ... O42: =+SUM(O30:O41) -> 1 | Q42: =+SUM(Q30:Q41) -> 1 | R42: =+SUM(R30:R41) -> 1 | S42: =+SUM(S30:S41) -> 1 | T42: =+SUM(T30:T41) -> 1 | U42: =+SUM(U30:U41) -> 1 | V42: =+SUM(V30:V41) -> 1 | W42: =+SUM(W30:W41) -> 1 | X42: =+SUM(X30:X41) -> 1 | ... AR42: =+SUM(AR30:AR41) -> 1 | AV42: =+SUM(AV30:AV41) -> 1
B44: % yoy/qoq growth in revenue
B45: =+B9 -> Mobile
B46: =+B10 -> Malaysia | D46: =+D10/C10-1 -> -0.004182982 | E46: =+E10/D10-1 -> 0.11230394 | F46: =+F10/E10-1 -> -0.086931227 | G46: =+G10/F10-1 -> -0.07176311 | H46: =+H10/G10-1 -> 0.069629046 | U46: =+U10/T10-1 -> -0.12886096 | V46: =+V10/U10-1 -> 5.4495649e-05 | W46: =+W10/V10-1 -> -0.018084304 | X46: =+X10/W10-1 -> 0.064624814 | Y46: =+Y10/X10-1 -> -0.10915858 | Z46: =+Z10/Y10-1 -> -0.065876151 | AA46: =+AA10/Z10-1 -> 0.093924744 | AB46: =+AB10/AA10-1 -> 0.035534316 | ... AG46: =+AG10/AF10-1 -> -1
B47: =+B11 -> Indonesia | D47: =+D11/C11-1 -> 0.10359833 | E47: =+E11/D11-1 -> -0.11830824 | F47: =+F11/E11-1 -> 0.12998424 | G47: =+G11/F11-1 -> 0.031512657 | H47: =+H11/G11-1 -> 0.03397309 | J47: =+J11/H11-1 -> 0.11376978 | K47: =+K11/I11-1 -> 0.1122661 | L47: =+L11/K11-1 -> 0.11004565 | M47: =+M11/K11-1 -> 0.11004565 | N47: =+N11/M11-1 -> 0.012393741 | O47: =+O11/N11-1 -> 0 | U47: =+U11/T11-1 -> 0.015777433 | V47: =+V11/U11-1 -> 0.039033345 | W47: =+W11/V11-1 -> 0.05640589 | X47: =+X11/W11-1 -> -0.0097874165 | Y47: =+Y11/X11-1 -> 0.0052171437 | Z47: =+Z11/Y11-1 -> 0.0040050128 | AA47: =+AA11/Z11-1 -> 0.014409421 | AB47: =+AB11/AA11-1 -> -0.052433388 | ... AR47: =+AR11/AQ11-1 -> 0.063209034 | AV47: =+AV11/AU11-1 -> #DIV/0!
B48: =+B12 -> Bangladesh | D48: =+D12/C12-1 -> 0.30798382 | E48: =+E12/D12-1 -> -0.10111813 | F48: =+F12/E12-1 -> 0.11618858 | G48: =+G12/F12-1 -> 0.016200777 | H48: =+H12/G12-1 -> 0.039371988 | J48: =+J12/H12-1 -> 0.028514679 | K48: =+K12/I12-1 -> 0.028515975 | L48: =+L12/K12-1 -> 0.036514028 | M48: =+M12/K12-1 -> 0.036514028 | N48: =+N12/M12-1 -> -0.059677302 | O48: =+O12/N12-1 -> 0 | U48: =+U12/T12-1 -> 0.020561167 | V48: =+V12/U12-1 -> 0.024557283 | W48: =+W12/V12-1 -> 0.012917232 | X48: =+X12/W12-1 -> -0.0069317653 | Y48: =+Y12/X12-1 -> 0.03568792 | Z48: =+Z12/Y12-1 -> -0.059641498 | AA48: =+AA12/Z12-1 -> 0.057369033 | AB48: =+AB12/AA12-1 -> -0.032451003 | ... AR48: =+AR12/AQ12-1 -> -0.073499345 | AV48: =+AV12/AU12-1 -> #DIV/0!
B49: =+B13 -> Sri Lanka | D49: =+D13/C13-1 -> 0.093701592 | E49: =+E13/D13-1 -> 0.02196851 | F49: =+F13/E13-1 -> -0.0086609507 | G49: =+G13/F13-1 -> 0.008623044 | H49: =+H13/G13-1 -> 0.08277149 | J49: =+J13/H13-1 -> -0.14222046 | K49: =+K13/I13-1 -> -0.1421452 | L49: =+L13/K13-1 -> 0.045861108 | M49: =+M13/K13-1 -> 0.045861108 | N49: =+N13/M13-1 -> 0.011997278 | O49: =+O13/N13-1 -> 0 | U49: =+U13/T13-1 -> -0.025076772 | V49: =+V13/U13-1 -> 0.038677381 | W49: =+W13/V13-1 -> -0.030604535 | X49: =+X13/W13-1 -> 0.0029297095 | Y49: =+Y13/X13-1 -> -0.022835092 | Z49: =+Z13/Y13-1 -> 0.0081022819 | AA49: =+AA13/Z13-1 -> 0.049158131 | AB49: =+AB13/AA13-1 -> 0.020571938 | ... AR49: =+AR13/AQ13-1 -> -0.0026139352 | AV49: =+AV13/AU13-1 -> #DIV/0!
B50: =+B14 -> Nepal | D50: =+D14/C14-1 -> 0.4582483 | E50: =+E14/D14-1 -> -0.10805512 | F50: =+F14/E14-1 -> -0.058894997 | G50: =+G14/F14-1 -> -0.25219362 | H50: =+H14/G14-1 -> -0.026254889 | J50: =+J14/H14-1 -> -0.034857024 | U50: =+U14/T14-1 -> -0.026868935 | V50: =+V14/U14-1 -> 0.045691777 | W50: =+W14/V14-1 -> -0.061093804 | X50: =+X14/W14-1 -> -0.042033234 | Y50: =+Y14/X14-1 -> -0.053856032 | Z50: =+Z14/Y14-1 -> -0.2876342 | AA50: =+AA14/Z14-1 -> 0.1054759 | AB50: =+AB14/AA14-1 -> 0.059849502 | ... AL50: =+AL14/AK14-1 -> 0.060956168
B51: =+B15 -> Cambodia | D51: =+D15/C15-1 -> 0.088542449 | E51: =+E15/D15-1 -> -0.022573819 | F51: =+F15/E15-1 -> 0.11771309 | G51: =+G15/F15-1 -> 0.061909088 | H51: =+H15/G15-1 -> 0.042864066 | J51: =+J15/H15-1 -> 0.13415373 | K51: =+K15/I15-1 -> 0.13406251 | L51: =+L15/K15-1 -> 0.04751596 | M51: =+M15/K15-1 -> 0.04751596 | N51: =+N15/M15-1 -> 0.092523525 | O51: =+O15/N15-1 -> 0 | U51: =+U15/T15-1 -> -0.051849341 | V51: =+V15/U15-1 -> 0.053794368 | W51: =+W15/V15-1 -> 0.034093943 | X51: =+X15/W15-1 -> 0.010472604 | Y51: =+Y15/X15-1 -> -0.045883831 | Z51: =+Z15/Y15-1 -> -0.022525148 | AA51: =+AA15/Z15-1 -> 0.04945 | AB51: =+AB15/AA15-1 -> 0.25463122 | ... AR51: =+AR15/AQ15-1 -> 0.024310077 | AV51: =+AV15/AU15-1 -> #DIV/0!
B52: =+B16 -> Fixed BB
B53: =+B17 -> Indonesia | L53: =+L17/K17-1 -> 0.75118973 | M53: =+M17/K17-1 -> 0.75118973 | N53: =+N17/M17-1 -> -0.1990466 | O53: =+O17/N17-1 -> 0
B54: =+B18 -> Infrastructure
B55: =+B19 -> Malaysia | D55: =+D19/C19-1 -> 0.85372713 | E55: =+E19/D19-1 -> 0.34328153 | F55: =+F19/E19-1 -> 0.15027592 | G55: =+G19/F19-1 -> 0.14799633 | H55: =+H19/G19-1 -> 0.0422879 | J55: =+J19/H19-1 -> 1.3235225 | K55: =+K19/I19-1 -> 0.10484449 | L55: =+L19/K19-1 -> 0.21324551 | M55: =+M19/K19-1 -> 0.41882294 | N55: =+N19/M19-1 -> 0.021360978 | O55: =+O19/N19-1 -> 0 | U55: =+U19/T19-1 -> -0.065403971 | V55: =+V19/U19-1 -> -0.025765647 | W55: =+W19/V19-1 -> 0.13755891 | X55: =+X19/W19-1 -> 0.044709114 | Y55: =+Y19/X19-1 -> -0.0030599958 | Z55: =+Z19/Y19-1 -> 0.010936773 | AA55: =+AA19/Z19-1 -> 0.0098374492 | AB55: =+AB19/AA19-1 -> 0.1612224 | ... AR55: =+AR19/AQ19-1 -> 0.7068212 | AV55: =+AV19/AU19-1 -> #DIV/0!
B56: =+B20 -> Others | D56: =+D20/C20-1 -> 0.24547501 | E56: =+E20/D20-1 -> 0.16390977 | F56: =+F20/E20-1 -> 0.10649756 | G56: =+G20/F20-1 -> 0.25290238 | H56: =+H20/G20-1 -> 1.1212703 | J56: =+J20/H20-1 -> -0.0054454924 | K56: =+K20/I20-1 -> -0.088552884 | L56: =+L20/K20-1 -> -0.12193219 | M56: =+M20/K20-1 -> -0.12193219 | N56: =+N20/M20-1 -> 0.14704584 | O56: =+O20/N20-1 -> 0 | U56: =+U20/T20-1 -> -0.46015968 | V56: =+V20/U20-1 -> 0.77836412 | W56: =+W20/V20-1 -> -0.016881867 | X56: =+X20/W20-1 -> -0.15311009 | Y56: =+Y20/X20-1 -> -0.27246282 | Z56: =+Z20/Y20-1 -> 0.44625976 | AA56: =+AA20/Z20-1 -> 0.21099271 | AB56: =+AB20/AA20-1 -> 0.59263403 | ... AR56: =+AR20/AQ20-1 -> -0.028017869 | AV56: =+AV20/AU20-1 -> #DIV/0!
B57: =+B21 -> Eliminations
B58: Total | D58: =+D22/C22-1 -> 0.13155379 | E58: =+E22/D22-1 -> -0.021170868 | F58: =+F22/E22-1 -> 0.029202771 | G58: =+G22/F22-1 -> -0.015463376 | H58: =+H22/G22-1 -> 0.070135025 | J58: =+J22/H22-1 -> -0.16118994 | K58: =+K22/I22-1 -> 0.0012959649 | L58: =+L22/K22-1 -> 0.098999065 | M58: =+M22/K22-1 -> 0.11478591 | N58: =+N22/M22-1 -> 0.00072993826 | O58: =+O22/N22-1 -> 0 | U58: =+U22/T22-1 -> -0.050671494 | V58: =+V22/U22-1 -> 0.034318709 | W58: =+W22/V22-1 -> 0.0096918656 | X58: =+X22/W22-1 -> 0.0086513444 | Y58: =+Y22/X22-1 -> -0.036767631 | Z58: =+Z22/Y22-1 -> -0.040448373 | AA58: =+AA22/Z22-1 -> 0.055113982 | AB58: =+AB22/AA22-1 -> 0.024683813 | ... AR58: =+AR22/AQ22-1 -> 0.051390342 | AV58: =+AV22/AU22-1 -> #DIV/0!
B60: EBITDA by segment
B61: Mobile
B62: Malaysia | C62: 2304.248 | D62: 2317.905 | E62: 1906.001 | F62: 2618.458 | G62: 2589.948 | H62: 2825.957 | Q62: 456.629 | R62: =951.574-Q62 -> 494.945 | S62: =1439.753-R62-Q62 -> 488.179 | T62: =+E62-Q62-R62-S62 -> 466.248 | U62: 570.377 | V62: =1280.477-U62 -> 710.1 | W62: =1920.977-V62-U62 -> 640.5 | X62: =+F62-U62-V62-W62 -> 697.481 | Y62: 514.033 | Z62: =1085.357-Y62 -> 571.324 | AA62: =1795.099-Z62-Y62 -> 709.742 | AB62: =+G62-Y62-Z62-AA62 -> 794.849 | AC62: 645.879 | AD62: =1323.618-AC62 -> 677.739 | AE62: =2025.347-AD62-AC62 -> 701.729 | AF62: =+H62-AC62-AD62-AE62 -> 800.61
B63: Indonesia | C63: 2612.231 | D63: 2761.979 | E63: 2527.143 | F63: 3721.054 | G63: 3776.653 | H63: 3889.711 | I63: 3889.711 | J63: 4219.018 | K63: 4219.018 | L63: 4776.579 | M63: 4776.579 | N63: 5205.194 | O63: 5205.194 | Q63: 603.034 | R63: =1214.147-Q63 -> 611.113 | S63: =1844.17-R63-Q63 -> 630.023 | T63: =+E63-Q63-R63-S63 -> 682.973 | U63: 829.586 | V63: =1771.033-U63 -> 941.447 | W63: =2738.37-V63-U63 -> 967.337 | X63: =+F63-U63-V63-W63 -> 982.684 | Y63: 932.458 | Z63: =1900.18-Y63 -> 967.722 | AA63: =2877.807-Z63-Y63 -> 977.627 | AB63: =+G63-Y63-Z63-AA63 -> 898.846 | AC63: 900.994 | AD63: =1873.133-AC63 -> 972.139 | AE63: =2885.777-AD63-AC63 -> 1012.644 | AF63: =+H63-AC63-AD63-AE63 -> 1003.934 | AG63: 933.466 | AH63: =1992.907-AG63 -> 1059.441 | AI63: =3087.236-AH63-AG63 -> 1094.329 | AJ63: =K63-AG63-AH63-AI63 -> 1131.782 | AK63: 1038.517 | AL63: =2275.258-AK63 -> 1236.741 | AM63: =3528.819-AL63-AK63 -> 1253.561 | AN63: =L63-AK63-AL63-AM63 -> 1247.76 | AO63: 1355.821 | AP63: =2680.119-AO63 -> 1324.298 | AQ63: =3909.734-AP63-AO63 -> 1229.615 | AR63: =N63-AO63-AP63-AQ63 -> 1295.46 | AV63: =R63-AS63-AT63-AU63 -> 611.113
B64: Bangladesh | C64: 758.352 | D64: 693.173 | E64: 794.746 | F64: 1404.249 | G64: 1580.705 | H64: 1592.997 | I64: 1592.997 | J64: 1804.99 | K64: 1804.99 | L64: 1922.829 | M64: 1922.829 | N64: 1979.456 | O64: 1979.456 | Q64: 182.503 | R64: =329.989-Q64 -> 147.486 | S64: =547.611-R64-Q64 -> 217.622 | T64: =+E64-Q64-R64-S64 -> 247.135 | U64: 348.608 | V64: =763.433-U64 -> 414.825 | W64: =1111.057-V64-U64 -> 347.624 | X64: =+F64-U64-V64-W64 -> 293.192 | Y64: 383.314 | Z64: =826.741-Y64 -> 443.427 | AA64: =1212.671-Z64-Y64 -> 385.93 | AB64: =+G64-Y64-Z64-AA64 -> 368.034 | AC64: 384.965 | AD64: =795.964-AC64 -> 410.999 | AE64: =1216.548-AD64-AC64 -> 420.584 | AF64: =+H64-AC64-AD64-AE64 -> 376.449 | AG64: 407.708 | AH64: =880.453-AG64 -> 472.745 | AI64: =1331.813-AH64-AG64 -> 451.36 | AJ64: =K64-AG64-AH64-AI64 -> 473.177 | AK64: 432.963 | AL64: =880.814-AK64 -> 447.851 | AM64: =1379.76-AL64-AK64 -> 498.946 | AN64: =L64-AK64-AL64-AM64 -> 543.069 | AO64: 518.955 | AP64: =1020.862-AO64 -> 501.907 | AQ64: =1509.436-AP64-AO64 -> 488.574 | AR64: =N64-AO64-AP64-AQ64 -> 470.02 | AV64: =R64-AS64-AT64-AU64 -> 147.486
B65: Sri Lanka | C65: 828.42 | D65: 954.966 | E65: 1081.774 | F65: 1082.8 | G65: 1153.679 | H65: 1223.195 | I65: 1223.195 | J65: 727.754 | K65: 729.856 | L65: 859.292 | M65: 859.292 | N65: 1033.535 | O65: 1033.535 | Q65: 252.537 | R65: =525.02-Q65 -> 272.483 | S65: =808.339-R65-Q65 -> 283.319 | T65: =+E65-Q65-R65-S65 -> 273.435 | U65: 274.6 | V65: =536.211-U65 -> 261.611 | W65: =814.639-V65-U65 -> 278.428 | X65: =+F65-U65-V65-W65 -> 268.161 | Y65: 278.201 | Z65: =523.491-Y65 -> 245.29 | AA65: =832.958-Z65-Y65 -> 309.467 | AB65: =+G65-Y65-Z65-AA65 -> 320.721 | AC65: 284.81 | AD65: =580.289-AC65 -> 295.479 | AE65: =907.288-AD65-AC65 -> 326.999 | AF65: =+H65-AC65-AD65-AE65 -> 315.907 | AG65: 283.206 | AH65: =434.883-AG65 -> 151.677 | AI65: =608.925-AH65-AG65 -> 174.042 | AJ65: =K65-AG65-AH65-AI65 -> 120.931 | AK65: 162.057 | AL65: =367.367-AK65 -> 205.31 | AM65: =615.797-AL65-AK65 -> 248.43 | AN65: =L65-AK65-AL65-AM65 -> 243.495 | AO65: 204.894 | AP65: =417.497-AO65 -> 212.603 | AQ65: =707.562-AP65-AO65 -> 290.065 | AR65: =N65-AO65-AP65-AQ65 -> 325.973 | AV65: =R65-AS65-AT65-AU65 -> 272.483
B66: Nepal | C66: 1021.197 | D66: 1560.896 | E66: 1301.146 | F66: 1193.287 | G66: 850.21 | H66: 841.529 | I66: 841.529 | J66: 736.737 | Q66: 342.609 | R66: =691.843-Q66 -> 349.234 | S66: =1015.917-R66-Q66 -> 324.074 | T66: =+E66-Q66-R66-S66 -> 285.229 | U66: 315.196 | V66: =609.81-U66 -> 294.614 | W66: =908.381-V66-U66 -> 298.571 | X66: =+F66-U66-V66-W66 -> 284.906 | Y66: 261.036 | Z66: =414.858-Y66 -> 153.822 | AA66: =632.423-Z66-Y66 -> 217.565 | AB66: =+G66-Y66-Z66-AA66 -> 217.787 | AC66: 224.133 | AD66: =427.919-AC66 -> 203.786 | AE66: =635.612-AD66-AC66 -> 207.693 | AF66: =+H66-AC66-AD66-AE66 -> 205.917 | AG66: 196.939 | AH66: =384.995-AG66 -> 188.056 | AJ66: =K66-AG66-AH66-AI66 -> -384.995 | AK66: 172.318 | AL66: =329.844-AK66 -> 157.526 | AN66: =L66-AK66-AL66-AM66 -> -329.844 | AR66: =N66-AO66-AP66-AQ66 -> 0 | AV66: =R66-AS66-AT66-AU66 -> 349.234
B67: Cambodia | C67: 538.012 | D67: 589.433 | E67: 543.772 | F67: 695.179 | G67: 751.947 | H67: 774.663 | I67: 774.663 | J67: 827.859 | K67: 827.859 | L67: 918.619 | M67: 918.619 | N67: 1082.718 | O67: 1082.718 | Q67: 118.45 | R67: =246.87-Q67 -> 128.42 | S67: =390.125-R67-Q67 -> 143.255 | T67: =+E67-Q67-R67-S67 -> 153.647 | U67: 159.387 | V67: =330.32-U67 -> 170.933 | W67: =515.105-V67-U67 -> 184.785 | X67: =+F67-U67-V67-W67 -> 180.074 | Y67: 182.536 | Z67: =367.094-Y67 -> 184.558 | AA67: =559.688-Z67-Y67 -> 192.594 | AB67: =+G67-Y67-Z67-AA67 -> 192.259 | AC67: 181.281 | AD67: =370.823-AC67 -> 189.542 | AE67: =575.344-AD67-AC67 -> 204.521 | AF67: =+H67-AC67-AD67-AE67 -> 199.319 | AG67: 196.432 | AH67: =406.876-AG67 -> 210.444 | AI67: =593.727-AH67-AG67 -> 186.851 | AJ67: =K67-AG67-AH67-AI67 -> 234.132 | AK67: 225.925 | AL67: =430.697-AK67 -> 204.772 | AM67: =671.92-AL67-AK67 -> 241.223 | AN67: =L67-AK67-AL67-AM67 -> 246.699 | AO67: 254.391 | AP67: =572.626-AO67 -> 318.235 | AQ67: =828.284-AP67-AO67 -> 255.658 | AR67: =N67-AO67-AP67-AQ67 -> 254.434 | AV67: =R67-AS67-AT67-AU67 -> 128.42
B68: Fixed BB | AR68: =N68-AO68-AP68-AQ68 -> 0 | AV68: =R68-AS68-AT68-AU68 -> 0
B69: Indonesia | J69: 307.572 | K69: 309.074 | L69: 488.638 | M69: 488.638 | N69: 392.88 | O69: 392.88 | AI69: =173.921-AH69-AG69 -> 173.921 | AJ69: =K69-AG69-AH69-AI69 -> 135.153 | AK69: 122 | AL69: =268.621-AK69 -> 146.621 | AM69: =388.473-SUM(AK69:AL69) -> 119.852 | AN69: =L69-AK69-AL69-AM69 -> 100.165 | AO69: 135.579 | AP69: =261.238-AO69 -> 125.659 | AQ69: =364.782-SUM(AO69:AP69) -> 103.544 | AR69: =N69-AO69-AP69-AQ69 -> 28.098 | AV69: =R69-AS69-AT69-AU69 -> 0
B70: Infrastructure | AR70: =N70-AO70-AP70-AQ70 -> 0 | AV70: =R70-AS70-AT70-AU70 -> 0
B71: Malaysia | C71: 254.782 | D71: 626.319 | E71: 684.228 | F71: 1112.584 | G71: 1087.192 | H71: 1238.069 | I71: 1238.069 | J71: 1647.214 | K71: 1395.009 | L71: 1595.573 | M71: 1876.044 | N71: 2065.523 | O71: 2065.523 | Q71: 156.842 | R71: =320.368-Q71 -> 163.526 | S71: =515.453-R71-Q71 -> 195.085 | T71: =+E71-Q71-R71-S71 -> 168.775 | U71: 228.826 | V71: =476.104-U71 -> 247.278 | W71: =836.033-V71-U71 -> 359.929 | X71: =+F71-U71-V71-W71 -> 276.551 | Y71: 274.61 | Z71: =577.223-Y71 -> 302.613 | AA71: =860.935-Z71-Y71 -> 283.712 | AB71: =+G71-Y71-Z71-AA71 -> 226.257 | AC71: 303.182 | AD71: =619.233-AC71 -> 316.051 | AE71: =892.957-AD71-AC71 -> 273.724 | AF71: =+H71-AC71-AD71-AE71 -> 345.112 | AG71: 392.558 | AH71: =820.791-AG71 -> 428.233 | AI71: =1264.816-AH71-AG71 -> 444.025 | AJ71: =K71-AG71-AH71-AI71 -> 130.193 | AK71: 447.815 | AL71: =927.511-AK71 -> 479.696 | AM71: =1371.863-AL71-AK71 -> 444.352 | AN71: =L71-AK71-AL71-AM71 -> 223.71 | AO71: 438.675 | AP71: =935.859-AO71 -> 497.184 | AQ71: =1358.132-AP71-AO71 -> 422.273 | AR71: =N71-AO71-AP71-AQ71 -> 707.391 | AV71: =R71-AS71-AT71-AU71 -> 163.526
B72: Others | C72: -286.423 | D72: -802.615 | E72: -5169.732 | F72: -2074.985 | G72: -553.282 | H72: -407.517 | I72: -407.517 | J72: -347.052 | K72: =118.175-132.343-263.809 -> -277.977 | L72: =16.55-129.194-441.454 -> -554.098 | M72: =16.55-129.194-441.453 -> -554.097 | N72: =66.931-110.139-274.829 -> -318.037 | O72: =66.931-110.139-274.829 -> -318.037 | Q72: -131.502 | R72: =-266.374-Q72 -> -134.872 | S72: =-385.509-R72-Q72 -> -119.135 | T72: =+E72-Q72-R72-S72 -> -4784.223 | U72: -148.262 | V72: =-331.518-U72 -> -183.256 | W72: =-548.777-V72-U72 -> -217.259 | X72: =+F72-U72-V72-W72 -> -1526.208 | Y72: -93.644 | Z72: =-179.836-Y72 -> -86.192 | AA72: =-452.876-Z72-Y72 -> -273.04 | AB72: =+G72-Y72-Z72-AA72 -> -100.406 | AC72: -86.429 | AD72: =-199.975-AC72 -> -113.546 | AE72: =-312.987-AD72-AC72 -> -113.012 | AF72: =+H72-AC72-AD72-AE72 -> -94.53 | AG72: =18.026-41.588-63.729 -> -87.291 | AH72: =-202.49-AG72 -> -115.199 | AI72: =73.428-136.636-253.847-AH72-AG72 -> -114.565 | AJ72: =K72-AG72-AH72-AI72 -> 39.078 | AK72: =4.024-41.548-54.82 -> -92.344 | AL72: =-0.371-88.076-70.361-AK72 -> -66.464 | AM72: =-9.263-129.629-200.644-AL72-AK72 -> -180.728 | AN72: =L72-AK72-AL72-AM72 -> -214.562 | AO72: =12.812-31.617-46.038 -> -64.843 | AP72: =31.963-72.164-78.991-AO72 -> -54.349 | AQ72: =44.752-99.966-141.441-AP72-AO72 -> -77.463 | AR72: =N72-AO72-AP72-AQ72 -> -121.382 | AV72: =R72-AS72-AT72-AU72 -> -134.872
B73: Eliminations | C73: -18.171 | D73: 528.062 | E73: 4665.056 | F73: 866.524 | G73: -580.177 | H73: -574.587 | I73: -250.388 | J73: -327.447 | K73: -387.915 | L73: -378.56 | M73: -378.56 | N73: -312.025 | O73: -312.025 | Q73: 55.308 | R73: =66.141-Q73 -> 10.833 | S73: =74.736-R73-Q73 -> 8.595 | T73: =+E73-Q73-R73-S73 -> 4590.32 | U73: -156.55 | V73: =-343.575-U73 -> -187.025 | W73: =-401.813-V73-U73 -> -58.238 | X73: =+F73-U73-V73-W73 -> 1268.337 | Y73: -228.651 | Z73: =-427.465-Y73 -> -198.814 | AA73: =-391.424-Z73-Y73 -> 36.041 | AB73: =+G73-Y73-Z73-AA73 -> -188.753 | AC73: -146.96 | AD73: =-288.281-AC73 -> -141.321 | AE73: =-463.777-AD73-AC73 -> -175.496 | AF73: =+H73-AC73-AD73-AE73 -> -110.81 | AG73: -77.018 | AH73: =-142.462-AG73 -> -65.444 | AI73: =-244.545-AH73-AG73 -> -102.083 | AJ73: =K73-AG73-AH73-AI73 -> -143.37 | AK73: -92.52 | AL73: =-175.8-AK73 -> -83.28 | AM73: =-268.188-AL73-AK73 -> -92.388 | AN73: =L73-AK73-AL73-AM73 -> -110.372 | AO73: -106.603 | AP73: =-206.942-AO73 -> -100.339 | AQ73: =-284.42-AP73-AO73 -> -77.478 | AR73: =N73-AO73-AP73-AQ73 -> -27.605 | AV73: =R73-AS73-AT73-AU73 -> 10.833
B74: Total Continuing Operations | C74: =+SUM(C62:C73) -> 8012.648 | D74: =+SUM(D62:D73) -> 9230.118 | E74: =+SUM(E62:E73) -> 8334.134 | F74: =+SUM(F62:F73) -> 10619.15 | G74: =+SUM(G62:G73) -> 10656.875 | H74: =+SUM(H62:H73) -> 11404.017 | I74: =+SUM(I62:I73) -> 8902.259 | J74: =+SUM(J62:J73) -> 9596.645 | ... O74: =+SUM(O62:O73) -> 11129.244 | Q74: =+SUM(Q62:Q73) -> 2036.41 | R74: =+SUM(R62:R73) -> 2043.168 | S74: =+SUM(S62:S73) -> 2171.017 | T74: =+SUM(T62:T73) -> 2083.539 | U74: =+SUM(U62:U73) -> 2421.768 | V74: =+SUM(V62:V73) -> 2670.527 | W74: =+SUM(W62:W73) -> 2801.677 | X74: =+SUM(X62:X73) -> 2725.178 | ... AR74: =+SUM(AR62:AR73) -> 2932.389 | AV74: =+SUM(AV62:AV73) -> 1548.223
B75: Discontinued Operation | I75: 2501.758 | K75: 3814.34 | L75: 931.402 | AG75: 652.184 | AH75: =1333.148-AG75 -> 680.964 | AI75: =2064.298+549.569-AG75-AH75 -> 1280.719 | AJ75: =K75-AG75-AH75-AI75 -> 1200.473 | AM75: =510.295-AL75-AK75 -> 510.295 | AN75: =L75-AK75-AL75-AM75 -> 421.107 | AO75: 66.677 | AR75: =N75-AO75-AP75-AQ75 -> -66.677 | AV75: =R75-AS75-AT75-AU75 -> 0
B76: Total | G76: =G74+G75 -> 10656.875 | H76: =H74+H75 -> 11404.017 | I76: =I74+I75 -> 11404.017 | J76: =J74+J75 -> 9596.645 | K76: =K74+K75 -> 12434.254 | L76: =L74+L75 -> 10560.274 | M76: =M74+M75 -> 9909.344 | N76: =N74+N75 -> 11129.244 | O76: =O74+O75 -> 11129.244 | Q76: =Q74+Q75 -> 2036.41 | R76: =R74+R75 -> 2043.168 | S76: =S74+S75 -> 2171.017 | T76: =T74+T75 -> 2083.539 | U76: =U74+U75 -> 2421.768 | V76: =V74+V75 -> 2670.527 | W76: =W74+W75 -> 2801.677 | X76: =X74+X75 -> 2725.178 | ... AW76: =AW74+AW75 -> 0 | AY76: =AY74+AY75 -> 0 | BC76: =BC74+BC75 -> 0 | BD76: =BD74+BD75 -> 0 | BF76: =BF74+BF75 -> 0 | BG76: =BG74+BG75 -> 0
B78: Check | C78: =+C74-Model!C59 -> 0 | D78: =+D74-Model!D59 -> 0 | E78: =+E74-Model!E59 -> 0 | F78: =+F74-Model!F59 -> 0 | G78: =+G74-Model!G59 -> 0 | H78: =+H74-Model!H59 -> 0 | I78: =+I74-Model!J59 -> 0 | J78: =+J74-Model!K59 -> 0 | K78: =+K74-Model!L59 -> 0 | L78: =+L74-Model!M59 -> 0 | M78: =+M74-Model!N59 -> 0.044 | N78: =+N74-Model!O59 -> 0.044 | O78: =+O74-Model!P59 -> 5440.927 | Q78: =+Q74-Model!T59 -> 2036.41 | R78: =+R74-Model!U59 -> 2043.168 | S78: =+S74-Model!V59 -> 2171.017 | T78: =+T74-Model!W59 -> -6250.595 | U78: =+U74-Model!X59 -> 0 | V78: =+V74-Model!Y59 -> 0 | W78: =+W74-Model!Z59 -> 0 | X78: =+X74-Model!AA59 -> 0 | ... AF78: =+AF74-Model!AI59 -> 0 | AG78: =+AG74-Model!AR59 -> 0 | AH78: =+AH74-Model!AS59 -> 0.001 | AI78: =+AI74-Model!AV59 -> 0.08 | AJ78: =+AJ74-Model!AW59 -> -0.081 | AK78: =+AK74-Model!AX59 -> 0 | AL78: =+AL74-Model!AZ59 -> 0 | AM78: =+AM74-Model!BC59 -> -4.752 | AN78: =+AN74-Model!BD59 -> 4.752 | AO78: =+AO74-Model!BE59 -> 0 | AP78: =+AP74-Model!BF59 -> 0 | AQ78: =+AQ74-Model!BG59 -> -0.012 | AR78: =+AR74-Model!BH59 -> 0.056 | AV78: =+AV74-Model!BL59 -> 1344.396
B80: % of EBITDA by segment
B81: =+B61 -> Mobile
B82: =+B62 -> Malaysia | C82: =+C62/C$74 -> 0.28757634 | D82: =+D62/D$74 -> 0.25112409 | E82: =+E62/E$74 -> 0.22869815 | F82: =+F62/F$74 -> 0.24657887 | G82: =+G62/G$74 -> 0.24303072 | H82: =+H62/H$74 -> 0.24780365 | Q82: =+Q62/Q$74 -> 0.22423235 | R82: =+R62/R$74 -> 0.24224391 | S82: =+S62/S$74 -> 0.2248619 | T82: =+T62/T$74 -> 0.22377695 | U82: =+U62/U$74 -> 0.23552091 | V82: =+V62/V$74 -> 0.26590257 | W82: =+W62/W$74 -> 0.22861308 | X82: =+X62/X$74 -> 0.25593961 | ... AF82: =+AF62/AF$74 -> 0.26319336
B83: =+B63 -> Indonesia | C83: =+C63/C$74 -> 0.32601345 | D83: =+D63/D$74 -> 0.2992355 | E83: =+E63/E$74 -> 0.30322803 | F83: =+F63/F$74 -> 0.35040978 | G83: =+G63/G$74 -> 0.35438653 | H83: =+H63/H$74 -> 0.34108253 | I83: =+I63/I$74 -> 0.43693528 | J83: =+J63/J$74 -> 0.43963468 | ... O83: =+O63/O$74 -> 0.46770419 | Q83: =+Q63/Q$74 -> 0.29612603 | R83: =+R63/R$74 -> 0.29910071 | S83: =+S63/S$74 -> 0.29019717 | T83: =+T63/T$74 -> 0.32779468 | U83: =+U63/U$74 -> 0.34255387 | V83: =+V63/V$74 -> 0.35253229 | W83: =+W63/W$74 -> 0.34527071 | X83: =+X63/X$74 -> 0.36059443 | ... AR83: =+AR63/AR$74 -> 0.44177631 | AV83: =+AV63/AV$74 -> 0.39471898
B84: =+B64 -> Bangladesh | C84: =+C64/C$74 -> 0.094644367 | D84: =+D64/D$74 -> 0.07509904 | E84: =+E64/E$74 -> 0.095360358 | F84: =+F64/F$74 -> 0.13223742 | G84: =+G64/G$74 -> 0.14832725 | H84: =+H64/H$74 -> 0.13968736 | I84: =+I64/I$74 -> 0.17894301 | J84: =+J64/J$74 -> 0.18808552 | ... O84: =+O64/O$74 -> 0.17786078 | Q84: =+Q64/Q$74 -> 0.089619968 | R84: =+R64/R$74 -> 0.07218496 | S84: =+S64/S$74 -> 0.10023966 | T84: =+T64/T$74 -> 0.11861309 | U84: =+U64/U$74 -> 0.14394773 | V84: =+V64/V$74 -> 0.15533451 | W84: =+W64/W$74 -> 0.12407712 | X84: =+X64/X$74 -> 0.10758637 | ... AR84: =+AR64/AR$74 -> 0.16028569 | AV84: =+AV64/AV$74 -> 0.095261471
B85: =+B65 -> Sri Lanka | C85: =+C65/C$74 -> 0.10338904 | D85: =+D65/D$74 -> 0.10346195 | E85: =+E65/E$74 -> 0.12980041 | F85: =+F65/F$74 -> 0.10196673 | G85: =+G65/G$74 -> 0.10825678 | H85: =+H65/H$74 -> 0.10726001 | I85: =+I65/I$74 -> 0.13740276 | J85: =+J65/J$74 -> 0.075834211 | ... O85: =+O65/O$74 -> 0.092866595 | Q85: =+Q65/Q$74 -> 0.12401088 | R85: =+R65/R$74 -> 0.13336299 | S85: =+S65/S$74 -> 0.13050059 | T85: =+T65/T$74 -> 0.13123584 | U85: =+U65/U$74 -> 0.11338824 | V85: =+V65/V$74 -> 0.097962312 | W85: =+W65/W$74 -> 0.09937905 | X85: =+X65/X$74 -> 0.098401279 | ... AR85: =+AR65/AR$74 -> 0.11116295 | AV85: =+AV65/AV$74 -> 0.17599726
