Workbook
Name \A: #REF!
Name \B: #REF!
Name \C: #REF!
Name \L: #REF!
Name \M: #REF!
Name \P: #REF!
Name \Y: #REF!
Name _01_30_04: MonthlyOpStats
Name _01_30_04: MonthlyOpStats
Name _1_30_01: MonthlyOpStats
Name _1_30_01: MonthlyOpStats
Name _1_30_02: MonthlyOpStats
Name _1_30_02: MonthlyOpStats
Name _1_31_01: MonthlyOpStats
Name _1_31_01: MonthlyOpStats
Name _1_31_02: MonthlyOpStats
Name _1_31_02: MonthlyOpStats
Name _12_31_05: MonthlyOpStats
Name _12_31_05: MonthlyOpStats
Name _A: #REF!
Name _A___0: #REF!
Name _B: #REF!
Name _B___0: #REF!
Name _C: #REF!
Name _C___0: #REF!
Name _ent1: [1]Inputs!$J$17
Name _ent10: [1]Inputs!$J$476
Name _ent11: [1]Inputs!$J$527
Name _ent12: [1]Inputs!$J$578
Name _ent13: [1]Inputs!$J$629
Name _ent14: [1]Inputs!$J$680
Name _ent15: [1]Inputs!$J$731
Name _ent2: [1]Inputs!$J$68
Name _ent3: [1]Inputs!$J$119
Name _ent4: [1]Inputs!$J$170
Name _ent5: [1]Inputs!$J$221
Name _ent6: [1]Inputs!$J$272
Name _ent7: [1]Inputs!$J$323
Name _ent8: [1]Inputs!$J$374
Name _ent9: [1]Inputs!$J$425
Name _eps1: [1]Inputs!$P$42
Name _eps10: [1]Inputs!$P$501
Name _eps11: [1]Inputs!$P$552
Name _eps12: [1]Inputs!$P$603
Name _eps13: [1]Inputs!$P$654
Name _eps14: [1]Inputs!$P$705
Name _eps15: [1]Inputs!$P$756
Name _eps2: [1]Inputs!$P$93
Name _eps3: [1]Inputs!$P$144
Name _eps4: [1]Inputs!$P$195
Name _eps5: [1]Inputs!$P$246
Name _eps6: [1]Inputs!$P$297
Name _eps7: [1]Inputs!$P$348
Name _eps8: [1]Inputs!$P$399
Name _eps9: [1]Inputs!$P$450
Name _fye1: [1]Inputs!$E$12
Name _fye10: [1]Inputs!$E$471
Name _fye11: [1]Inputs!$E$522
Name _fye12: [1]Inputs!$E$573
Name _fye13: [1]Inputs!$E$624

Sheet Capitalisation
A3: 2Q26
B5: Debt Breakdown as on 30 Jun 2026 | C5: USD mn | D5: Leverage | G5: Company reported | H5: USD mm
G6: Total debentures and lease liabilities | H6: 4353
B7: Current portion | C7: =SUM(C8) -> 830.109 | G7: Debt to Equity | H7: 0.26
B8: Debentures | C8: =Model!$AG$106 -> 830.109 | G8: Debt to EBITDA | H8: 0.61
B10: Non Current portion | C10: =SUM(C11) -> 2449.44
B11: Debentures | C11: =Model!$AG$107 -> 2449.44
B13: Leases | C13: =SUM(C14:C15) -> 1073.788
B14: Current | C14: =Model!$AG$111 -> 410
B15: Non curremt | C15: =Model!$AG$112 -> 663.788
B17: Total Loans & Borrowings | C17: =C13+C7+C10 -> 4353.337 | D17: =C17/C23 -> 0.64801087
B18: Cash and Cash Equivalents | C18: =Model!$AG$119 -> 2498.089
B19: Investments | C19: =Model!$AG$120 -> 98.813
B20: Net debt | C20: =C17-C18-C19 -> 1756.435 | D20: =C20/C23 -> 0.26145207
B21: Equity | C21: =Model!$AG$124 -> 17067.98
B22: Total Capitalisation | C22: =C20+C21 -> 18824.415
B23: LTM Adjusted EBITDA | C23: =Model!$AG$90 -> 6718
B24: check | C24: =+C17-Model!$AG$118 -> 0
B26: Liquidity at the end | C26: USD mn
B27: Cash and Cash Equivalents | C27: =C18 -> 2498.089
B28: Investments | C28: =C19 -> 98.813
B29: Total debt | C29: =SUM(C27:C28) -> 2596.902
B33: Debt Maturity Profile
A65: 1Q26
B67: Debt Breakdown as on 31-Mar-2026 | C67: USD mn | D67: Leverage | G67: Company reported | H67: USD mm
G68: Total debentures and lease liabilities | H68: 3943
B69: Current portion | C69: =SUM(C70) -> 228.105 | G69: Debt to Equity | H69: 0.24
B70: Debentures | C70: =Model!$AF$106 -> 228.105 | G70: Debt to EBITDA | H70: 0.64
B72: Non Current portion | C72: =SUM(C73) -> 2603.826
B73: Debentures | C73: =Model!$AF$107 -> 2603.826
B75: Leases | C75: =SUM(C76:C77) -> 1111.113
B76: Current | C76: =Model!$AF$111 -> 433
B77: Non curremt | C77: =Model!$AF$112 -> 678.113
B79: Total Loans & Borrowings | C79: =C75+C69+C72 -> 3943.044 | D79: =C79/C85 -> 0.64000065
B80: Cash and Cash Equivalents | C80: =Model!$AF$119 -> 2460.358
B81: Investments | C81: =Model!$AF$120 -> 71.839
B82: Net debt | C82: =C79-C80-C81 -> 1410.847 | D82: =C82/C85 -> 0.22899643
B83: Equity | C83: =Model!$AF$124 -> 16226.257
B84: Total Capitalisation | C84: =C82+C83 -> 17637.104
B85: LTM Adjusted EBITDA | C85: =Model!$AF$90 -> 6161
B86: check | C86: =+C79-Model!$AF$118 -> 0
B89: Debt Maturity at the end | C89: USD mn
B90: 2026 | C90: 227
B91: 2027 | C91: 648
B92: 2029 | C92: 379
B93: 2030 | C93: 350
B94: 2032 | C94: 179
B95: 2042 | C95: 458
B96: 2059 | C96: 600
B97: Total debt | C97: =SUM(C90:C96) -> 2841
B101: Liquidity at the end | C101: USD mn
B102: Cash and Cash Equivalents | C102: =C80 -> 2460.358
B103: Investments | C103: =C81 -> 71.839
B104: Total debt | C104: =SUM(C102:C103) -> 2532.197
A110: FY25
B112: Debt Breakdown as on 31-Dec-2025 | C112: USD mn | D112: Leverage | G112: Company reported | H112: USD mm
G113: Interest bearing debt | H113: 4014
B114: Current portion | C114: =SUM(C115) -> 236.872 | G114: Debt to Equity | H114: 0.24
B115: Debentures | C115: =Model!$AE$106 -> 236.872 | G115: Debt to EBITDA | H115: 0.65
B117: Non Current portion | C117: =SUM(C118) -> 2631.133
B118: Debentures | C118: =Model!$AE$107 -> 2631.133
B120: Leases | C120: =SUM(C121:C122) -> 1146.042
B121: Current | C121: =Model!$AE$111 -> 432
B122: Non curremt | C122: =Model!$AE$112 -> 714.042
B124: Total Loans & Borrowings | C124: =C120+C114+C117 -> 4014.047 | D124: =C124/C130 -> 0.67395013
B125: Cash and Cash Equivalents | C125: =Model!$AE$119 -> 2313.792
B126: Investments | C126: =Model!$AE$120 -> 121.839
B127: Net debt | C127: =C124-C125-C126 -> 1578.416 | D127: =C127/C130 -> 0.26501276
B128: Equity | C128: =Model!$AE$124 -> 16451.134
B129: Total Capitalisation | C129: =C127+C128 -> 18029.55
B130: LTM Adjusted EBITDA | C130: =Model!$AE$90 -> 5956
B131: check | C131: =+C124-Model!$AE$118 -> 0
B134: Debt Maturity at FY25 | C134: USD mn
B135: 2026 | C135: 229
B136: 2027 | C136: 648
B137: 2029 | C137: 379
B138: 2030 | C138: 350
B139: 2032 | C139: 180
B140: 2042 | C140: 458
B141: 2059 | C141: 600
B142: Total debt | C142: =SUM(C135:C141) -> 2844
B143: check
B146: Liquidity at FY25 | C146: USD mn
B147: Cash and Cash Equivalents | C147: =C125 -> 2313.792
B148: Investments | C148: =C126 -> 121.839
B149: Total debt | C149: =SUM(C147:C148) -> 2435.631
A156: 3Q25
B158: Debt Breakdown as on 30-Sep-2025 | C158: USD mn | D158: Leverage | G158: Company reported | H158: USD mm
G159: Interest bearing debt | H159: 3976
B160: Current portion | C160: =SUM(C161) -> 46.722 | G160: Debt to Equity | H160: 0.25
B161: Debentures | C161: =Model!$AD$106 -> 46.722 | G161: Debt to EBITDA | H161: 0.64
B163: Non Current portion | C163: =SUM(C164) -> 2799
B164: Debentures | C164: =Model!$AD$107 -> 2799
B166: Leases | C166: =SUM(C167:C168) -> 1129.623
B167: Current | C167: =Model!$AD$111 -> 418
B168: Non curremt | C168: =Model!$AD$112 -> 711.623
B170: Total Loans & Borrowings | C170: =C166+C160+C163 -> 3975.345 | D170: =C170/C176 -> 0.65308773
B171: Cash and Cash Equivalents | C171: =Model!$AD$119 -> 2565.544
B172: Investments | C172: =Model!$AD$120 -> 217.581
B173: Net debt | C173: =C170-C171-C172 -> 1192.22 | D173: =C173/C176 -> 0.19586332
...

Sheet Model
B2: PTT EP | C2: Annual | D2: Annual | E2: Annual | F2: Annual | G2: Annual | H2: Annual | I2: Annual | J2: LTM | L2: Quarters | M2: Quarters | N2: Quarters | O2: Quarters | P2: Quarters | Q2: Quarters | R2: Quarters | S2: Quarters | T2: Quarters | U2: Quarters | V2: Quarters | W2: Quarters | X2: Quarters | Y2: Quarters | Z2: Quarters | AA2: Quarters | AB2: Quarters | AC2: Quarters | AD2: Quarters | AE2: Quarters | AF2: Quarters | AG2: Quarters
B3: (USD million) | C3: 43830 | D3: 44196 | E3: 44561 | F3: 44926 | G3: 45291 | H3: 45657 | I3: 46022 | J3: =AG3 -> 46203 | L3: 44286 | M3: 44377 | N3: 44469 | O3: 44561 | P3: 44651 | Q3: 44742 | R3: 44834 | S3: 44926 | T3: 45016 | U3: 45107 | V3: 45199 | W3: 45291 | X3: 45382 | Y3: 45473 | Z3: 45565 | AA3: 45657 | AB3: 45747 | AC3: 45838 | AD3: 45930 | AE3: 46022 | AF3: 46112 | AG3: 46203
C4: Act | D4: Act | E4: Act | F4: Act | G4: Act | H4: Act | I4: Act | J4: Act | L4: Act | M4: Act | N4: Act | O4: Act | P4: Act | Q4: Act | R4: Act | S4: Act | T4: Act | U4: Act | V4: Act | W4: Act | X4: Act | Y4: Act | Z4: Act | AA4: Act | AB4: Act | AC4: Act | AD4: Act | AE4: Act | AF4: Act | AG4: Act
C5: FY | D5: FY | E5: FY | F5: FY | G5: FY | H5: FY | I5: FY | J5: LTM | L5: 1Q | M5: 2Q | N5: 3Q | O5: 4Q | P5: 1Q | Q5: 2Q | R5: 3Q | S5: 4Q | T5: 1Q | U5: 2Q | V5: 3Q | W5: 4Q | X5: 1Q | Y5: 2Q | Z5: 3Q | AA5: 4Q | AB5: 1Q | AC5: 2Q | AD5: 3Q | AE5: 4Q | AF5: 1Q | AG5: 2Q
B6: INCOME STATEMENT
B7: Total Revenues | C7: =C8+C9 -> 6162.8123 | D7: =D8+D9 -> 5135.52 | E7: =E8+E9 -> 6824.007 | F7: =F8+F9 -> 9421.487 | G7: =G8+G9 -> 8639.146 | H7: =H8+H9 -> 8842.301 | I7: =I8+I9 -> 8562.19 | J7: =J8+J9 -> 9669.379 | L7: =L8+L9 -> 1411.727 | M7: =M8+M9 -> 1748.699 | N7: =N8+N9 -> 1770.325 | O7: =O8+O9 -> 1893.256 | P7: =P8+P9 -> 2060.633 | Q7: =Q8+Q9 -> 2415.255 | R7: =R8+R9 -> 2431.326 | S7: =S8+S9 -> 2514.273 | ... AG7: =AG8+AG9 -> 2949.73
B8: Revenue from sales | C8: 6046.4162 | D8: 5043.17 | E8: 6730.86 | F8: 9270.564 | G8: 8511.079 | H8: 8698.463 | I8: 8437.335 | J8: =SUM(AD8:AG8) -> 9553.838 | L8: 1391.318 | M8: 1728.895 | N8: 1743.639 | O8: =E8-SUM(L8:N8) -> 1867.008 | P8: 2030.275 | Q8: 2382.536 | R8: 2388.305 | S8: =F8-SUM(P8:R8) -> 2469.448 | T8: 2193.048 | U8: 1923.876 | V8: 2192.607 | W8: =G8-SUM(T8:V8) -> 2201.548 | X8: 2093.482 | Y8: 2257.467 | Z8: 2133.415 | AA8: =H8-SUM(X8:Z8) -> 2214.099 | AB8: 2063.802 | AC8: =4184.017-AB8 -> 2120.215 | AD8: 2093.213 | AE8: =I8-SUM(AB8:AD8) -> 2160.105 | AF8: 2376.871 | AG8: =5300.52-AF8 -> 2923.649
B9: Revenue from pipeline transportation | C9: 116.39614 | D9: 92.35 | E9: 93.147 | F9: 150.923 | G9: 128.067 | H9: 143.838 | I9: 124.855 | J9: =SUM(AD9:AG9) -> 115.541 | L9: 20.409 | M9: 19.804 | N9: 26.686 | O9: =E9-SUM(L9:N9) -> 26.248 | P9: 30.358 | Q9: 32.719 | R9: 43.021 | S9: =F9-SUM(P9:R9) -> 44.825 | T9: 34.181 | U9: 33.595 | V9: 30.801 | W9: =G9-SUM(T9:V9) -> 29.49 | X9: 29.417 | Y9: 40.881 | Z9: 40.044 | AA9: =H9-SUM(X9:Z9) -> 33.496 | AB9: 31.985 | AC9: =62.61-AB9 -> 30.625 | AD9: 33.522 | AE9: =I9-SUM(AB9:AD9) -> 28.723 | AF9: 27.215 | AG9: =53.296-AF9 -> 26.081
B10: % of growth | D10: =(D7/C7)-1 -> -0.16669213 | E10: =(E7/D7)-1 -> 0.32878598 | F10: =(F7/E7)-1 -> 0.38063853 | G10: =(G7/F7)-1 -> -0.083037954 | H10: =(H7/G7)-1 -> 0.023515635 | I10: =(I7/H7)-1 -> -0.031678519 | P10: =(P7/L7)-1 -> 0.45965403 | Q10: =(Q7/M7)-1 -> 0.38117252 | R10: =(R7/N7)-1 -> 0.37337833 | S10: =(S7/O7)-1 -> 0.32801533 | T10: =(T7/P7)-1 -> 0.080847002 | U10: =(U7/Q7)-1 -> -0.18953858 | V10: =(V7/R7)-1 -> -0.085516299 | W10: =(W7/S7)-1 -> -0.11265085 | ... AG10: =(AG7/AC7)-1 -> 0.37143163
B11: Operating expenses:
B12: Operating expenses | C12: -750.68233 | D12: -795.112 | E12: -861.495 | F12: -1110.01 | G12: -1224.841 | H12: -1401.808 | I12: -1530.354 | J12: =SUM(AD12:AG12) -> -1722.637 | L12: -174.202 | M12: -192.455 | N12: -219.801 | O12: =E12-SUM(L12:N12) -> -275.037 | P12: -196.719 | Q12: -291.598 | R12: -300.286 | S12: =F12-SUM(P12:R12) -> -321.407 | T12: -360.053 | U12: -247.249 | V12: -337.237 | W12: =G12-SUM(T12:V12) -> -280.302 | X12: -299.61 | Y12: -309.718 | Z12: -367.986 | AA12: =H12-SUM(X12:Z12) -> -424.494 | AB12: -356.128 | AC12: =-734.836-AB12 -> -378.708 | AD12: -369.789 | AE12: =I12-SUM(AB12:AD12) -> -425.729 | AF12: -424.43 | AG12: =-927.119-AF12 -> -502.689
B13: Exploration expenses | C13: -128.09799 | D13: -104.314 | E13: -226.252 | F13: -71.683 | G13: -94.044 | H13: -124.794 | I13: -133.45 | J13: =SUM(AD13:AG13) -> -137.235 | L13: -148.805 | M13: -7.464 | N13: -50.285 | O13: =E13-SUM(L13:N13) -> -19.698 | P13: -6.122 | Q13: -16.553 | R13: -41.497 | S13: =F13-SUM(P13:R13) -> -7.511 | T13: -10.842 | U13: -5.625 | V13: -15.426 | W13: =G13-SUM(T13:V13) -> -62.151 | X13: -46.299 | Y13: -26.601 | Z13: -45.837 | AA13: =H13-SUM(X13:Z13) -> -6.057 | AB13: -8.454 | AC13: =-48.96-AB13 -> -40.506 | AD13: -35.782 | AE13: =I13-SUM(AB13:AD13) -> -48.708 | AF13: -6.761 | AG13: =-52.745-AF13 -> -45.984
B14: Administrative expenses | C14: -383.77651 | D14: -314.117 | E14: -355.039 | F14: -578.363 | G14: -486.938 | H14: -516.071 | I14: -618.145 | J14: =SUM(AD14:AG14) -> -684.189 | L14: -74.945 | M14: -82.935 | N14: -71.625 | O14: =E14-SUM(L14:N14) -> -125.534 | P14: -92.609 | Q14: -112.4 | R14: -80.444 | S14: =F14-SUM(P14:R14) -> -292.91 | T14: -100.293 | U14: -105.718 | V14: -113.153 | W14: =G14-SUM(T14:V14) -> -167.774 | X14: -105.356 | Y14: -111.533 | Z14: -129.436 | AA14: =H14-SUM(X14:Z14) -> -169.746 | AB14: -125.502 | AC14: =-251.496-AB14 -> -125.994 | AD14: -166.273 | AE14: =I14-SUM(AB14:AD14) -> -200.376 | AF14: -152.818 | AG14: =-317.54-AF14 -> -164.722
B15: Petroleum royalties | C15: -546.33421 | D15: -410.154 | E15: -530.215 | F15: -687.723 | G15: -450.155 | H15: -396.387 | I15: -362.676 | J15: =SUM(AD15:AG15) -> -406.894 | L15: -117.6 | M15: -137.964 | N15: -131.997 | O15: =E15-SUM(L15:N15) -> -142.654 | P15: -164.209 | Q15: -178.681 | R15: -170.824 | S15: =F15-SUM(P15:R15) -> -174.009 | T15: -140.516 | U15: -93.562 | V15: -106.837 | W15: =G15-SUM(T15:V15) -> -109.24 | X15: -103.908 | Y15: -104.226 | Z15: -93.523 | AA15: =H15-SUM(X15:Z15) -> -94.73 | AB15: -95.097 | AC15: =-183.889-AB15 -> -88.792 | AD15: -87.983 | AE15: =I15-SUM(AB15:AD15) -> -90.804 | AF15: -104.388 | AG15: =-228.107-AF15 -> -123.719
B16: Depreciation, depletion and amortisation | C16: -2026.0556 | D16: -2086.083 | E16: -2202.064 | F16: -2363.135 | G16: -2334.711 | H16: -2688.941 | I16: -2897.044 | J16: =SUM(AD16:AG16) -> -2879.629 | L16: -546.659 | M16: -629.714 | N16: -605.821 | O16: =E16-SUM(L16:N16) -> -419.87 | P16: -516.759 | Q16: -565.33 | R16: -631.112 | S16: =F16-SUM(P16:R16) -> -649.934 | T16: -491.624 | U16: -559.716 | V16: -629.444 | W16: =G16-SUM(T16:V16) -> -653.927 | X16: -623.245 | Y16: -716.25 | Z16: -722.533 | AA16: =H16-SUM(X16:Z16) -> -626.913 | AB16: -680.711 | AC16: =-1435.575-AB16 -> -754.864 | AD16: -736.682 | AE16: =I16-SUM(AB16:AD16) -> -724.787 | AF16: -668.858 | AG16: =-1418.16-AF16 -> -749.302
B17: Gain/(Loss) on foreign exchange rate | C17: 108.59753 | D17: 26.062 | E17: -37.592 | F17: -91.064 | G17: 48.129 | H17: 6.49 | I17: 51.425 | J17: =SUM(AD17:AG17) -> 38.053 | L17: -4.462 | M17: -1.753 | N17: -36.323 | O17: =E17-SUM(L17:N17) -> 4.946 | P17: -4.824 | Q17: -44.217 | R17: -86.591 | S17: =F17-SUM(P17:R17) -> 44.568 | T17: 18.966 | U17: 8.798 | V17: -4.905 | W17: =G17-SUM(T17:V17) -> 25.27 | X17: -2.063 | Y17: 0.799 | Z17: 0 | AA17: =H17-SUM(X17:Z17) -> 7.754 | AB17: 0 | AC17: =1.814-AB17 -> 1.814 | AD17: 0 | AE17: =I17-SUM(AB17:AD17) -> 49.611 | AF17: 23.191 | AG17: =-11.558-AF17 -> -34.749
B18: Loss on remeasuring of financial instruments | C18: -109.39972 | D18: 0 | E18: -234.29 | F18: -184.486 | G18: -55.588 | H18: 0 | I18: 0 | J18: =SUM(AD18:AG18) -> -152.523 | L18: -98.359 | M18: -124.35 | N18: -5.052 | O18: =E18-SUM(L18:N18) -> -6.529 | P18: -245.612 | Q18: 0 | R18: 0 | S18: =F18-SUM(P18:R18) -> 61.126 | T18: -41.765 | U18: 0 | V18: -19.904 | W18: =G18-SUM(T18:V18) -> 6.081 | X18: -11.832 | Y18: 0 | Z18: -31.036 | AA18: =H18-SUM(X18:Z18) -> 42.868 | AB18: 0 | AC18: =0-AB18 -> 0 | AD18: -17.577 | AE18: =I18-SUM(AB18:AD18) -> 17.577 | AF18: -276.41 | AG18: =-152.523-AF18 -> 123.887
B19: Impairment loss on assets and goodwill | C19: 0 | D19: -91.576 | E19: 0 | F19: 0 | G19: 0 | H19: 0 | I19: 0 | J19: =SUM(AD19:AG19) -> 0 | L19: 0 | M19: 0 | N19: 0 | O19: =E19-SUM(L19:N19) -> 0 | P19: 0 | Q19: 0 | R19: 0 | S19: =F19-SUM(P19:R19) -> 0 | T19: 0 | U19: 0 | V19: 0 | W19: =G19-SUM(T19:V19) -> 0 | X19: 0 | Y19: 0 | Z19: 0 | AA19: =H19-SUM(X19:Z19) -> 0 | AB19: 0 | AC19: =0-AB19 -> 0 | AD19: 0 | AE19: =I19-SUM(AB19:AD19) -> 0 | AF19: 0 | AG19: =0-AF19 -> 0
B20: Impairment loss on assets held-for-sale | C20: 0 | D20: 0 | E20: -183 | F20: -300.08 | G20: -120 | H20: 0 | I20: 0 | J20: =SUM(AD20:AG20) -> 0 | L20: 0 | M20: 0 | N20: 0 | O20: =E20-SUM(L20:N20) -> -183 | P20: 0 | Q20: 0 | R20: -94.996 | S20: =F20-SUM(P20:R20) -> -205.084 | T20: 0 | U20: 0 | V20: 0 | W20: =G20-SUM(T20:V20) -> -120 | X20: 0 | Y20: 0 | Z20: 0 | AA20: =H20-SUM(X20:Z20) -> 0 | AB20: 0 | AC20: =0-AB20 -> 0 | AD20: 0 | AE20: =I20-SUM(AB20:AD20) -> 0 | AF20: 0 | AG20: =0-AF20 -> 0
B21: Gain on debt modification | C21: 0 | D21: 22.307 | E21: 0 | F21: 0 | G21: 0 | H21: 0 | I21: 0 | J21: =SUM(AD21:AG21) -> 0 | L21: 0 | M21: 0 | N21: 0 | O21: =E21-SUM(L21:N21) -> 0 | P21: 0 | Q21: 0 | R21: 0 | S21: =F21-SUM(P21:R21) -> 0 | T21: 0 | U21: 0 | V21: 0 | W21: =G21-SUM(T21:V21) -> 0 | X21: 0 | Y21: 0 | Z21: 22.741 | AA21: =H21-SUM(X21:Z21) -> -22.741 | AB21: -8.202 | AC21: =0-AB21 -> 8.202 | AD21: 34.656 | AE21: =I21-SUM(AB21:AD21) -> -34.656 | AF21: 0 | AG21: =0-AF21 -> 0
B22: Gain on remeasuring of financial instruments | C22: 0 | D22: 99.331 | E22: 0 | F22: 0 | G22: 0 | H22: 0 | I22: 0 | J22: =SUM(AD22:AG22) -> -6.573 | L22: 0 | M22: 0 | N22: 0 | O22: =E22-SUM(L22:N22) -> 0 | P22: 0 | Q22: 8.724 | R22: 152.519 | S22: =F22-SUM(P22:R22) -> -161.243 | T22: 0 | U22: 28.538 | V22: 0 | W22: =G22-SUM(T22:V22) -> -28.538 | X22: 0 | Y22: 13.964 | Z22: 0 | AA22: =H22-SUM(X22:Z22) -> -13.964 | AB22: 4.609 | AC22: =6.573-AB22 -> 1.964 | AD22: 0 | AE22: =I22-SUM(AB22:AD22) -> -6.573 | AF22: 0 | AG22: =0-AF22 -> 0
B23: Other operating income/(loss), net | C23: 55.390651 | D23: =37.012-20.341 -> 16.671 | E23: 131.594 | F23: 195.134 | G23: =144.545+73.239 -> 217.784 | H23: =174.592+11.089 -> 185.681 | I23: =(17076+161400)/1000 -> 178.476 | J23: =SUM(AD23:AG23) -> 188.303 | L23: 11.675 | M23: 14.392 | N23: 10.459 | O23: =E23-SUM(L23:N23) -> 95.068 | P23: 18.173 | Q23: 39.519 | R23: 21.835 | S23: =F23-SUM(P23:R23) -> 115.607 | T23: 33.373 | U23: 41.488 | V23: 31.442 | W23: =G23-SUM(T23:V23) -> 111.481 | X23: 29.487 | Y23: 32.171 | Z23: 50.93 | AA23: =H23-SUM(X23:Z23) -> 73.093 | AB23: 30.623 | AC23: =72.194-AB23 -> 41.571 | AD23: 33.209 | AE23: =I23-SUM(AB23:AD23) -> 73.073 | AF23: 35.631 | AG23: =82.021-AF23 -> 46.39
B24: Operating profit | C24: =C7+SUM(C12:C23) -> 2382.4541 | D24: =D7+SUM(D12:D23) -> 1498.535 | E24: =E7+SUM(E12:E23) -> 2325.654 | F24: =F7+SUM(F12:F23) -> 4230.077 | G24: =G7+SUM(G12:G23) -> 4138.782 | H24: =H7+SUM(H12:H23) -> 3906.471 | I24: =I7+SUM(I12:I23) -> 3250.422 | J24: =J7+SUM(J12:J23) -> 3906.055 | L24: =L7+SUM(L12:L23) -> 258.37 | M24: =M7+SUM(M12:M23) -> 586.456 | N24: =N7+SUM(N12:N23) -> 659.88 | O24: =O7+SUM(O12:O23) -> 820.948 | P24: =P7+SUM(P12:P23) -> 851.952 | Q24: =Q7+SUM(Q12:Q23) -> 1254.719 | R24: =R7+SUM(R12:R23) -> 1199.93 | S24: =S7+SUM(S12:S23) -> 923.476 | ... AG24: =AG7+SUM(AG12:AG23) -> 1498.842
B25: Finance exps | C25: -234.97874 | D25: -254.476 | E25: -202.226 | F25: -233.583 | G25: -294.457 | H25: -334.466 | I25: -397.662 | J25: =SUM(AD25:AG25) -> -389.98 | L25: -48.02 | M25: -51.372 | N25: -52.008 | O25: =E25-SUM(L25:N25) -> -50.826 | P25: -51.968 | Q25: -63.694 | R25: -62.335 | S25: =F25-SUM(P25:R25) -> -55.586 | T25: -77.159 | U25: -75.596 | V25: -75.458 | W25: =G25-SUM(T25:V25) -> -66.244 | X25: -84.854 | Y25: -87.501 | Z25: -84.507 | AA25: =H25-SUM(X25:Z25) -> -77.604 | AB25: -96.744 | AC25: =-193.895-AB25 -> -97.151 | AD25: -98.579 | AE25: =I25-SUM(AB25:AD25) -> -105.188 | AF25: -91.919 | AG25: =-186.213-AF25 -> -94.294
B26: Finance income | C26: 86.234821 | D26: 36.729 | E26: 16.75 | F26: 44.031 | G26: 152.274 | H26: 238.34 | I26: 178.192 | J26: =SUM(AD26:AG26) -> 133.267 | L26: 5.131 | M26: 4.726 | N26: 3.465 | O26: =E26-SUM(L26:N26) -> 3.428 | P26: 4.264 | Q26: 5.587 | R26: 11.402 | S26: =F26-SUM(P26:R26) -> 22.778 | T26: 34.787 | U26: 37.334 | V26: 36.906 | W26: =G26-SUM(T26:V26) -> 43.247 | X26: 56.7 | Y26: 66.399 | Z26: 59.846 | AA26: =H26-SUM(X26:Z26) -> 55.395 | AB26: 54.049 | AC26: =103.79-AB26 -> 49.741 | AD26: 39.804 | AE26: =I26-SUM(AB26:AD26) -> 34.598 | AF26: 28.37 | AG26: =58.865-AF26 -> 30.495
B27: Gain from a bargain purchase | C27: 0 | D27: 0 | E27: 341.874 | F27: 0 | G27: 0 | H27: 0 | I27: 0 | J27: =SUM(AD27:AG27) -> 0 | L27: 349.971 | M27: 0 | N27: 0 | O27: =E27-SUM(L27:N27) -> -8.097 | P27: 0 | Q27: 0 | R27: 0 | S27: =F27-SUM(P27:R27) -> 0 | T27: 0 | U27: 0 | V27: 0 | W27: =G27-SUM(T27:V27) -> 0 | X27: 0 | Y27: 0 | Z27: 0 | AA27: =H27-SUM(X27:Z27) -> 0 | AB27: 0 | AC27: =0-AB27 -> 0 | AD27: 0 | AE27: =I27-SUM(AB27:AD27) -> 0 | AF27: 0 | AG27: =0-AF27 -> 0
B28: Share of net profit /(loss) of associates | C28: 12.351839 | D28: 41.636 | E28: 15.174 | F28: 19.556 | G28: 42.566 | H28: 37.752 | I28: 130.224 | J28: =SUM(AD28:AG28) -> 152.513 | L28: 2.179 | M28: 2.795 | N28: 6.895 | O28: =E28-SUM(L28:N28) -> 3.305 | P28: 10.567 | Q28: 12.964 | R28: -17.485 | S28: =F28-SUM(P28:R28) -> 13.51 | T28: 12.42 | U28: 9.623 | V28: 9.096 | W28: =G28-SUM(T28:V28) -> 11.427 | X28: 10.181 | Y28: 5.475 | Z28: 1.019 | AA28: =H28-SUM(X28:Z28) -> 21.077 | AB28: 13.758 | AC28: =18.535-AB28 -> 4.777 | AD28: 4.868 | AE28: =I28-SUM(AB28:AD28) -> 106.821 | AF28: 24.791 | AG28: =40.824-AF28 -> 16.033
B29: Profit before tax | C29: =C24+SUM(C25:C28) -> 2246.062 | D29: =D24+SUM(D25:D28) -> 1322.424 | E29: =E24+SUM(E25:E28) -> 2497.226 | F29: =F24+SUM(F25:F28) -> 4060.081 | G29: =G24+SUM(G25:G28) -> 4039.165 | H29: =H24+SUM(H25:H28) -> 3848.097 | I29: =I24+SUM(I25:I28) -> 3161.176 | J29: =J24+SUM(J25:J28) -> 3801.855 | L29: =L24+SUM(L25:L28) -> 567.631 | M29: =M24+SUM(M25:M28) -> 542.605 | N29: =N24+SUM(N25:N28) -> 618.232 | O29: =O24+SUM(O25:O28) -> 768.758 | P29: =P24+SUM(P25:P28) -> 814.815 | Q29: =Q24+SUM(Q25:Q28) -> 1209.576 | R29: =R24+SUM(R25:R28) -> 1131.512 | S29: =S24+SUM(S25:S28) -> 904.178 | ... AG29: =AG24+SUM(AG25:AG28) -> 1451.076
B30: Income taxes | C30: -676.99805 | D30: -602.88 | E30: -1286.688 | F30: -2061.501 | G30: -1831.388 | H30: -1621.179 | I30: -1331.232 | J30: =SUM(AD30:AG30) -> -1657.999 | L30: -191.611 | M30: -320.957 | N30: -326.179 | O30: =E30-SUM(L30:N30) -> -447.941 | P30: -496.785 | Q30: -609.835 | R30: -467.916 | S30: =F30-SUM(P30:R30) -> -486.965 | T30: -535.276 | U30: -385.423 | V30: -484.442 | W30: =G30-SUM(T30:V30) -> -426.247 | X30: -418.589 | Y30: -408.277 | Z30: -321.662 | AA30: =H30-SUM(X30:Z30) -> -472.651 | AB30: -340.537 | AC30: =-705.767-AB30 -> -365.23 | AD30: -334.071 | AE30: =I30-SUM(AB30:AD30) -> -291.394 | AF30: =(-414661)/1000 -> -414.661 | AG30: =-1032.534-AF30 -> -617.873
B31: Net profit/loss | C31: =+C29+C30 -> 1569.064 | D31: =+D29+D30 -> 719.544 | E31: =+E29+E30 -> 1210.538 | F31: =+F29+F30 -> 1998.58 | G31: =+G29+G30 -> 2207.777 | H31: =+H29+H30 -> 2226.918 | I31: =+I29+I30 -> 1829.944 | J31: =+J29+J30 -> 2143.856 | L31: =+L29+L30 -> 376.02 | M31: =+M29+M30 -> 221.648 | N31: =+N29+N30 -> 292.053 | O31: =+O29+O30 -> 320.817 | P31: =+P29+P30 -> 318.03 | Q31: =+Q29+Q30 -> 599.741 | R31: =+R29+R30 -> 663.596 | S31: =+S29+S30 -> 417.213 | ... AG31: =+AG29+AG30 -> 833.203
B32: % margin | C32: =+C31/C7 -> 0.25460195 | D32: =+D31/D7 -> 0.14011123 | E32: =+E31/E7 -> 0.17739401 | F32: =+F31/F7 -> 0.21213 | G32: =+G31/G7 -> 0.25555501 | H32: =+H31/H7 -> 0.25184825 | I32: =+I31/I7 -> 0.21372383 | J32: =+J31/J7 -> 0.221716 | L32: =+L31/L7 -> 0.26635461 | M32: =+M31/M7 -> 0.12675023 | N32: =+N31/N7 -> 0.1649714 | O32: =+O31/O7 -> 0.16945252 | P32: =+P31/P7 -> 0.15433607 | Q32: =+Q31/Q7 -> 0.24831374 | R32: =+R31/R7 -> 0.27293584 | S32: =+S31/S7 -> 0.16593783 | ... AG32: =+AG31/AG7 -> 0.28246755
B34: As % of sales unless stated otherwise
B35: =B12 -> Operating expenses | C35: =-C12/C7 -> 0.1218084 | D35: =-D12/D7 -> 0.154826 | E35: =-E12/E7 -> 0.12624474 | F35: =-F12/F7 -> 0.11781686 | G35: =-G12/G7 -> 0.14177802 | H35: =-H12/H7 -> 0.1585343 | I35: =-I12/I7 -> 0.17873395 | J35: =-J12/J7 -> 0.17815384 | L35: =-L12/L7 -> 0.12339638 | M35: =-M12/M7 -> 0.1100561 | N35: =-N12/N7 -> 0.12415856 | O35: =-O12/O7 -> 0.14527195 | P35: =-P12/P7 -> 0.095465325 | Q35: =-Q12/Q7 -> 0.12073177 | R35: =-R12/R7 -> 0.12350709 | S35: =-S12/S7 -> 0.12783298 | ... AG35: =-AG12/AG7 -> 0.17041865
B36: =B13 -> Exploration expenses | C36: =-C13/C7 -> 0.020785639 | D36: =-D13/D7 -> 0.020312257 | E36: =-E13/E7 -> 0.0331553 | F36: =-F13/F7 -> 0.0076084593 | G36: =-G13/G7 -> 0.010885798 | H36: =-H13/H7 -> 0.014113295 | I36: =-I13/I7 -> 0.015585966 | J36: =-J13/J7 -> 0.014192742 | L36: =-L13/L7 -> 0.10540636 | M36: =-M13/M7 -> 0.004268316 | N36: =-N13/N7 -> 0.028404389 | O36: =-O13/O7 -> 0.010404298 | P36: =-P13/P7 -> 0.0029709317 | Q36: =-Q13/Q7 -> 0.0068535206 | R36: =-R13/R7 -> 0.017067641 | S36: =-S13/S7 -> 0.0029873447 | ... AG36: =-AG13/AG7 -> 0.015589223
B37: =B15 -> Petroleum royalties | C37: =-C15/C7 -> 0.088650146 | D37: =-D15/D7 -> 0.079866109 | E37: =-E15/E7 -> 0.077698484 | F37: =-F15/F7 -> 0.072995165 | G37: =-G15/G7 -> 0.052106423 | H37: =-H15/H7 -> 0.04482849 | I37: =-I15/I7 -> 0.042357855 | J37: =-J15/J7 -> 0.042080676 | L37: =-L15/L7 -> 0.083302225 | M37: =-M15/M7 -> 0.078895224 | N37: =-N15/N7 -> 0.074560886 | O37: =-O15/O7 -> 0.0753485 | P37: =-P15/P7 -> 0.07968862 | Q37: =-Q15/Q7 -> 0.07398018 | R37: =-R15/R7 -> 0.070259603 | S37: =-S15/S7 -> 0.069208475 | ... AG37: =-AG15/AG7 -> 0.041942483
B38: =B23 -> Other operating income/(loss), net | C38: =-C23/C7 -> -0.0089878855 | D38: =-D23/D7 -> -0.0032462146 | E38: =-E23/E7 -> -0.019283978 | F38: =-F23/F7 -> -0.020711593 | G38: =-G23/G7 -> -0.025208973 | H38: =-H23/H7 -> -0.020999172 | I38: =-I23/I7 -> -0.020844667 | J38: =-J23/J7 -> -0.019474157 | L38: =-L23/L7 -> -0.0082700125 | M38: =-M23/M7 -> -0.0082301185 | N38: =-N23/N7 -> -0.0059079548 | O38: =-O23/O7 -> -0.050214023 | P38: =-P23/P7 -> -0.0088191347 | Q38: =-Q23/Q7 -> -0.016362247 | R38: =-R23/R7 -> -0.0089806961 | S38: =-S23/S7 -> -0.045980289 | ... AG38: =-AG23/AG7 -> -0.015726863
B39: Finance exps as % of debt | C39: =-C25/C118 -> 0.068273994 | D39: =-D25/D118 -> 0.064718223 | E39: =-E25/E118 -> 0.04939914 | F39: =-F25/F118 -> 0.060939645 | G39: =-G25/G118 -> 0.080593088 | H39: =-H25/H118 -> 0.088925792 | I39: =-I25/I118 -> 0.099067599 | J39: =-J25/J118 -> 0.089581854 | O39: =-SUM(L25:O25)/O118 -> 0.04939914 | P39: =-SUM(M25:P25)/P118 -> 0.05034977 | Q39: =-SUM(N25:Q25)/Q118 -> 0.051495118 | R39: =-SUM(O25:R25)/R118 -> 0.053541992 | S39: =-SUM(P25:S25)/S118 -> 0.060939645 | T39: =-SUM(Q25:T25)/T118 -> 0.067229375 | U39: =-SUM(R25:U25)/U118 -> 0.073937636 | V39: =-SUM(S25:V25)/V118 -> 0.07880648 | ... AG39: =-SUM(AD25:AG25)/AG118 -> 0.089581854
B40: Finance income as % of cash and cash equivalents | C40: =C26/C119 -> 0.030548341 | D40: =D26/D119 -> 0.0099160287 | E40: =E26/E119 -> 0.0065450422 | F40: =F26/F119 -> 0.012440877 | G40: =G26/G119 -> 0.037888916 | H40: =H26/H119 -> 0.060520603 | I40: =I26/I119 -> 0.077012973 | J40: =J26/J119 -> 0.053347579 | O40: =SUM(L26:O26)/O119 -> 0.0065450422 | P40: =SUM(M26:P26)/P119 -> 0.0047468591 | Q40: =SUM(N26:Q26)/Q119 -> 0.005966386 | R40: =SUM(O26:R26)/R119 -> 0.0071829446 | S40: =SUM(P26:S26)/S119 -> 0.012440877 | T40: =SUM(Q26:T26)/T119 -> 0.017576895 | U40: =SUM(R26:U26)/U119 -> 0.034686395 | V40: =SUM(S26:V26)/V119 -> 0.043411629 | ... AG40: =SUM(AD26:AG26)/AG119 -> 0.053347579
B41: =B28 -> Share of net profit /(loss) of associates | C41: =-C28/C7 -> -0.0020042536 | D41: =-D28/D7 -> -0.0081074555 | E41: =-E28/E7 -> -0.0022236202 | F41: =-F28/F7 -> -0.0020756808 | G41: =-G28/G7 -> -0.0049271074 | H41: =-H28/H7 -> -0.0042694769 | I41: =-I28/I7 -> -0.015209193 | J41: =-J28/J7 -> -0.015772781 | L41: =-L28/L7 -> -0.0015434996 | M41: =-M28/M7 -> -0.0015983311 | N41: =-N28/N7 -> -0.0038947651 | O41: =-O28/O7 -> -0.0017456699 | P41: =-P28/P7 -> -0.0051280359 | Q41: =-Q28/Q7 -> -0.0053675492 | R41: =-R28/R7 -> 0.007191549 | S41: =-S28/S7 -> -0.0053733226 | ... AG41: =-AG28/AG7 -> -0.0054354127
B42: Tax % of PBT | C42: =-C30/C29 -> 0.30141556 | D42: =-D30/D29 -> 0.45589009 | E42: =-E30/E29 -> 0.51524692 | F42: =-F30/F29 -> 0.50774874 | G42: =-G30/G29 -> 0.45340757 | H42: =-H30/H29 -> 0.42129369 | I42: =-I30/I29 -> 0.42111923 | J42: =-J30/J29 -> 0.43610264 | L42: =-L30/L29 -> 0.33756261 | M42: =-M30/M29 -> 0.59151132 | N42: =-N30/N29 -> 0.52759967 | O42: =-O30/O29 -> 0.58268142 | P42: =-P30/P29 -> 0.60969054 | Q42: =-Q30/Q29 -> 0.50417254 | R42: =-R30/R29 -> 0.41353163 | S42: =-S30/S29 -> 0.53857205 | ... AG42: =-AG30/AG29 -> 0.42580333
B44: Working capital /sales | C44: =C64/C7 -> -0.1790478 | D44: =D64/D7 -> 0.0085428545 | E44: =E64/E7 -> -0.065642664 | F44: =F64/F7 -> -0.091445862 | G44: =G64/G7 -> -0.073521619 | H44: =H64/H7 -> 0.047266204 | I44: =I64/I7 -> -0.027371736 | J44: =J64/J7 -> -0.026870495 | L44: =L64/L7 -> -0.11352337 | M44: =M64/M7 -> -0.031445663 | N44: =N64/N7 -> -0.14642679 | O44: =O64/O7 -> 0.014012896 | P44: =P64/P7 -> -0.089263833 | Q44: =Q64/Q7 -> -0.17649399 | R44: =R64/R7 -> -0.33691327 | S44: =S64/S7 -> 0.22583387 | ... AG44: =AG64/AG7 -> -0.028733816
B45: Capex/sales | C45: =-C68/C7 -> 0.19184764 | D45: =-D68/D7 -> 0.23109461 | E45: =-E68/E7 -> 0.24087724 | F45: =-F68/F7 -> 0.19748241 | G45: =-G68/G7 -> 0.27380878 | H45: =-H68/H7 -> 0.335462 | I45: =-I68/I7 -> 0.41927171 | J45: =-J68/J7 -> 0.42376227 | L45: =-L68/L7 -> 0.2922208 | M45: =-M68/M7 -> 0.17394646 | N45: =-N68/N7 -> 0.19780662 | O45: =-O68/O7 -> 0.30468674 | P45: =-P68/P7 -> 0.18716385 | Q45: =-Q68/Q7 -> 0.15912564 | R45: =-R68/R7 -> 0.20775083 | S45: =-S68/S7 -> 0.23285578 | ... AG45: =-AG68/AG7 -> 0.32097209
B47: EBITDA | C47: =C3 -> 43830 | D47: =D3 -> 44196 | E47: =E3 -> 44561 | F47: =F3 -> 44926 | G47: =G3 -> 45291 | H47: =H3 -> 45657 | I47: =I3 -> 46022 | J47: =J2 -> LTM | L47: =L3 -> 44286 | M47: =M3 -> 44377 | N47: =N3 -> 44469 | O47: =O3 -> 44561 | P47: =P3 -> 44651 | Q47: =Q3 -> 44742 | R47: =R3 -> 44834 | S47: =S3 -> 44926 | ... AG47: =AG3 -> 46203
B48: Operating profit | C48: =C24 -> 2382.4541 | D48: =D24 -> 1498.535 | E48: =E24 -> 2325.654 | F48: =F24 -> 4230.077 | G48: =G24 -> 4138.782 | H48: =H24 -> 3906.471 | I48: =I24 -> 3250.422 | J48: =J24 -> 3906.055 | L48: =L24 -> 258.37 | M48: =M24 -> 586.456 | N48: =N24 -> 659.88 | O48: =O24 -> 820.948 | P48: =P24 -> 851.952 | Q48: =Q24 -> 1254.719 | R48: =R24 -> 1199.93 | S48: =S24 -> 923.476 | ... AG48: =AG24 -> 1498.842
B49: Depreciation, depletion & amortization | C49: =-C16 -> 2026.0556 | D49: =-D16 -> 2086.083 | E49: =-E16 -> 2202.064 | F49: =-F16 -> 2363.135 | G49: =-G16 -> 2334.711 | H49: =-H16 -> 2688.941 | I49: =-I16 -> 2897.044 | J49: =-J16 -> 2879.629 | L49: =-L16 -> 546.659 | M49: =-M16 -> 629.714 | N49: =-N16 -> 605.821 | O49: =-O16 -> 419.87 | P49: =-P16 -> 516.759 | Q49: =-Q16 -> 565.33 | R49: =-R16 -> 631.112 | S49: =-S16 -> 649.934 | ... AG49: =-AG16 -> 749.302
B50: EBITDA | C50: =SUM(C48:C49) -> 4408.5097 | D50: =SUM(D48:D49) -> 3584.618 | E50: =SUM(E48:E49) -> 4527.718 | F50: =SUM(F48:F49) -> 6593.212 | G50: =SUM(G48:G49) -> 6473.493 | H50: =SUM(H48:H49) -> 6595.412 | I50: =SUM(I48:I49) -> 6147.466 | J50: =SUM(J48:J49) -> 6785.684 | L50: =SUM(L48:L49) -> 805.029 | M50: =SUM(M48:M49) -> 1216.17 | N50: =SUM(N48:N49) -> 1265.701 | O50: =SUM(O48:O49) -> 1240.818 | P50: =SUM(P48:P49) -> 1368.711 | Q50: =SUM(Q48:Q49) -> 1820.049 | R50: =SUM(R48:R49) -> 1831.042 | S50: =SUM(S48:S49) -> 1573.41 | ... AG50: =SUM(AG48:AG49) -> 2248.144
B51: % growth | D51: =+D50/C50-1 -> -0.18688667 | E51: =+E50/D50-1 -> 0.26309637 | F51: =+F50/E50-1 -> 0.45618875 | G51: =+G50/F50-1 -> -0.018157918 | H51: =+H50/G50-1 -> 0.018833573 | I51: =+I50/H50-1 -> -0.067917819 | P51: =P50/L50-1 -> 0.70020086 | Q51: =Q50/M50-1 -> 0.4965416 | R51: =R50/N50-1 -> 0.44666236 | S51: =S50/O50-1 -> 0.26804253 | T51: =T50/P50-1 -> 0.18805139 | U51: =U50/Q50-1 -> -0.12961629 | V51: =V50/R50-1 -> -0.094838895 | W51: =W50/S50-1 -> 0.020627173 | ... AG51: =AG50/AC50-1 -> 0.43158233
B52: % margin | C52: =+C50/C7 -> 0.71534058 | D52: =+D50/D7 -> 0.69800488 | E52: =+E50/E7 -> 0.66349844 | F52: =+F50/F7 -> 0.69980588 | G52: =+G50/G7 -> 0.74932094 | H52: =+H50/H7 -> 0.74589318 | I52: =+I50/I7 -> 0.71797823 | J52: =+J50/J7 -> 0.7017704 | L52: =+L50/L7 -> 0.57024411 | M52: =+M50/M7 -> 0.69547132 | N52: =+N50/N7 -> 0.71495403 | O52: =+O50/O7 -> 0.65538839 | P52: =+P50/P7 -> 0.66421871 | Q52: =+Q50/Q7 -> 0.75356391 | R52: =+R50/R7 -> 0.75310427 | S52: =+S50/S7 -> 0.62579123 | ... AG52: =+AG50/AG7 -> 0.76215247
B54: Adjustment | C54: =C55-C50 -> -54.509714 | D54: =D55-D50 -> -72.618 | E54: =E55-E50 -> 468.282 | F54: =F55-F50 -> 509.788 | G54: =G55-G50 -> -40.493 | H54: =H55-H50 -> -133.412 | I54: =I55-I50 -> -191.466 | J54: =J55-J50 -> -67.684 | L54: =L55-L50 -> 235.971 | M54: =M55-M50 -> 111.83 | N54: =N55-N50 -> 31.299 | O54: =O55-O50 -> 89.182 | P54: =P55-P50 -> 232.289 | Q54: =Q55-Q50 -> -4.049 | R54: =R55-R50 -> 6.958 | S54: =S55-S50 -> 274.59 | ... AG54: =AG55-AG50 -> -135.144
B55: Adj. EBITDA | C55: 4354 | D55: 3512 | E55: 4996 | F55: 7103 | G55: 6433 | H55: 6462 | I55: 5956 | J55: =SUM(AD55:AG55) -> 6718 | L55: 1041 | M55: 1328 | N55: 1297 | O55: =E55-SUM(L55:N55) -> 1330 | P55: 1601 | Q55: 1816 | R55: 1838 | S55: =F55-SUM(P55:R55) -> 1848 | T55: 1616 | U55: 1505 | V55: 1651 | W55: =G55-SUM(T55:V55) -> 1661 | X55: 1568 | Y55: 1776 | Z55: 1565 | AA55: =H55-SUM(X55:Z55) -> 1553 | AB55: 1511 | AC55: 1556 | AD55: 1467 | AE55: =I55-SUM(AB55:AD55) -> 1422 | AF55: 1716 | AG55: 2113
B56: % growth | D56: =+D55/C55-1 -> -0.19338539 | E56: =+E55/D55-1 -> 0.42255125 | F56: =+F55/E55-1 -> 0.42173739 | G56: =+G55/F55-1 -> -0.094326341 | H56: =+H55/G55-1 -> 0.0045080056 | I56: =+I55/H55-1 -> -0.078303931 | P56: =P55/L55-1 -> 0.53794428 | Q56: =Q55/M55-1 -> 0.36746988 | R56: =R55/N55-1 -> 0.41711642 | S56: =S55/O55-1 -> 0.38947368 | T56: =T55/P55-1 -> 0.0093691443 | U56: =U55/Q55-1 -> -0.17125551 | V56: =V55/R55-1 -> -0.10174102 | W56: =W55/S55-1 -> -0.10119048 | ... AG56: =AG55/AC55-1 -> 0.35796915
B57: % margin | C57: =+C55/C7 -> 0.70649564 | D57: =+D55/D7 -> 0.68386454 | E57: =+E55/E7 -> 0.73212117 | F57: =+F55/F7 -> 0.75391496 | G57: =+G55/G7 -> 0.74463379 | H57: =+H55/H7 -> 0.73080525 | I57: =+I55/I7 -> 0.69561643 | J57: =+J55/J7 -> 0.69477057 | L57: =+L55/L7 -> 0.73739469 | M57: =+M55/M7 -> 0.75942172 | N57: =+N55/N7 -> 0.73263384 | O57: =+O55/O7 -> 0.70249348 | P57: =+P55/P7 -> 0.77694572 | Q57: =+Q55/Q7 -> 0.75188748 | R57: =+R55/R7 -> 0.75596609 | S57: =+S55/S7 -> 0.73500372 | ... AG57: =+AG55/AG7 -> 0.71633675
B59: Capex sales | C59: =-C68/C7 -> 0.19184764 | D59: =-D68/D7 -> 0.23109461 | E59: =-E68/E7 -> 0.24087724 | F59: =-F68/F7 -> 0.19748241 | G59: =-G68/G7 -> 0.27380878 | H59: =-H68/H7 -> 0.335462 | I59: =-I68/I7 -> 0.41927171 | J59: =-J68/J7 -> 0.42376227 | L59: =-L68/L7 -> 0.2922208 | M59: =-M68/M7 -> 0.17394646 | N59: =-N68/N7 -> 0.19780662 | O59: =-O68/O7 -> 0.30468674 | P59: =-P68/P7 -> 0.18716385 | Q59: =-Q68/Q7 -> 0.15912564 | R59: =-R68/R7 -> 0.20775083 | S59: =-S68/S7 -> 0.23285578 | ... AG59: =-AG68/AG7 -> 0.32097209
B60: WC SALES | C60: =C64/C7 -> -0.1790478 | D60: =D64/D7 -> 0.0085428545 | E60: =E64/E7 -> -0.065642664 | F60: =F64/F7 -> -0.091445862 | G60: =G64/G7 -> -0.073521619 | H60: =H64/H7 -> 0.047266204 | I60: =I64/I7 -> -0.027371736 | J60: =J64/J7 -> -0.026870495 | L60: =L64/L7 -> -0.11352337 | M60: =M64/M7 -> -0.031445663 | N60: =N64/N7 -> -0.14642679 | O60: =O64/O7 -> 0.014012896 | P60: =P64/P7 -> -0.089263833 | Q60: =Q64/Q7 -> -0.17649399 | R60: =R64/R7 -> -0.33691327 | S60: =S64/S7 -> 0.22583387 | ... AG60: =AG64/AG7 -> -0.028733816
B62: CASH FLOW | C62: =C3 -> 43830 | D62: =D3 -> 44196 | E62: =E3 -> 44561 | F62: =F3 -> 44926 | G62: =G3 -> 45291 | H62: =H3 -> 45657 | I62: =I3 -> 46022 | J62: =J2 -> LTM | L62: =L3 -> 44286 | M62: =M3 -> 44377 | N62: =N3 -> 44469 | O62: =O3 -> 44561 | P62: =P3 -> 44651 | Q62: =Q3 -> 44742 | R62: =R3 -> 44834 | S62: =S3 -> 44926 | ... AG62: =AG3 -> 46203
B63: Adj. EBITDA | C63: =C55 -> 4354 | D63: =D55 -> 3512 | E63: =E55 -> 4996 | F63: =F55 -> 7103 | G63: =G55 -> 6433 | H63: =H55 -> 6462 | I63: =I55 -> 5956 | J63: =J55 -> 6718 | L63: =L55 -> 1041 | M63: =M55 -> 1328 | N63: =N55 -> 1297 | O63: =O55 -> 1330 | P63: =P55 -> 1601 | Q63: =Q55 -> 1816 | R63: =R55 -> 1838 | S63: =S55 -> 1848 | ... AG63: =AG55 -> 2113
B64: Working Capital | C64: -1103.438 | D64: =3857.325-3813.453 -> 43.872 | E64: =4410.536-4858.482 -> -447.946 | F64: =6255.805-7117.361 -> -861.556 | G64: =6017.558-6652.722 -> -635.164 | H64: =7148.22-6730.278 -> 417.942 | I64: =6073.329-6307.691 -> -234.362 | J64: =SUM(AD64:AG64) -> -259.821 | L64: =873.642-1033.906 -> -160.264 | M64: =2109.509-2324.762-L64 -> -54.989 | N64: =3236.77-3601.268-(L64-M64) -> -259.223 | O64: =E64-SUM(L64:N64) -> 26.53 | P64: =1391.891-1575.831 -> -183.94 | Q64: =2779.249-3389.467-P64 -> -426.278 | R64: =4645.469-5222.277-(P64-Q64) -> -819.146 | S64: =F64-SUM(P64:R64) -> 567.808 | T64: =1717.569-1727.445 -> -9.876 | U64: =2995.144-3259.235-T64 -> -254.215 | V64: =4396.113-4953.03-(T64-U64) -> -801.256 | W64: =G64-SUM(T64:V64) -> 430.183 | X64: =1919.118-1632.493 -> 286.625 | Y64: =3712.444-3439.126-X64 -> -13.307 | Z64: =5783.098-5100.852-(X64-Y64) -> 382.314 | AA64: =H64-SUM(X64:Z64) -> -237.69 | AB64: =(1299674-1557281)/1000 -> -257.607 | AC64: =2971.19-3169.347-AB64 -> 59.45 | AD64: =4629.779-4722.244-(AB64-AC64) -> 224.592 | AE64: =I64-SUM(AB64:AD64) -> -260.797 | AF64: =1616.466-1755.325 -> -138.859 | AG64: =3727.736-3951.352-AF64 -> -84.757
B65: Taxes | D65: -1110.196 | E65: -989.083 | F65: -1611.247 | G65: -1786.615 | H65: -1620.349 | I65: -1621.224 | J65: =SUM(AD65:AG65) -> -1437.421 | L65: -60.83 | M65: =-680.055-L65 -> -619.225 | N65: =-835.951-L65-M65 -> -155.896 | O65: =E65-SUM(L65:N65) -> -153.132 | P65: -169.776 | Q65: =-1117.335-P65 -> -947.559 | R65: =-1347.413-P65-Q65 -> -230.078 | S65: =F65-SUM(P65:R65) -> -263.834 | T65: -270.313 | U65: =-1262.509-T65 -> -992.196 | V65: =-1540.874-T65-U65 -> -278.365 | W65: =G65-SUM(T65:V65) -> -245.741 | X65: -220.659 | Y65: =-921.859-X65 -> -701.2 | Z65: =-1364.339-X65-Y65 -> -442.48 | AA65: =H65-SUM(X65:Z65) -> -256.01 | AB65: -220.573 | AC65: =-1045.778-AB65 -> -825.205 | AD65: =-1436.969-AB65-AC65 -> -391.191 | AE65: =I65-SUM(AB65:AD65) -> -184.255 | AF65: -206.547 | AG65: =-861.975-AF65 -> -655.428
B66: Cash interest paid | C66: =-109.932-53.611 -> -163.543 | D66: =-147.594-10.126 -> -157.72 | E66: =-133.914-9.138 -> -143.052 | F66: =-144.365-4.256 -> -148.621 | G66: -136.604 | H66: -131.498 | I66: -152.793 | J66: =SUM(AD66:AG66) -> -155.727 | L66: =-8.93-2.348 -> -11.278 | M66: =-67.048-4.716-L66 -> -60.486 | N66: =-77.912-6.955-L66-M66 -> -13.103 | O66: =E66-SUM(L66:N66) -> -58.185 | P66: =-7.842-2.153 -> -9.995 | Q66: =-69.376-4.256-P66 -> -63.637 | R66: =-79.206-4.256-P66-Q66 -> -9.83 | S66: =F66-SUM(P66:R66) -> -65.159 | T66: -12.824 | U66: =-70.262-0-T66 -> -57.438 | V66: =-80.349-T66-U66 -> -10.087 | W66: =G66-SUM(T66:V66) -> -56.255 | X66: -11.431 | Y66: =-69.698-0-X66 -> -58.267 | Z66: =-80.167-X66-Y66 -> -10.469 | AA66: =H66-SUM(X66:Z66) -> -51.331 | AB66: -14.256 | AC66: =-74.36-0-AB66 -> -60.104 | AD66: =-90.242-AB66-AC66 -> -15.882 | AE66: =I66-SUM(AB66:AD66) -> -62.551 | AF66: -15.339 | AG66: =-77.294-0-AF66 -> -61.955
B67: Net cash from operations | C67: =SUM(C63:C66) -> 3087.019 | D67: =SUM(D63:D66) -> 2287.956 | E67: =SUM(E63:E66) -> 3415.919 | F67: =SUM(F63:F66) -> 4481.576 | G67: =SUM(G63:G66) -> 3874.617 | H67: =SUM(H63:H66) -> 5128.095 | I67: =SUM(I63:I66) -> 3947.621 | J67: =SUM(J63:J66) -> 4865.031 | L67: =SUM(L63:L66) -> 808.628 | M67: =SUM(M63:M66) -> 593.3 | N67: =SUM(N63:N66) -> 868.778 | O67: =SUM(O63:O66) -> 1145.213 | P67: =SUM(P63:P66) -> 1237.289 | Q67: =SUM(Q63:Q66) -> 378.526 | R67: =SUM(R63:R66) -> 778.946 | S67: =SUM(S63:S66) -> 2086.815 | ... AG67: =SUM(AG63:AG66) -> 1310.86
B68: Net Capex | C68: =-1063.093-119.228 -> -1182.321 | D68: =-1093.14-93.651 -> -1186.791 | E68: =-1512.174-131.574 -> -1643.748 | F68: =-1765.221-95.357 -> -1860.578 | G68: =-2206.914-158.56 -> -2365.474 | H68: =-2853.998-112.258 -> -2966.256 | I68: =-3501.689-88.195 -> -3589.884 | J68: =SUM(AD68:AG68) -> -4097.518 | L68: =-388.059-24.477 -> -412.536 | M68: =-660.988-55.728-L68 -> -304.18 | N68: =-1040.655-26.243-L68-M68 -> -350.182 | O68: =E68-SUM(L68:N68) -> -576.85 | P68: =-365.846-19.83 -> -385.676 | Q68: =-733.461-36.544-P68 -> -384.329 | R68: =-1207.432-67.683-P68-Q68 -> -505.11 | S68: =F68-SUM(P68:R68) -> -585.463 | T68: =-628.915-25.942 -> -654.857 | U68: =-1148.026-80.008-T68 -> -573.177 | V68: =-1662.009-112.683-T68-U68 -> -546.658 | W68: =G68-SUM(T68:V68) -> -590.782 | X68: =-585.957-26.409 -> -612.366 | Y68: =-1231.575-37.859-X68 -> -657.068 | Z68: =-2023.19-92.63-X68-Y68 -> -846.386 | AA68: =H68-SUM(X68:Z68) -> -850.436 | AB68: =(-674606-19303)/1000 -> -693.909 | AC68: =-1566.874-51.95-44.046+48.578-AB68 -> -920.383 | AD68: =-2513.288-65.524-41.889+50.639-AB68-AC68 -> -955.77 | AE68: =I68-SUM(AB68:AD68) -> -1019.822 | AF68: =-1153.947-21.198 -> -1175.145 | AG68: =-2088.446-33.48-AF68 -> -946.781
B69: Purchase of intangible assets | C69: -26.147 | D69: -28.466 | E69: -29.067 | F69: -31.077 | G69: -26.414 | H69: -53.45 | I69: =-91.636 -> -91.636 | J69: =SUM(AD69:AG69) -> -86.305 | L69: -4.137 | M69: =-13.686-L69 -> -9.549 | N69: =-26.243-L69-M69 -> -12.557 | O69: =E69-SUM(L69:N69) -> -2.824 | P69: -8.434 | Q69: =-14.267-P69 -> -5.833 | R69: =-21.313-P69-Q69 -> -7.046 | S69: =F69-SUM(P69:R69) -> -9.764 | T69: -3.638 | U69: =-8.519-T69 -> -4.881 | V69: -15.463 | W69: =G69-SUM(T69:V69) -> -2.432 | X69: -4.267 | Y69: =-9.148-X69 -> -4.881 | Z69: -18.241 | AA69: =H69-SUM(X69:Z69) -> -26.061 | AB69: -20.507 | AC69: =-41.523-AB69 -> -21.016 | AD69: =-64.123-AC69-AB69 -> -22.6 | AE69: =I69-SUM(AB69:AD69) -> -27.513 | AF69: -18.508 | AG69: =-36.192-AF69 -> -17.684
B70: Disposals/ Acquistion, of subsidiaries, businesses | C70: -2713.3 | D70: 0 | E70: -2299.492 | F70: 0 | G70: 0 | H70: 0 | I70: =-382.317-92.689 -> -475.006 | J70: =SUM(AD70:AG70) -> -475.006 | L70: -2364 | M70: =-2364-L70 -> 0 | N70: =-2299.908-L70-M70 -> 64.092 | O70: =E70-SUM(L70:N70) -> 0.416 | P70: 0 | Q70: =0-P70 -> 0 | R70: =0-P70-Q70 -> 0 | S70: =F70-SUM(P70:R70) -> 0 | T70: 0 | U70: =0-T70 -> 0 | V70: =0-T70-U70 -> 0 | W70: =G70-SUM(T70:V70) -> 0 | X70: 0 | Y70: =0-X70 -> 0 | Z70: =0-X70-Y70 -> 0 | AA70: =H70-SUM(X70:Z70) -> 0 | AB70: 0 | AC70: =0-AB70 -> 0 | AD70: =-382.317-AB70-AC70 -> -382.317 | AE70: =I70-SUM(AB70:AD70) -> -92.689 | AF70: 0 | AG70: =0-AF70 -> 0
B71: Free cash flow | C71: =SUM(C67:C70) -> -834.749 | D71: =SUM(D67:D70) -> 1072.699 | E71: =SUM(E67:E70) -> -556.388 | F71: =SUM(F67:F70) -> 2589.921 | G71: =SUM(G67:G70) -> 1482.729 | H71: =SUM(H67:H70) -> 2108.389 | I71: =SUM(I67:I70) -> -208.905 | J71: =SUM(J67:J70) -> 206.202 | L71: =SUM(L67:L70) -> -1972.045 | M71: =SUM(M67:M70) -> 279.571 | N71: =SUM(N67:N70) -> 570.131 | O71: =SUM(O67:O70) -> 565.955 | P71: =SUM(P67:P70) -> 843.179 | Q71: =SUM(Q67:Q70) -> -11.636 | R71: =SUM(R67:R70) -> 266.79 | S71: =SUM(S67:S70) -> 1491.588 | ... AG71: =SUM(AG67:AG70) -> 346.395
B72: Other Investing | C72: =-3343.628-SUM(C68:C70) -> 578.14 | D72: =-1071.612-SUM(D68:D70) -> 143.645 | E72: =-3853.365-SUM(E68:E70) -> 118.942 | F72: =-1679.604-SUM(F68:F70) -> 212.051 | G72: =-2370.704-SUM(G68:G70) -> 21.184 | H72: =-4266.047-SUM(H68:H70) -> -1246.341 | I72: =(-281839+420852-9390-267+19038-34876+10196+21558-584862+5384+20533-673+3887)/1000 -> -410.459 | J72: =SUM(AD72:AG72) -> -574.784 | L72: =-2772.07-SUM(L68:L70) -> 8.603 | M72: =-2975.066-SUM(M68:M70)-SUM(L68:L70)-L72 -> 110.733 | N72: =-3301.244-SUM(N68:N70)-L72-M72-SUM(L68:M70) -> -27.531 | O72: =E72-SUM(L72:N72) -> 27.137 | P72: =-391.031-SUM(P68:P70) -> 3.079 | Q72: =-605.884-SUM(Q68:Q70)-P72-(SUM(P68:P70)) -> 175.309 | R72: =-1096.714-SUM(R68:R70)-P72-Q72-SUM(P68:Q70) -> 21.326 | S72: =F72-SUM(P72:R72) -> 12.337 | T72: =-712.708-SUM(T68:T70) -> -54.213 | U72: =-1436.381-SUM(U68:U70)-T72-(SUM(T68:T70)) -> -145.615 | V72: =-2026.331-SUM(V68:V70)-T72-U72-SUM(T68:U70) -> -27.829 | W72: =G72-SUM(T72:V72) -> 248.841 | X72: =-499.893-SUM(X68:X70) -> 116.74 | Y72: =-2351.596-SUM(Y68:Y70)-X72-(SUM(X68:X70)) -> -1189.754 | Z72: =-3140.311-SUM(Z68:Z70)-X72-Y72-SUM(X68:Y70) -> 75.912 | AA72: =H72-SUM(X72:Z72) -> -249.239 | AB72: =-805.114-SUM(AB68:AB70) -> -90.698 | AC72: =-1609.137-SUM(AC68:AC70)-AB72-(SUM(AB68:AB70)) -> 137.376 | AD72: =-3198.279-SUM(AD68:AD70)-AB72-AC72-SUM(AB68:AC70) -> -228.455 | AE72: =I72-SUM(AB72:AD72) -> -228.682 | AF72: =(50000-5000-173-82-8484+2760+6733-6010+1951+18076)/1000 -> 59.771 | AG72: =((-223556+50000-5000+129-205-99-17521+2761+12434-6010+21182+1952+28208+18078)/1000)-AF72 -> -177.418
B73: Equity Issuance | C73: 0 | D73: 0 | E73: 0 | F73: 0 | G73: 0 | H73: 0 | I73: 0 | J73: =SUM(AD73:AG73) -> 0.225 | L73: 0 | M73: =0-L73 -> 0 | N73: =0-L73-M73 -> 0 | O73: =E73-SUM(L73:N73) -> 0 | P73: 0 | Q73: =0-P73 -> 0 | R73: =0-P73-Q73 -> 0 | S73: =F73-SUM(P73:R73) -> 0 | T73: 0 | U73: =0-T73 -> 0 | V73: =0-T73-U73 -> 0 | W73: =G73-SUM(T73:V73) -> 0 | X73: 0 | Y73: =0-X73 -> 0 | Z73: =0-X73-Y73 -> 0 | AA73: =H73-SUM(X73:Z73) -> 0 | AB73: 0 | AC73: =0-AB73 -> 0 | AD73: =0-AB73-AC73 -> 0 | AE73: =I73-SUM(AB73:AD73) -> 0 | AF73: 0.225 | AG73: =0.225-AF73 -> 0
B74: Dividends | C74: -697.76 | D74: -671 | E74: -605.341 | F74: -819.492 | G74: -1098.772 | H74: -1080.024 | I74: -1108.407 | J74: =SUM(AD74:AG74) -> -1087.455 | L74: 0 | M74: =-364.153-L74 -> -364.153 | N74: =-605.341-L74-M74 -> -241.188 | O74: =E74-SUM(L74:N74) -> 0 | P74: 0 | Q74: =-361.317-P74 -> -361.317 | R74: =-819.492-P74-Q74 -> -458.175 | S74: =F74-SUM(P74:R74) -> 0 | T74: 0 | U74: =-603.716-T74 -> -603.716 | V74: =-1098.772-T74-U74 -> -495.056 | W74: =G74-SUM(T74:V74) -> 0 | X74: 0 | Y74: =-585.644-X74 -> -585.644 | Z74: =-1080.024-X74-Y74 -> -494.38 | AA74: =H74-SUM(X74:Z74) -> 0 | AB74: 0 | AC74: =-603.017-AB74 -> -603.017 | AD74: =-1108.407-AB74-AC74 -> -505.39 | AE74: =I74-SUM(AB74:AD74) -> 0 | AF74: 0 | AG74: =-582.065-AF74 -> -582.065
B75: Net Change in debt | C75: =259.581-258.826-418.199+1130.045-7.785+600-990.846 -> 313.97 | D75: =-730.443+850-96.362-30.852 -> -7.657 | E75: =200-200+179.96-128.482 -> 51.478 | F75: =-1025.126+358.644-0.563-177.008-142.59 -> -986.643 | G75: =-71.46+44.55-1.058-261.489 -> -289.457 | H75: -317.712 | I75: -396.949 | J75: =SUM(AD75:AG75) -> 30.133 | L75: -28.138 | M75: =200-60.9-L75 -> 167.238 | N75: =-88.169-L75-M75 -> -227.269 | O75: =E75-SUM(L75:N75) -> 139.647 | P75: -36.036 | Q75: =-425.126+358.644-86.432-142.59-P75 -> -259.468 | R75: =-425.126+358.644-123.026-P75-Q75 -> 105.996 | S75: =F75-SUM(P75:R75) -> -797.135 | T75: =-55.593 -> -55.593 | U75: =-71.46+44.55-134.514-0-T75 -> -105.831 | V75: =-71.46+44.55-199.426-T75-U75 -> -64.912 | W75: =G75-SUM(T75:V75) -> -63.121 | X75: =-67.976 -> -67.976 | Y75: =-134.445-0.974-X75 -> -67.443 | Z75: =-219.417-X75-Y75 -> -83.998 | AA75: =H75-SUM(X75:Z75) -> -98.295 | AB75: -84.444 | AC75: =-181.303-AB75 -> -96.859 | AD75: =-285.56-AB75-AC75 -> -104.257 | AE75: =I75-SUM(AB75:AD75) -> -111.389 | AF75: -110.848 | AG75: =-44.55+511.355-221.026-AF75 -> 356.627
B76: Other financing activities | C76: =-553.593-SUM(C73:C75)-C66 -> -6.26 | D76: =-846.322-SUM(D73:D75)-D66 -> -9.945 | E76: =-695.359-SUM(E73:E75)-E66 -> 1.556 | F76: =-1999.68-SUM(F73:F75)-F66 -> -44.924 | G76: 3.496 | H76: 4.736 | I76: 0 | J76: =SUM(AD76:AG76) -> -0.455 | L76: =-39.416-SUM(L73:L75)-L66 -> 0 | M76: =-296.817-SUM(M73:M75)-M66-SUM(L73:L76)-L66 -> 0 | N76: =-778.377-SUM(N73:N75)-L76-M76-N66-SUM(L73:M75)-L66-M66 -> 0 | O76: =E76-SUM(L76:N76) -> 1.556 | P76: =-46.031-SUM(P73:P75)-P66 -> 0 | Q76: =-775.94-SUM(Q73:Q75)-Q66-SUM(P73:P76)-P66 -> -45.487 | R76: =-1280.539-SUM(R73:R75)-P76-Q76-R66-SUM(P73:Q75)-P66-Q66 -> -142.59 | S76: =F76-SUM(P76:R76) -> 143.153 | T76: 0 | U76: =-832.88-SUM(U73:U75)-U66-SUM(T73:T76)-T66 -> 2.522 | V76: =-1402.937-SUM(V73:V75)-T76-U76-V66-SUM(T73:U75)-T66-U66 -> -0.002 | W76: =G76-SUM(T76:V76) -> 0.976 | X76: 2.742 | Y76: =0-X76 -> -2.742 | Z76: =-1375.267-SUM(Z73:Z75)-X76-Y76-Z66-SUM(X73:Y75)-X66-Y66 -> 4.341 | AA76: =H76-SUM(X76:Z76) -> 0.395 | AB76: 0 | AC76: =0-AB76 -> 0 | AD76: =-1484.209-SUM(AD73:AD75)-AB76-AC76-AD66-SUM(AB73:AC75)-AB66-AC66 -> -2.4158453e-13 | AE76: =I76-SUM(AB76:AD76) -> 2.4158453e-13 | AF76: 0 | AG76: =-0.455-AF76 -> -0.455
B77: Cash flow after financing activities | C77: =SUM(C71:C76) -> -646.659 | D77: =SUM(D71:D76) -> 527.742 | E77: =SUM(E71:E76) -> -989.753 | F77: =SUM(F71:F76) -> 950.913 | G77: =SUM(G71:G76) -> 119.18 | H77: =SUM(H71:H76) -> -530.952 | I77: =SUM(I71:I76) -> -2124.72 | J77: =SUM(J71:J76) -> -1426.134 | L77: =SUM(L71:L76) -> -1991.58 | M77: =SUM(M71:M76) -> 193.389 | N77: =SUM(N71:N76) -> 74.143 | O77: =SUM(O71:O76) -> 734.295 | P77: =SUM(P71:P76) -> 810.222 | Q77: =SUM(Q71:Q76) -> -502.599 | R77: =SUM(R71:R76) -> -206.653 | S77: =SUM(S71:S76) -> 849.943 | ... AG77: =SUM(AG71:AG76) -> -56.916
B78: Balancing figure | C78: =-377.615-C77 -> 269.044 | D78: =853.566-D77 -> 325.824 | E78: =-1120.416-E77 -> -130.663 | F78: =992.918-F77 -> 42.005 | G78: =469.868-G77 -> 350.688 | H78: =-68.976-H77 -> 461.976 | I78: =-1653.04-I77 -> 471.68 | J78: =SUM(AD78:AG78) -> 447.371 | L78: =-1994.853-L77 -> -3.273 | M78: =-1837.385-M77-L77-L78 -> -35.921 | N78: =-1673.055-N77-M77-L77-L78-M78 -> 90.187 | O78: =E78-SUM(L78:N78) -> -181.656 | P78: =786.674-P77 -> -23.548 | Q78: =284.824-Q77-P77-P78 -> 0.749 | R78: =930.651-R77-Q77-P77-P78-Q78 -> 852.48 | S78: =F78-SUM(P78:R78) -> -787.676 | T78: =691.255-T77 -> 136.569 | U78: =-469.702-U77-T77-T78 -> 68.59 | V78: =-480.227-V77-U77-T77-T78-U78 -> 578.103 | W78: =G78-SUM(T78:V78) -> -432.574 | X78: =1164.205-X77 -> 106.797 | Y78: =-236.409-Y77-X77-X78 -> 103.692 | Z78: =48.454-Z77-Y77-X77-X78-Y78 -> 153.25 | AA78: =H78-SUM(X78:Z78) -> 98.237 | AB78: =205.551-AB77 -> 76.545 | AC78: =-472.058-AC77-AB77-AB78 -> 96.149 | AD78: =-1392.901-AD77-AC77-AB77-AB78-AC78 -> -6.573 | AE78: =I78-SUM(AB78:AD78) -> 305.559 | AF78: =161.651-AF77 -> 50.901 | AG78: =202.219-AG77-AF77-AF78 -> 97.484
B79: FX | C79: 20.417 | D79: 27.54 | E79: -24.398 | F79: -12.887 | G79: 9.871 | H79: -11.82 | I79: 28.669 | J79: =SUM(AD79:AG79) -> -6.033 | L79: -13.721 | M79: =-16.64-L79 -> -2.919 | N79: =-30.851-L79-M79 -> -14.211 | O79: =E79-SUM(L79:N79) -> 6.453 | P79: 0.139 | Q79: =-37.624-P79 -> -37.763 | R79: =-53.784-P79-Q79 -> -16.16 | S79: =F79-SUM(P79:R79) -> 40.897 | T79: 11.116 | U79: =-4.887-T79 -> -16.003 | V79: =-22.825-T79-U79 -> -17.938 | W79: =G79-SUM(T79:V79) -> 32.696 | X79: -28.841 | Y79: =-31.329-X79 -> -2.488 | Z79: =2.231-X79-Y79 -> 33.56 | AA79: =H79-SUM(X79:Z79) -> -14.051 | AB79: -0.048 | AC79: =16.78-AB79 -> 16.828 | AD79: =20.282-AB79-AC79 -> 3.502 | AE79: =I79-SUM(AB79:AD79) -> 8.387 | AF79: -15.085 | AG79: =-17.922-AF79 -> -2.837
B80: Net change in cash | C80: =SUM(C77:C79) -> -357.198 | D80: =SUM(D77:D79) -> 881.106 | E80: =SUM(E77:E79) -> -1144.814 | F80: =SUM(F77:F79) -> 980.031 | G80: =SUM(G77:G79) -> 479.739 | H80: =SUM(H77:H79) -> -80.796 | I80: =SUM(I77:I79) -> -1624.371 | J80: =SUM(J77:J79) -> -984.796 | L80: =SUM(L77:L79) -> -2008.574 | M80: =SUM(M77:M79) -> 154.549 | N80: =SUM(N77:N79) -> 150.119 | O80: =SUM(O77:O79) -> 559.092 | P80: =SUM(P77:P79) -> 786.813 | Q80: =SUM(Q77:Q79) -> -539.613 | R80: =SUM(R77:R79) -> 629.667 | S80: =SUM(S77:S79) -> 103.164 | ... AG80: =SUM(AG77:AG79) -> 37.731
B81: Cash and cash equivalents | C81: =3180.095+C80 -> 2822.897 | D81: =C81+D80 -> 3704.003 | E81: =D81+E80 -> 2559.189 | F81: =E81+F80 -> 3539.22 | G81: =F81+G80 -> 4018.959 | H81: =G81+H80 -> 3938.163 | I81: =H81+I80 -> 2313.792 | J81: =AC81+J80 -> 2498.089 | L81: =3704.003+L80 -> 1695.429 | M81: =L81+M80 -> 1849.978 | N81: =M81+N80 -> 2000.097 | O81: =N81+O80 -> 2559.189 | P81: =O81+P80 -> 3346.002 | Q81: =P81+Q80 -> 2806.389 | R81: =Q81+R80 -> 3436.056 | S81: =R81+S80 -> 3539.22 | T81: =S81+T80 -> 4241.591 | ... AG81: =AF81+AG80 -> 2498.089
B83: check 1 | C83: =+C81-C119 -> 0 | D83: =+D81-D119 -> 0 | E83: =+E81-E119 -> 0 | F83: =+F81-F119 -> 0 | G83: =+G81-G119 -> 0 | H83: =+H81-H119 -> 0 | I83: =+I81-I119 -> 0 | J83: =+J81-J119 -> 0 | L83: =+L81-L119 -> 0 | M83: =+M81-M119 -> 0 | N83: =+N81-N119 -> 0 | O83: =+O81-O119 -> 0 | P83: =+P81-P119 -> 0 | Q83: =+Q81-Q119 -> 0 | R83: =+R81-R119 -> 0 | S83: =+S81-S119 -> 0 | ... AG83: =+AG81-AG119 -> 0
B84: check 2 | C84: =3519.606-(C67+C78)+C66 -> 0 | D84: =2771.5-(D67+D78)+D66 -> 0 | E84: =3428.308-(E67+E78)+E66 -> 5.968559e-13 | F84: =4672.202-(F67+F78)+F66 -> 0 | G84: =4361.909-(G67+G78)+G66 -> -6.5369932e-13 | H84: =5721.569-(H67+H78)+H66 -> 5.1159077e-13 | I84: =4572.094-(I67+I78)+I66 -> 5.6843419e-13 | L84: =816.633-(L67+L78)+L66 -> -3.1974423e-13 | M84: =1434.498-(M67+M78)-L67-L78+M66+L66 -> -3.2684966e-13 | N84: =2406.566-(N67+N78)-M67-M78-L67-L78+L66+M66+N66 -> -2.8421709e-14 | P84: =1223.736-(P67+P78)+P66 -> 1.1901591e-13 | Q84: =1666.648-(Q67+Q78)-P67-P78+Q66+P66 -> -1.7230661e-13 | R84: =3307.904-(R67+R78)-Q67-Q78-P67-P78+P66+Q66+R66 -> -1.4210855e-14 | T84: =1472.38-(T67+T78)+T66 -> 6.9277917e-14 | U84: =1799.559-(U67+U78)-T67-T78+U66+T66 -> -1.7230661e-13 | V84: =2949.041-(V67+V78)-U67-U78-T67-T78+T66+U66+V66 -> 2.7000624e-13 | X84: =1740.763-(X67+X78)+X66 -> -1.8651747e-13 | Y84: =2900.633-(Y67+Y78)-X67-X78+Y66+X66 -> -5.315 | Z84: =4564.032-(Z67+Z78)-Y67-Y78-X67-X78+X66+Y66+Z66 -> -3.126388e-13 | AB84: =1109.365-(AB67+AB78)+AB66 -> -1.4210855e-13 | AC84: =1995.759-(AC67+AC78)-AB67-AB78+AC66+AB66 -> -4.2632564e-14 | AD84: =3289.587-(AD67+AD78)-AC67-AC78-AB67-AB78+AB66+AC66+AD66 -> 1.4210855e-14 | AF84: =1421.495-(AF67+AF78)+AF66 -> -5.8619776e-14 | AG84: =2891.794-(AG67+AG78)-AF67-AF78+AG66+AF66 -> -2.0072832e-13
B86: LTM | C86: =C3 -> 43830 | D86: =D3 -> 44196 | E86: =E3 -> 44561 | F86: =F3 -> 44926 | G86: =G3 -> 45291 | H86: =H3 -> 45657 | I86: =I3 -> 46022 | J86: =J2 -> LTM | L86: =L3 -> 44286 | M86: =M3 -> 44377 | N86: =N3 -> 44469 | O86: =O3 -> 44561 | P86: =P3 -> 44651 | Q86: =Q3 -> 44742 | R86: =R3 -> 44834 | S86: =S3 -> 44926 | ... AG86: =AG3 -> 46203
B87: =B7 -> Total Revenues | C87: =C7 -> 6162.8123 | D87: =D7 -> 5135.52 | E87: =E7 -> 6824.007 | F87: =F7 -> 9421.487 | G87: =G7 -> 8639.146 | H87: =H7 -> 8842.301 | I87: =I7 -> 8562.19 | J87: =J7 -> 9669.379 | O87: =SUM(L7:O7) -> 6824.007 | P87: =SUM(M7:P7) -> 7472.913 | Q87: =SUM(N7:Q7) -> 8139.469 | R87: =SUM(O7:R7) -> 8800.47 | S87: =SUM(P7:S7) -> 9421.487 | T87: =SUM(Q7:T7) -> 9588.083 | U87: =SUM(R7:U7) -> 9130.299 | V87: =SUM(S7:V7) -> 8922.381 | ... AG87: =SUM(AD7:AG7) -> 9669.379
B88: Operating profit | C88: =C24 -> 2382.4541 | D88: =D24 -> 1498.535 | E88: =E24 -> 2325.654 | F88: =F24 -> 4230.077 | G88: =G24 -> 4138.782 | H88: =H24 -> 3906.471 | I88: =I24 -> 3250.422 | J88: =J24 -> 3906.055 | O88: =SUM(L24:O24) -> 2325.654 | P88: =SUM(M24:P24) -> 2919.236 | Q88: =SUM(N24:Q24) -> 3587.499 | R88: =SUM(O24:R24) -> 4127.549 | S88: =SUM(P24:S24) -> 4230.077 | T88: =SUM(Q24:T24) -> 4512.6 | U88: =SUM(R24:U24) -> 4282.306 | V88: =SUM(S24:V24) -> 4110.32 | ... AG88: =SUM(AD24:AG24) -> 3906.055
B89: EBITDA | C89: =+C50 -> 4408.5097 | D89: =+D50 -> 3584.618 | E89: =+E50 -> 4527.718 | F89: =+F50 -> 6593.212 | G89: =+G50 -> 6473.493 | H89: =+H50 -> 6595.412 | I89: =+I50 -> 6147.466 | J89: =+J50 -> 6785.684 | O89: =SUM(L50:O50) -> 4527.718 | P89: =SUM(M50:P50) -> 5091.4 | Q89: =SUM(N50:Q50) -> 5695.279 | R89: =SUM(O50:R50) -> 6260.62 | S89: =SUM(P50:S50) -> 6593.212 | T89: =SUM(Q50:T50) -> 6850.6 | U89: =SUM(R50:U50) -> 6614.692 | V89: =SUM(S50:V50) -> 6441.038 | ... AG89: =SUM(AD50:AG50) -> 6785.684
B90: Adjusted EBITDA | C90: =+C55 -> 4354 | D90: =+D55 -> 3512 | E90: =+E55 -> 4996 | F90: =+F55 -> 7103 | G90: =+G55 -> 6433 | H90: =+H55 -> 6462 | I90: =+I55 -> 5956 | J90: =+J55 -> 6718 | O90: =SUM(L55:O55) -> 4996 | P90: =SUM(M55:P55) -> 5556 | Q90: =SUM(N55:Q55) -> 6044 | R90: =SUM(O55:R55) -> 6585 | S90: =SUM(P55:S55) -> 7103 | T90: =SUM(Q55:T55) -> 7118 | U90: =SUM(R55:U55) -> 6807 | V90: =SUM(S55:V55) -> 6620 | ... AG90: =SUM(AD55:AG55) -> 6718
B91: Cash interest paid | C91: =-C66 -> 163.543 | D91: =-D66 -> 157.72 | E91: =-E66 -> 143.052 | F91: =-F66 -> 148.621 | G91: =-G66 -> 136.604 | H91: =-H66 -> 131.498 | I91: =-I66 -> 152.793 | J91: =-J66 -> 155.727 | O91: =-SUM(L66:O66) -> 143.052 | P91: =-SUM(M66:P66) -> 141.769 | Q91: =-SUM(N66:Q66) -> 144.92 | R91: =-SUM(O66:R66) -> 141.647 | S91: =-SUM(P66:S66) -> 148.621 | T91: =-SUM(Q66:T66) -> 151.45 | U91: =-SUM(R66:U66) -> 145.251 | V91: =-SUM(S66:V66) -> 145.508 | ... AG91: =-SUM(AD66:AG66) -> 155.727
B92: Net Income | C92: =+C31 -> 1569.064 | D92: =+D31 -> 719.544 | E92: =+E31 -> 1210.538 | F92: =+F31 -> 1998.58 | G92: =+G31 -> 2207.777 | H92: =+H31 -> 2226.918 | I92: =+I31 -> 1829.944 | J92: =+J31 -> 2143.856 | O92: =SUM(L31:O31) -> 1210.538 | P92: =SUM(M31:P31) -> 1152.548 | Q92: =SUM(N31:Q31) -> 1530.641 | R92: =SUM(O31:R31) -> 1902.184 | S92: =SUM(P31:S31) -> 1998.58 | T92: =SUM(Q31:T31) -> 2249.797 | U92: =SUM(R31:U31) -> 2260.419 | V92: =SUM(S31:V31) -> 2110.869 | ... AG92: =SUM(AD31:AG31) -> 2143.856
B93: Capex | C93: =-C68 -> 1182.321 | D93: =-D68 -> 1186.791 | E93: =-E68 -> 1643.748 | F93: =-F68 -> 1860.578 | G93: =-G68 -> 2365.474 | H93: =-H68 -> 2966.256 | I93: =-I68 -> 3589.884 | J93: =-J68 -> 4097.518 | O93: =-SUM(L68:O68) -> 1643.748 | P93: =-SUM(M68:P68) -> 1616.888 | Q93: =-SUM(N68:Q68) -> 1697.037 | R93: =-SUM(O68:R68) -> 1851.965 | S93: =-SUM(P68:S68) -> 1860.578 | T93: =-SUM(Q68:T68) -> 2129.759 | U93: =-SUM(R68:U68) -> 2318.607 | V93: =-SUM(S68:V68) -> 2360.155 | ... AG93: =-SUM(AD68:AG68) -> 4097.518
B94: Free cash flow | C94: =+C71 -> -834.749 | D94: =+D71 -> 1072.699 | E94: =+E71 -> -556.388 | F94: =+F71 -> 2589.921 | G94: =+G71 -> 1482.729 | H94: =+H71 -> 2108.389 | I94: =+I71 -> -208.905 | J94: =+J71 -> 206.202 | O94: =SUM(L71:O71) -> -556.388 | P94: =SUM(M71:P71) -> 2258.836 | Q94: =SUM(N71:Q71) -> 1967.629 | R94: =SUM(O71:R71) -> 1664.288 | S94: =SUM(P71:S71) -> 2589.921 | T94: =SUM(Q71:T71) -> 2411.234 | U94: =SUM(R71:U71) -> 2045.963 | V94: =SUM(S71:V71) -> 1778.344 | ... AG94: =SUM(AD71:AG71) -> 206.202
B96: BALANCE SHEET | C96: =C3 -> 43830 | D96: =D3 -> 44196 | E96: =E3 -> 44561 | F96: =F3 -> 44926 | G96: =G3 -> 45291 | H96: =H3 -> 45657 | I96: =I3 -> 46022 | J96: =J2 -> LTM | L96: =L3 -> 44286 | M96: =M3 -> 44377 | N96: =N3 -> 44469 | O96: =O3 -> 44561 | P96: =P3 -> 44651 | Q96: =Q3 -> 44742 | R96: =R3 -> 44834 | S96: =S3 -> 44926 | ... AG96: =AG3 -> 46203
B98: Tangible fixed assets | C98: 10661.984 | D98: =9837.537+482.778 -> 10320.315 | E98: =11379.664+519.711 -> 11899.375 | F98: =11880.375+974.706 -> 12855.081 | G98: =12864.663+838.921 -> 13703.584 | H98: =14431.173+891.709 -> 15322.882 | I98: =16194.084+1046.501 -> 17240.585 | J98: =AG98 -> 18047.446 | L98: =11998.782+477.84 -> 12476.622 | M98: =11723.345+525.411 -> 12248.756 | N98: =11610.497+519.113 -> 12129.61 | O98: =E98 -> 11899.375 | P98: =11204.081+534.414 -> 11738.495 | Q98: =11697.849+827.258 -> 12525.107 | R98: =11761.839+911.52 -> 12673.359 | S98: =F98 -> 12855.081 | T98: =12106.507+966.203 -> 13072.71 | U98: =12344.356+882.998 -> 13227.354 | V98: =12339.612+845.687 -> 13185.299 | W98: =G98 -> 13703.584 | X98: =12889.681+892.727 -> 13782.408 | Y98: =13493.71+835.021 -> 14328.731 | Z98: =13638.915+856.946 -> 14495.861 | AA98: =H98 -> 15322.882 | AB98: =(14660724+1004527)/1000 -> 15665.251 | AC98: =15217.344+949.808 -> 16167.152 | AD98: =15838.256+1029.767 -> 16868.023 | AE98: =I98 -> 17240.585 | AF98: =(16652397+1010047)/1000 -> 17662.444 | AG98: =17031.674+1015.772 -> 18047.446
B99: Inventory | C99: 330.337 | D99: 338.105 | E99: 420.969 | F99: 553.046 | G99: 611.11 | H99: 669.624 | I99: 657.04 | J99: =AG99 -> 570.768 | L99: 385.368 | M99: 422.12 | N99: 424.666 | O99: =E99 -> 420.969 | P99: 428.483 | Q99: 448.927 | R99: 494.714 | S99: =F99 -> 553.046 | T99: 567.45 | U99: 625.195 | V99: 619.54 | W99: =G99 -> 611.11 | X99: 605.339 | Y99: 625.019 | Z99: 619.607 | AA99: =H99 -> 669.624 | AB99: 646.956 | AC99: 638.857 | AD99: 686.03 | AE99: =I99 -> 657.04 | AF99: 589.624 | AG99: 570.768
B100: Trade accounts receivable | C100: 983.201 | D100: 790.763 | E100: 1000.303 | F100: 1219.995 | G100: 1818.678 | H100: 1273.117 | I100: 1408.769 | J100: =AG100 -> 1761.367 | L100: 794.62 | M100: 853.355 | N100: 855.283 | O100: =E100 -> 1000.303 | P100: 1040.926 | Q100: 1073.142 | R100: 1014.973 | S100: =F100 -> 1219.995 | T100: 962.4 | U100: 894.503 | V100: 1353.489 | W100: =G100 -> 1818.678 | X100: 1424.063 | Y100: 1513.31 | Z100: 1080.364 | AA100: =H100 -> 1273.117 | AB100: 1224.086 | AC100: 1237.587 | AD100: 1223.173 | AE100: =I100 -> 1408.769 | AF100: 1524.287 | AG100: 1761.367
B101: Trade accounts payable | C101: 888.925 | D101: 893.694 | E101: 1096.946 | F101: 1531.737 | G101: 1443.807 | H101: 1797.389 | I101: 2118.841 | J101: =AG101 -> 2130.945 | L101: 863.106 | M101: 917.902 | N101: 977.05 | O101: =E101 -> 1096.946 | P101: 1049.566 | Q101: 1168.519 | R101: 1338.122 | S101: =F101 -> 1531.737 | T101: 1291.944 | U101: 1237.12 | V101: 1372.069 | W101: =G101 -> 1443.807 | X101: 1405.391 | Y101: 1653.37 | Z101: 1682.974 | AA101: =H101 -> 1797.389 | AB101: 1677.098 | AC101: 1783.787 | AD101: 2005.939 | AE101: =I101 -> 2118.841 | AF101: 1900.307 | AG101: 2130.945
B102: Net working capital | C102: =+C99+C100-C101 -> 424.613 | D102: =+D99+D100-D101 -> 235.174 | E102: =+E99+E100-E101 -> 324.326 | F102: =+F99+F100-F101 -> 241.304 | G102: =+G99+G100-G101 -> 985.981 | H102: =+H99+H100-H101 -> 145.352 | I102: =+I99+I100-I101 -> -53.032 | J102: =+J99+J100-J101 -> 201.19 | L102: =+L99+L100-L101 -> 316.882 | M102: =+M99+M100-M101 -> 357.573 | N102: =+N99+N100-N101 -> 302.899 | O102: =+O99+O100-O101 -> 324.326 | P102: =+P99+P100-P101 -> 419.843 | Q102: =+Q99+Q100-Q101 -> 353.55 | R102: =+R99+R100-R101 -> 171.565 | S102: =+S99+S100-S101 -> 241.304 | ... AG102: =+AG99+AG100-AG101 -> 201.19
B103: % of revenues | C103: =+C102/C87 -> 0.068899226 | D103: =+D102/D87 -> 0.04579361 | E103: =+E102/E87 -> 0.047527208 | F103: =+F102/F87 -> 0.025612093 | G103: =+G102/G87 -> 0.11412945 | H103: =+H102/H87 -> 0.016438255 | I103: =+I102/I87 -> -0.0061937425 | J103: =+J102/J87 -> 0.02080692 | O103: =+O102/O87 -> 0.047527208 | P103: =+P102/P87 -> 0.056181973 | Q103: =+Q102/Q87 -> 0.043436494 | R103: =+R102/R87 -> 0.019494982 | S103: =+S102/S87 -> 0.025612093 | T103: =+T102/T87 -> 0.024812676 | U103: =+U102/U87 -> 0.030949479 | V103: =+V102/V87 -> 0.067354219 | ... AG103: =+AG102/AG87 -> 0.02080692
B105: Debt Breakdown
B106: Short-term debt | C106: 0 | D106: 0 | E106: 0 | F106: 0 | G106: 0 | H106: 0 | I106: =668.872-I111 -> 236.872 | J106: =AG106 -> 830.109 | L106: 0 | M106: 0 | N106: 0 | O106: =E106 -> 0 | P106: 0 | Q106: 0 | R106: 0 | S106: =F106 -> 0 | T106: 0 | U106: 0 | V106: 0 | W106: =G106 -> 0 | X106: 0 | Y106: 0 | Z106: 0 | AA106: =H106 -> 0 | AB106: 0 | AC106: =460.848-415 -> 45.848 | AD106: =464.722-AD111 -> 46.722 | AE106: =I106 -> 236.872 | AF106: =661.105-AF111 -> 228.105 | AG106: =1240.109-AG111 -> 830.109
B107: Long-term debt | C107: =2704.746+593.261 -> 3298.007 | D107: =2830.375+594.659 -> 3425.034 | E107: =2475.802+596.057 -> 3071.859 | F107: 2809.26 | G107: 2785.242 | H107: 2795.37 | I107: 2631.133 | J107: =AG107 -> 2449.44 | L107: =2794.842+595.004 -> 3389.846 | M107: =2309.243+595.352 -> 2904.595 | N107: =2290.566+595.704 -> 2886.27 | O107: =E107 -> 3071.859 | P107: =2478.666+596.402 -> 3075.068 | Q107: =2789.659+596.752 -> 3386.411 | R107: =2733.314+597.105 -> 3330.419 | S107: =F107 -> 2809.26 | T107: 2821.794 | U107: 2748.424 | V107: 2726.732 | W107: =G107 -> 2785.242 | X107: 2730.74 | Y107: 2722.852 | Z107: 2842.123 | AA107: =H107 -> 2795.37 | AB107: 2798.013 | AC107: 2791.225 | AD107: 2799 | AE107: =I107 -> 2631.133 | AF107: 2603.826 | AG107: 2449.44
B108: Total Debt | C108: =SUM(C106:C107) -> 3298.007 | D108: =SUM(D106:D107) -> 3425.034 | E108: =SUM(E106:E107) -> 3071.859 | F108: =SUM(F106:F107) -> 2809.26 | G108: =SUM(G106:G107) -> 2785.242 | H108: =SUM(H106:H107) -> 2795.37 | I108: =SUM(I106:I107) -> 2868.005 | J108: =SUM(J106:J107) -> 3279.549 | L108: =SUM(L106:L107) -> 3389.846 | M108: =SUM(M106:M107) -> 2904.595 | N108: =SUM(N106:N107) -> 2886.27 | O108: =SUM(O106:O107) -> 3071.859 | P108: =SUM(P106:P107) -> 3075.068 | Q108: =SUM(Q106:Q107) -> 3386.411 | R108: =SUM(R106:R107) -> 3330.419 | S108: =SUM(S106:S107) -> 2809.26 | ... AG108: =SUM(AG106:AG107) -> 3279.549
B110: Lease Obligations
B111: Short-term | C111: 18.282 | D111: 135.475 | E111: 633.346 | F111: 303.193 | G111: 280.86 | H111: 389.966 | I111: 432 | J111: =AG111 -> 410 | L111: 151.213 | M111: 638.694 | N111: 623.823 | O111: =E111 -> 633.346 | P111: 633.665 | Q111: 216.904 | R111: 258.951 | S111: =F111 -> 303.193 | T111: 325.938 | U111: 272.227 | V111: 253.392 | W111: =G111 -> 280.86 | X111: 339.558 | Y111: 339.047 | Z111: 373.024 | AA111: =H111 -> 389.966 | AB111: 416.815 | AC111: 415 | AD111: 418 | AE111: =I111 -> 432 | AF111: 433 | AG111: 410
B112: Long-term | C112: 125.413 | D112: 371.552 | E112: 388.51 | F112: 720.569 | G112: 587.524 | H112: 575.845 | I112: 714.042 | J112: =AG112 -> 663.788 | L112: 353.681 | M112: 387.729 | N112: 377.518 | O112: =E112 -> 388.51 | P112: 386.102 | Q112: 639.728 | R112: 684.341 | S112: =F112 -> 720.569 | T112: 701.389 | U112: 640.218 | V112: 621.09 | W112: =G112 -> 587.524 | X112: 615.086 | Y112: 571.562 | Z112: 564.671 | AA112: =H112 -> 575.845 | AB112: 667.69 | AC112: =630.663 -> 630.663 | AD112: 711.623 | AE112: =I112 -> 714.042 | AF112: 678.113 | AG112: 663.788
B113: Total Lease | C113: =SUM(C111:C112) -> 143.695 | D113: =SUM(D111:D112) -> 507.027 | E113: =SUM(E111:E112) -> 1021.856 | F113: =SUM(F111:F112) -> 1023.762 | G113: =SUM(G111:G112) -> 868.384 | H113: =SUM(H111:H112) -> 965.811 | I113: =SUM(I111:I112) -> 1146.042 | J113: =SUM(J111:J112) -> 1073.788 | L113: =SUM(L111:L112) -> 504.894 | M113: =SUM(M111:M112) -> 1026.423 | N113: =SUM(N111:N112) -> 1001.341 | O113: =SUM(O111:O112) -> 1021.856 | P113: =SUM(P111:P112) -> 1019.767 | Q113: =SUM(Q111:Q112) -> 856.632 | R113: =SUM(R111:R112) -> 943.292 | S113: =SUM(S111:S112) -> 1023.762 | ... AG113: =SUM(AG111:AG112) -> 1073.788
...

Sheet KPIs
B2: PTT EP | C2: Annual | D2: Annual | E2: Annual | F2: Annual | G2: Annual | H2: Annual | I2: Annual | J2: LTM | L2: Quarters | M2: Quarters | N2: Quarters | O2: Quarters | P2: Quarters | Q2: Quarters | R2: Quarters | S2: Quarters | T2: Quarters | U2: Quarters | V2: Quarters | W2: Quarters | X2: Quarters | Y2: Quarters | Z2: Quarters | AA2: Quarters | AB2: Quarters | AC2: Quarters | AD2: Quarters | AE2: Quarters | AF2: Quarters | AG2: Quarters
B3: (USD million) | C3: 43830 | D3: 44196 | E3: 44561 | F3: 44926 | G3: 45291 | H3: 45657 | I3: 46022 | J3: =AG3 -> 46203 | L3: 44286 | M3: 44377 | N3: 44469 | O3: 44561 | P3: 44651 | Q3: 44742 | R3: 44834 | S3: 44926 | T3: 45016 | U3: 45107 | V3: 45199 | W3: 45291 | X3: 45382 | Y3: 45473 | Z3: 45565 | AA3: 45657 | AB3: 45747 | AC3: 45838 | AD3: 45930 | AE3: 46022 | AF3: 46112 | AG3: 46203
C4: Act | D4: Act | E4: Act | F4: Act | G4: Act | H4: Act | I4: Act | J4: Act | L4: Act | M4: Act | N4: Act | O4: Act | P4: Act | Q4: Act | R4: Act | S4: Act | T4: Act | U4: Act | V4: Act | W4: Act | X4: Act | Y4: Act | Z4: Act | AA4: Act | AB4: Act | AC4: Act | AD4: Act | AE4: Act | AF4: Act | AG4: Act
C5: FY | D5: FY | E5: FY | F5: FY | G5: FY | H5: FY | I5: FY | J5: LTM | L5: 1Q | M5: 2Q | N5: 3Q | O5: 4Q | P5: 1Q | Q5: 2Q | R5: 3Q | S5: 4Q | T5: 1Q | U5: 2Q | V5: 3Q | W5: 4Q | X5: 1Q | Y5: 2Q | Z5: 3Q | AA5: 4Q | AB5: 1Q | AC5: 2Q | AD5: 3Q | AE5: 4Q | AF5: 1Q | AG5: 2Q
B7: Exploration and Production | C7: =SUM(C10:C16) -> 1634 | D7: =SUM(D10:D16) -> 868 | E7: =SUM(E10:E16) -> 1698 | F7: =SUM(F10:F16) -> 2489 | G7: =SUM(G10:G16) -> 2513 | H7: =SUM(H10:H16) -> 2399 | I7: =SUM(I10:I16) -> 2057 | J7: =SUM(J10:J16) -> 2559 | L7: =SUM(L10:L16) -> 539 | M7: =SUM(M10:M16) -> 394.5 | N7: =SUM(N10:N16) -> 365.5 | O7: =SUM(O10:O16) -> 399 | P7: =SUM(P10:P16) -> 631 | Q7: =SUM(Q10:Q16) -> 682 | R7: =SUM(R10:R16) -> 610 | S7: =SUM(S10:S16) -> 566 | ... AG7: =SUM(AG10:AG16) -> 812
B9: Southeast Asia | C9: =SUM(C10:C11) -> 1660 | D9: =SUM(D10:D11) -> 944 | E9: =SUM(E10:E11) -> 1576 | F9: =SUM(F10:F11) -> 2626 | G9: =SUM(G10:G11) -> 2277 | H9: =SUM(H10:H11) -> 2100 | I9: =SUM(I10:I11) -> 1767 | J9: =SUM(J10:J11) -> 2215 | L9: =SUM(L10:L11) -> 324 | M9: =SUM(M10:M11) -> 382 | N9: =SUM(N10:N11) -> 324 | O9: =SUM(O10:O11) -> 546 | P9: =SUM(P10:P11) -> 584 | Q9: =SUM(Q10:Q11) -> 632 | R9: =SUM(R10:R11) -> 682 | S9: =SUM(S10:S11) -> 728 | ... AG9: =SUM(AG10:AG11) -> 724
B10: Thailand | C10: 1236 | D10: 799 | E10: 1220 | F10: 1843 | G10: 1608 | H10: 1530 | I10: 1214 | J10: =SUM(AD10:AG10) -> 1674 | L10: 270 | M10: 307 | N10: 271 | O10: =E10-SUM(L10:N10) -> 372 | P10: 418 | Q10: 480 | R10: 421 | S10: =F10-SUM(P10:R10) -> 524 | T10: 413 | U10: 413 | V10: 384 | W10: =G10-SUM(T10:V10) -> 398 | X10: 394 | Y10: 404 | Z10: 362 | AA10: =H10-SUM(X10:Z10) -> 370 | AB10: 318 | AC10: 282 | AD10: 302 | AE10: =I10-SUM(AB10:AD10) -> 312 | AF10: 498 | AG10: 562
B11: Other Southeast Asia | C11: 424 | D11: 145 | E11: 356 | F11: 783 | G11: 669 | H11: 570 | I11: 553 | J11: =SUM(AD11:AG11) -> 541 | L11: 54 | M11: 75 | N11: 53 | O11: =E11-SUM(L11:N11) -> 174 | P11: 166 | Q11: 152 | R11: 261 | S11: =F11-SUM(P11:R11) -> 204 | T11: 163 | U11: 163 | V11: 173 | W11: =G11-SUM(T11:V11) -> 170 | X11: 97 | Y11: 176 | Z11: 194 | AA11: =H11-SUM(X11:Z11) -> 103 | AB11: 155 | AC11: 136 | AD11: 141 | AE11: =I11-SUM(AB11:AD11) -> 121 | AF11: 117 | AG11: 162
B12: Middle East | C12: 0 | D12: -13 | E12: 426 | F12: 292 | G12: 223 | H12: 204 | I12: 142 | J12: =SUM(AD12:AG12) -> 48 | L12: 351 | M12: 6 | N12: 32 | O12: =E12-SUM(L12:N12) -> 37 | P12: 54 | Q12: 56 | R12: 64 | S12: =F12-SUM(P12:R12) -> 118 | T12: 69 | U12: 69 | V12: 39 | W12: =G12-SUM(T12:V12) -> 46 | X12: 57 | Y12: 57 | Z12: 34 | AA12: =H12-SUM(X12:Z12) -> 56 | AB12: 31 | AC12: 63 | AD12: 16 | AE12: =I12-SUM(AB12:AD12) -> 32
B13: Australia | C13: -15 | D13: -28 | E13: 5 | F13: -164 | G13: 22 | H13: 0 | I13: 0 | J13: =SUM(AD13:AG13) -> 0 | L13: -1 | M13: -0.5 | N13: -0.5 | O13: =E13-SUM(L13:N13) -> 7 | P13: -1 | Q13: -1 | R13: -31 | S13: =F13-SUM(P13:R13) -> -131 | T13: 1 | U13: 1 | V13: -1 | W13: =G13-SUM(T13:V13) -> 21 | X13: 0 | Y13: -30 | Z13: -23 | AA13: =H13-SUM(X13:Z13) -> 53
B14: America | C14: -10 | D14: -56 | E14: -175 | F14: -110 | G14: -8 | H14: 0 | I14: 0 | J14: =SUM(AD14:AG14) -> 0 | L14: -146 | M14: -2 | N14: -2 | O14: =E14-SUM(L14:N14) -> -25 | P14: -7 | Q14: -4 | R14: -96 | S14: =F14-SUM(P14:R14) -> -3 | T14: -2 | U14: -2 | V14: -3 | W14: =G14-SUM(T14:V14) -> -1 | X14: -2 | Y14: -2 | Z14: 0 | AA14: =H14-SUM(X14:Z14) -> 4
B15: Africa | C15: 14 | D15: 23 | E15: -147 | F15: -167 | G15: -6 | H15: 144 | I15: 180 | J15: =SUM(AD15:AG15) -> 139 | L15: 7 | M15: 6 | N15: 9 | O15: =E15-SUM(L15:N15) -> -169 | P15: -3 | Q15: -6 | R15: -10 | S15: =F15-SUM(P15:R15) -> -148 | T15: 19 | U15: 19 | V15: 33 | W15: =G15-SUM(T15:V15) -> -77 | X15: 23 | Y15: 56 | Z15: 23 | AA15: =H15-SUM(X15:Z15) -> 42 | AB15: 13 | AC15: 28 | AD15: 16 | AE15: =I15-SUM(AB15:AD15) -> 123
B16: Others | C16: -15 | D16: -2 | E16: 13 | F16: 12 | G16: 5 | H16: -49 | I16: -32 | J16: =SUM(AD16:AG16) -> 157 | L16: 4 | M16: 3 | N16: 3 | O16: =E16-SUM(L16:N16) -> 3 | P16: 4 | Q16: 5 | R16: 1 | S16: =F16-SUM(P16:R16) -> 2 | T16: 1 | U16: 1 | V16: 1 | W16: =G16-SUM(T16:V16) -> 2 | X16: 4 | Y16: 2 | Z16: 0 | AA16: =H16-SUM(X16:Z16) -> -55 | AB16: 1 | AC16: -37 | AD16: 3 | AE16: =I16-SUM(AB16:AD16) -> 1 | AF16: 65 | AG16: 88
B17: Head office and others | C17: -65 | D17: -148 | E17: -487 | F17: -490 | G17: -305 | H17: -172 | I17: -227 | J17: =SUM(AD17:AG17) -> -437 | L17: -163 | M17: -173 | N17: -74 | O17: =E17-SUM(L17:N17) -> -77 | P17: -313 | Q17: -82 | R17: 54 | S17: =F17-SUM(P17:R17) -> -149 | T17: -95 | U17: -95 | V17: -16 | W17: =G17-SUM(T17:V17) -> -99 | X17: -49 | Y17: -10 | Z17: -79 | AA17: =H17-SUM(X17:Z17) -> -34 | AB17: -30 | AC17: -64 | AD17: -85 | AE17: =I17-SUM(AB17:AD17) -> -48 | AF17: -304 | AG17: 0
B19: Total | C19: =C17+C7 -> 1569 | D19: =D17+D7 -> 720 | E19: =E17+E7 -> 1211 | F19: =F17+F7 -> 1999 | G19: =G17+G7 -> 2208 | H19: =H17+H7 -> 2227 | I19: =I17+I7 -> 1830 | J19: =J17+J7 -> 2122 | L19: =L17+L7 -> 376 | M19: =M17+M7 -> 221.5 | N19: =N17+N7 -> 291.5 | O19: =O17+O7 -> 322 | P19: =P17+P7 -> 318 | Q19: =Q17+Q7 -> 600 | R19: =R17+R7 -> 664 | S19: =S17+S7 -> 417 | ... AG19: =AG17+AG7 -> 812
B21: Average Sales Volume (Barrels of Oil Equivalent per Day)
B22: By product type
B23: Gas | C23: 248537 | D23: 236314 | E23: 296838 | F23: 339421 | G23: 331083 | H23: 354391 | I23: 369255 | J23: =AVERAGE(AD23:AG23) -> 400111.25 | L23: 270982 | M23: 317243 | N23: 300319 | O23: =E23 -> 296838 | P23: 310757 | Q23: 336924 | R23: 347908 | S23: =F23 -> 339421 | T23: 332351 | U23: 323336 | V23: 328265 | W23: 340325 | X23: 345454 | Y23: 373464 | Z23: 343138 | AA23: 355616 | AB23: 354884 | AC23: 356674 | AD23: 378417 | AE23: 386598 | AF23: 412304 | AG23: 423126
B24: Liquid | C24: 102114 | D24: 117738 | E24: 119303 | F24: 128709 | G24: 130924 | H24: 134403 | I24: 140651 | J24: =AVERAGE(AD24:AG24) -> 143956.5 | L24: 111895 | M24: 125883 | N24: 116848 | O24: =E24 -> 119303 | P24: 116611 | Q24: 128535 | R24: 130415 | S24: =F24 -> 128709 | T24: 128466 | U24: 121532 | V24: 139187 | W24: 134354 | X24: 127594 | Y24: 133245 | Z24: 131940 | AA24: 144749 | AB24: 129334 | AC24: 148098 | AD24: 132080 | AE24: 152925 | AF24: 141065 | AG24: 149756
B25: Total | C25: =SUM(C23:C24) -> 350651 | D25: =SUM(D23:D24) -> 354052 | E25: =SUM(E23:E24) -> 416141 | F25: =SUM(F23:F24) -> 468130 | G25: =SUM(G23:G24) -> 462007 | H25: =SUM(H23:H24) -> 488794 | I25: =SUM(I23:I24) -> 509906 | J25: =SUM(J23:J24) -> 544067.75 | L25: =SUM(L23:L24) -> 382877 | M25: =SUM(M23:M24) -> 443126 | N25: =SUM(N23:N24) -> 417167 | O25: =SUM(O23:O24) -> 416141 | P25: =SUM(P23:P24) -> 427368 | Q25: =SUM(Q23:Q24) -> 465459 | R25: =SUM(R23:R24) -> 478323 | S25: =SUM(S23:S24) -> 468130 | ... AG25: =SUM(AG23:AG24) -> 572882
B27: By geographical region
B28: Thailand | C28: 273981 | D28: 249481 | E28: 264382 | F28: 295362 | G28: 306750 | H28: 334205 | I28: 353491 | J28: =AVERAGE(AD28:AG28) -> 379139.5 | L28: 274242 | M28: 272819 | N28: 255150 | O28: =E28 -> 264382 | P28: 264424 | Q28: 290086 | R28: 302056 | S28: =F28 -> 295362 | T28: 314421 | U28: 295986 | V28: 301386 | W28: 315258 | X28: 320221 | Y28: 349190 | Z28: 328333 | AA28: 339087 | AB28: 330645 | AC28: 348042 | AD28: 360342 | AE28: 374380 | AF28: 385519 | AG28: 396317
B29: Other Southeast Asia | C29: 70560 | D29: 85248 | E29: 95766 | F29: 98715 | G29: 93653 | H29: 88624 | I29: 89160 | J29: =AVERAGE(AD29:AG29) -> 93036.25 | L29: 85215 | M29: 102239 | N29: 97468 | O29: =E29 -> 95766 | P29: 97600 | Q29: 98166 | R29: 101076 | S29: =F29 -> 98715 | T29: 88779 | U29: 91316 | V29: 99326 | W29: 95058 | X29: 90056 | Y29: 88675 | Z29: 88933 | AA29: 86850 | AB29: 100429 | AC29: 82192 | AD29: 86703 | AE29: 87487 | AF29: 97587 | AG29: 100368
B30: Rest of the World | C30: 6110 | D30: 19323 | E30: 55993 | F30: 74053 | G30: 61604 | H30: 65965 | I30: 67255 | J30: =AVERAGE(AD30:AG30) -> 71892 | L30: 23420 | M30: 68068 | N30: 64549 | O30: =E30 -> 55993 | P30: 65344 | Q30: 77207 | R30: 75191 | S30: =F30 -> 74053 | T30: 57617 | U30: 57566 | V30: 66740 | W30: 64363 | X30: 62771 | Y30: 68844 | Z30: 57812 | AA30: 74428 | AB30: 53144 | AC30: 74538 | AD30: 63452 | AE30: 77656 | AF30: 70263 | AG30: 76197
B31: Total | C31: =SUM(C28:C30) -> 350651 | D31: =SUM(D28:D30) -> 354052 | E31: =SUM(E28:E30) -> 416141 | F31: =SUM(F28:F30) -> 468130 | G31: =SUM(G28:G30) -> 462007 | H31: =SUM(H28:H30) -> 488794 | I31: =SUM(I28:I30) -> 509906 | J31: =SUM(J28:J30) -> 544067.75 | L31: =SUM(L28:L30) -> 382877 | M31: =SUM(M28:M30) -> 443126 | N31: =SUM(N28:N30) -> 417167 | O31: =SUM(O28:O30) -> 416141 | P31: =SUM(P28:P30) -> 427368 | Q31: =SUM(Q28:Q30) -> 465459 | R31: =SUM(R28:R30) -> 478323 | S31: =SUM(S28:S30) -> 468130 | ... AG31: =SUM(AG28:AG30) -> 572882
B33: By geographical region (% Share)
B34: Thailand | C34: =C28/C$31 -> 0.78134955 | D34: =D28/D$31 -> 0.70464508 | E34: =E28/E$31 -> 0.63531832 | F34: =F28/F$31 -> 0.63094012 | G34: =G28/G$31 -> 0.66395098 | H34: =H28/H$31 -> 0.68373384 | I34: =I28/I$31 -> 0.69324738 | J34: =J28/J$31 -> 0.69686082 | L34: =L28/L$31 -> 0.71626658 | M34: =M28/M$31 -> 0.61566913 | N34: =N28/N$31 -> 0.61162556 | O34: =O28/O$31 -> 0.63531832 | P34: =P28/P$31 -> 0.61872672 | Q34: =Q28/Q$31 -> 0.62322568 | R34: =R28/R$31 -> 0.6314896 | S34: =S28/S$31 -> 0.63094012 | ... AG34: =AG28/AG$31 -> 0.69179517
B35: Other Southeast Asia | C35: =C29/C$31 -> 0.20122572 | D35: =D29/D$31 -> 0.24077819 | E35: =E29/E$31 -> 0.23012873 | F35: =F29/F$31 -> 0.21087091 | G35: =G29/G$31 -> 0.20270905 | H35: =H29/H$31 -> 0.18131155 | I35: =I29/I$31 -> 0.17485576 | J35: =J29/J$31 -> 0.17100122 | L35: =L29/L$31 -> 0.22256495 | M35: =M29/M$31 -> 0.23072219 | N35: =N29/N$31 -> 0.23364264 | O35: =O29/O$31 -> 0.23012873 | P35: =P29/P$31 -> 0.22837461 | Q35: =Q29/Q$31 -> 0.2109015 | R35: =R29/R$31 -> 0.21131328 | S35: =S29/S$31 -> 0.21087091 | ... AG35: =AG29/AG$31 -> 0.17519838
B36: Rest of the World | C36: =C30/C$31 -> 0.017424733 | D36: =D30/D$31 -> 0.054576729 | E36: =E30/E$31 -> 0.13455295 | F36: =F30/F$31 -> 0.15818896 | G36: =G30/G$31 -> 0.13333997 | H36: =H30/H$31 -> 0.1349546 | I36: =I30/I$31 -> 0.13189686 | J36: =J30/J$31 -> 0.13213796 | L36: =L30/L$31 -> 0.061168469 | M36: =M30/M$31 -> 0.15360868 | N36: =N30/N$31 -> 0.1547318 | O36: =O30/O$31 -> 0.13455295 | P36: =P30/P$31 -> 0.15289867 | Q36: =Q30/Q$31 -> 0.16587283 | R36: =R30/R$31 -> 0.15719712 | S36: =S30/S$31 -> 0.15818896 | ... AG36: =AG30/AG$31 -> 0.13300645
B37: Total | C37: =SUM(C34:C36) -> 1 | D37: =SUM(D34:D36) -> 1 | E37: =SUM(E34:E36) -> 1 | F37: =SUM(F34:F36) -> 1 | G37: =SUM(G34:G36) -> 1 | H37: =SUM(H34:H36) -> 1 | I37: =SUM(I34:I36) -> 1 | J37: =SUM(J34:J36) -> 1 | L37: =SUM(L34:L36) -> 1 | M37: =SUM(M34:M36) -> 1 | N37: =SUM(N34:N36) -> 1 | O37: =SUM(O34:O36) -> 1 | P37: =SUM(P34:P36) -> 1 | Q37: =SUM(Q34:Q36) -> 1 | R37: =SUM(R34:R36) -> 1 | S37: =SUM(S34:S36) -> 1 | ... AG37: =SUM(AG34:AG36) -> 1
B39: By geographical region (YoY % Growth)
B40: Thailand | D40: =D28/C28-1 -> -0.089422259 | E40: =E28/D28-1 -> 0.059727995 | F40: =F28/E28-1 -> 0.11717893 | G40: =G28/F28-1 -> 0.038556077 | H40: =H28/G28-1 -> 0.089502852 | I40: =I28/H28-1 -> 0.057707096 | P40: =P28/L28-1 -> -0.035800497 | Q40: =Q28/M28-1 -> 0.063291046 | R40: =R28/N28-1 -> 0.18383696 | S40: =S28/O28-1 -> 0.11717893 | T40: =T28/P28-1 -> 0.1890789 | U40: =U28/Q28-1 -> 0.020338796 | V40: =V28/R28-1 -> -0.0022181317 | W40: =W28/S28-1 -> 0.067361407 | ... AG40: =AG28/AC28-1 -> 0.13870452
B41: Other Southeast Asia | D41: =D29/C29-1 -> 0.20816327 | E41: =E29/D29-1 -> 0.12338119 | F41: =F29/E29-1 -> 0.03079381 | G41: =G29/F29-1 -> -0.051278934 | H41: =H29/G29-1 -> -0.053698226 | I41: =I29/H29-1 -> 0.0060480231 | P41: =P29/L29-1 -> 0.14533826 | Q41: =Q29/M29-1 -> -0.039838027 | R41: =R29/N29-1 -> 0.037017277 | S41: =S29/O29-1 -> 0.03079381 | T41: =T29/P29-1 -> -0.090379098 | U41: =U29/Q29-1 -> -0.069779761 | V41: =V29/R29-1 -> -0.017313705 | W41: =W29/S29-1 -> -0.037046042 | ... AG41: =AG29/AC29-1 -> 0.22114074
B42: Rest of the World | D42: =D30/C30-1 -> 2.1625205 | E42: =E30/D30-1 -> 1.8977384 | F42: =F30/E30-1 -> 0.32254032 | G42: =G30/F30-1 -> -0.16810933 | H42: =H30/G30-1 -> 0.070790858 | I42: =I30/H30-1 -> 0.019555825 | P42: =P30/L30-1 -> 1.7900939 | Q42: =Q30/M30-1 -> 0.1342628 | R42: =R30/N30-1 -> 0.164867 | S42: =S30/O30-1 -> 0.32254032 | T42: =T30/P30-1 -> -0.1182511 | U42: =U30/Q30-1 -> -0.25439403 | V42: =V30/R30-1 -> -0.11239377 | W42: =W30/S30-1 -> -0.13085223 | ... AG42: =AG30/AC30-1 -> 0.022257104
B43: Total | D43: =D31/C31-1 -> 0.0096991025 | E43: =E31/D31-1 -> 0.1753669 | F43: =F31/E31-1 -> 0.12493121 | G43: =G31/F31-1 -> -0.0130797 | H43: =H31/G31-1 -> 0.057979641 | I43: =I31/H31-1 -> 0.04319202 | P43: =P31/L31-1 -> 0.11620181 | Q43: =Q31/M31-1 -> 0.050398758 | R43: =R31/N31-1 -> 0.14659836 | S43: =S31/O31-1 -> 0.12493121 | T43: =T31/P31-1 -> 0.078267442 | U43: =U31/Q31-1 -> -0.044238053 | V43: =V31/R31-1 -> -0.02272732 | W43: =W31/S31-1 -> 0.013989704 | ... AG43: =AG31/AC31-1 -> 0.13493221
B46: Product price table
B47: Gas ($/MMBTU) | C47: 6.27 | D47: 6.27 | E47: 5.69 | F47: 6.27 | G47: 6 | H47: 5.87 | I47: 5.81 | J47: =AVERAGE(AD47:AG47) -> 5.8275 | L47: 5.61 | M47: 5.59 | N47: 5.76 | O47: 5.81 | P47: 6.07 | Q47: 6.1 | R47: 6.18 | S47: 6.27 | T47: 6.52 | U47: 5.87 | V47: 5.75 | W47: 5.86 | X47: 5.9 | Y47: 5.8 | Z47: 5.93 | AA47: 5.86 | AB47: 5.95 | AC47: 5.79 | AD47: 5.8 | AE47: 5.74 | AF47: 5.81 | AG47: 5.96
B48: Liquid ($/BBL) | C48: 41.55 | D48: 41.55 | E48: 66.7 | F48: 94.89 | G48: 79.09 | H48: 77.2 | I48: 67.13 | J48: =AVERAGE(AD48:AG48) -> 251.6975 | L48: 56.59 | M48: 63.98 | N48: 69.16 | O48: 76.17 | P48: 91.19 | Q48: 105.47 | R48: 97.94 | S48: 94.89 | T48: 78.14 | U48: 73.66 | V48: 81.89 | W48: 81.95 | X48: 79.36 | Y48: 81.15 | Z48: 76.91 | AA48: 71.98 | AB48: 73.37 | AC48: 66.32 | AD48: 67.03 | AE48: 762.78 | AF48: 77.47 | AG48: 99.51
B49: Weighted Avg. ($/BOE) | C49: 38.92 | D49: 38.92 | E49: 43.49 | F49: 53.39 | G49: 48.21 | H49: 46.78 | I49: 43.82 | J49: =AG49 -> 52.89 | L49: 40.38 | M49: 42.19 | N49: 44.25 | O49: 46.87 | P49: 51.35 | Q49: 55.61 | R49: 53.68 | S49: 46.87 | T49: 50.01 | U49: 55.61 | V49: 53.68 | W49: 48.41 | X49: 47.24 | Y49: 55.61 | Z49: 53.68 | AA49: 45.83 | AB49: 45.74 | AC49: 44.01 | AD49: 43.17 | AE49: 42.55 | AF49: 46.02 | AG49: 52.89
B50: Avg. Dubai ($/BBL) | C50: 42.27 | D50: 42.27 | E50: 69.39 | F50: 96.38 | G50: 82.09 | H50: 79.58 | I50: 69.36 | J50: =AVERAGE(AD50:AG50) -> 79.4175 | L50: 60.01 | M50: 67.02 | N50: 71.68 | O50: 78.27 | P50: 96.21 | Q50: 108.22 | R50: 96.68 | S50: 96.38 | T50: 80.23 | U50: 77.59 | V50: 86.63 | W50: 83.75 | X50: 81.22 | Y50: 85.34 | Z50: 78.43 | AA50: 73.62 | AB50: 76.94 | AC50: 66.95 | AD50: 70.11 | AE50: 63.82 | AF50: 87.87 | AG50: 95.87
B51: Avg. HSFO ($/BBL) | C51: 39.3 | D51: 39.3 | E51: 64.42 | F51: 82.38 | G51: 71.87 | H51: 74.02 | L51: 56.74 | M51: 61.21 | N51: 68.35 | O51: 71.38 | P51: 87.96 | Q51: 104.67 | R51: 74.44 | S51: 96.38 | T51: 64.22 | U51: 69.01 | V51: 81.41 | W51: 72.64 | X51: 71.53 | Y51: 80.15 | Z51: 76.91 | AA51: 71.35 | AB51: 74.94 | AC51: 68.66
B53: Revenue Mix (%)
B54: Gas | C54: 0.62 | D54: 0.64 | E54: 0.53 | F54: 0.53 | G54: 0.53 | H54: 0.55 | I54: 0.58 | J54: =AVERAGE(AD54:AG54) -> 0.5575 | L54: 0.59 | M54: 0.57 | N54: 0.56 | O54: 0.53 | P54: 0.52 | Q54: 0.48 | R54: 0.5 | S54: 0.53 | T54: 0.56 | U54: 0.44 | V54: 0.5 | W54: 0.53 | X54: 0.54 | Y54: 0.55 | Z54: 0.45 | AA54: 0.55 | AB54: 0.57 | AC54: 0.56 | AD54: 0.6 | AE54: 0.58 | AF54: 0.56 | AG54: 0.49
B55: Liquid | C55: 0.38 | D55: 0.36 | E55: 0.47 | F55: 0.47 | G55: 0.47 | H55: 0.45 | I55: 0.42 | J55: =AVERAGE(AD55:AG55) -> 0.4425 | L55: 0.41 | M55: 0.43 | N55: 0.44 | O55: 0.47 | P55: 0.48 | Q55: 0.52 | R55: 0.5 | S55: 0.47 | T55: 0.44 | U55: 0.56 | V55: 0.5 | W55: 0.47 | X55: 0.46 | Y55: 0.45 | Z55: 0.55 | AA55: 0.45 | AB55: 0.43 | AC55: 0.44 | AD55: 0.4 | AE55: 0.42 | AF55: 0.44 | AG55: 0.51
B56: Total | C56: =SUM(C54:C55) -> 1 | D56: =SUM(D54:D55) -> 1 | E56: =SUM(E54:E55) -> 1 | F56: =SUM(F54:F55) -> 1 | G56: =SUM(G54:G55) -> 1 | H56: =SUM(H54:H55) -> 1 | I56: =SUM(I54:I55) -> 1 | J56: =SUM(J54:J55) -> 1 | L56: =SUM(L54:L55) -> 1 | M56: =SUM(M54:M55) -> 1 | N56: =SUM(N54:N55) -> 1 | O56: =SUM(O54:O55) -> 1 | P56: =SUM(P54:P55) -> 1 | Q56: =SUM(Q54:Q55) -> 1 | R56: =SUM(R54:R55) -> 1 | S56: =SUM(S54:S55) -> 1 | ... AG56: =SUM(AG54:AG55) -> 1
B58: Volume Mix (%)
B59: Gas | C59: 0.71 | D59: 0.67 | E59: 0.71 | F59: 0.73 | G59: 0.72 | H59: 0.71 | I59: 0.72 | J59: =AVERAGE(AD59:AG59) -> 0.735 | L59: 0.71 | M59: 0.72 | N59: 0.72 | O59: 0.71 | P59: 0.73 | Q59: 0.72 | R59: 0.73 | S59: 0.73 | T59: 0.72 | U59: 0.73 | V59: 0.7 | W59: 0.72 | X59: 0.73 | Y59: 0.74 | Z59: 0.72 | AA59: 0.71 | AB59: 0.73 | AC59: 0.71 | AD59: 0.74 | AE59: 0.71 | AF59: 0.75 | AG59: 0.74
B60: Liquid | C60: 0.29 | D60: 0.33 | E60: 0.29 | F60: 0.27 | G60: 0.28 | H60: 0.29 | I60: 0.28 | J60: =AVERAGE(AD60:AG60) -> 0.265 | L60: 0.29 | M60: 0.28 | N60: 0.28 | O60: 0.29 | P60: 0.27 | Q60: 0.28 | R60: 0.27 | S60: 0.27 | T60: 0.28 | U60: 0.27 | V60: 0.3 | W60: 0.28 | X60: 0.27 | Y60: 0.26 | Z60: 0.28 | AA60: 0.29 | AB60: 0.27 | AC60: 0.29 | AD60: 0.26 | AE60: 0.29 | AF60: 0.25 | AG60: 0.26
B61: Total | C61: =SUM(C59:C60) -> 1 | D61: =SUM(D59:D60) -> 1 | E61: =SUM(E59:E60) -> 1 | F61: =SUM(F59:F60) -> 1 | G61: =SUM(G59:G60) -> 1 | H61: =SUM(H59:H60) -> 1 | I61: =SUM(I59:I60) -> 1 | J61: =SUM(J59:J60) -> 1 | L61: =SUM(L59:L60) -> 1 | M61: =SUM(M59:M60) -> 1 | N61: =SUM(N59:N60) -> 1 | O61: =SUM(O59:O60) -> 1 | P61: =SUM(P59:P60) -> 1 | Q61: =SUM(Q59:Q60) -> 1 | R61: =SUM(R59:R60) -> 1 | S61: =SUM(S59:S60) -> 1 | ... AG61: =SUM(AG59:AG60) -> 1
B63: Reserves (MMBOE) by geography
B64: Proven | C64: 1140 | D64: 1074 | E64: 1350 | F64: 1442 | G64: 1436 | H64: 1637 | I64: 1838
B65: Domestic | C65: =C64*0.5 -> 570 | D65: =D64*0.5 -> 537 | E65: =E64*0.45 -> 607.5 | F65: =F64*0.49 -> 706.58 | G65: =G64*0.48 -> 689.28 | H65: =H64*0.46 -> 753.02 | I65: =I64*0.46 -> 845.48
B66: International | C66: =C64*0.5 -> 570 | D66: =D64*0.5 -> 537 | E66: =E64*0.55 -> 742.5 | F66: =F64*0.51 -> 735.42 | G66: =G64*0.52 -> 746.72 | H66: =H64*0.54 -> 883.98 | I66: =I64*0.54 -> 992.52
B67: Probable | C67: 507 | D67: 548 | E67: 772 | F67: 844 | G67: 844 | H67: 931 | I67: 888
B68: Proven+Probable | C68: =C64+C67 -> 1647 | D68: =D64+D67 -> 1622 | E68: =E64+E67 -> 2122 | F68: =F64+F67 -> 2286 | G68: =G64+G67 -> 2280 | H68: =H64+H67 -> 2568 | I68: =I64+I67 -> 2726
B69: Domestic | C69: =C68*0.51 -> 839.97 | D69: =D68*0.53 -> 859.66 | E69: =E68*0.46 -> 976.12 | F69: =F68*0.54 -> 1234.44 | G69: =G68*0.47 -> 1071.6 | H69: =H68*0.48 -> 1232.64 | I69: =I68*0.49 -> 1335.74
B70: International | C70: =C68*0.49 -> 807.03 | D70: =D68*0.47 -> 762.34 | E70: =E68*0.54 -> 1145.88 | F70: =F68*0.46 -> 1051.56 | G70: =G68*0.53 -> 1208.4 | H70: =H68*0.52 -> 1335.36 | I70: =I68*0.51 -> 1390.26
B72: Reserves (MMBOE) by product type
B73: Proven | C73: 1140 | D73: 1074 | E73: 1350 | F73: 1442 | G73: 1436 | H73: 1637 | I73: 1838
B74: Gas | C74: =C73*0.73 -> 832.2 | D74: =D73*0.73 -> 784.02 | E74: =E73*0.74 -> 999 | F74: =F73*0.75 -> 1081.5 | G74: =G73*0.75 -> 1077 | H74: =H73*0.7 -> 1145.9 | I74: =I73*0.7 -> 1286.6
B75: Liquid | C75: =C73*0.27 -> 307.8 | D75: =D73*0.27 -> 289.98 | E75: =E73*0.26 -> 351 | F75: =F73*0.25 -> 360.5 | G75: =G73*0.25 -> 359 | H75: =H73*0.3 -> 491.1 | I75: =I73*0.3 -> 551.4
B76: Probable | C76: 507 | D76: 548 | E76: 773 | F76: 844 | G76: 844 | H76: 931 | I76: 88
B77: Proven+Probable | C77: =C73+C76 -> 1647 | D77: =D73+D76 -> 1622 | E77: =E73+E76 -> 2123 | F77: =F73+F76 -> 2286 | G77: =G73+G76 -> 2280 | H77: =H73+H76 -> 2568 | I77: =I73+I76 -> 1926
B78: Gas | C78: =C77*0.69 -> 1136.43 | D78: =D77*0.69 -> 1119.18 | E78: =E77*0.7 -> 1486.1 | F78: =F77*0.72 -> 1645.92 | G78: =G77*0.73 -> 1664.4 | H78: =H77*0.69 -> 1771.92 | I78: =I77*0.69 -> 1328.94
B79: Liquid | C79: =C77*0.31 -> 510.57 | D79: =D77*0.31 -> 502.82 | E79: =E77*0.3 -> 636.9 | F79: =F77*0.28 -> 640.08 | G79: =G77*0.27 -> 615.6 | H79: =H77*0.31 -> 796.08 | I79: =I77*0.31 -> 597.06
AA88: 2Q26
