Workbook
Name \A: #REF!
Name \B: #REF!
Name \C: #REF!
Name \L: #REF!
Name \M: #REF!
Name \P: #REF!
Name \Y: #REF!
Name _01_30_04: MonthlyOpStats
Name _01_30_04: MonthlyOpStats
Name _1_30_01: MonthlyOpStats
Name _1_30_01: MonthlyOpStats
Name _1_30_02: MonthlyOpStats
Name _1_30_02: MonthlyOpStats
Name _1_31_01: MonthlyOpStats
Name _1_31_01: MonthlyOpStats
Name _1_31_02: MonthlyOpStats
Name _1_31_02: MonthlyOpStats
Name _12_31_05: MonthlyOpStats
Name _12_31_05: MonthlyOpStats
Name _A: #REF!
Name _A___0: #REF!
Name _B: #REF!
Name _B___0: #REF!
Name _C: #REF!
Name _C___0: #REF!
Name _ent1: [1]Inputs!$J$17
Name _ent10: [1]Inputs!$J$476
Name _ent11: [1]Inputs!$J$527
Name _ent12: [1]Inputs!$J$578
Name _ent13: [1]Inputs!$J$629
Name _ent14: [1]Inputs!$J$680
Name _ent15: [1]Inputs!$J$731
Name _ent2: [1]Inputs!$J$68
Name _ent3: [1]Inputs!$J$119
Name _ent4: [1]Inputs!$J$170
Name _ent5: [1]Inputs!$J$221
Name _ent6: [1]Inputs!$J$272
Name _ent7: [1]Inputs!$J$323
Name _ent8: [1]Inputs!$J$374
Name _ent9: [1]Inputs!$J$425
Name _eps1: [1]Inputs!$P$42
Name _eps10: [1]Inputs!$P$501
Name _eps11: [1]Inputs!$P$552
Name _eps12: [1]Inputs!$P$603
Name _eps13: [1]Inputs!$P$654
Name _eps14: [1]Inputs!$P$705
Name _eps15: [1]Inputs!$P$756
Name _eps2: [1]Inputs!$P$93
Name _eps3: [1]Inputs!$P$144
Name _eps4: [1]Inputs!$P$195
Name _eps5: [1]Inputs!$P$246
Name _eps6: [1]Inputs!$P$297
Name _eps7: [1]Inputs!$P$348
Name _eps8: [1]Inputs!$P$399
Name _eps9: [1]Inputs!$P$450
Name _fye1: [1]Inputs!$E$12
Name _fye10: [1]Inputs!$E$471
Name _fye11: [1]Inputs!$E$522
Name _fye12: [1]Inputs!$E$573
Name _fye13: [1]Inputs!$E$624

Sheet Capitalisation
A3: 1Q26 | I3: Exchange rate as at end | J3: =Model!$I$203 -> 0.0010795988
I4: LTM Average exchange rate | J4: =Model!$I$204 -> 0.0010682761
B6: Debt Breakdown as on 31-Mar-2026 | C6: CLP millions | D6: Leverage | E6: USD mn | F6: Leverage | I6: Company Reported | J6: CLP millions
I7: Total Financial Debt | J7: 1247190
B8: Included in non-current liabilities | C8: =SUM(C9:C10) -> 1046265.7 | E8: =SUM(E9:E10) -> 1129.5472 | I8: Net Financial Debt | J8: 635620
B9: Bank borrowings | C9: 40280.382 | E9: =C9*J3 -> 43.486653 | I9: Net Financial Debt / EBITDA | J9: 1.69x
B10: Bonds payable | C10: 1005985.3 | E10: =C10*J3 -> 1086.0605
B12: Included in current liabilities | C12: =SUM(C13:C14) -> 120403.68 | E12: =SUM(E13:E14) -> 129.98767
B13: Bank borrowings | C13: 85852.526 | E13: =C13*J3 -> 92.686286
B14: Bonds payable | C14: 34551.156 | E14: =C14*J3 -> 37.301387
B16: Lease Obligations | C16: =SUM(C17:C18) -> 56851.904 | E16: =SUM(E17:E18) -> 61.377249
B17: Short-term | C17: =Model!$AE$111 -> 11649.606 | E17: =C17*J3 -> 12.576901
B18: Long-term | C18: =Model!$AE$112 -> 45202.298 | E18: =C18*J3 -> 48.800348
B20: Total Loans & Borrowings | C20: =C12+C8+C16 -> 1223521.2 | D20: =C20/C25 -> 3.2514735 | E20: =E12+E8+E16 -> 1320.9121 | F20: =E20/E25 -> 3.285936
B21: Cash and Cash Equivalents | C21: =Model!AE$119 -> 611569.36 | E21: =C21*J3 -> 660.24957
B22: Net debt | C22: =C20-C21 -> 611951.88 | D22: =C22/C25 -> 1.626245 | E22: =E20-E21 -> 660.66253 | F22: =E22/E25 -> 1.6434817
B23: Equity | C23: =Model!AE$123 -> 1739768.3 | E23: =C23*J3 -> 1878.2518
B24: Total Capitalisation | C24: =C22+C23 -> 2351720.2 | E24: =E22+E23 -> 2538.9144
B25: LTM Adjusted EBITDA | C25: =Model!AE$86 -> 376297.47 | E25: =C25*J4 -> 401.9896
B26: check | C26: =+C20-Model!AE$118 -> 0
B29: Liquidity at 1Q26 | C29: CLP millions | D29: USD mn
B30: Cash and Cash Equivalents | C30: =C21 -> 611569.36 | D30: =C30*J3 -> 660.24957
B31: Total liquidity | C31: =SUM(C30:C30) -> 611569.36 | D31: =SUM(D30:D30) -> 660.24957
B34: Debt Maturity | C34: CLP millions | D34: USD mn
B35: 1 year | C35: =C13+C14 -> 120403.68 | D35: =C35*$J3 -> 129.98767
B36: >1-3 years | C36: =33144.521+14984.664 -> 48129.185 | D36: =C36*$J3 -> 51.960211
B37: >3-5 years | C37: =3687.815+80599.741 -> 84287.556 | D37: =C37*$J3 -> 90.996746
B38: More than 5 years | C38: =3448.046+910400.872 -> 913848.92 | D38: =C38*$J3 -> 986.59021
B39: Total | C39: =SUM(C35:C38) -> 1166669.3 | D39: =SUM(D35:D38) -> 1259.5348
B40: check | C40: =C39-C8-C12 -> 0
B43: Bank Borrowings
B44: Company | C44: Creditor name | D44: Interest rate | E44: CLP millions | F44: USD mn
B45: Current:
B46: Viña San Pedro Tarapacá S.A | C46: Banco Itaú | D46: 0.0143 | E46: 59736.308 | F46: =E46*$J3 -> 64.491248
B47: Cervecería Kunstmann S.A. | C47: Banco Itaú | D47: 0.0546 | E47: 2020.93 | F47: =E47*$J3 -> 2.1817936
B48: Cervecería Kunstmann S.A. | C48: Banco del Estado de Chile | D48: 0.062 | E48: 2035.133 | F48: =E48*$J3 -> 2.1971272
B49: Cervecería Kunstmann S.A. | C49: Banco del Estado de Chile | D49: 0.0627 | E49: 1017.765 | F49: =E49*$J3 -> 1.0987779
B50: Cervecería Kunstmann S.A. | C50: Banco del Estado de Chile | D50: 0.06074 | E50: 43.836 | F50: =E50*$J3 -> 0.047325294
B51: Cervecería Kunstmann S.A. | C51: Banco Itaú | D51: 0.0614 | E51: 3005.961 | F51: =E51*$J3 -> 3.245232
B52: Cervecería Kunstmann S.A. | C52: Banco del Estado de Chile | D52: 0.0633 | E52: 98.021 | F52: =E52*$J3 -> 0.10582336
B53: Compañía Pisquera de Chile S.A. | C53: Banco del Estado de Chile | D53: 0.0586 | E53: 164.08 | F53: =E53*$J3 -> 0.17714057
B54: Aguas de Origen S.A. | C54: Banco BBVA | D54: 0.22 | E54: 2381.71 | F54: =E54*$J3 -> 2.5712913
B55: Aguas de Origen S.A. | C55: Banco Patagonia | D55: 0.22 | E55: 5332.367 | F55: =E55*$J3 -> 5.7568171
B56: Finca La Celia S.A. | C56: Banco BBVA | D56: 0.22 | E56: 1005.854 | F56: =E56*$J3 -> 1.0859188
B57: Finca La Celia S.A. | C57: Banco BBVA | D57: 0.065 | E57: 569.557 | F57: =E57*$J3 -> 0.61489307
B58: Finca La Celia S.A. | C58: Banco Patagonia | D58: 0.235 | E58: 1847.085 | F58: =E58*$J3 -> 1.9941108
B59: Finca La Celia S.A. | C59: Banco Santander | D59: 0.25 | E59: 1004.734 | F59: =E59*$J3 -> 1.0847096
B60: Finca La Celia S.A. | C60: Banco Supervielle | D60: 0.0595 | E60: 565.457 | F60: =E60*$J3 -> 0.61046671
B61: Finca La Celia S.A. | C61: Banco Supervielle | D61: 0.0595 | E61: 752.249 | F61: =E61*$J3 -> 0.81212713
B62: Finca La Celia S.A. | C62: Banco Supervielle | D62: 0.0595 | E62: 562.1 | F62: =E62*$J3 -> 0.6068425
B63: Finca La Celia S.A. | C63: Banco Macro | D63: 0.24 | E63: 669.926 | F63: =E63*$J3 -> 0.72325132
B64: Finca La Celia S.A. | C64: Banco Galicia | D64: 0.235 | E64: 167.181 | F64: =E64*$J3 -> 0.18048841
B65: Bebidas Bolivianas BBO S.A. | C65: Banco Mercantil Santa Cruz S.A. | D65: 0.055 | E65: 47.802 | F65: =E65*$J3 -> 0.051606983
B66: Bebidas Bolivianas BBO S.A. | C66: Banco Mercantil Santa Cruz S.A. | D66: 0.05 | E66: 31.99 | F66: =E66*$J3 -> 0.034536366
B67: Bebidas Bolivianas BBO S.A. | C67: Banco Mercantil Santa Cruz S.A. | D67: 0.055 | E67: 16.832 | F67: =E67*$J3 -> 0.018171807
B68: Bebidas Bolivianas BBO S.A. | C68: Banco Mercantil Santa Cruz S.A. | D68: 0.055 | E68: 22.249 | F68: =E68*$J3 -> 0.024019994
B69: Bebidas Bolivianas BBO S.A. | C69: Banco Mercantil Santa Cruz S.A. | D69: 0.0595 | E69: 487.969 | F69: =E69*$J3 -> 0.52681076
B70: Bebidas Bolivianas BBO S.A. | C70: Banco Mercantil Santa Cruz S.A. | D70: 0.0595 | E70: 243.984 | F70: =E70*$J3 -> 0.26340484
B71: Bebidas Bolivianas BBO S.A. | C71: Banco Mercantil Santa Cruz S.A. | D71: 0.0595 | E71: 66.219 | F71: =E71*$J3 -> 0.071489954
B72: Bebidas Bolivianas BBO S.A. | C72: Banco Mercantil Santa Cruz S.A. | D72: 0.0595 | E72: 100.79 | F72: =E72*$J3 -> 0.10881277
B73: Bebidas Bolivianas BBO S.A. | C73: Banco Mercantil Santa Cruz S.A. | D73: 0.0995 | E73: 189.013 | F73: =E73*$J3 -> 0.20405821
B74: Bebidas Bolivianas BBO S.A. | C74: Banco Mercantil Santa Cruz S.A. | D74: 0.0995 | E74: 521.156 | F74: =E74*$J3 -> 0.5626394
B75: Bebidas Bolivianas BBO S.A. | C75: Banco Mercantil Santa Cruz S.A. | D75: 0.0995 | E75: 494.173 | F75: =E75*$J3 -> 0.53350859
B76: Bebidas Bolivianas BBO S.A. | C76: Banco Mercantil Santa Cruz S.A. | D76: 0.0995 | E76: 245.768 | F76: =E76*$J3 -> 0.26533084
B77: Bebidas Bolivianas BBO S.A. | C77: Banco Mercantil Santa Cruz S.A. | D77: 0.0995 | E77: 152.559 | F77: =E77*$J3 -> 0.16470252
B78: Bebidas Bolivianas BBO S.A. | C78: Banco Mercantil Santa Cruz S.A. | D78: 0.0995 | E78: 251.768 | F78: =E78*$J3 -> 0.27180844
B79: Total | E79: =SUM(E46:E78) -> 85852.526 | F79: =SUM(F46:F78) -> 92.686286
B80: Check | E80: =E79-C13 -> 0
B82: Non-current:
B83: Cervecería Kunstmann S.A. | C83: Banco del Estado de Chile | D83: 0.0607 | E83: 6746.067 | F83: =E83*$J3 -> 7.283046
B84: Cervecería Kunstmann S.A. | C84: Banco del Estado de Chile | D84: 0.0633 | E84: 5989.281 | F84: =E84*$J3 -> 6.4660207
B85: Compañía Pisquera de Chile S.A. | C85: Banco del Estado de Chile | D85: 0.0586 | E85: 16000 | F85: =E85*$J3 -> 17.273581
B86: Bebidas Bolivianas BBO S.A. | C86: Banco Mercantil Santa Cruz S.A. | D86: 0.055 | E86: 3120.078 | F86: =E86*$J3 -> 3.3684325
B87: Bebidas Bolivianas BBO S.A. | C87: Banco Mercantil Santa Cruz S.A. | D87: 0.05 | E87: 6244.488 | F87: =E87*$J3 -> 6.7415419
B88: Bebidas Bolivianas BBO S.A. | C88: Banco Mercantil Santa Cruz S.A. | D88: 0.055 | E88: 1147.615 | F88: =E88*$J3 -> 1.2389638
B89: Bebidas Bolivianas BBO S.A. | C89: Banco Mercantil Santa Cruz S.A. | D89: 0.055 | E89: 1032.853 | F89: =E89*$J3 -> 1.1150669
B90: Total | E90: =SUM(E83:E89) -> 40280.382 | F90: =SUM(F83:F89) -> 43.486653
B91: Check | E91: =E90-C9 -> 0
B94: Bond payable
B95: Company | D95: Interest rate | E95: CLP millions | F95: USD mn
B96: Current:
B97: Compañía Cervecerías Unidas S.A. | D97: 0.029 | E97: 483.513 | F97: =E97*$J3 -> 0.52200006
B98: Compañía Cervecerías Unidas S.A. | D98: 0.012 | E98: 30294.075 | F98: =E98*$J3 -> 32.705448
B99: Compañía Cervecerías Unidas S.A. | D99: 0.016 | E99: 703.239 | F99: =E99*$J3 -> 0.759216
B100: Compañía Cervecerías Unidas S.A. | D100: 0.0335 | E100: 2797.466 | F100: =E100*$J3 -> 3.020141
B101: Compañía Cervecerías Unidas S.A. | D101: 0.027 | E101: 133.517 | F101: =E101*$J3 -> 0.1441448
B102: Compañía Cervecerías Unidas S.A. | D102: 0.0335 | E102: 139.346 | F102: =E102*$J3 -> 0.15043778
B103: Total | E103: =SUM(E97:E102) -> 34551.156 | F103: =SUM(F97:F102) -> 37.301387
B104: Check | E104: =E103-C14 -> 0
B106: Non-current:
B107: Compañía Cervecerías Unidas S.A. | D107: 0.029 | E107: 119628.14 | F107: =E107*$J3 -> 129.15039
B108: Compañía Cervecerías Unidas S.A. | D108: 0.012 | E108: 14984.664 | F108: =E108*$J3 -> 16.177426
B109: Compañía Cervecerías Unidas S.A. | D109: 0.016 | E109: 80599.741 | F109: =E109*$J3 -> 87.015385
B110: Compañía Cervecerías Unidas S.A. | D110: 0.0335 | E110: 552252.38 | F110: =E110*$J3 -> 596.21102
B111: Compañía Cervecerías Unidas S.A. | D111: 0.027 | E111: 158683.13 | F111: =E111*$J3 -> 171.31412
B112: Compañía Cervecerías Unidas S.A. | D112: 0.0335 | E112: 79837.224 | F112: =E112*$J3 -> 86.192173
B113: Total | E113: =SUM(E107:E112) -> 1005985.3 | F113: =SUM(F107:F112) -> 1086.0605
B114: Check | E114: =E113-C10 -> 0
A118: 4Q25 | I118: Exchange rate as at end | J118: =Model!$I$203 -> 0.0010795988
I119: LTM Average exchange rate | J119: =Model!$I$204 -> 0.0010682761
...

Sheet Model
B2: Compañía Cervecerías Unidas S.A. | C2: Annual | D2: Annual | E2: Annual | F2: Annual | G2: Annual | H2: Annual | I2: LTM | K2: Quarters | L2: Quarters | M2: Quarters | N2: Quarters | O2: Quarters | P2: Quarters | Q2: Quarters | R2: Quarters | S2: Quarters | T2: Quarters | U2: Quarters | V2: Quarters | W2: Quarters | X2: Quarters | Y2: Quarters | Z2: Quarters | AA2: Quarters | AB2: Quarters | AC2: Quarters | AD2: Quarters | AE2: Quarters
B3: (CLP millions) | C3: 44196 | D3: 44561 | E3: 44926 | F3: 45291 | G3: 45657 | H3: 46022 | I3: =AE3 -> 46112 | K3: 44286 | L3: 44377 | M3: 44469 | N3: 44561 | O3: 44651 | P3: 44742 | Q3: 44834 | R3: 44926 | S3: 45016 | T3: 45107 | U3: 45199 | V3: 45291 | W3: 45382 | X3: 45473 | Y3: 45565 | Z3: 45657 | AA3: 45747 | AB3: 45838 | AC3: 45930 | AD3: 46022 | AE3: 46112
C4: Act | D4: Act | E4: Act | F4: Act | G4: Act | H4: Act | I4: Act | K4: Act | L4: Act | M4: Act | N4: Act | O4: Act | P4: Act | Q4: Act | R4: Act | S4: Act | T4: Act | U4: Act | V4: Act | W4: Act | X4: Act | Y4: Act | Z4: Act | AA4: Act | AB4: Act | AC4: Act | AD4: Act | AE4: Act
C5: FY | D5: FY | E5: FY | F5: FY | G5: FY | H5: FY | I5: LTM | K5: 1Q | L5: 2Q | M5: 3Q | N5: 4Q | O5: 1Q | P5: 2Q | Q5: 3Q | R5: 4Q | S5: 1Q | T5: 2Q | U5: 3Q | V5: 4Q | W5: 1Q | X5: 2Q | Y5: 3Q | Z5: 4Q | AA5: 1Q | AB5: 2Q | AC5: 3Q | AD5: 4Q | AE5: 1Q
B6: INCOME STATEMENT
B7: Revenue | C7: 1857593.7 | D7: 2484712.3 | E7: 2711434.9 | F7: 2565556.1 | G7: 2904566.5 | H7: 2909625.4 | I7: =AE7+AB7+AC7+AD7 -> 2911470.1 | K7: 569639.46 | L7: 469994.59 | M7: 622729.63 | N7: =D7-SUM(K7:M7) -> 822348.61 | O7: 700464.93 | P7: 558502.88 | Q7: 684105.54 | R7: =E7-SUM(O7:Q7) -> 768361.6 | S7: 732030.76 | T7: 574241.7 | U7: 686676.91 | V7: =F7-SUM(S7:U7) -> 572606.7 | W7: =746023.982 -> 746023.98 | X7: 524641.48 | Y7: 665823.27 | Z7: =G7-SUM(W7:Y7) -> 968077.72 | AA7: 817670.59 | AB7: 579913.9 | AC7: 658627.85 | AD7: =H7-SUM(AA7:AC7) -> 853413.1 | AE7: 819515.28
B8: % of growth | D8: =(D7/C7)-1 -> 0.3375973 | E8: =(E7/D7)-1 -> 0.091247051 | F8: =(F7/E7)-1 -> -0.053801358 | G8: =(G7/F7)-1 -> 0.13213915 | H8: =(H7/G7)-1 -> 0.0017417381 | O8: =(O7/K7)-1 -> 0.22966365 | P8: =(P7/L7)-1 -> 0.1883177 | Q8: =(Q7/M7)-1 -> 0.09855948 | R8: =(R7/N7)-1 -> -0.065649788 | S8: =(S7/O7)-1 -> 0.04506411 | T8: =(T7/P7)-1 -> 0.028180372 | U8: =(U7/Q7)-1 -> 0.0037587344 | V8: =(V7/R7)-1 -> -0.25476924 | ... AE8: =(AE7/AA7)-1 -> 0.0022560283
B9: Cost of sales | C9: -984035.92 | D9: -1291559.8 | E9: -1514925.3 | F9: -1378612 | G9: -1590957.8 | H9: -1618034.2 | I9: =AE9+AB9+AC9+AD9 -> -1614537.9 | K9: -280270.89 | L9: -249566.84 | M9: -330148.4 | N9: =D9-SUM(K9:M9) -> -431573.67 | O9: -376740.25 | P9: -333194.47 | Q9: -391714.49 | R9: =E9-SUM(O9:Q9) -> -413276.09 | S9: -377085.58 | T9: -324826.38 | U9: -368362.24 | V9: =F9-SUM(S9:U9) -> -308337.77 | W9: =-(393897.326) -> -393897.33 | X9: -314528.12 | Y9: -377538.5 | Z9: =G9-SUM(W9:Y9) -> -504993.83 | AA9: -435489.18 | AB9: -343082.28 | AC9: -378691.84 | AD9: =H9-SUM(AA9:AC9) -> -460770.92 | AE9: -431992.86
B10: Gross Profit | C10: =C7+C9 -> 873557.76 | D10: =D7+D9 -> 1193152.5 | E10: =E7+E9 -> 1196509.6 | F10: =F7+F9 -> 1186944.1 | G10: =G7+G9 -> 1313608.7 | H10: =H7+H9 -> 1291591.2 | I10: =I7+I9 -> 1296932.2 | K10: =K7+K9 -> 289368.56 | L10: =L7+L9 -> 220427.75 | M10: =M7+M9 -> 292581.23 | N10: =N7+N9 -> 390774.94 | O10: =O7+O9 -> 323724.68 | P10: =P7+P9 -> 225308.41 | Q10: =Q7+Q9 -> 292391.04 | R10: =R7+R9 -> 355085.51 | ... AE10: =AE7+AE9 -> 387522.42
B11: Gross Profit margin | C11: =C10/C7 -> 0.4702631 | D11: =D10/D7 -> 0.48019744 | E11: =E10/E7 -> 0.44128281 | F11: =F10/F7 -> 0.46264594 | G11: =G10/G7 -> 0.45225637 | H11: =H10/H7 -> 0.44390292 | I11: =I10/I7 -> 0.44545614 | K11: =K10/K7 -> 0.50798546 | L11: =L10/L7 -> 0.46900061 | M11: =M10/M7 -> 0.4698367 | N11: =N10/N7 -> 0.47519378 | O11: =O10/O7 -> 0.46215687 | P11: =P10/P7 -> 0.40341494 | Q11: =Q10/Q7 -> 0.42740634 | R11: =R10/R7 -> 0.46213334 | ... AE11: =AE10/AE7 -> 0.47286784
B12: Operating expenses:
B13: Other income | C13: 19295.892 | D13: 11808.439 | E13: 5284.666 | F13: 4419.789 | G13: 40211.51 | H13: 11829.734 | I13: =AE13+AB13+AC13+AD13 -> 9378.399 | K13: 4561.577 | L13: 567.084 | M13: 4108.153 | N13: =D13-SUM(K13:M13) -> 2571.625 | O13: 814.593 | P13: 1114.213 | Q13: 1548.689 | R13: =E13-SUM(O13:Q13) -> 1807.171 | S13: 801.632 | T13: 847.974 | U13: 1159.522 | V13: =F13-SUM(S13:U13) -> 1610.661 | W13: =1064.779 -> 1064.779 | X13: 32676.846 | Y13: 1268.001 | Z13: =G13-SUM(W13:Y13) -> 5201.884 | AA13: 4875.644 | AB13: 1387.728 | AC13: 1115.279 | AD13: =H13-SUM(AA13:AC13) -> 4451.083 | AE13: 2424.309
B14: Distribution costs | C14: -337101.55 | D14: -438601.94 | E14: -504184.25 | F14: -470120.81 | G14: -536420.14 | H14: -547393.15 | I14: =AE14+AB14+AC14+AD14 -> -550250.65 | K14: -95679.199 | L14: -85926.112 | M14: -111353.57 | N14: =D14-SUM(K14:M14) -> -145643.06 | O14: -122682.67 | P14: -108715.38 | Q14: -132334.85 | R14: =E14-SUM(O14:Q14) -> -140451.36 | S14: -138549.18 | T14: -116809.79 | U14: -122158.33 | V14: =F14-SUM(S14:U14) -> -92603.519 | W14: =(-134752.73) -> -134752.73 | X14: -112936.63 | Y14: -126083.58 | Z14: =G14-SUM(W14:Y14) -> -162647.2 | AA14: -148691.25 | AB14: -121478.43 | AC14: -124892.65 | AD14: =H14-SUM(AA14:AC14) -> -152330.83 | AE14: -151548.75
B15: Administrative expenses | C15: -138811.67 | D15: -161390.78 | E15: -187421.8 | F15: -197256.57 | G15: -214915.09 | H15: -205911.74 | I15: =AE15+AB15+AC15+AD15 -> -211725.68 | K15: -32461.71 | L15: -34744.59 | M15: -41787.512 | N15: =D15-SUM(K15:M15) -> -52396.967 | O15: -35449.088 | P15: -45691.984 | Q15: -54960.501 | R15: =E15-SUM(O15:Q15) -> -51320.223 | S15: -32358.416 | T15: -52476.442 | U15: -62630.221 | V15: =F15-SUM(S15:U15) -> -49791.492 | W15: =-(42611.167) -> -42611.167 | X15: -56689.94 | Y15: -57729.046 | Z15: =G15-SUM(W15:Y15) -> -57884.936 | AA15: -52433.131 | AB15: -54706.522 | AC15: -44928.956 | AD15: =H15-SUM(AA15:AC15) -> -53843.13 | AE15: -58247.067
B16: Other expenses by function | C16: -230349.57 | D16: -284087.36 | E16: -278757.1 | F16: -270703.33 | G16: -339783.07 | H16: -329266.8 | I16: =AE16+AB16+AC16+AD16 -> -323585.04 | K16: -66040.26 | L16: -65654.567 | M16: -72084.366 | N16: =D16-SUM(K16:M16) -> -80308.165 | O16: -60512.679 | P16: -73686.271 | Q16: -73113.137 | R16: =E16-SUM(O16:Q16) -> -71445.018 | S16: -80616.94 | T16: -68025.521 | U16: -83614.081 | V16: =F16-SUM(S16:U16) -> -38446.792 | W16: =(-86913.343) -> -86913.343 | X16: -70719.768 | Y16: -72111.628 | Z16: =G16-SUM(W16:Y16) -> -110038.33 | AA16: -94049.42 | AB16: -79374.07 | AC16: -74837.454 | AD16: =H16-SUM(AA16:AC16) -> -81005.853 | AE16: -88367.661
B17: Other gains (losses) | C17: -11410.085 | D17: 9590.45 | E17: -12669.54 | F17: -13316.208 | G17: -94.937 | H17: -27672.922 | I17: =AE17+AB17+AC17+AD17 -> -14296.718 | K17: -1040.928 | L17: 1738.588 | M17: 7304.058 | N17: =D17-SUM(K17:M17) -> 1588.732 | O17: -8991.582 | P17: 13516.855 | Q17: 1328.953 | R17: =E17-SUM(O17:Q17) -> -18523.766 | S17: -7452.796 | T17: -2873.551 | U17: 5063.367 | V17: =F17-SUM(S17:U17) -> -8053.228 | W17: =1064.348 -> 1064.348 | X17: -5256.413 | Y17: -4311.792 | Z17: =G17-SUM(W17:Y17) -> 8408.92 | AA17: -7444.459 | AB17: -9465.32 | AC17: 4187.269 | AD17: =H17-SUM(AA17:AC17) -> -14950.412 | AE17: 5931.745
B18: Operating profit | C18: =C10+SUM(C13:C17) -> 175180.78 | D18: =D10+SUM(D13:D17) -> 330471.3 | E18: =E10+SUM(E13:E17) -> 218761.62 | F18: =F10+SUM(F13:F17) -> 239966.97 | G18: =G10+SUM(G13:G17) -> 262606.95 | H18: =H10+SUM(H13:H17) -> 193176.34 | I18: =I10+SUM(I13:I17) -> 206452.55 | K18: 94146.466 | L18: 35841.066 | M18: 74659.845 | N18: =N10+SUM(N14:N17) -> 114015.48 | O18: =O10+SUM(O14:O17) -> 96088.659 | P18: =P10+SUM(P14:P17) -> 10731.635 | Q18: =Q10+SUM(Q14:Q17) -> 33311.509 | R18: =R10+SUM(R14:R17) -> 73345.147 | S18: =S10+SUM(S14:S17) -> 95967.851 | T18: =T10+SUM(T14:T17) -> 9230.02 | U18: =U10+SUM(U13:U17) -> 56134.93 | V18: =V10+SUM(V13:V17) -> 76984.56 | W18: =W10+SUM(W13:W17) -> 89978.543 | X18: =X10+SUM(X13:X17) -> -2812.544 | Y18: =Y10+SUM(Y13:Y17) -> 29316.724 | Z18: =Z10+SUM(Z13:Z17) -> 146124.23 | AA18: =AA10+SUM(AA13:AA17) -> 84438.794 | AB18: =AB10+SUM(AB13:AB17) -> -26804.989 | ... AE18: =AE10+SUM(AE13:AE17) -> 97715
B19: Finance income | C19: 3451.143 | D19: 14263.669 | E19: 22870.538 | F19: 39402.492 | G19: 38102.053 | H19: 27522.243 | I19: =AE19+AB19+AC19+AD19 -> 23045.073 | K19: 3352.77 | L19: 3464.805 | M19: 2689.372 | N19: =D19-SUM(K19:M19) -> 4756.722 | O19: 6348.294 | P19: 6505.17 | Q19: 4680.264 | R19: =E19-SUM(O19:Q19) -> 5336.81 | S19: 10393.133 | T19: 13458.819 | U19: 10560.575 | V19: =F19-SUM(S19:U19) -> 4989.965 | W19: =12703.221 -> 12703.221 | X19: 9103.863 | Y19: 7834.17 | Z19: =G19-SUM(W19:Y19) -> 8460.799 | AA19: 9495.959 | AB19: 7982.055 | AC19: 5392.814 | AD19: =H19-SUM(AA19:AC19) -> 4651.415 | AE19: 5018.789
B20: Finance exps | C20: -28714.063 | D20: -35660.493 | E20: -75930.875 | F20: -77023.048 | G20: -97165.278 | H20: -79947.714 | I20: =AE20+AB20+AC20+AD20 -> -77524.639 | K20: -7168.197 | L20: -6941.675 | M20: -8903.459 | N20: =D20-SUM(K20:M20) -> -12647.162 | O20: -12718.817 | P20: -17018.053 | Q20: -23375.161 | R20: =E20-SUM(O20:Q20) -> -22818.844 | S20: -20451.345 | T20: -19000.454 | U20: -21375.537 | V20: =F20-SUM(S20:U20) -> -16195.712 | W20: =-19368.518 -> -19368.518 | X20: -21389.854 | Y20: -27687.403 | Z20: =G20-SUM(W20:Y20) -> -28719.503 | AA20: -20752.884 | AB20: -18154.517 | AC20: -20330.452 | AD20: =H20-SUM(AA20:AC20) -> -20709.861 | AE20: -18329.809
B21: Share of profit of equity-accounted investees | C21: -8437.209 | D21: 226.026 | E21: -10978.068 | F21: -19217.758 | G21: -9494.703 | H21: -14352.591 | I21: =AE21+AB21+AC21+AD21 -> -15194.615 | K21: -596.475 | L21: -1752.132 | M21: -1013.287 | N21: =D21-SUM(K21:M21) -> 3587.92 | O21: -564.64 | P21: -3837.066 | Q21: -3495.437 | R21: =E21-SUM(O21:Q21) -> -3080.925 | S21: -3818.77 | T21: -6179.91 | U21: -11709.227 | V21: =F21-SUM(S21:U21) -> 2490.149 | W21: =(-3317.839) -> -3317.839 | X21: -2577.643 | Y21: -530.841 | Z21: =G21-SUM(W21:Y21) -> -3068.38 | AA21: -1517.971 | AB21: -6064.957 | AC21: -5357.183 | AD21: =H21-SUM(AA21:AC21) -> -1412.48 | AE21: -2359.995
B22: Gains (losses) on exchange differences | C22: 2551.823 | D22: -10149.345 | E22: -20173.381 | F22: -65944.57 | G22: -17797.269 | H22: 1473.55 | I22: =AE22+AB22+AC22+AD22 -> 7.988 | K22: -1387.312 | L22: -1378.951 | M22: -4483.454 | N22: =D22-SUM(K22:M22) -> -2899.628 | O22: 1594.225 | P22: -11430.455 | Q22: -8095.775 | R22: =E22-SUM(O22:Q22) -> -2241.376 | S22: -4327.369 | T22: -7117.365 | U22: -24484.632 | V22: =F22-SUM(S22:U22) -> -30015.204 | W22: =(-8467.435) -> -8467.435 | X22: 1.628 | Y22: 4573.011 | Z22: =G22-SUM(W22:Y22) -> -13904.473 | AA22: -444.237 | AB22: 1916.962 | AC22: -9350.023 | AD22: =H22-SUM(AA22:AC22) -> 9350.848 | AE22: -1909.799
B23: Result as per adjustment units | C23: -429.198 | D23: 2529.298 | E23: 1198.565 | F23: -14025.895 | G23: -10722.033 | H23: -17631.014 | I23: =AE23+AB23+AC23+AD23 -> -14480.093 | K23: 67.942 | L23: 729.558 | M23: 551.589 | N23: =D23-SUM(K23:M23) -> 1180.209 | O23: -3591.675 | P23: -1480.671 | Q23: 4641.027 | R23: =E23-SUM(O23:Q23) -> 1629.884 | S23: -1656.078 | T23: -3533.385 | U23: -692.545 | V23: =F23-SUM(S23:U23) -> -8143.887 | W23: =(-1879.441) -> -1879.441 | X23: -3395.306 | Y23: 54.079 | Z23: =G23-SUM(W23:Y23) -> -5501.365 | AA23: -6017.421 | AB23: -6474.768 | AC23: -2553.246 | AD23: =H23-SUM(AA23:AC23) -> -2585.579 | AE23: -2866.5
B24: Other expenses | C24: 0 | D24: 0 | E24: 0 | F24: 0 | G24: 0 | H24: 0 | I24: =AE24+AB24+AC24+AD24 -> 0 | K24: 0 | L24: 0 | M24: 0 | N24: =D24-SUM(K24:M24) -> 0 | O24: 0 | P24: 0 | Q24: 0 | R24: =E24-SUM(O24:Q24) -> 0 | U24: 0 | V24: =F24-SUM(S24:U24) -> 0 | W24: 0 | Y24: 0 | Z24: =G24-SUM(W24:Y24) -> 0 | AA24: 0 | AB24: 0 | AC24: 0 | AD24: =H24-SUM(AA24:AC24) -> 0 | AE24: 0
B25: Profit before tax | C25: =C18+SUM(C19:C24) -> 143603.28 | D25: =D18+SUM(D19:D24) -> 301680.45 | E25: =E18+SUM(E19:E24) -> 135748.39 | F25: =F18+SUM(F19:F24) -> 103158.19 | G25: =G18+SUM(G19:G24) -> 165529.72 | H25: =H18+SUM(H19:H24) -> 110240.82 | I25: =I18+SUM(I19:I24) -> 122306.26 | K25: 92976.771 | L25: 30529.755 | M25: 67608.759 | N25: =N18+SUM(N19:N24) -> 107993.54 | O25: =O18+SUM(O19:O24) -> 87156.046 | P25: =P18+SUM(P19:P24) -> -16529.44 | Q25: =Q18+SUM(Q19:Q24) -> 7666.427 | R25: =R18+SUM(R19:R24) -> 52170.696 | S25: =S18+SUM(S19:S24) -> 76107.422 | T25: =T18+SUM(T19:T24) -> -13142.275 | U25: =U18+SUM(U19:U24) -> 8433.564 | ... AE25: =AE18+SUM(AE19:AE24) -> 77267.686
B26: Income tax (expense)/benefit | C26: -35408.42 | D26: -82629.773 | E26: -263.943 | F26: 15267.255 | G26: 11015.074 | H26: 27051.867 | I26: =AE26+AB26+AC26+AD26 -> 12546.153 | K26: -23531.533 | L26: -7973.321 | M26: -20856.945 | N26: =D26-SUM(K26:M26) -> -30267.974 | O26: -17564.609 | P26: 8020.38 | Q26: 10185.069 | R26: =E26-SUM(O26:Q26) -> -904.783 | S26: -15347.635 | T26: 8695.389 | U26: 4226.575 | V26: =F26-SUM(S26:U26) -> 17692.926 | W26: =(-14620.924) -> -14620.924 | X26: 27900.465 | Y26: 18994.161 | Z26: =G26-SUM(W26:Y26) -> -21258.628 | AA26: -3714.274 | AB26: 36387.682 | AC26: 12304.256 | AD26: =H26-SUM(AA26:AC26) -> -17925.797 | AE26: -18219.988
B27: Net profit/loss | C27: =+C25+C26 -> 108194.86 | D27: =+D25+D26 -> 219050.68 | E27: =+E25+E26 -> 135484.45 | F27: =+F25+F26 -> 118425.44 | G27: =+G25+G26 -> 176544.8 | H27: =+H25+H26 -> 137292.68 | I27: =+I25+I26 -> 134852.42 | K27: 69445.238 | L27: 22556.434 | M27: 46751.814 | N27: =+N25+N26 -> 77725.57 | O27: =+O25+O26 -> 69591.437 | P27: =+P25+P26 -> -8509.06 | Q27: =+Q25+Q26 -> 17851.496 | R27: =+R25+R26 -> 51265.913 | S27: =+S25+S26 -> 60759.787 | T27: =+T25+T26 -> -4446.886 | U27: =+U25+U26 -> 12660.139 | ... AE27: =+AE25+AE26 -> 59047.698
B28: % margin | C28: =+C27/C7 -> 0.05824463 | D28: =+D27/D7 -> 0.088159375 | E28: =+E27/E7 -> 0.049967805 | F28: =+F27/F7 -> 0.046159756 | G28: =+G27/G7 -> 0.060781807 | H28: =+H27/H7 -> 0.04718569 | I28: =+I27/I7 -> 0.046317637 | K28: 0.12191086 | L28: 0.047992966 | M28: 0.075075622 | N28: =+N27/N7 -> 0.09451657 | O28: =+O27/O7 -> 0.099350351 | P28: =+P27/P7 -> -0.015235481 | Q28: =+Q27/Q7 -> 0.026094652 | R28: =+R27/R7 -> 0.066721076 | S28: =+S27/S7 -> 0.083001686 | T28: =+T27/T7 -> -0.0077439273 | U28: =+U27/U7 -> 0.018436821 | ... AE28: =+AE27/AE7 -> 0.072051979
B29: Non-controlling interest | C29: -12042.584 | D29: -19887.95 | E29: -17316.101 | F29: -12772.715 | G29: -15600.659 | H29: -20140.477 | I29: =AE29+AB29+AC29+AD29 -> -21621.842 | K29: -5061.367 | L29: -3588.571 | M29: -4583.744 | N29: =D29-SUM(K29:M29) -> -6654.268 | O29: -5861.566 | P29: -3060.295 | Q29: -2174.103 | R29: =E29-SUM(O29:Q29) -> -6220.137 | S29: -3193.432 | T29: -344.586 | U29: -3161.322 | V29: =F29-SUM(S29:U29) -> -6073.375 | W29: =-2824.874 -> -2824.874 | X29: -1790.357 | Y29: 3005.456 | Z29: =G29-SUM(W29:Y29) -> -13990.884 | AA29: -3710.358 | AB29: -5.49 | AC29: -5189.17 | AD29: =H29-SUM(AA29:AC29) -> -11235.459 | AE29: -5191.723
B30: Net profit/loss | C30: =+C27+C29 -> 96152.272 | D30: =+D27+D29 -> 199162.73 | E30: =+E27+E29 -> 118168.35 | F30: =+F27+F29 -> 105652.73 | G30: =+G27+G29 -> 160944.14 | H30: =+H27+H29 -> 117152.21 | I30: =+I27+I29 -> 113230.57 | K30: 64383.871 | L30: 18967.863 | M30: 42168.07 | N30: =+N27+N29 -> 71071.302 | O30: =+O27+O29 -> 63729.871 | P30: =+P27+P29 -> -11569.355 | Q30: =+Q27+Q29 -> 15677.393 | R30: =+R27+R29 -> 45045.776 | S30: =+S27+S29 -> 57566.355 | T30: =+T27+T29 -> -4791.472 | U30: =+U27+U29 -> 9498.817 | ... AE30: =+AE27+AE29 -> 53855.975
B32: % of sales or stated otherwise
B33: =B14 -> Distribution costs | C33: =-C14/C7 -> 0.18147217 | D33: =-D14/D7 -> 0.17652021 | E33: =-E14/E7 -> 0.18594739 | F33: =-F14/F7 -> 0.18324324 | G33: =-G14/G7 -> 0.18468166 | H33: =-H14/H7 -> 0.18813183 | I33: =-I14/I7 -> 0.18899409 | K33: =-K14/K7 -> 0.16796449 | L33: =-L14/L7 -> 0.18282362 | M33: =-M14/M7 -> 0.17881527 | N33: =-N14/N7 -> 0.17710623 | O33: =-O14/O7 -> 0.17514463 | P33: =-P14/P7 -> 0.19465499 | Q33: =-Q14/Q7 -> 0.19344215 | R33: =-R14/R7 -> 0.18279331 | ... AE33: =-AE14/AE7 -> 0.18492486
B34: =B15 -> Administrative expenses | C34: =-C15/C7 -> 0.074726604 | D34: =-D15/D7 -> 0.064953508 | E34: =-E15/E7 -> 0.069122734 | F34: =-F15/F7 -> 0.076886478 | G34: =-G15/G7 -> 0.07399214 | H34: =-H15/H7 -> 0.070769157 | I34: =-I15/I7 -> 0.072721225 | K34: =-K15/K7 -> 0.056986414 | L34: =-L15/L7 -> 0.073925511 | M34: =-M15/M7 -> 0.06710378 | N34: =-N15/N7 -> 0.063716247 | O34: =-O15/O7 -> 0.050607941 | P34: =-P15/P7 -> 0.081811545 | Q34: =-Q15/Q7 -> 0.080339214 | R34: =-R15/R7 -> 0.066791759 | ... AE34: =-AE15/AE7 -> 0.071075023
B35: =B16 -> Other expenses by function | C35: =-C16/C7 -> 0.12400428 | D35: =-D16/D7 -> 0.11433411 | E35: =-E16/E7 -> 0.10280796 | F35: =-F16/F7 -> 0.10551449 | G35: =-G16/G7 -> 0.11698237 | H35: =-H16/H7 -> 0.11316467 | I35: =-I16/I7 -> 0.11114146 | K35: =-K16/K7 -> 0.11593344 | L35: =-L16/L7 -> 0.13969218 | M35: =-M16/M7 -> 0.11575548 | N35: =-N16/N7 -> 0.097657081 | O35: =-O16/O7 -> 0.086389306 | P35: =-P16/P7 -> 0.13193535 | Q35: =-Q16/Q7 -> 0.10687406 | R35: =-R16/R7 -> 0.092983588 | ... AE35: =-AE16/AE7 -> 0.10782918
B36: Finance exps as % of debt | C36: =-C20/C108 -> 0.062650334 | D36: =-D20/D108 -> 0.066223149 | E36: =-E20/E108 -> 0.056999551 | F36: =-F20/F108 -> 0.059797792 | G36: =-G20/G108 -> 0.071165523 | H36: =-H20/H108 -> 0.066730309 | I36: =-I20/I108 -> 0.066449538 | N36: =-SUM(K20:N20)/N108 -> 0.066223149 | O36: =-SUM(L20:O20)/O108 -> 0.040440843 | P36: =-SUM(M20:P20)/P108 -> 0.042637557 | Q36: =-SUM(N20:Q20)/Q108 -> 0.050224194 | R36: =-SUM(O20:R20)/R108 -> 0.056999551 | S36: =-SUM(P20:S20)/S108 -> 0.066731718 | T36: =-SUM(Q20:T20)/T108 -> 0.066015632 | U36: =-SUM(R20:U20)/U108 -> 0.063494599 | ... AE36: =-SUM(AB20:AE20)/AE108 -> 0.066449538
B37: Finance income as % of cash and cash equivalents | C37: =C19/C119 -> 0.0087064547 | D37: =D19/D119 -> 0.053710019 | E37: =E19/E119 -> 0.038303869 | F37: =F19/F119 -> 0.063742192 | G37: =G19/G119 -> 0.053883218 | H37: =H19/H119 -> 0.0530114 | I37: =I19/I119 -> 0.037681863 | N37: =SUM(K19:N19)/N119 -> 0.053710019 | O37: =SUM(L19:O19)/O119 -> 0.023257784 | P37: =SUM(M19:P19)/P119 -> 0.031521093 | Q37: =SUM(N19:Q19)/Q119 -> 0.035076323 | R37: =SUM(O19:R19)/R119 -> 0.038303869 | S37: =SUM(P19:S19)/S119 -> 0.047029408 | T37: =SUM(Q19:T19)/T119 -> 0.057306499 | U37: =SUM(R19:U19)/U119 -> 0.063444044 | ... AE37: =SUM(AB19:AE19)/AE119 -> 0.037681863
B38: Tax % of PBT | C38: =-C26/C25 -> 0.24657112 | D38: =-D26/D25 -> 0.27389833 | E38: =-E26/E25 -> 0.0019443545 | F38: =-F26/F25 -> -0.14799848 | G38: =-G26/G25 -> -0.066544387 | H38: =-H26/H25 -> -0.24538885 | I38: =-I26/I25 -> -0.10257981 | K38: =-K26/K25 -> 0.25309045 | L38: =-L26/L25 -> 0.26116557 | M38: =-M26/M25 -> 0.30849472 | N38: =-N26/N25 -> 0.28027577 | O38: =-O26/O25 -> 0.20153059 | P38: =-P26/P25 -> 0.48521789 | Q38: =-Q26/Q25 -> -1.3285288 | R38: =-R26/R25 -> 0.017342744 | ... AE38: =-AE26/AE25 -> 0.23580346
B40: Working capital /sales | C40: =C60/C7 -> 0.46370505 | D40: =D60/D7 -> 0.43894697 | E40: =E60/E7 -> 0.31097275 | F40: =F60/F7 -> 0.41309329 | G40: =G60/G7 -> 0.39827044 | H40: =H60/H7 -> 0.4032648 | I40: =I60/I7 -> 0.41410095 | K40: =K60/K7 -> 0.5909214 | L40: =L60/L7 -> 0.44365836 | M40: =M60/M7 -> 0.38111731 | N40: =N60/N7 -> 0.37477381 | O40: =O60/O7 -> 0.44609453 | P40: =P60/P7 -> 0.23257376 | Q40: =Q60/Q7 -> 0.25032778 | R40: =R60/R7 -> 0.29877219 | ... AE40: =AE60/AE7 -> 0.55988574
B41: Capex/sales | C41: =-C64/C7 -> 0.062780923 | D41: =-D64/D7 -> 0.068225266 | E41: =-E64/E7 -> 0.068261659 | F41: =-F64/F7 -> 0.048008726 | G41: =-G64/G7 -> 0.034596397 | H41: =-H64/H7 -> 0.047924791 | I41: =-I64/I7 -> 0.052186982 | K41: =-K64/K7 -> 0.049412573 | L41: =-L64/L7 -> 0.086456551 | M41: =-M64/M7 -> 0.057544596 | N41: =-N64/N7 -> 0.078925126 | O41: =-O64/O7 -> 0.038880676 | P41: =-P64/P7 -> 0.084083471 | Q41: =-Q64/Q7 -> 0.082327388 | R41: =-R64/R7 -> 0.071022571 | ... AE41: =-AE64/AE7 -> 0.046654361
B43: EBITDA | C43: =C3 -> 44196 | D43: =D3 -> 44561 | E43: =E3 -> 44926 | F43: =F3 -> 45291 | G43: =G3 -> 45657 | H43: =H3 -> 46022 | I43: =I3 -> 46112 | K43: =K3 -> 44286 | L43: =L3 -> 44377 | M43: =M3 -> 44469 | N43: =N3 -> 44561 | O43: =O3 -> 44651 | P43: =P3 -> 44742 | Q43: =Q3 -> 44834 | R43: =R3 -> 44926 | ... AE43: =AE3 -> 46112
B44: Operating profit | C44: =C18 -> 175180.78 | D44: =D18 -> 330471.3 | E44: =E18 -> 218761.62 | F44: =F18 -> 239966.97 | G44: =G18 -> 262606.95 | H44: =H18 -> 193176.34 | I44: =I18 -> 206452.55 | K44: =K18 -> 94146.466 | L44: =L18 -> 35841.066 | M44: =M18 -> 74659.845 | N44: =N18 -> 114015.48 | O44: =O18 -> 96088.659 | P44: =P18 -> 10731.635 | Q44: =Q18 -> 33311.509 | R44: =R18 -> 73345.147 | ... AE44: =AE18 -> 97715
B45: Depreciation, depletion & amortization | C45: 109813.98 | D45: 124116.74 | E45: 126497.49 | F45: 126119.2 | G45: 153234.22 | H45: 155358.69 | I45: =AE45+AB45+AC45+AD45 -> 155548.16 | K45: 26798.423 | L45: 26906.024 | M45: 30008.333 | N45: =D45-SUM(K45:M45) -> 40403.959 | O45: 29230.951 | P45: 34141.889 | Q45: 34075.411 | R45: =E45-SUM(O45:Q45) -> 29049.242 | S45: 31154.428 | T45: 34174.295 | U45: 35272.291 | V45: =F45-SUM(S45:U45) -> 25518.184 | W45: =35249.053 -> 35249.053 | X45: 36277.691 | Y45: 36802.182 | Z45: =G45-SUM(W45:Y45) -> 44905.298 | AA45: 39670.795 | AB45: 37156.952 | AC45: 37243.232 | AD45: =H45-SUM(AA45:AC45) -> 41287.714 | AE45: 39860.26
B46: EBITDA | C46: =SUM(C44:C45) -> 284994.76 | D46: =SUM(D44:D45) -> 454588.04 | E46: =SUM(E44:E45) -> 345259.11 | F46: =SUM(F44:F45) -> 366086.16 | G46: =SUM(G44:G45) -> 415841.18 | H46: =SUM(H44:H45) -> 348535.04 | I46: =SUM(I44:I45) -> 362000.71 | K46: =SUM(K44:K45) -> 120944.89 | L46: =SUM(L44:L45) -> 62747.09 | M46: =SUM(M44:M45) -> 104668.18 | N46: =SUM(N44:N45) -> 154419.44 | O46: =SUM(O44:O45) -> 125319.61 | P46: =SUM(P44:P45) -> 44873.524 | Q46: =SUM(Q44:Q45) -> 67386.92 | R46: =SUM(R44:R45) -> 102394.39 | ... AE46: =SUM(AE44:AE45) -> 137575.26
B47: % growth | D47: =+D46/C46-1 -> 0.5950751 | E47: =+E46/D46-1 -> -0.24050111 | F47: =+F46/E46-1 -> 0.060322973 | G47: =+G46/F46-1 -> 0.13591066 | H47: =+H46/G46-1 -> -0.1618554 | O47: =O46/K46-1 -> 0.036171194 | P47: =P46/L46-1 -> -0.28485091 | Q47: =Q46/M46-1 -> -0.35618522 | R47: =R46/N46-1 -> -0.3369074 | S47: =S46/O46-1 -> 0.014384572 | T47: =T46/P46-1 -> -0.03274111 | U47: =U46/Q46-1 -> 0.35645346 | V47: =V46/R46-1 -> 0.0010582123 | ... AE47: =AE46/AA46-1 -> 0.10849823
B48: % margin | C48: =+C46/C7 -> 0.15342147 | D48: =+D46/D7 -> 0.18295399 | E48: =+E46/E7 -> 0.12733446 | F48: =+F46/F7 -> 0.14269272 | G48: =+G46/G7 -> 0.14316807 | H48: =+H46/H7 -> 0.11978691 | I48: =+I46/I7 -> 0.12433605 | K48: =+K46/K7 -> 0.21231831 | L48: =+L46/L7 -> 0.13350598 | M48: =+M46/M7 -> 0.16807965 | N48: =+N46/N7 -> 0.18777856 | O48: =+O46/O7 -> 0.17890919 | P48: =+P46/P7 -> 0.080346092 | Q48: =+Q46/Q7 -> 0.098503691 | R48: =+R46/R7 -> 0.13326328 | ... AE48: =+AE46/AE7 -> 0.16787394
B50: Adjustment | C50: =C51-C46 -> 11410.085 | D50: =D51-D46 -> -9590.45 | E50: =E51-E46 -> 12669.54 | F50: =F51-F46 -> 13316.208 | G50: =G51-G46 -> 94.937 | H50: =H51-H46 -> 27672.922 | I50: =I51-I46 -> 14296.766 | K50: =K51-K46 -> 5602.505 | L50: =L51-L46 -> -1171.504 | M50: =M51-M46 -> -3195.905 | N50: =E50-SUM(K50:M50) -> 11434.444 | O50: =O51-O46 -> 9806.175 | P50: =P51-P46 -> -12402.642 | Q50: =Q51-Q46 -> 219.736 | R50: =J50-SUM(O50:Q50) -> 2376.731 | S50: =S51-S46 -> 8254.428 | T50: =T51-T46 -> 3721.525 | U50: =U51-U46 -> -5063.367 | V50: =N50-SUM(S50:U50) -> 4521.858 | W50: =W51-W46 -> -1064.348 | X50: =X51-X46 -> 5256.853 | Y50: =Y51-Y46 -> 4311.792 | Z50: =Z51-Z46 -> -8409.36 | AA50: =AA51-AA46 -> 7444.411 | AB50: =AB51-AB46 -> 9465.32 | AC50: =AC51-AC46 -> -4187.729 | AD50: =AD51-AD46 -> 14950.92 | AE50: =AE51-AE46 -> -5931.745
B51: Adj. EBITDA | C51: 296404.84 | D51: 444997.59 | E51: 357928.65 | F51: 379402.37 | G51: 415936.11 | H51: 376207.96 | I51: =AE51+AB51+AC51+AD51 -> 376297.47 | K51: 126547.39 | L51: 61575.586 | M51: 101472.27 | N51: =D51-SUM(K51:M51) -> 155402.33 | O51: 135125.79 | P51: 32470.882 | Q51: 67606.656 | R51: =E51-SUM(O51:Q51) -> 122725.33 | S51: 135376.71 | T51: 47125.84 | U51: 86343.854 | V51: =F51-SUM(S51:U51) -> 110555.97 | W51: =124163.248 -> 124163.25 | X51: 38722 | Y51: 70430.698 | Z51: =G51-SUM(W51:Y51) -> 182620.17 | AA51: 131554 | AB51: 19817.283 | AC51: 73635 | AD51: =H51-SUM(AA51:AC51) -> 151201.67 | AE51: 131643.52
B52: % growth | D52: =+D51/C51-1 -> 0.50131687 | E52: =+E51/D51-1 -> -0.1956616 | F52: =+F51/E51-1 -> 0.059994426 | G52: =+G51/F51-1 -> 0.096292864 | H52: =+H51/G51-1 -> -0.095515043 | O52: =O51/K51-1 -> 0.06778797 | P52: =P51/L51-1 -> -0.47266629 | Q52: =Q51/M51-1 -> -0.33374257 | R52: =R51/N51-1 -> -0.2102736 | S52: =S51/O51-1 -> 0.0018569513 | T52: =T51/P51-1 -> 0.45132615 | U52: =U51/Q51-1 -> 0.2771502 | V52: =V51/R51-1 -> -0.099159272 | ... AE52: =AE51/AA51-1 -> 0.00068044301
B53: % margin | C53: =+C51/C7 -> 0.15956387 | D53: =+D51/D7 -> 0.17909421 | E53: =+E51/E7 -> 0.13200709 | F53: =+F51/F7 -> 0.1478831 | G53: =+G51/G7 -> 0.14320076 | H53: =+H51/H7 -> 0.12929773 | I53: =+I51/I7 -> 0.12924655 | K53: =+K51/K7 -> 0.22215349 | L53: =+L51/L7 -> 0.13101339 | M53: =+M51/M7 -> 0.16294756 | N53: =+N51/N7 -> 0.18897379 | O53: =+O51/O7 -> 0.19290871 | P53: =+P51/P7 -> 0.058139148 | Q53: =+Q51/Q7 -> 0.098824893 | R53: =+R51/R7 -> 0.1597234 | ... AE53: =+AE51/AE7 -> 0.16063583
B55: Capex sales | C55: =-C64/C7 -> 0.062780923 | D55: =-D64/D7 -> 0.068225266 | E55: =-E64/E7 -> 0.068261659 | F55: =-F64/F7 -> 0.048008726 | G55: =-G64/G7 -> 0.034596397 | H55: =-H64/H7 -> 0.047924791 | I55: =-I64/I7 -> 0.052186982 | K55: =-K64/K7 -> 0.049412573 | L55: =-L64/L7 -> 0.086456551 | M55: =-M64/M7 -> 0.057544596 | N55: =-N64/N7 -> 0.078925126 | O55: =-O64/O7 -> 0.038880676 | P55: =-P64/P7 -> 0.084083471 | Q55: =-Q64/Q7 -> 0.082327388 | R55: =-R64/R7 -> 0.071022571 | ... AE55: =-AE64/AE7 -> 0.046654361
B56: WC SALES | C56: =C60/C7 -> 0.46370505 | D56: =D60/D7 -> 0.43894697 | E56: =E60/E7 -> 0.31097275 | F56: =F60/F7 -> 0.41309329 | G56: =G60/G7 -> 0.39827044 | H56: =H60/H7 -> 0.4032648 | I56: =I60/I7 -> 0.41410095 | K56: =K60/K7 -> 0.5909214 | L56: =L60/L7 -> 0.44365836 | M56: =M60/M7 -> 0.38111731 | N56: =N60/N7 -> 0.37477381 | O56: =O60/O7 -> 0.44609453 | P56: =P60/P7 -> 0.23257376 | Q56: =Q60/Q7 -> 0.25032778 | R56: =R60/R7 -> 0.29877219 | ... AE56: =AE60/AE7 -> 0.55988574
B58: CASH FLOW | C58: =C3 -> 44196 | D58: =D3 -> 44561 | E58: =E3 -> 44926 | F58: =F3 -> 45291 | G58: =G3 -> 45657 | H58: =H3 -> 46022 | I58: =I3 -> 46112 | K58: =K3 -> 44286 | L58: =L3 -> 44377 | M58: =M3 -> 44469 | N58: =N3 -> 44561 | O58: =O3 -> 44651 | P58: =P3 -> 44742 | Q58: =Q3 -> 44834 | R58: =R3 -> 44926 | ... AE58: =AE3 -> 46112
B59: Adj. EBITDA | C59: =C51 -> 296404.84 | D59: =D51 -> 444997.59 | E59: =E51 -> 357928.65 | F59: =F51 -> 379402.37 | G59: =G51 -> 415936.11 | H59: =H51 -> 376207.96 | I59: =I51 -> 376297.47 | K59: =K51 -> 126547.39 | L59: =L51 -> 61575.586 | M59: =M51 -> 101472.27 | N59: =D59-SUM(K59:M59) -> 155402.33 | O59: =O51 -> 135125.79 | P59: =P51 -> 32470.882 | Q59: =Q51 -> 67606.656 | R59: =E59-SUM(O59:Q59) -> 122725.33 | S59: =S51 -> 135376.71 | T59: =T51 -> 47125.84 | U59: =U51 -> 86343.854 | V59: =F59-SUM(S59:U59) -> 110555.97 | W59: =W51 -> 124163.25 | X59: =X51 -> 38722 | Y59: =Y51 -> 70430.698 | Z59: =Z51 -> 182620.17 | AA59: =AA51 -> 131554 | AB59: =AB51 -> 19817.283 | AC59: =AC51 -> 73635 | AD59: =AD51 -> 151201.67 | AE59: =AE51 -> 131643.52
B60: Working Capital | C60: =2330736.906-1469361.333 -> 861375.57 | D60: =3138938.727-2048281.794 -> 1090656.9 | E60: =3293803.868-2450621.483 -> 843182.38 | F60: =3372357.634-2312543.646 -> 1059814 | G60: =3873449.09-2716646.141 -> 1156802.9 | H60: =3808416.362-2635066.842 -> 1173349.5 | I60: =AE60+AB60+AC60+AD60 -> 1205642.6 | K60: =770790.208-434178.066 -> 336612.14 | L60: =1408281.248-863152.08-K60 -> 208517.03 | M60: =2156445.322-1373983.115-L60-K60 -> 237333.04 | N60: =D60-SUM(K60:M60) -> 308194.73 | O60: =991584.286-679110.712 -> 312473.57 | P60: =1693396.257-1251029.565-O60 -> 129893.12 | Q60: =2461818.362-1848201.052-P60-O60 -> 171250.62 | R60: =E60-SUM(O60:Q60) -> 229565.07 | S60: =1038847.812-688322.773 -> 350525.04 | T60: =1862467.818-1266789.016-S60 -> 245153.76 | U60: =2686430.872-1845930.84-T60-S60 -> 244821.23 | V60: =F60-SUM(S60:U60) -> 219313.96 | W60: =1071409.644-691903.614 -> 379506.03 | X60: =1863504.195-1373078.334-W60 -> 110919.83 | Y60: =2686420.872-1845930.84-X60-W60 -> 350064.17 | Z60: =G60-SUM(W60:Y60) -> 316312.92 | AA60: =1174820.54-748278.652 -> 426541.89 | AB60: =2003696.331-1374934.826-AA60 -> 202219.62 | AC60: =2802487.604-1961116.276-AB60-AA60 -> 212609.82 | AD60: =H60-SUM(AA60:AC60) -> 331978.19 | AE60: =1148876.616-690041.696 -> 458834.92
B61: Taxes | C61: -43031.71 | D61: -78971.52 | E61: -66276.733 | F61: -8959.871 | G61: -14703.915 | H61: -57562.564 | I61: =AE61+AB61+AC61+AD61 -> -61352.405 | K61: =-17854.367 -> -17854.367 | L61: =-42613.836-K61 -> -24759.469 | M61: =-59418.262-K61-L61 -> -16804.426 | N61: =D61-SUM(K61:M61) -> -19553.258 | O61: -25404.388 | P61: =-45590.85-O61 -> -20186.462 | Q61: =-56486.507-O61-P61 -> -10895.657 | R61: =E61-SUM(O61:Q61) -> -9790.226 | S61: =-18661.397 -> -18661.397 | T61: =-16179.622-S61 -> 2481.775 | U61: =-5734.95-S61-T61 -> 10444.672 | V61: =F61-SUM(S61:U61) -> -3224.921 | W61: =-(5647.184) -> -5647.184 | X61: =-4237.31-W61 -> 1409.874 | Y61: =-9385.763-W61-X61 -> -5148.453 | Z61: =G61-SUM(W61:Y61) -> -5318.152 | AA61: -7687.465 | AB61: =-43819.802-AA61 -> -36132.337 | AC61: =-51411.225-AA61-AB61 -> -7591.423 | AD61: =H61-SUM(AA61:AC61) -> -6151.339 | AE61: -11477.306
B62: Cash interest paid | C62: -21975.481 | D62: -28984.61 | E62: -47102.233 | F62: -70452.675 | G62: -68811.141 | H62: -54985.787 | I62: =AE62+AB62+AC62+AD62 -> -54400.069 | K62: -6499.627 | L62: =-12117.682-K62 -> -5618.055 | M62: =-20450.136-K62-L62 -> -8332.454 | N62: =D62-SUM(K62:M62) -> -8534.474 | O62: -6654.623 | P62: =-14710.574-O62 -> -8055.951 | Q62: =-35793.763-O62-P62 -> -21083.189 | R62: =E62-SUM(O62:Q62) -> -11308.47 | S62: =-24811.635 -> -24811.635 | T62: =-40330.899-S62 -> -15519.264 | U62: =-62729.784-S62-T62 -> -22398.885 | V62: =F62-SUM(S62:U62) -> -7722.891 | W62: =-(19532.306) -> -19532.306 | X62: =-33450.129-W62 -> -13917.823 | Y62: =-54229.792-W62-X62 -> -20779.663 | Z62: =G62-SUM(W62:Y62) -> -14581.349 | AA62: -21319.801 | AB62: =-29763.076-AA62 -> -8443.275 | AC62: =-49469.732-AA62-AB62 -> -19706.656 | AD62: =H62-SUM(AA62:AC62) -> -5516.055 | AE62: -20734.083
B63: Net cash from operations | C63: =SUM(C59:C62) -> 1092773.2 | D63: =SUM(D59:D62) -> 1427698.4 | E63: =SUM(E59:E62) -> 1087732.1 | F63: =SUM(F59:F62) -> 1359803.8 | G63: =SUM(G59:G62) -> 1489224 | H63: =SUM(H59:H62) -> 1437009.1 | I63: =SUM(I59:I62) -> 1466187.6 | K63: =SUM(K59:K62) -> 438805.54 | L63: =SUM(L59:L62) -> 239715.09 | M63: =SUM(M59:M62) -> 313668.43 | N63: =SUM(N59:N62) -> 435509.33 | O63: =SUM(O59:O62) -> 415540.35 | P63: =SUM(P59:P62) -> 134121.59 | Q63: =SUM(Q59:Q62) -> 206878.43 | R63: =SUM(R59:R62) -> 331191.7 | ... AE63: =SUM(AE59:AE62) -> 558267.05
B64: Net Capex | C64: =-117013.658+392.213 -> -116621.44 | D64: =-169667.429+147.274 -> -169520.15 | E64: =-188669.637+3582.588 -> -185087.05 | F64: =-124400.618+1231.541 -> -123169.08 | G64: =-152916.896+52429.361 -> -100487.54 | H64: =-142378.558+2935.366 -> -139443.19 | I64: =AE64+AB64+AC64+AD64 -> -151940.84 | K64: =-28165.917+18.566 -> -28147.351 | L64: =-68832.106+50.644-K64 -> -40634.111 | M64: =-104707.151+90.964-K64-L64 -> -35834.725 | N64: =D64-SUM(K64:M64) -> -64903.968 | O64: -27234.55 | P64: =-77084.585+2889.174-O64 -> -46960.861 | Q64: =-133227.56+2711.527-O64-P64 -> -56320.622 | R64: =E64-SUM(O64:Q64) -> -54571.016 | S64: =-22090.58+132.064 -> -21958.516 | T64: =-52162.162+332.818-S64 -> -29870.828 | U64: =-97805.425+885.563-S64-T64 -> -45090.518 | V64: =F64-SUM(S64:U64) -> -26249.215 | W64: =-(44446.452)+86.284 -> -44360.168 | X64: =-80610.019+49820.877-W64 -> 13571.026 | Y64: =-114356.254+51312-W64-X64 -> -32255.112 | Z64: =G64-SUM(W64:Y64) -> -37443.281 | AA64: =-(28509.534)+2773.221 -> -25736.313 | AB64: =-61343.122+2814.686-AA64 -> -32792.123 | AC64: =-101970.12+2854.392-AA64-AB64 -> -40587.292 | AD64: =H64-SUM(AA64:AC64) -> -40327.464 | AE64: =-38658.645+424.683 -> -38233.962
B65: Purchase of intangible assets | C65: -5773.071 | D65: -2186.553 | E65: -14933.853 | F65: -5047.222 | G65: -7169.288 | H65: -14522.823 | I65: =AE65+AB65+AC65+AD65 -> -15950.022 | K65: =-1935.747 -> -1935.747 | L65: =-2019.125-K65 -> -83.378 | M65: =-2130.064-K65-L65 -> -110.939 | N65: =D65-SUM(K65:M65) -> -56.489 | O65: -252.286 | P65: =-1718.901-O65 -> -1466.615 | Q65: =-15223.269-O65-P65 -> -13504.368 | R65: =E65-SUM(O65:Q65) -> 289.416 | S65: =-784.887 -> -784.887 | T65: =-1334.514-S65 -> -549.627 | U65: =-1838.644-S65-T65 -> -504.13 | V65: =F65-SUM(S65:U65) -> -3208.578 | W65: =-401.315 -> -401.315 | X65: =-3326.38-W65 -> -2925.065 | Y65: =-4151.33-W65-X65 -> -824.95 | Z65: =G65-SUM(W65:Y65) -> -3017.958 | AA65: =-3254.285+912.191 -> -2342.094 | AB65: =-7885.974-AA65 -> -5543.88 | AC65: =-10839.218-AA65-AB65 -> -2953.244 | AD65: =H65-SUM(AA65:AC65) -> -3683.605 | AE65: =-3769.293 -> -3769.293
B66: Disposals/ Acquistion, of subsidiaries, businesses | C66: =-19287.372+1273.947-1028.076 -> -19041.501 | D66: -5791.718 | E66: -36465.915 | F66: =-7086.899-2000 -> -9086.899 | G66: =-10658.097-551.585 -> -11209.682 | H66: -10975.902 | I66: =AE66+AB66+AC66+AD66 -> -16779.08 | K66: 0 | L66: =0-K66 -> 0 | M66: =-5791.718-K66-L66 -> -5791.718 | N66: =D66-SUM(K66:M66) -> 0 | O66: 0 | P66: =0-O66 -> 0 | Q66: =0-O66-P66 -> 0 | R66: =E66-SUM(O66:Q66) -> -36465.915 | S66: -2000 | T66: =-2000-4176.846-S66 -> -4176.846 | U66: =-2000-8546.405-S66-T66 -> -4369.559 | V66: =F66-SUM(S66:U66) -> 1459.506 | W66: 0 | X66: =-500-10658.097-W66 -> -11158.097 | Y66: =-545.759-10658.097-W66-X66 -> -45.759 | Z66: =G66-SUM(W66:Y66) -> -5.826 | AA66: 0 | AB66: =0-0-AA66 -> 0 | AC66: =-7008.552-AA66-AB66 -> -7008.552 | AD66: =H66-SUM(AA66:AC66) -> -3967.35 | AE66: -5803.178
B67: Free cash flow | C67: =SUM(C63:C66) -> 951337.21 | D67: =SUM(D63:D66) -> 1250200 | E67: =SUM(E63:E66) -> 851245.25 | F67: =SUM(F63:F66) -> 1222500.6 | G67: =SUM(G63:G66) -> 1370357.5 | H67: =SUM(H63:H66) -> 1272067.2 | I67: =SUM(I63:I66) -> 1281517.6 | K67: =SUM(K63:K66) -> 408722.44 | L67: =SUM(L63:L66) -> 198997.6 | M67: =SUM(M63:M66) -> 271931.05 | N67: =SUM(N63:N66) -> 370548.87 | O67: =SUM(O63:O66) -> 388053.51 | P67: =SUM(P63:P66) -> 85694.111 | Q67: =SUM(Q63:Q66) -> 137053.44 | R67: =SUM(R63:R66) -> 240444.19 | ... AE67: =SUM(AE63:AE66) -> 510460.61
B68: Other Investing | C68: =29.702+861.168 -> 890.87 | D68: =31.495-1525.602 -> -1494.107 | E68: 30.021 | F68: =1245.265-1173.884 -> 71.381 | G68: =572.254 -> 572.254 | H68: =966.365-324.907 -> 641.458 | I68: =AE68+AB68+AC68+AD68 -> 668.638 | K68: 0 | L68: =25.229-K68 -> 25.229 | M68: =56.724-K68-L68 -> 31.495 | N68: =D68-SUM(K68:M68) -> -1550.831 | O68: 2253.769 | P68: =-27386.281-O68 -> -29640.05 | Q68: =-29428.835-O68-P68 -> -2042.554 | R68: =E68-SUM(O68:Q68) -> 29458.856 | S68: 0 | T68: =-624.589+71.381-S68 -> -553.208 | U68: =-1817.165+71.381-S68-T68 -> -1192.576 | V68: =F68-SUM(S68:U68) -> 1817.165 | W68: =(-9214.316) -> -9214.316 | X68: =0-W68 -> 9214.316 | Y68: =0+391.455-W68-X68 -> 391.455 | Z68: =G68-SUM(W68:Y68) -> 180.799 | AA68: 0 | AB68: =934.687-AA68 -> 934.687 | AC68: =964.809-AA68-AB68 -> 30.122 | AD68: =H68-SUM(AA68:AC68) -> -323.351 | AE68: =27.18 -> 27.18
B69: Equity Issuance | C69: 0 | D69: 0 | E69: 1648.121 | F69: 2768.7 | G69: 2746.184 | H69: 230.135 | I69: =AE69+AB69+AC69+AD69 -> 3310.421 | K69: 0 | L69: =0-K69 -> 0 | M69: =0-K69-L69 -> 0 | N69: =D69-SUM(K69:M69) -> 0 | O69: 0 | P69: =1648.121-O69 -> 1648.121 | Q69: =1648.121-O69-P69 -> 0 | R69: =E69-SUM(O69:Q69) -> 0 | S69: 1355.553 | T69: =2768.7-S69 -> 1413.147 | U69: =2768.7-S69-T69 -> 0 | V69: =F69-SUM(S69:U69) -> 0 | W69: =944.434 -> 944.434 | X69: =1363.603-W69 -> 419.169 | Y69: =1817.216-W69-X69 -> 453.613 | Z69: =G69-SUM(W69:Y69) -> 928.968 | AA69: 230.135 | AB69: =230.135-AA69 -> 0 | AC69: =230.135-AA69-AB69 -> 0 | AD69: =H69-SUM(AA69:AC69) -> 0 | AE69: 3310.421
B70: Dividends | C70: -102135.65 | D70: -274136.47 | E70: -158320.85 | F70: -65583.416 | G70: -81797.392 | H70: -78322.009 | I70: =AE70+AB70+AC70+AD70 -> -78292.831 | K70: -772.165 | L70: =-56960.133-K70 -> -56187.968 | M70: =-56960.133-K70-L70 -> 0 | N70: =D70-SUM(K70:M70) -> -217176.34 | O70: -2396.327 | P70: =-113816.528-O70 -> -111420.2 | Q70: =-113595.537-O70-P70 -> 220.991 | R70: =E70-SUM(O70:Q70) -> -44725.311 | S70: =-3319.827 -> -3319.827 | T70: =-36305.285-S70 -> -32985.458 | U70: =-36305.285-S70-T70 -> 0 | V70: =F70-SUM(S70:U70) -> -29278.131 | W70: 0 | X70: =-41753.925-W70 -> -41753.925 | Y70: =-41753.925-W70-X70 -> 0 | Z70: =G70-SUM(W70:Y70) -> -40043.467 | AA70: -29.178 | AB70: =-48172.529-AA70 -> -48143.351 | AC70: =-49674.962-AA70-AB70 -> -1502.433 | AD70: =H70-SUM(AA70:AC70) -> -28647.047 | AE70: 0
B71: Net Change in debt | C71: =196786.489+72550.018-95956.307 -> 173380.2 | D71: =92951.539+7274.374-46050.971 -> 54174.942 | E71: =736278.842+46843.478-79351.11 -> 703771.21 | F71: =8219.455+68928.016-159420.525 -> -82273.054 | G71: =52903.303-74305.996-16274.873 -> -37677.566 | H71: =206962.105-328742.122-12394.33+2049.656 -> -132124.69 | I71: =AE71+AB71+AC71+AD71 -> -168632.47 | K71: =1472.928-2871.727 -> -1398.799 | L71: =3000+5297.109-36883.919-K71 -> -27188.011 | M71: =3000+6793.452-39735.556-K71-L71 -> -1355.294 | N71: =D71-SUM(K71:M71) -> 84117.046 | O71: =489002.428+5154.8-4721.066 -> 489436.16 | P71: =553872.52+19088.327-17807.581-O71 -> 65717.104 | Q71: =597147.437+67509.667-29812.4-O71-P71 -> 79691.438 | R71: =E71-SUM(O71:Q71) -> 68926.506 | S71: =484.551+3395.232-43706.15 -> -39826.367 | T71: =9259.335+22662.341-44190.491-S71 -> 27557.552 | U71: =8219.454+55676.323-115630.473-S71-T71 -> -39465.881 | V71: =F71-SUM(S71:U71) -> -30538.358 | W71: =11987.083-18632.26 -> -6645.177 | X71: =77670.382-46404.086-W71 -> 37911.473 | Y71: =0+62121.047-49382.471-W71-X71 -> -18527.72 | Z71: =G71-SUM(W71:Y71) -> -50416.142 | AA71: =21041.764-28951.982 -> -7910.218 | AB71: =84160.613+463.677-223217.31-AA71 -> -130682.8 | AC71: =163691.599+1646.145-284997.321-8276.488-AA71-AB71 -> 10656.955 | AD71: =H71-SUM(AA71:AC71) -> -4188.626 | AE71: =15249.373-56223.405-3443.961 -> -44417.993
B72: Other financing activities | C72: =-86.912-6857.42+449.333-10+10 -> -6494.999 | D72: =-12207.458-7630.8+6130.317+25.616 -> -13682.325 | E72: =-438.105-9663.757+130.322-25 -> -9996.54 | F72: =-3205.058-10704.27+40960.923 -> 27051.595 | G72: =17112.779-32260.503+6840.724 -> -8307 | H72: =3637.15 -> 3637.15 | I72: =AE72+AB72+AC72+AD72 -> 5646.609 | K72: =-1806.152+273.995 -> -1532.157 | L72: =-3607.593+61.999-2732.874-K72 -> -4746.311 | M72: =-5695.907-8709.12+6080.317-K72-L72 -> -2046.242 | N72: =D72-SUM(K72:M72) -> -5357.615 | O72: =-2147.457+0+25.93 -> -2121.527 | P72: =-4682.314-25-O72 -> -2585.787 | Q72: =-7019.786+130.322-438.105-25-O72-P72 -> -2645.255 | R72: =E72-SUM(O72:Q72) -> -2643.971 | S72: =-2811.029+270.263-3205.058 -> -5745.824 | T72: =-5863.653+15004.423-3205.058-S72 -> 11681.536 | U72: =-8480.544+38026.713-3205.058-S72-T72 -> 20405.399 | V72: =F72-SUM(S72:U72) -> 710.484 | W72: =-2821.518-31549.348 -> -34370.866 | X72: =-7039.853+3267.304-31549.348-W72 -> -951.031 | Y72: =-11695.644+3267.304-31549.348-W72-X72 -> -4655.791 | Z72: =G72-SUM(W72:Y72) -> 31670.688 | AA72: =-2449.533-0 -> -2449.533 | AB72: =-6137.29+3637.15-AA72 -> -50.607 | AC72: =3637.15-AA72-AB72 -> 6137.29 | AD72: =H72-SUM(AA72:AC72) -> 0 | AE72: =-440.074 -> -440.074
B73: Cash flow after financing activities | C73: =SUM(C67:C72) -> 1016977.6 | D73: =SUM(D67:D72) -> 1015062 | E73: =SUM(E67:E72) -> 1388377.2 | F73: =SUM(F67:F72) -> 1104535.8 | G73: =SUM(G67:G72) -> 1245894 | H73: =SUM(H67:H72) -> 1066129.3 | I73: =SUM(I67:I72) -> 1044218 | K73: =SUM(K67:K72) -> 405019.32 | L73: =SUM(L67:L72) -> 110900.54 | M73: =SUM(M67:M72) -> 268561.01 | N73: =SUM(N67:N72) -> 230581.13 | O73: =SUM(O67:O72) -> 875225.59 | P73: =SUM(P67:P72) -> 9413.298 | Q73: =SUM(Q67:Q72) -> 212278.06 | R73: =SUM(R67:R72) -> 291460.27 | ... AE73: =SUM(AE67:AE72) -> 468940.15
B74: Balancing figure | C74: =204873.921-C73 -> -812103.71 | D74: =-119280.815-D73 -> -1134342.8 | E74: =346582.3-E73 -> -1041794.9 | F74: =38829.415-F73 -> -1065706.4 | G74: =44186.702-G73 -> -1201707.3 | H74: =-131829.35-H73 -> -1197958.6 | I74: =AE74+AB74+AC74+AD74 -> -1183296.6 | K74: =77070.608-K73 -> -327948.72 | L74: =-10923.427-L73-K73-K74 -> -198894.57 | M74: =-5309.633-M73-K73-L73-K74-L74 -> -262947.22 | N74: =D74-SUM(K74:M74) -> -344552.31 | O74: =510563.858-O73 -> -364661.73 | P74: =333619.736-P73-O73-O74 -> -186357.42 | Q74: =318505.338-Q73-O73-P73-O74-P74 -> -227392.46 | R74: =E74-SUM(O74:Q74) -> -263383.31 | S74: =21344.791-S73 -> -348804.05 | T74: =47309.991-T73-S73-S74 -> -225793.18 | U74: =35700.326-U73-S73-T73-S74-T74 -> -260603.27 | V74: =F74-SUM(S74:U74) -> -230505.9 | W74: =27232.775-W73 -> -357209.61 | X74: =-3035.753-X73-W73-W74 -> -171730.28 | Y74: =-11829.834-Y73-W73-X73-W74-X74 -> -347896.57 | Z74: =G74-SUM(W74:Y74) -> -324870.83 | AA74: =92192.55-AA73 -> -398658.87 | AB74: =-156346.272-AB73-AA73-AA74 -> -209722.03 | AC74: =-176498.058-AC73-AA73-AB73-AA74-AB74 -> -243871.38 | AD74: =H74-SUM(AA74:AC74) -> -345706.32 | AE74: =84943.275-AE73 -> -383996.87
B75: FX | C75: -4854.129 | D75: -11540.076 | E75: -15068.75 | F75: -17757.074 | G75: 44782.097 | H75: -56117.536 | I75: =AE75+AB75+AC75+AD75 -> -20787.049 | K75: -5788.317 | L75: =-10470.61-K75 -> -4682.293 | M75: =-8557.152-K75-L75 -> 1913.458 | N75: =D75-SUM(K75:M75) -> -2982.924 | O75: -34049.554 | P75: =44811.308-O75 -> 78860.862 | Q75: =51410.769-O75-P75 -> 6599.461 | R75: =E75-SUM(O75:Q75) -> -66479.519 | S75: -46116.968 | T75: =-53376.22-S75 -> -7259.252 | U75: =-6256.1-S75-T75 -> 47120.12 | V75: =F75-SUM(S75:U75) -> -11500.974 | W75: =46999.449 -> 46999.449 | X75: =21420.553-W75 -> -25578.896 | Y75: =-7045.179-W75-X75 -> -28465.732 | Z75: =G75-SUM(W75:Y75) -> 51827.276 | AA75: -27880.326 | AB75: =-39516.311-AA75 -> -11635.985 | AC75: =-31840.245-AA75-AB75 -> 7676.066 | AD75: =H75-SUM(AA75:AC75) -> -24277.291 | AE75: 7450.161
B76: Net change in cash | C76: =SUM(C73:C75) -> 200019.79 | D76: =SUM(D73:D75) -> -130820.89 | E76: =SUM(E73:E75) -> 331513.55 | F76: =SUM(F73:F75) -> 21072.341 | G76: =SUM(G73:G75) -> 88968.799 | H76: =SUM(H73:H75) -> -187946.89 | I76: =SUM(I73:I75) -> -159865.67 | K76: =SUM(K73:K75) -> 71282.291 | L76: =SUM(L73:L75) -> -92676.328 | M76: =SUM(M73:M75) -> 7527.252 | N76: =D76-SUM(K76:M76) -> -116954.11 | O76: =SUM(O73:O75) -> 476514.3 | P76: =SUM(P73:P75) -> -98083.26 | Q76: =SUM(Q73:Q75) -> -8514.937 | R76: =SUM(R73:R75) -> -38402.557 | S76: =SUM(S73:S75) -> -24772.177 | T76: =SUM(T73:T75) -> 18705.948 | U76: =SUM(U73:U75) -> 35510.455 | V76: =SUM(V73:V75) -> -8371.885 | ... AE76: =SUM(AE73:AE75) -> 92393.436
B77: Cash and cash equivalents | C77: =196369.224+C76 -> 396389.02 | D77: =C77+D76 -> 265568.12 | E77: =D77+E76 -> 597081.68 | F77: =E77+F76 -> 618154.02 | G77: =F77+G76 -> 707122.82 | H77: =G77+H76 -> 519175.93 | I77: =AA77+I76 -> 611569.37 | K77: =C77+K76 -> 467671.31 | L77: =K77+L76 -> 374994.98 | M77: =L77+M76 -> 382522.23 | N77: =M77+N76 -> 265568.12 | O77: =N77+O76 -> 742082.43 | P77: =O77+P76 -> 643999.17 | Q77: =P77+Q76 -> 635484.23 | R77: =Q77+R76 -> 597081.68 | S77: =R77+S76 -> 572309.5 | ... AE77: =AD77+AE76 -> 611569.37
B79: check 1 | C79: =+C77-C119 -> 0 | D79: =+D77-D119 -> 0 | E79: =+E77-E119 -> 0 | F79: =+F77-F119 -> 0 | G79: =+G77-G119 -> 0 | H79: =+H77-H119 -> 0 | I79: =+I77-I119 -> 0 | K79: =+K77-K119 -> 0 | L79: =+L77-L119 -> 0 | M79: =+M77-M119 -> 0 | N79: =+N77-N119 -> 0 | O79: =+O77-O119 -> 0 | P79: =+P77-P119 -> 0 | Q79: =+Q77-Q119 -> 0 | R79: =+R77-R119 -> 0 | ... AE79: =+AE77-AE119 -> 0
B80: check 2 | C80: =280669.513-(C63+C74) -> 0 | D80: =293355.573-(D63+D74) -> 0 | E80: =45937.153-(E63+E74) -> -1.6734703e-10 | F80: =294097.407-(F63+F74) -> 0 | G80: =287516.727-(G63+G74) -> 0 | H80: =239050.524-(H63+H74) -> 0 | K80: =110856.827-(K63+K74) -> 0 | L80: =151677.342-110856.827-(L63+L74) -> 0 | M80: =202398.559-151677.342-(M63+M74) -> 5.8207661e-11 | O80: =50878.617-(O63+O74) -> 0 | P80: =-1357.216-50878.617-(P63+P74) -> 0 | Q80: =-21871.244+1357.216-(Q63+Q74) -> 0 | S80: =93624.659-(S63+S74) -> 0 | T80: =147073.591-93624.659-(T63+T74) -> 0 | U80: =205681.191-147073.591-(U63+U74) -> 8.7311491e-11 | W80: =121280.183-(W63+W74) -> 0 | X80: =86683.789-121280.183-(X63+X74) -> 0 | Y80: =133353.972-86683.789-(Y63+Y74) -> 0 | AA80: =130429.751-(AA63+AA74) -> 0 | AB80: =98169.005-130429.751-(AB63+AB74) -> -4.3655746e-11 | AC80: =113244.373-(AC63+AC74)-98169.005 -> 0 | AE80: =174270.174-(AE63+AE74) -> 0
B82: LTM | C82: =C3 -> 44196 | D82: =D3 -> 44561 | E82: =E3 -> 44926 | F82: =F3 -> 45291 | G82: =G3 -> 45657 | H82: =H3 -> 46022 | I82: =I3 -> 46112 | K82: =K3 -> 44286 | L82: =L3 -> 44377 | M82: =M3 -> 44469 | N82: =N3 -> 44561 | O82: =O3 -> 44651 | P82: =P3 -> 44742 | Q82: =Q3 -> 44834 | R82: =R3 -> 44926 | ... AE82: =AE3 -> 46112
B83: =B7 -> Revenue | C83: =C7 -> 1857593.7 | D83: =D7 -> 2484712.3 | E83: =E7 -> 2711434.9 | F83: =F7 -> 2565556.1 | G83: =G7 -> 2904566.5 | H83: =H7 -> 2909625.4 | I83: =I7 -> 2911470.1 | N83: =SUM(K7:N7) -> 2484712.3 | O83: =SUM(L7:O7) -> 2615537.8 | P83: =SUM(M7:P7) -> 2704046.1 | Q83: =SUM(N7:Q7) -> 2765422 | R83: =SUM(O7:R7) -> 2711434.9 | S83: =SUM(P7:S7) -> 2743000.8 | T83: =SUM(Q7:T7) -> 2758739.6 | U83: =SUM(R7:U7) -> 2761311 | ... AE83: =SUM(AB7:AE7) -> 2911470.1
B84: Operating profit | C84: =C18 -> 175180.78 | D84: =D18 -> 330471.3 | E84: =E18 -> 218761.62 | F84: =F18 -> 239966.97 | G84: =G18 -> 262606.95 | H84: =H18 -> 193176.34 | I84: =I18 -> 206452.55 | N84: =SUM(K18:N18) -> 318662.86 | O84: =SUM(L18:O18) -> 320605.05 | P84: =SUM(M18:P18) -> 295495.62 | Q84: =SUM(N18:Q18) -> 254147.29 | R84: =SUM(O18:R18) -> 213476.95 | S84: =SUM(P18:S18) -> 213356.14 | T84: =SUM(Q18:T18) -> 211854.53 | U84: =SUM(R18:U18) -> 234677.95 | ... AE84: =SUM(AB18:AE18) -> 206452.55
B85: EBITDA | C85: =+C46 -> 284994.76 | D85: =+D46 -> 454588.04 | E85: =+E46 -> 345259.11 | F85: =+F46 -> 366086.16 | G85: =+G46 -> 415841.18 | H85: =+H46 -> 348535.04 | I85: =+I46 -> 362000.71 | N85: =SUM(K46:N46) -> 442779.6 | O85: =SUM(L46:O46) -> 447154.32 | P85: =SUM(M46:P46) -> 429280.75 | Q85: =SUM(N46:Q46) -> 391999.5 | R85: =SUM(O46:R46) -> 339974.44 | S85: =SUM(P46:S46) -> 341777.11 | T85: =SUM(Q46:T46) -> 340307.9 | U85: =SUM(R46:U46) -> 364328.2 | ... AE85: =SUM(AB46:AE46) -> 362000.71
B86: Adjusted EBITDA | C86: =+C51 -> 296404.84 | D86: =+D51 -> 444997.59 | E86: =+E51 -> 357928.65 | F86: =+F51 -> 379402.37 | G86: =+G51 -> 415936.11 | H86: =+H51 -> 376207.96 | I86: =+I51 -> 376297.47 | N86: =SUM(K51:N51) -> 444997.59 | O86: =SUM(L51:O51) -> 453575.98 | P86: =SUM(M51:P51) -> 424471.27 | Q86: =SUM(N51:Q51) -> 390605.66 | R86: =SUM(O51:R51) -> 357928.65 | S86: =SUM(P51:S51) -> 358179.57 | T86: =SUM(Q51:T51) -> 372834.53 | U86: =SUM(R51:U51) -> 391571.73 | ... AE86: =SUM(AB51:AE51) -> 376297.47
B87: Cash interest paid | C87: =-C62 -> 21975.481 | D87: =-D62 -> 28984.61 | E87: =-E62 -> 47102.233 | F87: =-F62 -> 70452.675 | G87: =-G62 -> 68811.141 | H87: =-H62 -> 54985.787 | I87: =-I62 -> 54400.069 | N87: =-SUM(K62:N62) -> 28984.61 | O87: =-SUM(L62:O62) -> 29139.606 | P87: =-SUM(M62:P62) -> 31577.502 | Q87: =-SUM(N62:Q62) -> 44328.237 | R87: =-SUM(O62:R62) -> 47102.233 | S87: =-SUM(P62:S62) -> 65259.245 | T87: =-SUM(Q62:T62) -> 72722.558 | U87: =-SUM(R62:U62) -> 74038.254 | ... AE87: =-SUM(AB62:AE62) -> 54400.069
B88: Net Income | C88: =+C27 -> 108194.86 | D88: =+D27 -> 219050.68 | E88: =+E27 -> 135484.45 | F88: =+F27 -> 118425.44 | G88: =+G27 -> 176544.8 | H88: =+H27 -> 137292.68 | I88: =+I27 -> 134852.42 | N88: =SUM(K27:N27) -> 216479.06 | O88: =SUM(L27:O27) -> 216625.25 | P88: =SUM(M27:P27) -> 185559.76 | Q88: =SUM(N27:Q27) -> 156659.44 | R88: =SUM(O27:R27) -> 130199.79 | S88: =SUM(P27:S27) -> 121368.14 | T88: =SUM(Q27:T27) -> 125430.31 | U88: =SUM(R27:U27) -> 120238.95 | ... AE88: =SUM(AB27:AE27) -> 134852.42
B89: Capex | C89: =-C64 -> 116621.44 | D89: =-D64 -> 169520.15 | E89: =-E64 -> 185087.05 | F89: =-F64 -> 123169.08 | G89: =-G64 -> 100487.54 | H89: =-H64 -> 139443.19 | I89: =-I64 -> 151940.84 | N89: =-SUM(K64:N64) -> 169520.15 | O89: =-SUM(L64:O64) -> 168607.35 | P89: =-SUM(M64:P64) -> 174934.1 | Q89: =-SUM(N64:Q64) -> 195420 | R89: =-SUM(O64:R64) -> 185087.05 | S89: =-SUM(P64:S64) -> 179811.02 | T89: =-SUM(Q64:T64) -> 162720.98 | U89: =-SUM(R64:U64) -> 151490.88 | ... AE89: =-SUM(AB64:AE64) -> 151940.84
B90: Free cash flow | C90: =+C67 -> 951337.21 | D90: =+D67 -> 1250200 | E90: =+E67 -> 851245.25 | F90: =+F67 -> 1222500.6 | G90: =+G67 -> 1370357.5 | H90: =+H67 -> 1272067.2 | I90: =+I67 -> 1281517.6 | N90: =SUM(K67:N67) -> 1250200 | O90: =SUM(L67:O67) -> 1229531 | P90: =SUM(M67:P67) -> 1116227.5 | Q90: =SUM(N67:Q67) -> 981349.93 | R90: =SUM(O67:R67) -> 851245.25 | S90: =SUM(P67:S67) -> 880877.05 | T90: =SUM(Q67:T67) -> 1039827.8 | U90: =SUM(R67:U67) -> 1172021 | ... AE90: =SUM(AB67:AE67) -> 1281517.6
B92: BALANCE SHEET | C92: =C3 -> 44196 | D92: =D3 -> 44561 | E92: =E3 -> 44926 | F92: =F3 -> 45291 | G92: =G3 -> 45657 | H92: =H3 -> 46022 | I92: =I3 -> 46112 | K92: =K3 -> 44286 | L92: =L3 -> 44377 | M92: =M3 -> 44469 | N92: =N3 -> 44561 | O92: =O3 -> 44651 | P92: =P3 -> 44742 | Q92: =Q3 -> 44834 | R92: =R3 -> 44926 | ... AE92: =AE3 -> 46112
B94: Tangible fixed assets | C94: =1082515.88+7705.942+25079.352 -> 1115301.2 | D94: =1222261.454+9551.614+28335.983 -> 1260149.1 | E94: =1356846.302+10283.994+34865.971 -> 1401996.3 | F94: =1273987.695+8121.156+35745.221 -> 1317854.1 | G94: =1522708.449+12666.98+45017.172 -> 1580392.6 | H94: =1460212.852+11105.298+47784.003 -> 1519102.2 | I94: =AE94 -> 1578322.7 | K94: =1095145.671+7842.829+118528.004 -> 1221516.5 | L94: =1125851.432+120592.935+8201.801 -> 1254646.2 | M94: =1172547.211+127227.342+8985.307 -> 1308759.9 | N94: =D94 -> 1260149.1 | O94: =1211838.813+9416.611+29577.472 -> 1250832.9 | P94: =1307387.195+10897.478+36177.004 -> 1354461.7 | Q94: =1370320.579+11472.054+36100.609 -> 1417893.2 | R94: =E94 -> 1401996.3 | S94: =1333257.564+9839.583+37378.345 -> 1380475.5 | T94: =1352027.696+10248.246+38340.16 -> 1400616.1 | U94: =1381696.187+10787.227+36298.873 -> 1428782.3 | V94: =F94 -> 1317854.1 | W94: =1433997.921+11219.795 +37753.382 -> 1482971.1 | X94: =1448144.739+11621.5+37936.985 -> 1497703.2 | Y94: =1453172.645+11545.945+41638.555 -> 1506357.1 | Z94: =G94 -> 1580392.6 | AA94: =1499397.684+12479.164+48986.017 -> 1560862.9 | AB94: =1454072.468+11889.772+46484.952 -> 1512447.2 | AC94: =1450360.298+11485.403+47553.133 -> 1509398.8 | AD94: =H94 -> 1519102.2 | AE94: =1512813.94+12472.221+53036.535 -> 1578322.7
B95: Inventory | C95: 231843.26 | D95: 353427.06 | E95: 480799.53 | F95: 425728.43 | G95: 459384.55 | H95: 424300.96 | I95: =AE95 -> 424223.56 | K95: 243132.08 | L95: 294350.76 | M95: 330783.03 | N95: =D95 -> 353427.06 | O95: 406541.97 | P95: 489035.37 | Q95: 512074.31 | R95: =E95 -> 480799.53 | S95: 457677.56 | T95: 485774.69 | U95: 494772.27 | V95: =F95 -> 425728.43 | W95: =433720.308 -> 433720.31 | X95: 452083.72 | Y95: 467674.92 | Z95: =G95 -> 459384.55 | AA95: 454802.22 | AB95: 461341.73 | AC95: 474938.17 | AD95: =H95 -> 424300.96 | AE95: 424223.56
B96: Trade accounts receivable | C96: =275387.923+5313.079 -> 280701 | D96: =372995.729+5307.264 -> 378302.99 | E96: =445263.536+6204.099 -> 451467.64 | F96: =446486.753+9040.528 -> 455527.28 | G96: =506711.173+15501.99 -> 522213.16 | H96: =473691.412+16123.78 -> 489815.19 | I96: =AE96 -> 404600.29 | K96: =232095.227+4765.117 -> 236860.34 | L96: =219403.103+3497.501 -> 222900.6 | M96: =286669.489+4829.683 -> 291499.17 | N96: =D96 -> 378302.99 | O96: =333712.709+6757.563 -> 340470.27 | P96: =305095.12+5930.381 -> 311025.5 | Q96: =387713.357+4794.889 -> 392508.25 | R96: =E96 -> 451467.64 | S96: =341427.15+6197.382 -> 347624.53 | T96: =310599.397+5197.48 -> 315796.88 | U96: =407376.971+9184.176 -> 416561.15 | V96: =F96 -> 455527.28 | W96: =404033.048+6533.92 -> 410566.97 | X96: =348027.739+7935.045 -> 355962.78 | Y96: =423027.147+6058.986 -> 429086.13 | Z96: =G96 -> 522213.16 | AA96: =412266.475+11361.595 -> 423628.07 | AB96: =336883.19+12334.713 -> 349217.9 | AC96: =399329.989+11205.402 -> 410535.39 | AD96: =H96 -> 489815.19 | AE96: =391339.484+13260.805 -> 404600.29
B97: Trade accounts payable | C97: =324521.077+18432.354 -> 342953.43 | D97: =515522.729+26208.319 -> 541731.05 | E97: =491315.277+34282.408 -> 525597.69 | F97: =434974.163+55140.63 -> 490114.79 | G97: =514887.185+36417.518 -> 551304.7 | H97: =460627.211+24463.561 -> 485090.77 | I97: =AE97 -> 459795.77 | K97: =311063.33+18860.422 -> 329923.75 | L97: =345652.067+21977.445 -> 367629.51 | M97: =425905.785+23127.519 -> 449033.3 | N97: =D97 -> 541731.05 | O97: =481113.715+29304.465 -> 510418.18 | P97: =428151.643+34203.271 -> 462354.91 | Q97: =489575.842+30964.613 -> 520540.46 | R97: =E97 -> 525597.69 | S97: =380844.221+36678.305 -> 417522.53 | T97: =352530.301+35488.377 -> 388018.68 | U97: =418482.221+52995.09 -> 471477.31 | V97: =F97 -> 490114.79 | W97: =390208.996+67980.409 -> 458189.4 | X97: =318533.227+41543.333 -> 360076.56 | Y97: =413338.508+29047.863 -> 442386.37 | Z97: =G97 -> 551304.7 | AA97: =434246.435+38098.08 -> 472344.52 | AB97: =370508.015+27502.55 -> 398010.57 | AC97: =407650.573+23529.942 -> 431180.51 | AD97: =H97 -> 485090.77 | AE97: =427444.261+32351.509 -> 459795.77
B98: Net working capital | C98: =+C95+C96-C97 -> 169590.83 | D98: =+D95+D96-D97 -> 189999.01 | E98: =+E95+E96-E97 -> 406669.48 | F98: =+F95+F96-F97 -> 391140.92 | G98: =+G95+G96-G97 -> 430293.02 | H98: =+H95+H96-H97 -> 429025.38 | I98: =+I95+I96-I97 -> 369028.08 | K98: =+K95+K96-K97 -> 150068.68 | L98: =+L95+L96-L97 -> 149621.85 | M98: =+M95+M96-M97 -> 173248.9 | N98: =+N95+N96-N97 -> 189999.01 | O98: =+O95+O96-O97 -> 236594.06 | P98: =+P95+P96-P97 -> 337705.95 | Q98: =+Q95+Q96-Q97 -> 384042.1 | R98: =+R95+R96-R97 -> 406669.48 | ... AE98: =+AE95+AE96-AE97 -> 369028.08
B99: % of revenues | C99: =+C98/C83 -> 0.091295978 | D99: =+D98/D83 -> 0.076467206 | E99: =+E98/E83 -> 0.14998312 | F99: =+F98/F83 -> 0.15245854 | G99: =+G98/G83 -> 0.14814363 | H99: =+H98/H83 -> 0.14745038 | I99: =+I98/I83 -> 0.12674974 | N99: =+N98/N83 -> 0.076467206 | O99: =+O98/O83 -> 0.09045714 | P99: =+P98/P83 -> 0.12488913 | Q99: =+Q98/Q83 -> 0.13887288 | R99: =+R98/R83 -> 0.14998312 | S99: =+S98/S83 -> 0.14137056 | T99: =+T98/T83 -> 0.14990646 | U99: =+U98/U83 -> 0.15929249 | ... AE99: =+AE98/AE83 -> 0.12674974
B101: Inventory Days | C101: =IFERROR((C95/-C9)*365,"-") -> 85.995631 | D101: =IFERROR((D95/-D9)*365,"-") -> 99.879911 | E101: =IFERROR((E95/-E9)*365,"-") -> 115.8419 | F101: =IFERROR((F95/-F9)*365,"-") -> 112.71546 | G101: =IFERROR((G95/-G9)*365,"-") -> 105.39272 | H101: =IFERROR((H95/-H9)*365,"-") -> 95.714817 | I101: =IFERROR((I95/-I9)*365,"-") -> 95.904593 | K101: =IFERROR((K95/-K9)*(365/4),"-") -> 79.158426 | L101: =IFERROR((L95/-L9)*(365/4),"-") -> 107.6245 | M101: =IFERROR((M95/-M9)*(365/4),"-") -> 91.425407 | N101: =IFERROR((N95/-N9)*(365/4),"-") -> 74.727032 | O101: =IFERROR((O95/-O9)*(365/4),"-") -> 98.468254 | P101: =IFERROR((P95/-P9)*(365/4),"-") -> 133.92922 | Q101: =IFERROR((Q95/-Q9)*(365/4),"-") -> 119.28785 | R101: =IFERROR((R95/-R9)*(365/4),"-") -> 106.15895 | ... AE101: =IFERROR((AE95/-AE9)*(365/4),"-") -> 89.608889
B102: Receivable Days | C102: =IFERROR((C96/C7)*365,"-") -> 55.155154 | D102: =IFERROR((D96/D7)*365,"-") -> 55.572065 | E102: =IFERROR((E96/E7)*365,"-") -> 60.774346 | F102: =IFERROR((F96/F7)*365,"-") -> 64.807571 | G102: =IFERROR((G96/G7)*365,"-") -> 65.623496 | H102: =IFERROR((H96/H7)*365,"-") -> 61.445209 | I102: =IFERROR((I96/I7)*365,"-") -> 50.723208 | K102: =IFERROR((K96/K7)*(365/4),"-") -> 37.942432 | L102: =IFERROR((L96/L7)*(365/4),"-") -> 43.276414 | M102: =IFERROR((M96/M7)*(365/4),"-") -> 42.714042 | N102: =IFERROR((N96/N7)*(365/4),"-") -> 41.977511 | O102: =IFERROR((O96/O7)*(365/4),"-") -> 44.353273 | P102: =IFERROR((P96/P7)*(365/4),"-") -> 50.816348 | Q102: =IFERROR((Q96/Q7)*(365/4),"-") -> 52.355047 | R102: =IFERROR((R96/R7)*(365/4),"-") -> 53.61593 | ... AE102: =IFERROR((AE96/AE7)*(365/4),"-") -> 45.050748
B103: Payable Days | C103: =IFERROR((C97/-C9)*365,"-") -> 127.20877 | D103: =IFERROR((D97/-D9)*365,"-") -> 153.09538 | E103: =IFERROR((E97/-E9)*365,"-") -> 126.63539 | F103: =IFERROR((F97/-F9)*365,"-") -> 129.76233 | G103: =IFERROR((G97/-G9)*365,"-") -> 126.48118 | H103: =IFERROR((H97/-H9)*365,"-") -> 109.42793 | I103: =IFERROR((I97/-I9)*365,"-") -> 103.94643 | K103: =IFERROR((K97/-K9)*(365/4),"-") -> 107.41587 | L103: =IFERROR((L97/-L9)*(365/4),"-") -> 134.41767 | M103: =IFERROR((M97/-M9)*(365/4),"-") -> 124.1087 | N103: =IFERROR((N97/-N9)*(365/4),"-") -> 114.54118 | O103: =IFERROR((O97/-O9)*(365/4),"-") -> 123.62804 | P103: =IFERROR((P97/-P9)*(365/4),"-") -> 126.62241 | Q103: =IFERROR((Q97/-Q9)*(365/4),"-") -> 121.26004 | R103: =IFERROR((R97/-R9)*(365/4),"-") -> 116.05024 | ... AE103: =IFERROR((AE97/-AE9)*(365/4),"-") -> 97.122819
B105: Debt Breakdown
B106: Short-term debt | C106: =37754.705+7691.023 -> 45445.728 | D106: =76169.204+8087.63 -> 84256.834 | E106: =134737.116+30871.086 -> 165608.2 | F106: =24494.87+38650.859 -> 63145.729 | G106: =41257.611+98433.154 -> 139690.76 | H106: =124816.755+41058.78 -> 165875.54 | I106: =AE106 -> 120403.68 | K106: =41411.279+7192.5 -> 48603.779 | L106: =61289.733+7804.49 -> 69094.223 | M106: =64126.525+7340.297 -> 71466.822 | N106: =D106 -> 84256.834 | O106: =81013.066+10569.594 -> 91582.66 | P106: =141492.315+17357.3 -> 158849.61 | Q106: =165097.613+11338.507 -> 176436.12 | R106: =E106 -> 165608.2 | S106: =107559.335+24587.681 -> 132147.02 | T106: =29621.543+44578.074 -> 74199.617 | U106: =42191.827+32208.645 -> 74400.472 | V106: =F106 -> 63145.729 | W106: =25097.484+33123.81 -> 58221.294 | X106: =75182.177+96174.313 -> 171356.49 | Y106: =71451.984+90263.742 -> 161715.73 | Z106: =G106 -> 139690.76 | AA106: =33795.782+92541.67 -> 126337.45 | AB106: =92000.97+40903.25 -> 132904.22 | AC106: =110690.862+34423.775 -> 145114.64 | AD106: =H106 -> 165875.54 | AE106: =85852.526+34551.156 -> 120403.68
B107: Long-term debt | C107: =88151.4+324725.456 -> 412876.86 | D107: =114492.596+339740.414 -> 454233.01 | E107: =84839.97+1081682.928 -> 1166522.9 | F107: =174074.17+1050838.488 -> 1224912.7 | G107: =166647.324+1059003.92 -> 1225651.2 | H107: =39713.245+992483.21 -> 1032196.5 | I107: =AE107 -> 1046265.7 | K107: =86983.317+325525.69 -> 412509.01 | L107: =39143.411+328780.956 -> 367924.37 | M107: =40855.587+330013.839 -> 370869.43 | N107: =D107 -> 454233.01 | O107: =112771.821+814692.362 -> 927464.18 | P107: =61820.938+982200.672 -> 1044021.6 | Q107: =126818.265+1006058.674 -> 1132876.9 | R107: =E107 -> 1166522.9 | S107: =74307.931+1047272.741 -> 1121580.7 | T107: =174395.287+1048761.511 -> 1223156.8 | U107: =176150.291+1066823.971 -> 1242974.3 | V107: =F107 -> 1224912.7 | W107: =172922.837+1117312.253 -> 1290235.1 | X107: =171173.692+1031632.249 -> 1202805.9 | Y107: =168609.778+1008309.288 -> 1176919.1 | Z107: =G107 -> 1225651.2 | AA107: =166263.683+1039093.986 -> 1205357.7 | AB107: =35006.446+1017335.003 -> 1052341.4 | AC107: =37701.506+1037259.218 -> 1074960.7 | AD107: =H107 -> 1032196.5 | AE107: =40280.382+1005985.277 -> 1046265.7
B108: Total Debt | C108: =SUM(C106:C107) -> 458322.58 | D108: =SUM(D106:D107) -> 538489.84 | E108: =SUM(E106:E107) -> 1332131.1 | F108: =SUM(F106:F107) -> 1288058.4 | G108: =SUM(G106:G107) -> 1365342 | H108: =SUM(H106:H107) -> 1198072 | I108: =SUM(I106:I107) -> 1166669.3 | K108: =SUM(K106:K107) -> 461112.79 | L108: =SUM(L106:L107) -> 437018.59 | M108: =SUM(M106:M107) -> 442336.25 | N108: =SUM(N106:N107) -> 538489.84 | O108: =SUM(O106:O107) -> 1019046.8 | P108: =SUM(P106:P107) -> 1202871.2 | Q108: =SUM(Q106:Q107) -> 1309313.1 | R108: =SUM(R106:R107) -> 1332131.1 | ... AE108: =SUM(AE106:AE107) -> 1166669.3
B110: Lease Obligations
B111: Short-term | C111: 4934.639 | D111: 6152.361 | E111: 9120.616 | F111: 7142.36 | G111: 9451.551 | H111: 9689.87 | I111: =AE111 -> 11649.606 | K111: 4999.485 | L111: 4467.807 | M111: 6201.679 | N111: =D111 -> 6152.361 | O111: 6703.534 | P111: 8758.514 | Q111: 9066.122 | R111: =E111 -> 9120.616 | S111: =8358.621 -> 8358.621 | T111: 8112.477 | U111: 7402.507 | V111: =F111 -> 7142.36 | W111: =6994.71 -> 6994.71 | X111: 8038.01 | Y111: 8902.02 | Z111: =G111 -> 9451.551 | AA111: 9974.047 | AB111: 9314.383 | AC111: 9589.431 | AD111: =H111 -> 9689.87 | AE111: 11649.606
B112: Long-term | C112: 27200.272 | D112: 29009.023 | E112: 31306.552 | F112: 34061.739 | G112: 39782.317 | H112: 42232.779 | I112: =AE112 -> 45202.298 | K112: 27224.502 | L112: 26681.947 | M112: 29251.951 | N112: =D112 -> 29009.023 | O112: 29067.283 | P112: 33339.877 | Q112: 32758.366 | R112: =E112 -> 31306.552 | S112: =34480.263 -> 34480.263 | T112: 35633.127 | U112: 34313.719 | V112: =F112 -> 34061.739 | W112: =35226.387 -> 35226.387 | X112: 34606.451 | Y112: 37191.65 | Z112: =G112 -> 39782.317 | AA112: 43489.886 | AB112: 41537.585 | AC112: 42358.944 | AD112: =H112 -> 42232.779 | AE112: 45202.298
B113: Total Lease | C113: =SUM(C111:C112) -> 32134.911 | D113: =SUM(D111:D112) -> 35161.384 | E113: =SUM(E111:E112) -> 40427.168 | F113: =SUM(F111:F112) -> 41204.099 | G113: =SUM(G111:G112) -> 49233.868 | H113: =SUM(H111:H112) -> 51922.649 | I113: =SUM(I111:I112) -> 56851.904 | K113: =SUM(K111:K112) -> 32223.987 | L113: =SUM(L111:L112) -> 31149.754 | M113: =SUM(M111:M112) -> 35453.63 | N113: =SUM(N111:N112) -> 35161.384 | O113: =SUM(O111:O112) -> 35770.817 | P113: =SUM(P111:P112) -> 42098.391 | Q113: =SUM(Q111:Q112) -> 41824.488 | R113: =SUM(R111:R112) -> 40427.168 | ... AE113: =SUM(AE111:AE112) -> 56851.904
B115: Debt Including Lease obligations
...

Sheet Adjusted EBITDA
B2: Compañía Cervecerías Unidas S.A. | C2: Annual | D2: Annual | E2: Annual | F2: Annual | G2: LTM | I2: Annual | J2: Annual | K2: Annual | L2: Annual | M2: Annual | N2: Annual | O2: Annual | P2: Annual | Q2: Annual
B3: (CLP millions) | C3: 44926 | D3: 45291 | E3: 45657 | F3: 46022 | G3: =Q3 -> 46112 | I3: 45382 | J3: 45473 | K3: 45565 | L3: 45657 | M3: 45747 | N3: 45838 | O3: 45565 | P3: 46022 | Q3: 46112
C4: Act | D4: Act | E4: Act | F4: Act | G4: Act | I4: Act | J4: Act | K4: Act | L4: Act | M4: Act | N4: Act | O4: Act | P4: Act | Q4: Act
C5: FY | D5: FY | E5: FY | F5: FY | G5: LTM | I5: 1Q | J5: 2Q | K5: 3Q | L5: 4Q | M5: 1Q | N5: 2Q | O5: 3Q | P5: 4Q | Q5: 1Q
B7: Profit (loss) for the year | C7: =Model!E27 -> 135484.45 | D7: =Model!F27 -> 118425.44 | E7: =Model!G27 -> 176544.8 | F7: =Model!H27 -> 137292.68 | G7: =Model!I27 -> 134852.42 | I7: =Model!W27 -> 55027.607 | J7: =Model!X27 -> 6830.609 | K7: =Model!Y27 -> 32553.901 | L7: =Model!Z27 -> 82132.68 | M7: =Model!AA27 -> 61487.966 | N7: =Model!AB27 -> -11212.532 | O7: =Model!AC27 -> 20685.663 | P7: =Model!AD27 -> 66331.587 | Q7: =Model!AE27 -> 59047.698
B8: Other gains (losses) | C8: =-Model!E17 -> 12669.54 | D8: =-Model!F17 -> 13316.208 | E8: =-Model!G17 -> 94.937 | F8: =-Model!H17 -> 27672.922 | G8: =-Model!I17 -> 14296.718 | I8: =-Model!W17 -> -1064.348 | J8: =-Model!X17 -> 5256.413 | K8: =-Model!Y17 -> 4311.792 | L8: =-Model!Z17 -> -8408.92 | M8: =-Model!AA17 -> 7444.459 | N8: =-Model!AB17 -> 9465.32 | O8: =-Model!AC17 -> -4187.269 | P8: =-Model!AD17 -> 14950.412 | Q8: =-Model!AE17 -> -5931.745
B9: Financial income | C9: =-Model!E19 -> -22870.538 | D9: =-Model!F19 -> -39402.492 | E9: =-Model!G19 -> -38102.053 | F9: =-Model!H19 -> -27522.243 | G9: =-Model!I19 -> -23045.073 | I9: =-Model!W19 -> -12703.221 | J9: =-Model!X19 -> -9103.863 | K9: =-Model!Y19 -> -7834.17 | L9: =-Model!Z19 -> -8460.799 | M9: =-Model!AA19 -> -9495.959 | N9: =-Model!AB19 -> -7982.055 | O9: =-Model!AC19 -> -5392.814 | P9: =-Model!AD19 -> -4651.415 | Q9: =-Model!AE19 -> -5018.789
B10: Financial costs | C10: =-Model!E20 -> 75930.875 | D10: =-Model!F20 -> 77023.048 | E10: =-Model!G20 -> 97165.278 | F10: =-Model!H20 -> 79947.714 | G10: =-Model!I20 -> 77524.639 | I10: =-Model!W20 -> 19368.518 | J10: =-Model!X20 -> 21389.854 | K10: =-Model!Y20 -> 27687.403 | L10: =-Model!Z20 -> 28719.503 | M10: =-Model!AA20 -> 20752.884 | N10: =-Model!AB20 -> 18154.517 | O10: =-Model!AC20 -> 20330.452 | P10: =-Model!AD20 -> 20709.861 | Q10: =-Model!AE20 -> 18329.809
B11: Share in profit (loss) of associates and joint ventures accounted for using the equity method | C11: =-Model!E21 -> 10978.068 | D11: =-Model!F21 -> 19217.758 | E11: =-Model!G21 -> 9494.703 | F11: =-Model!H21 -> 14352.591 | G11: =-Model!I21 -> 15194.615 | I11: =-Model!W21 -> 3317.839 | J11: =-Model!X21 -> 2577.643 | K11: =-Model!Y21 -> 530.841 | L11: =-Model!Z21 -> 3068.38 | M11: =-Model!AA21 -> 1517.971 | N11: =-Model!AB21 -> 6064.957 | O11: =-Model!AC21 -> 5357.183 | P11: =-Model!AD21 -> 1412.48 | Q11: =-Model!AE21 -> 2359.995
B12: Foreign currency exchange gains (losses) | C12: =-Model!E22 -> 20173.381 | D12: =-Model!F22 -> 65944.57 | E12: =-Model!G22 -> 17797.269 | F12: =-Model!H22 -> -1473.55 | G12: =-Model!I22 -> -7.988 | I12: =-Model!W22 -> 8467.435 | J12: =-Model!X22 -> -1.628 | K12: =-Model!Y22 -> -4573.011 | L12: =-Model!Z22 -> 13904.473 | M12: =-Model!AA22 -> 444.237 | N12: =-Model!AB22 -> -1916.962 | O12: =-Model!AC22 -> 9350.023 | P12: =-Model!AD22 -> -9350.848 | Q12: =-Model!AE22 -> 1909.799
B13: Result by adjustment units | C13: =-Model!E23 -> -1198.565 | D13: =-Model!F23 -> 14025.895 | E13: =-Model!G23 -> 10722.033 | F13: =-Model!H23 -> 17631.014 | G13: =-Model!I23 -> 14480.093 | I13: =-Model!W23 -> 1879.441 | J13: =-Model!X23 -> 3395.306 | K13: =-Model!Y23 -> -54.079 | L13: =-Model!Z23 -> 5501.365 | M13: =-Model!AA23 -> 6017.421 | N13: =-Model!AB23 -> 6474.768 | O13: =-Model!AC23 -> 2553.246 | P13: =-Model!AD23 -> 2585.579 | Q13: =-Model!AE23 -> 2866.5
B14: Income taxes | C14: =-Model!E26 -> 263.943 | D14: =-Model!F26 -> -15267.255 | E14: =-Model!G26 -> -11015.074 | F14: =-Model!H26 -> -27051.867 | G14: =-Model!I26 -> -12546.153 | I14: =-Model!W26 -> 14620.924 | J14: =-Model!X26 -> -27900.465 | K14: =-Model!Y26 -> -18994.161 | L14: =-Model!Z26 -> 21258.628 | M14: =-Model!AA26 -> 3714.274 | N14: =-Model!AB26 -> -36387.682 | O14: =-Model!AC26 -> -12304.256 | P14: =-Model!AD26 -> 17925.797 | Q14: =-Model!AE26 -> 18219.988
B15: Adjusted operating result | C15: =SUM(C7:C14) -> 231431.16 | D15: =SUM(D7:D14) -> 253283.17 | E15: =SUM(E7:E14) -> 262701.89 | F15: =SUM(F7:F14) -> 220849.26 | G15: =SUM(G7:G14) -> 220749.27 | I15: =SUM(I7:I14) -> 88914.195 | J15: =SUM(J7:J14) -> 2443.869 | K15: =SUM(K7:K14) -> 33628.516 | L15: =SUM(L7:L14) -> 137715.31 | M15: =SUM(M7:M14) -> 91883.253 | N15: =SUM(N7:N14) -> -17339.669 | O15: =SUM(O7:O14) -> 36392.228 | P15: =SUM(P7:P14) -> 109913.45 | Q15: =SUM(Q7:Q14) -> 91783.255
B16: Depreciation and amortization | C16: =Model!E45 -> 126497.49 | D16: =Model!F45 -> 126119.2 | E16: =Model!G45 -> 153234.22 | F16: =Model!H45 -> 155358.69 | G16: =Model!I45 -> 155548.16 | I16: =Model!W45 -> 35249.053 | J16: =Model!X45 -> 36277.691 | K16: =Model!Y45 -> 36802.182 | L16: =Model!Z45 -> 44905.298 | M16: =Model!AA45 -> 39670.795 | N16: =Model!AB45 -> 37156.952 | O16: =Model!AC45 -> 37243.232 | P16: =Model!AD45 -> 41287.714 | Q16: =Model!AE45 -> 39860.26
B17: ROADA | C17: =SUM(C15:C16) -> 357928.65 | D17: =SUM(D15:D16) -> 379402.37 | E17: =SUM(E15:E16) -> 415936.11 | F17: =SUM(F15:F16) -> 376207.96 | G17: =SUM(G15:G16) -> 376297.42 | I17: =SUM(I15:I16) -> 124163.25 | J17: =SUM(J15:J16) -> 38721.56 | K17: =SUM(K15:K16) -> 70430.698 | L17: =SUM(L15:L16) -> 182620.61 | M17: =SUM(M15:M16) -> 131554.05 | N17: =SUM(N15:N16) -> 19817.283 | O17: =SUM(O15:O16) -> 73635.46 | P17: =SUM(P15:P16) -> 151201.17 | Q17: =SUM(Q15:Q16) -> 131643.51
B18: check | C18: =C17-Model!E51 -> 0 | D18: =D17-Model!F51 -> 0 | E18: =E17-Model!G51 -> 0 | F18: =F17-Model!H51 -> 0 | G18: =G17-Model!I51 -> -0.048 | I18: =I17-Model!W51 -> 0 | J18: =J17-Model!X51 -> -0.44 | K18: =K17-Model!Y51 -> 0 | L18: =L17-Model!Z51 -> 0.44 | M18: =M17-Model!AA51 -> 0.048 | N18: =N17-Model!AB51 -> -6.184564e-11 | O18: =O17-Model!AC51 -> 0.46 | P18: =P17-Model!AD51 -> -0.508 | Q18: =Q17-Model!AE51 -> 0

Sheet KPIs
B2: Compañía Cervecerías Unidas S.A. | C2: Annual | D2: Annual | E2: Annual | F2: Annual | G2: Annual | H2: Annual | I2: LTM | K2: Quarters | L2: Quarters | M2: Quarters | N2: Quarters | O2: Quarters | P2: Quarters | Q2: Quarters | R2: Quarters | S2: Quarters | T2: Quarters | U2: Quarters | V2: Quarters | W2: Quarters | X2: Quarters | Y2: Quarters | Z2: Quarters | AA2: Quarters | AB2: Quarters | AC2: Quarters | AD2: Quarters | AE2: Quarters
B3: (CLP millions) | C3: 44196 | D3: 44561 | E3: 44926 | F3: 45291 | G3: 45657 | H3: 46022 | I3: =AE3 -> 46112 | K3: 44286 | L3: 44377 | M3: 44469 | N3: 44561 | O3: 44651 | P3: 44742 | Q3: 44834 | R3: 44926 | S3: 45016 | T3: 45107 | U3: 45199 | V3: 45291 | W3: 45382 | X3: 45473 | Y3: 45565 | Z3: 45657 | AA3: 45747 | AB3: 45838 | AC3: 45930 | AD3: 46022 | AE3: 46112
C4: Act | D4: Act | E4: Act | F4: Act | G4: Act | H4: Act | I4: Act | K4: Act | L4: Act | M4: Act | N4: Act | O4: Act | P4: Act | Q4: Act | R4: Act | S4: Act | T4: Act | U4: Act | V4: Act | W4: Act | X4: Act | Y4: Act | Z4: Act | AA4: Act | AB4: Act | AC4: Act | AD4: Act | AE4: Act
C5: FY | D5: FY | E5: FY | F5: FY | G5: FY | H5: FY | I5: LTM | K5: 1Q | L5: 2Q | M5: 3Q | N5: 4Q | O5: 1Q | P5: 2Q | Q5: 3Q | R5: 4Q | S5: 1Q | T5: 2Q | U5: 3Q | V5: 4Q | W5: 1Q | X5: 2Q | Y5: 3Q | Z5: 4Q | AA5: 1Q | AB5: 2Q | AC5: 3Q | AD5: 4Q | AE5: 1Q
B7: Volume by segment
B8: Chile | C8: 20483.028 | D8: 23897.316 | E8: 23387.927 | F8: 22781.417 | G8: 22707 | H8: 22966 | I8: =SUM(AB8:AE8) -> 23216 | K8: 6249.0652 | L8: 4752.3672 | M8: 5549.36 | N8: =D8-SUM(K8:M8) -> 7346.5238 | O8: 6729.0794 | P8: 4601.0906 | Q8: 5285.4316 | R8: =E8-SUM(O8:Q8) -> 6772.3255 | S8: 6645.1367 | T8: 4817.7771 | U8: 5038.5182 | V8: =F8-SUM(S8:U8) -> 6279.9847 | W8: 6587.9264 | X8: 4414 | Y8: 5127 | Z8: =G8-SUM(W8:Y8) -> 6578.0736 | AA8: 6463 | AB8: 4557 | AC8: 5096 | AD8: =H8-SUM(AA8:AC8) -> 6850 | AE8: 6713
B9: Interntional Business | C9: 8783.4653 | D9: 9424.2216 | E9: 9526.5548 | F9: 9095.3138 | G9: 9780 | H9: 12029 | I9: =SUM(AB9:AE9) -> 11973 | K9: 2461.7703 | L9: 1629.1315 | M9: 2316.5858 | N9: =D9-SUM(K9:M9) -> 3016.734 | O9: 2655.7975 | P9: 1601.8377 | Q9: 2285.9536 | R9: =E9-SUM(O9:Q9) -> 2982.966 | S9: 2440.6785 | T9: 1731.8667 | U9: 2187.2273 | V9: =F9-SUM(S9:U9) -> 2735.5412 | W9: 2081.5159 | X9: 1260 | Y9: 2517 | Z9: =G9-SUM(W9:Y9) -> 3921.4841 | AA9: 3382 | AB9: 2256 | AC9: 2650 | AD9: =H9-SUM(AA9:AC9) -> 3741 | AE9: 3326
B10: Wine | C10: 1532.9779 | D10: 1582.6787 | E10: 1573.3503 | F10: 1346.983 | G10: 1361 | H10: 1321 | I10: =SUM(AB10:AE10) -> 1304 | K10: 352.69224 | L10: 413.31011 | M10: 434.23146 | N10: =D10-SUM(K10:M10) -> 382.44485 | O10: 352.18244 | P10: 411.0761 | Q10: 436.74294 | R10: =E10-SUM(O10:Q10) -> 373.3488 | S10: 289.40475 | T10: 355.8627 | U10: 361.32585 | V10: =F10-SUM(S10:U10) -> 340.38974 | W10: 297.18898 | X10: 356 | Y10: 368 | Z10: =G10-SUM(W10:Y10) -> 339.81102 | AA10: 286 | AB10: 371 | AC10: 357 | AD10: =H10-SUM(AA10:AC10) -> 307 | AE10: 269
B11: Other/Eliminations | C11: -112.53026 | D11: -206.09447 | E11: -166.99954 | F11: -86.682108 | G11: -75 | H11: -67 | I11: =SUM(AB11:AE11) -> -61 | K11: -21.548217 | L11: -36.083045 | M11: -87.352718 | N11: =D11-SUM(K11:M11) -> -61.110496 | O11: -44.790978 | P11: -46.532536 | Q11: -44.379951 | R11: =E11-SUM(O11:Q11) -> -31.296077 | S11: -12.933892 | T11: -22.557995 | U11: -27.751202 | V11: =F11-SUM(S11:U11) -> -23.439017 | W11: -14.875382 | X11: -21 | Y11: =Y12-SUM(Y8:Y10) -> -21 | Z11: =G11-SUM(W11:Y11) -> -18.124618 | AA11: -18 | AB11: -18 | AC11: -17 | AD11: =H11-SUM(AA11:AC11) -> -14 | AE11: -12
B12: Total | C12: =SUM(C8:C11) -> 30686.941 | D12: =SUM(D8:D11) -> 34698.122 | E12: =SUM(E8:E11) -> 34320.833 | F12: =SUM(F8:F11) -> 33137.031 | G12: =SUM(G8:G11) -> 33773 | H12: =SUM(H8:H11) -> 36249 | I12: =SUM(I8:I11) -> 36432 | K12: =SUM(K8:K11) -> 9041.9795 | L12: =SUM(L8:L11) -> 6758.7258 | M12: =SUM(M8:M11) -> 8212.8245 | N12: =SUM(N8:N11) -> 10684.592 | O12: =SUM(O8:O11) -> 9692.2683 | P12: =SUM(P8:P11) -> 6567.4719 | Q12: =SUM(Q8:Q11) -> 7963.7482 | R12: =SUM(R8:R11) -> 10097.344 | ... X12: =SUM(X8:X11) -> 6009 | Y12: 7991 | Z12: =SUM(Z8:Z11) -> 10821.244 | AA12: =SUM(AA8:AA11) -> 10113 | AB12: =SUM(AB8:AB11) -> 7166 | AC12: =SUM(AC8:AC11) -> 8086 | AD12: =SUM(AD8:AD11) -> 10884 | AE12: =SUM(AE8:AE11) -> 10296
B15: Revenue by segment
B16: Chile | C16: 1242762.9 | D16: 1578151.9 | E16: 1673349.4 | F16: 1758971.2 | G16: 1829243.7 | H16: 1914527.6 | I16: =SUM(AB16:AE16) -> 1934647.8 | K16: 393220.48 | L16: 316435.84 | M16: 378830.11 | N16: =D16-SUM(K16:M16) -> 489665.48 | O16: 458484.32 | P16: 328283.18 | Q16: 379318.88 | R16: =E16-SUM(O16:Q16) -> 507262.97 | S16: 487817.87 | T16: 376377.67 | U16: 398549.51 | V16: =F16-SUM(S16:U16) -> 496226.19 | W16: 501876.69 | X16: 355612.75 | Y16: 426414.32 | Z16: =G16-SUM(W16:Y16) -> 545339.9 | AA16: 515794.59 | AB16: 389247 | AC16: 434113.76 | AD16: =H16-SUM(AA16:AC16) -> 575372.27 | AE16: 535914.74
B17: Interntional Business | C17: 402828.83 | D17: 677906.8 | E17: 782563.35 | F17: 586484.36 | G17: 850118.28 | H17: 780295.79 | I17: =SUM(AB17:AE17) -> 763245.66 | K17: 124661.8 | L17: 95899.854 | M17: 185198.93 | N17: =D17-SUM(K17:M17) -> 272146.2 | O17: 188548.22 | P17: 163888.84 | Q17: 232995.39 | R17: =E17-SUM(O17:Q17) -> 197130.91 | S17: 197386.87 | T17: 142511.78 | U17: 227378.59 | V17: =F17-SUM(S17:U17) -> 19207.123 | W17: 194253.75 | X17: 111001.54 | Y17: 177834.13 | Z17: =G17-SUM(W17:Y17) -> 367028.85 | AA17: 256029.91 | AB17: 128328 | AC17: 161979.26 | AD17: =H17-SUM(AA17:AC17) -> 233958.61 | AE17: 238979.79
B18: Wine | C18: 235210.37 | D18: 261620.06 | E18: 296349.89 | F18: 252825.5 | G18: 282637.92 | H18: 276488.98 | I18: =SUM(AB18:AE18) -> 272184.61 | K18: 56402.916 | L18: 64781.743 | M18: 70846.894 | N18: =D18-SUM(K18:M18) -> 69588.512 | O18: 64005.599 | P18: 75617.508 | Q18: 84892.705 | R18: =E18-SUM(O18:Q18) -> 71834.081 | S18: 52646.744 | T18: 64369.292 | U18: 72379.599 | V18: =F18-SUM(S18:U18) -> 63429.861 | W18: 58765.21 | X18: 72124.558 | Y18: 74774.164 | Z18: =G18-SUM(W18:Y18) -> 76973.991 | AA18: 60021.512 | AB18: 76444 | AC18: 75990.644 | AD18: =H18-SUM(AA18:AC18) -> 64032.826 | AE18: 55717.137
B19: Other/Eliminations | C19: -23208.385 | D19: -32966.495 | E19: -40827.654 | F19: -32725.024 | G19: -57433.404 | H19: -61686.943 | I19: =SUM(AB19:AE19) -> -58607.907 | K19: -4645.7401 | L19: -7122.854 | M19: -12146.316 | N19: =D19-SUM(K19:M19) -> -9051.5842 | O19: -10573.213 | P19: -9286.6365 | Q19: -13101.438 | R19: =E19-SUM(O19:Q19) -> -7866.3664 | S19: -5820.7235 | T19: -9017.0366 | U19: -11630.788 | V19: =F19-SUM(S19:U19) -> -6256.4757 | W19: -8871.6675 | X19: -14097.371 | Y19: -13199.343 | Z19: =G19-SUM(W19:Y19) -> -21265.023 | AA19: -14175.427 | AB19: -14104 | AC19: -13455.815 | AD19: =H19-SUM(AA19:AC19) -> -19951.701 | AE19: -11096.391
B20: Total | C20: =SUM(C16:C19) -> 1857593.7 | D20: =SUM(D16:D19) -> 2484712.3 | E20: =SUM(E16:E19) -> 2711434.9 | F20: =SUM(F16:F19) -> 2565556.1 | G20: =SUM(G16:G19) -> 2904566.5 | H20: =SUM(H16:H19) -> 2909625.4 | I20: =SUM(I16:I19) -> 2911470.1 | K20: =SUM(K16:K19) -> 569639.46 | L20: =SUM(L16:L19) -> 469994.59 | M20: =SUM(M16:M19) -> 622729.63 | N20: =SUM(N16:N19) -> 822348.61 | O20: =SUM(O16:O19) -> 700464.93 | P20: =SUM(P16:P19) -> 558502.88 | Q20: =SUM(Q16:Q19) -> 684105.54 | R20: =SUM(R16:R19) -> 768361.6 | ... AE20: =SUM(AE16:AE19) -> 819515.28
B21: Check | C21: =C20-Model!C7 -> -7.2000083e-05 | D21: =D20-Model!D7 -> 7.8819226e-05 | E21: =E20-Model!E7 -> 0.00025487412 | F21: =F20-Model!F7 -> 0.00038081966 | G21: =G20-Model!G7 -> 0 | H21: =H20-Model!H7 -> 0 | I21: =I20-Model!I7 -> 0 | K21: =K20-Model!K7 -> -2.0000036e-05 | L21: =L20-Model!L7 -> -0.00065585802 | M21: =M20-Model!M7 -> -0.00016058912 | N21: =N20-Model!N7 -> 0.00091526622 | O21: =O20-Model!O7 -> 0.00017039687 | P21: =P20-Model!P7 -> 0.00058699504 | Q21: =Q20-Model!Q7 -> 0.00027804589 | R21: =R20-Model!R7 -> -0.00078056392 | ... AE21: =AE20-Model!AE7 -> 0
B24: Revenue by segment (% Share)
B25: Chile | C25: =C16/C$20 -> 0.6690176 | D25: =D16/D$20 -> 0.63514473 | E25: =E16/E$20 -> 0.61714531 | F25: =F16/F$20 -> 0.68561013 | G25: =G16/G$20 -> 0.629782 | H25: =H16/H$20 -> 0.65799797 | I25: =I16/I$20 -> 0.66449171 | K25: =K16/K$20 -> 0.69029712 | L25: =L16/L$20 -> 0.6732755 | M25: =M16/M$20 -> 0.60833803 | N25: =N16/N$20 -> 0.59544757 | O25: =O16/O$20 -> 0.65454287 | P25: =P16/P$20 -> 0.58779137 | Q25: =Q16/Q$20 -> 0.55447422 | R25: =R16/R$20 -> 0.66018783 | ... AE25: =AE16/AE$20 -> 0.65394113
B26: Interntional Business | C26: =C17/C$20 -> 0.21685519 | D26: =D17/D$20 -> 0.2728311 | E26: =E17/E$20 -> 0.28861594 | F26: =F17/F$20 -> 0.22859932 | G26: =G17/G$20 -> 0.29268336 | H26: =H17/H$20 -> 0.2681774 | I26: =I17/I$20 -> 0.26215129 | K26: =K17/K$20 -> 0.21884334 | L26: =L17/L$20 -> 0.20404459 | M26: =M17/M$20 -> 0.29739862 | N26: =N17/N$20 -> 0.33093776 | O26: =O17/O$20 -> 0.26917582 | P26: =P17/P$20 -> 0.29344314 | Q26: =Q17/Q$20 -> 0.34058398 | R26: =R17/R$20 -> 0.25656007 | ... AE26: =AE17/AE$20 -> 0.29161114
B27: Wine | C27: =C18/C$20 -> 0.126621 | D27: =D18/D$20 -> 0.1052919 | E27: =E18/E$20 -> 0.10929633 | F27: =F18/F$20 -> 0.098546081 | G27: =G18/G$20 -> 0.097308128 | H27: =H18/H$20 -> 0.095025627 | I27: =I18/I$20 -> 0.093486999 | K27: =K18/K$20 -> 0.099015114 | L27: =L18/L$20 -> 0.13783508 | M27: =M18/M$20 -> 0.11376831 | N27: =N18/N$20 -> 0.084621669 | O27: =O18/O$20 -> 0.09137588 | P27: =P18/P$20 -> 0.13539323 | Q27: =Q18/Q$20 -> 0.124093 | R27: =R18/R$20 -> 0.093489942 | ... AE27: =AE18/AE$20 -> 0.067987917
B28: Other/Eliminations | C28: =C19/C$20 -> -0.01249379 | D28: =D19/D$20 -> -0.013267731 | E28: =E19/E$20 -> -0.015057582 | F28: =F19/F$20 -> -0.012755529 | G28: =G19/G$20 -> -0.019773486 | H28: =H19/H$20 -> -0.021200991 | I28: =I19/I$20 -> -0.020130005 | K28: =K19/K$20 -> -0.00815558 | L28: =L19/L$20 -> -0.015155183 | M28: =M19/M$20 -> -0.01950496 | N28: =N19/N$20 -> -0.011006992 | O28: =O19/O$20 -> -0.015094564 | P28: =P19/P$20 -> -0.016627732 | Q28: =Q19/Q$20 -> -0.019151195 | R28: =R19/R$20 -> -0.010237844 | ... AE28: =AE19/AE$20 -> -0.013540188
B29: Total | C29: =SUM(C25:C28) -> 1 | D29: =SUM(D25:D28) -> 1 | E29: =SUM(E25:E28) -> 1 | F29: =SUM(F25:F28) -> 1 | G29: =SUM(G25:G28) -> 1 | H29: =SUM(H25:H28) -> 1 | I29: =SUM(I25:I28) -> 1 | K29: =SUM(K25:K28) -> 1 | L29: =SUM(L25:L28) -> 1 | M29: =SUM(M25:M28) -> 1 | N29: =SUM(N25:N28) -> 1 | O29: =SUM(O25:O28) -> 1 | P29: =SUM(P25:P28) -> 1 | Q29: =SUM(Q25:Q28) -> 1 | R29: =SUM(R25:R28) -> 1 | ... AE29: =SUM(AE25:AE28) -> 1
B32: Revenue by segment (% YoY Growth)
B33: Chile | D33: =D16/C16-1 -> 0.26987372 | E33: =E16/D16-1 -> 0.060322104 | F33: =F16/E16-1 -> 0.051167963 | G33: =G16/F16-1 -> 0.039950865 | H33: =H16/G16-1 -> 0.046622529 | I33: =I16/H16-1 -> 0.0105092 | O33: =O16/K16-1 -> 0.16597266 | P33: =P16/L16-1 -> 0.037439924 | Q33: =Q16/M16-1 -> 0.0012902069 | R33: =R16/N16-1 -> 0.035937788 | S33: =S16/O16-1 -> 0.063979388 | T33: =T16/P16-1 -> 0.14650307 | U33: =U16/Q16-1 -> 0.050697776 | V33: =V16/R16-1 -> -0.021757521 | ... AE33: =AE16/AA16-1 -> 0.039008073
B34: Interntional Business | D34: =D17/C17-1 -> 0.68286566 | E34: =E17/D17-1 -> 0.15438192 | F34: =F17/E17-1 -> -0.25055989 | G34: =G17/F17-1 -> 0.44951568 | H34: =H17/G17-1 -> -0.08213268 | I34: =I17/H17-1 -> -0.02185085 | O34: =O17/K17-1 -> 0.51247788 | P34: =P17/L17-1 -> 0.70895815 | Q34: =Q17/M17-1 -> 0.25808167 | R34: =R17/N17-1 -> -0.27564336 | S34: =S17/O17-1 -> 0.046877392 | T34: =T17/P17-1 -> -0.13043632 | U34: =U17/Q17-1 -> -0.024106903 | V34: =V17/R17-1 -> -0.90256666 | ... AE34: =AE17/AA17-1 -> -0.066594273
B35: Wine | D35: =D18/C18-1 -> 0.11228117 | E35: =E18/D18-1 -> 0.1327491 | F35: =F18/E18-1 -> -0.14686828 | G35: =G18/F18-1 -> 0.11791701 | H35: =H18/G18-1 -> -0.021755541 | I35: =I18/H18-1 -> -0.01556798 | O35: =O18/K18-1 -> 0.13479238 | P35: =P18/L18-1 -> 0.16726571 | Q35: =Q18/M18-1 -> 0.19825584 | R35: =R18/N18-1 -> 0.032269258 | S35: =S18/O18-1 -> -0.17746659 | T35: =T18/P18-1 -> -0.14875148 | U35: =U18/Q18-1 -> -0.14739907 | V35: =V18/R18-1 -> -0.11699489 | ... AE35: =AE18/AA18-1 -> -0.071713872
B36: Other/Eliminations | D36: =D19/C19-1 -> 0.4204562 | E36: =E19/D19-1 -> 0.23845906 | F36: =F19/E19-1 -> -0.19845936 | G36: =G19/F19-1 -> 0.75503018 | H36: =H19/G19-1 -> 0.074060367 | I36: =I19/H19-1 -> -0.049913902 | O36: =O19/K19-1 -> 1.2758941 | P36: =P19/L19-1 -> 0.30378027 | Q36: =Q19/M19-1 -> 0.078634705 | R36: =R19/N19-1 -> -0.13094037 | S36: =S19/O19-1 -> -0.44948392 | T36: =T19/P19-1 -> -0.029030948 | U36: =U19/Q19-1 -> -0.11225107 | V36: =V19/R19-1 -> -0.20465494 | ... AE36: =AE19/AA19-1 -> -0.2172094
B37: Total | D37: =D20/C20-1 -> 0.3375973 | E37: =E20/D20-1 -> 0.091247051 | F37: =F20/E20-1 -> -0.053801357 | G37: =G20/F20-1 -> 0.13213915 | H37: =H20/G20-1 -> 0.0017417381 | I37: =I20/H20-1 -> 0.000633995 | O37: =O20/K20-1 -> 0.22966365 | P37: =P20/L20-1 -> 0.1883177 | Q37: =Q20/M20-1 -> 0.09855948 | R37: =R20/N20-1 -> -0.06564979 | S37: =S20/O20-1 -> 0.045064111 | T37: =T20/P20-1 -> 0.028180372 | U37: =U20/Q20-1 -> 0.0037587342 | V37: =V20/R20-1 -> -0.25476924 | ... AE37: =AE20/AA20-1 -> 0.0022560283
B40: EBITDA by segment
B41: Chile | C41: 244767.95 | D41: 334616.9 | E41: 227005.81 | F41: 283409.47 | G41: 290079.5 | H41: 312773.52 | I41: =SUM(AB41:AE41) -> 325730.75 | K41: 103945.9 | L41: 57934.894 | M41: 77634.79 | N41: =D41-SUM(K41:M41) -> 95101.317 | O41: 93444.911 | P41: 23711.452 | Q41: 37946.77 | R41: =E41-SUM(O41:Q41) -> 71902.682 | S41: 99760.923 | T41: 44105.783 | U41: 52618.074 | V41: =F41-SUM(S41:U41) -> 86924.69 | W41: 96733.379 | X41: 26587 | Y41: 59879.873 | Z41: =G41-SUM(W41:Y41) -> 106879.25 | AA41: 94399.941 | AB41: 42305 | AC41: 62756.235 | AD41: =H41-SUM(AA41:AC41) -> 113312.35 | AE41: 107357.17
B42: Interntional Business | C42: 24201.159 | D42: 90853.77 | E42: 101832.73 | F42: 85563.786 | G42: 78445.523 | H42: 55306.066 | I42: =SUM(AB42:AE42) -> 48811.582 | K42: 16706.271 | L42: -2223.2097 | M42: 16932.532 | N42: =D42-SUM(K42:M42) -> 59438.177 | O42: 33195.75 | P42: 1072.1762 | Q42: 19810.136 | R42: =E42-SUM(O42:Q42) -> 47754.672 | S42: 35807.11 | T42: 1875.4248 | U42: 25785.434 | V42: =F42-SUM(S42:U42) -> 22095.817 | W42: 26097.706 | X42: -24373 | Y42: 3953.738 | Z42: =G42-SUM(W42:Y42) -> 72767.079 | AA42: 34983.112 | AB42: -26892 | AC42: 6845.212 | AD42: =H42-SUM(AA42:AC42) -> 40369.742 | AE42: 28488.628
B43: Wine | C43: 43104.576 | D43: 45690.839 | E43: 51374.741 | F43: 32184.35 | G43: 41829.076 | H43: 35599.733 | I43: =SUM(AB43:AE43) -> 32295.95 | K43: 10179.583 | L43: 10808.991 | M43: 13404.368 | N43: =D43-SUM(K43:M43) -> 11297.897 | O43: 11469.427 | P43: 11788.401 | Q43: 14733.421 | R43: =E43-SUM(O43:Q43) -> 13383.492 | S43: 3496.4511 | T43: 6542.8742 | U43: 11606.13 | V43: =F43-SUM(S43:U43) -> 10538.895 | W43: 6666.9653 | X43: 10419 | Y43: 12521.319 | Z43: =G43-SUM(W43:Y43) -> 12221.792 | AA43: 6591.924 | AB43: 11285 | AC43: 11024.322 | AD43: =H43-SUM(AA43:AC43) -> 6698.487 | AE43: 3288.141
B44: Other/Eliminations | C44: -15668.846 | D44: -26163.923 | E44: -22284.642 | F44: -21755.234 | G44: 5582.014 | H44: -27471.364 | I44: =SUM(AB44:AE44) -> -30540.857 | K44: -4284.3604 | L44: -4945.091 | M44: -6499.4163 | N44: =D44-SUM(K44:M44) -> -10435.055 | O44: -2984.3032 | P44: -4101.1463 | Q44: -4883.6709 | R44: =E44-SUM(O44:Q44) -> -10315.521 | S44: -3687.7775 | T44: -5398.2414 | U44: -3665.7825 | V44: =F44-SUM(S44:U44) -> -9003.433 | W44: -5334.7994 | X44: 26089 | Y44: -5924.232 | Z44: =G44-SUM(W44:Y44) -> -9247.9546 | AA44: -4420.929 | AB44: -6881 | AC44: -6990.309 | AD44: =H44-SUM(AA44:AC44) -> -9179.126 | AE44: -7490.422
B45: Total | C45: =SUM(C41:C44) -> 296404.84 | D45: =SUM(D41:D44) -> 444997.59 | E45: =SUM(E41:E44) -> 357928.65 | F45: =SUM(F41:F44) -> 379402.37 | G45: =SUM(G41:G44) -> 415936.11 | H45: =SUM(H41:H44) -> 376207.96 | I45: =SUM(AB45:AE45) -> 376297.43 | K45: =SUM(K41:K44) -> 126547.39 | L45: =SUM(L41:L44) -> 61575.584 | M45: =SUM(M41:M44) -> 101472.27 | N45: =SUM(N41:N44) -> 155402.34 | O45: =SUM(O41:O44) -> 135125.78 | P45: =SUM(P41:P44) -> 32470.883 | Q45: =SUM(Q41:Q44) -> 67606.655 | R45: =SUM(R41:R44) -> 122725.32 | ... AE45: =SUM(AE41:AE44) -> 131643.52
B46: Check | C46: =C45-Model!C51 -> -0.00021999999 | D46: =D45-Model!D51 -> -0.0010331731 | E46: =E45-Model!E51 -> -0.0016961747 | F46: =F45-Model!F51 -> -0.0015146816 | G46: =G45-Model!G51 -> 0 | H46: =H45-Model!H51 -> 0 | I46: =I45-Model!I51 -> -0.048 | K46: =K45-Model!K51 -> -0.000711 | L46: =L45-Model!L51 -> -0.0017437525 | M46: =M45-Model!M51 -> 0.001019279 | N46: =N45-Model!N51 -> 0.00040230041 | O46: =O45-Model!O51 -> -0.00039269918 | P46: =P45-Model!P51 -> 0.0010080301 | Q46: =Q45-Model!Q51 -> -0.00063764671 | R46: =R45-Model!R51 -> -0.0016738589 | ... AE46: =AE45-Model!AE51 -> 0
