Workbook
Name \A: #REF!
Name \B: #REF!
Name \C: #REF!
Name \L: #REF!
Name \M: #REF!
Name \P: #REF!
Name \Y: #REF!
Name _01_30_04: MonthlyOpStats
Name _1_30_01: MonthlyOpStats
Name _1_30_02: MonthlyOpStats
Name _1_31_01: MonthlyOpStats
Name _1_31_02: MonthlyOpStats
Name _12_31_05: MonthlyOpStats
Name _A: #REF!
Name _A___0: #REF!
Name _B: #REF!
Name _B___0: #REF!
Name _C: #REF!
Name _C___0: #REF!
Name _ent1: [1]Inputs!$J$17
Name _ent10: [1]Inputs!$J$476
Name _ent11: [1]Inputs!$J$527
Name _ent12: [1]Inputs!$J$578
Name _ent13: [1]Inputs!$J$629
Name _ent14: [1]Inputs!$J$680
Name _ent15: [1]Inputs!$J$731
Name _ent2: [1]Inputs!$J$68
Name _ent3: [1]Inputs!$J$119
Name _ent4: [1]Inputs!$J$170
Name _ent5: [1]Inputs!$J$221
Name _ent6: [1]Inputs!$J$272
Name _ent7: [1]Inputs!$J$323
Name _ent8: [1]Inputs!$J$374
Name _ent9: [1]Inputs!$J$425
Name _eps1: [1]Inputs!$P$42
Name _eps10: [1]Inputs!$P$501
Name _eps11: [1]Inputs!$P$552
Name _eps12: [1]Inputs!$P$603
Name _eps13: [1]Inputs!$P$654
Name _eps14: [1]Inputs!$P$705
Name _eps15: [1]Inputs!$P$756
Name _eps2: [1]Inputs!$P$93
Name _eps3: [1]Inputs!$P$144
Name _eps4: [1]Inputs!$P$195
Name _eps5: [1]Inputs!$P$246
Name _eps6: [1]Inputs!$P$297
Name _eps7: [1]Inputs!$P$348
Name _eps8: [1]Inputs!$P$399
Name _eps9: [1]Inputs!$P$450
Name _fye1: [1]Inputs!$E$12
Name _fye10: [1]Inputs!$E$471
Name _fye11: [1]Inputs!$E$522
Name _fye12: [1]Inputs!$E$573
Name _fye13: [1]Inputs!$E$624
Name _fye14: [1]Inputs!$E$675
Name _fye15: [1]Inputs!$E$726
Name _fye2: [1]Inputs!$E$63
Name _fye3: [1]Inputs!$E$114
Name _fye4: [1]Inputs!$E$165
Name _fye5: [1]Inputs!$E$216

Sheet Capital Structure
AR2: Exchange rate at end of period | AS2: 72.49 | AT2: 69.77 | AU2: 69.16 | AV2: 69.02 | AW2: 71.77 | AX2: 70.8675 | AY2: 75.3245 | AZ2: 75.5087 | BA2: 73.7637 | BB2: 73.01 | BC2: 73.2065 | BD2: 74.3716 | BE2: 74.2236 | BF2: 74.467 | BG2: 74.36 | BH2: 78.92 | BI2: 81.461 | BJ2: 82.717 | BK2: 82.08 | BL2: 82.1 | BM2: 83.04 | BN2: 83.238 | BO2: 83.35 | BP2: 83.355 | BQ2: 83.755 | BR2: 85.554 | BS2: 85.45 | BT2: 85.7 | BU2: 88.841 | BV2: ='Model '!BY208 -> 89.871 | BW2: ='Model '!BZ208 -> 93.485
AS3: Amount in USD
C4: 40603 | D4: 40969 | E4: 41334 | F4: 41699 | G4: 42064 | H4: 42430 | I4: 42795 | J4: 43070 | K4: 43190 | L4: 43281 | M4: 43373 | N4: 43465 | O4: 43555 | P4: 43646 | Q4: 43738 | R4: 43830 | S4: 43921 | T4: 44012 | U4: 44104 | V4: 44196 | W4: 44286 | X4: 44377 | Y4: 44469 | Z4: 44561 | AA4: 44651 | AB4: 44742 | AC4: 44834 | AD4: 44926 | AE4: 45016 | AF4: 45107 | AG4: 45199 | AH4: 45290 | AI4: 45382 | AJ4: 45473 | AK4: 45565 | AL4: 45656 | AM4: 45746 | AN4: 45838 | AO4: 45930 | AP4: 46021 | AQ4: 46112 | AS4: 43373 | AT4: 43464 | AU4: 43555 | AV4: =P4 -> 43646 | AW4: =Q4 -> 43738 | AX4: =R4 -> 43830 | AY4: =S4 -> 43921 | AZ4: =T4 -> 44012 | BA4: =U4 -> 44104 | BB4: =V4 -> 44196 | BC4: =W4 -> 44286 | ... BW4: =AQ4 -> 46112
B5: Amounts in millions of INR unless stated | C5: FY11 | D5: FY12 | E5: FY13 | F5: FY14 | G5: FY15 | H5: FY16 | I5: FY17 | J5: 3Q18 | K5: 4Q18 | L5: 1Q19 | M5: 2Q19 | N5: 3Q19 | O5: 4Q19 | P5: 1Q20 | Q5: 2Q20 | R5: 3Q20 | S5: 4Q20 | T5: 1Q21 | U5: 2Q21 | V5: 3Q21 | W5: 4Q21 | X5: 1Q22 | Y5: 2Q22 | Z5: 3Q22 | AA5: 4Q22 | AB5: 1Q23 | AC5: 2Q23 | AD5: 3Q23 | AE5: 4Q23 | AF5: 1Q24 | AG5: 2Q24 | AH5: 3Q24 | AI5: 4Q24 | AJ5: 1Q25 | AK5: 2Q25 | AL5: 3Q25 | AM5: 4Q25 | AN5: 1Q26 | AO5: 2Q26 | AP5: 3Q26 | AQ5: 4Q26 | AS5: 2Q19 | AT5: 3Q19 | AU5: 4Q19 | AV5: =P5 -> 1Q20 | AW5: =Q5 -> 2Q20 | AX5: =R5 -> 3Q20 | AY5: =S5 -> 4Q20 | AZ5: =T5 -> 1Q21 | BA5: =U5 -> 2Q21 | BB5: =V5 -> 3Q21 | BC5: =W5 -> 4Q21 | ... BW5: =AQ5 -> 4Q26
B6: Secured debt | C6: 0 | D6: 0 | E6: 0 | F6: 0 | G6: 0 | H6: 43977 | I6: 12038 | J6: 12038 | K6: 21925 | L6: 21925 | M6: 21925 | N6: 21925 | O6: 3095 | P6: 3095 | Q6: 3095 | R6: 3095 | S6: 3095 | T6: 3095 | U6: 3095 | V6: 3095 | W6: 3095 | X6: 3095 | Y6: 3095 | Z6: 3095 | AA6: 3095 | AB6: 3095 | AC6: 3095 | AD6: 3095 | AE6: 3095 | AF6: 3095 | AG6: 3095 | AH6: 3095 | AI6: 3095 | AJ6: 3095 | AK6: 3095 | AL6: 3095 | AM6: 3095 | AN6: 3095 | AO6: 3095 | AP6: 3095 | AQ6: 3095 | AS6: =M6/$AS$2 -> 302.45551 | AT6: =N6/$AT$2 -> 314.24681 | AU6: =O6/AU$2 -> 44.751301 | AV6: =P6/AV$2 -> 44.842075 | AW6: =Q6/AW$2 -> 43.123868 | AX6: =R6/AX$2 -> 43.673052 | AY6: =S6/AY$2 -> 41.088889 | AZ6: =T6/AZ$2 -> 40.988654 | BA6: =U6/BA$2 -> 41.958307 | BB6: =V6/BB$2 -> 42.391453 | ... BW6: =AQ6/BW$2 -> 33.106916
B7: Lease Obligation | C7: 0 | D7: 0 | E7: 0 | F7: 0 | G7: 0 | H7: 57871 | I7: 56547 | J7: 48389.606 | K7: 48831 | L7: 50118 | M7: 52304.93 | N7: 49293.865 | O7: 47553.013 | P7: 281967.47 | Q7: 299807.14 | R7: 301529.25 | S7: 306078.13 | T7: 306132.55 | U7: 304383 | V7: 324529 | W7: 329953 | X7: 331104 | Y7: 348981 | Z7: 352346.29 | AA7: 367634 | AB7: 478105.47 | AC7: 523642.47 | AD7: 549018.04 | AE7: 604755 | AF7: 589108 | AG7: 595564.62 | AH7: 597143 | AI7: 636758 | AJ7: 674544 | AK7: 792003 | AL7: 629333 | AM7: 653298 | AN7: 660901 | AO7: 680618 | AP7: ='Model '!$BY$118 -> 701294 | AQ7: ='Model '!$BZ$118 -> 737403 | AS7: =M7/$AS$2 -> 721.54683 | AT7: =N7/$AT$2 -> 706.51949 | AU7: =O7/AU$2 -> 687.57971 | AV7: =P7/AV$2 -> 4085.3009 | AW7: =Q7/AW$2 -> 4177.3323 | AX7: =R7/AX$2 -> 4254.8312 | AY7: =S7/AY$2 -> 4063.4604 | AZ7: =T7/AZ$2 -> 4054.2685 | BA7: =U7/BA$2 -> 4126.4606 | BB7: =V7/BB$2 -> 4444.9938 | ... BW7: =AQ7/BW$2 -> 7887.9285
B8: Total Secured debt | C8: =SUM(C6:C7) -> 0 | D8: =SUM(D6:D7) -> 0 | E8: =SUM(E6:E7) -> 0 | F8: =SUM(F6:F7) -> 0 | G8: =SUM(G6:G7) -> 0 | H8: =SUM(H6:H7) -> 101848 | I8: =SUM(I6:I7) -> 68585 | J8: =SUM(J6:J7) -> 60427.606 | ... AQ8: =SUM(AQ6:AQ7) -> 740498 | AS8: =SUM(AS6:AS7) -> 1024.0023 | AT8: =SUM(AT6:AT7) -> 1020.7663 | AU8: =SUM(AU6:AU7) -> 732.33101 | AV8: =SUM(AV6:AV7) -> 4130.143 | AW8: =SUM(AW6:AW7) -> 4220.4562 | AX8: =SUM(AX6:AX7) -> 4298.5043 | AY8: =SUM(AY6:AY7) -> 4104.5493 | AZ8: =SUM(AZ6:AZ7) -> 4095.2572 | ... BW8: =SUM(BW6:BW7) -> 7921.0355
B10: Unsecured debt
B11: 1.5% Senior USD bond due 2025 | R11: 70867.5 | S11: 75324.5 | T11: 75508.7 | U11: 73763.7 | V11: 73010 | W11: 73206.5 | X11: 74371.6 | Y11: 74223.6 | Z11: 74467 | AA11: 74360 | AB11: 78920 | AC11: 81461 | AD11: 82717 | AE11: 82080 | AF11: 75917.87 | AG11: 65354.141 | AH11: 48087.425 | AI11: 48152.128 | AJ11: 48155.017 | AK11: 48386.101 | AL11: 49425.401 | AM11: 0 | AN11: 0 | AO11: 0 | AP11: 0 | AQ11: 0 | AX11: =R11/AX$2 -> 1000 | AY11: =S11/AY$2 -> 1000 | AZ11: =T11/AZ$2 -> 1000 | BA11: =U11/BA$2 -> 1000 | BB11: =V11/BB$2 -> 1000 | BC11: =W11/BC$2 -> 1000 | BD11: =X11/BD$2 -> 1000 | BE11: =Y11/BE$2 -> 1000 | ... BW11: =AQ11/BW$2 -> 0
B12: 4.375% Senior USD Bonds due 2025 | J12: 63880 | K12: 65180 | L12: 68470 | M12: 72490 | N12: 69770 | O12: 69160 | P12: 69020 | Q12: 71770 | R12: 70867.5 | S12: 75324.5 | T12: 75508.7 | U12: 73763.7 | V12: 73010 | W12: 73206.5 | X12: 74371.6 | Y12: 74223.6 | Z12: 74467 | AA12: 74360 | AB12: 78920 | AC12: 81461 | AD12: 82717 | AE12: 82080 | AF12: 82100 | AG12: 83040 | AH12: 83238 | AI12: 83350 | AJ12: 83355 | AK12: 83755 | AL12: 85554 | AM12: 85450 | AN12: 0 | AO12: 0 | AP12: 0 | AQ12: 0 | AS12: =M12/$AS$2 -> 1000 | AT12: =N12/$AT$2 -> 1000 | AU12: =O12/AU$2 -> 1000 | AV12: =P12/AV$2 -> 1000 | AW12: =Q12/AW$2 -> 1000 | AX12: =R12/AX$2 -> 1000 | AY12: =S12/AY$2 -> 1000 | AZ12: =T12/AZ$2 -> 1000 | BA12: =U12/BA$2 -> 1000 | BB12: =V12/BB$2 -> 1000 | ... BW12: =AQ12/BW$2 -> 0
B13: 5.125% Senior USD Bonds due 2023 | J13: 95820 | K13: 97770 | L13: 102705 | M13: 108735 | N13: 104655 | O13: 103740 | P13: 103530 | Q13: 107655 | R13: 106301.25 | S13: 112986.75 | T13: 38125.853 | U13: 37244.767 | V13: 36864.209 | W13: 36963.426 | X13: 37551.708 | Y13: 37476.98 | Z13: 37599.878 | AA13: 37545.851 | AB13: 39848.286 | AC13: 41131.288 | AD13: 41765.468 | AE13: 41443.834 | AF13: 0 | AG13: 0 | AH13: 0 | AI13: 0 | AJ13: 0 | AK13: 0 | AL13: 0 | AM13: 0 | AN13: 0 | AO13: 0 | AP13: 0 | AQ13: 0 | AS13: =M13/$AS$2 -> 1500 | AT13: =N13/$AT$2 -> 1500 | AU13: =O13/AU$2 -> 1500 | AV13: =P13/AV$2 -> 1500 | AW13: =Q13/AW$2 -> 1500 | AX13: =R13/AX$2 -> 1500 | AY13: =S13/AY$2 -> 1500 | AZ13: =T13/AZ$2 -> 504.92 | BA13: =U13/BA$2 -> 504.92 | BB13: =V13/BB$2 -> 504.92 | ... BW13: =AQ13/BW$2 -> 0
B14: 5.350% Senior USD Bonds due 2024 | J14: 63880 | K14: 65180 | L14: 68470 | M14: 72490 | N14: 69770 | O14: 69160 | P14: 69020 | Q14: 71770 | R14: 70867.5 | S14: 75324.5 | T14: 75508.7 | U14: 73763.7 | V14: 73010 | W14: 73206.5 | X14: 74371.6 | Y14: 74223.6 | Z14: 74467 | AA14: 74360 | AB14: 78920 | AC14: 81461 | AD14: 82717 | AE14: 82080 | AF14: 45155 | AG14: 45672 | AH14: 45780.9 | AI14: 45842.5 | AJ14: 45845.25 | AK14: 46065.25 | AL14: 47054.7 | AM14: 0 | AN14: 0 | AO14: 0 | AP14: 0 | AQ14: 0 | AS14: =M14/$AS$2 -> 1000 | AT14: =N14/$AT$2 -> 1000 | AU14: =O14/AU$2 -> 1000 | AV14: =P14/AV$2 -> 1000 | AW14: =Q14/AW$2 -> 1000 | AX14: =R14/AX$2 -> 1000 | AY14: =S14/AY$2 -> 1000 | AZ14: =T14/AZ$2 -> 1000 | BA14: =U14/BA$2 -> 1000 | BB14: =V14/BB$2 -> 1000 | ... BW14: =AQ14/BW$2 -> 0
B15: 3.375% Senior EUR Bonds due 2021 | J15: 47910 | K15: 48885 | L15: 51352.5 | M15: 74664.7 | N15: 71863.1 | O15: 71234.8 | P15: 71090.6 | Q15: 73923.1 | R15: 72993.525 | S15: 77584.235 | T15: 66651.529 | U15: 65368.653 | V15: 64700.732 | W15: 75402.695 | X15: 65647.811 | Y15: 65776.212 | Z15: 65991.911 | AA15: 65897.088 | AB15: 69662.684 | AC15: 71905.625 | AD15: 73302.978 | AE15: 72738.475 | AF15: 0 | AG15: 0 | AH15: 0 | AI15: 0 | AJ15: 0 | AK15: 0 | AL15: 0 | AM15: 0 | AN15: 0 | AO15: 0 | AP15: 0 | AQ15: 0 | AS15: =M15/$AS$2 -> 1030 | AT15: =N15/$AT$2 -> 1030 | AU15: =O15/AU$2 -> 1030 | AV15: =P15/AV$2 -> 1030 | AW15: =Q15/AW$2 -> 1030 | AX15: =R15/AX$2 -> 1030 | AY15: =S15/AY$2 -> 1030 | AZ15: =T15/AZ$2 -> 882.7 | BA15: =U15/BA$2 -> 886.19 | BB15: =V15/BB$2 -> 886.19 | ... BW15: =AQ15/BW$2 -> 0
B16: 3.25% Senior EUR Bonds due 2031 | AF16: 61575 | AG16: 62280 | AH16: 62428.5 | AI16: 62512.5 | AJ16: 62516.25 | AK16: 62816.25 | AL16: 64165.5 | AM16: 64087.5 | AN16: 64275 | AO16: 66630.75 | AP16: =750*$BV$2 -> 67403.25 | AQ16: =750*$BW$2 -> 70113.75 | BL16: =AF16/BL$2 -> 750 | BM16: =AG16/BM$2 -> 750 | BN16: =AH16/BN$2 -> 750 | BO16: =AI16/BO$2 -> 750 | BP16: =AJ16/BP$2 -> 750 | BQ16: =AK16/BQ$2 -> 750 | BR16: =AL16/BR$2 -> 750 | BS16: =AM16/BS$2 -> 750 | ... BW16: =AQ16/BW$2 -> 750
B17: 4.00% Senior EUR Bonds due 2018 | J17: 63880 | K17: 65180 | L17: 68470 | M17: 100036.2 | AI17: 0 | AJ17: 0 | AK17: 0 | AL17: 0 | AM17: 0 | AN17: 0 | AO17: 0 | AP17: 0 | AQ17: 0 | AS17: =M17/$AS$2 -> 1380 | AT17: =N17/$AT$2 -> 0 | AU17: =O17/AU$2 -> 0 | AV17: =P17/AV$2 -> 0 | AW17: =Q17/AW$2 -> 0 | AX17: =R17/AX$2 -> 0 | AY17: =S17/AY$2 -> 0 | AZ17: =T17/AZ$2 -> 0 | BA17: =U17/BA$2 -> 0 | BB17: =V17/BB$2 -> 0 | ... BW17: =AQ17/BW$2 -> 0
B18: 3.00% Senior CHF Bonds due 2020 | J18: 22358 | K18: 22813 | L18: 23964.5 | M18: 28695.166 | N18: 27618.454 | O18: 27376.986 | P18: 27321.567 | Q18: 28410.155 | R18: 28052.9 | S18: 29817.203 | T18: 0 | U18: 0 | V18: 0 | W18: 0 | X18: 0 | Y18: 0 | Z18: 0 | AA18: 0 | AB18: 0 | AC18: 0 | AD18: 0 | AE18: 0 | AF18: 0 | AG18: 0 | AH18: 0 | AI18: 0 | AJ18: 0 | AK18: 0 | AL18: 0 | AM18: 0 | AN18: 0 | AO18: 0 | AP18: 0 | AQ18: 0 | AS18: =M18/$AS$2 -> 395.85 | AT18: =N18/$AT$2 -> 395.85 | AU18: =O18/AU$2 -> 395.85 | AV18: =P18/AV$2 -> 395.85 | AW18: =Q18/AW$2 -> 395.85 | AX18: =R18/AX$2 -> 395.85 | AY18: =S18/AY$2 -> 395.85 | AZ18: =T18/AZ$2 -> 0 | BA18: =U18/BA$2 -> 0 | BB18: =V18/BB$2 -> 0 | ... BW18: =AQ18/BW$2 -> 0
B19: 8.250% subordinated INR bonds due 2020 | K19: 15000 | L19: 15000 | M19: 15000 | N19: 15000 | O19: 15000 | P19: 15000 | Q19: 15000 | R19: 15000 | S19: 15000 | T19: 14976.74 | U19: 0 | V19: 0 | W19: 0 | X19: 0 | Y19: 0 | Z19: 0 | AA19: 0 | AB19: 0 | AC19: 0 | AD19: 0 | AE19: 0 | AF19: 0 | AG19: 0 | AH19: 0 | AI19: 0 | AJ19: 0 | AK19: 0 | AL19: 0 | AM19: 0 | AN19: 0 | AO19: 0 | AP19: 0 | AQ19: 0 | AS19: =M19/$AS$2 -> 206.92509 | AT19: =N19/$AT$2 -> 214.99212 | AU19: =O19/AU$2 -> 216.88837 | AV19: =P19/AV$2 -> 217.32831 | AW19: =Q19/AW$2 -> 209.00098 | AX19: =R19/AX$2 -> 211.66261 | AY19: =S19/AY$2 -> 199.13839 | AZ19: =T19/AZ$2 -> 198.34456 | BA19: =U19/BA$2 -> 0 | BB19: =V19/BB$2 -> 0 | ... BW19: =AQ19/BW$2 -> 0
B20: 8.350% subordinated INR bonds due 2021 | K20: 15000 | L20: 15000 | M20: 15000 | N20: 15000 | O20: 15000 | P20: 15000 | Q20: 15000 | R20: 15000 | S20: 15000 | T20: 15000 | U20: 15000 | V20: 15000 | W20: 15000 | X20: 15000 | Y20: 15000 | Z20: 15000 | AA20: 15000 | AB20: 15000 | AC20: 15000 | AD20: 15000 | AE20: 15000 | AF20: 0 | AG20: 0 | AH20: 0 | AI20: 0 | AJ20: 0 | AK20: 0 | AL20: 0 | AM20: 0 | AN20: 0 | AO20: 0 | AP20: 0 | AQ20: 0 | AS20: =M20/$AS$2 -> 206.92509 | AT20: =N20/$AT$2 -> 214.99212 | AU20: =O20/AU$2 -> 216.88837 | AV20: =P20/AV$2 -> 217.32831 | AW20: =Q20/AW$2 -> 209.00098 | AX20: =R20/AX$2 -> 211.66261 | AY20: =S20/AY$2 -> 199.13839 | AZ20: =T20/AZ$2 -> 198.65261 | BA20: =U20/BA$2 -> 203.35206 | BB20: =V20/BB$2 -> 205.45131 | ... BW20: =AQ20/BW$2 -> 0
B21: 5.65% Subordinated USD Bond - perpetual | Q21: 53827.5 | R21: 53150.625 | S21: 56493.375 | T21: 75508.7 | U21: 73763.7 | V21: 73010 | W21: 54904.875 | X21: 74371.6 | Y21: 74223.6 | Z21: 74467 | AA21: 74360 | AB21: 78920 | AC21: 81461 | AD21: 82717 | AE21: 82080 | AF21: 82100 | AG21: 83040 | AH21: 83238 | AI21: 83350 | AJ21: 83355 | AK21: 83755 | AL21: 85554 | AM21: 0 | AN21: 0 | AO21: 0 | AP21: 0 | AQ21: 0 | AW21: 1 | AX21: =R21/AX$2 -> 750 | AY21: =S21/AY$2 -> 750 | AZ21: =T21/AZ$2 -> 1000 | BA21: =U21/BA$2 -> 1000 | BB21: =V21/BB$2 -> 1000 | BC21: =W21/BC$2 -> 750 | BD21: =X21/BD$2 -> 1000 | BE21: =Y21/BE$2 -> 1000 | ... BW21: =AQ21/BW$2 -> 0
B22: 3.975% Subordinated USD Bond - perpetual | AF22: 41050 | AG22: 41520 | AH22: 41619 | AI22: 41675 | AJ22: 41677.5 | AK22: 41877.5 | AL22: 42777 | AM22: 42725 | AN22: 42850 | AO22: 44420.5 | AP22: =500*$BV$2 -> 44935.5 | AQ22: =500*$BW$2 -> 46742.5 | BL22: =AF22/BL$2 -> 500 | BM22: =AG22/BM$2 -> 500 | BN22: =AH22/BN$2 -> 500 | BO22: =AI22/BO$2 -> 500 | BP22: =AJ22/BP$2 -> 500 | BQ22: =AK22/BQ$2 -> 500 | BR22: =AL22/BR$2 -> 500 | BS22: =AM22/BS$2 -> 500 | ... BW22: =AQ22/BW$2 -> 500
B23: DoT Obligations / Spectrum Debt | C23: 0 | D23: 0 | E23: 0 | F23: 0 | G23: 143143.33 | H23: 350025.16 | I23: 439229.05 | J23: =917139-446768 -> 470371 | K23: 0 | L23: 0 | M23: 0 | N23: 0 | O23: 0 | AI23: 0 | AJ23: 0 | AK23: 0 | AL23: 0 | AM23: 0 | AN23: 0 | AO23: 0 | AP23: 0 | AQ23: 0 | AS23: =M23/$AS$2 -> 0 | AT23: =N23/$AT$2 -> 0 | AU23: =O23/AU$2 -> 0 | AV23: =P23/AV$2 -> 0 | AW23: =Q23/AW$2 -> 0 | AX23: =R23/AX$2 -> 0 | AY23: =S23/AY$2 -> 0 | AZ23: =T23/AZ$2 -> 0 | BA23: =U23/BA$2 -> 0 | BB23: =V23/BB$2 -> 0 | ... BW23: =AQ23/BW$2 -> 0
B24: Other unsecured debt | C24: 616707 | D24: 690232 | E24: 667363 | F24: 759984 | G24: 663695.67 | H24: 552652.83 | I24: 566466.95 | J24: 173879 | K24: 675912 | L24: 717464 | M24: 723122.93 | N24: 770881.45 | O24: 835802.28 | P24: 642734.66 | Q24: 625533.17 | R24: 653879.14 | S24: 637172.12 | T24: 857839.48 | U24: 947348.17 | V24: 915867.06 | W24: 890851.5 | X24: 1085266.3 | Y24: 1109022 | Z24: 985437.31 | AA24: 983029.06 | AB24: 1015645.7 | AC24: 1279857.7 | AD24: 1290213.7 | AE24: 1276424.7 | AF24: 1269218.1 | AG24: 1194012 | AH24: 1220414.2 | AI24: 1144873.9 | AJ24: 1047161.8 | AK24: 1094797.8 | AL24: 1040385.4 | AM24: 1288775.5 | AN24: 1263525 | AO24: 1286387.8 | AP24: ='Model '!BY$122-AP23-AP18-AP17-AP15-AP14-AP13-AP12-AP19-AP20-AP21-AP11-AP16-AP22 -> 1163314.2 | AQ24: ='Model '!BZ$122-AQ23-AQ18-AQ17-AQ15-AQ14-AQ13-AQ12-AQ19-AQ20-AQ21-AQ11-AQ16-AQ22 -> 1097751.8 | AS24: =M24/$AS$2 -> 9975.4854 | AT24: =N24/$AT$2 -> 11048.896 | AU24: =O24/AU$2 -> 12085.053 | AV24: =P24/AV$2 -> 9312.2958 | AW24: =Q24/AW$2 -> 8715.8029 | AX24: =R24/AX$2 -> 9226.7844 | AY24: =S24/AY$2 -> 8459.0289 | AZ24: =T24/AZ$2 -> 11360.803 | BA24: =U24/BA$2 -> 12843.013 | BB24: =V24/BB$2 -> 12544.406 | ... BW24: =AQ24/BW$2 -> 11742.544
B25: Total debt | C25: =C24+C8+C23+C12+C13+C14+C15+C17+C18+C19+C20 -> 616707 | D25: =D24+D8+D23+D12+D13+D14+D15+D17+D18+D19+D20 -> 690232 | E25: =E24+E8+E23+E12+E13+E14+E15+E17+E18+E19+E20 -> 667363 | F25: =F24+F8+F23+F12+F13+F14+F15+F17+F18+F19+F20 -> 759984 | G25: =G24+G8+G23+G12+G13+G14+G15+G17+G18+G19+G20 -> 806839 | H25: =H24+H8+H23+H12+H13+H14+H15+H17+H18+H19+H20 -> 1004526 | I25: =I24+I8+I23+I12+I13+I14+I15+I17+I18+I19+I20 -> 1074281 | J25: =J24+J8+J23+J12+J13+J14+J15+J17+J18+J19+J20 -> 1062405.6 | ... P25: =P24+P8+P23+P12+P13+P14+P15+P17+P18+P19+P20 -> 1297779.3 | Q25: =Q24+Q8+Q23+Q12+Q13+Q14+Q15+Q17+Q18+Q19+Q20+Q21 -> 1365791.1 | R25: =R24+R8+R23+R12+R13+R14+R15+R17+R18+R19+R20+R21+R11 -> 1461604.2 | S25: =S24+S8+S23+S12+S13+S14+S15+S17+S18+S19+S20+S21+S11 -> 1479200.3 | T25: =T24+T8+T23+T12+T13+T14+T15+T17+T18+T19+T20 -> 1452838.5 | U25: =U24+U8+U23+U12+U13+U14+U15+U17+U18+U19+U20+U21 -> 1593730.7 | V25: =V24+V8+V23+V12+V13+V14+V15+V17+V18+V19+V20+V21 -> 1579086 | W25: =W24+W8+W23+W12+W13+W14+W15+W17+W18+W19+W20+W21+W11 -> 1625790 | X25: =X24+X8+X23+X12+X13+X14+X15+X17+X18+X19+X20 -> 1686408 | Y25: =Y24+Y8+Y23+Y12+Y13+Y14+Y15+Y17+Y18+Y19+Y20+Y21 -> 1802022 | Z25: =Z24+Z8+Z23+Z12+Z13+Z14+Z15+Z17+Z18+Z19+Z20+Z21 -> 1682871.4 | AA25: =AA24+AA8+AA23+AA12+AA13+AA14+AA15+AA17+AA18+AA19+AA20+AA21 -> 1695281 | AB25: =AB24+AB8+AB23+AB12+AB13+AB14+AB15+AB17+AB18+AB19+AB20 -> 1779197.2 | AC25: =AC24+AC8+AC23+AC12+AC13+AC14+AC15+AC17+AC18+AC19+AC20+AC21 -> 2179015 | AD25: =AD24+AD8+AD23+AD12+AD13+AD14+AD15+AD17+AD18+AD19+AD20+AD21 -> 2220546.2 | AE25: =AE24+AE8+AE23+AE12+AE13+AE14+AE15+AE17+AE18+AE19+AE20+AE21 -> 2259697 | AF25: =AF24+AF8+AF23+AF12+AF13+AF14+AF15+AF17+AF18+AF19+AF20+AF21+AF16+AF22+AF11 -> 2249319 | AG25: =AG24+AG8+AG23+AG12+AG13+AG14+AG15+AG17+AG18+AG19+AG20+AG21+AG16+AG22+AG11 -> 2173577.8 | AH25: =AH24+AH8+AH23+AH12+AH13+AH14+AH15+AH17+AH18+AH19+AH20+AH21+AH16+AH22+AH11 -> 2185044 | AI25: =AI24+AI8+AI23+AI12+AI13+AI14+AI15+AI17+AI18+AI19+AI20+AI21+AI16+AI22+AI11 -> 2149609 | AJ25: =AJ24+AJ8+AJ23+AJ12+AJ13+AJ14+AJ15+AJ17+AJ18+AJ19+AJ20+AJ21+AJ16+AJ22+AJ11 -> 2089704.8 | AK25: =AK24+AK8+AK23+AK12+AK13+AK14+AK15+AK17+AK18+AK19+AK20+AK21+AK16+AK22+AK11 -> 2256550.9 | AL25: =AL24+AL8+AL23+AL12+AL13+AL14+AL15+AL17+AL18+AL19+AL20+AL21+AL16+AL22+AL11 -> 2047344 | AM25: =AM24+AM8+AM23+AM12+AM13+AM14+AM15+AM17+AM18+AM19+AM20+AM21+AM16+AM22+AM11 -> 2137431 | ... AQ25: =AQ24+AQ8+AQ23+AQ12+AQ13+AQ14+AQ15+AQ17+AQ18+AQ19+AQ20+AQ21+AQ16+AQ22+AQ11 -> 1955106 | AS25: =AS24+AS8+AS23+AS12+AS13+AS14+AS15+AS17+AS18+AS19+AS20 -> 17719.188 | AT25: =AT24+AT8+AT23+AT12+AT13+AT14+AT15+AT17+AT18+AT19+AT20 -> 17425.496 | AU25: =AU24+AU8+AU23+AU12+AU13+AU14+AU15+AU17+AU18+AU19+AU20 -> 18177.011 | AV25: =AV24+AV8+AV23+AV12+AV13+AV14+AV15+AV17+AV18+AV19+AV20 -> 18802.945 | AW25: =AW24+AW8+AW23+AW12+AW13+AW14+AW15+AW17+AW18+AW19+AW20+AW21+AW11 -> 18281.111 | AX25: =AX24+AX8+AX23+AX12+AX13+AX14+AX15+AX17+AX18+AX19+AX20+AX21+AX11 -> 20624.464 | AY25: =AY24+AY8+AY23+AY12+AY13+AY14+AY15+AY17+AY18+AY19+AY20+AY21+AY11 -> 19637.705 | AZ25: =AZ24+AZ8+AZ23+AZ12+AZ13+AZ14+AZ15+AZ17+AZ18+AZ19+AZ20+AZ21+AZ11 -> 21240.678 | BA25: =BA24+BA8+BA23+BA12+BA13+BA14+BA15+BA17+BA18+BA19+BA20+BA21+BA11 -> 22605.894 | BB25: =BB24+BB8+BB23+BB12+BB13+BB14+BB15+BB17+BB18+BB19+BB20+BB21+BB11 -> 22628.352 | BC25: =BC24+BC8+BC23+BC12+BC13+BC14+BC15+BC17+BC18+BC19+BC20+BC21+BC11 -> 22208.274 | BD25: =BD24+BD8+BD23+BD12+BD13+BD14+BD15+BD17+BD18+BD19+BD20+BD21+BD11 -> 24675.43 | ... BK25: =BK24+BK8+BK23+BK12+BK13+BK14+BK15+BK17+BK18+BK19+BK20+BK21+BK11 -> 28530.422 | BL25: =BL24+BL8+BL23+BL12+BL13+BL14+BL15+BL17+BL18+BL19+BL20+BL21+BL11+BL16+BL22 -> 27397.308 | BM25: =BM24+BM8+BM23+BM12+BM13+BM14+BM15+BM17+BM18+BM19+BM20+BM21+BM11+BM16+BM22 -> 26175.07 | BN25: =BN24+BN8+BN23+BN12+BN13+BN14+BN15+BN17+BN18+BN19+BN20+BN21+BN11+BN16+BN22 -> 26250.559 | BO25: =BO24+BO8+BO23+BO12+BO13+BO14+BO15+BO17+BO18+BO19+BO20+BO21+BO11+BO16+BO22 -> 25790.15 | BP25: =BP24+BP8+BP23+BP12+BP13+BP14+BP15+BP17+BP18+BP19+BP20+BP21+BP11+BP16+BP22 -> 25069.94 | BQ25: =BQ24+BQ8+BQ23+BQ12+BQ13+BQ14+BQ15+BQ17+BQ18+BQ19+BQ20+BQ21+BQ11+BQ16+BQ22 -> 26942.283 | BR25: =BR24+BR8+BR23+BR12+BR13+BR14+BR15+BR17+BR18+BR19+BR20+BR21+BR11+BR16+BR22 -> 23930.43 | BS25: =BS24+BS8+BS23+BS12+BS13+BS14+BS15+BS17+BS18+BS19+BS20+BS21+BS11+BS16+BS22 -> 25013.821 | ... BW25: =BW24+BW8+BW23+BW12+BW13+BW14+BW15+BW17+BW18+BW19+BW20+BW21+BW11+BW16+BW22 -> 20913.58
B26: Cash & Equivalents | C26: 17195 | D26: 39838 | E26: 83796 | F26: 154568 | G26: 138422 | H26: 111547 | I26: 103733 | J26: 96877 | K26: 120593 | L26: 123793 | M26: 100117 | N26: 102809 | O26: 127222.85 | P26: 131321.27 | Q26: 184726.07 | R26: 312410.7 | S26: 290610 | T26: 287434 | U26: 215313.87 | V26: 104704 | W26: 140713 | X26: 90187 | Y26: 139629 | Z26: 91451.101 | AA26: 92208 | AB26: 106002.17 | AC26: 82596.571 | AD26: 123235.19 | AE26: 128434 | AF26: 172029 | AG26: 103420.17 | AH26: 164342 | AI26: 103147 | AJ26: 63902.835 | AK26: 54165.906 | AL26: 81257 | AM26: 99047 | AN26: 118852 | AO26: 134021 | AP26: ='Model '!BY$128 -> 153836 | AQ26: ='Model '!BZ$128 -> 307218 | AS26: =M26/$AS$2 -> 1381.1146 | AT26: =N26/$AT$2 -> 1473.5416 | AU26: =O26/AU$2 -> 1839.5438 | AV26: =P26/AV$2 -> 1902.6553 | AW26: =Q26/AW$2 -> 2573.862 | AX26: =R26/AX$2 -> 4408.3776 | AY26: =S26/AY$2 -> 3858.1073 | AZ26: =T26/AZ$2 -> 3806.6342 | BA26: =U26/BA$2 -> 2918.9679 | BB26: =V26/BB$2 -> 1434.1049 | ... BW26: =AQ26/BW$2 -> 3286.2812
B27: Net debt | C27: =C25-C26 -> 599512 | D27: =D25-D26 -> 650394 | E27: =E25-E26 -> 583567 | F27: =F25-F26 -> 605416 | G27: =G25-G26 -> 668417 | H27: =H25-H26 -> 892979 | I27: =I25-I26 -> 970548 | J27: =J25-J26 -> 965528.61 | ... AQ27: =AQ25-AQ26 -> 1647888 | AS27: =AS25-AS26 -> 16338.073 | AT27: =AT25-AT26 -> 15951.954 | AU27: =AU25-AU26 -> 16337.467 | AV27: =AV25-AV26 -> 16900.29 | AW27: =AW25-AW26 -> 15707.249 | AX27: =AX25-AX26 -> 16216.086 | AY27: =AY25-AY26 -> 15779.598 | AZ27: =AZ25-AZ26 -> 17434.043 | ... BW27: =BW25-BW26 -> 17627.298
B28: Shareholders Equity | C28: 516231 | D28: 533808 | E28: 544102.68 | F28: 639662 | G28: 668088.74 | H28: 722674 | I28: 743313 | J28: 799768.57 | K28: 783483 | L28: 784887 | M28: 763996 | N28: 832059 | O28: 849480 | P28: 1040449 | Q28: 870149 | R28: 911205 | S28: 1021295 | T28: 858446 | U28: 842970 | V28: 778411 | W28: 812266 | X28: 820943 | Y28: 835516 | Z28: 887636 | AA28: 919350 | AB28: 946108 | AC28: 1005595 | AD28: 1021997.9 | AE28: 1064443 | AF28: 1030533 | AG28: 1034092 | AH28: 1035469 | AI28: 1055639 | AJ28: 1120335 | AK28: 1103030 | AL28: 1514323 | AM28: 1534677 | AN28: 1607482 | AO28: 1603540 | AP28: ='Model '!BY$133 -> 1690131 | AQ28: ='Model '!BZ$133 -> 1959634 | AS28: =M28/$AS$2 -> 10539.33 | AT28: =N28/$AT$2 -> 11925.742 | AU28: =O28/AU$2 -> 12282.822 | AV28: =P28/AV$2 -> 15074.602 | AW28: =Q28/AW$2 -> 12124.133 | AX28: =R28/AX$2 -> 12857.869 | AY28: =S28/AY$2 -> 13558.603 | AZ28: =T28/AZ$2 -> 11368.836 | BA28: =U28/BA$2 -> 11427.979 | BB28: =V28/BB$2 -> 10661.704 | ... BW28: =AQ28/BW$2 -> 20962.015
B29: Total capitalisation | C29: =C27+C28 -> 1115743 | D29: =D27+D28 -> 1184202 | E29: =E27+E28 -> 1127669.7 | F29: =F27+F28 -> 1245078 | G29: =G27+G28 -> 1336505.7 | H29: =H27+H28 -> 1615653 | I29: =I27+I28 -> 1713861 | J29: =J27+J28 -> 1765297.2 | ... AQ29: =AQ27+AQ28 -> 3607522 | AS29: =AS27+AS28 -> 26877.403 | AT29: =AT27+AT28 -> 27877.696 | AU29: =AU27+AU28 -> 28620.29 | AV29: =AV27+AV28 -> 31974.892 | AW29: =AW27+AW28 -> 27831.382 | AX29: =AX27+AX28 -> 29073.955 | AY29: =AY27+AY28 -> 29338.201 | AZ29: =AZ27+AZ28 -> 28802.879 | ... BW29: =BW27+BW28 -> 38589.314
B30: LTM EBITDA | C30: 200718 | D30: 222533 | E30: 233340 | F30: 278430 | G30: 314517 | H30: 341682 | I30: 356208 | J30: 314066.81 | K30: 304479 | L30: 294618.39 | M30: 278014.62 | N30: 265212.62 | O30: 262937 | P30: 339705.61 | Q30: 357450.12 | R30: 374003.89 | S30: 371053 | T30: 425568 | U30: 473932 | V30: 487108 | W30: 461387 | X30: 527576 | Y30: 560708 | Z30: 535853 | AA30: 581103 | AB30: 664176 | AC30: 708848 | AD30: 689248 | AE30: 717330 | AF30: 748747 | AG30: 768185 | AH30: 782620.64 | AI30: 790458 | AJ30: 792439 | AK30: 815999 | AL30: 864356.36 | AM30: 942490 | AN30: 1024716 | AO30: 1103696 | AP30: ='Model '!BY$100 -> 1166337 | AQ30: ='Model '!BZ$100 -> 1212676
B31: Debt Check | C31: 0 | D31: 0 | E31: 0 | F31: 0 | G31: 0 | H31: 0 | I31: 0 | J31: 0 | K31: 0 | L31: 0 | M31: 0 | N31: 0 | O31: 0 | P31: 0 | Q31: 0 | R31: 0 | S31: 0 | T31: 0 | U31: 0 | V31: 0 | W31: 0 | X31: 0 | Y31: 0 | Z31: 0 | AA31: 0 | AB31: 0 | AC31: 0 | AD31: 0 | AE31: 0 | AF31: 0 | AG31: 0 | AH31: 0 | AI31: 0 | AJ31: 0 | AK31: 0 | AL31: 0 | AM31: 0 | AN31: 0 | AO31: 0 | AP31: =AP25-'Model '!BY$124 -> 0
B33: Secured Net Leverage | C33: =(C8-C26)/C30 -> -0.085667454 | D33: =(D8-D26)/D30 -> -0.17902064 | E33: =(E8-E26)/E30 -> -0.35911545 | F33: =(F8-F26)/F30 -> -0.55514133 | G33: =(G8-G26)/G30 -> -0.44010976 | H33: =(H8-H26)/H30 -> -0.028386043 | I33: =(I8-I26)/I30 -> -0.098672686 | J33: =(J8-J26)/J30 -> -0.11605618 | ... AQ33: =(AQ8-AQ26)/AQ30 -> 0.35729247
B34: Gross Leverage ( Total debt/ EBITDA) | C34: =C25/C30 -> 3.0725047 | D34: =D25/D30 -> 3.1017063 | E34: =E25/E30 -> 2.8600454 | F34: =F25/F30 -> 2.7295335 | G34: =G25/G30 -> 2.5653272 | H34: =H25/H30 -> 2.9399442 | I34: =I25/I30 -> 3.0158812 | J34: =J25/J30 -> 3.3827376 | ... AQ34: =AQ25/AQ30 -> 1.6122245
B35: Net Leverage ( Net debt/ EBITDA) | C35: =C27/C30 -> 2.9868373 | D35: =D27/D30 -> 2.9226856 | E35: =E27/E30 -> 2.50093 | F35: =F27/F30 -> 2.1743921 | G35: =G27/G30 -> 2.1252174 | H35: =H27/H30 -> 2.6134798 | I35: =I27/I30 -> 2.7246665 | J35: =J27/J30 -> 3.0742777 | ... AQ35: =AQ27/AQ30 -> 1.3588856
B38: Market Cap | C38: 1357238 | D38: 1283186 | E38: 1107929.4 | F38: 1320141.4 | G38: 1572177.4 | H38: 1402288 | I38: 1399289.9 | J38: 2117222.9 | K38: 1593763.4 | L38: 1429670.1 | M38: 1353319.8 | N38: 1224803 | O38: 1331533.9 | P38: 1778657.7 | Q38: 1467245.7 | R38: 2339165.6 | S38: 3184000 | T38: 3054294 | U38: 2296513.8 | V38: 3267610 | W38: 2841025.7 | X38: 2867946.4 | Y38: 3780162.2 | Z38: 4021230 | AA38: 4303000 | AB38: 4050000 | AC38: 4820000 | AD38: 4536000 | AE38: 4320000 | AF38: 5062740 | AG38: 5420642.3 | AH38: 6560410 | AI38: 7273000 | AJ38: 8757000 | AK38: 9798000 | AL38: 10033000 | AM38: 10980575 | AN38: 11567616 | AO38: 11989648 | AP38: ='Model '!BY$132 -> 12178531 | AQ38: ='Model '!BZ$132 -> 11417638
B39: EV | C39: =C38+C27 -> 1956750 | D39: =D38+D27 -> 1933580 | E39: =E38+E27 -> 1691496.4 | F39: =F38+F27 -> 1925557.4 | G39: =G38+G27 -> 2240594.4 | H39: =H38+H27 -> 2295267 | I39: =I38+I27 -> 2369837.9 | J39: =J38+J27 -> 3082751.5 | ... AQ39: =AQ38+AQ27 -> 13065526
B41: EV/EBITDA | C41: =C39/C30 -> 9.748752 | D41: =D39/D30 -> 8.6889585 | E41: =E39/E30 -> 7.2490632 | F41: =F39/F30 -> 6.9157684 | G41: =G39/G30 -> 7.1239214 | H41: =H39/H30 -> 6.7175532 | I41: =I39/I30 -> 6.6529609 | J41: =J39/J30 -> 9.8155915 | ... AQ41: =AQ39/AQ30 -> 10.774127
I43: Liquidity Table as of end-3Q24 | J43: INR mn | K43: USD mn | M43: Debt maturity profile | N43: INR mn | O43: USD mn
M44: 2024 | N44: =O44*BL$2 -> 279547.22 | O44: 3404.96
I45: Cash | J45: =AH26 -> 164342 | K45: =BN26 -> 1974.3627 | M45: 2025 | N45: =O45*BL$2 -> 130774.63 | O45: 1592.87
I46: Available RCF | M46: 2030 | N46: =O46*BL$2 -> 15927.4 | O46: 194
I47: Total liquidity | J47: =SUM(J45:J46) -> 164342 | K47: =SUM(K45:K46) -> 1974.3627 | M47: 2031 | N47: =O47*BL$2 -> 209948.58 | O47: 2557.23
M48: >2031 | N48: =O48*BL$2 -> 123150 | O48: 1500
M49: Total | N49: =SUM(N44:N48) -> 759347.83 | O49: =SUM(O44:O48) -> 9249.06
I53: Liquidity Table as of end-2Q24 | J53: INR mn | K53: USD mn | M53: Debt maturity profile | N53: INR mn | O53: USD mn
M54: 2023 | N54: =O54*BL$2 -> 0 | O54: 0
I55: Cash | J55: =$AF$26 -> 172029 | K55: =$BK$26 -> 1564.7417 | M55: 2024 | N55: =O55*BL$2 -> 294275.96 | O55: 3584.36
I56: Available RCF | M56: 2025 | N56: =O56*BL$2 -> 148432.7 | O56: 1807.95
I57: Total liquidity | J57: =SUM(J55:J56) -> 172029 | K57: =SUM(K55:K56) -> 1564.7417 | M57: 2030 | N57: =O57*BL$2 -> 15927.4 | O57: 194
M58: 2031 | N58: =O58*BL$2 -> 209483.08 | O58: 2551.56
M59: >2031 | N59: =O59*BL$2 -> 123150 | O59: 1500
M60: Total | N60: =SUM(N54:N59) -> 791269.13 | O60: =SUM(O54:O59) -> 9637.87
I63: Liquidity Table as of end-1Q24 | J63: INR mn | K63: USD mn | M63: Debt maturity profile | N63: INR mn | O63: USD mn
M64: 2023 | N64: =O64*BL$2 -> 9852 | O64: 120
I65: Cash | J65: =AF26 -> 172029 | K65: =BK14 -> 1000 | M65: 2024 | N65: =O65*BL$2 -> 294664.29 | O65: 3589.09
I66: Available RCF | M66: 2025 | N66: =O66*BL$2 -> 160037.53 | O66: 1949.3
I67: Total liquidity | J67: =SUM(J65:J66) -> 172029 | K67: =SUM(K65:K66) -> 1000 | M67: 2030 | N67: =O67*BL$2 -> 15927.4 | O67: 194
M68: 2031 | N68: =O68*BL$2 -> 211145.6 | O68: 2571.81
M69: >2031 | N69: =O69*BL$2 -> 123150 | O69: 1500
M70: Total | N70: =SUM(N64:N69) -> 814776.82 | O70: =SUM(O64:O69) -> 9924.2
I73: Liquidity Table as of end-4Q23 | J73: INR mn | K73: USD mn | M73: Debt maturity profile | N73: INR mn | O73: USD mn
M74: 2023 | N74: =O74*$BJ$2 -> 9926.04 | O74: 120
I75: Cash | J75: =AE26 -> 128434 | K75: =BK26 -> 1564.7417 | M75: 2024 | N75: =O75*$BJ$2 -> 296938.31 | O75: 3589.81
I76: Available RCF | M76: 2025 | N76: =O76*$BJ$2 -> 161240.25 | O76: 1949.3
I77: Total liquidity | J77: =SUM(J75:J76) -> 128434 | K77: =SUM(K75:K76) -> 1564.7417 | M77: 2030 | N77: =O77*$BJ$2 -> 16047.098 | O77: 194
M78: 2031 | N78: =O78*$BJ$2 -> 212988 | O78: 2574.9
I79: Liquidity Table as of end-3Q23 | J79: INR mn | K79: USD mn | M79: >2031 | N79: =O79*$BJ$2 -> 124075.5 | O79: 1500
M80: Total | N80: =SUM(N74:N79) -> 821215.2 | O80: =SUM(O74:O79) -> 9928.01
I81: Cash | J81: =AE26 -> 128434 | K81: =BJ26 -> 1489.8411
I82: Available RCF
I83: Total liquidity | J83: =SUM(J81:J82) -> 128434 | K83: =SUM(K81:K82) -> 1489.8411
I86: Liquidity Table as of end-2Q23 | J86: INR mn | K86: USD mn
I88: Cash | J88: =AC26 -> 82596.571 | K88: =BI26 -> 1013.9401
I89: Available RCF
I90: Total liquidity | J90: =SUM(J88:J89) -> 82596.571 | K90: =SUM(K88:K89) -> 1013.9401
I94: Liquidity Table as of end-1Q23 | J94: INR mn | K94: USD mn
I96: Cash | J96: =AB26 -> 106002.17 | K96: =BH26 -> 1343.1598
I97: Available RCF
I98: Total liquidity | J98: =SUM(J96:J97) -> 106002.17 | K98: =SUM(K96:K97) -> 1343.1598
I100: Liquidity Table as of end-4Q22 | J100: INR mn | K100: USD mn
I102: Cash | J102: =AA26 -> 92208 | K102: =BG26 -> 1240.0215
I103: Available RCF
I104: Total liquidity | J104: =SUM(J102:J103) -> 92208 | K104: =SUM(K102:K103) -> 1240.0215
I106: Liquidity Table as of end-3Q22 | J106: INR mn | K106: USD mn
I108: Cash | J108: =Z26 -> 91451.101 | K108: =BF26 -> 1228.0755
I109: Available RCF
I110: Total liquidity | J110: =SUM(J108:J109) -> 91451.101 | K110: =SUM(K108:K109) -> 1228.0755
I112: Liquidity Table as of end-2Q22 | J112: INR mn | K112: USD mn
I114: Cash | J114: =Y26 -> 139629 | K114: =BE26 -> 1881.1941
I115: Available RCF
I116: Total liquidity | J116: =SUM(J114:J115) -> 139629 | K116: =SUM(K114:K115) -> 1881.1941
I118: Liquidity Table as of end-1Q22 | J118: INR mn | K118: USD mn
I120: Cash | J120: =X26 -> 90187 | K120: =BD26 -> 1212.6538
I121: Available RCF
I122: Total liquidity | J122: =SUM(J120:J121) -> 90187 | K122: =SUM(K120:K121) -> 1212.6538
I124: Liquidity Table as of end-4Q21 | J124: INR mn | K124: USD mn
I126: Cash | J126: =W26 -> 140713 | K126: =BC26 -> 1922.1381
I127: Available RCF
I128: Total liquidity | J128: =SUM(J126:J127) -> 140713 | K128: =SUM(K126:K127) -> 1922.1381
I131: Liquidity Table as of end-3Q21 | J131: INR mn | K131: USD mn
I133: Cash | J133: =V26 -> 104704 | K133: =BB26 -> 1434.1049
I134: Available RCF
...

Sheet Model 
B2: Bharti Airtel | D2: Annual | E2: Annual | F2: Annual | G2: Annual | H2: Annual | I2: Annual | J2: Annual | K2: Annual | L2: Annual | M2: Annual | N2: Annual | O2: Annual | P2: Annual | Q2: Annual | R2: Annual | S2: Annual | T2: Annual | U2: LTM | W2: Quarter | X2: Quarter | Y2: Quarter | Z2: Quarter | AA2: Quarter | AB2: Quarter | AC2: Quarter | AD2: Quarter | AE2: Quarter | AF2: Quarter | AG2: Quarter | AH2: Quarter | AI2: Quarter | AJ2: Quarter | AK2: Quarter | AL2: Quarter | AM2: Quarter | AN2: Quarter | AO2: Quarter | AP2: Quarter | AQ2: Quarter | AR2: Quarter | AS2: Quarter | AT2: Quarter | AU2: Quarter | AV2: Quarter | AW2: Quarter | AX2: Quarter | AY2: Quarter | AZ2: Quarter | BA2: Quarter | BB2: Quarter | BC2: Quarter | BD2: Quarter | BE2: Quarter | BF2: Quarter | BG2: Quarter | BH2: Quarter | BI2: Quarter | BJ2: Quarter | BK2: Quarter | BL2: Quarter | BM2: Quarter | BN2: Quarter | BO2: Quarter | BP2: Quarter | BQ2: Quarter | BR2: Quarter | BS2: Quarter | BT2: Quarter | BU2: Quarter | BV2: Quarter | BW2: Quarter | BX2: Quarter | BY2: Quarter | BZ2: Quarter | CB2: Quarter | CC2: Quarter | CD2: Quarter | CE2: Quarter | CF2: Quarter | CH2: Annual
B3: (INR millions) | D3: 40612 | E3: 40979 | F3: 41346 | G3: 41713 | H3: 42080 | I3: 42460 | J3: 42825 | K3: 43190 | L3: 43190 | M3: 43555 | N3: 43921 | O3: 44286 | P3: 44651 | Q3: 45016 | R3: 45382 | S3: 45747 | T3: 46112 | U3: =BZ3 -> 46112 | W3: 41068 | X3: 41161 | Y3: 41253 | Z3: 41343 | AA3: 41433 | AB3: 41526 | AC3: 41618 | AD3: 41708 | AE3: 41798 | AF3: 41891 | AG3: 41983 | AH3: 42073 | AI3: 42163 | AJ3: 42256 | AK3: 42348 | AL3: 42439 | AM3: 42529 | AN3: 42622 | AO3: 42714 | AP3: 42804 | AQ3: 42916 | AR3: 43008 | AS3: 43100 | AT3: 43190 | AU3: 43281 | AV3: 43373 | AW3: 43465 | AX3: 43555 | AY3: 43646 | AZ3: 43738 | BA3: 43830 | BB3: 43921 | BC3: 44012 | BD3: 44104 | BE3: 44196 | BF3: 44286 | BG3: 44377 | BH3: 44469 | BI3: 44561 | BJ3: 44651 | BK3: 44742 | BL3: 44834 | BM3: 44926 | BN3: 45016 | BO3: 45107 | BP3: 45199 | BQ3: 45290 | BR3: 45382 | BS3: 45473 | BT3: 45565 | BU3: 45656 | BV3: 45747 | BW3: 45838 | BX3: 45930 | BY3: 46021 | BZ3: 46112 | CB3: 43646 | CC3: 43830 | CD3: 43921 | CE3: 44012 | CF3: 44104 | CH3: 43921
D4: Act | E4: Act | F4: Act | G4: Act | H4: Act | I4: Act | J4: Act | K4: Act | L4: Act | M4: Act | N4: Act | O4: Act | P4: Act | Q4: Act | R4: Act | S4: Act | T4: Act | U4: Act | W4: Act | X4: Act | Y4: Act | Z4: Act | AA4: Act | AB4: Act | AC4: Act | AD4: Act | AE4: Act | AF4: Act | AG4: Act | AH4: Act | AI4: Act | AJ4: Act | AK4: Act | AL4: Act | AM4: Act | AN4: Act | AO4: Act | AP4: Act | AQ4: Act | AR4: Act | AS4: Act | AT4: Act | AU4: Act | AV4: Act | AW4: Act | AX4: Act | AY4: Act | AZ4: Act | BA4: Act | BB4: Act | BC4: Act | BD4: Act | BE4: Act | BF4: Act | BG4: Act | BH4: Act | BI4: Act | BJ4: Act | BK4: Act | BL4: Act | BM4: Act | BN4: Act | BO4: Act | BP4: Act | BQ4: Act | BR4: Act | BS4: Act | BT4: Act | BU4: Act | BV4: Act | BW4: Act | BX4: Act | BY4: Act | BZ4: Act | CB4: Act | CC4: Act | CD4: Act | CE4: Act | CF4: Act | CH4: Act
D5: FY 11 | E5: FY 12 | F5: FY 13 | G5: FY 14 | H5: FY 15 | I5: FY 16 | J5: FY 17 | K5: FY 18 | L5: FY 18 | M5: FY 19 | N5: FY 20 | O5: FY 21 | P5: FY 22 | Q5: FY 23 | R5: FY 24 | S5: FY 25 | T5: FY 26 | U5: LTM | W5: 1Q | X5: 2Q | Y5: 3Q | Z5: 4Q | AA5: 1Q | AB5: 2Q | AC5: 3Q | AD5: 4Q | AE5: 1Q | AF5: 2Q | AG5: 3Q | AH5: 4Q | AI5: 1Q | AJ5: 2Q | AK5: 3Q | AL5: 4Q | AM5: 1Q | AN5: 2Q | AO5: 3Q | AP5: 4Q | AQ5: 1Q | AR5: 2Q | AS5: 3Q | AT5: 4Q | AU5: 1Q | AV5: 2Q | AW5: 3Q | AX5: 4Q | AY5: 1Q | AZ5: 2Q | BA5: 3Q | BB5: 4Q | BC5: 1Q | BD5: 2Q | BE5: 3Q | BF5: 4Q | BG5: 1Q | BH5: 2Q | BI5: 3Q | BJ5: 4Q | BK5: 1Q | BL5: 2Q | BM5: 3Q | BN5: 4Q | BO5: 1Q | BP5: 2Q | BQ5: 3Q | BR5: 4Q | BS5: 1Q | BT5: 2Q | BU5: 3Q | BV5: 4Q | BW5: 1Q | BX5: 2Q | BY5: 3Q | BZ5: 4Q | CB5: Q1 20 | CC5: Q3 20 | CD5: Q4 20 | CE5: Q1 21 | CF5: Q2 21 | CH5: FY 20
B6: INCOME STATEMENT | L6: Restated | AU6: Restated | AV6: Restated | AW6: Restated | CB6: Restated | CC6: Restated | CD6: Restated | CE6: Restated | CF6: Restated | CH6: Restated
B7: Revenue from operations | D7: 595383 | E7: 683267 | F7: 769044.92 | G7: 857460.94 | H7: 920394 | I7: 965321 | J7: 954683 | K7: 836879 | L7: 826388 | M7: 807802 | N7: 875390 | O7: 1006158 | P7: 1165469 | Q7: 1391448 | R7: 1499824 | S7: 1729852 | T7: 2109728 | U7: =SUM(BW7:BZ7) -> 2109728 | W7: 185601 | X7: 193998.74 | Y7: 193624.42 | Z7: =F7-SUM(W7:Y7) -> 195820.75 | AA7: 202639.24 | AB7: 213243.7 | AC7: 219385 | AD7: =G7-SUM(AA7:AC7) -> 222193 | AE7: 229616 | AF7: 228452 | AG7: 232171 | AH7: =H7-SUM(AE7:AG7) -> 230155 | AI7: 236709 | AJ7: 238357 | AK7: 240659 | AL7: =I7-SUM(AI7:AK7) -> 249596 | AM7: 255465 | AN7: 246515 | AO7: 233357 | AP7: =J7-SUM(AM7:AO7) -> 219346 | AQ7: 219581 | AR7: 217769 | AS7: 203186 | AT7: =+K7-AS7-AR7-AQ7 -> 196343 | AU7: 197992.29 | AV7: 201477.59 | AW7: 202310.66 | AX7: =M7-AW7-AV7-AU7 -> 206021.47 | AY7: 207379 | AZ7: 211313 | BA7: 219471 | BB7: =N7-BA7-AZ7-AY7 -> 237227 | BC7: 239387 | BD7: 257850 | BE7: 265178 | BF7: =O7-BE7-BD7-BC7 -> 243743 | BG7: 268536 | BH7: 283264 | BI7: 298666 | BJ7: =P7-BI7-BH7-BG7 -> 315003 | BK7: 328046 | BL7: 345268 | BM7: 358044 | BN7: =Q7-BM7-BL7-BK7 -> 360090 | BO7: 374400 | BP7: 370438 | BQ7: 378995 | BR7: =R7-BQ7-BP7-BO7 -> 375991 | BS7: 385064 | BT7: 414733 | BU7: 451293 | BV7: =S7-BU7-BT7-BS7 -> 478762 | BW7: 494626 | BX7: 521454 | BY7: 539816 | BZ7: =T7-SUM(BW7:BY7) -> 553832 | CB7: 207379 | CC7: 213436 | CD7: 230187 | CE7: 232903 | CF7: 250604 | CH7: 846765
B8: % growth | E8: =E7/D7-1 -> 0.14760919 | F8: =F7/E7-1 -> 0.12554084 | G8: =G7/F7-1 -> 0.11496861 | H8: =H7/G7-1 -> 0.073394669 | I8: =I7/H7-1 -> 0.048812791 | J8: =J7/I7-1 -> -0.011020168 | K8: =K7/J7-1 -> -0.12339593 | L8: =L7/J7-1 -> -0.13438492 | M8: =M7/L7-1 -> -0.022490646 | N8: =N7/M7-1 -> 0.083669018 | O8: =O7/N7-1 -> 0.14938256 | P8: =P7/O7-1 -> 0.15833597 | Q8: =Q7/P7-1 -> 0.19389533 | R8: =R7/Q7-1 -> 0.077887208 | S8: =S7/R7-1 -> 0.15337 | T8: =T7/S7-1 -> 0.21960029 | AE8: =AE7/AA7-1 -> 0.13312703 | AF8: =AF7/AB7-1 -> 0.071318882 | AG8: =AG7/AC7-1 -> 0.058281104 | AH8: =AH7/AD7-1 -> 0.035833712 | AI8: =AI7/AE7-1 -> 0.030890704 | AJ8: =AJ7/AF7-1 -> 0.043357029 | AK8: =AK7/AG7-1 -> 0.03655926 | AL8: =AL7/AH7-1 -> 0.084469162 | ... BB8: =BB7/AX7-1 -> 0.15146738 | BC8: =BC7/CB7-1 -> 0.15434543 | BD8: =BD7/AZ7-1 -> 0.22022781 | BE8: =BE7/BA7-1 -> 0.20825986 | BF8: =BF7/BB7-1 -> 0.027467362 | BG8: =BG7/CE7-1 -> 0.15299502 | BH8: =BH7/CF7-1 -> 0.13032513 | BI8: =BI7/BE7-1 -> 0.12628499 | BJ8: =BJ7/BF7-1 -> 0.29235711 | BK8: =BK7/BG7-1 -> 0.22160902 | BL8: =BL7/BH7-1 -> 0.21889121 | BM8: =BM7/BI7-1 -> 0.19881071 | BN8: =BN7/BJ7-1 -> 0.14313197 | BO8: =BO7/BK7-1 -> 0.14130335 | BP8: =BP7/BL7-1 -> 0.072899892 | ... BZ8: =BZ7/BV7-1 -> 0.15680025 | CB8: =CB7/AU7-1 -> 0.047409481 | CC8: =CC7/AY7-1 -> 0.029207393 | CD8: =CD7/AX7-1 -> 0.11729619 | CE8: =CE7/AW7-1 -> 0.15121469 | CF8: =CF7/AV7-1 -> 0.24383066 | CH8: =CH7/M7-1 -> 0.048233354
B9: Other income | D9: 635 | E9: 550 | F9: 425 | G9: 1174 | H9: 957 | I9: 871 | J9: 1206 | K9: 2488 | L9: 2488 | M9: 2912 | N9: 3248 | O9: 6428 | P9: 5343 | Q9: 9366 | R9: 14354 | S9: 15737 | T9: 28173 | U9: =SUM(BW9:BZ9) -> 28173 | W9: 102 | X9: 86 | Y9: 134 | Z9: =F9-SUM(W9:Y9) -> 103 | AA9: 356 | AB9: 184 | AC9: 222 | AD9: =G9-SUM(AA9:AC9) -> 412 | AE9: 439 | AF9: 165 | AG9: 110 | AH9: =H9-SUM(AE9:AG9) -> 243 | AI9: 99 | AJ9: 162 | AK9: 375 | AL9: =I9-SUM(AI9:AK9) -> 235 | AM9: 264 | AN9: 200 | AO9: 282 | AP9: 460 | AQ9: 486 | AR9: 553 | AS9: 696 | AT9: =+K9-AS9-AR9-AQ9 -> 753 | AU9: 997 | AV9: 813 | AW9: 675 | AX9: =M9-AW9-AV9-AU9 -> 427 | AY9: 746 | AZ9: 677 | BA9: 745 | BB9: =N9-BA9-AZ9-AY9 -> 1080 | BC9: =4805-4063 -> 742 | BD9: =1489-346 -> 1143 | BE9: =492-556 -> -64 | BF9: =O9-BE9-BD9-BC9 -> 4607 | BG9: =2098-1438 -> 660 | BH9: =1088-804 -> 284 | BI9: =1971-79 -> 1892 | BJ9: =P9-BI9-BH9-BG9 -> 2507 | BK9: 1922 | BL9: =2019 -> 2019 | BM9: 2576 | BN9: =Q9-BM9-BL9-BK9 -> 2849 | BO9: 3483 | BP9: 3304 | BQ9: 4398 | BR9: =R9-BQ9-BP9-BO9 -> 3169 | BS9: 3635 | BT9: 2547 | BU9: 4697 | BV9: =S9-BU9-BT9-BS9 -> 4858 | BW9: =5088 -> 5088 | BX9: 7277 | BY9: 7023 | BZ9: =T9-SUM(BW9:BY9) -> 8785 | CB9: =2945-2113 -> 832 | CC9: =3067-2970 -> 97 | CD9: =8198-4314 -> 3884 | CE9: =4066-3372 -> 694 | CF9: =1031-54 -> 977 | CH9: 15357
B10: Total income from operations | D10: =D7+D9 -> 596018 | E10: =E7+E9 -> 683817 | F10: =F7+F9 -> 769469.92 | G10: =G7+G9 -> 858634.94 | H10: =H7+H9 -> 921351 | I10: =I7+I9 -> 966192 | J10: =J7+J9 -> 955889 | K10: =K7+K9 -> 839367 | ... U10: =U7+U9 -> 2137901 | W10: =W7+W9 -> 185703 | X10: =X7+X9 -> 194084.74 | Y10: =Y7+Y9 -> 193758.42 | Z10: =Z7+Z9 -> 195923.75 | AA10: =AA7+AA9 -> 202995.24 | AB10: =AB7+AB9 -> 213427.7 | AC10: =AC7+AC9 -> 219607 | AD10: =AD7+AD9 -> 222605 | ... BZ10: =BZ7+BZ9 -> 562617 | CB10: =CB7+CB9 -> 208211 | CC10: =CC7+CC9 -> 213533 | CD10: =CD7+CD9 -> 234071 | CE10: =CE7+CE9 -> 233597 | CF10: =CF7+CF9 -> 251581 | CH10: =CH7+CH9 -> 862122
B11: % growth | E11: =E10/D10-1 -> 0.14730931 | F11: =F10/E10-1 -> 0.12525707 | G11: =G10/F10-1 -> 0.1158785 | H11: =H10/G10-1 -> 0.073041591 | I11: =I10/H10-1 -> 0.048668748 | J11: =J10/I10-1 -> -0.010663512 | K11: =K10/J10-1 -> -0.12189909 | L11: =L10/J10-1 -> -0.13287421 | M11: =M10/L10-1 -> -0.021911601 | N11: =N10/M10-1 -> 0.083782937 | O11: =O10/N10-1 -> 0.15244959 | P11: =P10/O10-1 -> 0.15625932 | Q11: =Q10/P10-1 -> 0.19644657 | R11: =R10/Q10-1 -> 0.080927232 | S11: =S10/R10-1 -> 0.15282946 | T11: =T10/S10-1 -> 0.22474477 | AQ11: =AQ10/AM10-1 -> -0.13945231 | AR11: =AR10/AN10-1 -> -0.11508421 | AS11: =AS10/AO10-1 -> -0.12736315 | AT11: =AT10/AP10-1 -> -0.10331838 | AU11: =AU10/AQ10-1 -> -0.095778612 | AV11: =AV10/AR10-1 -> -0.073430129 | AW11: =AW10/AS10-1 -> -0.0043963819 | AX11: =AX10/AT10-1 -> 0.047451331 | ... BB11: =BB10/AX10-1 -> 0.15431712 | BC11: =BC10/CB10-1 -> 0.15329642 | BD11: =BD10/AZ10-1 -> 0.22172272 | BE11: =BE10/BA10-1 -> 0.20388164 | BF11: =BF10/BB10-1 -> 0.042143118 | BG11: =BG10/CE10-1 -> 0.15239494 | BH11: =BH10/CF10-1 -> 0.12706444 | BI11: =BI10/BE10-1 -> 0.13369343 | BJ11: =BJ10/BF10-1 -> 0.27847795 | BK11: =BK10/BG10-1 -> 0.22575373 | BL11: =BL10/BH10-1 -> 0.22479086 | BM11: =BM10/BI10-1 -> 0.19983497 | BN11: =BN10/BJ10-1 -> 0.14307896 | BO11: =BO10/BK10-1 -> 0.14521105 | BP11: =BP10/BL10-1 -> 0.076176189 | ... BZ11: =BZ10/BV10-1 -> 0.16334519 | CB11: =CB10/AU10-1 -> 0.046342754 | CC11: =CC10/AY10-1 -> 0.025984384 | CD11: =CD10/AX10-1 -> 0.13379868 | CE11: =CE10/AW10-1 -> 0.15080545 | CF11: =CF10/AV10-1 -> 0.24366142 | CH11: =CH10/M10-1 -> 0.063410771
B12: Expenses
B13: Network operating expenses | I13: 201567 | J13: 209154 | K13: 197520 | L13: 197520 | M13: 223900 | N13: 197685 | O13: 219819 | P13: 250205 | Q13: 285433 | R13: 300188 | S13: 335043 | T13: 397500 | U13: =SUM(BW13:BZ13) -> 397500 | AM13: 53957.992 | AN13: 50933.404 | AO13: 52634.744 | AP13: =J13-SUM(AM13:AO13) -> 51627.86 | AQ13: 51612 | AR13: 50472 | AS13: 47365 | AT13: =+K13-AS13-AR13-AQ13 -> 48071 | AU13: 50677 | AV13: 56289.452 | AW13: 57539 | AX13: =M13-AW13-AV13-AU13 -> 59394.548 | AY13: 45957 | AZ13: 49688.872 | BA13: 49344.621 | BB13: =N13-BA13-AZ13-AY13 -> 52694.507 | BC13: 51036 | BD13: 54564 | BE13: 55479 | BF13: =O13-BE13-BD13-BC13 -> 58740 | BG13: 57973 | BH13: 61788 | BI13: 64986 | BJ13: =P13-BI13-BH13-BG13 -> 65458 | BK13: 66828 | BL13: 71303 | BM13: 73284 | BN13: =Q13-BM13-BL13-BK13 -> 74018 | BO13: 74036 | BP13: 74240 | BQ13: 75926 | BR13: =R13-BQ13-BP13-BO13 -> 75986 | BS13: 77606 | BT13: 80115 | BU13: 86267 | BV13: =S13-BU13-BT13-BS13 -> 91055 | BW13: 95456 | BX13: 101178 | BY13: 98786 | BZ13: =T13-SUM(BW13:BY13) -> 102080 | CB13: 46636 | CC13: 49849 | CD13: 51510 | CE13: 50963 | CF13: 54198 | CH13: 196305
B14: Access Charges | I14: 109423 | J14: 102786 | K14: 90446 | L14: 90446 | M14: 93521 | N14: 107395 | O14: 103521 | P14: 67611 | Q14: 76207 | R14: 75185 | S14: 71713 | T14: 55416 | U14: =SUM(BW14:BZ14) -> 55416 | AM14: 27041.285 | AN14: 28597.715 | AO14: 24386 | AP14: =J14-SUM(AM14:AO14) -> 22761 | AQ14: 25016 | AR14: 25603 | AS14: 19539 | AT14: =+K14-AS14-AR14-AQ14 -> 20288 | AU14: 21355 | AV14: 23294 | AW14: 24462 | AX14: =M14-AW14-AV14-AU14 -> 24410 | AY14: 25627 | AZ14: 26389 | BA14: 27109 | BB14: =N14-BA14-AZ14-AY14 -> 28270 | BC14: 28011 | BD14: 29229 | BE14: 30632 | BF14: =O14-BE14-BD14-BC14 -> 15649 | BG14: 16166 | BH14: 16708 | BI14: 17232 | BJ14: =P14-BI14-BH14-BG14 -> 17505 | BK14: 18698 | BL14: 19310 | BM14: 19352 | BN14: =Q14-BM14-BL14-BK14 -> 18847 | BO14: 19972 | BP14: 18144 | BQ14: 18568 | BR14: =R14-BQ14-BP14-BO14 -> 18501 | BS14: 19084 | BT14: 18211 | BU14: 19636 | BV14: =S14-BU14-BT14-BS14 -> 14782 | BW14: 12571 | BX14: 13215 | BY14: 14691 | BZ14: =T14-SUM(BW14:BY14) -> 14939 | CB14: 25627 | CC14: 27109 | CD14: 28270 | CE14: 28011 | CF14: 29229 | CH14: 107395
B15: License fee / spectrum charges (revenue share) | I15: 94928 | J15: 92760 | K15: 75558 | L15: 75558 | M15: 69426 | N15: 72561 | O15: 91084 | P15: 110636 | Q15: 117517 | R15: 120358 | S15: 138290 | T15: 153729 | U15: =SUM(BW15:BZ15) -> 153729 | AM15: 25498.85 | AN15: 24143.15 | AO15: 22268 | AP15: =J15-SUM(AM15:AO15) -> 20850 | AQ15: 20820 | AR15: 19720 | AS15: 17542 | AT15: =+K15-AS15-AR15-AQ15 -> 17476 | AU15: 16972 | AV15: 17697 | AW15: 17469 | AX15: =M15-AW15-AV15-AU15 -> 17288 | AY15: 17930 | AZ15: 16764 | BA15: 17666 | BB15: =N15-BA15-AZ15-AY15 -> 20201 | BC15: 20768 | BD15: 22355 | BE15: 22952 | BF15: =O15-BE15-BD15-BC15 -> 25009 | BG15: 26455 | BH15: 26794 | BI15: 27298 | BJ15: =P15-BI15-BH15-BG15 -> 30089 | BK15: 31306 | BL15: 29511 | BM15: 28421 | BN15: =Q15-BM15-BL15-BK15 -> 28279 | BO15: 29403 | BP15: 29643 | BQ15: 30205 | BR15: =R15-BQ15-BP15-BO15 -> 31107 | BS15: 31564 | BT15: 34658 | BU15: 35698 | BV15: =S15-BU15-BT15-BS15 -> 36370 | BW15: 37200 | BX15: 38249 | BY15: 38462 | BZ15: =T15-SUM(BW15:BY15) -> 39818 | CB15: 18391 | CC15: 17875 | CD15: 20569 | CE15: 20766 | CF15: 22354 | CH15: 73826
B16: Employee benefits | I16: 49108 | J16: 43032 | K16: 39771 | L16: 39771 | M16: 37975 | N16: 38072 | O16: 41146 | P16: 44333 | Q16: 48308 | R16: 53231 | S16: 63089 | T16: 75813 | U16: =SUM(BW16:BZ16) -> 75813 | AM16: 11144.376 | AN16: 10857.624 | AO16: 10532 | AP16: =J16-SUM(AM16:AO16) -> 10498 | AQ16: 10147 | AR16: 10089 | AS16: 9586 | AU16: 9656 | AV16: 9360 | AW16: 9530 | AX16: =M16-AW16-AV16-AU16 -> 9429 | AY16: 8641 | AZ16: 9464 | BA16: 9651 | BB16: =N16-BA16-AZ16-AY16 -> 10316 | BC16: 11566 | BD16: 11008 | BE16: 10260 | BF16: =O16-BE16-BD16-BC16 -> 8312 | BG16: 10345 | BH16: 11010 | BI16: 11336 | BJ16: =P16-BI16-BH16-BG16 -> 11642 | BK16: 11235 | BL16: 12086 | BM16: 12353 | BN16: =Q16-BM16-BL16-BK16 -> 12634 | BO16: 12572 | BP16: 13790 | BQ16: 13230 | BR16: =R16-BQ16-BP16-BO16 -> 13639 | BS16: 13728 | BT16: 14966 | BU16: 16082 | BV16: =S16-BU16-BT16-BS16 -> 18313 | BW16: 17380 | BX16: 18571 | BY16: 19581 | BZ16: =T16-SUM(BW16:BY16) -> 20281 | CB16: 8641 | CC16: 8914 | CD16: 9520 | CE16: 10725 | CF16: 10172 | CH16: 35137
B17: Sales and marketing expenses | I17: 82410 | J17: 66732 | K17: 55766 | L17: 45275 | M17: 41277 | N17: 34325 | O17: 38009 | P17: 53035 | Q17: 72454 | R17: 81326 | S17: 114601 | T17: 131073 | U17: =SUM(BW17:BZ17) -> 131073 | AM17: 19904.247 | AN17: 18012.026 | AO17: 16549.928 | AP17: =J17-SUM(AM17:AO17) -> 12265.799 | AQ17: 15365 | AR17: 14104 | AS17: 15902 | AT17: =+K17-AS17-AR17-AQ17 -> 10395 | AU17: 10144.288 | AV17: 10207.507 | AW17: 10560.657 | AX17: =M17-AW17-AV17-AU17 -> 10364.548 | AY17: 8364 | AZ17: 7580.9178 | BA17: 9003 | BB17: =N17-BA17-AZ17-AY17 -> 9377.0822 | BC17: 7301 | BD17: 8744 | BE17: 10524 | BF17: =O17-BE17-BD17-BC17 -> 11440 | BG17: 10613 | BH17: 12670 | BI17: 14425 | BJ17: =P17-BI17-BH17-BG17 -> 15327 | BK17: 15669 | BL17: 17823 | BM17: 19118 | BN17: =Q17-BM17-BL17-BK17 -> 19844 | BO17: 20596 | BP17: 19590 | BQ17: 20473 | BR17: =R17-BQ17-BP17-BO17 -> 20667 | BS17: 27157 | BT17: 28824 | BU17: 29261 | BV17: =S17-BU17-BT17-BS17 -> 29359 | BW17: 29659 | BX17: 31824 | BY17: 34269 | BZ17: =T17-SUM(BW17:BY17) -> 35321 | CB17: 8386 | CC17: 8979 | CD17: 9335 | CE17: 7278 | CF17: 8722 | CH17: 34236
B18: Other expenses | I18: 88043 | J18: 86921 | K18: 77027 | L18: 77027 | M18: 83514 | N18: 59257 | O18: 58862 | P18: 64310 | Q18: 78794 | R18: 86618 | S18: 75524 | T18: 99452 | U18: =SUM(BW18:BZ18) -> 99452 | AM18: 22438.19 | AN18: 19568.142 | AO18: 22171.328 | AP18: =J18-SUM(AM18:AO18) -> 22743.341 | AQ18: 19036.82 | AR18: 18561 | AS18: 18564 | AT18: =+K18-AS18-AR18-AQ18 -> 20865.18 | AU18: 21929.751 | AV18: 22314.036 | AW18: 20570.176 | AX18: =M18-AW18-AV18-AU18 -> 18700.037 | AY18: 17972 | AZ18: 12823.362 | BA18: 14028 | BB18: =N18-BA18-AZ18-AY18 -> 14433.638 | BC18: 16626 | BD18: 15530 | BE18: 14801 | BF18: =O18-BE18-BD18-BC18 -> 11905 | BG18: 17181 | BH18: 16189 | BI18: 16361 | BJ18: =P18-BI18-BH18-BG18 -> 14579 | BK18: 19016 | BL18: 19297 | BM18: 20984 | BN18: =Q18-BM18-BL18-BK18 -> 19497 | BO18: 21836 | BP18: 19894 | BQ18: 22445 | BR18: =R18-BQ18-BP18-BO18 -> 22443 | BS18: 18849 | BT18: 19497 | BU18: 18383 | BV18: =S18-BU18-BT18-BS18 -> 18795 | BW18: 23973 | BX18: 22803 | BY18: 26199 | BZ18: =T18-SUM(BW18:BY18) -> 26477 | CB18: 17357 | CC18: 13546 | CD18: 14808 | CE18: 15989 | CF18: 15232 | CH18: 57332
B19: Profit from operating activities before D&A and exceptional items | D19: 200718 | E19: =103442+133681 -> 237123 | F19: =84431+148147 -> 232578 | G19: =121934+156496 -> 278430 | H19: 313883 | I19: =I10-SUM(I13:I18) -> 340713 | J19: =J10-SUM(J13:J18) -> 354504 | K19: =K10-SUM(K13:K18) -> 303279 | L19: =L10-SUM(L13:L18) -> 303279 | M19: =M10-SUM(M13:M18) -> 261101 | N19: =N10-SUM(N13:N18) -> 369343 | O19: =O10-SUM(O13:O18) -> 460145 | P19: =P10-SUM(P13:P18) -> 580682 | ... U19: =U10-SUM(U13:U18) -> 1224918 | W19: =18955+35901 -> 54856 | X19: =22478+36891 -> 59369 | Y19: =20399+37350 -> 57749 | Z19: =F19-SUM(W19:Y19) -> 60604 | AA19: =26979+38470 -> 65449 | AB19: =29335+39394 -> 68729 | AC19: =31818+39188 -> 71006 | AD19: =G19-SUM(AA19:AC19) -> 73246 | AE19: =36913+40365 -> 77278 | AF19: =38523+38530 -> 77053 | AG19: =39842+38015 -> 77857 | AH19: =H19-SUM(AE19:AG19) -> 81695 | AI19: =42158+40404 -> 82562 | AJ19: =40112+42390 -> 82502 | AK19: =40971+43541 -> 84512 | AL19: =I19-SUM(AI19:AK19) -> 91137 | AM19: =AM10-SUM(AM13:AM18) -> 95744.06 | AN19: =AN10-SUM(AN13:AN18) -> 94602.94 | AO19: =AO10-SUM(AO13:AO18) -> 85097 | AP19: =AP10-SUM(AP13:AP18) -> 79060 | AQ19: =AQ10-SUM(AQ13:AQ18) -> 78070.18 | AR19: =AR10-SUM(AR13:AR18) -> 79773 | AS19: =AS10-SUM(AS13:AS18) -> 75384 | AT19: =AT10-SUM(AT13:AT18) -> 80000.82 | ... BZ19: =BZ10-SUM(BZ13:BZ18) -> 323701 | CB19: =CB10-SUM(CB13:CB18) -> 83173 | CC19: =CC10-SUM(CC13:CC18) -> 87261 | CD19: =CD10-SUM(CD13:CD18) -> 100059 | CE19: =CE10-SUM(CE13:CE18) -> 99865 | CF19: =CF10-SUM(CF13:CF18) -> 111674 | CH19: =CH10-SUM(CH13:CH18) -> 357891
B20: % margin | D20: =D19/D10 -> 0.336765 | E20: =E19/E10 -> 0.34676383 | F20: =F19/F10 -> 0.30225743 | G20: =G19/G10 -> 0.32427052 | H20: =H19/H10 -> 0.3406769 | I20: =I19/I10 -> 0.35263488 | J20: =J19/J10 -> 0.37086314 | K20: =K19/K10 -> 0.36131871 | ... U20: =U19/U10 -> 0.57295357 | W20: =W19/W10 -> 0.29539641 | X20: =X19/X10 -> 0.30589215 | Y20: =Y19/Y10 -> 0.2980464 | Z20: =Z19/Z10 -> 0.30932442 | AA20: =AA19/AA10 -> 0.32241643 | AB20: =AB19/AB10 -> 0.32202475 | AC20: =AC19/AC10 -> 0.32333213 | AD20: =AD19/AD10 -> 0.32904023 | ... BZ20: =BZ19/BZ10 -> 0.57534877 | CB20: =CB19/CB10 -> 0.39946497 | CC20: =CC19/CC10 -> 0.40865346 | CD20: =CD19/CD10 -> 0.42747286 | CE20: =CE19/CE10 -> 0.42750977 | CF20: =CF19/CF10 -> 0.44388885 | CH20: =CH19/CH10 -> 0.41512802
B21: Share of results of joint ventures and associates | D21: 57 | E21: 74 | F21: -3506 | G21: -5211 | H21: -7223 | I21: -10666 | J21: -10449 | K21: -10609 | L21: -10609 | M21: -3556 | N21: -6524 | O21: 928 | P21: -24232 | Q21: -7521 | R21: -27094 | S21: -37030 | T21: -3645 | U21: =SUM(BW21:BZ21) -> -3645 | W21: -706 | X21: -982 | Y21: -943 | Z21: =F21-SUM(W21:Y21) -> -875 | AA21: -822 | AB21: -1652 | AC21: -1064 | AD21: =G21-SUM(AA21:AC21) -> -1673 | AE21: -1578 | AF21: -1709 | AG21: -1800 | AH21: =H21-SUM(AE21:AG21) -> -2136 | AI21: -2126 | AJ21: -2404 | AK21: -2463 | AL21: =I21-SUM(AI21:AK21) -> -3673 | AM21: -2548 | AN21: -2697 | AO21: -2696 | AP21: =J21-SUM(AM21:AO21) -> -2508 | AQ21: -2855 | AR21: -3662 | AS21: -2256 | AT21: =+K21-AS21-AR21-AQ21 -> -1836 | AU21: -1653 | AV21: -1633 | AW21: 98 | AX21: =M21-AW21-AV21-AU21 -> -368 | AY21: -931 | AZ21: -3155 | BA21: -1523 | BB21: =N21-BA21-AZ21-AY21 -> -915 | BC21: -1666 | BD21: 423 | BE21: 2206 | BF21: =O21-BE21-BD21-BC21 -> -35 | BG21: -4947 | BH21: -5988 | BI21: -6161 | BJ21: =P21-BI21-BH21-BG21 -> -7136 | BK21: -1628 | BL21: -3567 | BM21: 3684 | BN21: =Q21-BM21-BL21-BK21 -> -6010 | BO21: -5899 | BP21: -5860 | BQ21: -7032 | BR21: =R21-BQ21-BP21-BO21 -> -8303 | BS21: -9117 | BT21: -10739 | BU21: -16597 | BV21: =S21-BU21-BT21-BS21 -> -577 | BW21: -828 | BX21: -810 | BY21: -1163 | BZ21: =T21-SUM(BW21:BY21) -> -844 | CB21: -931 | CC21: 2015 | CD21: 1243 | CE21: 1070 | CF21: 2926 | CH21: 6627
B22: Depreciation and amortisation | D22: =D65+D66 -> 102066 | E22: =E65+E66 -> 133681 | F22: =F65+F66 -> 148148 | G22: =G65+G66 -> 156496 | H22: =H65+H66 -> 155311 | I22: =I65+I66 -> 174498 | J22: =J65+J66 -> 197730 | K22: =K65+K66 -> 192431 | L22: 192431 | M22: 213475 | N22: 276896 | O22: 294044 | P22: 330907 | Q22: 364318 | R22: 395376 | S22: 455703 | T22: 527108 | U22: =SUM(BW22:BZ22) -> 527108 | W22: 35901 | X22: 36891 | Y22: 37350 | Z22: =F22-SUM(W22:Y22) -> 38006 | AA22: 38470 | AB22: 39394 | AC22: 39188 | AD22: =G22-SUM(AA22:AC22) -> 39444 | AE22: 40365 | AF22: 38530 | AG22: 38015 | AH22: =H22-SUM(AE22:AG22) -> 38401 | AI22: 40404 | AJ22: 42390 | AK22: 43541 | AL22: =I22-SUM(AI22:AK22) -> 48163 | AM22: 50402 | AN22: 49560 | AO22: 48350 | AP22: =J22-SUM(AM22:AO22) -> 49418 | AQ22: 48192 | AR22: 46873 | AS22: 48375 | AT22: =+K22-AS22-AR22-AQ22 -> 48991 | AU22: 51452 | AV22: 52366 | AW22: 54723 | AX22: =M22-AW22-AV22-AU22 -> 54934 | AY22: 67587 | AZ22: 69351 | BA22: 69408 | BB22: =N22-BA22-AZ22-AY22 -> 70550 | BC22: 72268 | BD22: 74211 | BE22: 75031 | BF22: =O22-BE22-BD22-BC22 -> 72534 | BG22: 77137 | BH22: 82472 | BI22: 85472 | BJ22: =P22-BI22-BH22-BG22 -> 85826 | BK22: 87814 | BL22: 89468 | BM22: 92977 | BN22: =Q22-BM22-BL22-BK22 -> 94059 | BO22: 96538 | BP22: 97343 | BQ22: 100743 | BR22: =R22-BQ22-BP22-BO22 -> 100752 | BS22: 105401 | BT22: 110000 | BU22: 117042 | BV22: =S22-BU22-BT22-BS22 -> 123260 | BW22: 124651 | BX22: 131821 | BY22: 134201 | BZ22: =T22-SUM(BW22:BY22) -> 136435 | CB22: 67587 | CC22: 68178 | CD22: 68615 | CE22: 71131 | CF22: 72862 | CH22: 270944
B23: Finance costs | D23: 25349 | E23: 40828 | F23: 45187 | G23: 60060 | H23: 73252 | I23: 85461 | J23: 105540 | K23: 95703 | L23: 93255 | M23: 110134 | N23: 139918 | O23: 150910 | P23: 166162 | Q23: 192999 | R23: 226477 | S23: 217539 | T23: 215553 | U23: =SUM(BW23:BZ23) -> 215553 | W23: 9929 | X23: 12681 | Y23: 13177 | Z23: =F23-SUM(W23:Y23) -> 9400 | AA23: 15889 | AB23: 16957 | AC23: 13160 | AD23: =G23-SUM(AA23:AC23) -> 14054 | AE23: 15727 | AF23: 12383 | AG23: 18669 | AH23: =H23-SUM(AE23:AG23) -> 26473 | AI23: 24441 | AJ23: 29735 | AK23: 19026 | AL23: =I23-SUM(AI23:AK23) -> 12259 | AM23: 25136 | AN23: 24626 | AO23: 33061 | AP23: =J23-SUM(AM23:AO23) -> 22717 | AQ23: 22039 | AR23: 24916 | AS23: 24846 | AT23: =+K23-AS23-AR23-AQ23 -> 23902 | AU23: 25498 | AV23: 33034 | AW23: 28381 | AX23: =M23-AW23-AV23-AU23 -> 23221 | AY23: 37840 | AZ23: 31872 | BA23: 32816 | BB23: =N23-BA23-AZ23-AY23 -> 37390 | BC23: 34562 | BD23: 37604 | BE23: 39719 | BF23: =O23-BE23-BD23-BC23 -> 39025 | BG23: 42257 | BH23: 39641 | BI23: 43671 | BJ23: =P23-BI23-BH23-BG23 -> 40593 | BK23: 45109 | BL23: 49403 | BM23: 46856 | BN23: =Q23-BM23-BL23-BK23 -> 51631 | BO23: 56137 | BP23: 51858 | BQ23: 66449 | BR23: =R23-BQ23-BP23-BO23 -> 52033 | BS23: 51523 | BT23: 54237 | BU23: 56755 | BV23: =S23-BU23-BT23-BS23 -> 55024 | BW23: 54608 | BX23: 48657 | BY23: 56232 | BZ23: =T23-SUM(BW23:BY23) -> 56056 | CB23: 33928 | CC23: 32893 | CD23: 41471 | CE23: 34671 | CF23: 37914 | CH23: 140732
B24: Finance Income | D24: -3536 | E24: -2643 | F24: -5103 | G24: -11680 | H24: -24788 | I24: -16326 | J24: -28566 | K24: -14988 | L24: -12540 | M24: -14240 | N24: -16098 | O24: 0 | P24: 0 | Q24: 0 | R24: 0 | S24: 0 | T24: 0 | U24: =SUM(BW24:BZ24) -> 0 | W24: -2562 | X24: -3431 | Y24: -867 | Z24: =F24-SUM(W24:Y24) -> 1757 | AA24: -4213 | AB24: -846 | AC24: -2478 | AD24: =G24-SUM(AA24:AC24) -> -4143 | AE24: -6162 | AF24: -3325 | AG24: -8219 | AH24: =H24-SUM(AE24:AG24) -> -7082 | AI24: -5250 | AJ24: -11110 | AK24: -5115 | AL24: =I24-SUM(AI24:AK24) -> 5149 | AM24: -5737 | AN24: -5569 | AO24: -13705 | AP24: =J24-SUM(AM24:AO24) -> -3555 | AQ24: -3765 | AR24: -1650 | AS24: -3964 | AT24: =+K24-AS24-AR24-AQ24 -> -5609 | AU24: -4232 | AV24: -3177 | AW24: -8933 | AX24: =M24-AW24-AV24-AU24 -> 2102 | AY24: -6025 | AZ24: -2789 | BA24: -2970 | BB24: =N24-BA24-AZ24-AY24 -> -4314 | BC24: -4063 | BD24: -346 | BE24: -556 | BF24: =O24-BE24-BD24-BC24 -> 4965 | BG24: -1438 | BH24: -804 | BI24: -79 | BJ24: =P24-BI24-BH24-BG24 -> 2321 | BK24: 0 | BL24: 0 | BM24: 0 | BN24: =Q24-BM24-BL24-BK24 -> 0 | BO24: 0 | BP24: 0 | BQ24: 0 | BR24: =R24-BQ24-BP24-BO24 -> 0 | BS24: 0 | BT24: 0 | BU24: 0 | BV24: =S24-BU24-BT24-BS24 -> 0 | BW24: 0 | BX24: 0 | BY24: 0 | BZ24: =T24-SUM(BW24:BY24) -> 0 | CB24: -2113 | CC24: -2970 | CD24: -4314 | CE24: -3372 | CF24: -54 | CH24: 0
B25: Net foreign exchange and derivative (gain)/loss | D25: 0 | E25: 0 | F25: 0 | G25: 0 | H25: 0 | I25: 0 | J25: 0 | K25: 0 | L25: 0 | M25: 0 | N25: 0 | O25: 0 | P25: 0 | Q25: 0 | R25: 0 | S25: 0 | T25: 0 | U25: =SUM(BW25:BZ25) -> 0 | W25: 0 | X25: 0 | Y25: 0 | Z25: =F25-SUM(W25:Y25) -> 0 | AA25: 0 | AB25: 0 | AC25: 0 | AD25: =G25-SUM(AA25:AC25) -> 0 | AE25: 0 | AF25: 0 | AG25: 0 | AH25: =H25-SUM(AE25:AG25) -> 0 | AI25: 0 | AJ25: 0 | AK25: 0 | AL25: =I25-SUM(AI25:AK25) -> 0 | AM25: 0 | AN25: 0 | AO25: 0 | AP25: =J25-SUM(AM25:AO25) -> 0 | AQ25: 0 | AR25: 0 | AS25: 0 | AT25: =+K25-AS25-AR25-AQ25 -> 0 | AU25: 0 | AV25: 0 | AW25: 0 | AX25: =M25-AW25-AV25-AU25 -> 0 | AY25: 0 | AZ25: 0 | BA25: 0 | BB25: =N25-BA25-AZ25-AY25 -> 0 | BC25: 0 | BD25: 0 | BE25: 0 | BF25: =O25-BE25-BD25-BC25 -> 0 | BG25: 0 | BH25: 0 | BI25: 0 | BJ25: =P25-BI25-BH25-BG25 -> 0 | BK25: 0 | BL25: 0 | BM25: 0 | BN25: =Q25-BM25-BL25-BK25 -> 0 | BO25: 0 | BP25: 0 | BQ25: 0 | BR25: =R25-BQ25-BP25-BO25 -> 0 | BS25: 0 | BT25: 0 | BU25: 0 | BV25: =S25-BU25-BT25-BS25 -> 0 | BW25: 0 | BX25: 0 | BY25: 0 | BZ25: =T25-SUM(BW25:BY25) -> 0 | CB25: 0 | CC25: 0 | CD25: 0 | CE25: 0 | CF25: 0 | CH25: 0
B26: Non-operating income / expenses, (net) | D26: 0 | E26: 0 | F26: 0 | G26: 660 | H26: 1669 | I26: 1024 | J26: 1319 | K26: 141 | L26: 141 | M26: 1894 | N26: 1272 | O26: 0 | P26: 0 | Q26: 0 | R26: 0 | S26: 0 | T26: 0 | U26: =SUM(BW26:BZ26) -> 0 | W26: 0 | X26: 0 | Y26: 0 | Z26: =F26-SUM(W26:Y26) -> 0 | AA26: 0 | AB26: 408 | AC26: 72 | AD26: =G26-SUM(AA26:AC26) -> 180 | AE26: 78 | AF26: 1206 | AG26: 73 | AH26: =H26-SUM(AE26:AG26) -> 312 | AI26: 85 | AJ26: 858 | AK26: 60 | AL26: =I26-SUM(AI26:AK26) -> 21 | AM26: 25 | AN26: 1329 | AO26: -509 | AP26: =J26-SUM(AM26:AO26) -> 474 | AQ26: -357 | AR26: 308 | AS26: 2 | AT26: =+K26-AS26-AR26-AQ26 -> 188 | AU26: 40 | AV26: 1074 | AW26: 721 | AX26: =M26-AW26-AV26-AU26 -> 59 | AY26: 461 | AZ26: 231 | BA26: 211 | BB26: =N26-BA26-AZ26-AY26 -> 369 | BC26: 0 | BD26: 0 | BE26: 0 | BF26: =O26-BE26-BD26-BC26 -> 0 | BG26: 0 | BH26: 0 | BI26: 0 | BJ26: =P26-BI26-BH26-BG26 -> 0 | BK26: 0 | BL26: 0 | BM26: 0 | BN26: =Q26-BM26-BL26-BK26 -> 0 | BO26: 0 | BP26: 0 | BQ26: 0 | BR26: =R26-BQ26-BP26-BO26 -> 0 | BS26: 0 | BT26: 0 | BU26: 0 | BV26: =S26-BU26-BT26-BS26 -> 0 | BW26: 0 | BX26: 0 | BY26: 0 | BZ26: =T26-SUM(BW26:BY26) -> 0 | CB26: 0 | CC26: 0 | CD26: 0 | CE26: 0 | CF26: 0 | CH26: 0
B27: Exceptional items | D27: 0 | E27: 0 | F27: 0 | G27: -538 | H27: 7960 | I27: -21741 | J27: 11697 | K27: 7931 | L27: 7931 | M27: -29288 | N27: 402344 | O27: 159145 | P27: -16986 | Q27: 6698 | R27: 75723 | S27: -72868 | T27: 34175 | U27: =SUM(BW27:BZ27) -> 34175 | W27: 0 | X27: 0 | Y27: 0 | Z27: =F27-SUM(W27:Y27) -> 0 | AA27: -2252 | AB27: 819 | AC27: -674 | AD27: =G27-SUM(AA27:AC27) -> 1569 | AE27: 1820 | AF27: 1750 | AG27: 2921 | AH27: =H27-SUM(AE27:AG27) -> 1469 | AI27: -14314 | AJ27: -6596 | AK27: 3405 | AL27: =I27-SUM(AI27:AK27) -> -4236 | AM27: 3536 | AN27: 66 | AO27: 2040 | AP27: =J27-SUM(AM27:AO27) -> 6055 | AQ27: 503 | AR27: 1786 | AS27: 2395 | AT27: =+K27-AS27-AR27-AQ27 -> 3247 | AU27: 3621 | AV27: 1449 | AW27: -14137 | AX27: =M27-AW27-AV27-AU27 -> -20221 | AY27: 14694 | AZ27: 307110 | BA27: 10500 | BB27: =N27-BA27-AZ27-AY27 -> 70040 | BC27: 117457 | BD27: 493 | BE27: 45599 | BF27: =O27-BE27-BD27-BC27 -> -4404 | BG27: -305 | BH27: -7221 | BI27: -398 | BJ27: =P27-BI27-BH27-BG27 -> -9062 | BK27: 0 | BL27: 0 | BM27: 6698 | BN27: =Q27-BM27-BL27-BK27 -> 0 | BO27: 34163 | BP27: 15703 | BQ27: 1302 | BR27: =R27-BQ27-BP27-BO27 -> 24555 | BS27: -7350 | BT27: 8537 | BU27: -75456 | BV27: =S27-BU27-BT27-BS27 -> 1401 | BW27: 0 | BX27: 0 | BY27: 2568 | BZ27: =T27-SUM(BW27:BY27) -> 31607 | CB27: 14694 | CC27: 10500 | CD27: 68588 | CE27: 117457 | CF27: 493 | CH27: 400892
B28: Profit before tax | D28: =D19-SUM(D21:D27) -> 76782 | E28: =E19-SUM(E21:E27) -> 65183 | F28: =F19-SUM(F21:F27) -> 47852 | G28: =G19-SUM(G21:G27) -> 78643 | H28: =H19-SUM(H21:H27) -> 107702 | I28: =I19-SUM(I21:I27) -> 128463 | J28: =J19-SUM(J21:J27) -> 77233 | K28: =K19-SUM(K21:K27) -> 32670 | ... U28: =U19-SUM(U21:U27) -> 451727 | W28: =W19-SUM(W21:W27) -> 12294 | X28: =X19-SUM(X21:X27) -> 14210 | Y28: =Y19-SUM(Y21:Y27) -> 9032 | Z28: =Z19-SUM(Z21:Z27) -> 12316 | AA28: =AA19-SUM(AA21:AA27) -> 18377 | AB28: =AB19-SUM(AB21:AB27) -> 13649 | AC28: =AC19-SUM(AC21:AC27) -> 22802 | AD28: =AD19-SUM(AD21:AD27) -> 23815 | ... BZ28: =BZ19-SUM(BZ21:BZ27) -> 100447 | CB28: =CB19-SUM(CB21:CB27) -> -29992 | CC28: =CC19-SUM(CC21:CC27) -> -23355 | CD28: =CD19-SUM(CD21:CD27) -> -75544 | CE28: =CE19-SUM(CE21:CE27) -> -121092 | CF28: =CF19-SUM(CF21:CF27) -> -2467 | CH28: =CH19-SUM(CH21:CH27) -> -461304
B29: Income Tax Expense | D29: -17790 | E29: -22602 | F29: -25184 | G29: -48449 | H29: -54047 | I29: -59533 | J29: -34819 | K29: =-18230+7395 -> -10835 | L29: =-18230+7395 -> -10835 | M29: =-19391+53584 -> 34193 | N29: =-23738+145561 -> 121823 | O29: =-20584-68741 -> -89325 | P29: =-30331-11448 -> -41779 | Q29: -42733 | R29: -41210 | S29: =-41121+31949 -> -9172 | T29: =-78812-34687 -> -113499 | U29: =SUM(BW29:BZ29) -> -113499 | W29: -4543 | X29: -7195 | Y29: -6192 | Z29: =F29-SUM(W29:Y29) -> -7254 | AA29: -9684 | AB29: -8634 | AC29: -16569 | AD29: =G29-SUM(AA29:AC29) -> -13562 | AE29: -15326 | AF29: -14765 | AG29: -13145 | AH29: =H29-SUM(AE29:AG29) -> -10811 | AI29: -21781 | AJ29: -13326 | AK29: -13499 | AL29: =I29-SUM(AI29:AK29) -> -10927 | AM29: -10089 | AN29: -11136 | AO29: -11841 | AP29: =J29-SUM(AM29:AO29) -> -1753 | AQ29: -8136 | AR29: -5341 | AS29: -379 | AT29: =+K29-AS29-AR29-AQ29 -> 3021 | AU29: =-7176+18443 -> 11267 | AV29: =-3850+26326 -> 22476 | AW29: =-5331+7155 -> 1824 | AX29: =M29-AW29-AV29-AU29 -> -1374 | AY29: =-7763+13833 -> 6070 | AZ29: =-4281+89320 -> 85039 | BA29: =-7309+17688 -> 10379 | BB29: =N29-BA29-AZ29-AY29 -> 20335 | BC29: =-5086-33089 -> -38175 | BD29: =-6494+977 -> -5517 | BE29: =-5594-37473 -> -43067 | BF29: =O29-BE29-BD29-BC29 -> -2566 | BG29: =-7274-1071 -> -8345 | BH29: =-7370-2938 -> -10308 | BI29: =-7922-1986 -> -9908 | BJ29: =P29-BI29-BH29-BG29 -> -13218 | BK29: -11233 | BL29: =-7953-4911 -> -12864 | BM29: =-6511-4245 -> -10756 | BN29: =Q29-BM29-BL29-BK29 -> -7880 | BO29: =5997-9324 -> -3327 | BP29: =-17574-891 -> -18465 | BQ29: =-7506-4814 -> -12320 | BR29: =R29-BQ29-BP29-BO29 -> -7098 | BS29: =-7883-5195 -> -13078 | BT29: -17440 | BU29: =-11336+3763 -> -7573 | BV29: =S29-BU29-BT29-BS29 -> 28919 | BW29: =-18657-12169 -> -30826 | BX29: =-18514-18201 -> -36715 | BY29: =-20153-17832 -> -37985 | BZ29: =T29-SUM(BW29:BY29) -> -7973 | CB29: =-7763+13833 -> 6070 | CC29: =17623-5986 -> 11637 | CD29: =-3021+24541 -> 21520 | CE29: =-3583-33439 -> -37022 | CF29: =-4949+814 -> -4135 | CH29: =-17932+143056 -> 125124
B30: Net profit/loss | D30: =D28+D29 -> 58992 | E30: =E28+E29 -> 42581 | F30: =F28+F29 -> 22668 | G30: =G28+G29 -> 30194 | H30: =H28+H29 -> 53655 | I30: =I28+I29 -> 68930 | J30: =J28+J29 -> 42414 | K30: =K28+K29 -> 21835 | ... U30: =U28+U29 -> 338228 | W30: =W28+W29 -> 7751 | X30: =X28+X29 -> 7015 | Y30: =Y28+Y29 -> 2840 | Z30: =Z28+Z29 -> 5062 | AA30: =AA28+AA29 -> 8693 | AB30: =AB28+AB29 -> 5015 | AC30: =AC28+AC29 -> 6233 | AD30: =AD28+AD29 -> 10253 | ... BZ30: =BZ28+BZ29 -> 92474 | CB30: =CB28+CB29 -> -23922 | CC30: =CC28+CC29 -> -11718 | CD30: =CD28+CD29 -> -54024 | CE30: =CE28+CE29 -> -158114 | CF30: =CF28+CF29 -> -6602 | CH30: =CH28+CH29 -> -336180
B31: Profit from discontinued operation before tax | O31: 113698 | P31: 0 | Q31: 0 | R31: 0 | S31: 0 | T31: 0 | U31: =SUM(BT31:BW31) -> 0 | CH31: 32839
B32: Tax expense of discontinued operation | O32: 3131 | P32: 0 | Q32: 0 | R32: 0 | S32: 0 | T32: 0 | U32: =SUM(BT32:BW32) -> 0 | CH32: 3301
B33: Profit for the period from discontinued operation | O33: =O31-O32 -> 110567 | P33: =P31-P32 -> 0 | Q33: =Q31-Q32 -> 0 | R33: =R31-R32 -> 0 | S33: =S31-S32 -> 0 | T33: =T31-T32 -> 0 | CH33: =CH31-CH32 -> 29538
B34: % margin | D34: =D30/D7 -> 0.099082439 | E34: =E30/E7 -> 0.062319708 | F34: =F30/F7 -> 0.029475522 | G34: =G30/G7 -> 0.035213266 | H34: =H30/H7 -> 0.058295686 | I34: =I30/I7 -> 0.071406299 | J34: =J30/J7 -> 0.044427313 | K34: =K30/K7 -> 0.026090988 | ... U34: =U30/U7 -> 0.1603183 | W34: =W30/W7 -> 0.041761629 | X34: =X30/X7 -> 0.036160028 | Y34: =Y30/Y7 -> 0.014667571 | Z34: =Z30/Z7 -> 0.025850172 | AA34: =AA30/AA7 -> 0.042898897 | AB34: =AB30/AB7 -> 0.023517694 | AC34: =AC30/AC7 -> 0.028411241 | AD34: =AD30/AD7 -> 0.046144568 | ... BZ34: =BZ30/BZ7 -> 0.16697121 | CB34: =CB30/CB7 -> -0.11535401 | CC34: =CC30/CC7 -> -0.054901704 | CD34: =CD30/CD7 -> -0.23469614 | CE34: =CE30/CE7 -> -0.67888348 | CF34: =CF30/CF7 -> -0.026344352 | CH34: =CH30/CH7 -> -0.39701688
B35: Check | D35: =58992-D30 -> 0 | E35: =42581-E30 -> 0 | F35: =22669-F30 -> 1 | G35: =30194-G30 -> 0 | H35: =53655-H30 -> 0 | I35: =68930-I30 -> 0 | J35: =42414-J30 -> 0 | K35: =21835-K30 -> 0 | L35: =21835-L30 -> 0 | M35: =16875-M30 -> 0 | N35: =-306642-N30 -> 0 | O35: =-123640-O30-O33 -> 0 | P35: =83052-P30-P33 -> 0 | Q35: =122874-Q30-Q33 -> 0 | R35: =85580-R30-R33 -> 0 | S35: =374813-S30-S33 -> 0 | T35: =338228-T30-T33 -> 0 | W35: =7751-W30 -> 0 | X35: =7015-X30 -> 0 | Y35: =2840-Y30 -> 0 | Z35: =F35-SUM(W35:Y35) -> 1 | AA35: =8693-AA30 -> 0 | AB35: =5015-AB30 -> 0 | AC35: =6233-AC30 -> 0 | AD35: =G35-SUM(AA35:AC35) -> 0 | AE35: =11702-AE30 -> 0 | AF35: =13453-AF30 -> 0 | AG35: =15053-AG30 -> 0 | AH35: =H35-SUM(AE35:AG35) -> 0 | AI35: =17541-AI30 -> 0 | AJ35: =16303-AJ30 -> 0 | AK35: =12559-AK30 -> 0 | AL35: =F35-SUM(AI35:AK35) -> 1 | AM35: =14841.1-AM30 -> 0.040353 | AN35: =16151.9-AN30 -> -0.040353 | AO35: =6715-AO30 -> 2.910383e-11 | AP35: =J35-SUM(AM35:AO35) -> -2.910383e-11 | AQ35: =6177.2-AQ30 -> 0.020439746 | AR35: =5861-AR30 -> 0 | AS35: =5607-AS30 -> 0 | AU35: =4796-AU30 -> -0.24858071 | AV35: =2492-AV30 -> 0.4075959 | AW35: =3826-AW30 -> 0.17572117 | AY35: =-23922-AY30 -> 0 | AZ35: =-228301-AZ30 -> 0.15134882 | BA35: =-4648.6-BA30 -> 0.021405443 | BB35: =N35-BA35-AZ35-AY35 -> -0.17275427 | BC35: =-151912-BC30 -> 0 | BD35: =-339-BD30 -> 0 | BE35: =-84600-BE30 -> 0 | BF35: =O35-BE35-BD35-BC35 -> 0 | BG35: =9414-BG30 -> 0 | BH35: =19981-BH30 -> 0 | BI35: =16507-BI30 -> 0 | BJ35: =P35-BI35-BH35-BG35 -> 0 | BK35: =24688-BK30 -> 0 | BL35: =29789-BL30 -> 0 | BM35: =26137-BM30 -> 0 | BN35: =Q35-BM35-BL35-BK35 -> 0 | BO35: =15202-BO30 -> 0 | BP35: =20932-BP30 -> 0 | BQ35: =28764-BQ30 -> 0 | BR35: =W35-BQ35-BP35-BO35 -> 0 | BS35: =47175-BS30+1 -> 0 | BT35: =41534-BT30 -> 0 | BU35: =161346-BU30 -> 0 | BV35: =AA35-BU35-BT35-BS35 -> 0 | BW35: =74218-BW30 -> 0 | BX35: =86508-BX30 -> 0 | BY35: =85028-BY30 -> 0 | BZ35: =92474-BZ30-BZ33 -> 0 | CB35: =-23922-CB30 -> 0 | CC35: =-11718-CC30 -> -1.4551915e-11 | CD35: =-54024.241071274-CD30 -> -0.24107127 | CE35: =-158115.337933-CE30 -> -1.337933 | CF35: =-6601.662067-CF30 -> 0.337933 | CH35: =-306642-CH30-CH33 -> 0
B37: As a % of Sales unless stated otherwise
B38: =B13 -> Network operating expenses | I38: =I13/I7 -> 0.20880826 | J38: =J13/J7 -> 0.21908215 | K38: =K13/K7 -> 0.23601978 | L38: =L13/L7 -> 0.23901606 | M38: =M13/M7 -> 0.27717188 | N38: =N13/N7 -> 0.22582506 | O38: =O13/O7 -> 0.21847364 | P38: =P13/P7 -> 0.21468181 | ... U38: =U13/U7 -> 0.18841291 | AM38: =AM13/AM7 -> 0.21121481 | AN38: =AN13/AN7 -> 0.20661381 | AO38: =AO13/AO7 -> 0.2255546 | AP38: =AP13/AP7 -> 0.23537179 | AQ38: =AQ13/AQ7 -> 0.23504766 | AR38: =AR13/AR7 -> 0.23176853 | AS38: =AS13/AS7 -> 0.23311153 | AT38: =AT13/AT7 -> 0.24483175 | ... BZ38: =BZ13/BZ7 -> 0.18431582 | CB38: =CB13/CB7 -> 0.22488294 | CC38: =CC13/CC7 -> 0.23355479 | CD38: =CD13/CD7 -> 0.22377458 | CE38: =CE13/CE7 -> 0.21881642 | CF38: =CF13/CF7 -> 0.21626949 | CH38: =CH13/CH7 -> 0.23182937
B39: =B14 -> Access Charges | I39: =I14/I7 -> 0.113354 | J39: =J14/J7 -> 0.10766506 | K39: =K14/K7 -> 0.10807536 | L39: =L14/L7 -> 0.10944738 | M39: =M14/M7 -> 0.11577218 | N39: =N14/N7 -> 0.12268246 | O39: =O14/O7 -> 0.10288742 | P39: =P14/P7 -> 0.058011839 | ... U39: =U14/U7 -> 0.026266893 | AM39: =AM14/AM7 -> 0.10585123 | AN39: =AN14/AN7 -> 0.11600801 | AO39: =AO14/AO7 -> 0.10450083 | AP39: =AP14/AP7 -> 0.10376756 | AQ39: =AQ14/AQ7 -> 0.11392607 | AR39: =AR14/AR7 -> 0.11756953 | AS39: =AS14/AS7 -> 0.096163121 | AT39: =AT14/AT7 -> 0.10332938 | ... BZ39: =BZ14/BZ7 -> 0.026973884 | CB39: =CB14/CB7 -> 0.12357568 | CC39: =CC14/CC7 -> 0.12701231 | CD39: =CD14/CD7 -> 0.12281319 | CE39: =CE14/CE7 -> 0.12026895 | CF39: =CF14/CF7 -> 0.11663421 | CH39: =CH14/CH7 -> 0.12682976
B40: =B15 -> License fee / spectrum charges (revenue share) | I40: =I15/I7 -> 0.098338273 | J40: =J15/J7 -> 0.097163142 | K40: =K15/K7 -> 0.090285453 | L40: =L15/L7 -> 0.091431628 | M40: =M15/M7 -> 0.085944328 | N40: =N15/N7 -> 0.082889912 | O40: =O15/O7 -> 0.090526538 | P40: =P15/P7 -> 0.094928308 | ... U40: =U15/U7 -> 0.072866739 | AM40: =AM15/AM7 -> 0.099813479 | AN40: =AN15/AN7 -> 0.097937852 | AO40: =AO15/AO7 -> 0.095424607 | AP40: =AP15/AP7 -> 0.095055301 | AQ40: =AQ15/AQ7 -> 0.094816947 | AR40: =AR15/AR7 -> 0.09055467 | AS40: =AS15/AS7 -> 0.086334688 | AT40: =AT15/AT7 -> 0.089007502 | ... BZ40: =BZ15/BZ7 -> 0.071895448 | CB40: =CB15/CB7 -> 0.088683039 | CC40: =CC15/CC7 -> 0.083748758 | CD40: =CD15/CD7 -> 0.089357783 | CE40: =CE15/CE7 -> 0.089161582 | CF40: =CF15/CF7 -> 0.089200492 | CH40: =CH15/CH7 -> 0.087185937
B41: =B16 -> Employee benefits | I41: =I16/I7 -> 0.050872197 | J41: =J16/J7 -> 0.045074648 | K41: =K16/K7 -> 0.047522999 | L41: =L16/L7 -> 0.048126304 | M41: =M16/M7 -> 0.047010282 | N41: =N16/N7 -> 0.043491472 | O41: =O16/O7 -> 0.040894174 | P41: =P16/P7 -> 0.038038764 | ... U41: =U16/U7 -> 0.035934964 | AM41: =AM16/AM7 -> 0.043623887 | AN41: =AN16/AN7 -> 0.044044475 | AO41: =AO16/AO7 -> 0.045132565 | AP41: =AP16/AP7 -> 0.047860458 | AQ41: =AQ16/AQ7 -> 0.046210738 | AR41: =AR16/AR7 -> 0.046328908 | AS41: =AS16/AS7 -> 0.047178447 | AT41: =AT16/AT7 -> 0 | ... BZ41: =BZ16/BZ7 -> 0.036619408 | CB41: =CB16/CB7 -> 0.041667671 | CC41: =CC16/CC7 -> 0.041764276 | CD41: =CD16/CD7 -> 0.041357679 | CE41: =CE16/CE7 -> 0.046049214 | CF41: =CF16/CF7 -> 0.040589935 | CH41: =CH16/CH7 -> 0.041495574
B42: =B17 -> Sales and marketing expenses | I42: =I17/I7 -> 0.085370566 | J42: =J17/J7 -> 0.069899642 | K42: =K17/K7 -> 0.066635679 | L42: =L17/L7 -> 0.054786614 | M42: =M17/M7 -> 0.051097918 | N42: =N17/N7 -> 0.039211094 | O42: =O17/O7 -> 0.037776373 | P42: =P17/P7 -> 0.045505286 | ... U42: =U17/U7 -> 0.062127914 | AM42: =AM17/AM7 -> 0.077913791 | AN42: =AN17/AN7 -> 0.073066654 | AO42: =AO17/AO7 -> 0.070921069 | AP42: =AP17/AP7 -> 0.055919868 | AQ42: =AQ17/AQ7 -> 0.069974178 | AR42: =AR17/AR7 -> 0.064765876 | AS42: =AS17/AS7 -> 0.078263266 | AT42: =AT17/AT7 -> 0.052943064 | ... BZ42: =BZ17/BZ7 -> 0.063775658 | CB42: =CB17/CB7 -> 0.040438039 | CC42: =CC17/CC7 -> 0.042068817 | CD42: =CD17/CD7 -> 0.040553984 | CE42: =CE17/CE7 -> 0.031249061 | CF42: =CF17/CF7 -> 0.034803914 | CH42: =CH17/CH7 -> 0.040431525
B43: =B18 -> Other expenses | I43: =I18/I7 -> 0.09120593 | J43: =J18/J7 -> 0.091046976 | K43: =K18/K7 -> 0.092040785 | L43: =L18/L7 -> 0.093209243 | M43: =M18/M7 -> 0.10338425 | N43: =N18/N7 -> 0.067692114 | O43: =O18/O7 -> 0.058501746 | P43: =P18/P7 -> 0.055179503 | ... U43: =U18/U7 -> 0.047139726 | AM43: =AM18/AM7 -> 0.087832736 | AN43: =AN18/AN7 -> 0.079379111 | AO43: =AO18/AO7 -> 0.095010339 | AP43: =AP18/AP7 -> 0.10368706 | AQ43: =AQ18/AQ7 -> 0.086696119 | AR43: =AR18/AR7 -> 0.085232517 | AS43: =AS18/AS7 -> 0.091364563 | AT43: =AT18/AT7 -> 0.10626903 | ... BZ43: =BZ18/BZ7 -> 0.047806916 | CB43: =CB18/CB7 -> 0.083696999 | CC43: =CC18/CC7 -> 0.063466332 | CD43: =CD18/CD7 -> 0.064330305 | CE43: =CE18/CE7 -> 0.068650898 | CF43: =CF18/CF7 -> 0.060781153 | CH43: =CH18/CH7 -> 0.067707097
B44: =B19 -> Profit from operating activities before D&A and exceptional items | D44: =D19/D7 -> 0.33712417 | E44: =E19/E7 -> 0.34704296 | F44: =F19/F7 -> 0.30242447 | G44: =G19/G7 -> 0.3247145 | H44: =H19/H7 -> 0.34103112 | I44: =I19/I7 -> 0.35295306 | J44: =J19/J7 -> 0.37133164 | K44: =K19/K7 -> 0.36239289 | ... U44: =U19/U7 -> 0.5806047 | W44: =W19/W7 -> 0.29555875 | X44: =X19/X7 -> 0.30602775 | Y44: =Y19/Y7 -> 0.29825267 | Z44: =Z19/Z7 -> 0.30948712 | AA44: =AA19/AA7 -> 0.32298285 | AB44: =AB19/AB7 -> 0.32230261 | AC44: =AC19/AC7 -> 0.32365932 | AD44: =AD19/AD7 -> 0.32965035 | ... BZ44: =BZ19/BZ7 -> 0.58447508 | CB44: =CB19/CB7 -> 0.40106761 | CC44: =CC19/CC7 -> 0.40883918 | CD44: =CD19/CD7 -> 0.43468571 | CE44: =CE19/CE7 -> 0.42878366 | CF44: =CF19/CF7 -> 0.44561938 | CH44: =CH19/CH7 -> 0.42265682
B45: Finance costs as a % of total debt | D45: =D23/D124 -> 0.041103798 | E45: =E23/E124 -> 0.059151126 | F45: =F23/F124 -> 0.067709777 | G45: =G23/G124 -> 0.07902798 | H45: =H23/H124 -> 0.090788869 | I45: =I23/I124 -> 0.085075946 | J45: =J23/J124 -> 0.098242452 | K45: =K23/K124 -> 0.08382676 | ... U45: =U23/U124 -> 0.11025131 | Z45: =SUM(W23:Z23)/Z124 -> 0.067709777 | AA45: =SUM(X23:AA23)/AA124 -> 0.068686974 | AB45: =SUM(Y23:AB23)/AB124 -> 0.07444955 | AC45: =SUM(Z23:AC23)/AC124 -> 0.07557356 | AD45: =SUM(AA23:AD23)/AD124 -> 0.07902798 | AE45: =SUM(AB23:AE23)/AE124 -> 0.083568771 | AF45: =SUM(AC23:AF23)/AF124 -> 0.073840749 | AG45: =SUM(AD23:AG23)/AG124 -> 0.076110511 | ... BZ45: =SUM(BW23:BZ23)/BZ124 -> 0.11025131 | CH45: =CH23/CH124 -> 0.09355127
B46: Finance income as a % of end of period cash | D46: =-D24/D128 -> 0.20564117 | E46: =-E24/E128 -> 0.066343692 | F46: =-F24/F128 -> 0.060897895 | G46: =-G24/G128 -> 0.075565447 | H46: =-H24/H128 -> 0.17907558 | I46: =-I24/I128 -> 0.14635983 | J46: =-J24/J128 -> 0.27538006 | K46: =-K24/K128 -> 0.12428582 | ... U46: =-U24/U128 -> 0 | Z46: =-SUM(W24:Z24)/Z128 -> 0.060897895 | AA46: =-SUM(X24:AA24)/AA128 -> 0.042900517 | AB46: =-SUM(Y24:AB24)/AB128 -> 0.03183974 | AC46: =-SUM(Z24:AC24)/AC128 -> 0.036883415 | AD46: =-SUM(AA24:AD24)/AD128 -> 0.075565447 | AE46: =-SUM(AB24:AE24)/AE128 -> 0.097833577 | AF46: =-SUM(AC24:AF24)/AF128 -> 0.12675879 | AG46: =-SUM(AD24:AG24)/AG128 -> 0.16693408 | ... BZ46: =-SUM(BW24:BZ24)/BZ128 -> 0 | CH46: =-CH24/CH128 -> 0
B47: Income Tax Expense as a % PBT | D47: =-D29/D28 -> 0.23169493 | E47: =-E29/E28 -> 0.34674685 | F47: =-F29/F28 -> 0.52628939 | G47: =-G29/G28 -> 0.61606246 | H47: =-H29/H28 -> 0.50181984 | I47: =-I29/I28 -> 0.46342527 | J47: =-J29/J28 -> 0.4508306 | K47: =-K29/K28 -> 0.33164983 | ... U47: =-U29/U28 -> 0.25125574 | W47: =-W29/W28 -> 0.36952985 | X47: =-X29/X28 -> 0.50633357 | Y47: =-Y29/Y28 -> 0.68556244 | Z47: =-Z29/Z28 -> 0.58898993 | AA47: =-AA29/AA28 -> 0.52696305 | AB47: =-AB29/AB28 -> 0.63257381 | AC47: =-AC29/AC28 -> 0.72664679 | AD47: =-AD29/AD28 -> 0.56947302 | ... BZ47: =-BZ29/BZ28 -> 0.079375193 | CB47: =-CB29/CB28 -> 0.2023873 | CC47: =-CC29/CC28 -> 0.4982659 | CD47: =-CD29/CD28 -> 0.2848671 | CE47: =-CE29/CE28 -> -0.30573448 | CF47: =-CF29/CF28 -> -1.6761248 | CH47: =-CH29/CH28 -> 0.27123979
B48: LTM Cash interest paid: % of debt | D48: =D101/D124 -> 0.035016629 | E48: =E101/E124 -> 0.046871197 | F48: =F101/F124 -> 0.051454756 | G48: =G101/G124 -> 0.049501042 | H48: =H101/H124 -> 0.041999705 | I48: =I101/I124 -> 0.032741811 | J48: =J101/J124 -> 0.054516463 | K48: =K101/K124 -> 0.038575743 | ... U48: =U101/U124 -> 0.076147278 | Z48: =Z101/Z124 -> 0.051454756 | AA48: =AA101/AA124 -> 0.046589018 | AB48: =AB101/AB124 -> 0.050146621 | AC48: =AC101/AC124 -> 0.04949123 | AD48: =AD101/AD124 -> 0.049501042 | AE48: =AE101/AE124 -> 0.051649736 | AF48: =AF101/AF124 -> 0.045502473 | AG48: =AG101/AG124 -> 0.039497192 | ... BZ48: =BZ101/BZ124 -> 0.076147278 | CH48: =CH101/CH124 -> 0.073117591
B49: Working capital/sales | D49: =D113/D97 -> -0.30639343 | E49: =E113/E97 -> -0.24510505 | F49: =F113/F97 -> -0.24818319 | G49: =G113/G97 -> -0.25635808 | H49: =H113/H97 -> -0.29421903 | I49: =I113/I97 -> -0.32605838 | J49: =J113/J97 -> -0.2308291 | K49: =K113/K97 -> -0.25990062 | ... P49: =P113/P97 -> -0.21218522 | Q49: =Q76/Q7 -> -0.022365191 | R49: =R76/R7 -> 0.016092555 | S49: =S76/S7 -> 0.048450966 | T49: =T76/T7 -> 0.03414753 | U49: =U76/U7 -> 0.03414753 | Z49: =Z113/Z97 -> -0.24818319 | AA49: =AA113/AA97 -> -0.28261502 | AB49: =AB113/AB97 -> -0.27782605 | AC49: =AC113/AC97 -> -0.2664355 | AD49: =AD113/AD97 -> -0.25635808 | AE49: =AE113/AE97 -> -0.27296623 | AF49: =AF113/AF97 -> -0.28911047 | AG49: =AG113/AG97 -> -0.29396601 | ... BQ49: =BQ113/BQ97 -> -0.20878036 | BR49: =BR76/BR7 -> -0.037381214 | BS49: =BS76/BS7 -> 0.063346872 | BT49: =BT76/BT7 -> 0.084127378 | BU49: =BU76/BU7 -> 0.04721323 | BV49: =BV76/BV7 -> 0.0067319461 | BW49: =BW76/BW7 -> 0.08151007 | BX49: =BX76/BX7 -> 0.036948609 | BY49: =BY76/BY7 -> 0.062639862 | BZ49: =BZ76/BZ7 -> -0.03856043 | CH49: =CH113/CH97 -> -0.23682611
B51: EBITDA
B52: =B19 -> Profit from operating activities before D&A and exceptional items | D52: =D19 -> 200718 | E52: =E19 -> 237123 | F52: =F19 -> 232578 | G52: =G19 -> 278430 | H52: =H19 -> 313883 | I52: =I19 -> 340713 | J52: =J19 -> 354504 | K52: =K19 -> 303279 | ... U52: =U19 -> 1224918 | W52: =W19 -> 54856 | X52: =X19 -> 59369 | Y52: =Y19 -> 57749 | Z52: =Z19 -> 60604 | AA52: =AA19 -> 65449 | AB52: =AB19 -> 68729 | AC52: =AC19 -> 71006 | AD52: =AD19 -> 73246 | ... AG52: =AG19 -> 77857 | AH52: =H52-SUM(AE52:AG52) -> 81695 | AI52: =AI19 -> 82562 | AJ52: =AJ19 -> 82502 | AK52: =AK19 -> 84512 | AL52: =I52-SUM(AI52:AK52) -> 91137 | AM52: =AM19 -> 95744.06 | AN52: =AN19 -> 94602.94 | AO52: =AO19 -> 85097 | AP52: =AP19 -> 79060 | AQ52: =AQ19 -> 78070.18 | AR52: =AR19 -> 79773 | AS52: =AS19 -> 75384 | AT52: =AT19 -> 80000.82 | ... BZ52: =BZ19 -> 323701 | CB52: =CB19 -> 83173 | CC52: =CC19 -> 87261 | CD52: =CD19 -> 100059 | CE52: =CE19 -> 99865 | CF52: =CF19 -> 111674 | CH52: =CH19 -> 357891
B54: EBITDA | D54: =D52+D53 -> 200718 | E54: =E52+E53 -> 237123 | F54: =F52+F53 -> 232578 | G54: =G52+G53 -> 278430 | H54: =H52+H53 -> 313883 | I54: =I52+I53 -> 340713 | J54: =J52+J53 -> 354504 | K54: =K52+K53 -> 303279 | ... U54: =U52+U53 -> 1224918 | W54: =W52+W53 -> 54856 | X54: =X52+X53 -> 59369 | Y54: =Y52+Y53 -> 57749 | Z54: =Z52+Z53 -> 60604 | AA54: =AA52+AA53 -> 65449 | AB54: =AB52+AB53 -> 68729 | AC54: =AC52+AC53 -> 71006 | AD54: =AD52+AD53 -> 73246 | ... BZ54: =BZ52+BZ53 -> 323701 | CB54: =CB52+CB53 -> 83173 | CC54: =CC52+CC53 -> 87261 | CD54: =CD52+CD53 -> 100059 | CE54: =CE52+CE53 -> 99865 | CF54: =CF52+CF53 -> 111674 | CH54: =CH52+CH53 -> 357891
B55: % growth | F55: =(F54-E54)/E54 -> -0.019167268 | G55: =(G54-F54)/F54 -> 0.19714676 | H55: =(H54-G54)/G54 -> 0.12733182 | I55: =(I54-H54)/H54 -> 0.08547771 | J55: =(J54-I54)/I54 -> 0.040476882 | K55: =(K54-J54)/J54 -> -0.14449766 | L55: =L54/J54-1 -> -0.14449766 | M55: =(M54-L54)/L54 -> -0.13907326 | N55: =(N54-M54)/M54 -> 0.41455988 | O55: =(O54-N54)/N54 -> 0.24584736 | P55: =(P54-O54)/O54 -> 0.26195438 | Q55: =(Q54-P54)/P54 -> 0.24353949 | R55: =(R54-Q54)/Q54 -> 0.1041004 | S55: =(S54-R54)/R54 -> 0.18821306 | T55: =(T54-S54)/S54 -> 0.2930228 | AA55: =AA54/W54-1 -> 0.19310559 | AB55: =AB54/X54-1 -> 0.15765804 | AC55: =AC54/Y54-1 -> 0.22956242 | AD55: =AD54/Z54-1 -> 0.20860009 | AE55: =AE54/AA54-1 -> 0.18073615 | AF55: =AF54/AB54-1 -> 0.12111336 | AG55: =AG54/AC54-1 -> 0.096484804 | AH55: =AH54/AD54-1 -> 0.11535101 | ... BZ55: =BZ54/BV54-1 -> 0.17732573 | CH55: =(CH54-M54)/M54 -> 0.37069946
B56: % margin | D56: =D54/D10 -> 0.336765 | E56: =E54/E10 -> 0.34676383 | F56: =F54/F10 -> 0.30225743 | G56: =G54/G10 -> 0.32427052 | H56: =H54/H10 -> 0.3406769 | I56: =I54/I10 -> 0.35263488 | J56: =J54/J10 -> 0.37086314 | K56: =K54/K10 -> 0.36131871 | ... U56: =U54/U10 -> 0.57295357 | W56: =W54/W10 -> 0.29539641 | X56: =X54/X10 -> 0.30589215 | Y56: =Y54/Y10 -> 0.2980464 | Z56: =Z54/Z10 -> 0.30932442 | AA56: =AA54/AA10 -> 0.32241643 | AB56: =AB54/AB10 -> 0.32202475 | AC56: =AC54/AC10 -> 0.32333213 | AD56: =AD54/AD10 -> 0.32904023 | ... BZ56: =BZ54/BZ10 -> 0.57534877 | CB56: =CB54/CB10 -> 0.39946497 | CC56: =CC54/CC10 -> 0.40865346 | CD56: =CD54/CD10 -> 0.42747286 | CE56: =CE54/CE10 -> 0.42750977 | CF56: =CF54/CF10 -> 0.44388885 | CH56: =CH54/CH10 -> 0.41512802
B58: Adjustment | D58: =D59-D54 -> 0 | E58: =E59-E54 -> -14590 | F58: =F59-F54 -> 762 | G58: =G59-G54 -> 0 | H58: =H59-H54 -> 634 | I58: =I59-I54 -> 969 | J58: =J59-J54 -> 1704 | K58: =K59-K54 -> 1200 | ... U58: =U59-U54 -> -12242 | W58: =W59-W54 -> 0 | X58: =X59-X54 -> 0 | Y58: =Y59-Y54 -> 0 | Z58: =Z59-Z54 -> 762 | AA58: =AA59-AA54 -> 0 | AB58: =AB59-AB54 -> 0 | AC58: =AC59-AC54 -> 0 | AD58: =AD59-AD54 -> 0 | ... AO58: =AO59-AO54 -> 607.88389 | AP58: =J58-SUM(AM58:AO58) -> 868.42594 | AQ58: =AQ59-AQ54 -> 160.42562 | AR58: =AR59-AR54 -> 263.77915 | AS58: =AS59-AS54 -> 487 | AT58: =AT59-AT54 -> -9660.2048 | AU58: =AU59-AU54 -> 114.75142 | AV58: =AV59-AV54 -> 304.4076 | AW58: =AW59-AW54 -> 214.17572 | AX58: =AX59-AX54 -> 1202.6653 | ... BZ58: =BZ59-BZ54 -> -3319 | CB58: =CB59-CB54 -> 1753.4013 | CC58: =CC59-CC54 -> 857.97165 | CD58: =CD59-CD54 -> -2447.3792 | CE58: =CE59-CE54 -> 1321 | CF58: =CF59-CF54 -> 919.25667 | CH58: =CH59-CH54 -> -10195
B59: Adj. EBITDA | D59: 200718 | E59: 222533 | F59: 233340 | G59: 278430 | H59: 314517 | I59: 341682 | J59: 356208 | K59: 304479 | L59: 304479 | M59: 262937 | N59: 371053 | O59: 461387 | P59: 581103 | Q59: 717330 | R59: 889064 | S59: 1049994 | T59: 1212676 | U59: =SUM(BW59:BZ59) -> 1212676 | W59: 54856 | X59: 59369 | Y59: 57749 | Z59: =F59-SUM(W59:Y59) -> 61366 | AA59: 65449 | AB59: 68729 | AC59: 71006 | AD59: =G59-SUM(AA59:AC59) -> 73246 | AE59: 73186 | AF59: 77668.995 | AG59: 77494.401 | AH59: =H59-SUM(AE59:AG59) -> 86167.604 | AI59: 82616.865 | AJ59: 82653.02 | AK59: 84747.507 | AL59: =I59-SUM(AI59:AK59) -> 91664.608 | AM59: 95913.042 | AN59: 94661.648 | AO59: 85704.884 | AP59: =J59-SUM(AM59:AO59) -> 79928.426 | AQ59: 78230.605 | AR59: 80036.779 | AS59: 75871 | AT59: =+K59-AS59-AR59-AQ59 -> 70340.616 | AU59: 68370 | AV59: 63433 | AW59: 63069 | AX59: =M59-AW59-AV59-AU59 -> 68065 | AY59: 84926.401 | AZ59: 89362.531 | BA59: 93500.972 | BB59: =N59-BA59-AZ59-AY59 -> 103263.1 | BC59: 106392 | BD59: 118483 | BE59: 121777 | BF59: =O59-BE59-BD59-BC59 -> 114735 | BG59: 131894 | BH59: 140177 | BI59: 149047 | BJ59: =P59-BI59-BH59-BG59 -> 159985 | BK59: 166044 | BL59: 177212 | BM59: 186007 | BN59: =Q59-BM59-BL59-BK59 -> 188067 | BO59: 197461 | BP59: 196650 | BQ59: 200442.64 | BR59: =R59-BQ59-BP59-BO59 -> 294510.36 | BS59: 230259 | BT59: 255125 | BU59: 290567 | BV59: =S59-BU59-BT59-BS59 -> 274043 | BW59: 281668 | BX59: 299190 | BY59: 311436 | BZ59: =T59-SUM(BW59:BY59) -> 320382 | CB59: 84926.401 | CC59: 88118.972 | CD59: 97611.621 | CE59: 101186 | CF59: 112593.26 | CH59: 347696
B60: % growth | C60: =+C59/B59-1 -> #VALUE! | F60: =(F59-E59)/E59 -> 0.048563584 | G60: =(G59-F59)/F59 -> 0.19323734 | H60: =(H59-G59)/G59 -> 0.12960888 | I60: =(I59-H59)/H59 -> 0.08637053 | J60: =(J59-I59)/I59 -> 0.042513214 | K60: =(K59-J59)/J59 -> -0.14522133 | L60: =(L59-J59)/J59 -> -0.14522133 | M60: =(M59-L59)/L59 -> -0.13643634 | N60: =(N59-M59)/M59 -> 0.41118595 | O60: =(O59-N59)/N59 -> 0.24345309 | P60: =(P59-O59)/O59 -> 0.25946982 | Q60: =(Q59-P59)/P59 -> 0.23442832 | R60: =(R59-Q59)/Q59 -> 0.23940725 | S60: =(S59-R59)/R59 -> 0.18101059 | T60: =(T59-S59)/S59 -> 0.15493612 | AQ60: =AQ59/AM59-1 -> -0.18435905 | AR60: =AR59/AN59-1 -> -0.15449624 | AS60: =AS59/AO59-1 -> -0.11474123 | AT60: =AT59/AP59-1 -> -0.11995495 | AU60: =AU59/AQ59-1 -> -0.12604536 | AV60: =AV59/AR59-1 -> -0.20745187 | AW60: =AW59/AS59-1 -> -0.16873377 | AX60: =AX59/AT59-1 -> -0.032351376 | ... BF60: =BF59/BB59-1 -> 0.11109394 | BG60: =BG59/CE59-1 -> 0.30348072 | BH60: =BH59/CF59-1 -> 0.24498575 | BI60: =BI59/BE59-1 -> 0.22393391 | BJ60: =BJ59/BF59-1 -> 0.39438707 | BK60: =BK59/BG59-1 -> 0.25892004 | BL60: =BL59/BH59-1 -> 0.26420169 | BM60: =BM59/BI59-1 -> 0.24797547 | BN60: =BN59/BJ59-1 -> 0.17552896 | BO60: =BO59/BK59-1 -> 0.18920888 | BP60: =BP59/BL59-1 -> 0.10968783 | ... BZ60: =BZ59/BV59-1 -> 0.1690939 | CB60: =CB59/AU59-1 -> 0.24215886 | CC60: =CC59/AY59-1 -> 0.037592202 | CD60: =CD59/AX59-1 -> 0.43409419 | CE60: =CE59/AW59-1 -> 0.60436982 | CF60: =CF59/AV59-1 -> 0.77499498 | CH60: =(CH59-M59)/M59 -> 0.32235478
B61: % margin | D61: =D59/D10 -> 0.336765 | E61: =E59/E10 -> 0.32542771 | F61: =F59/F10 -> 0.30324772 | G61: =G59/G10 -> 0.32427052 | H61: =H59/H10 -> 0.34136502 | I61: =I59/I10 -> 0.35363779 | J61: =J59/J10 -> 0.37264578 | K61: =K59/K10 -> 0.36274836 | ... U61: =U59/U10 -> 0.56722739 | W61: =W59/W10 -> 0.29539641 | X61: =X59/X10 -> 0.30589215 | Y61: =Y59/Y10 -> 0.2980464 | Z61: =Z59/Z10 -> 0.31321368 | AA61: =AA59/AA10 -> 0.32241643 | AB61: =AB59/AB10 -> 0.32202475 | AC61: =AC59/AC10 -> 0.32333213 | AD61: =AD59/AD10 -> 0.32904023 | ... BZ61: =BZ59/BZ10 -> 0.56944955 | CB61: =CB59/CB10 -> 0.40788624 | CC61: =CC59/CC10 -> 0.41267144 | CD61: =CD59/CD10 -> 0.41701715 | CE61: =CE59/CE10 -> 0.43316481 | CF61: =CF59/CF10 -> 0.44754277 | CH61: =CH59/CH10 -> 0.40330255
B62: Rent | C62: 15.555 | D62: 40590 | E62: 45361 | F62: 49925 | G62: 53825 | H62: 57451 | I62: 63941 | J62: 71059 | K62: 66386 | L62: =K62 -> 66386 | M62: 78255 | W62: =$F$62/4 -> 12481.25 | X62: =$F$62/4 -> 12481.25 | Y62: =$F$62/4 -> 12481.25 | Z62: =$F$62/4 -> 12481.25 | AA62: =$G$62/4 -> 13456.25 | AB62: =$G$62/4 -> 13456.25 | AC62: =$G$62/4 -> 13456.25 | AD62: =$G$62/4 -> 13456.25 | AE62: =$H$62/4 -> 14362.75 | AF62: =$H$62/4 -> 14362.75 | AG62: =$H$62/4 -> 14362.75 | AH62: =$H$62/4 -> 14362.75 | AI62: =$I$62/4 -> 15985.25 | AJ62: =$I$62/4 -> 15985.25 | AK62: =$I$62/4 -> 15985.25 | AL62: =$I$62/4 -> 15985.25 | AM62: =$J$62/4 -> 17764.75 | AN62: =$J$62/4 -> 17764.75 | AO62: =$J$62/4 -> 17764.75 | AP62: =$J$62/4 -> 17764.75 | AQ62: =$K$62/4 -> 16596.5 | AR62: =$K$62/4 -> 16596.5 | AS62: =$K$62/4 -> 16596.5 | AT62: =$K$62/4 -> 16596.5 | AU62: =$M$62/4 -> 19563.75 | AV62: =$M$62/4 -> 19563.75 | AW62: =$M$62/4 -> 19563.75 | AX62: =$M$62/4 -> 19563.75
B63: Adj. EBITDAR | C63: =C59+C62 -> 15.555 | D63: =D62+D59 -> 241308 | E63: =E62+E59 -> 267894 | F63: =F62+F59 -> 283265 | G63: =G62+G59 -> 332255 | H63: =H62+H59 -> 371968 | I63: =I62+I59 -> 405623 | J63: =J62+J59 -> 427267 | K63: =K62+K59 -> 370865 | ... M63: =M62+M59 -> 341192 | W63: =W59+W62 -> 67337.25 | X63: =X59+X62 -> 71850.25 | Y63: =Y59+Y62 -> 70230.25 | Z63: =Z59+Z62 -> 73847.25 | AA63: =AA59+AA62 -> 78905.25 | AB63: =AB59+AB62 -> 82185.25 | AC63: =AC59+AC62 -> 84462.25 | AD63: =AD59+AD62 -> 86702.25 | ... AX63: =AX59+AX62 -> 87628.75
B64: rent % of sales | C64: =C62/C18 -> #DIV/0! | D64: =D62/D7 -> 0.068174604 | E64: =E62/E7 -> 0.066388396 | F64: =F62/F7 -> 0.064918185 | G64: =G62/G7 -> 0.062772539 | H64: =H62/H7 -> 0.062420007 | I64: =I62/I7 -> 0.06623807 | J64: =J62/J7 -> 0.074432037 | K64: =K62/K7 -> 0.079325685 | ... M64: =M62/M7 -> 0.096873986 | W64: =W62/W7 -> 0.067247752 | X64: =X62/X7 -> 0.064336757 | Y64: =Y62/Y7 -> 0.064461135 | Z64: =Z62/Z7 -> 0.063738138 | AA64: =AA62/AA7 -> 0.066404957 | AB64: =AB62/AB7 -> 0.063102686 | AC64: =AC62/AC7 -> 0.061336235 | AD64: =AD62/AD7 -> 0.060561089 | ... AX64: =AX62/AX7 -> 0.094959764
B65: Depreciation | D65: 86980 | E65: 105426 | F65: 121835 | G65: 132118 | H65: 128932 | I65: 135280 | J65: 142585 | K65: 132963 | L65: =K65 -> 132963 | M65: 213475
B66: Amortisation | D66: 15086 | E66: 28255 | F66: 26313 | G66: 24378 | H66: 26379 | I66: 39218 | J66: 55145 | K66: 59468 | L66: =K66 -> 59468
B68: Comparable revenue | D68: =D7 -> 595383 | E68: =E7 -> 683267 | F68: =F7 -> 769044.92 | G68: =G7 -> 857460.94 | H68: =H7 -> 920394 | I68: =I7 -> 965321 | J68: =J7 -> 954683 | K68: =K7 -> 836879 | ... M68: =M7 -> 807802 | W68: =W7 -> 185601 | X68: =X7 -> 193998.74 | Y68: =Y7 -> 193624.42 | Z68: =Z7 -> 195820.75 | AA68: =AA7 -> 202639.24 | AB68: =AB7 -> 213243.7 | AC68: =AC7 -> 219385 | AD68: =AD7 -> 222193 | ... AX68: =AX7 -> 206021.47 | AY68: 207114
B69: % growth | C69: =+C68/B68-1 -> #VALUE! | E69: =E68/D68-1 -> 0.14760919 | F69: =F68/E68-1 -> 0.12554084 | G69: =G68/F68-1 -> 0.11496861 | H69: =H68/G68-1 -> 0.073394669 | I69: =I68/H68-1 -> 0.048812791 | J69: =J68/I68-1 -> -0.011020168 | K69: =K68/J68-1 -> -0.12339593 | L69: =L68/J68-1 -> -0.13438492 | M69: =M68/L68-1 -> -0.022490646 | AM69: =AM68/AI68-1 -> 0.079236531 | AN69: =AN68/AJ68-1 -> 0.034225972 | AO69: =AO68/AK68-1 -> -0.030341687 | AP69: =AP68/AL68-1 -> -0.12119585 | AQ69: =AQ68/AM68-1 -> -0.14046543 | AR69: =AR68/AN68-1 -> -0.11660954 | AS69: =AS68/AO68-1 -> -0.12929117 | AT69: =AT68/AP68-1 -> -0.10487084 | ... AY69: =AY68/AU68-1 -> 0.046071045
B70: Comparable EBITDA | D70: =D59 -> 200718 | E70: =E59 -> 222533 | F70: =F59 -> 233340 | G70: =G59 -> 278430 | H70: =H59 -> 314517 | I70: =I59 -> 341682 | J70: =J59 -> 356208 | K70: =K59 -> 304479 | ... M70: =M59 -> 262937 | AI70: =AI59 -> 82616.865 | AJ70: =AJ59 -> 82653.02 | AK70: =AK59 -> 84747.507 | AL70: =AL59 -> 91664.608 | AM70: =AM59 -> 95913.042 | AN70: =AN59 -> 94661.648 | AO70: =AO59 -> 85704.884 | AP70: =AP59 -> 79928.426 | ... AX70: =AX59 -> 68065 | AY70: 69804
B71: % growth | C71: =+C70/B70-1 -> #VALUE! | E71: =E70/D70-1 -> 0.10868482 | F71: =F70/E70-1 -> 0.048563584 | G71: =G70/F70-1 -> 0.19323734 | H71: =H70/G70-1 -> 0.12960888 | I71: =I70/H70-1 -> 0.08637053 | J71: =J70/I70-1 -> 0.042513214 | K71: =K70/J70-1 -> -0.14522133 | L71: =L70/J70-1 -> -0.14522133 | M71: =M70/L70-1 -> -0.13643634 | AM71: =AM70/AI70-1 -> 0.1609378 | AN71: =AN70/AJ70-1 -> 0.14528965 | AO71: =AO70/AK70-1 -> 0.011296809 | AP71: =AP70/AL70-1 -> -0.12803395 | AQ71: =AQ70/AM70-1 -> -0.18435905 | AR71: =AR70/AN70-1 -> -0.15449624 | AS71: =AS70/AO70-1 -> -0.11474123 | AT71: =AT70/AP70-1 -> -0.11995495 | ... AY71: =AY70/AU70-1 -> 0.020974111
D72: =D70/D68 -> 0.33712417 | E72: =E70/E68 -> 0.32568966 | F72: =F70/F68 -> 0.30341531 | G72: =G70/G68 -> 0.3247145 | H72: =H70/H68 -> 0.34171996 | I72: =I70/I68 -> 0.35395687 | J72: =J70/J68 -> 0.37311652 | K72: =K70/K68 -> 0.36382679 | ... M72: =M70/M68 -> 0.32549684 | W72: =W70/W68 -> 0 | X72: =X70/X68 -> 0 | Y72: =Y70/Y68 -> 0 | Z72: =Z70/Z68 -> 0 | AA72: =AA70/AA68 -> 0 | AB72: =AB70/AB68 -> 0 | AC72: =AC70/AC68 -> 0 | AD72: =AD70/AD68 -> 0 | ... AY72: =AY70/AY68 -> 0.33703178
B74: CASH FLOW
B75: Adj EBITDA | D75: =D59 -> 200718 | E75: =E59 -> 222533 | F75: =F59 -> 233340 | G75: =G59 -> 278430 | H75: =H59 -> 314517 | I75: =I59 -> 341682 | J75: =J59 -> 356208 | K75: =K59 -> 304479 | ... U75: =U59 -> 1212676 | W75: =W59 -> 54856 | X75: =X59 -> 59369 | Y75: =Y59 -> 57749 | Z75: =Z59 -> 61366 | AA75: =AA59 -> 65449 | AB75: =AB59 -> 68729 | AC75: =AC59 -> 71006 | AD75: =AD59 -> 73246 | ... BZ75: =BZ59 -> 320382 | CB75: =CB59 -> 84926.401 | CC75: =CC59 -> 88118.972 | CD75: =CD59 -> 97611.621 | CE75: =CE59 -> 101186 | CF75: =CF59 -> 112593.26 | CH75: =CH59 -> 347696
B76: Working Capital | D76: =-9207-211+16987 -> 7569 | E76: =-14094+1475+23961 -> 11342 | F76: =SUM(W76:Z76) -> 20500 | G76: =SUM(AA76:AD76) -> 18743 | H76: =SUM(AE76:AH76) -> 3057 | I76: =SUM(AI76:AL76) -> 4663 | J76: =SUM(AM76:AP76) -> 21017 | K76: =SUM(AQ76:AT76) -> -1862 | L76: =-24474+15122+15258 -> 5906 | M76: =8427+21580-88203 -> -58196 | N76: =-8925-2477-154562 -> -165964 | O76: =-3954+6902+27485 -> 30433 | P76: =-7131-4877-1181+2736+11655-15674 -> -14472 | Q76: =-5583+12671-1157+6494-11991-31554 -> -31120 | R76: =-14941-771-25398+6398+17332+41516 -> 24136 | S76: =29658+8586-1416+22699+48154-23868 -> 83813 | T76: =-5654+24977+52719 -> 72042 | U76: =SUM(BW76:BZ76) -> 72042 | W76: =-11947+34+25943 -> 14030 | X76: =-9895-53+6255 -> -3693 | Y76: =14450+117-1820 -> 12747 | Z76: =3569+170-6323 -> -2584 | AA76: =6225-269+33574 -> 39530 | AB76: =5217-63-4334 -> 820 | AC76: =-7132+191+522 -> -6419 | AD76: =-2238-6-12944 -> -15188 | AE76: =-12158-378+24367 -> 11831 | AF76: =-5800+472+11350 -> 6022 | AG76: =-5461+37+7968 -> 2544 | AH76: =12275-133-29482 -> -17340 | AI76: =(9338+433-27380)*-1 -> 17609 | AJ76: =1385-361-5659 -> -4635 | AK76: =2001+1413-206 -> 3208 | AL76: =5399-16790-128 -> -11519 | AM76: =(-2532-10565-15)*-1 -> 13112 | AN76: =(916-5562+32)*-1 -> 4614 | AO76: =(-3607-4039-191)*-1 -> 7837 | AP76: =7205-12525+774 -> -4546 | AQ76: =(-292-31941+310)*-1 -> 31923 | AR76: =(343-2851-266)*-1 -> 2774 | AS76: =(10786-9349+113)*-1 -> -1550 | AT76: =-5945-29019-45 -> -35009 | AU76: =4562+3503-25420 -> -17355 | AV76: =182+2363-21551 -> -19006 | AW76: =-1984+11057-16168 -> -7095 | AX76: =M76-AW76-AV76-AU76 -> -14740 | AY76: =91495-87273 -> 4222 | AZ76: =-3801-16497+3019 -> -17279 | BA76: =-907+23325+1225 -> 23643 | BB76: =N76-BA76-AZ76-AY76 -> -176550 | BC76: =126318-106790 -> 19528 | BD76: =7872+3539-26095 -> -14684 | BE76: =-7451+8058+3417 -> 4024 | BF76: =O76-BE76-BD76-BC76 -> 21565 | BG76: =134746-133093 -> 1653 | BH76: =-2534-13297+6259 -> -9572 | BI76: =258+5265+10000 -> 15523 | BJ76: =P76-BI76-BH76-BG76 -> -22076 | BK76: =199430-168219 -> 31211 | BL76: =-3682+8684-49885 -> -44883 | BM76: =-1683+3425+9140 -> 10882 | BN76: =Q76-BM76-BL76-BK76 -> -28330 | BO76: =222866-200987 -> 21879 | BP76: =-4239-5612+9246 -> -605 | BQ76: =-1145-3032+21094 -> 16917 | BR76: =R76-BQ76-BP76-BO76 -> -14055 | BS76: =227209-202816.4 -> 24392.6 | BT76: =256695.4-221805 -> 34890.4 | BU76: =15344+871+5092 -> 21307 | BV76: =S76-BU76-BT76-BS76 -> 3223 | BW76: =323683-283366 -> 40317 | BX76: =316862-297595 -> 19267 | BY76: =4346+3805+25663 -> 33814 | BZ76: =T76-SUM(BW76:BY76) -> -21356 | CB76: =92174-87273 -> 4901 | CC76: =-907.077975738735+23324.7563065251+4041.20815114947 -> 26458.886 | CD76: =7888.18498837911-15629.2352666895-173876.642148957 -> -181617.69 | CE76: =-14736.7192690098+11084.9752554349+23180.0913513218 -> 19528.347 | CF76: =7872+3539-3971 -> 7440 | CH76: =-8925-2477-154562 -> -165964
B77: Taxes | D77: -24388 | E77: -29453 | F77: =SUM(W77:Z77) -> -31294 | G77: =SUM(AA77:AD77) -> -35039 | H77: =SUM(AE77:AH77) -> -46111 | I77: =SUM(AI77:AL77) -> -46836 | J77: =SUM(AM77:AP77) -> -31587 | K77: =SUM(AQ77:AT77) -> -13723 | L77: -13723 | M77: -11706 | N77: -22937 | O77: -22328 | P77: -21754 | Q77: -37915 | R77: -28806 | S77: -44380 | T77: -62839 | U77: =SUM(BW77:BZ77) -> -62839 | W77: -6580 | X77: -9086 | Y77: -7772 | Z77: -7856 | AA77: -5474 | AB77: -9168 | AC77: -9595 | AD77: -10802 | AE77: -6641 | AF77: -11237 | AG77: -13880 | AH77: -14353 | AI77: -10299 | AJ77: -15663 | AK77: -11902 | AL77: -8972 | AM77: -7161.024 | AN77: -11111.044 | AO77: -5462.125 | AP77: -7852.807 | AQ77: -1426 | AR77: -6084 | AS77: -1841 | AT77: -4372 | AU77: -7310 | AV77: -5175 | AW77: 6372 | AX77: =M77-AW77-AV77-AU77 -> -5593 | AY77: -7188 | AZ77: -6189 | BA77: -5412 | BB77: =N77-BA77-AZ77-AY77 -> -4148 | BC77: -10079 | BD77: -3397 | BE77: -5472 | BF77: =O77-BE77-BD77-BC77 -> -3380 | BG77: -12526 | BH77: -3955 | BI77: -6570.5442 | BJ77: =P77-BI77-BH77-BG77 -> 1297.5442 | BK77: -19943 | BL77: -4977 | BM77: -8019.5153 | BN77: =Q77-BM77-BL77-BK77 -> -4975.4847 | BO77: -14769 | BP77: -5326 | BQ77: -3459 | BR77: =R77-BQ77-BP77-BO77 -> -5252 | BS77: -9175.213 | BT77: -7387.8735 | BU77: -14317 | BV77: =S77-BU77-BT77-BS77 -> -13499.913 | BW77: -16785 | BX77: -14848 | BY77: -19805 | BZ77: =T77-SUM(BW77:BY77) -> -11401 | CB77: -7188 | CC77: -5411.5031 | CD77: -4148.2945 | CE77: -10078.911 | CF77: -3397.2241 | CH77: -22937
B78: Cash interest paid | D78: -21595 | E78: -32352 | F78: =SUM(W78:Z78) -> -34339 | G78: =SUM(AA78:AD78) -> -37620 | H78: =SUM(AE78:AH78) -> -33887 | I78: =SUM(AI78:AL78) -> -32890 | J78: =SUM(AM78:AP78) -> -58566 | K78: =SUM(AQ78:AT78) -> -44041 | L78: -44041 | M78: -76171 | N78: -109993 | O78: -71294 | P78: -131588 | Q78: -66893 | R78: -140263 | S78: -175476 | T78: -148876 | U78: =SUM(BW78:BZ78) -> -148876 | W78: -9604 | X78: -7553 | Y78: -11106 | Z78: -6076 | AA78: -9957 | AB78: -10192 | AC78: -10059 | AD78: -7412 | AE78: -9357 | AF78: -7264 | AG78: -7536 | AH78: -9730 | AI78: -9232 | AJ78: -7841 | AK78: -8953 | AL78: -6864 | AM78: -9744 | AN78: -6411 | AO78: -9420 | AP78: -32991 | AQ78: -10936 | AR78: -6259 | AS78: -10379 | AT78: -16467 | AU78: -30987 | AV78: -5763 | AW78: -12801 | AX78: =M78-AW78-AV78-AU78 -> -26620 | AY78: -43271 | AZ78: -14643 | BA78: -21549 | BB78: =N78-BA78-AZ78-AY78 -> -30530 | BC78: -21335 | BD78: 98 | BE78: =-15879 -> -15879 | BF78: =O78-BE78-BD78-BC78 -> -34178 | BG78: -18727 | BH78: -11120 | BI78: -41428.461 | BJ78: =P78-BI78-BH78-BG78 -> -60312.539 | BK78: -17500.217 | BL78: -12173 | BM78: -17261.57 | BN78: =Q78-BM78-BL78-BK78 -> -19958.213 | BO78: -23200 | BP78: -54561 | BQ78: -23310 | BR78: =R78-BQ78-BP78-BO78 -> -39192 | BS78: -41579.665 | BT78: -63744.136 | BU78: -32502 | BV78: =S78-BU78-BT78-BS78 -> -37650.199 | BW78: -33273 | BX78: -26019 | BY78: -29968 | BZ78: =T78-SUM(BW78:BY78) -> -59616 | CB78: -43271 | CC78: =1038.19590303875-21548.6950793185 -> -20510.499 | CD78: =1207.83784290074-30529.8084018871 -> -29321.971 | CE78: =2240.1712552319-21335.1480313445 -> -19094.977 | CF78: =299.454337731082-22026.0582460548 -> -21726.604 | CH78: -109993
B79: Net cash from operations | D79: =SUM(D75:D78) -> 162304 | E79: =SUM(E75:E78) -> 172070 | F79: =SUM(F75:F78) -> 188207 | G79: =SUM(G75:G78) -> 224514 | H79: =SUM(H75:H78) -> 237576 | I79: =SUM(I75:I78) -> 266619 | J79: =SUM(J75:J78) -> 287072 | K79: =SUM(K75:K78) -> 244853 | ... U79: =SUM(U75:U78) -> 1073003 | W79: =SUM(W75:W78) -> 52702 | X79: =SUM(X75:X78) -> 39037 | Y79: =SUM(Y75:Y78) -> 51618 | Z79: =SUM(Z75:Z78) -> 44850 | AA79: =SUM(AA75:AA78) -> 89548 | AB79: =SUM(AB75:AB78) -> 50189 | AC79: =SUM(AC75:AC78) -> 44933 | AD79: =SUM(AD75:AD78) -> 39844 | ... BZ79: =SUM(BZ75:BZ78) -> 228009 | CB79: =SUM(CB75:CB78) -> 39368.401 | CC79: =SUM(CC75:CC78) -> 88655.856 | CD79: =SUM(CD75:CD78) -> -117476.34 | CE79: =SUM(CE75:CE78) -> 91540.46 | CF79: =SUM(CF75:CF78) -> 94909.429 | CH79: =SUM(CH75:CH78) -> 48802
B80: Net Capex | D80: =-109952+783-167925 -> -277094 | E80: =-144436+1074-6921 -> -150283 | F80: =SUM(W80:Z80) -> -130063 | G80: =SUM(AA80:AD80) -> -174659 | H80: =SUM(AE80:AH80) -> -209786 | I80: =SUM(AI80:AL80) -> -270967 | J80: =SUM(AM80:AP80) -> -384045 | K80: =SUM(AQ80:AT80) -> -267262 | L80: =-239604-27658 -> -267262 | M80: =-259746-45524 -> -305270 | N80: =-190585-30690 -> -221275 | O80: =-246706-87673 -> -334379 | P80: =-265406+13791-8593-174482 -> -434690 | Q80: =-260566+885-4819-123684 -> -388184 | R80: =-381915+1228-18600-121547 -> -520834 | S80: =-379077+3382-17722-213487 -> -606904 | T80: =-440076-23932 -> -464008 | U80: =SUM(BW80:BZ80) -> -464008 | W80: =-27432+279-1144 -> -28297 | X80: =-32741+310-981 -> -33412 | Y80: =-33248+814-1221 -> -33655 | Z80: =-32301-2398 -> -34699 | AA80: =-45988+5777-1638 -> -41849 | AB80: =-27645-2005-4831 -> -34481 | AC80: =-18952+431-943 -> -19464 | AD80: =-21574+157-57448 -> -78865 | AE80: =-29424+1156-6961 -> -35229 | AF80: =-36949+576-4846 -> -41219 | AG80: =-38225+60-5626 -> -43791 | AH80: =-41813+803-48537 -> -89547 | AI80: =-44062+387-67617 -> -111292 | AJ80: =(44716-359+8859)*-1 -> -53216 | AK80: =(49316-1588+1643)*-1 -> -49371 | AL80: =(55219-1464+3333)*-1 -> -57088 | AM80: =(59577-1688+47099)*-1 -> -104988 | AN80: =(44926-410+26520)*-1 -> -71036 | AO80: =(65378-2157+89226)*-1 -> -152447 | AP80: =(53149-207+2632)*-1 -> -55574 | AQ80: =(43792-744+2114)*-1 -> -45162 | AR80: =(57717-1672+3213)*-1 -> -59258 | AS80: =(81589-3167+3861)*-1 -> -82283 | AT80: =-62161+72-18470 -> -80559 | AU80: =-66704-14881 -> -81585 | AV80: =-5910-92057 -> -97967 | AW80: =-53366-13430 -> -66796 | AX80: =M80-AW80-AV80-AU80 -> -58922 | AY80: =-49202-10201 -> -59403 | AZ80: =-39691-3428 -> -43119 | BA80: =-56614-1884 -> -58498 | BB80: =N80-BA80-AZ80-AY80 -> -60255 | BC80: =-53338-1764 -> -55102 | BD80: =-54347-1398 -> -55745 | BE80: =-69766-6025 -> -75791 | BF80: =O80-BE80-BD80-BC80 -> -147741 | BG80: =-71552-3765 -> -75317 | BH80: =-60887-8081 -> -68968 | BI80: =-67700-132230 -> -199930 | BJ80: =P80-BI80-BH80-BG80 -> -90475 | BK80: =-70040.6223294805-4135.81590913265 -> -74176.438 | BL80: =-53588-88481 -> -142069 | BM80: =-64201-32133 -> -96334 | BN80: =Q80-BM80-BL80-BK80 -> -75604.562 | BO80: =-90931-12619 -> -103550 | BP80: =-97060-44009 -> -141069 | BQ80: =-98723-3537 -> -102260 | BR80: =R80-BQ80-BP80-BO80 -> -173955 | BS80: =-98751-70757 -> -169508 | BT80: =-95562-56608 -> -152170 | BU80: =-83524-34782 -> -118306 | BV80: =S80-BU80-BT80-BS80 -> -166920 | BW80: =-111296-2108 -> -113404 | BX80: =-108354-5519 -> -113873 | BY80: =-107797-4542 -> -112339 | BZ80: =T80-SUM(BW80:BY80) -> -124392 | CB80: =-49202-10201 -> -59403 | CC80: =-56614.3659090918-1883.66447034994 -> -58498.03 | CD80: =-45077.9171168354-15177.1305782764 -> -60255.048 | CE80: =-53338.3334177686-1764.26661115009 -> -55102.6 | CF80: =-54346.6990511994-1398.40093280662 -> -55745.1 | CH80: =-190585-30690 -> -221275
B81: Acquisitions / (Asset Sales) | D81: -373991 | E81: =-24985+2543-285 -> -22727 | F81: =SUM(W81:Z81) -> -9179 | G81: =SUM(AA81:AD81) -> -14053 | H81: =SUM(AE81:AH81) -> 663 | I81: =SUM(AI81:AL81) -> 56686 | J81: =SUM(AM81:AP81) -> 66638 | K81: =SUM(AQ81:AT81) -> -14689 | L81: =-19498+4869-60 -> -14689 | M81: =-5083+3051-60 -> -2092 | N81: =-1345-4761 -> -6106 | O81: =0-32603 -> -32603 | P81: =-26208+5887+998 -> -19323 | Q81: =-8106 -> -8106 | R81: =-300-6428 -> -6728 | S81: =-8788-69+1023+45 -> -7789 | T81: 0 | U81: =SUM(BW81:BZ81) -> 0 | W81: -9281 | X81: 0 | Y81: 0 | Z81: 102 | AA81: =-2928-8009 -> -10937 | AB81: -747 | AC81: 0 | AD81: -2369 | AE81: 0 | AF81: 0 | AG81: -358 | AH81: 1021 | AI81: 7346 | AJ81: =-135+36298 -> 36163 | AK81: 12723 | AL81: 454 | AM81: =(283-39611-120)*-1 -> 39448 | AN81: =(-20419-5290-447)*-1 -> 26156 | AO81: =(426-1212)*-1 -> 786 | AP81: =(-498+250)*-1 -> 248 | AQ81: 1840 | AR81: =(16764-92)*-1 -> -16672 | AS81: =(1468-1858)*-1 -> 390 | AT81: =-1266+1079-60 -> -247 | AU81: =6931+103 -> 7034 | AV81: =-6403-60+2870 -> -3593 | AW81: =-811+0+78 -> -733 | AX81: =M81-AW81-AV81-AU81 -> -4800 | AY81: =-1189-2605 -> -3794 | AZ81: =1189+2 -> 1191 | BA81: -2134 | BB81: =N81-BA81-AZ81-AY81 -> -1369 | BC81: -3317 | BD81: 6 | BE81: -17 | BF81: =O81-BE81-BD81-BC81 -> -29275 | BG81: 0 | BH81: 0 | BI81: =3320 -> 3320 | BJ81: =P81-BI81-BH81-BG81 -> -22643 | BK81: 0 | BL81: 0 | BM81: 0 | BN81: =Q81-BM81-BL81-BK81 -> -8106 | BO81: 0 | BP81: 0 | BQ81: 0 | BR81: =R81-BQ81-BP81-BO81 -> -6728 | BS81: 0 | BT81: 0 | BU81: 1023 | BV81: =S81-BU81-BT81-BS81 -> -8812 | BW81: 0 | BX81: 0 | BY81: 0 | BZ81: =T81-SUM(BW81:BY81) -> 0 | CB81: =-1189-2605 -> -3794 | CC81: 0 | CD81: -1345.2129 | CE81: 0 | CF81: 0 | CH81: =-1345-4761 -> -6106
B82: Free cash flow | D82: =SUM(D79:D81) -> -488781 | E82: =SUM(E79:E81) -> -940 | F82: =SUM(F79:F81) -> 48965 | G82: =SUM(G79:G81) -> 35802 | H82: =SUM(H79:H81) -> 28453 | I82: =SUM(I79:I81) -> 52338 | J82: =SUM(J79:J81) -> -30335 | K82: =SUM(K79:K81) -> -37098 | ... U82: =SUM(U79:U81) -> 608995 | W82: =SUM(W79:W81) -> 15124 | X82: =SUM(X79:X81) -> 5625 | Y82: =SUM(Y79:Y81) -> 17963 | Z82: =SUM(Z79:Z81) -> 10253 | AA82: =SUM(AA79:AA81) -> 36762 | AB82: =SUM(AB79:AB81) -> 14961 | AC82: =SUM(AC79:AC81) -> 25469 | AD82: =SUM(AD79:AD81) -> -41390 | ... BZ82: =SUM(BZ79:BZ81) -> 103617 | CB82: =SUM(CB79:CB81) -> -23828.599 | CC82: =SUM(CC79:CC81) -> 30157.825 | CD82: =SUM(CD79:CD81) -> -179076.6 | CE82: =SUM(CE79:CE81) -> 36437.86 | CF82: =SUM(CF79:CF81) -> 39164.329 | CH82: =SUM(CH79:CH81) -> -178579
B83: Other investing activities | D83: =46590+565 -> 47155 | E83: =401-10823-172+210 -> -10384 | F83: =SUM(W83:Z83) -> -45528 | G83: =SUM(AA83:AD83) -> -58435 | H83: =SUM(AE83:AH83) -> -9571 | I83: =SUM(AI83:AL83) -> 72024 | J83: =SUM(AM83:AP83) -> 1853 | K83: =SUM(AQ83:AT83) -> -7735 | L83: =-50259+36495+10377+5662 -> 2275 | M83: =18158-12091+11493+4793 -> 22353 | N83: =-85236+2950+4748 -> -77538 | O83: =67168+3578+3131-17 -> 73860 | P83: =10048+21298-89+8+4052 -> 35317 | Q83: =-12000+311-323+3508 -> -8504 | R83: =19015+69-304+5671 -> 24451 | S83: =7100-734+300+1090+4239 -> 11995 | T83: =-126994-1151+907+1813+4088 -> -121337 | U83: =SUM(BW83:BZ83) -> -121337 | W83: =-60-11156+66 -> -11150 | X83: =11343+567-40 -> 11870 | Y83: =-50004+155 -> -49849 | Z83: =-30+1092+111+2428 -> 3601 | AA83: =-47647+286+1154+324 -> -45883 | AB83: =20266-2500-30505+255+105 -> -12379 | AC83: =-23351-6342-2-60+139+233 -> -29383 | AD83: =28734+100+140+236 -> 29210 | AE83: =-15771-357+589-10-65+454+267 -> -14893 | AF83: =11791-2171+1029-89+523+127 -> 11210 | AG83: =11084+87+137+86 -> 11394 | AH83: =-20925-550+193+4000 -> -17282 | AI83: =4305+3092+410 -> 7807 | AJ83: =17710-2013+3450+976 -> 20123 | AK83: =33417-1002+1100-19+14+59+1774 -> 35343 | AL83: =8339-203+55+59+501 -> 8751 | AM83: =-32195+61+1365 -> -30769 | AN83: =33475-14736+1415+62+539 -> 20755 | AO83: =2188-30190+23138+62+51 -> -4751 | AP83: =2317-44147+58004+94+350 -> 16618 | AQ83: =6134+86+2014-9225 -> -991 | AR83: =8083+109+1279 -> 9471 | AS83: =-15890+1028+92+571 -> -14199 | AT83: =-33227+29333+80+1798 -> -2016 | AU83: =-2668+11331+932 -> 9595 | AV83: =16277+55+911+161 -> 17404 | AW83: =54+2608+14350-14694 -> 2318 | AX83: =M83-AW83-AV83-AU83 -> -6964 | AY83: =-8595+1620+522 -> -6453 | AZ83: =-4244+1830+882 -> -1532 | BA83: =-130950+599+1038 -> -129313 | BB83: =N83-BA83-AZ83-AY83 -> 59760 | BC83: =-832+2240+3561+4200 -> 9169 | BD83: =49218+76+299 -> 49593 | BE83: =72249-29234+217-42 -> 43190 | BF83: =O83-BE83-BD83-BC83 -> -28092 | BG83: =54972+392-75+0 -> 55289 | BH83: =-83058+0+401+10048+8 -> -72601 | BI83: =60065+581-919 -> 59727 | BJ83: =P83-BI83-BH83-BG83 -> -7098 | BK83: =-56813-BK80-BK81 -> 17363.438 | BL83: =13299+311+760 -> 14370 | BM83: =-43564+1189-157 -> -42532 | BN83: =Q83-BM83-BL83-BK83 -> 2294.5618 | BO83: =-55756-114+1041 -> -54829 | BP83: =54505-111+1120-300+463 -> 55677 | BQ83: =-52712+33+609+2367 -> -49703 | BR83: =R83-BQ83-BP83-BO83 -> 73306 | BS83: =27365-84+1839-67+1085-8638 -> 21500 | BT83: =7425-183+817+67+0-150-69 -> 7907 | BU83: =-11811-1-1+915 -> -10898 | BV83: =S83-BU83-BT83-BS83 -> -6514 | BW83: =-27136-28+1813+647 -> -24704 | BX83: =-4443-436+1026 -> -3853 | BY83: =-19719-354+634+2223 -> -17216 | BZ83: =T83-SUM(BW83:BY83) -> -75564 | CB83: =-8595+1620+522 -> -6453 | CC83: =-130950.129771264+598.765550883405-2133.58039961218 -> -132484.94 | CD83: =58553.5142202446-0.814497017655867-25.3731377987101 -> 58527.327 | CE83: =-831.977886+3561.29838313155-3317.059876345+4200 -> 3612.2606 | CF83: =49267.1563785833+33.1116189373765-0.368554520514408 -> 49299.899 | CH83: =-85236+2950+4748 -> -77538
B84: Dividends / Equity movements | D84: =-402+96-4428 -> -4734 | E84: =-544+187-4411-157 -> -4925 | F84: =SUM(W84:Z84) -> 26071 | G84: =SUM(AA84:AD84) -> 61319 | H84: =SUM(AE84:AH84) -> -20847 | I84: =SUM(AI84:AL84) -> -14265 | J84: =SUM(AM84:AP84) -> -18542 | K84: =SUM(AQ84:AT84) -> -33042 | L84: =-411-32652+21 -> -33042 | M84: =-238-46617+104341-5409 -> 52077 | N84: =-492+143055+70456-18263+128514+248759 -> 572029 | O84: =-1102+0+0-26906+36048+24239-10243 -> 22036 | P84: =52226-598+7-14438 -> 37197 | Q84: =52242-499+3-35898+13992 -> 29840 | R84: =-1368+6-41845+1072 -> -42135 | S84: =-3675-69349 -> -73024 | T84: =-1447-113277+75-19056+156949 -> 23244 | U84: =SUM(BW84:BZ84) -> 23244 | W84: =11-101 -> -90 | X84: =-4412-928+33-762 -> -6069 | Y84: =32303+13 -> 32316 | Z84: =-97+11 -> -86 | AA84: =67956-132+13 -> 67837 | AB84: =-4439-1772+13 -> -6198 | AC84: =-392+7 -> -385 | AD84: 65 | AE84: 83 | AF84: =-21331+32 -> -21299 | AG84: =-68+73 -> 5 | AH84: 364 | AI84: 367 | AJ84: =-15304+176-514 -> -15642 | AK84: 15 | AL84: =11+984 -> 995 | AM84: =-23+2 -> -21 | AN84: =-9145+250-7632+16 -> -16511 | AO84: =37+299-3052 -> -2716 | AP84: =10+696 -> 706 | AQ84: -10348 | AR84: =-8468+9 -> -8459 | AS84: =-241+1 -> -240 | AT84: =-183+3-13836+21 -> -13995 | AU84: =-52-97 -> -149 | AV84: =-26700-146+597-5366 -> -31615 | AW84: =-19820-42+89751-23 -> 69866 | AX84: =M84-AW84-AV84-AU84 -> 13975 | AY84: =-7774-83+231+249129 -> 241503 | AZ84: =2-3784+54799+7 -> 51024 | BA84: =-411-6377+53074-0 -> 46286 | BB84: =N84-BA84-AZ84-AY84 -> 233216 | BC84: =-21-5678 -> -5699 | BD84: =7-17113 -> -17106 | BE84: =-4115-1110-224 -> -5449 | BF84: =O84-BE84-BD84-BC84 -> 50290 | BG84: =0-2998 -> -2998 | BH84: =-205-3783 -> -3988 | BI84: =-6284-362+52254-12525 -> 33083 | BJ84: =P84-BI84-BH84-BG84 -> 11100 | BK84: -4015.7426 | BL84: =-23146-299 -> -23445 | BM84: =-8531-198+42 -> -8687 | BN84: =Q84-BM84-BL84-BK84 -> 65987.743 | BO84: -4032 | BP84: =-29813-119 -> -29932 | BQ84: =-8416+3106 -> -5310 | BR84: =R84-BQ84-BP84-BO84 -> -2861 | BS84: -4707 | BT84: -54404 | BU84: =-7786-1433+1 -> -9218 | BV84: =S84-BU84-BT84-BS84 -> -4695 | BW84: -2266 | BX84: -101531 | BY84: =-129-6460+75 -> -6514 | BZ84: =T84-SUM(BW84:BY84) -> 133555 | CB84: =-7774-83+231+249129 -> 241503 | CC84: =-6376.66208209059-411.18076372 -> -6787.8428 | CD84: =-328.350107458642+143055+70456.429158011+20409.9846617863-376.738128620199 -> 233216.33 | CE84: =-5677.800164025-0 -> -5677.8002 | CF84: =-17113.4723831087+7.45565455730972 -> -17106.017 | CH84: =-492+143055+70456-18263+128514+248759 -> 572029
B85: Principal Repayments | D85: =564390-139104+4300 -> 429586 | E85: =164864-163343-4351 -> -2830 | F85: =SUM(W85:Z85) -> -24026 | G85: =SUM(AA85:AD85) -> 14252 | H85: =SUM(AE85:AH85) -> -72451 | I85: =SUM(AI85:AL85) -> -120426 | J85: =SUM(AM85:AP85) -> 5454 | K85: =SUM(AQ85:AT85) -> 36141 | L85: =66947-26874-974 -> 39099 | M85: =7782+98101-3389 -> 102494 | N85: =-62413-117140-47740 -> -227293 | O85: =-82504-35659-64206 -> -182369 | P85: =254785-337212-76427+63649 -> -95205 | Q85: =136077-178227-75986-70972 -> -189108 | R85: =67123-100803-78552+15516 -> -96716 | S85: =235597-178594-71538+36927-86292 -> -63900 | T85: =-280642-44087-67197 -> -391926 | U85: =SUM(BW85:BZ85) -> -391926 | W85: =95433-97326-2295 -> -4188 | X85: =22660-49302-345 -> -26987 | Y85: =63206-52138+612 -> 11680 | Z85: =76395-75672-5254 -> -4531 | AA85: =77593-84698 -> -7105 | AB85: =22853-65228+4843 -> -37532 | AC85: =114756-106391-2092 -> 6273 | AD85: =146013-92108-1289 -> 52616 | AE85: =179013-229467+200 -> -50254 | AF85: =73352-110359+265 -> -36742 | AG85: =28508-51623+3325 -> -19790 | AH85: =63713-28876-502 -> 34335 | AI85: =76322-59293+2041-57 -> 19013 | AJ85: =60963-156486+9639-708 -> -86592 | AK85: =12675-72652-8709-873 -> -69559 | AL85: =37305-21225+1587-955 -> 16712 | AM85: =44646-71180+8691-844 -> -18687 | AN85: =21489-60004-4042-987 -> -43544 | AO85: =124276-68780+41143-866 -> 95773 | AP85: =68173-74644-20415-1202 -> -28088 | AQ85: =21337-75639-1874-1094 -> -57270 | AR85: =6659-30576+22200-1003 -> -2720 | AS85: =11196-9995+1636-1053 -> 1784 | AT85: =158472-14507-48836-782 -> 94347 | AU85: =40748+4500-682 -> 44566 | AV85: =33763+16347+651 -> 50761 | AW85: =-62549+11863-2029 -> -52715 | AX85: =M85-AW85-AV85-AU85 -> 59882 | AY85: =-105440-83799-11859 -> -201098 | AZ85: =52163-55053-6372 -> -9262 | BA85: =75316+17376-16243 -> 76449 | BB85: =N85-BA85-AZ85-AY85 -> -93382 | BC85: =-4293-22460-13868 -> -40621 | BD85: =-76170-6490-11389 -> -94049 | BE85: =-58710+5172-19676 -> -73214 | BF85: =O85-BE85-BD85-BC85 -> 25515 | BG85: =-61421+4097-17623 -> -74947 | BH85: =-60115+52488-16244 -> -23871 | BI85: =16380-3788-20335 -> -7743 | BJ85: =P85-BI85-BH85-BG85 -> 11356 | BK85: -88341 | BL85: =3056-4364-18871 -> -20179 | BM85: =20528-25385-19095 -> -23952 | BN85: =Q85-BM85-BL85-BK85 -> -56636 | BO85: =-20743+1277-19759 -> -39225 | BP85: =891-863-20935 -> -20907 | BQ85: =986+162-19646 -> -18498 | BR85: =R85-BQ85-BP85-BO85 -> -18086 | BS85: =-32599+19865-18471 -> -31205 | BT85: =342+44017-19667 -> 24692 | BU85: =-4147-44240-16321 -> -64708 | BV85: =S85-BU85-BT85-BS85 -> 7321 | BW85: =-162356+45139-16887 -> -134104 | BX85: =11341-14059-16030 -> -18748 | BY85: =-48076-76992-16139 -> -141207 | BZ85: =T85-SUM(BW85:BY85) -> -97867 | CB85: =-105440-83799-11859 -> -201098 | CC85: =75315.6222922733+17376.2320516344-16243.4749205974+53074.2419612836 -> 129522.62 | CD85: =-84452.0436612754+4336.41917541556-13265.6315757869 -> -93381.256 | CE85: =-4292.896554033-22460.402933-13868.2323984328 -> -40621.532 | CF85: =-76170.4219842342-6490.40467425-11388.5160557344 -> -94049.343 | CH85: =-62413-117140-47740 -> -227293
B86: Other financing activities | D86: -6104 | E86: 0 | F86: =SUM(W86:Z86) -> -13361 | G86: =SUM(AA86:AD86) -> -10207 | H86: =SUM(AE86:AH86) -> 30615 | I86: =SUM(AI86:AL86) -> 48120 | J86: =SUM(AM86:AP86) -> 68140 | K86: =SUM(AQ86:AT86) -> 60147 | L86: =57189 -> 57189 | M86: =16238 -> 16238 | N86: =-41517-1782 -> -43299 | O86: =0-221+7000-17 -> 6762 | P86: =0-704+10880+40911-13523 -> 37564 | Q86: =-3901-641 -> -4542 | R86: =-870+573+4391-1693 -> 2401 | S86: =14-37348-16427+829 -> -52932 | T86: -5368 | U86: =SUM(BW86:BZ86) -> -5368 | W86: 0 | X86: 0 | Y86: -646 | Z86: =-12782+67 -> -12715 | AA86: -3828 | AB86: 0 | AC86: -2153 | AD86: -4226 | AE86: -9173 | AF86: 21230 | AG86: 0 | AH86: =19182-624 -> 18558 | AI86: 4768 | AJ86: 31048 | AK86: 12099 | AL86: 205 | AM86: 92 | AN86: 5025 | AO86: 660 | AP86: =500+61863 -> 62363 | AQ86: 1077 | AR86: =99+25532 -> 25631 | AS86: =1191+31630 -> 32821 | AT86: =591+27 -> 618 | AU86: 0 | AV86: =16238 -> 16238 | AW86: =0 -> 0 | AX86: =M86-AW86-AV86-AU86 -> 0 | AY86: =-15784-251 -> -16035 | AZ86: 0 | BA86: -25733 | BB86: =N86-BA86-AZ86-AY86 -> -1531 | BC86: =-15 -> -15 | BD86: 0 | BE86: =-2-192 -> -194 | BF86: =O86-BE86-BD86-BC86 -> 6971 | BG86: =0+1124-913 -> 211 | BH86: =0+27673-570-40+4000 -> 31063 | BI86: =13092-818 -> 12274 | BJ86: =P86-BI86-BH86-BG86 -> -5984 | BK86: -1010 | BL86: =-5451-BL85-BL84-BL78 -> 50346 | BM86: =-1363 -> -1363 | BN86: =Q86-BM86-BL86-BK86 -> -52515 | BO86: =36+317+8 -> 361 | BP86: =-107541-BP85-BP84-BP78 -> -2141 | BQ86: =-46710-BQ85-BQ84-BQ78 -> 408 | BR86: =R86-BQ86-BP86-BO86 -> 3773 | BS86: =-447-7103+83-1524 -> -8991 | BT86: =-1790+66-2620-5237 -> -9581 | BU86: =-109072-BU85-BU84-BU78 -> -2644 | BV86: =S86-BU86-BT86-BS86 -> -31716 | BW86: =-1059-2873 -> -3932 | BX86: =-1245-1615-11271 -> -14131 | BY86: =-1414-449 -> -1863 | BZ86: =T86-SUM(BW86:BY86) -> 14558 | CB86: =-15784-251 -> -16035 | CC86: -25733.397 | CD86: -1781.8686 | CE86: -14.762781 | CF86: 0 | CH86: =-41517-1782 -> -43299
B87: Cash flow after financing activities | D87: =SUM(D82:D86) -> -22878 | E87: =SUM(E82:E86) -> -19079 | F87: =SUM(F82:F86) -> -7879 | G87: =SUM(G82:G86) -> 42731 | H87: =SUM(H82:H86) -> -43801 | I87: =SUM(I82:I86) -> 37791 | J87: =SUM(J82:J86) -> 26570 | K87: =SUM(K82:K86) -> 18413 | ... U87: =SUM(U82:U86) -> 113608 | W87: =SUM(W82:W86) -> -304 | X87: =SUM(X82:X86) -> -15561 | Y87: =SUM(Y82:Y86) -> 11464 | Z87: =SUM(Z82:Z86) -> -3478 | AA87: =SUM(AA82:AA86) -> 47783 | AB87: =SUM(AB82:AB86) -> -41148 | AC87: =SUM(AC82:AC86) -> -179 | AD87: =SUM(AD82:AD86) -> 36275 | ... BZ87: =SUM(BZ82:BZ86) -> 78299 | CB87: =SUM(CB82:CB86) -> -5911.5987 | CC87: =SUM(CC82:CC86) -> -5325.7376 | CD87: =SUM(CD82:CD86) -> 17503.93 | CE87: =SUM(CE82:CE86) -> -6263.9742 | CF87: =SUM(CF82:CF86) -> -22691.131 | CH87: =SUM(CH82:CH86) -> 45320
B88: Balancing figure | D88: =-18829-D87 -> 4049 | E88: =1536-E87 -> 20615 | F88: =SUM(W88:Z88) -> 3162 | G88: =SUM(AA88:AD88) -> -2394 | H88: =SUM(AE88:AH88) -> 2768 | I88: =SUM(AI88:AL88) -> -20083 | J88: =SUM(AM88:AP88) -> -53330 | K88: =SUM(AQ88:AT88) -> 19654 | L88: =38067-L87 -> 1876 | M88: =7509-M87 -> 4845 | N88: =67812-N87 -> -865 | O88: =-35937-O87 -> 12558 | P88: =-20562-P87 -> 5289 | Q88: =17749-Q87 -> 4951 | R88: =9158-R87 -> -95412 | S88: =15292-S87 -> -106105 | T88: =114025-T87 -> 417 | U88: =SUM(BW88:BZ88) -> 417 | W88: =2492-W87 -> 2796 | X88: =-9434-X87 -> 6127 | Y88: =9521-Y87 -> -1943 | Z88: =-7296-Z87 -> -3818 | AA88: =19443-AA87 -> -28340 | AB88: =-9780-AB87 -> 31368 | AC88: =4079-AC87 -> 4258 | AD88: =26595-AD87 -> -9680 | AE88: =-32495-AE87 -> 7952 | AF88: =-5629-AF87 -> -3998.9952 | AG88: =8239-AG87 -> 2156.5987 | AH88: =-11148-AH87 -> -3341.6035 | AI88: =5659-AI87 -> -3044.8653 | AJ88: =-17982-AJ87 -> -4380.0197 | AK88: =-1497-AK87 -> -9847.5075 | AL88: =31528-AL87 -> -2810.6075 | AM88: =-16049-AM87 -> 6755.982 | AN88: =-5170-AN87 -> -7768.6041 | AO88: =-6368-AO87 -> -22332.759 | AP88: =827-AP87 -> -29984.619 | AQ88: =11585-AQ87 -> 24647.395 | AR88: =-8655-AR87 -> -27115.779 | AS88: =-5803-AS87 -> -6177 | AT88: =40940-AT87 -> 28299.384 | AU88: =-4950-AU87 -> 2871 | AV88: =-12595-AV87 -> 2688 | AW88: =-551-AW87 -> -2036 | AX88: =M88-AW88-AV88-AU88 -> 1322 | AY88: =-4244-AY87 -> 2346.5987 | AZ88: =48726-AZ87 -> -827.53087 | BA88: =-2847-BA87 -> -86.971655 | BB88: =N88-BA88-AZ88-AY88 -> -2297.0962 | BC88: =-681-BC87 -> 398 | BD88: =-16825-BD87 -> -24 | BE88: =-4014-BE87 -> 3011 | BF88: =O88-BE88-BD88-BC88 -> 9173 | BG88: =5731-BG87 -> 1199 | BH88: =-22854-BH87 -> -19 | BI88: =16762-BI87 -> -539.99435 | BJ88: =P88-BI88-BH88-BG88 -> 4648.9944 | BK88: =11807-BK87 -> 2174.9592 | BL88: =-4250-BL87 -> 1548 | BM88: =29-BM87 -> 1289.0853 | BN88: =Q88-BM88-BL88-BK88 -> -61.044481 | BO88: =-16380-BO87 -> 3524 | BP88: =-1641-BP87 -> 573 | BQ88: =15674-BQ87 -> 446.361 | BR88: =R88-BQ88-BP88-BO88 -> -99955.361 | BS88: =-16457.4-BS87 -> -27443.122 | BT88: =2007-BT87 -> -33320.391 | BU88: =20025-BU87 -> -40279 | BV88: =S88-BU88-BT88-BS88 -> -5062.4871 | BW88: =-4785-BW87 -> 1698 | BX88: =23859-BX87 -> -1595 | BY88: =17933-BY87 -> 1595 | BZ88: =T88-SUM(BW88:BY88) -> -1281 | CB88: =-3565-CB87 -> 2346.5987 | CC88: =-29-CC87 -> 5296.7376 | CD88: =21109-CD87 -> 3605.0698 | CE88: =-660-CE87 -> 5603.9742 | CF88: =-16825-CF87 -> 5866.1313 | CH88: =67812-CH87 -> 22492
B89: FX | D89: -124 | E89: 493 | F89: =SUM(W89:Z89) -> -1624 | G89: =SUM(AA89:AD89) -> -2074 | H89: =SUM(AE89:AH89) -> 43 | I89: =SUM(AI89:AL89) -> 1340 | J89: =SUM(AM89:AP89) -> -755 | K89: =SUM(AQ89:AT89) -> 281 | L89: 281 | M89: 1338 | N89: 8934 | O89: -3972 | P89: 3919 | Q89: -1522 | R89: -8851 | S89: 718 | T89: 23291 | U89: =SUM(BW89:BZ89) -> 23291 | W89: -2431 | X89: 1669 | Y89: -725 | Z89: -137 | AA89: -84 | AB89: -826 | AC89: -301 | AD89: -863 | AE89: -475 | AF89: 46 | AG89: 24 | AH89: 448 | AI89: 1737 | AJ89: -314 | AK89: 64 | AL89: -147 | AM89: -821 | AN89: -157 | AO89: 88 | AP89: 135 | AQ89: -14 | AR89: -9 | AS89: -276 | AT89: 580 | AU89: 987 | AV89: 2104 | AW89: -1221 | AX89: =M89-AW89-AV89-AU89 -> -532 | AY89: -101 | AZ89: 2560 | BA89: -1.64 | BB89: =N89-BA89-AZ89-AY89 -> 6476.64 | BC89: -364 | BD89: -2295 | BE89: -1863 | BF89: =O89-BE89-BD89-BC89 -> 550 | BG89: 711 | BH89: -211 | BI89: 507 | BJ89: =P89-BI89-BH89-BG89 -> 2912 | BK89: 2355 | BL89: 1034 | BM89: -2172 | BN89: =Q89-BM89-BL89-BK89 -> -2739 | BO89: -1504 | BP89: -2942 | BQ89: -6201 | BR89: =R89-BQ89-BP89-BO89 -> 1796 | BS89: 1886.1463 | BT89: -633 | BU89: 1875 | BV89: =S89-BU89-BT89-BS89 -> -2410.1463 | BW89: 4626 | BX89: 5673 | BY89: 2558 | BZ89: =T89-SUM(BW89:BY89) -> 10434 | CB89: -101 | CC89: 988.35716 | CD89: 5486.0411 | CE89: -364.32529 | CF89: -2295.1691 | CH89: 8934
B90: Net change in cash | D90: =D87+D89+D88 -> -18953 | E90: =E87+E89+E88 -> 2029 | F90: =F87+F89+F88 -> -6341 | G90: =G87+G89+G88 -> 38263 | H90: =H87+H89+H88 -> -40990 | I90: =I87+I89+I88 -> 19048 | J90: =J87+J89+J88 -> -27515 | K90: =K87+K89+K88 -> 38348 | L90: =SUM(L87:L89) -> 38348 | M90: =SUM(M87:M89) -> 8847 | N90: =SUM(N87:N89) -> 76746 | O90: =SUM(O87:O89) -> -39909 | P90: =SUM(P87:P89) -> -16643 | Q90: =SUM(Q87:Q89) -> 16227 | R90: =SUM(R87:R89) -> 307 | S90: =SUM(S87:S89) -> 16010 | ... U90: =SUM(U87:U89) -> 137316 | W90: =W87+W89+W88 -> 61 | X90: =X87+X89+X88 -> -7765 | Y90: =Y87+Y89+Y88 -> 8796 | Z90: =Z87+Z89+Z88 -> -7433 | AA90: =AA87+AA89+AA88 -> 19359 | AB90: =AB87+AB89+AB88 -> -10606 | AC90: =AC87+AC89+AC88 -> 3778 | AD90: =SUM(AD87:AD89) -> 25732 | AE90: =SUM(AE87:AE89) -> -32970 | AF90: =SUM(AF87:AF89) -> -5583 | AG90: =SUM(AG87:AG89) -> 8263 | AH90: =SUM(AH87:AH89) -> -10700 | AI90: =SUM(AI87:AI89) -> 7396 | AJ90: =SUM(AJ87:AJ89) -> -18296 | AK90: =SUM(AK87:AK89) -> -1433 | ... AQ90: =SUM(AQ87:AQ89) -> 11571 | AR90: =AR87+AR89+AR88 -> -8664 | AS90: =AS87+AS89+AS88 -> -6079 | AT90: =AT87+AT89+AT88 -> 41520 | AU90: =SUM(AU87:AU89) -> -3963 | AV90: =SUM(AV87:AV89) -> -10491 | AW90: =SUM(AW87:AW89) -> -1772 | AX90: =SUM(AX87:AX89) -> 25073 | AY90: =SUM(AY87:AY89) -> -4345 | AZ90: =SUM(AZ87:AZ89) -> 51286 | BA90: =SUM(BA87:BA89) -> -2848.64 | BB90: =SUM(BB87:BB89) -> 32653.64 | ... BZ90: =SUM(BZ87:BZ89) -> 87452 | CB90: =SUM(CB87:CB89) -> -3666 | CC90: =SUM(CC87:CC89) -> 959.35716 | CD90: =SUM(CD87:CD89) -> 26595.041 | CE90: =SUM(CE87:CE89) -> -1024.3253 | CF90: =SUM(CF87:CF89) -> -19120.169 | CH90: =SUM(CH87:CH89) -> 76746
B91: Cash and cash equivalents | D91: =24961+D90 -> 6008 | E91: 7652 | F91: =F90+E91 -> 1311 | G91: =G90+F91 -> 39574 | H91: =H90+G91 -> -1416 | I91: =I90+H91 -> 17632 | J91: =J90+I91 -> -9883 | K91: =K90+J91 -> 28465 | L91: =-9880+L90 -> 28468 | M91: =AT91+M90 -> 37315 | N91: =53793+N90 -> 130539 | O91: =130539+O90 -> 90630 | P91: =90630+P90 -> 73987 | Q91: =P91+Q90 -> 90214 | R91: =Q91+R90 -> 90521 | S91: =R91+S90 -> 106531 | T91: =S91+T90 -> 243847 | U91: =U90+BV91 -> 243847 | W91: =E91+W90 -> 7713 | X91: =W91+X90 -> -52 | Y91: =X91+Y90 -> 8744 | Z91: =Y91+Z90 -> 1311 | AA91: =Z91+AA90 -> 20670 | AB91: =AA91+AB90 -> 10064 | AC91: =AB91+AC90 -> 13842 | AD91: =AC91+AD90 -> 39574 | AE91: =AD91+AE90 -> 6604 | ... AS91: =AR91+AS90 -> -13055 | AT91: =-13052+AT90 -> 28468 | AU91: =AT91+AU90 -> 24505 | AV91: =AU91+AV90 -> 14014 | AW91: =AV91+AW90 -> 12242 | AX91: =AW91+AX90 -> 37315 | AY91: =AX91+AY90 -> 32970 | AZ91: =AY91+AZ90 -> 84256 | BA91: =AZ91+BA90 -> 81407.36 | BB91: =N91 -> 130539 | BC91: =BB91+BC90 -> 129494 | BD91: =BC91+BD90 -> 110374 | BE91: =BD91+BE90 -> 104497 | BF91: =O91 -> 90630 | BG91: =BF91+BG90 -> 97072 | BH91: =BG91+BH90 -> 74007 | BI91: =BH91+BI90 -> 91276 | BJ91: =P91 -> 73987 | BK91: =BJ91+BK90 -> 88149 | BL91: =BK91+BL90 -> 84933 | BM91: =BL91+BM90 -> 82790 | BN91: =Q91 -> 90214 | BO91: =BN91+BO90 -> 72330 | BP91: =BO91+BP90 -> 67747 | BQ91: =BP91+BQ90 -> 77220 | BR91: =R91 -> 90521 | BS91: =BR91+BS90 -> 75949.746 | BT91: =BS91+BT90 -> 77323.746 | BU91: =BT91+BU90 -> 99223.746 | BV91: =BU91+BV90 -> 106531 | BW91: =BV91+BW90 -> 106372 | BX91: =BW91+BX90 -> 135904 | BY91: =BX91+BY90 -> 156395 | BZ91: =BY91+BZ90 -> 243847 | CB91: =53793+CB90 -> 50127 | CC91: =102985+CC90 -> 103944.36 | CD91: =103944+CD90 -> 130539.04 | CE91: =130539+CE90 -> 129514.67 | CF91: =129494+CF90 -> 110373.83 | CH91: =53793+CH90 -> 130539
B93: Check - CFO | D93: =188513-565-D75-D76-D77-D88 -> 0 | E93: =225438-401-E75-E76-E77-E88 -> 0 | L93: =298538-L75-L76-L77-L88 -> 0 | M93: =197880-M75-M76-M77-M88 -> 0 | N93: =181287-N75-N76-N77-N88 -> 0 | O93: =482050-O75-O76-O77-O88 -> 0 | P93: =550166-P75-P76-P77-P88 -> 0 | Q93: =653246-Q75-Q76-Q77-Q88 -> 0 | R93: =788982-R75-R76-R77-R88 -> 0 | S93: =983322-S75-S76-S77-S88 -> 0 | T93: =1222296-T75-T76-T77-T88 -> 0 | W93: =65168-66-W75-W76-W77-W88 -> 0 | X93: =53284-567-X75-X76-X77-X88 -> 0 | Y93: =60936-155-Y75-Y76-Y77-Y88 -> 0 | Z93: =48311-1092-111-Z75-Z76-Z77-Z88 -> 0 | AA93: =72643-1154-324-AA75-AA76-AA77-AA88 -> 0 | AB93: =92109-105-255-AB75-AB76-AB77-AB88 -> 0 | AC93: =59622-139-233-AC75-AC76-AC77-AC88 -> 0 | AD93: =37952-140-236-AD75-AD76-AD77-AD88 -> 0 | AE93: =87049-267-454-AE75-AE76-AE77-AE88 -> 0 | AF93: =69105-523-127-AF75-AF76-AF77-AF88 -> 0 | AG93: =68538-137-86-AG75-AG76-AG77-AG88 -> 0 | AH93: =51326-193-AH75-AH76-AH77-AH88 -> 0 | AI93: =86882-AI75-AI76-AI77-AI88 -> 0 | AJ93: =57972-AJ75-AJ76-AJ77-AJ88 -> -3 | AK93: =66206-AK75-AK76-AK77-AK88 -> 0 | AL93: =68363-AL75-AL76-AL77-AL88 -> 0 | AM93: =108620-AM75-AM76-AM77-AM88 -> 0 | AN93: =80396-AN75-AN76-AN77-AN88 -> 0 | AO93: =65747-AO75-AO76-AO77-AO88 -> 0 | AP93: =37544-AP75-AP76-AP77-AP88 -> -1 | AQ93: =133375-AQ75-AQ76-AQ77-AQ88 -> 0 | AR93: =49611-AR75-AR76-AR77-AR88 -> 0 | AS93: =66303-AS75-AS76-AS77-AS88 -> 0 | AT93: =59259-AT75-AT76-AT77-AT88 -> 0 | AU93: =46576-AU75-AU76-AU77-AU88 -> 0 | AV93: =41940-AV75-AV76-AV77-AV88 -> 0 | AW93: =60310-AW75-AW76-AW77-AW88 -> 0 | AX93: =M93-AW93-AV93-AU93 -> 0 | AY93: =84307-AY75-AY76-AY77-AY88 -> -1.4551915e-11 | AZ93: =65067-AZ75-AZ76-AZ77-AZ88 -> 0 | BA93: =111645-BA75-BA76-BA77-BA88 -> 0 | BB93: =N93-BA93-AZ93-AY93 -> 1.4551915e-11 | BC93: =116239-BC75-BC76-BC77-BC88 -> 0 | BD93: =100378-BD75-BD76-BD77-BD88 -> 0 | BE93: =123341-BE75-BE76-BE77-BE88 -> 1 | BF93: =O93-BE93-BD93-BC93 -> -1 | BG93: =122220-BG75-BG76-BG77-BG88 -> 0 | BH93: =126633-BH75-BH76-BH77-BH88-2 -> 0 | BI93: =157457-BI75-BI76-BI77-BI88+2 -> -0.46142977 | BJ93: =P93-BI93-BH93-BG93 -> 0.46142977 | BK93: =179487-BK75-BK76-BK77-BK88 -> 0.040825693 | BL93: =128900-BL75-BL76-BL77-BL88 -> 0 | BM93: =190159-BM75-BM76-BM77-BM88 -> 0.4299985 | BN93: =Q93-BM93-BL93-BK93 -> -0.47082419 | BO93: =208097-BO75-BO76-BO77-BO88-2 -> 0 | BP93: =191291-BP75-BP76-BP77-BP88 -> -1 | BQ93: =214346-BQ75-BQ76-BQ77-BQ88 -> -1 | BR93: =W93-BQ93-BP93-BO93 -> 2 | BS93: =218034-BS75-BS76-BS77-BS88-1 -> -0.26480252 | BT93: =249307.4-BT75-BT76-BT77-BT88 -> 0.26418193 | BU93: =257278-BU75-BU76-BU77-BU88 -> 0 | BV93: =AA93-BU93-BT93-BS93 -> 0.00062059168 | BW93: =306898-BW75-BW76-BW77-BW88 -> 0 | BX93: =302014-BX75-BX76-BX77-BX88 -> 0 | BY93: =327040-BY75-BY76-BY77-BY88 -> 0 | BZ93: =286344-BZ75-BZ76-BZ77-BZ88 -> 0 | CB93: =84986-CB75-CB76-CB77-CB88 -> -1.4551915e-11 | CC93: =114463-CC75-CC76-CC77-CC88 -> -0.092701497 | CD93: =-84550-CD75-CD76-CD77-CD88+1 -> 0.29639779 | CE93: =116239-CE75-CE76-CE77-CE88 -> -0.41101499 | CF93: =122502-CF75-CF76-CF77-CF88 -> -0.1638921 | CH93: =181287-CH75-CH76-CH77-CH88 -> 0
B95: LTM METRICS
B97: Revenue | D97: =D10 -> 596018 | E97: =E10 -> 683817 | F97: =F10 -> 769469.92 | G97: =G10 -> 858634.94 | H97: =H10 -> 921351 | I97: =I10 -> 966192 | J97: =J10 -> 955889 | K97: =K10 -> 839367 | ... U97: =U10 -> 2137901 | Z97: =SUM(W10:Z10) -> 769469.92 | AA97: =SUM(X10:AA10) -> 786762.16 | AB97: =SUM(Y10:AB10) -> 806105.11 | AC97: =SUM(Z10:AC10) -> 831953.69 | AD97: =SUM(AA10:AD10) -> 858634.94 | AE97: =SUM(AB10:AE10) -> 885694.7 | AF97: =SUM(AC10:AF10) -> 900884 | AG97: =SUM(AD10:AG10) -> 913558 | ... BZ97: =SUM(BW10:BZ10) -> 2137901 | CH97: =CH10 -> 862122
B98: Operating profit | D98: =+D19 -> 200718 | E98: =+E19 -> 237123 | F98: =+F19 -> 232578 | G98: =+G19 -> 278430 | H98: =+H19 -> 313883 | I98: =+I19 -> 340713 | J98: =+J19 -> 354504 | K98: =+K19 -> 303279 | ... U98: =+U19 -> 1224918 | Z98: =SUM(W19:Z19) -> 232578 | AA98: =SUM(X19:AA19) -> 243171 | AB98: =SUM(Y19:AB19) -> 252531 | AC98: =SUM(Z19:AC19) -> 265788 | AD98: =SUM(AA19:AD19) -> 278430 | AE98: =SUM(AB19:AE19) -> 290259 | AF98: =SUM(AC19:AF19) -> 298583 | AG98: =SUM(AD19:AG19) -> 305434 | ... BZ98: =SUM(BW19:BZ19) -> 1224918 | CH98: =+CH19 -> 357891
B99: EBITDA | D99: =+D54 -> 200718 | E99: =+E54 -> 237123 | F99: =+F54 -> 232578 | G99: =+G54 -> 278430 | H99: =+H54 -> 313883 | I99: =+I54 -> 340713 | J99: =+J54 -> 354504 | K99: =+K54 -> 303279 | ... U99: =+U54 -> 1224918 | Z99: =SUM(W54:Z54) -> 232578 | AA99: =SUM(X54:AA54) -> 243171 | AB99: =SUM(Y54:AB54) -> 252531 | AC99: =SUM(Z54:AC54) -> 265788 | AD99: =SUM(AA54:AD54) -> 278430 | AE99: =SUM(AB54:AE54) -> 290259 | AF99: =SUM(AC54:AF54) -> 298583 | AG99: =SUM(AD54:AG54) -> 305434 | ... BZ99: =SUM(BW54:BZ54) -> 1224918 | CH99: =+CH54 -> 357891
B100: Adjusted EBITDA | D100: =+D59 -> 200718 | E100: =+E59 -> 222533 | F100: =+F59 -> 233340 | G100: =+G59 -> 278430 | H100: =+H59 -> 314517 | I100: =+I59 -> 341682 | J100: =+J59 -> 356208 | K100: =+K59 -> 304479 | ... U100: =+U59 -> 1212676 | Z100: =SUM(W59:Z59) -> 233340 | AA100: =SUM(X59:AA59) -> 243933 | AB100: =SUM(Y59:AB59) -> 253293 | AC100: =SUM(Z59:AC59) -> 266550 | AD100: =SUM(AA59:AD59) -> 278430 | AE100: =SUM(AB59:AE59) -> 286167 | AF100: =SUM(AC59:AF59) -> 295107 | AG100: =SUM(AD59:AG59) -> 301595.4 | ... BZ100: =SUM(BW59:BZ59) -> 1212676 | CH100: =+CH59 -> 347696
B101: Cash interest paid | D101: =-D78 -> 21595 | E101: =-E78 -> 32352 | F101: =-F78 -> 34339 | G101: =-G78 -> 37620 | H101: =-H78 -> 33887 | I101: =-I78 -> 32890 | J101: =-J78 -> 58566 | K101: =-K78 -> 44041 | ... U101: =-U78 -> 148876 | Z101: =-SUM(W78:Z78) -> 34339 | AA101: =-SUM(X78:AA78) -> 34692 | AB101: =-SUM(Y78:AB78) -> 37331 | AC101: =-SUM(Z78:AC78) -> 36284 | AD101: =-SUM(AA78:AD78) -> 37620 | AE101: =-SUM(AB78:AE78) -> 37020 | AF101: =-SUM(AC78:AF78) -> 34092 | AG101: =-SUM(AD78:AG78) -> 31569 | ... BZ101: =-SUM(BW78:BZ78) -> 148876 | CH101: =-CH78 -> 109993
B102: Net Income | D102: =+D30 -> 58992 | E102: =+E30 -> 42581 | F102: =+F30 -> 22668 | G102: =+G30 -> 30194 | H102: =+H30 -> 53655 | I102: =+I30 -> 68930 | J102: =+J30 -> 42414 | K102: =+K30 -> 21835 | ... U102: =+U30 -> 338228 | Z102: =SUM(W30:Z30) -> 22668 | AA102: =SUM(X30:AA30) -> 23610 | AB102: =SUM(Y30:AB30) -> 21610 | AC102: =SUM(Z30:AC30) -> 25003 | AD102: =SUM(AA30:AD30) -> 30194 | AE102: =SUM(AB30:AE30) -> 33203 | AF102: =SUM(AC30:AF30) -> 41641 | AG102: =SUM(AD30:AG30) -> 50461 | ... BZ102: =SUM(BW30:BZ30) -> 338228 | CH102: =+CH30 -> -336180
B103: Capex | D103: =-D80 -> 277094 | E103: =-E80 -> 150283 | F103: =-F80 -> 130063 | G103: =-G80 -> 174659 | H103: =-H80 -> 209786 | I103: =-I80 -> 270967 | J103: =-J80 -> 384045 | K103: =-K80 -> 267262 | ... U103: =-U80 -> 464008 | Z103: =-SUM(W80:Z80) -> 130063 | AA103: =-SUM(X80:AA80) -> 143615 | AB103: =-SUM(Y80:AB80) -> 144684 | AC103: =-SUM(Z80:AC80) -> 130493 | AD103: =-SUM(AA80:AD80) -> 174659 | AE103: =-SUM(AB80:AE80) -> 168039 | AF103: =-SUM(AC80:AF80) -> 174777 | AG103: =-SUM(AD80:AG80) -> 199104 | ... BZ103: =-SUM(BW80:BZ80) -> 464008 | CH103: =-CH80 -> 221275
B104: Free cash flow | D104: =+D82 -> -488781 | E104: =+E82 -> -940 | F104: =+F82 -> 48965 | G104: =+G82 -> 35802 | H104: =+H82 -> 28453 | I104: =+I82 -> 52338 | J104: =+J82 -> -30335 | K104: =+K82 -> -37098 | ... U104: =+U82 -> 608995 | Z104: =SUM(W82:Z82) -> 48965 | AA104: =SUM(X82:AA82) -> 70603 | AB104: =SUM(Y82:AB82) -> 79939 | AC104: =SUM(Z82:AC82) -> 87445 | AD104: =SUM(AA82:AD82) -> 35802 | AE104: =SUM(AB82:AE82) -> 32830 | AF104: =SUM(AC82:AF82) -> 41839.995 | AG104: =SUM(AD82:AG82) -> 30844.396 | ... BZ104: =SUM(BW82:BZ82) -> 608995 | CH104: =+CH82 -> -178579
B106: BALANCE SHEET
B108: Tangible fixed assets | D108: 651426 | E108: 674931.56 | F108: =Z108 -> 688430.04 | G108: =AD108 -> 596429 | H108: =AH108 -> 579157 | I108: =AL108 -> 610508 | J108: =AP108 -> 620088 | K108: =+AT108 -> 706079 | L108: 758168 | M108: 903661 | N108: 1176594 | O108: 1189828 | P108: =905725+42386+322286 -> 1270397 | Q108: =952241+110293+546466 -> 1609000 | R108: =1066121+89077+559367 -> 1714565 | S108: =1432724+105962+602415 -> 2141101 | T108: 2370034 | U108: =BZ108 -> 2370034 | W108: 694282.77 | X108: 687485.33 | Y108: 687660.27 | Z108: 688430.04 | AA108: 613848.06 | AB108: 615313 | AC108: 605396 | AD108: 596429 | AE108: 584228 | AF108: 573972 | AG108: 560625 | AH108: 579157 | AI108: 552349 | AJ108: 562438 | AK108: 576367 | AL108: 610508 | AM108: 592300 | AN108: 595048 | AO108: 600057 | AP108: 620088 | AQ108: 619637 | AR108: 625541 | AS108: 647645 | AT108: 706079 | AU108: 815142 | AV108: 869810 | AW108: 880811 | AX108: =M108 -> 903661 | AY108: 1118292 | AZ108: 1143109 | BA108: 1153315 | BB108: =N108 -> 1176594 | BC108: 1171339 | BD108: 1184512 | BE108: 1164988 | BF108: =O108 -> 1189828 | BG108: 1213714 | BH108: 1246145 | BI108: 1259219 | BJ108: =P108 -> 1270397 | BK108: 1391332 | BL108: 1450932 | BM108: 1507572 | BN108: =Q108 -> 1609000 | BO108: 1607047 | BP108: 1636927 | BQ108: 1655598 | BR108: =R108 -> 1714565 | BS108: 1759878 | BT108: 1877458 | BU108: 2066509 | BV108: =S108 -> 2141101 | BW108: 1759878 | BX108: =1484396+102192+628893 -> 2215481 | BY108: 2260721 | BZ108: =T108 -> 2370034 | CH108: 1176594
B109: Net pension liability | D109: 0 | E109: 0 | F109: =Z109 -> 0 | G109: =AD109 -> 0 | H109: =AH109 -> 0 | I109: =AL109 -> 0 | J109: =AP109 -> 0 | K109: =+AT109 -> 0 | L109: 0 | M109: 0 | N109: 0 | O109: 0 | P109: 0 | Q109: 0 | R109: 0 | S109: 0 | T109: 0 | U109: =BZ109 -> 0 | W109: 0 | X109: 0 | Y109: 0 | Z109: 0 | AA109: 0 | AB109: 0 | AC109: 0 | AD109: 0 | AE109: 0 | AF109: 0 | AG109: 0 | AH109: 0 | AI109: 0 | AJ109: 0 | AK109: 0 | AL109: 0 | AM109: 0 | AN109: 0 | AO109: 0 | AP109: 0 | AQ109: 0 | AR109: 0 | AS109: 0 | AT109: 0 | AU109: 0 | AV109: 0 | AW109: 0 | AX109: =M109 -> 0 | AY109: 0 | AZ109: 0 | BA109: 0 | BB109: =N109 -> 0 | BC109: 0 | BD109: 0 | BE109: 0 | BF109: =O109 -> 0 | BG109: 0 | BH109: 0 | BI109: 0 | BJ109: =P109 -> 0 | BK109: 0 | BM109: 0 | BN109: =Q109 -> 0 | BO109: 0 | BR109: =R109 -> 0 | BS109: 0 | BT109: 0 | BU109: 0 | BV109: =S109 -> 0 | BW109: 0 | BX109: 0 | BY109: 0 | BZ109: =T109 -> 0 | CH109: 0
B110: Inventory | D110: 2139 | E110: 1308 | F110: =Z110 -> 1108.5035 | G110: =AD110 -> 1422 | H110: =AH110 -> 1339 | I110: =AL110 -> 1692 | J110: =AP110 -> 488 | K110: =+AT110 -> 693 | L110: 693 | M110: 884 | O110: 2660 | P110: 3750 | Q110: 2576 | R110: 3639 | S110: 4517 | T110: 0 | U110: =BZ110 -> 0 | W110: 1323 | X110: 1355 | Y110: 1252 | Z110: 1108.5035 | AA110: 1533.6933 | AB110: 1662 | AC110: 1442 | AD110: 1422 | AE110: 1770 | AF110: 1308 | AG110: 1264 | AH110: 1339 | AI110: 1748 | AJ110: 1571 | AK110: 1814 | AL110: 1692 | AM110: 1623 | AN110: 1483 | AO110: 1288 | AP110: 488 | AQ110: 807 | AR110: 544 | AS110: 645 | AT110: 693 | AU110: 809 | AV110: 730 | AX110: =M110 -> 884 | BB110: =N110 -> 0 | BF110: =O110 -> 2660 | BJ110: =P110 -> 3750 | BM110: 0 | BN110: =Q110 -> 2576 | BO110: 0 | BR110: =R110 -> 3639 | BS110: 0 | BT110: 0 | BU110: 0 | BV110: =S110 -> 4517 | BW110: 0 | BX110: 4296 | BY110: 0 | BZ110: =T110 -> 0
B111: Trade debtors | D111: 54929 | E111: 63735 | F111: =Z111 -> 67824 | G111: =AD111 -> 62441 | H111: =AH111 -> 67252 | I111: =AL111 -> 65767 | J111: =AP111 -> 47402 | K111: =+AT111 -> 58830 | L111: 58830 | M111: 43006 | N111: 46058 | O111: 36377 | P111: 40562 | Q111: 39815 | R111: 47277 | S111: 74557 | T111: 79776 | U111: =BZ111 -> 79776 | W111: 70882 | X111: 77332 | Y111: 68873 | Z111: 67824 | AA111: 57452 | AB111: 52474 | AC111: 62141 | AD111: 62441 | AE111: 64608 | AF111: 66654 | AG111: 72140 | AH111: 67252 | AI111: 70859 | AJ111: 67500 | AK111: 67495 | AL111: 65767 | AM111: 54896 | AN111: 56260 | AO111: 51360 | AP111: 47402 | AQ111: 48989 | AR111: 48989 | AS111: 54785 | AT111: 58830 | AU111: 51563 | AV111: 50480 | AW111: 48955 | AX111: =M111 -> 43006 | AY111: 51551 | AZ111: 53290 | BA111: 53558 | BB111: =N111 -> 46058 | BC111: 56047 | BD111: 49617 | BE111: 45826 | BF111: =O111 -> 36377 | BG111: 47707 | BH111: 50350 | BI111: 49846 | BJ111: =P111 -> 40562 | BK111: 44933 | BL111: 47751 | BM111: 47595 | BN111: =Q111 -> 39815 | BO111: 52163 | BP111: 55927 | BQ111: 55099 | BR111: =R111 -> 47277 | BS111: 50768 | BT111: 56452 | BU111: 99707 | BV111: =S111 -> 74557 | BW111: 80612 | BX111: 89089 | BY111: 83655 | BZ111: =T111 -> 79776 | CH111: 46058
B112: Trade creditors | D112: 239684 | E112: 232650 | F112: =Z112 -> 259902 | G112: =AD112 -> 283981 | H112: =AH112 -> 339670 | I112: =AL112 -> 382494 | J112: =AP112 -> 268537 | K112: =+AT112 -> 277675 | L112: 268536.59 | M112: 280031 | N112: 250231 | O112: 278721 | P112: 292741 | Q112: 328946 | R112: 351325 | S112: 381537 | T112: 450152 | U112: =BZ112 -> 450152 | W112: 274399.4 | X112: 276236.06 | Y112: 279301.61 | Z112: 259902 | AA112: 281336.49 | AB112: 278093 | AC112: 285245 | AD112: 283981 | AE112: 308142.74 | AF112: 328417 | AG112: 341959 | AH112: 339670 | AI112: =235152+129210 -> 364362 | AJ112: =250872+126464 -> 377336 | AK112: =260415+127944 -> 388359 | AL112: =255806+126688 -> 382494 | AM112: =(270748+124080) -> 394828 | AN112: =(278731+116761) -> 395492 | AO112: =(273660+108320) -> 381980 | AP112: 268537 | AQ112: =(298518+104718) -> 403236 | AR112: =304215+141402 -> 445617 | AS112: =301979+113788 -> 415767 | AT112: 277675 | AU112: 285372.27 | AV112: 306509 | AW112: 297379 | AX112: =M112 -> 280031 | AY112: 288947.47 | AZ112: 267212 | BA112: 294583 | BB112: =N112 -> 250231 | BC112: 272472 | BD112: 274995 | BE112: 301101 | BF112: =O112 -> 278721 | BG112: 304919 | BH112: 298625 | BI112: 308141 | BJ112: =P112 -> 292741 | BK112: 319775 | BL112: 333554 | BM112: 343933 | BN112: =Q112 -> 328946 | BO112: 361185 | BP112: 360453 | BQ112: 367843 | BR112: =R112 -> 351325 | BS112: 382085 | BT112: 395892 | BU112: 402031 | BV112: =S112 -> 381537 | BW112: 434766 | BX112: 452326 | BY112: 465069 | BZ112: =T112 -> 450152 | CH112: 250231
...

Sheet KPIs
B2: Consolidated | D2: Q4 FY 26 | E2: Q3 FY 26 | F2: Q2 FY 26 | G2: Q1 FY 26 | H2: Q4 FY 25 | I2: Q3 FY 25 | J2: Q2 FY 25 | K2: Q1 FY 25 | L2: Q4 FY 24 | M2: Q3 FY 24 | N2: Q2 FY 24 | O2: Q1 FY 24 | P2: Q4 FY 23 | Q2: Q3 FY 23 | R2: Q2 FY 23 | S2: Q1 FY 23 | T2: Q4 FY 22 | U2: Q3 FY 22 | V2: Q2 FY 22 | W2: Q1 FY 22 | X2: Q4 FY 21 | Y2: Q3 FY 21 | Z2: Q2 FY 21 | AA2: Q1 FY 21 | AB2: Q4 FY 20 | AC2: Q3 FY 20 | AD2: Q2 FY 20 | AE2: Q1 FY 20 | AF2: Q4 FY19 | AG2: Q3 FY19 | AH2: Q2 FY19 | AI2: Q1 FY 19 | AJ2: Q4 FY18 | AK2: Q3 FY 18 | AL2: Q2 FY 18 | AM2: Q1 FY 18 | AN2: Q4 FY17 | AO2: Q3 FY17 | AP2: Q2 FY17 | AQ2: Q1 FY 17 | AR2: Q4 FY16 | AS2: Q3 FY16 | AT2: Q2 FY16 | AU2: Q1 FY16 | AV2: Q4 FY15 | AW2: Q3 FY15 | AX2: Q4 FY15 | AY2: Q1 FY15 | AZ2: Q4 FY 14 | BA2: Q3 FY 14 | BB2: Q2 FY 14 | BC2: Q1 FY 14 | BD2: Q4 FY 13
D3: 46112 | E3: 46022 | F3: 45930 | G3: 45838 | H3: 45746 | I3: 45656 | J3: 45565 | K3: 45473 | L3: 45382 | M3: 45290 | N3: 45199 | O3: 45107 | P3: 45016 | Q3: 44926 | R3: 44834 | S3: 44742 | T3: 44651 | U3: 44561 | V3: 44469 | W3: 44377 | X3: 44286 | Y3: 44196 | Z3: 44104 | AA3: 44012 | AB3: 43921 | AC3: 43830 | AD3: 43738 | AE3: 43646 | AF3: 43555 | AG3: 43465 | AH3: 43373 | AI3: 43281 | AJ3: 43190 | AK3: 43100 | AL3: 43008 | AM3: 42916 | AN3: 42825 | AO3: 42735 | AP3: 42643 | AQ3: 42551 | AR3: 42460 | AS3: 42369 | AT3: 42277 | AU3: 42185 | AV3: 42094 | AW3: 42004 | AX3: 41912 | AY3: 41820 | AZ3: 41729 | BA3: 41639 | BB3: 41547 | BC3: 41455 | BD3: 41364
B6: Revenues Rs Mn | D6: 553832 | E6: 539816 | F6: 521454 | G6: 494626 | H6: 478762 | I6: 468780.32 | J6: 448963.34 | K6: 418604.62 | L6: 409376.96 | M6: 414217.74 | N6: 370437.58 | O6: 374400.45 | P6: 360090 | Q6: 358044 | R6: 345268 | S6: 328046 | T6: 315003 | U6: 298666 | V6: 283264 | W6: 268536 | X6: 257473 | Y6: 265177.93 | Z6: 250603.75 | AA6: 232903.32 | AB6: 230187.29 | AC6: 213436.28 | AD6: 211312.51 | AE6: 207379 | AF6: 206022 | AG6: 202310 | AH6: 201477 | AI6: 197992 | AJ6: 196343.41 | AK6: 203185.72 | AL6: 217769.23 | AM6: 219581 | AN6: 219346 | AO6: 233357 | AP6: 246515 | AQ6: 255464.82 | AR6: 249595.62 | AS6: 240658.6 | AT6: 238356.91 | AU6: 236709.01 | AV6: 230155.28 | AW6: 232170.78 | AX6: 228452.08 | AY6: 229616.4 | AZ6: 222193.48 | BA6: 219385.43 | BB6: 213243.7 | BC6: 202639.24 | BD6: 195820.75
B7: EBITDA Rs Mn | D7: 320382 | E7: 311436 | F7: 299190 | G7: 281668 | H7: 274043 | I7: 290566.86 | J7: 255125.21 | K7: 230259.05 | L7: 224251.17 | M7: 224368.5 | N7: 196649.57 | O7: 197460.51 | P7: 188067 | Q7: 186007.49 | R7: 177212 | S7: 166044.06 | T7: 159984.32 | U7: 149047.21 | V7: 140177 | W7: 131894.36 | X7: 125831 | Y7: 121777.18 | Z7: 112593.26 | AA7: 101185.56 | AB7: 97611.621 | AC7: 88118.972 | AD7: 89362.531 | AE7: 84926 | AF7: 68064 | AG7: 63069 | AH7: 63433 | AI7: 68370 | AJ7: 70341.144 | AK7: 75870.785 | AL7: 80036.779 | AM7: 78230.605 | AN7: 79928.175 | AO7: 85704.884 | AP7: 94661.648 | AQ7: 95913.042 | AR7: 91882.273 | AS7: 84747.375 | AT7: 82656.02 | AU7: 82397.036 | AV7: 80505.303 | AW7: 78275.606 | AX7: 77494.401 | AY7: 77668.995 | AZ7: 73185.69 | BA7: 70933.946 | BB7: 68321.052 | BC7: 65449.095 | BD7: 60605.204
B8: EBITDA Margins | D8: 0.57848177 | E8: 0.57692992 | F8: 0.57376106 | G8: 0.56945652 | H8: 0.57239923 | I8: 0.61983587 | J8: 0.56825399 | K8: 0.55006333 | L8: 0.54778649 | M8: 0.54166802 | N8: 0.5308575 | O8: 0.52740456 | P8: =P7/P6 -> 0.52227776 | Q8: =Q7/Q6 -> 0.51951014 | R8: =R7/R6 -> 0.51325927 | S8: =S7/S6 -> 0.5061609 | T8: =T7/T6 -> 0.50788188 | U8: =U7/U6 -> 0.49904312 | V8: =V7/V6 -> 0.49486345 | W8: =W7/W6 -> 0.49116083 | ... AA8: =AA7/AA6 -> 0.43445307 | AB8: 0.42405304 | AC8: 0.42602828 | AD8: 0.42289276 | AE8: =AE7/AE6 -> 0.40952073 | AF8: =AF7/AF6 -> 0.33037248 | AG8: =AG7/AG6 -> 0.31174435 | AH8: =AH7/AH6 -> 0.31483991 | AI8: 0.34048805 | AJ8: 0.3582557 | AK8: 0.37340609 | AL8: 0.36753026 | AM8: 0.35627208 | AN8: 0.36439269 | AO8: 0.36726938 | AP8: 0.38399883 | AQ8: 0.3754452 | AR8: 0.36812454 | AS8: 0.35214771 | AT8: 0.34677417 | AU8: 0.3480942 | AV8: 0.3497869 | AW8: 0.33714667 | AX8: 0.33921512 | AY8: 0.33825543 | AZ8: 0.3293782 | BA8: 0.32333025 | BB8: 0.32038955 | BC8: 0.32298332 | BD8: 0.30949327
B9: ARPU
B10: Capex Rs Mn | D10: 160656.06 | E10: 117868.76 | F10: 113623.43 | G10: 83069.67 | H10: 144008.3 | I10: 91608.301 | J10: 89999.029 | K10: 97288.005 | L10: 130559.65 | M10: 118325.99 | N10: 92060.654 | O10: 104857.55 | P10: 114360.33 | Q10: 93135.555 | R10: 70469 | S10: 63981.568 | T10: 59970.984 | U10: 61014.835 | V10: 69722 | W10: 65907.795 | X10: 68464.592 | Y10: 68637.73 | Z10: 65833.433 | AA10: 38749.534 | AB10: 110448.03 | AC10: 50220.16 | AD10: 37901 | AE10: 50468 | AF10: 62735 | AG10: 65679 | AH10: 76845 | AI10: 82167 | AJ10: 62824.136 | AK10: 64656.585 | AL10: 74838.181 | AM10: 65857.09 | AN10: 38081.655 | AO10: 58536.753 | AP10: 52875.197 | AQ10: 49251.557 | AR10: 60573.652 | AS10: 55081.972 | AT10: 50342.573 | AU10: 39921.133 | AV10: 64460.225 | AW10: 45095.067 | AX10: 37270.505 | AY10: 39856.613 | AZ10: 33278.162 | BA10: 28219.332 | BB10: 21391.208 | BC10: 22954.363 | BD10: 32878.131
B12: India | D12: =D2 -> Q4 FY 26 | E12: =E2 -> Q3 FY 26 | F12: =F2 -> Q2 FY 26 | G12: =G2 -> Q1 FY 26 | H12: =H2 -> Q4 FY 25 | I12: =I2 -> Q3 FY 25 | J12: =J2 -> Q2 FY 25 | K12: =K2 -> Q1 FY 25 | ... BD12: =BD2 -> Q4 FY 13
D13: =D3 -> 46112 | E13: =E3 -> 46022 | F13: =F3 -> 45930 | G13: =G3 -> 45838 | H13: =H3 -> 45746 | I13: =I3 -> 45656 | J13: =J3 -> 45565 | K13: =K3 -> 45473 | ... BD13: =BD3 -> 41364
B15: Revenues Rs Mn | D15: 395656 | E15: 392255 | F15: 386901 | G15: 375846 | H15: 367345.4 | I15: 364024.32 | J15: 349837.34 | K15: 324001.62 | L15: 285127.96 | M15: 278106.91 | N15: 269946.91 | O15: 263746.88 | P15: 252503 | Q15: 249615.05 | R15: 243333 | S15: 233189.22 | T15: 225003.61 | U15: 209126.82 | V15: 198904 | W15: 188283.79 | X15: 183378 | Y15: 190070.71 | Z15: 180223.69 | AA15: 169410.61 | AB15: 167343.07 | AC15: 151938.71 | AD15: 153609.73 | AE15: 153445.91 | AF15: 152408 | AG15: 147683 | AH15: 149198 | AI15: 149300 | AJ15: 147955.46 | AK15: 152941.79 | AL15: 167281.76 | AM15: 172436.12 | AN15: 170356.06 | AO15: 180126.19 | AP15: 192188.03 | AQ15: 191546.87 | AR15: 183281.06 | AS15: 176936.86 | AT15: 174522 | AU15: 173696.4 | AV15: 166705.33 | AW15: 162563.97 | AX15: 158154.88 | AY15: 157870.33 | AZ15: 149103.91 | BA15: 144430.31 | BB15: 140792.92 | BC15: 141232.84 | BD15: 133576.45
B16: EBITDA Rs Mn | D16: 239653 | E16: 236759 | F16: 232039 | G16: 223515 | H16: 220237.1 | I16: 240270.86 | J16: 207866.21 | K16: 186808.05 | L16: 152933.55 | M16: 150003.35 | N16: 145611.71 | O16: 141542.09 | P16: 134026 | Q16: 131671.4 | R16: 126056 | S16: 118816.8 | T16: 114360.66 | U16: 104066.71 | V16: 98576 | W16: 92734.138 | X16: 89702.465 | Y16: 85887.586 | Z16: 80025.63 | AA16: 72664.225 | AB16: 68826.472 | AC16: 59632.541 | AD16: 63213.158 | AE16: 60630.453 | AF16: 46466 | AG16: 41152 | AH16: 42487 | AI16: 49133 | AJ16: 52372.37 | AK16: 57657.564 | AL16: 63241.204 | AM16: 64701.998 | AN16: 66986.133 | AO16: 72517.709 | AP16: 82205.715 | AQ16: 81957.514 | AR16: 77349.091 | AS16: 71883.994 | AT16: 70171.619 | AU16: 69993.8 | AV16: 67869.886 | AW16: 63594.487 | AX16: 61087.849 | AY16: 60524.446 | AZ16: 55047.256 | BA16: 51970.449 | BB16: 49052.518 | BC16: 49316.433 | BD16: 45237.75
B17: EBITDA Margins | D17: 0.60571052 | E17: 0.6035844 | F17: 0.5997374 | G17: 0.59469836 | H17: 0.59953684 | I17: 0.66004068 | J17: 0.5941796 | K17: 0.57656518 | L17: 0.53636814 | M17: 0.53937296 | N17: 0.5394087 | O17: 0.53665884 | P17: =P16/P15 -> 0.53078973 | Q17: =Q16/Q15 -> 0.52749786 | R17: =R16/R15 -> 0.51803907 | S17: =S16/S15 -> 0.50952956 | T17: =T16/T15 -> 0.50826143 | U17: =U16/U15 -> 0.49762488 | V17: =V16/V15 -> 0.49559587 | W17: =W16/W15 -> 0.49252321 | ... AH17: =AH16/AH15 -> 0.28476923 | AI17: 0.329 | AJ17: 0.3539739 | AK17: 0.37699026 | AL17: 0.378052 | AM17: 0.375223 | AN17: 0.39321251 | AO17: 0.40259392 | AP17: 0.42773587 | AQ17: 0.42787185 | AR17: 0.42202447 | AS17: 0.40626919 | AT17: 0.40207892 | AU17: 0.40296633 | AV17: 0.40712487 | AW17: 0.39119669 | AX17: 0.38625333 | AY17: 0.38338075 | AZ17: 0.3691872 | BA17: 0.35983063 | BB17: 0.34840188 | BC17: 0.34918531 | BD17: 0.33866561
B18: ARPU
B19: Capex Rs Mn | D19: 134881.79 | E19: 92494.787 | F19: 96428.504 | G19: 72733.608 | H19: 125525.65 | I19: 79795.234 | J19: 75848.703 | K19: 85030.141 | L19: 84912.428 | M19: 77562.56 | N19: 77783.167 | O19: 93267.494 | P19: 89894 | Q19: 80953.946 | R19: 56840 | S19: 52879.784 | T19: 42767.089 | U19: 46537.76 | V19: 57993 | W19: 57135.006 | X19: 51413.927 | Y19: 53914.771 | Z19: 53829.83 | AA19: 33411.335 | AB19: 92270.146 | AC19: 39212.274 | AD19: 27469 | AE19: 43223 | AF19: 41075 | AG19: 53091 | AH19: 69036 | AI19: 78664 | AJ19: 46223.672 | AK19: 59600.602 | AL19: 71440.418 | AM19: 62417.7 | AN19: 28496.571 | AO19: 53713.602 | AP19: 45803.814 | AQ19: 41217.329 | AR19: 41440.797 | AS19: 42436.367 | AT19: 38360.392 | AU19: 29417.867 | AV19: 40920.073 | AW19: 27090.226 | AX19: 20588.402 | AY19: 29470.214 | AZ19: 20311.947 | BA19: 17420.951 | BB19: 10428.894 | BC19: 12799.531 | BD19: 18794.263
B20: Total Customers Base | C20: 000's | D20: 482421.3 | E20: 465918.03 | F20: 449737.71 | G20: 436095.84 | H20: 424461.23 | I20: 413868.96 | J20: 406527.64 | K20: 409274.82 | L20: 406348.72 | M20: 397011.7 | N20: 389452 | O20: 362471.35 | P20: 375343.83 | Q20: 355872.91 | R20: 364000 | S20: 362471.35 | T20: 359903.57 | U20: 355872.91 | V20: 354511 | W20: 350866.94 | X20: 350304.39 | Y20: 336224 | Z20: 320604.81 | AA20: 305688.59 | AB20: 309754 | AC20: 308738 | AD20: 304703 | AE20: 301451 | AF20: 302206 | AG20: 303268 | AH20: 348452.88 | AI20: 363165 | AJ20: 322292 | AK20: 307963.61 | AL20: 299471.37 | AM20: 297841.2 | AN20: 290329.5 | AO20: 282270.4 | AP20: 276142.79 | AQ20: 271614.84 | AR20: 266625.54 | AS20: 257992.86 | AT20: 249311.44 | AU20: 244518.12 | AV20: 239501.8 | AW20: 230413.41 | AX20: 224663.76 | AY20: 222149.48 | AZ20: 217887.45 | BA20: 210675.49 | BB20: 205367.22 | BC20: 202689.51 | BD20: 199603.91
B22: Mobile Services
B23: Total revenues | D23: 288305 | E23: 286516 | F23: 281167.49 | G23: 273966 | H23: 266168.4 | I23: 262687 | J23: 248371 | K23: 225274.4 | L23: 220656.78 | M23: 216385.55 | N23: 209520.94 | O23: 203924.44 | P23: 195492.58 | Q23: 193526.52 | R23: 189576 | S23: 181404.25 | T23: 176167.89 | U23: 160917.04 | V23: 151914 | W23: 143055.61 | X23: 140796.53 | Y23: 147789.16 | Z23: 138319.26 | AA23: 128771.03 | AB23: 129528.76 | AC23: 111652.89 | AD23: 109814.35 | AE23: 108667 | AF23: 106322 | AG23: 101894 | AH23: 102521 | AI23: 104803 | AJ23: 103532.14 | AK23: 107510.4 | AL23: 122450.17 | AM23: 129146.71 | AN23: 129718.05 | AO23: 138129.62 | AP23: 147243.01 | AQ23: 150420.13 | AR23: 146525.16 | AS23: 139750.42 | AT23: 136555.88 | AU23: 137986.81 | AV23: 134134.76 | AW23: 131634.53 | AX23: 126341.71 | AY23: 127524.97 | AZ23: 120835.81
B24: EBITDA | D24: 174790 | E24: 173298 | F24: 169515 | G24: 162743 | H24: 157535 | I24: 154568 | J24: 141710 | K24: 125274 | L24: 121607.11 | M24: 119239.75 | N24: 115039.44 | O24: 111664.93 | P24: 105226.98 | Q24: 104121.32 | R24: 99258 | S24: 93280.917 | T24: 89215.332 | U24: 79434.084 | V24: 74679 | W24: 70335.22 | X24: 66896.954 | Y24: 64598.766 | Z24: 58919.083 | AA24: 52227.348 | AB24: 50795.573 | AC24: 40109.023 | AD24: 39913.034 | AE24: 38742 | AF24: 25657 | AG24: 19498 | AH24: 21468 | AI24: 27603 | AJ24: 29428.12 | AK24: 35090.921 | AL24: 42087.359 | AM24: 44281.23 | AN24: 47873.155 | AO24: 52986.339 | AP24: 62775.283 | AQ24: 64098.838 | AR24: 58615.962 | AS24: 54362.286 | AT24: 52624.326 | AU24: 53425.333 | AV24: 51743.624 | AW24: 49128.239 | AX24: 46457.804 | AY24: 47411.659 | AZ24: 42174.046
B25: EBITDA Margins | D25: 0.60626767 | E25: 0.6048458 | F25: 0.60289578 | G25: 0.59402627 | H25: 0.59186214 | I25: 0.5884113 | J25: 0.57055775 | K25: 0.55609514 | L25: 0.55111428 | M25: 0.55105227 | N25: 0.5490594 | O25: 0.54757994 | P25: =P24/P23 -> 0.53826583 | Q25: =Q24/Q23 -> 0.53802092 | R25: =R24/R23 -> 0.52357893 | S25: =S24/S23 -> 0.51421572 | T25: =T24/T23 -> 0.50642221 | U25: =U24/U23 -> 0.49363377 | V25: =V24/V23 -> 0.49158735 | W25: =W24/W23 -> 0.49166348 | ... AH25: =AH24/AH23 -> 0.209401 | AI25: 0.263 | AJ25: 0.2842414 | AK25: 0.32639561 | AL25: 0.34371008 | AM25: 0.34287541 | AN25: 0.36905546 | AO25: 0.38359866 | AP25: 0.42633794 | AQ25: 0.42613206 | AR25: 0.40004024 | AS25: 0.38899552 | AT25: 0.38536843 | AU25: 0.3871771 | AV25: 0.3857585 | AW25: 0.37321695 | AX25: 0.36771547 | AY25: 0.37178333 | AZ25: 0.34901944
B26: Customer Base | D26: 373243.06 | E26: 368543.36 | F26: 364192.33 | G26: 362796.09 | H26: 361593.12 | I26: 356587.55 | J26: 351640.24 | K26: 354515.14 | L26: 352252.81 | M26: 345570.21 | N26: 342305.36 | O26: 338562.39 | P26: 335412.28 | Q26: 332243.62 | R26: 327797.96 | S26: 327307.74 | T26: 326043.25 | U26: 322917.59 | V26: 323476 | W26: 321238.12 | X26: 321373.51 | Y26: 307947.59 | Z26: 293742.22 | AA26: 279868.95 | AB26: 283667.18 | AC26: 283036.25 | AD26: 279430 | AE26: 276817 | AF26: 282640 | AG26: 284224 | AH26: 332764 | AI26: 344564 | AJ26: 304192 | AK26: 290113.08 | AL26: 282047.47 | AM26: 280647.32 | AN26: 273648.38 | AO26: 265852.6 | AP26: 259940.67 | AQ26: 255734.65 | AR26: 251237.26 | AS26: 243289.4 | AT26: 235211.88 | AU26: 230661.67 | AV26: 226017.41 | AW26: 217215.04 | AX26: 211752.43 | AY26: 209411.04 | AZ26: 205519.18 | BA26: 198513.45 | BB26: 193456.9 | BC26: 190948.45 | BD26: 188220.38
B27: Net Additions | C27: 000's | D27: 4699.704 | E27: 4351.024 | F27: 1396.242 | G27: 1202.966 | H27: 5005.57 | I27: 4947.31 | J27: -2874.896 | K27: 2262.328 | L27: 6682.606 | M27: 3264.844 | N27: 3742.977 | O27: 3150.103 | P27: 3168.662 | Q27: 4445.66 | R27: 490.22 | S27: 1264.486 | T27: 3125.661 | U27: -558.875 | V27: 2238.345 | W27: -135.387 | X27: 13425.924 | Y27: 14205.366 | Z27: 13873.267 | AA27: -3798.231 | AB27: 630.931 | AC27: 3606.145 | AD27: 2613 | AE27: -1533 | AF27: -1585 | AG27: -48539 | AH27: -11800 | AI27: 40372 | AJ27: 14079 | AK27: 8065.61 | AL27: 1400.152 | AM27: 6998.934 | AN27: 7795.778 | AO27: 5911.939 | AP27: 4206.016 | AQ27: 4497.387 | AR27: 7947.859 | AS27: 8077.522 | AT27: 4550.216 | AU27: 4644.253 | AV27: 8802.371 | AW27: 5462.609 | AX27: 2341.394 | AY27: 3891.856 | AZ27: 7005.732 | BA27: 5056.549 | BB27: 2508.45 | BC27: 2728.069 | BD27: 6298.28
B28: Pre-Paid (as % of total Customer Base) | C28: % | L28: 0.93446349 | M28: 0.93536918 | N28: 0.93729436 | O28: 0.93949491 | P28: 0.94141056 | Q28: 0.94284787 | R28: 0.94406394 | S28: 0.94484369 | T28: 0.94539226 | U28: 0.94551319 | V28: 0.94659875 | W28: 0.94732225 | X28: 0.9482444 | Y28: 0.94803015 | Z28: 0.94788702 | AA28: 0.94778647 | AB28: 0.94791527 | AC28: 0.94436151 | AD28: 0.94914 | AE28: 0.949 | AF28: 0.935 | AG28: 0.936 | AH28: 0.944 | AI28: 0.946 | AJ28: 0.939 | AK28: 0.93705363 | AL28: 0.93710301 | AM28: 0.93752912 | AN28: 0.93663113 | AO28: 0.93659574 | AP28: 0.93702492 | AQ28: 0.93877815 | AR28: 0.94004459 | AS28: 0.94102282 | AT28: 0.94227018 | AU28: 0.94425437 | AV28: 0.94583086 | AW28: 0.94627702 | AX28: 0.94684847 | AY28: 0.94945712 | AZ28: 0.95102192 | BA28: 0.95258166 | BB28: 0.95406066 | BC28: 0.95612838 | BD28: 0.95762696
B29: Monthly Churn | C29: % | D29: 0.024253394 | E29: 0.025802568 | F29: 0.028792908 | G29: 0.026784197 | H29: 0.023096849 | I29: 0.02493076 | J29: 0.03235432 | K29: 0.028147964 | L29: 0.023667535 | M29: 0.028518422 | N29: 0.029213686 | O29: 0.027832227 | P29: 0.028029256 | Q29: 0.029649219 | R29: 0.032546472 | S29: 0.029725829 | T29: 0.028139047 | U29: 0.029222616 | V29: 0.030038177 | W29: 0.027981353 | X29: 0.022472763 | Y29: 0.019245406 | Z29: 0.017216848 | AA29: 0.02212747 | AB29: 0.025705219 | AC29: 0.026322916 | AD29: 0.02103317 | AE29: 0.026 | AF29: 0.028 | AG29: 0.073 | AH29: 0.041 | AI29: 0.02 | AJ29: 0.028 | AK29: 0.033443775 | AL29: 0.039282704 | AM29: 0.038053703 | AN29: 0.036269536 | AO29: 0.041295692 | AP29: 0.03667598 | AQ29: 0.03565238 | AR29: 0.032697666 | AS29: 0.034489304 | AT29: 0.034848759 | AU29: 0.032947994 | AV29: 0.025127286 | AW29: 0.026562334 | AX29: 0.030672787 | AY29: 0.026988312 | AZ29: 0.024230429 | BA29: 0.026855512 | BB29: 0.032174193 | BC29: 0.032044944 | BD29: 0.031806285
B31: Average Revenue Per User (ARPU) | C31: Rs | D31: 257.19404 | E31: 258.62704 | F31: 255.7148 | G31: 250.25513 | H31: 244.99939 | I31: 245.29179 | J31: 232.97287 | K31: 210.58504 | L31: 208.8588 | M31: 207.8921 | N31: 202.80929 | O31: 199.76735 | P31: 193.30021 | Q31: 193.44512 | R31: 189.77471 | S31: 183.21636 | T31: 178.25448 | U31: 162.51066 | V31: 153.43464 | W31: 146.13645 | X31: 145.21147 | Y31: 166.08182 | Z31: 162.19168 | AA31: 156.80841 | AB31: 154.07077 | AC31: 134.85133 | AD31: 128.00756 | AE31: 129 | AF31: 123 | AG31: 104 | AH31: 100 | AI31: 105 | AJ31: 116 | AK31: 122.80158 | AL31: 144.7471 | AM31: 154.48483 | AN31: 157.58473 | AO31: 172.02435 | AP31: 187.87111 | AQ31: 195.73454 | AR31: 194.19472 | AS31: 191.98927 | AT31: 192.59115 | AU31: 198.24026 | AV31: 198.37007 | AW31: 202.27863 | AX31: 197.54347 | AY31: 202.47964 | AZ31: 196.36843 | BA31: 194.65963 | BB31: 192.06987 | BC31: 200.22362 | BD31: 192.88646
B32: Average Revenue Per User (ARPU) | C32: US | D32: 2.8040177 | E32: 2.9049595 | F32: 2.9297015 | G32: 2.9296332 | H32: 2.8367087 | I32: 2.9070225 | J32: 2.7824511 | K32: 2.5262106 | L32: 2.5134837 | M32: 2.4981745 | N32: 2.4586682 | O32: 2.4300533 | P32: 2.3493574 | Q32: 2.3545447 | R32: 2.3757475 | S32: 2.3785323 | T32: 2.3714039 | U32: 2.1761057 | V32: 2.0719129 | W32: 1.9905756 | X32: 1.9822062 | Y32: 2.2469425 | Z32: 2.1827828 | AA32: 2.0684852 | AB32: 2.1439911 | AC32: 1.9007646 | AD32: 1.82606 | AE32: 1.9 | AF32: 1.7 | AG32: 1.4 | AH32: 1.4420259 | AI32: 1.6 | AJ32: 1.8 | AK32: 1.8985531 | AL32: 2.2491684 | AM32: 2.3972818 | AN32: 2.3490016 | AO32: 2.5434848 | AP32: 2.7986857 | AQ32: 2.9298055 | AR32: 2.8694501 | AS32: 2.9153553 | AT32: 2.9674581 | AU32: 3.1226995 | AV32: 3.1923354 | AW32: 3.2686072 | AX32: 3.2660685 | AY32: 3.380715 | AZ32: 3.1819983 | BA32: 3.1369309 | BB32: 3.0610167 | BC32: 3.5843635 | BD32: 3.5642862
B34: Voice
B35: Total Revenues | C35: Rs Mn | AB35: 131222.2 | AC35: 113969.35 | AD35: 108118 | AE35: 107240 | AF35: 104870 | AG35: 100532 | AH35: 100703.82 | AI35: 103036 | AJ35: 102221 | AK35: 105709.12 | AL35: 122114.64 | AM35: 128569.8 | AN35: 127612.36 | AO35: 135643.69 | AP35: 145065.18 | AQ35: 148765.24 | AR35: 146524.88 | AS35: 139750.38 | AT35: 136555.84 | AU35: 137986.78 | AV35: 134134.7 | AW35: 131634.53 | AX35: 126341.71 | AY35: 127524.97 | AZ35: 120834.81 | BA35: 116445.64 | BB35: 113540.81 | BC35: 116013.33 | BD35: 110173.41
B36: Voice Average Revenue Per User (ARPU) | C36: Rs | AM36: 111.41414 | AN36: 114.31564 | AO36: 123.19973 | AP36: 131.58581 | AQ36: 138.71664 | AR36: 138.06522 | AS36: 136.54105 | AT36: 139.84396 | AU36: 148.06822 | AV36: 151.39895 | AW36: 156.66026 | AX36: 157.69544 | AY36: 165.78677 | AZ36: 162.33414 | BA36: 161.2226 | BB36: 160.35176 | BC36: 165.51684 | BD36: 159.37714
B37: Minutes on the network | C37: Mn | D37: 1279577.7 | E37: 1265645.3 | F37: 1248797.8 | G37: 1241763.1 | H37: 1253671.1 | I37: 1233305.5 | J37: 1199794.6 | K37: 1195079.7 | L37: 1209563.7 | M37: 1160820.4 | N37: 1147713.3 | O37: 1148792.6 | P37: 1124343.1 | Q37: 1081949.7 | R37: 1063010.6 | S37: 1078960.7 | T37: 1051115.7 | U37: 1029802.1 | V37: 1020414.6 | W37: 1002263.3 | X37: 996793.1 | Y37: 924910.76 | Z37: 860854.24 | AA37: 820246.12 | AB37: 821899.94 | AC37: 758896.61 | AD37: 716641.88 | AE37: 737108.47 | AF37: 731186.54 | AG37: 702880.67 | AH37: 693060.86 | AI37: 684191.41 | AJ37: 592657.14 | AK37: 494545.91 | AL37: 437142.18 | AM37: 421911.63 | AN37: 381236.13 | AO37: 330216.62 | AP37: 313403.14 | AQ37: 314831.3
B38: Voice Usage per customer | C38: min | D38: 1150.4277 | E38: 1151.6765 | F38: 1145.1531 | G38: 1143.4371 | H38: 1162.6866 | I38: 1160.1069 | J38: 1134.989 | K38: 1127.828 | L38: 1157.9182 | M38: 1126.6651 | N38: 1123.0891 | O38: 1137.8366 | P38: 1122.2648 | Q38: 1093.5772 | R38: 1081.701 | S38: 1103.8297 | T38: 1082.7037 | U38: 1060.6729 | V38: 1052.8949 | W38: 1043.988 | X38: 1052.798 | Y38: 1026.7119 | Z38: 1004.7855 | AA38: 993.71886 | AB38: 965.01021 | AC38: 897.94506 | AD38: 848.47755 | AE38: 888 | AF38: 858 | AG38: 725.58097 | AH38: 686 | AI38: 700 | AJ38: 670 | AK38: 574.51066 | AL38: 518.16118 | AM38: 506.95378 | AN38: 470.77722 | AO38: 418.7832 | AP38: 405.88234 | AQ38: 414.23225 | AR38: 415.22218 | AS38: 404.53383 | AT38: 404.44668 | AU38: 423.8887 | AV38: 417.98212 | AW38: 415.83273 | AX38: 418.43929 | AY38: 435.31704 | AZ38: 436.86683 | BA38: 434.18946 | BB38: 436.50353 | BC38: 454.89342 | BD38: 455.40297
B39: Voice Realization per minute | C39: paisa | AM39: 21.977179 | AN39: 24.282322 | AO39: 29.418498 | AP39: 32.419694 | AQ39: 33.487648 | AR39: 33.250925 | AS39: 33.75269 | AT39: 34.576613 | AU39: 34.930919 | AV39: 36.221395 | AW39: 37.673864 | AX39: 37.686576 | AY39: 38.084325 | AZ39: 37.159361 | BA39: 37.131854 | BB39: 36.735501 | BC39: 36.385851 | BD39: 34.996949
B41: Non Voice Revenue
B42: % of Mobile revenues | C42: % | AM42: 0.27880208 | AN42: 0.27457665 | AO42: 0.28382393 | AP42: 0.29959527 | AQ42: 0.2913022 | AR42: 0.28903723 | AS42: 0.28880893 | AT42: 0.27388169 | AU42: 0.25308704 | AV42: 0.23678531 | AW42: 0.2256435 | AX42: 0.20240669 | AY42: 0.18178667 | AZ42: 0.17378108 | BA42: 0.17214879 | BB42: 0.16536828 | BC42: 0.17346826 | BD42: 0.17380959
B44: Of Which
B45: Messaging & VAS as % of Mobile revenues | C45: % | AM45: 0.05524549 | AN45: 0.054595996 | AO45: 0.051918165 | AP45: 0.049072251 | AQ45: 0.050424633 | AR45: 0.051527369 | AS45: 0.05332194 | AT45: 0.054158527 | AU45: 0.056842413 | AV45: 0.056875747 | AW45: 0.059553098 | AX45: 0.054039415 | AY45: 0.054708533 | AZ45: 0.055930154 | BA45: 0.060518522 | BB45: 0.066945142 | BC45: 0.082389511 | BD45: 0.090565929
B46: Data as % of Mobile revenues | C46: % | AM46: 0.21940124 | AN46: 0.21526614 | AO46: 0.22759682 | AP46: 0.2465103 | AQ46: 0.23694923 | AR46: 0.23303708 | AS46: 0.23096546 | AT46: 0.21534203 | AU46: 0.19183594 | AV46: 0.17619163 | AW46: 0.16245191 | AX46: 0.14473506 | AY46: 0.12370728 | AZ46: 0.11450009 | BA46: 0.10264442 | BB46: 0.091996516 | BC46: 0.074248903 | BD46: 0.065330683
B47: Others as % of Mobile revenues | C47: % | AM47: 0.0041553441 | AN47: 0.0047145163 | AO47: 0.0043089439 | AP47: 0.0040127207 | AQ47: 0.0039283334 | AR47: 0.0044727859 | AS47: 0.0045215241 | AT47: 0.0043811275 | AU47: 0.0044086872 | AV47: 0.0037179304 | AW47: 0.0036384899 | AX47: 0.0036322152 | AY47: 0.0033708583 | AZ47: 0.0033508333 | BA47: 0.0089858508 | BB47: 0.0064266182 | BC47: 0.016829846 | BD47: 0.017912981
B49: Data
B50: Data Customer Base | C50: 000's | D50: 299123.99 | E50: 294107.69 | F50: 289432.56 | G50: 284750.81 | H50: 281208.89 | I50: 277594.91 | J50: 271162.96 | K50: 267129.04 | L50: 260846.76 | M50: 253158.92 | N50: 245887.26 | O50: 238226 | P50: 232678.12 | Q50: 225292.22 | R50: 219099.72 | S50: 213257.74 | T50: 208448.43 | U50: 202950.64 | V50: 200027.1 | W50: 192934.93 | X50: 188635.41 | Y50: 174742 | Z50: 162185.39 | AA50: 149089.25 | AB50: 148578.36 | AC50: 138443.11 | AD50: 124241.86 | AE50: 120047 | AF50: 115147.37 | AG50: 107511 | AH50: 97666.437 | AI50: 94783 | AJ50: 86077 | AK50: 70835.909 | AL50: 65768.695 | AM50: 62560.231 | AN50: 57362.377 | AO50: 54915.071 | AP50: 62659.047 | AQ50: 58902.69 | AR50: 58215.514 | AS50: 54859.986 | AT50: 51012.88 | AU50: 49469.812 | AV50: 46386.288 | AW50: 42248.682 | AX50: 40107.873 | AY50: 39319.591 | AZ50: 35604.79 | BA50: 54429.082 | BB50: 50630.987 | BC50: 46584.106 | BD50: 43490
B51: Of which Mobile Broadband costumers | C51: 000's | D51: 296755.98 | E51: 290997.22 | F51: 285822.67 | G51: 280691.9 | H51: 276783.95 | I51: 270155.49 | J51: 263635.77 | K51: 259428.94 | L51: 252748.51 | M51: 244909.6 | N51: 237466.74 | O51: 229747.83 | P51: 224124.42 | Q51: 216720.69 | R51: 210300.31 | S51: 205263.33 | T51: 200786.28 | U51: 195540.68 | V51: 192538.56 | W51: 184426.83 | X51: 179292.94 | Y51: 165628.57 | Z51: 152684.64 | AA51: 138293.85 | AB51: 136309.4 | AC51: 123793.11 | AD51: 103110.73 | AE51: 95173 | AF51: 86808.37 | AG51: 77067.869 | AH51: 65730.781 | AI51: 58281.225 | AJ51: 76578 | AK51: 62149.102 | AL51: 55217.635 | AM51: 48910.794 | AN51: 42715.539 | AO51: 37689.667 | AP51: 41335.493 | AQ51: 36572.358 | AR51: 35460.378 | AS51: 30881.472 | AT51: 25484.498 | AU51: 21732.521 | AV51: 19441.218 | AW51: 16940.373 | AX51: 15444.585 | AY51: 12535.319 | AZ51: 10255.274 | BA51: 9485.244 | BB51: 8014.912 | BC51: 6795.834 | BD51: 6390.915
B52: As % of customer base | C52: % | D52: 0.80141877 | E52: 0.79802738 | F52: 0.79472446 | G52: 0.78487839 | H52: 0.77769424 | I52: 0.77847615 | J52: 0.77113744 | K52: 0.7535053 | L52: 0.7405101 | M52: 0.73258317 | N52: 0.71832723 | O52: 0.7036399 | P52: 0.69370782 | Q52: 0.67809345 | R52: 0.66839866 | S52: 0.65155116 | T52: 0.63932753 | U52: 0.6284905 | V52: 0.61836679 | W52: 0.60059787 | X52: 0.58696626 | Y52: 0.56744072 | Z52: 0.55213509 | AA52: 0.53271095 | AB52: 0.52377706 | AC52: 0.48913561 | AD52: 0.44462589 | AE52: 0.434 | AF52: 0.40740011 | AG52: 0.37826219 | AH52: 0.29350084 | AI52: 0.27508103 | AJ52: 0.283 | AK52: 0.24416655 | AL52: 0.23318307 | AM52: 0.22291405 | AN52: 0.20962074 | AO52: 0.20656209 | AP52: 0.24105134 | AQ52: 0.23032737 | AR52: 0.23171529 | AS52: 0.22549271 | AT52: 0.21688054 | AU52: 0.21446915 | AV52: 0.20523325 | AW52: 0.19450164 | AX52: 0.18940927 | AY52: 0.18776274 | AZ52: 0.17324315 | BA52: 0.27418334 | BB52: 0.26171714 | BC52: 0.24396168 | BD52: 0.23105893
B53: Total MBs on the network | C53: Mn MBs | D53: 27984.635 | E53: 26055.616 | F53: 24445.934 | G53: 22840 | H53: 21078.207 | I53: 20174.386 | J53: 19311.255 | K53: 18788.716 | L53: 17390.877 | M53: 16376.505 | N53: 15748977 | O53: 14915279 | P53: 14248315 | Q53: 13853330 | R53: 13485280 | S53: 12561338 | T53: 11849334 | U53: 11311780 | V53: 11270769 | W53: 10771051 | X53: 9207030.3 | Y53: 8453705.6 | Z53: 7639997.1 | AA53: 7239836 | AB53: 6452825.2 | AC53: 5547222.9 | AD53: 4828576.8 | AE53: 4191715 | AF53: 3705034.4 | AG53: 3216897.2 | AH53: 2660297 | AI53: 2150644.7 | AJ53: 1539746 | AK53: 1105839 | AL53: 783808.91 | AM53: 472384.99 | AN53: 225109.16 | AO53: 171817.38 | AP53: 178125.43 | AQ53: 158034.67 | AR53: 146768.33 | AS53: 133946.31 | AT53: 114959.53 | AU53: 102015.31 | AV53: 86627.134 | AW53: 77281.408 | AX53: 67668.026 | AY53: 55609.754 | AZ53: 47655.289 | BA53: 38960.353 | BB53: 33630.019 | BC53: 27271.307 | BD53: 23936.71
B54: Data Average Revenue Per User (ARPU) | C54: Rs | AM54: 155.93242 | AN54: 162.44259 | AO54: 174.72323 | AP54: 200.75677 | AQ54: 201.66619 | AR54: 196.47383 | AS54: 200.26121 | AT54: 192.64379 | AU54: 180.52828 | AV54: 175.91173 | AW54: 170.13721 | AX54: 150.27876 | AY54: 138.70594 | AZ54: 132.91638 | BA54: 74.918711 | BB54: 69.792078 | BC54: 62.830258 | BD54: 54.791365
B55: Data Usage per customer | C55: MBs | D55: 31.44217 | E55: 29.77301 | F55: 28.341754 | G55: 26.923344 | H55: 25.123988 | I55: 24.499315 | J55: 23.898736 | K55: 23.743115 | L55: 22.59846 | M55: 21.954032 | N55: =21.7011465069509*1000 -> 21701.147 | O55: 21123.969 | P55: 20761.945 | Q55: 20779.131 | R55: 20758.04 | S55: 19929.993 | T55: 19228.494 | U55: 18726.723 | V55: 19065.599 | W55: 18931.596 | X55: 16839.763 | Y55: 16765.893 | Z55: 16409.302 | AA55: 16654.579 | AB55: 14971.576 | AC55: 13927.659 | AD55: 13116 | AE55: 11930 | AF55: 11048.151 | AG55: 10528.103 | AH55: 9220.6516 | AI55: 7864.3198 | AJ55: 6585 | AK55: 5349.2343 | AL55: 4086.5036 | AM55: 2611.286 | AN55: 1331.1427 | AO55: 972.41567 | AP55: 999.99508 | AQ55: 904.12545 | AR55: 859.05488 | AS55: 842.50794 | AT55: 765.48119 | AU55: 705.89976 | AV55: 655.85078 | AW55: 621.94242 | AX55: 563.44851 | AY55: 494.62858 | AZ55: 464.4316 | BA55: 248.59462 | BB55: 230.64295 | BC55: 202.88646 | BD55: 187.21473
B56: Data Realization per MB | C56: paisa | AM56: 5.9714799 | AN56: 12.203244 | AO56: 17.967957 | AP56: 20.075775 | AQ56: 22.305112 | AR56: 22.870929 | AS56: 23.769653 | AT56: 25.166365 | AU56: 25.574209 | AV56: 26.821914 | AW56: 27.355781 | AX56: 26.67125 | AY56: 28.042444 | AZ56: 28.61915 | BA56: 30.1369 | BB56: 30.259792 | BC56: 30.968186 | BD56: 29.266589
B58: Homes Services
B59: Total revenues | D59: 21914 | E59: 20008 | F59: 18646 | G59: 17179 | H59: 15960.701 | I59: 15092 | J59: 14321 | K59: 13670 | L59: 13155.007 | M59: 12718.116 | N59: 12207.438 | O59: 11620.919 | P59: 10965.961 | Q59: 10343.149 | R59: 9898 | S59: 9264.5887 | T59: 8762.0578 | U59: 7968.7393 | V59: 7126.5198 | W59: 6532.6126 | X59: 6009.089 | Y59: 5673.7789 | Z59: 5873.4223 | AA59: 5785.6428 | AB59: 5725.11 | AC59: 5546.376 | AD59: 5475.0318 | AE59: 5704.7096 | AF59: 5535.5993 | AG59: 5502.8459 | AH59: 5607.2734 | AI59: 5744.8566 | AJ59: 6041.5555 | AK59: 6152.7652 | AL59: 6367.2893 | AM59: 6703.4412 | AN59: 6785.0174 | AO59: 7025.4571 | AP59: 7063.1589 | AQ59: 6644.0226
B60: EBITDA | D60: 10997 | E60: 10031 | F60: 9335 | G60: 8589 | H60: 7956.7553 | I60: 7465 | J60: 7203 | K60: 6867 | L60: 6565.5191 | M60: 6383.5627 | N60: 6073.4302 | O60: 5860.43 | P60: 5526.1887 | Q60: 4357.5205 | R60: 4983 | S60: 4927.086 | T60: 4773.5691 | U60: 4357.5205 | V60: 3778.7742 | W60: 3229.5171 | X60: 3344.5647 | Y60: 3150.9537 | Z60: 3424.4684 | AA60: 3513.7932 | AB60: 3011.8008 | AC60: 3302.3406 | AD60: 2470.5297 | AE60: 2523.9843 | AF60: 2450.3505 | AG60: 2583.0923 | AH60: 2932.341 | AI60: 2859.2827 | AJ60: 3001.3863 | AK60: 3071.802 | AL60: 2714.9258 | AM60: 3014.3476 | AN60: 3322.8897 | AO60: 3413.6455 | AP60: 3347.3472 | AQ60: 2914.141
B61: EBITDA / Total revenues | D61: 0.50182532 | E61: 0.50134946 | F61: 0.50064357 | G61: 0.49997089 | H61: 0.49852166 | I61: 0.49463292 | J61: 0.50296767 | K61: 0.50234089 | L61: 0.49908899 | M61: 0.50192675 | N61: 0.49751884 | O61: 0.50430005 | P61: 0.50394024 | Q61: 0.54682684 | R61: 0.503 | S61: 0.53181918 | T61: 0.5448 | U61: 0.54682684 | V61: 0.53024118 | W61: 0.49436837 | X61: 0.55658432 | Y61: 0.55535363 | Z61: 0.58304482 | AA61: 0.60732979 | AB61: 0.52606862 | AC61: 0.59540511 | AD61: 0.45123568 | AE61: 0.44243871 | AF61: 0.44265316 | AG61: 0.46941025 | AH61: 0.5229531 | AI61: 0.49771176 | AJ61: 0.49679033 | AK61: 0.49925552 | AL61: 0.42638644 | AM61: 0.44967168 | AN61: 0.48973931 | AO61: 0.48589656 | AP61: 0.47391646 | AQ61: 0.43861094
B62: Capex | D62: 18893.839 | E62: 16055.243 | F62: 18606.323 | G62: 14571.303 | H62: 15169.317 | I62: 11403.186 | J62: 9460.0614 | K62: 7072.2861 | L62: 8156.9988 | M62: 7816.7454 | N62: 7569.4758 | O62: 4995.1243 | P62: 4280.0117 | Q62: 4062.0317 | R62: 5886 | S62: 6603.9398 | T62: 4967.7889 | U62: 4062.0317 | V62: 3499.6503 | W62: 3891.9739 | X62: 3324.6922 | Y62: 3415.8811 | Z62: 3086.6367 | AA62: 1181.618 | AB62: 973.37358 | AC62: 2660.5112 | AD62: 1023.3296 | AE62: 1168.8534 | AF62: 1431.0345 | AG62: 2371.7322 | AH62: 1929.5537 | AI62: 1922.8342 | AJ62: 1290.305 | AK62: 3208.8108 | AL62: 1598.6487 | AM62: 2065.3832 | AN62: 2021.5572 | AO62: 1858.4981 | AP62: 2161.7268 | AQ62: 2570.6628
B64: Homes Customers | C64: 000's | D64: 14220.896 | E64: 13086.195 | F64: 11927.625 | G64: 10976.433 | H64: 10038.285 | I64: 9226.4463 | J64: 8552.6343 | K64: 7969.2423 | L64: 7620.9523 | M64: 7289.8523 | N64: 6931.0943 | O64: 6459.5983 | P64: 6046.2063 | Q64: 5642.0883 | R64: 5210.1793 | S64: 4792.8793 | T64: 4482.8513 | U64: 4160.1123 | V64: 3819.2013 | W64: 3351.7103 | X64: 3066.5153 | Y64: 2792.9953 | Z64: 2577.9203 | AA64: 2448.6453 | AB64: 2414.3063 | AC64: 2351.505 | AD64: 2349.8763 | AE64: 2342.2873 | AF64: 2270.153 | AG64: 2245.3997 | AH64: 2212.7832 | AI64: 2188.6186 | AJ64: 2172.2879 | AK64: 2164.084 | AL64: 2159.4669 | AM64: 2136.915 | AN64: 2129.3468 | AO64: 2102.3558 | AP64: 2083.41 | AQ64: 2019.5843
B65: Of which no. of Broadband (DSL) customers | C65: 000's | AI65: 2060.8917 | AJ65: 2041.7057 | AK65: 2023.7447 | AL65: 2000.8097 | AM65: 1978.1717 | AN65: 1965.8217 | AO65: 1922.4577 | AP65: 1897.1657 | AQ65: 1810.9597
B66: As % of Customer Base | C66: % | AI66: 0.9416404 | AJ66: 0.93988726 | AK66: 0.93515074 | AL66: 0.92652946 | AM66: 0.92571381 | AN66: 0.9232041 | AO66: 0.91443024 | AP66: 0.91060603 | AQ66: 0.89669923
B67: Net Additions | C67: 000's | D67: 1134.701 | E67: 1158.57 | F67: 951.19166 | G67: 938.518 | H67: 811.839 | I67: 673.812 | J67: 583.392 | K67: 348.29 | L67: 331.1 | M67: 358.758 | N67: 471.496 | O67: 413.392 | P67: 404.118 | Q67: 431.909 | R67: 417.3 | S67: 310.028 | T67: 322.739 | U67: 341.033 | V67: 467.491 | W67: 285.195 | X67: 273.52 | Y67: 215.075 | Z67: 129.275 | AA67: 34.339 | AB67: 62.801344 | AC67: 1.6286557 | AD67: 7.5890805 | AE67: 72.13428 | AF67: 24.753283 | AG67: 32.616514 | AH67: 24.164552 | AI67: 16.330744 | AJ67: 8.2039198 | AK67: 4.6170474 | AL67: 22.551923 | AM67: 7.5681696 | AN67: 26.991039 | AO67: 18.945791 | AP67: 63.825656 | AQ67: 70.211
B68: Average Revenue Per User (ARPU) | C68: Rs | D68: 527.08086 | E68: 528.79294 | F68: 533.9292 | G68: 537.30404 | H68: 543.34411 | I68: 554.39186 | J68: 566.18922 | K68: 572.05132 | L68: 577.47184 | M68: 583.1981 | N68: 595.01571 | O68: 608.27383 | P68: 614.25976 | Q68: 623.64345 | R68: 645.91095 | S68: 652.05581 | T68: 650.21634 | U68: 656.98566 | V68: 661.10511 | W68: 681.35662 | X68: 684.06609 | Y68: 704.84742 | Z68: 783.01967 | AA68: 802.40419 | AB68: 803.25811 | AC68: 787.48152 | AD68: 777.0967 | AE68: 824.67505 | AF68: 815.14885 | AG68: 820.98957 | AH68: 846.58852 | AI68: 879.05541 | AJ68: 929.3803 | AK68: 948.40321 | AL68: 989.08119 | AM68: 1048.4845 | AN68: 1063.6757 | AO68: 1111.5024 | AP68: 1142.7754 | AQ68: 1117.5088
B69: Average Revenue Per User (ARPU) | C69: US | D69: 5.7464165 | E69: 5.9395261 | F69: 6.1171789 | G69: 6.289996 | H69: 6.2910726 | I69: 6.5702548 | J69: 6.7621343 | K69: 6.8624157 | L69: 6.9495084 | M69: 7.0081093 | N69: 7.2134083 | O69: 7.3992963 | P69: 7.4656705 | Q69: 7.5907649 | R69: 8.0860158 | S69: 8.4650508 | T69: 8.6501364 | U69: 8.7973932 | V69: 8.927268 | W69: 9.2809965 | X69: 9.3378301 | Y69: 9.5359723 | Z69: 10.537914 | AA69: 10.584644 | AB69: 11.177839 | AC69: 11.099757 | AD69: 11.085479 | AE69: 11.840982 | AF69: 11.549699 | AG69: 11.440503 | AH69: 12.109836 | AI69: 13.081668 | AJ69: 14.454002 | AK69: 14.662628 | AL69: 15.368944 | AM69: 16.270288 | AN69: 15.855445 | AO69: 16.434239 | AP69: 17.023742 | AQ69: 16.727161
B70: Non Voice Revenue as % of Homes Revenues | AI70: 0.92079872 | AJ70: 0.90904918 | AK70: 0.90200694 | AL70: 0.90400608 | AM70: 0.89123291 | AN70: 0.89408103 | AO70: 0.87935323 | AP70: 0.8665303 | AQ70: 0.88428877
B72: Digital TV Services
B73: Total revenues | D73: 7467.49 | E73: 7552 | F73: 7532 | G73: 7628 | H73: 7644.2988 | I73: 7607 | J73: 7586 | K73: 7771 | L73: 7693.4151 | M73: 7837.1639 | N73: 7514.5563 | O73: 7403.2365 | P73: 7290.4514 | Q73: 7390.221 | R73: 7288 | S73: 7481.7754 | T73: 7551.7784 | U73: 7912.4454 | V73: 7979.0099 | W73: 8094.5149 | X73: 7673.1986 | Y73: 7892.0325 | Z73: 7548.4164 | AA73: 7448.2673 | AB73: 6034.7939 | AC73: 7921.6576 | AD73: 7892.5594 | AE73: 7389.4105 | AF73: 10505.676 | AG73: 10329.501 | AH73: 10241.892 | AI73: 9924.263 | AJ73: 9584.8888 | AK73: 9642.4638 | AL73: 9369.1622 | AM73: 8973.6715 | AN73: 8657.3839 | AO73: 8734.7009 | AP73: 8545.3096 | AQ73: 8368.8925
B74: EBITDA | D74: 3300 | E74: 3477 | F74: 3663 | G74: 3882 | H74: 3849.2447 | I74: 4425 | J74: 4243 | K74: 4402 | L74: 4391.1461 | M74: 4285.0463 | N74: 4212.1458 | O74: 4263.8057 | P74: 4081.3692 | Q74: 4132.1345 | R74: 4352 | S74: 4779.2624 | T74: 4952.0217 | U74: 5318.8596 | V74: 5314.3857 | W74: 5420.7717 | X74: 5105.0719 | Y74: 5291.4703 | Z74: 5350.9238 | AA74: 5041.1498 | AB74: 3648.1673 | AC74: 5440.6775 | AD74: 5607.2981 | AE74: 5263.1007 | AF74: 3925.8859 | AG74: 3825.8353 | AH74: 3960.0095 | AI74: 4010.3775 | AJ74: 3701.3636 | AK74: 3708.4245 | AL74: 3516.7825 | AM74: 3299.826 | AN74: 3152.8717 | AO74: 3025.8288 | AP74: 3029.5357 | AQ74: 3010.7101
B75: EBITDA / Total revenues | D75: 0.44191556 | E75: 0.46040784 | F75: 0.48632501 | G75: 0.50891453 | H75: 0.50354451 | I75: 0.58170106 | J75: 0.5593198 | K75: 0.56646506 | L75: 0.57076683 | M75: 0.54675982 | N75: 0.56053153 | O75: 0.57593807 | P75: 0.55982393 | Q75: 0.55913544 | R75: 0.597 | S75: 0.6387872 | T75: 0.65574245 | U75: 0.67221438 | V75: 0.66604576 | W75: 0.66968456 | X75: 0.66531211 | Y75: 0.67048258 | Z75: 0.70888031 | AA75: 0.67682182 | AB75: 0.60452228 | AC75: 0.68681048 | AD75: 0.7104537 | AE75: 0.71224906 | AF75: 0.37369189 | AG75: 0.37037948 | AH75: 0.38664825 | AI75: 0.40409826 | AJ75: 0.38616657 | AK75: 0.38459304 | AL75: 0.37535721 | AM75: 0.36772307 | AN75: 0.36418296 | AO75: 0.3464147 | AP75: 0.35452616 | AQ75: 0.35975012
B76: Capex | D76: 9829.3304 | E76: 3287.4943 | F76: 3062.8936 | G76: 3056.9753 | H76: 3695.0695 | I76: 4626.5133 | J76: 4251.6729 | K76: 4078.0987 | L76: 3070.6824 | M76: 3716.8138 | N76: 3754.7317 | O76: 3843.0835 | P76: 3544.2172 | Q76: 4534.0648 | R76: 3054 | S76: 2469.6392 | T76: 3143.297 | U76: 4373.7662 | V76: 2578.5871 | W76: 2931.5904 | X76: 3690.3759 | Y76: 3226.3078 | Z76: 3469.0483 | AA76: 2457.2098 | AB76: 2514.3763 | AC76: 3509.4065 | AD76: 2051.741 | AE76: 2436.671 | AF76: 1916.6303 | AG76: 3268.0672 | AH76: 1797.0684 | AI76: 1808.8751 | AJ76: 2064.3503 | AK76: 2360.476 | AL76: 3191.0903 | AM76: 2661.09 | AN76: 1386.004 | AO76: 2650.2536 | AP76: 2541.1707 | AQ76: 2030.1525
B78: Digital TV Customers | C78: 000's | D78: 15996.825 | E78: 15427.221 | F78: 15353.865 | G78: 15694.957 | H78: 15898.47 | I78: 15822.852 | J78: 15794.24 | K78: 16340.511 | L78: 16146.321 | M78: 16137.174 | N78: 15749.462 | O78: 15918.012 | P78: 15945.659 | Q78: 15985.056 | R78: 15770.837 | S78: 15705.247 | T78: 16027.615 | U78: 16205.163 | V78: 16324.651 | W78: 17998.514 | X78: 17716.127 | Y78: 17872.267 | Z78: 17386.909 | AA78: 16838.249 | AB78: 16612.595 | AC78: 16308.468 | AD78: 16207.258 | AE78: 16026.75 | AF78: 15392.284 | AG78: 15001.454 | AH78: 14778.968 | AI78: 14646.164 | AJ78: 14167.639 | AK78: 13937.388 | AL78: 13521.086 | AM78: 13314.377 | AN78: 12815.349 | AO78: 12587.687 | AP78: 12404.831 | AQ78: 12148.72
B79: Net additions | C79: 000's | D79: 569.604 | E79: 73.356 | F79: -341.092 | G79: -203.526 | H79: 75.618 | I79: 28.612 | J79: -546.271 | K79: 194.19 | L79: 9.147 | M79: 387.712 | N79: -168.55 | O79: -27.647 | P79: -39.397 | Q79: 214.219 | R79: 65.59 | S79: -322.368 | T79: -177.548 | U79: =U78-V78 -> -119.488 | V79: =V78-W78 -> -1673.8628 | W79: 282.387 | X79: -156.13981 | Y79: 485.35781 | Z79: 548.66 | AA79: 225.654 | AB79: 304.127 | AC79: 101.21 | AD79: 180.508 | AE79: 634.466 | AF79: 390.83 | AG79: 222.486 | AH79: 132.804 | AI79: 478.525 | AJ79: 230.251 | AK79: 416.302 | AL79: 206.709 | AM79: 499.028 | AN79: 227.662 | AO79: 182.856 | AP79: 256.111 | AQ79: 424.094
B80: Average Revenue Per User (ARPU) $ | C80: Rs | D80: 158.85703 | E80: 163.37016 | F80: 163.15362 | G80: 160.72752 | H80: 161.55375 | I80: 159.59899 | J80: 157.82629 | K80: 159.15327 | L80: 160.07841 | M80: 162.97802 | N80: 158.95802 | O80: 153.84561 | P80: 152.55904 | Q80: 153.99934 | R80: 154.96253 | S80: 157.5871 | T80: 156.58278 | U80: 160.78887 | V80: 163.48896 | W80: 150.73214 | X80: 143.83368 | Y80: 148.89065 | Z80: 147.74966 | AA80: 148.78737 | AB80: 122.65648 | AC80: 162.46206 | AD80: 162.47452 | AE80: 156.57654 | AF80: 232.65857 | AG80: 231.16086 | AH80: 231.80535 | AI80: 228.93165 | AJ80: 227.7298 | AK80: 233.48721 | AL80: 232.62872 | AM80: 228.26818 | AN80: 227.53435 | AO80: 232.21084 | AP80: 231.92547 | AQ80: 233.11766
B81: Average Revenue Per User (ARPU) | C81: US | D81: 1.7319139 | E81: 1.8350119 | F81: 1.8692364 | G81: 1.8815705 | H81: 1.870539 | I81: 1.8914528 | J81: 1.8849574 | K81: 1.9092271 | L81: 1.9264424 | M81: 1.958456 | N81: 1.9270568 | O81: 1.8714421 | P81: 1.854192 | Q81: 1.8744248 | R81: 1.9399415 | S81: 2.0421875 | T81: 2.083095 | U81: 2.1530499 | V81: 2.2076819 | W81: 2.0531751 | X81: 1.9633987 | Y81: 2.0143609 | Z81: 1.9884215 | AA81: 1.9626783 | AB81: 1.7068415 | AC81: 2.289945 | AD81: 2.3177397 | AE81: 2.2481825 | AF81: 3.2964977 | AG81: 3.2212303 | AH81: 3.3158077 | AI81: 3.4068477 | AJ81: 3.5417224 | AK81: 3.6097896 | AL81: 3.6147263 | AM81: 3.5422451 | AN81: 3.3916901 | AO81: 3.4333786 | AP81: 3.4549565 | AQ81: 3.4893657
B82: Monthly Churn | C82: % | D82: 0.019264046 | E82: 0.030579496 | F82: 0.031298122 | G82: 0.025129594 | H82: 0.022592561 | I82: 0.025075051 | J82: 0.037461898 | K82: 0.020309825 | L82: 0.023497643 | M82: 0.01813214 | N82: 0.026644812 | O82: 0.022071828 | P82: 0.023240502 | Q82: 0.020184646 | R82: 0.022681344 | S82: 0.02419222 | T82: 0.016627995 | U82: 0.026645576 | V82: 0.022588188 | W82: 0.013584787 | X82: 0.02158276 | Y82: 0.014211244 | Z82: 0.015179011 | AA82: 0.013280954 | AB82: 0.010483148 | AC82: 0.017894445 | AD82: 0.015991551 | AE82: 0.0097275905 | AF82: 0.0080600765 | AG82: 0.013065717 | AH82: 0.01338492 | AI82: 0.0072486642 | AJ82: 0.01097074 | AK82: 0.012272986 | AL82: 0.013607365 | AM82: 0.0091814276 | AN82: 0.01154208 | AO82: 0.013436788 | AP82: 0.012251925 | AQ82: 0.0084426781
B84: B2B Services
B85: Airtel Business
B86: Total revenues | D86: 54904 | E86: 53531 | F86: 52760 | G86: 50571 | H86: 53155 | I86: 56459 | J86: 56555 | K86: 54765 | L86: 54616.101 | M86: 51948.01 | N86: 51100.11 | O86: 50545.195 | P86: 47849.531 | Q86: 47779.058 | R86: 46646 | S86: 43656.238 | T86: 41798.32 | U86: 41058.526 | V86: 39953.065 | W86: 37893.218 | X86: 37020.96 | Y86: 36214.321 | Z86: 35820.581 | AA86: 35019.395 | AB86: 33762.461 | AC86: 33176.344 | AD86: 33311.707 | AE86: 32080.418 | AF86: 30039.9 | AG86: 31116.058 | AH86: 33458.334 | AI86: 29923.388 | AJ86: 28282.098 | AK86: 29098.687 | AL86: 28313.093 | AM86: 27871.895 | AN86: 25769.648 | AO86: 27050.018 | AP86: 29816.443 | AQ86: 26793.238
B87: EBITDA | D87: 23577 | E87: 22446 | F87: 21943 | G87: 21535 | H87: 22359 | I87: 19846 | J87: 20208 | K87: 19855 | L87: 20830.156 | M87: 20625.114 | N87: 20577.683 | O87: 19979.335 | P87: 19680.074 | Q87: 19049.598 | R87: 18293 | S87: 17011.212 | T87: 16450.991 | U87: 15823.696 | V87: 15922.426 | W87: 14684.871 | X87: 14867.042 | Y87: 14017.881 | Z87: 13377.363 | AA87: 12710.87 | AB87: 13466.499 | AC87: 12125.215 | AD87: 9396.0648 | AE87: 7655.1305 | AF87: 9586.7882 | AG87: 9874.4239 | AH87: 10758.82 | AI87: 10425.287 | AJ87: 11467.858 | AK87: 11682.407 | AL87: 9929.3476 | AM87: 9394.3286 | AN87: 9423.9508 | AO87: 8287.2352 | AP87: 8440.1476 | AQ87: 7732.7619
B88: EBITDA / Total revenues | D88: 0.42942226 | E88: 0.41930844 | F88: 0.4159022 | G88: 0.42583694 | H88: 0.42063776 | I88: 0.35151172 | J88: 0.35731589 | K88: 0.36254907 | L88: 0.38139221 | M88: 0.39703376 | N88: 0.40269352 | O88: 0.39527664 | P88: 0.41129085 | Q88: 0.39870183 | R88: 0.392 | S88: 0.38966281 | T88: 0.39358021 | U88: 0.38539367 | V88: 0.39852826 | W88: 0.38753296 | X88: 0.40158446 | Y88: 0.38708115 | Z88: 0.37345467 | AA88: 0.36296658 | AB88: 0.39886011 | AC88: 0.36547772 | AD88: 0.28206494 | AE88: 0.23862316 | AF88: 0.31913516 | AG88: 0.31734174 | AH88: 0.32155874 | AI88: 0.34839929 | AJ88: 0.40548118 | AK88: 0.40147541 | AL88: 0.3506981 | AM88: 0.33705381 | AN88: 0.36569963 | AO88: 0.30636709 | AP88: 0.28307024 | AQ88: 0.28860872
B89: Capex | D89: 14137.361 | E89: 7596.0074 | F89: 7660.9917 | G89: 7312.0596 | H89: 24852.738 | I89: 9082.5282 | J89: 9006.1766 | K89: 8180.6548 | L89: 13582.507 | M89: 8549.9818 | N89: 9602.8226 | O89: 6139.7652 | P89: 15598.857 | Q89: 7660.3562 | R89: 8792 | S89: 6860.92 | T89: 8478.3709 | U89: 8367.6732 | V89: 5621.9133 | W89: 6567.1948 | X89: 7006.1731 | Y89: 5223.2091 | Z89: 5537.8631 | AA89: 4187.8794 | AB89: 18813.99 | AC89: 7627.5943 | AD89: 2619.7456 | AE89: 1155.2416 | AF89: 1385.3257 | AG89: 8603.1339 | AH89: 3084.8641 | AI89: 1395.5732 | AJ89: 4220.6862 | AK89: 822.5996 | AL89: 1532.3703 | AM89: 2248.2587 | AN89: 6544.5279 | AO89: 5383.9383 | AP89: 6113.7892 | AQ89: 4695.1863
B91: Airtel Business Customer | C91: 000's | AH91: 1783.1338 | AI91: 1766.4874 | AJ91: 1760.2451 | AK91: 1749.057 | AL91: 1743.3451 | AM91: 1742.589 | AN91: 1736.4172 | AO91: 1727.7522 | AP91: 1713.879 | AQ91: 1711.8827
B93: Minutes & Network Statistics
B95: Mobile Services | C95: Mn Min | AF95: 731186.54 | AG95: 702880.67 | AH95: 693060.86 | AI95: 684191.41 | AJ95: 592657.14 | AK95: 494545.91 | AL95: 437142.18 | AM95: 421911.63 | AN95: 381236.13 | AO95: 330216.62 | AP95: 313403.14 | AQ95: 314831.3
B96: Homes Services | C96: Mn Min | AF96: 3752.1174 | AG96: 3698.4665 | AH96: 3450.7433 | AI96: 2841.4426 | AJ96: 2830.6277 | AK96: 3071.439 | AL96: 3500.2404 | AM96: 3473.9555 | AN96: 2411.3184 | AO96: 2425.7666 | AP96: 3127.8447 | AQ96: 2823.438
B97: Airtel Business | C97: Mn Min | AF97: 3014.6172 | AG97: 2744.1426 | AH97: 2864.8011 | AI97: 3065.1802 | AJ97: 2714.1746 | AK97: 2868.809 | AL97: 3151.4597 | AM97: 3172.5777 | AN97: 2897.0617 | AO97: 2841.7231 | AP97: 3002.336 | AQ97: 3189.9154
B98: National Long Distance Services | C98: Mn Min | AF98: 99284.706 | AG98: 97932.898 | AH98: 93190.824 | AI98: 66244.126 | AJ98: 66138.907 | AK98: 59515.991 | AL98: 56709.05 | AM98: 51125.271 | AN98: 43235.04 | AO98: 34754.757 | AP98: 34226.454 | AQ98: 33551.643
B99: International Long Distance Services | C99: Mn Min | AF99: 3543.8736 | AG99: 4422.8142 | AH99: 5213.0249 | AI99: 5109.0593 | AJ99: 5085.4532 | AK99: 5475.7673 | AL99: 5102.6293 | AM99: 5168.1793 | AN99: 4444.748 | AO99: 4909.7709 | AP99: 5192.6623 | AQ99: 5695.2679
B100: Total Minutes on Network (Gross) | C100: Mn Min | AF100: 840781.85 | AG100: 811678.99 | AH100: 797780.26 | AI100: 761451.22 | AJ100: 669426.3 | AK100: 565477.91 | AL100: 505605.56 | AM100: 484851.61 | AN100: 434224.29 | AO100: 375148.63 | AP100: 358952.43 | AQ100: 360091.56
B101: Eliminations | C101: Mn Min | AF101: -99373.165 | AG101: -98024.22 | AH101: -93298.421 | AI101: -65937.126 | AJ101: -58122.686 | AK101: -55562.321 | AL101: -56880.561 | AM101: -51262.467 | AN101: -43271.386 | AO101: -34802.827 | AP101: -34258.09 | AQ101: -33573.41
B102: Total Minutes on Network (Net) | C102: Mn Min | AF102: 741408.69 | AG102: 713654.77 | AH102: 704481.83 | AI102: 695514.1 | AJ102: 611303.62 | AK102: 509915.59 | AL102: 448725 | AM102: 433589.14 | AN102: 390952.91 | AO102: 340345.81 | AP102: 324694.34 | AQ102: 326518.15
B105: Mobile Services
B106: Census Towns | C106: Nos | D106: 7918 | E106: 7918 | F106: 7918 | G106: 7918 | H106: 7918 | I106: 7918 | J106: 7918 | K106: 7918 | L106: 7918 | M106: 7916 | N106: 7916 | O106: 7915 | P106: 7915 | Q106: 7915 | R106: 7914 | S106: 7914 | T106: 7913 | U106: 7913 | V106: 7913 | W106: 7913 | X106: 7907 | Y106: 7907 | Z106: 7907 | AA106: 7907 | AB106: 7907 | AC106: 7906 | AD106: 7906 | AE106: 7906 | AF106: 7906 | AG106: 7906 | AH106: 7904 | AI106: 7902 | AJ106: 7899 | AK106: 7897 | AL106: 7896 | AM106: 7896 | AN106: 7893 | AO106: 7892 | AP106: 7889 | AQ106: 7885
B107: Non-Census Towns & Villages | C107: Nos | D107: 816832 | E107: 816312 | F107: 816254 | G107: 814916 | H107: 814066 | I107: 812655 | J107: 811186 | K107: 810902 | L107: 809051 | M107: 808106 | N107: 806201 | O107: 804582 | P107: 802577 | Q107: 801620 | R107: 799569 | S107: 798104 | T107: 795126 | U107: 794484 | V107: 793591 | W107: 793350 | X107: 792827 | Y107: 791672 | Z107: 790450 | AA107: 789572 | AB107: 788185 | AC107: 786719 | AD107: 786268 | AE107: 786246 | AF107: 786192 | AG107: 786134 | AH107: 786129 | AI107: 786112 | AJ107: 786043 | AK107: 786032 | AL107: 786032 | AM107: 785823 | AN107: 785494 | AO107: 784769 | AP107: 781679 | AQ107: 781484
B108: Population Coverage | C108: % | D108: 0.96508237 | E108: 0.96460969 | F108: 0.96457862 | G108: 0.96372606 | H108: 0.97032435 | I108: 0.96287459 | J108: 0.96174069 | K108: 0.96160306 | L108: 0.96109052 | M108: 0.9607204 | N108: 0.96007988 | O108: 0.95958939 | P108: 0.95879321 | Q108: 0.95834811 | R108: 0.957 | S108: 0.95698933 | T108: 0.95655404 | U108: 0.9563317 | V108: 0.95562185 | W108: 0.95526101 | X108: 0.95476298 | Y108: 0.95433677 | Z108: 0.95378723 | AA108: 0.95378723 | AB108: 0.95355974 | AC108: 0.95330187 | AD108: 0.9529684 | AE108: 0.95296194 | AF108: 0.95277848 | AG108: 0.95271891 | AH108: 0.95267033 | AI108: 0.95306648 | AJ108: 0.95250289 | AK108: 0.952792 | AL108: 0.95290381 | AM108: 0.9531 | AN108: 0.953 | AO108: 0.95274244 | AP108: 0.9514 | AQ108: 0.9514
B109: Optic Fibre Network | C109: R kms | D109: 532388.47 | E109: 519113 | F109: 507655 | G109: 497399 | H109: 489098 | I109: 477505 | J109: 463551 | K109: 453744 | L109: 444708 | M109: 430412 | N109: 415903 | O109: 403708 | P109: 388726 | Q109: 376978 | R109: 367976 | S109: 361538 | T109: 355079 | U109: 346243 | V109: 340690 | W109: 332542 | X109: 324825 | Y109: 314458.67 | Z109: 310288.67 | AA109: 306787.67 | AB109: 304906.63 | AC109: 299592.5 | AD109: 294866.77 | AE109: 286661.6 | AF109: 280533.58 | AG109: 273599.89 | AH109: 263506.96 | AI109: 245847.17 | AJ109: 237892.59 | AK109: 233719.95 | AL109: 232150.08 | AM109: 230914.44 | AN109: 229855.57 | AO109: 223607.27 | AP109: 218798.83 | AQ109: 214030.55
B110: Network towers | C110: Nos | D110: 345912 | E110: 343486 | F110: 342339 | G110: 339860 | H110: 338029 | I110: 334757 | J110: 329543 | K110: 324498 | L110: 318171 | M110: 307663 | N110: 295318 | O110: 284221 | P110: 275069 | Q110: 262619 | R110: 253998 | S110: 245626 | T110: 237577 | U110: 230562 | V110: 222812 | W110: 219310 | X110: 216901 | Y110: 208606 | Z110: 201192 | AA110: 196145 | AB110: 194409 | AC110: 189857 | AD110: 185582 | AE110: 182600 | AF110: 181079 | AG110: 175300 | AH110: 171031 | AI110: 167355 | AJ110: 165748 | AK110: 163808 | AL110: 162954 | AM110: 162380 | AN110: 162046 | AO110: 160199 | AP110: 158934 | AQ110: 157055
B111: Of which Mobile Broadband towers | C111: Nos | I111: 334757 | J111: 329543 | K111: 324498 | L111: 318171 | M111: 307663 | N111: 294713 | O111: 283636 | P111: 274302 | Q111: 261763 | R111: 253307 | S111: 244920 | T111: 236882 | U111: 229823 | V111: 221979 | W111: 218328 | X111: 215801 | Y111: 207360 | Z111: 199464 | AA111: 194205 | AB111: 192068 | AC111: 188591 | AD111: 181825 | AE111: 177141 | AF111: 172627 | AG111: 164859 | AH111: 154531 | AI111: 146428 | AJ111: 144708 | AK111: 130334 | AL111: 123181 | AM111: 120132 | AN111: 116717 | AO111: 113367 | AP111: 110382 | AQ111: 108015
B112: Total Mobile Broadband Base stations | C112: Nos | D112: 1187894 | E112: 1171148 | F112: 1154810 | G112: 999933 | H112: 992465 | I112: 978832 | J112: 962565 | K112: 947377 | L112: 931854 | M112: 905556 | N112: 876096 | O112: 852650 | P112: 832369 | Q112: 806197 | R112: 787498 | S112: 766673 | T112: 752136 | U112: 748335 | V112: 717534 | W112: 661750 | X112: 606783 | Y112: 568345 | Z112: 537206 | AA112: 506957 | AB112: 503883 | AC112: 473859 | AD112: 461891 | AE112: 443804 | AF112: 417613 | AG112: 371562 | AH112: 347642 | AI112: 320204 | AJ112: 298014 | AK112: 259002 | AL112: 226132 | AM112: 203506 | AN112: 190860 | AO112: 170844 | AP112: 148078 | AQ112: 137567
E113: 0 | F113: 0 | G113: 0 | H113: 0 | I113: 0 | J113: 0 | K113: 0 | M113: 0 | N113: 0
B114: Homes Services - Cities covered | C114: Nos | D114: 1635 | E114: 1591 | F114: 1551 | G114: 1512 | H114: 1476 | I114: 1427 | J114: 1345 | K114: 1317 | L114: 1290 | M114: 1267 | N114: 1239 | O114: 1225 | P114: 1199 | Q114: 1140 | R114: 1060 | S114: 983 | T114: 847 | U114: 672 | V114: 523 | W114: 387 | X114: 291 | Y114: 219 | Z114: 145 | AA114: 117 | AB114: 111 | AC114: 103 | AD114: 100 | AE114: 99 | AF114: 93 | AG114: 90 | AH114: 89 | AI114: 89 | AJ114: 89 | AK114: 89 | AL114: 88 | AM114: 88 | AN114: 87 | AO114: 87 | AP114: 87 | AQ114: 87
E115: 0 | F115: 0 | G115: 0 | H115: 0 | I115: 0 | J115: 0 | K115: 0 | L115: 0 | M115: 0 | N115: 0 | P115: 0 | Q115: 0 | T115: 0 | U115: 0 | V115: 0 | W115: 0 | X115: 0 | Y115: 0 | Z115: 0 | AA115: 0 | AB115: 0 | AC115: 0 | AD115: 0 | AE115: 0 | AF115: 0 | AG115: 0 | AH115: 0 | AI115: 0 | AJ115: 0 | AK115: 0 | AL115: 0 | AM115: 0 | AN115: 0 | AO115: 0 | AP115: 0 | AQ115: 0
B116: Airtel Business - Submarine Cable System | C116: Nos | D116: 8 | E116: 8 | F116: 8 | G116: 7 | H116: 7 | I116: 7 | J116: 7 | K116: 7 | L116: 7 | M116: 7 | N116: 7 | O116: 7 | P116: 7 | Q116: 7 | R116: 7 | S116: 7 | T116: 7 | U116: 7 | V116: 7 | W116: 7 | X116: 7 | Y116: 7 | Z116: 7 | AA116: 7 | AB116: 7 | AC116: 7 | AD116: 7 | AE116: 7 | AF116: 7 | AG116: 7 | AH116: 7 | AI116: 7 | AJ116: 7 | AK116: 7 | AL116: 7 | AM116: 7 | AN116: 7 | AO116: 7 | AP116: 7 | AQ116: 7
B118: Digital TV Services
B119: Districts Covered | C119: Nos | D119: 640 | E119: 640 | F119: 640 | G119: 640 | H119: 639 | I119: 639 | J119: 639 | K119: 639 | L119: 639 | M119: 639 | N119: 639 | O119: 639 | P119: 639 | Q119: 639 | R119: 639 | S119: 639 | T119: 639 | U119: 639 | V119: 639 | W119: 639 | X119: 639 | Y119: 639 | Z119: 639 | AA119: 639 | AB119: 639 | AC119: 639 | AD119: 639 | AE119: 639 | AF119: 639 | AG119: 639 | AH119: 639 | AI119: 639 | AJ119: 639 | AK119: 639 | AL119: 639 | AM119: 639 | AN119: 639 | AO119: 639 | AP119: 639 | AQ119: 639
B120: Coverage | C120: % | D120: 1 | E120: 1 | F120: 1 | G120: 1 | H120: 0.9984375 | I120: 0.9984375 | J120: 0.9984375 | K120: 0.9984375 | L120: 0.9984375 | M120: 0.9984375 | N120: 0.9984375 | O120: 0.9984375 | P120: 0.9984375 | Q120: 0.9984375 | R120: 0.9984375 | S120: 0.9984375 | T120: 0.9984375 | U120: 0.9984375 | V120: 0.9984375 | W120: 0.9984375 | X120: 0.9984375 | Y120: 0.9984375 | Z120: 0.9984375 | AA120: 0.9984375 | AB120: 0.9984375 | AC120: 0.9984375 | AD120: 0.9984375 | AE120: 0.9984375 | AF120: 0.9984375 | AG120: 0.9984375 | AH120: 0.9984375 | AI120: 0.9984375 | AJ120: 0.9984375 | AK120: 0.9984375 | AL120: 0.9984375 | AM120: 0.9984375 | AN120: 0.9984375 | AO120: 0.9984375 | AP120: 0.9984375 | AQ120: 0.9984375
B123: Bharti Infratel Consolidated | E123: =E2 -> Q3 FY 26 | F123: =F2 -> Q2 FY 26 | G123: =G2 -> Q1 FY 26 | H123: =H2 -> Q4 FY 25 | I123: =I2 -> Q3 FY 25 | J123: =J2 -> Q2 FY 25 | K123: =K2 -> Q1 FY 25 | L123: =L2 -> Q4 FY 24 | ... BD123: =BD2 -> Q4 FY 13
B125: Revenues Rs Mn | Z125: 17663.26 | AA125: 16420.748 | AB125: 16825.547 | AC125: 16662.105 | AD125: 16673.535 | AE125: 17261.688 | AF125: 16705.129 | AG125: 17325.259 | AH125: 17205.611 | AI125: 16949.454 | AJ125: 16739 | AK125: 16949.72 | AL125: 16613.098 | AM125: 15982.125 | AN125: 16017.211 | AO125: 15292.244 | AP125: 14962.476 | AQ125: 14556.973 | AR125: 14147.919 | AS125: 13979.216 | AT125: 13724.335 | AU125: 13737.127 | AV125: 13517.7 | AW125: 13692.12 | AX125: 13743.938 | AY125: 13327.864 | AZ125: 13060.381 | BA125: 12592.16 | BB125: 12602.002 | BC125: 12832.094 | BD125: 13160.346
...

Sheet EBITDA
B2: Bharti Airtel | C2: Annual | D2: Annual | E2: Annual | F2: Annual | G2: LTM | I2: Quarter | J2: Quarter | K2: Quarter | L2: Quarter
B3: (INR millions) | C3: 45016 | D3: 45382 | E3: 45747 | F3: 46112 | G3: =L3 -> 46112 | I3: 45838 | J3: 45930 | K3: 46021 | L3: 46112
C4: Act | D4: Act | E4: Act | F4: Act | G4: Act | I4: Act | J4: Act | K4: Act | L4: Act
C5: FY | D5: FY | E5: FY | F5: FY | G5: LTM | I5: 1Q | J5: 2Q | K5: 3Q | L5: 4Q
B8: Profit / (Loss) from Operating Activities | C8: 722101 | D8: 797272 | E8: 947329 | F8: 1224918 | G8: =SUM(I8:L8) -> 1224918 | I8: 283475 | J8: 302891 | K8: 314851 | L8: =F8-SUM(I8:K8) -> 323701
B9: Add: Charity and donation | C9: 783 | D9: 3699 | E9: 3558 | F9: 4572 | G9: =SUM(I9:L9) -> 4572 | I9: 810 | J9: 676 | K9: 698 | L9: =F9-SUM(I9:K9) -> 2388
B10: Less: Finance Income/Derviatives MTM | C10: -5554 | D10: -20424 | E10: -9021 | F10: -16814 | G10: =SUM(I10:L10) -> -16814 | I10: -2617 | J10: -4376 | K10: -4113 | L10: =F10-SUM(I10:K10) -> -5708
B11: Add: Impact of difference in effective date of Indus Consolidation | C11: 0 | D11: 108517 | E11: 108128 | F11: 0 | G11: =SUM(I11:L11) -> 0 | I11: 0 | J11: 0 | K11: 0 | L11: =F11-SUM(I11:K11) -> 0
B12: EBITDA | C12: =SUM(C8:C11) -> 717330 | D12: =SUM(D8:D11) -> 889064 | E12: =SUM(E8:E11) -> 1049994 | F12: =SUM(F8:F11) -> 1212676 | G12: =SUM(G8:G11) -> 1212676 | I12: =SUM(I8:I11) -> 281668 | J12: =SUM(J8:J11) -> 299191 | K12: =SUM(K8:K11) -> 311436 | L12: =SUM(L8:L11) -> 320381
