Workbook
Name \A: #REF!
Name \B: #REF!
Name \C: #REF!
Name \L: #REF!
Name \M: #REF!
Name \P: #REF!
Name \Y: #REF!
Name _01_30_04: MonthlyOpStats
Name _01_30_04: MonthlyOpStats
Name _01_30_04: MonthlyOpStats
Name _01_30_04: MonthlyOpStats
Name _1_30_01: MonthlyOpStats
Name _1_30_01: MonthlyOpStats
Name _1_30_01: MonthlyOpStats
Name _1_30_01: MonthlyOpStats
Name _1_30_02: MonthlyOpStats
Name _1_30_02: MonthlyOpStats
Name _1_30_02: MonthlyOpStats
Name _1_30_02: MonthlyOpStats
Name _1_31_01: MonthlyOpStats
Name _1_31_01: MonthlyOpStats
Name _1_31_01: MonthlyOpStats
Name _1_31_01: MonthlyOpStats
Name _1_31_02: MonthlyOpStats
Name _1_31_02: MonthlyOpStats
Name _1_31_02: MonthlyOpStats
Name _1_31_02: MonthlyOpStats
Name _12_31_05: MonthlyOpStats
Name _12_31_05: MonthlyOpStats
Name _12_31_05: MonthlyOpStats
Name _12_31_05: MonthlyOpStats
Name _A: #REF!
Name _A___0: #REF!
Name _B: #REF!
Name _B___0: #REF!
Name _C: #REF!
Name _C___0: #REF!
Name _ent1: [1]Inputs!$J$17
Name _ent10: [1]Inputs!$J$476
Name _ent11: [1]Inputs!$J$527
Name _ent12: [1]Inputs!$J$578
Name _ent13: [1]Inputs!$J$629
Name _ent14: [1]Inputs!$J$680
Name _ent15: [1]Inputs!$J$731
Name _ent2: [1]Inputs!$J$68
Name _ent3: [1]Inputs!$J$119
Name _ent4: [1]Inputs!$J$170
Name _ent5: [1]Inputs!$J$221
Name _ent6: [1]Inputs!$J$272
Name _ent7: [1]Inputs!$J$323
Name _ent8: [1]Inputs!$J$374
Name _ent9: [1]Inputs!$J$425
Name _eps1: [1]Inputs!$P$42
Name _eps10: [1]Inputs!$P$501
Name _eps11: [1]Inputs!$P$552
Name _eps12: [1]Inputs!$P$603
Name _eps13: [1]Inputs!$P$654
Name _eps14: [1]Inputs!$P$705
Name _eps15: [1]Inputs!$P$756
Name _eps2: [1]Inputs!$P$93

Sheet Capitalisation
B3: 1Q26 | I3: Exchange rate as at end | J3: =Model!$O$208 -> 0.0010795988
I4: LTM Average exchange rate | J4: =Model!$O$207 -> 0.0010741488
C6: Amount outstanding as on 31-Mar-2026 | D6: Ch$ (mn) | E6: USD (mn) | F6: Leverage (Ch$) | G6: Leverage (USD) | I6: Company Reported | J6: Ch$ (mn)
I7: Net debt | J7: =1335.7*1000 -> 1335700
C8: Short-term debt | I8: Net debt to EBITDA | J8: 2.34
C9: Interest bearing borrowings (Loans) | D9: =Model!$BE$107 -> 14561.932 | E9: =+D9*$J3 -> 15.721045
C10: Liabilities with bondholders | D10: =Model!$BE$108 -> 8921.722 | E10: =+D10*$J3 -> 9.6318806
C11: Liabilities for leases current | D11: =Model!$BE$110 -> 148848.49 | E11: =+D11*$J3 -> 160.69666
C12: Long-term debt
C13: Interest bearing borrowings (Loans) | D13: =Model!$BE$112 -> 170467.77 | E13: =+D13*$J3 -> 184.0368
C14: Liabilities with bondholders | D14: =Model!$BE$113 -> 1403972.5 | E14: =+D14*$J3 -> 1515.727
C15: Liabilities for leases non-current | D15: =Model!$BE$115 -> 522425.65 | E15: =+D15*$J3 -> 564.01012
C16: Total Loans & Borrows | D16: =SUM(D9:D15) -> 2269198 | E16: =SUM(E9:E15) -> 2449.8235 | F16: =+D16/D21 -> 2.6528389 | G16: =+E16/E21 -> 2.6662989
C17: Cash & Equivalents | D17: =Model!$BE$118 -> 215586.38 | E17: =+D17*$J3 -> 232.7468
C18: Net debt | D18: =+D16-D17 -> 2053611.7 | E18: =+E16-E17 -> 2217.0767 | F18: =+D18/D21 -> 2.4008045 | G18: =+E18/E21 -> 2.4129858
C19: Equity | D19: =Model!$BE$125 -> 1969186.8 | E19: =+D19*$J3 -> 2125.9317
C20: Total Capitalisation | D20: =D16+D19 -> 4238384.8 | E20: =E16+E19 -> 4575.7552 | F20: =D20/D21 -> 4.9549452 | G20: =E20/E21 -> 4.9800858
C21: LTM Adjusted EBITDA | D21: =Model!$BE$84 -> 855384.79 | E21: =+D21*J4 -> 918.81052
C22: check | D22: =D16-Model!$BE$121 -> 0
C25: Liquidity Table at end-1Q26 | D25: =D6 -> Ch$ (mn) | E25: =E6 -> USD (mn)
C26: Cash and cash equivalents | D26: =D17 -> 215586.38 | E26: =D26*$J3 -> 232.7468
C27: Total | D27: =SUM(D26:D26) -> 215586.38 | E27: =SUM(E26:E26) -> 232.7468
C30: Debt Maturity Profile at end-1Q26 | D30: =D25 -> Ch$ (mn) | E30: =E25 -> USD (mn)
C31: Less than 1 year | D31: =14561.932+7915.943+1005.779 -> 23483.654 | E31: =D31*$J3 -> 25.352925
C32: Year 1-2 | D32: 0 | E32: =D32*$J3 -> 0
C33: Year 2-3 | D33: 248006.15 | E33: =D33*$J3 -> 267.74715
C34: Year 3-4 | D34: 0 | E34: =D34*$J3 -> 0
C35: Year 4-5 | D35: =170467.765+39692.799 -> 210160.56 | E35: =D35*$J3 -> 226.8891
C36: Over 5 years | D36: 1116273.5 | E36: =D36*$J3 -> 1205.1276
C37: Total debt (excluding leases) | D37: =SUM(D31:D36) -> 1597923.9 | E37: =SUM(E31:E36) -> 1725.1167
C38: check | D38: =D37-D9-D10-D13-D14 -> 0
C41: Lease liabilities Maturity Profile at end-1Q26 | D41: (Ch$ millions) | E41: (USD millions)
C42: Less than 1 year | D42: 148848.49 | E42: =D42*$J3 -> 160.69666
C43: Year 1-2 | D43: 129322.58 | E43: =D43*$J3 -> 139.61651
C44: Year 2-3 | D44: 115938.55 | E44: =D44*$J3 -> 125.16712
C45: Year 3-4 | D45: 95222.316 | E45: =D45*$J3 -> 102.8019
C46: Year 4-5 | D46: 52805.087 | E46: =D46*$J3 -> 57.00831
C47: Over 5 years | D47: 129137.12 | E47: =D47*$J3 -> 139.41628
C48: Total debt | D48: =SUM(D42:D47) -> 671274.14 | E48: =SUM(E42:E47) -> 724.70677
C49: check | D49: =D48-D11-D15 -> 0
C52: Debt Maturity Profile at end-1Q26 | D52: (Ch$ millions) | E52: (USD millions)
C53: Less than 1 year | D53: =+D31+D42 -> 172332.15 | E53: =D53*$J3 -> 186.04958
C54: Year 1-2 | D54: =+D32+D43 -> 129322.58 | E54: =D54*$J3 -> 139.61651
C55: Year 2-3 | D55: =+D33+D44 -> 363944.7 | E55: =D55*$J3 -> 392.91427
C56: Year 3-4 | D56: =+D34+D45 -> 95222.316 | E56: =D56*$J3 -> 102.8019
C57: Year 4-5 | D57: =+D35+D46 -> 262965.65 | E57: =D57*$J3 -> 283.89741
C58: Over 5 years | D58: =+D36+D47 -> 1245410.6 | E58: =D58*$J3 -> 1344.5439
C59: Total debt (including leases) | D59: =SUM(D53:D58) -> 2269198 | E59: =SUM(E53:E58) -> 2449.8235
C60: check | D60: =D59-Model!$BE$121 -> 0
B65: FY25 | I65: Exchange rate as at end FY25 | J65: =Model!$O$208 -> 0.0010795988
I66: LTM Average exchange rate FY25 | J66: =Model!$O$207 -> 0.0010741488
C68: Amount outstanding as on 30-Dec-2025 | D68: Ch$ (mn) | E68: USD (mn) | F68: Leverage (Ch$) | G68: Leverage (USD) | I68: Company Reported | J68: Ch$ (mn)
I69: Net debt | J69: 1369000
C70: Short-term debt | I70: Net debt to EBITDA | J70: 2.47
C71: Interest bearing borrowings (Loans) | D71: =Model!$BD$107 -> 14630.288 | E71: =+D71*$J65 -> 15.794842
C72: Liabilities with bondholders | D72: =Model!$BD$108 -> 9337.567 | E72: =+D72*$J65 -> 10.080826
C73: Liabilities for leases current | D73: =Model!$BD$110 -> 148627.24 | E73: =+D73*$J65 -> 160.4578
C74: Long-term debt
C75: Interest bearing borrowings (Loans) | D75: =Model!$BD$112 -> 168379.24 | E75: =+D75*$J65 -> 181.78203
C76: Liabilities with bondholders | D76: =Model!$BD$113 -> 1386290.2 | E76: =+D76*$J65 -> 1496.6373
C77: Liabilities for leases non-current | D77: =Model!$BD$115 -> 543261.78 | E77: =+D77*$J65 -> 586.50478
C78: Total Loans & Borrows | D78: =SUM(D71:D77) -> 2270526.4 | E78: =SUM(E71:E77) -> 2451.2576 | F78: =+D78/D83 -> 2.7176535 | G78: =+E78/E83 -> 2.7314424
C79: Cash & Equivalents | D79: =Model!$BD$118 -> 233650.19 | E79: =+D79*$J65 -> 252.24847
C80: Net debt | D80: =+D78-D79 -> 2036876.2 | E80: =+E78-E79 -> 2199.0091 | F80: =+D80/D83 -> 2.4379913 | G80: =+E80/E83 -> 2.4503613
C81: Equity | D81: =Model!$BD$125 -> 1943296.9 | E81: =+D81*$J65 -> 2097.981
C82: Total Capitalisation | D82: =D78+D81 -> 4213823.2 | E82: =E78+E81 -> 4549.2386 | F82: =D82/D83 -> 5.0436373 | G82: =E82/E83 -> 5.0692278
C83: LTM Adjusted EBITDA | D83: =Model!$BD$84 -> 835473.1 | E83: =+D83*J66 -> 897.4224
C85: check | D85: =D78-Model!$BD$121 -> 0
C87: Liquidity Table at end-FY25 | D87: =D68 -> Ch$ (mn) | E87: =E68 -> USD (mn)
C88: Cash and cash equivalents | D88: =D79 -> 233650.19 | E88: =D88*$J65 -> 252.24847
C89: Total | D89: =SUM(D88:D88) -> 233650.19 | E89: =SUM(E88:E88) -> 252.24847
C92: Debt Maturity Profile at end-FY25 | D92: =D87 -> Ch$ (mn) | E92: =E87 -> USD (mn)
C93: Less than 1 year | D93: =1030.652+6517.225+13599.636+2820.342 -> 23967.855 | E93: =D93*$J65 -> 25.875668
C94: Year 1-2 | D94: 0 | E94: =D94*$J65 -> 0
C95: Year 2-3 | D95: 0 | E95: =D95*$J65 -> 0
C96: Year 3-4 | D96: 248145.99 | E96: =D96*$J65 -> 267.89812
C97: Year 4-5 | D97: =168379.243+39571.039 -> 207950.28 | E97: =D97*$J65 -> 224.50288
C98: Over 5 years | D98: 1098573.2 | E98: =D98*$J65 -> 1186.0183
C99: Total debt (excluding leases) | D99: =SUM(D93:D98) -> 1578637.3 | E99: =SUM(E93:E98) -> 1704.295
C100: check | D100: =D99-D71-D72-D75-D76 -> 0
C103: Lease liabilities Maturity Profile at end-3Q25 | D103: (Ch$ millions) | E103: (USD millions)
C104: Less than 1 year | D104: 148627.24 | E104: =D104*$J65 -> 160.4578
C105: Year 1-2 | D105: 132191.14 | E105: =D105*$J65 -> 142.7134
C106: Year 2-3 | D106: 116416.14 | E106: =D106*$J65 -> 125.68273
C107: Year 3-4 | D107: 102783.2 | E107: =D107*$J65 -> 110.96462
C108: Year 4-5 | D108: 57488.077 | E108: =D108*$J65 -> 62.06406
C109: Over 5 years | D109: 134383.22 | E109: =D109*$J65 -> 145.07996
C110: Total debt | D110: =SUM(D104:D109) -> 691889.02 | E110: =SUM(E104:E109) -> 746.96257
C111: check | D111: =D110-D73-D77 -> 0
C114: Debt Maturity Profile at end-3Q25 | D114: (Ch$ millions) | E114: (USD millions)
C115: Less than 1 year | D115: =+D93+D104 -> 172595.1 | E115: =D115*$J65 -> 186.33347
C116: Year 1-2 | D116: =+D94+D105 -> 132191.14 | E116: =D116*$J65 -> 142.7134
C117: Year 2-3 | D117: =+D95+D106 -> 116416.14 | E117: =D117*$J65 -> 125.68273
C118: Year 3-4 | D118: =+D96+D107 -> 350929.2 | E118: =D118*$J65 -> 378.86275
C119: Year 4-5 | D119: =+D97+D108 -> 265438.36 | E119: =D119*$J65 -> 286.56694
C120: Over 5 years | D120: =+D98+D109 -> 1232956.4 | E120: =D120*$J65 -> 1331.0983
C121: Total debt (including leases) | D121: =SUM(D115:D120) -> 2270526.4 | E121: =SUM(E115:E120) -> 2451.2576
C122: check | D122: =D121-Model!$BD$121 -> 0
B131: 3Q25 | I131: Exchange rate as at end 3Q25 | J131: =Model!$O$208 -> 0.0010795988
I132: LTM Average exchange rate 3Q25 | J132: =Model!$O$207 -> 0.0010741488
...

Sheet Model
B2: ENTEL | C2: Annual | D2: Annual | E2: Annual | F2: Annual | G2: Annual | H2: Annual | I2: Annual | J2: Annual | K2: Annual | L2: Annual | M2: Annual | N2: Annual | O2: LTM | Q2: Quarterly | R2: Quarterly | S2: Quarterly | T2: Quartdrly | U2: Quarterly | V2: Quarterly | W2: Quarterly | X2: Quarterly | Y2: Quarterly | Z2: Quarterly | AA2: Quarterly | AB2: Quarterly | AC2: Quarterly | AD2: Quarterly | AE2: Quarterly | AF2: Quarterly | AG2: Quarterly | AH2: Quarterly | AI2: Quarterly | AJ2: Quarterly | AK2: Quarterly | AL2: Quarterly | AM2: Quarterly | AN2: Quarterly | AO2: Quarterly | AP2: Quarterly | AQ2: Quarterly | AR2: Quarterly | AS2: Quarterly | AT2: Quarterly | AU2: Quarterly | AV2: Quarterly | AW2: Quarterly | AX2: Quarterly | AY2: Quarterly | AZ2: Quarterly | BA2: Quarterly | BB2: Quarterly | BC2: Quarterly | BD2: Quarterly | BE2: Quarterly
B3: (Ch$ millions) | C3: 41974 | D3: 42340 | E3: 42707 | F3: 43073 | G3: 43438 | H3: 43803 | I3: 44169 | J3: 44534 | K3: 44926 | L3: 45291 | M3: 45657 | N3: 46022 | O3: =BE3 -> 46112 | Q3: 42437 | R3: 42527 | S3: 42622 | T3: 42714 | U3: 42801 | V3: 42892 | W3: 42987 | X3: 43079 | Y3: 43190 | Z3: 43281 | AA3: 43373 | AB3: 43465 | AC3: 43555 | AD3: 43646 | AE3: 43738 | AF3: 43830 | AG3: 43921 | AH3: 44012 | AI3: 44104 | AJ3: 44196 | AK3: 44286 | AL3: 44377 | AM3: 44469 | AN3: 44560 | AO3: 44651 | AP3: 44742 | AQ3: 44834 | AR3: 44926 | AS3: 45016 | AT3: 45107 | AU3: 45199 | AV3: 45291 | AW3: 45382 | AX3: 45473 | AY3: 45565 | AZ3: 45657 | BA3: 45747 | BB3: 45838 | BC3: 45930 | BD3: 46022 | BE3: 46112
C4: Act | D4: Act | E4: Act | F4: Act | G4: Act | H4: Act | I4: Act | J4: Act | K4: Act | L4: Act | M4: Act | N4: Act | O4: Act | Q4: Act | R4: Act | S4: Act | T4: Act | U4: Act | V4: Act | W4: Act | X4: Act | Y4: Act | Z4: Act | AA4: Act | AB4: Act | AC4: Act | AD4: Act | AE4: Act | AF4: Act | AG4: Act | AH4: Act | AI4: Act | AJ4: Act | AK4: Act | AL4: Act | AM4: Act | AN4: Act | AO4: Act | AP4: Act | AQ4: Act | AR4: Act | AS4: Act | AT4: Act | AU4: Act | AV4: Act | AW4: Act | AX4: Act | AY4: Act | AZ4: Act | BA4: Act | BB4: Act | BC4: Act | BD4: Act | BE4: Act
C5: FY | D5: FY | E5: FY | F5: FY | G5: FY | H5: FY | I5: FY | J5: FY | K5: FY | L5: FY | M5: FY | N5: FY | O5: LTM | Q5: Q1 | R5: Q2 | S5: Q3 | T5: Q4 | U5: Q1 | V5: Q2 | W5: Q3 | X5: Q4 | Y5: Q1 | Z5: Q2 | AA5: Q3 | AB5: Q4 | AC5: Q1 | AD5: Q2 | AE5: Q3 | AF5: Q4 | AG5: Q1 | AH5: Q2 | AI5: Q3 | AJ5: Q4 | AK5: Q1 | AL5: Q2 | AM5: Q3 | AN5: Q4 | AO5: Q1 | AP5: Q2 | AQ5: Q3 | AR5: Q4 | AS5: Q1 | AT5: Q2 | AU5: Q3 | AV5: Q4 | AW5: Q1 | AX5: Q2 | AY5: Q3 | AZ5: Q4 | BA5: Q1 | BB5: Q2 | BC5: Q3 | BD5: Q4 | BE5: Q1
B6: INCOME STATEMENT
B7: Revenues | C7: 1657770.4 | D7: 1784612.7 | E7: 1867697.1 | F7: 1943071.2 | G7: 1913174.3 | H7: 1978792 | I7: 2092644.2 | J7: 2408809.6 | K7: 2540682.9 | L7: 2473692.3 | M7: 2703236.7 | N7: 2954930.3 | O7: =SUM(BB7:BE7) -> 3002583.4 | Q7: 459463.63 | R7: =916299.774-Q7 -> 456836.15 | S7: =1384201.053-R7-Q7 -> 467901.28 | T7: =E7-S7-R7-Q7 -> 483496.02 | U7: 473615.34 | V7: =952346.117-U7 -> 478730.78 | W7: =1432252.759-V7-U7 -> 479906.64 | X7: =F7-W7-V7-U7 -> 510818.44 | Y7: 461181.57 | Z7: =926857.408-Y7 -> 465675.84 | AA7: =1408181.843-Z7-Y7 -> 481324.44 | AB7: =G7-AA7-Z7-Y7 -> 504992.44 | AC7: 471553.29 | AD7: 482669.9 | AE7: 496056.71 | AF7: =H7-AE7-AD7-AC7 -> 528512.09 | AG7: 513442.28 | AH7: 457638.94 | AI7: 534454.77 | AJ7: =I7-AI7-AH7-AG7 -> 587108.25 | AK7: 557729.51 | AL7: 591680.99 | AM7: 608206.88 | AN7: =J7-AM7-AL7-AK7 -> 651192.23 | AO7: 640785.58 | AP7: 646628.75 | AQ7: 622782.23 | AR7: =K7-AO7-AP7-AQ7 -> 630486.35 | AS7: 601409.66 | AT7: 607222.76 | AU7: 603807.07 | AV7: =L7-AS7-AT7-AU7 -> 661252.82 | AW7: 649744.56 | AX7: 660664.46 | AY7: 659565.95 | AZ7: =M7-AW7-AX7-AY7 -> 733261.76 | BA7: 707083.93 | BB7: =1412720.853-BA7 -> 705636.93 | BC7: 730437.04 | BD7: =N7-BA7-BB7-BC7 -> 811772.39 | BE7: 754737.08
B8: % y-o-y growth | D8: =D7/C7-1 -> 0.076513787 | E8: =E7/D7-1 -> 0.046555989 | F8: =F7/E7-1 -> 0.04035672 | G8: =G7/F7-1 -> -0.015386423 | H8: =H7/G7-1 -> 0.034297819 | I8: =I7/H7-1 -> 0.057536237 | J8: =J7/I7-1 -> 0.15108415 | K8: =K7/J7-1 -> 0.054746256 | ... N8: =N7/M7-1 -> 0.093108216 | U8: =U7/Q7-1 -> 0.030800503 | V8: =V7/R7-1 -> 0.047926663 | W8: =W7/S7-1 -> 0.025657897 | X8: =X7/T7-1 -> 0.056510128 | Y8: =Y7/U7-1 -> -0.026252883 | Z8: =Z7/V7-1 -> -0.027269901 | AA8: =AA7/W7-1 -> 0.00295431 | AB8: =AB7/X7-1 -> -0.011405227 | ... BE8: =BE7/BA7-1 -> 0.067393909
B9: Other income | C9: 4299.76 | D9: 8284.735 | E9: 19214.192 | F9: 11974.824 | G9: 9874.347 | H9: 11475.402 | I9: 13254.828 | J9: 30500.293 | K9: 52062.685 | L9: 48125.237 | M9: 64957.031 | N9: 77576.278 | O9: =SUM(BB9:BE9) -> 81218.768 | Q9: 1821.463 | R9: =3760.468-Q9 -> 1939.005 | S9: =6011.072-R9-Q9 -> 2250.604 | T9: =E9-S9-R9-Q9 -> 13203.12 | U9: 3735.191 | V9: =6370.919-U9 -> 2635.728 | W9: =9113.878-V9-U9 -> 2742.959 | X9: =F9-W9-V9-U9 -> 2860.946 | Y9: 2432.787 | Z9: =5301.876-Y9 -> 2869.089 | AA9: =7461.375-Z9-Y9 -> 2159.499 | AB9: =G9-AA9-Z9-Y9 -> 2412.972 | AC9: 3249.484 | AD9: 2802.708 | AE9: 2712.27 | AF9: =H9-AE9-AD9-AC9 -> 2710.94 | AG9: 3526.614 | AH9: 3893.964 | AI9: 2856.609 | AJ9: =I9-AI9-AH9-AG9 -> 2977.641 | AK9: 6730.949 | AL9: 6747.994 | AM9: 8478.316 | AN9: =J9-AM9-AL9-AK9 -> 8543.034 | AO9: 9547.493 | AP9: 16613.511 | AQ9: 13210.508 | AR9: =K9-AO9-AP9-AQ9 -> 12691.173 | AS9: 12412.806 | AT9: 10381.294 | AU9: 14140.534 | AV9: =L9-AS9-AT9-AU9 -> 11190.603 | AW9: 15015.756 | AX9: 19267.787 | AY9: 14488.232 | AZ9: =M9-AW9-AX9-AY9 -> 16185.256 | BA9: 17224.497 | BB9: =34236.661-BA9 -> 17012.164 | BC9: 17565.94 | BD9: =N9-BA9-BB9-BC9 -> 25773.677 | BE9: 20866.987
B10: Salaries and Expenses / Employee Benefits Expenses | C10: -222224.88 | D10: -247005.73 | E10: -245606.06 | F10: -249163.56 | G10: -260153.63 | H10: -260168.14 | I10: -256582.14 | J10: -257334.49 | K10: -296125.85 | L10: -301943.15 | M10: -323940.67 | N10: -350441.87 | O10: =SUM(BB10:BE10) -> -352609.42 | Q10: -60587.981 | R10: =-121638.494-Q10 -> -61050.513 | S10: =-183842.004-R10-Q10 -> -62203.51 | T10: =E10-S10-R10-Q10 -> -61764.055 | U10: -64682.209 | V10: =-126399.286-U10 -> -61717.077 | W10: =-187449.049-V10-U10 -> -61049.763 | X10: =F10-W10-V10-U10 -> -61714.509 | Y10: -62514.423 | Z10: =-132921.69-Y10 -> -70407.267 | AA10: =-199812.093-Z10-Y10 -> -66890.403 | AB10: =G10-AA10-Z10-Y10 -> -60341.534 | AC10: -60638.208 | AD10: -69113.453 | AE10: -62648.176 | AF10: =H10-AE10-AD10-AC10 -> -67768.301 | AG10: -64271.068 | AH10: -63243.043 | AI10: -65576.948 | AJ10: =I10-AI10-AH10-AG10 -> -63491.076 | AK10: -64370.446 | AL10: -63447.64 | AM10: -61902.616 | AN10: =J10-AM10-AL10-AK10 -> -67613.785 | AO10: -73170.807 | AP10: -71226.364 | AQ10: -78205.358 | AR10: =K10-AO10-AP10-AQ10 -> -73523.323 | AS10: -83977.997 | AT10: -71676.127 | AU10: -71810 | AV10: =L10-AS10-AT10-AU10 -> -74479.023 | AW10: -77056.052 | AX10: -77702.524 | AY10: -85387.053 | AZ10: =M10-AW10-AX10-AY10 -> -83795.041 | BA10: -88567.207 | BB10: =-170273.897-BA10 -> -81706.69 | BC10: -87719.734 | BD10: =N10-BA10-BB10-BC10 -> -92448.235 | BE10: -90734.76
B11: Depreciation and amortization expenses | C11: -239635.27 | D11: -273625.47 | E11: -299584.31 | F11: -315867.65 | G11: -331565.83 | H11: -422651.52 | I11: -467435.7 | J11: -466882.18 | K11: -518018.76 | L11: -504142.39 | M11: -544468.26 | N11: -570766.45 | O11: =SUM(BB11:BE11) -> -577039.63 | Q11: -73266.158 | R11: =-147348.536-Q11 -> -74082.378 | S11: =-222514.129-R11-Q11 -> -75165.593 | T11: =E11-S11-R11-Q11 -> -77070.185 | U11: -77803.059 | V11: =-156844.167-U11 -> -79041.108 | W11: =-235710.501-V11-U11 -> -78866.334 | X11: =F11-W11-V11-U11 -> -80157.151 | Y11: -81303.266 | Z11: =-163860.322-Y11 -> -82557.056 | AA11: =-247607.981-Z11-Y11 -> -83747.659 | AB11: =G11-AA11-Z11-Y11 -> -83957.847 | AC11: -101130.35 | AD11: -103801.07 | AE11: -107265 | AF11: =H11-AE11-AD11-AC11 -> -110455.09 | AG11: -115515.19 | AH11: -116506.96 | AI11: -116989.27 | AJ11: =I11-AI11-AH11-AG11 -> -118424.28 | AK11: -114882.64 | AL11: -114555.78 | AM11: -116826.47 | AN11: =J11-AM11-AL11-AK11 -> -120617.3 | AO11: -123409.77 | AP11: -138669.03 | AQ11: -127929.62 | AR11: =K11-AO11-AP11-AQ11 -> -128010.34 | AS11: -123770.5 | AT11: -124236.54 | AU11: -127476.87 | AV11: =L11-AS11-AT11-AU11 -> -128658.49 | AW11: -132760.02 | AX11: -139544.61 | AY11: -139744.07 | AZ11: =M11-AW11-AX11-AY11 -> -132419.55 | BA11: -139408.61 | BB11: =-280948.855-BA11 -> -141540.25 | BC11: -139017.99 | BD11: =N11-BA11-BB11-BC11 -> -150799.61 | BE11: -145681.78
B12: Impairment losses (reversals), Net | D12: -53796.077 | E12: -58901.242 | F12: -52089.5 | G12: -68584.398 | H12: -70132.193 | I12: -79684.088 | J12: -98585.66 | K12: -106577.97 | L12: -122085.65 | M12: -91587.508 | N12: -89695.735 | O12: =SUM(BB12:BE12) -> -88741.266 | Q12: -14397.242 | R12: =-25060.834-Q12 -> -10663.592 | S12: =-39164.733-R12-Q12 -> -14103.899 | T12: =E12-S12-R12-Q12 -> -19736.509 | U12: -11569.119 | V12: =-24323.843-U12 -> -12754.724 | W12: =-36739.808-V12-U12 -> -12415.965 | X12: =F12-W12-V12-U12 -> -15349.692 | Y12: -19552.524 | Z12: =-37733.019-Y12 -> -18180.495 | AA12: =-52556.869-Z12-Y12 -> -14823.85 | AB12: =G12-AA12-Z12-Y12 -> -16027.529 | AC12: -14484.416 | AD12: -15851.207 | AE12: -18695.275 | AF12: =H12-AE12-AD12-AC12 -> -21101.295 | AG12: -18307.127 | AH12: -23134.682 | AI12: -17233.733 | AJ12: =I12-AI12-AH12-AG12 -> -21008.546 | AK12: -19896.875 | AL12: -22872.512 | AM12: -23589.972 | AN12: =J12-AM12-AL12-AK12 -> -32226.301 | AO12: -27789.105 | AP12: -25952.236 | AQ12: -28648.557 | AR12: =K12-AO12-AP12-AQ12 -> -24188.069 | AS12: -55592.447 | AT12: -21322.947 | AU12: -21708.639 | AV12: =L12-AS12-AT12-AU12 -> -23461.619 | AW12: -22258.555 | AX12: -21931.153 | AY12: -20617.08 | AZ12: =M12-AW12-AX12-AY12 -> -26780.72 | BA12: -22782.496 | BB12: =-44683.182-BA12 -> -21900.686 | BC12: -22915.503 | BD12: =N12-BA12-BB12-BC12 -> -22097.05 | BE12: -21828.027
B13: Other expenses | C13: -1024171.9 | D13: -1137592.9 | E13: -1168814.9 | F13: -1220664.5 | G13: -1171742.7 | H13: -1100674.4 | I13: -1131313.5 | J13: -1342942.4 | K13: -1459378.3 | L13: -1395401.4 | M13: -1573911.2 | N13: -1771543.5 | O13: =SUM(BB13:BE13) -> -1802036.4 | Q13: -278000.77 | R13: =-567454.367-Q13 -> -289453.59 | S13: =-856123.189-R13-Q13 -> -288668.82 | T13: =E13-S13-R13-Q13 -> -312691.67 | U13: -291753.2 | V13: =-600966.078-U13 -> -309212.88 | W13: =-899434.203-V13-U13 -> -298468.13 | X13: =F13-W13-V13-U13 -> -321230.34 | Y13: -283190.07 | Z13: =-570100.181-Y13 -> -286910.11 | AA13: =-865812.941-Z13-Y13 -> -295712.76 | AB13: =G13-AA13-Z13-Y13 -> -305929.76 | AC13: -262815.12 | AD13: -263786.01 | AE13: -270708.18 | AF13: =H13-AE13-AD13-AC13 -> -303365.12 | AG13: -276511.41 | AH13: -227174.53 | AI13: -296649.36 | AJ13: =I13-AI13-AH13-AG13 -> -330978.17 | AK13: -308125.44 | AL13: -318886.29 | AM13: -335253.03 | AN13: =J13-AM13-AL13-AK13 -> -380677.62 | AO13: -360282.34 | AP13: -367199.45 | AQ13: -357200.58 | AR13: =K13-AO13-AP13-AQ13 -> -374695.95 | AS13: -343565.86 | AT13: -334024.95 | AU13: -335885.75 | AV13: =L13-AS13-AT13-AU13 -> -381924.83 | AW13: -380732.04 | AX13: -383573.39 | AY13: -375359.64 | AZ13: =M13-AW13-AX13-AY13 -> -434246.17 | BA13: -423133.58 | BB13: =-843243.564-BA13 -> -420109.98 | BC13: -427235.42 | BD13: =N13-BA13-BB13-BC13 -> -501064.53 | BE13: -453626.47
B14: Other gains (losses) | C14: 5981.586 | D14: -33.432 | E14: 390.536 | F14: 124.569 | G14: -89 | H14: 207275.45 | I14: 41585.368 | J14: 20809.511 | K14: 544963.98 | L14: 51324.376 | M14: -3433.485 | N14: -205.502 | O14: =SUM(BB14:BE14) -> -533.823 | Q14: 25.257 | R14: =250.944-Q14 -> 225.687 | S14: =268.965-R14-Q14 -> 18.021 | T14: =E14-S14-R14-Q14 -> 121.571 | U14: -325.238 | V14: =-341.523-U14 -> -16.285 | W14: =27.174-V14-U14 -> 368.697 | X14: =F14-W14-V14-U14 -> 97.395 | Y14: -75.017 | Z14: =-80.968-Y14 -> -5.951 | AA14: =-124.264-Z14-Y14 -> -43.296 | AB14: =G14-AA14-Z14-Y14 -> 35.264 | AC14: -18.014 | AD14: -33.814 | AE14: -281.206 | AF14: =H14-AE14-AD14-AC14 -> 207608.49 | AG14: 13736.444 | AH14: 14560.646 | AI14: 5728.474 | AJ14: =I14-AI14-AH14-AG14 -> 7559.804 | AK14: 4298.592 | AL14: 10024.151 | AM14: 6660.594 | AN14: =J14-AM14-AL14-AK14 -> -173.826 | AO14: -392.27 | AP14: 486325.08 | AQ14: 59602.71 | AR14: =K14-AO14-AP14-AQ14 -> -571.538 | AS14: -484.16 | AT14: 118.857 | AU14: -509.306 | AV14: =L14-AS14-AT14-AU14 -> 52198.985 | AW14: -116.948 | AX14: 490.644 | AY14: -609.822 | AZ14: =M14-AW14-AX14-AY14 -> -3197.359 | BA14: 306.804 | BB14: =675.27-BA14 -> 368.466 | BC14: -449.802 | BD14: =N14-BA14-BB14-BC14 -> -430.97 | BE14: -21.517
B15: Operating Profit | C15: =C7+SUM(C9:C14) -> 182019.64 | D15: =D7+SUM(D9:D14) -> 80843.799 | E15: =E7+SUM(E9:E14) -> 114395.32 | F15: =F7+SUM(F9:F14) -> 117385.34 | G15: =G7+SUM(G9:G14) -> 90913.071 | H15: =H7+SUM(H9:H14) -> 343916.57 | I15: =I7+SUM(I9:I14) -> 212469.04 | J15: =J7+SUM(J9:J14) -> 294374.69 | ... O15: =O7+SUM(O9:O14) -> 262841.65 | Q15: =Q7+SUM(Q9:Q14) -> 35058.193 | R15: =R7+SUM(R9:R14) -> 23750.762 | S15: =S7+SUM(S9:S14) -> 30028.08 | T15: =T7+SUM(T9:T14) -> 25558.286 | U15: =U7+SUM(U9:U14) -> 31217.703 | V15: =V7+SUM(V9:V14) -> 18624.436 | W15: =W7+SUM(W9:W14) -> 32218.111 | X15: =X7+SUM(X9:X14) -> 35325.086 | ... BE15: =BE7+SUM(BE9:BE14) -> 63711.506
B16: Finance Income | C16: 10818.705 | D16: 12183.865 | E16: 5952.92 | F16: 5225.532 | G16: 1889.772 | H16: 8746.947 | I16: 10894.534 | J16: 4919.952 | K16: 26563.887 | L16: 26535.094 | M16: 48118.158 | N16: 28768.371 | O16: =SUM(BB16:BE16) -> 26993.533 | Q16: 6119.225 | R16: =9473.433-Q16 -> 3354.208 | S16: =7842.692-R16-Q16 -> -1630.741 | T16: =E16-S16-R16-Q16 -> -1889.772 | U16: 2528.653 | V16: =5048.04-U16 -> 2519.387 | W16: =4953.604-V16-U16 -> -94.436 | X16: =F16-W16-V16-U16 -> 271.928 | Y16: 835.356 | Z16: =1402.952-Y16 -> 567.596 | AA16: =1687.118-Z16-Y16 -> 284.166 | AB16: =G16-AA16-Z16-Y16 -> 202.654 | AC16: 3186.538 | AD16: 4354.644 | AE16: 517.6 | AF16: =H16-AE16-AD16-AC16 -> 688.165 | AG16: 4796.556 | AH16: 3554.087 | AI16: 1444.183 | AJ16: =I16-AI16-AH16-AG16 -> 1099.708 | AK16: 644.156 | AL16: 460.657 | AM16: 1479.932 | AN16: =J16-AM16-AL16-AK16 -> 2335.207 | AO16: 3384.097 | AP16: 8608.77 | AQ16: 8591.226 | AR16: =K16-AO16-AP16-AQ16 -> 5979.794 | AS16: 5825.119 | AT16: 4203.163 | AU16: 6803.021 | AV16: =L16-AS16-AT16-AU16 -> 9703.791 | AW16: 11361.421 | AX16: 8768.153 | AY16: 5351.549 | AZ16: =M16-AW16-AX16-AY16 -> 22637.035 | BA16: 5102.986 | BB16: =7564.088-BA16 -> 2461.102 | BC16: 6263.529 | BD16: =N16-BA16-BB16-BC16 -> 14940.754 | BE16: 3328.148
B17: Financial expenses | C17: -55252.785 | D17: -70978.326 | E17: -82221.963 | F17: -80035.968 | G17: -77711.185 | H17: -97558.997 | I17: -102535.94 | J17: -113951.13 | K17: -113696.38 | L17: -113270.2 | M17: -111986.5 | N17: -165362.52 | O17: =SUM(BB17:BE17) -> -138918.41 | Q17: -18462.272 | R17: =-37632.325-Q17 -> -19170.053 | S17: =-56930.486-R17-Q17 -> -19298.161 | T17: =E17-S17-R17-Q17 -> -25291.477 | U17: -18449.335 | V17: =-40529.797-U17 -> -22080.462 | W17: =-60237.471-V17-U17 -> -19707.674 | X17: =F17-W17-V17-U17 -> -19798.497 | Y17: -21373.738 | Z17: =-42191.821-Y17 -> -20818.083 | AA17: =-61902.072-Z17-Y17 -> -19710.251 | AB17: =G17-AA17-Z17-Y17 -> -15809.113 | AC17: -22786.558 | AD17: -24444.595 | AE17: -24471.645 | AF17: =H17-AE17-AD17-AC17 -> -25856.199 | AG17: -27204.418 | AH17: -26018.812 | AI17: -24679.518 | AJ17: =I17-AI17-AH17-AG17 -> -24633.19 | AK17: -23329.043 | AL17: -22877.109 | AM17: -41353.92 | AN17: =J17-AM17-AL17-AK17 -> -26391.061 | AO17: -24603.053 | AP17: -30773.087 | AQ17: -29217.044 | AR17: =K17-AO17-AP17-AQ17 -> -29103.199 | AS17: -27587.608 | AT17: -28198.521 | AU17: -28353.268 | AV17: =L17-AS17-AT17-AU17 -> -29130.803 | AW17: -27500.891 | AX17: -27692.341 | AY17: -27330.747 | AZ17: =M17-AW17-AX17-AY17 -> -29462.518 | BA17: -52370.305 | BB17: =-93066.125-BA17 -> -40695.82 | BC17: -16715.392 | BD17: =N17-BA17-BB17-BC17 -> -55581.004 | BE17: -25926.197
B18: Foreign currency translation differences | C18: -11243.068 | D18: -12945.839 | E18: -16051.379 | F18: -6973.571 | G18: -994.222 | H18: 4551.31 | I18: -115.094 | J18: 250.185 | K18: -350.491 | L18: -3187.775 | M18: -2897.341 | N18: 753.395 | O18: =SUM(BB18:BE18) -> -37.313 | Q18: -5943.731 | R18: =-9364.382-Q18 -> -3420.651 | S18: =-13744.459-R18-Q18 -> -4380.077 | T18: =E18-S18-R18-Q18 -> -2306.92 | U18: -1659.109 | V18: =-4111.661-U18 -> -2452.552 | W18: =-5895.437-V18-U18 -> -1783.776 | X18: =F18-W18-V18-U18 -> -1078.134 | Y18: -1176.139 | Z18: =-473.89-Y18 -> 702.249 | AA18: =-983.773-Z18-Y18 -> -509.883 | AB18: =G18-AA18-Z18-Y18 -> -10.449 | AC18: 1969.702 | AD18: 51.292 | AE18: 2081.58 | AF18: =H18-AE18-AD18-AC18 -> 448.736 | AG18: -635.473 | AH18: -24.416 | AI18: -722.503 | AJ18: =I18-AI18-AH18-AG18 -> 1267.298 | AK18: -602.037 | AL18: -1581.046 | AM18: 739.708 | AN18: =J18-AM18-AL18-AK18 -> 1693.56 | AO18: 2569.758 | AP18: -2760.954 | AQ18: -2817.641 | AR18: =K18-AO18-AP18-AQ18 -> 2658.346 | AS18: 191.191 | AT18: -1189.346 | AU18: -2525.323 | AV18: =L18-AS18-AT18-AU18 -> 335.703 | AW18: -1343.755 | AX18: -1544.142 | AY18: 442.993 | AZ18: =M18-AW18-AX18-AY18 -> -452.437 | BA18: 20.189 | BB18: =895.96-BA18 -> 875.771 | BC18: -863.595 | BD18: =N18-BA18-BB18-BC18 -> 721.03 | BE18: -770.519
B19: Results from inflation-adjusted units | C19: -22635.632 | D19: -22985.872 | E19: -15934.835 | F19: -9600.405 | G19: -16368.412 | H19: -19445.992 | I19: -26758.482 | J19: -66963.329 | K19: -130374.24 | L19: -39051.828 | M19: -32919.657 | N19: -24859.269 | O19: =SUM(BB19:BE19) -> -17398.975 | Q19: -3977.408 | R19: =-9499.781-Q19 -> -5522.373 | S19: =-13185.375-R19-Q19 -> -3685.594 | T19: =E19-S19-R19-Q19 -> -2749.46 | U19: -2766.358 | V19: =-7173.524-U19 -> -4407.166 | W19: =-7063.271-V19-U19 -> 110.253 | X19: =F19-W19-V19-U19 -> -2537.134 | Y19: -3444.75 | Z19: =-7426.083-Y19 -> -3981.333 | AA19: =-11862.017-Z19-Y19 -> -4435.934 | AB19: =G19-AA19-Z19-Y19 -> -4506.395 | AC19: 29.344 | AD19: -7543.41 | AE19: -3406.778 | AF19: =H19-AE19-AD19-AC19 -> -8525.148 | AG19: -10321.723 | AH19: -3890.407 | AI19: -152.219 | AJ19: =I19-AI19-AH19-AG19 -> -12394.133 | AK19: -12030.81 | AL19: -9283.999 | AM19: -12972.845 | AN19: =J19-AM19-AL19-AK19 -> -32675.675 | AO19: -26497.446 | AP19: -45863.712 | AQ19: -34966.079 | AR19: =K19-AO19-AP19-AQ19 -> -23047.008 | AS19: -11742.475 | AT19: -13578.407 | AU19: -126.653 | AV19: =L19-AS19-AT19-AU19 -> -13604.293 | AW19: -5147.068 | AX19: -11048.467 | AY19: -7258.756 | AZ19: =M19-AW19-AX19-AY19 -> -9465.366 | BA19: -9520.27 | BB19: =-16946.774-BA19 -> -7426.504 | BC19: -3732.227 | BD19: =N19-BA19-BB19-BC19 -> -4180.268 | BE19: -2059.976
B20: Profit before tax | C20: =SUM(C15,C16,C17,C18,C19) -> 103706.86 | D20: =SUM(D15,D16,D17,D18,D19) -> -13882.373 | E20: =SUM(E15,E16,E17,E18,E19) -> 6140.064 | F20: =SUM(F15,F16,F17,F18,F19) -> 26000.924 | G20: =SUM(G15,G16,G17,G18,G19) -> -2270.976 | H20: =SUM(H15,H16,H17,H18,H19) -> 240209.84 | I20: =SUM(I15,I16,I17,I18,I19) -> 93954.056 | J20: =SUM(J15,J16,J17,J18,J19) -> 118630.36 | ... O20: =SUM(O15,O16,O17,O18,O19) -> 133480.48 | Q20: =SUM(Q15,Q16,Q17,Q18,Q19) -> 12794.007 | R20: =SUM(R15,R16,R17,R18,R19) -> -1008.107 | S20: =SUM(S15,S16,S17,S18,S19) -> 1033.507 | T20: =SUM(T15,T16,T17,T18,T19) -> -6679.343 | U20: =SUM(U15,U16,U17,U18,U19) -> 10871.554 | V20: =SUM(V15,V16,V17,V18,V19) -> -7796.357 | W20: =SUM(W15,W16,W17,W18,W19) -> 10742.478 | X20: =SUM(X15,X16,X17,X18,X19) -> 12183.249 | ... BE20: =SUM(BE15,BE16,BE17,BE18,BE19) -> 38282.962
B21: Income tax benefit/(expense) | C21: 8013.985 | D21: 12780.376 | E21: 28018.036 | F21: 17408.617 | G21: -21343.116 | H21: -86057.731 | I21: -9487.808 | J21: -43655.049 | K21: -82964.112 | L21: -31710.265 | M21: -63495.128 | N21: 102243.01 | O21: =SUM(BB21:BE21) -> 62679.768 | Q21: 11174.927 | R21: =20979.756-Q21 -> 9804.829 | S21: =29402.861-R21-Q21 -> 8423.105 | T21: =E21-S21-R21-Q21 -> -1384.825 | U21: 3254.391 | V21: =8408.878-U21 -> 5154.487 | W21: =15330.006-V21-U21 -> 6921.128 | X21: =F21-W21-V21-U21 -> 2078.611 | Y21: 8203.185 | Z21: =-2388.757-Y21 -> -10591.942 | AA21: =-5550.49-Z21-Y21 -> -3161.733 | AB21: =G21-AA21-Z21-Y21 -> -15792.626 | AC21: -7977.813 | AD21: -928.308 | AE21: -28643.649 | AF21: =H21-AE21-AD21-AC21 -> -48507.961 | AG21: -45200.064 | AH21: 2864.235 | AI21: 4783.213 | AJ21: =I21-AI21-AH21-AG21 -> 28064.808 | AK21: -8842.548 | AL21: -10736.441 | AM21: -31470.177 | AN21: =J21-AM21-AL21-AK21 -> 7394.117 | AO21: 32165.322 | AP21: -167083.23 | AQ21: -2399.995 | AR21: =K21-AO21-AP21-AQ21 -> 54353.796 | AS21: 29914.65 | AT21: -5353.759 | AU21: -48449.803 | AV21: =L21-AS21-AT21-AU21 -> -7821.353 | AW21: -49637.925 | AX21: 17931.563 | AY21: 17658.1 | AZ21: =M21-AW21-AX21-AY21 -> -49446.866 | BA21: 29045.018 | BB21: =34640.927-BA21 -> 5595.909 | BC21: -24920.226 | BD21: =N21-BA21-BB21-BC21 -> 92522.308 | BE21: -10518.223
B22: Income from Continuing Operations | C22: =SUM(C20,C21) -> 111720.84 | D22: =SUM(D20,D21) -> -1101.997 | E22: =SUM(E20,E21) -> 34158.1 | F22: =SUM(F20,F21) -> 43409.541 | G22: =SUM(G20,G21) -> -23614.092 | H22: =SUM(H20,H21) -> 154152.11 | I22: =SUM(I20,I21) -> 84466.248 | J22: =SUM(J20,J21) -> 74975.311 | ... O22: =SUM(O20,O21) -> 196160.25 | Q22: =SUM(Q20,Q21) -> 23968.934 | R22: =SUM(R20,R21) -> 8796.722 | S22: =SUM(S20,S21) -> 9456.612 | T22: =SUM(T20,T21) -> -8064.168 | U22: =SUM(U20,U21) -> 14125.945 | V22: =SUM(V20,V21) -> -2641.87 | W22: =SUM(W20,W21) -> 17663.606 | X22: =SUM(X20,X21) -> 14261.86 | ... BE22: =SUM(BE20,BE21) -> 27764.739
B23: Discontinued Operations | C23: 0 | D23: 0 | E23: 0 | F23: 0 | G23: 0 | H23: 0 | I23: 0 | J23: 0 | K23: 0 | L23: 0 | M23: 0 | N23: 0 | O23: =SUM(BB23:BE23) -> 0 | Q23: 0 | R23: 0 | S23: 0 | T23: =E23-S23-R23-Q23 -> 0 | U23: 0 | V23: 0 | W23: 0 | X23: =F23-W23-V23-U23 -> 0 | Y23: 0 | Z23: 0 | AA23: 0 | AB23: =G23-AA23-Z23-Y23 -> 0 | AC23: 0 | AD23: 0 | AE23: 0 | AF23: =H23-AE23-AD23-AC23 -> 0 | AG23: 0 | AH23: 0 | AI23: 0 | AJ23: =I23-AI23-AH23-AG23 -> 0 | AK23: 0 | AL23: 0 | AM23: 0 | AN23: =J23-AM23-AL23-AK23 -> 0 | AO23: 0 | AP23: 0 | AQ23: 0 | AR23: =K23-AO23-AP23-AQ23 -> 0 | AS23: 0 | AT23: 0 | AU23: 0 | AV23: =L23-AS23-AT23-AU23 -> 0 | AW23: 0 | AX23: 0 | AY23: 0 | AZ23: =M23-AW23-AX23-AY23 -> 0 | BA23: 0 | BB23: =0-BA23 -> 0 | BC23: 0 | BD23: =N23-BA23-BB23-BC23 -> 0 | BE23: 0
B24: Net income | C24: =C22+C23 -> 111720.84 | D24: =D22+D23 -> -1101.997 | E24: =E22+E23 -> 34158.1 | F24: =F22+F23 -> 43409.541 | G24: =G22+G23 -> -23614.092 | H24: =H22+H23 -> 154152.11 | I24: =I22+I23 -> 84466.248 | J24: =J22+J23 -> 74975.311 | ... O24: =O22+O23 -> 196160.25 | Q24: =Q22+Q23 -> 23968.934 | R24: =R22+R23 -> 8796.722 | S24: =S22+S23 -> 9456.612 | T24: =T22+T23 -> -8064.168 | U24: =U22+U23 -> 14125.945 | V24: =V22+V23 -> -2641.87 | W24: =W22+W23 -> 17663.606 | X24: =X22+X23 -> 14261.86 | ... BE24: =BE22+BE23 -> 27764.739
B26: As % of Revenues unless stated otherwise
B27: =B10 -> Salaries and Expenses / Employee Benefits Expenses | C27: =-C10/C7 -> 0.13405046 | D27: =-D10/D7 -> 0.1384086 | E27: =-E10/E7 -> 0.13150209 | F27: =-F10/F7 -> 0.12823182 | G27: =-G10/G7 -> 0.1359801 | H27: =-H10/H7 -> 0.13147827 | I27: =-I10/I7 -> 0.12261145 | J27: =-J10/J7 -> 0.10683056 | ... O27: =-O10/O7 -> 0.11743534 | Q27: =-Q10/Q7 -> 0.13186676 | R27: =-R10/R7 -> 0.13363766 | S27: =-S10/S7 -> 0.13294153 | T27: =-T10/T7 -> 0.1277447 | U27: =-U10/U7 -> 0.13657119 | V27: =-V10/V7 -> 0.12891813 | W27: =-W10/W7 -> 0.12721175 | X27: =-X10/X7 -> 0.12081496 | ... BE27: =-BE10/BE7 -> 0.12022036
B28: =B11 -> Depreciation and amortization expenses | C28: =-C11/C7 -> 0.14455275 | D28: =-D11/D7 -> 0.15332485 | E28: =-E11/E7 -> 0.16040305 | F28: =-F11/F7 -> 0.16256103 | G28: =-G11/G7 -> 0.17330665 | H28: =-H11/H7 -> 0.21359068 | I28: =-I11/I7 -> 0.22337084 | J28: =-J11/J7 -> 0.19382278 | ... O28: =-O11/O7 -> 0.19218105 | Q28: =-Q11/Q7 -> 0.15946019 | R28: =-R11/R7 -> 0.162164 | S28: =-S11/S7 -> 0.16064413 | T28: =-T11/T7 -> 0.1594019 | U28: =-U11/U7 -> 0.16427479 | V28: =-V11/V7 -> 0.16510555 | W28: =-W11/W7 -> 0.16433683 | X28: =-X11/X7 -> 0.15691906 | ... BE28: =-BE11/BE7 -> 0.19302322
B29: =B12 -> Impairment losses (reversals), Net | C29: =-C12/C7 -> 0 | D29: =-D12/D7 -> 0.030144399 | E29: =-E12/E7 -> 0.031536828 | F29: =-F12/F7 -> 0.026807818 | G29: =-G12/G7 -> 0.035848484 | H29: =-H12/H7 -> 0.035441923 | I29: =-I12/I7 -> 0.038078182 | J29: =-J12/J7 -> 0.040927129 | ... O29: =-O12/O7 -> 0.029554971 | Q29: =-Q12/Q7 -> 0.031334889 | R29: =-R12/R7 -> 0.023342269 | S29: =-S12/S7 -> 0.030142895 | T29: =-T12/T7 -> 0.040820417 | U29: =-U12/U7 -> 0.024427247 | V29: =-V12/V7 -> 0.026642791 | W29: =-W12/W7 -> 0.025871626 | X29: =-X12/X7 -> 0.030049213 | ... BE29: =-BE12/BE7 -> 0.028921366
B30: =B13 -> Other expenses | C30: =-C13/C7 -> 0.61780084 | D30: =-D13/D7 -> 0.63744526 | E30: =-E13/E7 -> 0.62580537 | F30: =-F13/F7 -> 0.62821401 | G30: =-G13/G7 -> 0.61245999 | H30: =-H13/H7 -> 0.55623554 | I30: =-I13/I7 -> 0.54061433 | J30: =-J13/J7 -> 0.55751288 | ... O30: =-O13/O7 -> 0.60016198 | Q30: =-Q13/Q7 -> 0.60505502 | R30: =-R13/R7 -> 0.63360484 | S30: =-S13/S7 -> 0.61694386 | T30: =-T13/T7 -> 0.64673061 | U30: =-U13/U7 -> 0.61601299 | V30: =-V13/V7 -> 0.64590139 | W30: =-W13/W7 -> 0.62192956 | X30: =-X13/X7 -> 0.62885424 | ... BE30: =-BE13/BE7 -> 0.60103907
B31: =B15 -> Operating Profit | C31: =C15/C7 -> 0.10979786 | D31: =D15/D7 -> 0.045300474 | E31: =E15/E7 -> 0.061249398 | F31: =F15/F7 -> 0.060412267 | G31: =G15/G7 -> 0.047519493 | H31: =H15/H7 -> 0.17380127 | I31: =I15/I7 -> 0.10153137 | J31: =J15/J7 -> 0.12220754 | ... O31: =O15/O7 -> 0.087538501 | Q31: =Q15/Q7 -> 0.076302434 | R31: =R15/R7 -> 0.051989673 | S31: =S15/S7 -> 0.064176102 | T31: =T15/T7 -> 0.05286142 | U31: =U15/U7 -> 0.065913623 | V31: =V15/V7 -> 0.038903778 | W31: =W15/W7 -> 0.067134122 | X31: =X15/X7 -> 0.069153898 | ... BE31: =BE15/BE7 -> 0.084415498
B32: Finance Income as a % of cash at end of period | C32: =C16/C118 -> 0.028551469 | D32: =D16/D118 -> 0.089264007 | E32: =E16/E118 -> 0.053671092 | F32: =F16/F118 -> 0.035878193 | G32: =G16/G118 -> 0.025976872 | H32: =H16/H118 -> 0.019550105 | I32: =I16/I118 -> 0.053805153 | J32: =J16/J118 -> 0.045301436 | ... O32: =O16/O118 -> 0.12520983 | T32: =SUM(Q16:T16)/T118 -> 0.053671092 | U32: =SUM(R16:U16)/U118 -> 0.030126738 | V32: =SUM(S16:V16)/V118 -> 0.014129165 | W32: =SUM(T16:W16)/W118 -> 0.022288379 | X32: =SUM(U16:X16)/X118 -> 0.035878193 | Y32: =SUM(V16:Y16)/Y118 -> 0.07116953 | Z32: =SUM(W16:Z16)/Z118 -> 0.048754874 | AA32: =SUM(X16:AA16)/AA118 -> 0.21489915 | ... BE32: =SUM(BB16:BE16)/BE118 -> 0.12520983
B33: Finance costs as a % of debt including leases at end of period | C33: =-C17/C116 -> 0.038065864 | D33: =-D17/D116 -> 0.042415867 | E33: =-E17/E116 -> 0.051581876 | F33: =-F17/F116 -> 0.050506168 | G33: =-G17/G116 -> 0.042991844 | H33: =-H17/H116 -> 0.039196339 | I33: =-I17/I116 -> 0.043195758 | J33: =-J17/J116 -> 0.041924574 | ... O33: =-O17/O116 -> 0.061219167 | T33: =-SUM(Q17:T17)/T116 -> 0.051581876 | U33: =-SUM(R17:U17)/U116 -> 0.051816578 | V33: =-SUM(S17:V17)/V116 -> 0.050552252 | W33: =-SUM(T17:W17)/W116 -> 0.052332811 | X33: =-SUM(U17:X17)/X116 -> 0.050506168 | Y33: =-SUM(V17:Y17)/Y116 -> 0.052972583 | Z33: =-SUM(W17:Z17)/Z116 -> 0.049183176 | AA33: =-SUM(X17:AA17)/AA116 -> 0.048477946 | ... BE33: =-SUM(BB17:BE17)/BE116 -> 0.061219167
B34: =B20 -> Profit before tax | C34: =C20/C7 -> 0.062558037 | D34: =D20/D7 -> -0.0077789278 | E34: =E20/E7 -> 0.0032875053 | F34: =F20/F7 -> 0.013381354 | G34: =G20/G7 -> -0.0011870199 | H34: =H20/H7 -> 0.12139216 | I34: =I20/I7 -> 0.044897291 | J34: =J20/J7 -> 0.049248542 | ... O34: =O20/O7 -> 0.044455213 | Q34: =Q20/Q7 -> 0.027845527 | R34: =R20/R7 -> -0.0022067146 | S34: =S20/S7 -> 0.0022088142 | T34: =T20/T7 -> -0.013814681 | U34: =U20/U7 -> 0.022954396 | V34: =V20/V7 -> -0.016285473 | W34: =W20/W7 -> 0.022384516 | X34: =X20/X7 -> 0.023850449 | ... BE34: =BE20/BE7 -> 0.050723574
B35: Income tax benefit/(expense) as a % of Profit before tax | C35: =-C21/C20 -> -0.077275361 | D35: =-D21/D20 -> 0.92061897 | E35: =-E21/E20 -> -4.5631505 | F35: =-F21/F20 -> -0.6695384 | G35: =-G21/G20 -> -9.3982129 | H35: =-H21/H20 -> 0.35826064 | I35: =-I21/I20 -> 0.10098348 | J35: =-J21/J20 -> 0.36799222 | ... O35: =-O21/O20 -> -0.46958001 | Q35: =-Q21/Q20 -> -0.87345012 | R35: =-R21/R20 -> 9.7259805 | S35: =-S21/S20 -> -8.1500222 | T35: =-T21/T20 -> -0.20732952 | U35: =-U21/U20 -> -0.2993492 | V35: =-V21/V20 -> 0.66114045 | W35: =-W21/W20 -> -0.64427667 | X35: =-X21/X20 -> -0.17061221 | ... BE35: =-BE21/BE20 -> 0.27474946
B37: capex/sales | C37: =-C63/C7 -> 0.33260349 | D37: =-D63/D7 -> 0.2931655 | E37: =-E63/E7 -> 0.24318154 | F37: =-F63/F7 -> 0.25584701 | G37: =-G63/G7 -> 0.26546149 | H37: =-H63/H7 -> -0.0064757044 | I37: =-I63/I7 -> 0.13939777 | J37: =-J63/J7 -> 0.10812001 | ... O37: =-O63/O7 -> 0.16451557 | Q37: =-Q63/Q7 -> 0.23118316 | R37: =-R63/R7 -> 0.23778357 | S37: =-S63/S7 -> 0.23813522 | T37: =-T63/T7 -> 0.26456741 | U37: =-U63/U7 -> 0.24741341 | V37: =-V63/V7 -> 0.23029247 | W37: =-W63/W7 -> 0.28192044 | X37: =-X63/X7 -> 0.26312007 | ... BE37: =-BE63/BE7 -> 0.14393768
B38: D/A/sales | C38: =C42/C7 -> 0.14681209 | D38: =D42/D7 -> 0.15451056 | E38: =E42/E7 -> 0.16618616 | F38: =F42/F7 -> 0.16454228 | G38: =G42/G7 -> 0.17563349 | H38: =H42/H7 -> 0.2155328 | I38: =I42/I7 -> 0.22543863 | J38: =J42/J7 -> 0.19847047 | ... O38: =O42/O7 -> 0.19734444 | Q38: =Q42/Q7 -> 0.16100167 | R38: =R42/R7 -> 0.1637665 | S38: =S42/S7 -> 0.16215239 | T38: =T42/T7 -> 0.17730288 | U38: =U42/U7 -> 0.16628905 | V38: =V42/V7 -> 0.16709855 | W38: =W42/W7 -> 0.16636322 | X38: =X42/X7 -> 0.15881627 | ... BE38: =BE42/BE7 -> 0.19843412
B40: EBITDA | C40: =+C3 -> 41974 | D40: =+D3 -> 42340 | E40: =+E3 -> 42707 | F40: =+F3 -> 43073 | G40: =G3 -> 43438 | H40: =H3 -> 43803 | I40: =I3 -> 44169 | J40: =J3 -> 44534 | K40: =K3 -> 44926 | L40: =L3 -> 45291 | M40: =M3 -> 45657 | N40: =N3 -> 46022 | O40: =+O3 -> 46112 | Q40: =+Q3 -> 42437 | R40: =+R3 -> 42527 | S40: =+S3 -> 42622 | T40: =+T3 -> 42714 | U40: =+U3 -> 42801 | V40: =+V3 -> 42892 | W40: =+W3 -> 42987 | X40: =+X3 -> 43079 | Y40: =+Y3 -> 43190 | Z40: =Z3 -> 43281 | AA40: =AA3 -> 43373 | AB40: =AB3 -> 43465 | AC40: =+AC3 -> 43555 | AD40: =+AD3 -> 43646 | AE40: =+AE3 -> 43738 | AF40: =+AF3 -> 43830 | AG40: =+AG3 -> 43921 | AH40: =+AH3 -> 44012 | AI40: =+AI3 -> 44104 | AJ40: =+AJ3 -> 44196 | ... BE40: =+BE3 -> 46112
B41: Operating profit | C41: =C15 -> 182019.64 | D41: =D15 -> 80843.799 | E41: =E15 -> 114395.32 | F41: =F15 -> 117385.34 | G41: =G15 -> 90913.071 | H41: =H15 -> 343916.57 | I41: =I15 -> 212469.04 | J41: =J15 -> 294374.69 | ... O41: =O15 -> 262841.65 | Q41: =Q15 -> 35058.193 | R41: =R15 -> 23750.762 | S41: =S15 -> 30028.08 | T41: =T15 -> 25558.286 | U41: =U15 -> 31217.703 | V41: =V15 -> 18624.436 | W41: =W15 -> 32218.111 | X41: =X15 -> 35325.086 | ... BE41: =BE15 -> 63711.506
B42: Depreciation & amortisation | C42: 243380.73 | D42: 275741.49 | E42: 310385.41 | F42: 319717.36 | G42: 336017.48 | H42: 426494.59 | I42: 471762.85 | J42: 478077.57 | K42: 524404.22 | L42: 512992.83 | M42: 557760.31 | N42: 585619.61 | O42: =SUM(BB42:BE42) -> 592543.14 | Q42: 73974.41 | R42: =148788.867-Q42 -> 74814.457 | S42: =224660.177-SUM(Q42:R42) -> 75871.31 | T42: =E42-SUM(Q42:S42) -> 85725.236 | U42: 78757.047 | V42: =158752.268-U42 -> 79995.221 | W42: =238591.082-SUM(U42:V42) -> 79838.814 | X42: =F42-SUM(U42:W42) -> 81126.281 | Y42: 82362.655 | Z42: =166100.984-Y42 -> 83738.329 | AA42: =250942.805-SUM(Y42:Z42) -> 84841.821 | AB42: =G42-SUM(Y42:AA42) -> 85074.677 | AC42: 102088.16 | AD42: =206851.644-AC42 -> 104763.48 | AE42: =315077.947-SUM(AC42:AD42) -> 108226.3 | AF42: =H42-SUM(AC42:AE42) -> 111416.64 | AG42: 116596.81 | AH42: =234183.773-AG42 -> 117586.96 | AI42: =352256.697-SUM(AG42:AH42) -> 118072.92 | AJ42: =I42-SUM(AG42:AI42) -> 119506.16 | AK42: 116113.26 | AL42: =231725.243-AK42 -> 115611.98 | AM42: =349893.458-SUM(AK42:AL42) -> 118168.21 | AN42: =J42-SUM(AK42:AM42) -> 128184.11 | AO42: 124298.24 | AP42: =264572.517-AO42 -> 140274.28 | AQ42: =391141.616-SUM(AO42:AP42) -> 126569.1 | AR42: =K42-SUM(AO42:AQ42) -> 133262.6 | AS42: 125691.76 | AT42: =252462.754-AS42 -> 126770.99 | AU42: =382058.243-SUM(AS42:AT42) -> 129595.49 | AV42: =L42-SUM(AS42:AU42) -> 130934.59 | AW42: 135933.67 | AX42: =278199.116-AW42 -> 142265.44 | AY42: =420571.122-SUM(AW42:AX42) -> 142372.01 | AZ42: =M42-SUM(AW42:AY42) -> 137189.19 | BA42: 142842.06 | BB42: =287730.669-BA42 -> 144888.61 | BC42: =430692.527-SUM(BA42:BB42) -> 142961.86 | BD42: =N42-SUM(BA42:BC42) -> 154927.08 | BE42: 149765.59
B43: EBITDA | C43: =SUM(C41:C42) -> 425400.36 | D43: =SUM(D41:D42) -> 356585.29 | E43: =SUM(E41:E42) -> 424780.73 | F43: =SUM(F41:F42) -> 437102.7 | G43: =SUM(G41:G42) -> 426930.55 | H43: =SUM(H41:H42) -> 770411.16 | I43: =SUM(I41:I42) -> 684231.89 | J43: =SUM(J41:J42) -> 772452.26 | ... O43: =SUM(O41:O42) -> 855384.79 | Q43: =SUM(Q41:Q42) -> 109032.6 | R43: =SUM(R41:R42) -> 98565.219 | S43: =SUM(S41:S42) -> 105899.39 | T43: =SUM(T41:T42) -> 111283.52 | U43: =SUM(U41:U42) -> 109974.75 | V43: =SUM(V41:V42) -> 98619.657 | W43: =SUM(W41:W42) -> 112056.93 | X43: =SUM(X41:X42) -> 116451.37 | ... BE43: =SUM(BE41:BE42) -> 213477.1
B44: % growth | D44: =+D43/C43-1 -> -0.16176543 | E44: =+E43/D43-1 -> 0.1912458 | F44: =+F43/E43-1 -> 0.029007825 | G44: =+G43/F43-1 -> -0.023271753 | H44: =+H43/G43-1 -> 0.80453507 | I44: =+I43/H43-1 -> -0.1118614 | J44: =+J43/I43-1 -> 0.12893344 | K44: =+K43/J43-1 -> 0.65966619 | ... N44: =+N43/M43-1 -> 0.059421035 | U44: =+U43/Q43-1 -> 0.0086409659 | V44: =+V43/R43-1 -> 0.00055230436 | W44: =+W43/S43-1 -> 0.058145141 | X44: =+X43/T43-1 -> 0.046438546 | Y44: =+Y43/U43-1 -> -0.096686139 | Z44: =+Z43/V43-1 -> -0.044588322 | AA44: =+AA43/W43-1 -> -0.044166284 | AB44: =+AB43/X43-1 -> 0.084218084 | ... BE44: =+BE43/BA43-1 -> 0.10286807
B45: % margin | C45: =C43/C7 -> 0.25660995 | D45: =D43/D7 -> 0.19981103 | E45: =E43/E7 -> 0.22743556 | F45: =F43/F7 -> 0.22495455 | G45: =G43/G7 -> 0.22315299 | H45: =H43/H7 -> 0.38933408 | I45: =I43/I7 -> 0.32697 | J45: =J43/J7 -> 0.32067801 | ... O45: =O43/O7 -> 0.28488294 | Q45: =Q43/Q7 -> 0.2373041 | R45: =R43/R7 -> 0.21575617 | S45: =S43/S7 -> 0.22632849 | T45: =T43/T7 -> 0.2301643 | U45: =U43/U7 -> 0.23220268 | V45: =V43/V7 -> 0.20600233 | W45: =W43/W7 -> 0.23349734 | X45: =X43/X7 -> 0.22797017 | ... BE45: =BE43/BE7 -> 0.28284962
B47: Adjustment | C47: =C48-C43 -> 0 | D47: =D48-D43 -> 0 | E47: =E48-E43 -> 0 | F47: =F48-F43 -> 0 | G47: =G48-G43 -> -9.553 | H47: =H48-H43 -> -0.156 | I47: =I48-I43 -> 0 | J47: =J48-J43 -> 0 | ... O47: =O48-O43 -> 0 | Q47: =(E47-T47)/3 -> -0.070666667 | R47: =(E47-T47)/3 -> -0.070666667 | S47: =(E47-T47)/3 -> -0.070666667 | T47: =T48-T43 -> 0.212 | U47: =U48-U43 -> 0.25 | V47: =V48-V43 -> 0.343 | W47: =W48-W43 -> 0.075 | X47: =X48-X43 -> -0.668 | Y47: =Y48-Y43 -> 0.284 | Z47: =Z48-Z43 -> -0.372 | AA47: =AA48-AA43 -> 0.213 | ... BE47: =BE48-BE43 -> 0
B48: Adj. EBITDA | C48: =C43 -> 425400.36 | D48: 356585.29 | E48: 424780.73 | F48: 437102.7 | G48: 426921 | H48: 770411 | I48: 684231.89 | J48: 772452.26 | K48: 1282013 | L48: 762562.17 | M48: 788612.9 | N48: 835473.1 | O48: =SUM(BB48:BE48) -> 855384.79 | Q48: 109033 | R48: 98565 | S48: 105899 | T48: =+E48-S48-R48-Q48 -> 111283.73 | U48: 109975 | V48: 98620 | W48: 112057 | X48: =F48-W48-V48-U48 -> 116450.7 | Y48: 99342 | Z48: 94222 | AA48: 107108 | AB48: =G48-AA48-Z48-Y48 -> 126249 | AC48: 137805 | AD48: 137651 | AE48: 147397 | AF48: =H48-AE48-AD48-AC48 -> 347558 | AG48: 172697 | AH48: 163621 | AI48: 164663 | AJ48: =I48-AI48-AH48-AG48 -> 183250.89 | AK48: 177597 | AL48: 204303 | AM48: 203942 | AN48: =J48-AM48-AL48-AK48 -> 186610.26 | AO48: 189587 | AP48: 686795 | AQ48: 233180 | AR48: =K48-AO48-AP48-AQ48 -> 172451 | AS48: 132123 | AT48: 193233 | AU48: 190153 | AV48: =L48-AS48-AT48-AU48 -> 247053.17 | AW48: 187770 | AX48: 199937 | AY48: 194709 | AZ48: =M48-AW48-AX48-AY48 -> 206196.9 | BA48: 193565.4 | BB48: =396214-BA48 -> 202648.6 | BC48: 213626 | BD48: =N48-BA48-BB48-BC48 -> 225633.1 | BE48: 213477.1
B49: % growth | D49: =+D48/C48-1 -> -0.16176543 | E49: =+E48/D48-1 -> 0.1912458 | F49: =+F48/E48-1 -> 0.029007825 | G49: =+G48/F48-1 -> -0.023293608 | H49: =+H48/G48-1 -> 0.80457509 | I49: =+I48/H48-1 -> -0.11186122 | J49: =+J48/I48-1 -> 0.12893344 | K49: =+K48/J48-1 -> 0.65966632 | ... N49: =+N48/M48-1 -> 0.059421035 | U49: =+U48/Q48-1 -> 0.0086395862 | V49: =+V48/R48-1 -> 0.00055800741 | W49: =+W48/S48-1 -> 0.058149746 | X49: =+X48/T48-1 -> 0.04643055 | Y49: =+Y48/U48-1 -> -0.09668561 | Z49: =+Z48/V48-1 -> -0.044595417 | AA49: =+AA48/W48-1 -> -0.044165023 | AB49: =+AB48/X48-1 -> 0.084141195 | ... BE49: =+BE48/BA48-1 -> 0.10286807
B50: % margin | C50: =C48/C7 -> 0.25660995 | D50: =D48/D7 -> 0.19981103 | E50: =E48/E7 -> 0.22743556 | F50: =F48/F7 -> 0.22495455 | G50: =G48/G7 -> 0.22314799 | H50: =H48/H7 -> 0.389334 | I50: =I48/I7 -> 0.32697 | J50: =J48/J7 -> 0.32067801 | ... O50: =O48/O7 -> 0.28488294 | Q50: =Q48/Q7 -> 0.23730496 | R50: =R48/R7 -> 0.21575569 | S50: =S48/S7 -> 0.22632766 | T50: =T48/T7 -> 0.23016474 | U50: =U48/U7 -> 0.23220321 | V50: =V48/V7 -> 0.20600305 | W50: =W48/W7 -> 0.2334975 | X50: =X48/X7 -> 0.22796886 | ... BE50: =BE48/BE7 -> 0.28284962
B51: Adj. EBITDA | C51: =C48 -> 425400.36 | D51: =D48 -> 356585.29 | E51: =E48 -> 424780.73 | F51: =F48 -> 437102.7 | G51: =G48 -> 426921 | H51: 687180 | I51: =I48 -> 684231.89 | J51: =J48 -> 772452.26 | K51: =K48 -> 1282013 | L51: =L48 -> 762562.17 | M51: =M48 -> 788612.9 | N51: =N48 -> 835473.1 | O51: =O48 -> 855384.79 | Q51: 109033 | R51: 98565 | S51: 105899 | T51: =+E51-S51-R51-Q51 -> 111283.73 | U51: 109975 | V51: 98620 | W51: 112057 | X51: =F51-W51-V51-U51 -> 116450.7 | Y51: =Y48 -> 99342 | Z51: =Z48 -> 94222 | AA51: =AA48 -> 107108 | AB51: =G51-AA51-Z51-Y51 -> 126249 | AC51: 118091 | AD51: 116911 | AE51: 126772 | AF51: =H51-AE51-AD51-AC51 -> 325406
B52: % growth | D52: =+D51/C51-1 -> -0.16176543 | E52: =+E51/D51-1 -> 0.1912458 | F52: =+F51/E51-1 -> 0.029007825 | G52: =+G51/F51-1 -> -0.023293608 | H52: =+H51/G51-1 -> 0.60961864 | I52: =+I51/H51-1 -> -0.0042901583 | J52: =+J51/I51-1 -> 0.12893344 | K52: =+K51/J51-1 -> 0.65966632 | ... N52: =+N51/M51-1 -> 0.059421035 | U52: =+U51/Q51-1 -> 0.0086395862 | V52: =+V51/R51-1 -> 0.00055800741 | W52: =+W51/S51-1 -> 0.058149746 | X52: =+X51/T51-1 -> 0.04643055 | Y52: =+Y51/U51-1 -> -0.09668561 | Z52: =+Z51/V51-1 -> -0.044595417 | AA52: =+AA51/W51-1 -> -0.044165023 | AB52: =+AB51/X51-1 -> 0.084141195 | ... AF52: =+AF51/AB51-1 -> 1.5774937
B53: % margin | C53: =C48/C7 -> 0.25660995 | D53: =D48/D7 -> 0.19981103 | E53: =E48/E7 -> 0.22743556 | F53: =F48/F7 -> 0.22495455 | G53: =G48/G7 -> 0.22314799 | H53: =H48/H7 -> 0.389334 | I53: =I48/I7 -> 0.32697 | J53: =J48/J7 -> 0.32067801 | ... N53: =N48/N7 -> 0.28273868 | Q53: =Q48/Q7 -> 0.23730496 | R53: =R48/R7 -> 0.21575569 | S53: =S48/S7 -> 0.22632766 | T53: =T48/T7 -> 0.23016474 | U53: =U48/U7 -> 0.23220321 | V53: =V48/V7 -> 0.20600305 | W53: =W48/W7 -> 0.2334975 | X53: =X48/X7 -> 0.22796886 | ... AF53: =AF48/AF7 -> 0.65761599
B56: CASH FLOW | C56: =+C40 -> 41974 | D56: =+D40 -> 42340 | E56: =+E40 -> 42707 | F56: =+F40 -> 43073 | G56: =G3 -> 43438 | H56: =H3 -> 43803 | I56: =I3 -> 44169 | J56: =J3 -> 44534 | K56: =K3 -> 44926 | L56: =L3 -> 45291 | M56: =M3 -> 45657 | N56: =N3 -> 46022 | O56: =+O40 -> 46112 | Q56: =+Q40 -> 42437 | R56: =+R40 -> 42527 | S56: =+S40 -> 42622 | T56: =+T40 -> 42714 | U56: =+U40 -> 42801 | V56: =+V40 -> 42892 | W56: =+W40 -> 42987 | X56: =+X40 -> 43079 | Y56: =+Y40 -> 43190 | Z56: =Z3 -> 43281 | AA56: =AA3 -> 43373 | AB56: =AB3 -> 43465 | AC56: =+AC40 -> 43555 | AD56: =+AD40 -> 43646 | AE56: =+AE40 -> 43738 | AF56: =+AF40 -> 43830 | AG56: =+AG40 -> 43921 | AH56: =+AH40 -> 44012 | AI56: =+AI40 -> 44104 | AJ56: =+AJ40 -> 44196 | ... BE56: =+BE40 -> 46112
B57: Adjusted EBITDA | C57: =C48 -> 425400.36 | D57: =D48 -> 356585.29 | E57: =E48 -> 424780.73 | F57: =F48 -> 437102.7 | G57: =G48 -> 426921 | H57: =H48 -> 770411 | I57: =I48 -> 684231.89 | J57: =J48 -> 772452.26 | ... O57: =O48 -> 855384.79 | Q57: =Q48 -> 109033 | R57: =R48 -> 98565 | S57: =S48 -> 105899 | T57: =T48 -> 111283.73 | U57: =U48 -> 109975 | V57: =V48 -> 98620 | W57: =W48 -> 112057 | X57: =X48 -> 116450.7 | ... BE57: =BE48 -> 213477.1
B58: Working Capital | C58: =1941498.368-1126295.714 -> 815202.65 | D58: =2068914.746-1327335.808 -> 741578.94 | E58: =2151996.649-1385826.645 -> 766170 | F58: =2253556.915-1327187.348 -> 926369.57 | G58: =2207115.207-1367127.786 -> 839987.42 | H58: =2231794.506-1218180.319 -> 1013614.2 | I58: =2751909.058-1593219.688 -> 1158689.4 | J58: =2658932.073-1746165.583 -> 912766.49 | K58: =2878859.206-1751875.79 -> 1126983.4 | L58: 95491 | M58: -57898 | N58: 26000 | O58: =SUM(BB58:BE58) -> 20854 | Q58: =551539.209-326123.809 -> 225415.4 | R58: =1079131.461-669572.112-Q58 -> 184143.95 | S58: =1608052.361-1061885.554-R58-Q58 -> 136607.46 | T58: =E58-Q58-R58-S58 -> 220003.2 | U58: =573647.243-354765.819 -> 218881.42 | V58: =1121670.411-708787.15-U58 -> 194001.84 | W58: =1682230.886-1012704.434-V58-U58 -> 256643.19 | X58: =F58-U58-V58-W58 -> 256843.12 | Y58: =559159.458-382442.332 -> 176717.13 | Z58: =1075707.571-685013.647-Y58 -> 213976.8 | AA58: =1623090.85-1006459.901-Z58-Y58 -> 225937.03 | AB58: =G58-Y58-Z58-AA58 -> 223356.47 | AC58: =564296.889-329533.03 -> 234763.86 | AD58: =1119341.196-630418.379-AC58 -> 254158.96 | AE58: =1686799.527-967221.03-AD58-AC58 -> 230655.68 | AF58: =H58-AC58-AD58-AE58 -> 294035.69 | AG58: =593306.152-363147.204 -> 230158.95 | AH58: =1187882.896-687341.909-AG58 -> 270382.04 | AI58: =1934722.041-1034410.938-AH58-AG58 -> 399770.12 | AJ58: =I58-AG58-AH58-AI58 -> 258378.27 | AK58: =645909.091-384801.424 -> 261107.67 | AL58: =1425449.43-879715.446-AK58 -> 284626.32 | AM58: =1942766.882-1145461.166-AL58-AK58 -> 251571.73 | AN58: =J58-AK58-AL58-AM58 -> 115460.77 | AO58: =712177.108-436348.431 -> 275828.68 | AP58: =1376160.462-918919.509-AO58 -> 181412.28 | AQ58: =2099841.438-1410844.641-AP58-AO58 -> 231755.84 | AR58: =K58-AO58-AP58-AQ58 -> 437986.62 | AS58: -9422 | AT58: =-88-AS58 -> 9334 | AU58: =18671-AT58-AS58 -> 18759 | AV58: =L58-AS58-AT58-AU58 -> 76820 | AW58: -63898 | AX58: =-59449-AW58 -> 4449 | AY58: =-97106-AX58-AW58 -> -37657 | AZ58: =M58-AW58-AX58-AY58 -> 39208 | BA58: -28854 | BB58: =-20574-BA58 -> 8280 | BC58: =-24000-BB58-BA58 -> -3426 | BD58: =N58-BA58-BB58-BC58 -> 50000 | BE58: -34000
B59: Taxes, net | C59: -38853.279 | D59: -77538.637 | E59: -86929.865 | F59: -23661.061 | G59: 17586.026 | H59: -36425.48 | I59: -176907.77 | J59: 31681.634 | K59: -162133.04 | L59: 14581.583 | M59: -72752.674 | N59: -35874.522 | O59: =SUM(BB59:BE59) -> -39960.969 | Q59: -14808.188 | R59: =-39975.061-Q59 -> -25166.873 | S59: =-60444.478-R59-Q59 -> -20469.417 | T59: =IFERROR(E59-SUM(Q59:S59),"NA") -> -26485.387 | U59: -24048.451 | V59: =-46422.932-U59 -> -22374.481 | W59: =-25489.303-V59-U59 -> 20933.629 | X59: =+IFERROR(F59-U59-V59-W59,"NA") -> 1828.242 | Y59: -14742.535 | Z59: =17225.331-Y59 -> 31967.866 | AA59: =10106.649-Z59-Y59 -> -7118.682 | AB59: =G59-AA59-Z59-Y59 -> 7479.377 | AC59: 8044.41 | AD59: =-24120.781-AC59 -> -32165.191 | AE59: =-23349.44-AD59-AC59 -> 771.341 | AF59: =H59-AE59-AD59-AC59 -> -13076.04 | AG59: -29859.098 | AH59: =-125076.931-AG59 -> -95217.833 | AI59: =-142463.619-AH59-AG59 -> -17386.688 | AJ59: =I59-AI59-AH59-AG59 -> -34444.151 | AK59: -20678.626 | AL59: =45342.607-AK59 -> 66021.233 | AM59: =40116.588-AL59-AK59 -> -5226.019 | AN59: =J59-AM59-AL59-AK59 -> -8434.954 | AO59: -8089.189 | AP59: =-64431.288-AO59 -> -56342.099 | AQ59: =-101619.458-AP59-AO59 -> -37188.17 | AR59: =K59-AO59-AP59-AQ59 -> -60513.58 | AS59: -55090.51 | AT59: =-80603.184-AS59 -> -25512.674 | AU59: =21524.035-AT59-AS59 -> 102127.22 | AV59: =L59-AS59-AT59-AU59 -> -6942.452 | AW59: -11094.646 | AX59: =-57583.367-AW59 -> -46488.721 | AY59: =-67368.541-AX59-AW59 -> -9785.174 | AZ59: =M59-AW59-AX59-AY59 -> -5384.133 | BA59: -10152.6 | BB59: =-37337.978-BA59 -> -27185.378 | BC59: =-27438.127-BB59-BA59 -> 9899.851 | BD59: =N59-BA59-BB59-BC59 -> -8436.395 | BE59: -14239.047
B60: Cash interest paid | C60: -38230.206 | D60: -63085.944 | E60: -67686.202 | F60: -70675.87 | G60: -77123.244 | H60: -86893.145 | I60: -94388.228 | J60: -148370.22 | K60: -107881.51 | L60: -112936.64 | M60: -119124.6 | N60: -110625.8 | O60: =SUM(BB60:BE60) -> -105448 | Q60: -14972.798 | R60: =-33666.604-Q60 -> -18693.806 | S60: =-48632.44-R60-Q60 -> -14965.836 | T60: =IFERROR(E60-SUM(Q60:S60),"NA") -> -19053.762 | U60: -15139.847 | V60: =-34362.406-U60 -> -19222.559 | W60: =-50056.413-V60-U60 -> -15694.007 | X60: =+IFERROR(F60-U60-V60-W60,"NA") -> -20619.457 | Y60: -16316.999 | Z60: =-37771.077-Y60 -> -21454.078 | AA60: =-54664.95-Z60-Y60 -> -16893.873 | AB60: =G60-AA60-Z60-Y60 -> -22458.294 | AC60: -20268.822 | AD60: =-46527.502-AC60 -> -26258.68 | AE60: =-61096.92-AD60-AC60 -> -14569.418 | AF60: =H60-AE60-AD60-AC60 -> -25796.225 | AG60: -20571.295 | AH60: =-47728.052-AG60 -> -27156.757 | AI60: =-69118.55-AH60-AG60 -> -21390.498 | AJ60: =I60-AI60-AH60-AG60 -> -25269.678 | AK60: -19155.063 | AL60: =-45658.662-AK60 -> -26503.599 | AM60: =-127077.101-AL60-AK60 -> -81418.439 | AN60: =J60-AM60-AL60-AK60 -> -21293.116 | AO60: -29869.194 | AP60: =-48140.464-AO60 -> -18271.27 | AQ60: =-81118.83-AP60-AO60 -> -32978.366 | AR60: =K60-AO60-AP60-AQ60 -> -26762.682 | AS60: -35002.688 | AT60: =-58010.914-AS60 -> -23008.226 | AU60: =-92166.262-AT60-AS60 -> -34155.348 | AV60: =L60-AS60-AT60-AU60 -> -20770.38 | AW60: -35176.863 | AX60: =-56499.994-AW60 -> -21323.131 | AY60: =-92858.043-AX60-AW60 -> -36358.049 | AZ60: =M60-AW60-AX60-AY60 -> -26266.557 | BA60: -34611.734 | BB60: =-52774.842-BA60 -> -18163.108 | BC60: =-90061.881-BB60-BA60 -> -37287.039 | BD60: =N60-BA60-BB60-BC60 -> -20563.922 | BE60: -29433.935
B61: Cash interest received | C61: 4507.459 | D61: 6880.246 | E61: 3601.845 | F61: 3129.505 | G61: 1129.6 | H61: 1375.222 | I61: 5309.384 | J61: 3451.137 | K61: 26563.887 | L61: 23305.167 | M61: 28910.144 | N61: 12839.054 | O61: =SUM(BB61:BE61) -> 11680.673 | Q61: 1194.878 | R61: =1711.725-Q61 -> 516.847 | S61: =2701.178-R61-Q61 -> 989.453 | T61: =IFERROR(E61-SUM(Q61:S61),"NA") -> 900.667 | U61: 796.67 | V61: =1415.229-U61 -> 618.559 | W61: =2287.848-V61-U61 -> 872.619 | X61: =+IFERROR(F61-U61-V61-W61,"NA") -> 841.657 | Y61: 496.024 | Z61: =718.993-Y61 -> 222.969 | AA61: =904.25-Z61-Y61 -> 185.257 | AB61: =G61-AA61-Z61-Y61 -> 225.35 | AC61: 376.924 | AD61: =538.908-AC61 -> 161.984 | AE61: =687.057-AD61-AC61 -> 148.149 | AF61: =H61-AE61-AD61-AC61 -> 688.165 | AG61: 2661.968 | AH61: =4154.929-AG61 -> 1492.961 | AI61: =4742.58-AH61-AG61 -> 587.651 | AJ61: =I61-AI61-AH61-AG61 -> 566.804 | AK61: 588.55 | AL61: =1104.813-AK61 -> 516.263 | AM61: =2114.162-AL61-AK61 -> 1009.349 | AN61: =J61-AM61-AL61-AK61 -> 1336.975 | AO61: 3384.097 | AP61: =11992.867-AO61 -> 8608.77 | AQ61: =20584.093-AP61-AO61 -> 8591.226 | AR61: =K61-AO61-AP61-AQ61 -> 5979.794 | AS61: 5825.119 | AT61: =10028.282-AS61 -> 4203.163 | AU61: =16831.303-AT61-AS61 -> 6803.021 | AV61: =L61-AS61-AT61-AU61 -> 6473.864 | AW61: 11361.421 | AX61: =19366.355-AW61 -> 8004.934 | AY61: =24999.502-AX61-AW61 -> 5633.147 | AZ61: =M61-AW61-AX61-AY61 -> 3910.642 | BA61: 3368.683 | BB61: =6762.896-BA61 -> 3394.213 | BC61: =10202.011-BB61-BA61 -> 3439.115 | BD61: =N61-BA61-BB61-BC61 -> 2637.043 | BE61: 2210.302
B62: Net cash from operations | C62: =SUM(C57:C61) -> 1168027 | D62: =SUM(D57:D61) -> 964419.9 | E62: =SUM(E57:E61) -> 1039936.5 | F62: =SUM(F57:F61) -> 1272264.8 | G62: =SUM(G57:G61) -> 1208500.8 | H62: =SUM(H57:H61) -> 1662081.8 | I62: =SUM(I57:I61) -> 1576934.6 | J62: =SUM(J57:J61) -> 1571981.3 | ... O62: =SUM(O57:O61) -> 742510.49 | Q62: =SUM(Q57:Q61) -> 305862.29 | R62: =SUM(R57:R61) -> 239365.12 | S62: =SUM(S57:S61) -> 208060.66 | T62: =SUM(T57:T61) -> 286648.45 | U62: =SUM(U57:U61) -> 290464.8 | V62: =SUM(V57:V61) -> 251643.36 | W62: =SUM(W57:W61) -> 374812.43 | X62: =SUM(X57:X61) -> 355344.26 | ... BE62: =SUM(BE57:BE61) -> 138014.42
B63: Net Capex | C63: =-561516.005+10135.787 -> -551380.22 | D63: =-523595.343+408.473 -> -523186.87 | E63: =-458030.431+3840.988 -> -454189.44 | F63: =-501504.528+4375.572 -> -497128.96 | G63: =421.583-508295.673 -> -507874.09 | H63: =490062.013-477247.941 -> 12814.072 | I63: =-402506.254+110796.307 -> -291709.95 | J63: =-305004.114+44563.586 -> -260440.53 | K63: =-596641.654+609501.777 -> 12860.123 | L63: =(540626.516)+409115.556 -> 949742.07 | M63: =-539724.12 -> -539724.12 | N63: -533826.28 | O63: =SUM(BB63:BE63) -> -493971.73 | Q63: =544.062-106764.315 -> -106220.25 | R63: =587.544-215435.925-Q63 -> -108628.13 | S63: =1520.17-327792.323-R63-Q63 -> -111423.77 | T63: =IFERROR(E63-SUM(Q63:S63),"NA") -> -127917.29 | U63: =344.28-117523.064 -> -117178.78 | V63: =1242.4-228669.278-U63 -> -110248.09 | W63: =2774.595-365496.967-V63-U63 -> -135295.49 | X63: =+IFERROR(F63-U63-V63-W63,"NA") -> -134406.58 | Y63: =265.702-139576.136 -> -139310.43 | Z63: =332.502-263335.746-Y63 -> -123692.81 | AA63: =356.082-386535.981-Z63-Y63 -> -123176.66 | AB63: =G63-AA63-Z63-Y63 -> -121694.19 | AC63: =46.334-149618.935 -> -149572.6 | AD63: =-277771.407+92.381-AC63 -> -128106.43 | AE63: =-367026.862+143.473-AD63-AC63 -> -89204.363 | AF63: =H63-AE63-AD63-AC63 -> 379697.46 | AG63: =33077.545-97852.499 -> -64774.954 | AH63: =-206875.648+68622.061-AG63 -> -73478.633 | AI63: =-338091.593+85067.36-AH63-AG63 -> -114770.65 | AJ63: =I63-AI63-AH63-AG63 -> -38685.714 | AK63: =10936.313-122998.185 -> -112061.87 | AL63: =-240514.749+27334.936-AK63 -> -101117.94 | AM63: =-346927.295+44940.185-AL63-AK63 -> -88807.297 | AN63: =J63-AM63-AL63-AK63 -> 41546.582 | AO63: -151226.7 | AP63: =-263692.831+537150.1-AO63 -> 424683.97 | AQ63: =-422073.027+610073.315-AP63-AO63 -> -85456.981 | AR63: =K63-AO63-AP63-AQ63 -> -175140.16 | AS63: =-170174.193+91.878 -> -170082.32 | AT63: =-305828.498+210.735-AS63 -> -135535.45 | AU63: =-422303.4+0-AT63-AS63 -> -116685.64 | AV63: =L63-AS63-AT63-AU63 -> 1372045.5 | AW63: =-120567.728+0 -> -120567.73 | AX63: =-286698.604-AW63 -> -166130.88 | AY63: =-424311.497-AX63-AW63 -> -137612.89 | AZ63: =M63-AW63-AX63-AY63 -> -115412.62 | BA63: -148489.65 | BB63: =-263030.347-BA63 -> -114540.69 | BC63: =-371139.475+198.693-BB63-BA63 -> -107910.43 | BD63: =N63-BA63-BB63-BC63 -> -162885.5 | BE63: -108635.1
B64: Purchase and development of intangible assets | C64: -242.942 | D64: -7500.484 | E64: -193709.25 | F64: -739.014 | G64: -592.006 | H64: -1258.342 | I64: -864.886 | J64: -100844.64 | K64: 0 | L64: 0 | M64: -23.457 | N64: -1491.185 | O64: =SUM(BB64:BE64) -> -1476.006 | Q64: -396.015 | R64: =-281.749-Q64 -> 114.266 | S64: =-193839.722-R64-Q64 -> -193557.97 | T64: =IFERROR(E64-SUM(Q64:S64),"NA") -> 130.475 | U64: -84.214 | V64: =-127.99-U64 -> -43.776 | W64: =-338.645-V64-U64 -> -210.655 | X64: =+IFERROR(F64-U64-V64-W64,"NA") -> -400.369 | Y64: -193.199 | Z64: =-327.225-Y64 -> -134.026 | AA64: =-442.533-Z64-Y64 -> -115.308 | AB64: =G64-AA64-Z64-Y64 -> -149.473 | AC64: -338.785 | AD64: =-640.335-AC64 -> -301.55 | AE64: =-1120.595-AD64-AC64 -> -480.26 | AF64: =H64-AE64-AD64-AC64 -> -137.747 | AG64: -141.961 | AH64: =-162.818-AG64 -> -20.857 | AI64: =-241.955-AH64-AG64 -> -79.137 | AJ64: =I64-AI64-AH64-AG64 -> -622.931 | AK64: -101264.14 | AL64: =-101338.466-AK64 -> -74.324 | AM64: =-100561.709+7652.715-AL64-AK64 -> 8429.472 | AN64: =J64-AM64-AL64-AK64 -> -7935.649 | AO64: 0 | AP64: =-132.984-AO64 -> -132.984 | AQ64: =0-AP64-AO64 -> 132.984 | AR64: =K64-AO64-AP64-AQ64 -> 0 | AS64: -23.273 | AT64: =-23.875-AS64 -> -0.602 | AU64: =-99.876-AT64-AS64 -> -76.001 | AV64: =L64-AS64-AT64-AU64 -> 99.876 | AW64: -3.07 | AX64: =-3.211-AW64 -> -0.141 | AY64: =-22.961-AX64-AW64 -> -19.75 | AZ64: =M64-AW64-AX64-AY64 -> -0.496 | BA64: -15.179 | BB64: =-0.918-BA64 -> 14.261 | BC64: =-28.691-BB64-BA64 -> -27.773 | BD64: =N64-BA64-BB64-BC64 -> -1462.494 | BE64: 0
B65: Disposals/ Acquistion, of subsidiaries | C65: 0 | D65: 0 | E65: 0 | F65: 0 | G65: -1873.506 | H65: 0 | I65: 0 | J65: 0 | K65: 0 | L65: 0 | M65: 0 | N65: 0 | O65: =SUM(BB65:BE65) -> 0 | Q65: 0 | R65: =-Q65 -> 0 | S65: =-R65-Q65 -> 0 | T65: =IFERROR(E65-SUM(Q65:S65),"NA") -> 0 | U65: 0 | V65: =-U65 -> 0 | W65: =-V65-U65 -> 0 | X65: =+IFERROR(F65-U65-V65-W65,"NA") -> 0 | Y65: 0 | Z65: =-1873.506-Y65 -> -1873.506 | AA65: =-1873.506-Z65-Y65 -> 0 | AB65: =G65-AA65-Z65-Y65 -> 0 | AC65: 0 | AD65: =-AC65 -> 0 | AE65: =-AD65-AC65 -> 0 | AF65: =H65-AE65-AD65-AC65 -> 0 | AG65: 0 | AH65: =0-AG65 -> 0 | AI65: =-AH65-AG65 -> 0 | AJ65: =I65-AI65-AH65-AG65 -> 0 | AK65: 0 | AL65: =0-AK65 -> 0 | AM65: =-AL65-AK65 -> 0 | AN65: =J65-AM65-AL65-AK65 -> 0 | AO65: 0 | AP65: =0-AO65 -> 0 | AQ65: =-AP65-AO65 -> 0 | AR65: =K65-AO65-AP65-AQ65 -> 0 | AS65: 0 | AT65: =0-AS65 -> 0 | AU65: =-AT65-AS65 -> 0 | AV65: =L65-AS65-AT65-AU65 -> 0 | AW65: 0 | AX65: =0-AW65 -> 0 | AY65: =-AX65-AW65 -> 0 | AZ65: =M65-AW65-AX65-AY65 -> 0 | BA65: 0 | BB65: =0-BA65 -> 0 | BC65: =-BB65-BA65 -> 0 | BD65: =N65-BA65-BB65-BC65 -> 0 | BE65: 0
B66: Free cash flow | C66: =SUM(C62:C65) -> 616403.83 | D66: =SUM(D62:D65) -> 433732.54 | E66: =SUM(E62:E65) -> 392037.83 | F66: =SUM(F62:F65) -> 774396.87 | G66: =SUM(G62:G65) -> 698161.2 | H66: =SUM(H62:H65) -> 1673637.5 | I66: =SUM(I62:I65) -> 1284359.8 | J66: =SUM(J62:J65) -> 1210696.1 | ... O66: =SUM(O62:O65) -> 247062.76 | Q66: =SUM(Q62:Q65) -> 199246.02 | R66: =SUM(R62:R65) -> 130851.25 | S66: =SUM(S62:S65) -> -96921.087 | T66: =SUM(T62:T65) -> 158861.63 | U66: =SUM(U62:U65) -> 173201.8 | V66: =SUM(V62:V65) -> 141351.49 | W66: =SUM(W62:W65) -> 239306.28 | X66: =SUM(X62:X65) -> 220537.3 | ... BE66: =SUM(BE62:BE65) -> 29379.314
B67: Other investing activities | C67: =863.574+4143.045 -> 5006.619 | D67: 2018.426 | E67: 1701.201 | F67: 1996.042 | G67: 0 | H67: =-153141.449 -> -153141.45 | I67: -233660 | J67: =139525.125+7652.715 -> 147177.84 | K67: 121892.01 | L67: 767.365 | M67: -79714.43 | N67: 178081.53 | O67: =SUM(BB67:BE67) -> 88520.66 | Q67: 1701.201 | R67: =1701.201-Q67 -> 0 | S67: =1701.201-39302.242-R67-Q67 -> -39302.242 | T67: =IFERROR(E67-SUM(Q67:S67),"NA") -> 39302.242 | U67: 1996.042 | V67: =1996.042-U67 -> 0 | W67: =1996.042-V67-U67 -> 0 | X67: =+IFERROR(F67-U67-V67-W67,"NA") -> 0 | Y67: 0 | Z67: =-Y67 -> 0 | AA67: =-Z67-Y67 -> 0 | AB67: =G67-AA67-Z67-Y67 -> 0 | AC67: 0 | AD67: =-AC67 -> 0 | AE67: =-AD67-AC67 -> 0 | AF67: =H67-AE67-AD67-AC67 -> -153141.45 | AG67: -17486.673 | AH67: =82201.517-AG67 -> 99688.19 | AI67: =-90471.479-AH67-AG67 -> -172673 | AJ67: =I67-AI67-AH67-AG67 -> -143188.52 | AK67: -30033.462 | AL67: =-34259.594+7652.715-AK67 -> 3426.583 | AM67: =-26448.415-AL67-AK67 -> 158.464 | AN67: =J67-AM67-AL67-AK67 -> 173626.25 | AO67: 27515.073 | AP67: =19246.829-AO67 -> -8268.244 | AQ67: =89701.948-AP67-AO67 -> 70455.119 | AR67: =K67-AO67-AP67-AQ67 -> 32190.065 | AS67: 2050.145 | AT67: =23630.777-AS67 -> 21580.632 | AU67: =-2190.232-AT67-AS67 -> -25821.009 | AV67: =L67-AS67-AT67-AU67 -> 2957.597 | AW67: -180029.97 | AX67: =-207253.221-AW67 -> -27223.251 | AY67: =-52444.337-AX67-AW67 -> 154808.88 | AZ67: =M67-AW67-AX67-AY67 -> -27270.093 | BA67: 105338.26 | BB67: =193858.915-BA67 -> 88520.66 | BC67: =193858.915-BB67-BA67 -> 0 | BD67: =N67-BA67-BB67-BC67 -> -15777.384 | BE67: 15777.384
B68: Equity Issuance/Buyback | C68: 0 | D68: 0 | E68: 353703.38 | F68: 0 | G68: 0 | H68: 0 | I68: 0 | J68: 0 | K68: 0 | L68: 0 | M68: 0 | N68: 0 | O68: =SUM(BB68:BE68) -> 0 | Q68: 0 | R68: =3142.266-Q68 -> 3142.266 | S68: =353703.381-R68-Q68 -> 350561.11 | T68: =IFERROR(E68-SUM(Q68:S68),"NA") -> 0 | U68: 0 | V68: =-U68 -> 0 | W68: =-V68-U68 -> 0 | X68: =+IFERROR(F68-U68-V68-W68,"NA") -> 0 | Y68: 0 | Z68: =-Y68 -> 0 | AA68: =-Z68-Y68 -> 0 | AB68: =G68-AA68-Z68-Y68 -> 0 | AC68: 0 | AD68: =-AC68 -> 0 | AE68: =-AD68-AC68 -> 0 | AF68: =H68-AE68-AD68-AC68 -> 0 | AG68: 0 | AH68: =0-AG68 -> 0 | AI68: =-AH68-AG68 -> 0 | AJ68: =I68-AI68-AH68-AG68 -> 0 | AK68: 0 | AL68: =0-AK68 -> 0 | AM68: =-AL68-AK68 -> 0 | AN68: =J68-AM68-AL68-AK68 -> 0 | AO68: 0 | AP68: =0-AO68 -> 0 | AQ68: =0-AP68-AO68 -> 0 | AR68: =K68-AO68-AP68-AQ68 -> 0 | AS68: 0 | AT68: =0-AS68 -> 0 | AU68: =0-AT68-AS68 -> 0 | AV68: =L68-AS68-AT68-AU68 -> 0 | AW68: 0 | AX68: =0-AW68 -> 0 | AY68: =0-AX68-AW68 -> 0 | AZ68: =M68-AW68-AX68-AY68 -> 0 | BA68: 0 | BB68: =0-BA68 -> 0 | BC68: =0-BB68-BA68 -> 0 | BD68: =N68-BA68-BB68-BC68 -> 0 | BE68: 0
B69: Dividends Paid | C69: =-55101.61+1.367 -> -55100.243 | D69: =-9091.059+0 -> -9091.059 | E69: =-37.482+2.9 -> -34.582 | F69: =-10309.263+2.016 -> -10307.247 | G69: =-13304.915+2.064 -> -13302.851 | H69: =-21.514+2.125 -> -19.389 | I69: =-46476.842+2.502 -> -46474.34 | J69: =-253366.851+0 -> -253366.85 | K69: -374267.09 | L69: -28442.741 | M69: -86224.531 | N69: -73673.692 | O69: =SUM(BB69:BE69) -> -73669.89 | Q69: -0.63 | R69: =-24.657-Q69 -> -24.027 | S69: =-29.903-R69-Q69 -> -5.246 | T69: =IFERROR(E69-SUM(Q69:S69),"NA") -> -4.679 | U69: =-13.071 -> -13.071 | V69: =-10301.919-U69 -> -10288.848 | W69: =-10295.847-V69-U69 -> 6.072 | X69: =+IFERROR(F69-U69-V69-W69,"NA") -> -11.4 | Y69: =-0.562 -> -0.562 | Z69: =-13302.585-Y69 -> -13302.023 | AA69: =-13292.451-Z69-Y69 -> 10.134 | AB69: =G69-AA69-Z69-Y69 -> -10.4 | AC69: -44.495 | AD69: =-16.611-AC69 -> 27.884 | AE69: =-16.859-AD69-AC69 -> -0.248 | AF69: =H69-AE69-AD69-AC69 -> -2.53 | AG69: 0 | AH69: =-46515.3-AG69 -> -46515.3 | AI69: =-46471.826-AH69-AG69 -> 43.474 | AJ69: =I69-AI69-AH69-AG69 -> -2.514 | AK69: -2.943 | AL69: =-41987.645-AK69 -> -41984.702 | AM69: =-41950.512-AL69-AK69 -> 37.133 | AN69: =J69-AM69-AL69-AK69 -> -211416.34 | AO69: 0 | AP69: =-344167.415-AO69 -> -344167.41 | AQ69: =-343968.166-AP69-AO69 -> 199.249 | AR69: =K69-AO69-AP69-AQ69 -> -30298.929 | AS69: -23.142 | AT69: =-28416.496-AS69 -> -28393.354 | AU69: =-28415.717-AT69-AS69 -> 0.779 | AV69: =L69-AS69-AT69-AU69 -> -27.024 | AW69: -0.207 | AX69: =-71118.173-AW69 -> -71117.966 | AY69: =-71076.356-AX69-AW69 -> 41.817 | AZ69: =M69-AW69-AX69-AY69 -> -15148.175 | BA69: -3.802 | BB69: =-38964.875-BA69 -> -38961.073 | BC69: =-38941.723-BB69-BA69 -> 23.152 | BD69: =N69-BA69-BB69-BC69 -> -34731.969 | BE69: 0
B70: Change in debt | C70: =621015.32+279667.148-421515.178-2837.334 -> 476329.96 | D70: =23061.254-23061.254-1136.67 -> -1136.67 | E70: =163809.658-163809.658-464.426 -> -464.426 | F70: =298201.75+36274.474-238334.207-1303.725 -> 94838.292 | G70: =55076.8+239729.272-240816.952-1096.743 -> 52892.377 | H70: =224433.122+408410.738-571382.276-91748.232 -> -30286.648 | I70: =2403.9+92032.202-155218.823-97187.05 -> -157969.77 | J70: =627295.067+110551.916-718712.876-96740.586 -> -77606.479 | K70: =0+244729.545-341900.102-113469.413 -> -210639.97 | L70: =0+196695.253-338773.16-142777.05 -> -284854.96 | M70: =59520.233-317230.813-147507.683 -> -405218.26 | N70: =373624.749-723759.533-155490.847 -> -505625.63 | O70: =SUM(BB70:BE70) -> -508689.54 | Q70: =808.578-808.578-306.948 -> -306.948 | R70: =7889.786-7889.786-428.152-Q70 -> -121.204 | S70: =153836.13-153836.13-455.255-R70-Q70 -> -27.103 | T70: =IFERROR(E70-SUM(Q70:S70),"NA") -> -9.171 | U70: =10459.458-10459.458-313.509 -> -313.509 | V70: =298201.75+19423.878-218268.943-636.256-U70 -> 99033.938 | W70: =298201.75+22026.387-220865.162-966.086-V70-U70 -> -323.54 | X70: =+IFERROR(F70-U70-V70-W70,"NA") -> -3558.597 | Y70: -330.225 | Z70: =66404.06-66339.677-635.624-Y70 -> -241.016 | AA70: =127863.848-127785.743-927.478-Z70-Y70 -> -278.132 | AB70: =G70-AA70-Z70-Y70 -> 53741.75 | AC70: =102992.499-102987.793-12855.728 -> -12851.022 | AD70: =243220.805-207466.206-34716.778-AC70 -> 13888.843 | AE70: =359559.731-346651.937-51310.922-AD70-AC70 -> -39440.949 | AF70: =H70-AE70-AD70-AC70 -> 8116.48 | AG70: =47825.786-108127.098-17812.105 -> -78113.417 | AH70: =62387.364-118259.135-44457.6-AG70 -> -22215.954 | AI70: =2403.9+74020.784-133775.301-65581.699-AH70-AG70 -> -22602.945 | AJ70: =I70-AI70-AH70-AG70 -> -35037.455 | AK70: =35676.369-36561.474-23731.079 -> -24616.184 | AL70: =38984.774-40806.431-52282.123-AK70 -> -29487.596 | AM70: =627408+63673.765-67013.084-75716.443-AL70-AK70 -> 602456.02 | AN70: =J70-AM70-AL70-AK70 -> -625958.72 | AO70: =55713.961-27599.635-25694.716 -> 2419.61 | AP70: =113870.526-64200.602-49776.012-AO70 -> -2525.698 | AQ70: =167156.444-93776.518-80981.675-AP70-AO70 -> -7495.661 | AR70: =K70-AO70-AP70-AQ70 -> -203038.22 | AS70: =48235.014-54857.149-34636.53 -> -41258.665 | AT70: =50472.605-55297.487-60249.364-AS70 -> -23815.581 | AU70: =88157.94-88711.598-104000.523-AT70-AS70 -> -39479.935 | AV70: =L70-AS70-AT70-AU70 -> -180300.78 | AW70: =19852.256-50787.239-29136.64 -> -60071.623 | AX70: =23154.86-95269.191-73472.952-AW70 -> -85515.66 | AY70: =31783.861-111923.282-111577.157-AX70-AW70 -> -46129.295 | AZ70: =M70-AW70-AX70-AY70 -> -213501.68 | BA70: =7115.508-7225.411-34507.251 -> -34617.154 | BB70: =77947.146+38654.295-84163.77-75132.485-BA70 -> -8077.66 | BC70: =253494.146+108121.633-696678.891-113221.416-BB70-BA70 -> -405589.71 | BD70: =N70-BA70-BB70-BC70 -> -57341.103 | BE70: =944.936-944.936-37681.059 -> -37681.059
B71: Other financing activities | C71: 24042.985 | D71: 39073.893 | E71: -16493.821 | F71: -24769.175 | G71: 429.609 | H71: 20287.902 | I71: 24813.957 | J71: 19468.497 | K71: 22521.106 | L71: -2886.179 | M71: 21026.527 | N71: 278738.17 | O71: =SUM(BB71:BE71) -> 225152.9 | Q71: 8594.262 | R71: =129.666-Q71 -> -8464.596 | S71: =-9972.714-R71-Q71 -> -10102.38 | T71: =IFERROR(E71-SUM(Q71:S71),"NA") -> -6521.107 | U71: -4634.466 | V71: =-9623.102-U71 -> -4988.636 | W71: =-20549.38-V71-U71 -> -10926.278 | X71: =+IFERROR(F71-U71-V71-W71,"NA") -> -4219.795 | Y71: -6124.373 | Z71: =-7790.535-Y71 -> -1666.162 | AA71: =-4382.997-Z71-Y71 -> 3407.538 | AB71: =G71-AA71-Z71-Y71 -> 4812.606 | AC71: -706.585 | AD71: =1100.75-AC71 -> 1807.335 | AE71: =13366.543-AD71-AC71 -> 12265.793 | AF71: =H71-AE71-AD71-AC71 -> 6921.359 | AG71: 3496.885 | AH71: =19607.222-AG71 -> 16110.337 | AI71: =22976.503-AH71-AG71 -> 3369.281 | AJ71: =I71-AI71-AH71-AG71 -> 1837.454 | AK71: -6348.982 | AL71: =4458.573-AK71 -> 10807.555 | AM71: =581.469-AL71-AK71 -> -3877.104 | AN71: =J71-AM71-AL71-AK71 -> 18887.028 | AO71: -8602.597 | AP71: =-1962.366-AO71 -> 6640.231 | AQ71: =201.734-AP71-AO71 -> 2164.1 | AR71: =K71-AO71-AP71-AQ71 -> 22319.372 | AS71: -4312.043 | AT71: =-9892.523-AS71 -> -5580.48 | AU71: =-12585.925-AT71-AS71 -> -2693.402 | AV71: =L71-AS71-AT71-AU71 -> 9699.746 | AW71: 5769.735 | AX71: =2164.174-AW71 -> -3605.561 | AY71: =12674.677-AX71-AW71 -> 10510.503 | AZ71: =M71-AW71-AX71-AY71 -> 8351.85 | BA71: 7323.065 | BB71: =5293.919-BA71 -> -2029.146 | BC71: =283030.467 -BB71-BA71 -> 277736.55 | BD71: =N71-BA71-BB71-BC71 -> -4292.293 | BE71: -46262.204
B72: Cash flow after financing activities | C72: =SUM(C66:C71) -> 1066683.1 | D72: =SUM(D66:D71) -> 464597.13 | E72: =SUM(E66:E71) -> 730449.58 | F72: =SUM(F66:F71) -> 836154.78 | G72: =SUM(G66:G71) -> 738180.34 | H72: =SUM(H66:H71) -> 1510477.9 | I72: =SUM(I66:I71) -> 871069.65 | J72: =SUM(J66:J71) -> 1046369.1 | ... O72: =SUM(O66:O71) -> -21623.106 | Q72: =SUM(Q66:Q71) -> 209233.91 | R72: =SUM(R66:R71) -> 125383.69 | S72: =SUM(S66:S71) -> 204203.06 | T72: =SUM(T66:T71) -> 191628.92 | U72: =SUM(U66:U71) -> 170236.79 | V72: =SUM(V66:V71) -> 225107.94 | W72: =SUM(W66:W71) -> 228062.54 | X72: =SUM(X66:X71) -> 212747.51 | ... BE72: =SUM(BE66:BE71) -> -38786.565
B73: FX | C73: 22593.597 | D73: 5962.804 | E73: -2323.404 | F73: 525.962 | G73: 628.915 | H73: -3522.877 | I73: -10542.67 | J73: 4813.65 | K73: -3809.314 | L73: 625.037 | M73: 2318.321 | N73: 823.821 | O73: =SUM(BB73:BE73) -> 719.523 | Q73: 130.386 | R73: =-141.334-Q73 -> -271.72 | S73: =-447.752-R73-Q73 -> -306.418 | T73: =IFERROR(E73-SUM(Q73:S73),"NA") -> -1875.652 | U73: 188.274 | V73: =297.224-U73 -> 108.95 | W73: =329.328-V73-U73 -> 32.104 | X73: =+IFERROR(F73-U73-V73-W73,"NA") -> 196.634 | Y73: -0.671 | Z73: =100.759-Y73 -> 101.43 | AA73: =4.264-Z73-Y73 -> -96.495 | AB73: =G73-AA73-Z73-Y73 -> 624.651 | AC73: -2274.353 | AD73: =-2196.168-AC73 -> 78.185 | AE73: =-2156.263-AD73-AC73 -> 39.905 | AF73: =H73-AE73-AD73-AC73 -> -1366.614 | AG73: 1105.107 | AH73: =-1520.645-AG73 -> -2625.752 | AI73: =-4429.01-AH73-AG73 -> -2908.365 | AJ73: =I73-AI73-AH73-AG73 -> -6113.66 | AK73: 1096.439 | AL73: =1557.048-AK73 -> 460.609 | AM73: =4795.813-AL73-AK73 -> 3238.765 | AN73: =J73-AM73-AL73-AK73 -> 17.837 | AO73: -165.302 | AP73: =664.789-AO73 -> 830.091 | AQ73: =46.83-AP73-AO73 -> -617.959 | AR73: =K73-AO73-AP73-AQ73 -> -3856.144 | AS73: -272.808 | AT73: =-296.421-AS73 -> -23.613 | AU73: =924.002-AT73-AS73 -> 1220.423 | AV73: =L73-AS73-AT73-AU73 -> -298.965 | AW73: 1592.267 | AX73: =-749.64-AW73 -> -2341.907 | AY73: =-1353.239-AX73-AW73 -> -603.599 | AZ73: =M73-AW73-AX73-AY73 -> 3671.56 | BA73: 111.285 | BB73: =108.019-BA73 -> -3.266 | BC73: =1039.738 -BB73-BA73 -> 931.719 | BD73: =N73-BA73-BB73-BC73 -> -215.917 | BE73: 6.987
B74: Balancing figure | C74: =337075.377-C73-C72 -> -752201.37 | D74: =-248389.708-D73-D72 -> -718949.64 | E74: =-23254.238-E72-E73 -> -751380.41 | F74: =34205.673-F72-F73 -> -802475.07 | G74: =-73527.13-G72-G73 -> -812336.38 | H74: =378186.387-H72-H73 -> -1128768.7 | I74: =-234387.853-I72-I73 -> -1094914.8 | J74: =-98690.119-J72-J73 -> -1149872.9 | K74: =81746.942-K72-K73 -> -1652355.7 | L74: =343694.954-L72-L73 -> -1074258.9 | M74: =-453261.836-M72-M73 -> 66550.346 | N74: =152907.498-N72-N73 -> 82068.939 | O74: =SUM(BB74:BE74) -> 55490.464 | Q74: =1161.749-Q72-Q73 -> -208202.55 | R74: =-62715.136-Q74-Q73-Q72-R72-R73 -> -188988.86 | S74: =(-49864.248-R74-R73-R72-Q74-Q73-Q72-S72-S73) -> -191045.75 | T74: =IFERROR(E74-SUM(Q74:S74),"NA") -> -163143.26 | U74: =-32689.437-U72-U73 -> -203114.51 | V74: =-3100.425-U74-U73-U72-V72-V73 -> -195627.88 | W74: =26219.044-V74-V73-V72-U74-U73-U72-W72-W73 -> -198775.17 | X74: =+IFERROR(F74-U74-V74-W74,"NA") -> -204957.52 | Y74: =-96014.512-Y72-Y73 -> -195550.66 | Z74: =-113331.101-Y74-Y73-Y72-Z72-Z73 -> -195444.03 | AA74: =-136534.611-Z74-Z73-Z72-Y74-Y73-Y72-AA72-AA73 -> -212172.32 | AB74: =G74-AA74-Z74-Y74 -> -209169.37 | AC74: =-36151.03-AC72-AC73 -> -231084.56 | AD74: =-44676.74-AC74-AC73-AC72-AD72-AD73 -> -229468.05 | AE74: =-36290.907-AD74-AD73-AD72-AC74-AC73-AC72-AE72-AE73 -> -239196.8 | AF74: =H74-AE74-AD74-AC74 -> -429019.26 | AG74: =-148621.088-AG72-AG73 -> -347793.6 | AH74: =-105317.373-AG74-AG73-AG72-AH72-AH73 -> -240759.73 | AI74: =-140138.496-AH74-AH73-AH72-AG74-AG73-AG72-AI72-AI73 -> -251443.37 | AJ74: =I74-AI74-AH74-AG74 -> -254918.14 | AK74: =-152987.171-AK72-AK73 -> -279215.55 | AL74: =-97360.491-AK74-AK73-AK72-AL72-AL73 -> -315366.72 | AM74: =-91630.697-AL74-AL73-AL72-AK74-AK73-AK72-AM72-AM73 -> -885784.28 | AN74: =J74-AM74-AL74-AK74 -> 330493.64 | AO74: =2715.97-AO72-AO73 -> -298065.51 | AP74: =102553.762-AO74-AO73-AO72-AP72-AP73 -> -779424.83 | AQ74: =164947.396-AP74-AP73-AP72-AO74-AO73-AO72-AQ72-AQ73 -> -320347.75 | AR74: =K74-AO74-AP74-AQ74 -> -254517.58 | AS74: =-85209.171-AS72-AS73 -> 90280.009 | AT74: =-100510.86-AS74-AS73-AS72-AT72-AT73 -> -1782.506 | AU74: =19223.146 -AT74-AT73-AT72-AS74-AS73-AS72-AU72-AU73 -> 19581.896 | AV74: =L74-AS74-AT74-AU74 -> -1182338.3 | AW74: =-247933.785-AW72-AW73 -> 16414.899 | AX74: =-442648.77-AW74-AW73-AW72-AX72-AX73 -> 16641.295 | AY74: =-310342.051-AX74-AX73-AX72-AW74-AW73-AW72-AY72-AY73 -> 34769.128 | AZ74: =M74-AW74-AX74-AY74 -> -1274.976 | BA74: =100249.814-BA72-BA73 -> 47287.25 | BB74: =192760.061-BA74-BA73-BA72-BB72-BB73 -> -1387.164 | BC74: =158934.723 -BB74-BB73-BB72-BA74-BA73-BA72-BC72-BC73 -> 14759.238 | BD74: =N74-BA74-BB74-BC74 -> 21409.615 | BE74: =-18070.803-BE72-BE73 -> 20708.775
B75: Net change in cash | C75: =SUM(C72:C74) -> 337075.38 | D75: =SUM(D72:D74) -> -248389.71 | E75: =SUM(E72:E74) -> -23254.238 | F75: =SUM(F72:F74) -> 34205.673 | G75: =SUM(G72:G74) -> -73527.13 | H75: =SUM(H72:H74) -> 378186.39 | I75: =SUM(I72:I74) -> -234387.85 | J75: =SUM(J72:J74) -> -98690.119 | ... O75: =SUM(O72:O74) -> 34586.881 | Q75: =SUM(Q72:Q74) -> 1161.749 | R75: =SUM(R72:R74) -> -63876.885 | S75: =SUM(S72:S74) -> 12850.888 | T75: =SUM(T72:T74) -> 26610.01 | U75: =SUM(U72:U74) -> -32689.437 | V75: =SUM(V72:V74) -> 29589.012 | W75: =SUM(W72:W74) -> 29319.469 | X75: =SUM(X72:X74) -> 7986.629 | ... BE75: =SUM(BE72:BE74) -> -18070.803
B76: Cash and cash equivalents | C76: =19250.402+C75+C73 -> 378919.38 | D76: =+C76+D75+D73 -> 136492.47 | E76: =+D76+E75+E73 -> 110914.83 | F76: =+E76+F75+F73 -> 145646.47 | G76: =+F76+G75+G73 -> 72748.25 | H76: =+G76+H75+H73 -> 447411.76 | I76: =+H76+I75+I73 -> 202481.24 | J76: =+I76+J75+J73 -> 108604.77 | K76: =+J76+K75+K73 -> 186542.4 | ... N76: =+M76+N75+N73 -> 233650.19 | O76: =O75+BA76+O73 -> 215586.38 | Q76: =D76+Q75+Q73 -> 137784.61 | R76: =Q76+R75+R73 -> 73636.002 | S76: =R76+S75+S73 -> 86180.472 | T76: =S76+T75+T73 -> 110914.83 | U76: =E76+U75+U73 -> 78413.667 | V76: =+U76+V75+V73 -> 108111.63 | W76: =+V76+W75+W73 -> 137463.2 | X76: =+W76+X75+X73 -> 145646.47 | Y76: =F76+Y75+Y73 -> 49631.282 | Z76: =+Y76+Z75+Z73 -> 32416.123 | AA76: =+Z76+AA75+AA73 -> 9116.118 | AB76: =+AA76+AB75+AB73 -> 72748.25 | AC76: =AB76+AC75+AC73 -> 34322.867 | AD76: =AC76+AD75+AD73 -> 25875.342 | AE76: =AD76+AE75+AE73 -> 34301.08 | AF76: =AE76+AF75+AF73 -> 447411.76 | AG76: =AF76+AG75+AG73 -> 299895.78 | AH76: =AG76+AH75+AH73 -> 340573.74 | AI76: =AH76+AI75+AI73 -> 302844.25 | AJ76: =AI76+AJ75+AJ73 -> 202481.24 | ... BE76: =BD76+BE75+BE73 -> 215586.38
B78: check | C78: =C76-C118 -> 0 | D78: =D76-D118 -> 0 | E78: =E76-E118 -> 0 | F78: =F76-F118 -> 0 | G78: =G76-G118 -> 0 | H78: =H76-H118 -> 0 | I78: =I76-I118 -> 0 | J78: =J76-J118 -> 0 | ... O78: =O76-O118 -> 4.9476512e-10 | Q78: =Q76-Q118 -> 0 | R78: =R76-R118 -> 0 | S78: =S76-S118 -> 0 | T78: =T76-T118 -> 1.7462298e-10 | U78: =U76-U118 -> 0 | V78: =V76-V118 -> 0 | W78: =W76-W118 -> 0 | X78: =X76-X118 -> 0 | ... BE78: =BE76-BE118 -> 4.9476512e-10
B80: LTM | C80: =+C56 -> 41974 | D80: =+D56 -> 42340 | E80: =+E56 -> 42707 | F80: =+F56 -> 43073 | G80: =G3 -> 43438 | H80: =H3 -> 43803 | I80: =I3 -> 44169 | J80: =J3 -> 44534 | K80: =K3 -> 44926 | L80: =L3 -> 45291 | M80: =M3 -> 45657 | N80: =N3 -> 46022 | O80: =+O56 -> 46112 | Q80: =+Q56 -> 42437 | R80: =+R56 -> 42527 | S80: =+S56 -> 42622 | T80: =+T56 -> 42714 | U80: =+U56 -> 42801 | V80: =+V56 -> 42892 | W80: =+W56 -> 42987 | X80: =+X56 -> 43079 | Y80: =+Y56 -> 43190 | Z80: =Z56 -> 43281 | AA80: =AA56 -> 43373 | AB80: =AB3 -> 43465 | AC80: =+AC56 -> 43555 | AD80: =+AD56 -> 43646 | AE80: =+AE56 -> 43738 | AF80: =+AF56 -> 43830 | AG80: =+AG56 -> 43921 | AH80: =+AH56 -> 44012 | AI80: =+AI56 -> 44104 | AJ80: =+AJ56 -> 44196 | ... BE80: =+BE56 -> 46112
B81: =+B7 -> Revenues | C81: =+C7 -> 1657770.4 | D81: =+D7 -> 1784612.7 | E81: =+E7 -> 1867697.1 | F81: =+F7 -> 1943071.2 | G81: =+G7 -> 1913174.3 | H81: =+H7 -> 1978792 | I81: =+I7 -> 2092644.2 | ... O81: =+O7 -> 3002583.4 | T81: =+T7+S7+R7+Q7 -> 1867697.1 | U81: =+U7+T7+S7+R7 -> 1881848.8 | V81: =+V7+U7+T7+S7 -> 1903743.4 | W81: =+W7+V7+U7+T7 -> 1915748.8 | X81: =+X7+W7+V7+U7 -> 1943071.2 | Y81: =+Y7+X7+W7+V7 -> 1930637.4 | Z81: =+Z7+Y7+X7+W7 -> 1917582.5 | AA81: =+AA7+Z7+Y7+X7 -> 1919000.3 | ... BE81: =+BE7+BD7+BC7+BB7 -> 3002583.4
B82: Operating profit | C82: =C15 -> 182019.64 | D82: =D15 -> 80843.799 | E82: =E15 -> 114395.32 | F82: =F15 -> 117385.34 | G82: =G15 -> 90913.071 | H82: =H15 -> 343916.57 | I82: =I15 -> 212469.04 | J82: =J15 -> 294374.69 | ... O82: =O15 -> 262841.65 | T82: =T15+S15+R15+Q15 -> 114395.32 | U82: =U15+T15+S15+R15 -> 110554.83 | V82: =V15+U15+T15+S15 -> 105428.51 | W82: =W15+V15+U15+T15 -> 107618.54 | X82: =X15+W15+V15+U15 -> 117385.34 | Y82: =Y15+X15+W15+V15 -> 103146.69 | Z82: =Z15+Y15+X15+W15 -> 95006.301 | AA82: =AA15+Z15+Y15+X15 -> 85054.156 | ... BE82: =BE15+BD15+BC15+BB15 -> 262841.65
B83: EBITDA | C83: =C43 -> 425400.36 | D83: =D43 -> 356585.29 | E83: =E43 -> 424780.73 | F83: =F43 -> 437102.7 | G83: =G43 -> 426930.55 | H83: =H43 -> 770411.16 | I83: =I43 -> 684231.89 | J83: =J43 -> 772452.26 | ... O83: =O43 -> 855384.79 | T83: =T43+S43+R43+Q43 -> 424780.73 | U83: =U43+T43+S43+R43 -> 425722.88 | V83: =V43+U43+T43+S43 -> 425777.32 | W83: =W43+V43+U43+T43 -> 431934.85 | X83: =X43+W43+V43+U43 -> 437102.7 | Y83: =Y43+X43+W43+V43 -> 426469.67 | Z83: =Z43+Y43+X43+W43 -> 422072.38 | AA83: =AA43+Z43+Y43+X43 -> 417123.24 | ... BE83: =BE43+BD43+BC43+BB43 -> 855384.79
B84: Adjusted EBITDA | C84: =+C48 -> 425400.36 | D84: =+D48 -> 356585.29 | E84: =+E48 -> 424780.73 | F84: =+F48 -> 437102.7 | G84: =+G48 -> 426921 | H84: =+H48 -> 770411 | I84: =+I48 -> 684231.89 | J84: =+J48 -> 772452.26 | ... O84: =+O48 -> 855384.79 | T84: =+T48+S48+R48+Q48 -> 424780.73 | U84: =+U48+T48+S48+R48 -> 425722.73 | V84: =+V48+U48+T48+S48 -> 425777.73 | W84: =+W48+V48+U48+T48 -> 431935.73 | X84: =+X48+W48+V48+U48 -> 437102.7 | Y84: =+Y48+X48+W48+V48 -> 426469.7 | Z84: =+Z48+Y48+X48+W48 -> 422071.7 | AA84: =+AA48+Z48+Y48+X48 -> 417122.7 | ... BE84: =+BE48+BD48+BC48+BB48 -> 855384.79
B85: Adjusted EBITDA (pre-IFRS 16) | C85: =+C51 -> 425400.36 | D85: =+D51 -> 356585.29 | E85: =+E51 -> 424780.73 | F85: =+F51 -> 437102.7 | G85: =+G51 -> 426921 | H85: =+H51 -> 687180 | I85: =+I51 -> 684231.89 | J85: =+J51 -> 772452.26 | ... O85: =+O51 -> 855384.79 | T85: =+T51+S51+R51+Q51 -> 424780.73 | U85: =+U51+T51+S51+R51 -> 425722.73 | V85: =+V51+U51+T51+S51 -> 425777.73 | W85: =+W51+V51+U51+T51 -> 431935.73 | X85: =+X51+W51+V51+U51 -> 437102.7 | Y85: =+Y51+X51+W51+V51 -> 426469.7 | Z85: =+Z51+Y51+X51+W51 -> 422071.7 | AA85: =+AA51+Z51+Y51+X51 -> 417122.7 | ... AF85: =+AF51+AE51+AD51+AC51 -> 687180 | AJ85: =+AJ51+AI51+AH51+AG51 -> 0
B86: Cash interest paid | C86: =-C60 -> 38230.206 | D86: =-D60 -> 63085.944 | E86: =-E60 -> 67686.202 | F86: =-F60 -> 70675.87 | G86: =-G60 -> 77123.244 | H86: =-H60 -> 86893.145 | I86: =-I60 -> 94388.228 | J86: =-J60 -> 148370.22 | ... O86: =-O60 -> 105448 | T86: =-T60-S60-R60-Q60 -> 67686.202 | U86: =-U60-T60-S60-R60 -> 67853.251 | V86: =-V60-U60-T60-S60 -> 68382.004 | W86: =-W60-V60-U60-T60 -> 69110.175 | X86: =-X60-W60-V60-U60 -> 70675.87 | Y86: =-Y60-X60-W60-V60 -> 71853.022 | Z86: =-Z60-Y60-X60-W60 -> 74084.541 | AA86: =-AA60-Z60-Y60-X60 -> 75284.407 | ... BE86: =-BE60-BD60-BC60-BB60 -> 105448
B87: Net Income | C87: =+C24 -> 111720.84 | D87: =+D24 -> -1101.997 | E87: =+E24 -> 34158.1 | F87: =+F24 -> 43409.541 | G87: =+G24 -> -23614.092 | H87: =+H24 -> 154152.11 | I87: =+I24 -> 84466.248 | J87: =+J24 -> 74975.311 | ... O87: =+O24 -> 196160.25 | T87: =+T24+S24+R24+Q24 -> 34158.1 | U87: =+U24+T24+S24+R24 -> 24315.111 | V87: =+V24+U24+T24+S24 -> 12876.519 | W87: =+W24+V24+U24+T24 -> 21083.513 | X87: =+X24+W24+V24+U24 -> 43409.541 | Y87: =+Y24+X24+W24+V24 -> 29306.571 | Z87: =+Z24+Y24+X24+W24 -> 8310.971 | AA87: =+AA24+Z24+Y24+X24 -> -14620.304 | ... BE87: =+BE24+BD24+BC24+BB24 -> 196160.25
B88: Capex | C88: =-C63 -> 551380.22 | D88: =-D63 -> 523186.87 | E88: =-E63 -> 454189.44 | F88: =-F63 -> 497128.96 | G88: =-G63 -> 507874.09 | H88: =-H63 -> -12814.072 | I88: =-I63 -> 291709.95 | J88: =-J63 -> 260440.53 | ... O88: =-O63 -> 493971.73 | T88: =-T63-S63-R63-Q63 -> 454189.44 | U88: =-U63-T63-S63-R63 -> 465147.97 | V88: =-V63-U63-T63-S63 -> 466767.94 | W88: =-W63-V63-U63-T63 -> 490639.66 | X88: =-X63-W63-V63-U63 -> 497128.96 | Y88: =-Y63-X63-W63-V63 -> 519260.61 | Z88: =-Z63-Y63-X63-W63 -> 532705.32 | AA88: =-AA63-Z63-Y63-X63 -> 520586.48 | ... BE88: =-BE63-BD63-BC63-BB63 -> 493971.73
B89: Free cash flow | C89: =+C66 -> 616403.83 | D89: =+D66 -> 433732.54 | E89: =+E66 -> 392037.83 | F89: =+F66 -> 774396.87 | G89: =+G66 -> 698161.2 | H89: =+H66 -> 1673637.5 | I89: =+I66 -> 1284359.8 | J89: =+J66 -> 1210696.1 | ... O89: =+O66 -> 247062.76 | T89: =+T66+S66+R66+Q66 -> 392037.83 | U89: =+U66+T66+S66+R66 -> 365993.6 | V89: =+V66+U66+T66+S66 -> 376493.83 | W89: =+W66+V66+U66+T66 -> 712721.2 | X89: =+X66+W66+V66+U66 -> 774396.87 | Y89: =+Y66+X66+W66+V66 -> 707187.05 | Z89: =+Z66+Y66+X66+W66 -> 759070.78 | AA89: =+AA66+Z66+Y66+X66 -> 705690.26 | ... BE89: =+BE66+BD66+BC66+BB66 -> 247062.76
B91: BALANCE SHEET | C91: =+C80 -> 41974 | D91: =+D80 -> 42340 | E91: =+E80 -> 42707 | F91: =+F80 -> 43073 | G91: =G3 -> 43438 | H91: =H3 -> 43803 | I91: =I3 -> 44169 | J91: =J3 -> 44534 | K91: =K3 -> 44926 | L91: =L3 -> 45291 | M91: =M3 -> 45657 | N91: =N3 -> 46022 | O91: =+O80 -> 46112 | Q91: =+Q80 -> 42437 | R91: =+R80 -> 42527 | S91: =+S80 -> 42622 | T91: =+T80 -> 42714 | U91: =+U80 -> 42801 | V91: =+V80 -> 42892 | W91: =+W80 -> 42987 | X91: =+X80 -> 43079 | Y91: =+Y80 -> 43190 | Z91: =Z3 -> 43281 | AA91: =AA3 -> 43373 | AB91: =AB3 -> 43465 | AC91: =+AC80 -> 43555 | AD91: =+AD80 -> 43646 | AE91: =+AE80 -> 43738 | AF91: =+AF80 -> 43830 | AG91: =+AG80 -> 43921 | AH91: =+AH80 -> 44012 | AI91: =+AI80 -> 44104 | AJ91: =+AJ80 -> 44196 | ... BE91: =+BE80 -> 46112
B93: Tangible fixed assets | C93: 1614978.5 | D93: 1785575.3 | E93: 1829611.3 | F93: 1876555.2 | G93: 2035133.2 | H93: =2042852.51+385861.761 -> 2428714.3 | I93: =1940341.846+362410.839 -> 2302752.7 | J93: =2049999.322+442122.455 -> 2492121.8 | K93: =2017214.172+472828.691 -> 2490042.9 | L93: =2136965.468+485851.073 -> 2622816.5 | M93: =2290984.914+580796.729 -> 2871781.6 | N93: =2326734.435+612919.721 -> 2939654.2 | O93: =BE93 -> 2888468 | Q93: 1759890.4 | R93: 1768739.6 | S93: 1778871.3 | T93: =+E93 -> 1829611.3 | U93: 1845811.6 | V93: 1849052.5 | W93: 1850630.9 | X93: =+F93 -> 1876555.2 | Y93: 1880227 | Z93: 1944974.7 | AA93: 1981661.2 | AB93: =G93 -> 2035133.2 | AC93: =2058772.69+355744.282 -> 2414517 | AD93: =2084972.147+368806.648 -> 2453778.8 | AE93: =2128251.684+366917.97 -> 2495169.7 | AF93: =H93 -> 2428714.3 | AG93: =2126115.385+408083.01 -> 2534198.4 | AH93: =2075238.356+388644.477 -> 2463882.8 | AI93: =2029702.082+377882.486 -> 2407584.6 | AJ93: =I93 -> 2302752.7 | AK93: =1934259.558+352384.193 -> 2286643.8 | AL93: =1932945.698+339898.311 -> 2272844 | AM93: =1967387.664+381086.875 -> 2348474.5 | AN93: =J93 -> 2492121.8 | AO93: =2025652.313+430287.928 -> 2455940.2 | AP93: =2134002.322+462301.697 -> 2596304 | AQ93: =1967387.664+381086.875 -> 2348474.5 | AR93: =K93 -> 2490042.9 | AS93: =1985279.196+447184.664 -> 2432463.9 | AT93: =2047894.211+464212.168 -> 2512106.4 | AU93: =2104916.584+484905.371 -> 2589822 | AV93: =L93 -> 2622816.5 | AW93: =2236288.403+504591.654 -> 2740880.1 | AX93: =2207209.005+545062.1 -> 2752271.1 | AY93: =2200709.398+559639.64 -> 2760349 | AZ93: =M93 -> 2871781.6 | BA93: =2286181.41+576492.441 -> 2862673.9 | BB93: =2300377.008+587537.844 -> 2887914.9 | BC93: =2333464.83+605785.393 -> 2939250.2 | BD93: =N93 -> 2939654.2 | BE93: =2296001.366+592466.684 -> 2888468
B94: Inventory | C94: 107121.67 | D94: 94434.998 | E94: 91416.726 | F94: 96928.834 | G94: 120229.7 | H94: 82615.111 | I94: 77736.315 | J94: 121126.31 | K94: 120441.25 | L94: 107545.48 | M94: 108113.75 | N94: 125739.12 | O94: =BE94 -> 155330.22 | Q94: 98816.001 | R94: 105282.83 | S94: 101435.27 | T94: =+E94 -> 91416.726 | U94: 108875.57 | V94: 108898.22 | W94: 103748.31 | X94: =+F94 -> 96928.834 | Y94: 100329.38 | Z94: 109569.7 | AA94: 97852.007 | AB94: =G94 -> 120229.7 | AC94: 113361.16 | AD94: 106915.69 | AE94: 101965.2 | AF94: =H94 -> 82615.111 | AG94: 103170.66 | AH94: 86894.804 | AI94: 81924.814 | AJ94: =I94 -> 77736.315 | AK94: 110294.06 | AL94: 107066.2 | AM94: 109462.31 | AN94: =J94 -> 121126.31 | AO94: 163986.25 | AP94: =171328.1 -> 171328.1 | AQ94: 109462.31 | AR94: =K94 -> 120441.25 | AS94: 126613.12 | AT94: 105618.9 | AU94: 100933.03 | AV94: =L94 -> 107545.48 | AW94: 121357.96 | AX94: 101706.8 | AY94: 112304.9 | AZ94: =M94 -> 108113.75 | BA94: 127606.01 | BB94: 124712.87 | BC94: 132993.68 | BD94: =N94 -> 125739.12 | BE94: 155330.22
B95: Trade accounts receivables, net | C95: 300744.17 | D95: 308517.49 | E95: 330626.21 | F95: 346455.96 | G95: 438739.77 | H95: 508571.1 | I95: 489258.44 | J95: 620457.32 | K95: 627345.56 | L95: 633257.36 | M95: 681565.86 | N95: 736169.98 | O95: =BE95 -> 715967.46 | Q95: 293225.91 | R95: 292962.56 | S95: 310744.55 | T95: =+E95 -> 330626.21 | U95: 308272.71 | V95: 321258.17 | W95: 322523.39 | X95: =+F95 -> 346455.96 | Y95: 394089.28 | Z95: 408691.83 | AA95: 432868.1 | AB95: =G95 -> 438739.77 | AC95: 420776.15 | AD95: 425442.66 | AE95: 443425.29 | AF95: =H95 -> 508571.1 | AG95: 514699.47 | AH95: 478422.23 | AI95: 462450.53 | AJ95: =I95 -> 489258.44 | AK95: 491252.79 | AL95: 548225.47 | AM95: 578980.51 | AN95: =J95 -> 620457.32 | AO95: 639666.76 | AP95: =711871.506 -> 711871.51 | AQ95: 578980.51 | AR95: =K95 -> 627345.56 | AS95: 568740.76 | AT95: 572365.26 | AU95: 587206.34 | AV95: =L95 -> 633257.36 | AW95: 642310.19 | AX95: 637205.38 | AY95: 640630.12 | AZ95: =M95 -> 681565.86 | BA95: 661827.17 | BB95: 650214.67 | BC95: 660331.5 | BD95: =N95 -> 736169.98 | BE95: 715967.46
B96: Trade creditors /payables | C96: 529009.41 | D96: 525128.91 | E96: 505044.06 | F96: 545150.72 | G96: 553734.58 | H96: 660395.15 | I96: 662449.11 | J96: 746239.15 | K96: 694816.61 | L96: 791220.47 | M96: 791182.59 | N96: 869092.64 | O96: =BE96 -> 847968.44 | Q96: 499438.03 | R96: 483567.96 | S96: 440253.7 | T96: =+E96 -> 505044.06 | U96: 485300.59 | V96: 465226.11 | W96: 487163.42 | X96: =+F96 -> 545150.72 | Y96: 466171.63 | Z96: 480685.61 | AA96: 516462.21 | AB96: =G96 -> 553734.58 | AC96: 501078.09 | AD96: 486374.44 | AE96: 493059.25 | AF96: =H96 -> 660395.15 | AG96: 593149.97 | AH96: 508909.94 | AI96: 603796.22 | AJ96: =I96 -> 662449.11 | AK96: 660124.77 | AL96: 661828.4 | AM96: 667551.12 | AN96: =J96 -> 746239.15 | AO96: 730843.26 | AP96: 710856.34 | AQ96: 667551.12 | AR96: =K96 -> 694816.61 | AS96: 636198.56 | AT96: 615875.84 | AU96: 631002.36 | AV96: =L96 -> 791220.47 | AW96: 756695.39 | AX96: 715212.71 | AY96: 700470.91 | AZ96: =M96 -> 791182.59 | BA96: 774523.93 | BB96: 743803.49 | BC96: 755105.55 | BD96: =N96 -> 869092.64 | BE96: 847968.44
B97: Net working capital | C97: =C94+C95-C96 -> -121143.58 | D97: =D94+D95-D96 -> -122176.42 | E97: =E94+E95-E96 -> -83001.124 | F97: =F94+F95-F96 -> -101765.93 | G97: =G94+G95-G96 -> 5234.893 | H97: =H94+H95-H96 -> -69208.936 | I97: =I94+I95-I96 -> -95454.356 | J97: =J94+J95-J96 -> -4655.513 | ... O97: =O94+O95-O96 -> 23329.25 | Q97: =Q94+Q95-Q96 -> -107396.12 | R97: =R94+R95-R96 -> -85322.572 | S97: =S94+S95-S96 -> -28073.882 | T97: =T94+T95-T96 -> -83001.124 | U97: =U94+U95-U96 -> -68152.301 | V97: =V94+V95-V96 -> -35069.719 | W97: =W94+W95-W96 -> -60891.724 | X97: =X94+X95-X96 -> -101765.93 | ... BE97: =BE94+BE95-BE96 -> 23329.25
B98: % of revenues | C98: =+C97/C81 -> -0.073076209 | D98: =+D97/D81 -> -0.068461032 | E98: =+E97/E81 -> -0.044440357 | F98: =+F97/F81 -> -0.05237375 | G98: =+G97/G81 -> 0.0027362343 | H98: =+H97/H81 -> -0.034975347 | I98: =+I97/I81 -> -0.04561423 | J98: =+J97/J81 -> -0.0019327028 | ... O98: =+O97/O81 -> 0.0077697258 | T98: =+T97/T81 -> -0.044440357 | U98: =+U97/U81 -> -0.03621561 | V98: =+V97/V81 -> -0.018421453 | W98: =+W97/W81 -> -0.031784817 | X98: =+X97/X81 -> -0.05237375 | Y98: =+Y97/Y81 -> 0.014630934 | Z98: =+Z97/Z81 -> 0.019595464 | AA98: =+AA97/AA81 -> 0.0074298593 | ... BE98: =+BE97/BE81 -> 0.0077697258
B101: Inventory Days | H101: =H94/-H10*365 -> 115.90395 | I101: =I94/-I10*365 -> 110.58352 | J101: =J94/-J10*365 -> 171.80404 | K101: =K94/-K10*365 -> 148.45396 | L101: =L94/-L10*365 -> 130.00494 | M101: =M94/-M10*365 -> 121.81712 | N101: =N94/-N10*365 -> 130.9626 | O101: =O94/-O10*365 -> 160.78848 | Q101: =Q94/-Q10*(365/4) -> 148.82424 | R101: =R94/-R10*(365/4) -> 157.36245 | S101: =S94/-S10*(365/4) -> 148.80138 | T101: =T94/-T10*(365/4) -> 135.05875 | U101: =U94/-U10*(365/4) -> 153.5955 | V101: =V94/-V10*(365/4) -> 161.00831 | W101: =W94/-W10*(365/4) -> 155.07076 | X101: =X94/-X10*(365/4) -> 143.31729 | ... BE101: =BE94/-BE10*(365/4) -> 156.21227
B102: Receivable Days | C102: =C95/C7*365 -> 66.216422 | D102: =D95/D7*365 -> 63.099901 | E102: =E95/E7*365 -> 64.613565 | F102: =F95/F7*365 -> 65.080696 | G102: =G95/G7*365 -> 83.70383 | H102: =H95/H7*365 -> 93.808978 | I102: =I95/I7*365 -> 85.336689 | J102: =J95/J7*365 -> 94.016116 | ... N102: =N95/N7*365 -> 90.933463 | O102: =(O95/O7)*365 -> 87.034426 | Q102: =Q95/Q7*(365/4) -> 58.235 | R102: =R95/R7*(365/4) -> 58.517335 | S102: =S95/S7*(365/4) -> 60.601331 | T102: =T95/T7*(365/4) -> 62.398946 | U102: =U95/U7*(365/4) -> 59.393948 | V102: =V95/V7*(365/4) -> 61.234435 | W102: =W95/W7*(365/4) -> 61.324967 | X102: =X95/X7*(365/4) -> 61.889126 | ... AV102: =AV95/AV7*(365/4) -> 87.386749 | AW102: =AW95/AW7*365/4 -> 90.205919 | AX102: =AX95/AX7*(365/4) -> 88.009867 | AY102: =AY95/AY7*(365/4) -> 88.630255 | AZ102: =AZ95/AZ7*(365/4) -> 84.816758 | BA102: =BA95/BA7*365/4 -> 85.409563 | BB102: =BB95/BB7*(365/4) -> 84.083026 | BC102: =BC95/BC7*(365/4) -> 82.492052 | BD102: =BD95/BD7*(365/4) -> 82.751658 | BE102: =BE95/BE7*(365/4) -> 86.562636
B103: Payable Days | H103: =H96/-H10*365 -> 926.49404 | I103: =I96/-I10*365 -> 942.36461 | J103: =J96/-J10*365 -> 1058.4562 | K103: =K96/-K10*365 -> 856.41987 | L103: =L96/-L10*365 -> 956.45645 | M103: =M96/-M10*365 -> 891.46462 | N103: =N96/-N10*365 -> 905.19668 | O103: =O96/-O10*365 -> 877.76577 | Q103: =Q96/-Q10*(365/4) -> 752.19077 | R103: =R96/-R10*(365/4) -> 722.77159 | S103: =S96/-S10*(365/4) -> 645.83414 | T103: =T96/-T10*(365/4) -> 746.15034 | U103: =U96/-U10*(365/4) -> 684.6346 | V103: =V96/-V10*(365/4) -> 687.84662 | W103: =W96/-W10*(365/4) -> 728.15454 | X103: =X96/-X10*(365/4) -> 806.05038 | ... BE103: =BE96/-BE10*(365/4) -> 852.78365
B105: Debt Breakdown
B106: Short-term debt | C106: =C107+C108+C109+C110 -> 17246.352 | D106: =D107+D108+D109+D110 -> 19255.78 | E106: =E107+E108+E109+E110 -> 18433.492 | F106: =F107+F108+F109+F110 -> 17568.44 | G106: =G107+G108+G109+G110 -> 18032.775 | H106: =H107+H108+H109+H110 -> 88927.515 | I106: =I107+I108+I109+I110 -> 94730.719 | J106: =J107+J108+J109+J110 -> 296390.21 | ... O106: =O107+O108+O109+O110 -> 172332.15 | Q106: =Q107+Q108+Q109+Q110 -> 22143.041 | R106: =R107+R108+R109+R110 -> 18177.67 | S106: =S107+S108+S109+S110 -> 21446.4 | T106: =T107+T108+T109+T110 -> 18433.492 | U106: =U107+U108+U109+U110 -> 21771.075 | V106: =V107+V108+V109+V110 -> 18988.12 | W106: =W107+W108+W109+W110 -> 22048.759 | X106: =X107+X108+X109+X110 -> 17568.44 | ... BE106: =BE107+BE108+BE109+BE110 -> 172332.15
B107: Interest bearing borrowings (Loans) | C107: 482.431 | D107: 417.699 | E107: 468.598 | F107: 1109.07 | G107: 795.39 | H107: 504.735 | I107: 641.558 | J107: 47784.171 | K107: 90137.674 | L107: 151077.58 | M107: 77024.65 | N107: 14630.288 | O107: =BE107 -> 14561.932 | Q107: 876.765 | R107: 456.441 | S107: 466.398 | T107: =E107 -> 468.598 | U107: 515.6 | V107: 1145.185 | W107: 1548.172 | X107: =F107 -> 1109.07 | Y107: 1005.008 | Z107: 651.498 | AA107: 1080.445 | AB107: =G107 -> 795.39 | AC107: 1221.547 | AD107: 36481.927 | AE107: 13890.117 | AF107: =H107 -> 504.735 | AG107: 198.598 | AH107: 3091.453 | AI107: 422.232 | AJ107: =I107 -> 641.558 | AK107: 880.975 | AL107: 23982.593 | AM107: 40755.654 | AN107: =J107 -> 47784.171 | AO107: 75441.069 | AP107: =99872.456 -> 99872.456 | AQ107: 125892.92 | AR107: =K107 -> 90137.674 | AS107: 83043.452 | AT107: 116285.11 | AU107: 128875.26 | AV107: =L107 -> 151077.58 | AW107: 128906.26 | AX107: 122030.21 | AY107: 112612.27 | AZ107: =M107 -> 77024.65 | BA107: 74953.775 | BB107: 28955.56 | BC107: 31868.848 | BD107: =N107 -> 14630.288 | BE107: 14561.932
B108: Liabilities with bondholders | C108: 15611.596 | D108: 17532.996 | E108: 16587.414 | F108: 15303.757 | G108: 17237.385 | H108: 19479.764 | I108: 18636.014 | J108: 143291.9 | K108: 144370.76 | L108: 146937.95 | M108: 299932.56 | N108: 9337.567 | O108: =BE108 -> 8921.722 | Q108: 19937.174 | R108: 16361.167 | S108: 19645.124 | T108: =E108 -> 16587.414 | U108: 19841.176 | V108: 16478.462 | W108: 19179.822 | X108: =F108 -> 15303.757 | Y108: 18285.248 | Z108: 16175.514 | AA108: 19836.43 | AB108: =G108 -> 17237.385 | AC108: 20336.437 | AD108: 16860.634 | AE108: 21699.311 | AF108: =H108 -> 19479.764 | AG108: 27431.491 | AH108: 21231.726 | AI108: 25741.787 | AJ108: =I108 -> 18636.014 | AK108: 24096.222 | AL108: 19047.305 | AM108: 16626.663 | AN108: =J108 -> 143291.9 | AO108: 131521.07 | AP108: 158151.76 | AQ108: 159675.33 | AR108: =K108 -> 144370.76 | AS108: 130198.64 | AT108: 135483.35 | AU108: 146970 | AV108: =L108 -> 146937.95 | AW108: 157633.9 | AX108: 158205.65 | AY108: 396771.24 | AZ108: =M108 -> 299932.56 | BA108: 279327.4 | BB108: 282006.77 | BC108: 8877.971 | BD108: =N108 -> 9337.567 | BE108: 8921.722
B109: Finance Lease Liabilities | C109: 1152.325 | D109: 1305.085 | E109: 1377.48 | F109: 1155.613 | G109: 0 | H109: 0 | I109: 0 | J109: 0 | K109: 0 | L109: 0 | M109: 0 | N109: 0 | O109: =BE109 -> 0 | Q109: 1329.102 | R109: 1360.062 | S109: 1334.878 | T109: =E109 -> 1377.48 | U109: 1414.299 | V109: 1364.473 | W109: 1320.765 | X109: =F109 -> 1155.613 | Y109: 832.261 | Z109: 495.328 | AA109: 187.515 | AB109: =G109 -> 0 | AC109: 0 | AD109: 0 | AE109: 0 | AF109: =H109 -> 0 | AG109: 0 | AH109: 0 | AI109: 0 | AJ109: =I109 -> 0 | AK109: 0 | AL109: 0 | AM109: 0 | AN109: =J109 -> 0 | AO109: 0 | AP109: 0 | AQ109: 0 | AR109: =K109 -> 0 | AS109: 0 | AT109: 0 | AU109: 0 | AV109: =L109 -> 0 | AW109: 0 | AX109: 0 | AY109: 0 | AZ109: =M109 -> 0 | BA109: 0 | BB109: 0 | BC109: 0 | BD109: =N109 -> 0 | BE109: 0
B110: Liabilities for leases current | H110: 68943.016 | I110: 75453.147 | J110: 105314.13 | K110: 109048.29 | L110: 120979.89 | M110: 143981.55 | N110: 148627.24 | O110: =BE110 -> 148848.49 | AC110: 5 | AD110: 62175.225 | AE110: 64844.6 | AF110: =H110 -> 68943.016 | AG110: 80078.368 | AH110: 80380.434 | AI110: 78266.734 | AJ110: =I110 -> 75453.147 | AK110: 79474.096 | AL110: 79945.016 | AM110: 93476.001 | AN110: =J110 -> 105314.13 | AO110: 106538.96 | AP110: 115751.15 | AQ110: 118733.64 | AR110: =K110 -> 109048.29 | AS110: 108335.93 | AT110: 113149.86 | AU110: 127357.47 | AV110: =L110 -> 120979.89 | AW110: 126171.95 | AX110: 132432.21 | AY110: 136880.68 | AZ110: =M110 -> 143981.55 | BA110: 145493.66 | BB110: 139559.91 | BC110: 147439.54 | BD110: =N110 -> 148627.24 | BE110: 148848.49
B111: Long-term debt | C111: =C112+C113+C114+C115 -> 1434258.5 | D111: =D112+D113+D114+D115 -> 1654135.1 | E111: =E112+E113+E114+E115 -> 1575575.3 | F111: =F112+F113+F114+F115 -> 1567108.7 | G111: =G112+G113+G114+G115 -> 1789546.9 | H111: =H112+H113+H114+H115 -> 2400054.8 | I111: =I112+I113+I114+I115 -> 2279019.5 | J111: =J112+J113+J114+J115 -> 2421613.2 | ... O111: =O112+O113+O114+O115 -> 2096865.9 | Q111: =Q112+Q113+Q114+Q115 -> 1571602.3 | R111: =R112+R113+R114+R115 -> 1556107.1 | S111: =S112+S113+S114+S115 -> 1550662 | T111: =T112+T113+T114+T115 -> 1575575.3 | U111: =U112+U113+U114+U115 -> 1564768 | V111: =V112+V113+V114+V115 -> 1664803.1 | W111: =W112+W113+W114+W115 -> 1612278.7 | X111: =X112+X113+X114+X115 -> 1567108.7 | ... BE111: =BE112+BE113+BE114+BE115 -> 2096865.9
B112: Interest bearing borrowings (Loans) | C112: 181302.04 | D112: 210199.32 | E112: 198837.8 | F112: 284462.63 | G112: 357283.98 | H112: 170638.98 | I112: 110230.75 | J112: 97044.862 | K112: 97704.798 | L112: 35038.659 | M112: 0 | N112: 168379.24 | O112: =BE112 -> 170467.77 | Q112: 198117.78 | R112: 195896.82 | S112: 195175.79 | T112: =E112 -> 198837.8 | U112: 196963.54 | V112: 295026.1 | W112: 289456.88 | X112: =F112 -> 284462.63 | Y112: 282088.21 | Z112: 292883.54 | AA112: 295099.17 | AB112: =G112 -> 357283.98 | AC112: 352587.38 | AD112: 352980.81 | AE112: 368020.75 | AF112: =H112 -> 170638.98 | AG112: 119792.55 | AH112: 119672.39 | AI112: 116719.05 | AJ112: =I112 -> 110230.75 | AK112: 110882.35 | AL112: 88175.347 | AM112: 93949.43 | AN112: =J112 -> 97044.862 | AO112: 92327.006 | AP112: 103648.67 | AQ112: 105948.6 | AR112: =K112 -> 97704.798 | AS112: 92550.369 | AT112: 61606.933 | AU112: 65367.787 | AV112: =L112 -> 35038.659 | AW112: 39135.815 | AX112: 0 | AY112: 0 | AZ112: =M112 -> 0 | BA112: 0 | BB112: 0 | BC112: 173046.13 | BD112: =N112 -> 168379.24 | BE112: 170467.77
B113: Liabilities with bondholders | C113: 1249373.9 | D113: 1441510.4 | E113: 1375601.2 | F113: 1282646 | G113: 1432262.9 | H113: 1796470.1 | I113: 1740015 | J113: 1838465.7 | K113: 1798566.5 | L113: 1729378.7 | M113: 1633381 | N113: 1386290.2 | O113: =BE113 -> 1403972.5 | Q113: 1371363.4 | R113: 1358401.8 | S113: 1354007 | T113: =E113 -> 1375601.2 | U113: 1367005.2 | V113: 1369290.5 | W113: 1322639 | X113: =F113 -> 1282646 | Y113: 1263889.5 | Z113: 1350890.4 | AA113: 1369110.6 | AB113: =G113 -> 1432262.9 | AC113: 1403652.4 | AD113: 1407528.1 | AE113: 1496643.4 | AF113: =H113 -> 1796470.1 | AG113: 1985563.2 | AH113: 1931878.3 | AI113: 1872657 | AJ113: =I113 -> 1740015 | AK113: 1764360 | AL113: 1779756.9 | AM113: 1889335.9 | AN113: =J113 -> 1838465.7 | AO113: 1760325.8 | AP113: 2011913.7 | AQ113: 2075960.6 | AR113: =K113 -> 1798566.5 | AS113: 1711182.3 | AT113: 1735876.5 | AU113: 1874491.4 | AV113: =L113 -> 1729378.7 | AW113: 1871673.8 | AX113: 1830526.6 | AY113: 1522911.6 | AZ113: =M113 -> 1633381 | BA113: 1596195.4 | BB113: 1659653.9 | BC113: 1423842 | BD113: =N113 -> 1386290.2 | BE113: 1403972.5
B114: Finance Lease Liabilities | C114: 3582.507 | D114: 2425.36 | E114: 1136.294 | F114: 0 | G114: 0 | H114: 0 | I114: 0 | J114: 0 | K114: 0 | L114: 0 | M114: 0 | N114: 0 | O114: =BE114 -> 0 | Q114: 2121.187 | R114: 1808.449 | S114: 1479.177 | T114: =E114 -> 1136.294 | U114: 799.246 | V114: 486.417 | W114: 182.811 | X114: =F114 -> 0 | Y114: 0 | Z114: 0 | AA114: 0 | AB114: =G114 -> 0 | AD114: 0 | AE114: 0 | AF114: =H114 -> 0 | AG114: 0 | AH114: 0 | AI114: 0 | AJ114: =I114 -> 0 | AK114: 0 | AL114: 0 | AM114: 0 | AN114: =J114 -> 0 | AO114: 0 | AP114: 0 | AQ114: 0 | AR114: =K114 -> 0 | AS114: 0 | AT114: 0 | AU114: 0 | AV114: =L114 -> 0 | AW114: 0 | AX114: 0 | AY114: 0 | AZ114: =M114 -> 0 | BA114: 0 | BB114: 0 | BC114: 0 | BD114: =N114 -> 0 | BE114: 0
...

Sheet KPIS
B2: ENTEL | C2: Annual | D2: Annual | E2: Annual | F2: Annual | G2: Annual | H2: Annual | I2: Annual | J2: Annual | K2: Annual | L2: Annual | M2: Annual | N2: Annual | O2: Annual | P2: LTM | R2: Quarterly | S2: Quarterly | T2: Quarterly | U2: Quarterly | V2: Quarterly | W2: Quarterly | X2: Quarterly | Y2: Quarterly | Z2: Quarterly | AA2: Quarterly | AB2: Quarterly | AC2: Quarterly | AD2: Quarterly | AE2: Quarterly | AF2: Quarterly | AG2: Quarterly | AH2: Quarterly | AI2: Quarterly | AJ2: Quarterly | AK2: Quarterly | AL2: Quarterly | AM2: Quarterly | AN2: Quarterly | AO2: Quarterly | AP2: Quarterly | AQ2: Quarterly | AR2: Quarterly | AS2: Quarterly | AT2: Quarterly | AU2: Quarterly | AV2: Quarterly | AW2: Quarterly | AX2: Quarterly | AY2: Quarterly | AZ2: Quarterly | BA2: Quarterly | BB2: Quarterly | BC2: Quarterly | BD2: Quarterly | BE2: Quarterly | BF2: Quarterly
B3: (Ch$ millions) | C3: 41975 | D3: 42340 | E3: 42707 | F3: 43073 | G3: 43438 | H3: 43438 | I3: 43803 | J3: 44169 | K3: 44534 | L3: 44926 | M3: 45291 | N3: 45657 | O3: 46022 | P3: =BF3 -> 46112 | R3: 42437 | S3: 42527 | T3: 42622 | U3: 42714 | V3: 42801 | W3: 42892 | X3: 42987 | Y3: 43079 | Z3: 43190 | AA3: 43281 | AB3: 43373 | AC3: 43465 | AD3: 43555 | AE3: 43646 | AF3: 43738 | AG3: 43830 | AH3: 43921 | AI3: 44012 | AJ3: 44104 | AK3: 44196 | AL3: 44286 | AM3: 44377 | AN3: 44469 | AO3: 44561 | AP3: 44651 | AQ3: 44742 | AR3: 44834 | AS3: 44926 | AT3: 45016 | AU3: 45107 | AV3: 45199 | AW3: 45291 | AX3: 45382 | AY3: 45473 | AZ3: 45565 | BA3: 45657 | BB3: 45747 | BC3: 45838 | BD3: 45930 | BE3: 46022 | BF3: 46112
C4: Act | D4: Act | E4: Act | F4: Act | G4: Act | H4: Act | I4: Act | J4: Act | K4: Act | L4: Act | M4: Act | N4: Act | O4: Act | P4: Act | R4: Act | S4: Act | T4: Act | U4: Act | V4: Act | W4: Act | X4: Act | Y4: Act | Z4: Act | AA4: Act | AB4: Act | AC4: Act | AD4: Act | AE4: Act | AF4: Act | AG4: Act | AH4: Act | AI4: Act | AJ4: Act | AK4: Act | AL4: Act | AM4: Act | AN4: Act | AO4: Act | AP4: Act | AQ4: Act | AR4: Act | AS4: Act | AT4: Act | AU4: Act | AV4: Act | AW4: Act | AX4: Act | AY4: Act | AZ4: Act | BA4: Act | BB4: Act | BC4: Act | BD4: Act | BE4: Act | BF4: Act
C5: FY | D5: FY | E5: FY | F5: FY | G5: FY | H5: FY | I5: FY | J5: FY | K5: FY | L5: FY | M5: FY | N5: FY | O5: FY | P5: LTM | R5: Q1 | S5: Q2 | T5: Q3 | U5: Q4 | V5: Q1 | W5: Q2 | X5: Q3 | Y5: Q4 | Z5: Q1 | AA5: Q2 | AB5: Q3 | AC5: Q4 | AD5: Q1 | AE5: Q2 | AF5: Q3 | AG5: Q4 | AH5: Q1 | AI5: Q2 | AJ5: Q3 | AK5: Q4 | AL5: Q1 | AM5: Q2 | AN5: Q3 | AO5: Q4 | AP5: Q1 | AQ5: Q2 | AR5: Q3 | AS5: Q4 | AT5: Q1 | AU5: Q2 | AV5: Q3 | AW5: Q4 | AX5: Q1 | AY5: Q2 | AZ5: Q3 | BA5: Q4 | BB5: Q1 | BC5: Q2 | BD5: Q3 | BE5: Q4 | BF5: Q1
B7: Revenue by Segments
B8: Consumer | C8: 895081.71 | D8: 906619.38 | E8: 884434.6 | F8: 890684.32 | G8: 861262.83 | H8: 861262.83 | I8: 839092.67 | J8: 908564.8 | K8: 1069417.6 | L8: 1099807 | R8: 223641.22 | S8: =440677.368-R8 -> 217036.15 | T8: =658075.657-S8-R8 -> 217398.29 | U8: =E8-T8-S8-R8 -> 226358.94 | V8: 219034.59 | W8: =441203.792-V8 -> 222169.21 | X8: =659693.959-W8-V8 -> 218490.17 | Y8: =F8-X8-W8-V8 -> 230990.37 | Z8: 211645.11 | AA8: =425601.906-Z8 -> 213956.79 | AB8: =636162.288-AA8-Z8 -> 210560.38 | AC8: =H8-AB8-AA8-Z8 -> 225100.54 | AD8: 211447.79 | AE8: =413194.65-AD8 -> 201746.87 | AF8: =623214.391-AE8-AD8 -> 210019.74 | AG8: =I8-AF8-AE8-AD8 -> 215878.28 | AH8: 220500.89 | AI8: =420918.194-AH8 -> 200417.31 | AJ8: =653739.997-AH8-AI8 -> 232821.8 | AK8: =J8-AJ8-AI8-AH8 -> 254824.8 | AL8: 255744.43 | AM8: =521914.035-AL8 -> 266169.6 | AN8: =789686.56-AL8-AM8 -> 267772.53 | AO8: =K8-AN8-AM8-AL8 -> 279731.02 | AP8: 274822.06 | AQ8: =557472.167-AP8 -> 282650.11 | AR8: =821812.028-AP8-AQ8 -> 264339.86 | AS8: =L8-AP8-AQ8-AR8 -> 277994.97 | AT8: 267004.43
B9: Enterprise | C9: 296488.16 | D9: 307623.23 | E9: 303206.99 | F9: 293852.41 | G9: 281417.26 | H9: 281417.26 | I9: 258420.2 | J9: 248479.52 | K9: 266250.06 | L9: 265312.75 | R9: 76228.235 | S9: =151926.211-R9 -> 75697.976 | T9: =227221.075-S9-R9 -> 75294.864 | U9: =E9-T9-S9-R9 -> 75985.917 | V9: 74063.989 | W9: =149383.766-V9 -> 75319.777 | X9: =220788.305-W9-V9 -> 71404.539 | Y9: =F9-X9-W9-V9 -> 73064.103 | Z9: 73557.885 | AA9: =145612.934-Z9 -> 72055.049 | AB9: =213564.798-AA9-Z9 -> 67951.864 | AC9: =H9-AB9-AA9-Z9 -> 67852.462 | AD9: 65617.039 | AE9: =131531.307-AD9 -> 65914.268 | AF9: =195916.296-AE9-AD9 -> 64384.989 | AG9: =I9-AF9-AE9-AD9 -> 62503.904 | AH9: 61819.66 | AI9: =121424.285-AH9 -> 59604.625 | AJ9: =182397.994-AH9-AI9 -> 60973.709 | AK9: =J9-AJ9-AI9-AH9 -> 66081.531 | AL9: 63054.947 | AM9: =130964.334-AL9 -> 67909.387 | AN9: =198257.805-AL9-AM9 -> 67293.471 | AO9: =K9-AN9-AM9-AL9 -> 67992.259 | AP9: 63232.006 | AQ9: =129157.404-AP9 -> 65925.398 | AR9: =195203.759-AP9-AQ9 -> 66046.355 | AS9: =L9-AP9-AQ9-AR9 -> 70108.992 | AT9: 68887.652
B10: Corporate | C10: 211283.22 | D10: 220809.19 | E10: 223098.13 | F10: 226748.23 | G10: 224806.88 | H10: 224806.88 | I10: 227171.9 | J10: 236482.64 | K10: 250489.34 | L10: 252230.41 | R10: 54634.605 | S10: =109105.483-R10 -> 54470.878 | T10: =165253.832-S10-R10 -> 56148.349 | U10: =E10-T10-S10-R10 -> 57844.295 | V10: 57302.623 | W10: =111965.88-V10 -> 54663.257 | X10: =169637.433-W10-V10 -> 57671.553 | Y10: =F10-X10-W10-V10 -> 57110.794 | Z10: 53879.743 | AA10: =107835.737-Z10 -> 53955.994 | AB10: =164763.317-AA10-Z10 -> 56927.58 | AC10: =H10-AB10-AA10-Z10 -> 60043.564 | AD10: 54013.314 | AE10: =112125.32-AD10 -> 58112.006 | AF10: =169297.151-AE10-AD10 -> 57171.831 | AG10: =I10-AF10-AE10-AD10 -> 57874.749 | AH10: 53517.622 | AI10: =110884.785-AH10 -> 57367.163 | AJ10: =172022.101-AH10-AI10 -> 61137.316 | AK10: =J10-AJ10-AI10-AH10 -> 64460.541 | AL10: 53821.3 | AM10: =115750.386-AL10 -> 61929.086 | AN10: =182596.577-AL10-AM10 -> 66846.191 | AO10: =K10-AN10-AM10-AL10 -> 67892.765 | AP10: 61187.217 | AQ10: =120606.572-AP10 -> 59419.355 | AR10: =182406.406-AP10-AQ10 -> 61799.834 | AS10: =L10-AP10-AQ10-AR10 -> 69824.007 | AT10: 61938.237
B11: M. Serv.Peru | C11: 157552.71 | D11: 245329.15 | E11: 357503.12 | F11: 470592.48 | G11: 489053.02 | H11: 513507.4 | I11: 706075.74 | J11: 680167.74 | K11: 803030.91 | L11: 931642.21 | R11: 81205.092 | S11: =165931.915-R11 -> 84726.823 | T11: =258143.36-S11-R11 -> 92211.445 | U11: =E11-T11-S11-R11 -> 99359.757 | V11: 104826.2 | W11: =216133.498-V11 -> 111307.3 | X11: =336376.699-W11-V11 -> 120243.2 | Y11: =F11-X11-W11-V11 -> 134215.78 | Z11: 110263.73 | AA11: =223731.28-Z11 -> 113467.55 | AB11: =351884.754-AA11-Z11 -> 128153.47 | AC11: =H11-AB11-AA11-Z11 -> 161622.65 | AD11: 135105.93 | AE11: =284362.522-AD11 -> 149256.59 | AF11: =442462.785-AE11-AD11 -> 158100.26 | AG11: =I11-AF11-AE11-AD11 -> 263612.95 | AH11: 172827.85 | AI11: =311215.676-AH11 -> 138387.82 | AJ11: =485298.351-AH11-AI11 -> 174082.68 | AK11: =J11-AJ11-AI11-AH11 -> 194869.39 | AL11: 178622.67 | AM11: =370058.286-AL11 -> 191435.62 | AN11: =572030.287-AL11-AM11 -> 201972 | AO11: =K11-AN11-AM11-AL11 -> 231000.62 | AP11: 236412.59 | AQ11: =478148.667-AP11 -> 241736.08 | AR11: =703047.342-AP11-AQ11 -> 224898.67 | AS11: =L11-AP11-AQ11-AR11 -> 228594.87 | AT11: 203282.11
B12: Other businesses | C12: 433833.29 | D12: 550595.88 | E12: 691718.68 | F12: 787552.79 | G12: 875725.2 | H12: 851270.81 | I12: 965676.63 | J12: 934634.36 | K12: 956928.75 | L12: 1146092.8 | R12: 146657.24 | S12: =304552.99-R12 -> 157895.75 | T12: =483823.735-S12-R12 -> 179270.75 | U12: =E12-T12-S12-R12 -> 207894.94 | V12: 184112.83 | W12: =376737.385-V12 -> 192624.55 | X12: =574697.108-W12-V12 -> 197959.72 | Y12: =F12-X12-W12-V12 -> 212855.68 | Z12: 205020.86 | AA12: =423276.832-Z12 -> 218255.97 | AB12: =644243.208-AA12-Z12 -> 220966.38 | AC12: =H12-AB12-AA12-Z12 -> 207027.6 | AD12: 199264.82 | AE12: =400609.626-AD12 -> 201344.81 | AF12: =616086.195-AE12-AD12 -> 215476.57 | AG12: =I12-AF12-AE12-AD12 -> 349590.43 | AH12: 217437.98 | AI12: =452471.234-AH12 -> 235033.26 | AJ12: =693779.017-AH12-AI12 -> 241307.78 | AK12: =J12-AJ12-AI12-AH12 -> 240855.34 | AL12: 231398.51 | AM12: =475486.58-AL12 -> 244088.07 | AN12: =713083.937-AL12-AM12 -> 237597.36 | AO12: =K12-AN12-AM12-AL12 -> 243844.81 | AP12: 251639.61 | AQ12: =517640.049-AP12 -> 266000.44 | AR12: =870171.263-AP12-AQ12 -> 352531.21 | AS12: =L12-AP12-AQ12-AR12 -> 275921.51 | AT12: 306268.15
B13: Withdrawals | C13: -336468.72 | D13: -446364.16 | E13: -592264.44 | F13: -726359.03 | G13: -819090.9 | H13: -809305.56 | I13: -798893.3 | J13: -860844.64 | K13: -885997.24 | L13: -1106564.7 | R13: -122902.77 | S13: =-255894.193-R13 -> -132991.43 | T13: =-408316.606-S13-R13 -> -152422.41 | U13: =E13-T13-S13-R13 -> -183947.84 | V13: -165724.89 | W13: =-343078.204-V13 -> -177353.32 | X13: =-528940.745-W13-V13 -> -185862.54 | Y13: =F13-X13-W13-V13 -> -197418.29 | Z13: -193185.76 | AA13: =-399201.281-Z13 -> -206015.52 | AB13: =-602436.522-AA13-Z13 -> -203235.24 | AC13: =H13-AB13-AA13-Z13 -> -206869.03 | AD13: -190664.12 | AE13: =-381599.87-AD13 -> -190935.75 | AF13: =-588265.489-AE13-AD13 -> -206665.62 | AG13: =I13-AF13-AE13-AD13 -> -210627.81 | AH13: -195398.66 | AI13: =-410115.288-AH13 -> -214716.62 | AJ13: =-637398.726-AH13-AI13 -> -227283.44 | AK13: =J13-AJ13-AI13-AH13 -> -223445.91 | AL13: -213882.81 | AM13: =-436961.443-AL13 -> -223078.63 | AN13: =-655097.2-AL13-AM13 -> -218135.76 | AO13: =K13-AN13-AM13-AL13 -> -230900.04 | AP13: -237352.67 | AQ13: =-489290.186-AP13 -> -251937.51 | AR13: =-822245.791-AP13-AQ13 -> -332955.6 | AS13: =L13-AP13-AQ13-AR13 -> -284318.93 | AT13: -294042.27
B14: Un-Assigned | L14: 549189.18 | AQ14: =485773.466-AP14 -> 485773.47 | AR14: =544708.577-AP14-AQ14 -> 58935.111 | AS14: =L14-AP14-AQ14-AR14 -> 4480.605
B15: Total Revenue | C15: =SUM(C8:C13) -> 1657770.4 | D15: =SUM(D8:D13) -> 1784612.7 | E15: =SUM(E8:E13) -> 1867697.1 | F15: =SUM(F8:F13) -> 1943071.2 | G15: =SUM(G8:G13) -> 1913174.3 | H15: =SUM(H8:H13) -> 1922959.6 | I15: =SUM(I8:I13) -> 2197543.8 | J15: =SUM(J8:J13) -> 2147484.4 | K15: =SUM(K8:K13) -> 2460119.4 | L15: =SUM(L8:L14) -> 3137709.6 | R15: =SUM(R8:R13) -> 459463.63 | S15: =SUM(S8:S13) -> 456836.15 | T15: =SUM(T8:T13) -> 467901.28 | U15: =SUM(U8:U13) -> 483496.02 | V15: =SUM(V8:V13) -> 473615.34 | W15: =SUM(W8:W13) -> 478730.78 | X15: =SUM(X8:X13) -> 479906.64 | Y15: =SUM(Y8:Y13) -> 510818.44 | ... AP15: =SUM(AP8:AP13) -> 649940.8 | AQ15: =SUM(AQ8:AQ14) -> 1149567.3 | AR15: =SUM(AR8:AR14) -> 695595.45 | AS15: =SUM(AS8:AS14) -> 642606.03 | AT15: =SUM(AT8:AT13) -> 613338.3
B17: check | C17: =C15-Model!C7 -> 0 | D17: =D15-Model!D7 -> 0 | E17: =E15-Model!E7 -> 0 | F17: =F15-Model!F7 -> 0 | G17: =G15-Model!G7 -> 0 | H17: =H15-(Model!G7+Model!G9+Model!G14) -> 0 | I17: =I15-(Model!H7+Model!H9+Model!H14) -> 1 | J17: =J15-(Model!I7+Model!I9+Model!I14) -> 0 | K17: =K15-(Model!J7+Model!J9+Model!J14) -> 0 | L17: =L15-(Model!K7+Model!K9+Model!K14) -> 0.044 | R17: =R15-Model!Q7 -> 0 | S17: =S15-Model!R7 -> 0 | T17: =T15-Model!S7 -> 0 | U17: =U15-Model!T7 -> 0 | V17: =V15-Model!U7 -> 0 | W17: =W15-Model!V7 -> 0 | X17: =X15-Model!W7 -> 0 | Y17: =Y15-Model!X7 -> 0 | ... AB17: =AB15-Model!AA7 -> 0 | AD17: =AD15-(Model!AC7+Model!AC9+Model!AC14) -> 0 | AE17: =AE15-(Model!AD7+Model!AD9+Model!AD14) -> 0 | AF17: =AF15-(Model!AE7+Model!AE9+Model!AE14) -> 0 | AG17: =AG15-(Model!AF7+Model!AF9+Model!AF14) -> 1 | AH17: =AH15-(Model!AG7+Model!AG9+Model!AG14) -> 0 | AI17: =AI15-(Model!AH7+Model!AH9+Model!AH14) -> 0 | AJ17: =AJ15-(Model!AI7+Model!AI9+Model!AI14) -> 0 | AK17: =AK15-(Model!AJ7+Model!AJ9+Model!AJ14) -> 0 | ... AT17: =AT15-(Model!AS7+Model!AS9+Model!AS14) -> 0
B19: Revenue by Segments
B20: Consumer | M20: 1069314 | N20: 1174516 | O20: 1259066.9 | P20: =SUM(BC20:BF20) -> 1291499.1 | AQ20: 557472.17 | AR20: =821812.028-AQ20 -> 264339.86 | AS20: =1099806.956-AR20-AQ20-AP20 -> 277994.93 | AT20: 267004.43 | AU20: 528132.27 | AV20: =785819.121-AU20 -> 257686.85 | AW20: =1069313.998-AV20-AU20-AT20 -> 16490.449 | AX20: 275362.65 | AY20: =561627.796-AX20 -> 286265.14 | AZ20: =850184.207-AY20-AX20 -> 288556.41 | BA20: =N20-(AZ20+AY20+AX20) -> 324331.79 | BB20: 305177.14 | BC20: =603697.209-BB20 -> 298520.07 | BD20: =913447.031-BC20-BB20 -> 309749.82 | BE20: =O20-(BD20+BC20+BB20) -> 345619.92 | BF20: 337609.26
B21: B2B'Enterprise | M21: 425230.36 | N21: 454475.62 | O21: 471205.43 | P21: =SUM(BC21:BF21) -> 474783.26 | AQ21: 197227.38 | AR21: =298696.858-AQ21 -> 101469.48 | AS21: =409101.469-AR21-AQ21-AP21 -> 110404.61 | AT21: 103643.74 | AU21: 210945.58 | AV21: =311684.315-AU21 -> 100738.74 | AW21: =425230.358-AV21-AU21-AT21 -> 9902.305 | AX21: 107373.44 | AY21: =218317.691-AX21 -> 110944.25 | AZ21: =328985.203-AY21-AX21 -> 110667.51 | BA21: =N21-(AZ21+AY21+AX21) -> 125490.42 | BB21: 114922.49 | BC21: =232731.801-BB21 -> 117809.31 | BD21: =351039.001-BC21-BB21 -> 118307.2 | BE21: =O21-(BD21+BC21+BB21) -> 120166.43 | BF21: 118500.32
B22: Digital Business | M22: 121639.04 | N22: 127797.15 | O22: 136124.7 | P22: =SUM(BC22:BF22) -> 134910.05 | AQ22: 52536.599 | AR22: =78913.308-AQ22 -> 26376.709 | AS22: =108441.696-AR22-AQ22-AP22 -> 29528.388 | AT22: 27182.152 | AU22: 59656.763 | AV22: =88574.627-AU22 -> 28917.864 | AW22: =121639.036-AV22-AU22-AT22 -> 5882.257 | AX22: 30061.328 | AY22: =61330.209-AX22 -> 31268.881 | AZ22: =92899.209-AY22-AX22 -> 31569 | BA22: =N22-(AZ22+AY22+AX22) -> 34897.938 | BB22: 31665.012 | BC22: =63589.388-BB22 -> 31924.376 | BD22: =96069.253-BC22-BB22 -> 32479.865 | BE22: =O22-(BD22+BC22+BB22) -> 40055.446 | BF22: 30450.363
B23: M. Serv.Peru | M23: 848160.32 | N23: 956750.19 | O23: 1087917.5 | P23: =SUM(BC23:BF23) -> 1107143 | AQ23: 474140.88 | AR23: =703047.342-AQ23 -> 228906.46 | AS23: =931590.085-AR23-AQ23-AP23 -> 228542.74 | AT23: 203282.11 | AU23: 404276.06 | AV23: =620406.788-AU23 -> 216130.72 | AW23: =848160.321-AV23-AU23-AT23 -> 24471.418 | AX23: 234775.24 | AY23: =466234.522-AX23 -> 231459.28 | AZ23: =704668.514-AY23-AX23 -> 238433.99 | BA23: =N23-(AZ23+AY23+AX23) -> 252081.68 | BB23: 256299.7 | BC23: =513806.726-BB23 -> 257507.02 | BD23: =786777.496-BC23-BB23 -> 272970.77 | BE23: =O23-(BD23+BC23+BB23) -> 301139.97 | BF23: 275525.25
B24: Other businesses | M24: 1248089.6 | N24: 1242740 | O24: 1353541.6 | P24: =SUM(BC24:BF24) -> 1367744.8 | AQ24: 482444.25 | AR24: =870171.263-AQ24 -> 387727.01 | AS24: =1158491.777-AR24-AQ24-AP24 -> 288320.51 | AT24: 306268.15 | AU24: 615537.35 | AV24: =931413.902-AU24 -> 315876.55 | AW24: =1248089.636-AV24-AU24-AT24 -> 10407.588 | AX24: 304515.51 | AY24: =620990.349-AX24 -> 316474.84 | AZ24: =931185.302-AY24-AX24 -> 310194.95 | BA24: =N24-(AZ24+AY24+AX24) -> 311554.73 | BB24: 323318.58 | BC24: =662202.271-BB24 -> 338883.69 | BD24: =1001147.473-BC24-BB24 -> 338945.2 | BE24: =O24-(BD24+BC24+BB24) -> 352394.11 | BF24: 337521.75
B25: Un-Assigned | M25: 52251.177 | N25: 4227.887 | O25: 0 | P25: =SUM(BC25:BF25) -> -1411.434 | AQ25: 489781.26 | AR25: =549080.439-AQ25 -> 59299.184 | AS25: =536842.311-AR25-AQ25-AP25 -> -12238.128 | AT25: 0 | AU25: 0 | AV25: =0-AU25 -> 0 | AW25: =52251.177-AV25-AU25-AT25 -> 52251.177 | AX25: 0 | AY25: =0-AX25 -> 0 | AZ25: =0-AY25-AX25 -> 0 | BA25: =N25-(AZ25+AY25+AX25) -> 4227.887 | BB25: 1411.434 | BC25: =1411.434-BB25 -> 0 | BD25: =1411.434 -BC25-BB25 -> 0 | BE25: =O25-(BD25+BC25+BB25) -> -1411.434 | BF25: 0
B26: Withdrawals | M26: -1191542.6 | N26: -1195746.6 | O26: -1275555.1 | P26: =SUM(BC26:BF26) -> -1291400.3 | AQ26: -454094.39 | AR26: =-826617.654-AQ26 -> -372523.26 | AS26: =-1106564.722-AR26-AQ26-AP26 -> -279947.07 | AT26: -294042.27 | AU26: -587486.8 | AV26: =-889399.237-AU26 -> -301912.43 | AW26: =-1191542.603-AV26-AU26-AT26 -> -8101.092 | AX26: -287444.81 | AY26: =-583434.31-AX26 -> -295989.5 | AZ26: =-889411.817-AY26-AX26 -> -305977.51 | BA26: =N26-(AZ26+AY26+AX26) -> -306334.79 | BB26: -308179.14 | BC26: =-629806.045-BB26 -> -321626.91 | BD26: =-954705.731-BC26-BB26 -> -324899.69 | BE26: =O26-(BD26+BC26+BB26) -> -320849.35 | BF26: -324024.4
B27: Total Revenue | C27: =SUM(C20:C25) -> 0 | D27: =SUM(D20:D25) -> 0 | E27: =SUM(E20:E25) -> 0 | F27: =SUM(F20:F25) -> 0 | G27: =SUM(G20:G25) -> 0 | H27: =SUM(H20:H25) -> 0 | I27: =SUM(I20:I25) -> 0 | J27: =SUM(J20:J25) -> 0 | K27: =SUM(K20:K25) -> 0 | L27: =SUM(L20:L26) -> 0 | M27: =SUM(M20:M26) -> 2573141.9 | N27: =SUM(N20:N26) -> 2764760.3 | O27: =SUM(O20:O26) -> 3032301.1 | P27: =SUM(P20:P26) -> 3083268.4 | R27: =SUM(R20:R25) -> 0 | S27: =SUM(S20:S25) -> 0 | T27: =SUM(T20:T25) -> 0 | U27: =SUM(U20:U25) -> 0 | V27: =SUM(V20:V25) -> 0 | W27: =SUM(W20:W25) -> 0 | X27: =SUM(X20:X25) -> 0 | Y27: =SUM(Y20:Y25) -> 0 | ... AP27: =SUM(AP20:AP25) -> 0 | AQ27: =SUM(AQ20:AQ26) -> 1799508.1 | AR27: =SUM(AR20:AR26) -> 695595.45 | AS27: =SUM(AS20:AS26) -> 642605.99 | AT27: =SUM(AT20:AT26) -> 613338.3 | AU27: =SUM(AU20:AU26) -> 1231061.2 | AV27: =SUM(AV20:AV26) -> 617438.3 | AW27: =SUM(AW20:AW26) -> 111304.1 | AX27: =SUM(AX20:AX26) -> 664643.37 | ... BF27: =SUM(BF20:BF26) -> 775582.55
B28: check | M28: =M27-(Model!L7+Model!L9+Model!L14) -> 0 | N28: =N27-(Model!M7+Model!M9+Model!M14) -> 0 | O28: =O27-(Model!N7+Model!N9+Model!N14) -> 0 | P28: =P27-(Model!O7+Model!O9+Model!O14) -> 0 | AY28: =AY27-(Model!AX7+Model!AX9+Model!AX14) -> 0 | AZ28: =AZ27-(Model!AY7+Model!AY9+Model!AY14) -> 0 | BA28: =BA27-(Model!AZ7+Model!AZ9+Model!AZ14) -> 0 | BB28: =BB27-(Model!BA7+Model!BA9+Model!BA14) -> 0 | BC28: =BC27-(Model!BB7+Model!BB9+Model!BB14) -> 0 | BD28: =BD27-(Model!BC7+Model!BC9+Model!BC14) -> 0 | BE28: =BE27-(Model!BD7+Model!BD9+Model!BD14) -> 0 | BF28: =BF27-(Model!BE7+Model!BE9+Model!BE14) -> 0
B30: Revenue by Segments (Share %)
B31: Consumer | M31: =M20/M$27 -> 0.41556744 | N31: =N20/N$27 -> 0.42481658 | O31: =O20/O$27 -> 0.41521832 | P31: =P20/P$27 -> 0.41887339 | AQ31: =AQ20/AQ$27 -> 0.30979141 | AR31: =AR20/AR$27 -> 0.38001954 | AS31: =AS20/AS$27 -> 0.43260557 | AT31: =AT20/AT$27 -> 0.43532978 | AU31: =AU20/AU$27 -> 0.42900569 | AV31: =AV20/AV$27 -> 0.41734834 | AW31: =AW20/AW$27 -> 0.1481567 | AX31: =AX20/AX$27 -> 0.41430136 | ... BF31: =BF20/BF$27 -> 0.43529765
B32: B2B'Enterprise | M32: =M21/M$27 -> 0.16525725 | N32: =N21/N$27 -> 0.16438157 | O32: =O21/O$27 -> 0.15539533 | P32: =P21/P$27 -> 0.153987 | AQ32: =AQ21/AQ$27 -> 0.10960071 | AR32: =AR21/AR$27 -> 0.14587427 | AS32: =AS21/AS$27 -> 0.17180763 | AT32: =AT21/AT$27 -> 0.16898299 | AU32: =AU21/AU$27 -> 0.17135263 | AV32: =AV21/AV$27 -> 0.16315596 | AW32: =AW21/AW$27 -> 0.088966218 | AX32: =AX21/AX$27 -> 0.16155046 | ... BF32: =BF21/BF$27 -> 0.1527888
B33: Digital Business | M33: =M22/M$27 -> 0.047272572 | N33: =N22/N$27 -> 0.046223591 | O33: =O22/O$27 -> 0.044891552 | P33: =P22/P$27 -> 0.043755533 | AQ33: =AQ22/AQ$27 -> 0.029194977 | AR33: =AR22/AR$27 -> 0.037919611 | AS33: =AS22/AS$27 -> 0.045951 | AT33: =AT22/AT$27 -> 0.044318367 | AU33: =AU22/AU$27 -> 0.048459624 | AV33: =AV22/AV$27 -> 0.046835229 | AW33: =AW22/AW$27 -> 0.052848519 | AX33: =AX22/AX$27 -> 0.045229261 | ... BF33: =BF22/BF$27 -> 0.039261279
B34: M. Serv.Peru | M34: =M23/M$27 -> 0.3296205 | N34: =N23/N$27 -> 0.34605177 | O34: =O23/O$27 -> 0.35877621 | P34: =P23/P$27 -> 0.35908098 | AQ34: =AQ23/AQ$27 -> 0.2634836 | AR34: =AR23/AR$27 -> 0.32907988 | AS34: =AS23/AS$27 -> 0.35564988 | AT34: =AT23/AT$27 -> 0.33143554 | AU34: =AU23/AU$27 -> 0.32839639 | AV34: =AV23/AV$27 -> 0.35004425 | AW34: =AW23/AW$27 -> 0.21986088 | AX34: =AX23/AX$27 -> 0.35323491 | ... BF34: =BF23/BF$27 -> 0.35524942
B35: Other businesses | M35: =M24/M$27 -> 0.485045 | N35: =N24/N$27 -> 0.44949287 | O35: =O24/O$27 -> 0.44637441 | P35: =P24/P$27 -> 0.44360224 | AQ35: =AQ24/AQ$27 -> 0.26809784 | AR35: =AR24/AR$27 -> 0.55740303 | AS35: =AS24/AS$27 -> 0.44867387 | AT35: =AT24/AT$27 -> 0.49934619 | AU35: =AU24/AU$27 -> 0.50000548 | AV35: =AV24/AV$27 -> 0.51159209 | AW35: =AW24/AW$27 -> 0.09350588 | AX35: =AX24/AX$27 -> 0.45816376 | ... BF35: =BF24/BF$27 -> 0.43518482
B36: Un-Assigned | M36: =M25/M$27 -> 0.020306372 | N36: =N25/N$27 -> 0.0015292056 | O36: =O25/O$27 -> 0 | P36: =P25/P$27 -> -0.00045777202 | AQ36: =AQ25/AQ$27 -> 0.27217507 | AR36: =AR25/AR$27 -> 0.085249529 | AS36: =AS25/AS$27 -> -0.019044528 | AT36: =AT25/AT$27 -> 0 | AU36: =AU25/AU$27 -> 0 | AV36: =AV25/AV$27 -> 0 | AW36: =AW25/AW$27 -> 0.46944521 | AX36: =AX25/AX$27 -> 0 | ... BF36: =BF25/BF$27 -> 0
B37: Withdrawals | M37: =M26/M$27 -> -0.46306913 | N37: =N26/N$27 -> -0.43249558 | O37: =O26/O$27 -> -0.42065582 | P37: =P26/P$27 -> -0.41884137 | AQ37: =AQ26/AQ$27 -> -0.25234362 | AR37: =AR26/AR$27 -> -0.53554586 | AS37: =AS26/AS$27 -> -0.43564342 | AT37: =AT26/AT$27 -> -0.47941286 | AU37: =AU26/AU$27 -> -0.47721981 | AV37: =AV26/AV$27 -> -0.48897587 | AW37: =AW26/AW$27 -> -0.072783409 | AX37: =AX26/AX$27 -> -0.43247976 | ... BF37: =BF26/BF$27 -> -0.41778197
B38: Total Revenue | M38: =SUM(M31:M37) -> 1 | N38: =SUM(N31:N37) -> 1 | O38: =SUM(O31:O37) -> 1 | P38: =SUM(P31:P37) -> 1 | AQ38: =SUM(AQ31:AQ37) -> 1 | AR38: =SUM(AR31:AR37) -> 1 | AS38: =SUM(AS31:AS37) -> 1 | AT38: =SUM(AT31:AT37) -> 1 | AU38: =SUM(AU31:AU37) -> 1 | AV38: =SUM(AV31:AV37) -> 1 | AW38: =SUM(AW31:AW37) -> 1 | AX38: =SUM(AX31:AX37) -> 1 | ... BF38: =SUM(BF31:BF37) -> 1
B40: Revenue by Segments (YoY % Growth)
B41: Consumer | N41: =N20/M20-1 -> 0.098382701 | O41: =O20/N20-1 -> 0.07198791 | AU41: =AU20/AQ20-1 -> -0.052630249 | AV41: =AV20/AR20-1 -> -0.025168387 | AW41: =AW20/AS20-1 -> -0.94068076 | AX41: =AX20/AT20-1 -> 0.031303698 | AY41: =AY20/AU20-1 -> -0.45796695 | AZ41: =AZ20/AV20-1 -> 0.11979485 | BA41: =BA20/AW20-1 -> 18.667857 | BB41: =BB20/AX20-1 -> 0.10827352 | ... BF41: =BF20/BB20-1 -> 0.10627311
B42: B2B'Enterprise | N42: =N21/M21-1 -> 0.068775111 | O42: =O21/N21-1 -> 0.036811239 | AU42: =AU21/AQ21-1 -> 0.069555247 | AV42: =AV21/AR21-1 -> -0.0072015939 | AW42: =AW21/AS21-1 -> -0.91030895 | AX42: =AX21/AT21-1 -> 0.035985811 | AY42: =AY21/AU21-1 -> -0.47406221 | AZ42: =AZ21/AV21-1 -> 0.098559632 | BA42: =BA21/AW21-1 -> 11.672849 | BB42: =BB21/AX21-1 -> 0.07030652 | ... BF42: =BF21/BB21-1 -> 0.03113253
B43: Digital Business | N43: =N22/M22-1 -> 0.050626108 | O43: =O22/N22-1 -> 0.065162268 | AU43: =AU22/AQ22-1 -> 0.13552769 | AV43: =AV22/AR22-1 -> 0.096340866 | AW43: =AW22/AS22-1 -> -0.80079316 | AX43: =AX22/AT22-1 -> 0.10592156 | AY43: =AY22/AU22-1 -> -0.47585354 | AZ43: =AZ22/AV22-1 -> 0.091678141 | BA43: =BA22/AW22-1 -> 4.9327462 | BB43: =BB22/AX22-1 -> 0.053347078 | ... BF43: =BF22/BB22-1 -> -0.038359341
B44: M. Serv.Peru | N44: =N23/M23-1 -> 0.12802989 | O44: =O23/N23-1 -> 0.13709668 | AU44: =AU23/AQ23-1 -> -0.14735033 | AV44: =AV23/AR23-1 -> -0.05581205 | AW44: =AW23/AS23-1 -> -0.89292411 | AX44: =AX23/AT23-1 -> 0.15492326 | AY44: =AY23/AU23-1 -> -0.42747221 | AZ44: =AZ23/AV23-1 -> 0.10319341 | BA44: =BA23/AW23-1 -> 9.3010655 | BB44: =BB23/AX23-1 -> 0.09168114 | ... BF44: =BF23/BB23-1 -> 0.075011967
B45: Other businesses | N45: =N24/M24-1 -> -0.0042862314 | O45: =O24/N24-1 -> 0.089159075 | AU45: =AU24/AQ24-1 -> 0.27587248 | AV45: =AV24/AR24-1 -> -0.18531197 | AW45: =AW24/AS24-1 -> -0.96390271 | AX45: =AX24/AT24-1 -> -0.005722567 | AY45: =AY24/AU24-1 -> -0.48585599 | AZ45: =AZ24/AV24-1 -> -0.017986773 | BA45: =BA24/AW24-1 -> 28.935345 | BB45: =BB24/AX24-1 -> 0.061747516 | ... BF45: =BF24/BB24-1 -> 0.043929328
B46: Un-Assigned | N46: =N25/M25-1 -> -0.91908533 | O46: =O25/N25-1 -> -1 | AU46: =AU25/AQ25-1 -> -1 | AV46: =AV25/AR25-1 -> -1 | AW46: =AW25/AS25-1 -> -5.26954 | AX46: =AX25/AT25-1 -> #DIV/0! | AY46: =AY25/AU25-1 -> #DIV/0! | AZ46: =AZ25/AV25-1 -> #DIV/0! | BA46: =BA25/AW25-1 -> -0.91908533 | BB46: =BB25/AX25-1 -> #DIV/0! | ... BF46: =BF25/BB25-1 -> -1
B47: Withdrawals | N47: =N26/M26-1 -> 0.0035282045 | O47: =O26/N26-1 -> 0.066743636 | AU47: =AU26/AQ26-1 -> 0.29375481 | AV47: =AV26/AR26-1 -> -0.18954744 | AW47: =AW26/AS26-1 -> -0.97106206 | AX47: =AX26/AT26-1 -> -0.022437141 | AY47: =AY26/AU26-1 -> -0.49617676 | AZ47: =AZ26/AV26-1 -> 0.013464414 | BA47: =BA26/AW26-1 -> 36.814012 | BB47: =BB26/AX26-1 -> 0.072133267 | ... BF47: =BF26/BB26-1 -> 0.051415755
B48: Total Revenue | N48: =N27/M27-1 -> 0.074468629 | O48: =O27/N27-1 -> 0.096768166 | AU48: =AU27/AQ27-1 -> -0.31589017 | AV48: =AV27/AR27-1 -> -0.11236006 | AW48: =AW27/AS27-1 -> -0.82679262 | AX48: =AX27/AT27-1 -> 0.08364888 | AY48: =AY27/AU27-1 -> -0.44728753 | AZ48: =AZ27/AV27-1 -> 0.090707136 | BA48: =BA27/AW27-1 -> 5.7046016 | BB48: =BB27/AX27-1 -> 0.090231638 | ... BF48: =BF27/BB27-1 -> 0.07033708
B51: EBITDA by Segments
B52: Consumer | M52: 362876.17 | N52: 386510.75 | O52: 381081.14 | P52: =SUM(BC52:BF52) -> 387343.05 | AQ52: 201489.18 | AR52: =292749.498 -AQ52 -> 91260.313 | AS52: =385590.81-AR52-AQ52-AP52 -> 92841.312 | AT52: 88154.368 | AU52: 182489.39 | AV52: =274302.549-AU52 -> 91813.162 | AW52: =362876.166-AV52-AU52-AT52 -> 419.249 | AX52: 84547.736 | AY52: =177633.834-AX52 -> 93086.098 | AZ52: =277689.8-AY52-AX52 -> 100055.97 | BA52: =N52-AZ52-AY52-AX52 -> 108820.95 | BB52: 94773.643 | BC52: =184996.601-BB52 -> 90222.958 | BD52: =285132.099-BC52-BB52 -> 100135.5 | BE52: =O52-(BD52+BC52+BB52) -> 95949.04 | BF52: 101035.55
B53: B2B'Enterprise | M53: 136529.41 | N53: 150837.43 | O53: 155373.18 | P53: =SUM(BC53:BF53) -> 161056.62 | AQ53: 77461.273 | AR53: =113054.498-AQ53 -> 35593.225 | AS53: =149848.486-AR53-AQ53-AP53 -> 36793.988 | AT53: 30728.738 | AU53: 68090.013 | AV53: =99302.527-AU53 -> 31212.514 | AW53: =136529.407-AV53-AU53-AT53 -> 6498.142 | AX53: 35167.294 | AY53: =70494.539-AX53 -> 35327.245 | AZ53: =108260.199-AY53-AX53 -> 37765.66 | BA53: =N53-AZ53-AY53-AX53 -> 42577.229 | BB53: 34418.045 | BC53: =75406.46-BB53 -> 40988.415 | BD53: =118065.243-BC53-BB53 -> 42658.783 | BE53: =O53-(BD53+BC53+BB53) -> 37307.942 | BF53: 40101.476
B54: Digital Business | M54: 106.249 | N54: -10858.786 | O54: -19170.799 | P54: =SUM(BC54:BF54) -> -17759.704 | AQ54: 781.679 | AR54: =541.903-AQ54 -> -239.776 | AS54: =3259.167-AR54-AQ54-AP54 -> 2717.264 | AT54: -3131.931 | AU54: -498.455 | AV54: =64.664-AU54 -> 563.119 | AW54: =106.249-AV54-AU54-AT54 -> 3173.516 | AX54: -3168.784 | AY54: =-3030.51-AX54 -> 138.274 | AZ54: =-6546.271-AY54-AX54 -> -3515.761 | BA54: =N54-AZ54-AY54-AX54 -> -4312.515 | BB54: -7081.171 | BC54: =-11250.866-BB54 -> -4169.695 | BD54: =-16542.444-BC54-BB54 -> -5291.578 | BE54: =O54-(BD54+BC54+BB54) -> -2628.355 | BF54: -5670.076
B55: M. Serv.Peru | M55: 165431.64 | N55: 238229.67 | O55: 275170.38 | P55: =SUM(BC55:BF55) -> 283703.52 | AQ55: 87151.464 | AR55: =128404.37-AQ55 -> 41252.906 | AS55: =175072.019-AR55-AQ55-AP55 -> 46667.649 | AT55: 7322.458 | AU55: 54466.168 | AV55: =109780.727-AU55 -> 55314.559 | AW55: =165431.638-AV55-AU55-AT55 -> 48328.453 | AX55: 61427.771 | AY55: =120714.268-AX55 -> 59286.497 | AZ55: =183403.201-AY55-AX55 -> 62688.933 | BA55: =N55-AZ55-AY55-AX55 -> 54826.471 | BB55: 62529.779 | BC55: =127023.501-BB55 -> 64493.722 | BD55: =195354.08-BC55-BB55 -> 68330.579 | BE55: =O55-(BD55+BC55+BB55) -> 79816.298 | BF55: 71062.924
B56: Other businesses | M56: 45877.661 | N56: 19887.863 | O56: 43077.077 | P56: =SUM(BC56:BF56) -> 42500.378 | AQ56: 21947.557 | AR56: =33507.672-AQ56 -> 11560.115 | AS56: =39723.104-AR56-AQ56-AP56 -> 6215.432 | AT56: 9143.223 | AU56: 21110.493 | AV56: =32452.031-AU56 -> 11341.538 | AW56: =45877.661-AV56-AU56-AT56 -> 4282.407 | AX56: 9852.91 | AY56: =22036.2-AX56 -> 12183.29 | AZ56: =19780.638-AY56-AX56 -> -2255.562 | BA56: =N56-AZ56-AY56-AX56 -> 107.225 | BB56: 7553.464 | BC56: =18684.708-BB56 -> 11131.244 | BD56: =26477.813-BC56-BB56 -> 7793.105 | BE56: =O56-(BD56+BC56+BB56) -> 16599.264 | BF56: 6976.765
B57: Un-Assigned | M57: 52251.177 | N57: 4227.887 | O57: 0 | P57: =SUM(BC57:BF57) -> -1411.434 | AQ57: 488567.07 | AR57: =542874.532-AQ57 -> 54307.467 | AS57: =530636.403-AR57-AQ57-AP57 -> -12238.129 | AT57: 0 | AU57: 0 | AV57: =0-AU57 -> 0 | AW57: =52251.177-AV57-AU57-AT57 -> 52251.177 | AX57: 0 | AY57: =0-AX57 -> 0 | AZ57: =0-AY57-AX57 -> 0 | BA57: =N57-AZ57-AY57-AX57 -> 4227.887 | BB57: 1411.434 | BC57: =1411.434-BB57 -> 0 | BD57: =1411.434-BC57-BB57 -> 0 | BE57: =O57-(BD57+BC57+BB57) -> -1411.434 | BF57: 0
B58: Withdrawals | M58: -510.127 | N58: -221.917 | O58: -57.884 | P58: =SUM(BC58:BF58) -> -47.634 | AQ58: -1016.668 | AR58: =-1570.494-AQ58 -> -553.826 | AS58: =-2117.095-AR58-AQ58-AP58 -> -546.601 | AT58: -93.598 | AU58: -301.007 | AV58: =-393.364-AU58 -> -92.357 | AW58: =-510.127-AV58-AU58-AT58 -> -23.165 | AX58: -56.551 | AY58: =-141.308-AX58 -> -84.757 | AZ58: =-172.024-AY58-AX58 -> -30.716 | BA58: =N58-AZ58-AY58-AX58 -> -49.893 | BB58: -39.796 | BC58: =-57.883-BB58 -> -18.087 | BD58: =-57.882-BC58-BB58 -> 0.001 | BE58: =O58-(BD58+BC58+BB58) -> -0.002 | BF58: -29.546
B59: Total EBITDA | C59: =SUM(C52:C57) -> 0 | D59: =SUM(D52:D57) -> 0 | E59: =SUM(E52:E57) -> 0 | F59: =SUM(F52:F57) -> 0 | G59: =SUM(G52:G57) -> 0 | H59: =SUM(H52:H57) -> 0 | I59: =SUM(I52:I57) -> 0 | J59: =SUM(J52:J57) -> 0 | K59: =SUM(K52:K57) -> 0 | L59: =SUM(L52:L58) -> 0 | M59: =SUM(M52:M58) -> 762562.17 | N59: =SUM(N52:N58) -> 788612.9 | O59: =SUM(O52:O58) -> 835473.1 | P59: =SUM(P52:P58) -> 855384.79 | R59: =SUM(R52:R57) -> 0 | S59: =SUM(S52:S57) -> 0 | T59: =SUM(T52:T57) -> 0 | U59: =SUM(U52:U57) -> 0 | V59: =SUM(V52:V57) -> 0 | W59: =SUM(W52:W57) -> 0 | X59: =SUM(X52:X57) -> 0 | Y59: =SUM(Y52:Y57) -> 0 | ... AP59: =SUM(AP52:AP57) -> 0 | AQ59: =SUM(AQ52:AQ58) -> 876381.56 | AR59: =SUM(AR52:AR58) -> 233180.42 | AS59: =SUM(AS52:AS58) -> 172450.92 | AT59: =SUM(AT52:AT58) -> 132123.26 | AU59: =SUM(AU52:AU58) -> 325356.6 | AV59: =SUM(AV52:AV58) -> 190152.54 | AW59: =SUM(AW52:AW58) -> 114929.78 | AX59: =SUM(AX52:AX58) -> 187770.38 | ... BF59: =SUM(BF52:BF58) -> 213477.1
B60: check | M60: =M59-Model!L48 -> 0 | N60: =N59-Model!M48 -> 0 | O60: =O59-Model!N48 -> 0 | P60: =P59-Model!O48 -> 0 | AX60: =AX59-Model!AW48 -> 0.376 | AY60: =AY59-Model!AX48 -> -0.353 | AZ60: =AZ59-Model!AY48 -> -0.48 | BA60: =BA59-Model!AZ48 -> 0.457 | BB60: =BB59-Model!BA48 -> 0 | BC60: =BC59-Model!BB48 -> -0.045 | BD60: =BD59-Model!BC48 -> 0.388 | BE60: =BE59-Model!BD48 -> -0.343 | BF60: =BF59-Model!BE48 -> 0
B62: EBITDA Margin
B63: Consumer | M63: =M52/M20 -> 0.33935417 | N63: =N52/N20 -> 0.32908088 | O63: =O52/O20 -> 0.30266948 | P63: =P52/P20 -> 0.2999174 | AQ63: =AQ52/AQ20 -> 0.36143362 | AR63: =AR52/AR20 -> 0.34523856 | AU63: =AU52/AU20 -> 0.34553728 | AV63: =AV52/AV20 -> 0.35629742 | AW63: =AW52/AW20 -> 0.025423747 | AX63: =AX52/AX20 -> 0.3070414 | AY63: =AY52/AY20 -> 0.32517441 | AZ63: =AZ52/AZ20 -> 0.34674664 | BA63: =BA52/BA20 -> 0.33552355 | BB63: =BB52/BB20 -> 0.31055289 | ... BF63: =BF52/BF20 -> 0.29926772
B64: B2B'Enterprise | M64: =M53/M21 -> 0.32107164 | N64: =N53/N21 -> 0.33189333 | O64: =O53/O21 -> 0.32973555 | P64: =P53/P21 -> 0.33922134 | AQ64: =AQ53/AQ21 -> 0.39275112 | AR64: =AR53/AR21 -> 0.35077764 | AU64: =AU53/AU21 -> 0.32278474 | AV64: =AV53/AV21 -> 0.30983626 | AW64: =AW53/AW21 -> 0.65622519 | AX64: =AX53/AX21 -> 0.32752321 | AY64: =AY53/AY21 -> 0.3184234 | AZ64: =AZ53/AZ21 -> 0.34125336 | BA64: =BA53/BA21 -> 0.33928669 | BB64: =BB53/BB21 -> 0.29948919 | ... BF64: =BF53/BF21 -> 0.33840816
B65: Digital Business | M65: =M54/M22 -> 0.00087347782 | N65: =N54/N22 -> -0.084968923 | O65: =O54/O22 -> -0.14083263 | P65: =P54/P22 -> -0.13164107 | AQ65: =AQ54/AQ22 -> 0.014878751 | AR65: =AR54/AR22 -> -0.0090904441 | AU65: =AU54/AU22 -> -0.0083553813 | AV65: =AV54/AV22 -> 0.01947305 | AW65: =AW54/AW22 -> 0.53950652 | AX65: =AX54/AX22 -> -0.10541065 | AY65: =AY54/AY22 -> 0.0044220962 | AZ65: =AZ54/AZ22 -> -0.11136751 | BA65: =BA54/BA22 -> -0.12357507 | BB65: =BB54/BB22 -> -0.22362761 | ... BF65: =BF54/BF22 -> -0.18620717
B66: M. Serv.Peru | M66: =M55/M23 -> 0.1950476 | N66: =N55/N23 -> 0.24899882 | O66: =O55/O23 -> 0.25293314 | P66: =P55/P23 -> 0.25624831 | AQ66: =AQ55/AQ23 -> 0.18380922 | AR66: =AR55/AR23 -> 0.1802173 | AU66: =AU55/AU23 -> 0.13472519 | AV66: =AV55/AV23 -> 0.25593103 | AW66: =AW55/AW23 -> 1.9748939 | AX66: =AX55/AX23 -> 0.26164501 | AY66: =AY55/AY23 -> 0.25614223 | AZ66: =AZ55/AZ23 -> 0.26291945 | BA66: =BA55/BA23 -> 0.21749487 | BB66: =BB55/BB23 -> 0.24397133 | ... BF66: =BF55/BF23 -> 0.25791801
B67: Other businesses | M67: =M56/M24 -> 0.036758306 | N67: =N56/N24 -> 0.016003237 | O67: =O56/O24 -> 0.031825455 | P67: =P56/P24 -> 0.031073326 | AQ67: =AQ56/AQ24 -> 0.045492421 | AR67: =AR56/AR24 -> 0.029815088 | AU67: =AU56/AU24 -> 0.034296039 | AV67: =AV56/AV24 -> 0.035904969 | AW67: =AW56/AW24 -> 0.41146969 | AX67: =AX56/AX24 -> 0.032356021 | AY67: =AY56/AY24 -> 0.038496867 | AZ67: =AZ56/AZ24 -> -0.0072714336 | BA67: =BA56/BA24 -> 0.00034416104 | BB67: =BB56/BB24 -> 0.023362295 | ... BF67: =BF56/BF24 -> 0.020670564
B68: Un-Assigned
B69: Withdrawals | M69: =M58/M26 -> 0.00042812317 | N69: =N58/N26 -> 0.00018558865 | O69: =O58/O26 -> 4.5379459e-05 | P69: =P58/P26 -> 3.6885541e-05 | AQ69: =AQ58/AQ26 -> 0.0022388913 | AR69: =AR58/AR26 -> 0.0014866884 | AU69: =AU58/AU26 -> 0.00051236385 | AV69: =AV58/AV26 -> 0.00030590658 | AW69: =AW58/AW26 -> 0.002859491 | AX69: =AX58/AX26 -> 0.0001967369 | AY69: =AY58/AY26 -> 0.00028635137 | AZ69: =AZ58/AZ26 -> 0.00010038646 | BA69: =BA58/BA26 -> 0.00016287082 | BB69: =BB58/BB26 -> 0.00012913269 | ... BF69: =BF58/BF26 -> 9.118449e-05
B70: Total EBITDA | M70: =M59/M27 -> 0.29635449 | N70: =N59/N27 -> 0.28523735 | O70: =O59/O27 -> 0.27552446 | P70: =P59/P27 -> 0.27742794 | AQ70: =AQ59/AQ27 -> 0.48701172 | AR70: =AR59/AR27 -> 0.3352242 | AU70: =AU59/AU27 -> 0.26428954 | AV70: =AV59/AV27 -> 0.3079701 | AW70: =AW59/AW27 -> 1.0325745 | AX70: =AX59/AX27 -> 0.28251298 | AY70: =AY59/AY27 -> 0.29384174 | AZ70: =AZ59/AZ27 -> 0.2891234 | BA70: =BA59/BA27 -> 0.27631149 | BB70: =BB59/BB27 -> 0.26712853 | ... BF70: =BF59/BF27 -> 0.27524742
B72: EBITDA by Segments
B73: Consumer | C73: 263564.34 | D73: 292310.47 | E73: 294604.66 | F73: 277863.51 | G73: 255132.1 | H73: 255132.1 | I73: 298449.83 | J73: 338072.78 | K73: 395954.57 | L73: 385590.81 | R73: 81857.437 | S73: =153998.455-R73 -> 72141.018 | T73: =226620.891-S73-R73 -> 72622.436 | U73: =E73-T73-S73-R73 -> 67983.774 | V73: 74098.458 | W73: =141532.298-V73 -> 67433.84 | X73: =210100.359-W73-V73 -> 68568.061 | Y73: =F73-X73-W73-V73 -> 67763.146 | Z73: 59483.194 | AA73: =118314.934-Z73 -> 58831.74 | AB73: =186093.19-AA73-Z73 -> 67778.256 | AC73: =G73-AB73-AA73-Z73 -> 69038.905 | AD73: 76204.405 | AE73: =144706.077-AD73 -> 68501.672 | AF73: =221669.101-AE73-AD73 -> 76963.024 | AG73: =I73-AF73-AE73-AD73 -> 76780.725 | AH73: 82342.012 | AI73: =161960.248-AH73 -> 79618.236 | AJ73: =246395.952-AH73-AI73 -> 84435.704 | AK73: =J73-AJ73-AI73-AH73 -> 91676.826 | AL73: 93880.784 | AM73: =195010.462-AL73 -> 101129.68 | AN73: =299586.926-AL73-AM73 -> 104576.46 | AO73: =K73-AN73-AM73-AL73 -> 96367.646 | AP73: 102466.53 | AQ73: =201489.185-AP73 -> 99022.659 | AR73: =292749.498-AP73-AQ73 -> 91260.313 | AS73: =L73-AP73-AQ73-AR73 -> 92841.312 | AT73: 88154.368
B74: Enterprise | C74: 97721.901 | D74: 108214.22 | E74: 113145.1 | F74: 113303.22 | G74: 118024.5 | H74: 118024.5 | I74: 115241.04 | J74: 106855.55 | K74: 111481.16 | L74: 95553.809 | R74: 29302.468 | S74: =57443.916-R74 -> 28141.448 | T74: =85491.313-S74-R74 -> 28047.397 | U74: =E74-T74-S74-R74 -> 27653.783 | V74: 28580.681 | W74: =57490.104-V74 -> 28909.423 | X74: =85847.866-W74-V74 -> 28357.762 | Y74: =F74-X74-W74-V74 -> 27455.356 | Z74: 31316.839 | AA74: =59789.867-Z74 -> 28473.028 | AB74: =88787.653-AA74-Z74 -> 28997.786 | AC74: =G74-AB74-AA74-Z74 -> 29236.848 | AD74: 30382.113 | AE74: =59454.677-AD74 -> 29072.564 | AF74: =87414.12-AE74-AD74 -> 27959.443 | AG74: =I74-AF74-AE74-AD74 -> 27826.921 | AH74: 26771.809 | AI74: =52505.648-AH74 -> 25733.839 | AJ74: =76938.238-AH74-AI74 -> 24432.59 | AK74: =J74-AJ74-AI74-AH74 -> 29917.312 | AL74: 26008.487 | AM74: =55963.385-AL74 -> 29954.898 | AN74: =85142.908-AL74-AM74 -> 29179.523 | AO74: =K74-AN74-AM74-AL74 -> 26338.253 | AP74: 24341.578 | AQ74: =48488.53-AP74 -> 24146.952 | AR74: =71413.085-AP74-AQ74 -> 22924.555 | AS74: =L74-AP74-AQ74-AR74 -> 24140.724 | AT74: 22924.176
B75: Corporate | C75: 56108.359 | D75: 70225.671 | E75: 80482.538 | F75: 84232.758 | G75: 82564.471 | H75: 82564.471 | I75: 80415.047 | J75: 75681.378 | K75: 74407.224 | L75: 57553.843 | R75: 17644.477 | S75: =37389.817-R75 -> 19745.34 | T75: =57869.867-S75-R75 -> 20480.05 | U75: =E75-T75-S75-R75 -> 22612.671 | V75: 18892.891 | W75: =39253.65-V75 -> 20360.759 | X75: =62366.67-W75-V75 -> 23113.02 | Y75: =F75-X75-W75-V75 -> 21866.088 | Z75: 18180.78 | AA75: =35852.722-Z75 -> 17671.942 | AB75: =57191.968-AA75-Z75 -> 21339.246 | AC75: =G75-AB75-AA75-Z75 -> 25372.503 | AD75: 18850.145 | AE75: =40157.966-AD75 -> 21307.821 | AF75: =59958.774-AE75-AD75 -> 19800.808 | AG75: =I75-AF75-AE75-AD75 -> 20456.273 | AH75: 16879.166 | AI75: =35649.516-AH75 -> 18770.35 | AJ75: =54016.743-AH75-AI75 -> 18367.227 | AK75: =J75-AJ75-AI75-AH75 -> 21664.635 | AL75: 13794.419 | AM75: =34775.897-AL75 -> 20981.478 | AN75: =52609.46-AL75-AM75 -> 17833.563 | AO75: =K75-AN75-AM75-AL75 -> 21797.764 | AP75: 11409.803 | AQ75: =29754.423-AP75 -> 18344.62 | AR75: =42183.316-AP75-AQ75 -> 12428.893 | AS75: =L75-AP75-AQ75-AR75 -> 15370.527 | AT75: 4672.631
B76: M. Serv.Peru | C76: -109519.04 | D76: -169059.64 | E76: -121488.58 | F76: -75997.619 | G76: -54121.317 | H76: -54121.317 | I76: 126475.61 | J76: 103609.01 | K76: 134019.25 | L76: 175072.02 | R76: -31442.947 | S76: =-66078.942-R76 -> -34635.995 | T76: =-93123.662-S76-R76 -> -27044.72 | U76: =E76-T76-S76-R76 -> -28364.919 | V76: -23864.521 | W76: =-50883.38-V76 -> -27018.859 | X76: =-67037.466-W76-V76 -> -16154.086 | Y76: =F76-X76-W76-V76 -> -8960.153 | Z76: -16202.54 | AA76: =-34026.74-Z76 -> -17824.2 | AB76: =-49718.179-AA76-Z76 -> -15691.439 | AC76: =G76-AB76-AA76-Z76 -> -4403.138 | AD76: 6131.822 | AE76: =18607.726-AD76 -> 12475.904 | AF76: =34559.476-AE76-AD76 -> 15951.75 | AG76: =I76-AF76-AE76-AD76 -> 91916.134 | AH76: 30006.807 | AI76: =51606.927-AH76 -> 21600.12 | AJ76: =77668.105-AH76-AI76 -> 26061.178 | AK76: =J76-AJ76-AI76-AH76 -> 25940.902 | AL76: 29593.025 | AM76: =64035.53-AL76 -> 34442.505 | AN76: =101577.983-AL76-AM76 -> 37542.453 | AO76: =K76-AN76-AM76-AL76 -> 32441.265 | AP76: 42257.882 | AQ76: =91159.253-AP76 -> 48901.371 | AR76: =128404.37-AP76-AQ76 -> 37245.117 | AS76: =L76-AP76-AQ76-AR76 -> 46667.649 | AT76: 7322.458
B77: Other businesses | C77: 62633.269 | D77: 55411.97 | E77: 58544.193 | F77: 38202.039 | G77: 25323.456 | H77: 25323.456 | I77: 149830.77 | J77: 62024.679 | K77: 58410.506 | L77: 27324.104 | R77: 11800.706 | S77: =25102.019-R77 -> 13301.313 | T77: =37020.744-S77-R77 -> 11918.725 | U77: =E77-T77-S77-R77 -> 21523.449 | V77: 12394.313 | W77: =21456.339-V77 -> 9062.026 | X77: =29752.999-W77-V77 -> 8296.66 | Y77: =F77-X77-W77-V77 -> 8449.04 | Z77: 6564.459 | AA77: =13634.323-Z77 -> 7069.864 | AB77: =18318.284-AA77-Z77 -> 4683.961 | AC77: =G77-AB77-AA77-Z77 -> 7005.172 | AD77: 6237.479 | AE77: =12530.044-AD77 -> 6292.565 | AF77: =19252.47-AE77-AD77 -> 6722.426 | AG77: =I77-AF77-AE77-AD77 -> 130578.3 | AH77: 17088.506 | AI77: =35598.429-AH77 -> 18509.923 | AJ77: =47480.3-AH77-AI77 -> 11881.871 | AK77: =J77-AJ77-AI77-AH77 -> 14544.379 | AL77: 14780.671 | AM77: =33014.334-AL77 -> 18233.663 | AN77: =48268.088-AL77-AM77 -> 15253.754 | AO77: =K77-AN77-AM77-AL77 -> 10142.418 | AP77: 9605.647 | AQ77: =20733.367-AP77 -> 11127.72 | AR77: =29779.99-AP77-AQ77 -> 9046.623 | AS77: =L77-AP77-AQ77-AR77 -> -2455.886 | AT77: 9143.224
B78: Withdrawals | C78: -358.801 | D78: -517.409 | E78: -507.177 | F78: -501.206 | G78: -2.407 | H78: -2.407 | I78: -1.134 | J78: -2011.503 | K78: -1820.453 | L78: -2117.094 | R78: -129.538 | S78: =-257.443-R78 -> -127.905 | T78: =-381.941-S78-R78 -> -124.498 | U78: =E78-T78-S78-R78 -> -125.236 | V78: -127.072 | W78: =-254.604-V78 -> -127.532 | X78: =-379.096-W78-V78 -> -124.492 | Y78: =F78-X78-W78-V78 -> -122.11 | Z78: -1.016 | AA78: =-1.018-Z78 -> -0.002 | AB78: =-1.041-AA78-Z78 -> -0.023 | AC78: =G78-AB78-AA78-Z78 -> -1.366 | AD78: -1.133 | AE78: =-1.132-AD78 -> 0.001 | AF78: =-1.133-AE78-AD78 -> -0.001 | AG78: =I78-AF78-AE78-AD78 -> -0.001 | AH78: -390.951 | AI78: =-1002.122-AH78 -> -611.171 | AJ78: =-1517.224-AH78-AI78 -> -515.102 | AK78: =J78-AJ78-AI78-AH78 -> -494.279 | AL78: -460.477 | AM78: =-899.805-AL78 -> -439.328 | AN78: =-1343.649-AL78-AM78 -> -443.844 | AO78: =K78-AN78-AM78-AL78 -> -476.804 | AP78: -494.427 | AQ78: =-1016.669-AP78 -> -522.242 | AR78: =2157.188-AP78-AQ78 -> 3173.857 | AS78: =L78-AP78-AQ78-AR78 -> -4274.282 | AT78: -93.599
B79: Un-Assigned | L79: 543035.4 | AQ79: =485773.466-AP79 -> 485773.47 | AR79: =542874.532-AP79-AQ79 -> 57101.066 | AS79: =L79-AP79-AQ79-AR79 -> 160.871
B80: Total EBITDA | C80: =SUM(C73:C78) -> 370150.02 | D80: =SUM(D73:D78) -> 356585.29 | E80: =SUM(E73:E78) -> 424780.73 | F80: =SUM(F73:F78) -> 437102.7 | G80: =SUM(G73:G78) -> 426920.8 | H80: =SUM(H73:H78) -> 426920.8 | I80: =SUM(I73:I78) -> 770411.16 | J80: =SUM(J73:J78) -> 684231.89 | K80: =SUM(K73:K78) -> 772452.26 | L80: =SUM(L73:L79) -> 1282012.9 | R80: =SUM(R73:R78) -> 109032.6 | S80: =SUM(S73:S78) -> 98565.219 | T80: =SUM(T73:T78) -> 105899.39 | U80: =SUM(U73:U78) -> 111283.52 | V80: =SUM(V73:V78) -> 109974.75 | W80: =SUM(W73:W78) -> 98619.657 | X80: =SUM(X73:X78) -> 112056.92 | Y80: =SUM(Y73:Y78) -> 116451.37 | ... AP80: =SUM(AP73:AP78) -> 189587.01 | AQ80: =SUM(AQ73:AQ79) -> 686794.55 | AR80: =SUM(AR73:AR79) -> 233180.42 | AS80: =SUM(AS73:AS79) -> 172450.92 | AT80: =SUM(AT73:AT78) -> 132123.26
B82: check | C82: =C80-Model!C48 -> -55250.343 | D82: =D80-Model!D48 -> 0 | E82: =E80-Model!E48 -> 0 | F82: =F80-Model!F48 -> 0 | G82: =G80-Model!G48 -> -0.201 | H82: =H80-Model!G48 -> -0.201 | I82: =I80-Model!H48 -> 0.156 | J82: =J80-Model!I48 -> 0 | K82: =K80-Model!J48 -> 0 | L82: =L80-Model!K48 -> -0.106 | R82: =R80-Model!Q48 -> -0.397 | S82: =S80-Model!R48 -> 0.219 | T82: =T80-Model!S48 -> 0.39 | U82: =U80-Model!T48 -> -0.212 | V82: =V80-Model!U48 -> -0.25 | W82: =W80-Model!V48 -> -0.343 | X82: =X80-Model!W48 -> -0.075 | Y82: =Y80-Model!X48 -> 0.668 | ... AT82: =AT80-Model!AS48 -> 0.258
B84: EBITDA Margin
B85: Consumer | C85: =C73/C8 -> 0.29445841 | D85: =D73/D8 -> 0.32241808 | E85: =E73/E8 -> 0.33309943 | F85: =F73/F8 -> 0.31196631 | G85: =G73/G8 -> 0.29623024 | H85: =H73/H8 -> 0.29623024 | I85: =I73/I8 -> 0.3556816 | J85: =J73/J8 -> 0.37209539 | ... L85: =L73/L8 -> 0.35059861 | R85: =R73/R8 -> 0.36602124 | S85: =S73/S8 -> 0.33239172 | T85: =T73/T8 -> 0.33405247 | U85: =U73/U8 -> 0.30033615 | V85: =V73/V8 -> 0.3382957 | W85: =W73/W8 -> 0.30352469 | X85: =X73/X8 -> 0.31382676 | Y85: =Y73/Y8 -> 0.29335919 | ... AT85: =AT73/AT8 -> 0.3301607
B86: Enterprise | C86: =C74/C9 -> 0.32959798 | D86: =D74/D9 -> 0.3517752 | E86: =E74/E9 -> 0.37316124 | F86: =F74/F9 -> 0.38557867 | G86: =G74/G9 -> 0.41939326 | H86: =H74/H9 -> 0.41939326 | I86: =I74/I9 -> 0.4459444 | J86: =J74/J9 -> 0.43003765 | ... L86: =L74/L9 -> 0.36015536 | R86: =R74/R9 -> 0.38440439 | S86: =S74/S9 -> 0.37175958 | T86: =T74/T9 -> 0.3725008 | U86: =U74/U9 -> 0.363933 | V86: =V74/V9 -> 0.38589173 | W86: =W74/W9 -> 0.38382247 | X86: =X74/X9 -> 0.39714229 | Y86: =Y74/Y9 -> 0.37577079 | ... AT86: =AT74/AT9 -> 0.33277627
B87: Corporate | C87: =C75/C10 -> 0.26555994 | D87: =D75/D10 -> 0.31803781 | E87: =E75/E10 -> 0.3607495 | F87: =F75/F10 -> 0.37148144 | G87: =G75/G10 -> 0.36726843 | H87: =H75/H10 -> 0.36726843 | I87: =I75/I10 -> 0.35398325 | J87: =J75/J10 -> 0.32002932 | ... L87: =L75/L10 -> 0.22817963 | R87: =R75/R10 -> 0.32295423 | S87: =S75/S10 -> 0.36249351 | T87: =T75/T10 -> 0.36474893 | U87: =U75/U10 -> 0.3909231 | V87: =V75/V10 -> 0.32970377 | W87: =W75/W10 -> 0.37247614 | X87: =X75/X10 -> 0.40076986 | Y87: =Y75/Y10 -> 0.38287137 | ... AT87: =AT75/AT10 -> 0.075440168
B88: M. Serv.Peru | C88: =C76/C11 -> -0.69512634 | D88: =D76/D11 -> -0.68911353 | E88: =E76/E11 -> -0.33982524 | F88: =F76/F11 -> -0.16149349 | G88: =G76/G11 -> -0.11066554 | H88: =H76/H11 -> -0.1053954 | I88: =I76/I11 -> 0.17912471 | J88: =J76/J11 -> 0.15232861 | ... L88: =L76/L11 -> 0.18791765 | R88: =R76/R11 -> -0.38720413 | S88: =S76/S11 -> -0.4087961 | T88: =T76/T11 -> -0.29329027 | U88: =U76/U11 -> -0.28547694 | V88: =V76/V11 -> -0.22765799 | W88: =W76/W11 -> -0.24274112 | X88: =X76/X11 -> -0.13434511 | Y88: =Y76/Y11 -> -0.066759313 | ... AT88: =AT76/AT11 -> 0.036021162
B89: Other businesses | C89: =C77/C12 -> 0.14437174 | D89: =D77/D12 -> 0.10064 | E89: =E77/E12 -> 0.084635843 | F89: =F77/F12 -> 0.048507274 | G89: =G77/G12 -> 0.028917126 | H89: =H77/H12 -> 0.029747826 | I89: =I77/I12 -> 0.15515625 | J89: =J77/J12 -> 0.066362507 | ... L89: =L77/L12 -> 0.023841093 | R89: =R77/R12 -> 0.08046453 | S89: =S77/S12 -> 0.084241109 | T89: =T77/T12 -> 0.066484495 | U89: =U77/U12 -> 0.10353041 | V89: =V77/V12 -> 0.067319116 | W89: =W77/W12 -> 0.04704502 | X89: =X77/X12 -> 0.041910849 | Y89: =Y77/Y12 -> 0.039693749 | ... AT89: =AT77/AT12 -> 0.029853656
B90: Withdrawals | C90: =C78/C13 -> 0.0010663725 | D90: =D78/D13 -> 0.0011591634 | E90: =E78/E13 -> 0.00085633539 | F90: =F78/F13 -> 0.00069002515 | G90: =G78/G13 -> 2.9386238e-06 | H90: =H78/H13 -> 2.9741548e-06 | I90: =I78/I13 -> 1.4194637e-06 | J90: =J78/J13 -> 0.0023366621 | ... L90: =L78/L13 -> 0.001913213 | R90: =R78/R13 -> 0.0010539877 | S90: =S78/S13 -> 0.00096175372 | T90: =T78/T13 -> 0.00081679589 | U90: =U78/U13 -> 0.00068082344 | V90: =V78/V13 -> 0.00076676475 | W90: =W78/W13 -> 0.00071908437 | X90: =X78/X13 -> 0.00066980683 | Y90: =Y78/Y13 -> 0.0006185344 | ... AT90: =AT78/AT13 -> 0.00031831818
B91: Un-Assigned
B92: Total EBITDA | C92: =C80/C15 -> 0.22328184 | D92: =D80/D15 -> 0.19981103 | E92: =E80/E15 -> 0.22743556 | F92: =F80/F15 -> 0.22495455 | G92: =G80/G15 -> 0.22314789 | H92: =H80/H15 -> 0.22201236 | I92: =I80/I15 -> 0.35057829 | J92: =J80/J15 -> 0.31862019 | ... L92: =L80/L15 -> 0.40858239 | R92: =R80/R15 -> 0.2373041 | S92: =S80/S15 -> 0.21575617 | T92: =T80/T15 -> 0.22632849 | U92: =U80/U15 -> 0.2301643 | V92: =V80/V15 -> 0.23220268 | W92: =W80/W15 -> 0.20600233 | X92: =X80/X15 -> 0.23349734 | Y92: =Y80/Y15 -> 0.22797017 | ... AT92: =AT80/AT15 -> 0.21541661
B95: EBITDA breakdown by Services (in mn of Ch$)
B96: Mobile Services Chile | C96: 408097 | D96: 448997 | E96: 437098 | F96: 411818 | G96: 373302 | H96: 373302 | I96: 393415 | J96: 436357 | K96: 504247 | L96: 483446 | M96: =SUM(AT96:AW96) -> 472634 | N96: 491243 | O96: 514283 | P96: =SUM(BC96:BF96) -> 522832 | R96: 118283 | S96: 108425 | T96: 107343 | U96: =E96-T96-S96-R96 -> 103047 | V96: 110319 | W96: 103252 | X96: 101183 | Y96: =F96-X96-W96-V96 -> 97064 | Z96: 92660 | AA96: 89698 | AB96: 91440 | AC96: =G96-AB96-AA96-Z96 -> 99504 | AD96: 102308 | AE96: 91005 | AF96: 100443 | AG96: =I96-AF96-AE96-AD96 -> 99659 | AH96: 106311 | AI96: 101954 | AJ96: 108817 | AK96: =J96-AJ96-AI96-AH96 -> 119275 | AL96: 119515 | AM96: 129828 | AN96: 131351 | AO96: =K96-AN96-AM96-AL96 -> 123553 | AP96: 125826 | AQ96: 125040 | AR96: 116733 | AS96: =L96-AP96-AQ96-AR96 -> 115847 | AT96: 113039 | AU96: 123516 | AV96: 118513 | AW96: 117566 | AX96: 115637 | AY96: 119235 | AZ96: 125248 | BA96: =N96-AZ96-AY96-AX96 -> 131123 | BB96: 126585 | BC96: 123193 | BD96: 133196 | BE96: =O96-(BD96+BC96+BB96) -> 131309 | BF96: 135134
B97: Fixed Services | C97: 45989 | D97: 65926 | E97: 85883 | F97: 90992 | G97: 100686 | H97: 101695 | I97: 122257 | J97: 108289 | K97: 107112 | L97: 87159 | M97: =SUM(AT97:AW97) -> 66859 | N97: 48574 | O97: 34806 | P97: =SUM(BC97:BF97) -> 39073 | R97: 18479 | S97: 21194 | T97: 22369 | U97: =E97-T97-S97-R97 -> 23841 | V97: 19834 | W97: 21202 | X97: 24548 | Y97: =F97-X97-W97-V97 -> 25408 | Z97: 21300 | AA97: 20163 | AB97: 26675 | AC97: =G97-AB97-AA97-Z97 -> 32548 | AD97: 28650 | AE97: 32832 | AF97: 29671 | AG97: =I97-AF97-AE97-AD97 -> 31104 | AH97: 25655 | AI97: 27656 | AJ97: 24201 | AK97: =J97-AJ97-AI97-AH97 -> 30777 | AL97: 22062 | AM97: 28777 | AN97: 26924 | AO97: =K97-AN97-AM97-AL97 -> 29349 | AP97: 20676 | AQ97: 25639 | AR97: 19496 | AS97: =L97-AP97-AQ97-AR97 -> 21348 | AT97: 10183 | AU97: 21826 | AV97: 15549 | AW97: 19301 | AX97: 10026 | AY97: 14728 | AZ97: 10585 | BA97: =N97-AZ97-AY97-AX97 -> 13235 | BB97: 2707 | BC97: 12203 | BD97: 9733 | BE97: =O97-(BD97+BC97+BB97) -> 10163 | BF97: 6974
B98: Others | C98: 25583 | D98: 10722 | E98: 23288 | F98: 10290 | G98: 5383 | H98: 2585 | I98: 128264 | J98: 35977 | K98: 27074 | L98: 477483 | M98: =SUM(AT98:AW98) -> 57639 | N98: 6338 | O98: 9802 | P98: =SUM(BC98:BF98) -> 9773 | R98: 3714 | S98: 3582 | T98: 3233 | U98: =E98-T98-S98-R98 -> 12759 | V98: 3687 | W98: 1185 | X98: 2480 | Y98: =F98-X98-W98-V98 -> 2938 | Z98: 1584 | AA98: 1958 | AB98: 4684 | AC98: =G98-AB98-AA98-Z98 -> -2843 | AD98: 715 | AE98: 1338 | AF98: 1332 | AG98: =I98-AF98-AE98-AD98 -> 124879 | AH98: 10725 | AI98: 12412 | AJ98: 5585 | AK98: =J98-AJ98-AI98-AH98 -> 7255 | AL98: 6426 | AM98: 11256 | AN98: 8125 | AO98: =K98-AN98-AM98-AL98 -> 1267 | AP98: 828 | AQ98: 487215 | AR98: 1013 | AS98: =L98-AP98-AQ98-AR98 -> -11573 | AT98: 1579 | AU98: 748 | AV98: 776 | AW98: 54536 | AX98: 680 | AY98: 2459 | AZ98: 414 | BA98: =N98-AZ98-AY98-AX98 -> 2785 | BB98: 332 | BC98: 2759 | BD98: 2367 | BE98: =O98-(BD98+BC98+BB98) -> 4344 | BF98: 303
B99: Entel Peru | C99: -109519 | D99: -169060 | E99: -121489 | F99: -75998 | G99: -52450 | H99: -50741 | I99: 126476 | J99: 103609 | K99: 134019 | L99: 233926 | M99: =SUM(AT99:AW99) -> 165432 | N99: 242458 | O99: 276582 | P99: =SUM(BC99:BF99) -> 283704 | R99: -31443 | S99: -34636 | T99: -27045 | U99: =E99-T99-S99-R99 -> -28365 | V99: -23865 | W99: -27019 | X99: -16154 | Y99: =F99-X99-W99-V99 -> -8960 | Z99: -16203 | AA99: -17597 | AB99: -15691 | AC99: =G99-AB99-AA99-Z99 -> -2959 | AD99: 6132 | AE99: 12476 | AF99: 15952 | AG99: =I99-AF99-AE99-AD99 -> 91916 | AH99: 30007 | AI99: 21600 | AJ99: 26061 | AK99: =J99-AJ99-AI99-AH99 -> 25941 | AL99: 29593 | AM99: 34443 | AN99: 37542 | AO99: =K99-AN99-AM99-AL99 -> 32441 | AP99: 42258 | AQ99: 48901 | AR99: 95938 | AS99: =L99-AP99-AQ99-AR99 -> 46829 | AT99: 7322 | AU99: 47144 | AV99: 55315 | AW99: 55651 | AX99: 61428 | AY99: 63514 | AZ99: 58461 | BA99: =N99-AZ99-AY99-AX99 -> 59055 | BB99: 63941 | BC99: 64494 | BD99: 68331 | BE99: =O99-(BD99+BC99+BB99) -> 79816 | BF99: 71063
B100: Total EBITDA | C100: =+C96+C97+C98+C99 -> 370150 | D100: =+D96+D97+D98+D99 -> 356585 | E100: =+E96+E97+E98+E99 -> 424780 | F100: =+F96+F97+F98+F99 -> 437102 | G100: =+G96+G97+G98+G99 -> 426921 | H100: =+H96+H97+H98+H99 -> 426841 | I100: =+I96+I97+I98+I99 -> 770412 | J100: =+J96+J97+J98+J99 -> 684232 | ... P100: =+P96+P97+P98+P99 -> 855382 | R100: =+R96+R97+R98+R99 -> 109033 | S100: =+S96+S97+S98+S99 -> 98565 | T100: =+T96+T97+T98+T99 -> 105900 | U100: =+U96+U97+U98+U99 -> 111282 | V100: =+V96+V97+V98+V99 -> 109975 | W100: =+W96+W97+W98+W99 -> 98620 | X100: =+X96+X97+X98+X99 -> 112057 | Y100: =+Y96+Y97+Y98+Y99 -> 116450 | ... AS100: =+AS96+AS97+AS98+AS99 -> 172451 | AT100: =AT96+AT97+AT98+AT99 -> 132123 | AU100: =+AU96+AU97+AU98+AU99 -> 193234 | AV100: =+AV96+AV97+AV98+AV99 -> 190153 | AW100: =+AW96+AW97+AW98+AW99 -> 247054 | AX100: =AX96+AX97+AX98+AX99 -> 187771 | AY100: =+AY96+AY97+AY98+AY99 -> 199936 | AZ100: =+AZ96+AZ97+AZ98+AZ99 -> 194708 | BA100: =+BA96+BA97+BA98+BA99 -> 206198 | BB100: =BB96+BB97+BB98+BB99 -> 193565 | BC100: =+BC96+BC97+BC98+BC99 -> 202649 | BD100: =+BD96+BD97+BD98+BD99 -> 213627 | BE100: =+BE96+BE97+BE98+BE99 -> 225632 | BF100: =+BF96+BF97+BF98+BF99 -> 213474
B101: check | C101: =C100-Model!C48 -> -55250.365 | D101: =D100-Model!D48 -> -0.293 | E101: =E100-Model!E48 -> -0.734 | F101: =F100-Model!F48 -> -0.699 | G101: =G100-Model!G48 -> 0 | H101: =H100-Model!G48 -> -80 | I101: =I100-Model!H48 -> 1 | J101: =J100-Model!I48 -> 0.111 | K101: =K100-Model!J48 -> -0.258 | L101: =L100-Model!K48 -> 1 | M101: =M100-Model!L48 -> 1.829 | N101: =N100-Model!M48 -> 0.099 | O101: =O100-Model!N48 -> -0.096 | P101: =P100-Model!O48 -> -2.794 | R101: =R100-Model!Q48 -> 0 | S101: =S100-Model!R48 -> 0 | T101: =T100-Model!S48 -> 1 | U101: =U100-Model!T48 -> -1.734 | V101: =V100-Model!U48 -> 0 | W101: =W100-Model!V48 -> 0 | X101: =X100-Model!W48 -> 0 | Y101: =Y100-Model!X48 -> -0.699 | ... BF101: =BF100-Model!BE48 -> -3.096
B103: Operating Revenue (in mn of Ch$)
B104: Mobile Phone Services-Chile | C104: 1150532 | D104: 1144828 | E104: 1082156 | F104: 1050382 | G104: 1001678 | H104: 1001678 | I104: 950478 | J104: 1016431 | K104: 1187687 | L104: 1166819 | M104: 1160941 | N104: 1248400.2 | O104: 1322038.8 | P104: =SUM(BC104:BF104) -> 1354064.1 | R104: 278630 | S104: 263676 | T104: 265659 | U104: =E104-T104-S104-R104 -> 274191 | V104: 261267 | W104: 262955 | X104: 256358 | Y104: =F104-X104-W104-V104 -> 269802 | Z104: 251474 | AA104: 250034 | AB104: 243242 | AC104: =G104-AB104-AA104-Z104 -> 256928 | AD104: 240579 | AE104: 231029 | AF104: 237446 | AG104: =I104-AF104-AE104-AD104 -> 241424 | AH104: 243810 | AI104: 224752 | AJ104: 262294 | AK104: =J104-AJ104-AI104-AH104 -> 285575 | AL104: 278078 | AM104: 297419 | AN104: 296919 | AO104: =K104-AN104-AM104-AL104 -> 315271 | AP104: 292493 | AQ104: 301546 | AR104: 283967 | AS104: =L104-AR104-AQ104-AP104 -> 288813 | AT104: 289615 | AU104: 283897 | AV104: 278230 | AW104: =M104-AV104-AU104-AT104 -> 309199 | AX104: 295715.39 | AY104: 302300.97 | AZ104: 304040.05 | BA104: =N104-AZ104-AY104-AX104 -> 346343.82 | BB104: 318842.7 | BC104: 310733.64 | BD104: 322448 | BE104: =O104-(BD104+BC104+BB104) -> 370014.48 | BF104: 350868
B105: Mobile Phone Services-Peru | C105: 151729 | D105: 238899 | E105: 348295 | F105: 457018 | G105: 472958 | H105: 477854 | I105: 579251 | J105: 627019 | K105: 766725 | L105: 863972 | M105: 782787 | N105: 891056.86 | O105: 1020160.5 | P105: =SUM(BC105:BF105) -> 1038582.2 | R105: 79522 | S105: 82771 | T105: 90072 | U105: =E105-T105-S105-R105 -> 95930 | V105: 102238 | W105: 108142 | X105: 116420 | Y105: =F105-X105-W105-V105 -> 130218 | Z105: 106869 | AA105: 109828 | AB105: 124179 | AC105: =G105-AB105-AA105-Z105 -> 132082 | AD105: 124482 | AE105: 138038 | AF105: 146356 | AG105: =I105-AF105-AE105-AD105 -> 170375 | AH105: 159437 | AI105: 122354 | AJ105: 161992 | AK105: =J105-AJ105-AI105-AH105 -> 183236 | AL105: 170128 | AM105: 182627 | AN105: 193030 | AO105: =K105-AN105-AM105-AL105 -> 220940 | AP105: 222621 | AQ105: 220661 | AR105: 209811 | AS105: =L105-AR105-AQ105-AP105 -> 210879 | AT105: 187404 | AU105: 185211 | AV105: 199208 | AW105: =M105-AV105-AU105-AT105 -> 210964 | AX105: 218260.72 | AY105: 215293.48 | AZ105: 218512.96 | BA105: =N105-AZ105-AY105-AX105 -> 238989.69 | BB105: 239777.25 | BC105: 241208.54 | BD105: 255707 | BE105: =O105-(BD105+BC105+BB105) -> 283467.69 | BF105: 258199
B106: Data Services (including IT) | C106: 136842 | D106: 150668 | E106: 175284 | F106: 188921 | G106: 196426 | H106: 196426 | I106: 203086 | J106: 203605 | K106: 218644 | L106: =394530+26009 -> 420539 | M106: =412232+27960 -> 440192 | N106: =450582.626+32227.321 -> 482809.95 | O106: =479157.352+35125.311 -> 514282.66 | P106: =SUM(BC106:BF106) -> 513649.66 | R106: 39395 | S106: 45093 | T106: 44154 | U106: =E106-T106-S106-R106 -> 46642 | V106: 46916 | W106: 45075 | X106: 48301 | Y106: =F106-X106-W106-V106 -> 48629 | Z106: 45726 | AA106: 47081 | AB106: 49700 | AC106: =G106-AB106-AA106-Z106 -> 53919 | AD106: 48487 | AE106: 51595 | AF106: 50224 | AG106: =I106-AF106-AE106-AD106 -> 52780 | AH106: 47061 | AI106: 50163 | AJ106: 50164 | AK106: =J106-AJ106-AI106-AH106 -> 56217 | AL106: 46905 | AM106: 53568 | AN106: 59148 | AO106: =K106-AN106-AM106-AL106 -> 59023 | AP106: 54855 | AQ106: =95326+6084 -> 101410 | AR106: =97723+6993 -> 104716 | AS106: =L106-AR106-AQ106-AP106 -> 159558 | AT106: =96717+6526 -> 103243 | AU106: =105886+6921 -> 112807 | AV106: =98768+6947 -> 105715 | AW106: =M106-AV106-AU106-AT106 -> 118427 | AX106: =103704+7642 -> 111346 | AY106: =110335.711+7617.834 -> 117953.54 | AZ106: =111021.515+8256.5 -> 119278.01 | BA106: =N106-AZ106-AY106-AX106 -> 134232.39 | BB106: =115453+8937 -> 124390 | BC106: =119465.411+8462.374 -> 127927.78 | BD106: =120594+8943 -> 129537 | BE106: =O106-(BD106+BC106+BB106) -> 132427.88 | BF106: =115243+8514 -> 123757
B107: Local Telephone Services | C107: 50568 | D107: 60830 | E107: 63533 | F107: 57244 | G107: 52845 | H107: 52620 | I107: 50856 | J107: 45324 | K107: 34894 | R107: 15275 | S107: 16047 | T107: 16205 | U107: =E107-T107-S107-R107 -> 16006 | V107: 14951 | W107: 14626 | X107: 13941 | Y107: =F107-X107-W107-V107 -> 13726 | Z107: 13384 | AA107: 13290 | AB107: 13030 | AC107: =G107-AB107-AA107-Z107 -> 13141 | AD107: 12585 | AE107: 13831 | AF107: 12349 | AG107: =I107-AF107-AE107-AD107 -> 12091 | AH107: 11949 | AI107: 11769 | AJ107: 11236 | AK107: =J107-AJ107-AI107-AH107 -> 10370 | AL107: 9459 | AM107: 8930 | AN107: 8133 | AO107: =K107-AN107-AM107-AL107 -> 8372 | AP107: 7482
B108: Long Distance | C108: 26961 | D108: 19152 | E108: 16399 | F108: 12367 | G108: 10464 | H108: 10464 | I108: 8050 | J108: 5621 | K108: 3882 | R108: 4349 | S108: 4057 | T108: 3777 | U108: =E108-T108-S108-R108 -> 4216 | V108: 3506 | W108: 3155 | X108: 2815 | Y108: =F108-X108-W108-V108 -> 2891 | Z108: 2681 | AA108: 2491 | AB108: 2664 | AC108: =G108-AB108-AA108-Z108 -> 2628 | AD108: 2163 | AE108: 1927 | AF108: 1966 | AG108: =I108-AF108-AE108-AD108 -> 1994 | AH108: 1550 | AI108: 1761 | AJ108: 1023 | AK108: =J108-AJ108-AI108-AH108 -> 1287 | AL108: 1012 | AM108: 1107 | AN108: 951 | AO108: =K108-AN108-AM108-AL108 -> 812 | AP108: 860
B109: Internet | C109: 24097 | D109: 28698 | E109: 35079 | F109: 43845 | G109: 49366 | H109: 49366 | I109: 58155 | J109: 66271 | K109: 81954 | R109: 8053 | S109: 8484 | T109: 9093 | U109: =E109-T109-S109-R109 -> 9449 | V109: 9873 | W109: 10617 | X109: 11563 | Y109: =F109-X109-W109-V109 -> 11792 | Z109: 11664 | AA109: 12185 | AB109: 12827 | AC109: =G109-AB109-AA109-Z109 -> 12690 | AD109: 13157 | AE109: 13787 | AF109: 15417 | AG109: =I109-AF109-AE109-AD109 -> 15794 | AH109: 16327 | AI109: 16436 | AJ109: 15986 | AK109: =J109-AJ109-AI109-AH109 -> 17522 | AL109: 18760 | AM109: 20387 | AN109: 20884 | AO109: =K109-AN109-AM109-AL109 -> 21923 | AP109: 22537
B110: Services to Other Operators | C110: 22988 | D110: 55279 | E110: 52786 | F110: 43425 | G110: 34621 | H110: 29949 | I110: 29562 | J110: 32216 | K110: 41256 | L110: =61622+9500 -> 71122 | M110: =68784+5034 -> 73818 | N110: =55113.58+6967.934 -> 62081.514 | O110: =70896.672+7650.846 -> 78547.518 | P110: =SUM(BC110:BF110) -> 75702.518 | R110: 12124 | S110: 13881 | T110: 13076 | U110: =E110-T110-S110-R110 -> 13705 | V110: 13348 | W110: 12472 | X110: 8792 | Y110: =F110-X110-W110-V110 -> 8813 | Z110: 8487 | AA110: 8798 | AB110: 8528 | AC110: =G110-AB110-AA110-Z110 -> 8808 | AD110: 7561 | AE110: 7387 | AF110: 7140 | AG110: =I110-AF110-AE110-AD110 -> 7474 | AH110: 7785 | AI110: 7757 | AJ110: 7868 | AK110: =J110-AJ110-AI110-AH110 -> 8806 | AL110: 10758 | AM110: 9851 | AN110: 9558 | AO110: =K110-AN110-AM110-AL110 -> 11089 | AP110: 11365 | AQ110: =16353+2414 -> 18767 | AR110: =17032+2455 -> 19487 | AS110: =L110-AR110-AQ110-AP110 -> 21503 | AT110: =15604+2262 -> 17866 | AU110: =18113+2371 -> 20484 | AV110: =17248-766 -> 16482 | AW110: =M110-AV110-AU110-AT110 -> 18986 | AX110: =17909+1630 -> 19539 | AY110: =18857.333+1633.085 -> 20490.418 | AZ110: =11157.55+2084.928 -> 13242.478 | BA110: =N110-AZ110-AY110-AX110 -> 8809.618 | BB110: =17443+1921 -> 19364 | BC110: =18769.118+1892.648 -> 20661.766 | BD110: =15964+1922 -> 17886 | BE110: =O110-(BD110+BC110+BB110) -> 20635.752 | BF110: =14697+1822 -> 16519
B111: Traffic Business | C111: 28080 | D111: 26607 | E111: 26853 | F111: 19989 | G111: 23652 | H111: 23652 | I111: 25156 | J111: 22144 | K111: 18813 | R111: 6062 | S111: 5747 | T111: 8860 | U111: =E111-T111-S111-R111 -> 6184 | V111: 4456 | W111: 4459 | X111: 4610 | Y111: =F111-X111-W111-V111 -> 6464 | Z111: 4165 | AA111: 4007 | AB111: 9574 | AC111: =G111-AB111-AA111-Z111 -> 5906 | AD111: 4519 | AE111: 6508 | AF111: 7059 | AG111: =I111-AF111-AE111-AD111 -> 7070 | AH111: 7105 | AI111: 5571 | AJ111: 4869 | AK111: =J111-AJ111-AI111-AH111 -> 4599 | AL111: 4019 | AM111: 4382 | AN111: 4272 | AO111: =K111-AN111-AM111-AL111 -> 6140 | AP111: 4925
B112: TV Service | C112: 18020 | D112: 22418 | E112: 27725 | F112: 33161 | G112: 36521 | H112: 36521 | I112: 38589 | J112: 42364 | K112: 44328 | R112: 6291 | S112: 6892 | T112: 7096 | U112: =E112-T112-S112-R112 -> 7446 | V112: 7945 | W112: 8402 | X112: 8280 | Y112: =F112-X112-W112-V112 -> 8534 | Z112: 8671 | AA112: 9316 | AB112: 9163 | AC112: =G112-AB112-AA112-Z112 -> 9371 | AD112: 9650 | AE112: 10196 | AF112: 9274 | AG112: =I112-AF112-AE112-AD112 -> 9469 | AH112: 10536 | AI112: 9523 | AJ112: 10629 | AK112: =J112-AJ112-AI112-AH112 -> 11676 | AL112: 11194 | AM112: 11138 | AN112: 11015 | AO112: =K112-AN112-AM112-AL112 -> 10981 | AP112: 11058
B113: Americatel Peru | C113: 25450 | D113: 26379 | E113: 24050 | F113: 23710 | G113: 20448 | H113: 20448 | I113: 22147 | J113: 17905 | K113: 14966 | R113: 6261 | S113: 6240 | T113: 5906 | U113: =E113-T113-S113-R113 -> 5643 | V113: 5594 | W113: 5855 | X113: 5682 | Y113: =F113-X113-W113-V113 -> 6579 | Z113: 4539 | AA113: 5056 | AB113: 5317 | AC113: =G113-AB113-AA113-Z113 -> 5536 | AD113: 5267 | AE113: 5371 | AF113: 5311 | AG113: =I113-AF113-AE113-AD113 -> 6198 | AH113: 4869 | AI113: 4730 | AJ113: 4246 | AK113: =J113-AJ113-AI113-AH113 -> 4060 | AL113: 3562 | AM113: 3623 | AN113: 3806 | AO113: =K113-AN113-AM113-AL113 -> 3975 | AP113: 4035
B114: Call Center Services and Other | C114: 8000 | D114: 10855 | E114: 15537 | F114: 13007 | G114: 14195 | H114: 14195 | I114: 13463 | J114: 13727 | K114: 14072 | L114: 18230 | M114: 15955 | N114: 18888.174 | O114: 19900.802 | P114: =SUM(BC114:BF114) -> 20242.802 | R114: 3500 | S114: 3946 | T114: 4004 | U114: =E114-T114-S114-R114 -> 4087 | V114: 3522 | W114: 2975 | X114: 3144 | Y114: =F114-X114-W114-V114 -> 3366 | Z114: 3521 | AA114: 3588 | AB114: 3101 | AC114: =G114-AB114-AA114-Z114 -> 3985 | AD114: 3103 | AE114: 3002 | AF114: 3516 | AG114: =I114-AF114-AE114-AD114 -> 3842 | AH114: 3013 | AI114: 2822 | AJ114: 4148 | AK114: =J114-AJ114-AI114-AH114 -> 3744 | AL114: 3850 | AM114: 3052 | AN114: 5534 | AO114: =K114-AN114-AM114-AL114 -> 1636 | AP114: 4625 | AQ114: 4244 | AR114: 4802 | AS114: =L114-AR114-AQ114-AP114 -> 4559 | AT114: 3281 | AU114: 4823 | AV114: 4171 | AW114: =M114-AV114-AU114-AT114 -> 3680 | AX114: 4884 | AY114: 4626.041 | AZ114: 4492.445 | BA114: =N114-AZ114-AY114-AX114 -> 4885.688 | BB114: 4711 | BC114: 5105.2 | BD114: 4860 | BE114: =O114-(BD114+BC114+BB114) -> 5224.602 | BF114: 5053
B115: Other Revenue | C115: 24784 | D115: 8251 | E115: 19605 | F115: 12102 | G115: 9785 | H115: 9785 | I115: 218750 | J115: 54857 | K115: 32898 | L115: 597027 | M115: 99450 | N115: 61524 | O115: 77371 | P115: =SUM(BC115:BF115) -> 80685 | R115: 1848 | S115: 2167 | T115: 2268 | U115: =E115-T115-S115-R115 -> 13322 | V115: 3409 | W115: 2617 | X115: 3112 | Y115: =F115-X115-W115-V115 -> 2964 | Z115: 2358 | AA115: 2865 | AB115: 2116 | AC115: =G115-AB115-AA115-Z115 -> 2446 | AD115: 3232 | AE115: 2768 | AF115: 2430 | AG115: =I115-AF115-AE115-AD115 -> 210320 | AH115: 17263 | AI115: 18456 | AJ115: 8585 | AK115: =J115-AJ115-AI115-AH115 -> 10553 | AL115: 11034 | AM115: 12369 | AN115: 10096 | AO115: =K115-AN115-AM115-AL115 -> -601 | AP115: 9155 | AQ115: 502939 | AR115: 72813 | AS115: =L115-AR115-AQ115-AP115 -> 12120 | AT115: 11929 | AU115: 10500 | AV115: 13631 | AW115: =M115-AV115-AU115-AT115 -> 63390 | AX115: 14899 | AY115: 19758 | AZ115: 13878 | BA115: =N115-AZ115-AY115-AX115 -> 12989 | BB115: 17531 | BC115: =17012+368 -> 17380 | BD115: =17566 -450 -> 17116 | BE115: =O115-(BD115+BC115+BB115) -> 25344 | BF115: =20867-22 -> 20845
...
