Workbook
Name IQ_CH: 110000
Name IQ_CQ: 5000
Name IQ_CY: 10000
Name IQ_DAILY: 500000
Name IQ_FH: 100000
Name IQ_FQ: 500
Name IQ_FY: 1000
Name IQ_LTM: 2000
Name IQ_MONTH: 15000
Name IQ_NTM: 6000
Name IQ_WEEK: 50000
Name IQ_YTD: 3000

Sheet Capitalization
A3: 2Q26 | I3: Exchange rate as at end | J3: =1/Model!$AV$202 -> 0.016299919
I4: LTM Average exchange rate | J4: =1/AVERAGE(Model!$AS$201:$AV$201) -> 0.016968134
B6: Debt Breakdown as on 30-Jun-2026 | C6: PHP (mn) | D6: USD (mn) | E6: Leverage (PHP) | F6: Leverage (USD) | I6: Company reported | J6: =C6 -> PHP (mn)
B7: Interest-bearing financial liabilities | I7: Net debt | J7: 287339
B8: Long -term | C8: 267008 | D8: =C8*$J3 -> 4352.2086 | I8: Net debt to EBITDA | J8: 2.6x
B9: Short term | C9: 30917 | D9: =C9*$J3 -> 503.94458
B11: Lease Liabilites
B12: Long -term | C12: 52905 | D12: =C12*$J3 -> 862.34719
B13: Short tem | C13: 10187 | D13: =C13*$J3 -> 166.04727
B15: Total loan and borrowing | C15: =SUM(C8,C9,C12,C13) -> 361017 | D15: =SUM(D8,D9,D12,D13) -> 5884.5477 | E15: =C15/C20 -> 3.2306061 | F15: =D15/D20 -> 3.1033829
B16: Total cash and cash equivalents | C16: =Model!AV$119 -> 11906 | D16: =C16*$J3 -> 194.06683
B17: Net debt | C17: =C15-C16 -> 349111 | D17: =D15-D16 -> 5690.4808 | E17: =C17/C20 -> 3.1240638 | F17: =D17/D20 -> 3.0010362
B18: Equity | C18: =Model!AV$126 -> 114267 | D18: =C18*$J3 -> 1862.5428
B19: Total Capitalisation | C19: =C17+C18 -> 463378 | D19: =D17+D18 -> 7553.0236
B20: LTM Adjusted EBITDA | C20: =Model!AV$84 -> 111749 | D20: =C20*$J4 -> 1896.172
B21: check | C21: =C15-Model!AV$123 -> 0
B24: =B6 -> Debt Breakdown as on 30-Jun-2026 | C24: =C6 -> PHP (mn) | D24: =D6 -> USD (mn) | E24: =E6 -> Leverage (PHP) | F24: =F6 -> Leverage (USD)
B25: U.S. Dollar Debts
B26: Fixed Rate Notes
B27: 2.5000% to 3.4500% in 2026 and 2025 | C27: 36291 | D27: =C27*$J3 -> 591.54034
B28: Term Loans
B29: Unsecured Term Loans : SOFR + 1.31161 % in 2026 and 2025 | C29: 3849 | D29: =C29*$J3 -> 62.738386
B31: Philippine Peso Debts
B32: Term Loans
B33: Unsecured Term Loans : 4.0000% to 5.3500%; PHP BVAL + 0.4000% to 0.9000% in 2026; 4.0000% to 5.3500%; PHP BVAL + 0.4000% to 1.1250% (floor rate 4.5000% to 4.6250%) in 2025 | C33: 257485 | D33: =C33*$J3 -> 4196.9845
B34: Total Long term debt | C34: =SUM(C27,C29,C33) -> 297625 | D34: =SUM(D27,D29,D33) -> 4851.2632
B35: Less portion maturing within one year | C35: 30617 | D35: =C35*$J3 -> 499.0546
B36: Non current portion of long-term debt | C36: =+C34-C35 -> 267008 | D36: =+D34-D35 -> 4352.2086
B38: Long-term debt maturing within one year | C38: =C35 -> 30617 | D38: =D35 -> 499.0546
B39: Short-term debt | C39: 300 | D39: =C39*$J3 -> 4.8899756
B40: Total Debt | C40: =+C36+C38+C39 -> 297925 | D40: =+D36+D38+D39 -> 4856.1532
B42: Current portion of lease liabilities | C42: =C13 -> 10187 | D42: =C42*$J3 -> 166.04727
B43: Noncurrent portion of lease liabilities | C43: =C12 -> 52905 | D43: =C43*$J3 -> 862.34719
B44: Total Debt (including lease liabilities) | C44: =C40+C42+C43 -> 361017 | D44: =D40+D42+D43 -> 5884.5477 | E44: =C44/C49 -> 3.2306061 | F44: =D44/D49 -> 3.1033829
B45: Cash & Cash Equivalents | C45: =Model!AV$119 -> 11906 | D45: =C45*$J3 -> 194.06683
B46: Net debt | C46: =C44-C45 -> 349111 | D46: =D44-D45 -> 5690.4808 | E46: =C46/C49 -> 3.1240638 | F46: =D46/D49 -> 3.0010362
B47: Equity | C47: =Model!AV$126 -> 114267 | D47: =C47*$J3 -> 1862.5428
B48: Total Capitalisation | C48: =C46+C47 -> 463378 | D48: =D46+D47 -> 7553.0236
B49: LTM Adjusted EBITDA | C49: =Model!AV$84 -> 111749 | D49: =C49*J4 -> 1896.172
B50: check | C50: =C44-Model!AV$123 -> 0
B53: Liquidity table as of 2Q26 | C53: =C6 -> PHP (mn) | D53: =D6 -> USD (mn)
B54: =+B45 -> Cash & Cash Equivalents | C54: =Model!$AV$120 -> 11896 | D54: =+C54*$J3 -> 193.90383
B55: Short term investments | C55: =Model!$AV$121 -> 10 | D55: =+C55*$J3 -> 0.16299919
B56: Total | C56: =+SUM(C54:C55) -> 11906 | D56: =+SUM(D54:D55) -> 194.06683
B59: Debt Maturity: consolidated outstanding long-term and short-term debt at nominal values | C59: =C53 -> PHP (mn) | D59: =D53 -> USD (mn)
B60: 2026 | C60: 9527 | D60: =+C60*$J3 -> 155.28932
B61: 2027 | C61: 27996 | D61: =+C61*$J3 -> 456.33252
B62: 2028 | C62: 21824 | D62: =+C62*$J3 -> 355.72942
B63: 2029 | C63: 26743 | D63: =+C63*$J3 -> 435.90872
B64: 2030 | C64: 25131 | D64: =+C64*$J3 -> 409.63325
B65: 2031 and onwards | C65: 188473 | D65: =+C65*$J3 -> 3072.0945
B66: Total | C66: =+SUM(C60:C65) -> 299694 | D66: =+SUM(D60:D65) -> 4884.9878
A92: 1Q26 | I92: Exchange rate as at end | J92: =1/Model!$M$202 -> 0.016299919
I93: LTM Average exchange rate | J93: =1/Model!$M$201 -> 0.016968134
B95: Debt Breakdown as on 31-Mar-2026 | C95: PHP (mn) | D95: USD (mn) | E95: Leverage (PHP) | F95: Leverage (USD) | I95: Company reported | J95: =C95 -> PHP (mn)
B96: Interest-bearing financial liabilities | I96: Net debt | J96: 282272
B97: Long -term | C97: 266392 | D97: =C97*$J92 -> 4342.1679 | I97: Net debt to EBITDA | J97: 2.53x
B98: Short term | C98: 29070 | D98: =C98*$J92 -> 473.83863
B100: Lease Liabilites
B101: Long -term | C101: 52157 | D101: =C101*$J92 -> 850.15485
B102: Short tem | C102: 9679 | D102: =C102*$J92 -> 157.76691
B104: Total loan and borrowing | C104: =SUM(C97,C98,C101,C102) -> 357298 | D104: =SUM(D97,D98,D101,D102) -> 5823.9283 | E104: =C104/C109 -> 3.2000466 | F104: =D104/D109 -> 3.0740268
B105: Total cash and cash equivalents | C105: =Model!AU$119 -> 14544 | D105: =C105*$J92 -> 237.06601
B106: Net debt | C106: =C104-C105 -> 342754 | D106: =D104-D105 -> 5586.8623 | E106: =C106/C109 -> 3.069787 | F106: =D106/D109 -> 2.948897
B107: Equity | C107: =Model!AU$126 -> 127168 | D107: =C107*$J92 -> 2072.828
B108: Total Capitalisation | C108: =C106+C107 -> 469922 | D108: =D106+D107 -> 7659.6903
B109: LTM Adjusted EBITDA | C109: =Model!AU$84 -> 111654 | D109: =C109*$J93 -> 1894.56
B110: check | C110: =C104-Model!AU$123 -> 0
B113: =B95 -> Debt Breakdown as on 31-Mar-2026 | C113: =C95 -> PHP (mn) | D113: =D95 -> USD (mn) | E113: =E95 -> Leverage (PHP) | F113: =F95 -> Leverage (USD)
B114: U.S. Dollar Debts
B115: Fixed Rate Notes
B116: 2.5000% to 3.4500% in 2026 and 2025 | C116: 35915 | D116: =C116*$J92 -> 585.41157
B117: Term Loans
B118: SOFR + 1.31161 % in 2026 and 2025 | C118: 4021 | D118: =C118*$J92 -> 65.541972
B120: Philippine Peso Debts
B121: Term Loans
B122: 4.2500% to 5.3500%; PHP BVAL + 0.4000% to 0.9000% (floor rate 4.5000% to 4.6250%) in 2026; 4.0000% to 5.3500%; PHP BVAL + 0.4000% to 1.0000% (floor rate 4.5000% to 4.6250%) in 2025 | C122: 255226 | D122: =C122*$J92 -> 4160.163
B123: Total Long term debt | C123: =SUM(C116,C118,C122) -> 295162 | D123: =SUM(D116,D118,D122) -> 4811.1165
B124: Less portion maturing within one year | C124: 28770 | D124: =C124*$J92 -> 468.94866
B125: Non current portion of long-term debt | C125: =+C123-C124 -> 266392 | D125: =+D123-D124 -> 4342.1679
B127: Long-term debt maturing within one year | C127: =C124 -> 28770 | D127: =D124 -> 468.94866
B128: Short-term debt | C128: 300 | D128: =C128*$J92 -> 4.8899756
B129: Total Debt | C129: =+C125+C127+C128 -> 295462 | D129: =+D125+D127+D128 -> 4816.0065
B131: Current portion of lease liabilities | C131: =C102 -> 9679 | D131: =C131*$J92 -> 157.76691
B132: Noncurrent portion of lease liabilities | C132: =C101 -> 52157 | D132: =C132*$J92 -> 850.15485
B133: Total Debt (including lease liabilities) | C133: =C129+C131+C132 -> 357298 | D133: =D129+D131+D132 -> 5823.9283 | E133: =C133/C138 -> 3.2000466 | F133: =D133/D138 -> 3.0740268
B134: Cash & Cash Equivalents | C134: =Model!AU$119 -> 14544 | D134: =C134*$J92 -> 237.06601
B135: Net debt | C135: =C133-C134 -> 342754 | D135: =D133-D134 -> 5586.8623 | E135: =C135/C138 -> 3.069787 | F135: =D135/D138 -> 2.948897
B136: Equity | C136: =Model!AU$126 -> 127168 | D136: =C136*$J92 -> 2072.828
B137: Total Capitalisation | C137: =C135+C136 -> 469922 | D137: =D135+D136 -> 7659.6903
B138: LTM Adjusted EBITDA | C138: =Model!AU$84 -> 111654 | D138: =C138*J93 -> 1894.56
B139: check | C139: =C133-Model!AU$123 -> 0
B142: Liquidity table as of 1Q26 | C142: =C95 -> PHP (mn) | D142: =D95 -> USD (mn)
B143: =+B134 -> Cash & Cash Equivalents | C143: =Model!$AU$120 -> 14534 | D143: =+C143*$J92 -> 236.90302
B144: Short term investments | C144: =Model!$AU$121 -> 10 | D144: =+C144*$J92 -> 0.16299919
B145: Total | C145: =+SUM(C143:C144) -> 14544 | D145: =+SUM(D143:D144) -> 237.06601
B148: Debt Maturity: consolidated outstanding long-term and short-term debt at nominal values | C148: =C142 -> PHP (mn) | D148: =D142 -> USD (mn)
B149: 2026 | C149: 15500 | D149: =+C149*$J92 -> 252.64874
B150: 2027 | C150: 27907 | D150: =+C150*$J92 -> 454.88183
B151: 2028 | C151: 21727 | D151: =+C151*$J92 -> 354.14833
...

Sheet Model
B2: PLDT INC. | C2: Annual | D2: Annual | E2: Annual | F2: Annual | G2: Annual | H2: Annual | I2: Annual | J2: Annual | K2: Annual | L2: Annual | M2: LTM | O2: Quarter | P2: Quarter | Q2: Quarter | R2: Quarter | S2: Quarter | T2: Quarter | U2: Quarter | V2: Quarter | W2: Quarter | X2: Quarter | Y2: Quarter | Z2: Quarter | AA2: Quarter | AB2: Quarter | AC2: Quarter | AD2: Quarter | AE2: Quarter | AF2: Quarter | AG2: Quarter | AH2: Quarter | AI2: Quarter | AJ2: Quarter | AK2: Quarter | AL2: Quarter | AM2: Quarter | AN2: Quarter | AO2: Quarter | AP2: Quarter | AQ2: Quarter | AR2: Quarter | AS2: Quarter | AT2: Quarter | AU2: Quarter | AV2: Quarter | AY2: Quarter
B3: (PHP millions) | C3: 42735 | D3: 43100 | E3: 43465 | F3: 43830 | G3: 44196 | H3: 44561 | I3: 44926 | J3: 45291 | K3: 45657 | L3: 46022 | M3: =AV3 -> 46203 | O3: 43190 | P3: 43281 | Q3: 43373 | R3: 43465 | S3: 43555 | T3: 43646 | U3: 43738 | V3: 43830 | W3: 43921 | X3: 44012 | Y3: 44104 | Z3: 44196 | AA3: 44286 | AB3: 44348 | AC3: 44469 | AD3: 44561 | AE3: 44651 | AF3: 44742 | AG3: 44834 | AH3: 44926 | AI3: 45016 | AJ3: 45107 | AK3: 45199 | AL3: 45291 | AM3: 45382 | AN3: 45473 | AO3: 45565 | AP3: 45657 | AQ3: 45747 | AR3: 45838 | AS3: 45930 | AT3: 46022 | AU3: 46112 | AV3: 46203 | AY3: 44104
C4: Act | D4: Act | E4: Act | F4: Act | G4: Act | H4: Act | I4: Act | J4: Act | K4: Act | L4: Act | M4: Act | O4: Act | P4: Act | Q4: Act | R4: Act | S4: Act | T4: Act | U4: Act | V4: Act | W4: Act | X4: Act | Y4: Act | Z4: Act | AA4: Act | AB4: Act | AC4: Act | AD4: Act | AE4: Restated | AF4: Restated | AG4: Restated | AH4: Act | AI4: Act | AJ4: Act | AK4: Act | AL4: Act | AM4: Act | AN4: Act | AO4: Act | AP4: Act | AQ4: Act | AR4: Act | AS4: Act | AT4: Act | AU4: Act | AV4: Act | AY4: Act
C5: FY 16 | D5: FY 17 | E5: FY 18 | F5: FY 19 | G5: FY 20 | H5: FY 21 | I5: FY 22 | J5: FY 23 | K5: FY 24 | L5: FY 24 | M5: LTM | O5: Q1 18 | P5: Q2 18 | Q5: Q3 18 | R5: Q4 18 | S5: Q1 19 | T5: Q2 19 | U5: Q3 19 | V5: Q4 19 | W5: Q1 20 | X5: Q2 20 | Y5: Q3 20 | Z5: Q4 20 | AA5: Q1 21 | AB5: Q2 21 | AC5: Q3 21 | AD5: Q4 21 | AE5: Q1 22 | AF5: Q2 22 | AG5: Q3 22 | AH5: Q4 22 | AI5: Q1 23 | AJ5: Q2 23 | AK5: Q3 23 | AL5: Q4 23 | AM5: Q1 24 | AN5: Q2 24 | AO5: Q3 24 | AP5: Q4 24 | AQ5: Q1 25 | AR5: Q2 25 | AS5: Q3 25 | AT5: Q4 25 | AU5: Q1 26 | AV5: Q2 25 | AY5: Q3 20
B6: INCOME STATEMENT | AY6: Restated
B7: Service revenues | C7: 157210 | D7: 150172 | E7: 152369 | F7: 161355 | G7: 173634 | H7: 184680 | I7: 195344 | J7: 201832 | K7: 208382 | L7: 212186 | M7: =SUM(AS7:AV7) -> 214610 | O7: 37745 | P7: 38616 | Q7: 38015 | R7: =E7-Q7-P7-O7 -> 37993 | S7: 38792 | T7: 39564 | U7: 40652 | V7: =F7-U7-T7-S7 -> 42347 | W7: 41797 | X7: 41685 | Y7: 44367 | Z7: =G7-Y7-X7-W7 -> 45785 | AA7: 45677 | AB7: 45916 | AC7: 46867 | AD7: =H7-AC7-AB7-AA7 -> 46220 | AE7: 47651 | AF7: 48849 | AG7: 49215 | AH7: =I7-AG7-AF7-AE7 -> 49629 | AI7: 49726 | AJ7: 49525 | AK7: 50501 | AL7: =J7-AK7-AJ7-AI7 -> 52080 | AM7: 52195 | AN7: 51248 | AO7: 51552 | AP7: =K7-AO7-AN7-AM7 -> 53387 | AQ7: 53421 | AR7: 52887 | AS7: 52595 | AT7: =L7-AS7-AR7-AQ7 -> 53283 | AU7: 54905 | AV7: 53827 | AY7: 44367
B8: % growth | D8: =D7/C7-1 -> -0.044768145 | E8: =E7/D7-1 -> 0.014629891 | F8: =F7/E7-1 -> 0.058975251 | G8: =G7/F7-1 -> 0.076099284 | H8: =H7/G7-1 -> 0.063616573 | I8: =I7/H7-1 -> 0.057743123 | J8: =J7/I7-1 -> 0.033213203 | K8: =K7/J7-1 -> 0.032452733 | L8: =L7/K7-1 -> 0.018254936 | S8: =S7/O7-1 -> 0.027738773 | T8: =T7/P7-1 -> 0.02454941 | U8: =U7/Q7-1 -> 0.069367355 | V8: =V7/R7-1 -> 0.11460006 | W8: =W7/S7-1 -> 0.077464426 | X8: =X7/T7-1 -> 0.053609342 | Y8: =Y7/U7-1 -> 0.091385418 | Z8: =Z7/V7-1 -> 0.081186389 | ... AV8: =AV7/AR7-1 -> 0.017773744 | AY8: =AY7/U7-1 -> 0.091385418
B9: Non-service revenues | C9: 8052 | D9: 8761 | E9: 10545 | F9: 7832 | G9: 7370 | H9: 7506 | I9: 9018 | J9: 9121 | K9: 8451 | L9: 6202 | M9: =SUM(AS9:AV9) -> 6210 | O9: 2762 | P9: 3116 | Q9: 2397 | R9: =E9-Q9-P9-O9 -> 2270 | S9: 1826 | T9: 1802 | U9: 1800 | V9: =F9-U9-T9-S9 -> 2404 | W9: 1849 | X9: 1404 | Y9: 2120 | Z9: =G9-Y9-X9-W9 -> 1997 | AA9: 2247 | AB9: 1783 | AC9: 1366 | AD9: =H9-AC9-AB9-AA9 -> 2110 | AE9: 2174 | AF9: 2113 | AG9: 2132 | AH9: =I9-AG9-AF9-AE9 -> 2599 | AI9: 2636 | AJ9: 2151 | AK9: 1817 | AL9: =J9-AK9-AJ9-AI9 -> 2517 | AM9: 2029 | AN9: 2111 | AO9: 1807 | AP9: =K9-AO9-AN9-AM9 -> 2504 | AQ9: 1856 | AR9: 1410 | AS9: 1114 | AT9: =L9-AS9-AR9-AQ9 -> 1822 | AU9: 1608 | AV9: 1666 | AY9: 2120
B10: Total revenue | C10: =C7+C9 -> 165262 | D10: =D7+D9 -> 158933 | E10: =E7+E9 -> 162914 | F10: =F7+F9 -> 169187 | G10: =G7+G9 -> 181004 | H10: =H7+H9 -> 192186 | I10: =I7+I9 -> 204362 | J10: =J7+J9 -> 210953 | ... M10: =M7+M9 -> 220820 | O10: =O7+O9 -> 40507 | P10: =P7+P9 -> 41732 | Q10: =Q7+Q9 -> 40412 | R10: =R7+R9 -> 40263 | S10: =S7+S9 -> 40618 | T10: =T7+T9 -> 41366 | U10: =U7+U9 -> 42452 | V10: =V7+V9 -> 44751 | ... AV10: =AV7+AV9 -> 55493 | AY10: =AY7+AY9 -> 46487
B11: % growth | D11: =D10/C10-1 -> -0.038296765 | E11: =E10/D10-1 -> 0.025048291 | F11: =F10/E10-1 -> 0.038504978 | G11: =G10/F10-1 -> 0.069845792 | H11: =H10/G10-1 -> 0.06177764 | I11: =I10/H10-1 -> 0.063355291 | J11: =J10/I10-1 -> 0.032251593 | K11: =K10/J10-1 -> 0.027873507 | L11: =L10/K10-1 -> 0.0071714176 | S11: =S10/O10-1 -> 0.0027402671 | T11: =T10/P10-1 -> -0.0087702483 | U11: =U10/Q10-1 -> 0.050480055 | V11: =V10/R10-1 -> 0.1114671 | W11: =W10/S10-1 -> 0.07454823 | X11: =X10/T10-1 -> 0.041652565 | Y11: =Y10/U10-1 -> 0.095048525 | Z11: =Z10/V10-1 -> 0.06773033 | ... AV11: =AV10/AR10-1 -> 0.022027 | AY11: =AY10/U10-1 -> 0.095048525
B12: Expenses
B13: Cost of sales and services | C13: 18293 | D13: 13633 | E13: 14427 | F13: 13429 | G13: 12295 | H13: 12917 | I13: 14172 | J13: 15092 | K13: 14011 | L13: 12784 | M13: =SUM(AS13:AV13) -> 13664 | O13: 3614 | P13: 3896 | Q13: 3560 | R13: =E13-Q13-P13-O13 -> 3357 | S13: 2884 | T13: 3418 | U13: 3162 | V13: =F13-U13-T13-S13 -> 3965 | W13: 3029 | X13: 2587 | Y13: 3461 | Z13: =G13-Y13-X13-W13 -> 3218 | AA13: 3588 | AB13: 3109 | AC13: 2852 | AD13: =H13-AC13-AB13-AA13 -> 3368 | AE13: 3119 | AF13: 3286 | AG13: 3654 | AH13: =I13-AG13-AF13-AE13 -> 4113 | AI13: 4047 | AJ13: 3643 | AK13: 3212 | AL13: =J13-AK13-AJ13-AI13 -> 4190 | AM13: 3253 | AN13: 3592 | AO13: 3174 | AP13: =K13-AO13-AN13-AM13 -> 3992 | AQ13: 3366 | AR13: 2592 | AS13: 2883 | AT13: =L13-AS13-AR13-AQ13 -> 3943 | AU13: 3444 | AV13: 3394 | AY13: 3461
B14: Selling, general and administrative expenses | C14: 67196 | D14: 68990 | E14: 73916 | F14: 68230 | G14: 75255 | H14: 77686 | I14: 84476 | J14: 81876 | K14: 78308 | L14: 75789 | M14: =SUM(AS14:AV14) -> 74443 | O14: 17309 | P14: 17943 | Q14: 17758 | R14: =E14-Q14-P14-O14 -> 20906 | S14: 15891 | T14: 16172 | U14: 18964 | V14: =F14-U14-T14-S14 -> 17203 | W14: =17851 -> 17851 | X14: 16337 | Y14: 16941 | Z14: =G14-Y14-X14-W14 -> 24126 | AA14: 20014 | AB14: 19768 | AC14: 19536 | AD14: =H14-AC14-AB14-AA14 -> 18368 | AE14: 23359 | AF14: 21444 | AG14: 19934 | AH14: =I14-AG14-AF14-AE14 -> 19739 | AI14: 20251 | AJ14: 19582 | AK14: 19056 | AL14: =J14-AK14-AJ14-AI14 -> 22987 | AM14: 19276 | AN14: 20469 | AO14: 18990 | AP14: =K14-AO14-AN14-AM14 -> 19573 | AQ14: 18851 | AR14: 19121 | AS14: 19041 | AT14: =L14-AS14-AR14-AQ14 -> 18776 | AU14: 18204 | AV14: 18422 | AY14: 16941
B15: Interconnection costs | C15: 9573 | D15: 6626 | E15: 5493 | F15: 3638 | G15: 2146 | H15: 3698 | I15: 6104 | J15: 10418 | K15: 13718 | L15: 16010 | M15: =SUM(AS15:AV15) -> 17781 | O15: 1874 | P15: 2034 | Q15: 1441 | R15: =E15-Q15-P15-O15 -> 144 | S15: 835 | T15: 866 | U15: 1039 | V15: =F15-U15-T15-S15 -> 898 | W15: =302 -> 302 | X15: 339 | Y15: 619 | Z15: =G15-Y15-X15-W15 -> 886 | AA15: 833 | AB15: 894 | AC15: 839 | AD15: =H15-AC15-AB15-AA15 -> 1132 | AE15: 1596 | AF15: 1252 | AG15: 1709 | AH15: =I15-AG15-AF15-AE15 -> 1547 | AI15: 2619 | AJ15: 2101 | AK15: 2743 | AL15: =J15-AK15-AJ15-AI15 -> 2955 | AM15: 3491 | AN15: 3055 | AO15: 3556 | AP15: =K15-AO15-AN15-AM15 -> 3616 | AQ15: 4464 | AR15: 4723 | AS15: 3816 | AT15: =L15-AS15-AR15-AQ15 -> 3007 | AU15: 5996 | AV15: 4962 | AY15: 619
B16: Depreciation and amortisation | C16: 34455 | D16: 51915 | E16: 47240 | F16: 39656 | G16: 47480 | H16: 52072 | I16: 98631 | J16: 58441 | K16: 55988 | L16: 59487 | M16: =SUM(AS16:AV16) -> 61997 | O16: 9373 | P16: 8516 | Q16: 9611 | R16: =E16-Q16-P16-O16 -> 19740 | S16: 9346 | T16: 9557 | U16: 9710 | V16: =F16-U16-T16-S16 -> 11043 | W16: 10286 | X16: 10611 | Y16: 10690 | Z16: =G16-Y16-X16-W16 -> 15893 | AA16: 11721 | AB16: 12633 | AC16: 12839 | AD16: =H16-AC16-AB16-AA16 -> 14879 | AE16: 12543 | AF16: 28151 | AG16: 12061 | AH16: =I16-AG16-AF16-AE16 -> 45876 | AI16: 11679 | AJ16: 12271 | AK16: 12094 | AL16: =J16-AK16-AJ16-AI16 -> 22397 | AM16: 11642 | AN16: 12639 | AO16: 12881 | AP16: =K16-AO16-AN16-AM16 -> 18826 | AQ16: 13001 | AR16: 13042 | AS16: 15633 | AT16: =L16-AS16-AR16-AQ16 -> 17811 | AU16: 14280 | AV16: 14273 | AY16: 10690
B17: Asset impairment | C17: 11042 | D17: 8258 | E17: 8065 | F17: 4833 | G17: 7646 | H17: 4942 | I17: 6044 | J17: 4432 | K17: 4321 | L17: 3970 | M17: =SUM(AS17:AV17) -> 4011 | O17: 1391 | P17: 1421 | Q17: 1352 | R17: =E17-Q17-P17-O17 -> 3901 | S17: 1357 | T17: 1287 | U17: 1208 | V17: =F17-U17-T17-S17 -> 981 | W17: 1060 | X17: 2417 | Y17: 2943 | Z17: =G17-Y17-X17-W17 -> 1226 | AA17: 1592 | AB17: 1847 | AC17: 941 | AD17: =H17-AC17-AB17-AA17 -> 562 | AE17: 1076 | AF17: 1269 | AG17: 1513 | AH17: =I17-AG17-AF17-AE17 -> 2186 | AI17: 1102 | AJ17: 1045 | AK17: 1142 | AL17: =J17-AK17-AJ17-AI17 -> 1143 | AM17: 959 | AN17: 1090 | AO17: 1020 | AP17: =K17-AO17-AN17-AM17 -> 1252 | AQ17: 867 | AR17: 1001 | AS17: 984 | AT17: =L17-AS17-AR17-AQ17 -> 1118 | AU17: 828 | AV17: 1081 | AY17: 2943
B18: Operating profit | C18: =C10-SUM(C13:C17) -> 24703 | D18: =D10-SUM(D13:D17) -> 9511 | E18: =E10-SUM(E13:E17) -> 13773 | F18: =F10-SUM(F13:F17) -> 39401 | G18: =G10-SUM(G13:G17) -> 36182 | H18: =H10-SUM(H13:H17) -> 40871 | I18: =I10-SUM(I13:I17) -> -5065 | J18: =J10-SUM(J13:J17) -> 40694 | ... M18: =M10-SUM(M13:M17) -> 48924 | O18: =O10-SUM(O13:O17) -> 6946 | P18: =P10-SUM(P13:P17) -> 7922 | Q18: =Q10-SUM(Q13:Q17) -> 6690 | R18: =R10-SUM(R13:R17) -> -7785 | S18: =S10-SUM(S13:S17) -> 10305 | T18: =T10-SUM(T13:T17) -> 10066 | U18: =U10-SUM(U13:U17) -> 8369 | V18: =V10-SUM(V13:V17) -> 10661 | ... AV18: =AV10-SUM(AV13:AV17) -> 13361 | AY18: =AY10-SUM(AY13:AY17) -> 11833
B19: % margin | C19: =C18/C10 -> 0.1494778 | D19: =D18/D10 -> 0.059842827 | E19: =E18/E10 -> 0.084541537 | F19: =F18/F10 -> 0.23288432 | G19: =G18/G10 -> 0.19989613 | H19: =H18/H10 -> 0.21266377 | I19: =I18/I10 -> -0.024784451 | J19: =J18/J10 -> 0.19290553 | ... M19: =M18/M10 -> 0.22155602 | O19: =O18/O10 -> 0.17147653 | P19: =P18/P10 -> 0.18983035 | Q19: =Q18/Q10 -> 0.16554489 | R19: =R18/R10 -> -0.1933537 | S19: =S18/S10 -> 0.25370525 | T19: =T18/T10 -> 0.24333994 | U19: =U18/U10 -> 0.1971403 | V19: =V18/V10 -> 0.23822931 | ... AV19: =AV18/AV10 -> 0.24076911 | AY19: =AY18/AY10 -> 0.25454428
B20: Other expenses - net | C20: 2632 | D20: -5058 | E20: -9042 | F20: 7065 | G20: 3161 | H20: 6615 | I20: -19097 | J20: 4217 | K20: 7794 | L20: 10859 | M20: =SUM(AS20:AV20) -> 11833 | O20: -1889 | P20: 1195 | Q20: 1003 | R20: =E20-Q20-P20-O20 -> -9351 | S20: 1292 | T20: 2008 | U20: 2825 | V20: =F20-U20-T20-S20 -> 940 | W20: 2787 | X20: 2010 | Y20: 1371 | Z20: =G20-Y20-X20-W20 -> -3007 | AA20: 2480 | AB20: 436 | AC20: 3503 | AD20: =H20-AC20-AB20-AA20 -> 196 | AE20: -3795 | AF20: -14185 | AG20: -1616 | AH20: =I20-AG20-AF20-AE20 -> 499 | AI20: 442 | AJ20: 482 | AK20: 1301 | AL20: =J20-AK20-AJ20-AI20 -> 1992 | AM20: 2411 | AN20: 1403 | AO20: 978 | AP20: =K20-AO20-AN20-AM20 -> 3002 | AQ20: 2924 | AR20: 1944 | AS20: 2312 | AT20: =L20-AS20-AR20-AQ20 -> 3679 | AU20: 2504 | AV20: 3338 | AY20: 1371
B21: Profit before tax | C21: =C18-C20 -> 22071 | D21: =D18-D20 -> 14569 | E21: =E18-E20 -> 22815 | F21: =F18-F20 -> 32336 | G21: =G18-G20 -> 33021 | H21: =H18-H20 -> 34256 | I21: =I18-I20 -> 14032 | J21: =J18-J20 -> 36477 | ... M21: =M18-M20 -> 37091 | O21: =O18-O20 -> 8835 | P21: =P18-P20 -> 6727 | Q21: =Q18-Q20 -> 5687 | R21: =R18-R20 -> 1566 | S21: =S18-S20 -> 9013 | T21: =T18-T20 -> 8058 | U21: =U18-U20 -> 5544 | V21: =V18-V20 -> 9721 | ... AV21: =AV18-AV20 -> 10023 | AY21: =AY18-AY20 -> 10462
B22: Income Tax Expense | C22: -1909 | D22: -1103 | E22: -3842 | F22: -9550 | G22: -8441 | H22: -7459 | I22: -2697 | J22: -9612 | K22: -10138 | L22: -9271 | M22: =SUM(AS22:AV22) -> -8517 | O22: -1911 | P22: -1846 | Q22: -1166 | R22: =E22-Q22-P22-O22 -> 1081 | S22: -2290 | T22: -2546 | U22: -1743 | V22: =F22-U22-T22-S22 -> -2971 | W22: -2356 | X22: -2340 | Y22: -2985 | Z22: =G22-Y22-X22-W22 -> -760 | AA22: -1822 | AB22: -1818 | AC22: -1722 | AD22: =H22-AC22-AB22-AA22 -> -2097 | AE22: -2753 | AF22: -1881 | AG22: -3232 | AH22: =I22-AG22-AF22-AE22 -> 5169 | AI22: -3148 | AJ22: -3090 | AK22: -3295 | AL22: =J22-AK22-AJ22-AI22 -> -79 | AM22: -3299 | AN22: -2487 | AO22: -3053 | AP22: =K22-AO22-AN22-AM22 -> -1299 | AQ22: -2740 | AR22: -2760 | AS22: -2083 | AT22: =L22-AS22-AR22-AQ22 -> -1688 | AU22: -2339 | AV22: -2407 | AY22: -2985
B23: Net profit/loss from continuing operations | C23: =C21+C22 -> 20162 | D23: =D21+D22 -> 13466 | E23: =E21+E22 -> 18973 | F23: =F21+F22 -> 22786 | G23: =G21+G22 -> 24580 | H23: =H21+H22 -> 26797 | I23: =I21+I22 -> 11335 | J23: =J21+J22 -> 26865 | ... M23: =M21+M22 -> 28574 | O23: =O21+O22 -> 6924 | P23: =P21+P22 -> 4881 | Q23: =Q21+Q22 -> 4521 | R23: =R21+R22 -> 2647 | S23: =S21+S22 -> 6723 | T23: =T21+T22 -> 5512 | U23: =U21+U22 -> 3801 | V23: =V21+V22 -> 6750 | ... AV23: =AV21+AV22 -> 7616 | AY23: =AY19+AY20 -> 1371.2545
B24: Net Loss From Discontinued Operations | H24: -121 | I24: -600 | J24: -41 | K24: 0 | L24: 0 | M24: =SUM(AS24:AV24) -> 0 | AE24: -20 | AF24: -41 | AG24: -64 | AH24: =I24-AG24-AF24-AE24 -> -475 | AI24: -25 | AJ24: -4 | AK24: 16 | AL24: =J24-AK24-AJ24-AI24 -> -28 | AM24: 0 | AN24: 0 | AO24: 0 | AP24: =K24-AO24-AN24-AM24 -> 0 | AQ24: 0 | AR24: 0 | AS24: 0 | AT24: =L24-AS24-AR24-AQ24 -> 0 | AU24: 0 | AV24: 0
B25: Net profit/loss | C25: =C23+C24 -> 20162 | D25: =D23+D24 -> 13466 | E25: =E23+E24 -> 18973 | F25: =F23+F24 -> 22786 | G25: =G23+G24 -> 24580 | H25: =H23+H24 -> 26676 | I25: =I23+I24 -> 10735 | J25: =J23+J24 -> 26824 | ... M25: =M23+M24 -> 28574 | O25: =O23+O24 -> 6924 | P25: =P23+P24 -> 4881 | Q25: =Q23+Q24 -> 4521 | R25: =R23+R24 -> 2647 | S25: =S23+S24 -> 6723 | T25: =T23+T24 -> 5512 | U25: =U23+U24 -> 3801 | V25: =V23+V24 -> 6750 | ... AV25: =AV23+AV24 -> 7616 | AY25: =AY21+AY22 -> 7477
B26: % margin | C26: =C25/C10 -> 0.12200022 | D26: =D25/D10 -> 0.084727527 | E26: =E25/E10 -> 0.11646022 | F26: =F25/F10 -> 0.13467938 | G26: =G25/G10 -> 0.1357981 | H26: =H25/H10 -> 0.13880303 | I26: =I25/I10 -> 0.052529335 | J26: =J25/J10 -> 0.12715629 | ... M26: =M25/M10 -> 0.12939951 | O26: =O25/O10 -> 0.17093342 | P26: =P25/P10 -> 0.11696061 | Q26: =Q25/Q10 -> 0.11187271 | R26: =R25/R10 -> 0.065742741 | S26: =S25/S10 -> 0.16551775 | T26: =T25/T10 -> 0.13324953 | U26: =U25/U10 -> 0.089536418 | V26: =V25/V10 -> 0.15083462 | ... AV26: =AV25/AV10 -> 0.13724254 | AY26: =AY25/AY10 -> 0.16084067
B28: Net income attributACle to non-controlling interests | C28: 156 | D28: 95 | E28: 57 | F28: 265 | G28: 296 | H28: 309 | I28: 250 | J28: 210 | K28: 248 | L28: 207 | M28: =SUM(AS28:AV28) -> 254 | O28: 24 | P28: 19 | Q28: 14 | R28: =E28-Q28-P28-O28 -> 0 | S28: 15 | T28: 13 | U28: 12 | V28: =F28-U28-T28-S28 -> 225 | W28: 63 | X28: 80 | Y28: 70 | Z28: =G28-Y28-X28-W28 -> 83 | AA28: 71 | AB28: 75 | AC28: 76 | AD28: =H28-AC28-AB28-AA28 -> 87 | AE28: 75 | AF28: 116 | AG28: 83 | AH28: =I28-AG28-AF28-AE28 -> -24 | AI28: 34 | AJ28: 22 | AK28: 63 | AL28: =J28-AK28-AJ28-AI28 -> 91 | AM28: 69 | AN28: 35 | AO28: 50 | AP28: =K28-AO28-AN28-AM28 -> 94 | AQ28: 39 | AR28: 2 | AS28: 23 | AT28: =L28-AS28-AR28-AQ28 -> 143 | AU28: 49 | AV28: 39 | AY28: 70
B29: Net income attributACle to shareholders | C29: 20006 | D29: 13371 | E29: 18916 | F29: 22521 | G29: 24284 | H29: 26367 | I29: 10485 | J29: 26614 | K29: 32307 | L29: 30011 | M29: =SUM(AS29:AV29) -> 28320 | O29: 6900 | P29: 4862 | Q29: 4507 | R29: =E29-Q29-P29-O29 -> 2647 | S29: 6708 | T29: 5499 | U29: 3789 | V29: =F29-U29-T29-S29 -> 6525 | W29: 5912 | X29: 6368 | Y29: 7407 | Z29: =G29-Y29-X29-W29 -> 4597 | AA29: 5803 | AB29: 7119 | AC29: 5925 | AD29: =H29-AC29-AB29-AA29 -> 7520 | AE29: 9079 | AF29: 7707 | AG29: 10713 | AH29: =I29-AG29-AF29-AE29 -> -17014 | AI29: 9015 | AJ29: 9436 | AK29: 9428 | AL29: =J29-AK29-AJ29-AI29 -> -1265 | AM29: 9824 | AN29: 8589 | AO29: 9657 | AP29: =K29-AO29-AN29-AM29 -> 4237 | AQ29: 9025 | AR29: 9112 | AS29: 6934 | AT29: =L29-AS29-AR29-AQ29 -> 4940 | AU29: 8869 | AV29: 7577 | AY29: 7407
B30: Check | C30: =C25-C28-C29 -> 0 | D30: =D25-D28-D29 -> 0 | E30: =E25-E28-E29 -> 0 | F30: =F25-F28-F29 -> 0 | G30: =G25-G28-G29 -> 0 | H30: =H25-H28-H29 -> 0 | I30: =I25-I28-I29 -> 0 | J30: =J25-J28-J29 -> 0 | ... M30: =M25-M28-M29 -> 0 | O30: =O25-O28-O29 -> 0 | P30: =P25-P28-P29 -> 0 | Q30: =Q25-Q28-Q29 -> 0 | R30: =R25-R28-R29 -> 0 | S30: =S25-S28-S29 -> 0 | T30: =T25-T28-T29 -> 0 | U30: =U25-U28-U29 -> 0 | V30: =V25-V28-V29 -> 0 | ... AV30: =AV25-AV28-AV29 -> 0 | AY30: =AY25-AY28-AY29 -> 0
B32: As % of service revenues unless stated otherwise
B33: =B13 -> Cost of sales and services | C33: =C13/C7 -> 0.11636028 | D33: =D13/D7 -> 0.090782569 | E33: =E13/E7 -> 0.094684614 | F33: =F13/F7 -> 0.083226426 | G33: =G13/G7 -> 0.070809864 | H33: =H13/H7 -> 0.069942603 | I33: =I13/I7 -> 0.072548939 | J33: =J13/J7 -> 0.07477506 | ... M33: =M13/M7 -> 0.063668981 | O33: =O13/O7 -> 0.095747781 | P33: =P13/P7 -> 0.10089082 | Q33: =Q13/Q7 -> 0.093647245 | R33: =R13/R7 -> 0.088358382 | S33: =S13/S7 -> 0.074345226 | T33: =T13/T7 -> 0.086391669 | U33: =U13/U7 -> 0.077782151 | V33: =V13/V7 -> 0.09363119 | ... AV33: =AV13/AV7 -> 0.063053858 | AY33: =AY13/AY7 -> 0.07800843
B34: =B14 -> Selling, general and administrative expenses | C34: =C14/C7 -> 0.42742828 | D34: =D14/D7 -> 0.45940655 | E34: =E14/E7 -> 0.4851118 | F34: =F14/F7 -> 0.42285643 | G34: =G14/G7 -> 0.43341166 | H34: =H14/H7 -> 0.42065194 | I34: =I14/I7 -> 0.43244737 | J34: =J14/J7 -> 0.40566412 | ... M34: =M14/M7 -> 0.34687573 | O34: =O14/O7 -> 0.4585773 | P34: =P14/P7 -> 0.46465196 | Q34: =Q14/Q7 -> 0.4671314 | R34: =R14/R7 -> 0.55025926 | S34: =S14/S7 -> 0.40964632 | T34: =T14/T7 -> 0.40875543 | U34: =U14/U7 -> 0.46649611 | V34: =V14/V7 -> 0.40623893 | ... AV34: =AV14/AV7 -> 0.3422446 | AY34: =AY14/AY7 -> 0.38183785
B35: =B15 -> Interconnection costs | C35: =C15/C7 -> 0.060893073 | D35: =D15/D7 -> 0.044122739 | E35: =E15/E7 -> 0.03605064 | F35: =F15/F7 -> 0.022546559 | G35: =G15/G7 -> 0.012359331 | H35: =H15/H7 -> 0.020023825 | I35: =I15/I7 -> 0.03124744 | J35: =J15/J7 -> 0.051617187 | ... M35: =M15/M7 -> 0.082852616 | O35: =O15/O7 -> 0.04964896 | P35: =P15/P7 -> 0.052672467 | Q35: =Q15/Q7 -> 0.03790609 | R35: =R15/R7 -> 0.0037901719 | S35: =S15/S7 -> 0.021525057 | T35: =T15/T7 -> 0.021888586 | U35: =U15/U7 -> 0.025558398 | V35: =V15/V7 -> 0.021205752 | ... AV35: =AV15/AV7 -> 0.09218422 | AY35: =AY15/AY7 -> 0.013951811
B36: =B18 -> Operating profit | C36: =C18/C7 -> 0.15713377 | D36: =D18/D7 -> 0.063334044 | E36: =E18/E7 -> 0.090392403 | F36: =F18/F7 -> 0.24418828 | G36: =G18/G7 -> 0.20838085 | H36: =H18/H7 -> 0.22130713 | I36: =I18/I7 -> -0.025928618 | J36: =J18/J7 -> 0.20162313 | ... M36: =M18/M7 -> 0.22796701 | O36: =O18/O7 -> 0.18402437 | P36: =P18/P7 -> 0.20514813 | Q36: =Q18/Q7 -> 0.17598316 | R36: =R18/R7 -> -0.20490617 | S36: =S18/S7 -> 0.26564756 | T36: =T18/T7 -> 0.25442321 | U36: =U18/U7 -> 0.20586933 | V36: =V18/V7 -> 0.25175337 | ... AV36: =AV18/AV7 -> 0.24822115 | AY36: =AY18/AY7 -> 0.26670724
B37: PBT | C37: =C21/C7 -> 0.14039183 | D37: =D21/D7 -> 0.097015422 | E37: =E21/E7 -> 0.14973518 | F37: =F21/F7 -> 0.20040284 | G37: =G21/G7 -> 0.19017589 | H37: =H21/H7 -> 0.18548841 | I37: =I21/I7 -> 0.071832255 | J37: =J21/J7 -> 0.18072952 | ... M37: =M21/M7 -> 0.17282978 | O37: =O21/O7 -> 0.23407074 | P37: =P21/P7 -> 0.1742024 | Q37: =Q21/Q7 -> 0.14959884 | R37: =R21/R7 -> 0.041218119 | S37: =S21/S7 -> 0.23234172 | T37: =T21/T7 -> 0.20367 | U37: =U21/U7 -> 0.13637705 | V37: =V21/V7 -> 0.22955581 | ... AV37: =AV21/AV7 -> 0.18620767 | AY37: =AY21/AY7 -> 0.23580589
B38: Income Tax Expense as a % PBT | C38: =-C22/C21 -> 0.086493589 | D38: =-D22/D21 -> 0.075708697 | E38: =-E22/E21 -> 0.16839798 | F38: =-F22/F21 -> 0.29533647 | G38: =-G22/G21 -> 0.25562521 | H38: =-H22/H21 -> 0.21774288 | I38: =-I22/I21 -> 0.19220353 | J38: =-J22/J21 -> 0.26350851 | ... M38: =-M22/M21 -> 0.22962444 | O38: =-O22/O21 -> 0.21629881 | P38: =-P22/P21 -> 0.27441653 | Q38: =-Q22/Q21 -> 0.20502901 | R38: =-R22/R21 -> -0.69029374 | S38: =-S22/S21 -> 0.25407744 | T38: =-T22/T21 -> 0.3159593 | U38: =-U22/U21 -> 0.31439394 | V38: =-V22/V21 -> 0.30562699 | ... AV38: =-AV22/AV21 -> 0.24014766 | AY38: =-AY22/AY21 -> 0.28531829
B39: =B20 -> Other expenses - net | C39: =C20/C7 -> 0.016741938 | D39: =D20/D7 -> -0.033681379 | E39: =E20/E7 -> -0.05934278 | F39: =F20/F7 -> 0.043785442 | G39: =G20/G7 -> 0.01820496 | H39: =H20/H7 -> 0.035818713 | I39: =I20/I7 -> -0.097760873 | J39: =J20/J7 -> 0.020893614 | ... M39: =M20/M7 -> 0.055137226 | O39: =O20/O7 -> -0.050046364 | P39: =P20/P7 -> 0.030945722 | Q39: =Q20/Q7 -> 0.026384322 | R39: =R20/R7 -> -0.24612429 | S39: =S20/S7 -> 0.033305836 | T39: =T20/T7 -> 0.05075321 | U39: =U20/U7 -> 0.069492276 | V39: =V20/V7 -> 0.022197558 | ... AV39: =AV20/AV7 -> 0.062013488 | AY39: =AY20/AY7 -> 0.030901346
B41: Working capital/sales | C41: =C97/C81 -> -0.14988322 | D41: =D97/D81 -> -0.14314837 | E41: =E97/E81 -> -0.2926452 | F41: =F97/F81 -> -0.30733449 | G41: =G97/G81 -> -0.31090473 | H41: =H97/H81 -> -0.38642773 | I41: =I97/I81 -> -0.36877697 | J41: =J97/J81 -> -0.24454736 | ... M41: =M97/M81 -> -0.068675845 | R41: =R97/R81 -> -0.2926452 | S41: =S97/S81 -> -0.28257016 | T41: =T97/T81 -> -0.30377046 | U41: =U97/U81 -> -0.33776161 | V41: =V97/V81 -> -0.30733449 | W41: =W97/W81 -> -0.30916587 | X41: =X97/X81 -> -0.18130598 | Y41: =Y97/Y81 -> -0.18603384 | ... AV41: =AV97/AV81 -> -0.068675845 | AY41: =AY97/AY81 -> -0.18603384
B43: EBITDA | C43: =C3 -> 42735 | D43: =D3 -> 43100 | E43: =E3 -> 43465 | F43: =F3 -> 43830 | G43: =G3 -> 44196 | H43: =H3 -> 44561 | I43: =I3 -> 44926 | J43: =J3 -> 45291 | ... M43: =M3 -> 46203 | O43: =O3 -> 43190 | P43: =P3 -> 43281 | Q43: =Q3 -> 43373 | R43: =R3 -> 43465 | S43: =S3 -> 43555 | T43: =T3 -> 43646 | U43: =U3 -> 43738 | V43: =V3 -> 43830 | ... AV43: =AV3 -> 46203 | AY43: =AY3 -> 44104
B44: =B18 -> Operating profit | C44: =C18 -> 24703 | D44: =D18 -> 9511 | E44: =E18 -> 13773 | F44: =F18 -> 39401 | G44: =G18 -> 36182 | H44: =H18 -> 40871 | I44: =I18 -> -5065 | ... M44: =M18 -> 48924 | O44: =O18 -> 6946 | P44: =P18 -> 7922 | Q44: =Q18 -> 6690 | R44: =R18 -> -7785 | S44: =S18 -> 10305 | T44: =T18 -> 10066 | U44: =U18 -> 8369 | V44: =V18 -> 10661 | ... AV44: =AV18 -> 13361 | AY44: =AY18 -> 11833
B45: Depreciation & amortisation | C45: 34455 | D45: 51915 | E45: 47240 | F45: 39656 | G45: 47480 | H45: 52169 | I45: 98714 | J45: 58462 | K45: 55988 | L45: 59487 | M45: =SUM(AS45:AV45) -> 61997 | O45: 9373 | P45: 8516 | Q45: 9611 | R45: =#REF!-Q45-P45-O45 -> #REF! | S45: 9346 | T45: 9557 | U45: 9710 | V45: =F45-U45-T45-S45 -> 11043 | W45: 10286 | X45: 10611 | Y45: 10690 | Z45: =G45-Y45-X45-W45 -> 15893 | AA45: 11721 | AB45: 12633 | AC45: 12839 | AD45: =H45-AC45-AB45-AA45 -> 14976 | AE45: 12564 | AF45: 28151 | AG45: 12061 | AH45: =I45-AG45-AF45-AE45 -> 45938 | AI45: 11688 | AJ45: 12271 | AK45: 12094 | AL45: =J45-AK45-AJ45-AI45 -> 22409 | AM45: 11642 | AN45: 12639 | AO45: 12881 | AP45: =K45-AO45-AN45-AM45 -> 18826 | AQ45: 13001 | AR45: =26043-AQ45 -> 13042 | AS45: =41820-AR45-AQ45 -> 15777 | AT45: =L45-AS45-AR45-AQ45 -> 17667 | AU45: 14280 | AV45: =28553-AU45 -> 14273 | AY45: 10690
B46: EBITDA | C46: =C44+C45 -> 59158 | D46: =D44+D45 -> 61426 | E46: =E44+E45 -> 61013 | F46: =F44+F45 -> 79057 | G46: =G44+G45 -> 83662 | H46: =H44+H45 -> 93040 | I46: =I44+I45 -> 93649 | J46: =J44+J45 -> 99156 | ... M46: =M44+M45 -> 110921 | O46: =O44+O45 -> 16319 | P46: =P44+P45 -> 16438 | Q46: =Q44+Q45 -> 16301 | R46: =R44+R45 -> #REF! | S46: =S44+S45 -> 19651 | T46: =T44+T45 -> 19623 | U46: =U44+U45 -> 18079 | V46: =V44+V45 -> 21704 | ... AV46: =AV44+AV45 -> 27634 | AY46: =AY44+AY45 -> 22523
B47: % growth | D47: =(D46-C46)/C46 -> 0.03833801 | E47: =(E46-D46)/D46 -> -0.0067235373 | F47: =(F46-E46)/E46 -> 0.29574025 | G47: =(G46-F46)/F46 -> 0.058249111 | H47: =(H46-G46)/G46 -> 0.1120939 | I47: =(I46-H46)/H46 -> 0.0065455718 | J47: =(J46-I46)/I46 -> 0.058804686 | K47: =(K46-J46)/J46 -> 0.073812982 | L47: =(L46-K46)/K46 -> 0.031556703 | S47: =S46/O46-1 -> 0.20417918 | T47: =T46/P46-1 -> 0.19375836 | U47: =U46/Q46-1 -> 0.10907306 | V47: =V46/R46-1 -> #REF! | W47: =W46/S46-1 -> 0.089206656 | X47: =X46/T46-1 -> 0.091015645 | Y47: =Y46/U46-1 -> 0.24581006 | Z47: =Z46/V46-1 -> -0.15563951 | ... AV47: =AV46/AR46-1 -> 0.028816083 | AY47: =AY46/U46-1 -> 0.24581006
B48: % margin | C48: =C46/C10 -> 0.35796493 | D48: =D46/D10 -> 0.3864899 | E48: =E46/E10 -> 0.37451048 | F48: =F46/F10 -> 0.46727585 | G48: =G46/G10 -> 0.46221078 | H48: =H46/H10 -> 0.48411435 | I48: =I46/I10 -> 0.45825056 | J48: =J46/J10 -> 0.47003835 | ... M48: =M46/M10 -> 0.5023141 | O48: =O46/O10 -> 0.40286864 | P48: =P46/P10 -> 0.39389437 | Q48: =Q46/Q10 -> 0.40337029 | R48: =R46/R10 -> #REF! | S48: =S46/S10 -> 0.48380029 | T48: =T46/T10 -> 0.47437509 | U48: =U46/U10 -> 0.42586922 | V48: =V46/V10 -> 0.48499475 | ... AV48: =AV46/AV10 -> 0.49797272 | AY48: =AY46/AY10 -> 0.48450104
B50: Adjustment | C50: =C51-C46 -> -4629 | D50: =D51-D46 -> -2268 | E50: =E51-E46 -> -4307 | F50: =F51-F46 -> -532 | G50: =G51-G46 -> 1112 | H50: =H51-H46 -> 3129 | I50: =I51-I46 -> 6613 | J50: =J51-J46 -> 5141 | ... M50: =M51-M46 -> 828 | O50: =O51-O46 -> -1425 | P50: =P51-P46 -> -1599 | Q50: =Q51-Q46 -> -1637 | R50: =R51-R46 -> #REF! | S50: =S51-S46 -> 125 | T50: =T51-T46 -> -89 | U50: =U51-U46 -> -222 | V50: =V51-V46 -> -346 | ... AV50: =AV51-AV46 -> 128 | AY50: =AY51-AY46 -> -168
B51: Adj. EBITDA | C51: =61161-6632 -> 54529 | D51: =66174-7016 -> 59158 | E51: =64027-7321 -> 56706 | F51: =79815-1290 -> 78525 | G51: =86158-1384 -> 84774 | H51: 96169 | I51: 100262 | J51: 104297 | K51: 108515 | L51: 111231 | M51: =SUM(AS51:AV51) -> 111749 | O51: =16533-O54 -> 14894 | P51: =33185-16533-P54 -> 14839 | Q51: =49699-5302-P51-O51 -> 14664 | R51: =E51-Q51-P51-O51 -> 12309 | S51: =19847-71 -> 19776 | T51: =39666 -19847-T54 -> 19534 | U51: =57935-768-T51-S51 -> 17857 | V51: =F51-U51-T51-S51 -> 21358 | W51: =21612-338 -> 21274 | X51: =43165-21612-X54 -> 21440 | Y51: =65864-795-X51-W51 -> 22355 | Z51: =G51-Y51-X51-W51 -> 19705 | AA51: =23072 -> 23072 | AB51: =46327-AA51 -> 23255 | AC51: =70816-AB51-AA51 -> 24489 | AD51: =H51-AC51-AB51-AA51 -> 25353 | AE51: =20907 -> 20907 | AF51: =44736-AE51 -> 23829 | AG51: =69342-AF51-AE51 -> 24606 | AH51: =I51-AG51-AF51-AE51 -> 30920 | AI51: 26021 | AJ51: 26107 | AK51: 26236 | AL51: =J51-AK51-AJ51-AI51 -> 25933 | AM51: 27315 | AN51: 26621 | AO51: =80718-AN51-AM51 -> 26782 | AP51: =K51-AO51-AN51-AM51 -> 27797 | AQ51: 27865 | AR51: =55532-AQ51 -> 27667 | AS51: =82845-AR51-AQ51 -> 27313 | AT51: =L51-AS51-AR51-AQ51 -> 28386 | AU51: 28288 | AV51: =56050-AU51 -> 27762 | AY51: =65864-795-X51-W51 -> 22355
B52: % growth | D52: =(D51-C51)/C51 -> 0.084890609 | E52: =(E51-D51)/D51 -> -0.041448325 | F52: =(F51-E51)/E51 -> 0.3847741 | G52: =(G51-F51)/F51 -> 0.079579752 | H52: =(H51-G51)/G51 -> 0.13441621 | I52: =(I51-H51)/H51 -> 0.042560492 | J52: =(J51-I51)/I51 -> 0.040244559 | K52: =(K51-J51)/J51 -> 0.040442199 | L52: =(L51-K51)/K51 -> 0.025028798 | S52: =S51/O51-1 -> 0.327783 | T52: =T51/P51-1 -> 0.31639598 | U52: =U51/Q51-1 -> 0.21774414 | V52: =V51/R51-1 -> 0.73515314 | W52: =W51/S51-1 -> 0.075748382 | X52: =X51/T51-1 -> 0.097573462 | Y52: =Y51/U51-1 -> 0.25189002 | Z52: =Z51/V51-1 -> -0.077394887 | ... AV52: =AV51/AR51-1 -> 0.0034336936 | AY52: =AY51/U51-1 -> 0.25189002
B53: % margin | C53: =C51/C10 -> 0.32995486 | D53: =D51/D10 -> 0.37221974 | E53: =E51/E10 -> 0.34807322 | F53: =F51/F10 -> 0.4641314 | G53: =G51/G10 -> 0.46835429 | H53: =H51/H10 -> 0.50039545 | I53: =I51/I10 -> 0.4906098 | J53: =J51/J10 -> 0.49440871 | ... M53: =M51/M10 -> 0.50606376 | O53: =O51/O10 -> 0.36768954 | P53: =P51/P10 -> 0.35557845 | Q53: =Q51/Q10 -> 0.36286252 | R53: =R51/R10 -> 0.30571492 | S53: =S51/S10 -> 0.48687774 | T53: =T51/T10 -> 0.47222357 | U53: =U51/U10 -> 0.42063978 | V53: =V51/V10 -> 0.47726308 | ... AV53: =AV51/AV10 -> 0.50027931 | AY53: =AY51/AY10 -> 0.48088713
B54: Rent | C54: 6632 | D54: 7016 | E54: 7321 | F54: 1290 | G54: 1384 | H54: 2231 | I54: 2031 | J54: 1372 | K54: 1398 | L54: 1413 | M54: =SUM(AS54:AV54) -> 1475 | O54: 1639 | P54: =3452-O54 -> 1813 | Q54: =5302-P54-O54 -> 1850 | R54: =E54-Q54-P54-O54 -> 2019 | S54: 71 | T54: =356-S54 -> 285 | U54: =768-T54-S54 -> 412 | V54: =F54-U54-T54-S54 -> 522 | W54: 338 | X54: =451-W54 -> 113 | Y54: =795-X54-W54 -> 344 | Z54: =G54-Y54-X54-W54 -> 589 | AA54: 523 | AB54: =964-AA54 -> 441 | AC54: =1624-AB54-AA54 -> 660 | AD54: =H54-AC54-AB54-AA54 -> 607 | AE54: 392 | AF54: =1110-AE54 -> 718 | AG54: 1450 | AH54: =I54-AG54-AF54-AE54 -> -529 | AI54: 460 | AJ54: =1032-AI54 -> 572 | AK54: 1196 | AL54: =J54-AK54-AJ54-AI54 -> -856 | AM54: 372 | AN54: =621-AM54 -> 249 | AO54: 905 | AP54: =K54-AO54-AN54-AM54 -> -128 | AQ54: 313 | AR54: =592-AQ54 -> 279 | AS54: 1000 | AT54: =L54-AS54-AR54-AQ54 -> -179 | AU54: 326 | AV54: =654-AU54 -> 328 | AY54: =795-X54-W54 -> 344
B55: Adj. EBITDAR | C55: =C54+C51 -> 61161 | D55: =D54+D51 -> 66174 | E55: =E54+E51 -> 64027 | F55: =F54+F51 -> 79815 | G55: =G54+G51 -> 86158 | H55: =H54+H51 -> 98400 | I55: =I54+I51 -> 102293 | J55: =J54+J51 -> 105669 | ... M55: =M54+M51 -> 113224 | O55: =O51+O54 -> 16533 | P55: =P51+P54 -> 16652 | Q55: =Q51+Q54 -> 16514 | R55: =R51+R54 -> 14328 | S55: =S51+S54 -> 19847 | T55: =T51+T54 -> 19819 | U55: =U51+U54 -> 18269 | V55: =V51+V54 -> 21880 | ... AV55: =AV51+AV54 -> 28090 | AY55: =AY51+AY54 -> 22699
B56: rent % of sales | C56: =C54/C7 -> 0.042185612 | D56: =D54/D7 -> 0.046719761 | E56: =E54/E7 -> 0.048047831 | F56: =F54/F7 -> 0.0079947941 | G56: =G54/G7 -> 0.0079707891 | H56: =H54/H7 -> 0.012080355 | I56: =I54/I7 -> 0.010397043 | J56: =J54/J7 -> 0.0067977328 | ... M56: =M54/M7 -> 0.0068729323 | O56: =O54/O7 -> 0.04342297 | P56: =P54/P7 -> 0.046949451 | Q56: =Q54/Q7 -> 0.048665001 | R56: =R54/R7 -> 0.053141368 | S56: =S54/S7 -> 0.0018302743 | T56: =T54/T7 -> 0.0072035184 | U56: =U54/U7 -> 0.010134803 | V56: =V54/V7 -> 0.012326729 | ... AV56: =AV54/AV7 -> 0.0060935962 | AY56: =AY54/AY7 -> 0.0077535105
B58: CASH FLOW | C58: =C43 -> 42735 | D58: =D43 -> 43100 | E58: =E43 -> 43465 | F58: =F43 -> 43830 | G58: =G43 -> 44196 | H58: =H43 -> 44561 | I58: =I43 -> 44926 | J58: =J43 -> 45291 | ... M58: =M43 -> 46203 | O58: =O43 -> 43190 | P58: =P43 -> 43281 | Q58: =Q43 -> 43373 | R58: =R43 -> 43465 | S58: =S43 -> 43555 | T58: =T43 -> 43646 | U58: =U43 -> 43738 | V58: =V43 -> 43830 | ... AV58: =AV43 -> 46203 | AY58: =AY43 -> 44104
B59: Adj EBITDA | C59: =C51 -> 54529 | D59: =D51 -> 59158 | E59: =E51 -> 56706 | F59: =F51 -> 78525 | G59: =G51 -> 84774 | H59: =H51 -> 96169 | I59: =I51 -> 100262 | J59: =J51 -> 104297 | ... M59: =M51 -> 111749 | O59: =O51 -> 14894 | P59: =P51 -> 14839 | Q59: =Q51 -> 14664 | R59: =R51 -> 12309 | S59: =S51 -> 19776 | T59: =T51 -> 19534 | U59: =U51 -> 17857 | V59: =V51 -> 21358 | ... AV59: =AV51 -> 27762 | AY59: =AY51 -> 22355
B60: Working Capital | C60: =-5634-99-7060-917+1-5863-10+1358+755 -> -17469 | D60: =-212+162-10674-542+13-5841+38+4622-1392 -> -13826 | E60: =-4318-12175+26+390-250-5733-11+7729+5184 -> -9158 | F60: =-28898-198-1560+12+337+12-7965-1559+18768+4375 -> -16676 | G60: =-18894+324+1196-1017+160+166-249+371+5220+7924+7178 -> 2379 | H60: =-34002-38-3713-120+57-101-3846-95+29382-301 -> -12777 | I60: =12218-209-8366+208+850+44-6847-68-18306-507 -> -20983 | J60: =10264+101+952+156+1629-75-5174-57-21285-4414 -> -17903 | K60: =85013-115098 -> -30085 | L60: =101394-119282 -> -17888 | M60: =SUM(AS60:AV60) -> -20036 | O60: =947-326-5154-1077+486+7-3475+14+4534+2380 -> -1664 | P60: =1034+22-8461-1539-28+15-4361+34+14470+3348-O60 -> 6198 | Q60: =837+243-12385-1686+356+20-4849+30+4977+1624-P60-O60 -> -15367 | R60: =E60-Q60-P60-O60 -> 1675 | S60: =-4653+159+774+149+246+2-2570-29+2430-1337 -> -4829 | T60: =-12435-461+2995+227+320+5-3267-1885+5773+2442-S60 -> -1457 | U60: =-17412+157+1656-36+388+11-5945+78+12409+4664-T60-S60 -> 2256 | V60: =F60-U60-T60-S60 -> -12646 | W60: =-2129+429-2776+596-6-0-1392-473-564+154 -> -6161 | X60: =-431+452-9484+589-83+8-1530-1777-2913+1075-W60 -> -7933 | Y60: =-8475+571-9676-820+31+108-1683+51+6063+3883-X60-W60 -> 4147 | Z60: =G60-Y60-X60-W60 -> 12326 | AA60: =-10652-53-1239-243-79-0-2240-1+9251-1611 -> -6867 | AB60: =-29724+13-1484-569-171-97-2440+131+28153-1263-AA60 -> -584 | AC60: =-32221-284-2733-1210-7-103-2764+120+29184+2587-AB60-AA60 -> 20 | AD60: =H60-AC60-AB60-AA60 -> -5346 | AE60: =-4990-38-3166-1511+247+2-2525+34+6016+3867 -> -2064 | AF60: =-764-1475+3221+117-71+7-7956-155-5084+4014-AE60 -> -6082 | AG60: =56897-73258-AF60-AE60 -> -8215 | AH60: =I60-AG60-AF60-AE60 -> -4622 | AI60: =26632-24794 -> 1838 | AJ60: =44277-53802-AI60 -> -11363 | AK60: =68199-81311-AJ60-AI60 -> -3587 | AL60: =J60-AK60-AJ60-AI60 -> -4791 | AM60: =24529-28421 -> -3892 | AN60: =53138-56085-AM60 -> 945 | AO60: =70684-85719-AN60-AM60 -> -12088 | AP60: =K60-AO60-AN60-AM60 -> -15050 | AQ60: =25444-29865 -> -4421 | AR60: =49677-58990-AQ60 -> -4892 | AS60: =79422-88688-AR60-AQ60 -> 47 | AT60: =L60-AS60-AR60-AQ60 -> -8622 | AU60: =23568-30392 -> -6824 | AV60: =48653-60114-AU60 -> -4637 | AY60: =-8475+571-9676-820+31+108-1683+54+6429+3880-X60-W60 -> 4513
B61: Taxes | C61: -6965 | D61: -4550 | E61: -2444 | F61: -2097 | G61: -2248 | H61: -2122 | I61: -4188 | J61: -2058 | K61: -3282 | L61: -2656 | M61: =SUM(AS61:AV61) -> -2561 | O61: -183 | P61: =-667-O61 -> -484 | Q61: =-1686-P61-O61 -> -1019 | R61: =E61-Q61-P61-O61 -> -758 | S61: -554 | T61: =-1176-S61 -> -622 | U61: =-1532-T61-S61 -> -356 | V61: =F61-U61-T61-S61 -> -565 | W61: -372 | X61: =-849-W61 -> -477 | Y61: =-1112-X61-W61 -> -263 | Z61: =G61-Y61-X61-W61 -> -1136 | AA61: -300 | AB61: =-310-AA61 -> -10 | AC61: =-1764-AB61-AA61 -> -1454 | AD61: =H61-AC61-AB61-AA61 -> -358 | AE61: -360 | AF61: =-2154-AE61 -> -1794 | AG61: =-3614-AF61-AE61 -> -1460 | AH61: =I61-AG61-AF61-AE61 -> -574 | AI61: 0 | AJ61: =-1372-AI61 -> -1372 | AK61: =-2361-AJ61-AI61 -> -989 | AL61: =J61-AK61-AJ61-AI61 -> 303 | AM61: -762 | AN61: =-2109-AM61 -> -1347 | AO61: =-2566-AN61-AM61 -> -457 | AP61: =K61-AO61-AN61-AM61 -> -716 | AQ61: -899 | AR61: =-2972-AQ61 -> -2073 | AS61: =-3657-AR61-AQ61 -> -685 | AT61: =L61-AS61-AR61-AQ61 -> 1001 | AU61: -817 | AV61: =-2877-AU61 -> -2060 | AY61: =-1112-X61-W61 -> -263
B62: Cash interest paid | C62: -6512 | D62: -7076 | E62: -6614 | F62: -7143 | G62: -8348 | H62: -8922 | I62: -9013 | J62: -9715 | K62: -10740 | L62: -13233 | M62: =SUM(AS62:AV62) -> -13113 | O62: -1513 | P62: =-3111-O62 -> -1598 | Q62: =-4802-P62-O62 -> -1691 | R62: =E62-Q62-P62-O62 -> -1812 | S62: -1703 | T62: =-3529-S62 -> -1826 | U62: =-5252-T62-S62 -> -1723 | V62: =F62-U62-T62-S62 -> -1891 | W62: -1955 | X62: =-4086-W62 -> -2131 | Y62: =-8498-X62-W62 -> -4412 | Z62: =G62-Y62-X62-W62 -> 150 | AA62: -2116 | AB62: =-4316-AA62 -> -2200 | AC62: =-6637-AB62-AA62 -> -2321 | AD62: =H62-AC62-AB62-AA62 -> -2285 | AE62: -2070 | AF62: =-4430-AE62 -> -2360 | AG62: =-6590-AF62-AE62 -> -2160 | AH62: =I62-AG62-AF62-AE62 -> -2423 | AI62: -2203 | AJ62: =-4479-AI62 -> -2276 | AK62: =-6831-AJ62-AI62 -> -2352 | AL62: =J62-AK62-AJ62-AI62 -> -2884 | AM62: -2140 | AN62: =-4858-AM62 -> -2718 | AO62: =-7285-AN62-AM62 -> -2427 | AP62: =K62-AO62-AN62-AM62 -> -3455 | AQ62: -2808 | AR62: =-6494-AQ62 -> -3686 | AS62: =-9430-AR62-AQ62 -> -2936 | AT62: =L62-AS62-AR62-AQ62 -> -3803 | AU62: -3090 | AV62: =-6374-AU62 -> -3284 | AY62: =-6052-X62-W62 -> -1966
B63: Net cash from operations | C63: =SUM(C59:C62) -> 23583 | D63: =SUM(D59:D62) -> 33706 | E63: =SUM(E59:E62) -> 38490 | F63: =SUM(F59:F62) -> 52609 | G63: =SUM(G59:G62) -> 76557 | H63: =SUM(H59:H62) -> 72348 | I63: =SUM(I59:I62) -> 66078 | J63: =SUM(J59:J62) -> 74621 | ... M63: =SUM(M59:M62) -> 76039 | O63: =SUM(O59:O62) -> 11534 | P63: =SUM(P59:P62) -> 18955 | Q63: =SUM(Q59:Q62) -> -3413 | R63: =SUM(R59:R62) -> 11414 | S63: =SUM(S59:S62) -> 12690 | T63: =SUM(T59:T62) -> 15629 | U63: =SUM(U59:U62) -> 18034 | V63: =SUM(V59:V62) -> 6256 | ... AV63: =SUM(AV59:AV62) -> 17781 | AY63: =SUM(AY59:AY62) -> 24639
B64: Net Capex | C64: =1889-566-42259 -> -40936 | D64: =484-816-36616 -> -36948 | E64: =345-1524-47247 -> -48426 | F64: =224-1455-88246 -> -89477 | G64: =151-1597-76503 -> -77949 | H64: =1217-1582-102395 -> -102760 | I64: =60833-1748-93803 -> -34718 | J64: =23971-2169-76266 -> -54464 | K64: =4827-2589-65668 -> -63430 | L64: =-60140+1220-2724 -> -61644 | M64: =SUM(AS64:AV64) -> -51971 | O64: =22-304-12640 -> -12922 | P64: =59-706-31303-O64 -> -19028 | Q64: =276-1120-39364-P64-O64 -> -8258 | R64: =E64-Q64-P64-O64 -> -8218 | S64: =37-358-18580 -> -18901 | T64: =74-768-40193-S64 -> -21986 | U64: =172-1152-60005-T64-S64 -> -20098 | V64: =F64-U64-T64-S64 -> -28492 | W64: =33-391-16683 -> -17041 | X64: =57-819-40227-W64 -> -23948 | Y64: =61-1247-59016-X64-W64 -> -19213 | Z64: =G64-Y64-X64-W64 -> -17747 | AA64: =22-376-19629 -> -19983 | AB64: =730-808-54331-AA64 -> -34426 | AC64: =1149-1208-83322-AB64-AA64 -> -28972 | AD64: =H64-AC64-AB64-AA64 -> -19379 | AE64: =194-421-22168 -> -22395 | AF64: =39490-945-48103-AE64 -> 12837 | AG64: =54513-1387-77829-AF64-AE64 -> -15145 | AH64: =I64-AG64-AF64-AE64 -> -10015 | AI64: =5753-479-21009 -> -15735 | AJ64: =9673-988-55556-AI64 -> -31136 | AK64: =14263-1628-65199-AJ64-AI64 -> -5693 | AL64: =J64-AK64-AJ64-AI64 -> -1900 | AM64: =1580-774-17980 -> -17174 | AN64: =1737-1422-36035-AM64 -> -18546 | AO64: =3480-2126-46550-AN64-AM64 -> -9476 | AP64: =K64-AO64-AN64-AM64 -> -18234 | AQ64: =65-608-15534 -> -16077 | AR64: =-32802+1063-1276-AQ64 -> -16938 | AS64: =1083-2065-50028-AR64-AQ64 -> -17995 | AT64: =L64-AS64-AR64-AQ64 -> -10634 | AU64: =383-638-11750 -> -12005 | AV64: =-22466+394-1270-AU64 -> -11337 | AY64: =61-1247-61828-X64-W64 -> -22025
B65: Acquisitions investments in associates and joint ventures / (Asset Sales) | C65: =0+17000-21524-22-159 -> -4705 | D65: =290+14884-5633-266-137 -> 9138 | E65: =11643+1710-111-2814-21 -> 10407 | F65: =1023+11-20-80 -> 934 | G65: =2020+0-579-0 -> 1441 | H65: =359+482-1754 -> -913 | I65: =2458-3514 -> -1056 | J65: =-1636 -> -1636 | K65: =-3770-29 -> -3799 | L65: =-186+175 -> -11 | M65: =SUM(AS65:AV65) -> -166 | O65: =-60+1710 -> 1650 | P65: =1710-111-O65 -> -51 | Q65: =-12-111-P65-O65 -> -1722 | R65: =E65-Q65-P65-O65 -> 10530 | S65: 0 | T65: =-70-S65 -> -70 | U65: =-70-0-T65-S65 -> 0 | V65: =F65-U65-T65-S65 -> 1004 | W65: =0+0 -> 0 | X65: =-60-W65 -> -60 | Y65: =-60-0-X65-W65 -> 0 | Z65: =G65-Y65-X65-W65 -> 1501 | AA65: -507 | AB65: =-1725+365-AA65 -> -853 | AC65: =-1727+359-AB65-AA65 -> -8 | AD65: =H65-AC65-AB65-AA65 -> 455 | AE65: -51 | AF65: =-3303+32-AE65 -> -3220 | AG65: =-3303+32-AF65-AE65 -> 0 | AH65: =I65-AG65-AF65-AE65 -> 2215 | AI65: -71 | AJ65: =-71-AI65 -> 0 | AK65: =-72-AJ65-AI65 -> -1 | AL65: =J65-AK65-AJ65-AI65 -> -1564 | AM65: -81 | AN65: =-2976-AM65 -> -2895 | AO65: =-3692-AN65-AM65 -> -716 | AP65: =K65-AO65-AN65-AM65 -> -107 | AQ65: -8 | AR65: =-115-AQ65 -> -107 | AS65: =-184-AR65-AQ65 -> -69 | AT65: =L65-AS65-AR65-AQ65 -> 173 | AU65: 0 | AV65: =-270-AU65 -> -270 | AY65: =-60-0-X65-W65 -> 0
B66: Free cash flow | C66: =SUM(C63:C65) -> -22058 | D66: =SUM(D63:D65) -> 5896 | E66: =SUM(E63:E65) -> 471 | F66: =SUM(F63:F65) -> -35934 | G66: =SUM(G63:G65) -> 49 | H66: =SUM(H63:H65) -> -31325 | I66: =SUM(I63:I65) -> 30304 | J66: =SUM(J63:J65) -> 18521 | ... M66: =SUM(M63:M65) -> 23902 | O66: =SUM(O63:O65) -> 262 | P66: =SUM(P63:P65) -> -124 | Q66: =SUM(Q63:Q65) -> -13393 | R66: =SUM(R63:R65) -> 13726 | S66: =SUM(S63:S65) -> -6211 | T66: =SUM(T63:T65) -> -6427 | U66: =SUM(U63:U65) -> -2064 | V66: =SUM(V63:V65) -> -21232 | ... AV66: =SUM(AV63:AV65) -> 6174 | AY66: =SUM(AY63:AY65) -> 2614
B67: Other investing activities | C67: =947+1557+2502+609-21524-2734-3500-6-20+4409-105 -> -17865 | D67: =1217+2001+20254+456+833-18424-76-511+1000 -> 6750 | E67: =1115+11707+6102+105-5992-72 -> 12965 | F67: =1723+1771+1415-572-145+35 -> 4227 | G67: =1106+0+4375-5147-0+20+2534+316+150-1194 -> 2160 | H67: =2518+993+170+714-404-3847-111 -> 33 | I67: =182+636+0-200-6368-9-173+8700 -> 2768 | J67: =973-449+18+440 -> 982 | K67: =881-37+626+21-166+200 -> 1525 | L67: =600+126+25+686-217-544 -> 676 | M67: =SUM(AS67:AV67) -> 356 | O67: =352+0+4852-7413-2629-51 -> -4889 | P67: =426+0+11707+3060+10059+105+0+0-6102-162-O67 -> 23982 | Q67: =904+11707+5249+11400+1710+105-P67-O67 -> 11982 | R67: =E67-Q67-P67-O67 -> -18110 | S67: =577+1167+0-105-61-69-82 -> 1427 | T67: =1065+2+1771+1263+681-2-82-125-751-S67 -> 2395 | U67: =1363+1771+1283+1021-552-2251-129-T67-S67 -> -1316 | V67: =F67-U67-T67-S67 -> 1721 | W67: =380+303+150-2943-88 -> -2198 | X67: =742+316+150+2826+2940+0-0-0-4943-498-62-W67 -> 3669 | Y67: =1055+2826+4375+1508-4685-0+17+150-X67-W67 -> 3775 | Z67: =G67-Y67-X67-W67 -> -3086 | AA67: =232+0+0-6-46-100 -> 80 | AB67: =389+0+0+170+261-1676-100-195-AA67 -> -1231 | AC67: =605+170+1941+0-1615-108+7+0-AB67-AA67 -> 2151 | AD67: =H67-AC67-AB67-AA67 -> -967 | AE67: =155+0+0-140-898+41 -> -842 | AF67: =262+2775-6767-175-53-AE67 -> -3116 | AG67: =7454+182+474-281-6466+186-AF67-AE67 -> 5507 | AH67: =I67-AG67-AF67-AE67 -> 1219 | AI67: =461+285-340-127 -> 279 | AJ67: =440+471-324-248-AI67 -> 60 | AK67: =440+706-329-39-AJ67-AI67 -> 439 | AL67: =J67-AK67-AJ67-AI67 -> 204 | AM67: =200+39+272-24+61 -> 548 | AN67: =200+21+480-20+79-AM67 -> 212 | AO67: =21+700-3+915-AN67-AM67 -> 873 | AP67: =K67-AO67-AN67-AM67 -> -108 | AQ67: =0+36+198-0+0 -> 234 | AR67: =126+25+361+148-AQ67 -> 426 | AS67: =600+126+25+534+325-AR67-AQ67 -> 950 | AT67: =L67-AS67-AR67-AQ67 -> -934 | AU67: =47+145-40+24 -> 176 | AV67: =47+305-40+28-AU67 -> 164 | AY67: =1055+2826+4375+1508-4685-0+17+150-X67-W67 -> 3775
B68: Dividends / Equity movements | C68: =-22987+5 -> -22982 | D68: -16617 | E68: =-13928 -> -13928 | F68: =-15592 -> -15592 | G68: -16721 | H68: -17712 | I68: -25235 | J68: -23328 | K68: -20750 | L68: =-20590 -> -20590 | M68: =SUM(AS68:AV68) -> -20311 | O68: -16 | P68: =-6054-O68 -> -6038 | Q68: =-13798-P68-O68 -> -7744 | R68: =E68-Q68-P68-O68 -> -130 | S68: -15 | T68: =-7796-S68 -> -7781 | U68: =-15556-T68-S68 -> -7760 | V68: =F68-U68-T68-S68 -> -36 | W68: -18 | X68: =-8448-W68 -> -8430 | Y68: =-17020-X68-W68 -> -8572 | Z68: =G68-Y68-X68-W68 -> 299 | AA68: -25 | AB68: =-8705-AA68 -> -8680 | AC68: =-17717-AB68-AA68 -> -9012 | AD68: =H68-AC68-AB68-AA68 -> 5 | AE68: -15 | AF68: =-9064-AE68 -> -9049 | AG68: =-25231-AF68-AE68 -> -16167 | AH68: =I68-AG68-AF68-AE68 -> -4 | AI68: -25 | AJ68: =-12736-AI68 -> -12711 | AK68: =-23313-AJ68-AI68 -> -10577 | AL68: =J68-AK68-AJ68-AI68 -> -15 | AM68: -7 | AN68: =-10032-AM68 -> -10025 | AO68: =-20744-AN68-AM68 -> -10712 | AP68: =K68-AO68-AN68-AM68 -> -6 | AQ68: -39 | AR68: =-10213-AQ68 -> -10174 | AS68: =-20576-AR68-AQ68 -> -10363 | AT68: =L68-AS68-AR68-AQ68 -> -14 | AU68: -19 | AV68: =-9934-AU68 -> -9915 | AY68: =-17020-X68-W68 -> -8572
B69: Principal Repayments | C69: =40569-19650 -> 20919 | D69: =26255-39199 -> -12944 | E69: =20500-18740 -> 1760 | F69: =37500-5399-20494 -> 11607 | G69: =61271-2541-28365-10000 -> 20365 | H69: =51500-6547-22565 -> 22388 | I69: =16000+5000-6000-8331-22353 -> -15684 | J69: =38000-10000-10707-22611 -> -5318 | K69: =37000-0-12079-12059-4200 -> 8662 | L69: =36150+1322-1022-14328-23712 -> -1590 | M69: =SUM(AS69:AV69) -> -12575 | O69: =4500-0-6402 -> -1902 | P69: =17500-0-8504-O69 -> 10898 | Q69: =20500+0-16458-P69-O69 -> -4954 | R69: =E69-Q69-P69-O69 -> -2282 | S69: =4000+0-1313-6320 -> -3633 | T69: =6000-3147-8921-S69 -> -2435 | U69: =18000-4363-15626-T69-S69 -> 4079 | V69: =F69-U69-T69-S69 -> 13596 | W69: =12000+4000-1788-3119 -> 11093 | X69: =47541+10000-3018-3733-10000-W69 -> 29697 | Y69: =47541-4313-14963-X69-W69 -> -12525 | Z69: =G69-Y69-X69-W69 -> -7900 | AA69: =12000+0-1924-13634 -> -3558 | AB69: =27000+0-3426-14444-0-AA69 -> 12688 | AC69: =37000-4971-15798-AB69-AA69 -> 7101 | AD69: =H69-AC69-AB69-AA69 -> 6157 | AE69: =5000-2261-5797 -> -3058 | AF69: =10000+5000-3743-11896-AE69 -> 2419 | AG69: =10000+5000-2000-5927-15544-AF69-AE69 -> -7832 | AH69: =I69-AG69-AF69-AE69 -> -7213 | AI69: =3000-3215-2048-4000 -> -6263 | AJ69: =25500-5570-2687-4000-AI69 -> 19506 | AK69: =35000-4000-7993-8975-AJ69-AI69 -> 789 | AL69: =J69-AK69-AJ69-AI69 -> -19350 | AM69: =4200-3139-4720-4200 -> -7859 | AN69: =14200-6146-7966-AM69 -> 7947 | AO69: =25300-0-8994-10084-AN69-AM69 -> 6134 | AP69: =K69-AO69-AN69-AM69 -> 2440 | AQ69: =5800+1022-1022-3829-4016 -> -2045 | AR69: =18900+1022-1022-6944-7719-AQ69 -> 6282 | AS69: =33150+1122-1022-10693-17522-AR69-AQ69 -> 798 | AT69: =L69-AS69-AR69-AQ69 -> -6625 | AU69: =150-1083-4530 -> -5463 | AV69: =8150-7063-7835-AU69 -> -1285 | AY69: =47541-4313-14963-X69-W69 -> -12525
B70: Other financing activities | C70: =-185-6040-541 -> -6766 | D70: =218+4165-153-177-7735 -> -3682 | E70: =886-38-236+26 -> 638 | F70: =-50-195-236-4 -> -485 | G70: =-430-927-236-0+10000 -> 8407 | H70: =-25-397-236-8922 -> -9580 | I70: =7839+87-0-62-236-9013 -> -1385 | J70: =-214-236-607 -> -1057 | K70: =-219-59-0+704+71 -> 497 | L70: =-243-271 -> -514 | M70: =SUM(AS70:AV70) -> 793 | O70: =218+66-59-23-1463 -> -1261 | P70: =596+66-38-118-11938+35-O70 -> -10136 | Q70: =709+-38+0-177+26-P70-O70 -> 11917 | R70: =E70-Q70-P70-O70 -> 118 | S70: =25-59+0 -> -34 | T70: =25-1-30-118-S70 -> -90 | U70: =-54-160-177-T70-S70 -> -267 | V70: =F70-U70-T70-S70 -> -94 | W70: =-41-59-124 -> -224 | X70: =0+0-661-118-81-W70 -> -636 | Y70: =-808-350-177-X70-W70 -> -475 | Z70: =G70-Y70-X70-W70 -> 9742 | AA70: =-91-59-90 -> -240 | AB70: =0+0-187-118-159-AA70 -> -224 | AC70: =-263-10-177-AB70-AA70 -> 14 | AD70: =H70-AC70-AB70-AA70 -> -9130 | AE70: =-30-52-59 -> -141 | AF70: =-52-118+157+7839-AE70 -> 7967 | AG70: =7839+855-52-177-AF70-AE70 -> 639 | AH70: =I70-AG70-AF70-AE70 -> -9850 | AI70: =-22-59-1247 -> -1328 | AJ70: =-142-118-800-AI70 -> 268 | AK70: =-199-177-1042-AJ70-AI70 -> -358 | AL70: =J70-AK70-AJ70-AI70 -> 361 | AM70: =-31-59-472 -> -562 | AN70: =319-59-99-4200-AM70 -> -3477 | AO70: =-150-59-0-AN70-AM70 -> 3830 | AP70: =K70-AO70-AN70-AM70 -> 706 | AQ70: =-12-14 -> -26 | AR70: =-142-712-AQ70 -> -828 | AS70: =-249-944-AR70-AQ70 -> -339 | AT70: =L70-AS70-AR70-AQ70 -> 679 | AU70: =213-1 -> 212 | AV70: =514-61-AU70 -> 241 | AY70: =-808-350-177-X70-W70 -> -475
B71: Cash flow after financing activities | C71: =SUM(C66:C70) -> -48752 | D71: =SUM(D66:D70) -> -20597 | E71: =SUM(E66:E70) -> 1906 | F71: =SUM(F66:F70) -> -36177 | G71: =SUM(G66:G70) -> 14260 | H71: =SUM(H66:H70) -> -36196 | I71: =SUM(I66:I70) -> -9232 | J71: =SUM(J66:J70) -> -10200 | ... M71: =SUM(M66:M70) -> -7835 | O71: =SUM(O66:O70) -> -7806 | P71: =SUM(P66:P70) -> 18582 | Q71: =SUM(Q66:Q70) -> -2192 | R71: =SUM(R66:R70) -> -6678 | S71: =SUM(S66:S70) -> -8466 | T71: =SUM(T66:T70) -> -14338 | U71: =SUM(U66:U70) -> -7328 | V71: =SUM(V66:V70) -> -6045 | ... AV71: =SUM(AV66:AV70) -> -4621 | AY71: =SUM(AY66:AY70) -> -15183
B72: Balancing figure | C72: =-7733-C71-C73 -> 40405 | D72: =-5817-D71-D73 -> 15332 | E72: =18749-E71-E73 -> 16012 | F72: =-27285-F71-F73 -> 9640 | G72: =15868-G71-G73 -> 2610 | H72: =-16330-H71-H73 -> 19622 | I72: =1304-I71-I73 -> 10122 | J72: =-9034-J71-J73 -> 1429 | K72: =-6166-K71-K73 -> 6583 | L72: =1855-L71-L73 -> 8051 | M72: =SUM(AS72:AV72) -> 10279 | O72: =-3685-O71-O73 -> 3269 | P72: =19459+3685-P71-P73 -> 4013 | Q72: =12301-19459-Q71-Q73 -> -5270 | R72: =E72-Q72-P72-O72 -> 14000 | S72: =-6368-S71-S73 -> 2084 | T72: =-19553+6368-T71-T73 -> 1896 | U72: =-24516+19553-U71-U73 -> 2096 | V72: =F72-U72-T72-S72 -> 3564 | W72: =6575-W71-W73 -> 2179 | X72: =21402-6575-X71-X73 -> 3940 | Y72: =9302-21402-Y71-Y73 -> 3753 | Z72: =G72-Y72-X72-W72 -> -7262 | AA72: =-8756-AA71-AA73 -> 1603 | AB72: =-17067+8756-AB71-AB73 -> 3955 | AC72: =-22149+17067-AC71-AC73 -> 2677 | AD72: =H72-AC72-AB72-AA72 -> 11387 | AE72: =1923-AE71-AE73 -> 11903 | AF72: =14956-AF71-AF73-1923 -> -8673 | AG72: =-4097-AG71-AG73-14956-(23907-23833) -> 538 | AH72: =I72-AG72-AF72-AE72 -> 6354 | AI72: =875-AI71-AI73 -> -1227 | AJ72: =-9026-AJ71-AJ73-875 -> 2901 | AK72: =-3739-AK71-AK73+9026 -> 1569 | AL72: =J72-AK72-AJ72-AI72 -> -1814 | AM72: =-2120-AM71-AM73 -> 1106 | AN72: =-4211-AN71-AN73+2120 -> 1043 | AO72: =-3871-AO71-AO73+4211 -> -2753 | AP72: =K72-AO72-AN72-AM72 -> 7187 | AQ72: =3748-AQ71-AQ73 -> 2000 | AR72: =826-AR71-AR73-AQ71-AQ72-AQ73 -> -164 | AS72: =81-AS71-AS73-AR71-AQ71-AR73-AQ73-AQ72-AR72 -> 2470 | AT72: =L72-AS72-AR72-AQ72 -> 3745 | AU72: =2668-AU71-AU73 -> 2104 | AV72: =30-AV71-AV73-AU71-AU72-AU73 -> 1960 | AY72: =9302-21402-AY71-AY73 -> 3753
B73: FX | C73: 614 | D73: -552 | E73: 831 | F73: -748 | G73: -1002 | H73: 244 | I73: 414 | J73: -263 | K73: 138 | L73: 23 | M73: =SUM(AS73:AV73) -> -1385 | O73: 852 | P73: =1401-O73 -> 549 | Q73: =1705-P73-O73 -> 304 | R73: =E73-Q73-P73-O73 -> -874 | S73: 14 | T73: =-729-S73 -> -743 | U73: =-474-T73 -> 269 | V73: =F73-U73-T73-S73 -> -288 | W73: -2 | X73: =-306-W73 -> -304 | Y73: =-974-X73 -> -670 | Z73: =G73-Y73-X73-W73 -> -26 | AA73: 85 | AB73: =84-AA73 -> -1 | AC73: =232-AB73 -> 233 | AD73: =H73-AC73-AB73-AA73 -> -73 | AE73: 109 | AF73: =384-AE73 -> 275 | AG73: =837-AF73 -> 562 | AH73: =I73-AG73-AF73-AE73 -> -532 | AI73: -411 | AJ73: =-296-AI73 -> 115 | AK73: -189 | AL73: =J73-AK73-AJ73-AI73 -> 222 | AM73: 1388 | AN73: =1537-AM73 -> 149 | AO73: 1350 | AP73: =K73-AO73-AN73-AM73 -> -2749 | AQ73: -28 | AR73: =1537-AQ73 -> 1565 | AS73: 64 | AT73: =L73-AS73-AR73-AQ73 -> -1578 | AU73: 106 | AV73: =129-AU73 -> 23 | AY73: =-974-X73 -> -670
B74: Net change in cash | C74: =SUM(C71:C73) -> -7733 | D74: =SUM(D71:D73) -> -5817 | E74: =SUM(E71:E73) -> 18749 | F74: =SUM(F71:F73) -> -27285 | G74: =SUM(G71:G73) -> 15868 | H74: =SUM(H71:H73) -> -16330 | I74: =SUM(I71:I73) -> 1304 | J74: =SUM(J71:J73) -> -9034 | ... M74: =SUM(M71:M73) -> 1059 | O74: =SUM(O71:O73) -> -3685 | P74: =SUM(P71:P73) -> 23144 | Q74: =SUM(Q71:Q73) -> -7158 | R74: =SUM(R71:R73) -> 6448 | S74: =SUM(S71:S73) -> -6368 | T74: =SUM(T71:T73) -> -13185 | U74: =SUM(U71:U73) -> -4963 | V74: =SUM(V71:V73) -> -2769 | ... AV74: =SUM(AV71:AV73) -> -2638 | AY74: =SUM(AY71:AY73) -> -12100
B75: Cash and cash equivalents | C75: 38722 | D75: =C75+D74 -> 32905 | E75: =D75+E74 -> 51654 | F75: =E75+F74 -> 24369 | G75: =F75+G74 -> 40237 | H75: =G75+H74 -> 23907 | I75: =H75+I74 -> 25211 | J75: =I75+J74 -> 16177 | K75: =J75+K74 -> 10011 | L75: =K75+L74 -> 11866 | M75: =AR75+M74 -> 11896 | O75: =32905+O74 -> 29220 | P75: =O75+P74 -> 52364 | Q75: =P75+Q74 -> 45206 | R75: =Q75+R74 -> 51654 | S75: =E75+S74 -> 45286 | T75: =S75+T74 -> 32101 | U75: =T75+U74 -> 27138 | V75: =U75+V74 -> 24369 | W75: =F75+W74 -> 30944 | X75: =W75+X74 -> 45771 | Y75: =X75+Y74 -> 33671 | Z75: =Y75+Z74 -> 40237 | AA75: =Z75+AA74 -> 31481 | AB75: =AA75+AB74 -> 23170 | AC75: =AB75+AC74 -> 18088 | AD75: =AC75+AD74 -> 23907 | AE75: =AD75+AE74 -> 25830 | ... AV75: =AU75+AV74 -> 11896 | AY75: =X75+AY74 -> 33671
B77: Check | C77: =C75-C119 -> 0 | D77: =D75-D119 -> 0 | E77: =E75-E119 -> 0 | F77: =F75-F119 -> 0 | G77: =G75-G119 -> 0 | H77: =H75-H119 -> 0 | I77: =I75-I120 -> 0 | J77: =J75-J120 -> 0 | K77: =K75-K120 -> 0 | L77: =L75-L120 -> 0 | M77: =M75-M120 -> 0 | O77: =O75-O119 -> 0 | P77: =P75-P119 -> 0 | Q77: =Q75-Q119 -> 0 | R77: =R75-R119 -> 0 | S77: =S75-S119 -> 0 | T77: =T75-T119 -> 0 | U77: =U75-U119 -> 0 | V77: =V75-V119 -> 0 | ... AO77: =AO75-AO119 -> 0 | AP77: =AP75-AP120 -> 0 | AQ77: =AQ75-AQ120 -> 0 | AR77: =AR75-AR120 -> 0 | AS77: =AS75-AS120 -> 0 | AT77: =AT75-AT120 -> 0 | AU77: =AU75-AU120 -> 0 | AV77: =AV75-AV120 -> 0 | AY77: =AY75-AY119 -> 0
B79: LTM METRICS | C79: =C58 -> 42735 | D79: =D58 -> 43100 | E79: =E58 -> 43465 | F79: =F58 -> 43830 | G79: =G58 -> 44196 | H79: =H58 -> 44561 | I79: =I58 -> 44926 | J79: =J58 -> 45291 | ... M79: =M58 -> 46203 | O79: =O58 -> 43190 | P79: =P58 -> 43281 | Q79: =Q58 -> 43373 | R79: =R58 -> 43465 | S79: =S58 -> 43555 | T79: =T58 -> 43646 | U79: =U58 -> 43738 | V79: =V58 -> 43830 | ... AV79: =AV58 -> 46203 | AY79: =AY58 -> 44104
B81: Revenue | C81: =C10 -> 165262 | D81: =D10 -> 158933 | E81: =E10 -> 162914 | F81: =F10 -> 169187 | G81: =G10 -> 181004 | H81: =H10 -> 192186 | I81: =I10 -> 204362 | J81: =J10 -> 210953 | ... M81: =M10 -> 220820 | R81: =SUM(O10:R10) -> 162914 | S81: =SUM(P10:S10) -> 163025 | T81: =SUM(Q10:T10) -> 162659 | U81: =SUM(R10:U10) -> 164699 | V81: =SUM(S10:V10) -> 169187 | W81: =SUM(T10:W10) -> 172215 | X81: =SUM(U10:X10) -> 173938 | Y81: =SUM(V10:Y10) -> 177973 | ... AV81: =SUM(AS10:AV10) -> 220820 | AY81: =SUM(V10:X10,AY10) -> 177973
B82: Operating profit | C82: =+C18 -> 24703 | D82: =+D18 -> 9511 | E82: =+E18 -> 13773 | F82: =+F18 -> 39401 | G82: =+G18 -> 36182 | H82: =+H18 -> 40871 | I82: =+I18 -> -5065 | J82: =+J18 -> 40694 | ... M82: =+M18 -> 48924 | R82: =SUM(O18:R18) -> 13773 | S82: =SUM(P18:S18) -> 17132 | T82: =SUM(Q18:T18) -> 19276 | U82: =SUM(R18:U18) -> 20955 | V82: =SUM(S18:V18) -> 39401 | W82: =SUM(T18:W18) -> 40214 | X82: =SUM(U18:X18) -> 40946 | Y82: =SUM(V18:Y18) -> 44410 | ... AV82: =SUM(AS18:AV18) -> 48924 | AY82: =SUM(V18:X18,AY18) -> 44410
B83: EBITDA | C83: =+C46 -> 59158 | D83: =+D46 -> 61426 | E83: =+E46 -> 61013 | F83: =+F46 -> 79057 | G83: =+G46 -> 83662 | H83: =+H46 -> 93040 | I83: =+I46 -> 93649 | J83: =+J46 -> 99156 | ... M83: =+M46 -> 110921 | R83: =SUM(O46:R46) -> #REF! | S83: =SUM(P46:S46) -> #REF! | T83: =SUM(Q46:T46) -> #REF! | U83: =SUM(R46:U46) -> #REF! | V83: =SUM(S46:V46) -> 79057 | W83: =SUM(T46:W46) -> 80810 | X83: =SUM(U46:X46) -> 82596 | Y83: =SUM(V46:Y46) -> 87040 | ... AV83: =SUM(AS46:AV46) -> 110921 | AY83: =SUM(V46:X46,AY46) -> 87040
B84: Adjusted EBITDA | C84: =+C51 -> 54529 | D84: =+D51 -> 59158 | E84: =+E51 -> 56706 | F84: =+F51 -> 78525 | G84: =+G51 -> 84774 | H84: =+H51 -> 96169 | I84: =+I51 -> 100262 | J84: =+J51 -> 104297 | ... M84: =+M51 -> 111749 | R84: =SUM(O51:R51) -> 56706 | S84: =SUM(P51:S51) -> 61588 | T84: =SUM(Q51:T51) -> 66283 | U84: =SUM(R51:U51) -> 69476 | V84: =SUM(S51:V51) -> 78525 | W84: =SUM(T51:W51) -> 80023 | X84: =SUM(U51:X51) -> 81929 | Y84: =SUM(V51:Y51) -> 86427 | ... AV84: =SUM(AS51:AV51) -> 111749 | AY84: =SUM(V51:X51,AY51) -> 86427
B85: Cash interest paid | C85: =-C62 -> 6512 | D85: =-D62 -> 7076 | E85: =-E62 -> 6614 | F85: =-F62 -> 7143 | G85: =-G62 -> 8348 | H85: =-H62 -> 8922 | I85: =-I62 -> 9013 | J85: =-J62 -> 9715 | ... M85: =-M62 -> 13113 | R85: =-SUM(O62:R62) -> 6614 | S85: =-SUM(P62:S62) -> 6804 | T85: =-SUM(Q62:T62) -> 7032 | U85: =-SUM(R62:U62) -> 7064 | V85: =-SUM(S62:V62) -> 7143 | W85: =-SUM(T62:W62) -> 7395 | X85: =-SUM(U62:X62) -> 7700 | Y85: =-SUM(V62:Y62) -> 10389 | ... AV85: =-SUM(AS62:AV62) -> 13113 | AY85: =-SUM(V62:X62,AY62) -> 7943
B86: Net Income | C86: =+C25 -> 20162 | D86: =+D25 -> 13466 | E86: =+E25 -> 18973 | F86: =+F25 -> 22786 | G86: =+G25 -> 24580 | H86: =+H25 -> 26676 | I86: =+I25 -> 10735 | J86: =+J25 -> 26824 | ... M86: =+M25 -> 28574 | R86: =SUM(O25:R25) -> 18973 | S86: =SUM(P25:S25) -> 18772 | T86: =SUM(Q25:T25) -> 19403 | U86: =SUM(R25:U25) -> 18683 | V86: =SUM(S25:V25) -> 22786 | W86: =SUM(T25:W25) -> 22038 | X86: =SUM(U25:X25) -> 22974 | Y86: =SUM(V25:Y25) -> 26650 | ... AV86: =SUM(AS25:AV25) -> 28574 | AY86: =SUM(V25:X25,AY25) -> 26650
B87: Capex | C87: =-C64 -> 40936 | D87: =-D64 -> 36948 | E87: =-E64 -> 48426 | F87: =-F64 -> 89477 | G87: =-G64 -> 77949 | H87: =-H64 -> 102760 | I87: =-I64 -> 34718 | J87: =-J64 -> 54464 | ... M87: =-M64 -> 51971 | R87: =-SUM(O64:R64) -> 48426 | S87: =-SUM(P64:S64) -> 54405 | T87: =-SUM(Q64:T64) -> 57363 | U87: =-SUM(R64:U64) -> 69203 | V87: =-SUM(S64:V64) -> 89477 | W87: =-SUM(T64:W64) -> 87617 | X87: =-SUM(U64:X64) -> 89579 | Y87: =-SUM(V64:Y64) -> 88694 | ... AV87: =-SUM(AS64:AV64) -> 51971 | AY87: =-SUM(V64:X64,AY64) -> 91506
B88: Free cash flow | C88: =+C66 -> -22058 | D88: =+D66 -> 5896 | E88: =+E66 -> 471 | F88: =+F66 -> -35934 | G88: =+G66 -> 49 | H88: =+H66 -> -31325 | I88: =+I66 -> 30304 | J88: =+J66 -> 18521 | ... M88: =+M66 -> 23902 | R88: =SUM(O66:R66) -> 471 | S88: =SUM(P66:S66) -> -6002 | T88: =SUM(Q66:T66) -> -12305 | U88: =SUM(R66:U66) -> -976 | V88: =SUM(S66:V66) -> -35934 | W88: =SUM(T66:W66) -> -33978 | X88: =SUM(U66:X66) -> -40660 | Y88: =SUM(V66:Y66) -> -35982 | ... AV88: =SUM(AS66:AV66) -> 23902 | AY88: =SUM(V66:X66,AY66) -> -35982
B90: BALANCE SHEET | C90: =C79 -> 42735 | D90: =D79 -> 43100 | E90: =E79 -> 43465 | F90: =F79 -> 43830 | G90: =G79 -> 44196 | H90: =H79 -> 44561 | I90: =I79 -> 44926 | J90: =J79 -> 45291 | ... M90: =M79 -> 46203 | O90: =O79 -> 43190 | P90: =P79 -> 43281 | Q90: =Q79 -> 43373 | R90: =R79 -> 43465 | S90: =S79 -> 43555 | T90: =T79 -> 43646 | U90: =U79 -> 43738 | V90: =V79 -> 43830 | ... AV90: =AV79 -> 46203 | AY90: =AY79 -> 44104
B92: Tangible fixed assets | C92: 203188 | D92: 186907 | E92: =195964 -> 195964 | F92: =232134+15890 -> 248024 | G92: =260868+18303 -> 279171 | H92: =302736+20081 -> 322817 | I92: =292745+28863 -> 321608 | J92: =287103+32717 -> 319820 | K92: =318069+39111 -> 357180 | L92: =327989+48777 -> 376766 | M92: =AV92 -> 375456 | O92: 184455 | P92: 190726 | Q92: 194748 | R92: =E92 -> 195964 | S92: =200062 +15615 -> 215677 | T92: =211957+20220 -> 232177 | U92: =224021+18836 -> 242857 | V92: =F92 -> 248024 | W92: =242512+16065 -> 258577 | X92: =245064+16155 -> 261219 | Y92: =247148+17746 -> 264894 | Z92: =G92 -> 279171 | AA92: =270964+19257 -> 290221 | AB92: =280177+19870 -> 300047 | AC92: =290676+20187 -> 310863 | AD92: =H92 -> 322817 | AE92: =307125+20189 -> 327314 | AF92: =292135+20515 -> 312650 | AG92: =298008+25038 -> 323046 | AH92: =I92 -> 321608 | AI92: =301712+26983 -> 328695 | AJ92: =313415+28213 -> 341628 | AK92: =315436+29950 -> 345386 | AL92: =J92 -> 319820 | AM92: =296691+34753 -> 331444 | AN92: =305639+37101 -> 342740 | AO92: =308216+37310 -> 345526 | AP92: =K92 -> 357180 | AQ92: =318342+39603 -> 357945 | AR92: =326937+40473 -> 367410 | AS92: =325310+45667 -> 370977 | AT92: =L92 -> 376766 | AU92: =327288+47348 -> 374636 | AV92: =327142+48314 -> 375456 | AY92: =247148+17746 -> 264894
B93: Pension and other employee benefits | C93: 11206 | D93: 8997 | E93: 7182 | F93: 8985 | G93: 13342 | H93: 7760 | I93: 1745 | J93: 5661 | K93: 3548 | L93: 3810 | M93: =AV93 -> 4025 | O93: 7777 | P93: 8425 | Q93: 8741 | R93: =E93 -> 7182 | S93: 5910 | T93: 6223 | U93: 4735 | V93: =F93 -> 8985 | W93: 9504 | X93: 9967 | Y93: 10123 | Z93: =G93 -> 13342 | AA93: 11659 | AB93: 12028 | AC93: 12274 | AD93: =H93 -> 7760 | AE93: 7868 | AF93: 3252 | AG93: 3247 | AH93: =I93 -> 1745 | AI93: 2081 | AJ93: 2172 | AK93: 2348 | AL93: =J93 -> 5661 | AM93: 5936 | AN93: 4064 | AO93: 4578 | AP93: =K93 -> 3548 | AQ93: 3606 | AR93: 3879 | AS93: 2555 | AT93: =L93 -> 3810 | AU93: 3898 | AV93: 4025 | AY93: 10123
B94: Inventory | C94: 3744 | D94: 3933 | E94: 2878 | F94: 3412 | G94: 4085 | H94: 3662 | I94: 3568 | J94: 3340 | K94: 3306 | L94: 1843 | M94: =AV94 -> 2787 | O94: 4902 | P94: 5234 | Q94: 5218 | R94: =E94 -> 2878 | S94: 2685 | T94: 2645 | U94: 3179 | V94: =F94 -> 3412 | W94: 2868 | X94: 2785 | Y94: 4179 | Z94: =G94 -> 4085 | AA94: 4124 | AB94: 4210 | AC94: 4848 | AD94: =H94 -> 3662 | AE94: 3955 | AF94: 4065 | AG94: 4906 | AH94: =I94 -> 3568 | AI94: 4162 | AJ94: 2991 | AK94: 2465 | AL94: =J94 -> 3340 | AM94: 2367 | AN94: 2017 | AO94: 1985 | AP94: =K94 -> 3306 | AQ94: 2747 | AR94: 2473 | AS94: 2172 | AT94: =L94 -> 1843 | AU94: 2328 | AV94: 2787 | AY94: 4179
B95: Trade debtors | C95: 24436 | D95: 33761 | E95: 24056 | F95: 22436 | G95: 22053 | H95: 21790 | I95: 26255 | J95: 26086 | K95: 31612 | L95: 31367 | M95: =AV95 -> 35393 | O95: 34013 | P95: 36201 | Q95: 38959 | R95: =E95 -> 24056 | S95: 22177 | T95: 20841 | U95: 20622 | V95: =F95 -> 22436 | W95: 24434 | X95: 29041 | Y95: 24978 | Z95: =G95 -> 22053 | AA95: 22081 | AB95: 20889 | AC95: 21505 | AD95: =H95 -> 21790 | AE95: 24262 | AF95: 25326 | AG95: 25261 | AH95: =I95 -> 26255 | AI95: 24601 | AJ95: 25095 | AK95: 25269 | AL95: =J95 -> 26086 | AM95: 28131 | AN95: 27950 | AO95: 28596 | AP95: =K95 -> 31612 | AQ95: 31362 | AR95: 31215 | AS95: 30015 | AT95: =L95 -> 31367 | AU95: 32259 | AV95: 35393 | AY95: 24978
B96: Trade creditors | C96: 52950 | D96: 60445 | E96: 74610 | F96: 77845 | G96: 82413 | H96: 99718 | I96: 105187 | J96: 81014 | K96: 66722 | L96: 56379 | M96: =AV96 -> 53345 | O96: 59757 | P96: 52364 | Q96: 63102 | R96: =E96 -> 74610 | S96: 70928 | T96: 72897 | U96: 79430 | V96: =F96 -> 77845 | W96: 80545 | X96: 63362 | Y96: 62266 | Z96: =G96 -> 82413 | AA96: 92377 | AB96: 94450 | AC96: 93292 | AD96: =H96 -> 99718 | AE96: 99686 | AF96: 110712 | AG96: 107230 | AH96: =I96 -> 105187 | AI96: 91283 | AJ96: 84691 | AK96: 87379 | AL96: =J96 -> 81014 | AM96: 84655 | AN96: 90880 | AO96: 74954 | AP96: =K96 -> 66722 | AQ96: 60011 | AR96: 60398 | AS96: 55029 | AT96: =L96 -> 56379 | AU96: 53731 | AV96: 53345 | AY96: 62266
B97: Net working capital | C97: =C94+C95-C96 -> -24770 | D97: =D94+D95-D96 -> -22751 | E97: =E94+E95-E96 -> -47676 | F97: =F94+F95-F96 -> -51997 | G97: =G94+G95-G96 -> -56275 | H97: =H94+H95-H96 -> -74266 | I97: =I94+I95-I96 -> -75364 | J97: =J94+J95-J96 -> -51588 | ... M97: =M94+M95-M96 -> -15165 | O97: =O94+O95-O96 -> -20842 | P97: =P94+P95-P96 -> -10929 | Q97: =Q94+Q95-Q96 -> -18925 | R97: =R94+R95-R96 -> -47676 | S97: =S94+S95-S96 -> -46066 | T97: =T94+T95-T96 -> -49411 | U97: =U94+U95-U96 -> -55629 | V97: =V94+V95-V96 -> -51997 | ... AV97: =AV94+AV95-AV96 -> -15165 | AY97: =AY94+AY95-AY96 -> -33109
B98: % of revenues | C98: =C97/C81 -> -0.14988322 | D98: =D97/D81 -> -0.14314837 | E98: =E97/E81 -> -0.2926452 | F98: =F97/F81 -> -0.30733449 | G98: =G97/G81 -> -0.31090473 | H98: =H97/H81 -> -0.38642773 | I98: =I97/I81 -> -0.36877697 | J98: =J97/J81 -> -0.24454736 | ... M98: =M97/M81 -> -0.068675845 | R98: =R97/R81 -> -0.2926452 | S98: =S97/S81 -> -0.28257016 | T98: =T97/T81 -> -0.30377046 | U98: =U97/U81 -> -0.33776161 | V98: =V97/V81 -> -0.30733449 | W98: =W97/W81 -> -0.30916587 | X98: =X97/X81 -> -0.18130598 | Y98: =Y97/Y81 -> -0.18603384 | ... AV98: =AV97/AV81 -> -0.068675845 | AY98: =AY97/AY81 -> -0.18603384
B100: Inventory Days | F100: =IFERROR((F94/F13)*365,"-") -> 92.738104 | G100: =IFERROR((G94/G13)*365,"-") -> 121.27084 | H100: =IFERROR((H94/H13)*365,"-") -> 103.47836 | I100: =IFERROR((I94/I13)*365,"-") -> 91.893875 | J100: =IFERROR((J94/J13)*365,"-") -> 80.777896 | K100: =IFERROR((K94/K13)*365,"-") -> 86.124474 | L100: =IFERROR((L94/L13)*365,"-") -> 52.620072 | M100: =IFERROR((M94/M13)*365,"-") -> 74.447819 | AA100: =IFERROR((AA94/AA13)*(365/4),"-") -> 104.88155 | AB100: =IFERROR((AB94/AB13)*(365/4),"-") -> 123.56465 | AC100: =IFERROR((AC94/AC13)*(365/4),"-") -> 155.1122 | AD100: =IFERROR((AD94/AD13)*(365/4),"-") -> 99.21541 | AE100: =IFERROR((AE94/AE13)*(365/4),"-") -> 115.70816 | AF100: =IFERROR((AF94/AF13)*(365/4),"-") -> 112.8823 | AG100: =IFERROR((AG94/AG13)*(365/4),"-") -> 122.51574 | AH100: =IFERROR((AH94/AH13)*(365/4),"-") -> 79.158765 | ... AV100: =IFERROR((AV94/AV13)*(365/4),"-") -> 74.930392
B101: Receivable Days | F101: =IFERROR((F95/F10)*365,"-") -> 48.402891 | G101: =IFERROR((G95/G10)*365,"-") -> 44.470537 | H101: =IFERROR((H95/H10)*365,"-") -> 41.383608 | I101: =IFERROR((I95/I10)*365,"-") -> 46.892646 | J101: =IFERROR((J95/J10)*365,"-") -> 45.135125 | K101: =IFERROR((K95/K10)*365,"-") -> 53.21321 | L101: =IFERROR((L95/L10)*365,"-") -> 52.424836 | M101: =IFERROR((M95/M10)*365,"-") -> 58.502151 | AA101: =IFERROR((AA95/AA10)*(365/4),"-") -> 42.04347 | AB101: =IFERROR((AB95/AB10)*(365/4),"-") -> 39.961451 | AC101: =IFERROR((AC95/AC10)*(365/4),"-") -> 40.684412 | AD101: =IFERROR((AD95/AD10)*(365/4),"-") -> 41.140855 | AE101: =IFERROR((AE95/AE10)*(365/4),"-") -> 44.433668 | AF101: =IFERROR((AF95/AF10)*(365/4),"-") -> 45.347465 | AG101: =IFERROR((AG95/AG10)*(365/4),"-") -> 44.891936 | AH101: =IFERROR((AH95/AH10)*(365/4),"-") -> 45.871348 | ... AV101: =IFERROR((AV95/AV10)*(365/4),"-") -> 58.198534
B102: Payable Days | F102: =IFERROR((F96/F13)*365,"-") -> 2115.8258 | G102: =IFERROR((G96/G13)*365,"-") -> 2446.5836 | H102: =IFERROR((H96/H13)*365,"-") -> 2817.765 | I102: =IFERROR((I96/I13)*365,"-") -> 2709.0922 | J102: =IFERROR((J96/J13)*365,"-") -> 1959.3235 | K102: =IFERROR((K96/K13)*365,"-") -> 1738.1722 | L102: =IFERROR((L96/L13)*365,"-") -> 1609.6945 | M102: =IFERROR((M96/M13)*365,"-") -> 1424.9799 | AA102: =IFERROR((AA96/AA13)*(365/4),"-") -> 2349.3315 | AB102: =IFERROR((AB96/AB13)*(365/4),"-") -> 2772.1333 | AC102: =IFERROR((AC96/AC13)*(365/4),"-") -> 2984.886 | AD102: =IFERROR((AD96/AD13)*(365/4),"-") -> 2701.6827 | AE102: =IFERROR((AE96/AE13)*(365/4),"-") -> 2916.4307 | AF102: =IFERROR((AF96/AF13)*(365/4),"-") -> 3074.3974 | AG102: =IFERROR((AG96/AG13)*(365/4),"-") -> 2677.8154 | AH102: =IFERROR((AH96/AH13)*(365/4),"-") -> 2333.6527 | ... AV102: =IFERROR((AV96/AV13)*(365/4),"-") -> 1434.2166
B104: Debt Breakdown
B105: Short-term debt | C105: 33273 | D105: 14957 | E105: 20441 | F105: 19722 | G105: 17570 | H105: 11482 | I105: 32292 | J105: 11646 | K105: 23340 | L105: 16180 | M105: =AV105 -> 30917 | O105: 11840 | P105: 10950 | Q105: 14258 | R105: =E105 -> 20441 | S105: 17292 | T105: 15192 | U105: 17140 | V105: =F105 -> 19722 | W105: 39263 | X105: 35571 | Y105: 25335 | Z105: =G105 -> 17570 | AA105: 5317 | AB105: 7328 | AC105: 10494 | AD105: =H105 -> 11482 | AE105: 14213 | AF105: 15827 | AG105: 19592 | AH105: =I105 -> 32292 | AI105: 30850 | AJ105: 33446 | AK105: 29344 | AL105: =J105 -> 11646 | AM105: 10908 | AN105: 11424 | AO105: 19107 | AP105: =K105 -> 23340 | AQ105: 20165 | AR105: 22529 | AS105: 17406 | AT105: =L105 -> 16180 | AU105: 29070 | AV105: 30917 | AY105: 25335
B106: Long-term debt | C106: 151759 | D106: 157654 | E106: 155835 | F106: 172834 | G106: 205195 | H106: 241075 | I106: 217288 | J106: 243152 | K106: 258246 | L106: 278868 | M106: =AV106 -> 267008 | O106: 160399 | P106: 172860 | Q106: 164965 | R106: =E106 -> 155835 | S106: 156694 | T106: 157651 | U106: 161244 | V106: =F106 -> 172834 | W106: 166075 | X106: 199729 | Y106: 197487 | Z106: =G106 -> 205195 | AA106: 216212 | AB106: 228455 | AC106: 235465 | AD106: =H106 -> 241075 | AE106: 242620 | AF106: 243374 | AG106: 236882 | AH106: =I106 -> 217288 | AI106: 214619 | AJ106: 234623 | AK106: 242910 | AL106: =J106 -> 243152 | AM106: 244031 | AN106: 251950 | AO106: 251476 | AP106: =K106 -> 258246 | AQ106: 262901 | AR106: 269284 | AS106: 280130 | AT106: =L106 -> 278868 | AU106: 266392 | AV106: 267008 | AY106: 197487
B107: Total Debt | C107: =C105+C106 -> 185032 | D107: =D105+D106 -> 172611 | E107: =E105+E106 -> 176276 | F107: =F105+F106 -> 192556 | G107: =G105+G106 -> 222765 | H107: =H105+H106 -> 252557 | I107: =I105+I106 -> 249580 | J107: =J105+J106 -> 254798 | ... L107: =L105+L106 -> 295048 | M107: =SUM(M105:M106) -> 297925 | O107: =O105+O106 -> 172239 | P107: =P105+P106 -> 183810 | Q107: =Q105+Q106 -> 179223 | R107: =E107 -> 176276 | S107: =S105+S106 -> 173986 | T107: =T105+T106 -> 172843 | U107: =U105+U106 -> 178384 | V107: =F107 -> 192556 | W107: =W105+W106 -> 205338 | X107: =X105+X106 -> 235300 | Y107: =Y105+Y106 -> 222822 | Z107: =G107 -> 222765 | AA107: =AA105+AA106 -> 221529 | AB107: =AB105+AB106 -> 235783 | AC107: =AC105+AC106 -> 245959 | AD107: =H107 -> 252557 | AE107: =AE105+AE106 -> 256833 | AF107: =AF105+AF106 -> 259201 | AG107: =AG105+AG106 -> 256474 | AH107: =I107 -> 249580 | AI107: =AI105+AI106 -> 245469 | AJ107: =AJ105+AJ106 -> 268069 | AK107: =AK105+AK106 -> 272254 | AL107: =J107 -> 254798 | AM107: =AM105+AM106 -> 254939 | AN107: =AN105+AN106 -> 263374 | AO107: =AO105+AO106 -> 270583 | AP107: =AP105+AP106 -> 281586 | AQ107: =AQ105+AQ106 -> 283066 | AR107: =AR105+AR106 -> 291813 | AS107: =AS105+AS106 -> 297536 | AT107: =AT105+AT106 -> 295048 | ... AV107: =AV105+AV106 -> 297925 | AY107: =AY105+AY106 -> 222822
B109: Lease Obligations
B110: Short-term debt | C110: 0 | D110: 0 | E110: 0 | F110: 3215 | G110: 4043 | H110: 4555 | I110: 10477 | J110: 5921 | K110: 7335 | L110: 8897 | M110: =AV110 -> 10187 | O110: 0 | P110: 0 | Q110: 0 | R110: =E110 -> 0 | S110: 8156 | T110: 4601 | U110: 4476 | V110: =F110 -> 3215 | W110: 3657 | X110: 3570 | Y110: 3867 | Z110: =G110 -> 4043 | AA110: 4220 | AB110: 4272 | AC110: 4462 | AD110: =H110 -> 4555 | AE110: 4652 | AF110: 5412 | AG110: 13521 | AH110: =I110 -> 10477 | AI110: 12462 | AJ110: 10250 | AK110: 11121 | AL110: =J110 -> 5921 | AM110: 6389 | AN110: 6958 | AO110: 7098 | AP110: =K110 -> 7335 | AQ110: 7584 | AR110: 7869 | AS110: 8667 | AT110: =L110 -> 8897 | AU110: 9679 | AV110: 10187 | AY110: 3867
B111: Long-term debt | C111: 0 | D111: 0 | E111: 0 | F111: 13100 | G111: 15982 | H111: 17131 | I111: 31958 | J111: 41625 | K111: 46703 | L111: 55276 | M111: =AV111 -> 52905 | O111: 0 | P111: 0 | Q111: 0 | R111: =E111 -> 0 | S111: 9002 | T111: 17757 | U111: 17101 | V111: =F111 -> 13100 | W111: 12676 | X111: 13036 | Y111: 14224 | Z111: =G111 -> 15982 | AA111: 16248 | AB111: 16953 | AC111: 17231 | AD111: =H111 -> 17131 | AE111: 16581 | AF111: 28963 | AG111: 24001 | AH111: =I111 -> 31958 | AI111: 28285 | AJ111: 32269 | AK111: 32839 | AL111: =J111 -> 41625 | AM111: 43152 | AN111: 44917 | AO111: 45477 | AP111: =K111 -> 46703 | AQ111: 46231 | AR111: 47896 | AS111: 52088 | AT111: =L111 -> 55276 | AU111: 52157 | AV111: 52905 | AY111: 14224
B112: Total Lease | C112: =C110+C111 -> 0 | D112: =D110+D111 -> 0 | E112: =E110+E111 -> 0 | F112: =F110+F111 -> 16315 | G112: =G110+G111 -> 20025 | H112: =H110+H111 -> 21686 | I112: =I110+I111 -> 42435 | J112: =J110+J111 -> 47546 | ... L112: =L110+L111 -> 64173 | M112: =SUM(M110:M111) -> 63092 | O112: =SUM(O110:O111) -> 0 | P112: =SUM(P110:P111) -> 0 | Q112: =SUM(Q110:Q111) -> 0 | R112: =SUM(R110:R111) -> 0 | S112: =SUM(S110:S111) -> 17158 | T112: =SUM(T110:T111) -> 22358 | U112: =SUM(U110:U111) -> 21577 | V112: =SUM(V110:V111) -> 16315 | ... AL112: =SUM(AL110:AL111) -> 47546 | AM112: =AM110+AM111 -> 49541 | AN112: =SUM(AN110:AN111) -> 51875 | AO112: =SUM(AO110:AO111) -> 52575 | AP112: =SUM(AP110:AP111) -> 54038 | AQ112: =SUM(AQ110:AQ111) -> 53815 | AR112: =SUM(AR110:AR111) -> 55765 | AS112: =SUM(AS110:AS111) -> 60755 | AT112: =SUM(AT110:AT111) -> 64173 | AU112: =SUM(AU110:AU111) -> 61836 | AV112: =SUM(AV110:AV111) -> 63092 | AY112: =SUM(AY110:AY111) -> 18091
B114: Debt Including Lease
B115: Short-term debt | C115: =C105+C110 -> 33273 | D115: =D105+D110 -> 14957 | E115: =E105+E110 -> 20441 | F115: =F105+F110 -> 22937 | G115: =G105+G110 -> 21613 | H115: =H105+H110 -> 16037 | I115: =I105+I110 -> 42769 | J115: =J105+J110 -> 17567 | ... M115: =M105+M110 -> 41104 | O115: =O105+O110 -> 11840 | P115: =P105+P110 -> 10950 | Q115: =Q105+Q110 -> 14258 | R115: =E115 -> 20441 | S115: =S105+S110 -> 25448 | T115: =T105+T110 -> 19793 | U115: =U105+U110 -> 21616 | V115: =F115 -> 22937 | W115: =W105+W110 -> 42920 | X115: =X105+X110 -> 39141 | Y115: =Y105+Y110 -> 29202 | Z115: =G115 -> 21613 | AA115: =AA105+AA110 -> 9537 | AB115: =AB105+AB110 -> 11600 | AC115: =AC105+AC110 -> 14956 | AD115: =H115 -> 16037 | AE115: =AE105+AE110 -> 18865 | AF115: =AF105+AF110 -> 21239 | AG115: =AG105+AG110 -> 33113 | AH115: =I115 -> 42769 | AI115: =AI105+AI110 -> 43312 | AJ115: =AJ105+AJ110 -> 43696 | AK115: =AK105+AK110 -> 40465 | AL115: =J115 -> 17567 | AM115: =AM105+AM110 -> 17297 | AN115: =AN105+AN110 -> 18382 | AO115: =AO105+AO110 -> 26205 | AP115: =AP105+AP110 -> 30675 | AQ115: =AQ105+AQ110 -> 27749 | AR115: =AR105+AR110 -> 30398 | AS115: =AS105+AS110 -> 26073 | AT115: =AT105+AT110 -> 25077 | ... AV115: =AV105+AV110 -> 41104 | AY115: =AY105+AY110 -> 29202
B116: Long-term debt | C116: =C106+C111 -> 151759 | D116: =D106+D111 -> 157654 | E116: =E106+E111 -> 155835 | F116: =F106+F111 -> 185934 | G116: =G106+G111 -> 221177 | H116: =H106+H111 -> 258206 | I116: =I106+I111 -> 249246 | J116: =J106+J111 -> 284777 | ... M116: =M106+M111 -> 319913 | O116: =O106+O111 -> 160399 | P116: =P106+P111 -> 172860 | Q116: =Q106+Q111 -> 164965 | R116: =AA116 -> 232460 | S116: =S106+S111 -> 165696 | T116: =T106+T111 -> 175408 | U116: =U106+U111 -> 178345 | V116: =F116 -> 185934 | W116: =W106+W111 -> 178751 | X116: =X106+X111 -> 212765 | Y116: =Y106+Y111 -> 211711 | Z116: =G116 -> 221177 | AA116: =AA106+AA111 -> 232460 | AB116: =AB106+AB111 -> 245408 | AC116: =AC106+AC111 -> 252696 | AD116: =H116 -> 258206 | AE116: =AE106+AE111 -> 259201 | AF116: =AF106+AF111 -> 272337 | AG116: =AG106+AG111 -> 260883 | AH116: =I116 -> 249246 | AI116: =AI106+AI111 -> 242904 | AJ116: =AJ106+AJ111 -> 266892 | AK116: =AK106+AK111 -> 275749 | AL116: =J116 -> 284777 | AM116: =AM106+AM111 -> 287183 | AN116: =AN106+AN111 -> 296867 | AO116: =AO106+AO111 -> 296953 | AP116: =AP106+AP111 -> 304949 | AQ116: =AQ106+AQ111 -> 309132 | AR116: =AR106+AR111 -> 317180 | AS116: =AS106+AS111 -> 332218 | AT116: =AT106+AT111 -> 334144 | ... AV116: =AV106+AV111 -> 319913 | AY116: =AY106+AY111 -> 211711
...

Sheet KPIs
B2: PLDT INC. | C2: Annual | D2: Annual | E2: Annual | F2: Annual | G2: Annual | H2: Annual | I2: Annual | J2: Annual | K2: Annual | L2: Annual | M2: LTM | O2: Quarterly | P2: Quarterly | Q2: Quarterly | R2: Quarterly | S2: Quarterly | T2: Quarterly | U2: Quarterly | V2: Quarterly | W2: Quarterly | X2: Quarterly | Y2: Quarterly | Z2: Quarterly | AA2: Quarterly | AB2: Quarterly | AC2: Quarterly | AD2: Quarterly | AE2: Quarterly | AF2: Quarterly | AG2: Quarterly | AH2: Quarterly | AI2: Quarterly | AJ2: Quarterly | AK2: Quarterly | AL2: Quarterly | AM2: Quarterly | AN2: Quarterly | AO2: Quarterly | AP2: Quarterly | AQ2: Quarterly | AR2: Quarterly | AS2: Quarterly | AT2: Quarterly | AU2: Quarterly | AV2: Quarterly
B3: (PHP millions) | C3: 42735 | D3: =EDATE(C3,12) -> 43100 | E3: =EDATE(D3,12) -> 43465 | F3: =EDATE(E3,12) -> 43830 | G3: =EDATE(F3,12) -> 44196 | H3: =EDATE(G3,12) -> 44561 | I3: =EDATE(H3,12) -> 44926 | J3: =EDATE(I3,12) -> 45291 | K3: =EDATE(J3,12) -> 45657 | L3: =EDATE(K3,12) -> 46022 | M3: =AV3 -> 46203 | O3: 43160 | P3: 43252 | Q3: 43344 | R3: 43435 | S3: 43525 | T3: 43617 | U3: 43709 | V3: 43800 | W3: 43891 | X3: 43983 | Y3: 44075 | Z3: 44166 | AA3: 44256 | AB3: 44348 | AC3: 44440 | AD3: 44531 | AE3: 44651 | AF3: 44742 | AG3: 44805 | AH3: 44896 | AI3: 45016 | AJ3: 45107 | AK3: 45170 | AL3: 45261 | AM3: 45382 | AN3: 45473 | AO3: 45536 | AP3: 45627 | AQ3: 45747 | AR3: 45838 | AS3: 45901 | AT3: 45992 | AU3: 46112 | AV3: 46203
I4: Act | J4: Act | K4: Act | L4: Act | M4: Act | AM4: Act | AN4: Act | AO4: Act | AP4: Act | AQ4: Act | AR4: Act | AS4: Act | AT4: Act | AU4: Act | AV4: Act
C5: FY | D5: FY | E5: FY | F5: FY | G5: FY | H5: FY | I5: FY | J5: FY | K5: FY | L5: FY | M5: LTM | O5: Q1 | P5: Q2 | Q5: Q3 | R5: Q4 | S5: Q1 | T5: Q2 | U5: Q3 | V5: Q4 | W5: Q1 | X5: Q2 | Y5: Q3 | Z5: Q4 | AA5: Q1 | AB5: Q2 | AC5: Q3 | AD5: Q4 | AE5: Q1 | AF5: Q2 | AG5: Q3 | AH5: Q4 | AI5: Q1 | AJ5: Q2 | AK5: Q3 | AL5: Q4 | AM5: Q1 | AN5: Q2 | AO5: Q3 | AP5: Q4 | AQ5: Q1 | AR5: Q2 | AS5: Q3 | AT5: Q4 | AU5: Q1 | AV5: Q2
B8: Revenue by business segment
B9: Wireless | C9: 104087 | D9: 92572 | E9: 89929 | F9: 96906 | G9: 104211 | H9: 106619 | I9: 104274 | J9: 104401 | K9: 105734 | L9: 103316 | M9: =SUM(AS9:AV9) -> 104236 | O9: 22592 | P9: =45235-O9 -> 22643 | Q9: =67363-P9-O9 -> 22128 | R9: =+E9-SUM(O9:Q9) -> 22566 | S9: 22489 | T9: =46231-S9 -> 23742 | U9: =70635-T9-S9 -> 24404 | V9: =+F9-SUM(S9:U9) -> 26271 | W9: 25354 | X9: =49911-W9 -> 24557 | Y9: =76716-X9-W9 -> 26805 | Z9: =+G9-SUM(W9:Y9) -> 27495 | AA9: 27383 | AB9: =53902-AA9 -> 26519 | AC9: =79821-AB9-AA9 -> 25919 | AD9: =+H9-SUM(AA9:AC9) -> 26798 | AE9: 25747 | AF9: =52012-AE9 -> 26265 | AG9: =77971-AF9-AE9 -> 25959 | AH9: =+I9-SUM(AE9:AG9) -> 26303 | AI9: 25879 | AJ9: =51589-AI9 -> 25710 | AK9: =77234-AJ9-AI9 -> 25645 | AL9: =+J9-SUM(AI9:AK9) -> 27167 | AM9: 26668 | AN9: =52999-AM9 -> 26331 | AO9: =78535-AN9-AM9 -> 25536 | AP9: =+K9-SUM(AM9:AO9) -> 27199 | AQ9: 26117 | AR9: =51372-AQ9 -> 25255 | AS9: =76468-AR9-AQ9 -> 25096 | AT9: =+L9-SUM(AQ9:AS9) -> 26848 | AU9: 26145 | AV9: =52292-AU9 -> 26147
B10: Fixed Line | C10: 72728 | D10: 78341 | E10: 85222 | F10: 89406 | G10: 98739 | H10: 115992 | I10: 127810 | J10: 120734 | K10: 126490 | L10: 130810 | M10: =SUM(AS10:AV10) -> 129615 | O10: 20457 | P10: =41652-O10 -> 21195 | Q10: =63336-P10-O10 -> 21684 | R10: =+E10-SUM(O10:Q10) -> 21886 | S10: 21999 | T10: =44217-S10 -> 22218 | U10: =66468-T10-S10 -> 22251 | V10: =+F10-SUM(S10:U10) -> 22938 | W10: 22695 | X10: =46483-W10 -> 23788 | Y10: =72031-X10-W10 -> 25548 | Z10: =+G10-SUM(W10:Y10) -> 26708 | AA10: 26555 | AB10: =54840-AA10 -> 28285 | AC10: =84779-AB10-AA10 -> 29939 | AD10: =+H10-SUM(AA10:AC10) -> 31213 | AE10: 34214 | AF10: =70446-AE10 -> 36232 | AG10: =105104-AF10-AE10 -> 34658 | AH10: =+I10-SUM(AE10:AG10) -> 22706 | AI10: 30047 | AJ10: =59606-AI10 -> 29559 | AK10: =89727-AJ10-AI10 -> 30121 | AL10: =+J10-SUM(AI10:AK10) -> 31007 | AM10: 31845 | AN10: =64106-AM10 -> 32261 | AO10: =95435-AN10-AM10 -> 31329 | AP10: =+K10-SUM(AM10:AO10) -> 31055 | AQ10: 33467 | AR10: =67092-AQ10 -> 33625 | AS10: =100248-AR10-AQ10 -> 33156 | AT10: =+L10-SUM(AQ10:AS10) -> 30562 | AU10: 33932 | AV10: =65897-AU10 -> 31965
B11: Others. | C11: 847 | D11: 1279 | E11: 1138 | F11: 0 | G11: 0 | H11: 0 | I11: 0 | J11: 0 | K11: 0 | L11: 0 | M11: =SUM(AS11:AV11) -> 0 | O11: 312 | P11: =612-O11 -> 300 | Q11: =922-P11-O11 -> 310 | R11: =+E11-SUM(O11:Q11) -> 216 | S11: 0 | T11: =0-S11 -> 0 | U11: =0-T11-S11 -> 0 | V11: =+F11-SUM(S11:U11) -> 0 | W11: 0 | X11: =0-W11 -> 0 | Y11: =0-X11-W11 -> 0 | Z11: =+G11-SUM(W11:Y11) -> 0 | AA11: 0 | AB11: =0-AA11 -> 0 | AC11: =0-AB11-AA11 -> 0 | AD11: =+H11-SUM(AA11:AC11) -> 0 | AE11: 0 | AF11: =0-AE11 -> 0 | AG11: =0-AF11-AE11 -> 0 | AH11: =+I11-SUM(AE11:AG11) -> 0 | AI11: 0 | AJ11: =0-AI11 -> 0 | AK11: =0-AJ11-AI11 -> 0 | AL11: =+J11-SUM(AI11:AK11) -> 0 | AM11: 0 | AN11: =0-AM11 -> 0 | AO11: =0-AN11-AM11 -> 0 | AP11: =+K11-SUM(AM11:AO11) -> 0 | AQ11: 0 | AR11: =0-AQ11 -> 0 | AS11: =0-AR11-AQ11 -> 0 | AT11: =+L11-SUM(AQ11:AS11) -> 0 | AU11: 0 | AV11: =0-AU11 -> 0
B12: Inter-segment transactions | C12: -13216 | D12: -13259 | E12: -13375 | F12: -17125 | G12: -21946 | H12: -30425 | I12: -27722 | J12: -14182 | K12: -15391 | L12: -15738 | M12: =SUM(AS12:AV12) -> -13031 | O12: -2854 | P12: =-5260-O12 -> -2406 | Q12: =-9745-P12-O12 -> -4485 | R12: =+E12-SUM(O12:Q12) -> -3630 | S12: -3870 | T12: =-8464-S12 -> -4594 | U12: =-12667-T12-S12 -> -4203 | V12: =+F12-SUM(S12:U12) -> -4458 | W12: -4403 | X12: =-9659-W12 -> -5256 | Y12: =-15525-X12-W12 -> -5866 | Z12: =+G12-SUM(W12:Y12) -> -6421 | AA12: -6014 | AB12: =-13119-AA12 -> -7105 | AC12: =-20744-AB12-AA12 -> -7625 | AD12: =+H12-SUM(AA12:AC12) -> -9681 | AE12: -10136 | AF12: =-21671-AE12 -> -11535 | AG12: =-30941-AF12-AE12 -> -9270 | AH12: =+I12-SUM(AE12:AG12) -> 3219 | AI12: -3564 | AJ12: =-7157-AI12 -> -3593 | AK12: =-10605-AJ12-AI12 -> -3448 | AL12: =+J12-SUM(AI12:AK12) -> -3577 | AM12: -4289 | AN12: =-9522-AM12 -> -5233 | AO12: =-13028-AN12-AM12 -> -3506 | AP12: =+K12-SUM(AM12:AO12) -> -2363 | AQ12: -4307 | AR12: =-8890-AQ12 -> -4583 | AS12: =-13433-AR12-AQ12 -> -4543 | AT12: =+L12-SUM(AQ12:AS12) -> -2305 | AU12: -3564 | AV12: =-6183-AU12 -> -2619
B13: Total | C13: =+C9+C10+C11+C12 -> 164446 | D13: =+D9+D10+D11+D12 -> 158933 | E13: =+E9+E10+E11+E12 -> 162914 | F13: =+F9+F10+F11+F12 -> 169187 | G13: =+G9+G10+G11+G12 -> 181004 | H13: =+H9+H10+H11+H12 -> 192186 | I13: =+I9+I10+I11+I12 -> 204362 | J13: =+J9+J10+J11+J12 -> 210953 | ... M13: =+M9+M10+M11+M12 -> 220820 | O13: =+O9+O10+O11+O12 -> 40507 | P13: =+P9+P10+P11+P12 -> 41732 | Q13: =+Q9+Q10+Q11+Q12 -> 39637 | R13: =+R9+R10+R11+R12 -> 41038 | S13: =+S9+S10+S11+S12 -> 40618 | T13: =+T9+T10+T11+T12 -> 41366 | U13: =+U9+U10+U11+U12 -> 42452 | V13: =+V9+V10+V11+V12 -> 44751 | ... AV13: =+AV9+AV10+AV11+AV12 -> 55493
B14: Check | C14: =C13-Model!C10 -> -816 | D14: =D13-Model!D10 -> 0 | E14: =E13-Model!E10 -> 0 | F14: =F13-Model!F10 -> 0 | G14: =G13-Model!G10 -> 0 | H14: =H13-Model!H10 -> 0 | I14: =I13-Model!I10 -> 0 | J14: =J13-Model!J10 -> 0 | ... M14: =M13-Model!M10 -> 0 | O14: =O13-Model!O10 -> 0 | P14: =P13-Model!P10 -> 0 | Q14: =Q13-Model!Q10 -> -775 | R14: =R13-Model!R10 -> 775 | S14: =S13-Model!S10 -> 0 | T14: =T13-Model!T10 -> 0 | U14: =U13-Model!U10 -> 0 | V14: =V13-Model!V10 -> 0 | ... AV14: =AV13-Model!AV10 -> 0
B16: Revenue by business segment (Share %)
B17: Wireless | C17: =+C9/C$13 -> 0.6329555 | D17: =+D9/D$13 -> 0.58245928 | E17: =+E9/E$13 -> 0.5520029 | F17: =+F9/F$13 -> 0.5727745 | G17: =+G9/G$13 -> 0.57573866 | H17: =+H9/H$13 -> 0.55476986 | I17: =+I9/I$13 -> 0.51024163 | J17: =+J9/J$13 -> 0.49490171 | ... M17: =+M9/M$13 -> 0.47204058 | O17: =+O9/O$13 -> 0.55773076 | P17: =+P9/P$13 -> 0.54258123 | Q17: =+Q9/Q$13 -> 0.55826627 | R17: =+R9/R$13 -> 0.5498806 | S17: =+S9/S$13 -> 0.55367079 | T17: =+T9/T$13 -> 0.57394962 | U17: =+U9/U$13 -> 0.57486102 | V17: =+V9/V$13 -> 0.58704833 | ... AV17: =+AV9/AV$13 -> 0.47117654
B18: Fixed Line | C18: =+C10/C$13 -> 0.44226068 | D18: =+D10/D$13 -> 0.4929184 | E18: =+E10/E$13 -> 0.52311035 | F18: =+F10/F$13 -> 0.52844486 | G18: =+G10/G$13 -> 0.54550728 | H18: =+H10/H$13 -> 0.60354032 | I18: =+I10/I$13 -> 0.62540981 | J18: =+J10/J$13 -> 0.57232654 | ... M18: =+M10/M$13 -> 0.58697129 | O18: =+O10/O$13 -> 0.50502382 | P18: =+P10/P$13 -> 0.50788364 | Q18: =+Q10/Q$13 -> 0.54706461 | R18: =+R10/R$13 -> 0.53331059 | S18: =+S10/S$13 -> 0.54160717 | T18: =+T10/T$13 -> 0.53710777 | U18: =+U10/U$13 -> 0.52414492 | V18: =+V10/V$13 -> 0.51256955 | ... AV18: =+AV10/AV$13 -> 0.5760186
B19: Others. | C19: =+C11/C$13 -> 0.005150627 | D19: =+D11/D$13 -> 0.0080474162 | E19: =+E11/E$13 -> 0.0069852806 | F19: =+F11/F$13 -> 0 | G19: =+G11/G$13 -> 0 | H19: =+H11/H$13 -> 0 | I19: =+I11/I$13 -> 0 | J19: =+J11/J$13 -> 0 | ... M19: =+M11/M$13 -> 0 | O19: =+O11/O$13 -> 0.0077023724 | P19: =+P11/P$13 -> 0.0071887281 | Q19: =+Q11/Q$13 -> 0.0078209754 | R19: =+R11/R$13 -> 0.0052634144 | S19: =+S11/S$13 -> 0 | T19: =+T11/T$13 -> 0 | U19: =+U11/U$13 -> 0 | V19: =+V11/V$13 -> 0 | ... AV19: =+AV11/AV$13 -> 0
B20: Inter-segment transactions | C20: =+C12/C$13 -> -0.080366807 | D20: =+D12/D$13 -> -0.083425091 | E20: =+E12/E$13 -> -0.082098531 | F20: =+F12/F$13 -> -0.10121936 | G20: =+G12/G$13 -> -0.12124594 | H20: =+H12/H$13 -> -0.15831018 | I20: =+I12/I$13 -> -0.13565144 | J20: =+J12/J$13 -> -0.067228245 | ... M20: =+M12/M$13 -> -0.059011865 | O20: =+O12/O$13 -> -0.070456958 | P20: =+P12/P$13 -> -0.057653599 | Q20: =+Q12/Q$13 -> -0.11315185 | R20: =+R12/R$13 -> -0.088454603 | S20: =+S12/S$13 -> -0.095277956 | T20: =+T12/T$13 -> -0.11105739 | U20: =+U12/U$13 -> -0.099005936 | V20: =+V12/V$13 -> -0.099617886 | ... AV20: =+AV12/AV$13 -> -0.047195142
B21: Total | C21: =+C17+C18+C19+C20 -> 1 | D21: =+D17+D18+D19+D20 -> 1 | E21: =+E17+E18+E19+E20 -> 1 | F21: =+F17+F18+F19+F20 -> 1 | G21: =+G17+G18+G19+G20 -> 1 | H21: =+H17+H18+H19+H20 -> 1 | I21: =+I17+I18+I19+I20 -> 1 | J21: =+J17+J18+J19+J20 -> 1 | ... M21: =+M17+M18+M19+M20 -> 1 | O21: =+O17+O18+O19+O20 -> 1 | P21: =+P17+P18+P19+P20 -> 1 | Q21: =+Q17+Q18+Q19+Q20 -> 1 | R21: =+R17+R18+R19+R20 -> 1 | S21: =+S17+S18+S19+S20 -> 1 | T21: =+T17+T18+T19+T20 -> 1 | U21: =+U17+U18+U19+U20 -> 1 | V21: =+V17+V18+V19+V20 -> 1 | ... AV21: =+AV17+AV18+AV19+AV20 -> 1
B23: Revenue by business segment (YoY % Growth)
B24: Wireless | D24: =D9/C9-1 -> -0.11062861 | E24: =E9/D9-1 -> -0.02855075 | F24: =F9/E9-1 -> 0.077583427 | G24: =G9/F9-1 -> 0.075382329 | H24: =H9/G9-1 -> 0.023106966 | I24: =I9/H9-1 -> -0.021994204 | J24: =J9/I9-1 -> 0.001217945 | K24: =K9/J9-1 -> 0.012768077 | L24: =L9/K9-1 -> -0.022868708 | S24: =S9/O9-1 -> -0.004559136 | T24: =T9/P9-1 -> 0.048535971 | U24: =U9/Q9-1 -> 0.10285611 | V24: =V9/R9-1 -> 0.16418506 | W24: =W9/S9-1 -> 0.12739562 | X24: =X9/T9-1 -> 0.034327352 | Y24: =Y9/U9-1 -> 0.098385511 | Z24: =Z9/V9-1 -> 0.046591298 | ... AV24: =AV9/AR9-1 -> 0.035319739
B25: Fixed Line | D25: =D10/C10-1 -> 0.077177978 | E25: =E10/D10-1 -> 0.087833957 | F25: =F10/E10-1 -> 0.049095304 | G25: =G10/F10-1 -> 0.10438897 | H25: =H10/G10-1 -> 0.17473339 | I25: =I10/H10-1 -> 0.10188634 | J25: =J10/I10-1 -> -0.05536343 | K25: =K10/J10-1 -> 0.047675054 | L25: =L10/K10-1 -> 0.034152897 | S25: =S10/O10-1 -> 0.075377621 | T25: =T10/P10-1 -> 0.0482661 | U25: =U10/Q10-1 -> 0.026148312 | V25: =V10/R10-1 -> 0.048067258 | W25: =W10/S10-1 -> 0.031637802 | X25: =X10/T10-1 -> 0.070663426 | Y25: =Y10/U10-1 -> 0.14817312 | Z25: =Z10/V10-1 -> 0.16435609 | ... AV25: =AV10/AR10-1 -> -0.04936803
B26: Others. | D26: =D11/C11-1 -> 0.51003542 | E26: =E11/D11-1 -> -0.11024238 | F26: =F11/E11-1 -> -1 | G26: =G11/F11-1 -> #DIV/0! | H26: =H11/G11-1 -> #DIV/0! | I26: =I11/H11-1 -> #DIV/0! | J26: =J11/I11-1 -> #DIV/0! | K26: =K11/J11-1 -> #DIV/0! | L26: =L11/K11-1 -> #DIV/0! | S26: =S11/O11-1 -> -1 | T26: =T11/P11-1 -> -1 | U26: =U11/Q11-1 -> -1 | V26: =V11/R11-1 -> -1 | W26: =W11/S11-1 -> #DIV/0! | X26: =X11/T11-1 -> #DIV/0! | Y26: =Y11/U11-1 -> #DIV/0! | Z26: =Z11/V11-1 -> #DIV/0! | ... AV26: =AV11/AR11-1 -> #DIV/0!
B27: Inter-segment transactions | D27: =D12/C12-1 -> 0.003253632 | E27: =E12/D12-1 -> 0.0087487744 | F27: =F12/E12-1 -> 0.28037383 | G27: =G12/F12-1 -> 0.28151825 | H27: =H12/G12-1 -> 0.38635742 | I27: =I12/H12-1 -> -0.088841413 | J27: =J12/I12-1 -> -0.48842075 | K27: =K12/J12-1 -> 0.085248907 | L27: =L12/K12-1 -> 0.022545644 | S27: =S12/O12-1 -> 0.35599159 | T27: =T12/P12-1 -> 0.90939318 | U27: =U12/Q12-1 -> -0.062876254 | V27: =V12/R12-1 -> 0.22809917 | W27: =W12/S12-1 -> 0.1377261 | X27: =X12/T12-1 -> 0.144101 | Y27: =Y12/U12-1 -> 0.39566976 | Z27: =Z12/V12-1 -> 0.44033199 | ... AV27: =AV12/AR12-1 -> -0.42854026
B28: Total | D28: =D13/C13-1 -> -0.033524683 | E28: =E13/D13-1 -> 0.025048291 | F28: =F13/E13-1 -> 0.038504978 | G28: =G13/F13-1 -> 0.069845792 | H28: =H13/G13-1 -> 0.06177764 | I28: =I13/H13-1 -> 0.063355291 | J28: =J13/I13-1 -> 0.032251593 | K28: =K13/J13-1 -> 0.027873507 | L28: =L13/K13-1 -> 0.0071714176 | S28: =S13/O13-1 -> 0.0027402671 | T28: =T13/P13-1 -> -0.0087702483 | U28: =U13/Q13-1 -> 0.071019502 | V28: =V13/R13-1 -> 0.090477119 | W28: =W13/S13-1 -> 0.07454823 | X28: =X13/T13-1 -> 0.041652565 | Y28: =Y13/U13-1 -> 0.095048525 | Z28: =Z13/V13-1 -> 0.06773033 | ... AV28: =AV13/AR13-1 -> 0.022027
B31: EBITDA by business segment
B32: Wireless | C32: 32915 | D32: 36395 | E32: 34235 | F32: 52789 | G32: 60272 | H32: 60971 | I32: 52215 | J32: 56505 | K32: 55634 | L32: 57589 | M32: =SUM(AS32:AV32) -> 59003 | O32: 8539 | P32: =17577-O32 -> 9038 | Q32: =26046-P32-O32 -> 8469 | R32: =+E32-SUM(O32:Q32) -> 8189 | S32: 12166 | T32: =26005-S32 -> 13839 | U32: =39126-T32-S32 -> 13121 | V32: =+F32-SUM(S32:U32) -> 13663 | W32: 14213 | X32: =29012-W32 -> 14799 | Y32: =44248-X32-W32 -> 15236 | Z32: =+G32-SUM(W32:Y32) -> 16024 | AA32: 14802 | AB32: =30138-AA32 -> 15336 | AC32: =45469-AB32-AA32 -> 15331 | AD32: =+H32-SUM(AA32:AC32) -> 15502 | AE32: 13292 | AF32: =25640-AE32 -> 12348 | AG32: =36160-AF32-AE32 -> 10520 | AH32: =+I32-SUM(AE32:AG32) -> 16055 | AI32: 13236 | AJ32: =25803-AI32 -> 12567 | AK32: =39408-AJ32-AI32 -> 13605 | AL32: =+J32-SUM(AI32:AK32) -> 17097 | AM32: 12832 | AN32: =25015-AM32 -> 12183 | AO32: =38285-AM32-AN32 -> 13270 | AP32: =+K32-SUM(AM32:AO32) -> 17349 | AQ32: 13706 | AR32: =27116-AQ32 -> 13410 | AS32: =40084-AQ32-AR32 -> 12968 | AT32: =+L32-SUM(AQ32:AS32) -> 17505 | AU32: 13637 | AV32: =28530-AU32 -> 14893
B33: Fixed Line | C33: 26950 | D33: 29478 | E33: 30875 | F33: 33162 | G33: 33405 | H33: 46019 | I33: 55051 | J33: 56966 | K33: 61953 | L33: 63253 | M33: =SUM(AS33:AV33) -> 60678 | O33: 8229 | P33: =16127-O33 -> 7898 | Q33: =24320-P33-O33 -> 8193 | R33: =+E33-SUM(O33:Q33) -> 6555 | S33: 9044 | T33: =16389-S33 -> 7345 | U33: =23039-T33-S33 -> 6650 | V33: =+F33-SUM(S33:U33) -> 10123 | W33: 9068 | X33: =17373-W33 -> 8305 | Y33: =26475-X33-W33 -> 9102 | Z33: =+G33-SUM(W33:Y33) -> 6930 | AA33: 10307 | AB33: =20534-AA33 -> 10227 | AC33: =32120-AB33-AA33 -> 11586 | AD33: =+H33-SUM(AA33:AC33) -> 13899 | AE33: 11213 | AF33: =26555-AE33 -> 15342 | AG33: =44410-AF33-AE33 -> 17855 | AH33: =+I33-SUM(AE33:AG33) -> 10641 | AI33: 13621 | AJ33: =28896-AI33 -> 15275 | AK33: =43630-AJ33-AI33 -> 14734 | AL33: =+J33-SUM(AI33:AK33) -> 13336 | AM33: 15597 | AN33: =31989-AM33 -> 16392 | AO33: =47819-AM33-AN33 -> 15830 | AP33: =+K33-SUM(AM33:AO33) -> 14134 | AQ33: 16449 | AR33: =32823-AQ33 -> 16374 | AS33: =49331-AQ33-AR33 -> 16508 | AT33: =+L33-SUM(AQ33:AS33) -> 13922 | AU33: 15846 | AV33: =30248-AU33 -> 14402
B34: Others. | C34: -276 | D34: -1307 | E34: -2688 | F34: -101 | G34: -12 | H34: -7 | I34: -12 | J34: -18 | K34: -48 | L34: -7 | M34: =SUM(AS34:AV34) -> -3 | O34: -621 | P34: =-1313-O34 -> -692 | Q34: =-1839-P34-O34 -> -526 | R34: =+E34-SUM(O34:Q34) -> -849 | S34: -6 | T34: =-10-S34 -> -4 | U34: =-91-T34-S34 -> -81 | V34: =+F34-SUM(S34:U34) -> -10 | W34: -6 | X34: =-8-W34 -> -2 | Y34: =-7-X34-W34 -> 1 | Z34: =+G34-SUM(W34:Y34) -> -5 | AA34: -2 | AB34: =-4-AA34 -> -2 | AC34: =-7-AB34-AA34 -> -3 | AD34: =+H34-SUM(AA34:AC34) -> 0 | AE34: -5 | AF34: =-8-AE34 -> -3 | AG34: =-11-AF34-AE34 -> -3 | AH34: =+I34-SUM(AE34:AG34) -> -1 | AI34: -5 | AJ34: =-7-AI34 -> -2 | AK34: =-15-AJ34-AI34 -> -8 | AL34: =+J34-SUM(AI34:AK34) -> -3 | AM34: -31 | AN34: =-46-AM34 -> -15 | AO34: =-102-AM34-AN34 -> -56 | AP34: =+K34-SUM(AM34:AO34) -> 54 | AQ34: -5 | AR34: =-6-AQ34 -> -1 | AS34: =-6-AQ34-AR34 -> 0 | AT34: =+L34-SUM(AQ34:AS34) -> -1 | AU34: -1 | AV34: =-2-AU34 -> -1
B35: Inter-segment transactions | C35: 1572 | D35: 1608 | E35: 1605 | F35: -6035 | G35: -7507 | H35: -10801 | I35: -9666 | J35: -9156 | K35: -9024 | L35: -9604 | M35: =SUM(AS35:AV35) -> -7929 | O35: 386 | P35: =794-O35 -> 408 | Q35: =1172-P35-O35 -> 378 | R35: =+E35-SUM(O35:Q35) -> 433 | S35: -1357 | T35: =-2718-S35 -> -1361 | U35: =-4139-T35-S35 -> -1421 | V35: =+F35-SUM(S35:U35) -> -1896 | W35: -1663 | X35: =-3212-W35 -> -1549 | Y35: =-4852-X35-W35 -> -1640 | Z35: =+G35-SUM(W35:Y35) -> -2655 | AA35: -2035 | AB35: =-4341-AA35 -> -2306 | AC35: =-6766-AB35-AA35 -> -2425 | AD35: =+H35-SUM(AA35:AC35) -> -4035 | AE35: -3597 | AF35: =-7443-AE35 -> -3846 | AG35: =-11158-AF35-AE35 -> -3715 | AH35: =+I35-SUM(AE35:AG35) -> 1492 | AI35: -2453 | AJ35: =-4934-AI35 -> -2481 | AK35: =-7044-AJ35-AI35 -> -2110 | AL35: =+J35-SUM(AI35:AK35) -> -2112 | AM35: -1083 | AN35: =-3022-AM35 -> -1939 | AO35: =-5284-AM35-AN35 -> -2262 | AP35: =+K35-SUM(AM35:AO35) -> -3740 | AQ35: -2285 | AR35: =-4401-AQ35 -> -2116 | AS35: =-6564-AQ35-AR35 -> -2163 | AT35: =+L35-SUM(AQ35:AS35) -> -3040 | AU35: -1194 | AV35: =-2726-AU35 -> -1532
B36: Discontinued Operations | H36: -13 | I36: -326 | J36: 0 | K36: 0 | L36: 0 | M36: =SUM(AS36:AV36) -> 0 | AD36: =+H36-SUM(AA36:AC36) -> -13 | AE36: 4 | AF36: =-8-AE36 -> -12 | AG36: =-59-AF36-AE36 -> -51 | AH36: =+I36-SUM(AE36:AG36) -> -267 | AI36: -21 | AJ36: =-39-AI36 -> -18 | AK36: =-45-AJ36-AI36 -> -6 | AL36: =+J36-SUM(AI36:AK36) -> 45 | AM36: 0 | AN36: =0-AM36 -> 0 | AO36: =0-AM36-AN36 -> 0 | AP36: =+K36-SUM(AM36:AO36) -> 0 | AQ36: 0 | AR36: =0-AQ36 -> 0 | AS36: =0-AQ36-AR36 -> 0 | AT36: =+L36-SUM(AQ36:AS36) -> 0 | AU36: 0 | AV36: =0-AU36 -> 0
B37: Total | C37: =+C32+C33+C34+C35+C36 -> 61161 | D37: =+D32+D33+D34+D35+D36 -> 66174 | E37: =+E32+E33+E34+E35+E36 -> 64027 | F37: =+F32+F33+F34+F35+F36 -> 79815 | G37: =+G32+G33+G34+G35+G36 -> 86158 | H37: =+H32+H33+H34+H35+H36 -> 96169 | I37: 100262 | J37: =+J32+J33+J34+J35+J36 -> 104297 | K37: =+K32+K33+K34+K35+K36 -> 108515 | L37: =+L32+L33+L34+L35+L36 -> 111231 | M37: =+M32+M33+M34+M35+M36 -> 111749 | O37: =+O32+O33+O34+O35+O36 -> 16533 | P37: =+P32+P33+P34+P35+P36 -> 16652 | Q37: =+Q32+Q33+Q34+Q35+Q36 -> 16514 | R37: =+R32+R33+R34+R35+R36 -> 14328 | S37: =+S32+S33+S34+S35+S36 -> 19847 | T37: =+T32+T33+T34+T35+T36 -> 19819 | U37: =+U32+U33+U34+U35+U36 -> 18269 | V37: =+V32+V33+V34+V35+V36 -> 21880 | ... AG37: =+AG32+AG33+AG34+AG35+AG36 -> 24606 | AH37: =+AH32+AH33+AH34+AH35+AH36+3000 -> 30920 | AI37: =+AI32+AI33+AI34+AI35+AI36 -> 24378 | AJ37: =+AJ32+AJ33+AJ34+AJ35+AJ36 -> 25341 | AK37: =+AK32+AK33+AK34+AK35+AK36 -> 26215 | AL37: =+AL32+AL33+AL34+AL35+AL36 -> 28363 | AM37: =+AM32+AM33+AM34+AM35+AM36 -> 27315 | AN37: =+AN32+AN33+AN34+AN35+AN36 -> 26621 | AO37: =+AO32+AO33+AO34+AO35+AO36 -> 26782 | AP37: =+AP32+AP33+AP34+AP35+AP36 -> 27797 | ... AV37: =+AV32+AV33+AV34+AV35+AV36 -> 27762
B38: Check | C38: =C37-Model!C55 -> 0 | D38: =D37-Model!D55 -> 0 | E38: =E37-Model!E55 -> 0 | F38: =F37-Model!F55 -> 0 | G38: =G37-Model!G55 -> 0 | H38: =H37-Model!H51 -> 0 | I38: =I37-Model!I51 -> 0 | J38: =J37-Model!J51 -> 0 | K38: =K37-Model!K51 -> 0 | L38: =L37-Model!L51 -> 0 | M38: =M37-Model!M51 -> 0 | O38: =O37-Model!O55 -> 0 | P38: =P37-Model!P55 -> 0 | Q38: =Q37-Model!Q55 -> 0 | R38: =R37-Model!R55 -> 0 | S38: =S37-Model!S55 -> 0 | T38: =T37-Model!T55 -> 0 | U38: =U37-Model!U55 -> 0 | V38: =V37-Model!V55 -> 0 | ... Z38: =Z37-Model!Z55 -> 0 | AA38: =AA37-Model!AA51 -> 0 | AB38: =AB37-Model!AB51 -> 0 | AC38: =AC37-Model!AC51 -> 0 | AD38: =AD37-Model!AD51 -> 0 | AE38: =AE37-Model!AE51 -> 0 | AF38: =AF37-Model!AF51 -> 0 | AG38: =AG37-Model!AG51 -> 0 | AH38: =AH37-Model!AH51 -> 0 | ... AV38: =AV37-Model!AV51 -> 0
B40: % margin
B41: Wireless | C41: =+C32/C9 -> 0.31622585 | D41: =+D32/D9 -> 0.39315344 | E41: =+E32/E9 -> 0.38068921 | F41: =+F32/F9 -> 0.54474439 | G41: =+G32/G9 -> 0.57836505 | H41: =+H32/H9 -> 0.57185867 | I41: =+I32/I9 -> 0.50074803 | J41: =+J32/J9 -> 0.54123045 | ... M41: =+M32/M9 -> 0.56605204 | O41: =+O32/O9 -> 0.37796565 | P41: =+P32/P9 -> 0.39915206 | Q41: =+Q32/Q9 -> 0.38272777 | R41: =+R32/R9 -> 0.36289108 | S41: =+S32/S9 -> 0.54097559 | T41: =+T32/T9 -> 0.58289108 | U41: =+U32/U9 -> 0.53765776 | V41: =+V32/V9 -> 0.52007917 | ... AV41: =+AV32/AV9 -> 0.56958733
B42: Fixed Line | C42: =+C33/C10 -> 0.37055879 | D42: =+D33/D10 -> 0.37627807 | E42: =+E33/E10 -> 0.36228908 | F42: =+F33/F10 -> 0.3709147 | G42: =+G33/G10 -> 0.33831617 | H42: =+H33/H10 -> 0.39674288 | I42: =+I33/I10 -> 0.4307253 | J42: =+J33/J10 -> 0.47183064 | ... M42: =+M33/M10 -> 0.46814026 | O42: =+O33/O10 -> 0.4022584 | P42: =+P33/P10 -> 0.37263506 | Q42: =+Q33/Q10 -> 0.37783619 | R42: =+R33/R10 -> 0.29950653 | S42: =+S33/S10 -> 0.4111096 | T42: =+T33/T10 -> 0.33058781 | U42: =+U33/U10 -> 0.29886297 | V42: =+V33/V10 -> 0.44132008 | ... AV42: =+AV33/AV10 -> 0.45055529
B43: Others. | C43: =+IFERROR(C34/C11,"") -> -0.32585596 | D43: =+IFERROR(D34/D11,"") -> -1.0218921 | E43: =+IFERROR(E34/E11,"") -> -2.3620387 | F43: =+IFERROR(F34/F11,"") | G43: =+IFERROR(G34/G11,"") | H43: =+IFERROR(H34/H11,"") | I43: =+IFERROR(I34/I11,"") | J43: =+IFERROR(J34/J11,"") | ... M43: =+IFERROR(M34/M11,"") | O43: =+IFERROR(O34/O11,"") -> -1.9903846 | P43: =+IFERROR(P34/P11,"") -> -2.3066667 | Q43: =+IFERROR(Q34/Q11,"") -> -1.6967742 | R43: =+IFERROR(R34/R11,"") -> -3.9305556 | S43: =+IFERROR(S34/S11,"") | T43: =+IFERROR(T34/T11,"") | U43: =+IFERROR(U34/U11,"") | V43: =+IFERROR(V34/V11,"") | ... AV43: =+IFERROR(AV34/AV11,"")
B44: Inter-segment transactions | C44: =+C35/C12 -> -0.11894673 | D44: =+D35/D12 -> -0.12127611 | E44: =+E35/E12 -> -0.12 | F44: =+F35/F12 -> 0.35240876 | G44: =+G35/G12 -> 0.34206689 | H44: =+H35/H12 -> 0.35500411 | I44: =+I35/I12 -> 0.34867614 | J44: =+J35/J12 -> 0.64560711 | ... M44: =+M35/M12 -> 0.6084721 | O44: =+O35/O12 -> -0.13524877 | P44: =+P35/P12 -> -0.16957606 | Q44: =+Q35/Q12 -> -0.084280936 | R44: =+R35/R12 -> -0.11928375 | S44: =+S35/S12 -> 0.35064599 | T44: =+T35/T12 -> 0.29625599 | U44: =+U35/U12 -> 0.33809184 | V44: =+V35/V12 -> 0.42530283 | ... AV44: =+AV35/AV12 -> 0.58495609
B45: Total | C45: =+C37/C13 -> 0.37192148 | D45: =+D37/D13 -> 0.41636413 | E45: =+E37/E13 -> 0.39301104 | F45: =+F37/F13 -> 0.4717561 | G45: =+G37/G13 -> 0.47600053 | H45: =+H37/H13 -> 0.50039545 | I45: =+I37/I13 -> 0.4906098 | J45: =+J37/J13 -> 0.49440871 | ... M45: =+M37/M13 -> 0.50606376 | O45: =+O37/O13 -> 0.40815168 | P45: =+P37/P13 -> 0.39902233 | Q45: =+Q37/Q13 -> 0.41663093 | R45: =+R37/R13 -> 0.34913982 | S45: =+S37/S13 -> 0.48862573 | T45: =+T37/T13 -> 0.47911328 | U45: =+U37/U13 -> 0.43034486 | V45: =+V37/V13 -> 0.48892762 | ... AV45: =+AV37/AV13 -> 0.50027931
B48: Mobile Subscribers by Category | C48: =+C49+C54 -> 62763209 | D48: =+D49+D54 -> 58293908 | E48: =+E49+E54 -> 60499017 | F48: =+F49+F54 -> 73118155 | G48: =+G49+G54 -> 72933839 | H48: =+H49+H54 -> 71221952 | I48: =+I49+I54 -> 66304761 | J48: =+J49+J54 -> 57827126 | ... M48: =+M49+M54 -> 60088208 | O48: =+O49+O54 -> 58117819 | P48: =+P49+P54 -> 58510872 | Q48: =+Q49+Q54 -> 58034007 | R48: =+R49+R54 -> 60499017 | S48: =+S49+S54 -> 63948886 | T48: =+T49+T54 -> 67547646 | U48: =+U49+U54 -> 71451288 | V48: =+V49+V54 -> 73118155 | ... AV48: =+AV49+AV54 -> 60088208
B49: Prepaid | C49: =+C50+C51+C52 -> 59952941 | D49: =+D50+D51+D52 -> 55776646 | E49: =+E50+E51+E52 -> 58178978 | F49: =+F50+F51+F52 -> 70721789 | G49: =+G50+G51+G52 -> 70779021 | H49: =+H50+H51+H52 -> 69205731 | I49: =+I50+I51+I52 -> 64287019 | J49: =+J50+J51+J52 -> 55667880 | ... M49: =+M50+M51+M52 -> 57684768 | O49: =+O50+O51+O52 -> 55666020 | P49: =+P50+P51+P52 -> 56081230 | Q49: =+Q50+Q51+Q52 -> 55627968 | R49: =+R50+R51+R52 -> 58178978 | S49: =+S50+S51+S52 -> 61585197 | T49: =+T50+T51+T52 -> 65151418 | U49: =+U50+U51+U52 -> 69012106 | V49: =+V50+V51+V52 -> 70721789 | ... AV49: =+AV50+AV51+AV52 -> 57684768
B50: Smart Prepaid | C50: 21643963 | D50: 20433351 | E50: 20532174 | F50: 25866195 | G50: 29090167 | H50: 26665974 | I50: 24394379 | J50: 21530993 | K50: 21759728 | L50: 21713502 | M50: =AV50 -> 21737420 | O50: 20198965 | P50: 20261130 | Q50: 19526064 | R50: =+E50 -> 20532174 | S50: 22011859 | T50: 23734790 | U50: 25240171 | V50: =+F50 -> 25866195 | W50: 24830033 | X50: 23413304 | Y50: 23983929 | Z50: =+G50 -> 29090167 | AA50: 27227210 | AB50: 26915884 | AC50: 25966496 | AD50: =+H50 -> 26665974 | AE50: 26229708 | AF50: 25679480 | AG50: 25103659 | AH50: =+I50 -> 24394379 | AI50: 24044239 | AJ50: 23486725 | AK50: 20494009 | AL50: =+J50 -> 21530993 | AM50: 21856044 | AN50: 22550066 | AO50: 22416116 | AP50: =+K50 -> 21759728 | AQ50: 21324961 | AR50: 21247707 | AS50: 21420767 | AT50: =L50 -> 21713502 | AU50: 22005736 | AV50: 21737420
B51: Sun Prepaid | C51: 8463469 | D51: 6535331 | E51: 5753163 | F51: 6547231 | O51: 6235105 | P51: 6066566 | Q51: 5972878 | R51: =+E51 -> 5753163 | S51: 6041687 | T51: 5837580 | U51: 6152209 | V51: =+F51 -> 6547231 | W51: 6889658 | X51: 5686892 | Y51: 5597613
B52: TNT | C52: 29845509 | D52: 28807964 | E52: 31893641 | F52: 38308363 | G52: 41688854 | H52: 42539757 | I52: 39892640 | J52: 34136887 | K52: 34971761 | L52: 35821310 | M52: =AV52 -> 35947348 | O52: 29231950 | P52: 29753534 | Q52: 30129026 | R52: =+E52 -> 31893641 | S52: 33531651 | T52: 35579048 | U52: 37619726 | V52: =+F52 -> 38308363 | W52: 38871067 | X52: 38638225 | Y52: 40466221 | Z52: =+G52 -> 41688854 | AA52: 42479536 | AB52: 42709264 | AC52: 42558269 | AD52: =+H52 -> 42539757 | AE52: 41994310 | AF52: 41685682 | AG52: 40868460 | AH52: =+I52 -> 39892640 | AI52: 38955398 | AJ52: 37404410 | AK52: 32611067 | AL52: =+J52 -> 34136887 | AM52: 34929674 | AN52: 36024530 | AO52: 35645406 | AP52: =+K52 -> 34971761 | AQ52: 34976020 | AR52: 35533677 | AS52: 35516319 | AT52: =L52 -> 35821310 | AU52: 36472452 | AV52: 35947348
B54: Postpaid | C54: =+C55+C56 -> 2810268 | D54: =+D55+D56 -> 2517262 | E54: =+E55+E56 -> 2320039 | F54: =+F55+F56 -> 2396366 | G54: =+G55+G56 -> 2154818 | H54: =+H55+H56 -> 2016221 | I54: =+I55+I56 -> 2017742 | J54: 2159246 | K54: 2258318 | L54: 2356708 | M54: =AV54 -> 2403440 | O54: =+O55+O56 -> 2451799 | P54: =+P55+P56 -> 2429642 | Q54: =+Q55+Q56 -> 2406039 | R54: =+R55+R56 -> 2320039 | S54: =+S55+S56 -> 2363689 | T54: =+T55+T56 -> 2396228 | U54: =+U55+U56 -> 2439182 | V54: =+V55+V56 -> 2396366 | ... AJ54: =+AJ55+AJ56 -> 2062683 | AK54: 2141054 | AL54: =J54 -> 2159246 | AM54: 2034703 | AN54: 2185028 | AO54: 2209487 | AP54: =+K54 -> 2258318 | AQ54: 2307482 | AR54: 2313920 | AS54: 2345551 | AT54: =L54 -> 2356708 | AU54: 2404612 | AV54: 2403440
B55: Smart Postpaid | C55: 1383830 | D55: 1388090 | E55: 1424115 | F55: 1469407 | G55: 1443649 | H55: 1487073 | I55: 1964871 | O55: 1402046 | P55: 1425105 | Q55: 1430675 | R55: =+E55 -> 1424115 | S55: 1464873 | T55: 1469847 | U55: 1485550 | V55: =+F55 -> 1469407 | W55: 1476694 | X55: 1489015 | Y55: 1457452 | Z55: =+G55 -> 1443649 | AA55: 1442365 | AB55: 1434114 | AC55: 1444657 | AD55: =+H55 -> 1487073 | AE55: 1584121 | AF55: 1962471 | AG55: 1961675 | AH55: =+I55 -> 1964871 | AI55: 38955398 | AJ55: 2019828
B56: Sun Postpaid | C56: 1426438 | D56: 1129172 | E56: 895924 | F56: 926959 | G56: 711169 | H56: 529148 | I56: 52871 | O56: 1049753 | P56: 1004537 | Q56: 975364 | R56: =+E56 -> 895924 | S56: 898816 | T56: 926381 | U56: 953632 | V56: =+F56 -> 926959 | W56: 1008175 | X56: 958053 | Y56: 886948 | Z56: =+G56 -> 711169 | AA56: 655301 | AB56: 626867 | AC56: 595554 | AD56: =+H56 -> 529148 | AE56: 471532 | AF56: 70500 | AG56: 61940 | AH56: =+I56 -> 52871 | AI56: 47357 | AJ56: 42855
B58: Subscriber Base: Fixed Line and Broadband
B59: Fixed Line Subscribers | C59: 2438473 | D59: 2663210 | E59: 2710972 | F59: 2765209 | G59: 3042815 | H59: 3619372 | I59: 3825424 | J59: 3766105 | K59: 3711371 | L59: 3689997 | M59: =AU59 -> 3580475 | O59: 2707079 | P59: 2756865 | Q59: 2778274 | R59: =+E59 -> 2710972 | S59: 2707077 | T59: 2711411 | U59: 2727035 | V59: =+F59 -> 2765209 | W59: 2801187 | X59: 2917641 | Y59: 29991744 | Z59: =+G59 -> 3042815 | AA59: 3108796 | AB59: 3245547 | AC59: 3441847 | AD59: =+H59 -> 3619372 | AE59: 3766956 | AF59: 3821296 | AG59: 3835305 | AH59: =+I59 -> 3825424 | AI59: 3828445 | AJ59: 3823629 | AK59: 3792278 | AL59: =+J59 -> 3766105 | AM59: 3740780 | AN59: 3732523 | AO59: 3727873 | AP59: =+K59 -> 3711371 | AQ59: 3684725 | AR59: 3694922 | AS59: 3694183 | AT59: =+L59 -> 3689997 | AU59: 3580475 | AV59: 3633228
B61: Broadband Subscribers | C61: =+C62+C63 -> 1720753 | D61: =+D62+D63 -> 1950881 | E61: =+E62+E63 -> 2025563 | F61: =+F62+F63 -> 2161484 | G61: =+G62+G63 -> 3090118 | H61: =+H62+H63 -> 3951844 | I61: =+I62+I63 -> 3992303 | J61: =+J62+J63 -> 3709541 | ... M61: =+M62+M63 -> 4368227 | O61: =+O62+O63 -> 1995900 | P61: =+P62+P63 -> 2038333 | Q61: =+Q62+Q63 -> 2054225 | R61: =+R62+R63 -> 2025563 | S61: =+S62+S63 -> 2016507 | T61: =+T62+T63 -> 2041946 | U61: =+U62+U63 -> 2091014 | V61: =+V62+V63 -> 2161484 | ... AV61: =+AV62+AV63 -> 4368227
B62: Fixed Line Broadband | C62: 1450550 | D62: 1713527 | E62: 1812037 | F62: 1931333 | G62: 2273602 | H62: 2966886 | I62: 3247979 | J62: 3268996 | K62: 3431785 | L62: 3793927 | M62: =AV62 -> 3933307 | O62: 1772836 | P62: 1829096 | Q62: 1859210 | R62: =+E62 -> 1812037 | S62: 1818530 | T62: 1841147 | U62: 1878983 | V62: =+F62 -> 1931333 | W62: 1986783 | X62: 2105140 | Y62: 2194931 | Z62: =+G62 -> 2273602 | AA62: 2385197 | AB62: 2538865 | AC62: 2768978 | AD62: =+H62 -> 2966886 | AE62: 3134127 | AF62: 3200872 | AG62: 3241970 | AH62: =+I62 -> 3247979 | AI62: 3281289 | AJ62: 3294012 | AK62: 3280419 | AL62: =+J62 -> 3268996 | AM62: 3255012 | AN62: 3290093 | AO62: 3394975 | AP62: =+K62 -> 3431785 | AQ62: 3507947 | AR62: 3573691 | AS62: 3668384 | AT62: =+L62 -> 3793927 | AU62: 3837443 | AV62: 3933307
B63: Fixed Wireless Broadband | C63: 270203 | D63: 237354 | E63: 213526 | F63: 230151 | G63: 816516 | H63: 984958 | I63: 744324 | J63: 440545 | K63: 446446 | L63: 457499 | M63: =AV63 -> 434920 | O63: 223064 | P63: 209237 | Q63: 195015 | R63: =+E63 -> 213526 | S63: 197977 | T63: 200799 | U63: 212031 | V63: =+F63 -> 230151 | W63: 296005 | X63: 504026 | Y63: 646830 | Z63: =+G63 -> 816516 | AA63: 890873 | AB63: 912403 | AC63: 1008432 | AD63: =+H63 -> 984958 | AE63: 945873 | AF63: 881351 | AG63: 823135 | AH63: =+I63 -> 744324 | AI63: 695242 | AJ63: 607541 | AK63: 409289 | AL63: =+J63 -> 440545 | AM63: 456082 | AN63: 463211 | AO63: 463393 | AP63: =+K63 -> 446446 | AQ63: 437990 | AR63: 445454 | AS63: 454137 | AT63: =+L63 -> 457499 | AU63: 452998 | AV63: 434920
B65: Average monthly churn rates
B66: Smart Postpaid | C66: 0.048 | D66: 0.023 | E66: 0.02 | F66: 0.021 | G66: 0.023 | H66: 0.016 | I66: 0.016 | J66: 0.014 | K66: 0.011 | L66: 0.012 | O66: 0.02 | P66: 0.02 | Q66: 0.021 | R66: =E66 -> 0.02 | S66: 0.02 | T66: 0.021 | U66: 0.02 | V66: =F66 -> 0.021 | W66: 0.024 | X66: 0.017 | Y66: 0.022 | Z66: =+G66 -> 0.023 | AA66: 0.024 | AB66: 0.02 | AC66: 0.018 | AD66: =+H66 -> 0.016 | AE66: 0.012 | AF66: 0.013 | AG66: 0.015 | AH66: =+I66 -> 0.016 | AI66: 0.25 | AJ66: 0.014 | AK66: 0.014 | AL66: =+J66 -> 0.014 | AM66: 0.011 | AN66: 0.011 | AO66: 0.011 | AP66: =+K66 -> 0.011 | AQ66: 0.01 | AR66: 0.011 | AS66: 0.012 | AT66: =+L66 -> 0.012 | AU66: 0.011 | AV66: 0.01
B67: Smart Prepaid | C67: 0.076 | D67: 0.067 | E67: 0.065 | F67: 0.041 | G67: 0.048 | H67: 0.048 | I67: 0.046 | J67: 0.026 | K67: 0.022 | L67: 0.025 | O67: 0.068 | P67: 0.07 | Q67: 0.074 | R67: =E67 -> 0.065 | S67: 0.035 | T67: 0.036 | U67: 0.036 | V67: =F67 -> 0.041 | W67: 0.06 | X67: 0.058 | Y67: 0.052 | Z67: =+G67 -> 0.048 | AA67: 0.056 | AB67: 0.053 | AC67: 0.051 | AD67: =+H67 -> 0.048 | AE67: 0.046 | AF67: 0.046 | AG67: 0.046 | AH67: =+I67 -> 0.046 | AI67: -0.08 | AJ67: 0.039 | AK67: 0.032 | AL67: =+J67 -> 0.026 | AM67: 0.017 | AN67: 0.014 | AO67: 0.018 | AP67: =+K67 -> 0.022 | AQ67: 0.03 | AR67: 0.027 | AS67: 0.025 | AT67: =+L67 -> 0.025 | AU67: 0.024 | AV67: 0.03
B68: TNT | C68: 0.063 | D68: 0.068 | E68: 0.058 | F68: 0.04 | G68: 0.042 | H68: 0.042 | I68: 0.046 | J68: 0.028 | K68: 0.02 | L68: 0.023 | O68: 0.062 | P68: 0.062 | Q68: 0.063 | R68: =E68 -> 0.058 | S68: 0.038 | T68: 0.037 | U68: 0.036 | V68: =F68 -> 0.04 | W68: 0.045 | X68: 0.046 | Y68: 0.042 | Z68: =+G68 -> 0.042 | AA68: 0.04 | AB68: 0.041 | AC68: 0.041 | AD68: =+H68 -> 0.042 | AE68: 0.045 | AF68: 0.044 | AG68: 0.045 | AH68: =+I68 -> 0.046 | AI68: -0.07 | AJ68: 0.043 | AK68: 0.035 | AL68: =+J68 -> 0.028 | AM68: 0.016 | AN68: 0.014 | AO68: 0.018 | AP68: =+K68 -> 0.02 | AQ68: 0.022 | AR68: 0.021 | AS68: 0.022 | AT68: =+L68 -> 0.023 | AU68: 0.025 | AV68: 0.029
B69: Sun Postpaid | C69: 0.064 | D69: 0.035 | E69: 0.035 | F69: 0.02 | G69: 0.031 | H69: 0.025 | I69: 0.037 | O69: 0.039 | P69: 0.036 | Q69: 0.033 | R69: =E69 -> 0.035 | S69: 0.015 | T69: 0.012 | U69: 0.014 | V69: =F69 -> 0.02 | W69: 0.01 | X69: 0.011 | Y69: 0.015 | Z69: =+G69 -> 0.031 | AA69: 0.028 | AB69: 0.022 | AC69: 0.02 | AD69: =+H69 -> 0.025 | AE69: 0.028 | AF69: 0.029 | AG69: 0.033 | AH69: =+I69 -> 0.037 | AI69: -0.9 | AJ69: 0.035
B70: Sun Prepaid | C70: 0.088 | D70: 0.077 | E70: 0.061 | F70: 0.045 | O70: 0.062 | P70: 0.058 | Q70: 0.058 | R70: =E70 -> 0.061 | S70: 0.038 | T70: 0.051 | U70: 0.049 | V70: =F70 -> 0.045 | W70: 0.036 | X70: 0.077 | Y70: 0.072
B72: ARPU
B73: Mobile ARPU, Net
B74: Smart Postpaid | C74: 966 | D74: 1004 | E74: 836 | F74: 824 | G74: 844 | H74: 853 | I74: 766 | O74: 809 | P74: 813 | Q74: 810 | R74: 843 | S74: 796 | T74: 813 | U74: 809 | V74: 806 | W74: 804 | X74: 816 | Y74: 804 | Z74: 828 | AA74: 819 | AB74: 823 | AC74: 825 | AD74: 798 | AE74: 786 | AF74: 723 | AG74: 699 | AH74: 705 | AI74: 678 | AJ74: 691 | AK74: 700 | AL74: 694 | AM74: 703 | AN74: 688 | AO74: 690 | AP74: 684 | AQ74: 670 | AR74: 659 | AS74: 655 | AT74: 683 | AU74: 677 | AV74: 687
B75: Smart Prepaid | C75: 117 | D75: 118 | E75: 130 | F75: 132 | G75: 133 | H75: 123 | I75: 123 | O75: 112 | P75: 116 | Q75: 120 | R75: 123 | S75: 118 | T75: 118 | U75: 114 | V75: 114 | W75: 112 | X75: 110 | Y75: 116 | Z75: 113 | AA75: 104 | AB75: 104 | AC75: 104 | AD75: 105 | AE75: 99 | AF75: 104 | AG75: 106 | AH75: 109 | AI75: 107 | AJ75: 109 | AK75: 128 | AL75: 130 | AM75: 125 | AN75: 119 | AO75: 115 | AP75: 122 | AQ75: 121 | AR75: 118 | AS75: 120 | AT75: 125 | AU75: 118 | AV75: 119
B76: TNT | C76: 82 | D76: 81 | E76: 79 | F76: 77 | G76: 91 | H76: 98 | I76: 97 | O76: 73 | P76: 73 | Q76: 71 | R76: 69 | S76: 67 | T76: 67 | U76: 67 | V76: 74 | W76: 71 | X76: 76 | Y76: 84 | Z76: 86 | AA76: 83 | AB76: 85 | AC76: 84 | AD76: 85 | AE76: 82 | AF76: 86 | AG76: 85 | AH76: 86 | AI76: 86 | AJ76: 92 | AK76: 109 | AL76: 109 | AM76: 106 | AN76: 100 | AO76: 98 | AP76: 105 | AQ76: 103 | AR76: 102 | AS76: 100 | AT76: 103 | AU76: 99 | AV76: 98
B77: Sun Postpaid | C77: 443 | D77: 422 | E77: 403 | F77: 418 | G77: 386 | H77: 440 | I77: 570 | O77: 382 | P77: 403 | Q77: 406 | R77: 414 | S77: 423 | T77: 418 | U77: 401 | V77: 403 | W77: 377 | X77: 386 | Y77: 362 | Z77: 376 | AA77: 407 | AB77: 387 | AC77: 445 | AD77: 475 | AE77: 440 | AF77: 580 | AG77: 458 | AH77: 581 | AI77: 547 | AJ77: 514 | AK77: 534 | AL77: 630
B78: Sun Prepaid | C78: 90 | D78: 88 | E78: 89 | F78: 84 | O78: 80 | P78: 82 | Q78: 82 | R78: 82 | S78: 77 | T78: 73 | U78: 76 | V78: 75 | W78: 66 | X78: 67 | Y78: 79
B79: Broadband ARPU, Net :
B80: Fixed Line Broadband | O80: 1157 | P80: 1512 | Q80: 1300 | R80: 1315 | S80: 1341 | T80: 1358 | U80: 1352 | V80: 1373 | W80: 1329 | X80: 1372 | Y80: 1381 | Z80: 1398 | AA80: 1461 | AB80: 1480 | AC80: 1490 | AD80: 1359 | AE80: 1403 | AF80: 1445 | AG80: 1465 | AH80: 1444 | AI80: 1441 | AJ80: 1446 | AK80: 1451 | AL80: 1458
B81: Fixed Wireless Broadband | O81: 844 | P81: 851 | Q81: 872 | R81: 860 | S81: 859 | T81: 870 | U81: 849 | V81: 845 | W81: 847 | X81: 644 | Y81: 578 | Z81: 496 | AA81: 415 | AB81: 381 | AC81: 326 | AD81: 280 | AE81: 244 | AF81: 237 | AG81: 225 | AH81: 224 | AI81: 212 | AJ81: 252 | AK81: 370 | AL81: 337
B83: Fibre ARPU | AI83: 1489 | AJ83: 1476 | AK83: 1511 | AL83: 1506 | AM83: 1496 | AN83: 1500 | AO83: 1490 | AP83: 1489 | AQ83: 1493 | AR83: 1470 | AS83: 1446 | AT83: 1405 | AU83: 1347 | AV83: 1324
B85: ARPU
B86: Mobile ARPU, Gross
B87: Postpaid | AE87: 733 | AF87: 732 | AG87: 728 | AH87: 736 | AI87: 716 | AJ87: 726 | AK87: 736
B88: Smart Prepaid | AE88: 116 | AF88: 123 | AG88: 125 | AH88: 128 | AI88: 124 | AJ88: 124 | AK88: 145
B89: TNT | AE89: 94 | AF89: 99 | AG89: 97 | AH89: 98 | AI89: 96 | AJ89: 102 | AK89: 121
B90: Broadband ARPU, Gross
B91: Fixed Line Broadband | AE91: 1403 | AF91: 1445 | AG91: 1466 | AH91: 1444 | AI91: 1441 | AJ91: 1446 | AK91: 1451
B92: Fixed Wireless Broadband | AE92: 266 | AF92: 259 | AG92: 245 | AH92: 244 | AI92: 230 | AJ92: 273 | AK92: 400
