Workbook
Name \A: #REF!
Name \B: #REF!
Name \C: #REF!
Name \L: #REF!
Name \M: #REF!
Name \P: #REF!
Name \Y: #REF!
Name _01_30_04: MonthlyOpStats
Name _01_30_04: MonthlyOpStats
Name _01_30_04: MonthlyOpStats
Name _1_30_01: MonthlyOpStats
Name _1_30_01: MonthlyOpStats
Name _1_30_01: MonthlyOpStats
Name _1_30_02: MonthlyOpStats
Name _1_30_02: MonthlyOpStats
Name _1_30_02: MonthlyOpStats
Name _1_31_01: MonthlyOpStats
Name _1_31_01: MonthlyOpStats
Name _1_31_01: MonthlyOpStats
Name _1_31_02: MonthlyOpStats
Name _1_31_02: MonthlyOpStats
Name _1_31_02: MonthlyOpStats
Name _12_31_05: MonthlyOpStats
Name _12_31_05: MonthlyOpStats
Name _12_31_05: MonthlyOpStats
Name _A: #REF!
Name _A___0: #REF!
Name _B: #REF!
Name _B___0: #REF!
Name _C: #REF!
Name _C___0: #REF!
Name _ent1: [1]Inputs!$J$17
Name _ent10: [1]Inputs!$J$476
Name _ent11: [1]Inputs!$J$527
Name _ent12: [1]Inputs!$J$578
Name _ent13: [1]Inputs!$J$629
Name _ent14: [1]Inputs!$J$680
Name _ent15: [1]Inputs!$J$731
Name _ent2: [1]Inputs!$J$68
Name _ent3: [1]Inputs!$J$119
Name _ent4: [1]Inputs!$J$170
Name _ent5: [1]Inputs!$J$221
Name _ent6: [1]Inputs!$J$272
Name _ent7: [1]Inputs!$J$323
Name _ent8: [1]Inputs!$J$374
Name _ent9: [1]Inputs!$J$425
Name _eps1: [1]Inputs!$P$42
Name _eps10: [1]Inputs!$P$501
Name _eps11: [1]Inputs!$P$552
Name _eps12: [1]Inputs!$P$603
Name _eps13: [1]Inputs!$P$654
Name _eps14: [1]Inputs!$P$705
Name _eps15: [1]Inputs!$P$756
Name _eps2: [1]Inputs!$P$93
Name _eps3: [1]Inputs!$P$144
Name _eps4: [1]Inputs!$P$195
Name _eps5: [1]Inputs!$P$246
Name _eps6: [1]Inputs!$P$297
Name _eps7: [1]Inputs!$P$348
Name _eps8: [1]Inputs!$P$399

Sheet Capitalisation
B2: 1Q26 | I2: Exchange rate as at end | J2: =Model!$M$203 -> 0.2664535
I3: LTM Average Exchange rate | J3: =Model!$M$205 -> 0.26659423
C5: Amount outstanding as on Mar 2026 | D5: SAR (mn) | E5: USD (mn) | F5: Leverage | G5: USD Leverage | I5: Company reported | J5: =D5 -> SAR (mn)
I6: Net debt | J6: 11982
C7: Current Liabilities | D7: =SUM(D8:D13) -> 1555.181 | E7: =SUM(E8:E13) -> 414.38343 | I7: Net debt / EBITDA | J7: 2.48x
C8: Islamic Banking Facilities (Murabaha) | D8: 1058.026 | E8: =D8*$J$2 -> 281.91473
C9: Saudi Industrial Development Fund ("SIDF") | D9: 287.182 | E9: =D9*$J$2 -> 76.52065
C10: Banking Facilities of Non-GCC Subsidiaries | D10: 88.716 | E10: =D10*$J$2 -> 23.638689
C11: Supranational (Murabaha) | D11: 72.858 | E11: =D11*$J$2 -> 19.413269
C12: Agricultural Development Fund ("ADF") | D12: 24.207 | E12: =D12*$J$2 -> 6.45004
C13: International Sukuk | D13: 24.192 | E13: =D13*$J$2 -> 6.4460432
C15: Non-Current Liabilities | D15: =SUM(D16:D21) -> 12021.836 | E15: =SUM(E16:E21) -> 3203.2603
C16: Islamic Banking Facilities (Murabaha) | D16: 7132.026 | E16: =D16*$J$2 -> 1900.3533
C17: Saudi Industrial Development Fund ("SIDF") | D17: 41.169 | E17: =D17*$J$2 -> 10.969624
C18: Banking Facilities of Non-GCC Subsidiaries | D18: 136.616 | E18: =D18*$J$2 -> 36.401812
C19: Supranational (Murabaha) | D19: 23.205 | E19: =D19*$J$2 -> 6.1830536
C20: Agricultural Development Fund ("ADF") | D20: 18.643 | E20: =D20*$J$2 -> 4.9674927
C21: International Sukuk | D21: 4670.177 | E21: =D21*$J$2 -> 1244.385
C23: Bank Overdraft | D23: 24.934 | E23: =D23*$J$2 -> 6.6437517
C25: Leases | D25: =SUM(D26:D27) -> 536.34 | E25: =SUM(E26:E27) -> 142.90967
C26: Current | D26: 95.07 | E26: =D26*$J$2 -> 25.331735
C27: Non-current | D27: 441.27 | E27: =D27*$J$2 -> 117.57794
C29: Total Loans & Borrowings | D29: =SUM(D7,D15,D25,D23) -> 14138.291 | E29: =SUM(E7,E15,E25,E23) -> 3767.1972 | F29: =+D29/D34 -> 2.8615825 | G29: =+E29/E34 -> 2.8600719
C30: Cash & Equivalents | D30: =Model!$AU$109 -> 1620.349 | E30: =D30*$J$2 -> 431.74767
C31: Net debt | D31: =+D29-D30 -> 12517.942 | E31: =+E29-E30 -> 3335.4495 | F31: =+D31/D34 -> 2.5336247 | G31: =+E31/E34 -> 2.5322873
C32: Equity | D32: =Model!$AU$116 -> 21117.81 | E32: =D32*$J$2 -> 5626.9145
C33: Total Capitalisation | D33: =D29+D32 -> 35256.101 | E33: =E29+E32 -> 9394.1116 | F33: =D33/D34 -> 7.1358159 | G33: =E33/E34 -> 7.132049
C34: LTM Adjusted EBITDA | D34: =Model!$AU$82 -> 4940.7246 | E34: =D34*J3 -> 1317.1687
C35: check | D35: =D29-Model!$AU$112 -> 0
C38: Liquidity Table | D38: =D5 -> SAR (mn) | E38: =E5 -> USD (mn)
C39: Cash and cash equivalents | D39: =D30 -> 1620.349 | E39: =D39*$J$2 -> 431.74767
C40: Total Liquidity | D40: =SUM(D39:D39) -> 1620.349 | E40: =SUM(E39:E39) -> 431.74767
C44: Debt Maturity of the debt at end (from PPT) | D44: =D5 -> SAR (mn) | E44: =E5 -> USD (mn)
C46: less than 1 year | D46: 1600 | E46: =D46*J2 -> 426.32561
C47: Between 1-2 years | D47: 2400 | E47: =D47*J2 -> 639.48841
C48: Between 2-3 years | D48: 400 | E48: =D48*J2 -> 106.5814
C49: Between 3-4 years | D49: 0 | E49: =D49*J2 -> 0
C50: Between 4-5 years | D50: 3000 | E50: =D50*J2 -> 799.36051
C51: Over 5 years | D51: 6300 | E51: =D51*J2 -> 1678.6571
C53: Total debt (excluding lease liabilities and bank overdrafts) | D53: =SUM(D45:D52) -> 13700 | E53: =SUM(E45:E52) -> 3650.413
C54: Lease liabilities | D54: =D25 -> 536.34 | E54: =D54*J2 -> 142.90967
C55: Bank overdrafts | D55: =D23 -> 24.934 | E55: =D55*J2 -> 6.6437517
C56: Total debt (including lease liabilities and bank overdrafts) | D56: =+D53+D54+D55 -> 14261.274 | E56: =+E53+E54+E55 -> 3799.9664
B61: FY25 | I61: Exchange rate as at end FY25 | J61: =Model!$M$203 -> 0.2664535
I62: LTM Average Exchange rate of FY25 | J62: =Model!$M$205 -> 0.26659423
C64: Amount outstanding as on Dec 2025 | D64: SAR (mn) | E64: USD (mn) | F64: Leverage | G64: USD Leverage | I64: Company reported | J64: =D64 -> SAR (mn)
I65: Net debt | J65: 11965.994
C66: Current Liabilities | D66: =SUM(D67:D72) -> 1520.33 | E66: =SUM(E67:E72) -> 405.09726 | I66: Net debt / EBITDA | J66: 2.48x
C67: Islamic Banking Facilities (Murabaha) | D67: 1062.084 | E67: =D67*$J$61 -> 282.996
C68: Saudi Industrial Development Fund ("SIDF") | D68: 197.499 | E68: =D68*$J$61 -> 52.624301
C69: Banking Facilities of Non-GCC Subsidiaries | D69: 68.408 | E69: =D69*$J$61 -> 18.227551
C70: Supranational (Murabaha) | D70: 72.137 | E70: =D70*$J$61 -> 19.221156
C71: Agricultural Development Fund ("ADF") | D71: 23.886 | E71: =D71*$J$61 -> 6.3645084
C72: International Sukuk | D72: 96.316 | E72: =D72*$J$61 -> 25.663736
C74: Non-Current Liabilities | D74: =SUM(D75:D80) -> 10951.81 | E74: =SUM(E75:E80) -> 2918.1481
C75: Islamic Banking Facilities (Murabaha) | D75: 5960.307 | E75: =D75*$J$61 -> 1588.1447
C76: Saudi Industrial Development Fund ("SIDF") | D76: 128.143 | E76: =D76*$J$61 -> 34.144151
C77: Banking Facilities of Non-GCC Subsidiaries | D77: 128.588 | E77: =D77*$J$61 -> 34.262723
C78: Supranational (Murabaha) | D78: 47.277 | E78: =D78*$J$61 -> 12.597122
C79: Agricultural Development Fund ("ADF") | D79: 17.987 | E79: =D79*$J$61 -> 4.7926992
C80: International Sukuk | D80: 4669.508 | E80: =D80*$J$61 -> 1244.2068
C82: Bank Overdraft | D82: 16.893 | E82: =D82*$J$61 -> 4.501199
C84: Leases | D84: =SUM(D85:D86) -> 550.226 | E84: =SUM(E85:E86) -> 146.60965
C85: Current | D85: 107.75 | E85: =D85*$J$61 -> 28.710365
C86: Non-current | D86: 442.476 | E86: =D86*$J$61 -> 117.89928
C88: Total Loans & Borrowings | D88: =SUM(D66,D74,D84,D82) -> 13039.259 | E88: =SUM(E66,E74,E84,E82) -> 3474.3562 | F88: =+D88/D93 -> 2.6861406 | G88: =+E88/E93 -> 2.6847226
C89: Cash & Equivalents | D89: =Model!$AT$109 -> 523.039 | E89: =D89*$J$61 -> 139.36557
C90: Net debt | D90: =+D88-D89 -> 12516.22 | E90: =+E88-E89 -> 3334.9907 | F90: =+D90/D93 -> 2.5783924 | G90: =+E90/E93 -> 2.5770313
C91: Equity | D91: =Model!$AT$116 -> 20527.236 | E91: =D91*J61 -> 5469.554
C92: Total Capitalisation | D92: =D88+D91 -> 33566.495 | E92: =E88+E91 -> 8943.9102 | F92: =D92/D93 -> 6.914835 | G92: =E92/E93 -> 6.9111848
C93: LTM Adjusted EBITDA | D93: =Model!$AT$82 -> 4854.2727 | E93: =D93*J62 -> 1294.1211
C95: check | D95: =D88-Model!$AT$112 -> 0
C97: Liquidity Table at FY25 | D97: =D64 -> SAR (mn) | E97: =E64 -> USD (mn)
C98: Cash and cash equivalents | D98: =D89 -> 523.039 | E98: =E89 -> 139.36557
C99: Total Liquidity | D99: =SUM(D98:D98) -> 523.039 | E99: =SUM(E98:E98) -> 139.36557
C102: Debt Maturity of "Loans and Borrowings" at end-FY25 (from FS) undiscounted and include estimated interest | D102: =D97 -> SAR (mn) | E102: =E97 -> USD (mn)
C103: On Demand or Less than 1 year | D103: 2076.587 | E103: =D103*$J$61 -> 553.31388
C104: 1 year to 5 years | D104: 7855.883 | E104: =D104*$J$61 -> 2093.2276
C105: More than 5 years | D105: 5349.224 | E105: =D105*$J$61 -> 1425.3195
C106: Total debt (excluding lease liabilities and bank overdrafts) | D106: =SUM(D103:D105) -> 15281.694 | E106: =SUM(E103:E105) -> 4071.8609
C109: Debt Maturity of "Leases" at end-FY25 (from FS) undiscounted and include estimated interest | D109: =D102 -> SAR (mn) | E109: =E102 -> USD (mn)
C110: On Demand or Less than 1 year | D110: 101.238 | E110: =D110*$J$61 -> 26.97522
C111: 1 year to 5 years | D111: 222.512 | E111: =D111*$J$61 -> 59.289102
C112: More than 5 years | D112: 430.92 | E112: =D112*$J$61 -> 114.82014
C113: Total debt (excluding lease liabilities and bank overdrafts) | D113: =SUM(D110:D112) -> 754.67 | E113: =SUM(E110:E112) -> 201.08447
C116: Debt Maturity of the debt at end-FY25 (from PPT) | D116: =D64 -> SAR (mn) | E116: =E64 -> USD (mn)
C118: less than 1 year | D118: 1500 | E118: =D118*J61 -> 399.68026
C119: Between 1-2 years | D119: 2600 | E119: =D119*J61 -> 692.77911
C120: Between 2-3 years | D120: 500 | E120: =D120*J61 -> 133.22675
C121: Between 3-4 years | D121: 100 | E121: =D121*J61 -> 26.64535
C122: Between 4-5 years | D122: 3000 | E122: =D122*J61 -> 799.36051
C123: Over 5 years | D123: 4900 | E123: =D123*J61 -> 1305.6222
C125: Total debt (excluding lease liabilities and bank overdrafts) | D125: =SUM(D117:D124) -> 12600 | E125: =SUM(E117:E124) -> 3357.3141
C126: Lease liabilities | D126: =D84 -> 550.226 | E126: =D126*J61 -> 146.60965
C127: Bank overdrafts | D127: =D82 -> 16.893 | E127: =D127*J61 -> 4.501199
C128: Total debt (including lease liabilities and bank overdrafts) | D128: =+D125+D126+D127 -> 13167.119 | E128: =+E125+E126+E127 -> 3508.425
B134: 3Q25 | I134: Exchange rate as at end 3Q25 | J134: =Model!$M$203 -> 0.2664535
I135: LTM Average Exchange rate of 3Q25 | J135: =Model!$M$205 -> 0.26659423
C137: Amount outstanding as on Sep 2025 | D137: SAR (mn) | E137: USD (mn) | F137: Leverage | G137: USD Leverage | I137: Company reported | J137: =D137 -> SAR (mn)
I138: Net debt | J138: 11971
...

Sheet Model
B2: ALMARAI | C2: Annual | D2: Annual | E2: Annual | F2: Annual | G2: Annual | H2: Annual | I2: Annual | J2: Annual | K2: Annual | L2: Annual | M2: LTM | O2: Quarterly | P2: Quarterly | Q2: Quarterly | R2: Quarterly | S2: Quarterly | T2: Quarterly | U2: Quarterly | V2: Quarterly | W2: Quarterly | X2: Quarterly | Y2: Quarterly | Z2: Quarterly | AA2: Quarterly | AB2: Quarterly | AC2: Quarterly | AD2: Quarterly | AE2: Quarterly | AF2: Quarterly | AG2: Quarterly | AH2: QuarterIy | AI2: Quarterly | AJ2: Quarterly | AK2: Quarterly | AL2: QuarterIy | AM2: Quarterly | AN2: Quarterly | AO2: Quarterly | AP2: QuarterIy | AQ2: Quarterly | AR2: Quarterly | AS2: Quarterly | AT2: QuarterIy | AU2: Quarterly | AW2: Quarterly | AX2: Quarterly
B3: (SAR millions) | C3: 42735 | D3: 43100 | E3: 43465 | F3: 43830 | G3: 44196 | H3: 44561 | I3: 44926 | J3: 45291 | K3: 45657 | L3: 46022 | M3: =AU3 -> 46111 | O3: 43189 | P3: 43281 | Q3: 43373 | R3: 43464 | S3: 43554 | T3: 43646 | U3: 43738 | V3: 43829 | W3: 43920 | X3: 44012 | Y3: 44104 | Z3: 44195 | AA3: 44285 | AB3: 44377 | AC3: 44469 | AD3: 44560 | AE3: 44650 | AF3: 44742 | AG3: 44834 | AH3: 44926 | AI3: 45015 | AJ3: 45107 | AK3: 45199 | AL3: 45291 | AM3: 45381 | AN3: 45473 | AO3: 45565 | AP3: 45657 | AQ3: 45746 | AR3: 45838 | AS3: 45930 | AT3: 46022 | AU3: 46111 | AW3: 43554 | AX3: 43646
C4: Act | D4: Act | E4: Act | F4: Act | G4: Act | H4: Act | I4: Act | J4: Act | K4: Act | L4: Act | M4: Act | O4: Act | P4: Act | Q4: Act | R4: Act | S4: Act | T4: Act | U4: Act | V4: Act | W4: Act | X4: Act | Y4: Act | Z4: Act | AA4: Act | AB4: Act | AC4: Act | AD4: Act | AE4: Act | AF4: Act | AG4: Act | AH4: Act | AI4: Act | AJ4: Act | AK4: Act | AL4: Act | AM4: Act | AN4: Act | AO4: Act | AP4: Act | AQ4: Act | AR4: Act | AS4: Act | AT4: Act | AU4: Act | AW4: Restated | AX4: Restated
C5: FY | D5: FY | E5: FY | F5: FY | G5: FY | H5: FY | I5: FY | J5: FY | K5: FY | L5: FY | M5: LTM | O5: Q1 | P5: Q2 | Q5: Q3 | R5: Q4 | S5: Q1 | T5: Q2 | U5: Q3 | V5: Q4 | W5: Q1 | X5: Q2 | Y5: Q3 | Z5: Q4 | AA5: Q1 | AB5: Q2 | AC5: Q3 | AD5: Q4 | AE5: Q1 | AF5: Q2 | AG5: Q3 | AH5: Q4 | AI5: Q1 | AJ5: Q2 | AK5: Q3 | AL5: Q4 | AM5: Q1 | AN5: Q2 | AO5: Q3 | AP5: Q4 | AQ5: Q1 | AR5: Q2 | AS5: Q3 | AT5: Q4 | AU5: Q1 | AW5: Q1 | AX5: Q2
B6: INCOME STATEMENT
B7: Revenue | C7: 14338.579 | D7: 13935.532 | E7: 13557.837 | F7: 14351.277 | G7: 15356.948 | H7: 15849.72 | I7: 18722.258 | J7: 19575.585 | K7: 20979.512 | L7: 22064.876 | M7: =SUM(AR7:AU7) -> 22457.839 | O7: 3232.205 | P7: =6859.293-O7 -> 3627.088 | Q7: =10176.653-P7-O7 -> 3317.36 | R7: =E7-Q7-P7-O7 -> 3381.184 | S7: 3354.083 | T7: =7074.082-S7 -> 3719.999 | U7: =10647.339-T7-S7 -> 3573.257 | V7: =F7-U7-T7-S7 -> 3703.938 | W7: 3592.44 | X7: 4081.844 | Y7: 3863.079 | Z7: =G7-Y7-X7-W7 -> 3819.585 | AA7: 3645.014 | AB7: 4005.568 | AC7: 3941.73 | AD7: =H7-AC7-AB7-AA7 -> 4257.408 | AE7: 4503.457 | AF7: 4610.447 | AG7: 4769.121 | AH7: =I7-AG7-AF7-AE7 -> 4839.233 | AI7: 5066.564 | AJ7: 4792.349 | AK7: 4796.934 | AL7: =J7-AK7-AJ7-AI7 -> 4919.738 | AM7: 5458.641 | AN7: 5154.621 | AO7: 5208.921 | AP7: =K7-AO7-AN7-AM7 -> 5157.329 | AQ7: 5767.09 | AR7: 5288.402 | AS7: 5552.599 | AT7: =L7-AS7-AR7-AQ7 -> 5456.785 | AU7: 6160.053 | AW7: 3308.892 | AX7: 3767.424
B8: % y-o-y growth | D8: =D7/C7-1 -> -0.028109271 | E8: =E7/D7-1 -> -0.02710302 | F8: =F7/E7-1 -> 0.058522609 | G8: =G7/F7-1 -> 0.070075367 | H8: =H7/G7-1 -> 0.032087886 | I8: =I7/H7-1 -> 0.18123588 | J8: =J7/I7-1 -> 0.04557821 | K8: =K7/J7-1 -> 0.071718265 | L8: =L7/K7-1 -> 0.051734473 | S8: =S7/O7-1 -> 0.037707386 | T8: =T7/P7-1 -> 0.025615866 | U8: =U7/Q7-1 -> 0.077138749 | V8: =V7/R7-1 -> 0.095455911 | W8: =W7/AW7-1 -> 0.085692733 | X8: =X7/AX7-1 -> 0.083457556 | Y8: =Y7/U7-1 -> 0.081108636 | Z8: =Z7/V7-1 -> 0.031222715 | AA8: =AA7/W7-1 -> 0.014634622 | AB8: =AB7/X7-1 -> -0.018686652 | AC8: =AC7/Y7-1 -> 0.020359666 | AD8: =AD7/Z7-1 -> 0.1146258 | AE8: =AE7/AA7-1 -> 0.23551158 | AF8: =AF7/AB7-1 -> 0.15100954 | ... AU8: =AU7/AQ7-1 -> 0.068138871 | AW8: =AW7/O7-1 -> 0.023725908 | AX8: =AX7/W7-1 -> 0.048708955
B9: Cost of Sales | C9: -8816.092 | D9: -8351.893 | E9: -8230.763 | F9: -8984.603 | G9: -9821.44 | H9: -10790.45 | I9: -13098.035 | J9: -13524.295 | K9: -14315.46 | L9: -15177.063 | M9: =SUM(AR9:AU9) -> -15472.772 | O9: -1977.776 | P9: =-4201.65-O9 -> -2223.874 | Q9: =-6112.52-P9-O9 -> -1910.87 | R9: =E9-Q9-P9-O9 -> -2118.243 | S9: -2144.464 | T9: =-4444.682-S9 -> -2300.218 | U9: =-6574.174-T9-S9 -> -2129.492 | V9: =F9-U9-T9-S9 -> -2410.429 | W9: -2339.247 | X9: -2546.659 | Y9: -2348.379 | Z9: =G9-Y9-X9-W9 -> -2587.155 | AA9: -2409.909 | AB9: -2649.829 | AC9: -2666.017 | AD9: =H9-AC9-AB9-AA9 -> -3064.695 | AE9: -3171.541 | AF9: -3140.841 | AG9: -3280.406 | AH9: =I9-AG9-AF9-AE9 -> -3505.247 | AI9: -3448.713 | AJ9: -3225.27 | AK9: -3327.482 | AL9: =J9-AK9-AJ9-AI9 -> -3522.83 | AM9: -3750.18 | AN9: -3452.286 | AO9: -3539.024 | AP9: =K9-AO9-AN9-AM9 -> -3573.97 | AQ9: -3998.435 | AR9: -3575.223 | AS9: -3805.242 | AT9: =L9-AS9-AR9-AQ9 -> -3798.163 | AU9: -4294.144 | AW9: -2144.986 | AX9: -2301.203
B10: Gross Profit | C10: =C7+C9 -> 5522.487 | D10: =D7+D9 -> 5583.639 | E10: =E7+E9 -> 5327.074 | F10: =F7+F9 -> 5366.674 | G10: =G7+G9 -> 5535.508 | H10: =H7+H9 -> 5059.27 | I10: =I7+I9 -> 5624.223 | J10: =J7+J9 -> 6051.29 | ... M10: =M7+M9 -> 6985.067 | O10: =O7+O9 -> 1254.429 | P10: =P7+P9 -> 1403.214 | Q10: =Q7+Q9 -> 1406.49 | R10: =R7+R9 -> 1262.941 | S10: =S7+S9 -> 1209.619 | T10: =T7+T9 -> 1419.781 | U10: =U7+U9 -> 1443.765 | V10: =V7+V9 -> 1293.509 | ... AU10: =AU7+AU9 -> 1865.909 | AW10: =AW7+AW9 -> 1163.906 | AX10: =AX7+AX9 -> 1466.221
B11: Gross Profit margin | C11: =C10/C7 -> 0.38514884 | D11: =D10/D7 -> 0.40067641 | E11: =E10/E7 -> 0.39291474 | F11: =F10/F7 -> 0.37395097 | G11: =G10/G7 -> 0.36045626 | H11: =H10/H7 -> 0.31920248 | I11: =I10/I7 -> 0.30040303 | J11: =J10/J7 -> 0.30912435 | ... M11: =M10/M7 -> 0.31103024 | O11: =O10/O7 -> 0.38810317 | P11: =P10/P7 -> 0.38687068 | Q11: =Q10/Q7 -> 0.42397871 | R11: =R10/R7 -> 0.37352034 | S11: =S10/S7 -> 0.36064075 | T11: =T10/T7 -> 0.38166166 | U11: =U10/U7 -> 0.40404734 | V11: =V10/V7 -> 0.34922534 | ... AU11: =AU10/AU7 -> 0.3029047 | AW11: =AW10/AW7 -> 0.35175098 | AX11: =AX10/AX7 -> 0.38918396
B12: Selling and Distribution Expenses | C12: -2480.361 | D12: -2343.046 | E12: -2180.244 | F12: -2376.328 | G12: -2490.479 | H12: -2518.851 | I12: -2709.538 | J12: -2789.745 | K12: -2993.918 | L12: -3231.061 | M12: =SUM(AR12:AU12) -> -3295.359 | O12: -595.196 | P12: =-1107.697-O12 -> -512.501 | Q12: =-1647.242-P12-O12 -> -539.545 | R12: =E12-Q12-P12-O12 -> -533.002 | S12: -609.729 | T12: =-1148.217-S12 -> -538.488 | U12: =-1742.32-T12-S12 -> -594.103 | V12: =F12-U12-T12-S12 -> -634.008 | W12: -611.569 | X12: -632.958 | Y12: -642.003 | Z12: =G12-Y12-X12-W12 -> -603.949 | AA12: -604.052 | AB12: -634.826 | AC12: -646.441 | AD12: =H12-AC12-AB12-AA12 -> -633.532 | AE12: -647.428 | AF12: -666.308 | AG12: -709.792 | AH12: =I12-AG12-AF12-AE12 -> -686.01 | AI12: -678.841 | AJ12: -689.08 | AK12: -725.211 | AL12: =J12-AK12-AJ12-AI12 -> -696.613 | AM12: -695.754 | AN12: -726.777 | AO12: -778.439 | AP12: =K12-AO12-AN12-AM12 -> -792.948 | AQ12: -754.094 | AR12: -766.224 | AS12: -835.842 | AT12: =L12-AS12-AR12-AQ12 -> -874.901 | AU12: -818.392 | AW12: -564.538 | AX12: -585.913
B13: General and Administration Expenses | C13: -432.949 | D13: -397.339 | E13: -375.204 | F13: -400.273 | G13: -419.79 | H13: -428.157 | I13: -458.694 | J13: -469.023 | K13: -508.149 | L13: -561.463 | M13: =SUM(AR13:AU13) -> -570.157 | O13: -96.127 | P13: =-195.1-O13 -> -98.973 | Q13: =-274.326-P13-O13 -> -79.226 | R13: =E13-Q13-P13-O13 -> -100.878 | S13: -94.754 | T13: =-194.58-S13 -> -99.826 | U13: =-274.095-T13-S13 -> -79.515 | V13: =F13-U13-T13-S13 -> -126.178 | W13: -99.828 | X13: -105.109 | Y13: -83.956 | Z13: =G13-Y13-X13-W13 -> -130.897 | AA13: -97.308 | AB13: -104.96 | AC13: -85.095 | AD13: =H13-AC13-AB13-AA13 -> -140.794 | AE13: -104.787 | AF13: -110.733 | AG13: -95.831 | AH13: =I13-AG13-AF13-AE13 -> -147.343 | AI13: -113.199 | AJ13: -117.414 | AK13: -95.626 | AL13: =J13-AK13-AJ13-AI13 -> -142.784 | AM13: -121.607 | AN13: -124.305 | AO13: -103.052 | AP13: =K13-AO13-AN13-AM13 -> -159.185 | AQ13: -129.293 | AR13: -130.036 | AS13: -121.737 | AT13: =L13-AS13-AR13-AQ13 -> -180.397 | AU13: -137.987 | AW13: -94.754 | AX13: -99.826
B14: Other Expenses, net | C14: -91.398 | D14: -211.071 | E14: -275.075 | F14: -88.672 | G14: -78.428 | H14: -85.563 | I14: -153.356 | J14: -64.461 | K14: -63.166 | L14: -14.813 | M14: =SUM(AR14:AU14) -> -29.649 | O14: -44.446 | P14: =-78.251-O14 -> -33.805 | Q14: =-116.079-P14-O14 -> -37.828 | R14: =E14-Q14-P14-O14 -> -158.996 | S14: -22.437 | T14: =-67.604-S14 -> -45.167 | U14: =-81.511-T14-S14 -> -13.907 | V14: =F14-U14-T14-S14 -> -7.161 | W14: -0.491 | X14: -31.172 | Y14: -39.514 | Z14: =G14-Y14-X14-W14 -> -7.251 | AA14: -31.217 | AB14: -19.902 | AC14: -19.247 | AD14: =H14-AC14-AB14-AA14 -> -15.197 | AE14: -22.43 | AF14: -33.699 | AG14: -100.073 | AH14: =I14-AG14-AF14-AE14 -> 2.846 | AI14: -13.312 | AJ14: -38.782 | AK14: -2.779 | AL14: =J14-AK14-AJ14-AI14 -> -9.588 | AM14: -0.518 | AN14: -39.824 | AO14: -29.638 | AP14: =K14-AO14-AN14-AM14 -> 6.814 | AQ14: -11.373 | AR14: 11.991 | AS14: -30.428 | AT14: =L14-AS14-AR14-AQ14 -> 14.997 | AU14: -26.209 | AW14: -16.422 | AX14: -40.221
B15: Impairment (Loss) / Reversal on Financial Assets | C15: 0 | D15: -48.833 | E15: 24.684 | F15: -28.193 | G15: -24.477 | H15: -11.845 | I15: -26.303 | J15: -34.173 | K15: -103.458 | L15: -20.214 | M15: =SUM(AR15:AU15) -> -28.647 | O15: -33.45 | P15: =-27.245-O15 -> 6.205 | Q15: =-3.106-P15-O15 -> 24.139 | R15: =E15-Q15-P15-O15 -> 27.79 | S15: -1.882 | T15: =0.365-S15 -> 2.247 | U15: =-0.296-T15-S15 -> -0.661 | V15: =F15-U15-T15-S15 -> -27.897 | W15: -28.54 | X15: -6.721 | Y15: 0.96 | Z15: =G15-Y15-X15-W15 -> 9.824 | AA15: -0.176 | AB15: 5.595 | AC15: -6.29 | AD15: =H15-AC15-AB15-AA15 -> -10.974 | AE15: -10.165 | AF15: -12.567 | AG15: -4.115 | AH15: =I15-AG15-AF15-AE15 -> 0.544 | AI15: -9.956 | AJ15: -3.288 | AK15: -1.901 | AL15: =J15-AK15-AJ15-AI15 -> -19.028 | AM15: -21.716 | AN15: -18.475 | AO15: -16.354 | AP15: =K15-AO15-AN15-AM15 -> -46.913 | AQ15: 0.241 | AR15: -15.667 | AS15: -2.077 | AT15: =L15-AS15-AR15-AQ15 -> -2.711 | AU15: -8.192 | AW15: -1.882 | AX15: 2.247
B16: Operating Profit | C16: =C10+SUM(C12:C15) -> 2517.779 | D16: =D10+SUM(D12:D15) -> 2583.35 | E16: =E10+SUM(E12:E15) -> 2521.235 | F16: =F10+SUM(F12:F15) -> 2473.208 | G16: =G10+SUM(G12:G15) -> 2522.334 | H16: =H10+SUM(H12:H15) -> 2014.854 | I16: =I10+SUM(I12:I15) -> 2276.332 | J16: =J10+SUM(J12:J15) -> 2693.888 | ... M16: =M10+SUM(M12:M15) -> 3061.255 | O16: =O10+SUM(O12:O15) -> 485.21 | P16: =P10+SUM(P12:P15) -> 764.14 | Q16: =Q10+SUM(Q12:Q15) -> 774.03 | R16: =R10+SUM(R12:R15) -> 497.855 | S16: =S10+SUM(S12:S15) -> 480.817 | T16: =T10+SUM(T12:T15) -> 738.547 | U16: =U10+SUM(U12:U15) -> 755.579 | V16: =V10+SUM(V12:V15) -> 498.265 | ... AU16: =AU10+SUM(AU12:AU15) -> 875.129 | AW16: =AW10+SUM(AW12:AW15) -> 486.31 | AX16: =AX10+SUM(AX12:AX15) -> 742.508
B17: Exchange Gain, net | C17: 44.676 | D17: 7.094 | E17: 0 | F17: 0 | G17: 0 | H17: 0 | I17: 0 | J17: 0 | K17: 0 | L17: 0 | M17: =SUM(AR17:AU17) -> 0 | O17: -19.144 | P17: =7.024-O17 -> 26.168 | Q17: =-P17-O17 -> -7.024 | R17: =E17-Q17-P17-O17 -> 0 | S17: 9.355 | T17: =10.196-S17 -> 0.841 | U17: =-T17-S17 -> -10.196 | V17: =F17-U17-T17-S17 -> 0 | W17: 0 | X17: 0 | Y17: 0 | Z17: =G17-Y17-X17-W17 -> 0 | AA17: 0 | AB17: 0 | AC17: 0 | AD17: =H17-AC17-AB17-AA17 -> 0 | AE17: 0 | AF17: 0 | AG17: 0 | AH17: =I17-AG17-AF17-AE17 -> 0 | AI17: 0 | AJ17: 0 | AK17: 0 | AL17: =J17-AK17-AJ17-AI17 -> 0 | AM17: 0 | AN17: 0 | AO17: 0 | AP17: =K17-AO17-AN17-AM17 -> 0 | AQ17: 0 | AR17: 0 | AS17: 0 | AT17: =L17-AS17-AR17-AQ17 -> 0 | AU17: 0 | AW17: 0 | AX17: 0
B18: Financial Cost, net | C18: -351.336 | D18: -401.254 | E18: -436.766 | F18: -550.739 | G18: -495.881 | H18: -346.063 | I18: -428.119 | J18: -527.019 | K18: -530.26 | L18: -463.346 | M18: =SUM(AR18:AU18) -> -469.195 | O18: -102.271 | P18: =-197.209-O18 -> -94.938 | Q18: =-307.671-P18-O18 -> -110.462 | R18: =E18-Q18-P18-O18 -> -129.095 | S18: -130.281 | T18: =-266.425-S18 -> -136.144 | U18: =-396.887-T18-S18 -> -130.462 | V18: =F18-U18-T18-S18 -> -153.852 | W18: -124.875 | X18: -120.302 | Y18: -117.764 | Z18: =G18-Y18-X18-W18 -> -132.94 | AA18: -88.794 | AB18: -93.319 | AC18: -84.617 | AD18: =H18-AC18-AB18-AA18 -> -79.333 | AE18: -89.54 | AF18: -96.624 | AG18: -111.035 | AH18: =I18-AG18-AF18-AE18 -> -130.92 | AI18: -120.488 | AJ18: -136.379 | AK18: -128.527 | AL18: =J18-AK18-AJ18-AI18 -> -141.625 | AM18: -141.575 | AN18: -142.658 | AO18: -128.326 | AP18: =K18-AO18-AN18-AM18 -> -117.701 | AQ18: -99.691 | AR18: -124.962 | AS18: -118.633 | AT18: =L18-AS18-AR18-AQ18 -> -120.06 | AU18: -105.54 | AW18: -126.419 | AX18: -139.264
B19: Share of Results of Associates | C19: 13.323 | D19: 13.018 | E19: -5.413 | F19: 0 | G19: 1.405 | H19: -0.941 | I19: 0.716 | J19: -1.064 | K19: -1.774 | L19: -1.222 | M19: =SUM(AR19:AU19) -> -0.323 | O19: -3.43 | P19: =-7.456-O19 -> -4.026 | Q19: =-6.338-P19-O19 -> 1.118 | R19: =E19-Q19-P19-O19 -> 0.925 | S19: 0 | T19: =-S19 -> 0 | U19: =-T19-S19 -> 0 | V19: =F19-U19-T19-S19 -> 0 | W19: -1.598 | X19: 2.234 | Y19: 0.907 | Z19: =G19-Y19-X19-W19 -> -0.138 | AA19: -1.304 | AB19: -0.181 | AC19: -0.543 | AD19: =H19-AC19-AB19-AA19 -> 1.087 | AE19: -1.028 | AF19: 0.65 | AG19: 0.189 | AH19: =I19-AG19-AF19-AE19 -> 0.905 | AI19: -1.031 | AJ19: 0.097 | AK19: 1.358 | AL19: =J19-AK19-AJ19-AI19 -> -1.488 | AM19: -0.948 | AN19: -0.112 | AO19: -0.238 | AP19: =K19-AO19-AN19-AM19 -> -0.476 | AQ19: -0.899 | AR19: -0.323 | AS19: 0 | AT19: =L19-AS19-AR19-AQ19 -> 0 | AU19: 0 | AW19: 0 | AX19: 0
B20: Profit before Zakat and Income Tax | C20: =+C16+C18+C19+C17 -> 2224.442 | D20: =+D16+D18+D19+D17 -> 2202.208 | E20: =+E16+E18+E19+E17 -> 2079.056 | F20: =+F16+F18+F19+F17 -> 1922.469 | G20: =+G16+G18+G19+G17 -> 2027.858 | H20: =+H16+H18+H19+H17 -> 1667.85 | I20: =+I16+I18+I19+I17 -> 1848.929 | J20: =+J16+J18+J19+J17 -> 2165.805 | ... M20: =+M16+M18+M19+M17 -> 2591.737 | O20: =+O16+O18+O19+O17 -> 360.365 | P20: =+P16+P18+P19+P17 -> 691.344 | Q20: =+Q16+Q18+Q19+Q17 -> 657.662 | R20: =+R16+R18+R19+R17 -> 369.685 | S20: =+S16+S18+S19+S17 -> 359.891 | T20: =+T16+T18+T19+T17 -> 603.244 | U20: =+U16+U18+U19+U17 -> 614.921 | V20: =+V16+V18+V19+V17 -> 344.413 | ... AU20: =+AU16+AU18+AU19+AU17 -> 769.589 | AW20: =+AW16+AW18+AW19+AW17 -> 359.891 | AX20: =+AX16+AX18+AX19+AX17 -> 603.244
B21: Zakat and Income Tax | C21: -74.345 | D21: -42.245 | E21: =-49.352-21.146 -> -70.498 | F21: =-71.426-49.471 -> -120.897 | G21: =-72.042-20.26 -> -92.302 | H21: =-77.08-11.334 -> -88.414 | I21: =-62.6-8.191 -> -70.791 | J21: =-85.101-29.175 -> -114.276 | K21: =-105.326-44.334 -> -149.66 | L21: =-86.831-52.19 -> -139.021 | M21: =SUM(AR21:AU21) -> -134.153 | O21: -19.964 | P21: =-32.945-15.173-O21 -> -28.154 | Q21: =-49.312-15.223-P21-O21 -> -16.417 | R21: =E21-Q21-P21-O21 -> -5.963 | S21: -22.943 | T21: =-35.523-6.809-S21 -> -19.389 | U21: =-46.814-17.717-T21-S21 -> -22.199 | V21: =F21-U21-T21-S21 -> -56.366 | W21: =-12.985-5.913 -> -18.898 | X21: =-15.514-5.705 -> -21.219 | Y21: =-11.693-6.499 -> -18.192 | Z21: =G21-Y21-X21-W21 -> -33.993 | AA21: =-11.953-11.62 -> -23.573 | AB21: =-16.375-1.743 -> -18.118 | AC21: =-11.033-11.599 -> -22.632 | AD21: =H21-AC21-AB21-AA21 -> -24.091 | AE21: =-22.526-11.479 -> -34.005 | AF21: =-22.167-2.064 -> -24.231 | AG21: =12.636-5.8 -> 6.836 | AH21: =I21-AG21-AF21-AE21 -> -19.391 | AI21: =-26.975-18.093 -> -45.068 | AJ21: =-23.106-2.059 -> -25.165 | AK21: =-15.519-14.48 -> -29.999 | AL21: =J21-AK21-AJ21-AI21 -> -14.044 | AM21: =-24.869-8.093 -> -32.962 | AN21: =-22.949-6.125 -> -29.074 | AO21: =-22.909-22.115 -> -45.024 | AP21: =K21-AO21-AN21-AM21 -> -42.6 | AQ21: =-27.464-14.555 -> -42.019 | AR21: =-27.981-12.867 -> -40.848 | AS21: =(-20460-4664)/1000 -> -25.124 | AT21: =L21-AS21-AR21-AQ21 -> -31.03 | AU21: =-26.573-10.578 -> -37.151 | AW21: =-15.334-7.609 -> -22.943 | AX21: =-20.189+0.8 -> -19.389
B22: Profit for the year | C22: =C20+C21 -> 2150.097 | D22: =D20+D21 -> 2159.963 | E22: =E20+E21 -> 2008.558 | F22: =F20+F21 -> 1801.572 | G22: =G20+G21 -> 1935.556 | H22: =H20+H21 -> 1579.436 | I22: =I20+I21 -> 1778.138 | J22: =J20+J21 -> 2051.529 | ... M22: =M20+M21 -> 2457.584 | O22: =O20+O21 -> 340.401 | P22: =P20+P21 -> 663.19 | Q22: =Q20+Q21 -> 641.245 | R22: =R20+R21 -> 363.722 | S22: =S20+S21 -> 336.948 | T22: =T20+T21 -> 583.855 | U22: =U20+U21 -> 592.722 | V22: =V20+V21 -> 288.047 | ... AU22: =AU20+AU21 -> 732.438 | AW22: =AW20+AW21 -> 336.948 | AX22: =AX20+AX21 -> 583.855
B24: Profit (loss) attributable to non-controlling interests | C24: 2.311 | D24: -22.323 | E24: -3.417 | F24: -10.181 | G24: -48.805 | H24: 15.893 | I24: 18.326 | J24: 2.406 | K24: 0.567 | L24: 0.58 | M24: =SUM(AR24:AU24) -> 0.463 | O24: -4.466 | P24: =-2.663-O24 -> 1.803 | Q24: =3.627-P24-O24 -> 6.29 | R24: =E24-Q24-P24-O24 -> -7.044 | S24: 0.92 | T24: =2.244-S24 -> 1.324 | U24: 11.475 | V24: =F24-U24-T24-S24 -> -23.9 | W24: -15.611 | X24: -23.994 | Y24: -6.382 | Z24: =G24-Y24-X24-W24 -> -2.818 | AA24: 2.735 | AB24: 8.049 | AC24: 1.761 | AD24: =H24-AC24-AB24-AA24 -> 3.348 | AE24: 2.076 | AF24: 5.734 | AG24: 11.722 | AH24: =I24-AG24-AF24-AE24 -> -1.206 | AI24: 0.899 | AJ24: -0.016 | AK24: 0.504 | AL24: =J24-AK24-AJ24-AI24 -> 1.019 | AM24: 1.154 | AN24: 1.417 | AO24: -1.628 | AP24: =K24-AO24-AN24-AM24 -> -0.376 | AQ24: 0.333 | AR24: 0.244 | AS24: 0.277 | AT24: =L24-AS24-AR24-AQ24 -> -0.274 | AU24: 0.216 | AW24: 0.92 | AX24: 1.324
B25: Profit (loss) attributable to shareholders | C25: 2147.786 | D25: 2182.286 | E25: 2011.975 | F25: 1811.753 | G25: 1984.361 | H25: 1563.543 | I25: 1759.812 | J25: 2049.123 | K25: 2313.1 | L25: 2456.093 | M25: =SUM(AR25:AU25) -> 2457.121 | O25: 344.867 | P25: =1006.254-O25 -> 661.387 | Q25: =1641.209-P25-O25 -> 634.955 | R25: =E25-Q25-P25-O25 -> 370.766 | S25: 336.028 | T25: =918.559-S25 -> 582.531 | U25: 581.246 | V25: =F25-U25-T25-S25 -> 311.948 | W25: 383.005 | X25: 643.932 | Y25: 621.52 | Z25: =G25-Y25-X25-W25 -> 335.904 | AA25: 385.946 | AB25: 481.979 | AC25: 409.087 | AD25: =H25-AC25-AB25-AA25 -> 286.531 | AE25: 420.457 | AF25: 520.36 | AG25: 463.172 | AH25: =I25-AG25-AF25-AE25 -> 355.823 | AI25: 635.057 | AJ25: 557.084 | AK25: 486.263 | AL25: =J25-AK25-AJ25-AI25 -> 370.719 | AM25: 692.227 | AN25: 619.693 | AO25: 570.454 | AP25: =K25-AO25-AN25-AM25 -> 430.726 | AQ25: 731.194 | AR25: 646.866 | AS25: 613.239 | AT25: =L25-AS25-AR25-AQ25 -> 464.794 | AU25: 732.222 | AW25: 336.028 | AX25: 582.531
B27: check | C27: =C22-C24-C25 -> 0 | D27: =D22-D24-D25 -> 0 | E27: =E22-E24-E25 -> 0 | F27: =F22-F24-F25 -> 0 | G27: =G22-G24-G25 -> 0 | H27: =H22-H24-H25 -> 0 | I27: =I22-I24-I25 -> 2.0463631e-12 | J27: =J22-J24-J25 -> 0 | ... M27: =M22-M24-M25 -> 0 | O27: =O22-O24-O25 -> 0 | P27: =P22-P24-P25 -> 0 | Q27: =Q22-Q24-Q25 -> 0 | R27: =R22-R24-R25 -> -1.3073986e-12 | S27: =S22-S24-S25 -> 0 | T27: =T22-T24-T25 -> 0 | U27: =U22-U24-U25 -> 0.001 | V27: =V22-V24-V25 -> -0.001 | ... AU27: =AU22-AU24-AU25 -> 0 | AW27: =AW22-AW24-AW25 -> 0 | AX27: =AX22-AX24-AX25 -> 0
B29: As % of Net sales or stated otherwise
B30: =B9 -> Cost of Sales | C30: =-C9/C7 -> 0.61485116 | D30: =-D9/D7 -> 0.59932359 | E30: =-E9/E7 -> 0.60708526 | F30: =-F9/F7 -> 0.62604903 | G30: =-G9/G7 -> 0.63954374 | H30: =-H9/H7 -> 0.68079752 | I30: =-I9/I7 -> 0.69959697 | J30: =-J9/J7 -> 0.69087565 | ... M30: =-M9/M7 -> 0.68896976 | O30: =-O9/O7 -> 0.61189683 | P30: =-P9/P7 -> 0.61312932 | Q30: =-Q9/Q7 -> 0.57602129 | R30: =-R9/R7 -> 0.62647966 | S30: =-S9/S7 -> 0.63935925 | T30: =-T9/T7 -> 0.61833834 | U30: =-U9/U7 -> 0.59595266 | V30: =-V9/V7 -> 0.65077466 | ... AU30: =-AU9/AU7 -> 0.6970953 | AW30: =-AW9/AW7 -> 0.64824902 | AX30: =-AX9/AX7 -> 0.61081604
B31: =B12 -> Selling and Distribution Expenses | C31: =-C12/C7 -> 0.17298513 | D31: =-D12/D7 -> 0.16813466 | E31: =-E12/E7 -> 0.16081061 | F31: =-F12/F7 -> 0.16558303 | G31: =-G12/G7 -> 0.16217278 | H31: =-H12/H7 -> 0.15892085 | I31: =-I12/I7 -> 0.14472282 | J31: =-J12/J7 -> 0.14251145 | ... M31: =-M12/M7 -> 0.14673536 | O31: =-O12/O7 -> 0.1841455 | P31: =-P12/P7 -> 0.1412982 | Q31: =-Q12/Q7 -> 0.16264288 | R31: =-R12/R7 -> 0.15763768 | S31: =-S12/S7 -> 0.18178709 | T31: =-T12/T7 -> 0.14475488 | U31: =-U12/U7 -> 0.16626372 | V31: =-V12/V7 -> 0.17117133 | ... AU31: =-AU12/AU7 -> 0.1328547 | AW31: =-AW12/AW7 -> 0.1706124 | AX31: =-AX12/AX7 -> 0.15552085
B32: =B13 -> General and Administration Expenses | C32: =-C13/C7 -> 0.030194694 | D32: =-D13/D7 -> 0.028512654 | E32: =-E13/E7 -> 0.027674326 | F32: =-F13/F7 -> 0.027891107 | G32: =-G13/G7 -> 0.02733551 | H32: =-H13/H7 -> 0.027013537 | I32: =-I13/I7 -> 0.024499929 | J32: =-J13/J7 -> 0.02395959 | ... M32: =-M13/M7 -> 0.025387883 | O32: =-O13/O7 -> 0.029740378 | P32: =-P13/P7 -> 0.027287179 | Q32: =-Q13/Q7 -> 0.023882244 | R32: =-R13/R7 -> 0.029835111 | S32: =-S13/S7 -> 0.028250344 | T32: =-T13/T7 -> 0.026834953 | U32: =-U13/U7 -> 0.022252807 | V32: =-V13/V7 -> 0.034065905 | ... AU32: =-AU13/AU7 -> 0.022400294 | AW32: =-AW13/AW7 -> 0.028636172 | AX32: =-AX13/AX7 -> 0.02649715
B33: =B14 -> Other Expenses, net | C33: =-C14/C$7 -> 0.0063742718 | D33: =-D14/D$7 -> 0.015146246 | E33: =-E14/E$7 -> 0.020289003 | F33: =-F14/F$7 -> 0.0061786836 | G33: =-G14/G$7 -> 0.0051070043 | H33: =-H14/H$7 -> 0.0053983919 | I33: =-I14/I$7 -> 0.008191106 | J33: =-J14/J$7 -> 0.0032929284 | ... M33: =-M14/M$7 -> 0.0013202072 | O33: =-O14/O$7 -> 0.013750984 | P33: =-P14/P$7 -> 0.0093201488 | Q33: =-Q14/Q$7 -> 0.011403043 | R33: =-R14/R$7 -> 0.047023764 | S33: =-S14/S$7 -> 0.0066894588 | T33: =-T14/T$7 -> 0.01214167 | U33: =-U14/U$7 -> 0.0038919675 | V33: =-V14/V$7 -> 0.0019333477 | ... AU33: =-AU14/AU$7 -> 0.0042546712 | AW33: =-AW14/AW$7 -> 0.0049629906 | AX33: =-AX14/AX$7 -> 0.010675995
B34: =B15 -> Impairment (Loss) / Reversal on Financial Assets | C34: =-C15/C$7 -> 0 | D34: =-D15/D$7 -> 0.0035042078 | E34: =-E15/E$7 -> -0.0018206444 | F34: =-F15/F$7 -> 0.0019644942 | G34: =-G15/G$7 -> 0.0015938714 | H34: =-H15/H$7 -> 0.00074733181 | I34: =-I15/I$7 -> 0.0014049053 | J34: =-J15/J$7 -> 0.001745695 | ... M34: =-M15/M$7 -> 0.0012755902 | O34: =-O15/O$7 -> 0.010348972 | P34: =-P15/P$7 -> -0.0017107388 | Q34: =-Q15/Q$7 -> -0.0072765693 | R34: =-R15/R$7 -> -0.0082190144 | S34: =-S15/S$7 -> 0.00056110716 | T34: =-T15/T$7 -> -0.00060403242 | U34: =-U15/U$7 -> 0.00018498529 | V34: =-V15/V$7 -> 0.0075317135 | ... AU34: =-AU15/AU$7 -> 0.0013298587 | AW34: =-AW15/AW$7 -> 0.00056877045 | AX34: =-AX15/AX$7 -> -0.00059642875
B35: =B16 -> Operating Profit | C35: =C16/C7 -> 0.17559474 | D35: =D16/D7 -> 0.18537864 | E35: =E16/E7 -> 0.18596145 | F35: =F16/F7 -> 0.17233365 | G35: =G16/G7 -> 0.16424709 | H35: =H16/H7 -> 0.12712237 | I35: =I16/I7 -> 0.12158427 | J35: =J16/J7 -> 0.13761469 | ... M35: =M16/M7 -> 0.1363112 | O35: =O16/O7 -> 0.15011733 | P35: =P16/P7 -> 0.21067589 | Q35: =Q16/Q7 -> 0.2333271 | R35: =R16/R7 -> 0.1472428 | S35: =S16/S7 -> 0.14335274 | T35: =T16/T7 -> 0.19853419 | U35: =U16/U7 -> 0.21145386 | V35: =V16/V7 -> 0.13452304 | ... AU35: =AU16/AU7 -> 0.14206517 | AW35: =AW16/AW7 -> 0.14697065 | AX35: =AX16/AX7 -> 0.19708639
B36: Finance costs as a % of debt at end of period | D36: =-D18/D105 -> 0.031342795 | E36: =-E18/E105 -> 0.030278233 | F36: =-F18/F105 -> 0.040692253 | G36: =-G18/G105 -> 0.042462949 | H36: =-H18/H105 -> 0.033850165 | I36: =-I18/I105 -> 0.042522775 | J36: =-J18/J105 -> 0.042232359 | K36: =-K18/K105 -> 0.049706645 | ... M36: =-M18/M105 -> 0.033186118 | R36: =-(R18+Q18+P18+O18)/R105 -> 0.031364288 | S36: =-(S18+R18+Q18+P18)/S105 -> 0.034148637 | T36: =-(T18+S18+R18+Q18)/T105 -> 0.036254977 | U36: =-(U18+T18+S18+R18)/U105 -> 0.03699678 | V36: =-(V18+U18+T18+S18)/V105 -> 0.040692253 | W36: =-(W18+V18+U18+T18)/W105 -> 0.041609419 | X36: =-(X18+W18+V18+U18)/X105 -> 0.040137557 | Y36: =-(Y18+X18+W18+V18)/Y105 -> 0.039972035 | ... AU36: =-(AU18+AT18+AS18+AR18)/AU105 -> 0.033186118 | AW36: =-(AW18+R18+Q18+P18)/S105 -> 0.033864883 | AX36: =-(AX18+S18+R18+Q18)/T105 -> 0.036478533
B37: =B20 -> Profit before Zakat and Income Tax | C37: =C20/C7 -> 0.15513685 | D37: =D20/D7 -> 0.15802827 | E37: =E20/E7 -> 0.15334717 | F37: =F20/F7 -> 0.13395804 | G37: =G20/G7 -> 0.13204824 | H37: =H20/H7 -> 0.10522899 | I37: =I20/I7 -> 0.098755663 | J37: =J20/J7 -> 0.11063807 | ... M37: =M20/M7 -> 0.11540456 | O37: =O20/O7 -> 0.111492 | P37: =P20/P7 -> 0.1906058 | Q37: =Q20/Q7 -> 0.19824861 | R37: =R20/R7 -> 0.10933596 | S37: =S20/S7 -> 0.10729937 | T37: =T20/T7 -> 0.16216241 | U37: =U20/U7 -> 0.17208978 | V37: =V20/V7 -> 0.092985628 | ... AU37: =AU20/AU7 -> 0.1249322 | AW37: =AW20/AW7 -> 0.10876481 | AX37: =AX20/AX7 -> 0.16012108
B38: Income tax benefit/(expense) as a % of Profit before tax | C38: =-C21/C20 -> 0.033421865 | D38: =-D21/D20 -> 0.01918302 | E38: =-E21/E20 -> 0.033908659 | F38: =-F21/F20 -> 0.06288632 | G38: =-G21/G20 -> 0.045516994 | H38: =-H21/H20 -> 0.053010762 | I38: =-I21/I20 -> 0.038287571 | J38: =-J21/J20 -> 0.052763753 | ... M38: =-M21/M20 -> 0.051761811 | O38: =-O21/O20 -> 0.055399387 | P38: =-P21/P20 -> 0.040723576 | Q38: =-Q21/Q20 -> 0.024962671 | R38: =-R21/R20 -> 0.016129948 | S38: =-S21/S20 -> 0.063749858 | T38: =-T21/T20 -> 0.032141223 | U38: =-U21/U20 -> 0.036100572 | V38: =-V21/V20 -> 0.16365817 | ... AU38: =-AU21/AU20 -> 0.048273819 | AW38: =-AW21/AW20 -> 0.063749858 | AX38: =-AX21/AX20 -> 0.032141223
B40: capex/sales | C40: =-C61/C7 -> 0.34117356 | D40: =-D61/D7 -> 0.23204346 | E40: =-E61/E7 -> 0.17847692 | F40: =-F61/F7 -> 0.13918288 | G40: =-G61/G7 -> 0.08094805 | H40: =-H61/H7 -> 0.10214319 | I40: =-I61/I7 -> 0.10247316 | J40: =-J61/J7 -> 0.16852901 | ... M40: =-M61/M7 -> 0.21541017 | O40: =-O61/O7 -> 0.1724903 | P40: =-P61/P7 -> 0.15154223 | Q40: =-Q61/Q7 -> 0.18920798 | R40: =-R61/R7 -> 0.20256484 | S40: =-S61/S7 -> 0.1716973 | T40: =-T61/T7 -> 0.11017503 | U40: =-U61/U7 -> 0.1395805 | V40: =-V61/V7 -> 0.13848963 | ... AU40: =-AU61/AU7 -> 0.17425743 | AW40: =-AW61/AW7 -> 0.17404225 | AX40: =-AX61/AX7 -> 0.10878813
B41: D/A/sales | C41: =C45/C7 -> 0.12671137 | D41: =D45/D7 -> 0.13774967 | E41: =E45/E7 -> 0.15785165 | F41: =F45/F7 -> 0.15151788 | G41: =G45/G7 -> 0.13770783 | H41: =H45/H7 -> 0.13489342 | I41: =I45/I7 -> 0.12742485 | J41: =J45/J7 -> 0.12435439 | ... M41: =M45/M7 -> 0.11141513 | O41: =O45/O7 -> 0.16142479 | P41: =P45/P7 -> 0.15086813 | Q41: =Q45/Q7 -> 0.16411062 | R41: =R45/R7 -> 0.15578655 | S41: =S45/S7 -> 0.15302126 | T41: =T45/T7 -> 0.13662423 | U41: =U45/U7 -> 0.14914964 | V41: =V45/V7 -> 0.1673994 | ... AU41: =AU45/AU7 -> 0.10052495 | AW41: =AW45/AW7 -> 0.15511114 | AX41: =AX45/AX7 -> 0.13490438
B43: EBITDA | C43: =+C3 -> 42735 | D43: =+D3 -> 43100 | E43: =+E3 -> 43465 | F43: =F3 -> 43830 | G43: =G3 -> 44196 | H43: =H3 -> 44561 | I43: =I3 -> 44926 | J43: =J3 -> 45291 | K43: =K3 -> 45657 | L43: =L3 -> 46022 | M43: =M3 -> 46111 | O43: =O3 -> 43189 | P43: =P3 -> 43281 | Q43: =Q3 -> 43373 | R43: =R3 -> 43464 | S43: =S3 -> 43554 | T43: =T3 -> 43646 | U43: =U3 -> 43738 | V43: =V3 -> 43829 | ... AU43: =AU3 -> 46111 | AW43: =AW3 -> 43554 | AX43: =AX3 -> 43646
B44: Operating profit | C44: =C16 -> 2517.779 | D44: =D16 -> 2583.35 | E44: =E16 -> 2521.235 | F44: =F16 -> 2473.208 | G44: =G16 -> 2522.334 | H44: =H16 -> 2014.854 | I44: =I16 -> 2276.332 | J44: =J16 -> 2693.888 | ... M44: =M16 -> 3061.255 | O44: =O16 -> 485.21 | P44: =P16 -> 764.14 | Q44: =Q16 -> 774.03 | R44: =R16 -> 497.855 | S44: =S16 -> 480.817 | T44: =T16 -> 738.547 | U44: =U16 -> 755.579 | V44: =V16 -> 498.265 | ... AU44: =AU16 -> 875.129 | AW44: =AW16 -> 486.31 | AX44: =AX16 -> 742.508
B45: Depreciation & amortisation | C45: =1442.341+32.479+342.041 -> 1816.861 | D45: =1573.671+50.017+295.927 -> 1919.615 | E45: =1684.106+94.732+47.451+313.838 -> 2140.127 | F45: =1638.626+101.788+49.938+384.123 -> 2174.475 | G45: =1600.408+108.505+56.681+349.178 -> 2114.772 | H45: =1608.569+102.737+66.476+360.241 -> 2138.023 | I45: =1752.245+105.557+480.494+47.385 -> 2385.681 | J45: =1711.751+110.9+574.264+37.395 -> 2434.31 | K45: =1688.316+117.99+39.97+566.338 -> 2412.614 | L45: =1663.88+125.446+45.389+635.25 -> 2469.965 | M45: =SUM(AR45:AU45) -> 2502.143 | O45: =418.349+21.234+11.123+71.052 -> 521.758 | P45: =862.864+43.171+22.563+140.372-O45 -> 547.212 | Q45: =1286.854+66.946+34.678+224.906-P45-O45 -> 544.414 | R45: =E45-Q45-P45-O45 -> 526.743 | S45: =386.904+25.479+12.151+88.712 -> 513.246 | T45: =785.343+48.446+23.87+163.829-S45 -> 508.242 | U45: =1196.136+72.622+36.182+249.498-T45-S45 -> 532.95 | V45: =F45-U45-T45-S45 -> 620.037 | W45: =401.165+25.981+12.711+77.09 -> 516.947 | X45: =806.035+51.168+25.91+157.743-W45 -> 523.909 | Y45: =1196.136+72.622+36.182+249.498-X45-W45 -> 513.582 | Z45: =G45-Y45-X45-W45 -> 560.334 | AA45: =414.202+26.253+16.955+85.262 -> 542.672 | AB45: =808.738+51.799+35.38+155.797-AA45 -> 509.042 | AC45: =1209.29+76.739+51.327+241.321-AB45-AA45 -> 526.963 | AD45: =H45-AC45-AB45-AA45 -> 559.346 | AE45: =400.25+23.052+16.104+114.786 -> 554.192 | AF45: =801.961+50.397+21.803+211.568-AE45 -> 531.537 | AG45: =1207.267+75.034+32.268+319.268-AF45-AE45 -> 548.108 | AH45: =I45-AG45-AF45-AE45 -> 751.844 | AI45: 609.129 | AJ45: =1176.2-AI45 -> 567.071 | AK45: =1207.267+75.034+32.268+319.268-AJ45-AI45 -> 457.637 | AL45: =J45-AK45-AJ45-AI45 -> 800.473 | AM45: 543.063 | AN45: =1133.871-AM45 -> 590.808 | AO45: =1731.543-AN45-AM45 -> 597.672 | AP45: =K45-AO45-AN45-AM45 -> 681.071 | AQ45: 587.061 | AR45: 614.6 | AS45: =1801.121-AR45-AQ45 -> 599.46 | AT45: =L45-AS45-AR45-AQ45 -> 668.844 | AU45: 619.239 | AW45: =386.904+25.479+12.151+88.712 -> 513.246 | AX45: =785.343+48.446+23.87+163.829-AW45 -> 508.242
B46: EBITDA | C46: =SUM(C44:C45) -> 4334.64 | D46: =SUM(D44:D45) -> 4502.965 | E46: =SUM(E44:E45) -> 4661.362 | F46: =SUM(F44:F45) -> 4647.683 | G46: =SUM(G44:G45) -> 4637.106 | H46: =SUM(H44:H45) -> 4152.877 | I46: =SUM(I44:I45) -> 4662.013 | J46: =SUM(J44:J45) -> 5128.198 | ... M46: =SUM(M44:M45) -> 5563.398 | O46: =SUM(O44:O45) -> 1006.968 | P46: =SUM(P44:P45) -> 1311.352 | Q46: =SUM(Q44:Q45) -> 1318.444 | R46: =SUM(R44:R45) -> 1024.598 | S46: =SUM(S44:S45) -> 994.063 | T46: =SUM(T44:T45) -> 1246.789 | U46: =SUM(U44:U45) -> 1288.529 | V46: =SUM(V44:V45) -> 1118.302 | ... AU46: =SUM(AU44:AU45) -> 1494.368 | AW46: =SUM(AW44:AW45) -> 999.556 | AX46: =SUM(AX44:AX45) -> 1250.75
B47: % growth | D47: =+D46/C46-1 -> 0.038832521 | E47: =+E46/D46-1 -> 0.035176156 | F47: =+F46/E46-1 -> -0.00293455 | G47: =+G46/F46-1 -> -0.0022757576 | H47: =+H46/G46-1 -> -0.10442483 | I47: =+I46/H46-1 -> 0.12259838 | J47: =+J46/I46-1 -> 0.099996504 | K47: =+K46/J46-1 -> 0.054556591 | L47: =+L46/K46-1 -> 0.022605874 | S47: =S46/O46-1 -> -0.0128157 | T47: =T46/P46-1 -> -0.04923392 | U47: =U46/Q46-1 -> -0.022689625 | V47: =V46/R46-1 -> 0.091454405 | W47: =W46/AW46-1 -> 0.030169395 | X47: =X46/AX46-1 -> 0.025891665 | Y47: =Y46/U46-1 -> -0.01921571 | Z47: =Z46/V46-1 -> -0.051695338 | AA47: =AA46/W46-1 -> 0.014870177 | AB47: =AB46/X46-1 -> -0.13439438 | AC47: =AC46/Y46-1 -> -0.17263123 | AD47: =AD46/Z46-1 -> -0.10271563 | AE47: =AE46/AA46-1 -> 0.053849481 | AF47: =AF46/AB46-1 -> 0.060456222 | ... AU47: =AU46/AQ46-1 -> 0.022701251 | AW47: =AW46/O46-1 -> -0.0073607106 | AX47: =AX46/P46-1 -> -0.046213374
B48: % margin | C48: =C46/C7 -> 0.30230611 | D48: =D46/D7 -> 0.32312832 | E48: =E46/E7 -> 0.3438131 | F48: =F46/F7 -> 0.32385153 | G48: =G46/G7 -> 0.30195492 | H48: =H46/H7 -> 0.2620158 | I48: =I46/I7 -> 0.24900912 | J48: =J46/J7 -> 0.26196908 | ... M48: =M46/M7 -> 0.24772633 | O48: =O46/O7 -> 0.31154212 | P48: =P46/P7 -> 0.36154403 | Q48: =Q46/Q7 -> 0.39743772 | R48: =R46/R7 -> 0.30302935 | S48: =S46/S7 -> 0.296374 | T48: =T46/T7 -> 0.33515842 | U48: =U46/U7 -> 0.36060351 | V48: =V46/V7 -> 0.30192244 | ... AU48: =AU46/AU7 -> 0.24259012 | AW48: =AW46/AW7 -> 0.30208178 | AX48: =AX46/AX7 -> 0.33199077
B50: Adjustment | C50: =C51-C46 -> -618.64 | D50: =D51-D46 -> -583.865 | E50: =E51-E46 -> -637.862 | F50: =F51-F46 -> -629.783 | G50: =G51-G46 -> -623.706 | H50: =H51-H46 -> -660.377 | I50: =I51-I46 -> -730.33882 | J50: =J51-J46 -> -625.81345 | ... M50: =M51-M46 -> -622.67342 | O50: =O51-O46 -> -171.468 | P50: =P51-P46 -> -139.952 | Q50: =Q51-Q46 -> -159.144 | R50: =R51-R46 -> -167.298 | S50: =S51-S46 -> -147.663 | T50: =T51-T46 -> -143.689 | U50: =U51-U46 -> -141.929 | V50: =V51-V46 -> -196.502 | ... AU50: =AU51-AU46 -> -206.56633 | AW50: =AW51-AW46 -> -153.156 | AX50: =AX51-AX46 -> -149.35
B51: Adj. EBITDA | C51: 3716 | D51: 3919.1 | E51: 4023.5 | F51: 4017.9 | G51: 4013.4 | H51: 3492.5 | I51: =I7*21% -> 3931.6742 | J51: =J7*23% -> 4502.3845 | K51: =K7*22% -> 4615.4926 | L51: =L7*22% -> 4854.2727 | M51: =SUM(AR51:AU51) -> 4940.7246 | O51: 835.5 | P51: =2006.9-O51 -> 1171.4 | Q51: =3166.2-P51-O51 -> 1159.3 | R51: =E51-Q51-P51-O51 -> 857.3 | S51: 846.4 | T51: =1949.5-S51 -> 1103.1 | U51: =3096.1-T51-S51 -> 1146.6 | V51: =F51-U51-T51-S51 -> 921.8 | W51: 888.8 | X51: 1136.7 | Y51: 1151.4 | Z51: =G51-Y51-X51-W51 -> 836.5 | AA51: 897.8 | AB51: 929.9 | AC51: 879.1 | AD51: =H51-AC51-AB51-AA51 -> 785.7 | AE51: =2866.795-AF51-AG51 -> 938.494 | AF51: 986 | AG51: 942.301 | AH51: =I51-AG51-AF51-AE51 -> 1064.8792 | AI51: =3413.128-AJ51-AK51 -> 1242.907 | AJ51: 1108 | AK51: 1062.221 | AL51: =J51-AK51-AJ51-AI51 -> 1089.2565 | AM51: =(22%*19968)-AL51-AK51-AJ51 -> 1133.4825 | AN51: =(22%*20329)-AM51-AL51-AK51 -> 1187.42 | AO51: =(22%*20742)-AN51-AM51-AL51 -> 1153.081 | AP51: =K51-AO51-AN51-AM51 -> 1141.5092 | AQ51: =(22%*21288)-AP51-AO51-AN51 -> 1201.3498 | AR51: =(22%*21422)-AQ51-AP51-AO51 -> 1216.9 | AS51: =(22%*21765)-AR51-AQ51-AP51 -> 1228.541 | AT51: =L51-AS51-AR51-AQ51 -> 1207.4819 | AU51: =(22%*(AR7+AU7+AT7+AS7))-AR51-AT51-AS51 -> 1287.8017 | AW51: 846.4 | AX51: 1101.4
B52: % growth | D52: =+D51/C51-1 -> 0.054655544 | E52: =+E51/D51-1 -> 0.026638769 | F52: =+F51/E51-1 -> -0.001391823 | G52: =+G51/F51-1 -> -0.0011199881 | H52: =+H51/G51-1 -> -0.1297902 | I52: =+I51/H51-1 -> 0.1257478 | J52: =+J51/I51-1 -> 0.14515709 | K52: =+K51/J51-1 -> 0.025121819 | L52: =+L51/K51-1 -> 0.051734473 | S52: =S51/O51-1 -> 0.01304608 | T52: =T51/P51-1 -> -0.0583063 | U52: =U51/Q51-1 -> -0.010954887 | V52: =V51/R51-1 -> 0.075236207 | W52: =W51/AW51-1 -> 0.050094518 | X52: =X51/AX51-1 -> 0.032050118 | Y52: =Y51/U51-1 -> 0.0041862899 | Z52: =Z51/V51-1 -> -0.092536342 | AA52: =AA51/W51-1 -> 0.010126013 | AB52: =AB51/X51-1 -> -0.18193015 | AC52: =AC51/Y51-1 -> -0.2364947 | AD52: =AD51/Z51-1 -> -0.060729229 | AE52: =AE51/AA51-1 -> 0.045326353 | AF52: =AF51/AB51-1 -> 0.060329068 | ... AU52: =AU51/AQ51-1 -> 0.071962271 | AW52: =AW51/O51-1 -> 0.01304608 | AX52: =AX51/P51-1 -> -0.059757555
B53: % margin | C53: =C51/C7 -> 0.25916097 | D53: =D51/D7 -> 0.28123074 | E53: =E51/E7 -> 0.29676563 | F53: =F51/F7 -> 0.27996812 | G53: =G51/G7 -> 0.26134099 | H53: =H51/H7 -> 0.2203509 | I53: =I51/I7 -> 0.21 | J53: =J51/J7 -> 0.23 | ... M53: =M51/M7 -> 0.22 | O53: =O51/O7 -> 0.25849227 | P53: =P51/P7 -> 0.3229588 | Q53: =Q51/Q7 -> 0.34946463 | R53: =R51/R7 -> 0.25355024 | S53: =S51/S7 -> 0.25234915 | T53: =T51/T7 -> 0.29653234 | U53: =U51/U7 -> 0.32088372 | V53: =V51/V7 -> 0.24887026 | ... AU53: =AU51/AU7 -> 0.20905691 | AW53: =AW51/AW7 -> 0.2557956 | AX53: =AX51/AX7 -> 0.2923483
B55: CASH FLOW | C55: =+C43 -> 42735 | D55: =+D43 -> 43100 | E55: =+E43 -> 43465 | F55: =+F43 -> 43830 | G55: =+G43 -> 44196 | H55: =+H43 -> 44561 | I55: =+I43 -> 44926 | J55: =+J43 -> 45291 | ... M55: =+M43 -> 46111 | O55: =+O43 -> 43189 | P55: =+P43 -> 43281 | Q55: =+Q43 -> 43373 | R55: =+R43 -> 43464 | S55: =+S43 -> 43554 | T55: =+T43 -> 43646 | U55: =+U43 -> 43738 | V55: =+V43 -> 43829 | ... AD55: =+AD43 -> 44560 | AE55: 44651 | AF55: =+AF43 -> 44742 | AG55: =+AG43 -> 44834 | AH55: =+AH43 -> 44926 | AI55: =+AI43 -> 45015 | AJ55: =+AJ43 -> 45107 | AK55: =+AK43 -> 45199 | AL55: =+AL43 -> 45291 | AM55: =+AM43 -> 45381 | ... AU55: =+AU43 -> 46111 | AW55: =+AW43 -> 43554 | AX55: =+AX43 -> 43646
B56: Adjusted EBITDA | C56: =C51 -> 3716 | D56: =D51 -> 3919.1 | E56: =E51 -> 4023.5 | F56: =F51 -> 4017.9 | G56: =G51 -> 4013.4 | H56: =H51 -> 3492.5 | I56: =I51 -> 3931.6742 | J56: =J51 -> 4502.3845 | ... M56: =M51 -> 4940.7246 | O56: =O51 -> 835.5 | P56: =P51 -> 1171.4 | Q56: =Q51 -> 1159.3 | R56: =R51 -> 857.3 | S56: =S51 -> 846.4 | T56: =T51 -> 1103.1 | U56: =U51 -> 1146.6 | V56: =V51 -> 921.8 | ... AU56: =AU51 -> 1287.8017 | AW56: =AW51 -> 846.4 | AX56: =AX51 -> 1101.4
B57: Working Capital | C57: =844.604-1231.787-164.572+524.039 -> -27.716 | D57: =1083.062-1197.326-106.17+35.566 -> -184.868 | E57: =858.754-1614.754-257.234-314.422 -> -1327.656 | F57: =1068.299-1345.618+142.85+79.86 -> -54.609 | G57: =1148.049-1650.036-65.165+26.522 -> -540.63 | H57: =349.458-28.305-67.376+358.167 -> 611.944 | I57: =-1103.277-9.009-218.589+412.038 -> -918.837 | J57: =-1063.947-7.885-458.951+591.073 -> -939.71 | K57: =348.415-11.161+11.74-143.111 -> 205.883 | L57: =-312.092-33.032-112.054+266.588 -> -190.59 | M57: =SUM(AR57:AU57) -> -131.699 | O57: =246.641-332.26-400.95+46.956 -> -439.613 | P57: =398.156-744.273-682.516+182.41-O57 -> -406.61 | Q57: =439.613-1189.837-739.976-104.082-P57-O57 -> -748.059 | R57: =E57-Q57-P57-O57 -> 266.626 | S57: =378.055-339.441-258.234-42.814 -> -262.434 | T57: =469.011-645.312-428.393+220.509-S57 -> -121.751 | U57: =591.152-979.075-451.512+256.691-T57-S57 -> -198.559 | V57: =F57-U57-T57-S57 -> 528.135 | W57: =463.129-346.071-644.704-80.523 -> -608.169 | X57: =383.501-668.343-552.12+361.832-W57 -> 133.039 | Y57: =643.606-1224.917-536.84+378.496-X57-W57 -> -264.525 | Z57: =G57-Y57-X57-W57 -> 199.025 | AA57: =691.492-532.551-769.634+388.711 -> -221.982 | AB57: =1096.214-976.286-721.888+699.45-AA57 -> 319.472 | AC57: =1685.473-1423.968-415.307+300.447-AB57-AA57 -> 49.155 | AD57: =H57-AC57-AB57-AA57 -> 465.299 | AE57: =393.811-458.2-686.828+120.661 -> -630.556 | AF57: =141.046-931.572-628.02+472.534-AE57 -> -315.456 | AG57: =-702.574-12.201-596.8+499.708-AF57-AE57 -> 134.145 | AH57: =I57-AG57-AF57-AE57 -> -106.97 | AI57: =-81.974-55.258-1018.115+583.779 -> -571.568 | AJ57: =-378.661-AI57 -> 192.907 | AK57: =-940.838-1.463-941.274+558.751-AJ57-AI57 -> -946.163 | AL57: =J57-AK57-AJ57-AI57 -> 385.114 | AM57: =442.753-16.548-951.753+461.453 -> -64.095 | AN57: =412.787-AM57 -> 476.882 | AO57: =456.993-5.132-738.056+652.548-AN57-AM57 -> -46.434 | AP57: =K57-AO57-AN57-AM57 -> -160.47 | AQ57: =496.811-25.663-1226.797+396.312 -> -359.337 | AR57: =-340.958-AQ57 -> 18.379 | AS57: =69.232-7.572-1388.94+1004.33-AR57-AQ57 -> 18.008 | AT57: =L57-AS57-AR57-AQ57 -> 132.36 | AU57: =426.676-29.366-1410.698+712.942 -> -300.446 | AW57: =378.055-339.441-258.234-42.293 -> -261.913 | AX57: =469.011-645.312-428.393+220.509-AW57 -> -122.272
B58: Taxes, net | C58: -10.161 | D58: -11.922 | E58: -22.964 | F58: =-19.277 -> -19.277 | G58: =-84.763 -> -84.763 | H58: -34.749 | I58: -330.922 | J58: -8.255 | K58: -22.948 | L58: -194.322 | M58: =SUM(AR58:AU58) -> -103.056 | O58: -2.449 | P58: =-6.741-O58 -> -4.292 | Q58: =-10.389-P58-O58 -> -3.648 | R58: =E58-Q58-P58-O58 -> -12.575 | S58: -1.473 | T58: =-8.875-S58 -> -7.402 | U58: =-15.67-T58-S58 -> -6.795 | V58: =F58-U58-T58-S58 -> -3.607 | W58: -54.679 | X58: =-54.679-W58 -> 0 | Y58: =-69.317-X58-W58 -> -14.638 | Z58: =G58-Y58-X58-W58 -> -15.446 | AA58: -1.394 | AB58: =-22.054-AA58 -> -20.66 | AC58: =-23.732-AB58-AA58 -> -1.678 | AD58: =H58-AC58-AB58-AA58 -> -11.017 | AE58: -0.236 | AF58: =-95.281-AE58 -> -95.045 | AG58: =-95.281-AF58-AE58 -> -4.2188475e-15 | AH58: =I58-AG58-AF58-AE58 -> -235.641 | AI58: 0 | AJ58: =-7.085-AI58 -> -7.085 | AK58: =-7.631-AJ58-AI58 -> -0.546 | AL58: =J58-AK58-AJ58-AI58 -> -0.624 | AM58: 0 | AN58: =-19.663-AM58 -> -19.663 | AO58: =-21.331-AN58-AM58 -> -1.668 | AP58: =K58-AO58-AN58-AM58 -> -1.617 | AQ58: -94.088 | AR58: =-142.633-AQ58 -> -48.545 | AS58: =-190.673-AR58-AQ58 -> -48.04 | AT58: =L58-AS58-AR58-AQ58 -> -3.649 | AU58: -2.822 | AW58: -1.473 | AX58: =-8.875-AW58 -> -7.402
B59: Cash interest paid | C59: -360.596 | D59: -467.977 | E59: -420.625 | F59: -524.609 | G59: -467.844 | H59: -342.446 | I59: -431.81 | J59: -559.199 | K59: -645.039 | L59: =-681.389 -> -681.389 | M59: =SUM(AR59:AU59) -> -702.165 | O59: -131.238 | P59: =-208.485-O59 -> -77.247 | Q59: =-317.689-P59-O59 -> -109.204 | R59: =E59-Q59-P59-O59 -> -102.936 | S59: -131.456 | T59: =-264.288-S59 -> -132.832 | U59: =-392.084-T59-S59 -> -127.796 | V59: =F59-U59-T59-S59 -> -132.525 | W59: -106.799 | X59: =-239.447-W59 -> -132.648 | Y59: =-353.639-X59-W59 -> -114.192 | Z59: =G59-Y59-X59-W59 -> -114.205 | AA59: -86.896 | AB59: =-179.055-AA59 -> -92.159 | AC59: =-258.206-AB59-AA59 -> -79.151 | AD59: =H59-AC59-AB59-AA59 -> -84.24 | AE59: -89.475 | AF59: =-187.442-AE59 -> -97.967 | AG59: =-299.451-AF59-AE59 -> -112.009 | AH59: =I59-AG59-AF59-AE59 -> -132.359 | AI59: -126.396 | AJ59: =-270.274-AI59 -> -143.878 | AK59: =-405.494-AJ59-AI59 -> -135.22 | AL59: =J59-AK59-AJ59-AI59 -> -153.705 | AM59: -94.65 | AN59: =-280.007-AM59 -> -185.357 | AO59: =-489.049-AN59-AM59 -> -209.042 | AP59: =K59-AO59-AN59-AM59 -> -155.99 | AQ59: -147.117 | AR59: =-326.216-AQ59 -> -179.099 | AS59: =-508.49-AR59-AQ59 -> -182.274 | AT59: =L59-AS59-AR59-AQ59 -> -172.899 | AU59: -167.893 | AW59: -131.456 | AX59: =-264.288-AW59 -> -132.832
B60: Net cash from operations | C60: =SUM(C56:C59) -> 3317.527 | D60: =SUM(D56:D59) -> 3254.333 | E60: =SUM(E56:E59) -> 2252.255 | F60: =SUM(F56:F59) -> 3419.405 | G60: =SUM(G56:G59) -> 2920.163 | H60: =SUM(H56:H59) -> 3727.249 | I60: =SUM(I56:I59) -> 2250.1052 | J60: =SUM(J56:J59) -> 2995.2205 | ... M60: =SUM(M56:M59) -> 4003.8046 | O60: =SUM(O56:O59) -> 262.2 | P60: =SUM(P56:P59) -> 683.251 | Q60: =SUM(Q56:Q59) -> 298.389 | R60: =SUM(R56:R59) -> 1008.415 | S60: =SUM(S56:S59) -> 451.037 | T60: =SUM(T56:T59) -> 841.115 | U60: =SUM(U56:U59) -> 813.45 | V60: =SUM(V56:V59) -> 1313.803 | ... AU60: =SUM(AU56:AU59) -> 816.64067 | AW60: =SUM(AW56:AW59) -> 451.558 | AX60: =SUM(AX56:AX59) -> 838.894
B61: Net Capex | C61: =-4514.597+133.971-93.131-618.673+200.486 -> -4891.944 | D61: =-2797.282+30.79-81.536-582.895+197.274 -> -3233.649 | E61: =-1918.833+35.74-97.818-639.089+200.239 -> -2419.761 | F61: =-1516.698+45.937-125.695-629.785+228.789 -> -1997.452 | G61: =-823.691+110.636-119.968-644.437+234.345 -> -1243.115 | H61: =-1087.816+40.304-822.094+250.665 -> -1618.941 | I61: =-1300.535+43.894-889.409+227.521 -> -1918.529 | J61: =-2505.89+73.741-1095.263+228.358 -> -3299.054 | K61: =-3573.721+137.383-1072.814+287.126 -> -4222.026 | L61: =-4345.155+66.119-1041.703+306.417 -> -5014.322 | M61: =SUM(AR61:AU61) -> -4837.647 | O61: =-439.057+5.58-19.455-153.007+48.415 -> -557.524 | P61: =-886.323+18.627-37.611-300.826+98.952-O61 -> -549.657 | Q61: =-1355.457+20.373-66.984-480.718+147.934-P61-O61 -> -627.671 | R61: =E61-Q61-P61-O61 -> -684.909 | S61: =-466.484+12.282-28.294-153.167+59.776 -> -575.887 | T61: =-834.549+25.364-57.293-296.731+177.471-S61 -> -409.851 | U61: =-1158.216+41.039-89.195-446.975+168.852-T61-S61 -> -498.757 | V61: =F61-U61-T61-S61 -> -512.957 | W61: =-241.368+45.608-27.78-141.698+51.618 -> -313.62 | X61: =-465.82+65.763-63.333-288.276+110.977-W61 -> -327.069 | Y61: =-602.953+70.415-95.169-440.231+170.129-X61-W61 -> -257.12 | Z61: =G61-Y61-X61-W61 -> -345.306 | AA61: =-174.414+1.131-29.492-153.999+74.414 -> -282.36 | AB61: =-399.193+9.662-68.197-341.6+121.889-AA61 -> -395.079 | AC61: =-656.356+21.973-89.604-514.966+186.436-AB61-AA61 -> -375.078 | AD61: =H61-AC61-AB61-AA61 -> -566.424 | AE61: =-334.918+5.504-201.117+61.821 -> -468.71 | AF61: =-650.723+12.998-429.235+112.212-AE61 -> -486.038 | AG61: =-945.941+38.91-651.868+170.784-AF61-AE61 -> -433.367 | AH61: =I61-AG61-AF61-AE61 -> -530.414 | AI61: =-513.439+33.712-228.068+56.305 -> -651.49 | AJ61: =-992.416+39.544-444.092+105.704-AI61 -> -639.77 | AK61: =-1666.262+46.126-676.448+174.052-AJ61-AI61 -> -831.272 | AL61: =J61-AK61-AJ61-AI61 -> -1176.522 | AM61: =-777.891+25.674-217.177+74.276 -> -895.118 | AN61: =-186.969-1588.02+37.727-494.583+155.06-AM61 -> -1181.667 | AO61: =-2484.438+108.312-737.586+218.111-AN61-AM61 -> -818.816 | AP61: =K61-AO61-AN61-AM61 -> -1326.425 | AQ61: =-1099.195+25.734-253.011+76.362 -> -1250.11 | AR61: =(-2096.984+39.85-512.951+158.193)-AQ61 -> -1161.782 | AS61: =-3088.156+60.29-779.858+233.266-AR61-AQ61 -> -1162.566 | AT61: =L61-AS61-AR61-AQ61 -> -1439.864 | AU61: =-925.434+33.941-262.098+80.156 -> -1073.435 | AW61: =-466.484+12.282-28.294-153.167+59.776 -> -575.887 | AX61: =-834.549+25.364-57.293-296.731+177.471-AW61 -> -409.851
B62: Purchase and development of intangible assets | C62: -18.153 | D62: -52.927 | E62: -39.797 | F62: -132.983 | G62: -144.971 | H62: -57.175 | I62: -33.339 | J62: -24.517 | K62: -60.504 | L62: =-39.678 -> -39.678 | M62: =SUM(AR62:AU62) -> -63.22 | O62: -11.516 | P62: =-18.713-O62 -> -7.197 | Q62: =-26.608-P62-O62 -> -7.895 | R62: =E62-Q62-P62-O62 -> -13.189 | S62: -30.247 | T62: =-38.73-S62 -> -8.483 | U62: =-98.189-T62-S62 -> -59.459 | V62: =F62-U62-T62-S62 -> -34.794 | W62: -31.274 | X62: =-59.125-W62 -> -27.851 | Y62: =-90.223-X62-W62 -> -31.098 | Z62: =G62-Y62-X62-W62 -> -54.748 | AA62: -16.702 | AB62: =-44.123-AA62 -> -27.421 | AC62: =-79.385-AB62-AA62 -> -35.262 | AD62: =H62-AC62-AB62-AA62 -> 22.21 | AE62: =-14.421 -> -14.421 | AF62: =-18.63-AE62 -> -4.209 | AG62: =-43.793-AF62-AE62 -> -25.163 | AH62: =I62-AG62-AF62-AE62 -> 10.454 | AI62: -8.078 | AJ62: =-13.39-AI62 -> -5.312 | AK62: =-18.627-AJ62-AI62 -> -5.237 | AL62: =J62-AK62-AJ62-AI62 -> -5.89 | AM62: -12.042 | AN62: =-19.34-AM62 -> -7.298 | AO62: =-36.787-AN62-AM62 -> -17.447 | AP62: =K62-AO62-AN62-AM62 -> -23.717 | AQ62: -6.989 | AR62: =-10.666-AQ62 -> -3.677 | AS62: =-21.135-AR62-AQ62 -> -10.469 | AT62: =L62-AS62-AR62-AQ62 -> -18.543 | AU62: -30.531 | AW62: -30.247 | AX62: =-38.73-AW62 -> -8.483
B63: Disposals/ Acquisition, of subsidiaries | C63: 0 | D63: -25 | E63: =-3.872-9.375+105 -> 91.753 | F63: =-87.825-97.593-43.5 -> -228.918 | G63: 0 | H63: -219.369 | I63: -68.595 | J63: 0 | K63: 0 | L63: -1010.094 | M63: =SUM(AR63:AU63) -> -1010.094 | O63: 0 | P63: =-3.872-O63 -> -3.872 | Q63: =-3.872-9.375-P63-O63 -> -9.375 | R63: =E63-Q63-P63-O63 -> 105 | S63: 0 | T63: =-97.593-S63 -> -97.593 | U63: =-97.593-43.5-T63-S63 -> -43.5 | V63: =F63-U63-T63-S63 -> -87.825 | W63: 0 | X63: 0 | Y63: 0 | Z63: =G63-Y63-X63-W63 -> 0 | AA63: 0 | AB63: 0 | AC63: -150 | AD63: =H63-AC63-AB63-AA63 -> -69.369 | AE63: -68.55 | AF63: =-68.55-AE63 -> 0 | AG63: =-68.55-AF63-AE63 -> 0 | AH63: =I63-AG63-AF63-AE63 -> -0.045 | AI63: 0 | AJ63: =0-AI63 -> 0 | AK63: =0-AJ63-AI63 -> 0 | AL63: =J63-AK63-AJ63-AI63 -> 0 | AM63: 0 | AN63: 0 | AO63: =0-AN63-AM63 -> 0 | AP63: =K63-AO63-AN63-AM63 -> 0 | AQ63: 0 | AR63: =0-AQ63 -> 0 | AS63: =-1010.094-AR63-AQ63 -> -1010.094 | AT63: =L63-AS63-AR63-AQ63 -> 0 | AU63: 0 | AW63: 0 | AX63: =-97.593-AW63 -> -97.593
B64: Free cash flow | C64: =SUM(C60:C63) -> -1592.57 | D64: =SUM(D60:D63) -> -57.243 | E64: =SUM(E60:E63) -> -115.55 | F64: =SUM(F60:F63) -> 1060.052 | G64: =SUM(G60:G63) -> 1532.077 | H64: =SUM(H60:H63) -> 1831.764 | I64: =SUM(I60:I63) -> 229.64218 | J64: =SUM(J60:J63) -> -328.35045 | ... M64: =SUM(M60:M63) -> -1907.1564 | O64: =SUM(O60:O63) -> -306.84 | P64: =SUM(P60:P63) -> 122.525 | Q64: =SUM(Q60:Q63) -> -346.552 | R64: =SUM(R60:R63) -> 415.317 | S64: =SUM(S60:S63) -> -155.097 | T64: =SUM(T60:T63) -> 325.188 | U64: =SUM(U60:U63) -> 211.734 | V64: =SUM(V60:V63) -> 678.227 | ... AU64: =SUM(AU60:AU63) -> -287.32533 | AW64: =SUM(AW60:AW63) -> -154.576 | AX64: =SUM(AX60:AX63) -> 322.967
B65: Other investing activities | C65: =0.5-71.794 -> -71.294 | D65: 1.11 | E65: =0.225+17.861 -> 18.086 | F65: =-585+0.3 -> -584.7 | G65: =585+0.18+15.279 -> 600.459 | H65: =80.938+0.3 -> 81.238 | I65: =32.883+0.3 -> 33.183 | J65: =19.781-1876.25 -> -1856.469 | K65: =1876.25-27.5-187.87 -> 1660.88 | L65: =-1.176+99.242 -> 98.066 | M65: =SUM(AR65:AU65) -> 99.241 | O65: 17.861 | P65: =17.861-O65 -> 0 | Q65: =17.861-P65-O65 -> 0 | R65: =E65-Q65-P65-O65 -> 0.225 | S65: 0.3 | T65: =0.3-S65 -> 0 | U65: =0.3-T65-S65 -> 0 | V65: =F65-U65-T65-S65 -> -585 | W65: 585 | X65: =585-W65 -> 0 | Y65: =0.18+585-X65-W65 -> 0.18 | Z65: =G65-Y65-X65-W65 -> 15.279 | AA65: 0 | AB65: =0-AA65 -> 0 | AC65: =81.088+0.3-AB65-AA65 -> 81.388 | AD65: =H65-AC65-AB65-AA65 -> -0.15 | AE65: 0 | AF65: =32.883+0.3-AE65 -> 33.183 | AG65: =32.883+0.3-AF65-AE65 -> 0 | AH65: =I65-AG65-AF65-AE65 -> 0 | AI65: 19.782 | AJ65: =19.782-AI65 -> 0 | AK65: =19.782-1876.25-AJ65-AI65 -> -1876.25 | AL65: =J65-AK65-AJ65-AI65 -> -0.001 | AM65: 1876.25 | AN65: =1876.25-27.5-AM65 -> -27.5 | AO65: =-27.5+1876.25-187.87-AN65-AM65 -> -187.87 | AP65: =K65-AO65-AN65-AM65 -> 0 | AQ65: -1.175 | AR65: =88.529-1.175-AQ65 -> 88.529 | AS65: =-1.175-AR65-AQ65 -> -88.529 | AT65: =L65-AS65-AR65-AQ65 -> 99.241 | AU65: 0 | AW65: 0.3 | AX65: =0.3-AW65 -> 0
B66: Equity Issuance/Buyback | C66: =-75.414+27.119 -> -48.295 | D66: =-75.533+1.371 -> -74.162 | E66: =-222.707+75.112 -> -147.595 | F66: =-314.93+105.852 -> -209.078 | G66: =-250.461+102.246 -> -148.215 | H66: 29.147 | I66: 5.546 | J66: 273.316 | K66: 64.01 | L66: 10.26 | M66: =SUM(AR66:AU66) -> 10.26 | O66: 0 | P66: =-61.82-O66 -> -61.82 | Q66: =-172.982+75.112-P66-O66 -> -36.05 | R66: =E66-Q66-P66-O66 -> -49.725 | S66: =-68.845+63.856 -> -4.989 | T66: =-112.783+104.186-S66 -> -3.608 | U66: =-112.783+104.816-T66-S66 -> 0.63 | V66: =F66-U66-T66-S66 -> -201.111 | W66: =-253.157+7.832 -> -245.325 | X66: =-253.157+45.131-W66 -> 37.299 | Y66: =-253.157+91.539-X66-W66 -> 46.408 | Z66: =G66-Y66-X66-W66 -> 13.403 | AA66: =2.487 -> 2.487 | AB66: =0+21.36-AA66 -> 18.873 | AC66: =27.238-AB66-AA66 -> 5.878 | AD66: =H66-AC66-AB66-AA66 -> 1.909 | AE66: 0 | AF66: =-0.616-AE66 -> -0.616 | AG66: =0-AF66-AE66 -> 0.616 | AH66: =I66-AG66-AF66-AE66 -> 5.546 | AI66: 0 | AJ66: =0-AI66 -> 0 | AK66: =268.138-AJ66-AI66 -> 268.138 | AL66: =J66-AK66-AJ66-AI66 -> 5.178 | AM66: 21.62 | AN66: =0-AM66 -> -21.62 | AO66: =42.78-AN66-AM66 -> 42.78 | AP66: =K66-AO66-AN66-AM66 -> 21.23 | AQ66: 0 | AR66: =0-AQ66 -> 0 | AS66: =10.26-AR66-AQ66 -> 10.26 | AT66: =L66-AS66-AR66-AQ66 -> 0 | AU66: 0 | AW66: =-68.845+63.856 -> -4.989 | AX66: =-112.783+104.186-AW66 -> -3.608
B67: Dividends Paid | C67: -687.721 | D67: -717.905 | E67: -747.846 | F67: -849.969 | G67: -847.896 | H67: -978.187 | I67: -979.566 | J67: -980.576 | K67: -986.875 | L67: =-985.506 -> -985.506 | M67: =SUM(AR67:AU67) -> -985.506 | O67: 0 | P67: =-745.138-O67 -> -745.138 | Q67: =-745.403-P67-O67 -> -0.265 | R67: =E67-Q67-P67-O67 -> -2.443 | S67: 0 | T67: =-846.962-S67 -> -846.962 | U67: =-846.965-T67-S67 -> -0.003 | V67: =F67-U67-T67-S67 -> -3.004 | W67: 0 | X67: =-847.875-W67 -> -847.875 | Y67: =-847.883-X67-W67 -> -0.008 | Z67: =G67-Y67-X67-W67 -> -0.013 | AA67: 0 | AB67: =-978.147-AA67 -> -978.147 | AC67: =-978.171-AB67-AA67 -> -0.024 | AD67: =H67-AC67-AB67-AA67 -> -0.016 | AE67: 0 | AF67: =-979.564-AE67 -> -979.564 | AG67: =-979.566-AF67-AE67 -> -0.002 | AH67: =I67-AG67-AF67-AE67 -> 0 | AI67: 0 | AJ67: =-980.576-AI67 -> -980.576 | AK67: =-980.576-AJ67-AI67 -> 0 | AL67: =J67-AK67-AJ67-AI67 -> 0 | AM67: 0 | AN67: =-986.864-AM67 -> -986.864 | AO67: =-986.864-AN67-AM67 -> 0 | AP67: =K67-AO67-AN67-AM67 -> -0.011 | AQ67: 0 | AR67: =-985.446-AQ67 -> -985.446 | AS67: =-985.504-AR67-AQ67 -> -0.058 | AT67: =L67-AS67-AR67-AQ67 -> -0.002 | AU67: 0 | AW67: 0 | AX67: =-846.962-AW67 -> -846.962
B68: Change in debt | C68: 351.847 | D68: =1105.031+0 -> 1105.031 | E68: =9947.9-8833.451-1700-110.392 -> -695.943 | F68: =6900.918-7704.4-103.366 -> -906.848 | G68: =4813.121-6581.891-125.17 -> -1893.94 | H68: =10659.617-12129.264-86.765-14.369 -> -1570.781 | I68: =16232.882-16311.883-107.318-13.506 -> -199.825 | J68: =16099.196-13634.845-100.764-15.208 -> 2348.379 | K68: =14767.862-16576.34-122.093-5.72 -> -1936.291 | L68: =24779.624-22482.609-132.1-5.117 -> 2159.798 | M68: =SUM(AR68:AU68) -> 2906.349 | O68: =-612.854-25.763 -> -638.617 | P68: =1932.389-2818.053-52.111-O68 -> -299.158 | Q68: =3624.311-2619.381-1700-79.936-P68-O68 -> 162.769 | R68: =E68-Q68-P68-O68 -> 79.063 | S68: =-655.782-30.156 -> -685.938 | T68: =4691.53-5024.12-50.853-S68 -> 302.495 | U68: =5312.356-5352.671-111.721-T68-S68 -> 231.407 | V68: =F68-U68-T68-S68 -> -754.812 | W68: =2027.824-2464.731-27.952 -> -464.859 | X68: =2999.735-3290.793-54.983-W68 -> 118.818 | Y68: =4176.732-4717.902-94.175-X68-W68 -> -289.304 | Z68: =G68-Y68-X68-W68 -> -1258.595 | AA68: =1042.569-1459.202-28.273 -> -444.906 | AB68: =4476.415-4602.452-55.124-AA68 -> 263.745 | AC68: =-847.409-70.26-AB68-AA68 -> -736.508 | AD68: =H68-AC68-AB68-AA68 -> -653.112 | AE68: =1488.261-1204.632-32.638-1.213 -> 249.778 | AF68: =5990.699-4955.689+59.951-AE68 -> 845.183 | AG68: =11803.542-11518.037-81.69-AF68-AE68 -> -891.146 | AH68: =I68-AG68-AF68-AE68 -> -403.64 | AI68: =3534.562-3482.339-27.912-0.899 -> 23.412 | AJ68: =8547.134-7936.622-57.741-1.516-AI68 -> 527.843 | AK68: =14426.795-11744.34-87.882-AJ68-AI68 -> 2043.318 | AL68: =J68-AK68-AJ68-AI68 -> -246.194 | AM68: =2795.968-5193.132-34.477-1.197 -> -2432.838 | AN68: =6923.759-8658.061-60.034-1.959-AM68 -> 636.543 | AO68: =10561.906-12762.468-84.451-AN68-AM68 -> -488.718 | AP68: =K68-AO68-AN68-AM68 -> 348.722 | AQ68: =6429.845-6032.876-45.133 -> 351.836 | AR68: =(12523.157-11428.674-71.584-2.12)-AQ68 -> 668.943 | AS68: =20070.593-17581.176-99.745-AR68-AQ68 -> 1368.893 | AT68: =L68-AS68-AR68-AQ68 -> -229.874 | AU68: =5172.706-4033.301-41.018 -> 1098.387 | AW68: =2727.758-3383.54-30.156 -> -685.938 | AX68: =4691.53-5024.12-50.853-AW68 -> 302.495
B69: Other financing activities | C69: =86.864-59.321 -> 27.543 | D69: =-11.052-2.84-72.087 -> -85.979 | E69: =130.253-73.531-5.64 -> 51.082 | F69: =35.516-5.05 -> 30.466 | G69: =-23.889-5.767 -> -29.656 | H69: =-150-6.407-5.087 -> -161.494 | I69: =-250-0.616-4.865 -> -255.481 | J69: =-255-4.994-0.781 -> -260.775 | K69: =-5.477-29.651 -> -35.128 | L69: =-7.39-0.645 -> -8.035 | M69: =SUM(AR69:AU69) -> -8.158 | O69: =89.32-34.797 -> 54.523 | P69: =79.976-34.798-5.64-O69 -> -14.985 | Q69: =125.344-73.531-5.64-P69-O69 -> 6.635 | R69: =E69-Q69-P69-O69 -> 4.909 | S69: 36.024 | T69: =45.429-5.05-S69 -> 4.355 | U69: =35.516-5.05-T69-S69 -> -9.913 | V69: =F69-U69-T69-S69 -> 0 | W69: 0 | X69: =-0.861-5.767-W69 -> -6.628 | Y69: =-22.728-5.767-X69-W69 -> -21.867 | Z69: =G69-Y69-X69-W69 -> -1.161 | AA69: 0 | AB69: =0-5.185-AA69 -> -5.185 | AC69: =-6.407-5.185-AB69-AA69 -> -6.407 | AD69: =H69-AC69-AB69-AA69 -> -149.902 | AE69: -250 | AF69: =-250-2.016-4.865-AE69 -> -6.881 | AG69: =-250-0.616-3.645-4.865-AF69-AE69 -> -2.245 | AH69: =I69-AG69-AF69-AE69 -> 3.645 | AI69: =-255 -> -255 | AJ69: =-255+70-4.994+0.781-AI69 -> 65.787 | AK69: =-255-0.781-2.856-4.994-AJ69-AI69 -> -74.418 | AL69: =J69-AK69-AJ69-AI69 -> 2.856 | AM69: 0 | AN69: =21.62-0.728-5.477-AM69 -> 15.415 | AO69: =-0.728-2.989-5.477-AN69-AM69 -> -24.609 | AP69: =K69-AO69-AN69-AM69 -> -25.934 | AQ69: -1.095 | AR69: =(10.26-7.39)-AQ69 -> 3.965 | AS69: =-3.554-7.39-AR69-AQ69 -> -13.814 | AT69: =L69-AS69-AR69-AQ69 -> 2.909 | AU69: -1.218 | AW69: 36.024 | AX69: =45.429-5.05-AW69 -> 4.355
B70: Cash flow after financing activities | C70: =SUM(C64:C69) -> -2020.49 | D70: =SUM(D64:D69) -> 170.852 | E70: =SUM(E64:E69) -> -1637.766 | F70: =SUM(F64:F69) -> -1460.077 | G70: =SUM(G64:G69) -> -787.171 | H70: =SUM(H64:H69) -> -768.313 | I70: =SUM(I64:I69) -> -1166.5008 | J70: =SUM(J64:J69) -> -804.47545 | ... M70: =SUM(M64:M69) -> 115.02958 | O70: =SUM(O64:O69) -> -873.073 | P70: =SUM(P64:P69) -> -998.576 | Q70: =SUM(Q64:Q69) -> -213.463 | R70: =SUM(R64:R69) -> 447.346 | S70: =SUM(S64:S69) -> -809.7 | T70: =SUM(T64:T69) -> -218.532 | U70: =SUM(U64:U69) -> 433.855 | V70: =SUM(V64:V69) -> -865.7 | ... AU70: =SUM(AU64:AU69) -> 809.84367 | AW70: =SUM(AW64:AW69) -> -809.179 | AX70: =SUM(AX64:AX69) -> -220.753
B71: FX impact | C71: -30.98 | D71: 9.343 | E71: 9.343 | F71: 6.864 | G71: -0.311 | H71: 0.406 | I71: -14.93 | J71: -4.311 | K71: -5.631 | L71: =2.935 -> 2.935 | M71: =SUM(AR71:AU71) -> -1.54 | O71: -0.265 | P71: =1.093-O71 -> 1.358 | Q71: =6.086-P71-O71 -> 4.993 | R71: =E71-Q71-P71-O71 -> 3.257 | S71: 2.412 | T71: =4.416-S71 -> 2.004 | U71: =5.941-T71-S71 -> 1.525 | V71: =F71-U71-T71-S71 -> 0.923 | W71: -0.602 | X71: =-0.17-W71 -> 0.432 | Y71: =-0.445-X71-W71 -> -0.275 | Z71: =G71-Y71-X71-W71 -> 0.134 | AA71: 0.078 | AB71: =0.541-AA71 -> 0.463 | AC71: =0.208-AB71-AA71 -> -0.333 | AD71: =H71-AC71-AB71-AA71 -> 0.198 | AE71: -3.279 | AF71: =-7.947-AE71 -> -4.668 | AG71: =-8.263-AF71-AE71 -> -0.316 | AH71: =I71-AG71-AF71-AE71 -> -6.667 | AI71: -3.642 | AJ71: =-4-AI71 -> -0.358 | AK71: =-4.313-AJ71-AI71 -> -0.313 | AL71: =J71-AK71-AJ71-AI71 -> 0.002 | AM71: 6.242 | AN71: =-6.545-AM71 -> -12.787 | AO71: =-5.712-AN71-AM71 -> 0.833 | AP71: =K71-AO71-AN71-AM71 -> 0.081 | AQ71: -0.316 | AR71: =0.655-AQ71 -> 0.971 | AS71: =-0.284-AR71-AQ71 -> -0.939 | AT71: =L71-AS71-AR71-AQ71 -> 3.219 | AU71: -4.791 | AW71: 2.412 | AX71: =4.416-AW71 -> 2.004
B72: Balancing figure | C72: =-1226.069-C70 -> 794.421 | D72: =1062.689-D70 -> 891.837 | E72: =-641.874-E70 -> 995.892 | F72: =-672.01-F70 -> 788.067 | G72: =27.874-G70 -> 815.045 | H72: =76.997-H70 -> 845.31 | I72: =-19.067-I70 -> 1147.4338 | J72: =123.731-J70 -> 928.20645 | K72: =-132.491-K70 -> 1230.0544 | L72: =-8.11-L70 -> 993.42928 | M72: =SUM(AR72:AU72) -> 940.49142 | O72: =-629.846-O70 -> 243.227 | P72: =-1418.206-P70-O72-O70 -> 210.216 | Q72: =-1393.736-Q70-P72-P70-O72-O70 -> 237.933 | R72: =E72-Q72-P72-O72 -> 304.516 | S72: =-610.103-S70 -> 199.597 | T72: =-687.806-T70-S72-S70 -> 140.829 | U72: =-8.195-U70-T72-T70-S72-S70 -> 245.756 | V72: =F72-U72-T72-S72 -> 201.885 | W72: =-192.785-W70 -> 158.14 | X72: =94.573-X70-W72-W70 -> 203.573 | Y72: =504.393-Y70-X72-X70-W72-W70 -> 204.584 | Z72: =G72-Y72-X72-W72 -> 248.748 | AA72: =37.613-AA70 -> 191.566 | AB72: =128.328-AB70-AA72-AA70 -> 77.376 | AC72: =143.907-AC70-AB72-AB70-AA72-AA70 -> 384.166 | AD72: =H72-AC72-AB72-AA72 -> 192.202 | AE72: =-112.137-AE70 -> 221.539 | AF72: =-94.08-AF70-AE72-AE70 -> 139.467 | AG72: =-47.475-AG70-AF72-AF70-AE72-AE70 -> 433.475 | AH72: =I72-AG72-AF72-AE72 -> 352.95282 | AI72: =-88.509-AI70 -> 237.922 | AJ72: =240.018-AJ70-AI72-AI70 -> 210.611 | AK72: =-39.639-AK70-AJ72-AJ70-AI72-AI70 -> 215.772 | AL72: =J72-AK72-AJ72-AI72 -> 263.90145 | AM72: =-129.019-AM70 -> 338.37155 | AN72: =77.574-AN70-AM72-AM70 -> 320.302 | AO72: =-285.668-AO70-AN72-AN70-AM72-AM70 -> 235.501 | AP72: =K72-AO72-AN72-AM72 -> 335.87981 | AQ72: =38.47-AQ70 -> 345.19519 | AR72: =-70.154-AR70-AQ72-AQ70+0.01 -> 273.219 | AS72: =145.624-AS70-AR72-AR70-AQ72-AQ70 -> 105.91 | AT72: =L72-AS72-AR72-AQ72 -> 269.10509 | AU72: =1102.101-AU70 -> 292.25733 | AW72: =-610.103-AW70 -> 199.076 | AX72: =-687.806-AX70-AW72-AW70 -> 143.05
B73: Net change in cash | C73: =SUM(C70:C72) -> -1257.049 | D73: =SUM(D70:D72) -> 1072.032 | E73: =SUM(E70:E72) -> -632.531 | F73: =SUM(F70:F72) -> -665.146 | G73: =SUM(G70:G72) -> 27.563 | H73: =SUM(H70:H72) -> 77.403 | I73: =SUM(I70:I72) -> -33.997 | J73: =SUM(J70:J72) -> 119.42 | ... M73: =SUM(M70:M72) -> 1053.981 | O73: =SUM(O70:O72) -> -630.111 | P73: =SUM(P70:P72) -> -787.002 | Q73: =SUM(Q70:Q72) -> 29.463 | R73: =SUM(R70:R72) -> 755.119 | S73: =SUM(S70:S72) -> -607.691 | T73: =SUM(T70:T72) -> -75.699 | U73: =SUM(U70:U72) -> 681.136 | V73: =SUM(V70:V72) -> -662.892 | ... AU73: =SUM(AU70:AU72) -> 1097.31 | AW73: =SUM(AW70:AW72) -> -607.691 | AX73: =SUM(AX70:AX72) -> -75.699
B74: Cash and cash equivalents | C74: =1821.129+C73 -> 564.08 | D74: =+C74+D73 -> 1636.112 | E74: =+D74+E73 -> 1003.581 | F74: =+E74+F73 -> 338.435 | G74: =+F74+G73 -> 365.998 | H74: =+G74+H73+G102 -> 580.913 | I74: =+H74+I73 -> 546.916 | J74: =+I74+J73 -> 666.336 | K74: =+J74+K73 -> 528.214 | L74: =+K74+L73 -> 523.039 | M74: =+AQ74+M73 -> 1620.349 | O74: =D74+O73 -> 1006.001 | P74: =O74+P73 -> 218.999 | Q74: =P74+Q73 -> 248.462 | R74: =Q74+R73 -> 1003.581 | S74: =E74+S73 -> 395.89 | T74: =S74+T73 -> 320.191 | U74: =T74+U73 -> 1001.327 | V74: =U74+V73 -> 338.435 | W74: =F74+W73 -> 145.048 | X74: =W74+X73 -> 432.838 | Y74: =X74+Y73 -> 842.383 | Z74: =Y74+Z73 -> 365.998 | AA74: =Z74+AA73 -> 403.689 | AB74: =AA74+AB73 -> 494.867 | AC74: =AB74+AC73 -> 510.113 | AD74: =AC74+AD73+Z102 -> 580.913 | AE74: =AD74+AE73 -> 465.497 | AF74: =AE74+AF73 -> 478.886 | AG74: =AF74+AG73 -> 525.175 | AH74: =AG74+AH73 -> 546.916 | AI74: =AH74+AI73 -> 454.765 | AJ74: =AI74+AJ73 -> 782.934 | AK74: =AJ74+AK73 -> 502.964 | AL74: =AK74+AL73 -> 666.336 | ... AU74: =AT74+AU73 -> 1620.349 | AW74: =E74+AW73 -> 395.89 | AX74: =AW74+AX73 -> 320.191
B76: check | C76: =C74-(C107-C102) -> 0 | D76: =D74-(D107-D102) -> 0 | E76: =E74-(E107-E102) -> 0 | F76: =F74-(F107-F102) -> 0 | G76: =G74-(G107-G102) -> 0 | H76: =H74-H107 -> 0 | I76: =I74-I107 -> 0 | J76: =J74-J107 -> 0 | K76: =K74-K107 -> 0 | L76: =L74-L107 -> 0 | M76: =M74-M107 -> 2.5011104e-12 | O76: =O74-(O107-O102) -> 0 | P76: =P74-(P107-P102) -> 0 | Q76: =Q74-(Q107-Q102) -> 0 | R76: =R74-(R107-R102) -> 0 | S76: =S74-(S107-S102) -> 0 | T76: =T74-(T107-T102) -> 0 | U76: =U74-(U107-U102) -> 0 | V76: =V74-(V107-V102) -> 0 | ... AC76: =AC74-(AC107-AC102) -> 0 | AD76: =AD74-AD107 -> 0 | AE76: =AE74-AE107 -> 4.5474735e-13 | AF76: =AF74-AF107 -> 4.5474735e-13 | AG76: =AG74-AG107 -> 0 | AH76: =AH74-AH107 -> 0 | AI76: =AI74-AI107 -> 0 | AJ76: =AJ74-AJ107 -> 0 | AK76: =AK74-AK107 -> 0 | ... AU76: =AU74-AU107 -> 0 | AW76: =AW74-(S107-S102) -> 0 | AX76: =AX74-(T107-T102) -> 0
B78: LTM | C78: =+C55 -> 42735 | D78: =+D55 -> 43100 | E78: =+E55 -> 43465 | F78: =+F55 -> 43830 | G78: =+G55 -> 44196 | H78: =+H55 -> 44561 | I78: =+I55 -> 44926 | J78: =+J55 -> 45291 | ... M78: =+M55 -> 46111 | O78: =+O55 -> 43189 | P78: =+P55 -> 43281 | Q78: =+Q55 -> 43373 | R78: =+R55 -> 43464 | S78: =+S55 -> 43554 | T78: =+T55 -> 43646 | U78: =+U55 -> 43738 | V78: =+V55 -> 43829 | ... AD78: =+AD55 -> 44560 | AE78: 44651 | AF78: =+AF55 -> 44742 | AG78: =+AG55 -> 44834 | AH78: =+AH55 -> 44926 | AI78: =+AI55 -> 45015 | AJ78: =+AJ55 -> 45107 | AK78: =+AK55 -> 45199 | AL78: =+AL55 -> 45291 | AM78: =+AM55 -> 45381 | ... AU78: =+AU55 -> 46111 | AW78: =+AW55 -> 43554 | AX78: =+AX55 -> 43646
B79: =+B7 -> Revenue | C79: =+C7 -> 14338.579 | D79: =+D7 -> 13935.532 | E79: =+E7 -> 13557.837 | F79: =+F7 -> 14351.277 | G79: =+G7 -> 15356.948 | H79: =+H7 -> 15849.72 | I79: =+I7 -> 18722.258 | ... M79: =+M7 -> 22457.839 | R79: =+R7+Q7+P7+O7 -> 13557.837 | S79: =+S7+R7+Q7+P7 -> 13679.715 | T79: =+T7+S7+R7+Q7 -> 13772.626 | U79: =+U7+T7+S7+R7 -> 14028.523 | V79: =+V7+U7+T7+S7 -> 14351.277 | W79: =+W7+V7+U7+T7 -> 14589.634 | X79: =+X7+W7+V7+U7 -> 14951.479 | Y79: =+Y7+X7+W7+V7 -> 15241.301 | ... AU79: =+AU7+AT7+AS7+AR7 -> 22457.839 | AW79: =+AW7+R7+Q7+P7 -> 13634.524 | AX79: =+AX7+S7+R7+Q78 -> 53875.691
B80: Operating profit | C80: =C16 -> 2517.779 | D80: =D16 -> 2583.35 | E80: =E16 -> 2521.235 | F80: =F16 -> 2473.208 | G80: =G16 -> 2522.334 | H80: =H16 -> 2014.854 | I80: =I16 -> 2276.332 | J80: =J16 -> 2693.888 | ... M80: =M16 -> 3061.255 | R80: =R16+Q16+P16+O16 -> 2521.235 | S80: =S16+R16+Q16+P16 -> 2516.842 | T80: =T16+S16+R16+Q16 -> 2491.249 | U80: =U16+T16+S16+R16 -> 2472.798 | V80: =V16+U16+T16+S16 -> 2473.208 | W80: =W16+V16+U16+T16 -> 2505.156 | X80: =X16+W16+V16+U16 -> 2525.834 | Y80: =Y16+X16+W16+V16 -> 2520.442 | ... AU80: =AU16+AT16+AS16+AR16 -> 3061.255 | AW80: =AW16+R16+Q16+P16 -> 2522.335 | AX80: =AX16+S16+R16+Q16 -> 2495.21
B81: EBITDA | C81: =C46 -> 4334.64 | D81: =D46 -> 4502.965 | E81: =E46 -> 4661.362 | F81: =F46 -> 4647.683 | G81: =G46 -> 4637.106 | H81: =H46 -> 4152.877 | I81: =I46 -> 4662.013 | J81: =J46 -> 5128.198 | ... M81: =M46 -> 5563.398 | R81: =R46+Q46+P46+O46 -> 4661.362 | S81: =S46+R46+Q46+P46 -> 4648.457 | T81: =T46+S46+R46+Q46 -> 4583.894 | U81: =U46+T46+S46+R46 -> 4553.979 | V81: =V46+U46+T46+S46 -> 4647.683 | W81: =W46+V46+U46+T46 -> 4683.332 | X81: =X46+W46+V46+U46 -> 4719.677 | Y81: =Y46+X46+W46+V46 -> 4694.917 | ... AU81: =AU46+AT46+AS46+AR46 -> 5563.398 | AW81: =AW46+R46+Q46+P46 -> 4653.95 | AX81: =AX46+S46+R46+Q46 -> 4587.855
B82: Adjusted EBITDA | C82: =C51 -> 3716 | D82: =D51 -> 3919.1 | E82: =E51 -> 4023.5 | F82: =F51 -> 4017.9 | G82: =G51 -> 4013.4 | H82: =H51 -> 3492.5 | I82: =I51 -> 3931.6742 | J82: =J51 -> 4502.3845 | ... M82: =M51 -> 4940.7246 | R82: =R51+Q51+P51+O51 -> 4023.5 | S82: =S51+R51+Q51+P51 -> 4034.4 | T82: =T51+S51+R51+Q51 -> 3966.1 | U82: =U51+T51+S51+R51 -> 3953.4 | V82: =V51+U51+T51+S51 -> 4017.9 | W82: =W51+V51+U51+T51 -> 4060.3 | X82: =X51+W51+V51+U51 -> 4093.9 | Y82: =Y51+X51+W51+V51 -> 4098.7 | ... AU82: =AU51+AT51+AS51+AR51 -> 4940.7246 | AW82: =AW51+R51+Q51+P51 -> 4034.4 | AX82: =AX51+S51+R51+Q51 -> 3964.4
B83: Cash interest paid | C83: =-C59 -> 360.596 | D83: =-D59 -> 467.977 | E83: =-E59 -> 420.625 | F83: =-F59 -> 524.609 | G83: =-G59 -> 467.844 | H83: =-H59 -> 342.446 | I83: =-I59 -> 431.81 | J83: =-J59 -> 559.199 | ... M83: =-M59 -> 702.165 | R83: =-R59-Q59-P59-O59 -> 420.625 | S83: =-S59-R59-Q59-P59 -> 420.843 | T83: =-T59-S59-R59-Q59 -> 476.428 | U83: =-U59-T59-S59-R59 -> 495.02 | V83: =-V59-U59-T59-S59 -> 524.609 | W83: =-W59-V59-U59-T59 -> 499.952 | X83: =-X59-W59-V59-U59 -> 499.768 | Y83: =-Y59-X59-W59-V59 -> 486.164 | ... AU83: =-AU59-AT59-AS59-AR59 -> 702.165 | AW83: =-AW59-R59-Q59-P59 -> 420.843 | AX83: =-AX59-S59-R59-Q59 -> 476.428
B84: Net Income | C84: =C22 -> 2150.097 | D84: =D22 -> 2159.963 | E84: =E22 -> 2008.558 | F84: =F22 -> 1801.572 | G84: =G22 -> 1935.556 | H84: =H22 -> 1579.436 | I84: =I22 -> 1778.138 | J84: =J22 -> 2051.529 | ... M84: =M22 -> 2457.584 | R84: =SUM(O22:R22) -> 2008.558 | S84: =SUM(P22:S22) -> 2005.105 | T84: =SUM(Q22:T22) -> 1925.77 | U84: =SUM(R22:U22) -> 1877.247 | V84: =SUM(S22:V22) -> 1801.572 | W84: =SUM(T22:W22) -> 1832.018 | X84: =SUM(U22:X22) -> 1868.101 | Y84: =SUM(V22:Y22) -> 1890.517 | ... AU84: =SUM(AR22:AU22) -> 2457.584 | AW84: =SUM(P22:R22)+AW22 -> 2005.105 | AX84: =SUM(Q22:S22)+AX22 -> 1925.77
B85: Capex | C85: =-C61 -> 4891.944 | D85: =-D61 -> 3233.649 | E85: =-E61 -> 2419.761 | F85: =-F61 -> 1997.452 | G85: =-G61 -> 1243.115 | H85: =-H61 -> 1618.941 | I85: =-I61 -> 1918.529 | J85: =-J61 -> 3299.054 | ... M85: =-M61 -> 4837.647 | R85: =-R61-Q61-P61-O61 -> 2419.761 | S85: =-S61-R61-Q61-P61 -> 2438.124 | T85: =-T61-S61-R61-Q61 -> 2298.318 | U85: =-U61-T61-S61-R61 -> 2169.404 | V85: =-V61-U61-T61-S61 -> 1997.452 | W85: =-W61-V61-U61-T61 -> 1735.185 | X85: =-X61-W61-V61-U61 -> 1652.403 | Y85: =-Y61-X61-W61-V61 -> 1410.766 | ... AU85: =-AU61-AT61-AS61-AR61 -> 4837.647 | AW85: =-AW61-R61-Q61-P61 -> 2438.124 | AX85: =-AX61-S61-R61-Q61 -> 2298.318
B86: Free cash flow | C86: =+C64 -> -1592.57 | D86: =+D64 -> -57.243 | E86: =+E64 -> -115.55 | F86: =+F64 -> 1060.052 | G86: =+G64 -> 1532.077 | H86: =+H64 -> 1831.764 | I86: =+I64 -> 229.64218 | J86: =+J64 -> -328.35045 | ... M86: =+M64 -> -1907.1564 | R86: =+R64+Q64+P64+O64 -> -115.55 | S86: =+S64+R64+Q64+P64 -> 36.193 | T86: =+T64+S64+R64+Q64 -> 238.856 | U86: =+U64+T64+S64+R64 -> 797.142 | V86: =+V64+U64+T64+S64 -> 1060.052 | W86: =+W64+V64+U64+T64 -> 989.408 | X86: =+X64+W64+V64+U64 -> 1446.391 | Y86: =+Y64+X64+W64+V64 -> 1704.484 | ... AU86: =+AU64+AT64+AS64+AR64 -> -1907.1564 | AW86: =+AW64+R64+Q64+P64 -> 36.714 | AX86: =+AX64+S64+R64+Q64 -> 236.635
B88: BALANCE SHEET | C88: =+C78 -> 42735 | D88: =+D78 -> 43100 | E88: =+E78 -> 43465 | F88: =F3 -> 43830 | G88: =G3 -> 44196 | H88: =H3 -> 44561 | I88: =I3 -> 44926 | J88: =J3 -> 45291 | K88: =K3 -> 45657 | L88: =L3 -> 46022 | M88: =+M78 -> 46111 | O88: =O3 -> 43189 | P88: =P3 -> 43281 | Q88: =Q3 -> 43373 | R88: =R3 -> 43464 | S88: =S3 -> 43554 | T88: =T3 -> 43646 | U88: =U3 -> 43738 | V88: =V3 -> 43829 | ... AU88: =AU3 -> 46111
B90: Tangible fixed assets | C90: =21144.593+1271.425 -> 22416.018 | D90: =22401.692+1283.342 -> 23685.034 | E90: =22606.542+547.933+1366.566 -> 24521.041 | F90: =22576.888+461.375+1381.268 -> 24419.531 | G90: =21112.904+470.269+1392.079 -> 22975.252 | H90: =20873.448+464.704+1469.084 -> 22807.236 | I90: =20114.537+498.783+1564.899 -> 22178.219 | J90: =20807.81+473.831+1741.819 -> 23023.46 | K90: =22750.342+504.066+1838.353 -> 25092.761 | L90: =26058.632+1810.686+551.614 -> 28420.932 | M90: =AU90 -> 28924.556 | O90: =22413.54+1296.401 -> 23709.941 | P90: =22467.992+1322.537 -> 23790.529 | Q90: =22477.992+1356.208 -> 23834.2 | R90: =E90 -> 24521.041 | S90: =22712.626+436.244+1369.281 -> 24518.151 | T90: =22739.257+464.696+1357.945 -> 24561.898 | U90: =22668.783+463.194+1363.984 -> 24495.961 | V90: =F90 -> 24419.531 | W90: =22882.735+1386.439 -> 24269.174 | X90: =22672.336+1388.643 -> 24060.979 | Y90: =21814.487+1358.767 -> 23173.254 | Z90: =G90 -> 22975.252 | AA90: =20876.075+461.004+1392.36 -> 22729.439 | AB90: =21112.904+470.269+1392.079 -> 22975.252 | AC90: =20696.092+417.598+1475.861 -> 22589.551 | AD90: =H90 -> 22807.236 | AE90: =20700.515+472.59+1461.352 -> 22634.457 | AF90: =20589.98+477.926+1495.291 -> 22563.197 | AG90: =20451.199+474.98+1530.212 -> 22456.391 | AH90: =I90 -> 22178.219 | AI90: =20028.469+477.591 -> 20506.06 | AJ90: =20158.85+476.035+1538.05 -> 22172.935 | AK90: =20439.359+492.817+1542.98 -> 22475.156 | AL90: =J90 -> 23023.46 | AM90: =21058.725+479.082+1763.533 -> 23301.34 | AN90: =21653.932+459.687+1788.561 -> 23902.18 | AO90: =22093.639+472.176+1800.689 -> 24366.504 | AP90: =K90 -> 25092.761 | AQ90: =23499.685+506.944+1829.56 -> 25836.189 | AR90: =(24139475+489573+1815226)/1000 -> 26444.274 | AS90: =25205.426+492.208+1821.045 -> 27518.679 | AT90: =L90 -> 28420.932 | AU90: =26561.364+547.305+1815.887 -> 28924.556
B91: Inventory | C91: 3002.331 | D91: 3121.903 | E91: 3874.193 | F91: 4198.005 | G91: 4705.364 | H91: 4353.596 | I91: 5237.136 | J91: 6148.189 | K91: 5684.42 | L91: 6005.738 | M91: =AU91 -> 5578.408 | O91: 3157.93 | P91: 3446.312 | Q91: 3812.004 | R91: =E91 -> 3874.193 | S91: 3813.535 | T91: 4093.463 | U91: 4289.11 | V91: =F91 -> 4198.005 | W91: 4050.147 | X91: 4465.001 | Y91: 4757.505 | Z91: =G91 -> 4705.364 | AA91: 4512.653 | AB91: 4705.364 | AC91: 4393.894 | AD91: =H91 -> 4353.596 | AE91: 4360.137 | AF91: 5116.273 | AG91: 5068.353 | AH91: =I91 -> 5237.136 | AI91: 5264.616 | AJ91: 5787.002 | AK91: 6111.967 | AL91: =J91 -> 6148.189 | AM91: 5717.078 | AN91: 5580.143 | AO91: 5631.248 | AP91: =K91 -> 5684.42 | AQ91: 5189.237 | AR91: 5643.379 | AS91: 5680.155 | AT91: =L91 -> 6005.738 | AU91: 5578.408
B92: Trade accounts receivables, net | C92: 1548.684 | D92: 1702.375 | E92: 1913.202 | F92: 1868.895 | G92: 1936.341 | H92: 1991.205 | I92: 2156.142 | J92: 2564.646 | K92: 2421.526 | L92: 2696.342 | M92: =AU92 -> 4068.786 | O92: 2066.595 | P92: 2360.607 | Q92: 2439.655 | R92: =E92 -> 1913.202 | S92: 2188.285 | T92: 2382.126 | U92: 2390.011 | V92: =F92 -> 1868.895 | W92: 2516.041 | X92: 2417.628 | Y92: 2419.424 | Z92: =G92 -> 1936.341 | AA92: 2689.08 | AB92: 1936.341 | AC92: 2404.577 | AD92: =H92 -> 1991.205 | AE92: 2695.234 | AF92: 2636.041 | AG92: =2595.315 -> 2595.315 | AH92: =I92 -> 2156.142 | AI92: 3110.039 | AJ92: 2945.486 | AK92: 3028.042 | AL92: =J92 -> 2564.646 | AM92: 3397.449 | AN92: 3097.404 | AO92: 3185.974 | AP92: =K92 -> 2421.526 | AQ92: 3620.808 | AR92: 3367.729 | AS92: 3786.505 | AT92: =L92 -> 2696.342 | AU92: 4068.786
B93: Trade creditors /payables | C93: 3114.524 | D93: 3227.49 | E93: 2808.042 | F93: 3019.16 | G93: 3014.834 | H93: 3339.496 | I93: 3655.553 | J93: 4245.868 | K93: 4048.921 | L93: 4414.793 | M93: =AU93 -> 5103.942 | O93: 3239.928 | P93: 3400.335 | Q93: 3153.729 | R93: =E93 -> 2808.042 | S93: 2848.628 | T93: 3122.401 | U93: 3108.396 | V93: =F93 -> 3019.16 | W93: 2937.503 | X93: 3358.023 | Y93: 3376.433 | Z93: =G93 -> 3014.834 | AA93: 3379.14 | AB93: 3014.834 | AC93: 3345.944 | AD93: =H93 -> 3339.496 | AE93: 3448.955 | AF93: 3769.778 | AG93: 3669.272 | AH93: =I93 -> 3655.553 | AI93: 4091.629 | AJ93: 4620.178 | AK93: 3991.07 | AL93: =J93 -> 4245.868 | AM93: 4625.699 | AN93: 4728.333 | AO93: 4783.573 | AP93: =K93 -> 4048.921 | AQ93: 4409.953 | AR93: 4771.564 | AS93: 4897.159 | AT93: =L93 -> 4414.793 | AU93: 5103.942
B94: Net working capital | C94: =C91+C92-C93 -> 1436.491 | D94: =D91+D92-D93 -> 1596.788 | E94: =E91+E92-E93 -> 2979.353 | F94: =F91+F92-F93 -> 3047.74 | G94: =G91+G92-G93 -> 3626.871 | H94: =H91+H92-H93 -> 3005.305 | I94: =I91+I92-I93 -> 3737.725 | J94: =J91+J92-J93 -> 4466.967 | ... M94: =M91+M92-M93 -> 4543.252 | O94: =O91+O92-O93 -> 1984.597 | P94: =P91+P92-P93 -> 2406.584 | Q94: =Q91+Q92-Q93 -> 3097.93 | R94: =R91+R92-R93 -> 2979.353 | S94: =S91+S92-S93 -> 3153.192 | T94: =T91+T92-T93 -> 3353.188 | U94: =U91+U92-U93 -> 3570.725 | V94: =V91+V92-V93 -> 3047.74 | ... AU94: =AU91+AU92-AU93 -> 4543.252
B95: % of revenues | C95: =+C94/C79 -> 0.10018364 | D95: =+D94/D79 -> 0.11458393 | E95: =+E94/E79 -> 0.21975135 | F95: =+F94/F79 -> 0.21236716 | G95: =+G94/G79 -> 0.23617134 | H95: =+H94/H79 -> 0.1896125 | I95: =+I94/I79 -> 0.19964072 | J95: =+J94/J79 -> 0.22819073 | ... M95: =+M94/M79 -> 0.20230139 | R95: =+R94/R79 -> 0.21975135 | S95: =+S94/S79 -> 0.23050129 | T95: =+T94/T79 -> 0.24346759 | U95: =+U94/U79 -> 0.25453321 | V95: =+V94/V79 -> 0.21236716 | W95: =+W94/W79 -> 0.24871666 | X95: =+X94/X79 -> 0.23573628 | Y95: =+Y94/Y79 -> 0.24935509 | ... AU95: =+AU94/AU79 -> 0.20230139
B97: Inventory days | C97: =366/(-C9/C91) -> 124.64175 | D97: =365/(-D9/D91) -> 136.43549 | E97: =365/(-E9/E91) -> 171.8043 | F97: =365/(-F9/F91) -> 170.54419 | G97: =366/(-G9/G91) -> 175.34732 | H97: =365/(-H9/H91) -> 147.26564 | I97: =365/(-I9/I91) -> 145.94209 | J97: =365/(-J9/J91) -> 165.9302 | K97: =365/(-K9/K91) -> 144.93515 | L97: =365/(-L9/L91) -> 144.43469 | M97: =365/(-M9/M91) -> 131.59367 | O97: =90/(-O9/O91) -> 143.70369 | P97: =91/(-P9/P91) -> 141.02166 | Q97: =92/(-Q9/Q91) -> 183.53125 | R97: =92/(-R9/R91) -> 168.26481 | S97: =90/(-S9/S91) -> 160.04845 | T97: =91/(-T9/T91) -> 161.9434 | U97: =92/(-U9/U91) -> 185.30153 | V97: =92/(-V9/V91) -> 160.22727 | W97: =91/(-W9/W91) -> 157.55642 | X97: =91/(-X9/X91) -> 159.54829 | Y97: =92/(-Y9/Y91) -> 186.37982 | Z97: =92/(-Z9/Z91) -> 167.32414 | AA97: =90/(-AA9/AA91) -> 168.52867 | AB97: =91/(-AB9/AB91) -> 161.59085 | AC97: =92/(-AC9/AC91) -> 151.62628 | AD97: =92/(-AD9/AD91) -> 130.69191 | AE97: =90/(-AE9/AE91) -> 123.72923 | AF97: =91/(-AF9/AF91) -> 148.23445 | AG97: =92/(-AG9/AG91) -> 142.14353 | AH97: =92/(-AH9/AH91) -> 137.45579 | AI97: =90/(-AI9/AI91) -> 137.38906 | AJ97: =91/(-AJ9/AJ91) -> 163.27848 | AK97: =92/(-AK9/AK91) -> 168.98693 | AL97: =92/(-AL9/AL91) -> 160.56222 | AM97: =90/(-AM9/AM91) -> 137.20329 | AN97: =90/(-AN9/AN91) -> 145.47256 | AO97: =92/(-AO9/AO91) -> 146.38918 | AP97: =92/(-AP9/AP91) -> 146.32653 | AQ97: =90/(-AQ9/AQ91) -> 116.80353 | AR97: =90/(-AR9/AR91) -> 142.06222 | AS97: =92/(-AS9/AS91) -> 137.3301 | AT97: =92/(-AT9/AT91) -> 145.4724 | AU97: =90/(-AU9/AU91) -> 116.9166
B98: Receivable days | C98: =366/(C7/C92) -> 39.530998 | D98: =365/(D7/D92) -> 44.588673 | E98: =365/(E7/E92) -> 51.506647 | F98: =365/(F7/F92) -> 47.532124 | G98: =366/(G7/G92) -> 46.148545 | H98: =365/(H7/H92) -> 45.855058 | I98: =365/(I7/I92) -> 42.035092 | J98: =365/(J7/J92) -> 47.819556 | K98: =365/(K7/K92) -> 42.12953 | L98: =365/(L7/L92) -> 44.603234 | M98: =365/(M7/M92) -> 66.128664 | O98: =90/(O7/O92) -> 57.543859 | P98: =91/(P7/P92) -> 59.225262 | Q98: =92/(Q7/Q92) -> 67.658698 | R98: =92/(R7/R92) -> 52.057085 | S98: =90/(S7/S92) -> 58.71818 | T98: =91/(T7/T92) -> 58.272453 | U98: =92/(U7/U92) -> 61.53518 | V98: =92/(V7/V92) -> 46.420415 | W98: =91/(W7/W92) -> 63.733766 | X98: =91/(X7/X92) -> 53.898225 | Y98: =92/(Y7/Y92) -> 57.619067 | Z98: =92/(Z7/Z92) -> 46.639457 | AA98: =90/(AA7/AA92) -> 66.396782 | AB98: =91/(AB7/AB92) -> 43.990523 | AC98: =92/(AC7/AC92) -> 56.12284 | AD98: =92/(AD7/AD92) -> 43.02873 | AE98: =90/(AE7/AE92) -> 53.863301 | AF98: =91/(AF7/AF92) -> 52.029604 | AG98: =92/(AG7/AG92) -> 50.065616 | AH98: =92/(AH7/AH92) -> 40.991013 | AI98: =90/(AI7/AI92) -> 55.245233 | AJ98: =91/(AJ7/AJ92) -> 55.930657 | AK98: =92/(AK7/AK92) -> 58.074567 | AL98: =92/(AL7/AL92) -> 47.959349 | AM98: =90/(AM7/AM92) -> 56.015849 | AN98: =90/(AN7/AN92) -> 54.080865 | AO98: =92/(AO7/AO92) -> 56.270696 | AP98: =92/(AP7/AP92) -> 43.196855 | AQ98: =90/(AQ7/AQ92) -> 56.505572 | AR98: =90/(AR7/AR92) -> 57.31327 | AS98: =92/(AS7/AS92) -> 62.737911 | AT98: =92/(AT7/AT92) -> 45.459637 | AU98: =90/(AU7/AU92) -> 59.446037
B99: Payable days | C99: =366/(-C9/C93) -> 129.29944 | D99: =365/(-D9/D93) -> 141.04992 | E99: =365/(-E9/E93) -> 124.52495 | F99: =365/(-F9/F93) -> 122.65354 | G99: =366/(-G9/G93) -> 112.34903 | H99: =365/(-H9/H93) -> 112.96248 | I99: =365/(-I9/I93) -> 101.86847 | J99: =365/(-J9/J93) -> 114.58947 | K99: =365/(-K9/K93) -> 103.23498 | L99: =365/(-L9/L93) -> 106.17334 | M99: =365/(-M9/M93) -> 120.4011 | O99: =90/(-O9/O93) -> 147.43506 | P99: =91/(-P9/P93) -> 139.1403 | Q99: =92/(-Q9/Q93) -> 151.8382 | R99: =92/(-R9/R93) -> 121.9595 | S99: =90/(-S9/S93) -> 119.55273 | T99: =91/(-T9/T93) -> 123.52677 | U99: =92/(-U9/U93) -> 134.29139 | V99: =92/(-V9/V93) -> 115.23373 | W99: =91/(-W9/W93) -> 114.273 | X99: =91/(-X9/X93) -> 119.99254 | Y99: =92/(-Y9/Y93) -> 132.275 | Z99: =92/(-Z9/Z93) -> 107.20839 | AA99: =90/(-AA9/AA93) -> 126.19672 | AB99: =91/(-AB9/AB93) -> 103.53494 | AC99: =92/(-AC9/AC93) -> 115.4632 | AD99: =92/(-AD9/AD93) -> 100.24933 | AE99: =90/(-AE9/AE93) -> 97.87228 | AF99: =91/(-AF9/AF93) -> 109.22227 | AG99: =92/(-AG9/AG93) -> 102.90587 | AH99: =92/(-AH9/AH93) -> 95.944986 | AI99: =90/(-AI9/AI93) -> 106.77798 | AJ99: =91/(-AJ9/AJ93) -> 130.3569 | AK99: =92/(-AK9/AK93) -> 110.34724 | AL99: =92/(-AL9/AL93) -> 110.8824 | AM99: =90/(-AM9/AM93) -> 111.01145 | AN99: =90/(-AN9/AN93) -> 123.26614 | AO99: =92/(-AO9/AO93) -> 124.35313 | AP99: =92/(-AP9/AP93) -> 104.22604 | AQ99: =90/(-AQ9/AQ93) -> 99.262779 | AR99: =90/(-AR9/AR93) -> 120.1158 | AS99: =92/(-AS9/AS93) -> 118.39947 | AT99: =92/(-AT9/AT93) -> 106.93616 | AU99: =90/(-AU9/AU93) -> 106.97237
B101: Debt Breakdown
B102: Bank Overdrafts | C102: 165.62 | D102: 255.585 | E102: 179.321 | F102: 219.118 | G102: 137.512 | H102: 78.395 | I102: =87.13 -> 87.13 | J102: 0.844 | K102: 52.598 | L102: 16.893 | M102: =AU102 -> 24.934 | O102: 280.46 | P102: 175.139 | Q102: 156.371 | R102: =E102 -> 179.321 | S102: 215.923 | T102: 197.312 | U102: 180.647 | V102: =F102 -> 219.118 | W102: 230.981 | X102: 158.339 | Y102: 136.512 | Z102: =G102 -> 137.512 | AA102: 128.895 | AB102: 124.045 | AC102: 62.63 | AD102: =H102 -> 78.395 | AE102: 109.427 | AF102: 64.595 | AG102: 67.4 | AH102: =I102 -> 87.13 | AI102: 72.057 | AJ102: 58.578 | AK102: 63.053 | AL102: =J102 -> 0.844 | AM102: 39.286 | AN102: 54.34 | AO102: 69.393 | AP102: =K102 -> 52.598 | AQ102: 67.309 | AR102: 51.825 | AS102: 37.242 | AT102: =L102 -> 16.893 | AU102: 24.934
B103: Loans and Borrowings | C103: =1318.796+10128.343 -> 11447.139 | D103: =2003.403+10543.125 -> 12546.528 | E103: =11651.97+2094.292 -> 13746.262 | F103: =1986.393+10897.327 -> 12883.72 | G103: =1026.013+10088.955 -> 11114.968 | H103: =7072.24+2631.598 -> 9703.838 | I103: =8448.944+1065.089 -> 9514.033 | J103: =8499.169+3528.828 -> 12027.997 | K103: =8900.245+1229.996 -> 10130.241 | L103: =1520.33+10951.81 -> 12472.14 | M103: =AU103 -> 13577.017 | O103: =10828.844+1101.162 -> 11930.006 | P103: =9453.925+2187.052 -> 11640.977 | Q103: =11372.963+2150.107 -> 13523.07 | R103: =E103 -> 13746.262 | S103: =11309.68+1704.225 -> 13013.905 | T103: =10857.672+2487.299 -> 13344.971 | U103: =11200.547+2441.781 -> 13642.328 | V103: =F103 -> 12883.72 | W103: =1158.406+11292.838 -> 12451.244 | X103: =1349.94+11239.869 -> 12589.809 | Y103: =1307.724+11031.188 -> 12338.912 | Z103: =G103 -> 11114.968 | AA103: =979.678+9732.705 -> 10712.383 | AB103: =983.324+10018.5 -> 11001.824 | AC103: =2715.122+7568.302 -> 10283.424 | AD103: =H103 -> 9703.838 | AE103: =2739.143+7176.311 -> 9915.454 | AF103: =2851.249+7866.66 -> 10717.909 | AG103: =1192.786+8863.957 -> 10056.743 | AH103: =I103 -> 9514.033 | AI103: =6134.536+3417.942 -> 9552.478 | AJ103: =3584.896+6530.05 -> 10114.946 | AK103: =8705.458+3531.884 -> 12237.342 | AL103: =J103 -> 12027.997 | AM103: =8716.183+913.391 -> 9629.574 | AN103: =8814.221+1380.905 -> 10195.126 | AO103: =8458.789+1312.676 -> 9771.465 | AP103: =K103 -> 10130.241 | AQ103: =1148.834+9365.82 -> 10514.654 | AR103: =1628.262+9542.717 -> 11170.979 | AS103: =11044.216+1563.421 -> 12607.637 | AT103: =L103 -> 12472.14 | AU103: =1555.181+12021.836 -> 13577.017
B104: Lease Liabilities | E104: =409.703+89.796 -> 499.499 | F104: =335.659+95.75 -> 431.409 | G104: =330.98+94.509 -> 425.489 | H104: =360.434+80.71 -> 441.144 | I104: =391.738+75.092 -> 466.83 | J104: =369.113+81.079 -> 450.192 | K104: =397.701+87.249 -> 484.95 | L104: =107.75+442.476 -> 550.226 | M104: =AU104 -> 536.34 | R104: =E104 -> 499.499 | S104: =302.787+77.767 -> 380.554 | T104: =337.618+76.307 -> 413.925 | U104: =323.864+70.128 -> 393.992 | V104: =F104 -> 431.409 | W104: =336.877+86.897 -> 423.774 | X104: =354.261+89.5 -> 443.761 | Y104: =357.431+96.009 -> 453.44 | Z104: =G104 -> 425.489 | AA104: =328.562+91.783 -> 420.345 | AB104: =314.879+83.526 -> 398.405 | AC104: =316.591+80.881 -> 397.472 | AD104: =H104 -> 441.144 | AE104: =77.757+362.447 -> 440.204 | AF104: =363.738+81.991 -> 445.729 | AG104: =361.068+75.522 -> 436.59 | AH104: =I104 -> 466.83 | AI104: =377.492+66.673 -> 444.165 | AJ104: =376.249+66.765 -> 443.014 | AK104: =383.738+75.248 -> 458.986 | AL104: =J104 -> 450.192 | AM104: =369.403+78.369 -> 447.772 | AN104: =354.271+76.214 -> 430.485 | AO104: =365.55+81.657 -> 447.207 | AP104: =K104 -> 484.95 | AQ104: =388.741+84.501 -> 473.242 | AR104: =83.127+381.151 -> 464.278 | AS104: =88.53+377.657 -> 466.187 | AT104: =L104 -> 550.226 | AU104: =95.07+441.27 -> 536.34
B105: Total Debt | C105: =SUM(C102:C104) -> 11612.759 | D105: =SUM(D102:D104) -> 12802.113 | E105: =SUM(E102:E104) -> 14425.082 | F105: =SUM(F102:F104) -> 13534.247 | G105: =SUM(G102:G104) -> 11677.969 | H105: =SUM(H102:H104) -> 10223.377 | I105: =SUM(I102:I104) -> 10067.993 | J105: =SUM(J102:J104) -> 12479.033 | ... M105: =SUM(M102:M104) -> 14138.291 | O105: =SUM(O102:O103) -> 12210.466 | P105: =SUM(P102:P103) -> 11816.116 | Q105: =SUM(Q102:Q103) -> 13679.441 | R105: =SUM(R102:R103) -> 13925.583 | S105: =SUM(S102:S104) -> 13610.382 | T105: =SUM(T102:T104) -> 13956.208 | U105: =SUM(U102:U104) -> 14216.967 | V105: =SUM(V102:V104) -> 13534.247 | W105: =SUM(W102:W104) -> 13105.999 | X105: =SUM(X102:X104) -> 13191.909 | Y105: =SUM(Y102:Y104) -> 12928.864 | Z105: =SUM(Z102:Z104) -> 11677.969 | ... AU105: =SUM(AU102:AU104) -> 14138.291
B107: Cash and equivalents | C107: 729.7 | D107: 1891.697 | E107: 1182.902 | F107: 557.553 | G107: 503.51 | H107: 580.913 | I107: 546.916 | J107: 666.336 | K107: 528.214 | L107: 523.039 | M107: =AU107 -> 1620.349 | O107: 1286.461 | P107: 394.138 | Q107: 404.833 | R107: =E107 -> 1182.902 | S107: 611.813 | T107: 517.503 | U107: 1181.974 | V107: =F107 -> 557.553 | W107: 376.029 | X107: 591.177 | Y107: 978.895 | Z107: =G107 -> 503.51 | AA107: 532.584 | AB107: 618.912 | AC107: 572.743 | AD107: =H107 -> 580.913 | AE107: 465.497 | AF107: 478.886 | AG107: 525.175 | AH107: =I107 -> 546.916 | AI107: 454.765 | AJ107: 782.934 | AK107: 502.964 | AL107: =J107 -> 666.336 | AM107: 543.559 | AN107: 737.365 | AO107: 374.956 | AP107: =K107 -> 528.214 | AQ107: 566.368 | AR107: 458.725 | AS107: 673.554 | AT107: =L107 -> 523.039 | AU107: 1620.349
B108: Time Deposits | C108: 0 | D108: 0 | E108: 0 | F108: 590.038 | G108: 0 | H108: 0 | I108: 0 | J108: 1925.556 | K108: 0 | L108: 0 | M108: =AU108 -> 0 | O108: 0 | P108: 0 | Q108: 0 | R108: =E108 -> 0 | S108: 0 | T108: 0 | U108: 0 | V108: =F108 -> 590.038 | W108: 0 | X108: 0 | Y108: 0 | Z108: =G108 -> 0 | AA108: 0 | AB108: 0 | AC108: 0 | AD108: =H108 -> 0 | AE108: 0 | AF108: 0 | AG108: 0 | AH108: =I108 -> 0 | AI108: 0 | AJ108: 0 | AK108: 1876.25 | AL108: =J108 -> 1925.556 | AM108: 0 | AN108: 0 | AO108: 0 | AP108: =K108 -> 0 | AQ108: 0 | AR108: 0 | AS108: 0 | AT108: =L108 -> 0 | AU108: 0
B109: Cash & Equivalents (Including time deposits) | C109: =SUM(C107:C108) -> 729.7 | D109: =SUM(D107:D108) -> 1891.697 | E109: =SUM(E107:E108) -> 1182.902 | F109: =SUM(F107:F108) -> 1147.591 | G109: =SUM(G107:G108) -> 503.51 | H109: =SUM(H107:H108) -> 580.913 | I109: =SUM(I107:I108) -> 546.916 | J109: =SUM(J107:J108) -> 2591.892 | ... M109: =SUM(M107:M108) -> 1620.349 | O109: =SUM(O107:O108) -> 1286.461 | P109: =SUM(P107:P108) -> 394.138 | Q109: =SUM(Q107:Q108) -> 404.833 | R109: =SUM(R107:R108) -> 1182.902 | S109: =SUM(S107:S108) -> 611.813 | T109: =SUM(T107:T108) -> 517.503 | U109: =SUM(U107:U108) -> 1181.974 | V109: =SUM(V107:V108) -> 1147.591 | ... AU109: =SUM(AU107:AU108) -> 1620.349
B111: Net debt (including leases) | C111: =C105-C109 -> 10883.059 | D111: =D105-D109 -> 10910.416 | E111: =E105-E109 -> 13242.18 | F111: =F105-F109 -> 12386.656 | G111: =G105-G109 -> 11174.459 | H111: =H105-H109 -> 9642.464 | I111: =I105-I109 -> 9521.077 | J111: =J105-J109 -> 9887.141 | ... M111: =M105-M109 -> 12517.942 | O111: =O105-O109 -> 10924.005 | P111: =P105-P109 -> 11421.978 | Q111: =Q105-Q109 -> 13274.608 | R111: =R105-R109 -> 12742.681 | S111: =S105-S109 -> 12998.569 | T111: =T105-T109 -> 13438.705 | U111: =U105-U109 -> 13034.993 | V111: =V105-V109 -> 12386.656 | ... AU111: =AU105-AU109 -> 12517.942
B112: Gross debt (including leases) | C112: =C105 -> 11612.759 | D112: =D105 -> 12802.113 | E112: =E105 -> 14425.082 | F112: =F105 -> 13534.247 | G112: =G105 -> 11677.969 | H112: =H105 -> 10223.377 | I112: =I105 -> 10067.993 | J112: =J105 -> 12479.033 | ... M112: =M105 -> 14138.291 | O112: =O105 -> 12210.466 | P112: =P105 -> 11816.116 | Q112: =Q105 -> 13679.441 | R112: =E112 -> 14425.082 | S112: =S105 -> 13610.382 | T112: =T105 -> 13956.208 | U112: =U105 -> 14216.967 | V112: =F112 -> 13534.247 | W112: =W105 -> 13105.999 | X112: =X105 -> 13191.909 | Y112: =Y105 -> 12928.864 | Z112: =G112 -> 11677.969 | AA112: =AA105 -> 11261.623 | AB112: =AB105 -> 11524.274 | AC112: =AC105 -> 10743.526 | AD112: =H112 -> 10223.377 | AE112: =AE105 -> 10465.085 | AF112: =AF105 -> 11228.233 | AG112: =AG105 -> 10560.733 | AH112: =I112 -> 10067.993 | AI112: =AI105 -> 10068.7 | AJ112: =AJ105 -> 10616.538 | AK112: =AK105 -> 12759.381 | AL112: =J112 -> 12479.033 | AM112: =AM105 -> 10116.632 | AN112: =AN105 -> 10679.951 | AO112: =AO105 -> 10288.065 | AP112: =K112 -> 10667.789 | AQ112: =AQ105 -> 11055.205 | AR112: =AR105 -> 11687.082 | AS112: =AS105 -> 13111.066 | AT112: =AT105 -> 13039.259 | AU112: =AU105 -> 14138.291
B114: Company Reported Net Debt | C114: 10883 | D114: 10910 | E114: 12743 | F114: 11955 | G114: 10749 | H114: 9201.32 | I114: 9054.247 | J114: 9437 | K114: 9655 | L114: 11965.994 | M114: =AU114 -> 11982 | O114: =O102+O103-O107 -> 10924.005 | P114: =P102+P103-P107 -> 11421.978 | Q114: =Q102+Q103-Q107 -> 13274.608 | R114: =E114 -> 12743 | S114: =S102+S103-S107 -> 12618.015 | T114: =T102+T103-T107 -> 13024.78 | U114: =U102+U103-U107 -> 12641.001 | V114: =F114 -> 11955 | W114: =W102+W103-W107 -> 12306.196 | X114: =X102+X103-X107 -> 12156.971 | Y114: =Y102+Y103-Y107 -> 11496.529 | Z114: =G114 -> 10749 | AA114: =AA102+AA103-AA109 -> 10308.694 | AB114: =AB102+AB103-AB109 -> 10506.957 | AC114: =AC102+AC103-AC109 -> 9773.311 | AD114: =H114 -> 9201.32 | AE114: =AE102+AE103-AE109 -> 9559.384 | AF114: =AF102+AF103-AF109 -> 10303.618 | AG114: =AG102+AG103-AG109 -> 9598.968 | AH114: =I114 -> 9054.247 | AI114: =AI102+AI103-AI109 -> 9169.77 | AJ114: =AJ102+AJ103-AJ109 -> 9390.59 | AK114: =AK102+AK103-AK109 -> 9921.181 | AL114: =J114 -> 9437 | AM114: =AM102+AM103-AM109 -> 9125.301 | AN114: =AN102+AN103-AN109 -> 9512.101 | AO114: =AO102+AO103-AO109 -> 9465.902 | AP114: =K114 -> 9655 | AQ114: =AQ102+AQ103-AQ109 -> 10015.595 | AR114: =AR102+AR103-AR109 -> 10764.079 | AS114: 11971 | AT114: =L114 -> 11965.994 | AU114: 11982
B116: Equity (as reported on balance sheet) | C116: 13478.469 | D116: 14881.24 | E116: 14462.644 | F116: 15259.12 | G116: 16233.679 | H116: 16618.413 | I116: 16982.865 | J116: 17808.825 | K116: 18791.132 | L116: 20527.236 | M116: =AU116 -> 21117.81 | O116: 15295.625 | P116: 15101.39 | Q116: 13959.542 | R116: =E116 -> 14462.644 | S116: 14876.287 | T116: 14639.371 | U116: 15202.181 | V116: =F116 -> 15259.12 | W116: 15321.488 | X116: 15160.884 | Y116: 15886.263 | Z116: =G116 -> 16233.679 | AA116: 16621.091 | AB116: 15973.58 | AC116: 16366.518 | AD116: =H116 -> 16618.413 | AE116: 16695.308 | AF116: 16205.228 | AG116: 16641.819 | AH116: =I116 -> 16982.865 | AI116: 17251.499 | AJ116: 16830.807 | AK116: 17505.707 | AL116: =J116 -> 17808.825 | AM116: 18349.401 | AN116: 17958.767 | AO116: 17958.767 | AP116: =K116 -> 18791.132 | AQ116: 19703.783 | AR116: 19364.248 | AS116: 20043.786 | AT116: =L116 -> 20527.236 | AU116: 21117.81
B117: Total debt + Equity | C117: =C112+C116 -> 25091.228 | D117: =D112+D116 -> 27683.353 | E117: =E112+E116 -> 28887.726 | F117: =F112+F116 -> 28793.367 | G117: =G112+G116 -> 27911.648 | H117: =H112+H116 -> 26841.79 | I117: =I112+I116 -> 27050.858 | J117: =J112+J116 -> 30287.858 | ... M117: =M112+M116 -> 35256.101 | O117: =O112+O116 -> 27506.091 | P117: =P112+P116 -> 26917.506 | Q117: =Q112+Q116 -> 27638.983 | R117: =R112+R116 -> 28887.726 | S117: =S112+S116 -> 28486.669 | T117: =T112+T116 -> 28595.579 | U117: =U112+U116 -> 29419.148 | V117: =V112+V116 -> 28793.367 | ... AU117: =AU112+AU116 -> 35256.101
B119: CREDIT RATIOS | C119: =+C88 -> 42735 | D119: =+D88 -> 43100 | E119: =+E88 -> 43465 | F119: =+F88 -> 43830 | G119: =+G88 -> 44196 | H119: =+H88 -> 44561 | I119: =+I88 -> 44926 | J119: =+J88 -> 45291 | ... M119: =+M88 -> 46111 | O119: =+O88 -> 43189 | P119: =+P88 -> 43281 | Q119: =+Q88 -> 43373 | R119: =+R88 -> 43464 | S119: =+S88 -> 43554 | T119: =+T88 -> 43646 | U119: =+U88 -> 43738 | V119: =+V88 -> 43829 | ... AU119: =+AU88 -> 46111
...

Sheet KPIs
B2: ALMARAI | C2: Annual | D2: Annual | E2: Annual | F2: Annual | G2: Annual | H2: Annual | I2: Annual | J2: Annual | K2: Annual | L2: Annual | M2: LTM | O2: Quarterly | P2: Quarterly | Q2: Quarterly | R2: Quarterly | S2: Quarterly | T2: Quarterly | U2: Quarterly | V2: Quarterly | W2: Quarterly | X2: Quarterly | Y2: Quarterly | Z2: Quarterly | AA2: Quarterly | AB2: Quarterly | AC2: Quarterly | AD2: Quarterly | AE2: Quarterly | AF2: Quarterly | AG2: Quarterly | AH2: QuarterIy | AI2: Quarterly | AJ2: Quarterly | AK2: Quarterly | AL2: QuarterIy | AM2: Quarterly | AN2: Quarterly | AO2: Quarterly | AP2: QuarterIy | AQ2: Quarterly | AR2: Quarterly | AS2: Quarterly | AT2: QuarterIy | AU2: Quarterly | AW2: Quarterly | AX2: Quarterly
B3: (SAR millions) | C3: 42735 | D3: 43100 | E3: 43465 | F3: 43830 | G3: 44196 | H3: 44561 | I3: 44926 | J3: 45291 | K3: 45657 | L3: 46022 | M3: =AU3 -> 46111 | O3: 43189 | P3: 43281 | Q3: 43373 | R3: 43464 | S3: 43554 | T3: 43646 | U3: 43738 | V3: 43829 | W3: 43920 | X3: 44012 | Y3: 44104 | Z3: 44195 | AA3: 44285 | AB3: 44377 | AC3: 44469 | AD3: 44560 | AE3: 44650 | AF3: 44742 | AG3: 44834 | AH3: 44926 | AI3: 45015 | AJ3: 45107 | AK3: 45199 | AL3: 45291 | AM3: 45381 | AN3: 45473 | AO3: 45565 | AP3: 45657 | AQ3: 45746 | AR3: 45838 | AS3: 45930 | AT3: 46022 | AU3: 46111 | AW3: 43554 | AX3: 43646
C4: Act | D4: Act | E4: Act | F4: Act | G4: Act | H4: Act | I4: Act | J4: Act | K4: Act | L4: Act | M4: Act | O4: Act | P4: Act | Q4: Act | R4: Act | S4: Act | T4: Act | U4: Act | V4: Act | W4: Act | X4: Act | Y4: Act | Z4: Act | AA4: Act | AB4: Act | AC4: Act | AD4: Act | AE4: Act | AF4: Act | AG4: Act | AH4: Act | AI4: Act | AJ4: Act | AK4: Act | AL4: Act | AM4: Act | AN4: Act | AO4: Act | AP4: Act | AQ4: Act | AR4: Act | AS4: Act | AT4: Act | AU4: Act | AW4: Restated | AX4: Act
C5: FY | D5: FY | E5: FY | F5: FY | G5: FY | H5: FY | I5: FY | J5: FY | K5: FY | L5: FY | M5: LTM | O5: Q1 | P5: Q2 | Q5: Q3 | R5: Q4 | S5: Q1 | T5: Q2 | U5: Q3 | V5: Q4 | W5: Q1 | X5: Q2 | Y5: Q3 | Z5: Q4 | AA5: Q1 | AB5: Q2 | AC5: Q3 | AD5: Q4 | AE5: Q1 | AF5: Q2 | AG5: Q3 | AH5: Q4 | AI5: Q1 | AJ5: Q2 | AK5: Q3 | AL5: Q4 | AM5: Q1 | AN5: Q2 | AO5: Q3 | AP5: Q4 | AQ5: Q1 | AR5: Q2 | AS5: Q3 | AT5: Q4 | AU5: Q1 | AW5: Q1 | AX5: Q2
B7: Revenue by Business Segments
B8: Dairy and Juice | C8: 10961.324 | D8: 10510.471 | E8: 9919.665 | F8: 10209.987 | G8: 10923.68 | H8: 11141.325 | I8: 12504.123 | J8: 12902.558 | K8: 14007.348 | L8: 14632.844 | M8: =SUM(AR8:AU8) -> 14793.022 | O8: 2356.948 | P8: =5109.44-O8 -> 2752.492 | Q8: =7514.694-P8-O8 -> 2405.254 | R8: =E8-Q8-P8-O8 -> 2404.971 | S8: 2366.404 | T8: =5116.547-S8 -> 2750.143 | U8: =7669.403-T8-S8 -> 2552.856 | V8: =F8-U8-T8-S8 -> 2540.584 | W8: 2520.118 | X8: =5486.358-W8 -> 2966.24 | Y8: =8256.707-X8-W8 -> 2770.349 | Z8: =G8-Y8-X8-W8 -> 2666.973 | AA8: 2581.482 | AB8: =5477.111-AA8 -> 2895.629 | AC8: =8197.756-AB8-AA8 -> 2720.645 | AD8: =H8-AC8-AB8-AA8 -> 2943.569 | AE8: 3116.247 | AF8: =6252.251-AE8 -> 3136.004 | AG8: =9390.973-AF8-AE8 -> 3138.722 | AH8: =I8-AG8-AF8-AE8 -> 3113.15 | AI8: 3448.786 | AJ8: =6627.534-AI8 -> 3178.748 | AK8: =9772.245-AJ8-AI8 -> 3144.711 | AL8: =J8-AK8-AJ8-AI8 -> 3130.313 | AM8: 3792.198 | AN8: =7211.721-AM8 -> 3419.523 | AO8: =10696.12-AN8-AM8 -> 3484.399 | AP8: =K8-AO8-AN8-AM8 -> 3311.228 | AQ8: 4018.412 | AR8: =7533.771-AQ8 -> 3515.359 | AS8: =11189.163-AR8-AQ8 -> 3655.392 | AT8: =L8-AS8-AR8-AQ8 -> 3443.681 | AU8: 4178.59 | AW8: 2333.971 | AX8: 2783
B9: Bakery | C9: 1880.789 | D9: 1807.09 | E9: 1641.393 | F9: 1749.297 | G9: 1711.952 | H9: 1788.862 | I9: 2439.3 | J9: 2584.458 | K9: 2661.579 | L9: 2789.339 | M9: =SUM(AR9:AU9) -> 2818.396 | O9: 405.466 | P9: =782.901-O9 -> 377.435 | Q9: =1194.499-P9-O9 -> 411.598 | R9: =E9-Q9-P9-O9 -> 446.894 | S9: 430.019 | T9: =815.67-S9 -> 385.651 | U9: =1270.167-T9-S9 -> 454.497 | V9: =F9-U9-T9-S9 -> 479.13 | W9: 432.81 | X9: =857.026-W9 -> 424.216 | Y9: =1276.232-X9-W9 -> 419.206 | Z9: =G9-Y9-X9-W9 -> 435.72 | AA9: 391.085 | AB9: =792.002-AA9 -> 400.917 | AC9: =1259.39-AB9-AA9 -> 467.388 | AD9: =H9-AC9-AB9-AA9 -> 529.472 | AE9: 571.275 | AF9: =1138.796-AE9 -> 567.521 | AG9: =1754.7-AF9-AE9 -> 615.904 | AH9: =I9-AG9-AF9-AE9 -> 684.6 | AI9: 622.058 | AJ9: =1243.047-AI9 -> 620.989 | AK9: =1883.825-AJ9-AI9 -> 640.778 | AL9: =J9-AK9-AJ9-AI9 -> 700.633 | AM9: 624.382 | AN9: =1270.256-AM9 -> 645.874 | AO9: =1932.139-AN9-AM9 -> 661.883 | AP9: =K9-AO9-AN9-AM9 -> 729.44 | AQ9: 632.628 | AR9: =1327.445-AQ9 -> 694.817 | AS9: =2029.927-AR9-AQ9 -> 702.482 | AT9: =L9-AS9-AR9-AQ9 -> 759.412 | AU9: 661.685 | AW9: 421.073 | AX9: 395
B10: Poultry | C10: 1331.506 | D10: 1463.626 | E10: 1800.35 | F10: 2124.593 | G10: 2292.779 | H10: 2301.459 | I10: 3013.435 | J10: 3518.336 | K10: 3794.209 | L10: 3927.229 | M10: =SUM(AR10:AU10) -> 4048.118 | O10: 420.639 | P10: =855.297-O10 -> 434.658 | Q10: =1308.663-P10-O10 -> 453.366 | R10: =E10-Q10-P10-O10 -> 491.687 | S10: 502.267 | T10: =1026.643-S10 -> 524.376 | U10: =1515.605-T10-S10 -> 488.962 | V10: =F10-U10-T10-S10 -> 608.988 | W10: 558.388 | X10: =1173.006-W10 -> 614.618 | Y10: =1697.756-X10-W10 -> 524.75 | Z10: =G10-Y10-X10-W10 -> 595.023 | AA10: 551.842 | AB10: =1118.023-AA10 -> 566.181 | AC10: =1659.646-AB10-AA10 -> 541.623 | AD10: =H10-AC10-AB10-AA10 -> 641.813 | AE10: 659.468 | AF10: =1395.813-AE10 -> 736.345 | AG10: =2171.597-AE10-AF10 -> 775.784 | AH10: =I10-AG10-AF10-AE10 -> 841.838 | AI10: 848.032 | AJ10: =1697.441-AI10 -> 849.409 | AK10: =2573.457-AI10-AJ10 -> 876.016 | AL10: =J10-AK10-AJ10-AI10 -> 944.879 | AM10: 921.283 | AN10: =1890.687-AM10 -> 969.404 | AO10: =2819.222-AM10-AN10 -> 928.535 | AP10: =K10-AO10-AN10-AM10 -> 974.987 | AQ10: 979.975 | AR10: =1949.988-AQ10 -> 970.013 | AS10: =2905.302-AQ10-AR10 -> 955.314 | AT10: =L10-AS10-AR10-AQ10 -> 1021.927 | AU10: 1100.864 | AW10: 499.501 | AX10: 527
B11: Other Activities | C11: 164.96 | D11: 154.345 | E11: 196.429 | F11: 267.4 | G11: 428.537 | H11: 618.074 | I11: 765.4 | J11: 570.233 | K11: 516.376 | L11: 715.464 | M11: =SUM(AR11:AU11) -> 798.303 | O11: 49.152 | P11: =111.655-O11 -> 62.503 | Q11: =158.797-P11-O11 -> 47.142 | R11: =E11-Q11-P11-O11 -> 37.632 | S11: 55.393 | T11: =115.222-S11 -> 59.829 | U11: =192.164-T11-S11 -> 76.942 | V11: =F11-U11-T11-S11 -> 75.236 | W11: 81.124 | X11: =157.894-W11 -> 76.77 | Y11: =306.668-X11-W11 -> 148.774 | Z11: =G11-Y11-X11-W11 -> 121.869 | AA11: 120.605 | AB11: =263.446-AA11 -> 142.841 | AC11: =475.52-AB11-AA11 -> 212.074 | AD11: =H11-AC11-AB11-AA11 -> 142.554 | AE11: 156.467 | AF11: =327.044-AE11 -> 170.577 | AG11: =565.755-AE11-AF11 -> 238.711 | AH11: =I11-AG11-AF11-AE11 -> 199.645 | AI11: 147.688 | AJ11: =290.891-AI11 -> 143.203 | AK11: =426.32-AI11-AJ11 -> 135.429 | AL11: =J11-AK11-AJ11-AI11 -> 143.913 | AM11: 120.778 | AN11: =240.598-AM11 -> 119.82 | AO11: =374.702-AM11-AN11 -> 134.104 | AP11: =K11-AO11-AN11-AM11 -> 141.674 | AQ11: 136.075 | AR11: =244.288-AQ11 -> 108.213 | AS11: =483.699-AQ11-AR11 -> 239.411 | AT11: =L11-AS11-AR11-AQ11 -> 231.765 | AU11: 218.914 | AW11: 54.347 | AX11: 61
B12: Total | C12: =SUM(C8:C11) -> 14338.579 | D12: =SUM(D8:D11) -> 13935.532 | E12: =SUM(E8:E11) -> 13557.837 | F12: =SUM(F8:F11) -> 14351.277 | G12: =SUM(G8:G11) -> 15356.948 | H12: =SUM(H8:H11) -> 15849.72 | I12: =SUM(I8:I11) -> 18722.258 | J12: =SUM(J8:J11) -> 19575.585 | ... M12: =SUM(M8:M11) -> 22457.839 | O12: =SUM(O8:O11) -> 3232.205 | P12: =SUM(P8:P11) -> 3627.088 | Q12: =SUM(Q8:Q11) -> 3317.36 | R12: =SUM(R8:R11) -> 3381.184 | S12: =SUM(S8:S11) -> 3354.083 | T12: =SUM(T8:T11) -> 3719.999 | U12: =SUM(U8:U11) -> 3573.257 | V12: =SUM(V8:V11) -> 3703.938 | ... AU12: =SUM(AU8:AU11) -> 6160.053 | AW12: =SUM(AW8:AW11) -> 3308.892 | AX12: =SUM(AX8:AX11) -> 3766
B13: check | C13: =C12-Model!C7 -> 0 | D13: =D12-Model!D7 -> 0 | E13: =E12-Model!E7 -> 0 | F13: =F12-Model!F7 -> 0 | G13: =G12-Model!G7 -> 0 | H13: =H12-Model!H7 -> 0 | I13: =I12-Model!I7 -> 0 | J13: =J12-Model!J7 -> 0 | ... M13: =M12-Model!M7 -> 0 | O13: =O12-Model!O7 -> 0 | P13: =P12-Model!P7 -> 0 | Q13: =Q12-Model!Q7 -> 0 | R13: =R12-Model!R7 -> 0 | S13: =S12-Model!S7 -> 0 | T13: =T12-Model!T7 -> 0 | U13: =U12-Model!U7 -> 0 | V13: =V12-Model!V7 -> 0 | ... AU13: =AU12-Model!AU7 -> 0 | AW13: =AW12-Model!AW7 -> 0 | AX13: =AX12-Model!AX7 -> -1.424
B15: Revenue Composition (%)
B16: Dairy and Juice | C16: =C8/C$12 -> 0.76446376 | D16: =D8/D$12 -> 0.75422101 | E16: =E8/E$12 -> 0.73165543 | F16: =F8/F$12 -> 0.71143404 | G16: =G8/G$12 -> 0.71131842 | H16: =H8/H$12 -> 0.70293513 | I16: =I8/I$12 -> 0.66787473 | J16: =J8/J$12 -> 0.65911481 | ... M16: =M8/M$12 -> 0.65870193 | O16: =O8/O$12 -> 0.72920746 | P16: =P8/P$12 -> 0.75887103 | Q16: =Q8/Q$12 -> 0.72505064 | R16: =R8/R$12 -> 0.71128072 | S16: =S8/S$12 -> 0.70552935 | T16: =T8/T$12 -> 0.73928595 | U16: =U8/U$12 -> 0.71443392 | V16: =V8/V$12 -> 0.68591429 | ... AU16: =AU8/AU$12 -> 0.6783367 | AW16: =AW8/AW$12 -> 0.70536331 | AX16: =AX8/AX$12 -> 0.73898035
B17: Bakery | C17: =C9/C$12 -> 0.13116983 | D17: =D9/D$12 -> 0.12967499 | E17: =E9/E$12 -> 0.12106599 | F17: =F9/F$12 -> 0.12189138 | G17: =G9/G$12 -> 0.11147736 | H17: =H9/H$12 -> 0.11286395 | I17: =I9/I$12 -> 0.13028877 | J17: =J9/J$12 -> 0.13202456 | ... M17: =M9/M$12 -> 0.1254972 | O17: =O9/O$12 -> 0.12544563 | P17: =P9/P$12 -> 0.10406006 | Q17: =Q9/Q$12 -> 0.12407396 | R17: =R9/R$12 -> 0.13217086 | S17: =S9/S$12 -> 0.12820762 | T17: =T9/T$12 -> 0.10366965 | U17: =U9/U$12 -> 0.12719404 | V17: =V9/V$12 -> 0.12935692 | ... AU17: =AU9/AU$12 -> 0.10741547 | AW17: =AW9/AW$12 -> 0.12725498 | AX17: =AX9/AX$12 -> 0.10488582
B18: Poultry | C18: =C10/C$12 -> 0.092861782 | D18: =D10/D$12 -> 0.10502835 | E18: =E10/E$12 -> 0.13279036 | F18: =F10/F$12 -> 0.14804209 | G18: =G10/G$12 -> 0.14929913 | H18: =H10/H$12 -> 0.14520503 | I18: =I10/I$12 -> 0.16095468 | J18: =J10/J$12 -> 0.17973082 | ... M18: =M10/M$12 -> 0.18025412 | O18: =O10/O$12 -> 0.13013995 | P18: =P10/P$12 -> 0.11983663 | Q18: =Q10/Q$12 -> 0.1366647 | R18: =R10/R$12 -> 0.14541859 | S18: =S10/S$12 -> 0.14974793 | T18: =T10/T$12 -> 0.14096133 | U18: =U10/U$12 -> 0.1368393 | V18: =V10/V$12 -> 0.16441636 | ... AU18: =AU10/AU$12 -> 0.17871015 | AW18: =AW10/AW$12 -> 0.15095718 | AX18: =AX10/AX$12 -> 0.13993627
B19: Other Activities | C19: =C11/C$12 -> 0.011504627 | D19: =D11/D$12 -> 0.011075645 | E19: =E11/E$12 -> 0.014488226 | F19: =F11/F$12 -> 0.018632488 | G19: =G11/G$12 -> 0.027905089 | H19: =H11/H$12 -> 0.038995894 | I19: =I11/I$12 -> 0.040881821 | J19: =J11/J$12 -> 0.029129806 | ... M19: =M11/M$12 -> 0.035546742 | O19: =O11/O$12 -> 0.015206956 | P19: =P11/P$12 -> 0.017232281 | Q19: =Q11/Q$12 -> 0.014210698 | R19: =R11/R$12 -> 0.011129829 | S19: =S11/S$12 -> 0.016515095 | T19: =T11/T$12 -> 0.016083069 | U19: =U11/U$12 -> 0.021532736 | V19: =V11/V$12 -> 0.020312435 | ... AU19: =AU11/AU$12 -> 0.035537681 | AW19: =AW11/AW$12 -> 0.016424531 | AX19: =AX11/AX$12 -> 0.016197557
B20: Total | C20: =SUM(C16:C19) -> 1 | D20: =SUM(D16:D19) -> 1 | E20: =SUM(E16:E19) -> 1 | F20: =SUM(F16:F19) -> 1 | G20: =SUM(G16:G19) -> 1 | H20: =SUM(H16:H19) -> 1 | I20: =SUM(I16:I19) -> 1 | J20: =SUM(J16:J19) -> 1 | ... M20: =SUM(M16:M19) -> 1 | O20: =SUM(O16:O19) -> 1 | P20: =SUM(P16:P19) -> 1 | Q20: =SUM(Q16:Q19) -> 1 | R20: =SUM(R16:R19) -> 1 | S20: =SUM(S16:S19) -> 1 | T20: =SUM(T16:T19) -> 1 | U20: =SUM(U16:U19) -> 1 | V20: =SUM(V16:V19) -> 1 | ... AU20: =SUM(AU16:AU19) -> 1 | AW20: =SUM(AW16:AW19) -> 1 | AX20: =SUM(AX16:AX19) -> 1
B22: y-o-y growth in Revenue
B23: Dairy and Juice | D23: =D8/C8-1 -> -0.041131254 | E23: =E8/D8-1 -> -0.056211182 | F23: =F8/E8-1 -> 0.029267319 | G23: =G8/F8-1 -> 0.06990146 | H23: =H8/G8-1 -> 0.019924146 | I23: =I8/H8-1 -> 0.1223192 | J23: =J8/I8-1 -> 0.03186429 | K23: =K8/J8-1 -> 0.085625657 | L23: =L8/K8-1 -> 0.044654848 | S23: =S8/O8-1 -> 0.004011968 | T23: =T8/P8-1 -> -0.00085340847 | U23: =U8/Q8-1 -> 0.061366492 | V23: =V8/R8-1 -> 0.056388622 | W23: =W8/S8-1 -> 0.064956787 | X23: =X8/T8-1 -> 0.078576641 | Y23: =Y8/U8-1 -> 0.085195953 | Z23: =Z8/V8-1 -> 0.049748011 | ... AD23: =AD8/Z8-1 -> 0.10371159 | AE23: =$AE8/$AA8-1 -> 0.20715426 | AF23: =AF8/AB8-1 -> 0.083013052 | AG23: =AG8/AC8-1 -> 0.15366834 | AH23: =AH8/AD8-1 -> 0.057610676 | AI23: =AI8/AE8-1 -> 0.10671137 | AJ23: =AJ8/AF8-1 -> 0.013630085 | AK23: =AK8/AG8-1 -> 0.0019081015 | AL23: =AL8/AH8-1 -> 0.0055130655 | AM23: =AM8/AI8-1 -> 0.099574749 | ... AU23: =AU8/AQ8-1 -> 0.03986102 | AW23: =AW8/O8-1 -> -0.0097486241 | AX23: =AX8/P8-1 -> 0.011083774
B24: Bakery | D24: =D9/C9-1 -> -0.03918515 | E24: =E9/D9-1 -> -0.091692721 | F24: =F9/E9-1 -> 0.065739284 | G24: =G9/F9-1 -> -0.021348576 | H24: =H9/G9-1 -> 0.044925325 | I24: =I9/H9-1 -> 0.36360435 | J24: =J9/I9-1 -> 0.059508056 | K24: =K9/J9-1 -> 0.029840299 | L24: =L9/K9-1 -> 0.048001581 | S24: =S9/O9-1 -> 0.060555016 | T24: =T9/P9-1 -> 0.021767987 | U24: =U9/Q9-1 -> 0.10422548 | V24: =V9/R9-1 -> 0.072133437 | W24: =W9/S9-1 -> 0.0064904109 | X24: =X9/T9-1 -> 0.099999741 | Y24: =Y9/U9-1 -> -0.077648477 | Z24: =Z9/V9-1 -> -0.090601716 | ... AD24: =AD9/Z9-1 -> 0.2151657 | AE24: =$AE9/$AA9-1 -> 0.46074383 | AF24: =AF9/AB9-1 -> 0.41555733 | AG24: =AG9/AC9-1 -> 0.31775741 | AH24: =AH9/AD9-1 -> 0.29298622 | AI24: =AI9/AE9-1 -> 0.08889414 | AJ24: =AJ9/AF9-1 -> 0.094213254 | AK24: =AK9/AG9-1 -> 0.040386164 | AL24: =AL9/AH9-1 -> 0.023419515 | AM24: =AM9/AI9-1 -> 0.003735986 | ... AU24: =AU9/AQ9-1 -> 0.045930626 | AW24: =AW9/O9-1 -> 0.038491513 | AX24: =AX9/P9-1 -> 0.046537814
B25: Poultry | D25: =D10/C10-1 -> 0.099225989 | E25: =E10/D10-1 -> 0.2300615 | F25: =F10/E10-1 -> 0.18009998 | G25: =G10/F10-1 -> 0.079161515 | H25: =H10/G10-1 -> 0.0037857988 | I25: =I10/H10-1 -> 0.30935854 | J25: =J10/I10-1 -> 0.16754999 | K25: =K10/J10-1 -> 0.078410078 | L25: =L10/K10-1 -> 0.035058691 | S25: =S10/O10-1 -> 0.19405714 | T25: =T10/P10-1 -> 0.20641056 | U25: =U10/Q10-1 -> 0.078514931 | V25: =V10/R10-1 -> 0.23856844 | W25: =W10/S10-1 -> 0.11173539 | X25: =X10/T10-1 -> 0.17209407 | Y25: =Y10/U10-1 -> 0.073191782 | Z25: =Z10/V10-1 -> -0.022931486 | ... AD25: =AD10/Z10-1 -> 0.078635616 | AE25: =$AE10/$AA10-1 -> 0.19503046 | AF25: =AF10/AB10-1 -> 0.300547 | AG25: =AG10/AC10-1 -> 0.43233208 | AH25: =AH10/AD10-1 -> 0.3116562 | AI25: =AI10/AE10-1 -> 0.28593351 | AJ25: =AJ10/AF10-1 -> 0.15354759 | AK25: =AK10/AG10-1 -> 0.12920091 | AL25: =AL10/AH10-1 -> 0.12240003 | AM25: =AM10/AI10-1 -> 0.086377637 | ... AU25: =AU10/AQ10-1 -> 0.12335927 | AW25: =AW10/O10-1 -> 0.18748143 | AX25: =AX10/P10-1 -> 0.21244749
B26: Other Activities | D26: =D11/C11-1 -> -0.064348933 | E26: =E11/D11-1 -> 0.27266189 | F26: =F11/E11-1 -> 0.36130612 | G26: =G11/F11-1 -> 0.60260658 | H26: =H11/G11-1 -> 0.44228853 | I26: =I11/H11-1 -> 0.23836304 | J26: =J11/I11-1 -> -0.25498693 | K26: =K11/J11-1 -> -0.094447357 | L26: =L11/K11-1 -> 0.38554852 | S26: =S11/O11-1 -> 0.12697347 | T26: =T11/P11-1 -> -0.042781946 | U26: =U11/Q11-1 -> 0.63213271 | V26: =V11/R11-1 -> 0.99925595 | W26: =W11/S11-1 -> 0.46451718 | X26: =X11/T11-1 -> 0.283157 | Y26: =Y11/U11-1 -> 0.93358634 | Z26: =Z11/V11-1 -> 0.61982296 | ... AD26: =AD11/Z11-1 -> 0.16973143 | AE26: =$AE11/$AA11-1 -> 0.29735086 | AF26: =AF11/AB11-1 -> 0.19417394 | AG26: =AG11/AC11-1 -> 0.12560238 | AH26: =AH11/AD11-1 -> 0.40048683 | AI26: =AI11/AE11-1 -> -0.056107678 | AJ26: =AJ11/AF11-1 -> -0.16047885 | AK26: =AK11/AG11-1 -> -0.43266544 | AL26: =AL11/AH11-1 -> -0.2791555 | AM26: =AM11/AI11-1 -> -0.18220844 | ... AU26: =AU11/AQ11-1 -> 0.60877457 | AW26: =AW11/O11-1 -> 0.10569255 | AX26: =AX11/P11-1 -> -0.024046846
B27: Total | D27: =D12/C12-1 -> -0.028109271 | E27: =E12/D12-1 -> -0.02710302 | F27: =F12/E12-1 -> 0.058522609 | G27: =G12/F12-1 -> 0.070075367 | H27: =H12/G12-1 -> 0.032087886 | I27: =I12/H12-1 -> 0.18123588 | J27: =J12/I12-1 -> 0.04557821 | K27: =K12/J12-1 -> 0.071718265 | L27: =L12/K12-1 -> 0.051734473 | S27: =S12/O12-1 -> 0.037707386 | T27: =T12/P12-1 -> 0.025615866 | U27: =U12/Q12-1 -> 0.077138749 | V27: =V12/R12-1 -> 0.095455911 | W27: =W12/S12-1 -> 0.071064729 | X27: =X12/T12-1 -> 0.097270187 | Y27: =Y12/U12-1 -> 0.081108636 | Z27: =Z12/V12-1 -> 0.031222715 | ... AD27: =AD12/Z12-1 -> 0.1146258 | AE27: =$AE12/$AA12-1 -> 0.23551158 | AF27: =AF12/AB12-1 -> 0.15100954 | AG27: =AG12/AC12-1 -> 0.20990555 | AH27: =AH12/AD12-1 -> 0.13666179 | AI27: =AI12/AE12-1 -> 0.12503883 | AJ27: =AJ12/AF12-1 -> 0.039454309 | AK27: =AK12/AG12-1 -> 0.0058318923 | AL27: =AL12/AH12-1 -> 0.016635901 | AM27: =AM12/AI12-1 -> 0.077385186 | ... AU27: =AU12/AQ12-1 -> 0.068138871 | AW27: =AW12/O12-1 -> 0.023725908 | AX27: =AX12/P12-1 -> 0.038298492
B29: Profit / (loss) by Business Segments
B30: Dairy and Juice | C30: 2275.335 | D30: 2007.276 | E30: 1713.399 | F30: 1401.976 | G30: 1412.726 | H30: 1220.186 | I30: 1261.552 | J30: 1298.813 | K30: 1489.538 | L30: 1537.705 | M30: =SUM(AR30:AU30) -> 1554.679 | O30: 271.65 | P30: =826.677-O30 -> 555.027 | Q30: =1338.251-P30-O30 -> 511.574 | R30: =E30-Q30-P30-O30 -> 375.148 | S30: 266.301 | T30: =748.858-S30 -> 482.557 | U30: =1203.312-T30-S30 -> 454.454 | V30: =F30-U30-T30-S30 -> 198.664 | W30: 251.906 | X30: =730.447-W30 -> 478.541 | Y30: =1199.052-X30-W30 -> 468.605 | Z30: =G30-Y30-X30-W30 -> 213.674 | AA30: 288.564 | AB30: =683.115-AA30 -> 394.551 | AC30: =1013.099-AB30-AA30 -> 329.984 | AD30: =H30-AC30-AB30-AA30 -> 207.087 | AE30: 308.661 | AF30: =673.306-AE30 -> 364.645 | AG30: =1060.571-AE30-AF30 -> 387.265 | AH30: =I30-AG30-AF30-AE30 -> 200.981 | AI30: 429.96 | AJ30: =791.658-AI30 -> 361.698 | AK30: =1086.696-AI30-AJ30 -> 295.038 | AL30: =J30-AK30-AJ30-AI30 -> 212.117 | AM30: 498.489 | AN30: =892.978-AM30 -> 394.489 | AO30: =1249.743-AM30-AN30 -> 356.765 | AP30: =K30-AO30-AN30-AM30 -> 239.795 | AQ30: 521.292 | AR30: =905.237-AQ30 -> 383.945 | AS30: =1283.165-AQ30-AR30 -> 377.928 | AT30: =L30-AS30-AR30-AQ30 -> 254.54 | AU30: 538.266 | AX30: 483
B31: Bakery | C31: 347.014 | D31: 312.042 | E31: 212.714 | F31: 250.84 | G31: 237.012 | H31: 226.199 | I31: 334.07 | J31: 384.417 | K31: 403.325 | L31: 452.073 | M31: =SUM(AR31:AU31) -> 470.795 | O31: 45.207 | P31: =85.994-O31 -> 40.787 | Q31: =165.604-P31-O31 -> 79.61 | R31: =E31-Q31-P31-O31 -> 47.11 | S31: 56.668 | T31: =85.435-S31 -> 28.767 | U31: =166.41-T31-S31 -> 80.975 | V31: =F31-U31-T31-S31 -> 84.43 | W31: 63.919 | X31: =105.02-W31 -> 41.101 | Y31: =169.376-X31-W31 -> 64.356 | Z31: =G31-Y31-X31-W31 -> 67.636 | AA31: 41.769 | AB31: =76.7-AA31 -> 34.931 | AC31: =155.538-AB31-AA31 -> 78.838 | AD31: =H31-AC31-AB31-AA31 -> 70.661 | AE31: 68.253 | AF31: =147.587-AE31 -> 79.334 | AG31: =257.8-AE31-AF31 -> 110.213 | AH31: =I31-AG31-AF31-AE31 -> 76.27 | AI31: 88.468 | AJ31: =177.39-AI31 -> 88.922 | AK31: =292.2-AI31-AJ31 -> 114.81 | AL31: =J31-AK31-AJ31-AI31 -> 92.217 | AM31: 90.027 | AN31: =184.027-AM31 -> 94 | AO31: =304.421-AM31-AN31 -> 120.394 | AP31: =K31-AO31-AN31-AM31 -> 98.904 | AQ31: 90.085 | AR31: =191.6-AQ31 -> 101.515 | AS31: =324.473-AQ31-AR31 -> 132.873 | AT31: =L31-AS31-AR31-AQ31 -> 127.6 | AU31: 108.807 | AX31: 27
B32: Poultry | C32: -294.46 | D32: -29.161 | E32: 180.084 | F32: 263.295 | G32: 344.033 | H32: 217.487 | I32: 302.422 | J32: 429.854 | K32: 485.782 | L32: 489.6 | M32: =SUM(AR32:AU32) -> 451.978 | O32: 25.348 | P32: =92.001-O32 -> 66.653 | Q32: =142.909-P32-O32 -> 50.908 | R32: =E32-Q32-P32-O32 -> 37.175 | S32: 39.062 | T32: =121.776-S32 -> 82.714 | U32: =184.012-T32-S32 -> 62.236 | V32: =F32-U32-T32-S32 -> 79.283 | W32: 73.147 | X32: =198.616-W32 -> 125.469 | Y32: =271.186-X32-W32 -> 72.57 | Z32: =G32-Y32-X32-W32 -> 72.847 | AA32: 55.779 | AB32: =124.981-AA32 -> 69.202 | AC32: =161.279-AB32-AA32 -> 36.298 | AD32: =H32-AC32-AB32-AA32 -> 56.208 | AE32: 60.889 | AF32: =140.443-AE32 -> 79.554 | AG32: =234.428-AE32-AF32 -> 93.985 | AH32: =I32-AG32-AF32-AE32 -> 67.994 | AI32: 133.475 | AJ32: =237.248-AI32 -> 103.773 | AK32: =350.05-AI32-AJ32 -> 112.802 | AL32: =J32-AK32-AJ32-AI32 -> 79.804 | AM32: 140.165 | AN32: =271.245-AM32 -> 131.08 | AO32: =401.043-AM32-AN32 -> 129.798 | AP32: =K32-AO32-AN32-AM32 -> 84.739 | AQ32: 145.05 | AR32: =275.5-AQ32 -> 130.45 | AS32: =405.6-AQ32-AR32 -> 130.1 | AT32: =L32-AS32-AR32-AQ32 -> 84 | AU32: 107.428 | AX32: 83
B33: Other Activities | C33: -177.792 | D33: -130.194 | E33: -97.639 | F33: -114.539 | G33: -58.215 | H33: -84.436 | I33: -119.906 | J33: -61.555 | K33: -64.978 | L33: -22.705 | M33: =SUM(AR33:AU33) -> -19.868 | O33: -1.804 | P33: =-1.081-O33 -> 0.723 | Q33: =-1.928-P33-O33 -> -0.847 | R33: =E33-Q33-P33-O33 -> -95.711 | S33: -25.083 | T33: =-35.266-S33 -> -10.183 | U33: =-40.21-T33-S33 -> -4.944 | V33: =F33-U33-T33-S33 -> -74.329 | W33: -21.578 | X33: =-46.751-W33 -> -25.173 | Y33: =-37.144-X33-W33 -> 9.607 | Z33: =G33-Y33-X33-W33 -> -21.071 | AA33: 2.569 | AB33: =-6.087-AA33 -> -8.656 | AC33: =-40.359-AB33-AA33 -> -34.272 | AD33: =H33-AC33-AB33-AA33 -> -44.077 | AE33: -15.28 | AF33: =-12.709-AE33 -> 2.571 | AG33: =-129.278-AE33-AF33 -> -116.569 | AH33: =I33-AG33-AF33-AE33 -> 9.372 | AI33: -15.947 | AJ33: =-13.272-AI33 -> 2.675 | AK33: =-49.155-AI33-AJ33 -> -35.883 | AL33: =J33-AK33-AJ33-AI33 -> -12.4 | AM33: -35.3 | AN33: =-33.759-AM33 -> 1.541 | AO33: =-71.89-AM33-AN33 -> -38.131 | AP33: =K33-AO33-AN33-AM33 -> 6.912 | AQ33: -24.9 | AR33: =6.3-AQ33 -> 31.2 | AS33: =-21.085-AQ33-AR33 -> -27.385 | AT33: =L33-AS33-AR33-AQ33 -> -1.62 | AU33: -22.063
B34: Total | C34: =SUM(C30:C33) -> 2150.097 | D34: =SUM(D30:D33) -> 2159.963 | E34: =SUM(E30:E33) -> 2008.558 | F34: =SUM(F30:F33) -> 1801.572 | G34: =SUM(G30:G33) -> 1935.556 | H34: =SUM(H30:H33) -> 1579.436 | I34: =SUM(I30:I33) -> 1778.138 | J34: =SUM(J30:J33) -> 2051.529 | ... M34: =SUM(M30:M33) -> 2457.584 | O34: =SUM(O30:O33) -> 340.401 | P34: =SUM(P30:P33) -> 663.19 | Q34: =SUM(Q30:Q33) -> 641.245 | R34: =SUM(R30:R33) -> 363.722 | S34: =SUM(S30:S33) -> 336.948 | T34: =SUM(T30:T33) -> 583.855 | U34: =SUM(U30:U33) -> 592.721 | V34: =SUM(V30:V33) -> 288.048 | ... AU34: =SUM(AU30:AU33) -> 732.438 | AX34: =SUM(AX30:AX33) -> 593
B35: check | C35: =C34-Model!C22 -> 0 | D35: =D34-Model!D22 -> 0 | E35: =E34-Model!E22 -> 0 | F35: =F34-Model!F22 -> 0 | G35: =G34-Model!G22 -> 0 | H35: =H34-Model!H22 -> 1.8189894e-12 | I35: =I34-Model!I22 -> -2.0463631e-12 | J35: =J34-Model!J22 -> 0 | ... M35: =M34-Model!M22 -> 0 | O35: =O34-Model!O22 -> 0 | P35: =P34-Model!P22 -> 0 | Q35: =Q34-Model!Q22 -> 0 | R35: =R34-Model!R22 -> 1.2505552e-12 | S35: =S34-Model!S22 -> 0 | T35: =T34-Model!T22 -> 0 | U35: =U34-Model!U22 -> -0.001 | V35: =V34-Model!V22 -> 0.001 | ... AU35: =AU34-Model!AU22 -> 0 | AX35: =AX34-Model!AX22 -> 9.145
B37: Revenue Composition (%)
B38: Dairy and Juice | C38: =C30/C$34 -> 1.0582476 | D38: =D30/D$34 -> 0.92931036 | E38: =E30/E$34 -> 0.8530493 | F38: =F30/F$34 -> 0.77819593 | G38: =G30/G$34 -> 0.72988123 | H38: =H30/H$34 -> 0.77254539 | I38: =I30/I$34 -> 0.70947924 | J38: =J30/J$34 -> 0.63309512 | ... M38: =M30/M$34 -> 0.63260462 | O38: =O30/O$34 -> 0.79802938 | P38: =P30/P$34 -> 0.83690496 | Q38: =Q30/Q$34 -> 0.79778244 | R38: =R30/R$34 -> 1.0314141 | S38: =S30/S$34 -> 0.79033263 | T38: =T30/T$34 -> 0.82650144 | U38: =U30/U$34 -> 0.76672499 | V38: =V30/V$34 -> 0.68969061 | ... AU38: =AU30/AU$34 -> 0.73489633 | AX38: =AX30/AX$34 -> 0.81450253
B39: Bakery | C39: =C31/C$34 -> 0.16139458 | D39: =D31/D$34 -> 0.14446636 | E39: =E31/E$34 -> 0.10590384 | F39: =F31/F$34 -> 0.13923396 | G39: =G31/G$34 -> 0.12245164 | H39: =H31/H$34 -> 0.14321505 | I39: =I31/I$34 -> 0.18787631 | J39: =J31/J$34 -> 0.18738073 | ... M39: =M31/M$34 -> 0.19156822 | O39: =O31/O$34 -> 0.13280513 | P39: =P31/P$34 -> 0.061501229 | Q39: =Q31/Q$34 -> 0.12414912 | R39: =R31/R$34 -> 0.129522 | S39: =S31/S$34 -> 0.16818025 | T39: =T31/T$34 -> 0.049270795 | U39: =U31/U$34 -> 0.13661571 | V39: =V31/V$34 -> 0.29311087 | ... AU39: =AU31/AU$34 -> 0.14855455 | AX39: =AX31/AX$34 -> 0.045531197
B40: Poultry | C40: =C32/C$34 -> -0.13695196 | D40: =D32/D$34 -> -0.013500694 | E40: =E32/E$34 -> 0.089658352 | F40: =F32/F$34 -> 0.14614736 | G40: =G32/G$34 -> 0.17774376 | H40: =H32/H$34 -> 0.13769915 | I40: =I32/I$34 -> 0.17007791 | J40: =J32/J$34 -> 0.2095286 | ... M40: =M32/M$34 -> 0.18391152 | O40: =O32/O$34 -> 0.074465116 | P40: =P32/P$34 -> 0.10050363 | Q40: =Q32/Q$34 -> 0.079389313 | R40: =R32/R$34 -> 0.10220718 | S40: =S32/S$34 -> 0.11592887 | T40: =T32/T$34 -> 0.14166874 | U40: =U32/U$34 -> 0.1050005 | V40: =V32/V$34 -> 0.27524232 | ... AU40: =AU32/AU$34 -> 0.1466718 | AX40: =AX32/AX$34 -> 0.13996627
B41: Other Activities | C41: =C33/C$34 -> -0.082690223 | D41: =D33/D$34 -> -0.060276033 | E41: =E33/E$34 -> -0.048611491 | F41: =F33/F$34 -> -0.063577254 | G41: =G33/G$34 -> -0.030076629 | H41: =H33/H$34 -> -0.053459589 | I41: =I33/I$34 -> -0.067433461 | J41: =J33/J$34 -> -0.03000445 | ... M41: =M33/M$34 -> -0.0080843625 | O41: =O33/O$34 -> -0.0052996319 | P41: =P33/P$34 -> 0.0010901853 | Q41: =Q33/Q$34 -> -0.001320868 | R41: =R33/R$34 -> -0.26314328 | S41: =S33/S$34 -> -0.074441754 | T41: =T33/T$34 -> -0.017440974 | U41: =U33/U$34 -> -0.0083411926 | V41: =V33/V$34 -> -0.2580438 | ... AU41: =AU33/AU$34 -> -0.030122686 | AX41: =AX33/AX$34 -> 0
B42: Total | C42: =SUM(C38:C41) -> 1 | D42: =SUM(D38:D41) -> 1 | E42: =SUM(E38:E41) -> 1 | F42: =SUM(F38:F41) -> 1 | G42: =SUM(G38:G41) -> 1 | H42: =SUM(H38:H41) -> 1 | I42: =SUM(I38:I41) -> 1 | J42: =SUM(J38:J41) -> 1 | ... M42: =SUM(M38:M41) -> 1 | O42: =SUM(O38:O41) -> 1 | P42: =SUM(P38:P41) -> 1 | Q42: =SUM(Q38:Q41) -> 1 | R42: =SUM(R38:R41) -> 1 | S42: =SUM(S38:S41) -> 1 | T42: =SUM(T38:T41) -> 1 | U42: =SUM(U38:U41) -> 1 | V42: =SUM(V38:V41) -> 1 | ... AD42: =SUM(AD38:AD41) -> 1 | AE42: =AE34/AE$34 -> 1 | AF42: =SUM(AF38:AF41) -> 1 | AG42: =SUM(AG38:AG41) -> 1 | AH42: =SUM(AH38:AH41) -> 1 | AI42: =SUM(AI38:AI41) -> 1 | AJ42: =SUM(AJ38:AJ41) -> 1 | AK42: =SUM(AK38:AK41) -> 1 | AL42: =SUM(AL38:AL41) -> 1 | AM42: =SUM(AM38:AM41) -> 1 | ... AU42: =SUM(AU38:AU41) -> 1 | AX42: =SUM(AX38:AX41) -> 1
B44: y-o-y growth in Revenue
B45: Dairy and Juice | D45: =D30/C30-1 -> -0.11781078 | E45: =E30/D30-1 -> -0.14640588 | F45: =F30/E30-1 -> -0.18175743 | G45: =G30/F30-1 -> 0.0076677489 | H45: =H30/G30-1 -> -0.1362897 | I45: =I30/H30-1 -> 0.033901389 | J45: =J30/I30-1 -> 0.029535842 | K45: =K30/J30-1 -> 0.14684562 | L45: =L30/K30-1 -> 0.032336872 | S45: =S30/O30-1 -> -0.019690779 | T45: =T30/P30-1 -> -0.13057022 | U45: =U30/Q30-1 -> -0.1116554 | V45: =V30/R30-1 -> -0.47043833 | W45: =W30/S30-1 -> -0.054055373 | X45: =X30/T30-1 -> -0.0083223329 | Y45: =Y30/U30-1 -> 0.031138465 | Z45: =Z30/V30-1 -> 0.075554705 | ... AD45: =AD30/Z30-1 -> -0.030827335 | AE45: =$AE30/$AA30-1 -> 0.069644862 | AF45: =AF30/AB30-1 -> -0.075797552 | AG45: =AG30/AC30-1 -> 0.1735872 | AH45: =AH30/AD30-1 -> -0.029485192 | AI45: =AI30/AE30-1 -> 0.39298454 | AJ45: =AJ30/AF30-1 -> -0.008081833 | AK45: =AK30/AG30-1 -> -0.23814959 | AL45: =AL30/AH30-1 -> 0.055408223 | AM45: =AM30/AI30-1 -> 0.15938459 | ... AU45: =AU30/AQ30-1 -> 0.032561405 | AX45: =AX30/P30-1 -> -0.12977207
B46: Bakery | D46: =D31/C31-1 -> -0.1007798 | E46: =E31/D31-1 -> -0.31831612 | F46: =F31/E31-1 -> 0.17923597 | G46: =G31/F31-1 -> -0.055126774 | H46: =H31/G31-1 -> -0.045622163 | I46: =I31/H31-1 -> 0.4768854 | J46: =J31/I31-1 -> 0.15070794 | K46: =K31/J31-1 -> 0.04918617 | L46: =L31/K31-1 -> 0.12086531 | S46: =S31/O31-1 -> 0.25352268 | T46: =T31/P31-1 -> -0.29470174 | U46: =U31/Q31-1 -> 0.017146087 | V46: =V31/R31-1 -> 0.7921885 | W46: =W31/S31-1 -> 0.12795581 | X46: =X31/T31-1 -> 0.42875517 | Y46: =Y31/U31-1 -> -0.20523618 | Z46: =Z31/V31-1 -> -0.19891034 | ... AD46: =AD31/Z31-1 -> 0.044724703 | AE46: =$AE31/$AA31-1 -> 0.63405875 | AF46: =AF31/AB31-1 -> 1.2711632 | AG46: =AG31/AC31-1 -> 0.39796798 | AH46: =AH31/AD31-1 -> 0.079379007 | AI46: =AI31/AE31-1 -> 0.29617746 | AJ46: =AJ31/AF31-1 -> 0.12085613 | AK46: =AK31/AG31-1 -> 0.041710143 | AL46: =AL31/AH31-1 -> 0.20908614 | AM46: =AM31/AI31-1 -> 0.017622191 | ... AU46: =AU31/AQ31-1 -> 0.20782594 | AX46: =AX31/P31-1 -> -0.33802437
B47: Poultry | D47: =D32/C32-1 -> -0.90096787 | E47: =E32/D32-1 -> -7.1755084 | F47: =F32/E32-1 -> 0.4620677 | G47: =G32/F32-1 -> 0.30664464 | H47: =H32/G32-1 -> -0.36783099 | I47: =I32/H32-1 -> 0.39052909 | J47: =J32/I32-1 -> 0.42137146 | K47: =K32/J32-1 -> 0.13010929 | L47: =L32/K32-1 -> 0.0078594925 | S47: =S32/O32-1 -> 0.54102888 | T47: =T32/P32-1 -> 0.2409644 | U47: =U32/Q32-1 -> 0.22251905 | V47: =V32/R32-1 -> 1.1326967 | W47: =W32/S32-1 -> 0.87258717 | X47: =X32/T32-1 -> 0.51690161 | Y47: =Y32/U32-1 -> 0.16604538 | Z47: =Z32/V32-1 -> -0.081177554 | ... AD47: =AD32/Z32-1 -> -0.22841023 | AE47: =$AE32/$AA32-1 -> 0.091611538 | AF47: =AF32/AB32-1 -> 0.14959105 | AG47: =AG32/AC32-1 -> 1.5892611 | AH47: =AH32/AD32-1 -> 0.20968545 | AI47: =AI32/AE32-1 -> 1.1921037 | AJ47: =AJ32/AF32-1 -> 0.30443472 | AK47: =AK32/AG32-1 -> 0.2002128 | AL47: =AL32/AH32-1 -> 0.1736918 | AM47: =AM32/AI32-1 -> 0.050121746 | ... AU47: =AU32/AQ32-1 -> -0.25937263 | AX47: =AX32/P32-1 -> 0.24525528
B48: Other Activities | D48: =D33/C33-1 -> -0.26771733 | E48: =E33/D33-1 -> -0.25004993 | F48: =F33/E33-1 -> 0.17308657 | G48: =G33/F33-1 -> -0.49174517 | H48: =H33/G33-1 -> 0.45041656 | I48: =I33/H33-1 -> 0.42008148 | J48: =J33/I33-1 -> -0.48663953 | K48: =K33/J33-1 -> 0.055608805 | L48: =L33/K33-1 -> -0.65057404 | S48: =S33/O33-1 -> 12.904102 | T48: =T33/P33-1 -> -15.084371 | U48: =U33/Q33-1 -> 4.837072 | V48: =V33/R33-1 -> -0.2234017 | W48: =W33/S33-1 -> -0.13973608 | X48: =X33/T33-1 -> 1.4720613 | Y48: =Y33/U33-1 -> -2.9431634 | Z48: =Z33/V33-1 -> -0.71651711 | ... AD48: =AD33/Z33-1 -> 1.0918324 | AE48: =$AE33/$AA33-1 -> -6.9478396 | AF48: =AF33/AB33-1 -> -1.2970194 | AG48: =AG33/AC33-1 -> 2.4012897 | AH48: =AH33/AD33-1 -> -1.2126279 | AI48: =AI33/AE33-1 -> 0.043651832 | AJ48: =AJ33/AF33-1 -> 0.040451186 | AK48: =AK33/AG33-1 -> -0.69217373 | AL48: =AL33/AH33-1 -> -2.3230901 | AM48: =AM33/AI33-1 -> 1.2135825 | ... AU48: =AU33/AQ33-1 -> -0.11393574 | AX48: =AX33/P33-1 -> -1
B49: Total | D49: =D34/C34-1 -> 0.0045886302 | E49: =E34/D34-1 -> -0.070096108 | F49: =F34/E34-1 -> -0.10305204 | G49: =G34/F34-1 -> 0.074370605 | H49: =H34/G34-1 -> -0.18398848 | I49: =I34/H34-1 -> 0.12580567 | J49: =J34/I34-1 -> 0.15375128 | K49: =K34/J34-1 -> 0.12777689 | L49: =L34/K34-1 -> 0.06180924 | S49: =S34/O34-1 -> -0.010143918 | T49: =T34/P34-1 -> -0.11962635 | U49: =U34/Q34-1 -> -0.075671545 | V49: =V34/R34-1 -> -0.2080545 | W49: =W34/S34-1 -> 0.090358156 | X49: =X34/T34-1 -> 0.061801303 | Y49: =Y34/U34-1 -> 0.037820492 | Z49: =Z34/V34-1 -> 0.15635589 | ... AD49: =AD34/Z34-1 -> -0.12971725 | AE49: =$AE34/$AA34-1 -> 0.08706883 | AF49: =AF34/AB34-1 -> 0.073620283 | AG49: =AG34/AC34-1 -> 0.15588734 | AH49: =AH34/AD34-1 -> 0.22332766 | AI49: =AI34/AE34-1 -> 0.50513937 | AJ49: =AJ34/AF34-1 -> 0.058855283 | AK49: =AK34/AG34-1 -> 0.025001369 | AL49: =AL34/AH34-1 -> 0.048280257 | AM49: =AM34/AI34-1 -> 0.090297127 | ... AU49: =AU34/AQ34-1 -> 0.0012453402 | AX49: =AX34/P34-1 -> -0.10583694
B51: Net income margin
B52: Dairy and Juice | C52: =C30/C8 -> 0.20757848 | D52: =D30/D8 -> 0.19097869 | E52: =E30/E8 -> 0.17272751 | F52: =F30/F8 -> 0.13731418 | G52: =G30/G8 -> 0.12932693 | H52: =H30/H8 -> 0.10951893 | I52: =I30/I8 -> 0.10089088 | J52: =J30/J8 -> 0.10066322 | ... M52: =M30/M8 -> 0.10509543 | O52: =O30/O8 -> 0.11525498 | P52: =P30/P8 -> 0.20164527 | Q52: =Q30/Q8 -> 0.21269022 | R52: =R30/R8 -> 0.15598858 | S52: =S30/S8 -> 0.11253404 | T52: =T30/T8 -> 0.17546615 | U52: =U30/U8 -> 0.17801787 | V52: =V30/V8 -> 0.078196194 | ... AU52: =AU30/AU8 -> 0.12881522 | AX52: =AX30/AX8 -> 0.17355372
B53: Bakery | C53: =C31/C9 -> 0.18450448 | D53: =D31/D9 -> 0.17267651 | E53: =E31/E9 -> 0.12959358 | F53: =F31/F9 -> 0.14339475 | G53: =G31/G9 -> 0.13844547 | H53: =H31/H9 -> 0.12644855 | I53: =I31/I9 -> 0.13695322 | J53: =J31/J9 -> 0.14874183 | ... M53: =M31/M9 -> 0.1670436 | O53: =O31/O9 -> 0.11149394 | P53: =P31/P9 -> 0.10806364 | Q53: =Q31/Q9 -> 0.19341688 | R53: =R31/R9 -> 0.1054165 | S53: =S31/S9 -> 0.13178022 | T53: =T31/T9 -> 0.07459335 | U53: =U31/U9 -> 0.17816399 | V53: =V31/V9 -> 0.17621522 | ... AU53: =AU31/AU9 -> 0.16443927 | AX53: =AX31/AX9 -> 0.06835443
B54: Poultry | C54: =C32/C10 -> -0.22114808 | D54: =D32/D10 -> -0.019923806 | E54: =E32/E10 -> 0.10002722 | F54: =F32/F10 -> 0.12392727 | G54: =G32/G10 -> 0.15005066 | H54: =H32/H10 -> 0.09449962 | I54: =I32/I10 -> 0.1003579 | J54: =J32/J10 -> 0.12217537 | ... M54: =M32/M10 -> 0.11165139 | O54: =O32/O10 -> 0.060260699 | P54: =P32/P10 -> 0.15334585 | Q54: =Q32/Q10 -> 0.11228897 | R54: =R32/R10 -> 0.075607043 | S54: =S32/S10 -> 0.077771385 | T54: =T32/T10 -> 0.15773796 | U54: =U32/U10 -> 0.12728187 | V54: =V32/V10 -> 0.13018812 | ... AU54: =AU32/AU10 -> 0.097585169 | AX54: =AX32/AX10 -> 0.15749526
B55: Other Activities | C55: =C33/C11 -> -1.0777886 | D55: =D33/D11 -> -0.84352587 | E55: =E33/E11 -> -0.49707019 | F55: =F33/F11 -> -0.42834331 | G55: =G33/G11 -> -0.13584591 | H55: =H33/H11 -> -0.13661147 | I55: =I33/I11 -> -0.15665796 | J55: =J33/J11 -> -0.1079471 | ... M55: =M33/M11 -> -0.024887793 | O55: =O33/O11 -> -0.036702474 | P55: =P33/P11 -> 0.011567445 | Q55: =Q33/Q11 -> -0.017966993 | R55: =R33/R11 -> -2.5433408 | S55: =S33/S11 -> -0.45281895 | T55: =T33/T11 -> -0.17020174 | U55: =U33/U11 -> -0.064256193 | V55: =V33/V11 -> -0.9879446 | ... AU55: =AU33/AU11 -> -0.10078387 | AX55: =AX33/AX11 -> 0
B56: Total | C56: =C34/C12 -> 0.14995189 | D56: =D34/D12 -> 0.15499681 | E56: =E34/E12 -> 0.14814738 | F56: =F34/F12 -> 0.12553392 | G56: =G34/G12 -> 0.1260378 | H56: =H34/H12 -> 0.099650719 | I56: =I34/I12 -> 0.094974548 | J56: =J34/J12 -> 0.10480039 | ... M56: =M34/M12 -> 0.10943101 | O56: =O34/O12 -> 0.10531541 | P56: =P34/P12 -> 0.18284365 | Q56: =Q34/Q12 -> 0.19329979 | R56: =R34/R12 -> 0.10757238 | S56: =S34/S12 -> 0.10045905 | T56: =T34/T12 -> 0.15695031 | U56: =U34/U12 -> 0.16587696 | V56: =V34/V12 -> 0.07776804 | ... AU56: =AU34/AU12 -> 0.11890125 | AX56: =AX34/AX12 -> 0.1574615
B58: Revenue by geographical area
B59: Saudi Arabia | C59: 9057.081 | D59: 9300.015 | E59: 9179.802 | F59: 9737.264 | G59: 10285.861 | H59: 10222.762 | I59: 12099.752 | J59: 13188.218 | K59: 13904.171 | L59: 14578.333 | M59: =SUM(AR59:AU59) -> 14855.866 | O59: 2217.172 | P59: =4657.931-O59 -> 2440.759 | Q59: =6897.503-P59-O59 -> 2239.572 | R59: =E59-Q59-P59-O59 -> 2282.299 | S59: 2311.503 | T59: =4831.555-S59 -> 2520.052 | U59: =7245.543-T59-S59 -> 2413.988 | V59: =F59-U59-T59-S59 -> 2491.721 | W59: 2469.69 | X59: =5289.045-W59 -> 2819.355 | Y59: =7818.925-X59-W59 -> 2529.88 | Z59: =G59-Y59-X59-W59 -> 2466.936 | AA59: 2431.384 | AB59: =5028.302-AA59 -> 2596.918 | AC59: =7503.579-AB59-AA59 -> 2475.277 | AD59: =H59-AC59-AB59-AA59 -> 2719.183 | AE59: 2982.801 | AF59: =5990.596-AE59 -> 3007.795 | AG59: =9016.543-AE59-AF59 -> 3025.947 | AH59: =I59-AG59-AF59-AE59 -> 3083.209 | AI59: 3435.312 | AJ59: =6735.56-AI59 -> 3300.248 | AK59: =9952.725-AI59-AJ59 -> 3217.165 | AL59: =J59-AK59-AJ59-AI59 -> 3235.493 | AM59: 3592.39 | AN59: =7016.063-AM59 -> 3423.673 | AO59: =10473.25-AM59-AN59 -> 3457.187 | AP59: =K59-AO59-AN59-AM59 -> 3430.921 | AQ59: 3864.752 | AR59: =7390.989-AQ59 -> 3526.237 | AS59: =11022.803-AQ59-AR59 -> 3631.814 | AT59: =L59-AS59-AR59-AQ59 -> 3555.53 | AU59: 4142.285 | AW59: 2287.914 | AX59: 2544
B60: Other GCC Countries | C60: 3745.732 | D60: 3480.654 | E60: 3090.403 | F60: 3164.334 | G60: 3198.21 | H60: 3121.348 | I60: 3642.59 | J60: 3865.769 | K60: 4282.61 | L60: 4547.824 | M60: =SUM(AR60:AU60) -> 4571.746 | O60: 750.095 | P60: =1562.604-O60 -> 812.509 | Q60: =2305.195-P60-O60 -> 742.591 | R60: =E60-Q60-P60-O60 -> 785.208 | S60: 749.242 | T60: =1589.364-S60 -> 840.122 | U60: =2351.71-T60-S60 -> 762.346 | V60: =F60-U60-T60-S60 -> 812.624 | W60: 781.74 | X60: =1614.817-W60 -> 833.077 | Y60: =2411.13-X60-W60 -> 796.313 | Z60: =G60-Y60-X60-W60 -> 787.08 | AA60: 712.359 | AB60: =1510.245-AA60 -> 797.886 | AC60: =2267.525-AB60-AA60 -> 757.28 | AD60: =H60-AC60-AB60-AA60 -> 853.823 | AE60: 883.24 | AF60: =1788.184-AE60 -> 904.944 | AG60: =2668.775-AE60-AF60 -> 880.591 | AH60: =I60-AG60-AF60-AE60 -> 973.815 | AI60: 1006.777 | AJ60: =1932.294-AI60 -> 925.517 | AK60: =2833.407-AI60-AJ60 -> 901.113 | AL60: =J60-AK60-AJ60-AI60 -> 1032.362 | AM60: 1100.613 | AN60: =2180.648-AM60 -> 1080.035 | AO60: =3201.771-AM60-AN60 -> 1021.123 | AP60: =K60-AO60-AN60-AM60 -> 1080.839 | AQ60: 1203.691 | AR60: =2321.469-AQ60 -> 1117.778 | AS60: =3432.716-AQ60-AR60 -> 1111.247 | AT60: =L60-AS60-AR60-AQ60 -> 1115.108 | AU60: 1227.613 | AW60: 734.316 | AX60: 855
B61: Other Countries | C61: 1535.766 | D61: 1154.863 | E61: 1287.632 | F61: 1449.679 | G61: 1872.877 | H61: 2505.61 | I61: 2979.916 | J61: 2521.598 | K61: 2792.731 | L61: 2938.719 | M61: =SUM(AR61:AU61) -> 3030.227 | O61: 264.938 | P61: =638.758-O61 -> 373.82 | Q61: =973.955-P61-O61 -> 335.197 | R61: =E61-Q61-P61-O61 -> 313.677 | S61: 293.338 | T61: =653.163-S61 -> 359.825 | U61: =1050.086-T61-S61 -> 396.923 | V61: =F61-U61-T61-S61 -> 399.593 | W61: 341.01 | X61: =770.422-W61 -> 429.412 | Y61: =1307.308-X61-W61 -> 536.886 | Z61: =G61-Y61-X61-W61 -> 565.569 | AA61: 501.271 | AB61: =1112.035-AA61 -> 610.764 | AC61: =1821.208-AB61-AA61 -> 709.173 | AD61: =H61-AC61-AB61-AA61 -> 684.402 | AE61: 637.416 | AF61: =1335.124-AE61 -> 697.708 | AG61: =2197.707-AE61-AF61 -> 862.583 | AH61: =I61-AG61-AF61-AE61 -> 782.209 | AI61: 624.475 | AJ61: =1191.059-AI61 -> 566.584 | AK61: =1869.715-AI61-AJ61 -> 678.656 | AL61: =J61-AK61-AJ61-AI61 -> 651.883 | AM61: 765.638 | AN61: =1416.551-AM61 -> 650.913 | AO61: =2147.162-AM61-AN61 -> 730.611 | AP61: =K61-AO61-AN61-AM61 -> 645.569 | AQ61: 698.647 | AR61: =1343.034-AQ61 -> 644.387 | AS61: =2152.572-AQ61-AR61 -> 809.538 | AT61: =L61-AS61-AR61-AQ61 -> 786.147 | AU61: 790.155 | AW61: 286.662 | AX61: 367
B62: Total | C62: =SUM(C59:C61) -> 14338.579 | D62: =SUM(D59:D61) -> 13935.532 | E62: =SUM(E59:E61) -> 13557.837 | F62: =SUM(F59:F61) -> 14351.277 | G62: =SUM(G59:G61) -> 15356.948 | H62: =SUM(H59:H61) -> 15849.72 | I62: =SUM(I59:I61) -> 18722.258 | J62: =SUM(J59:J61) -> 19575.585 | ... M62: =SUM(M59:M61) -> 22457.839 | O62: =SUM(O59:O61) -> 3232.205 | P62: =SUM(P59:P61) -> 3627.088 | Q62: =SUM(Q59:Q61) -> 3317.36 | R62: =SUM(R59:R61) -> 3381.184 | S62: =SUM(S59:S61) -> 3354.083 | T62: =SUM(T59:T61) -> 3719.999 | U62: =SUM(U59:U61) -> 3573.257 | V62: =SUM(V59:V61) -> 3703.938 | ... AU62: =SUM(AU59:AU61) -> 6160.053 | AW62: =SUM(AW59:AW61) -> 3308.892 | AX62: =SUM(AX59:AX61) -> 3766
B64: check | C64: =C62-Model!C7 -> 0 | D64: =D62-Model!D7 -> 0 | E64: =E62-Model!E7 -> 0 | F64: =F62-Model!F7 -> 0 | G64: =G62-Model!G7 -> 0 | H64: =H62-Model!H7 -> 0 | I64: =I62-Model!I7 -> 0 | J64: =J62-Model!J7 -> 0 | ... M64: =M62-Model!M7 -> 0 | O64: =O62-Model!O7 -> 0 | P64: =P62-Model!P7 -> 0 | Q64: =Q62-Model!Q7 -> 0 | R64: =R62-Model!R7 -> 0 | S64: =S62-Model!S7 -> 0 | T64: =T62-Model!T7 -> 0 | U64: =U62-Model!U7 -> 0 | V64: =V62-Model!V7 -> 0 | ... AU64: =AU62-Model!AU7 -> 0 | AW64: =AW62-Model!AW7 -> 0 | AX64: =AX62-Model!AX7 -> -1.424
B66: Revenue Composition (%)
B67: Saudi Arabia | C67: =C59/C$62 -> 0.6316582 | D67: =D59/D$62 -> 0.66735988 | E67: =E59/E$62 -> 0.67708455 | F67: =F59/F$62 -> 0.6784946 | G67: =G59/G$62 -> 0.66978549 | H67: =H59/H$62 -> 0.64498061 | I67: =I59/I$62 -> 0.64627632 | J67: =J59/J$62 -> 0.67370748 | ... M67: =M59/M$62 -> 0.66150024 | O67: =O59/O$62 -> 0.68596268 | P67: =P59/P$62 -> 0.67292522 | Q67: =Q59/Q$62 -> 0.67510671 | R67: =R59/R$62 -> 0.67499994 | S67: =S59/S$62 -> 0.68916094 | T67: =T59/T$62 -> 0.67743352 | U67: =U59/U$62 -> 0.67557077 | V67: =V59/V$62 -> 0.67272211 | ... AU67: =AU59/AU$62 -> 0.67244308 | AW67: =AW59/AW$62 -> 0.69144415 | AX67: =AX59/AX$62 -> 0.67551779
B68: Other GCC Countries | C68: =C60/C$62 -> 0.26123453 | D68: =D60/D$62 -> 0.24976829 | E68: =E60/E$62 -> 0.22794219 | F68: =F60/F$62 -> 0.22049146 | G68: =G60/G$62 -> 0.20825818 | H68: =H60/H$62 -> 0.19693395 | I68: =I60/I$62 -> 0.19455933 | J68: =J60/J$62 -> 0.1974791 | ... M68: =M60/M$62 -> 0.20357017 | O68: =O60/O$62 -> 0.23206913 | P68: =P60/P$62 -> 0.22401138 | Q68: =Q60/Q$62 -> 0.22384999 | R68: =R60/R$62 -> 0.23222871 | S68: =S60/S$62 -> 0.22338207 | T68: =T60/T$62 -> 0.22583931 | U68: =U60/U$62 -> 0.21334765 | V68: =V60/V$62 -> 0.2193946 | ... AU68: =AU60/AU$62 -> 0.19928611 | AW68: =AW60/AW$62 -> 0.22192202 | AX68: =AX60/AX$62 -> 0.22703133
B69: Other Countries | C69: =C61/C$62 -> 0.10710727 | D69: =D61/D$62 -> 0.082871827 | E69: =E61/E$62 -> 0.094973262 | F69: =F61/F$62 -> 0.10101394 | G69: =G61/G$62 -> 0.12195633 | H69: =H61/H$62 -> 0.15808544 | I69: =I61/I$62 -> 0.15916435 | J69: =J61/J$62 -> 0.12881342 | ... M69: =M61/M$62 -> 0.13492959 | O69: =O61/O$62 -> 0.081968192 | P69: =P61/P$62 -> 0.10306339 | Q69: =Q61/Q$62 -> 0.1010433 | R69: =R61/R$62 -> 0.092771349 | S69: =S61/S$62 -> 0.087456989 | T69: =T61/T$62 -> 0.096727177 | U69: =U61/U$62 -> 0.11108157 | V69: =V61/V$62 -> 0.10788329 | ... AU69: =AU61/AU$62 -> 0.12827081 | AW69: =AW61/AW$62 -> 0.086633834 | AX69: =AX61/AX$62 -> 0.097450876
B70: Total | C70: =SUM(C67:C69) -> 1 | D70: =SUM(D67:D69) -> 1 | E70: =SUM(E67:E69) -> 1 | F70: =SUM(F67:F69) -> 1 | G70: =SUM(G67:G69) -> 1 | H70: =SUM(H67:H69) -> 1 | I70: =SUM(I67:I69) -> 1 | J70: =SUM(J67:J69) -> 1 | ... M70: =SUM(M67:M69) -> 1 | O70: =SUM(O67:O69) -> 1 | P70: =SUM(P67:P69) -> 1 | Q70: =SUM(Q67:Q69) -> 1 | R70: =SUM(R67:R69) -> 1 | S70: =SUM(S67:S69) -> 1 | T70: =SUM(T67:T69) -> 1 | U70: =SUM(U67:U69) -> 1 | V70: =SUM(V67:V69) -> 1 | ... AU70: =SUM(AU67:AU69) -> 1 | AW70: =SUM(AW67:AW69) -> 1 | AX70: =SUM(AX67:AX69) -> 1
B72: y-o-y growth in Revenue
B73: Saudi Arabia | D73: =D59/C59-1 -> 0.026822549 | E73: =E59/D59-1 -> -0.012926108 | F73: =F59/E59-1 -> 0.060727018 | G73: =G59/F59-1 -> 0.056339953 | H73: =H59/G59-1 -> -0.0061345375 | I73: =I59/H59-1 -> 0.18360889 | J73: =J59/I59-1 -> 0.089957712 | K73: =K59/J59-1 -> 0.054287319 | L73: =L59/K59-1 -> 0.048486314 | S73: =S59/O59-1 -> 0.042545639 | T73: =T59/P59-1 -> 0.032487026 | U73: =U59/Q59-1 -> 0.077879166 | V73: =V59/R59-1 -> 0.09175923 | W73: =W59/S59-1 -> 0.068434694 | X73: =X59/T59-1 -> 0.11876858 | Y73: =Y59/U59-1 -> 0.048008524 | Z73: =Z59/V59-1 -> -0.0099469403 | ... AD73: =AD59/Z59-1 -> 0.10225113 | AE73: =$AE59/$AA59-1 -> 0.22679141 | AF73: =AF59/AB59-1 -> 0.15821716 | AG73: =AG59/AC59-1 -> 0.22246803 | AH73: =AH59/AD59-1 -> 0.1338733 | AI73: =AI59/AE59-1 -> 0.15170673 | AJ73: =AJ59/AF59-1 -> 0.097231693 | AK73: =AK59/AG59-1 -> 0.063192779 | AL73: =AL59/AH59-1 -> 0.049391397 | AM73: =AM59/AI59-1 -> 0.045724522 | ... AU73: =AU59/AQ59-1 -> 0.071811335 | AW73: =AW59/O59-1 -> 0.031906411 | AX73: =AX59/P59-1 -> 0.042298728
B74: Other GCC Countries | D74: =D60/C60-1 -> -0.07076801 | E74: =E60/D60-1 -> -0.11212002 | F74: =F60/E60-1 -> 0.02392277 | G74: =G60/F60-1 -> 0.01070557 | H74: =H60/G60-1 -> -0.024032818 | I74: =I60/H60-1 -> 0.16699259 | J74: =J60/I60-1 -> 0.061269317 | K74: =K60/J60-1 -> 0.10782874 | L74: =L60/K60-1 -> 0.061928123 | S74: =S60/O60-1 -> -0.0011371893 | T74: =T60/P60-1 -> 0.033984854 | U74: =U60/Q60-1 -> 0.0266028 | V74: =V60/R60-1 -> 0.034915589 | W74: =W60/S60-1 -> 0.043374504 | X74: =X60/T60-1 -> -0.0083856868 | Y74: =Y60/U60-1 -> 0.044555884 | Z74: =Z60/V60-1 -> -0.031433972 | ... AD74: =AD60/Z60-1 -> 0.084798242 | AE74: =$AE60/$AA60-1 -> 0.23988045 | AF74: =AF60/AB60-1 -> 0.13417706 | AG74: =AG60/AC60-1 -> 0.16283409 | AH74: =AH60/AD60-1 -> 0.14053498 | AI74: =AI60/AE60-1 -> 0.13986799 | AJ74: =AJ60/AF60-1 -> 0.022734003 | AK74: =AK60/AG60-1 -> 0.023304803 | AL74: =AL60/AH60-1 -> 0.060121276 | AM74: =AM60/AI60-1 -> 0.093204354 | ... AU74: =AU60/AQ60-1 -> 0.019873871 | AW74: =AW60/O60-1 -> -0.021036002 | AX74: =AX60/P60-1 -> 0.052296036
B75: Other Countries | D75: =D61/C61-1 -> -0.24802151 | E75: =E61/D61-1 -> 0.11496515 | F75: =F61/E61-1 -> 0.12584885 | G75: =G61/F61-1 -> 0.29192532 | H75: =H61/G61-1 -> 0.33784013 | I75: =I61/H61-1 -> 0.18929762 | J75: =J61/I61-1 -> -0.15380232 | K75: =K61/J61-1 -> 0.10752428 | L75: =L61/K61-1 -> 0.052274279 | S75: =S61/O61-1 -> 0.10719489 | T75: =T61/P61-1 -> -0.037437804 | U75: =U61/Q61-1 -> 0.18414843 | V75: =V61/R61-1 -> 0.27389958 | W75: =W61/S61-1 -> 0.1625156 | X75: =X61/T61-1 -> 0.19339123 | Y75: =Y61/U61-1 -> 0.35262003 | Z75: =Z61/V61-1 -> 0.41536263 | ... AD75: =AD61/Z61-1 -> 0.21011229 | AE75: =$AE61/$AA61-1 -> 0.27159959 | AF75: =AF61/AB61-1 -> 0.14235286 | AG75: =AG61/AC61-1 -> 0.21632239 | AH75: =AH61/AD61-1 -> 0.1429087 | AI75: =AI61/AE61-1 -> -0.020302283 | AJ75: =AJ61/AF61-1 -> -0.18793535 | AK75: =AK61/AG61-1 -> -0.21322818 | AL75: =AL61/AH61-1 -> -0.16661276 | AM75: =AM61/AI61-1 -> 0.22605068 | ... AU75: =AU61/AQ61-1 -> 0.13097888 | AW75: =AW61/O61-1 -> 0.081996543 | AX75: =AX61/P61-1 -> -0.018244075
B76: Total | D76: =D62/C62-1 -> -0.028109271 | E76: =E62/D62-1 -> -0.02710302 | F76: =F62/E62-1 -> 0.058522609 | G76: =G62/F62-1 -> 0.070075367 | H76: =H62/G62-1 -> 0.032087886 | I76: =I62/H62-1 -> 0.18123588 | J76: =J62/I62-1 -> 0.04557821 | K76: =K62/J62-1 -> 0.071718265 | L76: =L62/K62-1 -> 0.051734473 | S76: =S62/O62-1 -> 0.037707386 | T76: =T62/P62-1 -> 0.025615866 | U76: =U62/Q62-1 -> 0.077138749 | V76: =V62/R62-1 -> 0.095455911 | W76: =W62/S62-1 -> 0.071064729 | X76: =X62/T62-1 -> 0.097270187 | Y76: =Y62/U62-1 -> 0.081108636 | Z76: =Z62/V62-1 -> 0.031222715 | ... AD76: =AD62/Z62-1 -> 0.1146258 | AE76: =$AE62/$AA62-1 -> 0.23551158 | AF76: =AF62/AB62-1 -> 0.15100954 | AG76: =AG62/AC62-1 -> 0.20990555 | AH76: =AH62/AD62-1 -> 0.13666179 | AI76: =AI62/AE62-1 -> 0.12503883 | AJ76: =AJ62/AF62-1 -> 0.039454309 | AK76: =AK62/AG62-1 -> 0.0058318923 | AL76: =AL62/AH62-1 -> 0.016635901 | AM76: =AM62/AI62-1 -> 0.077385186 | ... AU76: =AU62/AQ62-1 -> 0.068138871 | AW76: =AW62/O62-1 -> 0.023725908 | AX76: =AX62/P62-1 -> 0.038298492
