Workbook
Name \A: #REF!
Name \B: #REF!
Name \C: #REF!
Name \L: #REF!
Name \M: #REF!
Name \P: #REF!
Name \Y: #REF!
Name _01_30_04: MonthlyOpStats
Name _01_30_04: MonthlyOpStats
Name _01_30_04: MonthlyOpStats
Name _01_30_04: MonthlyOpStats
Name _1_30_01: MonthlyOpStats
Name _1_30_01: MonthlyOpStats
Name _1_30_01: MonthlyOpStats
Name _1_30_01: MonthlyOpStats
Name _1_30_02: MonthlyOpStats
Name _1_30_02: MonthlyOpStats
Name _1_30_02: MonthlyOpStats
Name _1_30_02: MonthlyOpStats
Name _1_31_01: MonthlyOpStats
Name _1_31_01: MonthlyOpStats
Name _1_31_01: MonthlyOpStats
Name _1_31_01: MonthlyOpStats
Name _1_31_02: MonthlyOpStats
Name _1_31_02: MonthlyOpStats
Name _1_31_02: MonthlyOpStats
Name _1_31_02: MonthlyOpStats
Name _12_31_05: MonthlyOpStats
Name _12_31_05: MonthlyOpStats
Name _12_31_05: MonthlyOpStats
Name _12_31_05: MonthlyOpStats
Name _A: #REF!
Name _A___0: #REF!
Name _B: #REF!
Name _B___0: #REF!
Name _C: #REF!
Name _C___0: #REF!
Name _ent1: [15]Inputs!$J$17
Name _ent10: [15]Inputs!$J$476
Name _ent11: [15]Inputs!$J$527
Name _ent12: [15]Inputs!$J$578
Name _ent13: [15]Inputs!$J$629
Name _ent14: [15]Inputs!$J$680
Name _ent15: [15]Inputs!$J$731
Name _ent2: [15]Inputs!$J$68
Name _ent3: [15]Inputs!$J$119
Name _ent4: [15]Inputs!$J$170
Name _ent5: [15]Inputs!$J$221
Name _ent6: [15]Inputs!$J$272
Name _ent7: [15]Inputs!$J$323
Name _ent8: [15]Inputs!$J$374
Name _ent9: [15]Inputs!$J$425
Name _eps1: [15]Inputs!$P$42
Name _eps10: [15]Inputs!$P$501
Name _eps11: [15]Inputs!$P$552
Name _eps12: [15]Inputs!$P$603
Name _eps13: [15]Inputs!$P$654
Name _eps14: [15]Inputs!$P$705
Name _eps15: [15]Inputs!$P$756
Name _eps2: [15]Inputs!$P$93

Sheet Capitalisation
A3: 1Q26
B4: As of March 2026 | C4: TRY (mn) | D4: USD( mn) | E4: Leverage (TRY) | F4: Leverage (USD) | H4: Company Reported
H5: Net Financial Debt / EBITDA on Combined Basis | I5: 1.5
B6: Current: | C6: =SUM(C7:C9) -> 759029 | D6: =SUM(D7:D9) -> 17074.597
B7: Bank borrowings | C7: 546345 | D7: =+C7/$C$28 -> 12290.203
B8: Issued debt securities | C8: 207996 | D8: =+C8/$C$28 -> 4678.9356
B9: Factoring debts | C9: 4688 | D9: =+C9/$C$28 -> 105.45804
B11: Non Current: | C11: =SUM(C12:C13) -> 602002 | D11: =SUM(D12:D13) -> 13542.225
B12: Bank borrowings | C12: 226305 | D12: =+C12/$C$28 -> 5090.8023
B13: Issued debt securities | C13: 375697 | D13: =+C13/$C$28 -> 8451.4225
B15: Lease Liabilities: | C15: =SUM(C16:C17) -> 23468 | D15: =SUM(D16:D17) -> 527.92006
B16: Current leases | C16: 7141 | D16: =+C16/$C$28 -> 160.63905
B17: Non-current leases | C17: 16327 | D17: =+C17/$C$28 -> 367.28101
B20: Total debt | C20: =SUM(C6,C11,C15) -> 1384499 | D20: =+C20/$C28 -> 31144.742 | E20: =+C20/C27 -> 5.9009769 | F20: =+D20/D27 -> 5.5027837
B21: Cash * | C21: =Model!BI$56 -> 898265 | D21: =+C21/$C28 -> 20206.754
B22: Net debt | C22: =+C20-C21 -> 486234 | D22: =+D20-D21 -> 10937.987 | E22: =+C22/C27 -> 2.0724144 | F22: =+D22/D27 -> 1.9325695
B24: Market cap | C24: =Model!BI$60 -> 469141.1 | D24: =+C24/$C28 -> 10553.477
B25: Total capitalisation | C25: =+C24+C22 -> 955375.1 | D25: =+D24+D22 -> 21491.464 | E25: =+C25/C27 -> 4.0719758 | F25: =+D25/D27 -> 3.7972021
B27: LTM EBITDA | C27: =Model!BI$44 -> 234622 | D27: =+C27/C29 -> 5659.8157
B28: TRY/USD exchange rate - end period | C28: =Model!BI$95 -> 44.4537
B29: TRY/USD exchange rate - average | C29: =AVERAGE(Model!$BF$96:$BI$96) -> 41.454
B30: check | C30: =C20-Model!$BI$55 -> 0
B33: Liquidity table | C33: TRY (mn) | D33: USD (mn)
B34: Cash | C34: =C21 -> 898265 | D34: =C34/$C$28 -> 20206.754
B35: Total | C35: =SUM(C34:C34) -> 898265 | D35: =SUM(D34:D34) -> 20206.754
B40: Debt maturity schedule: | C40: TRY mn | D40: USDmn
B41: Less than 1 year | C41: =Model!$BI$53 -> 766170 | D41: =C41/$C$28 -> 17235.236
B42: 1-2 years | C42: 180601 | D42: =C42/$C$28 -> 4062.6764
B43: 2-3 years | C43: 146917 | D43: =C43/$C$28 -> 3304.9442
B44: 3-4 years | C44: 87374 | D44: =C44/$C$28 -> 1965.5057
B45: 4-5 years | C45: 64503 | D45: =C45/$C$28 -> 1451.0153
B46: 5 years and over | C46: 138934 | D46: =C46/$C$28 -> 3125.3641
B47: Total | C47: =SUM(C41:C46) -> 1384499 | D47: =SUM(D41:D46) -> 31144.742
B48: check | C48: =C47-C20 -> 0
A53: FY25
B54: As of Dec 2025 | C54: TRY (mn) | D54: USD( mn) | E54: Leverage (TRY) | F54: Leverage (USD) | H54: Company Reported
H55: Net Financial Debt / EBITDA on Combined Basis | I55: 1.2
B56: Current: | C56: =SUM(C57:C59) -> 748278 | D56: =SUM(D57:D59) -> 17418.544
B57: Bank borrowings | C57: 504342 | D57: =+C57/$C$78 -> 11740.16
B58: Issued debt securities | C58: 240032 | D58: =+C58/$C$78 -> 5587.5061
B59: Factoring debts | C59: 3904 | D59: =+C59/$C$78 -> 90.877983
B61: Non Current: | C61: =SUM(C62:C63) -> 586223 | D61: =SUM(D62:D63) -> 13646.2
B62: Bank borrowings | C62: 263917 | D62: =+C62/$C$78 -> 6143.5053
B63: Issued debt securities | C63: 322306 | D63: =+C63/$C$78 -> 7502.6944
B65: Lease Liabilities: | C65: =SUM(C66:C67) -> 20767 | D65: =SUM(D66:D67) -> 483.41779
B66: Current leases | C66: 5451 | D66: =+C66/$C$78 -> 126.88931
B67: Non-current leases | C67: 15316 | D67: =+C67/$C$78 -> 356.52848
B70: Total debt | C70: =SUM(C56,C61,C65) -> 1355268 | D70: =+C70/$C78 -> 31548.161 | E70: =+C70/C77 -> 6.3818762 | F70: =+D70/D77 -> 5.9025302
B71: Cash * | C71: =Model!BH$56 -> 821118 | D71: =+C71/$C78 -> 19114.126
B72: Net debt | C72: =+C70-C71 -> 534150 | D72: =+D70-D71 -> 12434.035 | E72: =+C72/C77 -> 2.5152805 | F72: =+D72/D77 -> 2.3263565
B74: Market cap | C74: =Model!BH$60 -> 566773.21 | D74: =+C74/$C78 -> 13193.444
B75: Total capitalisation | C75: =+C74+C72 -> 1100923.2 | D75: =+D74+D72 -> 25627.48 | E75: =+C75/C77 -> 5.1841818 | F75: =+D75/D77 -> 4.7947952
B77: LTM EBITDA | C77: =Model!BH$44 -> 212362 | D77: =+C77/C79 -> 5344.8538
B78: TRY/USD exchange rate - end period | C78: =Model!BH$95 -> 42.9587
B79: TRY/USD exchange rate - average | C79: =AVERAGE(Model!$BE$96:$BH$96) -> 39.73205
B80: check | C80: =C70-Model!$BH$55 -> 0
B83: Liquidity table | C83: TRY (mn) | D83: USD (mn)
B84: Cash | C84: =C71 -> 821118 | D84: =C84/$C$78 -> 19114.126
B85: Total | C85: =SUM(C84:C84) -> 821118 | D85: =SUM(D84:D84) -> 19114.126
B88: Debt maturity schedule (undiscounted cash flows) | C88: TRY (mn) | D88: USD (mn)
B89: Less than 1 year | C89: =280512+562286 -> 842798 | D89: =C89/$C$78 -> 19618.797
B90: 1-5 years | C90: 539256 | D90: =C90/$C$78 -> 12552.894
B91: More than 5 years | C91: 184210 | D91: =C91/$C$78 -> 4288.072
B92: Total | C92: =SUM(C89:C91) -> 1566264 | D92: =SUM(D89:D91) -> 36459.763
B93: Carrying amount | C93: 1334501 | D93: =C93/$C$78 -> 31064.744
B94: check | C94: =C93-C56-C61 -> 0
B97: Lease maturity schedule (undiscounted cash flows) | C97: TRY (mn) | D97: USD (mn)
B98: Less than 1 year | C98: =2206+4674 -> 6880 | D98: =C98/$C$78 -> 160.15382
B99: 1-5 years | C99: 13189 | D99: =C99/$C$78 -> 307.01581
B100: More than 5 years | C100: 5923 | D100: =C100/$C$78 -> 137.87661
B101: Total | C101: =SUM(C98:C100) -> 25992 | D101: =SUM(D98:D100) -> 605.04624
B102: Carrying amount | C102: 20767 | D102: =C102/$C$78 -> 483.41779
B103: check | C103: =C102-C65 -> 0
B106: Debt maturity schedule: | C106: TRY mn | D106: USDmn
B107: Less than 1 year | C107: =Model!$BH$53 -> 753729 | D107: =C107/$C$78 -> 17545.433
B108: 1-2 years | C108: 179857 | D108: =C108/$C$78 -> 4186.7422
B109: 2-3 years | C109: 132645 | D109: =C109/$C$78 -> 3087.7331
B110: 3-4 years | C110: 42165 | D110: =C110/$C$78 -> 981.52412
B111: 4-5 years | C111: 95050 | D111: =C111/$C$78 -> 2212.5902
B112: 5 years and over | C112: 151822 | D112: =C112/$C$78 -> 3534.1386
B113: Total | C113: =SUM(C107:C112) -> 1355268 | D113: =SUM(D107:D112) -> 31548.161
B114: check | C114: =C113-C70 -> 0
A120: 3Q25
B121: As of Sep 2025 | C121: TRY mn | D121: USDmn | E121: Leverage | H121: Company Reported
H122: Net financial debt
B123: Lease liabilities | C123: =14806+5992 -> 20798 | D123: =+C123/$C135 -> 500.12985 | H123: Net Financial Debt / EBITDA on Combined Basis | I123: 1.4
B124: Bank borrowings | C124: =475520+212256 -> 687776 | D124: =+C124/$C135 -> 16538.961
B125: Factoring payables | C125: =2634 -> 2634 | D125: =+C125/$C135 -> 63.339842
B126: Debt securiteis in Issue | C126: =227282+271896 -> 499178 | D126: =+C126/$C135 -> 12003.742
B127: Total debt | C127: =SUM(C123:C126) -> 1210386 | D127: =+C127/$C135 -> 29106.172 | E127: =+C127/C134 -> 7.0274447
B128: Cash * | C128: =Model!BG$56 -> 863544 | D128: =+C128/$C135 -> 20765.657
B129: Net debt | C129: =+C127-C128 -> 346842 | D129: =+D127-D128 -> 8340.5154 | E129: =+C129/C134 -> 2.0137485
B131: Market cap | C131: =Model!BG$60 -> 488634 | D131: =+C131/$C135 -> 11750.19
B132: Total capitalisation | C132: =+C131+C129 -> 835476 | D132: =+D131+D129 -> 20090.705 | E132: =+C132/C134 -> 4.8507347
B134: LTM EBITDA | C134: =Model!BG$44 -> 172237 | D134: =+C134/C136 -> 4550.1981
B135: TRY/USD exchange rate - end period | C135: =Model!BG$95 -> 41.5852
B136: TRY/USD exchange rate - average | C136: =AVERAGE(Model!$BD$96:$BG$96) -> 37.852638
B139: Liquidity table | C139: TRY mn | D139: USDmn
B140: Cash | C140: =C128 -> 863544 | D140: =C140/$C135 -> 20765.657
B141: Total | C141: =SUM(C140:C140) -> 863544 | D141: =SUM(D140:D140) -> 20765.657
...

Sheet Model
B2: KOC HOLDING | D2: Annual | E2: Annual | F2: Annual | G2: Annual | H2: Annual | I2: Annual | J2: Annual | K2: Annual | L2: Annual | M2: Annual | N2: Annual | O2: Annual | P2: Annual | Q2: Annual | R2: Annual | S2: Annual | T2: Annual | U2: LTM | V2: Annual | W2: Annual | Y2: Quarters | Z2: Quarters | AA2: Quarters | AB2: Quarters | AC2: Quarters | AD2: Quarters | AE2: Quarters | AF2: Quarters | AG2: Quarters | AH2: Quarters | AI2: Quarters | AJ2: Quarters | AK2: Quarters | AL2: Quarters | AM2: Quarters | AN2: Quarters | AO2: Quarters | AP2: Quarters | AQ2: Quarters | AR2: Quarters | AS2: Quarters | AT2: Quarters | AU2: Quarters | AV2: Quarters | AW2: Quarters | AX2: Quarters | AY2: Quarters | AZ2: Quarters | BA2: Quarters | BB2: Quarters | BC2: Quarters | BD2: Quarters | BE2: Quarters | BF2: Quarters | BG2: Quarters | BH2: Quarters | BI2: Quarters | BK2: 9M | BL2: 9M | BN2: Quarters | BO2: Quarters | BP2: Quarters | BQ2: Quarters | BR2: Quarters | BS2: H1 | BT2: H2 | BU2: H1 | BV2: H2 | BW2: H1 | BX2: H2 | BY2: H1 | BZ2: H2 | CA2: H1 | CB2: H2 | CC2: H1 | CD2: H2 | CE2: H1 | CF2: H2 | CG2: H1 | CI2: H1 | CJ2: H2 | CK2: H1
B3: TRY mn | D3: 41274 | E3: =D3+365 -> 41639 | F3: =E3+365 -> 42004 | G3: =F3+365 -> 42369 | H3: =G3+365 -> 42734 | I3: =H3+365 -> 43099 | J3: =I3+365 -> 43464 | K3: =J3+365 -> 43829 | L3: =K3+365 -> 44194 | ... N3: =M3+365 -> 44924 | O3: =N3 -> 44924 | P3: =N3+365 -> 45289 | Q3: =O3+365 -> 45289 | R3: =P3+365 -> 45654 | S3: =Q3+365 -> 45654 | T3: =R3+365 -> 46019 | U3: =BI3 -> 46111 | V3: =G3+366 -> 42735 | W3: =V3+365 -> 43100 | Y3: 42825 | Z3: =EDATE(Y3,3) -> 42916 | AA3: =EDATE(Z3,3) -> 43008 | AB3: =EDATE(AA3,3) -> 43099 | AC3: =EDATE(AB3,3) -> 43189 | AD3: =EDATE(AC3,3) -> 43281 | AE3: =EDATE(AD3,3) -> 43373 | AF3: =EDATE(AE3,3) -> 43464 | AG3: =EDATE(AF3,3) -> 43554 | ... BI3: =EDATE(BH3,3) -> 46111 | BK3: 45565 | BL3: 45930 | BN3: 45381 | BO3: =EDATE(BN3,3) -> 45473 | BP3: =EDATE(BO3,3) -> 45565 | BQ3: =EDATE(BP3,3) -> 45656 | BR3: 45746 | BS3: 42156 | BT3: 42369 | BU3: 42522 | BV3: 42735 | BW3: 43983 | BX3: 44196 | BY3: 44348 | BZ3: 44561 | CA3: 44713 | CB3: 44926 | CC3: 45078 | CD3: 45291 | CE3: 45444 | CF3: 45657 | CG3: 45809 | CI3: 45078 | CJ3: 45291 | CK3: 45444
D4: Act | E4: Act | F4: Act | G4: Act | H4: Act | I4: Act | J4: Act | K4: Act | L4: Act | M4: Act | N4: Act | O4: Act | P4: Act | Q4: Act | R4: Act | S4: Act | T4: Act | U4: Act | V4: Proj | W4: Proj | Y4: Act | Z4: Act | AA4: Act | AB4: Act | AC4: Act | AD4: Act | AE4: Act | AF4: Act | AG4: Act | AH4: Act | AI4: Act | AJ4: Act | AK4: Act | AL4: Act | AM4: Act | AN4: Act | AO4: Act | AP4: Act | AQ4: Act | AR4: Act | AS4: Act | AT4: Act | AU4: Act | AV4: Act | AW4: Act | AX4: Act | AY4: Act | AZ4: Act | BA4: Act | BB4: Act | BC4: Act | BD4: Act | BE4: Act | BF4: Act | BG4: Act | BH4: Act | BI4: Act | BK4: Act | BL4: Act | BN4: Act | BO4: Act | BP4: Act | BQ4: Act | BR4: Act | BS4: Act | BT4: Act | BU4: Act | BV4: Act | BW4: Act | BX4: Act | BY4: Act | BZ4: Act | CA4: Act | CB4: Act | CC4: Act | CD4: Act | CE4: Act | CF4: Act | CG4: Act | CI4: Restated | CJ4: Restated | CK4: Restated
D5: FY | E5: FY | F5: FY | G5: FY | H5: FY | I5: FY | J5: FY | K5: FY | L5: FY | M5: FY | N5: FY | O5: FY | P5: FY | Q5: FY | R5: FY | S5: FY | T5: FY | U5: FY | Y5: 1Q | Z5: 2Q | AA5: 3Q | AB5: 4Q | AC5: 1Q | AD5: 2Q | AE5: 3Q | AF5: 4Q | AG5: 1Q | AH5: 2Q | AI5: 3Q | AJ5: 4Q | AK5: 1Q | AL5: 2Q | AM5: 3Q | AN5: 4Q | AO5: 1Q | AP5: 2Q | AQ5: 3Q | AR5: 4Q | AS5: 1Q | AT5: 2Q | AU5: 3Q | AV5: 4Q | AW5: 1Q | AX5: 2Q | AY5: 3Q | AZ5: 4Q | BA5: 1Q | BB5: 2Q | BC5: 3Q | BD5: 4Q | BE5: 1Q | BF5: 2Q | BG5: 3Q | BH5: 4Q | BI5: 1Q | BK5: 9M | BL5: 9M | BS5: 6M | BT5: 6M | BU5: 6M | BV5: 6M | BW5: 6M | BX5: 6M | BY5: 6M | BZ5: 6M | CA5: 6M | CB5: 6M | CC5: 6M | CD5: 6M | CE5: 6M | CF5: 6M | CG5: 6M
B6: SUMMARY FINANCIALS - CONSOLIDATED | O6: Restated | Q6: Restated | S6: Restated | BN6: Restated | BO6: Restated | BP6: Restated | BQ6: Restated | BR6: Restated
B7: Combined revenues by segment:
B8: Energy | D8: 63225 | E8: 65458 | F8: 68343 | G8: 62397 | H8: 67273.473 | I8: 97574.116 | J8: 153250.04 | K8: 153426.36 | L8: 115839.99 | M8: 229549.24 | N8: 713727 | O8: 1353617 | P8: 1051742 | Q8: 1518495 | R8: 1291970 | S8: 1691087 | T8: 1419042 | U8: =BG8+BF8+BH8+BI8 -> 1558911 | Y8: 21706.751 | Z8: =44766.375-Y8 -> 23059.624 | AA8: =70993.13-Z8-Y8 -> 26226.755 | AB8: =I8-AA8-Z8-Y8 -> 26580.986 | AC8: 25753.228 | AD8: =61647.231-AC8 -> 35894.003 | AE8: =111704.372-AD8-AC8 -> 50057.141 | AF8: =J8-AE8-AD8-AC8 -> 41545.665 | AG8: 35505.985 | AH8: =75465.13-AG8 -> 39959.145 | AI8: =115889.709-AH8-AG8 -> 40424.579 | AJ8: =K8-AI8-AH8-AG8 -> 37536.655 | AK8: 29045.338 | AL8: =48227.598-AK8 -> 19182.26 | AM8: =81690.069-AL8-AK8 -> 33462.471 | AN8: =L8-AM8-AL8-AK8 -> 34149.92 | AO8: 33280.593 | AP8: =82076.796-AO8 -> 48796.203 | AQ8: =146275.599-AP8-AO8 -> 64198.803 | AR8: =M8-AQ8-AP8-AO8 -> 83273.639 | AS8: 113178.05 | AT8: =310142.923-AS8 -> 196964.87 | AU8: =528048.25-AT8-AS8 -> 217905.33 | AV8: =N8-AU8-AT8-AS8 -> 185678.75 | AW8: 253773 | AX8: 282047 | AY8: =1056315-AX8-AW8 -> 520495 | AZ8: =Q8-AY8-AX8-AW8 -> 462180 | BA8: 258566 | BB8: 288610 | BC8: =948415-BB8-BA8 -> 401239 | BD8: =R8-BC8-BB8-BA8 -> 343555 | BE8: 264705 | BF8: 308079 | BG8: 390749 | BH8: =T8-BG8-BF8-BE8 -> 455509 | BI8: 404574 | BK8: 1264180 | BL8: 1023611 | BN8: 357090 | BO8: 389765 | BP8: 417656 | BQ8: =S8-BN8-BO8-BP8 -> 526576 | BR8: 346406 | BS8: 29443 | BT8: =G8-BS8 -> 32954 | BU8: 28996 | BV8: =H8-BU8 -> 38277.473 | BW8: 48227.598 | BX8: =L8-BW8 -> 67612.391 | BY8: =82076.796 -> 82076.796 | BZ8: =M8-BY8 -> 147472.44 | CA8: 310142.92 | CB8: =N8-CA8 -> 403584.08 | CC8: 307307 | CD8: =P8-CC8 -> 744435 | CE8: 568908 | CF8: =R8-CE8 -> 723062 | CG8: 588686 | CI8: 55715 | CJ8: =Q8-CI8 -> 1462780 | CK8: 768305
B9: Automotive | D9: 22172 | E9: 25114 | F9: 26829 | G9: 35868 | H9: 42703.575 | I9: 55556.629 | J9: 65716.103 | K9: 74447.601 | L9: 98338.398 | M9: 139014.96 | N9: 312873 | O9: 589035 | P9: 739103 | Q9: 1067110 | R9: 971573 | S9: 1271711 | T9: 1444986 | U9: =BG9+BF9+BH9+BI9 -> 1559576 | Y9: 12165.689 | Z9: =25936.526-Y9 -> 13770.837 | AA9: =38317.951-Z9-Y9 -> 12381.425 | AB9: =I9-AA9-Z9-Y9 -> 17238.678 | AC9: 14500.697 | AD9: =30978.781-AC9 -> 16478.084 | AE9: =46354.832-AD9-AC9 -> 15376.051 | AF9: =J9-AE9-AD9-AC9 -> 19361.271 | AG9: 16272.41 | AH9: =34500.939-AG9 -> 18228.529 | AI9: =51563.928-AH9-AG9 -> 17062.989 | AJ9: =K9-AI9-AH9-AG9 -> 22883.673 | AK9: 17854.572 | AL9: =30904.898-AK9 -> 13050.326 | AM9: =57973.607-AL9-AK9 -> 27068.709 | AN9: =L9-AM9-AL9-AK9 -> 40364.791 | AO9: 30610.845 | AP9: =57579.073-AO9 -> 26968.228 | AQ9: =90847.275-AP9-AO9 -> 33268.202 | AR9: =M9-AQ9-AP9-AO9 -> 48167.689 | AS9: 50194.507 | AT9: =114997.673-AS9 -> 64803.166 | AU9: =199588.174-AT9-AS9 -> 84590.501 | AV9: =N9-AU9-AT9-AS9 -> 113284.83 | AW9: 196083 | AX9: 232543 | AY9: =733428-AX9-AW9 -> 304802 | AZ9: =Q9-AY9-AX9-AW9 -> 333682 | BA9: 211002 | BB9: 182446 | BC9: =668056-BB9-BA9 -> 274608 | BD9: =R9-BC9-BB9-BA9 -> 303517 | BE9: 236908 | BF9: 325057 | BG9: 343285 | BH9: =T9-BG9-BF9-BE9 -> 539736 | BI9: 351498 | BK9: 890479 | BL9: 962719 | BN9: 291402 | BO9: 246392 | BP9: 293510 | BQ9: =S9-BN9-BO9-BP9 -> 440407 | BR9: 310030 | BS9: 16257 | BT9: =G9-BS9 -> 19611 | BU9: 19920 | BV9: =H9-BU9 -> 22783.575 | BW9: 30904.898 | BX9: =L9-BW9 -> 67433.5 | BY9: =57579.073 -> 57579.073 | BZ9: =M9-BY9 -> 81435.891 | CA9: 114997.67 | CB9: =N9-CA9 -> 197875.33 | CC9: 247251 | CD9: =P9-CC9 -> 491852 | CE9: 411183 | CF9: =R9-CE9 -> 560390 | CG9: 576196 | CI9: 445107 | CJ9: =Q9-CI9 -> 622003 | CK9: 555299
B10: Consumer durables | D10: 11194 | E10: 11806 | F10: 12941 | G10: 14651 | H10: 17997.17 | I10: 23360.88 | J10: 30244.192 | K10: 36310.763 | L10: 47170.723 | M10: 76889.132 | N10: 153713 | O10: 291269 | P10: 297189 | Q10: 429079 | R10: 485412 | S10: 635365 | T10: 597907 | U10: =BG10+BF10+BH10+BI10 -> 615784 | Y10: 5085.728 | Z10: =10900.311-Y10 -> 5814.583 | AA10: =17034.106-Z10-Y10 -> 6133.795 | AB10: =I10-AA10-Z10-Y10 -> 6326.774 | AC10: 6173.981 | AD10: =13734.803-AC10 -> 7560.822 | AE10: =22125.788-AD10-AC10 -> 8390.985 | AF10: =J10-AE10-AD10-AC10 -> 8118.404 | AG10: 7886.199 | AH10: =17602.89-AG10 -> 9716.691 | AI10: =26769.357-AH10-AG10 -> 9166.467 | AJ10: =K10-AI10-AH10-AG10 -> 9541.406 | AK10: 9028.126 | AL10: =18168.213-AK10 -> 9140.087 | AM10: =32219.42-AL10-AK10 -> 14051.207 | AN10: =L10-AM10-AL10-AK10 -> 14951.303 | AO10: 15105.577 | AP10: =31855.798-AO10 -> 16750.221 | AQ10: =52304.98-AP10-AO10 -> 20449.182 | AR10: =M10-AQ10-AP10-AO10 -> 24584.152 | AS10: 32558.289 | AT10: =70240.258-AS10 -> 37681.969 | AU10: =109212.105-AT10-AS10 -> 38971.847 | AV10: =N10-AU10-AT10-AS10 -> 44500.895 | AW10: 81504 | AX10: 94599 | AY10: =303150-AX10-AW10 -> 127047 | AZ10: =Q10-AY10-AX10-AW10 -> 125929 | BA10: 86490 | BB10: 113384 | BC10: =344026-BB10-BA10 -> 144152 | BD10: =R10-BC10-BB10-BA10 -> 141386 | BE10: 125545 | BF10: 140988 | BG10: 140857 | BH10: =T10-BG10-BF10-BE10 -> 190517 | BI10: 143422 | BK10: 458566 | BL10: 435498 | BN10: 119446 | BO10: 153124 | BP10: 157829 | BQ10: =S10-BN10-BO10-BP10 -> 204966 | BR10: 164294 | BS10: 6510 | BT10: =G10-BS10 -> 8141 | BU10: 8425 | BV10: =H10-BU10 -> 9572.17 | BW10: 18168.213 | BX10: =L10-BW10 -> 29002.51 | BY10: =31855.798 -> 31855.798 | BZ10: =M10-BY10 -> 45033.334 | CA10: 70240.258 | CB10: =N10-CA10 -> 83472.742 | CC10: 103353 | CD10: =P10-CC10 -> 193836 | CE10: 207143 | CF10: =R10-CE10 -> 278269 | CG10: 274074 | CI10: 182953 | CJ10: =Q10-CI10 -> 246126 | CK10: 279745
B11: Finance | D11: 12985 | E11: 13834 | F11: 16838 | G11: 21514 | H11: 24235.787 | I11: 29699.776 | J11: 43227.187 | K11: 47843.543 | L11: 45183.224 | M11: 73513.573 | N11: 168699 | O11: 317826 | P11: 388576 | Q11: 561022 | R11: 710437 | S11: 929906 | T11: 923792 | U11: =BG11+BF11+BH11+BI11 -> 982056 | Y11: 6839.52 | Z11: =14096.285-Y11 -> 7256.765 | AA11: =21544.943-Z11-Y11 -> 7448.658 | AB11: =I11-AA11-Z11-Y11 -> 8154.833 | AC11: 8405.358 | AD11: =17865.292-AC11 -> 9459.934 | AE11: =30424.138-AD11-AC11 -> 12558.846 | AF11: =J11-AE11-AD11-AC11 -> 12803.049 | AG11: 12149.961 | AH11: =24643.626-AG11 -> 12493.665 | AI11: =36596.155-AH11-AG11 -> 11952.529 | AJ11: =K11-AI11-AH11-AG11 -> 11247.388 | AK11: 10945.379 | AL11: =21200.874-AK11 -> 10255.495 | AM11: =32785.443-AL11-AK11 -> 11584.569 | AN11: =L11-AM11-AL11-AK11 -> 12397.781 | AO11: 14095.293 | AP11: =29611.25-AO11 -> 15515.957 | AQ11: =47600.715-AP11-AO11 -> 17989.465 | AR11: =M11-AQ11-AP11-AO11 -> 25912.858 | AS11: 27471.108 | AT11: =63841.977-AS11 -> 36370.869 | AU11: =111649.534-AT11-AS11 -> 47807.557 | AV11: =N11-AU11-AT11-AS11 -> 57049.466 | AW11: 86708 | AX11: 120107 | AY11: =378450-AX11-AW11 -> 171635 | AZ11: =Q11-AY11-AX11-AW11 -> 182572 | BA11: 139382 | BB11: 156197 | BC11: =503349-BB11-BA11 -> 207770 | BD11: =R11-BC11-BB11-BA11 -> 207088 | BE11: 187607 | BF11: 201398 | BG11: 225849 | BH11: =T11-BG11-BF11-BE11 -> 308938 | BI11: 245871 | BK11: 670934 | BL11: 656161 | BN11: 192492 | BO11: 210942 | BP11: 224796 | BQ11: =S11-BN11-BO11-BP11 -> 301676 | BR11: 245512 | BS11: 9973 | BT11: =G11-BS11 -> 11541 | BU11: 11993 | BV11: =H11-BU11 -> 12242.787 | BW11: 21200.874 | BX11: =L11-BW11 -> 23982.35 | BY11: =29611.25 -> 29611.25 | BZ11: =M11-BY11 -> 43902.323 | CA11: 63841.977 | CB11: =N11-CA11 -> 104857.02 | CC11: 118506 | CD11: =P11-CC11 -> 270070 | CE11: 307294 | CF11: =R11-CE11 -> 403143 | CG11: 400275 | CI11: 214103 | CJ11: =Q11-CI11 -> 346919 | CK11: 414997
B12: Other | D12: 7008 | E12: 7265 | F12: 8514 | G12: 9880 | H12: 9581.51 | I12: 11107.987 | J12: 13837.305 | K12: 17014.195 | L12: 18365.73 | M12: 25364.622 | N12: 56527 | O12: 106791 | P12: 116697 | Q12: 168486 | R12: 166325 | S12: 217706 | T12: 217750 | U12: =BG12+BF12+BH12+BI12 -> 230369 | Y12: 2373.273 | Z12: =5057.218-Y12 -> 2683.945 | AA12: =7899.816-Z12-Y12 -> 2842.598 | AB12: =I12-AA12-Z12-Y12 -> 3208.171 | AC12: 2645.087 | AD12: =5882.612-AC12 -> 3237.525 | AE12: =9555.058-AD12-AC12 -> 3672.446 | AF12: =J12-AE12-AD12-AC12 -> 4282.247 | AG12: 3580.001 | AH12: =7892.198-AG12 -> 4312.197 | AI12: =12208.894-AH12-AG12 -> 4316.696 | AJ12: =K12-AI12-AH12-AG12 -> 4805.301 | AK12: 3825.729 | AL12: =7625.018-AK12 -> 3799.289 | AM12: =11943.176-AL12-AK12 -> 4318.158 | AN12: =L12-AM12-AL12-AK12 -> 6422.554 | AO12: 4584.137 | AP12: =10263.258-AO12 -> 5679.121 | AQ12: =16332.193-AP12-AO12 -> 6068.935 | AR12: =M12-AQ12-AP12-AO12 -> 9032.429 | AS12: 9527.536 | AT12: =22832.153-AS12 -> 13304.617 | AU12: =37428.86-AT12-AS12 -> 14596.707 | AV12: =N12-AU12-AT12-AS12 -> 19098.14 | AW12: 26204 | AX12: 36307 | AY12: =110914-AX12-AW12 -> 48403 | AZ12: =Q12-AY12-AX12-AW12 -> 57572 | BA12: 30042 | BB12: 35894 | BC12: =112056-BB12-BA12 -> 46120 | BD12: =R12-BC12-BB12-BA12 -> 54269 | BE12: 40111 | BF12: 49493 | BG12: 52923 | BH12: =T12-BG12-BF12-BE12 -> 75223 | BI12: 52730 | BK12: 149364 | BL12: 151841 | BN12: 41489 | BO12: 48475 | BP12: 49970 | BQ12: =S12-BN12-BO12-BP12 -> 77772 | BR12: 52491 | BS12: 4618 | BT12: =G12-BS12 -> 5262 | BU12: 4616 | BV12: =H12-BU12 -> 4965.51 | BW12: 7625.018 | BX12: =L12-BW12 -> 10740.712 | BY12: =10263.258 -> 10263.258 | BZ12: =M12-BY12 -> 15101.364 | CA12: 22832.153 | CB12: =N12-CA12 -> 33694.847 | CC12: 35744 | CD12: =P12-CC12 -> 80953 | CE12: 68461 | CF12: =R12-CE12 -> 97864 | CG12: 92013 | CI12: 64713 | CJ12: =Q12-CI12 -> 103773 | CK12: 92456
B13: Total combined revenues | D13: =SUM(D8:D12) -> 116584 | E13: =SUM(E8:E12) -> 123477 | F13: =SUM(F8:F12) -> 133465 | G13: =SUM(G8:G12) -> 144310 | H13: =SUM(H8:H12) -> 161791.52 | I13: =SUM(I8:I12) -> 217299.39 | J13: =SUM(J8:J12) -> 306274.82 | K13: =SUM(K8:K12) -> 329042.47 | ... U13: =SUM(U8:U12) -> 4946696 | Y13: =SUM(Y8:Y12) -> 48170.961 | Z13: =SUM(Z8:Z12) -> 52585.754 | AA13: =SUM(AA8:AA12) -> 55033.231 | AB13: =SUM(AB8:AB12) -> 61509.442 | AC13: =SUM(AC8:AC12) -> 57478.351 | AD13: =SUM(AD8:AD12) -> 72630.368 | AE13: =SUM(AE8:AE12) -> 90055.469 | AF13: =SUM(AF8:AF12) -> 86110.636 | ... BI13: =SUM(BI8:BI12) -> 1198095 | BK13: =SUM(BK8:BK12) -> 3433523 | BL13: =SUM(BL8:BL12) -> 3229830 | BN13: =SUM(BN8:BN12) -> 1001919 | BO13: =SUM(BO8:BO12) -> 1048698 | BP13: =SUM(BP8:BP12) -> 1143761 | BQ13: =SUM(BQ8:BQ12) -> 1551397 | BR13: =SUM(BR8:BR12) -> 1118733 | BS13: =SUM(BS8:BS12) -> 66801 | BT13: =SUM(BT8:BT12) -> 77509 | BU13: =SUM(BU8:BU12) -> 73950 | ... CG13: =SUM(CG8:CG12) -> 1931244 | CI13: =SUM(CI8:CI12) -> 962591 | CJ13: =SUM(CJ8:CJ12) -> 2781601 | CK13: =SUM(CK8:CK12) -> 2110802
B15: Combined operating profit by segment:
B16: Energy | D16: 1674 | E16: 453 | F16: 618 | G16: 3277 | H16: 3393.549 | I16: 6048.895 | J16: 7069.308 | K16: 3842.488 | L16: 329.861 | M16: 3439.376 | N16: 49727 | O16: 78106 | P16: 75417 | Q16: 108886 | R16: 36628 | S16: 50560 | T16: 49495 | U16: =BG16+BF16+BH16+BI16 -> 58190 | Y16: 1576.47 | Z16: =3328.217-Y16 -> 1751.747 | AA16: =5014.777-Z16-Y16 -> 1686.56 | AB16: =I16-AA16-Z16-Y16 -> 1034.118 | AC16: 917.008 | AD16: =2486.617-AC16 -> 1569.609 | AE16: =3843.024-AD16-AC16 -> 1356.407 | AF16: =J16-AE16-AD16-AC16 -> 3226.284 | AG16: 594.485 | AH16: =2294.591-AG16 -> 1700.106 | AI16: =3446.398-AH16-AG16 -> 1151.807 | AJ16: =K16-AI16-AH16-AG16 -> 396.09 | AK16: -1957.239 | AL16: =-1608.476-AK16 -> 348.763 | AM16: =-890.364-AL16-AK16 -> 718.112 | AN16: =L16-AM16-AL16-AK16 -> 1220.225 | AO16: -310.571 | AP16: =2196.575-AO16 -> 2507.146 | AQ16: =5552.116-AP16-AO16 -> 3355.541 | AR16: =M16-AQ16-AP16-AO16 -> -2112.74 | AS16: 4204.592 | AT16: =18060.696-AS16 -> 13856.104 | AU16: =33221.418-AT16-AS16 -> 15160.722 | AV16: =N16-AU16-AT16-AS16 -> 16505.582 | AW16: 15632 | AX16: 13758 | AY16: =78810-AX16-AW16 -> 49420 | AZ16: =Q16-AY16-AX16-AW16 -> 30076 | BA16: 4003 | BB16: 10225 | BC16: =29706-BB16-BA16 -> 15478 | BD16: =R16-BC16-BB16-BA16 -> 6922 | BE16: 4852 | BF16: 12103 | BG16: 18589 | BH16: =T16-BG16-BF16-BE16 -> 13951 | BI16: 13547 | BK16: 39596 | BL16: 37129 | BN16: 5528 | BO16: 13809 | BP16: 18336 | BQ16: =S16-BN16-BO16-BP16 -> 12887 | BR16: 6350 | BS16: 1503 | BT16: =G16-BS16 -> 1774 | BU16: 1125 | BV16: =H16-BU16 -> 2268.549 | BW16: -1608.476 | BX16: =L16-BW16 -> 1938.337 | BY16: =2196.575 -> 2196.575 | BZ16: =M16-BY16 -> 1242.801 | CA16: 18060.696 | CB16: =N16-CA16 -> 31666.304 | CC16: 21657 | CD16: =P16-CC16 -> 53760 | CE16: 14564 | CF16: =R16-CE16 -> 22064 | CG16: 17246 | CI16: 30704 | CJ16: =Q16-CI16 -> 78182 | CK16: 19669
B17: Automotive | D17: 1649 | E17: 1705 | F17: 1618 | G17: 2529 | H17: 2915.291 | I17: 3940.78 | J17: 5033.674 | K17: 5917.559 | L17: 10178.502 | M17: 18553.981 | N17: 39861 | O17: 47807 | P17: 76416 | Q17: 110329 | R17: 33235 | S17: 43502 | T17: 52735 | U17: =BG17+BF17+BH17+BI17 -> 49290 | Y17: 798.689 | Z17: =1676.912-Y17 -> 878.223 | AA17: =2660.983-Z17-Y17 -> 984.071 | AB17: =I17-AA17-Z17-Y17 -> 1279.797 | AC17: 989.857 | AD17: =2277.998-AC17 -> 1288.141 | AE17: =3513.38-AD17-AC17 -> 1235.382 | AF17: =J17-AE17-AD17-AC17 -> 1520.294 | AG17: 1209.477 | AH17: =2796.337-AG17 -> 1586.86 | AI17: =4088.696-AH17-AG17 -> 1292.359 | AJ17: =K17-AI17-AH17-AG17 -> 1828.863 | AK17: 1562.445 | AL17: =2962.411-AK17 -> 1399.966 | AM17: =5937.128-AL17-AK17 -> 2974.717 | AN17: =L17-AM17-AL17-AK17 -> 4241.374 | AO17: 3056.525 | AP17: =6390.94-AO17 -> 3334.415 | AQ17: =10260.536-AP17-AO17 -> 3869.596 | AR17: =M17-AQ17-AP17-AO17 -> 8293.445 | AS17: 6035.239 | AT17: =14219.273-AS17 -> 8184.034 | AU17: =24028.789-AT17-AS17 -> 9809.516 | AV17: =N17-AU17-AT17-AS17 -> 15832.211 | AW17: 16813 | AX17: 31348 | AY17: =91282-AX17-AW17 -> 43121 | AZ17: =Q17-AY17-AX17-AW17 -> 19047 | BA17: 14664 | BB17: 7526 | BC17: =32944-BB17-BA17 -> 10754 | BD17: =R17-BC17-BB17-BA17 -> 291 | BE17: 6480 | BF17: 15872 | BG17: 9837 | BH17: =T17-BG17-BF17-BE17 -> 20546 | BI17: 3035 | BK17: 43912 | BL17: 34284 | BN17: 20252 | BO17: 10164 | BP17: 11469 | BQ17: =S17-BN17-BO17-BP17 -> 1617 | BR17: 8480 | BS17: 1071 | BT17: =G17-BS17 -> 1458 | BU17: 1370 | BV17: =H17-BU17 -> 1545.291 | BW17: 2962.411 | BX17: =L17-BW17 -> 7216.091 | BY17: =6390.94 -> 6390.94 | BZ17: =M17-BY17 -> 12163.041 | CA17: 14219.273 | CB17: =N17-CA17 -> 25641.727 | CC17: 33543 | CD17: =P17-CC17 -> 42873 | CE17: 23423 | CF17: =R17-CE17 -> 9812 | CG17: 22741 | CI17: 49574 | CJ17: =Q17-CI17 -> 60755 | CK17: 31633
B18: Consumer durables | D18: 743 | E18: 1157 | F18: 954 | G18: 1292 | H18: 1571.926 | I18: 1784.994 | J18: 2791.546 | K18: 2759.185 | L18: 5047.164 | M18: 7131.123 | N18: 9789 | O18: 11071 | P18: 12175 | Q18: 17578 | R18: 10098 | S18: 13217 | T18: 13113 | U18: =BG18+BF18+BH18+BI18 -> 11095 | Y18: 435.89 | Z18: =807.479-Y18 -> 371.589 | AA18: =1329.221-Z18-Y18 -> 521.742 | AB18: =I18-AA18-Z18-Y18 -> 455.773 | AC18: 522.334 | AD18: =1203.676-AC18 -> 681.342 | AE18: =2640.988-AD18-AC18 -> 1437.312 | AF18: =J18-AE18-AD18-AC18 -> 150.558 | AG18: 663.147 | AH18: =1370.553-AG18 -> 707.406 | AI18: =2139.414-AH18-AG18 -> 768.861 | AJ18: =K18-AI18-AH18-AG18 -> 619.771 | AK18: 791.701 | AL18: =1610.986-AK18 -> 819.285 | AM18: =3610.968-AL18-AK18 -> 1999.982 | AN18: =L18-AM18-AL18-AK18 -> 1436.196 | AO18: 1709.324 | AP18: =2816.317-AO18 -> 1106.993 | AQ18: =4107.18-AP18-AO18 -> 1290.863 | AR18: =M18-AQ18-AP18-AO18 -> 3023.943 | AS18: 2875.79 | AT18: =5005.57-AS18 -> 2129.78 | AU18: =7089.788-AT18-AS18 -> 2084.218 | AV18: =N18-AU18-AT18-AS18 -> 2699.212 | AW18: 2110 | AX18: 6504 | AY18: =12158-AX18-AW18 -> 3544 | AZ18: =Q18-AY18-AX18-AW18 -> 5420 | BA18: 3388 | BB18: 730 | BC18: =3646-BB18-BA18 -> -472 | BD18: =R18-BC18-BB18-BA18 -> 6452 | BE18: 2610 | BF18: 3895 | BG18: 3100 | BH18: =T18-BG18-BF18-BE18 -> 3508 | BI18: 592 | BK18: 26214 | BL18: 10262 | BN18: 4679 | BO18: 20847 | BP18: -1530 | BQ18: =S18-BN18-BO18-BP18 -> -10779 | BR18: 3416 | BS18: 470 | BT18: =G18-BS18 -> 822 | BU18: 681 | BV18: =H18-BU18 -> 890.926 | BW18: 1610.986 | BX18: =L18-BW18 -> 3436.178 | BY18: =2816.317 -> 2816.317 | BZ18: =M18-BY18 -> 4314.806 | CA18: 5005.57 | CB18: =N18-CA18 -> 4783.43 | CC18: 6728 | CD18: =P18-CC18 -> 5447 | CE18: 4403 | CF18: =R18-CE18 -> 5695 | CG18: 6662 | CI18: 8791 | CJ18: =Q18-CI18 -> 8787 | CK18: 25807
B19: Finance | D19: 2825 | E19: 3313 | F19: 3044 | G19: 3382 | H19: 3984.558 | I19: 4236.005 | J19: 6038.627 | K19: 4575.856 | L19: 6269.404 | M19: 13487.672 | N19: 69108 | O19: 125026 | P19: 95956 | Q19: 138540 | R19: 19228 | S19: 25168 | T19: 37862 | U19: =BG19+BF19+BH19+BI19 -> 49935 | Y19: 1171.935 | Z19: =2249.02-Y19 -> 1077.085 | AA19: =3408.338-Z19-Y19 -> 1159.318 | AB19: =I19-AA19-Z19-Y19 -> 827.667 | AC19: 1618.949 | AD19: =3167.2-AC19 -> 1548.251 | AE19: =4577.795-AD19-AC19 -> 1410.595 | AF19: =J19-AE19-AD19-AC19 -> 1460.832 | AG19: 1584.131 | AH19: =2888.95-AG19 -> 1304.819 | AI19: =4112.097-AH19-AG19 -> 1223.147 | AJ19: =K19-AI19-AH19-AG19 -> 463.759 | AK19: 1674.497 | AL19: =3044.416-AK19 -> 1369.919 | AM19: =5146.49-AL19-AK19 -> 2102.074 | AN19: =L19-AM19-AL19-AK19 -> 1122.914 | AO19: 1649.76 | AP19: =4378.401-AO19 -> 2728.641 | AQ19: =8626.036-AP19-AO19 -> 4247.635 | AR19: =M19-AQ19-AP19-AO19 -> 4861.636 | AS19: 9496.257 | AT19: =24237.42-AS19 -> 14741.163 | AU19: =45782.457-AT19-AS19 -> 21545.037 | AV19: =N19-AU19-AT19-AS19 -> 23325.543 | AW19: 26217 | AX19: 24868 | AY19: =106531-AX19-AW19 -> 55446 | AZ19: =Q19-AY19-AX19-AW19 -> 32009 | BA19: 11699 | BB19: 6786 | BC19: =17242-BB19-BA19 -> -1243 | BD19: =R19-BC19-BB19-BA19 -> 1986 | BE19: 8923 | BF19: 8000 | BG19: 6293 | BH19: =T19-BG19-BF19-BE19 -> 14646 | BI19: 20996 | BK19: 22983 | BL19: 25062 | BN19: 16157 | BO19: 9163 | BP19: -5281 | BQ19: =S19-BN19-BO19-BP19 -> 5129 | BR19: 11677 | BS19: 1463 | BT19: =G19-BS19 -> 1919 | BU19: 2157 | BV19: =H19-BU19 -> 1827.558 | BW19: 3044.416 | BX19: =L19-BW19 -> 3224.988 | BY19: =4378.401 -> 4378.401 | BZ19: =M19-BY19 -> 9109.271 | CA19: 24237.42 | CB19: =N19-CA19 -> 44870.58 | CC19: 30836 | CD19: =P19-CC19 -> 65120 | CE19: 19468 | CF19: =R19-CE19 -> -240 | CG19: 17459 | CI19: 53289 | CJ19: =Q19-CI19 -> 85251 | CK19: 26291
B20: Other | D20: 138 | E20: 131 | F20: 80 | G20: 207 | H20: 70.063 | I20: 185.121 | J20: 73.931 | K20: 390.828 | L20: 511.901 | M20: 723.378 | N20: 2056 | O20: -565 | P20: -864 | Q20: -1247 | R20: -256 | S20: -333 | T20: -1010 | U20: =BG20+BF20+BH20+BI20 -> -4131 | Y20: -18.943 | Z20: =39.073-Y20 -> 58.016 | AA20: =107.522-Z20-Y20 -> 68.449 | AB20: =I20-AA20-Z20-Y20 -> 77.599 | AC20: -57.355 | AD20: =-44.972-AC20 -> 12.383 | AE20: =-54.408-AD20-AC20 -> -9.436 | AF20: =J20-AE20-AD20-AC20 -> 128.339 | AG20: -124.809 | AH20: =-36.135-AG20 -> 88.674 | AI20: =99.751-AH20-AG20 -> 135.886 | AJ20: =K20-AI20-AH20-AG20 -> 291.077 | AK20: 41.935 | AL20: =56.213-AK20 -> 14.278 | AM20: =155.275-AL20-AK20 -> 99.062 | AN20: =L20-AM20-AL20-AK20 -> 356.626 | AO20: -55.917 | AP20: =48.091-AO20 -> 104.008 | AQ20: =283.327-AP20-AO20 -> 235.236 | AR20: =M20-AQ20-AP20-AO20 -> 440.051 | AS20: -45.155 | AT20: =415.158-AS20 -> 460.313 | AU20: =1098.523-AT20-AS20 -> 683.365 | AV20: =N20-AU20-AT20-AS20 -> 957.477 | AW20: -777 | AX20: -16 | AY20: =-84-AX20-AW20 -> 709 | AZ20: =Q20-AY20-AX20-AW20 -> -1163 | BA20: -824 | BB20: -576 | BC20: =-1632-BB20-BA20 -> -232 | BD20: =R20-BC20-BB20-BA20 -> 1376 | BE20: -1001 | BF20: 248 | BG20: -213 | BH20: =T20-BG20-BF20-BE20 -> -44 | BI20: -4122 | BK20: -2175 | BL20: -1087 | BN20: -1138 | BO20: -778 | BP20: -42 | BQ20: =S20-BN20-BO20-BP20 -> 1625 | BR20: -1310 | BS20: -32 | BT20: =G20-BS20 -> 239 | BU20: 63 | BV20: =H20-BU20 -> 7.063 | BW20: 56.213 | BX20: =L20-BW20 -> 455.688 | BY20: =48.091 -> 48.091 | BZ20: =M20-BY20 -> 675.287 | CA20: 415.158 | CB20: =N20-CA20 -> 1640.842 | CC20: 657 | CD20: =P20-CC20 -> -1521 | CE20: -1469 | CF20: =R20-CE20 -> 1213 | CG20: -813 | CI20: -858 | CJ20: =Q20-CI20 -> -389 | CK20: -1984
B21: Total combined operating profit | D21: =SUM(D16:D20) -> 7029 | E21: =SUM(E16:E20) -> 6759 | F21: =SUM(F16:F20) -> 6314 | G21: =SUM(G16:G20) -> 10687 | H21: =SUM(H16:H20) -> 11935.387 | I21: =SUM(I16:I20) -> 16195.795 | J21: =SUM(J16:J20) -> 21007.086 | K21: =SUM(K16:K20) -> 17485.916 | ... U21: =SUM(U16:U20) -> 164379 | Y21: =SUM(Y16:Y20) -> 3964.041 | Z21: =SUM(Z16:Z20) -> 4136.66 | AA21: =SUM(AA16:AA20) -> 4420.14 | AB21: =SUM(AB16:AB20) -> 3674.954 | AC21: =SUM(AC16:AC20) -> 3990.793 | AD21: =SUM(AD16:AD20) -> 5099.726 | AE21: =SUM(AE16:AE20) -> 5430.26 | AF21: =SUM(AF16:AF20) -> 6486.307 | ... BI21: =SUM(BI16:BI20) -> 34048 | BK21: =SUM(BK16:BK20) -> 130530 | BL21: =SUM(BL16:BL20) -> 105650 | BN21: =SUM(BN16:BN20) -> 45478 | BO21: =SUM(BO16:BO20) -> 53205 | BP21: =SUM(BP16:BP20) -> 22952 | BQ21: =SUM(BQ16:BQ20) -> 10479 | BR21: =SUM(BR16:BR20) -> 28613 | BS21: =SUM(BS16:BS20) -> 4475 | BT21: =SUM(BT16:BT20) -> 6212 | BU21: =SUM(BU16:BU20) -> 5396 | ... CG21: =SUM(CG16:CG20) -> 63295 | CI21: =SUM(CI16:CI20) -> 141500 | CJ21: =SUM(CJ16:CJ20) -> 232586 | CK21: =SUM(CK16:CK20) -> 101416
B23: Combined operating profit % margin by segment:
B24: Energy | D24: =+D16/D8 -> 0.026476868 | E24: =+E16/E8 -> 0.0069204681 | F24: =+F16/F8 -> 0.0090426232 | G24: =+G16/G8 -> 0.052518551 | H24: =+H16/H8 -> 0.050444088 | I24: =+I16/I8 -> 0.061992824 | J24: =+J16/J8 -> 0.046129242 | K24: =+K16/K8 -> 0.025044509 | ... U24: =+U16/U8 -> 0.037327339 | Y24: =+Y16/Y8 -> 0.072625793 | Z24: =+Z16/Z8 -> 0.075965983 | AA24: =+AA16/AA8 -> 0.06430685 | AB24: =+AB16/AB8 -> 0.038904426 | AC24: =+AC16/AC8 -> 0.035607497 | AD24: =+AD16/AD8 -> 0.043729004 | AE24: =+AE16/AE8 -> 0.027097173 | AF24: =+AF16/AF8 -> 0.077656333 | ... BI24: =+BI16/BI8 -> 0.033484604 | BK24: =+BK16/BK8 -> 0.031321489 | BL24: =+BL16/BL8 -> 0.036272568 | BN24: =+BN16/BN8 -> 0.015480691 | BO24: =+BO16/BO8 -> 0.035429041 | BP24: =+BP16/BP8 -> 0.043902159 | BQ24: =+BQ16/BQ8 -> 0.0244732 | BR24: =+BR16/BR8 -> 0.018331091 | BS24: =+BS16/BS8 -> 0.051047787 | BT24: =+BT16/BT8 -> 0.053832615 | BU24: =+BU16/BU8 -> 0.038798455 | ... CG24: =+CG16/CG8 -> 0.029295754 | CI24: =+CI16/CI8 -> 0.55109037 | CJ24: =+CJ16/CJ8 -> 0.053447545 | CK24: =+CK16/CK8 -> 0.02560051
B25: Automotive | D25: =+D17/D9 -> 0.074373083 | E25: =+E17/E9 -> 0.06789042 | F25: =+F17/F9 -> 0.060307876 | G25: =+G17/G9 -> 0.070508531 | H25: =+H17/H9 -> 0.068268078 | I25: =+I17/I9 -> 0.070932669 | J25: =+J17/J9 -> 0.076597269 | K25: =+K17/K9 -> 0.079486228 | ... U25: =+U17/U9 -> 0.031604744 | Y25: =+Y17/Y9 -> 0.065650947 | Z25: =+Z17/Z9 -> 0.063774119 | AA25: =+AA17/AA9 -> 0.079479624 | AB25: =+AB17/AB9 -> 0.074239858 | AC25: =+AC17/AC9 -> 0.068262719 | AD25: =+AD17/AD9 -> 0.078172984 | AE25: =+AE17/AE9 -> 0.080344557 | AF25: =+AF17/AF9 -> 0.078522428 | ... BI25: =+BI17/BI9 -> 0.008634473 | BK25: =+BK17/BK9 -> 0.049312786 | BL25: =+BL17/BL9 -> 0.035611637 | BN25: =+BN17/BN9 -> 0.069498493 | BO25: =+BO17/BO9 -> 0.041251339 | BP25: =+BP17/BP9 -> 0.03907533 | BQ25: =+BQ17/BQ9 -> 0.0036716038 | BR25: =+BR17/BR9 -> 0.027352192 | BS25: =+BS17/BS9 -> 0.065879314 | BT25: =+BT17/BT9 -> 0.07434603 | BU25: =+BU17/BU9 -> 0.0687751 | ... CG25: =+CG17/CG9 -> 0.039467473 | CI25: =+CI17/CI9 -> 0.11137547 | CJ25: =+CJ17/CJ9 -> 0.097676378 | CK25: =+CK17/CK9 -> 0.056965707
B26: Consumer durables | D26: =+D18/D10 -> 0.066374844 | E26: =+E18/E10 -> 0.098001016 | F26: =+F18/F10 -> 0.073719187 | G26: =+G18/G10 -> 0.088185107 | H26: =+H18/H10 -> 0.087342954 | I26: =+I18/I10 -> 0.076409536 | J26: =+J18/J10 -> 0.092300234 | K26: =+K18/K10 -> 0.075988075 | ... U26: =+U18/U10 -> 0.018017682 | Y26: =+Y18/Y10 -> 0.085708477 | Z26: =+Z18/Z10 -> 0.063906388 | AA26: =+AA18/AA10 -> 0.085060228 | AB26: =+AB18/AB10 -> 0.072038767 | AC26: =+AC18/AC10 -> 0.084602463 | AD26: =+AD18/AD10 -> 0.090114805 | AE26: =+AE18/AE10 -> 0.1712924 | AF26: =+AF18/AF10 -> 0.018545271 | ... BI26: =+BI18/BI10 -> 0.0041276792 | BK26: =+BK18/BK10 -> 0.057165163 | BL26: =+BL18/BL10 -> 0.023563828 | BN26: =+BN18/BN10 -> 0.039172513 | BO26: =+BO18/BO10 -> 0.13614456 | BP26: =+BP18/BP10 -> -0.009694036 | BQ26: =+BQ18/BQ10 -> -0.05258921 | BR26: =+BR18/BR10 -> 0.020791995 | BS26: =+BS18/BS10 -> 0.072196621 | BT26: =+BT18/BT10 -> 0.1009704 | BU26: =+BU18/BU10 -> 0.080830861 | ... CG26: =+CG18/CG10 -> 0.024307304 | CI26: =+CI18/CI10 -> 0.048050592 | CJ26: =+CJ18/CJ10 -> 0.035701226 | CK26: =+CK18/CK10 -> 0.092251872
B27: Finance | D27: =+D19/D11 -> 0.21755872 | E27: =+E19/E11 -> 0.23948243 | F27: =+F19/F11 -> 0.18078157 | G27: =+G19/G11 -> 0.15719996 | H27: =+H19/H11 -> 0.16440803 | I27: =+I19/I11 -> 0.14262751 | J27: =+J19/J11 -> 0.13969512 | K27: =+K19/K11 -> 0.095642081 | ... U27: =+U19/U11 -> 0.050847406 | Y27: =+Y19/Y11 -> 0.17134755 | Z27: =+Z19/Z11 -> 0.14842495 | AA27: =+AA19/AA11 -> 0.15564119 | AB27: =+AB19/AB11 -> 0.10149405 | AC27: =+AC19/AC11 -> 0.19260917 | AD27: =+AD19/AD11 -> 0.16366404 | AE27: =+AE19/AE11 -> 0.11231884 | AF27: =+AF19/AF11 -> 0.11410032 | ... BI27: =+BI19/BI11 -> 0.085394373 | BK27: =+BK19/BK11 -> 0.034255232 | BL27: =+BL19/BL11 -> 0.038194894 | BN27: =+BN19/BN11 -> 0.083935956 | BO27: =+BO19/BO11 -> 0.043438481 | BP27: =+BP19/BP11 -> -0.023492411 | BQ27: =+BQ19/BQ11 -> 0.017001684 | BR27: =+BR19/BR11 -> 0.04756183 | BS27: =+BS19/BS11 -> 0.14669608 | BT27: =+BT19/BT11 -> 0.16627675 | BU27: =+BU19/BU11 -> 0.17985492 | ... CG27: =+CG19/CG11 -> 0.043617513 | CI27: =+CI19/CI11 -> 0.24889422 | CJ27: =+CJ19/CJ11 -> 0.24573748 | CK27: =+CK19/CK11 -> 0.063352265
B28: Other | D28: =+D20/D12 -> 0.019691781 | E28: =+E20/E12 -> 0.018031659 | F28: =+F20/F12 -> 0.0093962885 | G28: =+G20/G12 -> 0.020951417 | H28: =+H20/H12 -> 0.007312313 | I28: =+I20/I12 -> 0.016665576 | J28: =+J20/J12 -> 0.0053428757 | K28: =+K20/K12 -> 0.022970702 | ... U28: =+U20/U12 -> -0.0179321 | Y28: =+Y20/Y12 -> -0.007981804 | Z28: =+Z20/Z12 -> 0.021615942 | AA28: =+AA20/AA12 -> 0.024079733 | AB28: =+AB20/AB12 -> 0.024187925 | AC28: =+AC20/AC12 -> -0.021683597 | AD28: =+AD20/AD12 -> 0.0038248353 | AE28: =+AE20/AE12 -> -0.0025694047 | AF28: =+AF20/AF12 -> 0.029970013 | ... BI28: =+BI20/BI12 -> -0.078171819 | BK28: =+BK20/BK12 -> -0.014561742 | BL28: =+BL20/BL12 -> -0.0071588043 | BN28: =+BN20/BN12 -> -0.027428957 | BO28: =+BO20/BO12 -> -0.01604951 | BP28: =+BP20/BP12 -> -0.0008405043 | BQ28: =+BQ20/BQ12 -> 0.020894409 | BR28: =+BR20/BR12 -> -0.024956659 | BS28: =+BS20/BS12 -> -0.0069294067 | BT28: =+BT20/BT12 -> 0.045419992 | BU28: =+BU20/BU12 -> 0.01364818 | ... CG28: =+CG20/CG12 -> -0.008835708 | CI28: =+CI20/CI12 -> -0.013258542 | CJ28: =+CJ20/CJ12 -> -0.0037485666 | CK28: =+CK20/CK12 -> -0.021458856
B29: Total combined operating profit | D29: =+D21/D13 -> 0.060291292 | E29: =+E21/E13 -> 0.054738939 | F29: =+F21/F13 -> 0.047308283 | G29: =+G21/G13 -> 0.074055852 | H29: =+H21/H13 -> 0.073770167 | I29: =+I21/I13 -> 0.07453217 | J29: =+J21/J13 -> 0.068589007 | K29: =+K21/K13 -> 0.053141822 | ... U29: =+U21/U13 -> 0.033230059 | Y29: =+Y21/Y13 -> 0.082291092 | Z29: =+Z21/Z13 -> 0.078665032 | AA29: =+AA21/AA13 -> 0.080317654 | AB29: =+AB21/AB13 -> 0.059746177 | AC29: =+AC21/AC13 -> 0.069431237 | AD29: =+AD21/AD13 -> 0.070214789 | AE29: =+AE21/AE13 -> 0.060299059 | AF29: =+AF21/AF13 -> 0.075325271 | ... BI29: =+BI21/BI13 -> 0.028418448 | BK29: =+BK21/BK13 -> 0.038016346 | BL29: =+BL21/BL13 -> 0.0327107 | BN29: =+BN21/BN13 -> 0.045390895 | BO29: =+BO21/BO13 -> 0.050734339 | BP29: =+BP21/BP13 -> 0.020067129 | BQ29: =+BQ21/BQ13 -> 0.0067545573 | BR29: =+BR21/BR13 -> 0.025576255 | BS29: =+BS21/BS13 -> 0.066990015 | BT29: =+BT21/BT13 -> 0.080145531 | BU29: =+BU21/BU13 -> 0.072968222 | ... CG29: =+CG21/CG13 -> 0.032774212 | CI29: =+CI21/CI13 -> 0.14699909 | CJ29: =+CJ21/CJ13 -> 0.083615874 | CK29: =+CK21/CK13 -> 0.048046193
B31: Consolidated revenues | D31: 65666 | E31: 66182 | F31: 68622 | G31: 69491 | H31: 70432.243 | I31: 98866.749 | J31: 143248.31 | K31: 153516.01 | L31: 183777.28 | M31: 346688.7 | N31: 901857 | O31: 1715942 | P31: 1604647 | Q31: 2316773 | R31: 2317907 | S31: 3033955 | T31: 2757295 | U31: =BG31+BF31+BH31+BI31 -> 2957018 | Y31: 22274.111 | Z31: 23059.286 | AA31: 25874.941 | AB31: =I31-AA31-Z31-Y31 -> 27658.411 | AC31: 24587.937 | AD31: 33272.37 | AE31: 45553.375 | AF31: =J31-AE31-AD31-AC31 -> 39834.626 | AG31: 34261.702 | AH31: 40487.809 | AI31: 39364.507 | AJ31: =K31-AI31-AH31-AG31 -> 39401.989 | AK31: 39435.731 | AL31: 34530.996 | AM31: 51753.061 | AN31: =L31-AM31-AL31-AK31 -> 58057.488 | AO31: 57304.999 | AP31: 74654.636 | AQ31: 91650.156 | AR31: =M31-AQ31-AP31-AO31 -> 123078.91 | AS31: 152105.05 | AT31: 233773.06 | AU31: 260994.13 | AV31: =N31-AU31-AT31-AS31 -> 254984.76 | AW31: 386677 | AX31: 467136 | AY31: 628852 | AZ31: =Q31-AY31-AX31-AW31 -> 834108 | BA31: 450415 | BB31: 521453 | BC31: 560733 | BD31: =R31-BC31-BB31-BA31 -> 785306 | BE31: 538320 | BF31: 606756 | BG31: 688860 | BH31: =T31-BG31-BF31-BE31 -> 923359 | BI31: 738043 | BK31: 2213367 | BL31: 1954626 | BN31: 622041 | BO31: 704216 | BP31: 747418 | BQ31: =S31-BN31-BO31-BP31 -> 960280 | BR31: 704473 | BS31: 32128 | BT31: =G31-BS31 -> 37363 | BU31: 31122 | BV31: =H31-BU31 -> 39310.243 | BW31: 73966.727 | BX31: =L31-BW31 -> 109810.55 | BY31: 131959.64 | BZ31: =M31-BY31 -> 214729.07 | CA31: 385878.11 | CB31: =N31-CA31 -> 515978.89 | CC31: 490302 | CD31: =P31-CC31 -> 1114345 | CE31: 1009725 | CF31: =R31-CE31 -> 1308182 | CG31: 1177413 | CI31: 886314 | CJ31: =Q31-CI31 -> 1430459 | CK31: 1363623
B32: % growth | E32: =+E31/D31-1 -> 0.0078579478 | F32: =+F31/E31-1 -> 0.036868031 | G32: =+G31/F31-1 -> 0.012663577 | H32: =+H31/G31-1 -> 0.013544819 | I32: =+I31/H31-1 -> 0.40371433 | J32: =+J31/I31-1 -> 0.44890279 | K32: =+K31/J31-1 -> 0.071677628 | L32: =+L31/K31-1 -> 0.19712126 | ... N32: =+N31/M31-1 -> 1.6013452 | O32: =+O31/M31-1 -> 3.9495181 | P32: =+P31/O31-1 -> -0.064859418 | Q32: =+Q31/O31-1 -> 0.35014645 | R32: =+R31/P31-1 -> 0.44449652 | S32: =+S31/Q31-1 -> 0.30956076 | T32: =+T31/S31-1 -> -0.091187905 | V32: =+V31/G31-1 -> -1 | W32: =+W31/V31-1 -> #DIV/0! | AC32: =+AC31/Y31-1 -> 0.10387961 | AD32: =+AD31/Z31-1 -> 0.44290547 | AE32: =+AE31/AA31-1 -> 0.76052092 | AF32: =+AF31/AB31-1 -> 0.44023552 | AG32: =+AG31/AC31-1 -> 0.39343541 | AH32: =+AH31/AD31-1 -> 0.21685978 | AI32: =+AI31/AE31-1 -> -0.1358597 | AJ32: =+AJ31/AF31-1 -> -0.010860827 | ... BD32: =+BD31/AZ31-1 -> -0.058508011 | BE32: =+BE31/BN31-1 -> -0.13459081 | BF32: =+BF31/BB31-1 -> 0.16358713 | BG32: =+BG31/BC31-1 -> 0.22849913 | BH32: =+BH31/BD31-1 -> 0.17579517 | BI32: =+BI31/BR31-1 -> 0.047652642 | BL32: =BL31/BK31-1 -> -0.11689928 | BN32: =+BN31/AW31-1 -> 0.60868373 | BO32: =+BO31/AX31-1 -> 0.50751815 | BP32: =+BP31/AY31-1 -> 0.18854357 | BQ32: =+BQ31/AZ31-1 -> 0.15126578 | BR32: =+BR31/BA31-1 -> 0.56405315 | BU32: =+BU31/BS31-1 -> -0.031312251 | BV32: =+BV31/BT31-1 -> 0.05211688 | BY32: =+BY31/BW31-1 -> 0.78404048 | CA32: =+CA31/BY31-1 -> 1.9242132 | CC32: =+CC31/CA31-1 -> 0.27061367 | CD32: =+CD31/CB31-1 -> 1.1596717 | CE32: =+CE31/CC31-1 -> 1.059394 | CF32: =+CF31/CJ31-1 -> -0.085480954 | CG32: =+CG31/CE31-1 -> 0.16607294 | CI32: =+CI31/CE31-1 -> -0.12222239 | CJ32: =+CJ31/CB31-1 -> 1.7723208 | CK32: =+CK31/CI31-1 -> 0.53853262
B33: Consolidated operating profit | D33: 3811 | E33: 3727 | F33: 3329 | G33: 6677 | H33: 6948.742 | I33: 10426.63 | J33: 12963.431 | K33: 10373.674 | L33: 16831.917 | M33: 34674.985 | N33: 149346 | O33: 240746 | P33: 222656 | Q33: 321467 | R33: 87366 | S33: 114356 | T33: 117608 | U33: =BG33+BF33+BH33+BI33 -> 130556 | Y33: 2604.591 | Z33: 2711.758 | AA33: 2842.224 | AB33: =I33-AA33-Z33-Y33 -> 2268.057 | AC33: 2132.406 | AD33: 2861.476 | AE33: 3439.073 | AF33: =J33-AE33-AD33-AC33 -> 4530.476 | AG33: 1944.846 | AH33: 3450.31 | AI33: 2893.682 | AJ33: =K33-AI33-AH33-AG33 -> 2084.836 | AK33: 1060.524 | AL33: 3532.662 | AM33: 6419.996 | AN33: =L33-AM33-AL33-AK33 -> 5818.735 | AO33: 5173.743 | AP33: 8181.422 | AQ33: 11021.515 | AR33: =M33-AQ33-AP33-AO33 -> 10298.305 | AS33: 19335.686 | AT33: 34279.746 | AU33: 43946.037 | AV33: =N33-AU33-AT33-AS33 -> 51784.531 | AW33: 52455 | AX33: 59902 | AY33: 110545 | AZ33: =Q33-AY33-AX33-AW33 -> 98565 | BA33: 26574 | BB33: 21477 | BC33: 12188 | BD33: =R33-BC33-BB33-BA33 -> 27127 | BE33: 17485 | BF33: 28190 | BG33: 30879 | BH33: =T33-BG33-BF33-BE33 -> 41054 | BI33: 30433 | BK33: 110599 | BL33: 81111 | BN33: 36698 | BO33: 50099 | BP33: 16245 | BQ33: =S33-BN33-BO33-BP33 -> 11314 | BR33: 22883 | BS33: 2490 | BT33: =G33-BS33 -> 4187 | BU33: 2755 | BV33: =H33-BU33 -> 4193.742 | BW33: 4593.186 | BX33: =L33-BW33 -> 12238.731 | BY33: 13355.165 | BZ33: =M33-BY33 -> 21319.82 | CA33: 53615.432 | CB33: =N33-CA33 -> 95730.568 | CC33: 75796 | CD33: =P33-CC33 -> 146860 | CE33: 50284 | CF33: =R33-CE33 -> 37082 | CG33: 46726 | CI33: 116767 | CJ33: =Q33-CI33 -> 204700 | CK33: 87769
B34: % margin | D34: =+D33/D31 -> 0.058036122 | E34: =+E33/E31 -> 0.056314406 | F34: =+F33/F31 -> 0.048512139 | G34: =+G33/G31 -> 0.096084385 | H34: =+H33/H31 -> 0.098658536 | I34: =+I33/I31 -> 0.10546144 | J34: =+J33/J31 -> 0.090496224 | K34: =+K33/K31 -> 0.067573891 | ... W34: =+W33/W31 -> #DIV/0! | Y34: =+Y33/Y31 -> 0.11693356 | Z34: =+Z33/Z31 -> 0.11759939 | AA34: =+AA33/AA31 -> 0.10984466 | AB34: =+AB33/AB31 -> 0.082002433 | AC34: =+AC33/AC31 -> 0.086725698 | AD34: =+AD33/AD31 -> 0.086001568 | AE34: =+AE33/AE31 -> 0.07549546 | AF34: =+AF33/AF31 -> 0.11373211 | ... BI34: =+BI33/BI31 -> 0.041234725 | BL34: =BL33/BK33-1 -> -0.26662086 | BN34: =+BN33/BN31 -> 0.058996111 | BO34: =+BO33/BO31 -> 0.071141525 | BP34: =+BP33/BP31 -> 0.021734826 | BQ34: =+BQ33/BQ31 -> 0.01178198 | BR34: =+BR33/BR31 -> 0.032482437 | BS34: =+BS33/BS31 -> 0.07750249 | BT34: =+BT33/BT31 -> 0.11206274 | BU34: =+BU33/BU31 -> 0.088522589 | ... CG34: =+CG33/CG31 -> 0.03968531 | CI34: =+CI33/CI31 -> 0.13174451 | CJ34: =+CJ33/CJ31 -> 0.14310092 | CK34: =+CK33/CK31 -> 0.064364564
B35: Depreciation and amortisation | H35: 1428.311 | I35: 1579.49 | J35: 2113.296 | K35: 2765.255 | L35: 4063.559 | M35: 5285.513 | N35: 8260 | O35: 25457 | P35: 30612 | Q35: 44197 | R35: 58268 | S35: 76268 | T35: 74392 | U35: =BG35+BF35+BH35+BI35 -> 79278 | Y35: 378.934 | Z35: =769.774-Y35 -> 390.84 | AA35: =1164.154-Z35-Y35 -> 394.38 | AB35: =I35-AA35-Z35-Y35 -> 415.336 | AC35: 446.431 | AD35: =962.39-AC35 -> 515.959 | AE35: =1540.756-AD35-AC35 -> 578.366 | AF35: =J35-AE35-AD35-AC35 -> 572.54 | AG35: 643.715 | AH35: =1331.263-AG35 -> 687.548 | AI35: =2049.401-AH35-AG35 -> 718.138 | AJ35: =K35-AI35-AH35-AG35 -> 715.854 | AK35: 895.994 | AL35: 1016.824 | AM35: 1068.361 | AN35: =L35-AM35-AL35-AK35 -> 1082.38 | AO35: 1129.65 | AP35: 1210.899 | AQ35: 1349.258 | AR35: =M35-AQ35-AP35-AO35 -> 1595.706 | AS35: 1780.528 | AT35: 1940.226 | AU35: 2184.199 | AV35: =N35-AU35-AT35-AS35 -> 2355.047 | AW35: 13446 | AX35: 12913 | AY35: 3346 | AZ35: =Q35-AY35-AX35-AW35 -> 14492 | BA35: 13106 | BB35: 18966 | BC35: 18387 | BD35: =R35-BC35-BB35-BA35 -> 7809 | BE35: 15193 | BF35: 16665 | BG35: 18745 | BH35: =T35-BG35-BF35-BE35 -> 23789 | BI35: 20079 | BK35: 49606 | BL35: 53974 | BN35: 11858 | BO35: 17414 | BP35: 17370 | BQ35: =S35-BN35-BO35-BP35 -> 29626 | BR35: 19882 | BS35: 568.401 | BU35: 697.347 | BV35: =H35-BU35 -> 730.964 | BW35: 1912.818 | BX35: =L35-BW35 -> 2150.741 | BY35: 2340.549 | BZ35: =M35-BY35 -> 2944.964 | CA35: 3720.754 | CB35: =N35-CA35 -> 4539.246 | CC35: 5118 | CD35: =P35-CC35 -> 25494 | CE35: 33174 | CF35: =R35-CE35 -> 25094 | CG35: 32770 | CI35: 26963 | CJ35: =Q35-CI35 -> 17234 | CK35: 29985
B36: Other adjustments | H36: =-1807.742+1864.258-2235.378 -> -2178.862 | I36: =-2508.489+2239.369-2691.404 -> -2960.524 | J36: =7275.918-5637.086-3175.787 -> -1536.955 | K36: =4086.379-3626.01-2902.947 -> -2442.578 | L36: =12342.768-4878.475-2966.673 -> 4497.62 | M36: =30422.344-12314.28-5879.657 -> 12228.407 | N36: =36082-15045-12416 -> 8621 | O36: =73325-30260-16157 -> 26908 | P36: =64942-30720-38273 -> -4051 | Q36: =93764-55258-44353 -> -5847 | R36: =69329-57949-20615 -> -9235 | S36: =90746-75851-26983 -> -12088 | T36: =89403-52600-16441 -> 20362 | U36: =BG36+BF36+BH36+BI36 -> 24788 | Y36: =-747.773+701.997-615.381 -> -661.157 | Z36: =-327.401+146.521-685.8 -> -866.68 | AA36: =-413.466+326.706-685.424 -> -772.184 | AB36: =I36-AA36-Z36-Y36 -> -660.503 | AC36: =-616.567+570.02-795.066 -> -841.613 | AD36: =-1182.042+1859.496-920.138 -> -242.684 | AE36: =-2733.757+4771.926-712.894 -> 1325.275 | AF36: =J36-AE36-AD36-AC36 -> -1777.933 | AG36: =-924.618+1109.753-779.731 -> -594.596 | AH36: =-1030.045+905.51-794.367 -> -918.902 | AI36: =-952.255+985.474-733.016 -> -699.797 | AJ36: =K36-AI36-AH36-AG36 -> -229.283 | AK36: =-1194.826+2974.263-441.042 -> 1338.395 | AL36: =-968.469+2677.523-231.381 -> 1477.673 | AM36: =-1366.953+3853.362-958.54 -> 1527.869 | AN36: =L36-AM36-AL36-AK36 -> 153.683 | AO36: =-1907.956+4992.94-985.257 -> 2099.727 | AP36: =-1521.476+2347.805-953.147 -> -126.818 | AQ36: =-1700.121+2283.821-1364.086 -> -780.386 | AR36: =M36-AQ36-AP36-AO36 -> 11035.884 | AS36: =-3669.155+6850.833-1942.431 -> 1239.247 | AT36: =-4811.662+11524.462-2584.094 -> 4128.706 | AU36: =-3683.503+9843.317-2934.035 -> 3225.779 | AV36: =N36-AU36-AT36-AS36 -> 27.268 | AW36: =-4959+6962-5392 -> -3389 | AX36: =-20349+40453-8754 -> 11350 | AY36: =-11293+21324-11406 -> -1375 | AZ36: =Q36-AY36-AX36-AW36 -> -12433 | BA36: =-8355+15579-5381 -> 1843 | BB36: =-9285+7282-3668 -> -5671 | BC36: =-8966+14936-4585 -> 1385 | BD36: =R36-BC36-BB36-BA36 -> -6792 | BE36: =21671-12959-2394 -> 6318 | BF36: =18994-11708-3486 -> 3800 | BG36: =20765-9708-4239 -> 6818 | BH36: =T36-BG36-BF36-BE36 -> 3426 | BI36: =28954-15720-2490 -> 10744 | BK36: =-59934+55002-19905 -> -24837 | BL36: =-37062+65881-10715 -> 18104 | BN36: =21516-11539-7431 -> 2546 | BO36: =-9835+32401+4954 -> 27520 | BP36: =19909-11952-6111 -> 1846 | BQ36: =S36-BN36-BO36-BP36 -> -44000 | BR36: =28360-16959-3133 -> 8268 | BS36: =-988.769+1152.559-797.775 -> -633.985 | BU36: =-516.137+458.802-1143.482 -> -1200.817 | BV36: =H36-BU36 -> -978.045 | BW36: =-2163.295+5651.786-672.423 -> 2816.068 | BX36: =L36-BW36 -> 1681.552 | BY36: =-3429.432+7340.745-1938.404 -> 1972.909 | BZ36: =M36-BY36 -> 10255.498 | CA36: =-8480.817+18375.295-4526.525 -> 5367.953 | CB36: =N36-CA36 -> 3253.047 | CC36: =-14823+27193-9641 -> 2729 | CD36: =P36-CC36 -> -6780 | CE36: =-18342+24170-9501 -> -3673 | CF36: =R36-CE36 -> -5562 | CG36: =25445-41967+6024 -> -10498 | CI36: =-25725+48000-14599 -> 7676 | CJ36: =Q36-CI36 -> -13523 | CK36: =44633-32643+12831 -> 24821
B37: Consolidated EBITDA | D37: 4410 | E37: 4962 | F37: 4339 | G37: 8236 | H37: =+H33+H35+H36 -> 6198.191 | I37: =+I33+I35+I36 -> 9045.596 | J37: =+J33+J35+J36 -> 13539.772 | K37: =+K33+K35+K36 -> 10696.351 | L37: =+L33+L35+L36 -> 25393.096 | M37: =+M33+M35+M36 -> 52188.905 | N37: =+N33+N35+N36 -> 166227 | O37: =+O33+O35+O36 -> 293111 | ... U37: =+U33+U35+U36 -> 234622 | Y37: =+Y33+Y35+Y36 -> 2322.368 | Z37: =+Z33+Z35+Z36 -> 2235.918 | AA37: =+AA33+AA35+AA36 -> 2464.42 | AB37: =+AB33+AB35+AB36 -> 2022.89 | AC37: =+AC33+AC35+AC36 -> 1737.224 | AD37: =+AD33+AD35+AD36 -> 3134.751 | AE37: =+AE33+AE35+AE36 -> 5342.714 | AF37: =+AF33+AF35+AF36 -> 3325.083 | ... BI37: =+BI33+BI35+BI36 -> 61256 | BK37: =+BK33+BK35+BK36 -> 135368 | BL37: =+BL33+BL35+BL36 -> 153189 | BN37: =+BN33+BN35+BN36 -> 51102 | BO37: =+BO33+BO35+BO36 -> 95033 | BP37: =+BP33+BP35+BP36 -> 35461 | BQ37: =+BQ33+BQ35+BQ36 -> -3060 | BR37: =+BR33+BR35+BR36 -> 51033 | BS37: =+BS33+BS35+BS36 -> 2424.416 | BT37: =+BT33+BT35+BT36 -> 4187 | BU37: =+BU33+BU35+BU36 -> 2251.53 | ... CG37: =+CG33+CG35+CG36 -> 68998 | CI37: =+CI33+CI35+CI36 -> 151406 | CJ37: =+CJ33+CJ35+CJ36 -> 208411 | CK37: =+CK33+CK35+CK36 -> 142575
B38: % growth | E38: =+E37/D37-1 -> 0.12517007 | F38: =+F37/E37-1 -> -0.12555421 | G38: =+G37/F37-1 -> 0.89813321 | H38: =+H37/G37-1 -> -0.24742703 | I38: =+I37/H37-1 -> 0.45939291 | J38: =+J37/I37-1 -> 0.49683581 | K38: =+K37/J37-1 -> -0.21000509 | L38: =+L37/K37-1 -> 1.3739961 | ... N38: =+N37/M37-1 -> 2.1851023 | O38: =+O37/M37-1 -> 4.616347 | P38: =+P37/O37-1 -> -0.14975214 | Q38: =+Q37/O37-1 -> 0.22757931 | R38: =+R37/P37-1 -> -0.45268982 | S38: =+S37/Q37-1 -> -0.50381444 | T38: =+T37/S37-1 -> 0.18946319 | V38: =+V37/V31 -> #DIV/0! | W38: =+W37/W31 -> #DIV/0! | AC38: =+AC37/Y37-1 -> -0.25196007 | AD38: =+AD37/Z37-1 -> 0.4019973 | AE38: =+AE37/AA37-1 -> 1.1679397 | AF38: =+AF37/AB37-1 -> 0.64372902 | AG38: =+AG37/AC37-1 -> 0.14778808 | AH38: =+AH37/AD37-1 -> 0.026861783 | AI38: =+AI37/AE37-1 -> -0.45495435 | AJ38: =+AJ37/AF37-1 -> -0.22666382 | ... BD38: =+BD37/AZ37-1 -> -0.72030529 | BE38: =+BE37/BN37-1 -> -0.23689875 | BF38: =+BF37/BB37-1 -> 0.39925802 | BG38: =+BG37/BC37-1 -> 0.76602003 | BH38: =+BH37/BD37-1 -> 1.4257035 | BI38: =+BI37/BR37-1 -> 0.20032136 | BL38: =BL37/BK37-1 -> 0.13164854 | BN38: =+BN37/AW37-1 -> -0.18252496 | BO38: =+BO37/AX37-1 -> 0.12912731 | BP38: =+BP37/AY37-1 -> -0.68483593 | BQ38: =+BQ37/AZ37-1 -> -1.0304102 | BR38: =+BR37/BA37-1 -> 0.22902969 | BU38: =+BU37/BS37-1 -> -0.071310369 | BV38: =+BV37/BT37-1 -> -0.057401242 | BY38: =+BY37/BW37-1 -> 0.89535363 | CA38: =+CA37/BY37-1 -> 2.5488979 | CC38: =+CC37/CA37-1 -> 0.33393108 | CD38: =+CD37/CB37-1 -> 0.59939552 | CE38: =+CE37/CC37-1 -> -0.046124601 | CF38: =+CF37/CJ37-1 -> -0.72835407 | CG38: =+CG37/CE37-1 -> -0.13520085 | CI38: =+CI37/CE37-1 -> 0.897675 | CJ38: =+CJ37/CB37-1 -> 1.0131882 | CK38: =+CK37/CI37-1 -> -0.058326618
B39: % margin | D39: =+D37/D31 -> 0.067158042 | E39: =+E37/E31 -> 0.074975069 | F39: =+F37/F31 -> 0.063230451 | G39: =+G37/G31 -> 0.11851894 | H39: =+H37/H31 -> 0.088002181 | I39: =+I37/I31 -> 0.091492803 | J39: =+J37/J31 -> 0.094519595 | K39: =+K37/K31 -> 0.069675803 | ... U39: =+U37/U31 -> 0.079344123 | Y39: =+Y37/Y31 -> 0.10426311 | Z39: =+Z37/Z31 -> 0.096963887 | AA39: =+AA37/AA31 -> 0.095243502 | AB39: =+AB37/AB31 -> 0.07313833 | AC39: =+AC37/AC31 -> 0.070653508 | AD39: =+AD37/AD31 -> 0.09421484 | AE39: =+AE37/AE31 -> 0.1172847 | AF39: =+AF37/AF31 -> 0.083472178 | ... BI39: =+BI37/BI31 -> 0.082997874 | BL39: =+BL37/BL31 -> 0.078372538 | BN39: =+BN37/BN31 -> 0.082152141 | BO39: =+BO37/BO31 -> 0.13494865 | BP39: =+BP37/BP31 -> 0.04744467 | BQ39: =+BQ37/BQ31 -> -0.0031865706 | BR39: =+BR37/BR31 -> 0.072441385 | BS39: =+BS37/BS31 -> 0.075461155 | BT39: =+BT37/BT31 -> 0.11206274 | BU39: =+BU37/BU31 -> 0.072345286 | ... CG39: =+CG37/CG31 -> 0.058601357 | CI39: =+CI37/CI31 -> 0.17082659 | CJ39: =+CJ37/CJ31 -> 0.14569519 | CK39: =+CK37/CK31 -> 0.10455602
B40: Consolidated net profit attributable to Equity holders | D40: 2324 | E40: 2680 | F40: 2710 | G40: 3567 | H40: 3459.993 | I40: 4908.74 | J40: 5537.028 | K40: 4391.159 | L40: 9272.57 | M40: 15192.711 | N40: 69806 | O40: 72662 | P40: 72230 | Q40: 108176 | R40: 1306 | S40: 1709 | T40: 22001 | U40: =BG40+BF40+BH40+BI40 -> 23938 | Y40: 1124.52 | Z40: 1417.058 | AA40: 1289.954 | AB40: =I40-AA40-Z40-Y40 -> 1077.208 | AC40: 1141.185 | AD40: 1418.434 | AE40: 1267.019 | AF40: =J40-AE40-AD40-AC40 -> 1710.39 | AG40: 779.309 | AH40: 1425.446 | AI40: 1075.923 | AJ40: =K40-AI40-AH40-AG40 -> 1110.481 | AK40: 3469.812 | AL40: 961.37 | AM40: 2305.391 | AN40: =L40-AM40-AL40-AK40 -> 2535.997 | AO40: 2113.184 | AP40: 3198.229 | AQ40: 4105.632 | AR40: =M40-AQ40-AP40-AO40 -> 5775.666 | AS40: =6713.112 -> 6713.112 | AT40: 15448.77 | AU40: 19860.447 | AV40: =N40-AU40-AT40-AS40 -> 27783.671 | AW40: 10693 | AX40: 9693 | AY40: 13477 | AZ40: =Q40-AY40-AX40-AW40 -> 74313 | BA40: 1354 | BB40: 164 | BC40: -3682 | BD40: =R40-BC40-BB40-BA40 -> 3470 | BE40: -1415 | BF40: 7733 | BG40: 7650 | BH40: =T40-BG40-BF40-BE40 -> 8033 | BI40: 522 | BK40: 9300 | BL40: 14352 | BN40: 2737 | BO40: 9857 | BP40: -4413 | BQ40: =S40-BN40-BO40-BP40 -> -6472 | BR40: -1852 | BS40: 1326 | BT40: =G40-BS40 -> 2241 | BU40: 1433 | BV40: =H40-BU40 -> 2026.993 | BW40: 4431.182 | BX40: =L40-BW40 -> 4841.388 | BY40: 5311.413 | BZ40: =M40-BY40 -> 9881.298 | CA40: 22161.882 | CB40: =N40-CA40 -> 47644.118 | CC40: 37372 | CD40: =P40-CC40 -> 34858 | CE40: 1632 | CF40: =R40-CE40 -> -326 | CG40: 6235 | CI40: 36165 | CJ40: =Q40-CI40 -> 72011 | CK40: 12758
B41: % margin | D41: =+D40/D31 -> 0.035391222 | E41: =+E40/E31 -> 0.040494394 | F41: =+F40/F31 -> 0.039491708 | G41: =+G40/G31 -> 0.051330388 | H41: =+H40/H31 -> 0.049125129 | I41: =+I40/I31 -> 0.04965006 | J41: =+J40/J31 -> 0.038653357 | K41: =+K40/K31 -> 0.028603916 | ... W41: =+W40/W31 -> #DIV/0! | Y41: =+Y40/Y31 -> 0.050485517 | Z41: =+Z40/Z31 -> 0.061452813 | AA41: =+AA40/AA31 -> 0.049853408 | AB41: =+AB40/AB31 -> 0.038946851 | AC41: =+AC40/AC31 -> 0.046412393 | AD41: =+AD40/AD31 -> 0.042630988 | AE41: =+AE40/AE31 -> 0.027813944 | AF41: =+AF40/AF31 -> 0.042937268 | ... BI41: =+BI40/BI31 -> 0.00070727586 | BN41: =+BN40/BN31 -> 0.0044000315 | BO41: =+BO40/BO31 -> 0.013997126 | BP41: =+BP40/BP31 -> -0.0059043266 | BQ41: =+BQ40/BQ31 -> -0.0067397009 | BR41: =+BR40/BR31 -> -0.0026289155 | BS41: =+BS40/BS31 -> 0.04127241 | BT41: =+BT40/BT31 -> 0.059979124 | BU41: =+BU40/BU31 -> 0.046044599 | ... CG41: =+CG40/CG31 -> 0.005295508 | CI41: =+CI40/CI31 -> 0.040803823 | CJ41: =+CJ40/CJ31 -> 0.050341184 | CK41: =+CK40/CK31 -> 0.0093559584
B43: LTM revenues | D43: =+D31 -> 65666 | E43: =+E31 -> 66182 | F43: =+F31 -> 68622 | G43: =+G31 -> 69491 | H43: =+H31 -> 70432.243 | I43: =+I31 -> 98866.749 | J43: =+J31 -> 143248.31 | K43: =+K31 -> 153516.01 | ... W43: =+W31 -> 0 | AB43: =+AB31+AA31+Z31+Y31 -> 98866.749 | AC43: =+AC31+AB31+AA31+Z31 -> 101180.57 | AD43: =+AD31+AC31+AB31+AA31 -> 111393.66 | AE43: =+AE31+AD31+AC31+AB31 -> 131072.09 | AF43: =+AF31+AE31+AD31+AC31 -> 143248.31 | AG43: =+AG31+AF31+AE31+AD31 -> 152922.07 | AH43: =+AH31+AG31+AF31+AE31 -> 160137.51 | AI43: =+AI31+AH31+AG31+AF31 -> 153948.64 | ... BI43: =+BI31+BH31+BG31+BF31 -> 2957018 | BN43: =BN31+AZ31+AY31+AX31 -> 2552137 | BO43: =+BO31+BN31+AY31+AZ31 -> 2789217 | BP43: =+BP31+BO31+AZ31+BN31 -> 2907783 | BQ43: =S43 -> 3033955 | BR43: =BR31+BD31+BC31+BB31 -> 2571965 | BT43: =+BT31+BS31 -> 69491 | BU43: =+BU31+BT31 -> 68485 | BV43: =+BV31+BU31 -> 70432.243 | BX43: =+BX31+BW31 -> 183777.28 | BY43: =+BY31+BX31 -> 241770.18 | BZ43: =+BZ31+BY31 -> 346688.7 | CA43: =+CA31+BZ31 -> 600607.18 | CB43: =+CB31+CA31 -> 901857 | CC43: =+CC31+CB31 -> 1006280.9 | CD43: =+CD31+CC31 -> 1604647 | CE43: =+CE31+CD31 -> 2124070 | ... CG43: =+CG31+CF31 -> 2485595 | CI43: =+CI31+CH31 -> 886314 | CJ43: =+CJ31+CI31 -> 2316773 | CK43: =+CK31+CJ31 -> 2794082
B44: LTM EBITDA | D44: =+D37 -> 4410 | E44: =+E37 -> 4962 | F44: =+F37 -> 4339 | G44: =+G37 -> 8236 | H44: =+H37 -> 6198.191 | I44: =+I37 -> 9045.596 | J44: =+J37 -> 13539.772 | K44: =+K37 -> 10696.351 | ... W44: =+W37 -> 0 | AB44: =+AB37+AA37+Z37+Y37 -> 9045.596 | AC44: =+AC37+AB37+AA37+Z37 -> 8460.452 | AD44: =+AD37+AC37+AB37+AA37 -> 9359.285 | AE44: =+AE37+AD37+AC37+AB37 -> 12237.579 | AF44: =+AF37+AE37+AD37+AC37 -> 13539.772 | AG44: =+AG37+AF37+AE37+AD37 -> 13796.513 | AH44: =+AH37+AG37+AF37+AE37 -> 13880.718 | AI44: =+AI37+AH37+AG37+AF37 -> 11450.027 | ... BI44: =+BI37+BH37+BG37+BF37 -> 234622 | BN44: =BN37+AZ37+AY37+AX37 -> 348407 | BO44: =+BO37+BN37+AZ37+AY37 -> 359275 | BP44: =+BP37+BO37+BA37+AZ37 -> 272641 | BQ44: =S44 -> 178536 | BR44: =BR37+BD37+BC37+BB37 -> 145909 | BT44: =+BT37+BS37 -> 6611.416 | BU44: =+BU37+BT37 -> 6438.53 | BV44: =+BV37+BU37 -> 6198.191 | BX44: =+BX37+BW37 -> 25393.096 | BY44: =+BY37+BX37 -> 33739.647 | BZ44: =+BZ37+BY37 -> 52188.905 | CA44: =+CA37+BZ37 -> 97224.421 | CB44: =+CB37+CA37 -> 166227 | CC44: =+CC37+CB37 -> 187165.86 | CD44: =+CD37+CC37 -> 249217 | CE44: =+CE37+CD37 -> 245359 | ... CG44: =+CG37+CF37 -> 125612 | CI44: =+CI37+CH37 -> 151406 | CJ44: =+CJ37+CI37 -> 359817 | CK44: =+CK37+CJ37 -> 350986
B46: Cash flow from operations | D46: 3327.547 | E46: 3529.265 | F46: 4103.667 | G46: 2291.997 | H46: 8318.315 | I46: 5065.641 | J46: 6830.054 | K46: 19017.986 | L46: 20209.815 | M46: 50664.147 | N46: 115479 | O46: 153543 | P46: 339016 | Q46: 489465 | R46: 116308 | S46: 152242 | T46: -101956 | U46: =BG46+BF46+BH46+BI46 -> -12217 | Y46: 524.398 | Z46: =2311.695-Y46 -> 1787.297 | AA46: =4522.42-Z46-Y46 -> 2210.725 | AB46: =I46-AA46-Z46-Y46 -> 543.221 | AC46: -470.039 | AD46: =3166.38-AC46 -> 3636.419 | AE46: =5169.215-AD46-AC46 -> 2002.835 | AF46: =J46-AE46-AD46-AC46 -> 1660.839 | AG46: 5873.257 | AH46: =11013.459-AG46 -> 5140.202 | AI46: =14466.364-AH46-AG46 -> 3452.905 | AJ46: =K46-AI46-AH46-AG46 -> 4551.622 | AK46: 5743.255 | AL46: =10875.612-AK46 -> 5132.357 | AM46: =5514.364-AL46-AK46 -> -5361.248 | AN46: =L46-AM46-AL46-AK46 -> 14695.451 | AO46: 8866.78 | AP46: =17766.751-AO46 -> 8899.971 | AQ46: =32173.516-AP46-AO46 -> 14406.765 | AR46: =M46-AQ46-AP46-AO46 -> 18490.631 | AS46: 23376.924 | AT46: =57977.459-AS46 -> 34600.535 | AU46: =71485.456-AT46-AS46 -> 13507.997 | AV46: =N46-AU46-AT46-AS46 -> 43993.544 | AW46: 154703 | AX46: =131997-AW46 -> -22706 | AY46: =424611-AX46-AW46 -> 292614 | AZ46: =Q46-AY46-AX46-AW46 -> 64854 | BA46: -58747 | BB46: =89843-BA46 -> 148590 | BC46: =85903-BB46-BA46 -> -3940 | BD46: =R46-BC46-BB46-BA46 -> 30405 | BE46: -13401 | BF46: =-51070-BE46 -> -37669 | BG46: =-46711-BF46-BE46 -> 4359 | BH46: =T46-BG46-BF46-BE46 -> -55245 | BI46: 76338 | BN46: -81133 | BO46: =60177-BN46 -> 141310 | BP46: =114173-60177 -> 53996 | BQ46: =S46-BN46-BO46-BP46 -> 38069 | BR46: -17535 | BS46: -483.43 | BT46: =G46-BS46 -> 2775.427 | BU46: 3461.647 | BV46: =H46-BU46 -> 4856.668 | BW46: 10875.612 | BX46: =L46-BW46 -> 9334.203 | BY46: =17766.751 -> 17766.751 | BZ46: =M46-BY46 -> 32897.396 | CA46: 57977.459 | CB46: =N46-CA46 -> 57501.541 | CC46: 131997 | CD46: =P46-CC46 -> 207019 | CE46: 89843 | CF46: =R46-CE46 -> 26465 | CG46: =-51070 -> -51070
B47: Cash flow from investments | D47: -2845.784 | E47: -3560.59 | F47: -3559.465 | G47: -2539.232 | H47: -3181.111 | I47: -3431.871 | J47: -6524.418 | K47: -5955.333 | L47: 12836.726 | M47: -53600.409 | N47: -86421 | O47: -85638 | P47: -165463 | Q47: -238892 | R47: -121372 | S47: -158866 | T47: -190683 | U47: =BG47+BF47+BH47+BI47 -> -249978 | Y47: -419.345 | Z47: =-1402.339-Y47 -> -982.994 | AA47: =-2259.047-Z47-Y47 -> -856.708 | AB47: =I47-AA47-Z47-Y47 -> -1172.824 | AC47: -1482.72 | AD47: =-4638.537-AC47 -> -3155.817 | AE47: =-5618.33-AD47-AC47 -> -979.793 | AF47: =J47-AE47-AD47-AC47 -> -906.088 | AG47: -1856.864 | AH47: =-3768.021-AG47 -> -1911.157 | AI47: =-4447.707-AH47-AG47 -> -679.686 | AJ47: =K47-AI47-AH47-AG47 -> -1507.626 | AK47: 30684.177 | AL47: =23091.203-AK47 -> -7592.974 | AM47: =17360.282-AL47-AK47 -> -5730.921 | AN47: =L47-AM47-AL47-AK47 -> -4523.556 | AO47: -10924.47 | AP47: =-19402.567-AO47 -> -8478.097 | AQ47: =-29842.449-AP47-AO47 -> -10439.882 | AR47: =M47-AQ47-AP47-AO47 -> -23757.96 | AS47: -13414.694 | AT47: =-45820.858-AS47 -> -32406.164 | AU47: =-60263.614-AT47-AS47 -> -14442.756 | AV47: =N47-AU47-AT47-AS47 -> -26157.386 | AW47: -38234 | AX47: =-101117-AW47 -> -62883 | AY47: =-195025-AX47-AW47 -> -93908 | AZ47: =Q47-AY47-AX47-AW47 -> -43867 | BA47: -65992 | BB47: =-126763-BA47 -> -60771 | BC47: =-78826-BB47-BA47 -> 47937 | BD47: =R47-BC47-BB47-BA47 -> -42546 | BE47: 18036 | BF47: =-46931-BE47 -> -64967 | BG47: =-88617-BF47-BE47 -> -41686 | BH47: =T47-BG47-BF47-BE47 -> -102066 | BI47: -41259 | BN47: -91138 | BO47: =-110035-BN47 -> -18897 | BP47: =-104737-(-110035) -> 5298 | BQ47: =S47-BN47-BO47-BP47 -> -54129 | BR47: 23604 | BS47: -1433.751 | BT47: =G47-BS47 -> -1105.481 | BU47: -1286.141 | BV47: =H47-BU47 -> -1894.97 | BW47: 23091.203 | BX47: =L47-BW47 -> -10254.477 | BY47: =-19402.567 -> -19402.567 | BZ47: =M47-BY47 -> -34197.842 | CA47: -45820.858 | CB47: =N47-CA47 -> -40600.142 | CC47: -101117 | CD47: =P47-CC47 -> -64346 | CE47: -126763 | CF47: =R47-CE47 -> 5391 | CG47: =-46931 -> -46931
B48: Cash flow from financing | D48: 1994.012 | E48: 421.932 | F48: -66.483 | G48: -270.776 | H48: -883.828 | I48: 984.261 | J48: -2219.27 | K48: -3016.73 | L48: -10849.553 | M48: 10201.878 | N48: 673 | O48: -5561 | P48: -17416 | Q48: -25144 | R48: 9597 | S48: 12560 | T48: 281903 | U48: =BG48+BF48+BH48+BI48 -> 279611 | Y48: 1429.371 | Z48: =-2071.31-Y48 -> -3500.681 | AA48: =-1144.668-Z48-Y48 -> 926.642 | AB48: =I48-AA48-Z48-Y48 -> 2128.929 | AC48: 1198.883 | AD48: =-2909.299-AC48 -> -4108.182 | AE48: =-1498.97-AD48-AC48 -> 1410.329 | AF48: =J48-AE48-AD48-AC48 -> -720.3 | AG48: 7701.768 | AH48: =522.475-AG48 -> -7179.293 | AI48: =-2731.752-AH48-AG48 -> -3254.227 | AJ48: =K48-AI48-AH48-AG48 -> -284.978 | AK48: -465.147 | AL48: =-1898.007-AK48 -> -1432.86 | AM48: =-4412.027-AL48-AK48 -> -2514.02 | AN48: =L48-AM48-AL48-AK48 -> -6437.526 | AO48: 2949.942 | AP48: =5009.838-AO48 -> 2059.896 | AQ48: =-2060.892-AP48-AO48 -> -7070.73 | AR48: =M48-AQ48-AP48-AO48 -> 12262.77 | AS48: -12237.613 | AT48: =-14775.939-AS48 -> -2538.326 | AU48: =-2727.881-AT48-AS48 -> 12048.058 | AV48: =N48-AU48-AT48-AS48 -> 3400.881 | AW48: -36246 | AX48: =-23958-AW48 -> 12288 | AY48: =-59224-AX48-AW48 -> -35266 | AZ48: =Q48-AY48-AX48-AW48 -> 34080 | BA48: 35440 | BB48: =-8491-BA48 -> -43931 | BC48: =18622-BB48-BA48 -> 27113 | BD48: =R48-BC48-BB48-BA48 -> -9025 | BE48: -9151 | BF48: =45606-BE48 -> 54757 | BG48: =172893-BF48-BE48 -> 127287 | BH48: =T48-BG48-BF48-BE48 -> 109010 | BI48: -11443 | BN48: 48944 | BO48: =-11468-BN48 -> -60412 | BP48: =24823-(-11468) -> 36291 | BQ48: =S48-BN48-BO48-BP48 -> -12263 | BR48: -11975 | BS48: -88.198 | BT48: =G48-BS48 -> -182.578 | BU48: 1498.232 | BV48: =H48-BU48 -> -2382.06 | BW48: -1898.007 | BX48: =L48-BW48 -> -8951.546 | BY48: =5009.838 -> 5009.838 | BZ48: =M48-BY48 -> 5192.04 | CA48: -14775.939 | CB48: =N48-CA48 -> 15448.939 | CC48: -23958 | CD48: =P48-CC48 -> 6542 | CE48: -8491 | CF48: =R48-CE48 -> 18088 | CG48: =45606 -> 45606
B49: FX impact | D49: -102.995 | E49: 1316.652 | F49: 423.162 | G49: 1016.748 | H49: 2011.847 | I49: 1039.286 | J49: 5468.12 | K49: 2702.477 | L49: 26446.599 | M49: 52853.767 | N49: 42349 | O49: 77452 | P49: 79112 | Q49: 114221 | R49: 40828 | S49: 53441 | T49: 67450 | U49: =BG49+BF49+BH49+BI49 -> 54764 | Y49: 322.272 | Z49: =-6.692-Y49 -> -328.964 | AA49: =178.779-Z49-Y49 -> 185.471 | AB49: =I49-AA49-Z49-Y49 -> 860.507 | AC49: 853.404 | AD49: =3053.052-AC49 -> 2199.648 | AE49: =8829.203-AD49-AC49 -> 5776.151 | AF49: =J49-AE49-AD49-AC49 -> -3361.083 | AG49: 1380.682 | AH49: =2056.203-AG49 -> 675.521 | AI49: =1517.027-AH49-AG49 -> -539.176 | AJ49: =K49-AI49-AH49-AG49 -> 1185.45 | AK49: 6366.778 | AL49: =9925.05-AK49 -> 3558.272 | AM49: =19228.344-AL49-AK49 -> 9303.294 | AN49: =L49-AM49-AL49-AK49 -> 7218.255 | AO49: 7326.393 | AP49: =12658.632-AO49 -> 5332.239 | AQ49: =13112.186-AP49-AO49 -> 453.554 | AR49: =M49-AQ49-AP49-AO49 -> 39741.581 | AS49: 14519.617 | AT49: =27389.938-AS49 -> 12870.321 | AU49: =38424.379-AT49-AS49 -> 11034.441 | AV49: =N49-AU49-AT49-AS49 -> 3924.621 | AW49: 7156 | AX49: =47401-AW49 -> 40245 | AY49: =103018-AX49-AW49 -> 55617 | AZ49: =Q49-AY49-AX49-AW49 -> 11203 | BA49: 31247 | BB49: =23036-BA49 -> -8211 | BC49: =38129-BB49-BA49 -> 15093 | BD49: =R49-BC49-BB49-BA49 -> 2699 | BE49: 20580 | BF49: =42195-BE49 -> 21615 | BG49: =57269-BF49-BE49 -> 15074 | BH49: =T49-BG49-BF49-BE49 -> 10181 | BI49: 7894 | BN49: 43153 | BO49: =31110-BN49 -> -12043 | BP49: =50824-31110 -> 19714 | BQ49: =S49-BN49-BO49-BP49 -> 2617 | BR49: 26932 | BS49: 601.508 | BT49: =G49-BS49 -> 415.24 | BU49: -57.789 | BV49: =H49-BU49 -> 2069.636 | BW49: 9925.05 | BX49: =L49-BW49 -> 16521.549 | BY49: =12658.632 -> 12658.632 | BZ49: =M49-BY49 -> 40195.135 | CA49: 27389.938 | CB49: =N49-CA49 -> 14959.062 | CC49: 47401 | CD49: =P49-CC49 -> 31711 | CE49: 23036 | CF49: =R49-CE49 -> 17792 | CG49: =42195 -> 42195
B50: Inflation effect on cash and cash equivalents | N50: 0 | O50: -174284 | P50: -176733 | Q50: -255166 | R50: -173191 | S50: -226696 | T50: -135462 | U50: =BG50+BF50+BH50+BI50 -> -149652 | AV50: =N50-AU50-AT50-AS50 -> 0 | AY50: =-161804-AX50-AW50 -> -161804 | AZ50: =Q50-AY50-AX50-AW50 -> -93362 | BA50: 0 | BB50: 0 | BC50: =-139569-BB50-BA50 -> -139569 | BD50: =R50-BC50-BB50-BA50 -> -33622 | BE50: -42593 | BF50: =-69050-BE50 -> -26457 | BG50: =-108268-BF50-BE50 -> -39218 | BH50: =T50-BG50-BF50-BE50 -> -27194 | BI50: -56783 | BN50: -81775 | BO50: =-128980-BN50 -> -47205 | BP50: =-186040-(-128980) -> -57060 | BQ50: =S50-BN50-BO50-BP50 -> -40656 | BR50: -55743 | BZ50: =M50-BY50 -> 0 | CB50: =N50-CA50 -> 0 | CD50: =P50-CC50 -> -176733 | CE50: -95506 | CF50: =R50-CE50 -> -77685 | CG50: =-69050 -> -69050
B51: Net change in cash | D51: =SUM(D46:D49) -> 2372.78 | E51: =SUM(E46:E49) -> 1707.259 | F51: =SUM(F46:F49) -> 900.881 | G51: =SUM(G46:G49) -> 498.737 | H51: =SUM(H46:H49) -> 6265.223 | I51: =SUM(I46:I49) -> 3657.317 | J51: =SUM(J46:J49) -> 3554.486 | K51: =SUM(K46:K49) -> 12748.4 | ... M51: =SUM(M46:M49) -> 60119.383 | N51: =SUM(N46:N50) -> 72080 | O51: =SUM(O46:O50) -> -34488 | P51: =SUM(P46:P50) -> 58516 | Q51: =SUM(Q46:Q50) -> 84484 | R51: =SUM(R46:R50) -> -127830 | S51: =SUM(S46:S50) -> -167319 | T51: =SUM(T46:T50) -> -78748 | U51: =SUM(U46:U50) -> -77472 | Y51: =SUM(Y46:Y50) -> 1856.696 | Z51: =SUM(Z46:Z50) -> -3025.342 | AA51: =SUM(AA46:AA50) -> 2466.13 | AB51: =SUM(AB46:AB50) -> 2359.833 | AC51: =SUM(AC46:AC50) -> 99.528 | AD51: =SUM(AD46:AD50) -> -1427.932 | AE51: =SUM(AE46:AE50) -> 8209.522 | AF51: =SUM(AF46:AF50) -> -3326.632 | ... BI51: =SUM(BI46:BI50) -> -25253 | BN51: =SUM(BN46:BN50) -> -161949 | BO51: =SUM(BO46:BO50) -> 2753 | BP51: =SUM(BP46:BP50) -> 58239 | BQ51: =SUM(BQ46:BQ50) -> -66362 | BR51: =SUM(BR46:BR50) -> -34717 | BS51: =SUM(BS46:BS50) -> -1403.871 | BT51: =SUM(BT46:BT50) -> 1902.608 | BU51: =SUM(BU46:BU50) -> 3615.949 | ... CG51: =SUM(CG46:CG50) -> -79250
B53: Short term debt | D53: 4743 | E53: 4692 | F53: 5420 | G53: 7379 | H53: =2556.705+4926.372 -> 7483.077 | I53: =3402.487+9792.637 -> 13195.124 | J53: =8031.703+7581.929 -> 15613.632 | K53: =13641.034+7644.733 -> 21285.767 | L53: =23766.653+47957.577 -> 71724.23 | M53: =61806.242+61704.287 -> 123510.53 | N53: =92414+133538 -> 225952 | O53: =152273+220035 -> 372308 | P53: =221444+194432 -> 415876 | Q53: =277862+243967 -> 521829 | R53: =276806+249531 -> 526337 | S53: =362317+326616 -> 688933 | T53: =233739+519990 -> 753729 | U53: =BI53 -> 766170 | Y53: =2915.636+5704.848 -> 8620.484 | Z53: =2409.54+8037.452 -> 10446.992 | AA53: =3025.876+9060.422 -> 12086.298 | AB53: =I53 -> 13195.124 | AC53: =3423.526+12054.519 -> 15478.045 | AD53: =3336.929+10570.992 -> 13907.921 | AE53: =7853.733+9085.198 -> 16938.931 | AF53: =J53 -> 15613.632 | AG53: =11014.721+7804.45 -> 18819.171 | AH53: =12708.793+8305.801 -> 21014.594 | AI53: =11099.022+8156.739 -> 19255.761 | AJ53: =K53 -> 21285.767 | AK53: =26949.902+43255.861 -> 70205.763 | AL53: =35983.908+32003.306 -> 67987.214 | AM53: =35393.854+40051.992 -> 75445.846 | AN53: =L53 -> 71724.23 | AO53: =30613.922+54884.424 -> 85498.346 | AP53: =33392.208+57095.733 -> 90487.941 | AQ53: =30799.835+53980.519 -> 84780.354 | AR53: =M53 -> 123510.53 | AS53: =81626.113+82503.242 -> 164129.35 | AT53: =70396.052+121205.243 -> 191601.29 | AU53: =81984.66+126655.567 -> 208640.23 | AV53: =N53 -> 225952 | AW53: =78429+122705 -> 201134 | AX53: =98309+136564 -> 234873 | AY53: =129157+146570 -> 275727 | AZ53: =Q53 -> 521829 | BA53: =247512+172813 -> 420325 | BB53: =193899+260154 -> 454053 | BC53: =205956+263429 -> 469385 | BD53: =R53 -> 526337 | BE53: =248993+296365 -> 545358 | BF53: =199542+407492 -> 607034 | BG53: =203651+507777 -> 711428 | BH53: =T53 -> 753729 | BI53: =192463+573707 -> 766170 | BN53: =BA53 -> 420325 | BO53: =BB53 -> 454053 | BP53: =BC53 -> 469385 | BQ53: =S53 -> 688933 | BR53: =BE53 -> 545358 | BT53: =G53 -> 7379 | BU53: =4177+5492 -> 9669 | BV53: =H53 -> 7483.077 | BW53: =35983.908+32003.306 -> 67987.214 | BX53: =L53 -> 71724.23 | BY53: =33392.208+57095.733 -> 90487.941 | BZ53: =M53 -> 123510.53 | CA53: =70396.052+121205.243 -> 191601.29 | CB53: =N53 -> 225952 | CC53: =98309+136564 -> 234873 | CD53: =P53 -> 415876 | CE53: =193899+260154 -> 454053 | CF53: =R53 -> 526337 | CG53: =199542+407492 -> 607034
B54: Long term debt | D54: 7647 | E54: 12389 | F54: 14401 | G54: 17160 | H54: 22707.627 | I54: 23185.745 | J54: 34200.045 | K54: 39010.324 | L54: 110083.01 | M54: 162779.11 | N54: 152598 | O54: 251440 | P54: 284660 | Q54: 357184 | R54: 352987 | S54: 462032 | T54: 601539 | U54: =BI54 -> 618329 | Y54: 24140.392 | Z54: 20610.649 | AA54: 20526.112 | AB54: =I54 -> 23185.745 | AC54: 25609.167 | AD54: 29502.982 | AE54: 37118.362 | AF54: =J54 -> 34200.045 | AG54: 43169.514 | AH54: 39621.176 | AI54: 38462.63 | AJ54: =K54 -> 39010.324 | AK54: 102250.85 | AL54: 107196.22 | AM54: 113425.86 | AN54: =L54 -> 110083.01 | AO54: 115058.07 | AP54: 124019.55 | AQ54: 123672.78 | AR54: =M54 -> 162779.11 | AS54: 148223.25 | AT54: 152686.56 | AU54: 165592.96 | AV54: =N54 -> 152598 | AW54: 159580 | AX54: 194102 | AY54: 247886 | AZ54: =Q54 -> 357184 | BA54: 275263 | BB54: 302950 | BC54: 350587 | BD54: =R54 -> 352987 | BE54: 399013 | BF54: =446576 -> 446576 | BG54: 498958 | BH54: =T54 -> 601539 | BI54: 618329 | BN54: =BA54 -> 275263 | BO54: =BB54 -> 302950 | BP54: =BC54 -> 350587 | BQ54: =S54 -> 462032 | BR54: =BE54 -> 399013 | BT54: =G54 -> 17160 | BU54: 18919 | BV54: =H54 -> 22707.627 | BW54: 107196.22 | BX54: =L54 -> 110083.01 | BY54: 124019.55 | BZ54: =M54 -> 162779.11 | CA54: 152686.56 | CB54: =N54 -> 152598 | CC54: 194102 | CD54: =P54 -> 284660 | CE54: 302950 | CF54: =R54 -> 352987 | CG54: =446576 -> 446576
B55: Total debt | D55: =SUM(D53:D54) -> 12390 | E55: =SUM(E53:E54) -> 17081 | F55: =SUM(F53:F54) -> 19821 | G55: =SUM(G53:G54) -> 24539 | H55: =SUM(H53:H54) -> 30190.704 | I55: =SUM(I53:I54) -> 36380.869 | J55: =SUM(J53:J54) -> 49813.677 | K55: =SUM(K53:K54) -> 60296.091 | ... W55: =SUM(W53:W54) -> 0 | Y55: =SUM(Y53:Y54) -> 32760.876 | Z55: =SUM(Z53:Z54) -> 31057.641 | AA55: =SUM(AA53:AA54) -> 32612.41 | AB55: =SUM(AB53:AB54) -> 36380.869 | AC55: =SUM(AC53:AC54) -> 41087.212 | AD55: =SUM(AD53:AD54) -> 43410.903 | AE55: =SUM(AE53:AE54) -> 54057.293 | AF55: =SUM(AF53:AF54) -> 49813.677 | ... BI55: =SUM(BI53:BI54) -> 1384499 | BN55: =SUM(BN53:BN54) -> 695588 | BO55: =SUM(BO53:BO54) -> 757003 | BP55: =SUM(BP53:BP54) -> 819972 | BQ55: =SUM(BQ53:BQ54) -> 1150965 | BR55: =SUM(BR53:BR54) -> 944371 | BT55: =SUM(BT53:BT54) -> 24539 | BU55: =SUM(BU53:BU54) -> 28588 | BV55: =SUM(BV53:BV54) -> 30190.704 | BW55: =SUM(BW53:BW54) -> 175183.44 | BX55: =SUM(BX53:BX54) -> 181807.24 | BY55: =SUM(BY53:BY54) -> 214507.49 | BZ55: =SUM(BZ53:BZ54) -> 286289.64 | CA55: =SUM(CA53:CA54) -> 344287.85 | ... CG55: =SUM(CG53:CG54) -> 1053610
B56: Cash | D56: 7104 | E56: 8897 | F56: 9908 | G56: 10553 | H56: 16996.921 | I56: 20850.437 | J56: 24577.49 | K56: 37816.36 | L56: =60360.801+48972.272 -> 109333.07 | M56: =93849.314+103245.309 -> 197094.62 | N56: =151618+130959 -> 282577 | O56: =249825+215784 -> 465609 | P56: =333001+278016 -> 611017 | Q56: =417840+348846 -> 766686 | R56: =307172+367960 -> 675132 | S56: =402064+481630 -> 883694 | T56: =358830+462288 -> 821118 | U56: =BI56 -> 898265 | Y56: 18888.512 | Z56: 15910.549 | AA56: 18433.862 | AB56: =I56 -> 20850.437 | AC56: 21004.679 | AD56: 19585.856 | AE56: 27869.94 | AF56: =J56 -> 24577.49 | AG56: 37766.769 | AH56: 34701.485 | AI56: 33780.736 | AJ56: =K56 -> 37816.36 | AK56: =55020.804+46596.586 -> 101617.39 | AL56: =55074.952+46094.215 -> 101169.17 | AM56: =50946.583+55690.276 -> 106636.86 | AN56: =L56 -> 109333.07 | AO56: =68837.959+51348.261 -> 120186.22 | AP56: =70088.555+58666.93 -> 128755.48 | AQ56: =68340.445+61353.64 -> 129694.09 | AR56: =M56 -> 197094.62 | AS56: =116521.964+100745.279 -> 217267.24 | AT56: =125595.041+118002.714 -> 243597.76 | AU56: =130039.361+136504.403 -> 266543.76 | AV56: =N56 -> 282577 | AW56: =166139+121564 -> 287703 | AX56: =212434+144349 -> 356783 | AY56: =257595+232612 -> 490207 | AZ56: =Q56 -> 766686 | BA56: =272639+269381 -> 542020 | BB56: =287972+292491 -> 580463 | BC56: =329780+356528 -> 686308 | BD56: =R56 -> 675132 | BE56: =325424+387506 -> 712930 | BF56: =311130+432113 -> 743243 | BG56: =375008+488536 -> 863544 | BH56: =T56 -> 821118 | BI56: =392039+506226 -> 898265 | BN56: =BA56 -> 542020 | BO56: =BB56 -> 580463 | BP56: =BC56 -> 686308 | BQ56: =S56 -> 883694 | BR56: =BE56 -> 712930 | BT56: =G56 -> 10553 | BU56: 14252 | BV56: =H56 -> 16996.921 | BW56: =55074.952+46094.215 -> 101169.17 | BX56: =L56 -> 109333.07 | BY56: =70088.555+58666.93 -> 128755.48 | BZ56: =M56 -> 197094.62 | CA56: =125595.041+118002.714 -> 243597.76 | CB56: =N56 -> 282577 | CC56: =212434+144349 -> 356783 | CD56: =P56 -> 611017 | CE56: =287972+292491 -> 580463 | CF56: =R56 -> 675132 | CG56: =311130+432113 -> 743243
B57: Net debt | D57: =+D55-D56 -> 5286 | E57: =+E55-E56 -> 8184 | F57: =+F55-F56 -> 9913 | G57: =+G55-G56 -> 13986 | H57: =+H55-H56 -> 13193.783 | I57: =+I55-I56 -> 15530.432 | J57: =+J55-J56 -> 25236.187 | K57: =+K55-K56 -> 22479.731 | ... W57: =+W55-W56 -> 0 | Y57: =+Y55-Y56 -> 13872.364 | Z57: =+Z55-Z56 -> 15147.092 | AA57: =+AA55-AA56 -> 14178.548 | AB57: =+AB55-AB56 -> 15530.432 | AC57: =+AC55-AC56 -> 20082.533 | AD57: =+AD55-AD56 -> 23825.047 | AE57: =+AE55-AE56 -> 26187.353 | AF57: =+AF55-AF56 -> 25236.187 | ... BI57: =+BI55-BI56 -> 486234 | BN57: =+BN55-BN56 -> 153568 | BO57: =+BO55-BO56 -> 176540 | BP57: =+BP55-BP56 -> 133664 | BQ57: =+BQ55-BQ56 -> 267271 | BR57: =+BR55-BR56 -> 231441 | BT57: =+BT55-BT56 -> 13986 | BU57: =+BU55-BU56 -> 14336 | BV57: =+BV55-BV56 -> 13193.783 | BW57: =+BW55-BW56 -> 74014.27 | BX57: =+BX55-BX56 -> 72474.171 | BY57: =+BY55-BY56 -> 85752.01 | BZ57: =+BZ55-BZ56 -> 89195.017 | CA57: =+CA55-CA56 -> 100690.1 | ... CG57: =+CG55-CG56 -> 310367
B59: Equity (as reported on balance sheet) | D59: 24261 | E59: 26190 | F59: 29301 | G59: 33675 | H59: 36865.898 | I59: 42931.018 | J59: 46958.41 | K59: 49652.035 | L59: 88071.052 | M59: 121105.06 | N59: 247198 | O59: 609933 | P59: 775845 | Q59: 973506 | R59: 858664 | S59: 1123921 | T59: 1092573 | U59: =BI59 -> 1144002 | Y59: 36727.619 | Z59: 39207.565 | AA59: 41210.832 | AB59: =I59 -> 42931.018 | AC59: 40301.894 | AD59: 42637.26 | AE59: 45166.086 | AF59: =J59 -> 46958.41 | AG59: 44030.069 | AH59: 46624.362 | AI59: 47475.627 | AJ59: =K59 -> 49652.035 | AK59: 75752.702 | AL59: 78037.377 | AM59: 83580.067 | AN59: =L59 -> 88071.052 | AO59: 92746.57 | AP59: 96922.693 | AQ59: 104188.44 | AR59: =M59 -> 121105.06 | AS59: 138974.75 | AT59: 164018.19 | AU59: 204052.42 | AV59: =N59 -> 247198 | AW59: 255249 | AX59: 289432 | AY59: 349227 | AZ59: =Q59 -> 973506 | BA59: 754952 | BB59: 794901 | BC59: 841797 | BD59: =R59 -> 858664 | BE59: 916778 | BF59: 959379 | BG59: 1039810 | BH59: =T59 -> 1092573 | BI59: 1144002 | BN59: =BA59 -> 754952 | BO59: =BB59 -> 794901 | BP59: =BC59 -> 841797 | BQ59: =S59 -> 1123921 | BR59: =BE59 -> 916778 | BT59: =G59 -> 33675 | BU59: 33758 | BV59: =H59 -> 36865.898 | BW59: 78037.377 | BX59: =L59 -> 88071.052 | BY59: 96922.693 | BZ59: =M59 -> 121105.06 | CA59: 164018.19 | CB59: =N59 -> 247198 | CC59: 289432 | CD59: =P59 -> 775845 | CE59: 794901 | CF59: =R59 -> 858664 | CG59: 959379
B60: Market Cap | D60: 23482 | E60: 22318 | F60: 31445 | G60: 27717 | H60: 34995.392 | I60: 46863.395 | J60: 36009.752 | K60: 33601 | L60: 56703 | M60: =28.38*2540 -> 72085.2 | N60: =75.55*2540 -> 191897 | O60: =75.55*2535 -> 191519.25 | P60: =175.2*2535 -> 444132 | Q60: =175.2*2535 -> 444132 | R60: 452911.39 | S60: 452911.39 | T60: 566773.21 | U60: =BI60 -> 469141.1 | Y60: 38926.035 | Z60: 41030.83 | AA60: 41461.932 | AB60: =I60 -> 46863.395 | AC60: 41436.573 | AD60: 36060.47 | AE60: 43262.42 | AF60: =J60 -> 36009.752 | AG60: 40802.599 | AH60: 44479.651 | AI60: 47953.831 | AJ60: =K60 -> 33601 | AK60: 34057.111 | AL60: 45646.165 | AM60: =4712*AM95 -> 36379.938 | AN60: =L60 -> 56703 | AO60: 49221.78 | AP60: 46483.01 | AQ60: 79728.63 | AR60: =M60 -> 72085.2 | AS60: =38.76*2540 -> 98450.4 | AT60: 53640 | AU60: 161029.5 | AV60: =N60 -> 191897 | AW60: =76.5*2540 -> 194310 | AX60: 334381 | AY60: 376675.42 | AZ60: =Q60 -> 444132 | BA60: =199.2*2535 -> 504972 | BB60: 477260 | BC60: 417662.4 | BD60: =R60 -> 452911.39 | BE60: 414872.92 | BF60: 390528.3 | BG60: 488634 | BH60: =T60 -> 566773.21 | BI60: 469141.1 | BN60: =BA60 -> 504972 | BO60: =BB60 -> 477260 | BP60: =BC60 -> 417662.4 | BQ60: =S60 -> 452911.39 | BR60: =BE60 -> 414872.92 | BT60: =G60 -> 27717 | BU60: 33905 | BV60: =H60 -> 34995.392 | BW60: 45646.165 | BX60: =L60 -> 56703 | BY60: 46483.01 | BZ60: =M60 -> 72085.2 | CA60: 53640 | CB60: =N60 -> 191897 | CC60: 334381 | CD60: =P60 -> 444132 | CE60: 477260 | CF60: =R60 -> 452911.39 | CG60: 390528.3
B61: Total debt + Market Cap | D61: =+D55+D60 -> 35872 | E61: =+E55+E60 -> 39399 | F61: =+F55+F60 -> 51266 | G61: =+G55+G60 -> 52256 | H61: =+H55+H60 -> 65186.096 | I61: =+I55+I60 -> 83244.264 | J61: =+J55+J60 -> 85823.429 | K61: =+K55+K60 -> 93897.091 | ... W61: =+W55+W60 -> 0 | Y61: =+Y55+Y60 -> 71686.911 | Z61: =+Z55+Z60 -> 72088.471 | AA61: =+AA55+AA60 -> 74074.342 | AB61: =+AB55+AB60 -> 83244.264 | AC61: =+AC55+AC60 -> 82523.785 | AD61: =+AD55+AD60 -> 79471.373 | AE61: =+AE55+AE60 -> 97319.713 | AF61: =+AF55+AF60 -> 85823.429 | ... BI61: =+BI55+BI60 -> 1853640.1 | BN61: =+BN55+BN60 -> 1200560 | BO61: =+BO55+BO60 -> 1234263 | BP61: =+BP55+BP60 -> 1237634.4 | BQ61: =+BQ55+BQ60 -> 1603876.4 | BR61: =+BR55+BR60 -> 1359243.9 | BT61: =+BT55+BT60 -> 52256 | BU61: =+BU55+BU60 -> 62493 | BV61: =+BV55+BV60 -> 65186.096 | BW61: =+BW55+BW60 -> 220829.6 | BX61: =+BX55+BX60 -> 238510.24 | BY61: =+BY55+BY60 -> 260990.51 | BZ61: =+BZ55+BZ60 -> 358374.84 | CA61: =+CA55+CA60 -> 397927.85 | ... CG61: =+CG55+CG60 -> 1444138.3
B62: Net debt + Market Cap | D62: =+D57+D60 -> 28768 | E62: =+E57+E60 -> 30502 | F62: =+F57+F60 -> 41358 | G62: =+G57+G60 -> 41703 | H62: =+H57+H60 -> 48189.175 | I62: =+I57+I60 -> 62393.827 | J62: =+J57+J60 -> 61245.939 | K62: =+K57+K60 -> 56080.731 | ... W62: =+W57+W60 -> 0 | Y62: =+Y57+Y60 -> 52798.399 | Z62: =+Z57+Z60 -> 56177.922 | AA62: =+AA57+AA60 -> 55640.48 | AB62: =+AB57+AB60 -> 62393.827 | AC62: =+AC57+AC60 -> 61519.106 | AD62: =+AD57+AD60 -> 59885.517 | AE62: =+AE57+AE60 -> 69449.773 | AF62: =+AF57+AF60 -> 61245.939 | ... BI62: =+BI57+BI60 -> 955375.1 | BN62: =+BN57+BN60 -> 658540 | BO62: =+BO57+BO60 -> 653800 | BP62: =+BP57+BP60 -> 551326.4 | BQ62: =+BQ57+BQ60 -> 720182.39 | BR62: =+BR57+BR60 -> 646313.92 | BT62: =+BT57+BT60 -> 41703 | BU62: =+BU57+BU60 -> 48241 | BV62: =+BV57+BV60 -> 48189.175 | BW62: =+BW57+BW60 -> 119660.43 | BX62: =+BX57+BX60 -> 129177.17 | BY62: =+BY57+BY60 -> 132235.02 | BZ62: =+BZ57+BZ60 -> 161280.22 | CA62: =+CA57+CA60 -> 154330.1 | ... CG62: =+CG57+CG60 -> 700895.3
B64: CREDIT RATIOS - CONSOLIDATED
B65: Net leverage | D65: =+D57/D44 -> 1.1986395 | E65: =+E57/E44 -> 1.6493349 | F65: =+F57/F44 -> 2.2846278 | G65: =+G57/G44 -> 1.6981544 | H65: =+H57/H44 -> 2.1286506 | I65: =+I57/I44 -> 1.7169053 | J65: =+J57/J44 -> 1.8638561 | K65: =+K57/K44 -> 2.1016262 | ... U65: =+U57/U44 -> 2.0724144 | AB65: =+AB57/AB44 -> 1.7169053 | AC65: =+AC57/AC44 -> 2.373695 | AD65: =+AD57/AD44 -> 2.5456055 | AE65: =+AE57/AE44 -> 2.1399129 | AF65: =+AF57/AF44 -> 1.8638561 | AG65: =+AG57/AG44 -> 1.7556549 | AH65: =+AH57/AH44 -> 1.8683677 | AI65: =+AI57/AI44 -> 2.09062 | ... BI65: =+BI57/BI44 -> 2.0724144 | BN65: =+BN57/BN44 -> 0.44077186 | BO65: =+BO57/BO44 -> 0.49137847 | BP65: =+BP57/BP44 -> 0.49025642 | BQ65: =+BQ57/BQ44 -> 1.4970146 | BR65: =+BR57/BR44 -> 1.586201 | BT65: =+BT57/BT44 -> 2.1154319 | BU65: =+BU57/BU44 -> 2.2265952 | BV65: =+BV57/BV44 -> 2.1286506 | BX65: =+BX57/BX44 -> 2.8540896 | BY65: =+BY57/BY44 -> 2.5415799 | BZ65: =+BZ57/BZ44 -> 1.7090801 | CA65: =+CA57/CA44 -> 1.0356461 | CB65: =+CB57/CB44 -> 0.57736108 | CC65: =+CC57/CC44 -> 0.38571137 | CD65: =+CD57/CD44 -> 0.35920102 | CE65: =+CE57/CE44 -> 0.71951712 | ... CG65: =+CG57/CG44 -> 2.4708388
B66: Gross leverage | D66: =+D55/D44 -> 2.8095238 | E66: =+E55/E44 -> 3.442362 | F66: =+F55/F44 -> 4.5681032 | G66: =+G55/G44 -> 2.9794803 | H66: =+H55/H44 -> 4.8708896 | I66: =+I55/I44 -> 4.0219427 | J66: =+J55/J44 -> 3.6790632 | K66: =+K55/K44 -> 5.6370711 | ... U66: =+U55/U44 -> 5.9009769 | AB66: =+AB55/AB44 -> 4.0219427 | AC66: =+AC55/AC44 -> 4.856385 | AD66: =+AD55/AD44 -> 4.6382713 | AE66: =+AE55/AE44 -> 4.4173192 | AF66: =+AF55/AF44 -> 3.6790632 | AG66: =+AG55/AG44 -> 4.493069 | AH66: =+AH55/AH44 -> 4.3683454 | AI66: =+AI55/AI44 -> 5.0408956 | ... BI66: =+BI55/BI44 -> 5.9009769 | BN66: =+BN55/BN44 -> 1.9964811 | BO66: =+BO55/BO44 -> 2.1070294 | BP66: =+BP55/BP44 -> 3.0075154 | BQ66: =+BQ55/BQ44 -> 6.446683 | BR66: =+BR55/BR44 -> 6.4723286 | BT66: =+BT55/BT44 -> 3.7116103 | BU66: =+BU55/BU44 -> 4.4401439 | BV66: =+BV55/BV44 -> 4.8708896 | BX66: =+BX55/BX44 -> 7.1597116 | BY66: =+BY55/BY44 -> 6.3577279 | BZ66: =+BZ55/BZ44 -> 5.4856418 | CA66: =+CA55/CA44 -> 3.5411664 | CB66: =+CB55/CB44 -> 2.2773075 | CC66: =+CC55/CC44 -> 2.2919511 | CD66: =+CD55/CD44 -> 2.8109479 | CE66: =+CE55/CE44 -> 3.0852873 | ... CG66: =+CG55/CG44 -> 8.3878133
B67: (Net debt + Market Cap )/ EBITDA | D67: =+D62/D44 -> 6.523356 | E67: =+E62/E44 -> 6.1471181 | F67: =+F62/F44 -> 9.5316893 | G67: =+G62/G44 -> 5.0635017 | H67: =+H62/H44 -> 7.7747161 | I67: =+I62/I44 -> 6.8977022 | J67: =+J62/J44 -> 4.5234099 | K67: =+K62/K44 -> 5.2429778 | ... U67: =+U62/U44 -> 4.0719758 | AB67: =+AB62/AB44 -> 6.8977022 | AC67: =+AC62/AC44 -> 7.2713735 | AD67: =+AD62/AD44 -> 6.398514 | AE67: =+AE62/AE44 -> 5.6751236 | AF67: =+AF62/AF44 -> 4.5234099 | AG67: =+AG62/AG44 -> 4.7131123 | AH67: =+AH62/AH44 -> 5.0727877 | AI67: =+AI62/AI44 -> 6.2787176 | ... BI67: =+BI62/BI44 -> 4.0719758 | BN67: =+BN62/BN44 -> 1.8901457 | BO67: =+BO62/BO44 -> 1.8197759 | BP67: =+BP62/BP44 -> 2.0221698 | BQ67: =+BQ62/BQ44 -> 4.0338217 | BR67: =+BR62/BR44 -> 4.4295686 | BT67: =+BT62/BT44 -> 6.3077259 | BU67: =+BU62/BU44 -> 7.4925488 | BV67: =+BV62/BV44 -> 7.7747161 | BX67: =+BX62/BX44 -> 5.0870981 | BY67: =+BY62/BY44 -> 3.9192769 | BZ67: =+BZ62/BZ44 -> 3.0903162 | CA67: =+CA62/CA44 -> 1.5873594 | CB67: =+CB62/CB44 -> 1.7317885 | CC67: =+CC62/CC44 -> 2.1722605 | CD67: =+CD62/CD44 -> 2.1413106 | CE67: =+CE62/CE44 -> 2.6646669 | ... CG67: =+CG62/CG44 -> 5.5798435
B68: Net debt / (Net debt + Market Cap) | D68: =+D57/D62 -> 0.18374583 | E68: =+E57/E62 -> 0.26831027 | F68: =+F57/F62 -> 0.23968761 | G68: =+G57/G62 -> 0.33537156 | H68: =+H57/H62 -> 0.27379142 | I68: =+I57/I62 -> 0.24890975 | J68: =+J57/J62 -> 0.4120467 | K68: =+K57/K62 -> 0.4008459 | ... U68: =+U57/U62 -> 0.50894565 | Y68: =+Y57/Y62 -> 0.26274213 | Z68: =+Z57/Z62 -> 0.26962713 | AA68: =+AA57/AA62 -> 0.25482433 | AB68: =+AB57/AB62 -> 0.24890975 | AC68: =+AC57/AC62 -> 0.32644384 | AD68: =+AD57/AD62 -> 0.39784322 | AE68: =+AE57/AE62 -> 0.37706895 | AF68: =+AF57/AF62 -> 0.4120467 | ... BI68: =+BI57/BI62 -> 0.50894565 | BN68: =+BN57/BN62 -> 0.23319464 | BO68: =+BO57/BO62 -> 0.27002141 | BP68: =+BP57/BP62 -> 0.24244078 | BQ68: =+BQ57/BQ62 -> 0.37111571 | BR68: =+BR57/BR62 -> 0.35809379 | BT68: =+BT57/BT62 -> 0.33537156 | BU68: =+BU57/BU62 -> 0.2971746 | BV68: =+BV57/BV62 -> 0.27379142 | BW68: =+BW57/BW62 -> 0.61853586 | BX68: =+BX57/BX62 -> 0.56104473 | BY68: =+BY57/BY62 -> 0.64848185 | BZ68: =+BZ57/BZ62 -> 0.55304376 | CA68: =+CA57/CA62 -> 0.65243332 | ... CG68: =+CG57/CG62 -> 0.44281507
B69: Net debt / Market Cap | D69: =+D57/D60 -> 0.22510859 | E69: =+E57/E60 -> 0.36669953 | F69: =+F57/F60 -> 0.31524885 | G69: =+G57/G60 -> 0.50460006 | H69: =+H57/H60 -> 0.37701486 | I69: =+I57/I60 -> 0.33139793 | J69: =+J57/J60 -> 0.70081536 | K69: =+K57/K60 -> 0.6690197 | ... U69: =+U57/U60 -> 1.0364345 | Y69: =+Y57/Y60 -> 0.35637752 | Z69: =+Z57/Z60 -> 0.36916368 | AA69: =+AA57/AA60 -> 0.34196544 | AB69: =+AB57/AB60 -> 0.33139793 | AC69: =+AC57/AC60 -> 0.48465719 | AD69: =+AD57/AD60 -> 0.66069708 | AE69: =+AE57/AE60 -> 0.60531411 | AF69: =+AF57/AF60 -> 0.70081536 | ... BI69: =+BI57/BI60 -> 1.0364345 | BN69: =+BN57/BN60 -> 0.30411191 | BO69: =+BO57/BO60 -> 0.3699032 | BP69: =+BP57/BP60 -> 0.32002881 | BQ69: =+BQ57/BQ60 -> 0.59011764 | BR69: =+BR57/BR60 -> 0.55785998 | BT69: =+BT57/BT60 -> 0.50460006 | BU69: =+BU57/BU60 -> 0.42282849 | BV69: =+BV57/BV60 -> 0.37701486 | BW69: =+BW57/BW60 -> 1.6214784 | BX69: =+BX57/BX60 -> 1.2781364 | BY69: =+BY57/BY60 -> 1.8448033 | BZ69: =+BZ57/BZ60 -> 1.2373555 | CA69: =+CA57/CA60 -> 1.8771457 | ... CG69: =+CG57/CG60 -> 0.79473626
B71: SUMMARY FINANCIALS - KOC STAND-ALONE
B73: Dividends received / paid at the holding level
B74: Energy | D74: 61 | E74: 122 | F74: 71 | G74: 41 | H74: =335+128 -> 463 | I74: =337+183 -> 520 | J74: =1338+187 -> 1525
B75: Automotive | D75: 413 | E75: 399 | F75: 351 | G75: =154+121+113+36 -> 424 | H75: =255+137+113+32 -> 537 | I75: =304+132+94+27 -> 557 | J75: =463+301+113+31 -> 908
B76: Consumer durables | D76: 122 | E76: 144 | F76: 122 | G76: 142 | H76: 106 | I76: 172 | J76: 176
B77: Finance | D77: 0 | E77: 0 | F77: 0 | G77: 0 | H77: 0 | I77: 0 | J77: 0
B78: Other | D78: 72 | E78: 228 | F78: 197 | G78: =182+119 -> 301 | H78: 121 | I78: 43 | J78: 83
B79: Total dividends | D79: =SUM(D74:D78) -> 668 | E79: =SUM(E74:E78) -> 893 | F79: =SUM(F74:F78) -> 741 | G79: =SUM(G74:G78) -> 908 | H79: =SUM(H74:H78) -> 1227 | I79: =SUM(I74:I78) -> 1292 | J79: =SUM(J74:J78) -> 2692 | K79: 2548 | L79: 1158 | M79: 3497 | N79: 6038 | O79: 6038 | P79: 24239 | Q79: 24239 | R79: 38500 | S79: 38500 | T79: 38500 | V79: =SUM(V74:V78) -> 0 | W79: =SUM(W74:W78) -> 0
B80: Dividends paid | D80: -373 | E80: -546 | F80: -490 | G80: -585 | H80: -738 | I80: -826 | J80: -876 | K80: -1009.2874 | L80: -531 | M80: -1483.5004 | N80: -2287.38 | O80: -2287.38 | P80: -4395 | Q80: -4395 | R80: -20300 | S80: -20300 | T80: -20300
B81: Net dividends | D81: =SUM(D79:D80) -> 295 | E81: =SUM(E79:E80) -> 347 | F81: =SUM(F79:F80) -> 251 | G81: =SUM(G79:G80) -> 323 | H81: =SUM(H79:H80) -> 489 | I81: =SUM(I79:I80) -> 466 | J81: =SUM(J79:J80) -> 1816 | K81: =SUM(K79:K80) -> 1538.7126 | ... T81: =SUM(T79:T80) -> 18200 | V81: =SUM(V79:V80) -> 0 | W81: =SUM(W79:W80) -> 0
B83: Holdo total debt | D83: =750*D95 -> 1337.7 | E83: =750*E95 -> 1611.15 | F83: =750*F95 -> 1751.25 | G83: =750*G95 -> 2187.9 | H83: =1500*H95 -> 5285.25 | Y83: =1500*Y95 -> 5454.45 | Z83: =1500*Z95 -> 5281.05 | BT83: =G83 -> 2187.9 | BU83: =1500*BU95 -> 4316.55 | BV83: =H83-BU83 -> 968.7
B84: Holdo cash | E84: =+E83-E85 -> 3306.15 | F84: =+F83-F85 -> 3395.25 | G84: =1490*G95 -> 4346.628 | H84: =2000*H95 -> 7047 | Y84: =2000*Y95 -> 7272.6 | Z84: =2100*Z95 -> 7393.47 | BT84: =G84 -> 4346.628 | BU84: =2100*BU95 -> 6043.17 | BV84: =H84-BU84 -> 1003.83
B85: Holdco net debt | E85: -1695 | F85: -1644 | G85: =G83-G84 -> -2158.728 | H85: =H83-H84 -> -1761.75 | Y85: =Y83-Y84 -> -1818.15 | Z85: =Z83-Z84 -> -2112.42 | BT85: =BT83-BT84 -> -2158.728 | BU85: =BU83-BU84 -> -1726.62 | BV85: =BV83-BV84 -> -35.13
B87: Holdco interest | D87: 60 | E87: 60 | F87: 60 | G87: 60
B88: Holdco interest % | D88: =+D87/D83 -> 0.044853106 | E88: =+E87/E83 -> 0.03724048 | F88: =+F87/F83 -> 0.034261242 | G88: =+G87/G83 -> 0.027423557
B90: Holdco total debt / net dividends | D90: =+D83/D81 -> 4.5345763 | E90: =+E83/E81 -> 4.6430836 | F90: =+F83/F81 -> 6.9770916 | G90: =+G83/G81 -> 6.7736842 | H90: =+H83/H81 -> 10.808282 | V90: =+V83/V81 -> #DIV/0! | W90: =+W83/W81 -> #DIV/0!
B91: Holdco net debt / net dividends | D91: =+D85/D81 -> 0 | E91: =+E85/E81 -> -4.8847262 | F91: =+F85/F81 -> -6.5498008 | G91: =+G85/G81 -> -6.6833684 | H91: =+H85/H81 -> -3.6027607 | V91: =+V85/V81 -> #DIV/0! | W91: =+W85/W81 -> #DIV/0!
B92: Holdco net dividends / holdco interest | D92: =+D81/D87 -> 4.9166667 | E92: =+E81/E87 -> 5.7833333 | F92: =+F81/F87 -> 4.1833333 | G92: =+G81/G87 -> 5.3833333 | V92: =+V81/V87 -> #DIV/0! | W92: =+W81/W87 -> #DIV/0!
B94: FX:
B95: USD/TRY end period | D95: 1.7836 | E95: 2.1482 | F95: 2.335 | G95: 2.9172 | H95: 3.5235 | I95: 3.7982 | J95: 5.2894 | K95: 5.9488 | L95: 7.4392 | M95: 13.2978 | N95: 18.6905 | O95: 18.6905 | P95: 29.4768 | Q95: 29.4768 | R95: 35.335 | S95: 35.335 | T95: =BH95 -> 42.9587 | U95: =BI95 -> 44.4537 | Y95: 3.6363 | Z95: 3.5207 | AA95: 3.5633 | AB95: =I95 -> 3.7982 | AC95: 3.9553 | AD95: 4.5929 | AE95: 6.0559 | AF95: =J95 -> 5.2894 | AG95: 5.5707 | AH95: 5.7937 | AI95: 5.6504 | AJ95: =K95 -> 5.9488 | AK95: 6.6152 | AL95: 6.8529 | AM95: 7.7207 | AN95: =L95 -> 7.4392 | AO95: 8.2519 | AP95: 8.7076 | AQ95: 8.8862 | AR95: =M95 -> 13.2978 | AS95: 14.662 | AT95: =1/0.0601 -> 16.638935 | AU95: 18.5156 | AV95: =N95 -> 18.6905 | AW95: 19.181 | AX95: =1/0.0384 -> 26.041667 | AY95: 27.6155 | AZ95: =P95 -> 29.4768 | BA95: 32.4379 | BB95: 32.6485 | BC95: 34.1605 | BD95: =R95 -> 35.335 | BE95: 38.29 | BF95: 39.8392 | BG95: 41.5852 | BH95: 42.9587 | BI95: 44.4537 | BN95: 32.4379 | BO95: 32.6485 | BP95: =BC95 -> 34.1605 | BQ95: =BD95 -> 35.335 | BR95: =BE95 -> 38.29 | BS95: 2.6816 | BT95: 2.9172 | BU95: 2.8777 | BV95: 3.5235 | BW95: 6.8529 | BX95: =AN95 -> 7.4392 | BY95: 8.7076 | BZ95: =AR95 -> 13.2978 | CA95: =1/0.0601 -> 16.638935 | CB95: =AV95 -> 18.6905 | CC95: =1/0.0384 -> 26.041667 | CD95: =AZ95 -> 29.4768 | CE95: 32.6485 | CF95: =BD95 -> 35.335 | CG95: 39.8392 | CI95: =1/0.0384 -> 26.041667 | CJ95: =BD95 -> 35.335 | CK95: 32.6485
B96: USD/TRY average | D96: 1.8005 | E96: 1.9058 | F96: 2.188 | G96: 2.7253 | H96: 3.025 | I96: 3.6471 | J96: 4.8439 | K96: =AVERAGE(AG96:AJ96) -> 5.67825 | L96: =AVERAGE(AK96:AN96) -> 6.90455 | M96: =AVERAGE(AO96:AR96) -> 8.4775 | N96: =AVERAGE(AS96:AV96) -> 15.652128 | O96: =AVERAGE(AT96:AW96) -> 16.869028 | P96: =AVERAGE(AW96:AZ96) -> 22.756589 | Q96: =AVERAGE(Q95,O95) -> 24.08365 | R96: 32.8271 | S96: 32.8271 | T96: =AVERAGE(BE96:BH96) -> 39.73205 | U96: =AVERAGE(BF96:BI96) -> 41.454 | Y96: 3.6969 | Z96: 3.5771 | AA96: 3.513 | AB96: 3.8022 | AC96: 3.8176 | AD96: 4.374 | AE96: 5.6586 | AF96: 5.4996 | AG96: 5.3659 | AH96: 5.8726 | AI96: 5.6749 | AJ96: =AVERAGE(AI95:AJ95) -> 5.7996 | AK96: 6.1091 | AL96: 6.8614 | AM96: =AVERAGE(AJ95:AM95) -> 6.7844 | AN96: 7.8633 | AO96: 7.4057 | AP96: 8.3972 | AQ96: =AVERAGE(AN95:AQ95) -> 8.321225 | AR96: =AVERAGE(AO95:AR95) -> 9.785875 | AS96: =AVERAGE(AR95:AS95) -> 13.9799 | AT96: =1/0.0636 -> 15.72327 | AU96: =AVERAGE(AR95:AU95) -> 15.778584 | AV96: =AVERAGE(AS95:AV95) -> 17.126759 | AW96: 18.8475 | AX96: =1/0.0482 -> 20.746888 | AY96: =AVERAGE(AV95:AY95) -> 22.882167 | AZ96: 28.5498 | BA96: 26.8097 | BB96: 32.3486 | BC96: =AVERAGE(AZ95:BC95) -> 32.180925 | BD96: =AVERAGE(BC95:BD95) -> 34.74775 | BE96: =AVERAGE(BD95:BE95) -> 36.8125 | BF96: =AVERAGE(BE95:BF95) -> 39.0646 | BG96: 40.7857 | BH96: 42.2654 | BI96: 43.7003 | BN96: 26.8097 | BO96: 32.3486 | BP96: =BC96 -> 32.180925 | BQ96: =S96 -> 32.8271 | BR96: =BE96 -> 36.8125 | BS96: 2.5654 | BT96: 2.8816 | BU96: 2.9195 | BV96: 3.1288 | BW96: 6.4843 | BX96: 7.5462 | BY96: 7.9092 | BZ96: =AVERAGE(BY95:BZ95) -> 11.0027 | CA96: =1/0.0677 -> 14.771049 | CB96: =AVERAGE(CA95:CB95) -> 17.664718 | CC96: =1/0.0506 -> 19.762846 | CD96: =AVERAGE(AY96:AZ96) -> 25.715983 | CE96: 31.6252 | CF96: =AVERAGE(BC96:BD96) -> 33.464337 | CG96: =AVERAGE(CF95:CG95) -> 37.5871 | CI96: =1/0.0506 -> 19.762846 | CJ96: =AVERAGE(BC96:BD96) -> 33.464337 | CK96: 31.6252
B97: Q/Q change | AD97: =AD96/AC96-1 -> 0.14574602 | AE97: =AE96/AD96-1 -> 0.29368999 | AF97: =AF96/AE96-1 -> -0.028098823 | AG97: =AG96/AF96-1 -> -0.024310859 | AH97: =AH96/AG96-1 -> 0.094429639 | AI97: =AI96/AH96-1 -> -0.033664816 | AJ97: =AJ96/AI96-1 -> 0.021973955 | AK97: =AK96/AJ96-1 -> 0.053365749 | ... BI97: =BI96/BH96-1 -> 0.033949756 | BN97: =BN96/AZ96-1 -> -0.060949639 | BO97: =BO96/BN96-1 -> 0.2066006 | BP97: =BP96/BO96-1 -> -0.0051833773 | BQ97: =BQ96/BP96-1 -> 0.020079441 | BR97: =BR96/BD96-1 -> 0.059421114
B98: Y/Y change | E98: =+E96/D96-1 -> 0.058483755 | F98: =+F96/E96-1 -> 0.1480743 | G98: =+G96/F96-1 -> 0.24556673 | H98: =+H96/G96-1 -> 0.10996954 | I98: =+I96/H96-1 -> 0.20565289 | J98: =+J96/I96-1 -> 0.32815113 | K98: =+K96/J96-1 -> 0.17224757 | L98: =+L96/K96-1 -> 0.21596443 | ... O98: =+O96/N96-1 -> 0.077746616 | P98: =+P96/N96-1 -> 0.45389741 | Q98: =+Q96/O96-1 -> 0.42768449 | R98: =+R96/O96-1 -> 0.94599828 | S98: =+S96/Q96-1 -> 0.36304505 | T98: =+T96/S96-1 -> 0.21034298 | AC98: =+AC96/Y96-1 -> 0.032648976 | AD98: =+AD96/Z96-1 -> 0.22277823 | AE98: =+AE96/AA96-1 -> 0.61076003 | AF98: =+AF96/AB96-1 -> 0.44642575 | AG98: =+AG96/AC96-1 -> 0.40556894 | AH98: =+AH96/AD96-1 -> 0.34261545 | AI98: =+AI96/AE96-1 -> 0.0028805712 | AJ98: =+AJ96/AF96-1 -> 0.054549422 | ... BI98: =+BI96/BE96-1 -> 0.18710492 | BN98: =+BN96/AW96-1 -> 0.42245391 | BO98: =+BO96/BE96-1 -> -0.12126044 | BP98: =+BP96/BF96-1 -> -0.17621261 | BQ98: =+BQ96/BG96-1 -> -0.19513212 | BR98: =+BR96/BA96-1 -> 0.37310376 | BU98: =+BU96/BS96-1 -> 0.13802916 | BV98: =+BV96/BT96-1 -> 0.085785675
B101: SUMMARY in USD
B103: =+B2 -> KOC HOLDING | D103: =+D2 -> Annual | E103: =+E2 -> Annual | F103: =+F2 -> Annual | G103: =+G2 -> Annual | H103: =+H2 -> Annual | I103: =+I2 -> Annual | J103: =+J2 -> Annual | K103: =+K2 -> Annual | ... W103: =+W2 -> Annual | Y103: =+Y2 -> Quarters | Z103: =+Z2 -> Quarters | AA103: =+AA2 -> Quarters | AB103: =+AB2 -> Quarters | AC103: =+AC2 -> Quarters | AD103: =+AD2 -> Quarters | AE103: =+AE2 -> Quarters | AF103: =+AF2 -> Quarters | ... BI103: =+BI2 -> Quarters | BN103: =+BN2 -> Quarters | BO103: =+BO2 -> Quarters | BP103: =+BP2 -> Quarters | BQ103: =+BQ2 -> Quarters | BR103: =+BR2 -> Quarters | BS103: =+BS2 -> H1 | BT103: =+BT2 -> H2 | BU103: =+BU2 -> H1 | ... CG103: =+CG2 -> H1 | CI103: =+CI2 -> H1 | CJ103: =+CJ2 -> H2 | CK103: =+CK2 -> H1
B104: in USD mn | D104: =+D3 -> 41274 | E104: =+E3 -> 41639 | F104: =+F3 -> 42004 | G104: =+G3 -> 42369 | H104: =+H3 -> 42734 | I104: =+I3 -> 43099 | J104: =+J3 -> 43464 | K104: =+K3 -> 43829 | ... W104: =+W3 -> 43100 | Y104: =+Y3 -> 42825 | Z104: =+Z3 -> 42916 | AA104: =+AA3 -> 43008 | AB104: =+AB3 -> 43099 | AC104: =+AC3 -> 43189 | AD104: =+AD3 -> 43281 | AE104: =+AE3 -> 43373 | AF104: =+AF3 -> 43464 | ... BI104: =+BI3 -> 46111 | BN104: =+BN3 -> 45381 | BO104: =+BO3 -> 45473 | BP104: =+BP3 -> 45565 | BQ104: =+BQ3 -> 45656 | BR104: =+BR3 -> 45746 | BS104: =+BS3 -> 42156 | BT104: =+BT3 -> 42369 | BU104: =+BU3 -> 42522 | ... CG104: =+CG3 -> 45809 | CI104: =+CI3 -> 45078 | CJ104: =+CJ3 -> 45291 | CK104: =+CK3 -> 45444
D105: =+D4 -> Act | E105: =+E4 -> Act | F105: =+F4 -> Act | G105: =+G4 -> Act | H105: =+H4 -> Act | I105: =+I4 -> Act | J105: =+J4 -> Act | K105: =+K4 -> Act | ... W105: =+W4 -> Proj | Y105: =+Y4 -> Act | Z105: =+Z4 -> Act | AA105: =+AA4 -> Act | AB105: =+AB4 -> Act | AC105: =+AC4 -> Act | AD105: =+AD4 -> Act | AE105: =+AE4 -> Act | AF105: =+AF4 -> Act | ... BI105: =+BI4 -> Act | BN105: =+BN4 -> Act | BO105: =+BO4 -> Act | BP105: =+BP4 -> Act | BQ105: =+BQ4 -> Act | BR105: =+BR4 -> Act | BS105: =+BS4 -> Act | BT105: =+BT4 -> Act | BU105: =+BU4 -> Act | ... CG105: =+CG4 -> Act | CI105: =+CI4 -> Restated | CJ105: =+CJ4 -> Restated | CK105: =+CK4 -> Restated
B107: =+B31 -> Consolidated revenues | D107: =+D31/D$96 -> 36470.98 | E107: =+E31/E$96 -> 34726.624 | F107: =+F31/F$96 -> 31362.888 | G107: =+G31/G$96 -> 25498.477 | H107: =+H31/H$96 -> 23283.386 | I107: =+I31/I$96 -> 27108.319 | J107: =+J31/J$96 -> 29572.928 | K107: =+K31/K$96 -> 27035.796 | ... U107: =+U31/U$96 -> 71332.513 | Y107: =+Y31/Y$96 -> 6025.078 | Z107: =+Z31/Z$96 -> 6446.3633 | AA107: =+AA31/AA$96 -> 7365.4828 | AB107: =+AB31/AB$96 -> 7274.3178 | AC107: =+AC31/AC$96 -> 6440.6792 | AD107: =+AD31/AD$96 -> 7606.8519 | AE107: =+AE31/AE$96 -> 8050.2907 | AF107: =+AF31/AF$96 -> 7243.186 | ... BI107: =+BI31/BI$96 -> 16888.74 | BN107: =+BN31/BN$96 -> 23202.087 | BO107: =+BO31/BO$96 -> 21769.597 | BP107: =+BP31/BP$96 -> 23225.498 | BQ107: =+BQ31/BQ$96 -> 29252.66 | BR107: =+BR31/BR$96 -> 19136.788 | BS107: =+BS31/BS$96 -> 12523.583 | BT107: =+BT31/BT$96 -> 12966.061 | BU107: =+BU31/BU$96 -> 10660.045 | ... CG107: =+CG31/CG$96 -> 31324.923 | CI107: =+CI31/CI$96 -> 44847.488 | CJ107: =+CJ31/CJ$96 -> 42745.774 | CK107: =+CK31/CK$96 -> 43118.241
B108: =+B32 -> % growth | E108: =+E107/D107-1 -> -0.04782861 | F108: =+F107/E107-1 -> -0.096863303 | G108: =+G107/F107-1 -> -0.18698569 | H108: =+H107/G107-1 -> -0.086871506 | I108: =+I107/H107-1 -> 0.16427733 | J108: =+J107/I107-1 -> 0.090917102 | K108: =+K107/J107-1 -> -0.085792407 | L108: =+L107/K107-1 -> -0.015496476 | ... N108: =+N107/M107-1 -> 0.40893965 | O108: =+O107/M107-1 -> 1.4873715 | P108: =+P107/O107-1 -> -0.30679799 | Q108: =+Q107/O107-1 -> -0.054310347 | R108: =+R107/P107-1 -> 0.0013620765 | S108: =+S107/Q107-1 -> -0.039238834 | T108: =+T107/S107-1 -> -0.24912846 | AC108: =+AC107/Y107-1 -> 0.068978556 | AD108: =+AD107/Z107-1 -> 0.18002222 | AE108: =+AE107/AA107-1 -> 0.092975294 | AF108: =+AF107/AB107-1 -> -0.0042796747 | AG108: =+AG107/AC107-1 -> -0.0086324737 | AH108: =+AH107/AD107-1 -> -0.093664697 | AI108: =+AI107/AE107-1 -> -0.13834177 | AJ108: =+AJ107/AF107-1 -> -0.062026727 | ... BD108: =+BD107/AZ107-1 -> -0.22644177 | BE108: =+BE107/BN107-1 -> -0.36974232 | BF108: =+BF107/BB107-1 -> -0.036457185 | BG108: =+BG107/BC107-1 -> -0.030683837 | BH108: =+BH107/BD107-1 -> -0.033340829 | BI108: =+BI107/BR107-1 -> -0.11747258 | BN108: =+BN107/AW107-1 -> 0.13092152 | BO108: =+BO107/AX107-1 -> -0.03314795 | BP108: =+BP107/AY107-1 -> -0.15488905 | BQ108: =+BQ107/AZ107-1 -> 0.0012583463 | BR108: =+BR107/BA107-1 -> 0.13906406 | BU108: =+BU107/BS107-1 -> -0.14880235 | BV108: =+BV107/BT107-1 -> -0.031008693 | BY108: =+BY107/BW107-1 -> 0.46263259 | CA108: =+CA107/BY107-1 -> 0.56577827 | CC108: =+CC107/CA107-1 -> -0.0503242 | CD108: =+CD107/CB107-1 -> 0.48351279 | CE108: =+CE107/CC107-1 -> 0.28693214 | CF108: =+CF107/CJ107-1 -> -0.085480954 | CG108: =+CG107/CE107-1 -> -0.018884405 | CI108: =+CI107/CE107-1 -> 0.40465056 | CJ108: =+CJ107/CB107-1 -> 0.4634165 | CK108: =+CK107/CI107-1 -> -0.038558397
B109: =+B33 -> Consolidated operating profit | D109: =+D33/D$96 -> 2116.6343 | E109: =+E33/E$96 -> 1955.6092 | F109: =+F33/F$96 -> 1521.4808 | G109: =+G33/G$96 -> 2450.0055 | H109: =+H33/H$96 -> 2297.1048 | I109: =+I33/I$96 -> 2858.8824 | J109: =+J33/J$96 -> 2676.2384 | K109: =+K33/K$96 -> 1826.9139 | ... U109: =+U33/U$96 -> 3149.4186 | Y109: =+Y33/Y$96 -> 704.5338 | Z109: =+Z33/Z$96 -> 758.0884 | AA109: =+AA33/AA$96 -> 809.05892 | AB109: =+AB33/AB$96 -> 596.51176 | AC109: =+AC33/AC$96 -> 558.5724 | AD109: =+AD33/AD$96 -> 654.20119 | AE109: =+AE33/AE$96 -> 607.7604 | AF109: =+AF33/AF$96 -> 823.78282 | ... BI109: =+BI33/BI$96 -> 696.40254 | BN109: =+BN33/BN$96 -> 1368.8329 | BO109: =+BO33/BO$96 -> 1548.7224 | BP109: =+BP33/BP$96 -> 504.80215 | BQ109: =+BQ33/BQ$96 -> 344.65426 | BR109: =+BR33/BR$96 -> 621.60951 | BS109: =+BS33/BS$96 -> 970.60887 | BT109: =+BT33/BT$96 -> 1453.0122 | BU109: =+BU33/BU$96 -> 943.65474 | ... CG109: =+CG33/CG$96 -> 1243.1393 | CI109: =+CI33/CI$96 -> 5908.4102 | CJ109: =+CJ33/CJ$96 -> 6116.9596 | CK109: =+CK33/CK$96 -> 2775.2868
B110: =+B34 -> % margin | E110: =+E109/E107 -> 0.056314406 | F110: =+F109/F107 -> 0.048512139 | G110: =+G109/G107 -> 0.096084385 | H110: =+H109/H107 -> 0.098658536 | I110: =+I109/I107 -> 0.10546144 | J110: =+J109/J107 -> 0.090496224 | K110: =+K109/K107 -> 0.067573891 | L110: =+L109/L107 -> 0.091588674 | ... U110: =+U109/U107 -> 0.044151236 | Y110: =+Y109/Y107 -> 0.11693356 | Z110: =+Z109/Z107 -> 0.11759939 | AA110: =+AA109/AA107 -> 0.10984466 | AB110: =+AB109/AB107 -> 0.082002433 | AC110: =+AC109/AC107 -> 0.086725698 | AD110: =+AD109/AD107 -> 0.086001568 | AE110: =+AE109/AE107 -> 0.07549546 | AF110: =+AF109/AF107 -> 0.11373211 | ... BI110: =+BI109/BI107 -> 0.041234725 | BN110: =+BN109/BN107 -> 0.058996111 | BO110: =+BO109/BO107 -> 0.071141525 | BP110: =+BP109/BP107 -> 0.021734826 | BQ110: =+BQ109/BQ107 -> 0.01178198 | BR110: =+BR109/BR107 -> 0.032482437 | BS110: =+BS109/BS107 -> 0.07750249 | BT110: =+BT109/BT107 -> 0.11206274 | BU110: =+BU109/BU107 -> 0.088522589 | ... CG110: =+CG109/CG107 -> 0.03968531 | CI110: =+CI109/CI107 -> 0.13174451 | CJ110: =+CJ109/CJ107 -> 0.14310092 | CK110: =+CK109/CK107 -> 0.064364564
B111: =+B35 -> Depreciation and amortisation | H111: =+H35/H$96 -> 472.16893 | I111: =+I35/I$96 -> 433.08108 | J111: =+J35/J$96 -> 436.27986 | K111: =+K35/K$96 -> 486.99071 | L111: =+L35/L$96 -> 588.5335 | M111: =+M35/M$96 -> 623.47543 | N111: =+N35/N$96 -> 527.72376 | O111: =+O35/O$96 -> 1509.097 | ... U111: =+U35/U$96 -> 1912.4331 | Y111: =+Y35/Y$96 -> 102.50047 | Z111: =+Z35/Z$96 -> 109.26169 | AA111: =+AA35/AA$96 -> 112.26302 | AB111: =+AB35/AB$96 -> 109.23571 | AC111: =+AC35/AC$96 -> 116.94022 | AD111: =+AD35/AD$96 -> 117.96045 | AE111: =+AE35/AE$96 -> 102.21009 | AF111: =+AF35/AF$96 -> 104.10575 | ... BI111: =+BI35/BI$96 -> 459.47053 | BN111: =+BN35/BN$96 -> 442.3026 | BO111: =+BO35/BO$96 -> 538.32314 | BP111: =+BP35/BP$96 -> 539.76074 | BQ111: =+BQ35/BQ$96 -> 902.48606 | BR111: =+BR35/BR$96 -> 540.08829 | BS111: =+BS35/BS$96 -> 221.56428 | BT111: =+BT35/BT$96 -> 0 | BU111: =+BU35/BU$96 -> 238.85837 | ... CG111: =+CG35/CG$96 -> 871.84167 | CI111: =+CI35/CI$96 -> 1364.3278 | CJ111: =+CJ35/CJ$96 -> 514.996 | CK111: =+CK35/CK$96 -> 948.1363
B112: =+B36 -> Other adjustments | H112: =+H36/H$96 -> -720.28496 | I112: =+I36/I$96 -> -811.74742 | J112: =+J36/J$96 -> -317.29701 | K112: =+K36/K$96 -> -430.16387 | L112: =+L36/L$96 -> 651.39944 | M112: =+M36/M$96 -> 1442.4544 | N112: =+N36/N$96 -> 550.78772 | O112: =+O36/O$96 -> 1595.1126 | ... U112: =+U36/U$96 -> 597.96401 | Y112: =+Y36/Y$96 -> -178.84092 | Z112: =+Z36/Z$96 -> -242.28565 | AA112: =+AA36/AA$96 -> -219.80757 | AB112: =+AB36/AB$96 -> -173.71601 | AC112: =+AC36/AC$96 -> -220.45605 | AD112: =+AD36/AD$96 -> -55.48331 | AE112: =+AE36/AE$96 -> 234.20546 | AF112: =+AF36/AF$96 -> -323.28406 | ... BI112: =+BI36/BI$96 -> 245.85644 | BN112: =+BN36/BN$96 -> 94.965628 | BO112: =+BO36/BO$96 -> 850.73233 | BP112: =+BP36/BP$96 -> 57.363174 | BQ112: =+BQ36/BQ$96 -> -1340.356 | BR112: =+BR36/BR$96 -> 224.59762 | BS112: =+BS36/BS$96 -> -247.1291 | BT112: =+BT36/BT$96 -> 0 | BU112: =+BU36/BU$96 -> -411.30913 | ... CG112: =+CG36/CG$96 -> -279.29795 | CI112: =+CI36/CI$96 -> 388.4056 | CJ112: =+CJ36/CJ$96 -> -404.10183 | CK112: =+CK36/CK$96 -> 784.84879
B113: =+B37 -> Consolidated EBITDA | D113: =+D37/D$96 -> 2449.3196 | E113: =+E37/E$96 -> 2603.631 | F113: =+F37/F$96 -> 1983.0896 | G113: =+G37/G$96 -> 3022.0526 | H113: =+H37/H$96 -> 2048.9888 | I113: =+I37/I$96 -> 2480.2161 | J113: =+J37/J$96 -> 2795.2212 | K113: =+K37/K$96 -> 1883.7408 | ... U113: =+U37/U$96 -> 5659.8157 | Y113: =+Y37/Y$96 -> 628.19335 | Z113: =+Z37/Z$96 -> 625.06444 | AA113: =+AA37/AA$96 -> 701.51438 | AB113: =+AB37/AB$96 -> 532.03146 | AC113: =+AC37/AC$96 -> 455.05658 | AD113: =+AD37/AD$96 -> 716.67833 | AE113: =+AE37/AE$96 -> 944.17594 | AF113: =+AF37/AF$96 -> 604.60452 | ... BI113: =+BI37/BI$96 -> 1401.7295 | BN113: =+BN37/BN$96 -> 1906.1011 | BO113: =+BO37/BO$96 -> 2937.7778 | BP113: =+BP37/BP$96 -> 1101.9261 | BQ113: =+BQ37/BQ$96 -> -93.215666 | BR113: =+BR37/BR$96 -> 1386.2954 | BS113: =+BS37/BS$96 -> 945.04405 | BT113: =+BT37/BT$96 -> 1453.0122 | BU113: =+BU37/BU$96 -> 771.20397 | ... CG113: =+CG37/CG$96 -> 1835.683 | CI113: =+CI37/CI$96 -> 7661.1436 | CJ113: =+CJ37/CJ$96 -> 6227.8538 | CK113: =+CK37/CK$96 -> 4508.2719
B114: =+B38 -> % growth | E114: =+E113/D113-1 -> 0.063001735 | F114: =+F113/E113-1 -> -0.23833694 | G114: =+G113/F113-1 -> 0.5239113 | H114: =+H113/G113-1 -> -0.32198773 | I114: =+I113/H113-1 -> 0.2104586 | J114: =+J113/I113-1 -> 0.12700714 | K114: =+K113/J113-1 -> -0.32608526 | L114: =+L113/K113-1 -> 0.95235657 | ... N114: =+N113/M113-1 -> 0.72511393 | O114: =+O113/M113-1 -> 1.8224851 | P114: =+P113/O113-1 -> -0.36972736 | Q114: =+Q113/O113-1 -> -0.14016064 | R114: =+R113/P113-1 -> -0.62059053 | S114: =+S113/Q113-1 -> -0.63597274 | T114: =+T113/S113-1 -> -0.017251134 | AC114: =+AC113/Y113-1 -> -0.27561064 | AD114: =+AD113/Z113-1 -> 0.14656711 | AE114: =+AE113/AA113-1 -> 0.34591104 | AF114: =+AF113/AB113-1 -> 0.13640746 | AG114: =+AG113/AC113-1 -> -0.18339966 | AH114: =+AH113/AD113-1 -> -0.23517804 | AI114: =+AI113/AE113-1 -> -0.45651989 | AJ114: =+AJ113/AF113-1 -> -0.26666672 | ... BD114: =+BD113/AZ113-1 -> -0.77019439 | BE114: =+BE113/BN113-1 -> -0.44425085 | BF114: =+BF113/BB113-1 -> 0.15869708 | BG114: =+BG113/BC113-1 -> 0.39343343 | BH114: =+BH113/BD113-1 -> 0.99424919 | BI114: =+BI113/BR113-1 -> 0.011133335 | BN114: =+BN113/AW113-1 -> -0.42530648 | BO114: =+BO113/AX113-1 -> -0.27583024 | BP114: =+BP113/AY113-1 -> -0.77590338 | BQ114: =+BQ113/AZ113-1 -> -1.0264479 | BR114: =+BR113/BA113-1 -> -0.10492584 | BU114: =+BU113/BS113-1 -> -0.18394918 | BV114: =+BV113/BT113-1 -> -0.13187402 | BY114: =+BY113/BW113-1 -> 0.55389187 | CA114: =+CA113/BY113-1 -> 0.90026746 | CC114: =+CC113/CA113-1 -> -0.0029998115 | CD114: =+CD113/CB113-1 -> 0.098650195 | CE114: =+CE113/CC113-1 -> -0.40391547 | CF114: =+CF113/CJ113-1 -> -0.72835407 | CG114: =+CG113/CE113-1 -> -0.27237148 | CI114: =+CI113/CE113-1 -> 2.0367262 | CJ114: =+CJ113/CB113-1 -> 0.062695491 | CK114: =+CK113/CI113-1 -> -0.41154061
B115: =+B39 -> % margin | E115: =+E113/E107 -> 0.074975069 | F115: =+F113/F107 -> 0.063230451 | G115: =+G113/G107 -> 0.11851894 | H115: =+H113/H107 -> 0.088002181 | I115: =+I113/I107 -> 0.091492803 | J115: =+J113/J107 -> 0.094519595 | K115: =+K113/K107 -> 0.069675803 | L115: =+L113/L107 -> 0.13817321 | ... U115: =+U113/U107 -> 0.079344123 | Y115: =+Y113/Y107 -> 0.10426311 | Z115: =+Z113/Z107 -> 0.096963887 | AA115: =+AA113/AA107 -> 0.095243502 | AB115: =+AB113/AB107 -> 0.07313833 | AC115: =+AC113/AC107 -> 0.070653508 | AD115: =+AD113/AD107 -> 0.09421484 | AE115: =+AE113/AE107 -> 0.1172847 | AF115: =+AF113/AF107 -> 0.083472178 | ... BI115: =+BI113/BI107 -> 0.082997874 | BN115: =+BN113/BN107 -> 0.082152141 | BO115: =+BO113/BO107 -> 0.13494865 | BP115: =+BP113/BP107 -> 0.04744467 | BQ115: =+BQ113/BQ107 -> -0.0031865706 | BR115: =+BR113/BR107 -> 0.072441385 | BS115: =+BS113/BS107 -> 0.075461155 | BT115: =+BT113/BT107 -> 0.11206274 | BU115: =+BU113/BU107 -> 0.072345286 | ... CG115: =+CG113/CG107 -> 0.058601357 | CI115: =+CI113/CI107 -> 0.17082659 | CJ115: =+CJ113/CJ107 -> 0.14569519 | CK115: =+CK113/CK107 -> 0.10455602
B116: =+B40 -> Consolidated net profit attributable to Equity holders | D116: =+D40/D$96 -> 1290.7526 | E116: =+E40/E$96 -> 1406.2336 | F116: =+F40/F$96 -> 1238.574 | G116: =+G40/G$96 -> 1308.8467 | H116: =+H40/H$96 -> 1143.7993 | I116: =+I40/I$96 -> 1345.9296 | J116: =+J40/J$96 -> 1143.093 | K116: =+K40/K$96 -> 773.32964 | ... U116: =+U40/U$96 -> 577.45935 | Y116: =+Y40/Y$96 -> 304.17918 | Z116: =+Z40/Z$96 -> 396.14716 | AA116: =+AA40/AA$96 -> 367.19442 | AB116: =+AB40/AB$96 -> 283.31177 | AC116: =+AC40/AC$96 -> 298.92734 | AD116: =+AD40/AD$96 -> 324.28761 | AE116: =+AE40/AE$96 -> 223.91033 | AF116: =+AF40/AF$96 -> 311.00262 | ... BI116: =+BI40/BI$96 -> 11.944998 | BN116: =+BN40/BN$96 -> 102.08992 | BO116: =+BO40/BO$96 -> 304.7118 | BP116: =+BP40/BP$96 -> -137.13092 | BQ116: =+BQ40/BQ$96 -> -197.15418 | BR116: =+BR40/BR$96 -> -50.308998 | BS116: =+BS40/BS$96 -> 516.87846 | BT116: =+BT40/BT$96 -> 777.69295 | BU116: =+BU40/BU$96 -> 490.83747 | ... CG116: =+CG40/CG$96 -> 165.88138 | CI116: =+CI40/CI$96 -> 1829.949 | CJ116: =+CJ40/CJ$96 -> 2151.8729 | CK116: =+CK40/CK$96 -> 403.41247
B117: =+B41 -> % margin | E117: =+E116/E107 -> 0.040494394 | F117: =+F116/F107 -> 0.039491708 | G117: =+G116/G107 -> 0.051330388 | H117: =+H116/H107 -> 0.049125129 | I117: =+I116/I107 -> 0.04965006 | J117: =+J116/J107 -> 0.038653357 | K117: =+K116/K107 -> 0.028603916 | L117: =+L116/L107 -> 0.050455476 | ... U117: =+U116/U107 -> 0.0080953176 | Y117: =+Y116/Y107 -> 0.050485517 | Z117: =+Z116/Z107 -> 0.061452813 | AA117: =+AA116/AA107 -> 0.049853408 | AB117: =+AB116/AB107 -> 0.038946851 | AC117: =+AC116/AC107 -> 0.046412393 | AD117: =+AD116/AD107 -> 0.042630988 | AE117: =+AE116/AE107 -> 0.027813944 | AF117: =+AF116/AF107 -> 0.042937268 | ... BI117: =+BI116/BI107 -> 0.00070727586 | BN117: =+BN116/BN107 -> 0.0044000315 | BO117: =+BO116/BO107 -> 0.013997126 | BP117: =+BP116/BP107 -> -0.0059043266 | BQ117: =+BQ116/BQ107 -> -0.0067397009 | BR117: =+BR116/BR107 -> -0.0026289155 | BS117: =+BS116/BS107 -> 0.04127241 | BT117: =+BT116/BT107 -> 0.059979124 | BU117: =+BU116/BU107 -> 0.046044599 | ... CG117: =+CG116/CG107 -> 0.005295508 | CI117: =+CI116/CI107 -> 0.040803823 | CJ117: =+CJ116/CJ107 -> 0.050341184 | CK117: =+CK116/CK107 -> 0.0093559584
B119: =+B43 -> LTM revenues | D119: =+D43/D$96 -> 36470.98 | E119: =+E43/E$96 -> 34726.624 | F119: =+F43/F$96 -> 31362.888 | G119: =+G43/G$96 -> 25498.477 | H119: =+H43/H$96 -> 23283.386 | I119: =+I43/I$96 -> 27108.319 | J119: =+J43/J$96 -> 29572.928 | K119: =+K43/K$96 -> 27035.796 | ... U119: =+U43/U$96 -> 71332.513 | AB119: =AB107+AA107+Z107+Y107 -> 27111.242 | AC119: =AC107+AB107+AA107+Z107 -> 27526.843 | AD119: =AD107+AC107+AB107+AA107 -> 28687.332 | AE119: =AE107+AD107+AC107+AB107 -> 29372.14 | AF119: =AF107+AE107+AD107+AC107 -> 29341.008 | AG119: =AG107+AF107+AE107+AD107 -> 29285.409 | AH119: =AH107+AG107+AF107+AE107 -> 28572.915 | AI119: =AI107+AH107+AG107+AF107 -> 27459.224 | ... BC119: =BC107+BB107+BA107+AZ107 -> 79560.537 | BD119: =BD107+BC107+BB107+BN107 -> 79346.476 | BE119: =BE107+BD107+BC107+BB107 -> 70767.682 | BF119: =BF107+BE107+BD107+BC107 -> 70180 | BG119: =BG107+BF107+BE107+BD107 -> 69645.353 | BH119: =BH107+BG107+BF107+BT107 -> 67234.61 | BI119: =BI107+BH107+BG107+BF107 -> 71157.29 | BN119: =BN107+AZ107+AY107+AX107 -> 102416.13 | BO119: =BO107+BN107+AZ107+AY107 -> 101669.77 | BP119: =BP107+BO107+BN107+AZ107 -> 97413.079 | BQ119: =BQ107+BP107+BO107+BN107 -> 97449.843 | BR119: =BR107+BD107+BC107+BB107 -> 75281.176 | BT119: =BT107+BS107 -> 25489.644 | BU119: =BU107+BT107 -> 23626.105 | BV119: =BV107+BU107 -> 23224.044 | BW119: =BW107+BV107 -> 23971.049 | BX119: =BX107+BW107 -> 25958.817 | BY119: =BY107+BX107 -> 31236.089 | BZ119: =BZ107+BY107 -> 36200.355 | CA119: =CA107+BZ107 -> 45639.982 | ... CC119: =CC107+CB107 -> 54018.856 | CD119: =CD107+CI107 -> 88180.267 | CE119: =CE107+CJ107 -> 74673.635 | CF119: =CF107+CE107 -> 71019.686 | CG119: =CG107+CM107 -> 31324.923 | CI119: =CI107+CB107 -> 74057.063 | CJ119: =CJ107+CI107 -> 87593.262 | CK119: =CK107+CJ107 -> 85864.015
B120: =+B44 -> LTM EBITDA | D120: =+D44/D$96 -> 2449.3196 | E120: =+E44/E$96 -> 2603.631 | F120: =+F44/F$96 -> 1983.0896 | G120: =+G44/G$96 -> 3022.0526 | H120: =+H44/H$96 -> 2048.9888 | I120: =+I44/I$96 -> 2480.2161 | J120: =+J44/J$96 -> 2795.2212 | K120: =+K44/K$96 -> 1883.7408 | ... U120: =+U44/U$96 -> 5659.8157 | AB120: =AB113+AA113+Z113+Y113 -> 2486.8036 | AC120: =AC113+AB113+AA113+Z113 -> 2313.6668 | AD120: =AD113+AC113+AB113+AA113 -> 2405.2807 | AE120: =AE113+AD113+AC113+AB113 -> 2647.9423 | AF120: =AF113+AE113+AD113+AC113 -> 2720.5154 | AG120: =AG113+AF113+AE113+AD113 -> 2637.0581 | AH120: =AH113+AG113+AF113+AE113 -> 2468.5111 | AI120: =AI113+AH113+AG113+AF113 -> 2037.476 | ... BC120: =BC113+BB113+BA113+AZ113 -> 7141.3632 | BD120: =BD113+BC113+BB113+BN113 -> 4784.1029 | BE120: =BE113+BD113+BC113+BB113 -> 3937.3159 | BF120: =BF113+BE113+BD113+BC113 -> 4107.9018 | BG120: =BG113+BF113+BE113+BD113 -> 4498.6342 | BH120: =BH113+BG113+BF113+BT113 -> 5697.6262 | BI120: =BI113+BH113+BG113+BF113 -> 5646.3435 | BN120: =BN113+AZ113+AY113+AX113 -> 14404.554 | BO120: =BO113+BN113+AZ113+AY113 -> 13285.579 | BP120: =BP113+BO113+BN113+AZ113 -> 9470.3131 | BQ120: =BQ113+BP113+BO113+BN113 -> 5852.5894 | BR120: =BR113+BD113+BC113+BB113 -> 4264.2972 | BT120: =BT113+BS113 -> 2398.0563 | BU120: =BU113+BT113 -> 2224.2162 | BV120: =BV113+BU113 -> 2032.6016 | BW120: =BW113+BV113 -> 2699.035 | BX120: =BX113+BW113 -> 3567.3217 | BY120: =BY113+BX113 -> 4363.6174 | BZ120: =BZ113+BY113 -> 5371.3704 | CA120: =CA113+BZ113 -> 7382.5076 | ... CC120: =CC113+CB113 -> 10092.767 | CD120: =CD113+CI113 -> 14099.707 | CE120: =CE113+CJ113 -> 8750.6837 | CF120: =CF113+CE113 -> 4214.601 | CG120: =CG113+CM113 -> 1835.683 | CI120: =CI113+CB113 -> 13521.575 | CJ120: =CJ113+CI113 -> 13888.997 | CK120: =CK113+CJ113 -> 10736.126
...

Sheet KPI
B2: KOC HOLDING | C2: Annual | D2: Annual | E2: Annual | F2: Annual | G2: Annual | H2: Annual | I2: Annual | J2: Annual | K2: Annual | L2: Annual | M2: Annual | N2: Annual | O2: Annual | P2: Annual | Q2: Annual | R2: Annual | S2: Annual | T2: LTM | V2: Quarters | W2: Quarters | X2: Quarters | Y2: Quarters | Z2: Quarters | AA2: Quarters | AB2: Quarters | AC2: Quarters | AD2: Quarters | AE2: Quarters | AF2: Quarters | AG2: Quarters | AH2: Quarters | AI2: Quarters | AJ2: Quarters | AK2: Quarters | AL2: Quarters | AM2: Quarters | AN2: Quarters | AO2: Quarters | AP2: Quarters | AQ2: Quarters | AR2: Quarters | AS2: Quarters | AT2: Quarters | AU2: Quarters | AV2: Quarters | AW2: Quarters | AX2: Quarters | AY2: Quarters | AZ2: Quarters | BA2: Quarters | BB2: Quarters | BC2: Quarters | BD2: Quarters | BE2: Quarters | BF2: Quarters | BH2: Quarters
B3: TRY mn | C3: 41274 | D3: =C3+365 -> 41639 | E3: =D3+365 -> 42004 | F3: =E3+365 -> 42369 | G3: =F3+365 -> 42734 | H3: =G3+365 -> 43099 | I3: =H3+365 -> 43464 | J3: =I3+365 -> 43829 | K3: =J3+365 -> 44194 | ... M3: =L3+365 -> 44924 | N3: =M3 -> 44924 | O3: =M3+365 -> 45289 | P3: =N3+365 -> 45289 | Q3: =O3+365 -> 45654 | R3: =P3+365 -> 45654 | S3: =Q3+365 -> 46019 | T3: =BF3 -> 46111 | V3: 42825 | W3: =EDATE(V3,3) -> 42916 | X3: =EDATE(W3,3) -> 43008 | Y3: =EDATE(X3,3) -> 43099 | Z3: =EDATE(Y3,3) -> 43189 | AA3: =EDATE(Z3,3) -> 43281 | AB3: =EDATE(AA3,3) -> 43373 | AC3: =EDATE(AB3,3) -> 43464 | AD3: =EDATE(AC3,3) -> 43554 | ... BF3: =EDATE(BE3,3) -> 46111 | BH3: =BB3 -> 45746
C4: Act | D4: Act | E4: Act | F4: Act | G4: Act | H4: Act | I4: Act | J4: Act | K4: Act | L4: Act | M4: Act | N4: Act | O4: Act | P4: Act | Q4: Act | R4: Act | S4: Act | T4: Act | V4: Act | W4: Act | X4: Act | Y4: Act | Z4: Act | AA4: Act | AB4: Act | AC4: Act | AD4: Act | AE4: Act | AF4: Act | AG4: Act | AH4: Act | AI4: Act | AJ4: Act | AK4: Act | AL4: Act | AM4: Act | AN4: Act | AO4: Act | AP4: Act | AQ4: Act | AR4: Act | AS4: Act | AT4: Act | AU4: Act | AV4: Act | AW4: Act | AX4: Act | AY4: Act | AZ4: Act | BA4: Act | BB4: Act | BC4: Act | BD4: Act | BE4: Act | BF4: Act | BH4: Act
C5: FY | D5: FY | E5: FY | F5: FY | G5: FY | H5: FY | I5: FY | J5: FY | K5: FY | L5: FY | M5: FY | N5: FY | O5: FY | P5: FY | Q5: FY | R5: FY | S5: FY | T5: FY | V5: 1Q | W5: 2Q | X5: 3Q | Y5: 4Q | Z5: 1Q | AA5: 2Q | AB5: 3Q | AC5: 4Q | AD5: 1Q | AE5: 2Q | AF5: 3Q | AG5: 4Q | AH5: 1Q | AI5: 2Q | AJ5: 3Q | AK5: 4Q | AL5: 1Q | AM5: 2Q | AN5: 3Q | AO5: 4Q | AP5: 1Q | AQ5: 2Q | AR5: 3Q | AS5: 4Q | AT5: 1Q | AU5: 2Q | AV5: 3Q | AW5: 4Q | AX5: 1Q | AY5: 2Q | AZ5: 3Q | BA5: 4Q | BB5: 1Q | BC5: 2Q | BD5: 3Q | BE5: 4Q | BF5: 1Q | BH5: 1Q
N6: Restated | P6: Restated | R6: Restated | BH6: Restated
B8: Combined revenues by segment:
B9: Energy | C9: 63225 | D9: 65458 | E9: 68343 | F9: 62397 | G9: 67273.473 | H9: 97574.116 | I9: 153250.04 | J9: 153426.36 | K9: 115839.99 | L9: 229549.24 | M9: 713727 | N9: 1353617 | O9: 1051742 | P9: 1518495 | Q9: 1291970 | R9: 1691087 | S9: 1419042 | T9: =SUM(BC9:BF9) -> 1558911 | V9: 21706.751 | W9: =44766.375-V9 -> 23059.624 | X9: =70993.13-W9-V9 -> 26226.755 | Y9: =F9-X9-W9-V9 -> -8596.13 | Z9: 25753.228 | AA9: =61647.231-Z9 -> 35894.003 | AB9: =111704.372-AA9-Z9 -> 50057.141 | AC9: =G9-AB9-AA9-Z9 -> -44430.899 | AD9: 35505.985 | AE9: =75465.13-AD9 -> 39959.145 | AF9: =115889.709-AE9-AD9 -> 40424.579 | AG9: =H9-AF9-AE9-AD9 -> -18315.593 | AH9: 29045.338 | AI9: =48227.598-AH9 -> 19182.26 | AJ9: =81690.069-AI9-AH9 -> 33462.471 | AK9: =I9-AJ9-AI9-AH9 -> 71559.968 | AL9: 33280.593 | AM9: =82076.796-AL9 -> 48796.203 | AN9: =146275.599-AM9-AL9 -> 64198.803 | AO9: =J9-AN9-AM9-AL9 -> 7150.765 | AP9: 113178.05 | AQ9: =310142.923-AP9 -> 196964.87 | AR9: =528048.25-AQ9-AP9 -> 217905.33 | AS9: =K9-AR9-AQ9-AP9 -> -412208.26 | AT9: 253773 | AU9: 282047 | AV9: =1056315-AU9-AT9 -> 520495 | AW9: =N9-AV9-AU9-AT9 -> 297302 | AX9: 258566 | AY9: 288610 | AZ9: =948415-AY9-AX9 -> 401239 | BA9: =O9-AZ9-AY9-AX9 -> 103327 | BB9: 264705 | BC9: 308079 | BD9: 390749 | BE9: =S9-BD9-BC9-BB9 -> 455509 | BF9: 404574 | BH9: 346406
B10: Automotive | C10: 22172 | D10: 25114 | E10: 26829 | F10: 35868 | G10: 42703.575 | H10: 55556.629 | I10: 65716.103 | J10: 74447.601 | K10: 98338.398 | L10: 139014.96 | M10: 312873 | N10: 589035 | O10: 739103 | P10: 1067110 | Q10: 971573 | R10: 1271711 | S10: 1444986 | T10: =SUM(BC10:BF10) -> 1559576 | V10: 12165.689 | W10: =25936.526-V10 -> 13770.837 | X10: =38317.951-W10-V10 -> 12381.425 | Y10: =F10-X10-W10-V10 -> -2449.951 | Z10: 14500.697 | AA10: =30978.781-Z10 -> 16478.084 | AB10: =46354.832-AA10-Z10 -> 15376.051 | AC10: =G10-AB10-AA10-Z10 -> -3651.257 | AD10: 16272.41 | AE10: =34500.939-AD10 -> 18228.529 | AF10: =51563.928-AE10-AD10 -> 17062.989 | AG10: =H10-AF10-AE10-AD10 -> 3992.701 | AH10: 17854.572 | AI10: =30904.898-AH10 -> 13050.326 | AJ10: =57973.607-AI10-AH10 -> 27068.709 | AK10: =I10-AJ10-AI10-AH10 -> 7742.496 | AL10: 30610.845 | AM10: =57579.073-AL10 -> 26968.228 | AN10: =90847.275-AM10-AL10 -> 33268.202 | AO10: =J10-AN10-AM10-AL10 -> -16399.674 | AP10: 50194.507 | AQ10: =114997.673-AP10 -> 64803.166 | AR10: =199588.174-AQ10-AP10 -> 84590.501 | AS10: =K10-AR10-AQ10-AP10 -> -101249.78 | AT10: 196083 | AU10: 232543 | AV10: =733428-AU10-AT10 -> 304802 | AW10: =N10-AV10-AU10-AT10 -> -144393 | AX10: 211002 | AY10: 182446 | AZ10: =668056-AY10-AX10 -> 274608 | BA10: =O10-AZ10-AY10-AX10 -> 71047 | BB10: 236908 | BC10: 325057 | BD10: 343285 | BE10: =S10-BD10-BC10-BB10 -> 539736 | BF10: 351498 | BH10: 310030
B11: Consumer durables | C11: 11194 | D11: 11806 | E11: 12941 | F11: 14651 | G11: 17997.17 | H11: 23360.88 | I11: 30244.192 | J11: 36310.763 | K11: 47170.723 | L11: 76889.132 | M11: 153713 | N11: 291269 | O11: 297189 | P11: 429079 | Q11: 485412 | R11: 635365 | S11: 597907 | T11: =SUM(BC11:BF11) -> 615784 | V11: 5085.728 | W11: =10900.311-V11 -> 5814.583 | X11: =17034.106-W11-V11 -> 6133.795 | Y11: =F11-X11-W11-V11 -> -2383.106 | Z11: 6173.981 | AA11: =13734.803-Z11 -> 7560.822 | AB11: =22125.788-AA11-Z11 -> 8390.985 | AC11: =G11-AB11-AA11-Z11 -> -4128.618 | AD11: 7886.199 | AE11: =17602.89-AD11 -> 9716.691 | AF11: =26769.357-AE11-AD11 -> 9166.467 | AG11: =H11-AF11-AE11-AD11 -> -3408.477 | AH11: 9028.126 | AI11: =18168.213-AH11 -> 9140.087 | AJ11: =32219.42-AI11-AH11 -> 14051.207 | AK11: =I11-AJ11-AI11-AH11 -> -1975.228 | AL11: 15105.577 | AM11: =31855.798-AL11 -> 16750.221 | AN11: =52304.98-AM11-AL11 -> 20449.182 | AO11: =J11-AN11-AM11-AL11 -> -15994.217 | AP11: 32558.289 | AQ11: =70240.258-AP11 -> 37681.969 | AR11: =109212.105-AQ11-AP11 -> 38971.847 | AS11: =K11-AR11-AQ11-AP11 -> -62041.382 | AT11: 81504 | AU11: 94599 | AV11: =303150-AU11-AT11 -> 127047 | AW11: =N11-AV11-AU11-AT11 -> -11881 | AX11: 86490 | AY11: 113384 | AZ11: =344026-AY11-AX11 -> 144152 | BA11: =O11-AZ11-AY11-AX11 -> -46837 | BB11: 125545 | BC11: 140988 | BD11: 140857 | BE11: =S11-BD11-BC11-BB11 -> 190517 | BF11: 143422 | BH11: 164294
B12: Finance | C12: 12985 | D12: 13834 | E12: 16838 | F12: 21514 | G12: 24235.787 | H12: 29699.776 | I12: 43227.187 | J12: 47843.543 | K12: 45183.224 | L12: 73513.573 | M12: 168699 | N12: 317826 | O12: 388576 | P12: 561022 | Q12: 710437 | R12: 929906 | S12: 923792 | T12: =SUM(BC12:BF12) -> 982056 | V12: 6839.52 | W12: =14096.285-V12 -> 7256.765 | X12: =21544.943-W12-V12 -> 7448.658 | Y12: =F12-X12-W12-V12 -> -30.943 | Z12: 8405.358 | AA12: =17865.292-Z12 -> 9459.934 | AB12: =30424.138-AA12-Z12 -> 12558.846 | AC12: =G12-AB12-AA12-Z12 -> -6188.351 | AD12: 12149.961 | AE12: =24643.626-AD12 -> 12493.665 | AF12: =36596.155-AE12-AD12 -> 11952.529 | AG12: =H12-AF12-AE12-AD12 -> -6896.379 | AH12: 10945.379 | AI12: =21200.874-AH12 -> 10255.495 | AJ12: =32785.443-AI12-AH12 -> 11584.569 | AK12: =I12-AJ12-AI12-AH12 -> 10441.744 | AL12: 14095.293 | AM12: =29611.25-AL12 -> 15515.957 | AN12: =47600.715-AM12-AL12 -> 17989.465 | AO12: =J12-AN12-AM12-AL12 -> 242.828 | AP12: 27471.108 | AQ12: =63841.977-AP12 -> 36370.869 | AR12: =111649.534-AQ12-AP12 -> 47807.557 | AS12: =K12-AR12-AQ12-AP12 -> -66466.31 | AT12: 86708 | AU12: 120107 | AV12: =378450-AU12-AT12 -> 171635 | AW12: =N12-AV12-AU12-AT12 -> -60624 | AX12: 139382 | AY12: 156197 | AZ12: =503349-AY12-AX12 -> 207770 | BA12: =O12-AZ12-AY12-AX12 -> -114773 | BB12: 187607 | BC12: 201398 | BD12: 225849 | BE12: =S12-BD12-BC12-BB12 -> 308938 | BF12: 245871 | BH12: 245512
B13: Other | C13: 7008 | D13: 7265 | E13: 8514 | F13: 9880 | G13: 9581.51 | H13: 11107.987 | I13: 13837.305 | J13: 17014.195 | K13: 18365.73 | L13: 25364.622 | M13: 56527 | N13: 106791 | O13: 116697 | P13: 168486 | Q13: 166325 | R13: 217706 | S13: 217750 | T13: =SUM(BC13:BF13) -> 230369 | V13: 2373.273 | W13: =5057.218-V13 -> 2683.945 | X13: =7899.816-W13-V13 -> 2842.598 | Y13: =F13-X13-W13-V13 -> 1980.184 | Z13: 2645.087 | AA13: =5882.612-Z13 -> 3237.525 | AB13: =9555.058-AA13-Z13 -> 3672.446 | AC13: =G13-AB13-AA13-Z13 -> 26.452 | AD13: 3580.001 | AE13: =7892.198-AD13 -> 4312.197 | AF13: =12208.894-AE13-AD13 -> 4316.696 | AG13: =H13-AF13-AE13-AD13 -> -1100.907 | AH13: 3825.729 | AI13: =7625.018-AH13 -> 3799.289 | AJ13: =11943.176-AI13-AH13 -> 4318.158 | AK13: =I13-AJ13-AI13-AH13 -> 1894.129 | AL13: 4584.137 | AM13: =10263.258-AL13 -> 5679.121 | AN13: =16332.193-AM13-AL13 -> 6068.935 | AO13: =J13-AN13-AM13-AL13 -> 682.002 | AP13: 9527.536 | AQ13: =22832.153-AP13 -> 13304.617 | AR13: =37428.86-AQ13-AP13 -> 14596.707 | AS13: =K13-AR13-AQ13-AP13 -> -19063.13 | AT13: 26204 | AU13: 36307 | AV13: =110914-AU13-AT13 -> 48403 | AW13: =N13-AV13-AU13-AT13 -> -4123 | AX13: 30042 | AY13: 35894 | AZ13: =112056-AY13-AX13 -> 46120 | BA13: =O13-AZ13-AY13-AX13 -> 4641 | BB13: 40111 | BC13: 49493 | BD13: 52923 | BE13: =S13-BD13-BC13-BB13 -> 75223 | BF13: 52730 | BH13: 52491
B14: Total combined revenues | C14: =SUM(C9:C13) -> 116584 | D14: =SUM(D9:D13) -> 123477 | E14: =SUM(E9:E13) -> 133465 | F14: =SUM(F9:F13) -> 144310 | G14: =SUM(G9:G13) -> 161791.52 | H14: =SUM(H9:H13) -> 217299.39 | I14: =SUM(I9:I13) -> 306274.82 | J14: =SUM(J9:J13) -> 329042.47 | ... T14: =SUM(T9:T13) -> 4946696 | V14: =SUM(V9:V13) -> 48170.961 | W14: =SUM(W9:W13) -> 52585.754 | X14: =SUM(X9:X13) -> 55033.231 | Y14: =SUM(Y9:Y13) -> -11479.946 | Z14: =SUM(Z9:Z13) -> 57478.351 | AA14: =SUM(AA9:AA13) -> 72630.368 | AB14: =SUM(AB9:AB13) -> 90055.469 | AC14: =SUM(AC9:AC13) -> -58372.673 | ... BF14: =SUM(BF9:BF13) -> 1198095 | BH14: =SUM(BH9:BH13) -> 1118733
B17: Combined revenues by segment (% Share)
B18: Energy | C18: =C9/C$14 -> 0.54231284 | D18: =D9/D$14 -> 0.53012302 | E18: =E9/E$14 -> 0.51206683 | F18: =F9/F$14 -> 0.43238168 | G18: =G9/G$14 -> 0.41580347 | H18: =H9/H$14 -> 0.44903079 | I18: =I9/I$14 -> 0.50036773 | J18: =J9/J$14 -> 0.46628135 | ... T18: =T9/T$14 -> 0.31514186 | V18: =V9/V$14 -> 0.45061902 | W18: =W9/W$14 -> 0.43851466 | X18: =X9/X$14 -> 0.47656215 | Y18: =Y9/Y$14 -> 0.74879533 | Z18: =Z9/Z$14 -> 0.44805092 | AA18: =AA9/AA$14 -> 0.49420103 | AB18: =AB9/AB$14 -> 0.55584787 | AC18: =AC9/AC$14 -> 0.76115923 | ... BF18: =BF9/BF$14 -> 0.33768107 | BH18: =BH9/BH$14 -> 0.30964135
B19: Automotive | C19: =C10/C$14 -> 0.19018047 | D19: =D10/D$14 -> 0.20339011 | E19: =E10/E$14 -> 0.20101899 | F19: =F10/F$14 -> 0.24854826 | G19: =G10/G$14 -> 0.26394199 | H19: =H10/H$14 -> 0.25566859 | I19: =I10/I$14 -> 0.2145658 | J19: =J10/J$14 -> 0.2262553 | ... T19: =T10/T$14 -> 0.3152763 | V19: =V10/V$14 -> 0.25255234 | W19: =W10/W$14 -> 0.26187391 | X19: =X10/X$14 -> 0.22498088 | Y19: =Y10/Y$14 -> 0.21341137 | Z19: =Z10/Z$14 -> 0.25228102 | AA19: =AA10/AA$14 -> 0.22687595 | AB19: =AB10/AB$14 -> 0.17073978 | AC19: =AC10/AC$14 -> 0.062550793 | ... BF19: =BF10/BF$14 -> 0.29338074 | BH19: =BH10/BH$14 -> 0.277126
B20: Consumer durables | C20: =C11/C$14 -> 0.096016606 | D20: =D11/D$14 -> 0.095612948 | E20: =E11/E$14 -> 0.09696175 | F20: =F11/F$14 -> 0.1015245 | G20: =G11/G$14 -> 0.1112368 | H20: =H11/H$14 -> 0.1075055 | I20: =I11/I$14 -> 0.098748541 | J20: =J11/J$14 -> 0.11035282 | ... T20: =T11/T$14 -> 0.1244839 | V20: =V11/V$14 -> 0.10557664 | W20: =W11/W$14 -> 0.11057335 | X20: =X11/X$14 -> 0.1114562 | Y20: =Y11/Y$14 -> 0.20758861 | Z20: =Z11/Z$14 -> 0.10741402 | AA20: =AA11/AA$14 -> 0.10410001 | AB20: =AB11/AB$14 -> 0.09317574 | AC20: =AC11/AC$14 -> 0.07072861 | ... BF20: =BF11/BF$14 -> 0.11970837 | BH20: =BH11/BH$14 -> 0.1468572
B21: Finance | C21: =C12/C$14 -> 0.11137892 | D21: =D12/D$14 -> 0.11203706 | E21: =E12/E$14 -> 0.12616042 | F21: =F12/F$14 -> 0.14908184 | G21: =G12/G$14 -> 0.1497964 | H21: =H12/H$14 -> 0.13667676 | I21: =I12/I$14 -> 0.14113856 | J21: =J12/J$14 -> 0.14540234 | ... T21: =T12/T$14 -> 0.19852766 | V21: =V12/V$14 -> 0.1419843 | W21: =W12/W$14 -> 0.13799869 | X21: =X12/X$14 -> 0.13534837 | Y21: =Y12/Y$14 -> 0.002695396 | Z21: =Z12/Z$14 -> 0.1462352 | AA21: =AA12/AA$14 -> 0.13024764 | AB21: =AB12/AB$14 -> 0.13945678 | AC21: =AC12/AC$14 -> 0.10601452 | ... BF21: =BF12/BF$14 -> 0.20521828 | BH21: =BH12/BH$14 -> 0.2194554
B22: Other | C22: =C13/C$14 -> 0.060111164 | D22: =D13/D$14 -> 0.058836868 | E22: =E13/E$14 -> 0.063792005 | F22: =F13/F$14 -> 0.068463724 | G22: =G13/G$14 -> 0.059221338 | H22: =H13/H$14 -> 0.051118354 | I22: =I13/I$14 -> 0.045179375 | J22: =J13/J$14 -> 0.051708204 | ... T22: =T13/T$14 -> 0.046570276 | V22: =V13/V$14 -> 0.049267711 | W22: =W13/W$14 -> 0.051039394 | X22: =X13/X$14 -> 0.051652392 | Y22: =Y13/Y$14 -> -0.17249071 | Z22: =Z13/Z$14 -> 0.046018839 | AA22: =AA13/AA$14 -> 0.044575363 | AB22: =AB13/AB$14 -> 0.040779822 | AC22: =AC13/AC$14 -> -0.00045315725 | ... BF22: =BF13/BF$14 -> 0.044011535 | BH22: =BH13/BH$14 -> 0.046920043
B23: Total combined revenues | C23: =SUM(C18:C22) -> 1 | D23: =SUM(D18:D22) -> 1 | E23: =SUM(E18:E22) -> 1 | F23: =SUM(F18:F22) -> 1 | G23: =SUM(G18:G22) -> 1 | H23: =SUM(H18:H22) -> 1 | I23: =SUM(I18:I22) -> 1 | J23: =SUM(J18:J22) -> 1 | ... T23: =SUM(T18:T22) -> 1 | V23: =SUM(V18:V22) -> 1 | W23: =SUM(W18:W22) -> 1 | X23: =SUM(X18:X22) -> 1 | Y23: =SUM(Y18:Y22) -> 1 | Z23: =SUM(Z18:Z22) -> 1 | AA23: =SUM(AA18:AA22) -> 1 | AB23: =SUM(AB18:AB22) -> 1 | AC23: =SUM(AC18:AC22) -> 1 | ... BF23: =SUM(BF18:BF22) -> 1 | BH23: =SUM(BH18:BH22) -> 1
B26: Combined revenues by segment (% Share)
B27: Energy | D27: =D9/C9-1 -> 0.035318308 | E27: =E9/D9-1 -> 0.044074063 | F27: =F9/E9-1 -> -0.087002327 | G27: =G9/F9-1 -> 0.078152363 | H27: =H9/G9-1 -> 0.45040997 | I27: =I9/H9-1 -> 0.57060134 | J27: =J9/I9-1 -> 0.0011505837 | K27: =K9/J9-1 -> -0.2449799 | ... M27: =M9/L9-1 -> 2.1092545 | O27: =O9/N9-1 -> -0.2230136 | P27: =P9/N9-1 -> 0.1218055 | Q27: =Q9/O9-1 -> 0.22840963 | R27: =R9/P9-1 -> 0.11365991 | S27: =S9/R9-1 -> -0.1608699 | Z27: =Z9/V9-1 -> 0.1864156 | AA27: =AA9/W9-1 -> 0.55657365 | AB27: =AB9/X9-1 -> 0.90862884 | AC27: =AC9/Y9-1 -> 4.1687095 | AD27: =AD9/Z9-1 -> 0.37870037 | AE27: =AE9/AA9-1 -> 0.11325407 | AF27: =AF9/AB9-1 -> -0.19243133 | AG27: =AG9/AC9-1 -> -0.58777352 | ... BD27: =BD9/AZ9-1 -> -0.026144019 | BF27: =BF9/BH9-1 -> 0.16791857
B28: Automotive | D28: =D10/C10-1 -> 0.13268988 | E28: =E10/D10-1 -> 0.068288604 | F28: =F10/E10-1 -> 0.33691155 | G28: =G10/F10-1 -> 0.19057586 | H28: =H10/G10-1 -> 0.30098309 | I28: =I10/H10-1 -> 0.182867 | J28: =J10/I10-1 -> 0.13286695 | K28: =K10/J10-1 -> 0.32090755 | ... M28: =M10/L10-1 -> 1.2506426 | O28: =O10/N10-1 -> 0.25476924 | P28: =P10/N10-1 -> 0.8116241 | Q28: =Q10/O10-1 -> 0.31452991 | R28: =R10/P10-1 -> 0.19173375 | S28: =S10/R10-1 -> 0.13625344 | Z28: =Z10/V10-1 -> 0.19193389 | AA28: =AA10/W10-1 -> 0.19659277 | AB28: =AB10/X10-1 -> 0.24186441 | AC28: =AC10/Y10-1 -> 0.49033879 | AD28: =AD10/Z10-1 -> 0.12218123 | AE28: =AE10/AA10-1 -> 0.10622867 | AF28: =AF10/AB10-1 -> 0.10971205 | AG28: =AG10/AC10-1 -> -2.0935141 | ... BD28: =BD10/AZ10-1 -> 0.25009104 | BF28: =BF10/BH10-1 -> 0.1337548
B29: Consumer durables | D29: =D11/C11-1 -> 0.054672146 | E29: =E11/D11-1 -> 0.096137557 | F29: =F11/E11-1 -> 0.13213817 | G29: =G11/F11-1 -> 0.22839192 | H29: =H11/G11-1 -> 0.29803075 | I29: =I11/H11-1 -> 0.29465123 | J29: =J11/I11-1 -> 0.20058631 | K29: =K11/J11-1 -> 0.29908377 | ... M29: =M11/L11-1 -> 0.99915119 | O29: =O11/N11-1 -> 0.020324854 | P29: =P11/N11-1 -> 0.47313652 | Q29: =Q11/O11-1 -> 0.63334444 | R29: =R11/P11-1 -> 0.48076461 | S29: =S11/R11-1 -> -0.058955089 | Z29: =Z11/V11-1 -> 0.21398175 | AA29: =AA11/W11-1 -> 0.30032059 | AB29: =AB11/X11-1 -> 0.36799241 | AC29: =AC11/Y11-1 -> 0.73245252 | AD29: =AD11/Z11-1 -> 0.27732803 | AE29: =AE11/AA11-1 -> 0.28513685 | AF29: =AF11/AB11-1 -> 0.092418471 | AG29: =AG11/AC11-1 -> -0.17442665 | ... BD29: =BD11/AZ11-1 -> -0.022857817 | BF29: =BF11/BH11-1 -> -0.12704055
B30: Finance | D30: =D12/C12-1 -> 0.065383134 | E30: =E12/D12-1 -> 0.21714616 | F30: =F12/E12-1 -> 0.27770519 | G30: =G12/F12-1 -> 0.12651236 | H30: =H12/G12-1 -> 0.22545127 | I30: =I12/H12-1 -> 0.45547182 | J30: =J12/I12-1 -> 0.10679288 | K30: =K12/J12-1 -> -0.055604557 | ... M30: =M12/L12-1 -> 1.2948007 | O30: =O12/N12-1 -> 0.22260608 | P30: =P12/N12-1 -> 0.76518598 | Q30: =Q12/O12-1 -> 0.82830901 | R30: =R12/P12-1 -> 0.65752145 | S30: =S12/R12-1 -> -0.0065748581 | Z30: =Z12/V12-1 -> 0.22893975 | AA30: =AA12/W12-1 -> 0.30360209 | AB30: =AB12/X12-1 -> 0.68605486 | AC30: =AC12/Y12-1 -> 198.99195 | AD30: =AD12/Z12-1 -> 0.4455019 | AE30: =AE12/AA12-1 -> 0.32069262 | AF30: =AF12/AB12-1 -> -0.048278082 | AG30: =AG12/AC12-1 -> 0.11441303 | ... BD30: =BD12/AZ12-1 -> 0.087014487 | BF30: =BF12/BH12-1 -> 0.0014622503
B31: Other | D31: =D13/C13-1 -> 0.036672374 | E31: =E13/D13-1 -> 0.17192017 | F31: =F13/E13-1 -> 0.16044163 | G31: =G13/F13-1 -> -0.030211538 | H31: =H13/G13-1 -> 0.15931487 | I31: =I13/H13-1 -> 0.24570771 | J31: =J13/I13-1 -> 0.22958878 | K31: =K13/J13-1 -> 0.07943573 | ... M31: =M13/L13-1 -> 1.2285765 | O31: =O13/N13-1 -> 0.092760626 | P31: =P13/N13-1 -> 0.57771722 | Q31: =Q13/O13-1 -> 0.42527229 | R31: =R13/P13-1 -> 0.2921311 | S31: =S13/R13-1 -> 0.00020210743 | Z31: =Z13/V13-1 -> 0.11453128 | AA31: =AA13/W13-1 -> 0.20625609 | AB31: =AB13/X13-1 -> 0.29193294 | AC31: =AC13/Y13-1 -> -0.98664165 | AD31: =AD13/Z13-1 -> 0.35345302 | AE31: =AE13/AA13-1 -> 0.33194246 | AF31: =AF13/AB13-1 -> 0.17542804 | AG31: =AG13/AC13-1 -> -42.619046 | ... BD31: =BD13/AZ13-1 -> 0.1475065 | BF31: =BF13/BH13-1 -> 0.0045531615
B32: Total combined revenues | D32: =D14/C14-1 -> 0.059124751 | E32: =E14/D14-1 -> 0.080889558 | F32: =F14/E14-1 -> 0.081257258 | G32: =G14/F14-1 -> 0.12113863 | H32: =H14/G14-1 -> 0.34308272 | I32: =I14/H14-1 -> 0.40946013 | J32: =J14/I14-1 -> 0.074337295 | K32: =K14/J14-1 -> -0.012595341 | ... M32: =M14/L14-1 -> 1.5821378 | O32: =O14/N14-1 -> -0.024536418 | P32: =P14/N14-1 -> 0.40836505 | Q32: =Q14/O14-1 -> 0.39810558 | R32: =R14/P14-1 -> 0.26750311 | S32: =S14/R14-1 -> -0.029984144 | Z32: =Z14/V14-1 -> 0.19321578 | AA32: =AA14/W14-1 -> 0.38117955 | AB32: =AB14/X14-1 -> 0.63638346 | AC32: =AC14/Y14-1 -> 4.0847515 | AD32: =AD14/Z14-1 -> 0.31170353 | AE32: =AE14/AA14-1 -> 0.16631967 | AF32: =AF14/AB14-1 -> -0.079197955 | AG32: =AG14/AC14-1 -> -0.55923459 | ... BD32: =BD14/AZ14-1 -> 0.074285145 | BF32: =BF14/BB14-1 -> 0.40148396

Sheet Sheet2
E2: =AVERAGE(E3:E134) -> 7.5461818
D3: 44196 | E3: 7.4392 | F3: 7.381 | G3: 7.4928 | H3: 7.3461 | I3: 34.69K | J3: 0.0084
D4: 44195 | E4: 7.3774 | F4: 7.3865 | G4: 7.3993 | H4: 7.303 | I4: 39.47K | J4: -0.0006
D5: 44194 | E5: 7.3815 | F5: 7.4466 | G5: 7.4804 | H5: 7.3376 | I5: 46.00K | J5: -0.0081
D6: 44193 | E6: 7.4416 | F6: 7.5716 | G6: 7.5756 | H6: 7.4035 | I6: 28.59K | J6: -0.014
D7: 44190 | E7: 7.547 | F7: 7.5801 | G7: 7.6016 | H7: 7.5305 | I7: 3.00K | J7: -0.0037
D8: 44189 | E8: 7.5747 | F8: 7.6398 | G8: 7.6757 | H8: 7.546 | I8: 47.13K | J8: -0.008
D9: 44188 | E9: 7.6361 | F9: 7.6632 | G9: 7.6711 | H9: 7.614 | I9: 53.20K | J9: -0.0027
D10: 44187 | E10: 7.657 | F10: 7.6506 | G10: 7.6786 | H10: 7.6129 | I10: 56.36K | J10: 0.001
D11: 44186 | E11: 7.6491 | F11: 7.631 | G11: 7.7376 | H11: 7.6234 | I11: 51.53K | J11: 0.0033
D12: 44183 | E12: 7.6239 | F12: 7.7009 | G12: 7.7607 | H12: 7.6122 | I12: 57.81K | J12: -0.0094
D13: 44182 | E13: 7.6959 | F13: 7.7999 | G13: 7.8097 | H13: 7.6896 | I13: 63.73K | J13: -0.0127
D14: 44181 | E14: 7.7949 | F14: 7.844 | G14: 7.8492 | H14: 7.7573 | I14: 61.16K | J14: -0.0045
... D264: 43831 | E264: 5.9466 | F264: 5.9461 | G264: 5.9491 | H264: 5.9375 | I264: 1.19K | J264: -0.0004

Sheet Terms
B2: Tranches | C2: 4.125% 2018
B3: Format (i.e., LPN, Bond, Note, etc.) | C3: Notes
B4: Currency | C4: USD
B5: Type | C5: Senior Notes
B6: Size | C6: 700mn
B7: Rating | C7: Ba1 / BBB-
B8: Babson Recommendation | C8: BUY
B9: Maturity | C9: 43222
B10: Callable | C10: No
B11: Putable | C11: No
B12: Series | C12: 144A/RegS
B13: Bond price | C13: 92.125
B14: Spread over UST | C14: 293.87
B15: UST | C15: T23/4 02/15/24
B16: L OAS | C16: 326.4
B17: YTM | C17: 0.0554
B18: YTW | C18: 0.0554
B19: OAD | C19: 6.81
B20: Withholding tax (Y / N) | C20: Yes
B21: Change of control (Y / N) | C21: No
B22: Pre-empt language if tax event (Y/N) | C22: Yes
B23: Bookrunners | C23: Citi,DB
B24: Lead | C24: n/a
