Workbook
Name \A: #REF!
Name \B: #REF!
Name \C: #REF!
Name \L: #REF!
Name \M: #REF!
Name \P: #REF!
Name \Y: #REF!
Name _01_30_04: MonthlyOpStats
Name _01_30_04: MonthlyOpStats
Name _01_30_04: MonthlyOpStats
Name _01_30_04: MonthlyOpStats
Name _1_30_01: MonthlyOpStats
Name _1_30_01: MonthlyOpStats
Name _1_30_01: MonthlyOpStats
Name _1_30_01: MonthlyOpStats
Name _1_30_02: MonthlyOpStats
Name _1_30_02: MonthlyOpStats
Name _1_30_02: MonthlyOpStats
Name _1_30_02: MonthlyOpStats
Name _1_31_01: MonthlyOpStats
Name _1_31_01: MonthlyOpStats
Name _1_31_01: MonthlyOpStats
Name _1_31_01: MonthlyOpStats
Name _1_31_02: MonthlyOpStats
Name _1_31_02: MonthlyOpStats
Name _1_31_02: MonthlyOpStats
Name _1_31_02: MonthlyOpStats
Name _12_31_05: MonthlyOpStats
Name _12_31_05: MonthlyOpStats
Name _12_31_05: MonthlyOpStats
Name _12_31_05: MonthlyOpStats
Name _A: #REF!
Name _A___0: #REF!
Name _B: #REF!
Name _B___0: #REF!
Name _C: #REF!
Name _C___0: #REF!
Name _ent1: [1]Inputs!$J$17
Name _ent10: [1]Inputs!$J$476
Name _ent11: [1]Inputs!$J$527
Name _ent12: [1]Inputs!$J$578
Name _ent13: [1]Inputs!$J$629
Name _ent14: [1]Inputs!$J$680
Name _ent15: [1]Inputs!$J$731
Name _ent2: [1]Inputs!$J$68
Name _ent3: [1]Inputs!$J$119
Name _ent4: [1]Inputs!$J$170
Name _ent5: [1]Inputs!$J$221
Name _ent6: [1]Inputs!$J$272
Name _ent7: [1]Inputs!$J$323
Name _ent8: [1]Inputs!$J$374
Name _ent9: [1]Inputs!$J$425
Name _eps1: [1]Inputs!$P$42
Name _eps10: [1]Inputs!$P$501
Name _eps11: [1]Inputs!$P$552
Name _eps12: [1]Inputs!$P$603
Name _eps13: [1]Inputs!$P$654
Name _eps14: [1]Inputs!$P$705
Name _eps15: [1]Inputs!$P$756
Name _eps2: [1]Inputs!$P$93

Sheet Capitalisation
B3: 1Q26 | I3: Exchange rate as at end | J3: =Model!$Q$211 -> 0.055744467
I4: LTM Average exchange rate | J4: =Model!$Q$210 -> 0.054085873
C6: Amount outstanding as on 31-Mar-2026 | D6: MXN mn | E6: USD mn | F6: Leverage (MXN) | G6: Leverage (USD) | I6: Company reported | J6: =D6 -> MXN mn
I7: Total debt and lease liabilities | J7: 88557.8
C8: Current portion of long-term debt | D8: 0 | E8: =D8*$J3 -> 0 | I8: Net debt | J8: 49752.4
I9: Net debt / EBITDA | J9: =J8/D21 -> 2.1876949
C10: Long-term debt, net of current portion | D10: =SUM(D11:D12) -> 82048.136 | E10: =SUM(E11:E12) -> 4573.7296
C11: Long-term bank loans | D11: 9949.316 | E11: =D11*J3 -> 554.61932
C12: Long-term stock market loans | D12: 72098.82 | E12: =D12*J3 -> 4019.1103
C14: Lease Liabilties | D14: =Model!$BC$108 -> 6509.7 | E14: =D14*$J3 -> 362.87976
C16: Total Loans & Borrows (including finance lease obligations) | D16: =SUM(D8,D10,D14) -> 88557.836 | E16: =SUM(E8,E10,E14) -> 4936.6094 | F16: =+D16/D21 -> 3.8940338 | G16: =+E16/E21 -> 4.013448
C17: Cash & Equivalents | D17: =Model!BC$113 -> 24976.8 | E17: =D17*$J3 -> 1392.3184
C18: Net debt | D18: =+D16-D17 -> 63581.036 | E18: =+E16-E17 -> 3544.291 | F18: =+D18/D21 -> 2.7957628 | G18: =+E18/E21 -> 2.8814975
C19: Equity | D19: =Model!BC$120 -> 104339.7 | E19: =D19*$J3 -> 5816.361
C20: Total Capitalisation | D20: =D16+D19 -> 192897.54 | E20: =E16+E19 -> 10752.97 | F20: =D20/D21 -> 8.4820221 | G20: =E20/E21 -> 8.7421313
C21: LTM Adjusted EBITDA | D21: =Model!BC$85 -> 22741.928 | E21: =D21*J4 -> 1230.017
C22: check | D22: =D16-Model!BC$116 -> 0.036
C24: short term investments | D24: 9733.4 | E24: =D24*J3 -> 542.5832
C25: Net debt including short-term investments | D25: =D18-D24 -> 53847.636 | E25: =E18-E24 -> 3001.7078
C26: Net leverage including short-term investments | D26: =D25/D21 -> 2.3677692 | E26: =E25/E21 -> 2.440379
C30: Liquidity Table at end | D30: =D6 -> MXN mn | E30: =E6 -> USD mn
C31: Cash and cash equivalents | D31: =D17 -> 24976.8 | E31: =D31*$J3 -> 1392.3184
C32: short term investments | D32: =D24 -> 9733.4 | E32: =D32*$J3 -> 542.5832
C33: Total Liquidity | D33: =SUM(D31:D32) -> 34710.2 | E33: =SUM(E31:E32) -> 1934.9016
C36: Total Debt as at end (excluding leases) | D36: =D30 -> MXN mn | E36: =E30 -> USD mn
E37: =D37*$J3 -> 0
C38: Secured - Banks
B39: 2029 | C39: Union 1 TIE+1.25 | D39: 2469.409 | E39: =D39*$J3 -> 137.65589
B40: 2029 | C40: Union 2 TIE+1.25 | D40: 7479.907 | E40: =D40*$J3 -> 416.96343
C42: Unsecured - Notes
B43: 2037 | C43: Senior notes 1 @ 8.93% | D43: 4485.361 | E43: =D43*$J3 -> 250.03406
B44: 2043 | C44: Senior notes 2 @ 7.62% | D44: 6164.304 | E44: =D44*$J3 -> 343.62584
B45: 2027 | C45: Stock Certificates 3 @ 8.79% | D45: 4494.794 | E45: =D45*$J3 -> 250.5599
B46: 2032 | C46: Senior notes 4 @ 8.94% | D46: 5353.741 | E46: =D46*$J3 -> 298.44144
B47: 2040 | C47: Senior notes 5 @ 6.97% | D47: 10633.157 | E47: =D47*$J3 -> 592.73967
B48: 2045 | C48: Senior notes 6 @ 5.26% | D48: 13751.371 | E48: =D48*$J3 -> 766.56285
B49: 2046 | C49: Senior notes 7 @ 6.44% | D49: 15661.618 | E49: =D49*$J3 -> 873.04855
B50: 2049 | C50: Senior notes 8 @ 5.52% | D50: 11554.474 | E50: =D50*$J3 -> 644.098
C52: Total debt | D52: =SUM(D39:D51) -> 82048.136 | E52: =SUM(E39:E51) -> 4573.7296
C53: Check | D53: =D52-D8-D10 -> 0
C56: Debt Maturity Profile at end(excluding lease obligations) | D56: =D36 -> MXN mn | E56: =E36 -> USD mn
C57: 2026
C58: 2027 | D58: =D45 -> 4494.794 | E58: =D58*$J3 -> 250.5599
C59: 2029 | D59: =D39+D40 -> 9949.316 | E59: =D59*$J3 -> 554.61932
C60: 2032 | D60: =D46 -> 5353.741 | E60: =D60*$J3 -> 298.44144
C61: 2037 | D61: =D43 -> 4485.361 | E61: =D61*$J3 -> 250.03406
C62: 2040 + | D62: =D44+D47+D48+D49+D50 -> 57764.924 | E62: =D62*$J3 -> 3220.0749
C63: Total debt | D63: =SUM(D57:D62) -> 82048.136 | E63: =SUM(E61:E62) -> 3470.109
C64: Check | D64: =D63-D8-D10 -> 0
B70: FY25 | I70: Exchange rate as at end | J70: =Model!$Q$211 -> 0.055744467
I71: LTM Average exchange rate | J71: =Model!$Q$210 -> 0.054085873
C73: Amount outstanding as on 31-Dec-2025 | D73: MXN mn | E73: USD mn | F73: Leverage (MXN) | G73: Leverage (USD) | I73: Company reported | J73: =D73 -> MXN mn
I74: Total debt and lease liabilities | J74: 91430.2
C75: Current portion of long-term debt | D75: 3737 | E75: =D75*$J70 -> 208.31707 | I75: Net debt | J75: 49115.2
C76: Long-term debt, net of current portion | D76: 82257.2 | E76: =D76*$J70 -> 4585.3838 | I76: Net debt / EBITDA | J76: =J75/D84 -> 2.1927184
C77: Lease Liabilties | D77: =1583.9+3852.1 -> 5436 | E77: =D77*$J70 -> 303.02692
C79: Total Loans & Borrows (including finance lease obligations) | D79: =SUM(D75:D77) -> 91430.2 | E79: =SUM(E75:E77) -> 5096.7278 | F79: =+D79/D84 -> 4.081846 | G79: =+E79/E84 -> 4.2070197
C80: Cash & Equivalents | D80: =Model!BB$113 -> 36375.7 | E80: =D80*$J70 -> 2027.744
C81: Net debt | D81: =+D79-D80 -> 55054.5 | E81: =+E79-E80 -> 3068.9838 | F81: =+D81/D84 -> 2.4578749 | G81: =+E81/E84 -> 2.5332479
C82: Equity | D82: =Model!BB$120 -> 102889 | E82: =D82*$J70 -> 5735.4925
C83: Total Capitalisation | D83: =D79+D82 -> 194319.2 | E83: =D83*$J70 -> 10832.22 | F83: =D83/D84 -> 8.6752633 | G83: =E83/E84 -> 8.9412984
C84: LTM Adjusted EBITDA | D84: =Model!BB$85 -> 22399.228 | E84: =D84*J71 -> 1211.4818
C86: check | D86: =D79-Model!BB$116 -> 0
C88: Liquidity Table at end-FY25 | D88: =D73 -> MXN mn | E88: =E73 -> USD mn
C89: Cash and cash equivalents | D89: =D80 -> 36375.7 | E89: =D89*$J70 -> 2027.744
C90: Total Liquidity | D90: =SUM(D89:D89) -> 36375.7 | E90: =SUM(E89:E89) -> 2027.744
C93: Total Debt as at end-3Q25 (excluding leases) | D93: =D88 -> MXN mn | E93: =E88 -> USD mn
E94: =D94*$J70 -> 0
C95: Secured - Banks
B96: 2029 | C96: Union 1 TIE+1.25 | D96: 2468.36 | E96: =D96*$J70 -> 137.59741
B97: 2029 | C97: Union 2 TIE+1.25 | D97: 7476.733 | E97: =D97*$J70 -> 416.7865
C99: Unsecured - Notes
B100: 2037 | C100: Senior notes 1 @ 8.93% | D100: 4485.168 | E100: =D100*$J70 -> 250.0233
B101: 2043 | C101: Senior notes 2 @ 7.62% | D101: 6163.883 | E101: =D101*$J70 -> 343.60237
B102: 2027 | C102: Stock Certificates 3 @ 8.79% | D102: 4494.018 | E102: =D102*$J70 -> 250.51664
B103: 2032 | C103: Senior notes 4 @ 8.94% | D103: 5373.841 | E103: =D103*$J70 -> 299.5619
B104: 2040 | C104: Senior notes 5 @ 6.97% | D104: 10673.803 | E104: =D104*$J70 -> 595.00546
B105: 2045 | C105: Senior notes 6 @ 5.26% | D105: 13803.603 | E105: =D105*$J70 -> 769.4745
B106: 2026 | C106: Senior notes 7 @ 4.86% | D106: 3736.982 | E106: =D106*$J70 -> 208.31607
B107: 2046 | C107: Senior notes 8 @ 6.44% | D107: 15718.921 | E107: =D107*$J70 -> 876.24288
B108: 2049 | C108: Senior notes 9 @ 5.52% | D108: 11598.828 | E108: =D108*$J70 -> 646.57049
C110: Total debt | D110: =SUM(D96:D109) -> 85994.14 | E110: =SUM(E96:E109) -> 4793.6975
C111: Check | D111: =D110-D75-D76 -> -0.06
C114: Debt Maturity Profile at end-FY25 (excluding lease obligations) | D114: =D93 -> MXN mn | E114: =E93 -> USD mn
C115: 2026 | D115: =D106 -> 3736.982 | E115: =D115*$J70 -> 208.31607
C116: 2027 | D116: =D102 -> 4494.018 | E116: =D116*$J70 -> 250.51664
C117: 2029 | D117: =D96+D97 -> 9945.093 | E117: =D117*$J70 -> 554.38391
C118: 2032 | D118: =D103 -> 5373.841 | E118: =D118*$J70 -> 299.5619
C119: 2037 | D119: =D100 -> 4485.168 | E119: =D119*$J70 -> 250.0233
C120: 2040 + | D120: =D101+D104+D105+D107+D108 -> 57959.038 | E120: =D120*$J70 -> 3230.8957
C121: Total debt | D121: =SUM(D115:D120) -> 85994.14 | E121: =SUM(E119:E120) -> 3480.919
C122: Check | D122: =D121-D75-D76 -> -0.06
B127: 3Q25 | I127: Exchange rate as at end 3Q25 | J127: =Model!BA$211 -> 0.05461
C129: Amount outstanding as on 30-Sep-2025 | D129: (MXN millions) | E129: (USD millions) | F129: Leverage | I129: Company reported | J129: (MXN millions)
I130: Total debt and lease liabilities | J130: 91763.8
C131: Current portion of long-term debt | D131: 3802 | E131: =D131*$J127 -> 207.62722 | I131: Net debt | J131: 50086.3
C132: Long-term debt, net of current portion | D132: 83259.1 | E132: =D132*$J127 -> 4546.7795 | I132: Net debt / EBITDA | J132: =J131/D140 -> 2.2829885
C133: Lease Liabilties | D133: =1265.7+3437 -> 4702.7 | E133: =D133*$J127 -> 256.81445
C135: Total Loans & Borrows (including finance lease obligations) | D135: =SUM(D131:D133) -> 91763.8 | E135: =SUM(E131:E133) -> 5011.2211 | F135: =+D135/D140 -> 4.1826947
C136: Cash & Equivalents | D136: =Model!BA$113 -> 37856.776 | E136: =D136*$J127 -> 2067.3585
...

Sheet Model
B2: Grupo Televisa, S.A.B. | C2: Annual | D2: Annual | E2: Annual | F2: Annual | G2: Annual | H2: Annual | I2: Annual | J2: Annual | K2: Annual | L2: Annual | M2: Annual | N2: Annual | O2: Annual | P2: Annual | Q2: LTM | S2: Quarterly | T2: Quarterly | U2: Quarterly | V2: Quarterly | W2: Quarterly | X2: Quarterly | Y2: Quarterly | Z2: Quarterly | AA2: Quarterly | AB2: Quarterly | AC2: Quarterly | AD2: Quarterly | AE2: Quarterly | AF2: Quarterly | AG2: Quarterly | AH2: Quarterly | AI2: Quarterly | AJ2: Quarterly | AK2: Quarterly | AL2: Quarterly | AM2: Quarterly | AN2: Quarterly | AO2: Quarterly | AP2: Quarterly | AQ2: Quarterly | AR2: Quarterly | AS2: Quarterly | AT2: Quarterly | AU2: Quarterly | AV2: Quarterly | AW2: Quarterly | AX2: Quarterly | AY2: Quarterly | AZ2: Quarterly | BA2: Quarterly | BB2: Quarterly | BC2: Quarterly | BF2: Quarterly | BG2: Quarterly | BH2: Quarterly | BI2: Quarterly | BJ2: Quarterly | BK2: Quarterly | BL2: Quarterly
B3: (MXN millions) | C3: 42735 | D3: 43100 | E3: 43465 | F3: 43830 | G3: 43830 | H3: 44196 | I3: 44561 | J3: 44561 | K3: 44926 | L3: 44926 | M3: 45291 | N3: 45291 | O3: 45657 | P3: 46022 | Q3: =BC3 -> 46112 | S3: 42825 | T3: 42916 | U3: 43008 | V3: 43100 | W3: 43190 | X3: 43281 | Y3: 43373 | Z3: 43465 | AA3: 43555 | AB3: 43646 | AC3: 43738 | AD3: 43830 | AE3: 43921 | AF3: 44012 | AG3: 44104 | AH3: 44196 | AI3: 44286 | AJ3: 44377 | AK3: 44469 | AL3: 44561 | AM3: 44651 | AN3: 44742 | AO3: 44834 | AP3: 44926 | AQ3: 45016 | AR3: 45107 | AS3: 45199 | AT3: 45291 | AU3: 45382 | AV3: 45473 | AW3: 45565 | AX3: 45657 | AY3: 45747 | AZ3: 45838 | BA3: 45930 | BB3: 46022 | BC3: 46112 | BF3: 43830 | BG3: 44286 | BH3: 44377 | BI3: 44469 | BJ3: 44561 | BK3: 45016 | BL3: 45107
C4: Act | D4: Act | E4: Act | F4: Act | G4: Act | H4: Act | I4: Act | J4: Act | K4: Act | L4: Act | M4: Act | N4: Act | O4: Act | P4: Act | Q4: Act | S4: Act | T4: Act | U4: Act | V4: Act | W4: Act | X4: Act | Y4: Act | Z4: Act | AA4: Act | AB4: Act | AC4: Act | AD4: Act | AE4: Act | AF4: Act | AG4: Act | AH4: Act | AI4: Act | AJ4: Act | AK4: Act | AL4: Act | AM4: Act | AN4: Act | AO4: Act | AP4: Act | AQ4: Act | AR4: Act | AS4: Act | AT4: Act | AU4: Act | AV4: Act | AW4: Act | AX4: Act | AY4: Act | AZ4: Act | BA4: Act | BB4: Act | BC4: Act | BF4: Act | BG4: Act | BH4: Act | BI4: Act | BJ4: Act | BK4: Act | BL4: Act
C5: FY | D5: FY | E5: FY | F5: FY | G5: FY | H5: FY | I5: FY | J5: FY | K5: FY | L5: FY | M5: FY | N5: FY | O5: FY | P5: FY | Q5: LTM | S5: Q1 | T5: Q2 | U5: Q3 | V5: Q4 | W5: Q1 | X5: Q2 | Y5: Q3 | Z5: Q4 | AA5: Q1 | AB5: Q2 | AC5: Q3 | AD5: Q4 | AE5: Q1 | AF5: Q2 | AG5: Q3 | AH5: Q4 | AI5: Q1 | AJ5: Q2 | AK5: Q3 | AL5: Q4 | AM5: Q1 | AN5: Q2 | AO5: Q3 | AP5: Q4 | AQ5: Q1 | AR5: Q2 | AS5: Q3 | AT5: Q4 | AU5: Q1 | AV5: Q2 | AW5: Q3 | AX5: Q4 | AY5: Q1 | AZ5: Q2 | BA5: Q3 | BB5: Q4 | BC5: Q1 | BF5: Q4 | BG5: Q1 | BH5: Q2 | BI5: Q3 | BJ5: Q4 | BK5: Q1 | BL5: Q2
B6: INCOME STATEMENT | G6: restated | J6: restated | L6: restated | N6: restated | BF6: restated | BG6: Restated | BH6: Restated | BI6: Restated | BJ6: Restated | BK6: Restated | BL6: Restated
B7: Net Sales (LFL) | C7: 96287.4 | D7: 93586.2 | E7: 98548.7 | F7: 101492.18 | G7: 101757.18 | H7: 97361.634 | I7: 103521.82 | J7: 73915.4 | K7: 75526.609 | L7: 68615.768 | M7: 73767.9 | N7: 66222.836 | O7: 62260.864 | P7: 58878.15 | Q7: =SUM(AZ7:BC7) -> 58417.05 | S7: 21954.3 | T7: 22976.8 | U7: 22663 | V7: 25992.1 | W7: 22812 | X7: 24978.3 | Y7: 24023.1 | Z7: 26735.3 | AA7: 23395.2 | AB7: 24307.6 | AC7: 25786.149 | AD7: =F7-AA7-AB7-AC7 -> 28003.232 | AE7: 23228.8 | AF7: 22407.2 | AG7: 23943 | AH7: =H7-AE7-AF7-AG7 -> 27782.634 | AI7: 23828.9 | AJ7: 24753.2 | AK7: 26127.867 | AL7: =I7-AI7-AJ7-AK7 -> 28811.856 | AM7: 18609.2 | AN7: 18533.5 | AO7: 19251.7 | AP7: =K7-AM7-AN7-AO7 -> 19132.209 | AQ7: 18519.633 | AR7: 18520.2 | AS7: 16416 | AT7: =M7-AQ7-AR7-AS7 -> 20312.067 | AU7: 15951.4 | AV7: 15720.3 | AW7: 15362.8 | AX7: =O7-SUM(AU7:AW7) -> 15226.364 | AY7: 14973.6 | AZ7: 14729.4 | BA7: 14627.086 | BB7: =P7-SUM(AY7:BA7) -> 14548.064 | BC7: 14512.5 | BF7: =G7-AA7-AB7-AC7 -> 28268.232 | BG7: 18022.3 | BH7: 18473.9 | BI7: 18590.1 | BJ7: =J7-BG7-BH7-BI7 -> 18829.1 | BK7: 16753.3 | BL7: 16693.7
B8: Non-Recurring Licensing revenues | C8: 0 | D8: 0 | E8: 2733.6 | F8: 0 | G8: 0 | H8: 0 | I8: 0 | J8: 0 | K8: 0 | L8: 0 | M8: 0 | N8: 0 | O8: 0 | P8: 0 | Q8: =SUM(AZ8:BC8) -> 0 | S8: 0 | T8: 0 | U8: 0 | V8: =D8-U8-T8-S8 -> 0 | W8: 0 | X8: 1723.5 | Y8: 1010.1 | Z8: =E8-Y8-X8-W8 -> 0 | AA8: 0 | AB8: 0 | AC8: 0 | AD8: =F8-AA8-AB8-AC8 -> 0 | AE8: 0 | AF8: 0 | AG8: 0 | AH8: =H8-AE8-AF8-AG8 -> 0 | AI8: 0 | AJ8: 0 | AK8: 0 | AL8: =I8-AI8-AJ8-AK8 -> 0 | AM8: 0 | AN8: 0 | AO8: 0 | AP8: =K8-AM8-AN8-AO8 -> 0 | AQ8: 0 | AR8: 0 | AS8: 0 | AT8: =M8-AQ8-AR8-AS8 -> 0 | AU8: 0 | AV8: 0 | AW8: 0 | AX8: =S8-AU8-AV8-AW8 -> 0 | AY8: 0 | AZ8: 0 | BA8: 0 | BB8: =P8-SUM(AY8:BA8) -> 0 | BC8: 0 | BF8: =G8-AA8-AB8-AC8 -> 0 | BG8: 0 | BH8: 0 | BI8: 0 | BJ8: =J8-BG8-BH8-BI8 -> 0 | BK8: 0 | BL8: 0
B9: Net Sales including non-recurring licensing revenues | C9: =+C7+C8 -> 96287.4 | D9: =+D7+D8 -> 93586.2 | E9: =+E7+E8 -> 101282.3 | F9: =+F7+F8 -> 101492.18 | G9: =+G7+G8 -> 101757.18 | H9: =+H7+H8 -> 97361.634 | I9: =+I7+I8 -> 103521.82 | J9: =+J7+J8 -> 73915.4 | ... Q9: =+Q7+Q8 -> 58417.05 | S9: =+S7+S8 -> 21954.3 | T9: =+T7+T8 -> 22976.8 | U9: =+U7+U8 -> 22663 | V9: =+V7+V8 -> 25992.1 | W9: =+W7+W8 -> 22812 | X9: =+X7+X8 -> 26701.8 | Y9: =+Y7+Y8 -> 25033.2 | Z9: =+Z7+Z8 -> 26735.3 | ... BC9: =+BC7+BC8 -> 14512.5 | BF9: =+BF7+BF8 -> 28268.232 | BG9: =+BG7+BG8 -> 18022.3 | BH9: =+BH7+BH8 -> 18473.9 | BI9: =+BI7+BI8 -> 18590.1 | BJ9: =+BJ7+BJ8 -> 18829.1 | BK9: =+BK7+BK8 -> 16753.3 | BL9: =+BL7+BL8 -> 16693.7
B10: % y-o-y growth (LFL sales) | D10: =D7/C7-1 -> -0.028053515 | E10: =E7/D7-1 -> 0.05302598 | F10: =F7/E7-1 -> 0.029868288 | G10: =G7/E7-1 -> 0.032557314 | H10: =H7/G7-1 -> -0.043196431 | I10: =I7/H7-1 -> 0.063271216 | J10: =J7/H7-1 -> -0.24081595 | K10: =K7/J7-1 -> 0.021798015 | L10: =L7/J7-1 -> -0.071698618 | M10: =M7/K7-1 -> -0.023285952 | N10: =N7/L7-1 -> -0.034874375 | O10: =O7/N7-1 -> -0.059827882 | P10: =P7/O7-1 -> -0.054331305 | W10: =W7/S7-1 -> 0.039067518 | X10: =X7/T7-1 -> 0.087109606 | Y10: =Y7/U7-1 -> 0.06001412 | Z10: =Z7/V7-1 -> 0.028593303 | AA10: =AA7/W7-1 -> 0.025565492 | AB10: =AB7/X7-1 -> -0.026851307 | AC10: =AC7/Y7-1 -> 0.073389737 | AD10: =AD7/Z7-1 -> 0.047425389 | ... AG10: =AG7/AC7-1 -> -0.071478258 | AH10: =AH7/BF7-1 -> -0.017178223 | AI10: =AI7/AE7-1 -> 0.025834309 | AJ10: =AJ7/AF7-1 -> 0.10469849 | AK10: =AK7/AG7-1 -> 0.091252851 | AL10: =AL7/AH7-1 -> 0.037045516 | AM10: =AM7/BG7-1 -> 0.032565211 | AN10: =AN7/AJ7-1 -> -0.25126852 | AO10: =AO7/AK7-1 -> -0.26317368 | AP10: =AP7/AL7-1 -> -0.33596055 | AQ10: =AQ7/AM7-1 -> -0.0048130495 | AR10: =AR7/AN7-1 -> -0.00071761945 | AS10: =AS7/AO7-1 -> -0.14729608 | AT10: =AT7/AP7-1 -> 0.061668676 | AU10: =AU7/BK7-1 -> -0.047865197 | AV10: =AV7/AR7-1 -> -0.15118087 | AW10: =AW7/AS7-1 -> -0.06415692 | AX10: =AX7/AT7-1 -> -0.25037841 | AY10: =AY7/AU7-1 -> -0.061298695 | AZ10: =AZ7/AV7-1 -> -0.063033148 | BA10: =BA7/AW7-1 -> -0.047889317 | BB10: =BB7/AX7-1 -> -0.044547733 | BC10: =BC7/AY7-1 -> -0.030794198 | BL10: =BL7/BH7-1 -> -0.096362977
B11: % y-o-y growth | D11: =D9/C9-1 -> -0.028053515 | E11: =E9/D9-1 -> 0.082235415 | F11: =F9/E9-1 -> 0.0020722377 | G11: =G9/E9-1 -> 0.004688687 | H11: =H9/G9-1 -> -0.043196431 | I11: =I9/H9-1 -> 0.063271216 | J11: =J9/H9-1 -> -0.24081595 | K11: =K9/J9-1 -> 0.021798015 | L11: =L9/J9-1 -> -0.071698618 | M11: =M9/K9-1 -> -0.023285952 | N11: =N9/L9-1 -> -0.034874375 | O11: =O9/N9-1 -> -0.059827882 | P11: =P9/O9-1 -> -0.054331305 | W11: =W9/S9-1 -> 0.039067518 | X11: =X9/T9-1 -> 0.16212005 | Y11: =Y9/U9-1 -> 0.10458457 | Z11: =Z9/V9-1 -> 0.028593303 | AA11: =AA9/W9-1 -> 0.025565492 | AB11: =AB9/X9-1 -> -0.089664367 | AC11: =AC9/Y9-1 -> 0.030078016 | AD11: =AD9/Z9-1 -> 0.047425389 | ... AG11: =AG9/AC9-1 -> -0.071478258 | AH11: =AH9/BF9-1 -> -0.017178223 | AI11: =AI9/AE9-1 -> 0.025834309 | AJ11: =AJ9/AF9-1 -> 0.10469849 | AK11: =AK9/AG9-1 -> 0.091252851 | AL11: =AL9/AH9-1 -> 0.037045516 | AM11: =AM9/BG9-1 -> 0.032565211 | AN11: =AN9/AJ9-1 -> -0.25126852 | AO11: =AO9/AK9-1 -> -0.26317368 | AP11: =AP9/AL9-1 -> -0.33596055 | AQ11: =AQ9/AM9-1 -> -0.0048130495 | AR11: =AR9/AN9-1 -> -0.00071761945 | AS11: =AS9/AO9-1 -> -0.14729608 | AT11: =AT9/AP9-1 -> 0.061668676 | AU11: =AU9/BK9-1 -> -0.047865197 | AV11: =AV9/AR9-1 -> -0.15118087 | AW11: =AW9/AS9-1 -> -0.06415692 | AX11: =AX9/AT9-1 -> -0.25037841 | AY11: =AY9/AU9-1 -> -0.061298695 | AZ11: =AZ9/AV9-1 -> -0.063033148 | BA11: =BA9/AW9-1 -> -0.047889317 | BB11: =BB9/AX9-1 -> -0.044547733 | BC11: =BC9/AY9-1 -> -0.030794198 | BL11: =BL9/BH9-1 -> -0.096362977
B12: COGS | C12: -52377.79 | D12: -52983.38 | E12: -57839.268 | F12: -58725.362 | G12: -59067.362 | H12: -56989.655 | I12: -59561.521 | J12: -46653.6 | K12: -48807.606 | L12: -43357.747 | M12: -48893.6 | N12: -43297.44 | O12: -41117.033 | P12: -36394.735 | Q12: =SUM(AZ12:BC12) -> -36021.235 | S12: -12655.512 | T12: -12820.791 | U12: -12592.025 | V12: =D12-U12-T12-S12 -> -14915.052 | W12: -13060.608 | X12: -15079.753 | Y12: -14208.501 | Z12: =E12-Y12-X12-W12 -> -15490.406 | AA12: -13264.015 | AB12: -13815.4 | AC12: -14946.51 | AD12: =F12-AA12-AB12-AC12 -> -16699.437 | AE12: -13738 | AF12: -13941.8 | AG12: -13871 | AH12: =H12-AE12-AF12-AG12 -> -15438.855 | AI12: -13884.6 | AJ12: -14545.3 | AK12: -15358.168 | AL12: =I12-AI12-AJ12-AK12 -> -15773.453 | AM12: -11826.9 | AN12: -11848.2 | AO12: -12229.1 | AP12: =K12-AM12-AN12-AO12 -> -12903.406 | AQ12: -12081.971 | AR12: -12123.8 | AS12: -11071.6 | AT12: =M12-AQ12-AR12-AS12 -> -13616.229 | AU12: -10411.9 | AV12: -10506.6 | AW12: -9944.3 | AX12: =O12-SUM(AU12:AW12) -> -10254.233 | AY12: -9215.4 | AZ12: -9019.7 | BA12: -9258.735 | BB12: =P12-SUM(AY12:BA12) -> -8900.9 | BC12: -8841.9 | BF12: =G12-AA12-AB12-AC12 -> -17041.437 | BG12: -11383.2 | BH12: -11899.8 | BI12: -11505.9 | BJ12: =J12-BG12-BH12-BI12 -> -11864.7 | BK12: -10714.7 | BL12: -10797.7
B13: Gross Profit | C13: =C9+C12 -> 43909.61 | D13: =D9+D12 -> 40602.82 | E13: =E9+E12 -> 43443.032 | F13: =F9+F12 -> 42766.819 | G13: =G9+G12 -> 42689.819 | H13: =H9+H12 -> 40371.979 | I13: =I9+I12 -> 43960.302 | J13: =J9+J12 -> 27261.8 | ... Q13: =Q9+Q12 -> 22395.815 | S13: =S9+S12 -> 9298.788 | T13: =T9+T12 -> 10156.009 | U13: =U9+U12 -> 10070.975 | V13: =V9+V12 -> 11077.048 | W13: =W9+W12 -> 9751.392 | X13: =X9+X12 -> 11622.047 | Y13: =Y9+Y12 -> 10824.699 | Z13: =Z9+Z12 -> 11244.894 | ... BC13: =BC9+BC12 -> 5670.6 | BF13: =BF9+BF12 -> 11226.795 | BG13: =BG9+BG12 -> 6639.1 | BH13: =BH9+BH12 -> 6574.1 | BI13: =BI9+BI12 -> 7084.2 | BJ13: =BJ9+BJ12 -> 6964.4 | BK13: =BK9+BK12 -> 6038.6 | BL13: =BL9+BL12 -> 5896
B14: Gross Profit margin | C14: =C13/C9 -> 0.45602654 | D14: =D13/D9 -> 0.43385478 | E14: =E13/E9 -> 0.42893015 | F14: =F13/F9 -> 0.42138043 | G14: =G13/G9 -> 0.41952635 | H14: =H13/H9 -> 0.41466004 | I14: =I13/I9 -> 0.42464768 | J14: =J13/J9 -> 0.36882436 | ... Q14: =Q13/Q9 -> 0.38337805 | S14: =S13/S9 -> 0.42355201 | T14: =T13/T9 -> 0.44201146 | U14: =U13/U9 -> 0.44437961 | V14: =V13/V9 -> 0.4261698 | W14: =W13/W9 -> 0.42746765 | X14: =X13/X9 -> 0.43525332 | Y14: =Y13/Y9 -> 0.43241371 | Z14: =Z13/Z9 -> 0.420601 | ... BC14: =BC13/BC9 -> 0.39073902 | BF14: =BF13/BF9 -> 0.39715236 | BG14: =BG13/BG9 -> 0.3683825 | BH14: =BH13/BH9 -> 0.35585881 | BI14: =BI13/BI9 -> 0.3810738 | BJ14: =BJ13/BJ9 -> 0.36987429 | BK14: =BK13/BK9 -> 0.36044242 | BL14: =BL13/BL9 -> 0.35318713
B15: Distribution costs | C15: -10900.695 | D15: -10446.596 | E15: -11023.466 | F15: -11193.011 | G15: -11099.011 | H15: -10366.582 | I15: -10460.246 | J15: -8099.6 | K15: -9422.916 | L15: -9155.448 | M15: -9146.9 | N15: -8848.181 | O15: -8815.211 | P15: -7721.811 | Q15: =SUM(AZ15:BC15) -> -7453.011 | S15: -2607.368 | T15: -2490.263 | U15: -2472.521 | V15: =D15-U15-T15-S15 -> -2876.444 | W15: -2581.37 | X15: -2846.36 | Y15: -2609.679 | Z15: =E15-Y15-X15-W15 -> -2986.057 | AA15: -2764.384 | AB15: -2782.6 | AC15: -2797.238 | AD15: =F15-AA15-AB15-AC15 -> -2848.789 | AE15: -2718 | AF15: -2538.4 | AG15: -2312.3 | AH15: =H15-AE15-AF15-AG15 -> -2797.882 | AI15: -2522.6 | AJ15: -2571.9 | AK15: -2642.442 | AL15: =I15-AI15-AJ15-AK15 -> -2723.304 | AM15: -2133.2 | AN15: -2097.8 | AO15: -2462.4 | AP15: =K15-AM15-AN15-AO15 -> -2729.516 | AQ15: -2238.488 | AR15: -2212.9 | AS15: -2065.7 | AT15: =M15-AQ15-AR15-AS15 -> -2629.812 | AU15: -2354.9 | AV15: -2199.1 | AW15: -2131.4 | AX15: =O15-SUM(AU15:AW15) -> -2129.811 | AY15: -2029.4 | AZ15: -2247.9 | BA15: -1655.117 | BB15: =P15-SUM(AY15:BA15) -> -1789.394 | BC15: -1760.6 | BF15: =G15-AA15-AB15-AC15 -> -2754.789 | BG15: -1977.1 | BH15: -1970.6 | BI15: -2034.5 | BJ15: =J15-BG15-BH15-BI15 -> -2117.4 | BK15: -2162.8 | BL15: -2135.5
B16: Administrative expenses | C16: -13273.397 | D16: -13459.487 | E16: -13729.325 | F16: -13269.191 | G16: -13269.191 | H16: -12713.657 | I16: -13710.793 | J16: -12189.5 | K16: -12061.932 | L16: -11341.657 | M16: -12196.9 | N16: -11305.619 | O16: -10592.581 | P16: -9522.888 | Q16: =SUM(AZ16:BC16) -> -9170.988 | S16: -3250.568 | T16: -3375.039 | U16: -3419.804 | V16: =D16-U16-T16-S16 -> -3414.076 | W16: -3391.751 | X16: -3391.337 | Y16: -3440.751 | Z16: =E16-Y16-X16-W16 -> -3505.486 | AA16: -3707.54 | AB16: -3316.6 | AC16: -3057.286 | AD16: =F16-AA16-AB16-AC16 -> -3187.765 | AE16: -3631.1 | AF16: -2940.3 | AG16: -2856.6 | AH16: =H16-AE16-AF16-AG16 -> -3285.657 | AI16: -3728.3 | AJ16: -3251.4 | AK16: -3002.365 | AL16: =I16-AI16-AJ16-AK16 -> -3728.728 | AM16: -2843.4 | AN16: -2994.9 | AO16: -2906.7 | AP16: =K16-AM16-AN16-AO16 -> -3316.932 | AQ16: -2813.247 | AR16: -3010.1 | AS16: -2933.7 | AT16: =M16-AQ16-AR16-AS16 -> -3439.853 | AU16: -2551.9 | AV16: -2395.5 | AW16: -2603.1 | AX16: =O16-SUM(AU16:AW16) -> -3042.081 | AY16: -2640.1 | AZ16: -2234.2 | BA16: -2740.685 | BB16: =P16-SUM(AY16:BA16) -> -1907.903 | BC16: -2288.2 | BF16: =G16-AA16-AB16-AC16 -> -3187.765 | BG16: -2764.3 | BH16: -2666.5 | BI16: -2972.1 | BJ16: =J16-BG16-BH16-BI16 -> -3786.6 | BK16: -2584.2 | BL16: -2772.7
B17: Other income | C17: 0 | D17: 0 | E17: 1562.284 | F17: 0 | G17: 0 | H17: 233.628 | I17: 2393.963 | J17: 3716.2 | K17: 0 | L17: 0 | M17: 0 | N17: 0 | O17: 0 | P17: 0 | Q17: =SUM(AZ17:BC17) -> 0 | S17: 0 | T17: 0 | U17: 0 | V17: =D17-U17-T17-S17 -> 0 | W17: 0 | X17: 3237.923 | Y17: 0 | Z17: =E17-Y17-X17-W17 -> -1675.639 | AA17: 0 | AB17: 0 | AC17: 0 | AD17: =F17-AA17-AB17-AC17 -> 0 | AE17: 284.9 | AF17: 0 | AG17: 666 | AH17: =H17-AE17-AF17-AG17 -> -717.272 | AI17: 0 | AJ17: 0 | AK17: 0 | AL17: =I17-AI17-AJ17-AK17 -> 2393.963 | AM17: 0 | AN17: 0 | AO17: 0 | AP17: =K17-AM17-AN17-AO17 -> 0 | AQ17: 0 | AR17: 0 | AS17: 0 | AT17: =M17-AQ17-AR17-AS17 -> 0 | AU17: 2293.2 | AV17: 0 | AW17: 0 | AX17: =O17-SUM(AU17:AW17) -> -2293.2 | AY17: 0 | AZ17: 0 | BA17: 0 | BB17: =P17-SUM(AY17:BA17) -> 0 | BC17: 0 | BF17: =G17-AA17-AB17-AC17 -> 0 | BG17: 0 | BH17: 0 | BI17: 0 | BJ17: =J17-BG17-BH17-BI17 -> 3716.2 | BK17: 0 | BL17: 0
B18: Other expense | C18: -3137.384 | D18: -2453.572 | E18: 0 | F18: -1095.587 | G18: -1316.587 | H18: 0 | I18: 0 | J18: 0 | K18: =-846.654 -> -846.654 | L18: -1023.169 | M18: =-866.8 -> -866.8 | N18: -913.801 | O18: -4554.9 | P18: -1013.824 | Q18: =SUM(AZ18:BC18) -> -894.524 | S18: -410.743 | T18: -385.606 | U18: -500.501 | V18: =D18-U18-T18-S18 -> -1156.722 | W18: -154.086 | X18: 0 | Y18: -432.463 | Z18: =E18-Y18-X18-W18 -> 586.549 | AA18: -188.91 | AB18: -283 | AC18: -389.362 | AD18: =F18-AA18-AB18-AC18 -> -234.315 | AE18: 0 | AF18: -293.5 | AG18: 0 | AH18: =H18-AE18-AF18-AG18 -> 293.5 | AI18: -152.9 | AJ18: -398.9 | AK18: -293.662 | AL18: =I18-AI18-AJ18-AK18 -> 845.462 | AM18: -168.3 | AN18: -40.9 | AO18: -291.2 | AP18: =K18-AM18-AN18-AO18 -> -346.254 | AQ18: -182.18 | AR18: -181.2 | AS18: -726.6 | AT18: =M18-AQ18-AR18-AS18 -> 223.18 | AU18: 0 | AV18: -529.6 | AW18: -319.3 | AX18: =O18-SUM(AU18:AW18) -> -3706 | AY18: -198.7 | AZ18: -274.2 | BA18: -43.754 | BB18: =P18-SUM(AY18:BA18) -> -497.17 | BC18: -79.4 | BF18: =G18-AA18-AB18-AC18 -> -455.315 | BG18: -77.6 | BH18: -278.3 | BI18: -232.3 | BJ18: =J18-BG18-BH18-BI18 -> 588.2 | BK18: -179.2 | BL18: -194.8
B19: Operating Profit | C19: =C13+SUM(C15:C18) -> 16598.134 | D19: =D13+SUM(D15:D18) -> 14243.165 | E19: =E13+SUM(E15:E18) -> 20252.525 | F19: =F13+SUM(F15:F18) -> 17209.03 | G19: =G13+SUM(G15:G18) -> 17005.03 | H19: =H13+SUM(H15:H18) -> 17525.368 | I19: =I13+SUM(I15:I18) -> 22183.226 | J19: =J13+SUM(J15:J18) -> 10688.9 | ... Q19: =Q13+SUM(Q15:Q18) -> 4877.292 | S19: =S13+SUM(S15:S18) -> 3030.109 | T19: =T13+SUM(T15:T18) -> 3905.101 | U19: =U13+SUM(U15:U18) -> 3678.149 | V19: =V13+SUM(V15:V18) -> 3629.806 | W19: =W13+SUM(W15:W18) -> 3624.185 | X19: =X13+SUM(X15:X18) -> 8622.273 | Y19: =Y13+SUM(Y15:Y18) -> 4341.806 | Z19: =Z13+SUM(Z15:Z18) -> 3664.261 | ... BC19: =BC13+SUM(BC15:BC18) -> 1542.4 | BF19: =BF13+SUM(BF15:BF18) -> 4828.926 | BG19: =BG13+SUM(BG15:BG18) -> 1820.1 | BH19: =BH13+SUM(BH15:BH18) -> 1658.7 | BI19: =BI13+SUM(BI15:BI18) -> 1845.3 | BJ19: =BJ13+SUM(BJ15:BJ18) -> 5364.8 | BK19: =BK13+SUM(BK15:BK18) -> 1112.4 | BL19: =BL13+SUM(BL15:BL18) -> 793
B20: Finance income | C20: 1499.473 | D20: 3153.54 | E20: 1787.249 | F20: 2464.403 | G20: 2464.403 | H20: 4227.192 | I20: 620.222 | J20: 560 | K20: 2151.109 | L20: 2129.011 | M20: 3307.4 | N20: 3180.192 | O20: 4117.583 | P20: 3226.718 | Q20: =SUM(AZ20:BC20) -> 2178.218 | S20: 1504.788 | T20: 1116.156 | U20: 392.16 | V20: =D20-U20-T20-S20 -> 140.436 | W20: 1297.85 | X20: 1065.149 | Y20: 436.195 | Z20: =E20-Y20-X20-W20 -> -1011.945 | AA20: 435.445 | AB20: 674 | AC20: 920.723 | AD20: =F20-AA20-AB20-AC20 -> 434.235 | AE20: 2422 | AF20: 2803 | AG20: 3353.1 | AH20: =H20-AE20-AF20-AG20 -> -4350.908 | AI20: 121.3 | AJ20: 2156.7 | AK20: 186.032 | AL20: =I20-AI20-AJ20-AK20 -> -1843.81 | AM20: 338.9 | AN20: 1146 | AO20: 1283.4 | AP20: =K20-AM20-AN20-AO20 -> -617.191 | AQ20: 883.42 | AR20: 1318.3 | AS20: 905.4 | AT20: =M20-AQ20-AR20-AS20 -> 200.28 | AU20: 777.8 | AV20: 1282.7 | AW20: 1100.4 | AX20: =O20-SUM(AU20:AW20) -> 956.683 | AY20: 1421.3 | AZ20: 1224.4 | BA20: 1159.194 | BB20: =P20-SUM(AY20:BA20) -> -578.176 | BC20: 372.8 | BF20: =G20-AA20-AB20-AC20 -> 434.235 | BG20: 181.1 | BH20: 1796 | BI20: 204 | BJ20: =J20-BG20-BH20-BI20 -> -1621.1 | BK20: 885.2 | BL20: 1293.6
B21: Finance costs | C21: -11031.585 | D21: -9245.671 | E21: -10566.966 | F21: -11275.198 | G21: -11275.198 | H21: -10482.168 | I21: -12290.187 | J21: =-12478 -> -12478 | K21: -11346.39 | L21: -11385.381 | M21: -7931.7 | N21: -8026.093 | O21: -8812.754 | P21: -7508.6 | Q21: =SUM(AZ21:BC21) -> -7669 | S21: -2286.444 | T21: -2258.077 | U21: -2313.831 | V21: =D21-U21-T21-S21 -> -2387.319 | W21: -3498.519 | X21: -2840.369 | Y21: -2925.538 | Z21: =E21-Y21-X21-W21 -> -1302.54 | AA21: -2709.535 | AB21: -2942.5 | AC21: -3790.923 | AD21: =F21-AA21-AB21-AC21 -> -1832.24 | AE21: -11129.6 | AF21: -2891.9 | AG21: -3043.5 | AH21: =H21-AE21-AF21-AG21 -> 6582.832 | AI21: -4142.9 | AJ21: -2810.1 | AK21: -5078.375 | AL21: =I21-AI21-AJ21-AK21 -> -258.812 | AM21: -5228.6 | AN21: -2214.9 | AO21: -2306.6 | AP21: =K21-AM21-AN21-AO21 -> -1596.29 | AQ21: -3081.995 | AR21: -2069.8 | AS21: -1549.8 | AT21: =M21-AQ21-AR21-AS21 -> -1230.105 | AU21: -1911.2 | AV21: -1872.7 | AW21: -2359.7 | AX21: =O21-SUM(AU21:AW21) -> -2669.154 | AY21: -1850 | AZ21: -2896.8 | BA21: -1834.533 | BB21: =P21-SUM(AY21:BA21) -> -927.267 | BC21: -2010.4 | BF21: =G21-AA21-AB21-AC21 -> -1832.24 | BG21: -3797.1 | BH21: -2802.3 | BI21: -4702.7 | BJ21: =J21-BG21-BH21-BI21 -> -1175.9 | BK21: -3039.9 | BL21: -2123.9
B22: Share of profit (loss) of associates and joint ventures accounted for using equity method | C22: 1139.604 | D22: 1913.273 | E22: 532.933 | F22: 581.023 | G22: 581.023 | H22: -5739.668 | I22: 3558.811 | J22: 3671 | K22: -8453.302 | L22: -7378.249 | M22: -6210.1 | N22: -4086.628 | O22: -182.577 | P22: -578.343 | Q22: =SUM(AZ22:BC22) -> 669.557 | S22: 263.71 | T22: 86.956 | U22: 670.041 | V22: =D22-U22-T22-S22 -> 892.566 | W22: 107.096 | X22: 477.188 | Y22: 326.609 | Z22: =E22-Y22-X22-W22 -> -377.96 | AA22: 165.821 | AB22: 163.8 | AC22: 159.917 | AD22: =F22-AA22-AB22-AC22 -> 91.485 | AE22: -5348.6 | AF22: 137.6 | AG22: -119.9 | AH22: =H22-AE22-AF22-AG22 -> -408.768 | AI22: 51.8 | AJ22: 889.2 | AK22: 1240.248 | AL22: =I22-AI22-AJ22-AK22 -> 1377.563 | AM22: 465.4 | AN22: 4218.6 | AO22: 575.7 | AP22: =K22-AM22-AN22-AO22 -> -13713.002 | AQ22: 96.756 | AR22: 24.9 | AS22: 588.8 | AT22: =M22-AQ22-AR22-AS22 -> -6920.556 | AU22: -356.6 | AV22: 338.3 | AW22: 1736.1 | AX22: =O22-SUM(AU22:AW22) -> -1900.377 | AY22: 91.2 | AZ22: 1211.5 | BA22: 843.03 | BB22: =P22-SUM(AY22:BA22) -> -2724.073 | BC22: 1339.1 | BF22: =G22-AA22-AB22-AC22 -> 91.485 | BG22: 51.8 | BH22: 888.4 | BI22: 1240.2 | BJ22: =J22-BG22-BH22-BI22 -> 1490.6 | BK22: 96.756 | BL22: 24.8
B23: Profit before tax | C23: =SUM(C19,C20,C21,C22) -> 8205.626 | D23: =SUM(D19,D20,D21,D22) -> 10064.307 | E23: =SUM(E19,E20,E21,E22) -> 12005.741 | F23: =SUM(F19,F20,F21,F22) -> 8979.258 | G23: =SUM(G19,G20,G21,G22) -> 8775.258 | H23: =SUM(H19,H20,H21,H22) -> 5530.724 | I23: =SUM(I19,I20,I21,I22) -> 14072.072 | J23: =SUM(J19,J20,J21,J22) -> 2441.9 | ... Q23: =SUM(Q19,Q20,Q21,Q22) -> 56.067 | S23: =SUM(S19,S20,S21,S22) -> 2512.163 | T23: =SUM(T19,T20,T21,T22) -> 2850.136 | U23: =SUM(U19,U20,U21,U22) -> 2426.519 | V23: =SUM(V19,V20,V21,V22) -> 2275.489 | W23: =SUM(W19,W20,W21,W22) -> 1530.612 | X23: =SUM(X19,X20,X21,X22) -> 7324.241 | Y23: =SUM(Y19,Y20,Y21,Y22) -> 2179.072 | Z23: =SUM(Z19,Z20,Z21,Z22) -> 971.816 | ... BC23: =SUM(BC19,BC20,BC21,BC22) -> 1243.9 | BF23: =SUM(BF19,BF20,BF21,BF22) -> 3522.406 | BG23: =SUM(BG19,BG20,BG21,BG22) -> -1744.1 | BH23: =SUM(BH19,BH20,BH21,BH22) -> 1540.8 | BI23: =SUM(BI19,BI20,BI21,BI22) -> -1413.2 | BJ23: =SUM(BJ19,BJ20,BJ21,BJ22) -> 4058.4 | BK23: =SUM(BK19,BK20,BK21,BK22) -> -945.544 | BL23: =SUM(BL19,BL20,BL21,BL22) -> -12.5
B24: Tax income (expenses) | C24: -2872.235 | D24: -4037.931 | E24: -4390.504 | F24: -2776.445 | G24: -2668.445 | H24: -5227.9 | I24: -7493.818 | J24: -1673 | K24: 967.377 | L24: 1352.889 | M24: -2440.9 | N24: -2360.634 | O24: -688.587 | P24: -7926.381 | Q24: =SUM(AZ24:BC24) -> -7891.981 | S24: -798.013 | T24: -968.583 | U24: -906.006 | V24: =D24-U24-T24-S24 -> -1365.329 | W24: -535.715 | X24: -2563.5 | Y24: -699.487 | Z24: =E24-Y24-X24-W24 -> -591.802 | AA24: -503.987 | AB24: -741.9 | AC24: -726.784 | AD24: =F24-AA24-AB24-AC24 -> -803.774 | AE24: 1725.9 | AF24: -752.5 | AG24: -2119.2 | AH24: =H24-AE24-AF24-AG24 -> -4082.1 | AI24: 103.5 | AJ24: -1800 | AK24: -111.462 | AL24: =I24-AI24-AJ24-AK24 -> -5685.856 | AM24: 878.1 | AN24: -1510.9 | AO24: -351.5 | AP24: =K24-AM24-AN24-AO24 -> 1951.677 | AQ24: 187.965 | AR24: -93.1 | AS24: -869 | AT24: =M24-AQ24-AR24-AS24 -> -1666.765 | AU24: -541 | AV24: 84.2 | AW24: -171 | AX24: =O24-SUM(AU24:AW24) -> -60.787 | AY24: -221 | AZ24: 60 | BA24: -3008.176 | BB24: =P24-SUM(AY24:BA24) -> -4757.205 | BC24: -186.6 | BF24: =G24-AA24-AB24-AC24 -> -695.774 | BG24: 762.9 | BH24: -419.6 | BI24: -5 | BJ24: =J24-BG24-BH24-BI24 -> -2011.3 | BK24: 232.2 | BL24: -50.8
B25: Profit (loss) from Continuing Operations | C25: =C23+C24 -> 5333.391 | D25: =D23+D24 -> 6026.376 | E25: =E23+E24 -> 7615.237 | F25: =F23+F24 -> 6202.813 | G25: =G23+G24 -> 6106.813 | H25: =H23+H24 -> 302.824 | I25: =I23+I24 -> 6578.254 | J25: =J23+J24 -> 768.9 | ... Q25: =Q23+Q24 -> -7835.914 | S25: =S23+S24 -> 1714.15 | T25: =T23+T24 -> 1881.553 | U25: =U23+U24 -> 1520.513 | V25: =V23+V24 -> 910.16 | W25: =W23+W24 -> 994.897 | X25: =X23+X24 -> 4760.741 | Y25: =Y23+Y24 -> 1479.585 | Z25: =Z23+Z24 -> 380.014 | ... BC25: =BC23+BC24 -> 1057.3 | BF25: =BF23+BF24 -> 2826.632 | BG25: =BG23+BG24 -> -981.2 | BH25: =BH23+BH24 -> 1121.2 | BI25: =BI23+BI24 -> -1418.2 | BJ25: =BJ23+BJ24 -> 2047.1 | BK25: =BK23+BK24 -> -713.344 | BL25: =BL23+BL24 -> -63.3
B26: Discontinued Operations | C26: 0 | D26: 0 | E26: 0 | F26: 0 | G26: 0 | H26: 0 | I26: 0 | J26: 6585.9 | K26: 55922.583 | L26: 56827.807 | M26: 0 | N26: 628.116 | O26: 56.816 | P26: 0 | Q26: =SUM(AZ26:BC26) -> 0 | S26: 0 | T26: 0 | U26: 0 | V26: =D26-U26-T26-S26 -> 0 | W26: 0 | X26: 0 | Y26: 0 | Z26: =E26-Y26-X26-W26 -> 0 | AA26: 0 | AB26: 0 | AC26: 0 | AD26: =F26-AA26-AB26-AC26 -> 0 | AE26: 0 | AF26: 0 | AG26: 0 | AH26: =H26-AE26-AF26-AG26 -> 0 | AI26: 0 | AJ26: 0 | AK26: 0 | AL26: =I26-AI26-AJ26-AK26 -> 0 | AM26: 54765.4 | AN26: 98.9 | AO26: 739.4 | AP26: =K26-AM26-AN26-AO26 -> 318.883 | AQ26: 0 | AR26: 0 | AS26: 0 | AT26: =M26-AQ26-AR26-AS26 -> 0 | AU26: 56.8 | AV26: 0 | AW26: 0 | AX26: =O26-SUM(AU26:AW26) -> 0.016 | AY26: 0 | AZ26: 0 | BA26: 0 | BB26: =P26-SUM(AY26:BA26) -> 0 | BC26: 0 | BF26: =G26-AA26-AB26-AC26 -> 0 | BG26: 655.4 | BH26: 1300.4 | BI26: 2485.9 | BJ26: =J26-BG26-BH26-BI26 -> 2144.2 | BK26: 3.2 | BL26: 235.8
B27: Profit (loss)/Net Income | C27: =C25+C26 -> 5333.391 | D27: =D25+D26 -> 6026.376 | E27: =E25+E26 -> 7615.237 | F27: =F25+F26 -> 6202.813 | G27: =G25+G26 -> 6106.813 | H27: =H25+H26 -> 302.824 | I27: =I25+I26 -> 6578.254 | J27: =J25+J26 -> 7354.8 | ... Q27: =Q25+Q26 -> -7835.914 | S27: =S25+S26 -> 1714.15 | T27: =T25+T26 -> 1881.553 | U27: =U25+U26 -> 1520.513 | V27: =V25+V26 -> 910.16 | W27: =W25+W26 -> 994.897 | X27: =X25+X26 -> 4760.741 | Y27: =Y25+Y26 -> 1479.585 | Z27: =Z25+Z26 -> 380.014 | ... BC27: =BC25+BC26 -> 1057.3 | BF27: =BF25+BF26 -> 2826.632 | BG27: =BG25+BG26 -> -325.8 | BH27: =BH25+BH26 -> 2421.6 | BI27: =BI25+BI26 -> 1067.7 | BJ27: =BJ25+BJ26 -> 4191.3 | BK27: =BK25+BK26 -> -710.144 | BL27: =BL25+BL26 -> 172.5
B29: % of Net sales or stated otherwise
B30: =B12 -> COGS | C30: =-C12/C9 -> 0.54397346 | D30: =-D12/D9 -> 0.56614522 | E30: =-E12/E9 -> 0.57106985 | F30: =-F12/F9 -> 0.57861957 | G30: =-G12/G9 -> 0.58047365 | H30: =-H12/H9 -> 0.58533996 | I30: =-I12/I9 -> 0.57535232 | J30: =-J12/J9 -> 0.63117564 | ... Q30: =-Q12/Q9 -> 0.61662195 | S30: =-S12/S9 -> 0.57644799 | T30: =-T12/T9 -> 0.55798854 | U30: =-U12/U9 -> 0.55562039 | V30: =-V12/V9 -> 0.5738302 | W30: =-W12/W9 -> 0.57253235 | X30: =-X12/X9 -> 0.56474668 | Y30: =-Y12/Y9 -> 0.56758629 | Z30: =-Z12/Z9 -> 0.579399 | ... BC30: =-BC12/BC9 -> 0.60926098 | BF30: =-BF12/BF9 -> 0.60284764 | BG30: =-BG12/BG9 -> 0.6316175 | BH30: =-BH12/BH9 -> 0.64414119 | BI30: =-BI12/BI9 -> 0.6189262 | BJ30: =-BJ12/BJ9 -> 0.63012571 | BK30: =-BK12/BK9 -> 0.63955758 | BL30: =-BL12/BL9 -> 0.64681287
B31: =B15 -> Distribution costs | C31: =-C15/C9 -> 0.11320998 | D31: =-D15/D9 -> 0.11162539 | E31: =-E15/E9 -> 0.10883902 | F31: =-F15/F9 -> 0.11028447 | G31: =-G15/G9 -> 0.10907349 | H31: =-H15/H9 -> 0.10647502 | I31: =-I15/I9 -> 0.10104387 | J31: =-J15/J9 -> 0.10957933 | ... Q31: =-Q15/Q9 -> 0.1275828 | S31: =-S15/S9 -> 0.11876343 | T31: =-T15/T9 -> 0.10838163 | U31: =-U15/U9 -> 0.10909946 | V31: =-V15/V9 -> 0.11066609 | W31: =-W15/W9 -> 0.11315843 | X31: =-X15/X9 -> 0.10659806 | Y31: =-Y15/Y9 -> 0.10424872 | Z31: =-Z15/Z9 -> 0.11168968 | ... BC31: =-BC15/BC9 -> 0.12131611 | BF31: =-BF15/BF9 -> 0.097451761 | BG31: =-BG15/BG9 -> 0.10970298 | BH31: =-BH15/BH9 -> 0.10666941 | BI31: =-BI15/BI9 -> 0.10943997 | BJ31: =-BJ15/BJ9 -> 0.1124536 | BK31: =-BK15/BK9 -> 0.12909695 | BL31: =-BL15/BL9 -> 0.12792251
B32: General and Administrative expenses | C32: =-C16/C9 -> 0.13785186 | D32: =-D16/D9 -> 0.14381914 | E32: =-E16/E9 -> 0.13555503 | F32: =-F16/F9 -> 0.13074102 | G32: =-G16/G9 -> 0.13040054 | H32: =-H16/H9 -> 0.1305818 | I32: =-I16/I9 -> 0.1324435 | J32: =-J16/J9 -> 0.16491151 | ... Q32: =-Q16/Q9 -> 0.15699163 | S32: =-S16/S9 -> 0.14806065 | T32: =-T16/T9 -> 0.14688899 | U32: =-U16/U9 -> 0.15089812 | V32: =-V16/V9 -> 0.13135053 | W32: =-W16/W9 -> 0.14868275 | X32: =-X16/X9 -> 0.1270078 | Y32: =-Y16/Y9 -> 0.13744751 | Z32: =-Z16/Z9 -> 0.13111826 | ... BC32: =-BC16/BC9 -> 0.15767097 | BF32: =-BF16/BF9 -> 0.11276846 | BG32: =-BG16/BG9 -> 0.1533822 | BH32: =-BH16/BH9 -> 0.14433877 | BI32: =-BI16/BI9 -> 0.15987542 | BJ32: =-BJ16/BJ9 -> 0.20110361 | BK32: =-BK16/BK9 -> 0.15425021 | BL32: =-BL16/BL9 -> 0.1660926
B33: =B18 -> Other expense | C33: =-C18/C9 -> 0.032583536 | D33: =-D18/D9 -> 0.026217241 | E33: =-E18/E9 -> 0 | F33: =-F18/F9 -> 0.010794792 | G33: =-G18/G9 -> 0.012938517 | H33: =-H18/H9 -> 0 | I33: =-I18/I9 -> 0 | J33: =-J18/J9 -> 0 | ... Q33: =-Q18/Q9 -> 0.015312721 | S33: =-S18/S9 -> 0.018709 | T33: =-T18/T9 -> 0.016782407 | U33: =-U18/U9 -> 0.022084499 | V33: =-V18/V9 -> 0.04450283 | W33: =-W18/W9 -> 0.0067546028 | X33: =-X18/X9 -> 0 | Y33: =-Y18/Y9 -> 0.017275578 | Z33: =-Z18/Z9 -> -0.021939122 | ... BC33: =-BC18/BC9 -> 0.0054711456 | BF33: =-BF18/BF9 -> 0.01610695 | BG33: =-BG18/BG9 -> 0.0043057767 | BH33: =-BH18/BH9 -> 0.015064496 | BI33: =-BI18/BI9 -> 0.012495898 | BJ33: =-BJ18/BJ9 -> -0.03123888 | BK33: =-BK18/BK9 -> 0.0106964 | BL33: =-BL18/BL9 -> 0.011669073
B34: =B17 -> Other income | C34: =C17/C12 -> 0 | D34: =D17/D12 -> 0 | E34: =E17/E12 -> -0.027010784 | F34: =F17/F12 -> 0 | G34: =G17/G12 -> 0 | H34: =H17/H12 -> -0.0040994809 | I34: =I17/I12 -> -0.040193114 | J34: =J17/J12 -> -0.079655161 | ... Q34: =Q17/Q12 -> 0 | S34: =S17/S12 -> 0 | T34: =T17/T12 -> 0 | U34: =U17/U12 -> 0 | V34: =V17/V12 -> 0 | W34: =W17/W12 -> 0 | X34: =X17/X12 -> -0.2147199 | Y34: =Y17/Y12 -> 0 | Z34: =Z17/Z12 -> 0.1081727 | ... AH34: =AH17/AH12 -> 0.046458886 | AI34: =AI18/AI12 -> 0.011012201 | AJ34: =AJ18/AJ12 -> 0.027424666 | AK34: =AK17/AK12 -> 0 | AL34: =AL17/AL12 -> -0.15177165 | AM34: =AM17/AM12 -> 0 | AN34: =AN18/AN12 -> 0.0034520011 | AO34: =AO17/AO12 -> 0 | AP34: =AP17/AP12 -> 0 | AQ34: =AQ17/AQ12 -> 0 | AR34: =AR18/AR12 -> 0.014945809 | AS34: =AS17/AS12 -> 0 | AT34: =AT17/AT12 -> 0 | AU34: =AU17/AU12 -> -0.22024799 | AV34: =AV18/AV12 -> 0.050406411 | AW34: =AW17/AW12 -> 0 | AX34: =AX17/AX12 -> 0.22363447 | AY34: =AY17/AY12 -> 0 | AZ34: =AZ18/AZ12 -> 0.030400124 | BA34: =BA17/BA12 -> 0 | BB34: =BB17/BB12 -> 0 | BC34: =BC17/BC12 -> 0 | BF34: =BF17/BF12 -> 0 | BG34: =BG18/BG12 -> 0.0068170637 | BH34: =BH18/BH12 -> 0.023386948 | BI34: =BI18/BI12 -> 0.020189642 | BJ34: =BJ18/BJ12 -> -0.049575632 | BK34: =BK17/BK12 -> 0 | BL34: =BL17/BL12 -> 0
B35: =B19 -> Operating Profit | C35: =C19/C9 -> 0.17238116 | D35: =D19/D9 -> 0.152193 | E35: =E19/E9 -> 0.19996115 | F35: =F19/F9 -> 0.16956016 | G35: =G19/G9 -> 0.16711381 | H35: =H19/H9 -> 0.18000281 | I35: =I19/I9 -> 0.2142855 | J35: =J19/J9 -> 0.14460992 | ... Q35: =Q19/Q9 -> 0.083490899 | S35: =S19/S9 -> 0.13801893 | T35: =T19/T9 -> 0.16995844 | U35: =U19/U9 -> 0.16229753 | V35: =V19/V9 -> 0.13965036 | W35: =W19/W9 -> 0.15887187 | X35: =X19/X9 -> 0.3229098 | Y35: =Y19/Y9 -> 0.17344191 | Z35: =Z19/Z9 -> 0.13705704 | ... BC35: =BC19/BC9 -> 0.10628079 | BF35: =BF19/BF9 -> 0.17082519 | BG35: =BG19/BG9 -> 0.10099155 | BH35: =BH19/BH9 -> 0.089786131 | BI35: =BI19/BI9 -> 0.099262511 | BJ35: =BJ19/BJ9 -> 0.28492068 | BK35: =BK19/BK9 -> 0.066398859 | BL35: =BL19/BL9 -> 0.04750295
B36: Finance Income as a % of cash at end of period | C36: =C20/C113 -> 0.031537256 | D36: =D20/D113 -> 0.081413299 | E36: =E20/E113 -> 0.055732593 | F36: =F20/F113 -> 0.089771356 | G36: =G20/G113 -> 0.08977048 | H36: =H20/H113 -> 0.14547383 | I36: =I20/I113 -> 0.024233706 | J36: =J20/J113 -> 0.021681728 | ... Q36: =Q20/Q113 -> 0.087209651 | S36: =SUM(S20:S20)/S113 -> 0.034562412 | T36: =SUM(S20:T20)/T113 -> 0.063580082 | U36: =SUM(S20:U20)/U113 -> 0.077941452 | V36: =SUM(S20:V20)/V113 -> 0.081413299 | W36: =SUM(T20:W20)/W113 -> 0.078147901 | X36: =SUM(U20:X20)/X113 -> 0.064933856 | Y36: =SUM(V20:Y20)/Y113 -> 0.069287172 | Z36: =SUM(W20:Z20)/Z113 -> 0.055732593 | AA36: =SUM(X20:AA20)/AA113 -> 0.039249818 | AB36: =SUM(Y20:AB20)/AB113 -> 0.01407494 | AC36: =SUM(Z20:AC20)/AC113 -> 0.026303252 | ... BC36: =SUM(AZ20:BC20)/BC113 -> 0.087209651 | BF36: =SUM(AA20:AC20, BF20)/AD113 -> 0.089771356 | BG36: =SUM(AF20:AH20,BG20)/AI113 -> 0.068819824 | BH36: =SUM(AG20:AI20,BH20)/AJ113 -> 0.034853931 | BI36: =SUM(AH20:AJ20,BI20)/AK113 -> -0.086105818 | BJ36: =SUM(AI20:AK20, BJ20)/AL113 -> 0.032935571 | BK36: =SUM(BH20:BK20)/AQ113 -> 0.029026732 | BL36: =SUM(BI20:BL20)/AR113 -> 0.019579316
B37: Finance costs as a % of debt at end of period | C37: =-C21/C110 -> 0.079798853 | D37: =-D21/D110 -> 0.070252175 | E37: =-E21/E110 -> 0.081367787 | F37: =-F21/F110 -> 0.085661979 | G37: =-G21/G110 -> 0.085661993 | H37: =-H21/H110 -> 0.079503526 | I37: =-I21/I110 -> 0.090720764 | J37: =-J21/J110 -> 0.092107118 | ... Q37: =-Q21/Q110 -> 0.086598809 | S37: =-SUM(S21:S21)/S110 -> 0.017808708 | T37: =-SUM(S21:T21)/T110 -> 0.036198141 | U37: =-SUM(S21:U21)/U110 -> 0.054786959 | V37: =-SUM(S21:V21)/V110 -> 0.07026611 | W37: =-SUM(T21:W21)/W110 -> 0.083896475 | X37: =-SUM(U21:X21)/X110 -> 0.084481402 | Y37: =-SUM(V21:Y21)/Y110 -> 0.09238303 | Z37: =-SUM(W21:Z21)/Z110 -> 0.081367787 | AA37: =-SUM(X21:AA21)/AA110 -> 0.073965346 | AB37: =-SUM(Y21:AB21)/AB110 -> 0.068182112 | AC37: =-SUM(Z21:AC21)/AC110 -> 0.073730855 | ... BC37: =-SUM(AZ21:BC21)/BC110 -> 0.086598809 | BF37: =-SUM(AA21:AC21,BF21)/AD110 -> 0.085661979 | BG37: =SUM(AF21:AH21,BG21)/AI110 -> -0.023529674 | BH37: =SUM(AG21:AI21,BH21)/AJ110 -> -0.025978309 | BI37: =SUM(AH21:AJ21,BI21)/AK110 -> -0.037676374 | BJ37: =-SUM(AE21:AG21,BJ21)/AH110 -> 0.13835076 | BK37: =-SUM(BH21:BK21)/AQ110 -> 0.10957736 | BL37: =-SUM(BI21:BL21)/AR110 -> 0.10705145
B38: =B23 -> Profit before tax | C38: =C23/C9 -> 0.085220143 | D38: =D23/D9 -> 0.1075405 | E38: =E23/E9 -> 0.1185374 | F38: =F23/F9 -> 0.088472411 | G38: =G23/G9 -> 0.086237236 | H38: =H23/H9 -> 0.05680599 | I38: =I23/I9 -> 0.13593339 | J38: =J23/J9 -> 0.033036417 | ... Q38: =Q23/Q9 -> 0.00095977116 | S38: =S23/S9 -> 0.11442692 | T38: =T23/T9 -> 0.12404408 | U38: =U23/U9 -> 0.10706963 | V38: =V23/V9 -> 0.087545408 | W38: =W23/W9 -> 0.067096791 | X38: =X23/X9 -> 0.27429765 | Y38: =Y23/Y9 -> 0.087047281 | Z38: =Z23/Z9 -> 0.036349545 | ... BC38: =BC23/BC9 -> 0.085712317 | BF38: =BF23/BF9 -> 0.12460652 | BG38: =BG23/BG9 -> -0.096774552 | BH38: =BH23/BH9 -> 0.083404154 | BI38: =BI23/BI9 -> -0.076018956 | BJ38: =BJ23/BJ9 -> 0.21553871 | BK38: =BK23/BK9 -> -0.056439269 | BL38: =BL23/BL9 -> -0.00074878547
B39: Income tax benefit/(expense) as a % of Profit before tax | C39: =-C24/C23 -> 0.3500324 | D39: =-D24/D23 -> 0.40121302 | E39: =-E24/E23 -> 0.36570038 | F39: =-F24/F23 -> 0.30920651 | G39: =-G24/G23 -> 0.30408736 | H39: =-H24/H23 -> 0.94524695 | I39: =-I24/I23 -> 0.53253124 | J39: =-J24/J23 -> 0.68512224 | ... Q39: =-Q24/Q23 -> 140.75982 | S39: =-S24/S23 -> 0.31765972 | T39: =-T24/T23 -> 0.33983747 | U39: =-U24/U23 -> 0.37337684 | V39: =-V24/V23 -> 0.60001564 | W39: =-W24/W23 -> 0.35000052 | X39: =-X24/X23 -> 0.35000214 | Y39: =-Y24/Y23 -> 0.32100224 | Z39: =-Z24/Z23 -> 0.60896507 | ... BC39: =-BC24/BC23 -> 0.15001206 | BF39: =-BF24/BF23 -> 0.19752805 | BG39: =-BG24/BG23 -> 0.43741758 | BH39: =-BH24/BH23 -> 0.27232606 | BI39: =-BI24/BI23 -> -0.0035380696 | BJ39: =-BJ24/BJ23 -> 0.49558939 | BK39: =-BK24/BK23 -> 0.24557292 | BL39: =-BL24/BL23 -> -4.064
B41: capex/sales | C41: =-C63/C9 -> 0.27387149 | D41: =-D63/D9 -> 0.16934222 | E41: =-E63/E9 -> 0.17253716 | F41: =-F63/F9 -> 0.17860273 | G41: =-G63/G9 -> 0.17813761 | H41: =-H63/H9 -> 0.19115662 | I41: =-I63/I9 -> 0.21826724 | J41: =-J63/J9 -> 0.30569304 | ... Q41: =-Q63/Q9 -> 0.21771656 | S41: =-S63/S9 -> 0.19874225 | T41: =-T63/T9 -> 0.13048301 | U41: =-U63/U9 -> 0.15764325 | V41: =-V63/V9 -> 0.18906118 | W41: =-W63/W9 -> 0.12477977 | X41: =-X63/X9 -> 0.14097866 | Y41: =-Y63/Y9 -> 0.20665696 | Z41: =-Z63/Z9 -> 0.21285772 | ... BC41: =-BC63/BC9 -> 0.16800496 | BF41: =-BF63/BF9 -> 0 | BG41: =-BG63/BG9 -> 0 | BH41: =-BH63/BH9 -> 0 | BI41: =-BI63/BI9 -> 0 | BJ41: =-BJ63/BJ9 -> 0 | BK41: =-BK63/BK9 -> 0 | BL41: =-BL63/BL9 -> 0
B42: D/A/sales | C42: =C46/C9 -> 0.17634533 | D42: =D46/D9 -> 0.19772963 | E42: =E46/E9 -> 0.19583386 | F42: =F46/F9 -> 0.20699679 | G42: =G46/G9 -> 0.20646008 | H42: =H46/H9 -> 0.21836925 | I42: =I46/I9 -> 0.20689714 | J42: =J46/J9 -> 0.2897687 | ... Q42: =Q46/Q9 -> 0.2904993 | S42: =S46/S9 -> 0.20696779 | T42: =T46/T9 -> 0.19927444 | U42: =U46/U9 -> 0.20338049 | V42: =V46/V9 -> 0.18363391 | W42: =W46/W9 -> 0.21045068 | X42: =X46/X9 -> 0.18156544 | Y42: =Y46/Y9 -> 0.20124487 | Z42: =Z46/Z9 -> 0.19254603 | ... BC42: =BC46/BC9 -> 0.29363652 | BF42: =BF46/BF9 -> 0.19075731 | BG42: =BG46/BG9 -> 0.25846867 | BH42: =BH46/BH9 -> 0.27568624 | BI42: =BI46/BI9 -> 0.27108515 | BJ42: =BJ46/BJ9 -> 0.35199075 | BK42: =BK46/BK9 -> 0.31177738 | BL42: =BL46/BL9 -> 0.31203388
B44: EBITDA | C44: =+C3 -> 42735 | D44: =+D3 -> 43100 | E44: =E3 -> 43465 | F44: =F3 -> 43830 | G44: =G3 -> 43830 | H44: =H3 -> 44196 | I44: =I3 -> 44561 | J44: =J3 -> 44561 | K44: =K3 -> 44926 | L44: =L3 -> 44926 | ... P44: =P3 -> 46022 | Q44: =+Q3 -> 46112 | S44: =+S3 -> 42825 | T44: =+T3 -> 42916 | U44: =+U3 -> 43008 | V44: =+V3 -> 43100 | W44: =+W3 -> 43190 | X44: =X3 -> 43281 | Y44: =Y3 -> 43373 | Z44: =Z3 -> 43465 | AA44: =+AA3 -> 43555 | AB44: =AB3 -> 43646 | AC44: =+AC3 -> 43738 | AD44: =+AD3 -> 43830 | AE44: =+AE3 -> 43921 | AF44: =+AF3 -> 44012 | AG44: =+AG3 -> 44104 | AH44: =+AH3 -> 44196 | AI44: =+AI3 -> 44286 | AJ44: =+AJ3 -> 44377 | ... BC44: =+BC3 -> 46112 | BF44: =+BF3 -> 43830 | BG44: =+BG3 -> 44286 | BH44: =+BH3 -> 44377 | BI44: =+BI3 -> 44469 | BJ44: =+BJ3 -> 44561 | BK44: =+BK3 -> 45016 | BL44: =+BL3 -> 45107
B45: Operating profit | C45: =C19 -> 16598.134 | D45: =D19 -> 14243.165 | E45: =E19 -> 20252.525 | F45: =F19 -> 17209.03 | G45: =G19 -> 17005.03 | H45: =H19 -> 17525.368 | I45: =I19 -> 22183.226 | J45: =J19 -> 10688.9 | ... Q45: =Q19 -> 4877.292 | S45: =S19 -> 3030.109 | T45: =T19 -> 3905.101 | U45: =U19 -> 3678.149 | V45: =V19 -> 3629.806 | W45: =W19 -> 3624.185 | X45: =X19 -> 8622.273 | Y45: =Y19 -> 4341.806 | Z45: =Z19 -> 3664.261 | ... BC45: =BC19 -> 1542.4 | BF45: =BF19 -> 4828.926 | BG45: =BG19 -> 1820.1 | BH45: =BH19 -> 1658.7 | BI45: =BI19 -> 1845.3 | BJ45: =BJ19 -> 5364.8 | BK45: =BK19 -> 1112.4 | BL45: =BL19 -> 793
B46: Depreciation & amortisation | C46: 16979.833 | D46: 18504.765 | E46: 19834.504 | F46: 21008.556 | G46: 21008.796 | H46: 21260.787 | I46: 21418.369 | J46: 21418.369 | K46: 21239.306 | L46: 21239.306 | M46: 21554.4 | N46: 21469.152 | O46: 20542.361 | P46: 17160.512 | Q46: =SUM(AZ46:BC46) -> 16970.112 | S46: 4543.833 | T46: =9122.522-S46 -> 4578.689 | U46: =13731.734-T46-S46 -> 4609.212 | V46: =D46-U46-T46-S46 -> 4773.031 | W46: 4800.801 | X46: =9648.925-W46 -> 4848.124 | Y46: =14686.728-X46-W46 -> 5037.803 | Z46: =E46-Y46-X46-W46 -> 5147.776 | AA46: 5215.951 | AB46: =10295.173-AA46 -> 5079.222 | AC46: =15616.424-AB46-AA46 -> 5321.251 | AD46: =F46-AA46-AB46-AC46 -> 5392.132 | AE46: 5151.5 | AF46: 5234.1 | AG46: 5235.9 | AH46: =H46-AE46-AF46-AG46 -> 5639.287 | AI46: 5169.8 | AJ46: 5224.1 | AK46: 5347.8 | AL46: =I46-AI46-AJ46-AK46 -> 5676.669 | AM46: 5077.4 | AN46: 5167.5 | AO46: 5169.8 | AP46: =K46-AM46-AN46-AO46 -> 5824.606 | AQ46: 5311.659 | AR46: 5354.7 | AS46: 5457.5 | AT46: =M46-AQ46-AR46-AS46 -> 5430.541 | AU46: 5035 | AV46: 5209 | AW46: 4907.5 | AX46: =O46-SUM(AU46:AW46) -> 5390.861 | AY46: 4451.8 | AZ46: 4402.7 | BA46: =13458.97-AZ46-AY46 -> 4604.47 | BB46: =P46-SUM(AY46:BA46) -> 3701.542 | BC46: 4261.4 | BF46: =G46-AA46-AB46-AC46 -> 5392.372 | BG46: 4658.2 | BH46: 5093 | BI46: 5039.5 | BJ46: =J46-BG46-BH46-BI46 -> 6627.669 | BK46: 5223.3 | BL46: 5209
B47: EBITDA | C47: =SUM(C45:C46) -> 33577.967 | D47: =SUM(D45:D46) -> 32747.93 | E47: =SUM(E45:E46) -> 40087.029 | F47: =SUM(F45:F46) -> 38217.586 | G47: =SUM(G45:G46) -> 38013.826 | H47: =SUM(H45:H46) -> 38786.155 | I47: =SUM(I45:I46) -> 43601.595 | J47: =SUM(J45:J46) -> 32107.269 | ... Q47: =SUM(Q45:Q46) -> 21847.404 | S47: =SUM(S45:S46) -> 7573.942 | T47: =SUM(T45:T46) -> 8483.79 | U47: =SUM(U45:U46) -> 8287.361 | V47: =SUM(V45:V46) -> 8402.837 | W47: =SUM(W45:W46) -> 8424.986 | X47: =SUM(X45:X46) -> 13470.397 | Y47: =SUM(Y45:Y46) -> 9379.609 | Z47: =SUM(Z45:Z46) -> 8812.037 | ... BC47: =SUM(BC45:BC46) -> 5803.8 | BF47: =SUM(BF45:BF46) -> 10221.298 | BG47: =SUM(BG45:BG46) -> 6478.3 | BH47: =SUM(BH45:BH46) -> 6751.7 | BI47: =SUM(BI45:BI46) -> 6884.8 | BJ47: =SUM(BJ45:BJ46) -> 11992.469 | BK47: =SUM(BK45:BK46) -> 6335.7 | BL47: =SUM(BL45:BL46) -> 6002
B48: % growth | D48: =+D47/C46-1 -> 0.92863675 | E48: =+E47/D47-1 -> 0.22410879 | F48: =+F47/E47-1 -> -0.046634611 | G48: =+G47/E47-1 -> -0.051717552 | H48: =+H47/G47-1 -> 0.020317055 | I48: =+I47/H47-1 -> 0.12415358 | J48: =+J47/H47-1 -> -0.17219768 | K48: =+K47/J47-1 -> -0.20183785 | L48: =+L47/J47-1 -> -0.22207482 | M48: =+M47/K47-1 -> -0.054970055 | N48: =+N47/L47-1 -> -0.06606488 | O48: =+O47/N47-1 -> -0.24021347 | P48: =+P47/O47-1 -> 0.20661292 | W48: =+W47/S47-1 -> 0.11236474 | X48: =+X47/T47-1 -> 0.58778058 | Y48: =+Y47/U47-1 -> 0.13179684 | Z48: =+Z47/V47-1 -> 0.048697839 | AA48: =+AA47/W47-1 -> 0.031016787 | AB48: =+AB47/X47-1 -> -0.317821 | AC48: =+AC47/Y47-1 -> 0.057293966 | AD48: =+AD47/Z47-1 -> 0.18304746 | ... AG48: =+AG47/AC47-1 -> 0.089542769 | AH48: =+AH47/BF47-1 -> 0.12272972 | AI48: =+AI47/AE47-1 -> 0.015411338 | AJ48: =+AJ47/AF47-1 -> 0.1617827 | AK48: =+AK47/AG47-1 -> -0.057933364 | AL48: =+AL47/AH47-1 -> 0.35088846 | AM48: =+AM47/AI47-1 -> -0.22909659 | AN48: =+AN47/AJ47-1 -> -0.27042933 | AO48: =+AO47/AK47-1 -> -0.35827874 | AP48: =+AP47/AL47-1 -> -0.63485117 | ... AT48: =+AT47/AP47-1 -> 0.10938333 | AU48: =+AU47/BK47-1 -> 0.25651467 | AV48: =+AV47/AR47-1 -> -0.165183 | AW48: =+AW47/AS47-1 -> 0.038672945 | AX48: =+AX47/AT47-1 -> -1.1286805 | AY48: =+AY47/AU47-1 -> -0.32899547 | AZ48: =+AZ47/AV47-1 -> 0.010871001 | BA48: =+BA47/AW47-1 -> 0.049517279 | BB48: =+BB47/AX47-1 -> -7.3782193 | BC48: =+BC47/AY47-1 -> 0.086487701 | BL48: =+BL47/BH47-1 -> -0.1110387
B49: % margin | C49: =C47/C9 -> 0.34872649 | D49: =D47/D9 -> 0.34992264 | E49: =E47/E9 -> 0.39579501 | F49: =F47/F9 -> 0.37655695 | G49: =G47/G9 -> 0.37357389 | H49: =H47/H9 -> 0.39837206 | I49: =I47/I9 -> 0.42118264 | J49: =J47/J9 -> 0.43437861 | ... Q49: =Q47/Q9 -> 0.3739902 | S49: =S47/S9 -> 0.34498672 | T49: =T47/T9 -> 0.36923288 | U49: =U47/U9 -> 0.36567802 | V49: =V47/V9 -> 0.32328427 | W49: =W47/W9 -> 0.36932255 | X49: =X47/X9 -> 0.50447524 | Y49: =Y47/Y9 -> 0.37468678 | Z49: =Z47/Z9 -> 0.32960307 | ... BC49: =BC47/BC9 -> 0.39991731 | BL49: =BL47/BL9 -> 0.35953683
B51: Adjustment | C51: =C17+C18 -> -3137.384 | D51: =D17+D18 -> -2453.572 | E51: =E17+E18 -> 1562.284 | F51: =F17+F18 -> -1095.587 | G51: =G17+G18 -> -1316.587 | H51: =H17+H18 -> 233.628 | I51: =I17+I18 -> 2393.963 | J51: =J17+J18 -> 3716.2 | ... P51: =P17+P18 -> -1013.824 | Q51: =Q52-Q47 -> 894.524 | S51: =S17+S18 -> -410.743 | T51: =T17+T18 -> -385.606 | U51: =U17+U18 -> -500.501 | V51: =V17+V18 -> -1156.722 | W51: =W17+W18 -> -154.086 | X51: =X17+X18 -> 3237.923 | Y51: =Y17+Y18 -> -432.463 | Z51: =Z17+Z18 -> -1089.09 | ... BC51: =BC17+BC18 -> -79.4 | BF51: =BF17+BF18 -> -455.315 | BG51: =BG17+BG18 -> -77.6 | BH51: =BH17+BH18 -> -278.3 | BI51: =BI17+BI18 -> -232.3 | BJ51: =BJ17+BJ18 -> 4304.4 | BK51: =BK17+BK18 -> -179.2 | BL51: =BL17+BL18 -> -194.8
B52: Adj. EBITDA | C52: =C47-C51 -> 36715.351 | D52: =D47-D51 -> 35201.502 | E52: =E47-E51 -> 38524.745 | F52: =F47-F51 -> 39313.173 | G52: =G47-G51 -> 39330.413 | H52: =H47-H51 -> 38552.527 | I52: =I47-I51 -> 41207.632 | J52: =J47-J51 -> 28391.069 | ... P52: =P47-P51 -> 22399.228 | Q52: =SUM(AZ52:BC52) -> 22741.928 | S52: =S47-S51 -> 7984.685 | T52: =T47-T51 -> 8869.396 | U52: =U47-U51 -> 8787.862 | V52: =V47-V51 -> 9559.559 | W52: =W47-W51 -> 8579.072 | X52: =X47-X51 -> 10232.474 | Y52: =Y47-Y51 -> 9812.072 | Z52: =Z47-Z51 -> 9901.127 | ... BC52: =BC47-BC51 -> 5883.2 | BF52: =BF47-BF51 -> 10676.613 | BG52: =BG47-BG51 -> 6555.9 | BH52: =BH47-BH51 -> 7030 | BI52: =BI47-BI51 -> 7117.1 | BJ52: =BJ47-BJ51 -> 7688.069 | BK52: =BK47-BK51 -> 6514.9 | BL52: =BL47-BL51 -> 6196.8
B53: % growth | D53: =+D52/C51-1 -> -12.220017 | E53: =+E52/D52-1 -> 0.094406284 | F53: =+F52/E52-1 -> 0.020465496 | G53: =+G52/E52-1 -> 0.020913 | H53: =+H52/G52-1 -> -0.019778231 | I53: =+I52/H52-1 -> 0.068869805 | J53: =+J52/H52-1 -> -0.26357437 | K53: =+K52/J52-1 -> -0.067542649 | L53: =+L52/J52-1 -> -0.084211236 | M53: =+M52/K52-1 -> -0.052451057 | N53: =+N52/L52-1 -> -0.067671499 | O53: =+O52/N52-1 -> -0.080952452 | P53: =+P52/O52-1 -> 0.0054235493 | W53: =+W52/S52-1 -> 0.074440883 | X53: =+X52/T52-1 -> 0.15368329 | Y53: =+Y52/U52-1 -> 0.11654826 | Z53: =+Z52/V52-1 -> 0.035730519 | AA53: =+AA52/W52-1 -> 0.034518885 | AB53: =+AB52/X52-1 -> -0.074297965 | AC53: =+AC52/Y52-1 -> 0.050376108 | AD53: =+AD52/Z52-1 -> 0.076581787 | ... AG53: =+AG52/AC52-1 -> -0.01623909 | AH53: =+AH52/BF52-1 -> 0.11454138 | AI53: =+AI52/AE52-1 -> 0.068731009 | AJ53: =+AJ52/AF52-1 -> 0.16882785 | AK53: =+AK52/AG52-1 -> 0.032911727 | AL53: =+AL52/AH52-1 -> 0.030548525 | AM53: =+AM52/AI52-1 -> -0.2234069 | AN53: =+AN52/AJ52-1 -> -0.2964605 | AO53: =+AO52/AK52-1 -> -0.34846742 | AP53: =+AP52/AL52-1 -> -0.51015727 | ... AT53: =+AT52/AP52-1 -> 0.0082825575 | AU53: =+AU52/BK52-1 -> -0.13004037 | AV53: =+AV52/AR52-1 -> -0.10722875 | AW53: =+AW52/AS52-1 -> -0.036363636 | AX53: =+AX52/AT52-1 -> -0.14291809 | AY53: =+AY52/AU52-1 -> -0.022442966 | AZ53: =+AZ52/AV52-1 -> -0.03393902 | BA53: =+BA52/AW52-1 -> -0.0025898238 | BB53: =+BB52/AX52-1 -> 0.088672728 | BC53: =+BC52/AY52-1 -> 0.061853623 | BL53: =+BL52/BH52-1 -> -0.11852063
B54: % margin | C54: =C52/C9 -> 0.38131003 | D54: =D52/D9 -> 0.37613988 | E54: =E52/E9 -> 0.38036997 | F54: =F52/F9 -> 0.38735174 | G54: =G52/G9 -> 0.38651241 | H54: =H52/H9 -> 0.39597247 | I54: =I52/I9 -> 0.39805744 | J54: =J52/J9 -> 0.38410222 | ... Q54: =Q52/Q9 -> 0.38930292 | S54: =S52/S9 -> 0.36369572 | T54: =T52/T9 -> 0.38601528 | U54: =U52/U9 -> 0.38776252 | V54: =V52/V9 -> 0.3677871 | W54: =W52/W9 -> 0.37607715 | X54: =X52/X9 -> 0.38321289 | Y54: =Y52/Y9 -> 0.39196235 | Z54: =Z52/Z9 -> 0.3703391 | ... BC54: =BC52/BC9 -> 0.40538846 | BF54: =BF52/BF9 -> 0.37768945 | BG54: =BG52/BG9 -> 0.363766 | BH54: =BH52/BH9 -> 0.38053687 | BI54: =BI52/BI9 -> 0.38284356 | BJ54: =BJ52/BJ9 -> 0.40830783 | BK54: =BK52/BK9 -> 0.38887264 | BL54: =BL52/BL9 -> 0.3712059
B56: CASH FLOW | C56: =+C44 -> 42735 | D56: =+D44 -> 43100 | E56: =+E44 -> 43465 | F56: =+F44 -> 43830 | G56: =+G44 -> 43830 | H56: =+H44 -> 44196 | I56: =+I44 -> 44561 | J56: =+J44 -> 44561 | ... Q56: =+Q44 -> 46112 | S56: =+S44 -> 42825 | T56: =+T44 -> 42916 | U56: =+U44 -> 43008 | V56: =+V44 -> 43100 | W56: =+W44 -> 43190 | X56: =X3 -> 43281 | Y56: =Y3 -> 43373 | Z56: =Z3 -> 43465 | AA56: =+AA44 -> 43555 | AB56: =AB3 -> 43646 | AC56: =+AC44 -> 43738 | AD56: =+AD44 -> 43830 | AE56: =+AE44 -> 43921 | AF56: =+AF44 -> 44012 | AG56: =+AG44 -> 44104 | AH56: =+AH44 -> 44196 | AI56: =+AI44 -> 44286 | AJ56: =+AJ44 -> 44377 | ... BC56: =+BC44 -> 46112
B57: Adjusted EBITDA | C57: =C52 -> 36715.351 | D57: =D52 -> 35201.502 | E57: =E52 -> 38524.745 | F57: =F52 -> 39313.173 | G57: =G52 -> 39330.413 | H57: =H52 -> 38552.527 | I57: =I52 -> 41207.632 | J57: =J52 -> 28391.069 | ... Q57: =Q52 -> 22741.928 | S57: =S52 -> 7984.685 | T57: =T52 -> 8869.396 | U57: =U52 -> 8787.862 | V57: =V52 -> 9559.559 | W57: =W52 -> 8579.072 | X57: =X52 -> 10232.474 | Y57: =Y52 -> 9812.072 | Z57: =Z52 -> 9901.127 | ... BC57: =BC52 -> 5883.2
B58: Working Capital | C58: =-99.002-4649.477-1347.263+5255.698+438.556 -> -401.488 | D58: =839.128-1064.81+183.136-2696.279-3596.835 -> -6335.66 | E58: =-2523.789+3065.139-1703.088+2087.404-3083.16 -> -2157.494 | F58: =2010.127+4940.837-1182.107-1220.392-9664.678 -> -5116.213 | G58: =-15747.857+8816.632 -> -6931.225 | H58: =-10006.698+8681.478 -> -1325.22 | I58: =-2240.682-2833.536+321.712-6200.914+6965.158 -> -3988.262 | J58: =-6620.795-2024.974-2863.863+850.76+6861.117 -> -3797.755 | K58: =652.614-4147.622-2806.992-26.282-3717.588 -> -10045.87 | L58: =4176.638-588.954-2217.989-122.945+267.237 -> 1513.987 | M58: =14.321+533.303+1529.881-2403.935-2846.378 -> -3172.808 | N58: =523.619+564.745+1271.583-3216.45-734.349 -> -1590.852 | O58: =142.995+1099.637-738.598+1456.804-526.698 -> 1434.14 | P58: =467.885-355.036+1616.939+3033.245-703.589 -> 4059.444 | Q58: =SUM(AZ58:BC58) -> 2269.985 | S58: =-1744.393+4357.407-109.057+2569.522-4166.274 -> 907.205 | T58: =-1156.136+8095.822-835.882-936.555-8391.178-S58 -> -4131.134 | U58: =-329.655+10045.329-1425.324-3229.525-11643.828-T58-S58 -> -3359.074 | V58: =+IFERROR(D58-S58-T58-U58,"NA") -> 247.343 | W58: =-1599.793+1867.433-50.743-969.775+1243.824 -> 490.946 | X58: =-1422.317+5366.415-2278.475+569.329-3507.179-W58 -> -1763.173 | Y58: =-734.812+8270.566-2516.177-248.312-7335.641-X58-W58 -> -1292.149 | Z58: =E58-Y58-X58-W58 -> 406.882 | AA58: =-742.768-4859.621-1358.316-771.272+3296.257 -> -4435.72 | AB58: =-432.603-2193.103-2573.332+1315.508+164.163-AA58 -> 716.353 | AC58: =230.961+1444.993-1975.166+331.878-3729.732-AB58-AA58 -> 22.301 | AD58: =F58-AA58-AB58-AC58 -> -1419.147 | AE58: =382.237-5449.008-1960.935+3569.827+5785.138 -> 2327.259 | AF58: =-49.579-8074.866-2439.564+5478.479+7821.357-AE58 -> 408.568 | AG58: =-2001.382-4370.465-2084.62+5813.252+6541.591-AF58-AE58 -> 1162.549 | AH58: =H58-AE58-AF58-AG58 -> -5223.596 | AI58: =-4249.58-9814.265-2084.569+4854.812+12367.537 -> 1073.935 | AJ58: =-3681.128-9590.341-2036.384+4032.633+11463.441-AI58 -> -885.714 | AK58: =-4575.108-4034.252-1867.495+1143.376+7518.524-AJ58-AI58 -> -2003.176 | AL58: =I58-AI58-AJ58-AK58 -> -2173.307 | AM58: =-1000.428-3657.613-2925.763+1218.37+7461.999 -> 1096.565 | AN58: =-1084.808-4251.305-3795.488+2036.06+2527.47-AM58 -> -5664.636 | AO58: =-1854.478-4991.642-3653.208+1397.869+4244.119-AN58-AM58 -> -289.269 | AP58: =K58-AM58-AN58-AO58 -> -5188.53 | AQ58: =-38.329+101.64-934.137+1470.923-498.54 -> 101.557 | AR58: =-388.24+404.158+42.893-72.166-695.425-AQ58 -> -810.337 | AS58: =-144.497-312.21-470.635-1722.082-AR58-AQ58 -> -1940.644 | AT58: =M58-AQ58-AR58-AS58 -> -523.384 | AU58: =702.271-2349.161+504.002+1746.431-52.157 -> 551.386 | AV58: =1482.344-1112.718+573.844+154.821-135.34-AU58 -> 411.565 | AW58: =1913.738-961.016+1011.816+561.994-1138.017-AV58-AU58 -> 425.564 | AX58: =O58-SUM(AU58:AW58) -> 45.625 | AY58: =133.472-337.011-1524.237+1421.078+929.33 -> 622.632 | AZ58: =280.596+556.631-1404.553+583.356-287.698-AY58 -> -894.3 | BA58: =194.718-984.226-1156.958+1234.689+10.49-AZ58-AY58 -> -429.619 | BB58: =P58-SUM(AY58:BA58) -> 4760.731 | BC58: =0.574+235.811-958.913-475.587+31.288 -> -1166.827
B59: Taxes, net | C59: -7268.938 | D59: -6419.995 | E59: -6722.77 | F59: -8636.632 | G59: -8816.632 | H59: -8681.478 | I59: -9166.602 | J59: -9166.602 | K59: -11818.411 | L59: -12118.014 | M59: -7014.309 | N59: -7014.309 | O59: -812.215 | P59: -1934.09 | Q59: =SUM(AZ59:BC59) -> -1582.001 | S59: -2353.142 | T59: =-3850.969-S59 -> -1497.827 | U59: =-5333.484-T59-S59 -> -1482.515 | V59: =+IFERROR(D59-S59-T59-U59,"NA") -> -1086.511 | W59: -2715.804 | X59: =-3456.822-W59 -> -741.018 | Y59: =-5396.951-X59-W59 -> -1940.129 | Z59: =E59-Y59-X59-W59 -> -1325.819 | AA59: -4463.085 | AB59: =-6003.902-AA59 -> -1540.817 | AC59: =-7535.422-AB59-AA59 -> -1531.52 | AD59: =F59-AA59-AB59-AC59 -> -1101.21 | AE59: -3807.661 | AF59: =-5152.775-AE59 -> -1345.114 | AG59: =-7639.482-AF59-AE59 -> -2486.707 | AH59: =H59-AE59-AF59-AG59 -> -1041.996 | AI59: -3143.58 | AJ59: =-5345.583-AI59 -> -2202.003 | AK59: =-7456.848-AJ59-AI59 -> -2111.265 | AL59: =I59-AI59-AJ59-AK59 -> -1709.754 | AM59: 19097.912 | AN59: =-14763.292-AM59 -> -33861.204 | AO59: =-15257.682-AN59-AM59 -> -494.39 | AP59: =K59-AM59-AN59-AO59 -> 3439.271 | AQ59: -4815.806 | AR59: =-5844.376-AQ59 -> -1028.57 | AS59: =-6485.854-AR59-AQ59 -> -641.478 | AT59: =M59-AQ59-AR59-AS59 -> -528.455 | AU59: -1511.326 | AV59: =-2147.815-AU59 -> -636.489 | AW59: =-1608.127-AV59-AU59 -> 539.688 | AX59: =O59-SUM(AU59:AW59) -> 795.912 | AY59: -1007.745 | AZ59: =-1034.773-AY59 -> -27.028 | BA59: =-1686.532-AZ59-AY59 -> -651.759 | BB59: =P59-SUM(AY59:BA59) -> -247.558 | BC59: -655.656
B60: Cash interest paid | C60: -7633.026 | D60: -8860.881 | E60: -10129.304 | F60: -9170.336 | G60: -9180.141 | H60: -9455.387 | I60: -8258.243 | J60: -8258.243 | K60: =-8893 -> -8893 | L60: =-8893 -> -8893 | M60: =-7553.938 -> -7553.938 | N60: =-7553.938 -> -7553.938 | O60: -7417.915 | P60: -6816 | Q60: =SUM(AZ60:BC60) -> -6347 | S60: -2368.382 | T60: =-4547.532-S60 -> -2179.15 | U60: =-6688.34-T60-S60 -> -2140.808 | V60: =+IFERROR(D60-S60-T60-U60,"NA") -> -2172.541 | W60: -2360.314 | X60: =-4457.956-W60 -> -2097.642 | Y60: =-7014.365-X60-W60 -> -2556.409 | Z60: =E60-Y60-X60-W60 -> -3114.939 | AA60: -1467.99 | AB60: =-3591.148-AA60 -> -2123.158 | AC60: =-5991.238-AB60-AA60 -> -2400.09 | AD60: =F60-AA60-AB60-AC60 -> -3179.098 | AE60: -2144.314 | AF60: =-4588.589-AE60 -> -2444.275 | AG60: =-6867.123-AF60-AE60 -> -2278.534 | AH60: =H60-AE60-AF60-AG60 -> -2588.264 | AI60: -1998 | AJ60: =-4159.736-AI60 -> -2161.736 | AK60: =-6035-AJ60-AI60 -> -1875.264 | AL60: =I60-AI60-AJ60-AK60 -> -2223.243 | AM60: -2706.163 | AN60: =-5024.524-AM60 -> -2318.361 | AO60: =-6938-AN60-AM60 -> -1913.476 | AP60: =K60-AM60-AN60-AO60 -> -1955 | AQ60: -2111.199 | AR60: =-4134.286-AQ60 -> -2023.087 | AS60: =-6242-AR60-AQ60 -> -2107.714 | AT60: =M60-AQ60-AR60-AS60 -> -1311.938 | AU60: -2016.388 | AV60: =-3742.106-AU60 -> -1725.718 | AW60: =-5487-AV60-AU60 -> -1744.894 | AX60: =O60-SUM(AU60:AW60) -> -1930.915 | AY60: -2102 | AZ60: =-4042.293-AY60 -> -1940.293 | BA60: =-5381-AZ60-AY60 -> -1338.707 | BB60: =P60-SUM(AY60:BA60) -> -1435 | BC60: -1633
B61: Cash interest received | C61: 0 | D61: 0 | E61: 0 | F61: 0 | G61: 0 | H61: 0 | I61: 0 | J61: 0 | K61: 0 | L61: 0 | M61: 0 | N61: 0 | O61: 0 | P61: 0 | Q61: =SUM(AZ61:BC61) -> 88.782 | S61: 0 | T61: =-S61 -> 0 | U61: =-T61-S61 -> 0 | V61: =+IFERROR(D61-S61-T61-U61,"NA") -> 0 | W61: 0 | X61: =-W61 -> 0 | Y61: =-X61-W61 -> 0 | Z61: =E61-Y61-X61-W61 -> 0 | AA61: 0 | AB61: =-AA61 -> 0 | AC61: =-AB61-AA61 -> 0 | AD61: =F61-AA61-AB61-AC61 -> 0 | AE61: 0 | AF61: =-AE61 -> 0 | AG61: =-AF61-AE61 -> 0 | AH61: =H61-AE61-AF61-AG61 -> 0 | AI61: 0 | AJ61: =0-AI61 -> 0 | AK61: =-AJ61-AI61 -> 0 | AL61: =I61-AI61-AJ61-AK61 -> 0 | AM61: 109.581 | AN61: 0 | AO61: =-AN61-AM61 -> -109.581 | AP61: =K61-AM61-AN61-AO61 -> 0 | AQ61: 204.597 | AR61: 0 | AS61: =-AR61-AQ61 -> -204.597 | AT61: =M61-AQ61-AR61-AS61 -> 0 | AU61: -123.203 | AV61: =-305.268-AU61 -> -182.065 | AW61: =-548.169-AV61-AU61 -> -242.901 | AX61: =O61-SUM(AU61:AW61) -> 548.169 | AY61: -138.256 | AZ61: =-206.509-AY61 -> -68.253 | BA61: =-345.58-AZ61-AY61 -> -139.071 | BB61: =P61-SUM(AY61:BA61) -> 345.58 | BC61: -49.474
B62: Net cash from operations | C62: =SUM(C57:C61) -> 21411.899 | D62: =SUM(D57:D61) -> 13584.966 | E62: =SUM(E57:E61) -> 19515.177 | F62: =SUM(F57:F61) -> 16389.992 | G62: =SUM(G57:G61) -> 14402.415 | H62: =SUM(H57:H61) -> 19090.442 | I62: =SUM(I57:I61) -> 19794.525 | J62: =SUM(J57:J61) -> 7168.469 | ... Q62: =SUM(Q57:Q61) -> 17171.694 | S62: =SUM(S57:S61) -> 4170.366 | T62: =SUM(T57:T61) -> 1061.285 | U62: =SUM(U57:U61) -> 1805.465 | V62: =SUM(V57:V61) -> 6547.85 | W62: =SUM(W57:W61) -> 3993.9 | X62: =SUM(X57:X61) -> 5630.641 | Y62: =SUM(Y57:Y61) -> 4023.385 | Z62: =SUM(Z57:Z61) -> 5867.251 | ... BC62: =SUM(BC57:BC61) -> 2378.243
B63: Net Capex | C63: =-27941.585+1571.211 -> -26370.374 | D63: =-16759.566+911.471 -> -15848.095 | E63: =-18499.662+1024.702 -> -17474.96 | F63: =-19108.581+981.8 -> -18126.781 | G63: =-19108.284+981.503 -> -18126.781 | H63: =-20131.738+1520.417 -> -18611.321 | I63: =-23267.847+672.424 -> -22595.423 | J63: =-23267.847+672.424 -> -22595.423 | K63: =264.163-17315.387 -> -17051.224 | L63: =264.163-17315.387 -> -17051.224 | M63: =48.873-14708.016 -> -14659.143 | N63: =48.873-14708.016 -> -14659.143 | O63: =-9097.397+627.973 -> -8469.424 | P63: =133.176-12186.505 -> -12053.329 | Q63: =SUM(AZ63:BC63) -> -12718.359 | S63: =-4427.53+64.283 -> -4363.247 | T63: =-7626.308+264.979-S63 -> -2998.082 | U63: =-11497.184+563.186-T63-S63 -> -3572.669 | V63: =+IFERROR(D63-S63-T63-U63,"NA") -> -4914.097 | W63: =-2971.881+125.405 -> -2846.476 | X63: =-7253.498+642.638-W63 -> -3764.384 | Y63: =-12740.872+956.727-X63-W63 -> -5173.285 | Z63: =E63-Y63-X63-W63 -> -5690.815 | AA63: =-4279.827+161.542 -> -4118.285 | AB63: =-8859.401+1283.386-AA63 -> -3457.73 | AC63: =-13736.986+1967.674-AB63-AA63 -> -4193.297 | AD63: =F63-AA63-AB63-AC63 -> -6357.469 | AE63: =-4552.915+250.398 -> -4302.517 | AF63: =-9146.171+499.569-AE63 -> -4344.085 | AG63: =-14702.698+866.397-AF63-AE63 -> -5189.699 | AH63: =H63-AE63-AF63-AG63 -> -4775.02 | AI63: =-5596.853+326.998 -> -5269.855 | AJ63: =636.612-11220.368-AI63 -> -5313.901 | AK63: =-18467.093+1092.079-AJ63-AI63 -> -6791.258 | AL63: =I63-AI63-AJ63-AK63 -> -5220.409 | AM63: =-4689.334+139.331 -> -4550.003 | AN63: =221.937-9479.476-AM63 -> -4707.536 | AO63: =-13683.82+447.397-AN63-AM63 -> -3978.884 | AP63: =K63-AM63-AN63-AO63 -> -3814.801 | AQ63: =-3929.765+7.199 -> -3922.566 | AR63: =24.7+7534.897-AQ63 -> 11482.163 | AS63: =-10720.491+47.008-AR63-AQ63 -> -18233.08 | AT63: =M63-AQ63-AR63-AS63 -> -3985.66 | AU63: =-2053.902+16.739 -> -2037.163 | AV63: =525.442-3815.383-AU63 -> -1252.778 | AW63: =-6241.954+614.005-AV63-AU63 -> -2338.008 | AX63: =O63-SUM(AU63:AW63) -> -2841.475 | AY63: =-1776.969+3.827 -> -1773.142 | AZ63: =47.86-3902.323-AY63 -> -2081.321 | BA63: =-7558.905+112.212-AZ63-AY63 -> -3592.23 | BB63: =P63-SUM(AY63:BA63) -> -4606.636 | BC63: =-2491.726+53.554 -> -2438.172
B64: Purchase and development of intangible assets | C64: -2472.124 | D64: -1777.59 | E64: -7774.281 | F64: -2093.546 | G64: -2106.75 | H64: -1235.177 | I64: -1899.4 | J64: -1899.4 | K64: -1867 | L64: -1807.183 | M64: -1869.716 | N64: -1869.707 | O64: -1378.854 | P64: -1287.1 | Q64: =SUM(AZ64:BC64) -> -1244.53 | S64: -255.447 | T64: =-581.859-S64 -> -326.412 | U64: =-1205.043-T64-S64 -> -623.184 | V64: =+IFERROR(D64-S64-T64-U64,"NA") -> -572.547 | W64: -379.967 | X64: =-1080.85-W64 -> -700.883 | Y64: =-1540.012-X64-W64 -> -459.162 | Z64: =E64-Y64-X64-W64 -> -6234.269 | AA64: -477.957 | AB64: =-1441.524-AA64 -> -963.567 | AC64: =-2130.32-AB64-AA64 -> -688.796 | AD64: =F64-AA64-AB64-AC64 -> 36.774 | AE64: -199.971 | AF64: =-531.399-AE64 -> -331.428 | AG64: =-914.7-AF64-AE64 -> -383.301 | AH64: =H64-AE64-AF64-AG64 -> -320.477 | AI64: -486.2 | AJ64: =-937.6-AI64 -> -451.4 | AK64: =-1498.2-AJ64-AI64 -> -560.6 | AL64: =I64-AI64-AJ64-AK64 -> -401.2 | AM64: -511.2 | AN64: =-828.1-AM64 -> -316.9 | AO64: =-1087.4-AN64-AM64 -> -259.3 | AP64: =K64-AM64-AN64-AO64 -> -779.6 | AQ64: -203.8 | AR64: =-845.528-AQ64 -> -641.728 | AS64: =-1433.606-AR64-AQ64 -> -588.078 | AT64: =M64-AQ64-AR64-AS64 -> -436.11 | AU64: -379.9 | AV64: =-847.9-AU64 -> -468 | AW64: =-1149.423-AV64-AU64 -> -301.523 | AX64: =O64-SUM(AU64:AW64) -> -229.431 | AY64: -240.6 | AZ64: =-548.097-AY64 -> -307.497 | BA64: =-785.9-AZ64-AY64 -> -237.803 | BB64: =P64-SUM(AY64:BA64) -> -501.2 | BC64: -198.03
B65: Disposals/ Acquisition, of subsidiaries | C65: -90.133 | D65: =14.383+0.026-191.096 -> -176.687 | E65: =-5465.711+6256.874+95.161 -> 886.324 | F65: =12.19+107.883 -> 120.073 | G65: =-25.741 -> -25.741 | H65: -602.466 | I65: 10 | J65: 10 | K65: 10 | L65: 0 | M65: 8 | N65: 0 | O65: 0 | P65: =5 -> 5 | Q65: =SUM(AZ65:BC65) -> 5 | S65: =0.026-140 -> -139.974 | T65: =0.026-140-S65 -> 0 | U65: =0.026-182.5-T65-S65 -> -42.5 | V65: =+IFERROR(D65-S65-T65-U65,"NA") -> 5.787 | W65: 85 | X65: =5890.52+85-W65 -> 5890.52 | Y65: =5890.52+95.161-X65-W65 -> 10.161 | Z65: =E65-Y65-X65-W65 -> -5099.357 | AA65: 0 | AB65: =-0.674-107.883-AA65 -> -108.557 | AC65: =0.667+107.883-AB65-AA65 -> 217.107 | AD65: =F65-AA65-AB65-AC65 -> 11.523 | AE65: =10.601+179.59 -> 190.191 | AF65: =0-AE65 -> -190.191 | AG65: =0+0-AF65-AE65 -> 0 | AH65: =H65-AE65-AF65-AG65 -> -602.466 | AI65: 0 | AJ65: =0-AI65 -> 0 | AK65: =10-AJ65-AI65 -> 10 | AL65: =I65-AI65-AJ65-AK65 -> 0 | AM65: 0 | AN65: =0-AM65 -> 0 | AO65: =10-AN65-AM65 -> 10 | AP65: =K65-AM65-AN65-AO65 -> 0 | AQ65: 0 | AR65: =0-AQ65 -> 0 | AS65: =8-AR65-AQ65 -> 8 | AT65: =M65-AQ65-AR65-AS65 -> 0 | AU65: 0 | AV65: =0-AU65 -> 0 | AW65: =10-AV65-AU65 -> 10 | AX65: =O65-SUM(AU65:AW65) -> -10 | AY65: 0 | AZ65: =0-AY65 -> 0 | BA65: =5-AZ65-AY65 -> 5 | BB65: =P65-SUM(AY65:BA65) -> 0 | BC65: 0
B66: Free cash flow | C66: =SUM(C62:C65) -> -7520.732 | D66: =SUM(D62:D65) -> -4217.406 | E66: =SUM(E62:E65) -> -4847.74 | F66: =SUM(F62:F65) -> -3710.262 | G66: =SUM(G62:G65) -> -5856.857 | H66: =SUM(H62:H65) -> -1358.522 | I66: =SUM(I62:I65) -> -4690.298 | J66: =SUM(J62:J65) -> -17316.354 | ... Q66: =SUM(Q62:Q65) -> 3213.805 | S66: =SUM(S62:S65) -> -588.302 | T66: =SUM(T62:T65) -> -2263.209 | U66: =SUM(U62:U65) -> -2432.888 | V66: =SUM(V62:V65) -> 1066.993 | W66: =SUM(W62:W65) -> 852.457 | X66: =SUM(X62:X65) -> 7055.894 | Y66: =SUM(Y62:Y65) -> -1598.901 | Z66: =SUM(Z62:Z65) -> -11157.19 | ... BC66: =SUM(BC62:BC65) -> -257.959
B67: Other investing activities | C67: -114.979 | D67: 364.053 | E67: 464.843 | F67: 1856.225 | G67: =30.992+2301.682+149.39 -> 2482.064 | H67: =3155.643+1248+125.624 -> 4529.267 | I67: 5443.145 | J67: 5745.182 | K67: =66095.454+364.05+744.634 -> 67204.138 | L67: =66095.454-5738.832-7.922+752.556+364.42+10+87.663 -> 61563.339 | M67: 762.461 | N67: =45.556+716.905+8 -> 770.461 | O67: =50.767+777.838+10 -> 838.605 | P67: -3289.055 | Q67: =SUM(AZ67:BC67) -> -1656.325 | S67: 40.388 | T67: =262.283-S67 -> 221.895 | U67: =283.66-T67-S67 -> 21.377 | V67: =+IFERROR(D67-S67-T67-U67,"NA") -> 80.393 | W67: 293.163 | X67: =408.812-W67 -> 115.649 | Y67: =416.189-X67-W67 -> 7.377 | Z67: =E67-Y67-X67-W67 -> 48.654 | AA67: -0.008 | AB67: =51.472-AA67 -> 51.48 | AC67: =1216.055-AB67-AA67 -> 1164.583 | AD67: =F67-AA67-AB67-AC67 -> 640.17 | AE67: -20.196 | AF67: =529.374-AE67 -> 549.57 | AG67: =2678.03-AF67-AE67 -> 2148.656 | AH67: =H67-AE67-AF67-AG67 -> 1851.237 | AI67: 1268.731 | AJ67: =1824.817-AI67 -> 556.086 | AK67: =1337.948-AJ67-AI67 -> -486.869 | AL67: =I67-AI67-AJ67-AK67 -> 4105.197 | AM67: =23.892+65440.452 -> 65464.344 | AN67: =65174.953+364.42+315.567-AM67 -> 390.596 | AO67: =66039.81+400+515.77-AN67-AM67 -> 1100.64 | AP67: =K67-AM67-AN67-AO67 -> 248.558 | AQ67: =195.369 -> 195.369 | AR67: =378.306+8-AQ67 -> 190.937 | AS67: =0+567.086-AR67-AQ67 -> 180.78 | AT67: =M67-AQ67-AR67-AS67 -> 195.375 | AU67: =-521.479 -> -521.479 | AV67: =-333.742-AU67 -> 187.737 | AW67: =-114.014-AV67-AU67 -> 219.728 | AX67: =O67-SUM(AU67:AW67) -> 952.619 | AY67: 205.599 | AZ67: =-425.314-AY67 -> -630.913 | BA67: =780.305-AZ67-AY67 -> 1205.619 | BB67: =P67-SUM(AY67:BA67) -> -4069.36 | BC67: 1838.329
B68: Equity Issuance/Buyback | C68: -2379.424 | D68: =-1292.438-2883.808 -> -4176.246 | E68: =-1238.276-2641.18 -> -3879.456 | F68: =-1294.375-1385.75 -> -2680.125 | G68: =-1294.375-1385.75 -> -2680.125 | H68: =-195.597-1324.063 -> -1519.66 | I68: -438.154 | J68: -328.5 | K68: -1277.568 | L68: =-629.326 -> -629.326 | M68: -1197.082 | N68: -1197.082 | O68: 0 | P68: 0 | Q68: =SUM(AZ68:BC68) -> -40 | S68: -1292.438 | T68: =-1292.438-S68 -> 0 | U68: =-1292.438-T68-S68 -> 0 | V68: =+IFERROR(D68-S68-T68-U68,"NA") -> -2883.808 | W68: =-1184.02-562.036 -> -1746.056 | X68: =-1184.02-1541.181-W68 -> -979.145 | Y68: =-1184.02-1541.18-X68-W68 -> 0.001 | Z68: =E68-Y68-X68-W68 -> -1154.256 | AA68: -1294.375 | AB68: =-1294.375-1094.096-AA68 -> -1094.096 | AC68: =-2091.551-1385.75-AB68-AA68 -> -1088.83 | AD68: =F68-AA68-AB68-AC68 -> 797.176 | AE68: =-1330.001-195.597 -> -1525.598 | AF68: =-1324.063-195.597-AE68 -> 5.938 | AG68: =-1324.063-195.597-AF68-AE68 -> 0 | AH68: =H68-AE68-AF68-AG68 -> 0 | AI68: -50.5 | AJ68: =-50.5-AI68 -> 0 | AK68: =-113.5-AJ68-AI68 -> -63 | AL68: =I68-AI68-AJ68-AK68 -> -324.654 | AM68: =-596.242 -> -596.242 | AN68: =-646.242-AM68 -> -50 | AO68: =-1002.36-AN68-AM68 -> -356.118 | AP68: =K68-AM68-AN68-AO68 -> -275.208 | AQ68: =-823.712 -> -823.712 | AR68: =-910.936-AQ68 -> -87.224 | AS68: =-1097.255-AR68-AQ68 -> -186.319 | AT68: =M68-AQ68-AR68-AS68 -> -99.827 | AU68: 0 | AV68: =0-AU68 -> 0 | AW68: =0-AV68-AU68 -> 0 | AX68: =O68-SUM(AU68:AW68) -> 0 | AY68: 0 | AZ68: =0-AY68 -> 0 | BA68: =0-AZ68-AY68 -> 0 | BB68: =P68-SUM(AY68:BA68) -> 0 | BC68: -40
B69: Dividends Paid | C69: =-1084.192+47.2 -> -1036.992 | D69: =-1084.192+136 -> -948.192 | E69: -1068.868 | F69: =-1066.187+772.4 -> -293.787 | G69: =-1066.187+772.4-1594.629 -> -1888.416 | H69: =0-1420.477 -> -1420.477 | I69: -1053.392 | J69: -1053.392 | K69: -1053.392 | L69: -1053.392 | M69: -1027.354 | N69: -1027.354 | O69: -1018.954 | P69: -1018.954 | Q69: =SUM(AZ69:BC69) -> -1018.954 | S69: 0 | T69: =-1084.192-S69 -> -1084.192 | U69: =-1084.192-T69-S69 -> 0 | V69: =+IFERROR(D69-S69-T69-U69,"NA") -> 136 | W69: 0 | X69: =-1068.868-W69 -> -1068.868 | Y69: =-1068.868-X69-W69 -> 0 | Z69: =E69-Y69-X69-W69 -> 0 | AA69: 0 | AB69: =-1066.187+452.4-AA69 -> -613.787 | AC69: =-1066.187+452.4-AB69-AA69 -> 0 | AD69: =F69-AA69-AB69-AC69 -> 320 | AE69: 0 | AF69: 0 | AG69: =285.669-AF69-AE69 -> 285.669 | AH69: =H69-AE69-AF69-AG69 -> -1706.146 | AI69: 0 | AJ69: =-1053.392-AI69 -> -1053.392 | AK69: =-1053.392-AJ69-AI69 -> 0 | AL69: =I69-AI69-AJ69-AK69 -> 0 | AM69: 0 | AN69: =-1053.392-AM69 -> -1053.392 | AO69: =-1053.392-AN69-AM69 -> 0 | AP69: =K69-AM69-AN69-AO69 -> 0 | AQ69: 0 | AR69: =-1027.354-AQ69 -> -1027.354 | AS69: =-1027.354-AR69-AQ69 -> 0 | AT69: =M69-AQ69-AR69-AS69 -> 0 | AU69: 0 | AV69: =-1018.954-AU69 -> -1018.954 | AW69: =-1018.954-AV69-AU69 -> 0 | AX69: =O69-SUM(AU69:AW69) -> 0 | AY69: 0 | AZ69: =-1018.954-AY69 -> -1018.954 | BA69: =-1018.954-AZ69-AY69 -> 0 | BB69: =P69-SUM(AY69:BA69) -> 0 | BC69: 0
B70: Change in debt | C70: =-3622.6-329.064+5728.498 -> 1776.834 | D70: =-11252.655-569.711+10449.958 -> -1372.408 | E70: =-307.489-540.448 -> -847.937 | F70: =23880.911-21989.156-793.25-981.275 -> 117.23 | G70: =10000-989.156+14247.544-21000-559.623 -> 1698.765 | H70: =-492.489-2750-668.277 -> -3910.766 | I70: =-646.527+2650-1992.489 -> 10.984 | J70: =-646.527+2650-1992.489-1082.226 -> -1071.242 | K70: =-16099.582-610.403-699-991.048 -> -18400.033 | L70: =-10099.581-6000-610.403-1690.311 -> -18400.295 | M70: =-4899.89-1000-660.645-1132.957 -> -7693.492 | N70: =-4718.25-181.731+400-1400-1793.602-86-195.055 -> -7974.638 | O70: =-10000+10000-1567.3 -> -1567.3 | P70: =-3906.655-2650-732-1077.67 -> -8366.325 | Q70: =SUM(AZ70:BC70) -> -7699.098 | S70: =-16.249-107.694 -> -123.943 | T70: =-72.914-236.058-S70 -> -185.029 | U70: =-774.787-450.509-T70-S70 -> -916.324 | V70: =+IFERROR(D70-S70-T70-U70,"NA") -> -147.112 | W70: =-76.872-101.634 -> -178.506 | X70: =-153.744-216.318-W70 -> -191.556 | Y70: =-230.617-334.638-X70-W70 -> -195.193 | Z70: =E70-Y70-X70-W70 -> -282.682 | AA70: =-76.872-114.746-210.932 -> -402.55 | AB70: =14006.712-317.911-413.531-419.432-AA70 -> 13258.388 | AC70: =24006.712-11928.534-692.66-612.887-AB70-AA70 -> -2083.207 | AD70: =F70-AA70-AB70-AC70 -> -10655.401 | AE70: =14770.594-60.522-105.872-232.987 -> 14371.213 | AF70: =14770.695-371.245-227.362-484.117-AE70 -> -683.242 | AG70: =14770.695-3181.867-470.009-717.984-AF70-AE70 -> -3287.136 | AH70: =H70-AE70-AF70-AG70 -> -14311.601 | AI70: =-60.622-231-186.412 -> -478.034 | AJ70: =-121.284-326.376-378.002-AI70 -> -347.628 | AK70: =-181.782-476.901-581.148-AJ70-AI70 -> -414.169 | AL70: =I70-AI70-AJ70-AK70 -> 1250.815 | AM70: =-60.622-169.57-222.622+10177.58 -> 9724.766 | AN70: =10177.581-610.403-326.719-455.89-AM70 -> -940.197 | AO70: =16099.99-610.403-528.743-746.994-AN70-AM70 -> 5429.281 | AP70: =K70-AM70-AN70-AO70 -> -32613.883 | AQ70: =387.564-1000-174-255.639 -> -1042.075 | AR70: =370.621-1000-328.269-550.046-AQ70 -> -465.619 | AS70: =4499.981-1000-499.378-842.196-AR70-AQ70 -> 3666.101 | AT70: =M70-AQ70-AR70-AS70 -> -9851.899 | AU70: =-145.751-218.134 -> -363.885 | AV70: =-10000+10000-328.241-435.412-AU70 -> -399.768 | AW70: =10000-10000-504.241-642.804-AV70-AU70 -> -383.392 | AX70: =O70-SUM(AU70:AW70) -> -420.255 | AY70: =-4579.473-175.113-210.487 -> -4965.073 | AZ70: =-3994.932-2650-365-428.902-AY70 -> -2473.761 | BA70: =-3906.654-2650-545.5-679.553-AZ70-AY70 -> -342.873 | BB70: =P70-SUM(AY70:BA70) -> -584.618 | BC70: =-3673.863-172-451.983 -> -4297.846
B71: Other financing activities | C71: -671.104 | D71: -975.611 | E71: -579.349 | F71: -2190.675 | G71: =-883.533-596.046 -> -1479.579 | H71: =-953.771+1261.845-197 -> 111.074 | I71: =-1082.226-3021.618 -> -4103.844 | J71: =-3021.618 -> -3021.618 | K71: =-145.131 -> -145.131 | L71: =-648.242-145.131 -> -793.373 | M71: -195.055 | N71: -195.055 | O71: =-132.572+747.746 -> 615.174 | P71: =-16321.246-SUM(P70,P69,P68,P60) -> -119.967 | Q71: =SUM(AZ71:BC71) -> -1314.826 | S71: -3795.251 | T71: =-7299.003-S71 -> -3503.752 | U71: =-515.298-T71-S71 -> 6783.705 | V71: =+IFERROR(D71-S71-T71-U71,"NA") -> -460.313 | W71: -5.25 | X71: =-965.911-W71 -> -960.661 | Y71: =-952.377-X71-W71 -> 13.534 | Z71: =E71-Y71-X71-W71 -> 373.028 | AA71: -1585.479 | AB71: =-1823.025-AA71 -> -237.546 | AC71: =-1938.058-AB71-AA71 -> -115.033 | AD71: =F71-AA71-AB71-AC71 -> -252.617 | AE71: 50.934 | AF71: =697.001-AE71 -> 646.067 | AG71: =221.855-AF71-AE71 -> -475.146 | AH71: =H71-AE71-AF71-AG71 -> -110.781 | AI71: -745.593 | AJ71: =-1433.168-AI71 -> -687.575 | AK71: =-2557.2-AJ71-AI71 -> -1124.032 | AL71: =I71-AI71-AJ71-AK71 -> -1546.644 | AM71: -219.031 | AN71: =-246.02-AM71 -> -26.989 | AO71: =-189.182-AN71-AM71 -> 56.838 | AP71: =K71-AM71-AN71-AO71 -> 44.051 | AQ71: -68.47 | AR71: =-238.307-AQ71 -> -169.837 | AS71: =-314.83-AR71-AQ71 -> -76.523 | AT71: =M71-AQ71-AR71-AS71 -> 119.775 | AU71: 119.82 | AV71: =249.759-AU71 -> 129.939 | AW71: =464.523-AV71-AU71 -> 214.764 | AX71: =O71-SUM(AU71:AW71) -> 150.651 | AY71: 738.974 | AZ71: =688.93-AY71 -> -50.044 | BA71: =612.12-AZ71-AY71 -> -76.81 | BB71: =P71-SUM(AY71:BA71) -> -732.087 | BC71: =-6426.731-SUM(BC70,BC69,BC68,BC60) -> -455.885
B72: Net Cash from discontinued operations | C72: 0 | D72: 0 | E72: 0 | F72: 0 | G72: 0 | H72: 0 | I72: 0 | J72: 0 | K72: 0 | L72: 0 | M72: 0 | N72: 0 | O72: 0 | P72: 0 | Q72: =SUM(AZ72:BC72) -> 0 | S72: 0 | T72: =-S72 -> 0 | U72: =-T72-S72 -> 0 | V72: =+IFERROR(D72-S72-T72-U72,"NA") -> 0 | W72: 0 | X72: =-W72 -> 0 | Y72: =-X72-W72 -> 0 | Z72: =E72-Y72-X72-W72 -> 0 | AA72: 0 | AB72: 0 | AC72: 0 | AD72: 0 | AE72: 0 | AF72: 0 | AG72: 0 | AH72: 0 | AI72: 0 | AJ72: =0-AI72 -> 0 | AK72: 0 | AL72: 0 | AM72: 0 | AN72: 0 | AO72: 0 | AP72: 0 | AQ72: 0 | AR72: 0 | AS72: 0 | AT72: 0 | AU72: 0 | AV72: 0 | AW72: 0 | AX72: =O72-SUM(AU72:AW72) -> 0 | AY72: 0 | AZ72: 0 | BA72: 0 | BB72: =P72-SUM(AY72:BA72) -> 0 | BC72: 0
B73: Cash flow after financing activities | C73: =SUM(C66:C72) -> -9946.397 | D73: =SUM(D66:D72) -> -11325.81 | E73: =SUM(E66:E72) -> -10758.507 | F73: =SUM(F66:F72) -> -6901.394 | G73: =SUM(G66:G72) -> -7724.148 | H73: =SUM(H66:H72) -> -3569.084 | I73: =SUM(I66:I72) -> -4831.559 | J73: =SUM(J66:J72) -> -17045.924 | ... Q73: =SUM(Q66:Q72) -> -8515.398 | S73: =SUM(S66:S72) -> -5759.546 | T73: =SUM(T66:T72) -> -6814.287 | U73: =SUM(U66:U72) -> 3455.87 | V73: =SUM(V66:V72) -> -2207.847 | W73: =SUM(W66:W72) -> -784.192 | X73: =SUM(X66:X72) -> 3971.313 | Y73: =SUM(Y66:Y72) -> -1773.182 | Z73: =SUM(Z66:Z72) -> -12172.446 | ... BC73: =SUM(BC66:BC72) -> -3213.361
B74: FX | C74: 483.388 | D74: -110.447 | E74: 21.995 | F74: -60.449 | G74: -60.449 | H74: -11.516 | I74: 23.54 | J74: 23.54 | K74: =-100.344 -> -100.344 | L74: =-100.344 -> -100.344 | M74: =-234.637 -> -234.637 | N74: -234.637 | O74: 148.289 | P74: -66.999 | Q74: =SUM(AZ74:BC74) -> 4.451 | S74: -333.667 | T74: =-218.723-S74 -> 114.944 | U74: =-217.837-T74-S74 -> 0.886 | V74: =+IFERROR(D74-S74-T74-U74,"NA") -> 107.39 | W74: -147.673 | X74: =-2.686-W74 -> 144.987 | Y74: =-102.619-X74-W74 -> -99.933 | Z74: =E74-Y74-X74-W74 -> 124.614 | AA74: -15.58 | AB74: =-33.905-AA74 -> -18.325 | AC74: =3.994-AB74-AA74 -> 37.899 | AD74: =F74-AA74-AB74-AC74 -> -64.443 | AE74: 378.598 | AF74: =232.447-AE74 -> -146.151 | AG74: =197.018-AF74-AE74 -> -35.429 | AH74: =H74-AE74-AF74-AG74 -> -208.534 | AI74: 32.573 | AJ74: =4.524-AI74 -> -28.049 | AK74: =31.568-AJ74-AI74 -> 27.044 | AL74: =I74-AI74-AJ74-AK74 -> -8.028 | AM74: -44.274 | AN74: =-37.193-AM74 -> 7.081 | AO74: =-45.323-AN74-AM74 -> -8.13 | AP74: =K74-AM74-AN74-AO74 -> -55.021 | AQ74: -104.443 | AR74: =-169.199-AQ74 -> -64.756 | AS74: =-147.923-AR74-AQ74 -> 21.276 | AT74: =M74-AQ74-AR74-AS74 -> -86.714 | AU74: -19.066 | AV74: =81.436-AU74 -> 100.502 | AW74: =98.08-AV74-AU74 -> 16.644 | AX74: =O74-SUM(AU74:AW74) -> 50.209 | AY74: -35.298 | AZ74: =-64.536-AY74 -> -29.238 | BA74: =-79.565-AZ74-AY74 -> -15.029 | BB74: =P74-SUM(AY74:BA74) -> 12.566 | BC74: 36.152
B75: Balancing figure | C75: =-1851.043-C74-C73 -> 7611.966 | D75: =-8811.134-D74-D73 -> 2625.123 | E75: =-6666.658-E74-E73 -> 4069.854 | F75: =-4616.294-F74-F73 -> 2345.549 | G75: =-4098.07-G74-G73-517.956 -> 3168.571 | H75: =1034.49-H74-H73+571.338 -> 5186.428 | I75: =-3464.731-I74-I73 -> 1343.288 | J75: =-3229.878-J74-J73 -> 13792.506 | K75: =25302.777-K74-K73 -> 2267.151 | L75: =25302.777-L74-L73 -> -2928.62 | M75: =-18544.64-M74-M73 -> 217.533 | N75: =-18544.64-N74-N73 -> -239.134 | O75: =14303.737-O74-O73-696.916 -> 8956.875 | P75: =-9817.515-P74-P73 -> -1329.368 | Q75: =SUM(AZ75:BC75) -> -1280.54 | S75: =-4007.802-S73-S74 -> 2085.411 | T75: =-6323.362-S76-T73-T74 -> 4383.783 | U75: =-8887.527-T76-S76-U73-U74 -> -6020.921 | V75: =+IFERROR(D75-S75-T75-U75,"NA") -> 2176.85 | W75: =-1029.496-W73-W74 -> -97.631 | X75: =5858.044-W76-X73-X74 -> 2771.24 | Y75: =3691.808-X76-W76-Y73-Y74 -> -293.121 | Z75: =E75-Y75-X75-W75 -> 1689.366 | AA75: =-8505.277-AA73-AA74 -> 880.54 | AB75: =5849.809-AA76-AB73-AB74 -> 1014.226 | AC75: =6642.626-AB76-AA76-AC73-AC74 -> 1145.334 | AD75: =F75-AA75-AB75-AC75 -> -694.551 | AE75: =16970.316-AE73-AE74 -> 3359.178 | AF75: =18029.529-AF73-AF74-AE76 -> 712.756 | AG75: =17399.927-AF76-AE76-AG73-AG74 -> -229.524 | AH75: =H75-AE75-AF75-AG75 -> 1344.018 | AI75: =-195.886-AI73-AI74 -> 737.437 | AJ75: =-2676.755-AJ73-AJ74-AI76 -> 485.743 | AK75: =-7353.311-AJ76-AI76-AK73-AK74 -> 243.341 | AL75: =I75-AI75-AJ75-AK75 -> -123.233 | AM75: =35243.776-AM74-AM73 -> -58505.579 | AN75: =34063.982-AN73-AN74-AM76 -> 40601.644 | AO75: =28084.304-AN76-AM76-AO73-AO74 -> -11990.589 | AP75: =K75-AM75-AN75-AO75 -> 32161.675 | AQ75: =-7581.48-AQ74-AQ73 -> -1688.518 | AR75: =-12227.693-AR73-AR74-AQ76 -> -16528.901 | AS75: =-18442.85-AR76-AQ76-AS73-AS74 -> 8084.619 | AT75: =M75-AQ75-AR75-AS75 -> 10350.333 | AU75: =20.4-AU74-AU73 -> 653.904 | AV75: =4374.008-AV73-AV74-AU76 -> 3379.537 | AW75: =8447.3-AV76-AU76-AW73-AW74 -> 2066.122 | AX75: =O75-SUM(AU75:AW75) -> 2857.312 | AY75: =-2656.457-AY74-AY73 -> 497.952 | AZ75: =-7743.953-AZ73-AZ74-AY76 -> -1196.194 | BA75: =-8336.397-AZ76-AY76-BA73-BA74 -> -556.181 | BB75: =P75-SUM(AY75:BA75) -> -74.945 | BC75: =-2630.429-BC74-BC73 -> 546.78
B76: Net change in cash | C76: =SUM(C73:C75) -> -1851.043 | D76: =SUM(D73:D75) -> -8811.134 | E76: =SUM(E73:E75) -> -6666.658 | F76: =SUM(F73:F75) -> -4616.294 | G76: =SUM(G73:G75) -> -4616.026 | H76: =SUM(H73:H75) -> 1605.828 | I76: =SUM(I73:I75) -> -3464.731 | J76: =SUM(J73:J75) -> -3229.878 | ... Q76: =SUM(Q73:Q75) -> -9791.487 | S76: =SUM(S73:S75) -> -4007.802 | T76: =SUM(T73:T75) -> -2315.56 | U76: =SUM(U73:U75) -> -2564.165 | V76: =SUM(V73:V75) -> 76.393 | W76: =SUM(W73:W75) -> -1029.496 | X76: =SUM(X73:X75) -> 6887.54 | Y76: =SUM(Y73:Y75) -> -2166.236 | Z76: =SUM(Z73:Z75) -> -10358.466 | ... BC76: =SUM(BC73:BC75) -> -2630.429
B77: Cash and cash equivalents | C77: =49397.126+C76 -> 47546.083 | D77: =+C77+D76 -> 38734.949 | E77: =D77+E76 -> 32068.291 | F77: =E77+F76 -> 27451.997 | G77: =E77+G76 -> 27452.265 | H77: =G77+H76 -> 29058.093 | I77: =H77+I76 -> 25593.362 | J77: =H77+J76 -> 25828.215 | K77: =J77+K76 -> 51130.992 | L77: =J77+L76 -> 51130.992 | M77: =K77+M76 -> 32586.352 | N77: =L77+N76 -> 32586.352 | O77: =N77+O76 -> 46193.173 | P77: =O77+P76 -> 36375.658 | Q77: =BC77 -> 24976.815 | S77: =C76+S76 -> -5858.845 | T77: =+S77+T76 -> -8174.405 | U77: =+T77+U76 -> -10738.57 | V77: =+U77+V76 -> -10662.177 | W77: =D77+W76 -> 37705.453 | X77: =+W77+X76 -> 44592.993 | Y77: =+X77+Y76 -> 42426.757 | Z77: =+Y77+Z76 -> 32068.291 | AA77: =Z77+AA76 -> 23563.014 | AB77: =AA77+AB76 -> 37918.1 | AC77: =AB77+AC76 -> 38710.917 | AD77: =AC77+AD76 -> 27451.997 | AE77: =AE76+27969.933 -> 44940.249 | AF77: =AE77+AF76-(27969.933-27452) -> 45481.529 | AG77: =AF77+AG76 -> 44851.927 | AH77: =AG77+AH76 -> 29057.828 | AI77: =AH77+AI76 -> 28861.942 | AJ77: =AI77+AJ76 -> 26381.073 | AK77: =AJ77+AK76 -> 21704.517 | AL77: =AK77+AL76 -> 25593.097 | AM77: =25828.215+AM76 -> 61071.991 | AN77: =AM77+AN76 -> 59892.197 | AO77: =AN77+AO76 -> 53912.519 | AP77: =AO77+AP76 -> 51130.992 | AQ77: =AP77+AQ76 -> 43549.512 | AR77: =AQ77+AR76 -> 38903.299 | AS77: =AR77+AS76 -> 32688.142 | AT77: =AS77+AT76 -> 32586.352 | AU77: =AT77+AU76 -> 32606.752 | ... BB77: =BA77+BB76 -> 36375.658 | BC77: =27607.244+BC76 -> 24976.815
B79: check | C79: =C77-C113 -> 0 | D79: =D77-D113 -> 0 | E79: =E77-E113 -> 0 | F79: =F77-F113 -> 0 | G79: =G77-G113 -> 0 | H79: =H77-H113 -> 0 | I79: =I77-I113 -> 0 | J79: =J77-J113 -> 0.015 | ... Q79: =Q77-Q113 -> 0.015 | S79: =S77-S113 -> -49397.126 | T79: =T77-T113 -> -49397.126 | U79: =U77-U113 -> -49397.126 | V79: =V77-V113 -> -49397.126 | W79: =W77-W113 -> 0 | X79: =X77-X113 -> 0 | Y79: =Y77-Y113 -> 0 | Z79: =Z77-Z113 -> 0 | ... BC79: =BC77-BC113 -> 0.015
B81: LTM | C81: =+C56 -> 42735 | D81: =+D56 -> 43100 | E81: =+E56 -> 43465 | F81: =+F56 -> 43830 | G81: =+G56 -> 43830 | H81: =+H56 -> 44196 | I81: =+I56 -> 44561 | J81: =+J56 -> 44561 | ... Q81: =+Q56 -> 46112 | S81: =+S56 -> 42825 | T81: =+T56 -> 42916 | U81: =+U56 -> 43008 | V81: =+V56 -> 43100 | W81: =+W56 -> 43190 | X81: =X56 -> 43281 | Y81: =Y3 -> 43373 | Z81: =Z3 -> 43465 | AA81: =+AA56 -> 43555 | AB81: =+AB56 -> 43646 | AC81: =+AC56 -> 43738 | AD81: =+AD56 -> 43830 | AE81: =+AE56 -> 43921 | AF81: =+AF56 -> 44012 | AG81: =+AG56 -> 44104 | AH81: =+AH56 -> 44196 | ... BC81: =+BC56 -> 46112
B82: =+B9 -> Net Sales including non-recurring licensing revenues | C82: =+C9 -> 96287.4 | D82: =+D9 -> 93586.2 | E82: =+E9 -> 101282.3 | F82: =+F9 -> 101492.18 | G82: =+G9 -> 101757.18 | H82: =+H9 -> 97361.634 | I82: =+I9 -> 103521.82 | ... Q82: =+Q9 -> 58417.05 | V82: =+V9+U9+T9+S9 -> 93586.2 | W82: =+W9+V9+U9+T9 -> 94443.9 | X82: =+X9+W9+V9+U9 -> 98168.9 | Y82: =+Y9+X9+W9+V9 -> 100539.1 | Z82: =+Z9+Y9+X9+W9 -> 101282.3 | AA82: =+AA9+Z9+Y9+X9 -> 101865.5 | AB82: =+AB9+AA9+Z9+Y9 -> 99471.3 | AC82: =+AC9+AB9+AA9+Z9 -> 100224.25 | ... BC82: =+BC9+BB9+BA9+AZ9 -> 58417.05
B83: Operating profit | C83: =C19 -> 16598.134 | D83: =D19 -> 14243.165 | E83: =E19 -> 20252.525 | F83: =F19 -> 17209.03 | G83: =G19 -> 17005.03 | H83: =H19 -> 17525.368 | I83: =I19 -> 22183.226 | J83: =J19 -> 10688.9 | ... Q83: =Q19 -> 4877.292 | V83: =V19+U19+T19+S19 -> 14243.165 | W83: =W19+V19+U19+T19 -> 14837.241 | X83: =X19+W19+V19+U19 -> 19554.413 | Y83: =Y19+X19+W19+V19 -> 20218.07 | Z83: =Z19+Y19+X19+W19 -> 20252.525 | AA83: =AA19+Z19+Y19+X19 -> 20098.691 | AB83: =AB19+AA19+Z19+Y19 -> 15586.418 | AC83: =AC19+AB19+AA19+Z19 -> 15840.365 | ... BC83: =BC19+BB19+BA19+AZ19 -> 4877.292
B84: EBITDA | C84: =C47 -> 33577.967 | D84: =D47 -> 32747.93 | E84: =E47 -> 40087.029 | F84: =F47 -> 38217.586 | G84: =G47 -> 38013.826 | H84: =H47 -> 38786.155 | I84: =I47 -> 43601.595 | J84: =J47 -> 32107.269 | ... Q84: =Q47 -> 21847.404 | V84: =V47+U47+T47+S47 -> 32747.93 | W84: =W47+V47+U47+T47 -> 33598.974 | X84: =X47+W47+V47+U47 -> 38585.581 | Y84: =Y47+X47+W47+V47 -> 39677.829 | Z84: =Z47+Y47+X47+W47 -> 40087.029 | AA84: =AA47+Z47+Y47+X47 -> 40348.345 | AB84: =AB47+AA47+Z47+Y47 -> 36067.17 | AC84: =AC47+AB47+AA47+Z47 -> 36604.565 | ... BC84: =BC47+BB47+BA47+AZ47 -> 21847.404
B85: Adjusted EBITDA | C85: =+C52 -> 36715.351 | D85: =+D52 -> 35201.502 | E85: =+E52 -> 38524.745 | F85: =+F52 -> 39313.173 | G85: =+G52 -> 39330.413 | H85: =+H52 -> 38552.527 | I85: =+I52 -> 41207.632 | J85: =+J52 -> 28391.069 | ... Q85: =+Q52 -> 22741.928 | V85: =+V52+U52+T52+S52 -> 35201.502 | W85: =+W52+V52+U52+T52 -> 35795.889 | X85: =+X52+W52+V52+U52 -> 37158.967 | Y85: =+Y52+X52+W52+V52 -> 38183.177 | Z85: =+Z52+Y52+X52+W52 -> 38524.745 | AA85: =+AA52+Z52+Y52+X52 -> 38820.885 | AB85: =+AB52+AA52+Z52+Y52 -> 38060.633 | AC85: =+AC52+AB52+AA52+Z52 -> 38554.927 | ... BC85: =+BC52+BB52+BA52+AZ52 -> 22741.928
B86: Cash interest paid | C86: =-C60 -> 7633.026 | D86: =-D60 -> 8860.881 | E86: =-E60 -> 10129.304 | F86: =-F60 -> 9170.336 | G86: =-G60 -> 9180.141 | H86: =-H60 -> 9455.387 | I86: =-I60 -> 8258.243 | J86: =-J60 -> 8258.243 | ... Q86: =-Q60 -> 6347 | V86: =-V60-U60-T60-S60 -> 8860.881 | W86: =-W60-V60-U60-T60 -> 8852.813 | X86: =-X60-W60-V60-U60 -> 8771.305 | Y86: =-Y60-X60-W60-V60 -> 9186.906 | Z86: =-Z60-Y60-X60-W60 -> 10129.304 | AA86: =-AA60-Z60-Y60-X60 -> 9236.98 | AB86: =-AB60-AA60-Z60-Y60 -> 9262.496 | AC86: =-AC60-AB60-AA60-Z60 -> 9106.177 | ... BC86: =-BC60-BB60-BA60-AZ60 -> 6347
B87: Net Income | C87: =+C27 -> 5333.391 | D87: =+D27 -> 6026.376 | E87: =+E27 -> 7615.237 | F87: =+F27 -> 6202.813 | G87: =+G27 -> 6106.813 | H87: =+H27 -> 302.824 | I87: =+I27 -> 6578.254 | J87: =+J27 -> 7354.8 | ... P87: =+P27 -> -8561.714 | Q87: =Q27 -> -7835.914 | V87: =+V27+U27+T27+S27 -> 6026.376 | W87: =+W27+V27+U27+T27 -> 5307.123 | X87: =+X27+W27+V27+U27 -> 8186.311 | Y87: =+Y27+X27+W27+V27 -> 8145.383 | Z87: =+Z27+Y27+X27+W27 -> 7615.237 | AA87: =+AA27+Z27+Y27+X27 -> 7478.435 | AB87: =+AB27+AA27+Z27+Y27 -> 3981.094 | AC87: =+AC27+AB27+AA27+Z27 -> 3660.195 | ... BC87: =+BC27+BB27+BA27+AZ27 -> -7835.914
B88: Capex | C88: =-C63 -> 26370.374 | D88: =-D63 -> 15848.095 | E88: =-E63 -> 17474.96 | F88: =-F63 -> 18126.781 | G88: =-G63 -> 18126.781 | H88: =-H63 -> 18611.321 | I88: =-I63 -> 22595.423 | J88: =-J63 -> 22595.423 | ... Q88: =-Q63 -> 12718.359 | V88: =-V63-U63-T63-S63 -> 15848.095 | W88: =-W63-V63-U63-T63 -> 14331.324 | X88: =-X63-W63-V63-U63 -> 15097.626 | Y88: =-Y63-X63-W63-V63 -> 16698.242 | Z88: =-Z63-Y63-X63-W63 -> 17474.96 | AA88: =-AA63-Z63-Y63-X63 -> 18746.769 | AB88: =-AB63-AA63-Z63-Y63 -> 18440.115 | AC88: =-AC63-AB63-AA63-Z63 -> 17460.127 | ... BC88: =-BC63-BB63-BA63-AZ63 -> 12718.359
B89: Free cash flow | C89: =+C66 -> -7520.732 | D89: =+D66 -> -4217.406 | E89: =+E66 -> -4847.74 | F89: =+F66 -> -3710.262 | G89: =+G66 -> -5856.857 | H89: =+H66 -> -1358.522 | I89: =+I66 -> -4690.298 | J89: =+J66 -> -17316.354 | ... P89: =+P66 -> 4373.153 | Q89: =Q66 -> 3213.805 | V89: =+V66+U66+T66+S66 -> -4217.406 | W89: =+W66+V66+U66+T66 -> -2776.647 | X89: =+X66+W66+V66+U66 -> 6542.456 | Y89: =+Y66+X66+W66+V66 -> 7376.443 | Z89: =+Z66+Y66+X66+W66 -> -4847.74 | AA89: =+AA66+Z66+Y66+X66 -> -11788.022 | AB89: =+AB66+AA66+Z66+Y66 -> -16849.17 | AC89: =+AC66+AB66+AA66+Z66 -> -13518.198 | ... BC89: =+BC66+BB66+BA66+AZ66 -> 3213.805
B91: BALANCE SHEET | C91: =+C81 -> 42735 | D91: =+D81 -> 43100 | E91: =E3 -> 43465 | F91: =F3 -> 43830 | G91: =G3 -> 43830 | H91: =H3 -> 44196 | I91: =I3 -> 44561 | J91: =J3 -> 44561 | K91: =K3 -> 44926 | L91: =L3 -> 44926 | ... P91: =P3 -> 46022 | Q91: =+Q81 -> 46112 | S91: =+S81 -> 42825 | T91: =+T81 -> 42916 | U91: =+U81 -> 43008 | V91: =+V81 -> 43100 | W91: =+W81 -> 43190 | X91: =X3 -> 43281 | Y91: =Y3 -> 43373 | Z91: =Z3 -> 43465 | AA91: =+AA81 -> 43555 | AB91: =AB3 -> 43646 | AC91: =+AC81 -> 43738 | AD91: =+AD81 -> 43830 | AE91: =+AE81 -> 43921 | AF91: =+AF81 -> 44012 | AG91: =+AG81 -> 44104 | AH91: =+AH81 -> 44196 | AI91: =+AI81 -> 44286 | AJ91: =+AJ81 -> 44377 | ... BC91: =+BC81 -> 46112
B93: Tangible fixed assets | C93: 86783.572 | D93: 85719.81 | E93: 87342.53 | F93: =83329.232+7553.052 -> 90882.284 | G93: =83329.232+7553.052 -> 90882.284 | H93: =83281.627+7212.165 -> 90493.792 | I93: =87922.126+7604.567 -> 95526.693 | J93: =87922.126+7604.567 -> 95526.693 | K93: =82236.399+6670.298 -> 88906.697 | L93: =82236.399+6670.298 -> 88906.697 | M93: =77848.1+6085.9 -> 83934 | N93: =77848.1+6085.9 -> 83934 | O93: =63664.261+3336.917 -> 67001.178 | P93: =61142.7+4184.5 -> 65327.2 | Q93: =BC93 -> 65039.6 | S93: 86771.538 | T93: 85560.825 | U93: 84869.961 | V93: =+D93 -> 85719.81 | W93: 84176.944 | X93: 83738.439 | Y93: 84265.782 | Z93: =E93 -> 87342.53 | AA93: =83691.784+7988.523 -> 91680.307 | AB93: =82753.5+7726.8 -> 90480.3 | AC93: =83368.358+7676.159 -> 91044.517 | AD93: =F93 -> 90882.284 | AE93: =83329.5+7477.7 -> 90807.2 | AF93: =82896.955+7165.78 -> 90062.735 | AG93: =83540.9+7227.7 -> 90768.6 | AH93: =H93 -> 90493.792 | AI93: =84100.5+6912.5 -> 91013 | AJ93: =84863.4+6911.5 -> 91774.9 | AK93: =87078.758+7122.599 -> 94201.357 | AL93: =I93 -> 95526.693 | AM93: =85551.3+7009.9 -> 92561.2 | AN93: =85914+6723.9 -> 92637.9 | AO93: =82295+6548.3 -> 88843.3 | AP93: =K93 -> 88906.697 | AQ93: =81596.663+6581.288 -> 88177.951 | AR93: =80732.3+6403 -> 87135.3 | AS93: =79091.3+6229.3 -> 85320.6 | AT93: =M93 -> 83934 | AU93: =70412.7+4927 -> 75339.7 | AV93: =66970.9+4598.6 -> 71569.5 | AW93: =65396.1+4151.2 -> 69547.3 | AX93: =O93 -> 67001.178 | AY93: =61643.87+3140.997 -> 64784.867 | AZ93: =59985.684+3034.355 -> 63020.039 | BA93: =60094.005+3288.584 -> 63382.589 | BB93: =P93 -> 65327.2 | BC93: =59624.5+5415.1 -> 65039.6
B94: Net pension liability | C94: 520.473 | D94: 716.095 | E94: 962.497 | F94: 1468.112 | G94: 1468.112 | H94: 2080.651 | I94: 1941.836 | J94: 1913.68 | K94: 771.468 | L94: 771.468 | M94: 733.1 | N94: 733.1 | O94: 772.482 | P94: 954.2 | Q94: =BC94 -> 934.8 | S94: 449.841 | T94: 440.881 | U94: 455.116 | V94: =+D94 -> 716.095 | W94: 757.22 | X94: 783.71 | Y94: 808.362 | Z94: =E94 -> 962.497 | AA94: 988.041 | AB94: 1019.1 | AC94: 1015.874 | AD94: =F94 -> 1468.112 | AE94: 1517.6 | AF94: 1531.859 | AG94: 1586.9 | AH94: =H94 -> 2080.651 | AI94: 2120.7 | AJ94: 2167.2 | AK94: 2199.269 | AL94: =I94 -> 1941.836 | AM94: 823.767 | AN94: 798.6 | AO94: 861.1 | AP94: =K94 -> 771.468 | AQ94: 795.071 | AR94: 817.8 | AS94: 816.1 | AT94: =M94 -> 733.1 | AU94: 688.5 | AV94: 688.4 | AW94: 672.6 | AX94: =O94 -> 772.482 | AY94: 776.903 | AZ94: 0 | BA94: 830.863 | BB94: =P94 -> 954.2 | BC94: 934.8
B95: Inventory | C95: 1899.078 | D95: 1492.947 | E95: 1026.428 | F95: 1151.421 | G95: 1151.421 | H95: 1641.3 | I95: 2212.859 | J95: 2212.859 | K95: 1448.278 | L95: 1448.278 | M95: 1261.3 | N95: 1261.3 | O95: 463.225 | P95: 584.878 | Q95: =BC95 -> 557.7 | S95: 1880.975 | T95: 1890.874 | U95: 1577.324 | V95: =+D95 -> 1492.947 | W95: 1044.324 | X95: 1132.085 | Y95: 1045.297 | Z95: =E95 -> 1026.428 | AA95: 1042.466 | AB95: 1224 | AC95: 1354.241 | AD95: =F95 -> 1151.421 | AE95: 1115.7 | AF95: =1290.76 -> 1290.76 | AG95: 1780 | AH95: =H95 -> 1641.3 | AI95: 2259.5 | AJ95: 2458 | AK95: 2272.028 | AL95: =I95 -> 2212.859 | AM95: 2096.181 | AN95: 2211.7 | AO95: 2114.1 | AP95: =K95 -> 1448.278 | AQ95: 1475.058 | AR95: 1369.2 | AS95: 1312.6 | AT95: =M95 -> 1261.3 | AU95: 823.6 | AV95: 766.9 | AW95: 565.6 | AX95: =O95 -> 463.225 | AY95: 505.436 | AZ95: 546.716 | BA95: 419.508 | BB95: =P95 -> 584.878 | BC95: 557.7
B96: Trade accounts receivables, net | C96: 30992.004 | D96: 30357.412 | E96: 28225.291 | F96: 25335.712 | G96: =14486.184 -> 14486.184 | H96: =12343.797 -> 12343.797 | I96: 13312.919 | J96: 28581.358 | K96: 8457.3 | L96: 8457.3 | M96: 8131.5 | N96: 8131.5 | O96: 6175.819 | P96: 5815.2 | Q96: =BC96 -> 5296.7 | S96: 26275.871 | T96: 22633.869 | U96: 20872.494 | V96: =+D96 -> 30357.412 | W96: 28082.348 | X96: 27421.035 | Y96: 23687.944 | Z96: =E96 -> 28225.291 | AA96: 35155.92 | AB96: 33248.544 | AC96: 28440.722 | AD96: =F96 -> 25335.712 | AE96: 20749.1 | AF96: 22927.121 | AG96: 18064.7 | AH96: =H96 -> 12343.797 | AI96: 21888.9 | AJ96: 21294.7 | AK96: 15414.332 | AL96: =I96 -> 13312.919 | AM96: 8725.292 | AN96: 9051.8 | AO96: 9505.1 | AP96: =K96 -> 8457.3 | AQ96: 9336.9 | AR96: =8629.3 -> 8629.3 | AS96: 9339.6 | AT96: =M96 -> 8131.5 | AU96: 9620.1 | AV96: 8043.7 | AW96: 7664.4 | AX96: =O96 -> 6175.819 | AY96: 6153.545 | AZ96: 5553.304 | BA96: 6146.914 | BB96: =P96 -> 5815.2 | BC96: 5296.7
B97: Trade creditors /payables | C97: 50926.585 | D97: 44353.813 | E97: 41699.815 | F97: 33876.5 | G97: =20909.655 -> 20909.655 | H97: =21943.227 -> 21943.227 | I97: 22588.45 | J97: 41219.137 | K97: 16083.9 | L97: 16083.9 | M97: 13673.6 | N97: 12861.122 | O97: =11329.869 -> 11329.869 | P97: 14384.3 | Q97: =BC97 -> 13569.8 | S97: 48814.949 | T97: 41875.976 | U97: 35709.728 | V97: =+D97 -> 44353.813 | W97: 43737.754 | X97: 40257.72 | Y97: 35628.11 | Z97: =E97 -> 41699.815 | AA97: 45924.301 | AB97: 44859.165 | AC97: 39705.067 | AD97: =F97 -> 33876.5 | AE97: 24341.9 | AF97: 26453.798 | AG97: 26621.3 | AH97: =H97 -> 21943.227 | AI97: 26806.2 | AJ97: 25927 | AK97: 23038.457 | AL97: =I97 -> 22588.45 | AM97: 17235.545 | AN97: 18050.9 | AO97: 17411.9 | AP97: =K97 -> 16083.9 | AQ97: 17554.8 | AR97: 16112.7 | AS97: 15600.8 | AT97: =M97 -> 13673.6 | AU97: 13784.1 | AV97: 12204.2 | AW97: 13065 | AX97: =O97 -> 11329.869 | AY97: 12746.09 | AZ97: 11903.975 | BA97: 12553.011 | BB97: =P97 -> 14384.3 | BC97: 13569.8
B98: Net working capital | C98: =C95+C96-C97 -> -18035.503 | D98: =D95+D96-D97 -> -12503.454 | E98: =E95+E96-E97 -> -12448.096 | F98: =F95+F96-F97 -> -7389.367 | G98: =G95+G96-G97 -> -5272.05 | H98: =H95+H96-H97 -> -7958.13 | I98: =I95+I96-I97 -> -7062.672 | J98: =J95+J96-J97 -> -10424.92 | ... Q98: =Q95+Q96-Q97 -> -7715.4 | S98: =S95+S96-S97 -> -20658.103 | T98: =T95+T96-T97 -> -17351.233 | U98: =U95+U96-U97 -> -13259.91 | V98: =V95+V96-V97 -> -12503.454 | W98: =W95+W96-W97 -> -14611.082 | X98: =X95+X96-X97 -> -11704.6 | Y98: =Y95+Y96-Y97 -> -10894.869 | Z98: =Z95+Z96-Z97 -> -12448.096 | ... BC98: =BC95+BC96-BC97 -> -7715.4
B99: % of revenues | C99: =+C98/C82 -> -0.18730907 | D99: =+D98/D82 -> -0.13360361 | E99: =+E98/E82 -> -0.12290495 | F99: =+F98/F82 -> -0.072807254 | G99: =+G98/G82 -> -0.051810103 | H99: =+H98/H82 -> -0.081737843 | I99: =+I98/I82 -> -0.068223992 | J99: =+J98/J82 -> -0.14103854 | ... Q99: =+Q98/Q82 -> -0.13207445 | V99: =+V98/V82 -> -0.13360361 | W99: =+W98/W82 -> -0.15470647 | X99: =+X98/X82 -> -0.11922921 | Y99: =+Y98/Y82 -> -0.1083645 | Z99: =+Z98/Z82 -> -0.12290495 | AA99: =+AA98/AA82 -> -0.095478008 | AB99: =+AB98/AB82 -> -0.10441827 | AC99: =+AC98/AC82 -> -0.098879304 | ... BC99: =+BC98/BC82 -> -0.13207445
B101: Receivables days | C101: =C96/C7*365 -> 117.48247 | D101: =D96/D7*365 -> 118.39839 | E101: =E96/E7*365 -> 104.53949 | F101: =F96/F7*365 -> 91.115737 | G101: =G96/G7*365 -> 51.961514 | H101: =H96/H7*365 -> 46.275784 | I101: =I96/I7*365 -> 46.939044 | J101: =J96/J7*365 -> 141.13697 | ... Q101: =Q96/Q7*365 -> 33.094713 | S101: =S96/S7*365/4 -> 109.21201 | T101: =T96/T7*365/4 -> 89.888085 | U101: =U96/U7*365/4 -> 84.040731 | V101: =V96/V7*365/4 -> 106.57522 | W101: =W96/W7*365/4 -> 112.33185 | X101: =X96/X7*365/4 -> 100.17373 | Y101: =Y96/Y7*365/4 -> 89.976934 | Z101: =Z96/Z7*365/4 -> 96.335474 | ... BC101: =BC96/BC7*365/4 -> 33.303971
B102: Payable days | C102: =C97/-C12*365 -> 354.88713 | D102: =D97/-D12*365 -> 305.55132 | E102: =E97/-E12*365 -> 263.1505 | F102: =F97/-F12*365 -> 210.55507 | G102: =G97/-G12*365 -> 129.20882 | H102: =H97/-H12*365 -> 140.53915 | I102: =I97/-I12*365 -> 138.42468 | J102: =J97/-J12*365 -> 322.48283 | ... Q102: =Q97/-Q12*365 -> 137.50159 | S102: =S97/-S12*365/4 -> 351.97028 | T102: =T97/-T12*365/4 -> 298.04579 | U102: =U97/-U12*365/4 -> 258.77591 | V102: =V97/-V12*365/4 -> 271.35577 | W102: =W97/-W12*365/4 -> 305.58072 | X102: =X97/-X12*365/4 -> 243.60591 | Y102: =Y97/-Y12*365/4 -> 228.81126 | Z102: =Z97/-Z12*365/4 -> 245.64289 | ... BC102: =BC97/-BC12*365/4 -> 140.04278
B103: Inventory days | C103: =C95/-C12*365 -> 13.23392 | D103: =D95/-D12*365 -> 10.284841 | E103: =E95/-E12*365 -> 6.4773679 | F103: =F95/-F12*365 -> 7.1565104 | G103: =G95/-G12*365 -> 7.1150742 | H103: =H95/-H12*365 -> 10.511987 | I103: =I95/-I12*365 -> 13.56066 | J103: =J95/-J12*365 -> 17.312566 | ... Q103: =Q95/-Q12*365 -> 5.651125 | S103: =S95/-S12*365/4 -> 13.562388 | T103: =T95/-T12*365/4 -> 13.458004 | U103: =U95/-U12*365/4 -> 11.430315 | V103: =V95/-V12*365/4 -> 9.1338209 | W103: =W95/-W12*365/4 -> 7.2963345 | X103: =X95/-X12*365/4 -> 6.8504276 | Y103: =Y95/-Y12*365/4 -> 6.7131185 | Z103: =Z95/-Z12*365/4 -> 6.0464235 | ... BC103: =BC95/-BC12*365/4 -> 5.7555644
B105: Debt Breakdown
B106: Short-term debt | C106: =850.9 -> 850.9 | D106: =307 -> 307 | E106: =988.4 -> 988.4 | F106: 491.9 | G106: 491.951 | H106: 616.991 | I106: 4106.432 | J106: 4106.432 | K106: 1000 | L106: 1000 | M106: 9988 | N106: 9988 | O106: 4556.95 | P106: 3737 | Q106: =BC106 -> 0 | S106: =1536.3 -> 1536.3 | T106: =10608.8 -> 10608.8 | U106: =10039.8 -> 10039.8 | V106: =+D106 -> 307 | W106: =307 -> 307 | X106: =471 -> 471 | Y106: =1004.4 -> 1004.4 | Z106: =E106 -> 988.4 | AA106: 972.3 | AB106: 792.1 | AC106: 10484.4 | AD106: =F106 -> 491.9 | AE106: 492 | AF106: 617 | AG106: 15012.7 | AH106: =H106 -> 616.991 | AI106: 617 | AJ106: 1481.1 | AK106: 2045.613 | AL106: =I106 -> 4106.432 | AM106: 1549.6 | AN106: 1000 | AO106: 1000 | AP106: =K106 -> 1000 | AQ106: 0 | AR106: 9977.6 | AS106: 9982.8 | AT106: =M106 -> 9988 | AU106: 13578.5 | AV106: 3996.1 | AW106: 4285.7 | AX106: =O106 -> 4556.95 | AY106: 4234.769 | AZ106: 3909.996 | BA106: =3802 -> 3802 | BB106: =P106 -> 3737 | BC106: 0
B107: Long-term debt | C107: =126146.7 -> 126146.7 | D107: =121993.1 -> 121993.1 | E107: =120983.6 -> 120983.6 | F107: 120444.7 | G107: 120444.74 | H107: 121935.98 | I107: 121685.71 | J107: 121685.71 | K107: 104240.65 | L107: 104240.65 | M107: 78547.9 | N107: 78547.9 | O107: 98398.223 | P107: 82257.2 | Q107: =BC107 -> 82048.1 | S107: =117465.5 -> 117465.5 | T107: =105784.4 -> 105784.4 | U107: =106130.3 -> 106130.3 | V107: =+D107 -> 121993.1 | W107: =116643.1 -> 116643.1 | X107: =122087.4 -> 122087.4 | Y107: =117354 -> 117354 | Z107: =E107 -> 120983.6 | AA107: 120029.7 | AB107: 133196.8 | AC107: 124283.3 | AD107: =F107 -> 120444.7 | AE107: 157291.8 | AF107: 153204.7 | AG107: 131907.6 | AH107: =H107 -> 121935.98 | AI107: 124218.2 | AJ107: 120720 | AK107: 123389.1 | AL107: =I107 -> 121685.71 | AM107: 111453.1 | AN107: 112720.2 | AO107: 106668.3 | AP107: =K107 -> 104240.65 | AQ107: 98911.5 | AR107: 85442.4 | AS107: 80721.6 | AT107: =M107 -> 78547.9 | AU107: 73570.6 | AV107: 89678.6 | AW107: 94254.4 | AX107: =O107 -> 98398.223 | AY107: 92688.083 | AZ107: 84954.472 | BA107: 83259.055 | BB107: =P107 -> 82257.2 | BC107: 82048.1
B108: Lease obligations | C108: =575.6+5816.2 -> 6391.8 | D108: =580.9+5041.9 -> 5622.8 | E108: =651.8+4666.1 -> 5317.9 | F108: 9363.6 | G108: =1257.766+8105.754 -> 9363.52 | H108: =1277.754+8014.597 -> 9292.351 | I108: =1478.382+8202.177 -> 9680.559 | J108: =1478.382+8202.177 -> 9680.559 | K108: =1373.2+6995.8 -> 8369 | L108: =1373.2+6995.8 -> 8369 | M108: =1280.9+6010.6 -> 7291.5 | N108: =1280.9+6010.6 -> 7291.5 | O108: =1242.957+4143.682 -> 5386.639 | P108: =1583.9+3852.1 -> 5436 | Q108: =BC108 -> 6509.7 | S108: =540.7+5241.1 -> 5781.8 | T108: =532.2+4988.6 -> 5520.8 | U108: =543.4+4810.8 -> 5354.2 | V108: =+D108 -> 5622.8 | W108: =566.6+4610.5 -> 5177.1 | X108: =4953.2+627.3 -> 5580.5 | Y108: =683.5+4523.4 -> 5206.9 | Z108: =E108 -> 5317.9 | AA108: 9897.5 | AB108: 9612.5 | AC108: 9656.6 | AD108: =F108 -> 9363.6 | AE108: 10627.5 | AF108: 10079.3 | AG108: 9840 | AH108: =H108 -> 9292.351 | AI108: =1255.1+7769.1 -> 9024.2 | AJ108: =1301+7602.2 -> 8903.2 | AK108: =1341.5+7867 -> 9208.5 | AL108: =I108 -> 9680.559 | AM108: 8874.4 | AN108: =1451.4+7135.4 -> 8586.8 | AO108: =1217+7140 -> 8357 | AP108: =K108 -> 8369 | AQ108: =6693.7+1358.5 -> 8052.2 | AR108: =1289.5+6440.9 -> 7730.4 | AS108: =1266.8+6250.7 -> 7517.5 | AT108: =M108 -> 7291.5 | AU108: =1143.9+4791.8 -> 5935.7 | AV108: =1183.5+4562.7 -> 5746.2 | AW108: =1175+4161.6 -> 5336.6 | AX108: =O108 -> 5386.639 | AY108: =1244.874+3805.597 -> 5050.471 | AZ108: =1203.42+3435.8 -> 4639.22 | BA108: =1265.657+3436.956 -> 4702.613 | BB108: =P108 -> 5436 | BC108: =1843.9+4665.8 -> 6509.7
B109: Notes Payable | C109: =1202.3+3650.7 -> 4853 | D109: =1178.4+2505.6 -> 3684 | E109: =1288.4+1288.4 -> 2576.8 | F109: 1324.1 | G109: 1324.063 | H109: 0 | I109: 0 | J109: 0 | K109: 0 | L109: 0 | M109: 0 | N109: 0 | O109: 0 | P109: 0 | Q109: =BC109 -> 0 | S109: =1153.3+2452.2 -> 3605.5 | T109: =1161.7+2470 -> 3631.7 | U109: =1170.1+2487.8 -> 3657.9 | V109: =U109 -> 3657.9 | W109: =1261.7+1261.7 -> 2523.4 | X109: =1270.6+1270.6 -> 2541.2 | Y109: =1279.5+1279.5 -> 2559 | Z109: =E109 -> 2576.8 | AA109: 1297.3 | AB109: 1306.3 | AC109: 1315.2 | AD109: =F109 -> 1324.1 | AE109: 0 | AF109: 0 | AG109: 0 | AH109: =H109 -> 0 | AI109: 0 | AJ109: 0 | AK109: 0 | AL109: =I109 -> 0 | AM109: 0 | AN109: 0 | AO109: 0 | AP109: =K109 -> 0 | AQ109: 0 | AR109: 0 | AS109: 0 | AT109: =M109 -> 0 | AU109: 0 | AV109: 0 | AW109: 0 | AX109: =O109 -> 0 | AY109: 0 | AZ109: 0 | BA109: 0 | BB109: =P109 -> 0 | BC109: 0
B110: Total Debt | C110: =SUM(C106:C109) -> 138242.4 | D110: =SUM(D106:D109) -> 131606.9 | E110: =SUM(E106:E109) -> 129866.7 | F110: =SUM(F106:F109) -> 131624.3 | G110: =SUM(G106:G109) -> 131624.28 | H110: =SUM(H106:H109) -> 131845.32 | I110: =SUM(I106:I109) -> 135472.7 | J110: =SUM(J106:J109) -> 135472.7 | ... Q110: =SUM(Q106:Q109) -> 88557.8 | S110: =SUM(S106:S109) -> 128389.1 | T110: =SUM(T106:T109) -> 125545.7 | U110: =SUM(U106:U109) -> 125182.2 | V110: =SUM(V106:V109) -> 131580.8 | W110: =SUM(W106:W109) -> 124650.6 | X110: =SUM(X106:X109) -> 130680.1 | Y110: =SUM(Y106:Y109) -> 126124.3 | Z110: =SUM(Z106:Z109) -> 129866.7 | ... BC110: =SUM(BC106:BC109) -> 88557.8
B113: Cash and equivalents | C113: 47546.083 | D113: 38734.949 | E113: 32068.291 | F113: 27451.997 | G113: 27452.265 | H113: 29058.093 | I113: 25593.362 | J113: 25828.2 | K113: 51130.992 | L113: 51130.992 | M113: 32586.3 | N113: 32586.3 | O113: 46193.173 | P113: 36375.7 | Q113: =BC113 -> 24976.8 | S113: 43538.281 | T113: 41222.721 | U113: 38658.556 | V113: =+D113 -> 38734.949 | W113: 37705.453 | X113: 44592.993 | Y113: 42426.757 | Z113: =E113 -> 32068.291 | AA113: 23563.014 | AB113: 37918.1 | AC113: 38710.917 | AD113: =F113 -> 27451.997 | AE113: 44940.269 | AF113: 45481.794 | AG113: 44852.2 | AH113: =H113 -> 29058.093 | AI113: 28862.207 | AJ113: 26381.3 | AK113: 21704.782 | AL113: =I113 -> 25593.362 | AM113: 61071.991 | AN113: 59892.2 | AO113: 53912.5 | AP113: =K113 -> 51130.992 | AQ113: 43549.512 | AR113: 38903.3 | AS113: 32688.1 | AT113: =M113 -> 32586.3 | AU113: 32606.8 | AV113: 36960.4 | AW113: 41033.7 | AX113: =O113 -> 46193.173 | AY113: 43536.716 | AZ113: 38449.22 | BA113: 37856.776 | BB113: =P113 -> 36375.7 | BC113: =24976.8 -> 24976.8
B115: Net debt | C115: =C110-C113 -> 90696.317 | D115: =D110-D113 -> 92871.951 | E115: =E110-E113 -> 97798.409 | F115: =F110-F113 -> 104172.3 | G115: =G110-G113 -> 104172.01 | H115: =H110-H113 -> 102787.23 | I115: =I110-I113 -> 109879.34 | J115: =J110-J113 -> 109644.5 | ... Q115: =Q110-Q113 -> 63581 | S115: =S110-S113 -> 84850.819 | T115: =T110-T113 -> 84322.979 | U115: =U110-U113 -> 86523.644 | V115: =V110-V113 -> 92845.851 | W115: =W110-W113 -> 86945.147 | X115: =X110-X113 -> 86087.107 | Y115: =Y110-Y113 -> 83697.543 | Z115: =Z110-Z113 -> 97798.409 | ... BC115: =BC110-BC113 -> 63581
...

Sheet KPIS
B2: Grupo Televisa, S.A.B. | C2: Annual | D2: Annual | E2: Annual | F2: Annual | G2: Annual | H2: Annual | I2: Annual | J2: Annual | K2: Annual | L2: Annual | M2: Annual | N2: Annual | O2: Annual | P2: Annual | Q2: LTM | S2: Quarterly | T2: Quarterly | U2: Quarterly | V2: Quarterly | W2: Quarterly | X2: Quarterly | Y2: Quarterly | Z2: Quarterly | AA2: Quarterly | AB2: Quarterly | AC2: Quarterly | AD2: Quarterly | AE2: Quarterly | AF2: Quarterly | AG2: Quarterly | AH2: Quarterly | AI2: Quarterly | AJ2: Quarterly | AK2: Quarterly | AL2: Quarterly | AM2: Quarterly | AN2: Quarterly | AO2: Quarterly | AP2: Quarterly | AQ2: Quarterly | AR2: Quarterly | AS2: Quarterly | AT2: Quarterly | AU2: Quarterly | AV2: Quarterly | AW2: Quarterly | AX2: Quarterly | AY2: Quarterly | AZ2: Quarterly | BA2: Quarterly | BB2: Quarterly | BC2: Quarterly | BF2: Quarterly | BG2: Quarterly | BH2: Quarterly | BI2: Quarterly | BJ2: Quarterly
B3: (MXN millions) | C3: 42707 | D3: 43100 | E3: 43465 | F3: 43830 | G3: 43830 | H3: 44196 | I3: 44561 | J3: 44561 | K3: 44926 | L3: 44926 | M3: 45291 | N3: 45291 | O3: 45657 | P3: 46022 | Q3: =BC3 -> 46112 | S3: 42801 | T3: 42892 | U3: 42987 | V3: 43079 | W3: 43190 | X3: 43281 | Y3: 43373 | Z3: 43465 | AA3: 43555 | AB3: 43646 | AC3: 43738 | AD3: 43830 | AE3: 43921 | AF3: 44012 | AG3: 44104 | AH3: 44196 | AI3: 44286 | AJ3: 44377 | AK3: 44469 | AL3: 44561 | AM3: 44651 | AN3: 44742 | AO3: 44834 | AP3: 44926 | AQ3: 45016 | AR3: 45107 | AS3: 45199 | AT3: 45291 | AU3: 45382 | AV3: 45473 | AW3: 45565 | AX3: 45657 | AY3: 45747 | AZ3: 45838 | BA3: 45930 | BB3: 46022 | BC3: 46112 | BF3: 43830 | BG3: 44286 | BH3: 44377 | BI3: 44469 | BJ3: 44560
C4: Act | D4: Act | E4: Act | F4: Act | G4: Act | H4: Act | I4: Act | J4: Act | K4: Act | L4: Act | M4: Act | N4: Act | O4: Act | P4: Act | Q4: Act | S4: Act | T4: Act | U4: Act | V4: Act | W4: Act | X4: Act | Y4: Act | Z4: Act | AA4: Act | AB4: Act | AC4: Act | AD4: Act | AE4: Act | AF4: Act | AG4: Act | AH4: Act | AI4: Act | AJ4: Act | AK4: Act | AL4: Act | AM4: Act | AN4: Act | AO4: Act | AP4: Act | AQ4: Act | AR4: Act | AS4: Act | AT4: Act | AU4: Act | AV4: Act | AW4: Act | AX4: Act | AY4: Act | AZ4: Act | BA4: Act | BB4: Act | BC4: Act
C5: FY | D5: FY | E5: FY | F5: FY | G5: FY | H5: FY | I5: FY | J5: FY | K5: FY | L5: FY | M5: FY | N5: FY | O5: FY | P5: FY | Q5: LTM | S5: Q1 | T5: Q2 | U5: Q3 | V5: Q4 | W5: Q1 | X5: Q2 | Y5: Q3 | Z5: Q4 | AA5: Q1 | AB5: Q2 | AC5: Q3 | AD5: Q4 | AE5: Q1 | AF5: Q2 | AG5: Q3 | AH5: Q4 | AI5: Q1 | AJ5: Q2 | AK5: Q3 | AL5: Q4 | AM5: Q1 | AN5: Q2 | AO5: Q3 | AP5: Q4 | AQ5: Q1 | AR5: Q2 | AS5: Q3 | AT5: Q4 | AU5: Q1 | AV5: Q2 | AW5: Q3 | AX5: Q4 | AY5: Q1 | AZ5: Q2 | BA5: Q3 | BB5: Q4 | BC5: Q1 | BF5: Q4 | BG5: Q1 | BH5: Q2 | BI5: Q3 | BJ5: Q4
G6: Restated | J6: Restated | L6: Restated | N6: Restated | BF6: Restated | BG6: Restated | BH6: Restated | BI6: Restated | BJ6: Restated
B8: Net Sales by Business Segment
B9: Subtotal Content | D9: 33997.2 | T9: 8075.9 | U9: 8024.9
B10: World Cup rights
B11: Content | C11: 36686.7 | D11: =+D9+D10 -> 33997.2 | E11: 36490.1 | F11: 34795.5 | G11: 35060.5 | H11: 32613 | I11: 35941.918 | J11: 0 | K11: 0 | L11: 0 | M11: 0 | N11: 0 | O11: 0 | S11: 7290.7 | T11: =+T9+T10 -> 8075.9 | U11: =+U9+U10 -> 8024.9 | V11: =D11-U11-T11-S11 -> 10605.7 | W11: 7899.4 | X11: 9247.9 | Y11: 8700 | Z11: =E11-Y11-X11-W11 -> 10642.8 | AA11: 7184.9 | AB11: 8050 | AC11: 8659 | AD11: =F11-AC11-AB11-AA11 -> 10901.6 | AE11: 6727.6 | AF11: 6740.6 | AG11: 8033.4 | AH11: =H11-AG11-AF11-AE11 -> 11111.4 | AI11: 7416.1 | AJ11: 7856.8 | AK11: 9109.8 | AL11: =I11-AK11-AJ11-AI11 -> 11559.218 | AM11: 0 | AN11: 0 | AO11: 0 | AP11: =K11-AO11-AN11-AM11 -> 0 | AQ11: 0 | AR11: 0 | AS11: 0 | AT11: =N11-AS11-AR11-AQ11 -> 0 | AU11: 0 | AV11: 0 | AW11: 0 | AX11: =O11-SUM(AU11:AW11) -> 0 | AY11: 0 | AZ11: 0 | BA11: 0 | BC11: 0 | BF11: =G11-AC11-AB11-AA11 -> 11166.6 | BG11: 0 | BH11: 0 | BI11: 0 | BJ11: =J11-BG11-BH11-BI11 -> 0
B12: Sky | C12: 21941.2 | D12: 22196.6 | E12: 22002.2 | F12: 21347.1 | G12: 21347.1 | H12: 22134.7 | I12: 22026.616 | J12: 22026.616 | K12: 20339.038 | L12: 20339.038 | M12: 17585.2 | N12: 17585.175 | O12: 15337.288 | S12: 5540.6 | T12: 5641.9 | U12: 5445.2 | V12: =D12-U12-T12-S12 -> 5568.9 | W12: 5474.2 | X12: 5658.8 | Y12: 5407.3 | Z12: =E12-Y12-X12-W12 -> 5461.9 | AA12: 5281.6 | AB12: 5348.1 | AC12: 5338.3 | AD12: =F12-AC12-AB12-AA12 -> 5379.1 | AE12: 5405.3 | AF12: 5514.7 | AG12: 5597.9 | AH12: =H12-AG12-AF12-AE12 -> 5616.8 | AI12: 5624.8 | AJ12: 5570.1 | AK12: 5459.4 | AL12: =J12-AK12-AJ12-AI12 -> 5372.316 | AM12: 5275.7 | AN12: 5140.1 | AO12: 4986.6 | AP12: =K12-AO12-AN12-AM12 -> 4936.638 | AQ12: 4657.6 | AR12: 4449.5 | AS12: 4296.6 | AT12: =N12-AS12-AR12-AQ12 -> 4181.475 | AU12: 4083.6 | AV12: 3858.3 | AW12: 3731.1 | AX12: =O12-SUM(AU12:AW12) -> 3664.288 | AY12: 3544 | AZ12: 3229.5 | BA12: 3051 | BC12: 3544 | BF12: =G12-AC12-AB12-AA12 -> 5379.1 | BG12: 5624.8 | BH12: 5570.1 | BI12: 5459.4 | BJ12: =J12-BG12-BH12-BI12 -> 5372.316
B13: Cable | C13: 31891.6 | D13: 33048.3 | E13: 36233 | F13: 41702 | G13: 41702 | H13: 45367.1 | I13: 48020.929 | J13: 48020.929 | K13: 48411.776 | L13: 48411.776 | M13: 48802.5 | N13: 48802.544 | O13: 47393.111 | S13: 8096.3 | T13: 8036.7 | U13: 8322.5 | V13: =D13-U13-T13-S13 -> 8592.8 | W13: 8669.7 | X13: 8825.7 | Y13: 9219.9 | Z13: =E13-Y13-X13-W13 -> 9517.7 | AA13: 9898.1 | AB13: 10215.7 | AC13: 10572.1 | AD13: =F13-AC13-AB13-AA13 -> 11016.1 | AE13: 10824.7 | AF13: 11308.8 | AG13: 11407.9 | AH13: =H13-AG13-AF13-AE13 -> 11825.7 | AI13: 11676.5 | AJ13: 11981.6 | AK13: 12066.6 | AL13: =J13-AK13-AJ13-AI13 -> 12296.229 | AM13: 11804.5 | AN13: 11750 | AO13: 12394 | AP13: =K13-AO13-AN13-AM13 -> 12463.276 | AQ13: 12122.7 | AR13: 12291.5 | AS13: 12147.9 | AT13: =N13-AS13-AR13-AQ13 -> 12240.444 | AU13: 11908.7 | AV13: 11904.8 | AW13: 11675.4 | AX13: =O13-SUM(AU13:AW13) -> 11904.211 | AY13: 11537.7 | AZ13: 11602 | BA13: 11679.8 | BC13: 11537.7 | BF13: =G13-AC13-AB13-AA13 -> 11016.1 | BG13: 11676.5 | BH13: 11981.6 | BI13: 12066.6 | BJ13: =J13-BG13-BH13-BI13 -> 12296.229
B14: Other Businesses | C14: 8828.3 | D14: 7688.3 | E14: 8635.5 | F14: 8200.3 | G14: 8200.3 | H14: 4276 | I14: 5029.067 | J14: 4388.2 | K14: 7338.79 | L14: 0 | M14: 7870.6 | N14: 0 | O14: 0 | S14: 1758.6 | T14: 2009.6 | U14: 1801.7 | V14: =D14-U14-T14-S14 -> 2118.4 | W14: 1778.4 | X14: 2312.6 | Y14: 1946.5 | Z14: =E14-Y14-X14-W14 -> 2598 | AA14: 2260.3 | AB14: 1946.5 | AC14: 2633.1 | AD14: =F14-AC14-AB14-AA14 -> 1360.4 | AE14: 1756.5 | AF14: 567.1 | AG14: 782.5 | AH14: =H14-AG14-AF14-AE14 -> 1169.9 | AI14: 951.5 | AJ14: 1220.2 | AK14: 1409.1 | AL14: =J14-AK14-AJ14-AI14 -> 807.4 | AM14: 1661.1 | AN14: 1742.7 | AO14: 1932.7 | AP14: =K14-AO14-AN14-AM14 -> 2002.29 | AQ14: 1850.3 | AR14: 1917.6 | AS14: 1974.7 | AT14: =N14-AS14-AR14-AQ14 -> -5742.6 | AU14: 0 | AV14: 0 | AW14: 0 | AX14: =O14-SUM(AU14:AW14) -> 0 | AY14: 0 | AZ14: 0 | BA14: 0 | BC14: 0 | BF14: =G14-AC14-AB14-AA14 -> 1360.4 | BG14: 859.5 | BH14: 1051.1 | BI14: 1174.2 | BJ14: =J14-BG14-BH14-BI14 -> 1303.4
B15: Segment Net Sales | C15: =+C11+C12+C13+C14 -> 99347.8 | D15: =+D11+D12+D13+D14 -> 96930.4 | E15: =+E11+E12+E13+E14 -> 103360.8 | F15: =+F11+F12+F13+F14 -> 106044.9 | G15: =+G11+G12+G13+G14 -> 106309.9 | H15: =+H11+H12+H13+H14 -> 104390.8 | I15: =+I11+I12+I13+I14 -> 111018.53 | J15: =+J11+J12+J13+J14 -> 74435.745 | ... O15: =+O11+O12+O13+O14 -> 62730.399 | S15: =+S11+S12+S13+S14 -> 22686.2 | T15: =+T11+T12+T13+T14 -> 23764.1 | U15: =+U11+U12+U13+U14 -> 23594.3 | V15: =+V11+V12+V13+V14 -> 26885.8 | W15: =+W11+W12+W13+W14 -> 23821.7 | X15: =+X11+X12+X13+X14 -> 26045 | Y15: =+Y11+Y12+Y13+Y14 -> 25273.7 | Z15: =+Z11+Z12+Z13+Z14 -> 28220.4 | ... BA15: =+BA11+BA12+BA13+BA14 -> 14730.8 | BC15: =+BC11+BC12+BC13+BC14 -> 15081.7 | BF15: =+BF11+BF12+BF13+BF14 -> 28922.2 | BG15: =+BG11+BG12+BG13+BG14 -> 18160.8 | BH15: =+BH11+BH12+BH13+BH14 -> 18602.8 | BI15: =+BI11+BI12+BI13+BI14 -> 18700.2 | BJ15: =J15-BG15-BH15-BI15 -> 18971.945
B16: Intersegment Operations | C16: -3060.4 | D16: -3344.2 | E16: -4812.1 | F16: -5394.1 | G16: -5394.1 | H16: -7252.5 | I16: -7496.707 | J16: -520.3 | K16: -562.995 | L16: -135.046 | M16: -490.4 | N16: -164.883 | O16: -469.535 | S16: -731.9 | T16: -787.3 | U16: -931.3 | V16: =D16-U16-T16-S16 -> -893.7 | W16: -1009.7 | X16: -1066.7 | Y16: -1250.6 | Z16: =E16-Y16-X16-W16 -> -1485.1 | AA16: -1229.7 | AB16: -1252.7 | AC16: -1416.4 | AD16: =F16-AC16-AB16-AA16 -> -1495.3 | AE16: -1632.8 | AF16: -1799.8 | AG16: -1878.7 | AH16: =H16-AG16-AF16-AE16 -> -1941.2 | AI16: -1840 | AJ16: -1875.5 | AK16: -1917 | AL16: =J16-AK16-AJ16-AI16 -> 5112.2 | AM16: -132.1 | AN16: -99.3 | AO16: -61.6 | AP16: =K16-AO16-AN16-AM16 -> -269.995 | AQ16: -111 | AR16: -138.4 | AS16: -103.5 | AT16: =N16-AS16-AR16-AQ16 -> 188.017 | AU16: -40.9 | AV16: -42.8 | AW16: -43.7 | AX16: =O16-SUM(AU16:AW16) -> -342.135 | AY16: -108.1 | AZ16: -102.1 | BA16: -103.8 | BC16: -108.1 | BF16: =G16-AC16-AB16-AA16 -> -1495.3 | BG16: -138.5 | BH16: -128.9 | BI16: -110.1 | BJ16: =J16-BG16-BH16-BI16 -> -142.8
B17: Net Sales (LFL) | C17: =+C15+C16 -> 96287.4 | D17: =+D15+D16 -> 93586.2 | E17: =+E15+E16 -> 98548.7 | F17: =+F15+F16 -> 100650.8 | G17: =+G15+G16 -> 100915.8 | H17: =+H15+H16 -> 97138.3 | I17: =+I15+I16 -> 103521.82 | J17: =+J15+J16 -> 73915.445 | ... O17: =+O15+O16 -> 62260.864 | S17: =+S15+S16 -> 21954.3 | T17: =+T15+T16 -> 22976.8 | U17: =+U15+U16 -> 22663 | V17: =+V15+V16 -> 25992.1 | W17: =+W15+W16 -> 22812 | X17: =+X15+X16 -> 24978.3 | Y17: =+Y15+Y16 -> 24023.1 | Z17: =+Z15+Z16 -> 26735.3 | ... BA17: =+BA15+BA16 -> 14627 | BC17: =+BC15+BC16 -> 14973.6 | BF17: =+BF15+BF16 -> 27426.9 | BG17: =+BG15+BG16 -> 18022.3 | BH17: =+BH15+BH16 -> 18473.9 | BI17: =+BI15+BI16 -> 18590.1 | BJ17: =J17-BG17-BH17-BI17 -> 18829.145
B18: Non-Recurring Licensing revenues | C18: 0 | D18: 0 | E18: 2733.6 | F18: 0 | G18: 0 | H18: 0 | I18: 0 | J18: 0 | K18: 0 | L18: 0 | M18: 0 | N18: 0 | O18: 0 | S18: 0 | T18: 0 | U18: 0 | V18: =D18-U18-T18-S18 -> 0 | W18: 0 | X18: 1723.5 | Y18: 1010.1 | Z18: =E18-Y18-X18-W18 -> 0 | AA18: 0 | AB18: 0 | AC18: 0 | AD18: =F18-AC18-AB18-AA18 -> 0 | AE18: 0 | AF18: 0 | AG18: 0 | AH18: =H18-AG18-AF18-AE18 -> 0 | AI18: 0 | AJ18: 0 | AK18: 0 | AL18: =J18-AK18-AJ18-AI18 -> 0 | AM18: 0 | AN18: 0 | AO18: 0 | AP18: =K18-AO18-AN18-AM18 -> 0 | AQ18: 0 | AR18: 0 | AS18: 0 | AT18: =N18-AS18-AR18-AQ18 -> 0 | AU18: 0 | AV18: 0 | AW18: 0 | AX18: =O18-SUM(AU18:AW18) -> 0 | AY18: 0 | AZ18: 0 | BA18: 0 | BC18: 0 | BF18: =G18-AC18-AB18-AA18 -> 0 | BG18: 0 | BH18: 0 | BI18: 0 | BJ18: =J18-BG18-BH18-BI18 -> 0
B19: Held-to-sale Operations | F19: 841.4 | G19: 841.4 | H19: 223.3 | I19: 0 | J19: 0 | K19: 0 | L19: 0 | M19: 0 | N19: 0 | O19: 0 | AD19: =F19-AC19-AB19-AA19 -> 841.4 | AE19: 147.5 | AF19: 75.8 | AG19: 0 | AH19: =H19-AG19-AF19-AE19 -> 0 | AI19: 0 | AJ19: 0 | AK19: 0 | AL19: =J19-AK19-AJ19-AI19 -> 0 | AM19: 0 | AN19: 0 | AO19: 0 | AP19: =K19-AO19-AN19-AM19 -> 0 | AQ19: 0 | AR19: 0 | AS19: 0 | AT19: =N19-AS19-AR19-AQ19 -> 0 | AU19: 0 | AV19: 0 | AW19: 0 | AX19: =O19-SUM(AU19:AW19) -> 0 | AY19: 0 | AZ19: 0 | BA19: 0 | BC19: 0 | BF19: =G19-AC19-AB19-AA19 -> 841.4 | BG19: 0 | BH19: 0 | BI19: 0 | BJ19: =J19-BG19-BH19-BI19 -> 0
B20: Net Sales including non-recurring revenues | C20: =+C17+C18+C19 -> 96287.4 | D20: =+D17+D18+D19 -> 93586.2 | E20: =+E17+E18+E19 -> 101282.3 | F20: =+F17+F18+F19 -> 101492.2 | G20: =+G17+G18+G19 -> 101757.2 | H20: =+H17+H18+H19 -> 97361.6 | I20: =+I17+I18+I19 -> 103521.82 | J20: =+J17+J18+J19 -> 73915.445 | ... O20: =+O17+O18+O19 -> 62260.864 | S20: =+S17+S18+S19 -> 21954.3 | T20: =+T17+T18+T19 -> 22976.8 | U20: =+U17+U18+U19 -> 22663 | V20: =+V17+V18+V19 -> 25992.1 | W20: =+W17+W18+W19 -> 22812 | X20: =+X17+X18+X19 -> 26701.8 | Y20: =+Y17+Y18+Y19 -> 25033.2 | Z20: =+Z17+Z18+Z19 -> 26735.3 | ... BA20: =+BA17+BA18+BA19 -> 14627 | BC20: =+BC17+BC18+BC19 -> 14973.6 | BF20: =+BF17+BF18+BF19 -> 28268.3 | BG20: =+BG17+BG18+BG19 -> 18022.3 | BH20: =+BH17+BH18+BH19 -> 18473.9 | BI20: =+BI17+BI18+BI19 -> 18590.1 | BJ20: =J20-BG20-BH20-BI20 -> 18829.145
B21: Check | C21: =+C20-Model!C8 -> 96287.4 | D21: =+D20-Model!D9 -> 0 | E21: =+E20-Model!E9 -> 0 | F21: =+F20-Model!F9 -> 0.019 | G21: =+G20-Model!G9 -> 0.019 | H21: =+H20-Model!H9 -> -0.034 | I21: =+I20-Model!I9 -> 0 | J21: =+J20-Model!J9 -> 0.045 | K21: =+K20-Model!K9 -> 0 | L21: =+L20-Model!L9 -> 0 | M21: =+M20-Model!L9 -> 5152.132 | N21: =+N20-Model!N9 -> 0 | O21: =+O20-Model!O9 -> 0 | S21: =+S20-Model!S9 -> 0 | T21: =+T20-Model!T9 -> 0 | U21: =+U20-Model!U9 -> 0 | V21: =+V20-Model!V9 -> 0 | W21: =+W20-Model!W9 -> 0 | X21: =+X20-Model!X9 -> 0 | Y21: =+Y20-Model!Y9 -> 0 | Z21: =+Z20-Model!Z9 -> 0 | ... AJ21: =+AJ20-Model!AJ9 -> 0 | AK21: =+AJ20-Model!AJ9 -> 0 | AL21: =+AK20-Model!AK9 -> 0.033 | AM21: =+AM20-Model!AM9 -> 0 | AN21: =+AN20-Model!AN9 -> 0 | AO21: =+AO20-Model!AO9 -> 0 | AP21: =+AP20-Model!AP9 -> 0 | AQ21: =+AQ20-Model!AQ9 -> -0.033 | AR21: =+AR20-Model!AR9 -> 0 | AS21: =+AS20-Model!AS9 -> 1899.7 | AT21: =+AT20-Model!AT9 -> -9444.731 | ... BA21: =+BA20-Model!BA9 -> -0.086 | BC21: =+BC20-Model!BC9 -> 461.1 | BF21: =+BF20-Model!BF9 -> 0.068 | BG21: =+BG20-Model!BG9 -> 0 | BH21: =+BH20-Model!BH9 -> 0 | BI21: =+BI20-Model!BI9 -> 0 | BJ21: =+BJ20-Model!BJ9 -> 0.045
B23: Net Sales y-o-y Growth
B24: Content | D24: =D11/C11-1 -> -0.073309946 | E24: =E11/D11-1 -> 0.073326627 | F24: =F11/E11-1 -> -0.046439993 | G24: =G11/E11-1 -> -0.03917775 | H24: =H11/G11-1 -> -0.069807903 | I24: =I11/H11-1 -> 0.10207334 | W24: =W11/S11-1 -> 0.083489926 | X24: =X11/T11-1 -> 0.14512314 | Y24: =Y11/U11-1 -> 0.084125659 | Z24: =Z11/V11-1 -> 0.0034981189 | AA24: =AA11/W11-1 -> -0.090449908 | AB24: =AB11/X11-1 -> -0.12953211 | AC24: =AC11/Y11-1 -> -0.0047126437 | AD24: =AD11/Z11-1 -> 0.024316909 | ... AG24: =AG11/AC11-1 -> -0.072248528 | AH24: =AH11/BF11-1 -> -0.0049433131 | AI24: =AI11/AE11-1 -> 0.10233962 | AJ24: =AJ11/AF11-1 -> 0.16559357 | AK24: =AK11/AG11-1 -> 0.13399059 | AL24: =AL11/AH11-1 -> 0.040302572 | BF24: =BF11/Z11-1 -> 0.049216372
B25: Sky | D25: =D12/C12-1 -> 0.011640202 | E25: =E12/D12-1 -> -0.0087580981 | F25: =F12/E12-1 -> -0.029774295 | G25: =G12/E12-1 -> -0.029774295 | H25: =H12/G12-1 -> 0.036894941 | I25: =I12/H12-1 -> -0.0048830117 | J25: =J12/H12-1 -> -0.0048830117 | K25: =K12/J12-1 -> -0.0766154 | L25: =L12/J12-1 -> -0.0766154 | M25: =M12/K12-1 -> -0.13539667 | N25: =N12/L12-1 -> -0.1353979 | O25: =O12/N12-1 -> -0.12782853 | W25: =W12/S12-1 -> -0.011984262 | X25: =X12/T12-1 -> 0.0029954448 | Y25: =Y12/U12-1 -> -0.0069602586 | Z25: =Z12/V12-1 -> -0.019213848 | AA25: =AA12/W12-1 -> -0.035183223 | AB25: =AB12/X12-1 -> -0.054905634 | AC25: =AC12/Y12-1 -> -0.012760527 | AD25: =AD12/Z12-1 -> -0.01515956 | ... AG25: =AG12/AC12-1 -> 0.048629714 | AH25: =AH12/BF12-1 -> 0.044189548 | AI25: =AI12/AE12-1 -> 0.040608292 | AJ25: =AJ12/AF12-1 -> 0.010045877 | AK25: =AK12/AG12-1 -> -0.024741421 | AL25: =AL12/AH12-1 -> -0.043527275 | AM25: =AM12/BG12-1 -> -0.062064429 | AN25: =AN12/BH12-1 -> -0.077197896 | AO25: =AO12/AK12-1 -> -0.086602923 | AP25: =AP12/AL12-1 -> -0.081096868 | AQ25: =AQ12/AM12-1 -> -0.11715981 | AR25: =AR12/AN12-1 -> -0.13435536 | AS25: =AS12/AO12-1 -> -0.13837083 | AT25: =AT12/AP12-1 -> -0.15297111 | AU25: =AU12/AQ12-1 -> -0.12323944 | AV25: =AV12/AR12-1 -> -0.13286886 | ... BA25: =BA12/AW12-1 -> -0.18227868 | BC25: =BC12/AY12-1 -> 0 | BF25: =BF12/Z12-1 -> -0.01515956 | BG25: =BG12/AE12-1 -> 0.040608292 | BH25: =BH12/AF12-1 -> 0.010045877 | BI25: =BI12/AG12-1 -> -0.024741421 | BJ25: =BJ12/AH12-1 -> -0.043527275
B26: Cable | D26: =D13/C13-1 -> 0.036269739 | E26: =E13/D13-1 -> 0.096365017 | F26: =F13/E13-1 -> 0.15093975 | G26: =G13/E13-1 -> 0.15093975 | H26: =H13/G13-1 -> 0.087887871 | I26: =I13/H13-1 -> 0.058496774 | J26: =J13/H13-1 -> 0.058496774 | K26: =K13/J13-1 -> 0.008139097 | L26: =L13/J13-1 -> 0.008139097 | M26: =M13/K13-1 -> 0.0080708462 | N26: =N13/L13-1 -> 0.0080717551 | O26: =O13/N13-1 -> -0.028880318 | W26: =W13/S13-1 -> 0.070822474 | X26: =X13/T13-1 -> 0.098174624 | Y26: =Y13/U13-1 -> 0.10782818 | Z26: =Z13/V13-1 -> 0.10763663 | AA26: =AA13/W13-1 -> 0.14168887 | AB26: =AB13/X13-1 -> 0.15749459 | AC26: =AC13/Y13-1 -> 0.14666103 | AD26: =AD13/Z13-1 -> 0.15743299 | ... AG26: =AG13/AC13-1 -> 0.079057141 | AH26: =AH13/BF13-1 -> 0.073492434 | AI26: =AI13/AE13-1 -> 0.078690403 | AJ26: =AJ13/AF13-1 -> 0.059493492 | AK26: =AK13/AG13-1 -> 0.057740688 | AL26: =AL13/AH13-1 -> 0.039788681 | AM26: =AM13/BG13-1 -> 0.010962189 | AN26: =AN13/BH13-1 -> -0.019329639 | AO26: =AO13/AK13-1 -> 0.027132747 | AP26: =AP13/AL13-1 -> 0.013585222 | AQ26: =AQ13/AM13-1 -> 0.026955822 | AR26: =AR13/AN13-1 -> 0.046085106 | AS26: =AS13/AO13-1 -> -0.019856382 | AT26: =AT13/AP13-1 -> -0.017879087 | AU26: =AU13/AQ13-1 -> -0.017652833 | AV26: =AV13/AR13-1 -> -0.031460766 | ... BA26: =BA13/AW13-1 -> 0.00037686075 | BC26: =BC13/AY13-1 -> 0 | BF26: =BF13/Z13-1 -> 0.15743299 | BG26: =BG13/AE13-1 -> 0.078690403 | BH26: =BH13/AF13-1 -> 0.059493492 | BI26: =BI13/AG13-1 -> 0.057740688 | BJ26: =BJ13/AH13-1 -> 0.039788681
B27: Other Businesses | D27: =D14/C14-1 -> -0.12913018 | E27: =E14/D14-1 -> 0.12320019 | F27: =F14/E14-1 -> -0.050396619 | G27: =G14/E14-1 -> -0.050396619 | H27: =H14/G14-1 -> -0.47855566 | I27: =I14/H14-1 -> 0.17611483 | J27: =J14/H14-1 -> 0.026239476 | K27: =K14/J14-1 -> 0.67239187 | L27: =L14/J14-1 -> -1 | M27: =M14/K14-1 -> 0.072465624 | W27: =W14/S14-1 -> 0.011258956 | X27: =X14/T14-1 -> 0.15077627 | Y27: =Y14/U14-1 -> 0.080368541 | Z27: =Z14/V14-1 -> 0.22639728 | AA27: =AA14/W14-1 -> 0.27097391 | AB27: =AB14/X14-1 -> -0.15830667 | AC27: =AC14/Y14-1 -> 0.35273568 | AD27: =AD14/Z14-1 -> -0.47636644 | ... AG27: =AG14/AC14-1 -> -0.70282177 | AH27: =AH14/BF14-1 -> -0.14003234 | AI27: =AI14/AE14-1 -> -0.45829775 | AJ27: =AJ14/AF14-1 -> 1.1516487 | AK27: =AK14/AG14-1 -> 0.80076677 | AL27: =AL14/AH14-1 -> -0.30985554 | AM27: =AM14/BG14-1 -> 0.93263525 | AN27: =AN14/BH14-1 -> 0.65797736 | AO27: =AO14/AK14-1 -> 0.3715847 | AP27: =AP14/AL14-1 -> 1.4799232 | AQ27: =AQ14/AM14-1 -> 0.11390043 | AR27: =AR14/AN14-1 -> 0.10036151 | AS27: =AS14/AO14-1 -> 0.021731257 | AT27: =AT14/AP14-1 -> -3.8680161 | AU27: =AU14/AQ14-1 -> -1 | AV27: =AV14/AR14-1 -> -1 | ... BA27: =BA14/AW14-1 -> #DIV/0! | BC27: =BC14/AY14-1 -> #DIV/0! | BF27: =BF14/Z14-1 -> -0.47636644 | BG27: =BG14/AE14-1 -> -0.51067464 | BH27: =BH14/AF14-1 -> 0.853465 | BI27: =BI14/AG14-1 -> 0.50057508 | BJ27: =BJ14/AH14-1 -> 0.11411232
B28: Segment Net Sales | D28: =D15/C15-1 -> -0.024332698 | E28: =E15/D15-1 -> 0.066340384 | F28: =F15/E15-1 -> 0.025968259 | G28: =G15/E15-1 -> 0.028532093 | H28: =H15/G15-1 -> -0.018051941 | I28: =I15/H15-1 -> 0.063489599 | J28: =J15/H15-1 -> -0.2869511 | K28: =K15/J15-1 -> 0.022218613 | L28: =L15/J15-1 -> -0.07637367 | M28: =M15/K15-1 -> -0.024067729 | N28: =N15/L15-1 -> -0.034371884 | O28: =O15/N15-1 -> -0.05509031 | W28: =W15/S15-1 -> 0.050052455 | X28: =X15/T15-1 -> 0.095980912 | Y28: =Y15/U15-1 -> 0.071178208 | Z28: =Z15/V15-1 -> 0.049639587 | AA28: =AA15/W15-1 -> 0.033717157 | AB28: =AB15/X15-1 -> -0.018610098 | AC28: =AC15/Y15-1 -> 0.076316487 | AD28: =AD15/Z15-1 -> 0.015478165 | ... AG28: =AG15/AC15-1 -> -0.05076004 | AH28: =AH15/BF15-1 -> 0.027715734 | AI28: =AI15/AE15-1 -> 0.038633816 | AJ28: =AJ15/AF15-1 -> 0.10349672 | AK28: =AK15/AG15-1 -> 0.086098127 | AL28: =AL15/AH15-1 -> 0.010475208 | AM28: =AM15/BG15-1 -> 0.031964451 | AN28: =AN15/BH15-1 -> 0.0016126605 | AO28: =AO15/AK15-1 -> -0.3113436 | AP28: =AP15/AL15-1 -> -0.35401702 | AQ28: =AQ15/AM15-1 -> -0.0059067407 | AR28: =AR15/AN15-1 -> 0.001384655 | AS28: =AS15/AO15-1 -> -0.046294522 | AT28: =AT15/AP15-1 -> -0.44958217 | AU28: =AU15/AQ15-1 -> -0.14161111 | AV28: =AV15/AR15-1 -> -0.15518313 | ... BA28: =BA15/AW15-1 -> -0.043858112 | BC28: =BC15/AY15-1 -> 0 | BF28: =BF15/Z15-1 -> 0.024868535 | BG28: =BG15/AE15-1 -> -0.26516442 | BH28: =BH15/AF15-1 -> -0.2290976 | BI28: =BI15/AG15-1 -> -0.27579516 | BJ28: =BJ15/AH15-1 -> -0.36172545
B29: Intersegment Operations | D29: =D16/C16-1 -> 0.092732976 | E29: =E16/D16-1 -> 0.43893906 | F29: =F16/E16-1 -> 0.12094512 | G29: =G16/E16-1 -> 0.12094512 | H29: =H16/G16-1 -> 0.34452457 | I29: =I16/H16-1 -> 0.033672113 | J29: =J16/H16-1 -> -0.92825922 | K29: =K16/J16-1 -> 0.082058428 | L29: =L16/J16-1 -> -0.7404459 | M29: =M16/K16-1 -> -0.12894431 | N29: =N16/L16-1 -> 0.22093953 | O29: =O16/N16-1 -> 1.8476859 | W29: =W16/S16-1 -> 0.37956005 | X29: =X16/T16-1 -> 0.35488378 | Y29: =Y16/U16-1 -> 0.34285407 | Z29: =Z16/V16-1 -> 0.66174331 | AA29: =AA16/W16-1 -> 0.2178865 | AB29: =AB16/X16-1 -> 0.17436955 | AC29: =AC16/Y16-1 -> 0.13257636 | AD29: =AD16/Z16-1 -> 0.0068682244 | ... AG29: =AG16/AC16-1 -> 0.32639085 | AH29: =AH16/BF16-1 -> 0.29820103 | AI29: =AI16/AE16-1 -> 0.12689858 | AJ29: =AJ16/AF16-1 -> 0.042060229 | AK29: =AK16/AG16-1 -> 0.020386437 | AL29: =AL16/AH16-1 -> -3.6335257 | AM29: =AM16/BG16-1 -> -0.046209386 | AN29: =AN16/BH16-1 -> -0.22963538 | AO29: =AO16/AK16-1 -> -0.96786646 | AP29: =AP16/AL16-1 -> -1.0528139 | AQ29: =AQ16/AM16-1 -> -0.15972748 | AR29: =AR16/AN16-1 -> 0.39375629 | AS29: =AS16/AO16-1 -> 0.68019481 | AT29: =AT16/AP16-1 -> -1.6963722 | AU29: =AU16/AQ16-1 -> -0.63153153 | AV29: =AV16/AR16-1 -> -0.69075145 | ... BA29: =BA16/AW16-1 -> 1.375286 | BC29: =BC16/AY16-1 -> 0 | BF29: =BF16/Z16-1 -> 0.0068682244 | BG29: =BG16/AE16-1 -> -0.91517638 | BH29: =BH16/AF16-1 -> -0.92838093 | BI29: =BI16/AG16-1 -> -0.94139565 | BJ29: =BJ16/AH16-1 -> -0.92643726
B30: Net Sales | D30: =D17/C17-1 -> -0.028053515 | E30: =E17/D17-1 -> 0.05302598 | F30: =F17/E17-1 -> 0.021330571 | G30: =G17/E17-1 -> 0.024019596 | H30: =H17/G17-1 -> -0.037432196 | I30: =I17/H17-1 -> 0.06571582 | J30: =J17/H17-1 -> -0.23907002 | K30: =K17/J17-1 -> 0.021797393 | L30: =L17/J17-1 -> -0.071699183 | M30: =M17/K17-1 -> -0.023285952 | N30: =N17/L17-1 -> -0.034874375 | O30: =O17/N17-1 -> -0.059827882 | W30: =W17/S17-1 -> 0.039067518 | X30: =X17/T17-1 -> 0.087109606 | Y30: =Y17/U17-1 -> 0.06001412 | Z30: =Z17/V17-1 -> 0.028593303 | AA30: =AA17/W17-1 -> 0.025565492 | AB30: =AB17/X17-1 -> -0.026851307 | AC30: =AC17/Y17-1 -> 0.073387698 | AD30: =AD17/Z17-1 -> 0.015956432 | ... AG30: =AG17/AC17-1 -> -0.071476493 | AH30: =AH17/BF17-1 -> 0.012969019 | AI30: =AI17/AE17-1 -> 0.032389857 | AJ30: =AJ17/AF17-1 -> 0.10844819 | AK30: =AK17/AG17-1 -> 0.091254229 | AL30: =AL17/AH17-1 -> 0.26508545 | AM30: =AM17/BG17-1 -> 0.032565211 | AN30: =AN17/BH17-1 -> 0.0032261731 | AO30: =AO17/AK17-1 -> -0.26317461 | AP30: =AP17/AL17-1 -> -0.45565734 | AQ30: =AQ17/AM17-1 -> -0.0048148228 | AR30: =AR17/AN17-1 -> -0.00071761945 | AS30: =AS17/AO17-1 -> -0.048619083 | AT30: =AT17/AP17-1 -> -0.43198739 | AU30: =AU17/AQ17-1 -> -0.1386747 | AV30: =AV17/AR17-1 -> -0.15118087 | ... BA30: =BA17/AW17-1 -> -0.047894915 | BC30: =BC17/AY17-1 -> 0 | BF30: =BF17/Z17-1 -> 0.025868421 | BG30: =BG17/AE17-1 -> -0.21918176 | BH30: =BH17/AF17-1 -> -0.17273883 | BI30: =BI17/AG17-1 -> -0.22356848 | BJ30: =BJ17/AH17-1 -> -0.32226843
B31: Net Sales including non-recurring revenues | D31: =D20/C20-1 -> -0.028053515 | E31: =E20/D20-1 -> 0.082235415 | F31: =F20/E20-1 -> 0.0020724253 | G31: =G20/E20-1 -> 0.0046888746 | H31: =H20/G20-1 -> -0.043196943 | I31: =I20/H20-1 -> 0.063271588 | J31: =J20/H20-1 -> -0.24081522 | K31: =K20/J20-1 -> 0.021797393 | O31: =O20/N20-1 -> -0.059827882 | W31: =W20/S20-1 -> 0.039067518 | X31: =X20/T20-1 -> 0.16212005 | Y31: =Y20/U20-1 -> 0.10458457 | Z31: =Z20/V20-1 -> 0.028593303 | AA31: =AA20/W20-1 -> 0.025565492 | AB31: =AB20/X20-1 -> -0.089664367 | AC31: =AC20/Y20-1 -> 0.030076059 | AD31: =AD20/Z20-1 -> 0.047427932 | ... AG31: =AG20/AC20-1 -> -0.071476493 | AH31: =AH20/BF20-1 -> -0.01718179 | AI31: =AI20/AE20-1 -> 0.025834309 | AJ31: =AJ20/AF20-1 -> 0.10469849 | AK31: =AK20/AG20-1 -> 0.091254229 | AL31: =AL20/AH20-1 -> 0.26508545 | AM31: =AM20/BG20-1 -> 0.032565211 | AN31: =AN20/BH20-1 -> 0.0032261731 | AO31: =AO20/AK20-1 -> -0.26317461 | AP31: =AP20/AL20-1 -> -0.45565734 | AQ31: =AQ20/AM20-1 -> -0.0048148228 | AR31: =AR20/AN20-1 -> -0.00071761945 | AS31: =AS20/AO20-1 -> -0.048619083 | AT31: =AT20/AP20-1 -> -0.43198739 | AU31: =AU20/AQ20-1 -> -0.1386747 | AV31: =AV20/AR20-1 -> -0.15118087 | ... BA31: =BA20/AW20-1 -> -0.047894915 | BC31: =BC20/AY20-1 -> 0 | BF31: =BF20/Z20-1 -> 0.057339921 | BG31: =BG20/AE20-1 -> -0.22413986 | BH31: =BH20/AF20-1 -> -0.17553733 | BI31: =BI20/AG20-1 -> -0.22356848 | BJ31: =BJ20/AH20-1 -> -0.32226843
B34: % of Net Sales
B35: Subtotal Content | D35: =D9/D$17 -> 0.36327151 | T35: =T9/T$17 -> 0.35148062 | U35: =U9/U$17 -> 0.35409699
B36: World Cup rights
B37: Content | C37: =C11/C$17 -> 0.38101247 | D37: =D11/D$17 -> 0.36327151 | E37: =E11/E$17 -> 0.3702748 | F37: =F11/F$17 -> 0.34570515 | G37: =G11/G$17 -> 0.3474233 | H37: =H11/H$17 -> 0.33573781 | I37: =I11/I$17 -> 0.3471917 | S37: =S11/S$17 -> 0.33208529 | T37: =T11/T$17 -> 0.35148062 | U37: =U11/U$17 -> 0.35409699 | V37: =V11/V$17 -> 0.40803552 | W37: =W11/W$17 -> 0.34628266 | X37: =X11/X$17 -> 0.37023737 | Y37: =Y11/Y$17 -> 0.36215143 | Z37: =Z11/Z$17 -> 0.39808044 | ... AL37: =AL11/AL$17 -> 0.32887867 | BF37: =BF11/BF$17 -> 0.40714044 | BG37: =BG11/BG$17 -> 0 | BH37: =BH11/BH$17 -> 0 | BI37: =BI11/BI$17 -> 0 | BJ37: =BJ11/BJ$17 -> 0
B38: Sky | C38: =C12/C$17 -> 0.22787197 | D38: =D12/D$17 -> 0.23717813 | E38: =E12/E$17 -> 0.2232622 | F38: =F12/F$17 -> 0.21209071 | G38: =G12/G$17 -> 0.21153377 | H38: =H12/H$17 -> 0.2278679 | I38: =I12/I$17 -> 0.21277268 | J38: =J12/J$17 -> 0.29799748 | ... O38: =O12/O$17 -> 0.24633914 | S38: =S12/S$17 -> 0.2523697 | T38: =T12/T$17 -> 0.24554768 | U38: =U12/U$17 -> 0.24026828 | V38: =V12/V$17 -> 0.21425356 | W38: =W12/W$17 -> 0.23997019 | X38: =X12/X$17 -> 0.22654864 | Y38: =Y12/Y$17 -> 0.22508752 | Z38: =Z12/Z$17 -> 0.20429544 | ... BA38: =BA12/BA$17 -> 0.20858686 | BC38: =BC12/BC$17 -> 0.23668323 | BF38: =BF12/BF$17 -> 0.19612497 | BG38: =BG12/BG$17 -> 0.31210223 | BH38: =BH12/BH$17 -> 0.30151186 | BI38: =BI12/BI$17 -> 0.29367244 | BJ38: =BJ12/BJ$17 -> 0.28531917
B39: Cable | C39: =C13/C$17 -> 0.3312126 | D39: =D13/D$17 -> 0.35313219 | E39: =E13/E$17 -> 0.36766594 | F39: =F13/F$17 -> 0.41432358 | G39: =G13/G$17 -> 0.41323559 | H39: =H13/H$17 -> 0.46703617 | I39: =I13/I$17 -> 0.46387252 | J39: =J13/J$17 -> 0.64967381 | ... O39: =O13/O$17 -> 0.76120227 | S39: =S13/S$17 -> 0.36877969 | T39: =T13/T$17 -> 0.34977456 | U39: =U13/U$17 -> 0.36722852 | V39: =V13/V$17 -> 0.33059276 | W39: =W13/W$17 -> 0.38004997 | X39: =X13/X$17 -> 0.35333469 | Y39: =Y13/Y$17 -> 0.3837931 | Z39: =Z13/Z$17 -> 0.3559975 | ... BA39: =BA13/BA$17 -> 0.79850961 | BC39: =BC13/BC$17 -> 0.77053614 | BF39: =BF13/BF$17 -> 0.40165312 | BG39: =BG13/BG$17 -> 0.64789178 | BH39: =BH13/BH$17 -> 0.64856906 | BI39: =BI13/BI$17 -> 0.64908742 | BJ39: =BJ13/BJ$17 -> 0.65304234
B40: Other Businesses | C40: =C14/C$17 -> 0.09168697 | D40: =D14/D$17 -> 0.082152069 | E40: =E14/E$17 -> 0.087626727 | F40: =F14/F$17 -> 0.081472775 | G40: =G14/G$17 -> 0.081258832 | H40: =H14/H$17 -> 0.044019712 | I40: =I14/I$17 -> 0.048579776 | J40: =J14/J$17 -> 0.059367836 | ... O40: =O14/O$17 -> 0 | S40: =S14/S$17 -> 0.080102759 | T40: =T14/T$17 -> 0.087462136 | U40: =U14/U$17 -> 0.079499625 | V40: =V14/V$17 -> 0.081501687 | W40: =W14/W$17 -> 0.077958969 | X40: =X14/X$17 -> 0.092584363 | Y40: =Y14/Y$17 -> 0.081026179 | Z40: =Z14/Z$17 -> 0.097174896 | ... BA40: =BA14/BA$17 -> 0 | BC40: =BC14/BC$17 -> 0 | BF40: =BF14/BF$17 -> 0.049600939 | BG40: =BG14/BG$17 -> 0.047690916 | BH40: =BH14/BH$17 -> 0.056896486 | BI40: =BI14/BI$17 -> 0.063162651 | BJ40: =BJ14/BJ$17 -> 0.069222474
B41: Segment Net Sales as a % of Net sales | C41: =C15/C$17 -> 1.031784 | D41: =D15/D$17 -> 1.0357339 | E41: =E15/E$17 -> 1.0488297 | F41: =F15/F$17 -> 1.0535922 | G41: =G15/G$17 -> 1.0534515 | H41: =H15/H$17 -> 1.0746616 | I41: =I15/I$17 -> 1.0724167 | J41: =J15/J$17 -> 1.0070391 | ... O41: =O15/O$17 -> 1.0075414 | S41: =S15/S$17 -> 1.0333374 | T41: =T15/T$17 -> 1.034265 | U41: =U15/U$17 -> 1.0410934 | V41: =V15/V$17 -> 1.0343835 | W41: =W15/W$17 -> 1.0442618 | X41: =X15/X$17 -> 1.0427051 | Y41: =Y15/Y$17 -> 1.0520582 | Z41: =Z15/Z$17 -> 1.0555483 | ... BA41: =BA15/BA$17 -> 1.0070965 | BC41: =BC15/BC$17 -> 1.0072194 | BF41: =BF15/BF$17 -> 1.0545195 | BG41: =BG15/BG$17 -> 1.0076849 | BH41: =BH15/BH$17 -> 1.0069774 | BI41: =BI15/BI$17 -> 1.0059225 | BJ41: =BJ15/BJ$17 -> 1.007584
B42: Intersegment Operations | C42: =C16/C$17 -> -0.031784013 | D42: =D16/D$17 -> -0.035733901 | E42: =E16/E$17 -> -0.048829665 | F42: =F16/F$17 -> -0.053592222 | G42: =G16/G$17 -> -0.053451491 | H42: =H16/H$17 -> -0.074661591 | I42: =I16/I$17 -> -0.072416683 | J42: =J16/J$17 -> -0.0070391242 | ... O42: =O16/O$17 -> -0.0075414148 | S42: =S16/S$17 -> -0.033337433 | T42: =T16/T$17 -> -0.034264998 | U42: =U16/U$17 -> -0.041093412 | V42: =V16/V$17 -> -0.034383524 | W42: =W16/W$17 -> -0.044261792 | X42: =X16/X$17 -> -0.042705068 | Y42: =Y16/Y$17 -> -0.052058227 | Z42: =Z16/Z$17 -> -0.055548283 | ... BA42: =BA16/BA$17 -> -0.0070964654 | BC42: =BC16/BC$17 -> -0.0072193728 | BF42: =BF16/BF$17 -> -0.054519468 | BG42: =BG16/BG$17 -> -0.0076849237 | BH42: =BH16/BH$17 -> -0.0069774114 | BI42: =BI16/BI$17 -> -0.0059225071 | BJ42: =BJ16/BJ$17 -> -0.0075839875
B43: Net Sales | C43: =C17/C$17 -> 1 | D43: =D17/D$17 -> 1 | E43: =E17/E$17 -> 1 | F43: =F17/F$17 -> 1 | G43: =G17/G$17 -> 1 | H43: =H17/H$17 -> 1 | I43: =I17/I$17 -> 1 | J43: =J17/J$17 -> 1 | ... O43: =O17/O$17 -> 1 | S43: =S17/S$17 -> 1 | T43: =T17/T$17 -> 1 | U43: =U17/U$17 -> 1 | V43: =V17/V$17 -> 1 | W43: =W17/W$17 -> 1 | X43: =X17/X$17 -> 1 | Y43: =Y17/Y$17 -> 1 | Z43: =Z17/Z$17 -> 1 | ... BA43: =BA17/BA$17 -> 1 | BC43: =BC17/BC$17 -> 1 | BF43: =BF17/BF$17 -> 1 | BG43: =BG17/BG$17 -> 1 | BH43: =BH17/BH$17 -> 1 | BI43: =BI17/BI$17 -> 1 | BJ43: =BJ17/BJ$17 -> 1
B45: Operating Segment Income by Business Segment
B47: Subtotal Content | D47: 12825.3 | T47: 3185.1 | U47: 3102.1
B48: World Cup rights
B49: Content | C49: 14748 | D49: =+D47+D48 -> 12825.3 | E49: 13444.6 | F49: 12632.1 | G49: 12649.1 | H49: 12360.8 | I49: 13779 | S49: 2618.6 | T49: =+T47+T48 -> 3185.1 | U49: =+U47+U48 -> 3102.1 | V49: =D49-U49-T49-S49 -> 3919.5 | W49: 2820.1 | X49: 3477.1 | Y49: 3110.7 | Z49: =E49-Y49-X49-W49 -> 4036.7 | AA49: 2267.3 | AB49: 2928.3 | AC49: 3112.3 | AD49: =F49-AC49-AB49-AA49 -> 4324.2 | AE49: 1613.9 | AF49: 2080.8 | AG49: 3294.7 | AH49: =H49-AG49-AF49-AE49 -> 5371.4 | AI49: 2376.5 | AJ49: 2569.2 | AK49: 3389.6 | AL49: =I49-AK49-AJ49-AI49 -> 5443.7 | AM49: 0 | AN49: 0 | AO49: 0 | AP49: =K49-AO49-AN49-AM49 -> 0 | AQ49: 0 | AR49: 0 | AS49: 0 | AT49: =N49-AS49-AR49-AQ49 -> 0 | AU49: 0 | BF49: =G49-AC49-AB49-AA49 -> 4341.2 | BG49: 0 | BH49: 0 | BI49: 0 | BJ49: =J49-BG49-BH49-BI49 -> 0
B50: Sky | C50: 9898.5 | D50: 10106.6 | E50: 9767.3 | F50: 9121.2 | G50: 9121.2 | H50: 9135.3 | I50: 8504.2 | J50: 8504.2 | K50: 6416.27 | L50: 6416.27 | M50: 5731.4 | N50: 5731.376 | O50: 4672.316 | S50: 2466.3 | T50: 2655.9 | U50: 2660.4 | V50: =D50-U50-T50-S50 -> 2324 | W50: 2441.9 | X50: 2540.9 | Y50: 2569.9 | Z50: =E50-Y50-X50-W50 -> 2214.6 | AA50: 2306.9 | AB50: 2305.6 | AC50: 2399.9 | AD50: =F50-AC50-AB50-AA50 -> 2108.8 | AE50: 2234 | AF50: 2321.4 | AG50: 2436.7 | AH50: =H50-AG50-AF50-AE50 -> 2143.2 | AI50: 2154.4 | AJ50: 2242.7 | AK50: 2261.7 | AL50: =I50-AK50-AJ50-AI50 -> 1845.4 | AM50: 1861.4 | AN50: 1702.3 | AO50: 1701 | AP50: =K50-AO50-AN50-AM50 -> 1151.57 | AQ50: 1608.9 | AR50: 1448.4 | AS50: 1533.2 | AT50: =N50-AS50-AR50-AQ50 -> 1140.876 | AU50: 1215.6 | BF50: =G50-AC50-AB50-AA50 -> 2108.8 | BG50: 2154.4 | BH50: 2242.7 | BI50: 2261.7 | BJ50: =J50-BG50-BH50-BI50 -> 1845.4
B51: Cable | C51: 13236.1 | D51: 14034.8 | E51: 15302.5 | F51: 17797.6 | G51: 17797.6 | H51: 18898.3 | I51: 20285 | J51: 20285 | K51: 19902.785 | L51: 20505.283 | M51: 18821 | N51: 19299.121 | O51: 18485.611 | S51: 3397.3 | T51: 3442.3 | U51: 3523.5 | V51: =D51-U51-T51-S51 -> 3671.7 | W51: 3664.9 | X51: 3724.4 | Y51: 3907.5 | Z51: =E51-Y51-X51-W51 -> 4005.7 | AA51: 4297.1 | AB51: 4473.7 | AC51: 4481.7 | AD51: =F51-AC51-AB51-AA51 -> 4545.1 | AE51: 4490.3 | AF51: 4656.5 | AG51: 4796.7 | AH51: =H51-AG51-AF51-AE51 -> 4954.8 | AI51: 4834.6 | AJ51: 5020.1 | AK51: 5064.5 | AL51: =I51-AK51-AJ51-AI51 -> 5365.8 | AM51: 4979.3 | AN51: 4951.8 | AO51: 4912.4 | AP51: =K51-AO51-AN51-AM51 -> 5059.285 | AQ51: 4957 | AR51: 4841.4 | AS51: 4320.8 | AT51: =N51-AS51-AR51-AQ51 -> 5179.921 | AU51: 4667.8 | BF51: =G51-AC51-AB51-AA51 -> 4545.1 | BG51: 4834.6 | BH51: 5020.1 | BI51: 5064.5 | BJ51: =J51-BG51-BH51-BI51 -> 5365.8
B52: Other Businesses | C52: 1040.6 | D52: 525.8 | E52: 754.3 | F52: 1464.2 | G52: 1464.2 | H52: 116.5 | I52: 907.3 | J52: 589.745 | K52: 1691.041 | L52: 0 | M52: 1952.4 | N52: 0 | O52: 0 | S52: 83.2 | T52: 140 | U52: 52.1 | V52: =D52-U52-T52-S52 -> 250.5 | W52: 203.9 | X52: 193.2 | Y52: 126.7 | Z52: =E52-Y52-X52-W52 -> 230.5 | AA52: 535.1 | AB52: 220.5 | AC52: 770.5 | AD52: =F52-AC52-AB52-AA52 -> -61.9 | AE52: 371 | AF52: -422.4 | AG52: 3.3 | AH52: =H52-AG52-AF52-AE52 -> 164.6 | AI52: 12.1 | AJ52: 273.5 | AK52: 253.2 | AL52: =I52-AK52-AJ52-AI52 -> 368.5 | AM52: 376.4 | AN52: 391.6 | AO52: 423.7 | AP52: =K52-AO52-AN52-AM52 -> 499.341 | AQ52: 403.9 | AR52: 524.2 | AS52: 561 | AT52: =N52-AS52-AR52-AQ52 -> -1489.1 | AU52: 0 | BF52: =G52-AC52-AB52-AA52 -> -61.9 | BG52: -9.3 | BH52: 148.6 | BI52: 212.8 | BJ52: =J52-BG52-BH52-BI52 -> 237.645
B53: Operating Segment Income | C53: =+C49+C50+C51+C52 -> 38923.2 | D53: =+D49+D50+D51+D52 -> 37492.5 | E53: =+E49+E50+E51+E52 -> 39268.7 | F53: =+F49+F50+F51+F52 -> 41015.1 | G53: =+G49+G50+G51+G52 -> 41032.1 | H53: =+H49+H50+H51+H52 -> 40510.9 | I53: =+I49+I50+I51+I52 -> 43475.5 | J53: =+J49+J50+J51+J52 -> 29378.945 | ... O53: =+O49+O50+O51+O52 -> 23157.927 | S53: =+S49+S50+S51+S52 -> 8565.4 | T53: =+T49+T50+T51+T52 -> 9423.3 | U53: =+U49+U50+U51+U52 -> 9338.1 | V53: =+V49+V50+V51+V52 -> 10165.7 | W53: =+W49+W50+W51+W52 -> 9130.8 | X53: =+X49+X50+X51+X52 -> 9935.6 | Y53: =+Y49+Y50+Y51+Y52 -> 9714.8 | Z53: =+Z49+Z50+Z51+Z52 -> 10487.5 | ... AU53: =+AU49+AU50+AU51+AU52 -> 5883.4 | AV53: 5950.1 | AW53: 5717.1 | AX53: =O53-SUM(AU53:AW53) -> 5607.327 | AY53: 5702.1 | AZ53: 5694.3 | BA53: 5677.1 | BC53: 5702.1 | BF53: =+BF49+BF50+BF51+BF52 -> 10933.2 | BG53: =+BG49+BG50+BG51+BG52 -> 6979.7 | BH53: =+BH49+BH50+BH51+BH52 -> 7411.4 | BI53: =+BI49+BI50+BI51+BI52 -> 7539 | BJ53: =+BJ49+BJ50+BJ51+BJ52 -> 7448.845
B54: Non recurring licensing income | C54: 0 | D54: 0 | E54: 1410.5 | F54: 0 | G54: 0 | H54: 0 | I54: 0 | J54: 0 | K54: 0 | L54: 0 | M54: 0 | N54: 0 | O54: 0 | S54: 0 | T54: 0 | U54: 0 | V54: =D54-U54-T54-S54 -> 0 | W54: 0 | X54: 817.2 | Y54: 593.3 | Z54: =E54-Y54-X54-W54 -> 0 | AA54: 0 | AB54: 0 | AC54: 0 | AD54: =F54-AC54-AB54-AA54 -> 0 | AE54: 0 | AF54: 0 | AG54: 0 | AH54: =H54-AG54-AF54-AE54 -> 0 | AI54: 0 | AJ54: 0 | AK54: 0 | AL54: =I54-AK54-AJ54-AI54 -> 0 | AM54: 0 | AN54: 0 | AO54: 0 | AP54: =K54-AO54-AN54-AM54 -> 0 | AQ54: 0 | AR54: 0 | AS54: 0 | AT54: =N54-AS54-AR54-AQ54 -> 0 | AU54: 0 | AV54: 0 | AW54: 0 | AX54: =O54-SUM(AU54:AW54) -> 0 | AY54: 0 | AZ54: 0 | BA54: 0 | BC54: 0 | BF54: =G54-AC54-AB54-AA54 -> 0 | BG54: 0 | BH54: 0 | BI54: 0 | BJ54: =J54-BG54-BH54-BI54 -> 0
B55: Total Operating Segment Income | C55: =+C53+C54 -> 38923.2 | D55: =+D53+D54 -> 37492.5 | E55: =+E53+E54 -> 40679.2 | F55: =+F53+F54 -> 41015.1 | G55: =+G53+G54 -> 41032.1 | H55: =+H53+H54 -> 40510.9 | I55: =+I53+I54 -> 43475.5 | J55: =+J53+J54 -> 29378.945 | ... O55: =+O53+O54 -> 23157.927 | S55: =+S53+S54 -> 8565.4 | T55: =+T53+T54 -> 9423.3 | U55: =+U53+U54 -> 9338.1 | V55: =+V53+V54 -> 10165.7 | W55: =+W53+W54 -> 9130.8 | X55: =+X53+X54 -> 10752.8 | Y55: =+Y53+Y54 -> 10308.1 | Z55: =+Z53+Z54 -> 10487.5 | ... BA55: =+BA53+BA54 -> 5677.1 | BC55: =+BC53+BC54 -> 5702.1 | BF55: =+BF53+BF54 -> 10933.2 | BG55: =+BG53+BG54 -> 6979.7 | BH55: =+BH53+BH54 -> 7411.4 | BI55: =+BI53+BI54 -> 7539 | BJ55: =+BJ53+BJ54 -> 7448.845
B56: Corporate Expenses | C56: -2207.9 | D56: -2291 | E56: -2154.7 | F56: -1888.4 | G56: -1888.4 | H56: -1882.9 | I56: -2203.5 | J56: -2351.342 | K56: -1538.085 | L56: -1346.469 | M56: -1259.9 | N56: -1031.223 | O56: -756.045 | S56: -580.7 | T56: -553.9 | U56: -550.2 | V56: =D56-U56-T56-S56 -> -606.2 | W56: -551.7 | X56: -520.3 | Y56: -496 | Z56: =E56-Y56-X56-W56 -> -586.7 | AA56: -516.1 | AB56: -439.2 | AC56: -436.3 | AD56: =F56-AC56-AB56-AA56 -> -496.8 | AE56: -423.8 | AF56: -366 | AG56: -374.9 | AH56: =H56-AG56-AF56-AE56 -> -718.2 | AI56: -499.4 | AJ56: -481.9 | AK56: -480.7 | AL56: =I56-AK56-AJ56-AI56 -> -741.5 | AM56: -333.7 | AN56: -285.2 | AO56: -213.5 | AP56: =K56-AO56-AN56-AM56 -> -705.685 | AQ56: -242.4 | AR56: -238.3 | AS56: -189.8 | AT56: =N56-AS56-AR56-AQ56 -> -360.723 | AU56: -185.8 | AV56: -91.4 | AW56: -61.2 | AX56: =O56-SUM(AU56:AW56) -> -417.645 | AY56: -118.6 | AZ56: -22.1 | BA56: -57.4 | BC56: -118.6 | BF56: =G56-AC56-AB56-AA56 -> -496.8 | BG56: -423.3 | BH56: -381 | BI56: -421.5 | BJ56: =J56-BG56-BH56-BI56 -> -1125.542
B57: Depreciation and Amortization | C57: -16979.8 | D57: -18504.7 | E57: -19834.2 | F57: -21008.8 | G57: -21008.8 | H57: -21260.8 | I57: -21418.3 | J57: -20053.302 | K57: -21117.432 | L57: -20715.26 | M57: -21554.4 | N57: -21107.312 | O57: -20510.853 | S57: -4543.8 | T57: -4578.6 | U57: -4609.2 | V57: =D57-U57-T57-S57 -> -4773.1 | W57: -4800.8 | X57: -4848.1 | Y57: -5037.8 | Z57: =E57-Y57-X57-W57 -> -5147.5 | AA57: -5216 | AB57: -5079.2 | AC57: -5321.3 | AD57: =F57-AC57-AB57-AA57 -> -5392.3 | AE57: -5151.5 | AF57: -5234.1 | AG57: -5235.9 | AH57: =H57-AG57-AF57-AE57 -> -5639.3 | AI57: -5169.8 | AJ57: -5224.1 | AK57: -5347.8 | AL57: =I57-AK57-AJ57-AI57 -> -5676.6 | AM57: -5077.4 | AN57: -5167.5 | AO57: -5169.8 | AP57: =K57-AO57-AN57-AM57 -> -5702.732 | AQ57: -5311.7 | AR57: -5354.7 | AS57: -5544.1 | AT57: =N57-AS57-AR57-AQ57 -> -4896.812 | AU57: -5035 | AV57: -5209 | AW57: -4907.5 | AX57: =O57-SUM(AU57:AW57) -> -5359.353 | AY57: -4451.8 | AZ57: -4402.7 | BA57: -4604.5 | BC57: -4451.8 | BF57: =G57-AC57-AB57-AA57 -> -5392.3 | BG57: -4658.2 | BH57: -5093 | BI57: -5039.5 | BJ57: =J57-BG57-BH57-BI57 -> -5262.602
B58: Other Expense, net | C58: -3137.4 | D58: -2453.6 | E58: 1562.3 | F58: -1095.6 | G58: -1316.6 | H58: 257.5 | I58: 2394 | J58: 3716.237 | K58: -846.654 | L58: -1023.169 | M58: -866.8 | N58: -913.801 | O58: -4554.9 | S58: -410.7 | T58: -385.6 | U58: -500.5 | V58: =D58-U58-T58-S58 -> -1156.8 | W58: -154.1 | X58: 3237.9 | Y58: -432.5 | Z58: =E58-Y58-X58-W58 -> -1089 | AA58: -188.9 | AB58: -283 | AC58: -389.4 | AD58: =F58-AC58-AB58-AA58 -> -234.3 | AE58: 284.9 | AF58: -293.5 | AG58: 666 | AH58: =H58-AG58-AF58-AE58 -> -399.9 | AI58: -152.9 | AJ58: -398.9 | AK58: -293.7 | AL58: =I58-AK58-AJ58-AI58 -> 3239.5 | AM58: -168.3 | AN58: -40.9 | AO58: -291.2 | AP58: =K58-AO58-AN58-AM58 -> -346.254 | AQ58: -182.2 | AR58: -181.2 | AS58: -717.3 | AT58: =N58-AS58-AR58-AQ58 -> 166.899 | AU58: 2293.2 | AV58: -529.6 | AW58: -319.3 | AX58: =O58-SUM(AU58:AW58) -> -5999.2 | AY58: -198.7 | AZ58: -274.2 | BA58: -43.7 | BC58: -198.7 | BF58: =G58-AC58-AB58-AA58 -> -455.3 | BG58: -77.6 | BH58: -278.3 | BI58: -232.3 | BJ58: =J58-BG58-BH58-BI58 -> 4304.437
B59: Intersegment Operations | F59: -72.2 | G59: -72.2 | H59: -71.5 | I59: -64.4 | J59: -1.608 | K59: -120.424 | L59: -98.908 | M59: -160 | N59: -120.366 | O59: -154.99 | AA59: -15 | AB59: -16.7 | AC59: -21.7 | AD59: =F59-AC59-AB59-AA59 -> -18.8 | AE59: -17.8 | AF59: -19.9 | AG59: -17.5 | AH59: =H59-AG59-AF59-AE59 -> -16.3 | AI59: -15 | AJ59: -14.9 | AK59: -15.6 | AL59: =I59-AK59-AJ59-AI59 -> -18.9 | AM59: -0.3 | AN59: -0.4 | AO59: -0.3 | AP59: =K59-AO59-AN59-AM59 -> -119.424 | AQ59: -29.8 | AR59: -47.6 | AS59: -40.9 | AT59: =N59-AS59-AR59-AQ59 -> -2.066 | AU59: -29.9 | AV59: -30.6 | AW59: -64.4 | AX59: =O59-SUM(AU59:AW59) -> -30.09 | AY59: -43 | AZ59: -41.9 | BA59: -42.7 | BC59: -43 | BF59: =G59-AC59-AB59-AA59 -> -18.8 | BG59: -0.5 | BH59: -0.4 | BI59: -0.4 | BJ59: =J59-BG59-BH59-BI59 -> -0.308
B60: Held-to-sale Operations | F60: 258.9 | G60: 258.9 | H60: -4 | I60: 0 | J60: 0 | K60: 0 | L60: 0 | M60: 0 | N60: 0 | O60: 0 | AD60: =F60-AC60-AB60-AA60 -> 258.9 | AE60: 25.6 | AF60: -29.6 | AG60: 0 | AH60: =H60-AG60-AF60-AE60 -> 0 | AI60: 0 | AJ60: 0 | AK60: 0 | AL60: =I60-AK60-AJ60-AI60 -> 0 | AM60: 0 | AN60: 0 | AO60: 0 | AP60: =K60-AO60-AN60-AM60 -> 0 | AQ60: 0 | AR60: 0 | AS60: 0 | AT60: =N60-AS60-AR60-AQ60 -> 0 | AU60: 0 | AV60: 0 | AW60: 0 | AX60: =O60-SUM(AU60:AW60) -> 0 | AY60: 0 | AZ60: 0 | BA60: 0 | BC60: 0 | BF60: =G60-AC60-AB60-AA60 -> 258.9 | BG60: 0 | BH60: 0 | BI60: 0 | BJ60: =J60-BG60-BH60-BI60 -> 0
B61: Operating Income | C61: =+C55+C57+C56+C58+C59+C60 -> 16598.1 | D61: =+D55+D57+D56+D58+D59+D60 -> 14243.2 | E61: =+E55+E57+E56+E58+E59+E60 -> 20252.6 | F61: =+F55+F57+F56+F58+F59+F60 -> 17209 | G61: =+G55+G57+G56+G58+G59+G60 -> 17005 | H61: =+H55+H57+H56+H58+H59+H60 -> 17549.2 | I61: =+I55+I57+I56+I58+I59+I60 -> 22183.3 | J61: =+J55+J57+J56+J58+J59+J60 -> 10688.93 | ... O61: =+O55+O57+O56+O58+O59+O60 -> -2818.861 | S61: =+S55+S57+S56+S58+S59+S60 -> 3030.2 | T61: =+T55+T57+T56+T58+T59+T60 -> 3905.2 | U61: =+U55+U57+U56+U58+U59+U60 -> 3678.2 | V61: =+V55+V57+V56+V58+V59+V60 -> 3629.6 | W61: =+W55+W57+W56+W58+W59+W60 -> 3624.2 | X61: =+X55+X57+X56+X58+X59+X60 -> 8622.3 | Y61: =+Y55+Y57+Y56+Y58+Y59+Y60 -> 4341.8 | Z61: =+Z55+Z57+Z56+Z58+Z59+Z60 -> 3664.3 | ... BA61: =+BA55+BA57+BA56+BA58+BA59+BA60 -> 928.8 | BC61: =+BC55+BC57+BC56+BC58+BC59+BC60 -> 890 | BF61: =+BF55+BF57+BF56+BF58+BF59+BF60 -> 4828.9 | BG61: =+BG55+BG57+BG56+BG58+BG59+BG60 -> 1820.1 | BH61: =+BH55+BH57+BH56+BH58+BH59+BH60 -> 1658.7 | BI61: =+BI55+BI57+BI56+BI58+BI59+BI60 -> 1845.3 | BJ61: =+BJ55+BJ57+BJ56+BJ58+BJ59+BJ60 -> 5364.83
BJ62: =J62-BG62-BH62-BI62 -> 0
B63: =B56 -> Corporate Expenses | C63: =C56 -> -2207.9 | D63: =D56 -> -2291 | E63: =E56 -> -2154.7 | F63: =F56 -> -1888.4 | G63: =G56 -> -1888.4 | H63: =H56 -> -1882.9 | I63: =I56 -> -2203.5 | ... O63: =O56 -> -756.045 | S63: =S56 -> -580.7 | T63: =T56 -> -553.9 | U63: =U56 -> -550.2 | V63: =V56 -> -606.2 | W63: =W56 -> -551.7 | X63: =X56 -> -520.3 | Y63: =Y56 -> -496 | Z63: =Z56 -> -586.7 | ... AC63: =AC56 -> -436.3 | AD63: =F63-AC63-AB63-AA63 -> -496.8 | AE63: =AE56 -> -423.8 | AF63: =AF56 -> -366 | AG63: =AG56 -> -374.9 | AH63: =H63-AG63-AF63-AE63 -> -718.2 | AI63: =AI56 -> -499.4 | AJ63: =AJ56 -> -481.9 | AK63: =AK56 -> -480.7 | AL63: =I63-AK63-AJ63-AI63 -> -741.5 | AM63: =AM56 -> -333.7 | AN63: =AN56 -> -285.2 | AO63: =AO56 -> -213.5 | AP63: =K63-AO63-AN63-AM63 -> -705.685 | AQ63: =AQ56 -> -242.4 | AR63: =AR56 -> -238.3 | AS63: =AS56 -> -189.8 | AT63: =N63-AS63-AR63-AQ63 -> -360.723 | AU63: =AU56 -> -185.8 | AV63: =AV56 -> -91.4 | AW63: =AW56 -> -61.2 | AX63: =O63-SUM(AU63:AW63) -> -417.645 | AY63: =AY56 -> -118.6 | AZ63: =AZ56 -> -22.1 | BA63: =BA56 -> -57.4 | BC63: =BC56 -> -118.6 | BF63: =G63-AC63-AB63-AA63 -> -496.8 | BG63: =BG56 -> -423.3 | BH63: =BH56 -> -381 | BI63: =BI56 -> -421.5 | BJ63: =J63-BG63-BH63-BI63 -> -1125.542
B64: =B59 -> Intersegment Operations | C64: =C59 -> 0 | D64: =D59 -> 0 | E64: =E59 -> 0 | F64: =F59 -> -72.2 | G64: =G59 -> -72.2 | H64: =H59 -> -71.5 | I64: =I59 -> -64.4 | ... O64: =O59 -> -154.99 | S64: =S59 -> 0 | T64: =T59 -> 0 | U64: =U59 -> 0 | V64: =V59 -> 0 | W64: =W59 -> 0 | X64: =X59 -> 0 | Y64: =Y59 -> 0 | Z64: =Z59 -> 0 | ... AC64: =AC59 -> -21.7 | AD64: =F64-AC64-AB64-AA64 -> -18.8 | AE64: =AE59 -> -17.8 | AF64: =AF59 -> -19.9 | AG64: =AG59 -> -17.5 | AH64: =H64-AG64-AF64-AE64 -> -16.3 | AI64: =AI59 -> -15 | AJ64: =AJ59 -> -14.9 | AK64: =AK59 -> -15.6 | AL64: =I64-AK64-AJ64-AI64 -> -18.9 | AM64: =AM59 -> -0.3 | AN64: =AN59 -> -0.4 | AO64: =AO59 -> -0.3 | AP64: =K64-AO64-AN64-AM64 -> -119.424 | AQ64: =AQ59 -> -29.8 | AR64: =AR59 -> -47.6 | AS64: =AS59 -> -40.9 | AT64: =N64-AS64-AR64-AQ64 -> -2.066 | AU64: =AU59 -> -29.9 | AV64: =AV59 -> -30.6 | AW64: =AW59 -> -64.4 | AX64: =O64-SUM(AU64:AW64) -> -30.09 | AY64: =AY59 -> -43 | AZ64: =AZ59 -> -41.9 | BA64: =BA59 -> -42.7 | BC64: =BC59 -> -43 | BF64: =G64-AC64-AB64-AA64 -> -18.8 | BG64: =BG59 -> -0.5 | BH64: =BH59 -> -0.4 | BI64: =BI59 -> -0.4 | BJ64: =J64-BG64-BH64-BI64 -> -0.308
B65: =B60 -> Held-to-sale Operations | F65: =F60 -> 258.9 | G65: =G60 -> 258.9 | H65: =H60 -> -4 | I65: =I60 -> 0 | J65: 1365.1 | K65: 121.9 | L65: 524 | M65: 915.3 | N65: 361.8 | O65: 31.5 | AD65: =F65-AC65-AB65-AA65 -> 258.9 | AE65: =AE60 -> 25.6 | AF65: =AF60 -> -29.6 | AG65: =AG60 -> 0 | AH65: =H65-AG65-AF65-AE65 -> 0 | AI65: =AI60 -> 0 | AJ65: =AJ60 -> 0 | AK65: =AK60 -> 0 | AL65: =I65-AK65-AJ65-AI65 -> 0 | AM65: =AM60 -> 0 | AN65: =AN60 -> 0 | AO65: =AO60 -> 0 | AP65: =K65-AO65-AN65-AM65 -> 121.9 | AQ65: =AQ60 -> 0 | AR65: =AR60 -> 0 | AS65: =AS60 -> 0 | AT65: =N65-AS65-AR65-AQ65 -> 361.8 | AU65: =AU60 -> 0 | AV65: =AV60 -> 0 | AW65: =AW60 -> 0 | AX65: =O65-SUM(AU65:AW65) -> 31.5 | AY65: =AY60 -> 0 | AZ65: =AZ60 -> 0 | BA65: =BA60 -> 0 | BC65: =BC60 -> 0 | BF65: =G65-AC65-AB65-AA65 -> 258.9 | BG65: =BG60 -> 0 | BH65: =BH60 -> 0 | BI65: =BI60 -> 0 | BJ65: =J65-BG65-BH65-BI65 -> 1365.1
B66: Adjusted EBITDA | C66: =+C55+C63+C64+C65 -> 36715.3 | D66: =+D55+D63+D64+D65 -> 35201.5 | E66: =+E55+E63+E64+E65 -> 38524.5 | F66: =+F55+F63+F64+F65 -> 39313.4 | G66: =+G55+G63+G64+G65 -> 39330.4 | H66: =+H55+H63+H64+H65 -> 38552.5 | I66: =+I55+I63+I64+I65 -> 41207.6 | J66: =+J55+J63+J64+J65 -> 28391.095 | ... O66: =+O55+O63+O64+O65 -> 22278.392 | S66: =+S55+S63+S64+S65 -> 7984.7 | T66: =+T55+T63+T64+T65 -> 8869.4 | U66: =+U55+U63+U64+U65 -> 8787.9 | V66: =+V55+V63+V64+V65 -> 9559.5 | W66: =+W55+W63+W64+W65 -> 8579.1 | X66: =+X55+X63+X64+X65 -> 10232.5 | Y66: =+Y55+Y63+Y64+Y65 -> 9812.1 | Z66: =+Z55+Z63+Z64+Z65 -> 9900.8 | ... BA66: =+BA55+BA63+BA64+BA65 -> 5577 | BC66: =+BC55+BC63+BC64+BC65 -> 5540.5 | BF66: =+BF55+BF63+BF64+BF65 -> 10676.5 | BG66: =+BG55+BG63+BG64+BG65 -> 6555.9 | BH66: =+BH55+BH63+BH64+BH65 -> 7030 | BI66: =+BI55+BI63+BI64+BI65 -> 7117.1 | BJ66: =+BJ55+BJ63+BJ64+BJ65 -> 7688.095
B67: check | C67: =+C66-Model!C51 -> 39852.684 | D67: =+D66-Model!D52 -> -0.002 | E67: =+E66-Model!E52 -> -0.245 | F67: =+F66-Model!F52 -> 0.227 | G67: =+G66-Model!G52 -> -0.013 | H67: =+H66-Model!H52 -> -0.027 | I67: =+I66-Model!I52 -> -0.032 | J67: =+J66-Model!J52 -> 0.026 | K67: =+K66-Model!K52 -> 0.026 | L67: =+L66-Model!L52 -> -0.046 | M67: =+M66-Model!L52 -> -0.022 | N67: =+N66-Model!N52 -> -0.04 | O67: =+O66-Model!O52 -> -0.008 | S67: =+S66-Model!S52 -> 0.015 | T67: =+T66-Model!T52 -> 0.004 | U67: =+U66-Model!U52 -> 0.038 | V67: =+V66-Model!V52 -> -0.059 | W67: =+W66-Model!W52 -> 0.028 | X67: =+X66-Model!X52 -> 0.026 | Y67: =+Y66-Model!Y52 -> 0.028 | Z67: =+Z66-Model!Z52 -> -0.327 | ... BA67: =+BA66-Model!BA52 -> -0.019 | BC67: =+BC66-Model!BC52 -> -342.7 | BF67: =+BF66-Model!BF52 -> -0.113 | BG67: =+BG66-Model!BG52 -> 0 | BH67: =+BH66-Model!BH52 -> 0 | BI67: =+BI66-Model!BI52 -> 0 | BJ67: =J67-BG67-BH67-BI67 -> 0.026
B69: Operating Income y-o-y growth
B70: Content | D70: =D49/C49-1 -> -0.13037022 | E70: =E49/D49-1 -> 0.048287369 | F70: =F49/E49-1 -> -0.060433185 | G70: =G49/E49-1 -> -0.059168737 | H70: =H49/G49-1 -> -0.022792135 | I70: =I49/H49-1 -> 0.11473367 | W70: =W49/S49-1 -> 0.076949515 | X70: =X49/T49-1 -> 0.09167687 | Y70: =Y49/U49-1 -> 0.0027723155 | Z70: =Z49/V49-1 -> 0.029901773 | AA70: =AA49/W49-1 -> -0.19602142 | AB70: =AB49/X49-1 -> -0.15783268 | AC70: =AC49/Y49-1 -> 0.00051435368 | AD70: =AD49/Z49-1 -> 0.071221542 | ... AG70: =AG49/AC49-1 -> 0.058606175 | AH70: =AH49/BF49-1 -> 0.23730766 | AI70: =AI49/AE49-1 -> 0.47251998 | AJ70: =AJ49/AF49-1 -> 0.23471742 | AK70: =AK49/AG49-1 -> 0.028803836 | AL70: =AL49/AH49-1 -> 0.013460178 | BF70: =BF49/Z49-1 -> 0.075432903
B71: Sky | D71: =D50/C50-1 -> 0.021023387 | E71: =E50/D50-1 -> -0.033572121 | F71: =F50/E50-1 -> -0.066149294 | G71: =G50/E50-1 -> -0.066149294 | H71: =H50/G50-1 -> 0.0015458492 | I71: =I50/H50-1 -> -0.069083664 | J71: =J50/H50-1 -> -0.069083664 | K71: =K50/J50-1 -> -0.24551751 | L71: =L50/J50-1 -> -0.24551751 | M71: =M50/K50-1 -> -0.10673959 | N71: =N50/L50-1 -> -0.10674333 | O71: =O50/N50-1 -> -0.18478285 | W71: =W50/S50-1 -> -0.0098933625 | X71: =X50/T50-1 -> -0.043299823 | Y71: =Y50/U50-1 -> -0.034017441 | Z71: =Z50/V50-1 -> -0.04707401 | AA71: =AA50/W50-1 -> -0.055284819 | AB71: =AB50/X50-1 -> -0.092604982 | AC71: =AC50/Y50-1 -> -0.066150434 | AD71: =AD50/Z50-1 -> -0.047773864 | ... AG71: =AG50/AC50-1 -> 0.015333972 | AH71: =AH50/BF50-1 -> 0.016312595 | AI71: =AI50/AE50-1 -> -0.035631155 | AJ71: =AJ50/AF50-1 -> -0.033901956 | AK71: =AK50/AG50-1 -> -0.071818443 | AL71: =AL50/AH50-1 -> -0.1389511 | AM71: =AM50/BG50-1 -> -0.13600074 | AN71: =AN50/BH50-1 -> -0.24095956 | AO71: =AO50/AK50-1 -> -0.24791086 | AP71: =AP50/AL50-1 -> -0.37597811 | AQ71: =AQ50/AM50-1 -> -0.13565059 | AR71: =AR50/AN50-1 -> -0.14915115 | AS71: =AS50/AO50-1 -> -0.098647854 | AT71: =AT50/AP50-1 -> -0.0092864524 | AU71: =AU50/AQ50-1 -> -0.24445273 | BF71: =BF50/Z50-1 -> -0.047773864 | BG71: =BG50/AE50-1 -> -0.035631155 | BH71: =BH50/AF50-1 -> -0.033901956 | BI71: =BI50/AG50-1 -> -0.071818443 | BJ71: =BJ50/AH50-1 -> -0.1389511
B72: Cable | D72: =D51/C51-1 -> 0.060342548 | E72: =E51/D51-1 -> 0.090325477 | F72: =F51/E51-1 -> 0.16305179 | G72: =G51/E51-1 -> 0.16305179 | H72: =H51/G51-1 -> 0.061845417 | I72: =I51/H51-1 -> 0.07337697 | J72: =J51/H51-1 -> 0.07337697 | K72: =K51/J51-1 -> -0.018842248 | L72: =L51/J51-1 -> 0.010859404 | M72: =M51/K51-1 -> -0.054353449 | N72: =N51/L51-1 -> -0.058822012 | O72: =O51/N51-1 -> -0.042152697 | W72: =W51/S51-1 -> 0.078768434 | X72: =X51/T51-1 -> 0.081951021 | Y72: =Y51/U51-1 -> 0.10898255 | Z72: =Z51/V51-1 -> 0.090966038 | AA72: =AA51/W51-1 -> 0.1725013 | AB72: =AB51/X51-1 -> 0.20118677 | AC72: =AC51/Y51-1 -> 0.14694818 | AD72: =AD51/Z51-1 -> 0.13465811 | ... AG72: =AG51/AC51-1 -> 0.070285829 | AH72: =AH51/BF51-1 -> 0.090141031 | AI72: =AI51/AE51-1 -> 0.076676391 | AJ72: =AJ51/AF51-1 -> 0.078084398 | AK72: =AK51/AG51-1 -> 0.05583005 | AL72: =AL51/AH51-1 -> 0.082949867 | AM72: =AM51/BG51-1 -> 0.029930087 | AN72: =AN51/BH51-1 -> -0.013605307 | AO72: =AO51/AK51-1 -> -0.03003258 | AP72: =AP51/AL51-1 -> -0.057123821 | AQ72: =AQ51/AM51-1 -> -0.0044785412 | AR72: =AR51/AN51-1 -> -0.022294923 | AS72: =AS51/AO51-1 -> -0.12042993 | AT72: =AT51/AP51-1 -> 0.023844476 | AU72: =AU51/AQ51-1 -> -0.058341739 | BF72: =BF51/Z51-1 -> 0.13465811 | BG72: =BG51/AE51-1 -> 0.076676391 | BH72: =BH51/AF51-1 -> 0.078084398 | BI72: =BI51/AG51-1 -> 0.05583005 | BJ72: =BJ51/AH51-1 -> 0.082949867
B73: Other Businesses | D73: =D52/C52-1 -> -0.49471459 | E73: =E52/D52-1 -> 0.43457588 | F73: =F52/E52-1 -> 0.94113748 | G73: =G52/E52-1 -> 0.94113748 | H73: =H52/G52-1 -> -0.92043437 | I73: =I52/H52-1 -> 6.7879828 | J73: =J52/H52-1 -> 4.0621888 | K73: =K52/J52-1 -> 1.8674105 | L73: =L52/J52-1 -> -1 | M73: =M52/K52-1 -> 0.15455509 | W73: =W52/S52-1 -> 1.4507212 | X73: =X52/T52-1 -> 0.38 | Y73: =Y52/U52-1 -> 1.4318618 | Z73: =Z52/V52-1 -> -0.079840319 | AA73: =AA52/W52-1 -> 1.6243256 | AB73: =AB52/X52-1 -> 0.14130435 | AC73: =AC52/Y52-1 -> 5.0812944 | AD73: =AD52/Z52-1 -> -1.2685466 | ... AG73: =AG52/AC52-1 -> -0.99571707 | AH73: =AH52/BF52-1 -> -3.6591276 | AI73: =AI52/AE52-1 -> -0.96738544 | AJ73: =AJ52/AF52-1 -> -1.6474905 | AK73: =AK52/AG52-1 -> 75.727273 | AL73: =AL52/AH52-1 -> 1.2387606 | AM73: =AM52/BG52-1 -> -41.473118 | AN73: =AN52/BH52-1 -> 1.6352624 | AO73: =AO52/AK52-1 -> 0.67338073 | AP73: =AP52/AL52-1 -> 0.35506377 | AQ73: =AQ52/AM52-1 -> 0.073060574 | AR73: =AR52/AN52-1 -> 0.33861083 | AS73: =AS52/AO52-1 -> 0.32405004 | AT73: =AT52/AP52-1 -> -3.9821304 | AU73: =AU52/AQ52-1 -> -1 | BF73: =BF52/Z52-1 -> -1.2685466 | BG73: =BG52/AE52-1 -> -1.0250674 | BH73: =BH52/AF52-1 -> -1.3517992 | BI73: =BI52/AG52-1 -> 63.484848 | BJ73: =BJ52/AH52-1 -> 0.44377278
B74: Operating Segment Income | D74: =D53/C53-1 -> -0.036756998 | E74: =E53/D53-1 -> 0.047374808 | F74: =F53/E53-1 -> 0.044473079 | G74: =G53/E53-1 -> 0.044905994 | H74: =H53/G53-1 -> -0.01270225 | I74: =I53/H53-1 -> 0.073180305 | J74: =J53/H53-1 -> -0.27478913 | K74: =K53/J53-1 -> -0.046592858 | L74: =L53/J53-1 -> -0.083644665 | M74: =M53/K53-1 -> -0.053741194 | N74: =N53/L53-1 -> -0.070243199 | O74: =O53/N53-1 -> -0.074811539 | W74: =W53/S53-1 -> 0.06600976 | X74: =X53/T53-1 -> 0.054365244 | Y74: =Y53/U53-1 -> 0.040340112 | Z74: =Z53/V53-1 -> 0.031655469 | AA74: =AA53/W53-1 -> 0.030183555 | AB74: =AB53/X53-1 -> -0.00075486131 | AC74: =AC53/Y53-1 -> 0.10804134 | AD74: =AD53/Z53-1 -> 0.040877235 | ... AG74: =AG53/AC53-1 -> -0.021645424 | AH74: =AH53/BF53-1 -> 0.15556287 | AI74: =AI53/AE53-1 -> 0.076746429 | AJ74: =AJ53/AF53-1 -> 0.17011915 | AK74: =AK53/AG53-1 -> 0.04155193 | AL74: =AL53/AH53-1 -> 0.030821593 | AM74: =AM53/BG53-1 -> 0.034012923 | AN74: =AN53/BH53-1 -> -0.049342904 | AO74: =AO53/AK53-1 -> -0.35845565 | AP74: =AP53/AL53-1 -> -0.48475851 | AQ74: =AQ53/AM53-1 -> -0.034265841 | AR74: =AR53/AN53-1 -> -0.032885306 | AS74: =AS53/AO53-1 -> -0.088402893 | AT74: =AT53/AP53-1 -> -0.27994696 | AU74: =AU53/AQ53-1 -> -0.15587248 | AV74: =AV53/AR53-1 -> -0.12678309 | ... BA74: =BA53/AW53-1 -> -0.0069965542 | BC74: =BC53/AY53-1 -> 0 | BF74: =BF53/Z53-1 -> 0.042498212 | BG74: =BG53/AE53-1 -> -0.19858311 | BH74: =BH53/AF53-1 -> -0.14183157 | BI74: =BI53/AG53-1 -> -0.28414076 | BJ74: =BJ53/AH53-1 -> -0.41041278
B75: Corporate Expenses | D75: =D56/C56-1 -> 0.037637574 | E75: =E56/D56-1 -> -0.059493671 | F75: =F56/E56-1 -> -0.12359029 | G75: =G56/E56-1 -> -0.12359029 | H75: =H56/G56-1 -> -0.0029125185 | I75: =I56/H56-1 -> 0.17026927 | J75: =J56/H56-1 -> 0.24878751 | K75: =K56/J56-1 -> -0.3458693 | L75: =L56/J56-1 -> -0.42736148 | M75: =M56/K56-1 -> -0.18086452 | N75: =N56/L56-1 -> -0.23412793 | O75: =O56/N56-1 -> -0.26684626 | W75: =W56/S56-1 -> -0.049939728 | X75: =X56/T56-1 -> -0.060660769 | Y75: =Y56/U56-1 -> -0.098509633 | Z75: =Z56/V56-1 -> -0.032167601 | AA75: =AA56/W56-1 -> -0.064527823 | AB75: =AB56/X56-1 -> -0.15587161 | AC75: =AC56/Y56-1 -> -0.1203629 | AD75: =AD56/Z56-1 -> -0.15322993 | ... AG75: =AG56/AC56-1 -> -0.14072886 | AH75: =AH56/BF56-1 -> 0.44565217 | AI75: =AI56/AE56-1 -> 0.17838603 | AJ75: =AJ56/AF56-1 -> 0.31666667 | AK75: =AK56/AG56-1 -> 0.28220859 | AL75: =AL56/AH56-1 -> 0.032442217 | AM75: =AM56/BG56-1 -> -0.21167021 | AN75: =AN56/BH56-1 -> -0.25144357 | AO75: =AO56/AK56-1 -> -0.55585604 | AP75: =AP56/AL56-1 -> -0.048300742 | AQ75: =AQ56/AM56-1 -> -0.27359904 | AR75: =AR56/AN56-1 -> -0.164446 | AS75: =AS56/AO56-1 -> -0.11100703 | AT75: =AT56/AP56-1 -> -0.48883284 | AU75: =AU56/AQ56-1 -> -0.23349835 | AV75: =AV56/AR56-1 -> -0.61644985 | ... BA75: =BA56/AW56-1 -> -0.062091503 | BC75: =BC56/AY56-1 -> 0 | BF75: =BF56/Z56-1 -> -0.15322993 | BG75: =BG56/AE56-1 -> -0.0011798018 | BH75: =BH56/AF56-1 -> 0.040983607 | BI75: =BI56/AG56-1 -> 0.12429981 | BJ75: =BJ56/AH56-1 -> 0.5671707
B76: Depreciation and Amortization | D76: =D57/C57-1 -> 0.089806712 | E76: =E57/D57-1 -> 0.071846612 | F76: =F57/E57-1 -> 0.059220942 | G76: =G57/E57-1 -> 0.059220942 | H76: =H57/G57-1 -> 0.011994974 | I76: =I57/H57-1 -> 0.0074079997 | J76: =J57/H57-1 -> -0.05679457 | K76: =K57/J57-1 -> 0.053065076 | L76: =L57/J57-1 -> 0.033009925 | M76: =M57/K57-1 -> 0.020692289 | N76: =N57/L57-1 -> 0.018925758 | O76: =O57/N57-1 -> -0.028258406 | W76: =W57/S57-1 -> 0.056560588 | X76: =X57/T57-1 -> 0.058860787 | Y76: =Y57/U57-1 -> 0.092987937 | Z76: =Z57/V57-1 -> 0.078439589 | AA76: =AA57/W57-1 -> 0.086485586 | AB76: =AB57/X57-1 -> 0.047668159 | AC76: =AC57/Y57-1 -> 0.056274564 | AD76: =AD57/Z57-1 -> 0.047557067 | ... AG76: =AG57/AC57-1 -> -0.01604871 | AH76: =AH57/BF57-1 -> 0.045806057 | AI76: =AI57/AE57-1 -> 0.0035523634 | AJ76: =AJ57/AF57-1 -> -0.0019105481 | AK76: =AK57/AG57-1 -> 0.021371684 | AL76: =AL57/AH57-1 -> 0.0066142961 | AM76: =AM57/BG57-1 -> 0.089991842 | AN76: =AN57/BH57-1 -> 0.014627921 | AO76: =AO57/AK57-1 -> -0.033284715 | AP76: =AP57/AL57-1 -> 0.0046034598 | AQ76: =AQ57/AM57-1 -> 0.046145665 | AR76: =AR57/AN57-1 -> 0.036226415 | AS76: =AS57/AO57-1 -> 0.072401253 | AT76: =AT57/AP57-1 -> -0.14132174 | AU76: =AU57/AQ57-1 -> -0.05209255 | AV76: =AV57/AR57-1 -> -0.027209741 | ... BA76: =BA57/AW57-1 -> -0.061742231 | BC76: =BC57/AY57-1 -> 0 | BF76: =BF57/Z57-1 -> 0.047557067 | BG76: =BG57/AE57-1 -> -0.095758517 | BH76: =BH57/AF57-1 -> -0.026957834 | BI76: =BI57/AG57-1 -> -0.037510266 | BJ76: =BJ57/AH57-1 -> -0.066798716
B77: Other Expense, net | D77: =D58/C58-1 -> -0.21795117 | E77: =E58/D58-1 -> -1.6367379 | F77: =F58/E58-1 -> -1.7012738 | G77: =G58/E58-1 -> -1.8427319 | H77: =H58/G58-1 -> -1.1955795 | I77: =I58/H58-1 -> 8.2970874 | J77: =J58/H58-1 -> 13.431988 | K77: =K58/J58-1 -> -1.2278256 | L77: =L58/J58-1 -> -1.2753239 | M77: =M58/K58-1 -> 0.023794844 | N77: =N58/L58-1 -> -0.10689143 | O77: =O58/N58-1 -> 3.9845645 | W77: =W58/S58-1 -> -0.62478695 | X77: =X58/T58-1 -> -9.3970436 | Y77: =Y58/U58-1 -> -0.13586414 | Z77: =Z58/V58-1 -> -0.058609959 | AA77: =AA58/W58-1 -> 0.22582738 | AB77: =AB58/X58-1 -> -1.0874023 | AC77: =AC58/Y58-1 -> -0.099653179 | AD77: =AD58/Z58-1 -> -0.78484848 | ... AG77: =AG58/AC58-1 -> -2.7103236 | AH77: =AH58/BF58-1 -> -0.12167801 | AI77: =AI58/AE58-1 -> -1.5366795 | AJ77: =AJ58/AF58-1 -> 0.35911414 | AK77: =AK58/AG58-1 -> -1.440991 | AL77: =AL58/AH58-1 -> -9.1007752 | AM77: =AM58/BG58-1 -> 1.1688144 | AN77: =AN58/BH58-1 -> -0.85303629 | AO77: =AO58/AK58-1 -> -0.0085120872 | AP77: =AP58/AL58-1 -> -1.106885 | AQ77: =AQ58/AM58-1 -> 0.082590612 | AR77: =AR58/AN58-1 -> 3.4303178 | AS77: =AS58/AO58-1 -> 1.4632555 | AT77: =AT58/AP58-1 -> -1.4820132 | AU77: =AU58/AQ58-1 -> -13.586169 | AV77: =AV58/AR58-1 -> 1.9227373 | ... BA77: =BA58/AW58-1 -> -0.86313811 | BC77: =BC58/AY58-1 -> 0 | BF77: =BF58/Z58-1 -> -0.58191001 | BG77: =BG58/AE58-1 -> -1.2723763 | BH77: =BH58/AF58-1 -> -0.051788756 | BI77: =BI58/AG58-1 -> -1.3487988 | BJ77: =BJ58/AH58-1 -> -11.763783
B78: Operating Income | D78: =D61/C61-1 -> -0.14187768 | E78: =E61/D61-1 -> 0.42191361 | F78: =F61/E61-1 -> -0.15028194 | G78: =G61/E61-1 -> -0.16035472 | H78: =H61/G61-1 -> 0.032002352 | I78: =I61/H61-1 -> 0.26406332 | J78: =J61/H61-1 -> -0.3909164 | K78: =K61/J61-1 -> -0.58952851 | L78: =L61/J61-1 -> -0.65031607 | M78: =M61/K61-1 -> -0.39288903 | N78: =N61/L61-1 -> -0.50296395 | O78: =O61/N61-1 -> -2.5173154 | W78: =W61/S61-1 -> 0.19602666 | X78: =X61/T61-1 -> 1.2079023 | Y78: =Y61/U61-1 -> 0.18041433 | Z78: =Z61/V61-1 -> 0.0095602821 | AA78: =AA61/W61-1 -> -0.042436952 | AB78: =AB61/X61-1 -> -0.52332904 | AC78: =AC61/Y61-1 -> 0.058478051 | AD78: =AD61/Z61-1 -> 0.37349562 | ... AG78: =AG61/AC61-1 -> 0.21180669 | AH78: =AH61/BF61-1 -> 0.21358902 | AI78: =AI61/AE61-1 -> 0.033239946 | AJ78: =AJ61/AF61-1 -> 0.47991237 | AK78: =AK61/AG61-1 -> -0.13249897 | AL78: =AL61/AH61-1 -> 0.67668891 | AM78: =AM61/BG61-1 -> -0.1003791 | AN78: =AN61/BH61-1 -> -0.06450835 | AO78: =AO61/AK61-1 -> -0.71802037 | AP78: =AP61/AL61-1 -> -1.0166803 | AQ78: =AQ61/AM61-1 -> -0.26487114 | AR78: =AR61/AN61-1 -> -0.36057228 | AS78: =AS61/AO61-1 -> -1.0565955 | AT78: =AT61/AP61-1 -> 0.59247463 | AU78: =AU61/AQ61-1 -> 1.4307552 | AV78: =AV61/AR61-1 -> -0.90979641 | ... BA78: =BA61/AW61-1 -> 1.5467508 | BC78: =BC61/AY61-1 -> 0 | BF78: =BF61/Z61-1 -> 0.31782332 | BG78: =BG61/AE61-1 -> -0.46883208 | BH78: =BH61/AF61-1 -> -0.38411555 | BI78: =BI61/AG61-1 -> -0.66865382 | BJ78: =BJ61/AH61-1 -> -0.084546866
B81: Operating Income Margin
B82: Subtotal Content | D82: =D47/D9 -> 0.37724577 | T82: =T47/T9 -> 0.39439567 | U82: =U47/U9 -> 0.38655933
B83: World Cup rights
B84: Content | C84: =C49/C11 -> 0.40199854 | D84: =D49/D11 -> 0.37724577 | E84: =E49/E11 -> 0.36844514 | F84: =F49/F11 -> 0.36303832 | G84: =G49/G11 -> 0.36077922 | H84: =H49/H11 -> 0.3790145 | I84: =I49/I11 -> 0.38336852 | S84: =S49/S11 -> 0.3591699 | T84: =T49/T11 -> 0.39439567 | U84: =U49/U11 -> 0.38655933 | V84: =V49/V11 -> 0.36956542 | W84: =W49/W11 -> 0.3570018 | X84: =X49/X11 -> 0.37598806 | Y84: =Y49/Y11 -> 0.35755172 | Z84: =Z49/Z11 -> 0.37928928 | ... AL84: =AL49/AL11 -> 0.47094016 | BF84: =BF49/BF11 -> 0.3887665
B85: Sky | C85: =C50/C12 -> 0.45113759 | D85: =D50/D12 -> 0.45532199 | E85: =E50/E12 -> 0.44392379 | F85: =F50/F12 -> 0.42728052 | G85: =G50/G12 -> 0.42728052 | H85: =H50/H12 -> 0.41271397 | I85: =I50/I12 -> 0.38608745 | J85: =J50/J12 -> 0.38608745 | ... O85: =O50/O12 -> 0.30463769 | S85: =S50/S12 -> 0.4451323 | T85: =T50/T12 -> 0.47074567 | U85: =U50/U12 -> 0.4885771 | V85: =V50/V12 -> 0.4173176 | W85: =W50/W12 -> 0.44607431 | X85: =X50/X12 -> 0.44901746 | Y85: =Y50/Y12 -> 0.47526492 | Z85: =Z50/Z12 -> 0.4054633 | ... BA85: =BA50/BA12 -> 0 | BC85: =BC50/BC12 -> 0 | BF85: =BF50/BF12 -> 0.39203584 | BG85: =BG50/BG12 -> 0.38301806 | BH85: =BH50/BH12 -> 0.40263191 | BI85: =BI50/BI12 -> 0.41427629 | BJ85: =BJ50/BJ12 -> 0.34350176
B86: Cable | C86: =C51/C13 -> 0.41503405 | D86: =D51/D13 -> 0.4246754 | E86: =E51/E13 -> 0.42233599 | F86: =F51/F13 -> 0.42678049 | G86: =G51/G13 -> 0.42678049 | H86: =H51/H13 -> 0.41656399 | I86: =I51/I13 -> 0.42241998 | J86: =J51/J13 -> 0.42241998 | ... O86: =O51/O13 -> 0.39004848 | S86: =S51/S13 -> 0.41961143 | T86: =T51/T13 -> 0.42832257 | U86: =U51/U13 -> 0.42337038 | V86: =V51/V13 -> 0.4272996 | W86: =W51/W13 -> 0.42272512 | X86: =X51/X13 -> 0.42199486 | Y86: =Y51/Y13 -> 0.42381154 | Z86: =Z51/Z13 -> 0.42086849 | ... BA86: =BA51/BA13 -> 0 | BC86: =BC51/BC13 -> 0 | BF86: =BF51/BF13 -> 0.41258703 | BG86: =BG51/BG13 -> 0.4140453 | BH86: =BH51/BH13 -> 0.41898411 | BI86: =BI51/BI13 -> 0.41971226 | BJ86: =BJ51/BJ13 -> 0.43637769
B87: Other Businesses | C87: =C52/C14 -> 0.11787094 | D87: =D52/D14 -> 0.068389631 | E87: =E52/E14 -> 0.087348735 | F87: =F52/F14 -> 0.17855444 | G87: =G52/G14 -> 0.17855444 | H87: =H52/H14 -> 0.027245089 | I87: =I52/I14 -> 0.1804112 | J87: =J52/J14 -> 0.13439337 | ... O87: =O52/O14 -> #DIV/0! | S87: =S52/S14 -> 0.047310361 | T87: =T52/T14 -> 0.069665605 | U87: =U52/U14 -> 0.028917134 | V87: =V52/V14 -> 0.11824962 | W87: =W52/W14 -> 0.11465362 | X87: =X52/X14 -> 0.083542333 | Y87: =Y52/Y14 -> 0.065091189 | Z87: =Z52/Z14 -> 0.088722094 | ... AT87: =AT52/AT14 -> 0.25930763 | BF87: =BF52/BF14 -> -0.045501323 | BG87: =BG52/BG14 -> -0.010820244 | BH87: =BH52/BH14 -> 0.1413757 | BI87: =BI52/BI14 -> 0.18122977 | BJ87: =BJ52/BJ14 -> 0.18232699
B88: Operating Segment Income Margin | C88: =C53/C17 -> 0.40423981 | D88: =D53/D17 -> 0.40061996 | E88: =E53/E17 -> 0.39847 | F88: =F53/F17 -> 0.407499 | G88: =G53/G17 -> 0.40659738 | H88: =H53/H17 -> 0.41704353 | I88: =I53/I17 -> 0.41996459 | J88: =J53/J17 -> 0.39746693 | ... O88: =O53/O17 -> 0.37194998 | S88: =S53/S17 -> 0.3901468 | T88: =T53/T17 -> 0.41012238 | U88: =U53/U17 -> 0.41204165 | V88: =V53/V17 -> 0.3911073 | W88: =W53/W17 -> 0.40026302 | X88: =X53/X17 -> 0.39776926 | Y88: =Y53/Y17 -> 0.4043941 | Z88: =Z53/Z17 -> 0.39227164 | ... BA88: =BA53/BA17 -> 0.3881247 | BC88: =BC53/BC17 -> 0.38081023 | BF88: =BF53/BF17 -> 0.39863054 | BG88: =BG53/BG17 -> 0.38728131 | BH88: =BH53/BH17 -> 0.40118221 | BI88: =BI53/BI17 -> 0.40553843 | BJ88: =BJ53/BJ17 -> 0.39560187
B91: Content
B92: Advertising | C92: 23223.2 | D92: 20719.1 | E92: 21154.9 | F92: 19420.4 | G92: 19459.4 | H92: 16349.8 | I92: 19162 | J92: 19162 | S92: 4128.2 | T92: 4826.6 | U92: 4943.8 | V92: =D92-U92-T92-S92 -> 6820.5 | W92: 4272.7 | X92: 5265.8 | Y92: 5051.2 | Z92: =E92-Y92-X92-W92 -> 6565.2 | AA92: 3681.9 | AB92: 4370.3 | AC92: 4786.6 | AD92: =F92-AC92-AB92-AA92 -> 6581.6 | AE92: 2635.1 | AF92: 2922.2 | AG92: 4164.4 | AH92: =H92-AG92-AF92-AE92 -> 6628.1 | AI92: 3374.9 | AJ92: 3860.2 | AK92: 4823.8 | AL92: =J92-AK92-AJ92-AI92 -> 7103.1 | BF92: =G92-AC92-AB92-AA92 -> 6620.6
B93: Network Subscription Revenue | C93: 4399.3 | D93: 4058.1 | E93: 4814.3 | F93: 4939.2 | G93: 4993.2 | H93: 5466.2 | I93: 5390.8 | J93: 5390.8 | S93: 1042.3 | T93: 941.1 | U93: 929.7 | V93: =D93-U93-T93-S93 -> 1145 | W93: 1179.1 | X93: 1200.8 | Y93: 1182.8 | Z93: =E93-Y93-X93-W93 -> 1251.6 | AA93: 1218.3 | AB93: 1206 | AC93: 1238.9 | AD93: =F93-AC93-AB93-AA93 -> 1276 | AE93: 1332.1 | AF93: 1400.7 | AG93: 1331.7 | AH93: =H93-AG93-AF93-AE93 -> 1401.7 | AI93: 1344.8 | AJ93: 1329.6 | AK93: 1323.9 | AL93: =J93-AK93-AJ93-AI93 -> 1392.5 | BF93: =G93-AC93-AB93-AA93 -> 1330
B94: Licensing and Syndication | C94: 9064.2 | D94: 9220 | E94: 10520.9 | F94: 10435.9 | G94: 10607.9 | H94: 10797 | I94: 11389.1 | J94: 11389.1 | S94: 2120.2 | T94: 2308.2 | U94: 2151.4 | V94: =D94-U94-T94-S94 -> 2640.2 | W94: 2447.6 | X94: 2781.3 | Y94: 2466 | Z94: =E94-Y94-X94-W94 -> 2826 | AA94: 2284.7 | AB94: 2473.7 | AC94: 2633.5 | AD94: =F94-AC94-AB94-AA94 -> 3044 | AE94: 2760.4 | AF94: 2417.7 | AG94: 2537.3 | AH94: =H94-AG94-AF94-AE94 -> 3081.6 | AI94: 2696.4 | AJ94: 2667 | AK94: 2962.1 | AL94: =J94-AK94-AJ94-AI94 -> 3063.6 | BF94: =G94-AC94-AB94-AA94 -> 3216
B95: Subtotal Content | C95: =+C92+C93+C94 -> 36686.7 | D95: =+D92+D93+D94 -> 33997.2 | E95: =+E92+E93+E94 -> 36490.1 | F95: =+F92+F93+F94 -> 34795.5 | G95: =+G92+G93+G94 -> 35060.5 | H95: =+H92+H93+H94 -> 32613 | I95: =+I92+I93+I94 -> 35941.9 | J95: =+J92+J93+J94 -> 35941.9 | S95: =+S92+S93+S94 -> 7290.7 | T95: =+T92+T93+T94 -> 8075.9 | U95: =+U92+U93+U94 -> 8024.9 | V95: =+V92+V93+V94 -> 10605.7 | W95: =+W92+W93+W94 -> 7899.4 | X95: =+X92+X93+X94 -> 9247.9 | Y95: =+Y92+Y93+Y94 -> 8700 | Z95: =+Z92+Z93+Z94 -> 10642.8 | ... AL95: =+AL92+AL93+AL94 -> 11559.2 | BF95: =+BF92+BF93+BF94 -> 11166.6 | BG95: =+BG92+BG93+BG94 -> 0 | BH95: =+BH92+BH93+BH94 -> 0 | BI95: =+BI92+BI93+BI94 -> 0 | BJ95: =+BJ92+BJ93+BJ94 -> 0
B96: World Cup rights | E96: 2733.6 | X96: 1723.5 | Y96: 1010.1 | Z96: =E96-Y96-X96-W96 -> 0
B97: Net Sales | C97: =+C95+C96 -> 36686.7 | D97: =+D95+D96 -> 33997.2 | E97: =+E95+E96 -> 39223.7 | F97: =+F95+F96 -> 34795.5 | G97: =+G95+G96 -> 35060.5 | H97: =+H95+H96 -> 32613 | I97: =+I95+I96 -> 35941.9 | J97: =+J95+J96 -> 35941.9 | S97: =+S95+S96 -> 7290.7 | T97: =+T95+T96 -> 8075.9 | U97: =+U95+U96 -> 8024.9 | V97: =+V95+V96 -> 10605.7 | W97: =+W95+W96 -> 7899.4 | X97: =+X95+X96 -> 10971.4 | Y97: =+Y95+Y96 -> 9710.1 | Z97: =+Z95+Z96 -> 10642.8 | ... AL97: =+AL95+AL96 -> 11559.2 | BF97: =+BF95+BF96 -> 11166.6 | BG97: =+BG95+BG96 -> 0 | BH97: =+BH95+BH96 -> 0 | BI97: =+BI95+BI96 -> 0 | BJ97: =+BJ95+BJ96 -> 0
B99: Sky
B100: RGUs per service type for Sky
B101: Video | D101: 8002526 | E101: 7637040 | F101: 7429351 | G101: 7429351 | H101: 7477294 | I101: 7408075 | J101: 7408075 | K101: 6257059 | M101: 5567426 | N101: 5567426 | O101: 4696038 | W101: 7910225 | X101: 7961481 | Y101: 7835657 | AA101: 7386347 | AB101: 7393726 | AC101: 7412728 | AD101: =F101 -> 7429351 | AE101: 7437469 | AF101: 7457162 | AG101: 7472350 | AH101: =H101 -> 7477294 | AI101: 7487371 | AJ101: 7489876 | AK101: 7488278 | AL101: =J101 -> 7408075 | AM101: 7244246 | AN101: 7019369 | AO101: 6638602 | AP101: =K101 -> 6257059 | AQ101: 6073322 | AR101: 5909228 | AS101: 5697947 | AT101: =N101 -> 5567426 | AU101: 5354994 | AV101: 5144894 | AW101: 4927928 | AX101: =O101 -> 4696038 | AY101: 4404534 | AZ101: 4093569 | BA101: 3793812 | BC101: 4404534 | BF101: =G101 -> 7429351 | BG101: 7487371 | BH101: 7489876 | BI101: 7488278 | BJ101: 7408075
B102: Broadband | E102: 91841 | F102: 386114 | G102: 386114 | H102: 665907 | I102: 727226 | J102: 727226 | K102: 640294 | M102: 515089 | N102: 515089 | O102: 350885 | Y102: 51246 | AA102: 165262 | AB102: 238361 | AC102: 318977 | AD102: =F102 -> 386114 | AE102: 430412 | AF102: 502429 | AG102: 594011 | AH102: =H102 -> 665907 | AI102: 697948 | AJ102: 707115 | AK102: 722481 | AL102: =J102 -> 727226 | AM102: 719223 | AN102: 692767 | AO102: 667013 | AP102: =K102 -> 640294 | AQ102: 608122 | AR102: 575262 | AS102: 544954 | AT102: =N102 -> 515089 | AU102: 480875 | AV102: 438600 | AW102: 389305 | AX102: =O102 -> 350885 | AY102: 314697 | AZ102: 280214 | BA102: 251263 | BC102: 314697 | BF102: =G102 -> 386114 | BG102: 697948 | BH102: 707115 | BI102: 722481 | BJ102: 727226
B103: Voice | F103: 1145 | G103: 1145 | H103: 892 | I103: 601 | J103: 601 | K103: 453 | M103: 344 | N103: 344 | O103: 197 | AA103: 1493 | AB103: 1329 | AC103: 1252 | AD103: =F103 -> 1145 | AE103: 1052 | AF103: 945 | AG103: 837 | AH103: =H103 -> 892 | AI103: 7538 | AJ103: 685 | AK103: 649 | AL103: =J103 -> 601 | AM103: 559 | AN103: 531 | AO103: 489 | AP103: =K103 -> 453 | AQ103: 427 | AR103: 398 | AS103: 365 | AT103: =N103 -> 344 | AU103: 323 | AV103: 265 | AW103: 236 | AX103: =O103 -> 197 | AY103: 186 | AZ103: 162 | BA103: 163 | BC103: 186 | BF103: =G103 -> 1145 | BG103: 727 | BH103: 685 | BI103: 649 | BJ103: 601
B104: Mobile | J104: 30266 | K104: 15602 | M104: 32502 | N104: 32502 | O104: 15501 | AJ104: 14532 | AK104: 27555 | AM104: 26920 | AN104: 22331 | AO104: 17705 | AP104: =K104 -> 15602 | AQ104: 16381 | AR104: 22395 | AS104: 32514 | AT104: =N104 -> 32502 | AU104: 28604 | AV104: 19086 | AW104: 15523 | AX104: =O104 -> 15501 | AY104: 12394 | AZ104: 11286 | BA104: 10598 | BC104: 12394 | BG104: 6811 | BH104: 14532 | BI104: 27555 | BJ104: 30266
B105: Total RGUs | C105: =+C101+C102+C103 -> 0 | D105: =+D101+D102+D103 -> 8002526 | E105: =+E101+E102+E103 -> 7728881 | F105: =+F101+F102+F103 -> 7816610 | G105: =+G101+G102+G103 -> 7816610 | H105: =+H101+H102+H103 -> 8144093 | I105: =+I101+I102+I103 -> 8135902 | J105: =SUM(J101:J104) -> 8166168 | K105: =SUM(K101:K104) -> 6913408 | M105: =SUM(M101:M104) -> 6115361 | N105: =SUM(N101:N104) -> 6115361 | O105: =SUM(O101:O104) -> 5062621 | W105: =+W101+W102+W103 -> 7910225 | X105: =+X101+X102+X103 -> 7961481 | Y105: =+Y101+Y102+Y103 -> 7886903 | AA105: =+AA101+AA102+AA103 -> 7553102 | AB105: =+AB101+AB102+AB103 -> 7633416 | AC105: =+AC101+AC102+AC103 -> 7732957 | AD105: =+AD101+AD102+AD103 -> 7816610 | AE105: =+AE101+AE102+AE103 -> 7868933 | AF105: =+AF101+AF102+AF103 -> 7960536 | AG105: =+AG101+AG102+AG103 -> 8067198 | AH105: =+AH101+AH102+AH103 -> 8144093 | AI105: =+AI101+AI102+AI103 -> 8192857 | AJ105: =+AJ101+AJ102+AJ103+AJ104 -> 8212208 | AK105: =+AK101+AK102+AK103+AK104 -> 8238963 | AL105: =+AL101+AL102+AL103 -> 8135902 | AM105: =+AM101+AM102+AM103+AM104 -> 7990948 | AN105: =+AN101+AN102+AN103+AN104 -> 7734998 | AO105: =+AO101+AO102+AO103+AO104 -> 7323809 | AP105: =SUM(AP101:AP104) -> 6913408 | AQ105: =+AQ101+AQ102+AQ103+AQ104 -> 6698252 | AR105: =+AR101+AR102+AR103+AR104 -> 6507283 | AS105: =+AS101+AS102+AS103+AS104 -> 6275780 | AT105: =SUM(AT101:AT104) -> 6115361 | AU105: =+AU101+AU102+AU103+AU104 -> 5864796 | AV105: =+AV101+AV102+AV103+AV104 -> 5602845 | AW105: =+AW101+AW102+AW103+AW104 -> 5332992 | AX105: =SUM(AX101:AX104) -> 5062621 | AY105: =+AY101+AY102+AY103+AY104 -> 4731811 | AZ105: =+AZ101+AZ102+AZ103+AZ104 -> 4385231 | BA105: =+BA101+BA102+BA103+BA104 -> 4055836 | BC105: =+BC101+BC102+BC103+BC104 -> 4731811 | BF105: =+BF101+BF102+BF103 -> 7816610 | BG105: =+BG101+BG102+BG103+BG104 -> 8192857 | BH105: =+BH101+BH102+BH103+BH104 -> 8212208 | BI105: =+BI101+BI102+BI103+BI104 -> 8238963 | BJ105: =SUM(BJ101:BJ104) -> 8166168
B107: Cable
B108: RGUs per service type for Cable segment
B109: Video | C109: 4205864 | D109: 4185150 | E109: 4384247 | F109: 4318863 | G109: 4318863 | H109: 4284682 | I109: 4166460 | J109: 4166460 | K109: 4458220 | M109: 4059494 | N109: 4059494 | O109: 3846518 | S109: 4066899 | T109: 4092414 | U109: 4123373 | V109: =D109 -> 4185150 | W109: 4237862 | X109: 4315859 | Y109: 4281125 | Z109: =E109 -> 4384247 | AA109: 4375626 | AB109: 4387007 | AC109: 4345020 | AD109: =F109 -> 4318863 | AE109: 4308058 | AF109: 4335478 | AG109: 4333908 | AH109: =H109 -> 4284682 | AI109: 4246101 | AJ109: 4214596 | AK109: 4155529 | AL109: =J109 -> 4166460 | AM109: 4255501 | AN109: 4334648 | AO109: 4405695 | AP109: =K109 -> 4458220 | AQ109: 4489090 | AR109: 4442900 | AS109: 4059390 | AT109: =N109 -> 4059494 | AU109: 4062248 | AV109: 3996657 | AW109: 3941178 | AX109: =O109 -> 3846518 | AY109: 3773536 | AZ109: 3720523 | BA109: 3677832 | BC109: 3773536 | BF109: =G109 -> 4318863 | BG109: 4246101 | BH109: 4214596 | BI109: 4155529 | BJ109: 4166460
B110: Broadband | C110: 3411790 | D110: 3797336 | E110: 4479017 | F110: 4696054 | G110: 4696054 | H110: 5430859 | I110: 5649102 | J110: 5649102 | K110: 5984151 | M110: 5678431 | N110: 5678431 | O110: 5626206 | S110: 3376559 | T110: 3495575 | U110: 3640132 | V110: =D110 -> 3797336 | W110: 3970473 | X110: 4106599 | Y110: 4168248 | Z110: =E110 -> 4479017 | AA110: 4567517 | AB110: 4640275 | AC110: 4658764 | AD110: =F110 -> 4696054 | AE110: 4817103 | AF110: 5069277 | AG110: 5303245 | AH110: =H110 -> 5430859 | AI110: 5534819 | AJ110: 5566188 | AK110: 5590783 | AL110: =J110 -> 5649102 | AM110: 5732026 | AN110: 5809590 | AO110: 5905824 | AP110: =K110 -> 5984151 | AQ110: 6068862 | AR110: 4442900 | AS110: 5677836 | AT110: =N110 -> 5678431 | AU110: 5689143 | AV110: 5699824 | AW110: 5711169 | AX110: =O110 -> 5626206 | AY110: 5620444 | AZ110: 5626825 | BA110: 5648408 | BC110: 5620444 | BF110: =G110 -> 4696054 | BG110: 5534819 | BH110: 5566188 | BI110: 5590783 | BJ110: 5649102
B111: Voice | C111: 2113282 | D111: 2121952 | E111: 2978508 | F111: 3637992 | G111: 3637992 | H111: =4296530+75515 -> 4372045 | I111: =4617265+156051 -> 4773316 | J111: =4617265+156051 -> 4773316 | K111: 5233724 | M111: 5351145 | N111: 5351145 | O111: 5382949 | S111: 2061059 | T111: 2075844 | U111: 2099065 | V111: =D111 -> 2121952 | W111: 2158238 | X111: 2273073 | Y111: 2519972 | Z111: =E111 -> 2978508 | AA111: 3183248 | AB111: 3385387 | AC111: 3534461 | AD111: =F111 -> 3637992 | AE111: 3783519 | AF111: 3998047 | AG111: =4187264+40114 -> 4227378 | AH111: =H111 -> 4372045 | AI111: =4382405+93574 -> 4475979 | AJ111: 4417438 | AK111: 4485738 | AL111: =J111 -> 4773316 | AM111: 4764592 | AN111: 4911727 | AO111: 5064075 | AP111: =K111 -> 5233724 | AQ111: 5408560 | AR111: 5466034 | AS111: 5350757 | AT111: =N111 -> 5351145 | AU111: 5355450 | AV111: 5389305 | AW111: 5418270 | AX111: =O111 -> 5382949 | AY111: 5444680 | AZ111: 5472194 | BA111: 5512882 | BC111: 5444680 | BF111: =G111 -> 3637992 | BG111: 4382405 | BH111: 4417438 | BI111: 4485738 | BJ111: =4617265+156051 -> 4773316
B112: Mobile | K112: 240207 | M112: 307807 | N112: 307807 | O112: 333973 | AJ112: 120777 | AK112: 138979 | AL112: =J112 -> 0 | AM112: 172978 | AN112: 194354 | AO112: 213527 | AP112: =K112 -> 240207 | AQ112: 264313 | AR112: 285398 | AS112: 299292 | AT112: =N112 -> 307807 | AU112: 317924 | AV112: 327406 | AW112: 322957 | AX112: =O112 -> 333973 | AY112: 380112 | AZ112: 463601 | BA112: 557608 | BC112: 380112 | BG112: 93574 | BH112: 120777 | BI112: 138979
B113: Total RGUs | C113: =+C109+C110+C111 -> 9730936 | D113: =+D109+D110+D111 -> 10104438 | E113: =+E109+E110+E111 -> 11841772 | F113: =+F109+F110+F111 -> 12652909 | G113: =+G109+G110+G111 -> 12652909 | H113: =+H109+H110+H111 -> 14087586 | I113: =+I109+I110+I111 -> 14588878 | J113: =+J109+J110+J111 -> 14588878 | K113: =SUM(K109:K112) -> 15916302 | M113: =SUM(M109:M112) -> 15396877 | N113: =SUM(N109:N112) -> 15396877 | O113: =SUM(O109:O112) -> 15189646 | S113: =+S109+S110+S111 -> 9504517 | T113: =+T109+T110+T111 -> 9663833 | U113: =+U109+U110+U111 -> 9862570 | V113: =+V109+V110+V111 -> 10104438 | W113: =+W109+W110+W111 -> 10366573 | X113: =+X109+X110+X111 -> 10695531 | Y113: =+Y109+Y110+Y111 -> 10969345 | Z113: =+Z109+Z110+Z111 -> 11841772 | ... AI113: =+AI109+AI110+AI111 -> 14256899 | AJ113: =+AJ109+AJ110+AJ111+AJ112 -> 14318999 | AK113: =+AK109+AK110+AK111+AK112 -> 14371029 | AL113: =+AL109+AL110+AL111 -> 14588878 | AM113: =+AM109+AM110+AM111+AM112 -> 14925097 | AN113: =+AN109+AN110+AN111+AN112 -> 15250319 | AO113: =+AO109+AO110+AO111+AO112 -> 15589121 | AP113: =SUM(AP109:AP112) -> 15916302 | AQ113: =+AQ109+AQ110+AQ111+AQ112 -> 16230825 | AR113: =+AR109+AR110+AR111+AR112 -> 14637232 | AS113: =+AS109+AS110+AS111+AS112 -> 15387275 | AT113: =SUM(AT109:AT112) -> 15396877 | AU113: =+AU109+AU110+AU111+AU112 -> 15424765 | AV113: =+AV109+AV110+AV111+AV112 -> 15413192 | AW113: =+AW109+AW110+AW111+AW112 -> 15393574 | AX113: =SUM(AX109:AX112) -> 15189646 | AY113: =+AY109+AY110+AY111+AY112 -> 15218772 | AZ113: =+AZ109+AZ110+AZ111+AZ112 -> 15283143 | BA113: =+BA109+BA110+BA111+BA112 -> 15396730 | BC113: =+BC109+BC110+BC111+BC112 -> 15218772 | BF113: =+BF109+BF110+BF111 -> 12652909 | BG113: =+BG109+BG110+BG111+BG112 -> 14256899 | BH113: =+BH109+BH110+BH111+BH112 -> 14318999 | BI113: =+BI109+BI110+BI111+BI112 -> 14371029 | BJ113: =+BJ109+BJ110+BJ111 -> 14588878
B117: New Classification
...
