Workbook
Name \A: #REF!
Name \B: #REF!
Name \C: #REF!
Name \L: #REF!
Name \M: #REF!
Name \P: #REF!
Name \Y: #REF!
Name _01_30_04: MonthlyOpStats
Name _01_30_04: MonthlyOpStats
Name _1_30_01: MonthlyOpStats
Name _1_30_01: MonthlyOpStats
Name _1_30_02: MonthlyOpStats
Name _1_30_02: MonthlyOpStats
Name _1_31_01: MonthlyOpStats
Name _1_31_01: MonthlyOpStats
Name _1_31_02: MonthlyOpStats
Name _1_31_02: MonthlyOpStats
Name _12_31_05: MonthlyOpStats
Name _12_31_05: MonthlyOpStats
Name _A: #REF!
Name _A___0: #REF!
Name _B: #REF!
Name _B___0: #REF!
Name _C: #REF!
Name _C___0: #REF!
Name _ent1: [1]Inputs!$J$17
Name _ent10: [1]Inputs!$J$476
Name _ent11: [1]Inputs!$J$527
Name _ent12: [1]Inputs!$J$578
Name _ent13: [1]Inputs!$J$629
Name _ent14: [1]Inputs!$J$680
Name _ent15: [1]Inputs!$J$731
Name _ent2: [1]Inputs!$J$68
Name _ent3: [1]Inputs!$J$119
Name _ent4: [1]Inputs!$J$170
Name _ent5: [1]Inputs!$J$221
Name _ent6: [1]Inputs!$J$272
Name _ent7: [1]Inputs!$J$323
Name _ent8: [1]Inputs!$J$374
Name _ent9: [1]Inputs!$J$425
Name _eps1: [1]Inputs!$P$42
Name _eps10: [1]Inputs!$P$501
Name _eps11: [1]Inputs!$P$552
Name _eps12: [1]Inputs!$P$603
Name _eps13: [1]Inputs!$P$654
Name _eps14: [1]Inputs!$P$705
Name _eps15: [1]Inputs!$P$756
Name _eps2: [1]Inputs!$P$93
Name _eps3: [1]Inputs!$P$144
Name _eps4: [1]Inputs!$P$195
Name _eps5: [1]Inputs!$P$246
Name _eps6: [1]Inputs!$P$297
Name _eps7: [1]Inputs!$P$348
Name _eps8: [1]Inputs!$P$399
Name _eps9: [1]Inputs!$P$450
Name _fye1: [1]Inputs!$E$12
Name _fye10: [1]Inputs!$E$471
Name _fye11: [1]Inputs!$E$522
Name _fye12: [1]Inputs!$E$573
Name _fye13: [1]Inputs!$E$624

Sheet Capitalisation
A3: 2Q26 | H3: Exchange rate as at end | I3: =Model!$AL$206 -> 0
H4: LTM Average Exchange rate | I4: =Model!$AL$207 -> 0
B6: Debt Breakdown as on 30-Jun-2026 | C6: RMB mn | D6: Leverage | E6: USD mn | F6: Leverage
B7: Current | C7: =SUM(C8:C9) -> 17089 | E7: =SUM(E8:E9) -> 0
B8: Short-term debts | C8: 3534 | E8: =C8*$I3 -> 0
B9: Unsecured senior notes | C9: 13555 | E9: =C9*$I3 -> 0
B11: Non Current | C11: =SUM(C12:C13) -> 52803 | E11: =SUM(E12:E13) -> 0
B12: Long-term borrowings | C12: 36196 | E12: =C12*$I3 -> 0
B13: Unsecured senior notes | C13: 16607 | E13: =C13*$I3 -> 0
B15: Leases | C15: =SUM(C16:C17) -> 35416 | E15: =SUM(E16:E17) -> 0
B16: Current | C16: 10049 | E16: =C16*$I3 -> 0
B17: Non Current | C17: 25367 | E17: =C17*$I3 -> 0
B19: Total Loans & Borrowings | C19: =SUM(C7,C11,C15) -> 105308 | D19: =C19/C25 -> #DIV/0! | E19: =SUM(E7,E11,E15) -> 0 | F19: =E19/E25 -> #DIV/0!
B20: Cash and Cash Equivalents | C20: =Model!$AL$121 -> 0 | E20: =C20*$I3 -> 0
B21: Short term Investments | C21: =Model!$AL$122 -> 0 | E21: =C21*$I3 -> 0
B22: Net debt | C22: =C19-C20-C21 -> 105308 | D22: =C22/C25 -> #DIV/0! | E22: =E19-E20-E21 -> 0 | F22: =E22/E25 -> #DIV/0!
B23: Equity | C23: =Model!$AL$126 -> 0 | E23: =C23*$I3 -> 0
B24: Total Capitalisation | C24: =C22+C23 -> 105308 | E24: =C24*$I3 -> 0
B25: LTM Adjusted EBITDA | C25: =Model!$AL$87 -> 0 | E25: =C25*I4 -> 0
B26: check | C26: =+C19-Model!$AL$119 -> 105308
B29: Liquidity at end 2Q26 | C29: =C6 -> RMB mn | D29: USD mn
B30: Cash and Cash Equivalents | C30: =C20 -> 0 | D30: =C30*I3 -> 0
B31: Short term Investments | C31: =C21 -> 0 | D31: =C31*I3 -> 0
B32: Total liquidity | C32: =SUM(C30:C31) -> 0 | D32: =SUM(D30:D31) -> 0
B35: Debt Maturity Profile at end-2Q26 (from BBG), excluding leases | C35: =C6 -> RMB mn | D35: USD mn
B36: 2026 | C36: 2000 | D36: =C36*I3 -> 0
B37: 2028 | C37: 3600 | D37: =C37*I3 -> 0
B38: 2029 | C38: 13489.82 | D38: =C38*I3 -> 0
B39: 2030 | C39: 5121.44 | D39: =C39*I3 -> 0
B40: 2031 & beyond | C40: =C11+C7-SUM(C36:C39) -> 45680.74 | D40: =C40*I3 -> 0
B41: Total Debt | C41: =SUM(C36:C40) -> 69892 | D41: =SUM(D36:D40) -> 0
A47: 1Q26 | H47: Exchange rate as at end | I47: =Model!$K$206 -> 0
H48: LTM Average Exchange rate | I48: =Model!$K$207 -> 0
B50: Debt Breakdown as on 31-Mar-2026 | C50: RMB mn | D50: Leverage | E50: USD mn | F50: Leverage
B51: Current | C51: =SUM(C52:C53) -> 11733 | E51: =SUM(E52:E53) -> 0
B52: Short-term debts | C52: 8274 | E52: =C52*$I47 -> 0
B53: Unsecured senior notes | C53: 3459 | E53: =C53*$I47 -> 0
B55: Non Current | C55: =SUM(C56:C57) -> 62656 | E55: =SUM(E56:E57) -> 0
B56: Long-term borrowings | C56: 42162 | E56: =C56*$I47 -> 0
B57: Unsecured senior notes | C57: 20494 | E57: =C57*$I47 -> 0
B59: Lease | C59: =SUM(C60:C61) -> 33631 | E59: =SUM(E60:E61) -> 0
B60: Current | C60: 9486 | E60: =C60*$I47 -> 0
B61: Non Current | C61: 24145 | E61: =C61*$I47 -> 0
B63: Total Loans & Borrowings | C63: =SUM(C51,C55,C59) -> 108020 | D63: =C63/C69 -> 8.5323855 | E63: =SUM(E51,E55,E59) -> 0 | F63: =E63/E69 -> #DIV/0!
B64: Cash and Cash Equivalents | C64: =Model!$AK$121 -> 101829 | E64: =C64*$I47 -> 0
B65: Short term Investments | C65: =Model!$AK$122 -> 100304 | E65: =C65*$I47 -> 0
B66: Net debt | C66: =C63-C64-C65 -> -94113 | D66: =C66/C69 -> -7.4338863 | E66: =E63-E64-E65 -> 0 | F66: =E66/E69 -> #DIV/0!
B67: Equity | C67: =Model!$AK$126 -> 280730 | E67: =C67*$I47 -> 0
B68: Total Capitalisation | C68: =C66+C67 -> 186617 | E68: =C68*$I47 -> 0
B69: LTM Adjusted EBITDA | C69: =Model!$AK$87 -> 12660 | E69: =C69*I48 -> 0
B70: check | C70: =+C63-Model!$AK$119 -> 0
B73: Liquidity at end 1Q26 | C73: =C50 -> RMB mn | D73: USD mn
B74: Cash and Cash Equivalents | C74: =C64 -> 101829 | D74: =C74*I47 -> 0
B75: Short term Investments | C75: =C65 -> 100304 | D75: =C75*I47 -> 0
B76: Total liquidity | C76: =SUM(C74:C75) -> 202133 | D76: =SUM(D74:D75) -> 0
B79: Debt Maturity Profile at end-1Q26 (from BBG), excluding leases | C79: =C50 -> RMB mn | D79: USD mn
B80: 2026 | C80: 18009.52 | D80: =C80*I47 -> 0
B81: 2028 | C81: 3600 | D81: =C81*I47 -> 0
B82: 2029 | C82: 13600.82 | D82: =C82*I47 -> 0
B83: 2030 | C83: 11960.69 | D83: =C83*I47 -> 0
B84: 2031 & beyond | C84: =C55+C51-SUM(C80:C83) -> 27217.97 | D84: =C84*I47 -> 0
B85: Total Debt | C85: =SUM(C80:C84) -> 74389 | D85: =SUM(D80:D84) -> 0
A91: FY25 | H91: Exchange rate as at end | I91: =Model!$K$206 -> 0
H92: LTM Average Exchange rate | I92: =Model!$K$207 -> 0
B94: Debt Breakdown as on 31-Dec-2025 | C94: RMB mn | D94: Leverage | E94: USD mn | F94: Leverage
B95: Current | C95: =SUM(C96:C97) -> 11525 | E95: =SUM(E96:E97) -> 0
B96: Short-term debts | C96: 8014 | E96: =C96*$I91 -> 0
B97: Unsecured senior notes | C97: 3511 | E97: =C97*$I91 -> 0
B99: Non Current | C99: =SUM(C100:C101) -> 62473 | E99: =SUM(E100:E101) -> 0
B100: Long-term borrowings | C100: 41675 | E100: =C100*$I91 -> 0
B101: Unsecured senior notes | C101: 20798 | E101: =C101*$I91 -> 0
B103: Lease | C103: =SUM(C104:C105) -> 33107 | E103: =SUM(E104:E105) -> 0
B104: Current | C104: 9399 | E104: =C104*$I91 -> 0
B105: Non Current | C105: 23708 | E105: =C105*$I91 -> 0
B107: Total Loans & Borrowings | C107: =SUM(C95,C99,C103) -> 107105 | D107: =C107/C113 -> 5.8386939 | E107: =SUM(E95,E99,E103) -> 0 | F107: =E107/E113 -> #DIV/0!
B108: Cash and Cash Equivalents | C108: =Model!$AJ$121 -> 137488 | E108: =C108*$I91 -> 0
B109: Short term Investments | C109: =Model!$AJ$122 -> 75744 | E109: =C109*$I91 -> 0
B110: Net debt | C110: =C107-C108-C109 -> -106127 | D110: =C110/C113 -> -5.7853794 | E110: =E107-E108-E109 -> 0 | F110: =E110/E113 -> #DIV/0!
B111: Equity | C111: =Model!$AJ$126 -> 293783 | E111: =C111*$I91 -> 0
B112: Total Capitalisation | C112: =C110+C111 -> 187656 | E112: =C112*$I91 -> 0
B113: LTM Adjusted EBITDA | C113: =Model!$AJ$87 -> 18344 | E113: =C113*I92 -> 0
B114: check | C114: =+C107-Model!$AJ$119 -> 0
B117: Liquidity at end FY25 | C117: =C94 -> RMB mn | D117: USD mn
B118: Cash and Cash Equivalents | C118: =C108 -> 137488 | D118: =C118*I91 -> 0
B119: Short term Investments | C119: =C109 -> 75744 | D119: =C119*I91 -> 0
B120: Total liquidity | C120: =SUM(C118:C119) -> 213232 | D120: =SUM(D118:D119) -> 0
B123: Debt Maturity Profile at end-FY25 (from BBG), excluding leases | C123: =C94 -> RMB mn | D123: USD mn
B124: 2026 | C124: 5459.25 | D124: =C124*I91 -> 0
B125: 2028 | C125: 3600 | D125: =C125*I91 -> 0
B126: 2029 | C126: 13837 | D126: =C126*I91 -> 0
B127: 2030 | C127: 12161.45 | D127: =C127*I91 -> 0
B128: 2030 & beyond | C128: =C95+C99-SUM(C124:C127) -> 38940.3 | D128: =C128*I91 -> 0
B129: Total Debt | C129: =SUM(C124:C128) -> 73998 | D129: =SUM(D124:D128) -> 0
A135: 3Q25 | H135: Exchange rate as at end 3Q25 | I135: =Model!$K$206 -> 0
H136: Average Exchange rate of 3Q25 | I136: =Model!$K$207 -> 0
B138: Debt Breakdown as on 30-Sep-2025 | C138: RMB mn | D138: Leverage | E138: USD mn | F138: Leverage
B139: Current | C139: =SUM(C140:C141) -> 20609 | E139: =SUM(E140:E141) -> 0
B140: Short-term debts | C140: 17062 | E140: =C140*$I135 -> 0
B141: Unsecured senior notes | C141: 3547 | E141: =C141*$I135 -> 0
B143: Non Current | C143: =SUM(C144:C145) -> 59962 | E143: =SUM(E144:E145) -> 0
...

Sheet Model
B2: JD.com, Inc. | C2: Annual | D2: Annual | E2: Annual | F2: Annual | G2: Annual | H2: Annual | I2: Annual | J2: Annual | M2: Quarters | N2: Quarters | O2: Quarters | P2: Quarters | Q2: Quarters | R2: Quarters | S2: Quarters | T2: Quarters | U2: Quarters | V2: Quarters | W2: Quarters | X2: Quarters | Y2: Quarters | Z2: Quarters | AA2: Quarters | AB2: Quarters | AC2: Quarters | AD2: Quarters | AE2: Quarters | AF2: Quarters | AG2: Quarters | AH2: Quarters | AI2: Quarters | AJ2: Quarters | AK2: Quarters
B3: (RMB million) | C3: 43465 | D3: 43830 | E3: 44196 | F3: 44561 | G3: 44926 | H3: 45291 | I3: 45657 | J3: 46022 | M3: 43921 | N3: 44012 | O3: 44104 | P3: 44196 | Q3: 44286 | R3: 44377 | S3: 44469 | T3: 44561 | U3: 44651 | V3: 44742 | W3: 44834 | X3: 44926 | Y3: 45016 | Z3: 45107 | AA3: 45199 | AB3: 45291 | AC3: 45382 | AD3: 45473 | AE3: 45565 | AF3: 45657 | AG3: 45747 | AH3: 45838 | AI3: 45930 | AJ3: 46022 | AK3: 46112
C4: Act | D4: Act | E4: Act | F4: Act | G4: Act | H4: Act | I4: Act | J4: Act | M4: Act | N4: Act | O4: Act | P4: Act | Q4: Act | R4: Act | S4: Act | T4: Act | U4: Act | V4: Act | W4: Act | X4: Act | Y4: Act | Z4: Act | AA4: Act | AB4: Act | AC4: Act | AD4: Act | AE4: Act | AF4: Act | AG4: Act | AH4: Act | AI4: Act | AJ4: Act | AK4: Act
C5: FY | D5: FY | E5: FY | F5: FY | G5: FY | H5: FY | I5: FY | J5: FY | M5: 1Q | N5: 2Q | O5: 3Q | P5: 4Q | Q5: 1Q | R5: 2Q | S5: 3Q | T5: 4Q | U5: 1Q | V5: 2Q | W5: 3Q | X5: 4Q | Y5: 1Q | Z5: 2Q | AA5: 3Q | AB5: 4Q | AC5: 1Q | AD5: 2Q | AE5: 3Q | AF5: 4Q | AG5: 1Q | AH5: 2Q | AI5: 3Q | AJ5: 4Q | AK5: 1Q
B6: INCOME STATEMENT
B7: Revenue | C7: 462019.76 | D7: 576888.48 | E7: 745801.89 | F7: 951592.15 | G7: 1046236 | H7: 1084662 | I7: 1158819 | J7: 1309085 | M7: 146205.21 | N7: 201054.06 | O7: 174214.46 | P7: =E7-SUM(M7:O7) -> 224328.16 | Q7: 203176.17 | R7: 253800.47 | S7: 218708.36 | T7: =F7-SUM(Q7:S7) -> 275907.16 | U7: 239655 | V7: 267600 | W7: 243535 | X7: =G7-SUM(U7:W7) -> 295446 | Y7: 242956 | Z7: 287931 | AA7: 247698 | AB7: =H7-SUM(Y7:AA7) -> 306077 | AC7: 260049 | AD7: 291397 | AE7: 260387 | AF7: =I7-SUM(AC7:AE7) -> 346986 | AG7: 301082 | AH7: 356660 | AI7: 299059 | AJ7: =J7-SUM(AG7:AI7) -> 352284 | AK7: 315694
B8: % of growth | D8: =(D7/C7)-1 -> 0.24862297 | E8: =(E7/D7)-1 -> 0.29280079 | F8: =(F7/E7)-1 -> 0.27593155 | G8: =(G7/F7)-1 -> 0.099458414 | H8: =(H7/G7)-1 -> 0.036727851 | I8: =(I7/H7)-1 -> 0.068368764 | J8: =(J7/I7)-1 -> 0.12967167 | Q8: =(Q7/M7)-1 -> 0.38966437 | R8: =(R7/N7)-1 -> 0.2623494 | S8: =(S7/O7)-1 -> 0.25539724 | T8: =(T7/P7)-1 -> 0.22992656 | U8: =(U7/Q7)-1 -> 0.17954286 | V8: =(V7/R7)-1 -> 0.05437157 | W8: =(W7/S7)-1 -> 0.11351483 | X8: =(X7/T7)-1 -> 0.070816731 | ... AK8: =(AK7/AG7)-1 -> 0.048531629
B9: Cost of revenues | C9: -396066.13 | D9: -492467.39 | E9: -636693.55 | F9: -822525.46 | G9: -899163 | H9: -924958 | I9: -974951 | J9: -1099057 | M9: -123669.7 | N9: -172418.57 | O9: -147419.45 | P9: =E9-SUM(M9:O9) -> -193185.83 | Q9: -174054.15 | R9: -222070.88 | S9: -187615.62 | T9: =F9-SUM(Q9:S9) -> -238784.82 | U9: -206209 | V9: -231706 | W9: -207339 | X9: =G9-SUM(U9:W9) -> -253909 | Y9: -206938 | Z9: -246498 | AA9: -208947 | AB9: =H9-SUM(Y9:AA9) -> -262575 | AC9: -220279 | AD9: -245459 | AE9: -215344 | AF9: =I9-SUM(AC9:AE9) -> -293869 | AG9: -253234 | AH9: -300020 | AI9: -248585 | AJ9: =J9-SUM(AG9:AI9) -> -297218 | AK9: -262667
B10: Gross Profit | C10: =C7+C9 -> 65953.633 | D10: =D7+D9 -> 84421.093 | E10: =E7+E9 -> 109108.34 | F10: =F7+F9 -> 129066.69 | G10: =G7+G9 -> 147073 | H10: =H7+H9 -> 159704 | I10: =I7+I9 -> 183868 | J10: =J7+J9 -> 210028 | M10: =M7+M9 -> 22535.51 | N10: =N7+N9 -> 28635.487 | O10: =O7+O9 -> 26795.018 | P10: =P7+P9 -> 31142.32 | Q10: =Q7+Q9 -> 29122.019 | R10: =R7+R9 -> 31729.594 | S10: =S7+S9 -> 31092.737 | T10: =T7+T9 -> 37122.342 | ... AK10: =AK7+AK9 -> 53027
B11: Gross Profit margin | C11: =C10/C7 -> 0.14275068 | D11: =D10/D7 -> 0.14633867 | E11: =E10/E7 -> 0.14629667 | F11: =F10/F7 -> 0.13563236 | G11: =G10/G7 -> 0.14057345 | H11: =H10/H7 -> 0.14723849 | I11: =I10/I7 -> 0.15866844 | J11: =J10/J7 -> 0.16043878 | M11: =M10/M7 -> 0.15413616 | N11: =N10/N7 -> 0.1424268 | O11: =O10/O7 -> 0.15380478 | P11: =P10/P7 -> 0.13882484 | Q11: =Q10/Q7 -> 0.14333383 | R11: =R10/R7 -> 0.12501787 | S11: =S10/S7 -> 0.14216529 | T11: =T10/T7 -> 0.1345465 | ... AK11: =AK10/AK7 -> 0.16796962
B12: Operating expenses:
B13: Fulfillment | C13: -32009.658 | D13: -36968.041 | E13: -48700.211 | F13: -59055.207 | G13: -63011 | H13: -64558 | I13: -70426 | J13: -88176 | M13: -10399.79 | N13: -11956.352 | O13: -11592.062 | P13: =E13-SUM(M13:O13) -> -14752.007 | Q13: -13803.401 | R13: -14649.314 | S13: -14275.651 | T13: =F13-SUM(Q13:S13) -> -16326.841 | U13: -15486 | V13: -16308 | W13: -14354 | X13: =G13-SUM(U13:W13) -> -16863 | Y13: -15371 | Z13: -16679 | AA13: -15225 | AB13: =H13-SUM(Y13:AA13) -> -17283 | AC13: -16806 | AD13: -17221 | AE13: -16278 | AF13: =I13-SUM(AC13:AE13) -> -20121 | AG13: -19737 | AH13: -22145 | AI13: -22002 | AJ13: =J13-SUM(AG13:AI13) -> -24292 | AK13: -23393
B14: Marketing | C14: -19236.74 | D14: -22234.045 | E14: -27155.972 | F14: -38743.04 | G14: -37772 | H14: -40133 | I14: -47953 | J14: -83953 | M14: -4468.316 | N14: -6803.919 | O14: -5460.508 | P14: =E14-SUM(M14:O14) -> -10423.229 | Q14: -6998.757 | R14: -10612.42 | S14: -7769.166 | T14: =F14-SUM(Q14:S14) -> -13362.697 | U14: -8705 | V14: -9477 | W14: -7605 | X14: =G14-SUM(U14:W14) -> -11985 | Y14: -8005 | Z14: -11063 | AA14: -7955 | AB14: =H14-SUM(Y14:AA14) -> -13110 | AC14: -9254 | AD14: -11867 | AE14: -10000 | AF14: =I14-SUM(AC14:AE14) -> -16832 | AG14: -10543 | AH14: -27013 | AI14: -21050 | AJ14: =J14-SUM(AG14:AI14) -> -25347 | AK14: -15372
B15: Research and development | C15: -12144.383 | D15: -14618.677 | E15: -16148.948 | F15: -16332.036 | G15: -16893 | H15: -16393 | I15: -17031 | J15: -22229 | M15: -3935.159 | N15: -3603.6 | O15: -4106.739 | P15: =E15-SUM(M15:O15) -> -4503.45 | Q15: -4529.506 | R15: -3693.41 | S15: -4004.001 | T15: =F15-SUM(Q15:S15) -> -4105.119 | U15: -4384 | V15: -4027 | W15: -4116 | X15: =G15-SUM(U15:W15) -> -4366 | Y15: -4186 | Z15: -4072 | AA15: -3794 | AB15: =H15-SUM(Y15:AA15) -> -4341 | AC15: -4034 | AD15: -4217 | AE15: -4396 | AF15: =I15-SUM(AC15:AE15) -> -4384 | AG15: -4621 | AH15: -5299 | AI15: -5646 | AJ15: =J15-SUM(AG15:AI15) -> -6663 | AK15: -6866
B16: General and administrative | C16: =-5159.666-22.317 -> -5181.983 | D16: -5490.159 | E16: -6409.131 | F16: -11562.451 | G16: -11053 | H16: -9710 | I16: -8888 | J16: -11980 | M16: -1411.796 | N16: -1423.127 | O16: -1596.342 | P16: =E16-SUM(M16:O16) -> -1977.866 | Q16: -2213.373 | R16: -2561.031 | S16: -3050.183 | T16: =F16-SUM(Q16:S16) -> -3737.864 | U16: -2462 | V16: -2324 | W16: -2622 | X16: =G16-SUM(U16:W16) -> -3645 | Y16: -2501 | Z16: -2358 | AA16: -2474 | AB16: =H16-SUM(Y16:AA16) -> -2377 | AC16: -1976 | AD16: -2132 | AE16: -2325 | AF16: =I16-SUM(AC16:AE16) -> -2455 | AG16: -2414 | AH16: -3266 | AI16: -2990 | AJ16: =J16-SUM(AG16:AI16) -> -3310 | AK16: -3589
B17: Gain on sale of development properties | C17: 0 | D17: 3884.709 | E17: 1648.747 | F17: 766.992 | G17: 1379 | H17: 2283 | I17: 1527 | J17: 387 | M17: 0 | N17: 195.586 | O17: 343.982 | P17: =E17-SUM(M17:O17) -> 1109.179 | Q17: 82.762 | R17: 87.337 | S17: 578.701 | T17: =F17-SUM(Q17:S17) -> 18.192 | U17: 0 | V17: 0 | W17: 1229 | X17: =G17-SUM(U17:W17) -> 150 | Y17: 472 | Z17: 1009 | AA17: 0 | AB17: =H17-SUM(Y17:AA17) -> 802 | AC17: 0 | AD17: 0 | AE17: 0 | AF17: =I17-SUM(AC17:AE17) -> 1527 | AG17: 0 | AH17: 224 | AI17: 163 | AJ17: =J17-SUM(AG17:AI17) -> 0 | AK17: 0
B18: Impairment of goodwill and impairment of long-lived assets | H18: =-3143-2025 -> -5168 | I18: =-799-1562 -> -2361 | J18: =-1303 -> -1303 | T18: =F18-SUM(Q18:S18) -> 0 | X18: =G18-SUM(U18:W18) -> 0 | AB18: =H18-SUM(Y18:AA18) -> -5168 | AC18: 0 | AD18: 0 | AE18: 0 | AF18: =I18-SUM(AC18:AE18) -> -2361 | AG18: 0 | AH18: 0 | AI18: 0 | AJ18: =J18-SUM(AG18:AI18) -> -1303 | AK18: 0
B19: Operating profit | C19: =C10+SUM(C13:C18) -> -2619.131 | D19: =D10+SUM(D13:D18) -> 8994.88 | E19: =E10+SUM(E13:E18) -> 12342.82 | F19: =F10+SUM(F13:F18) -> 4140.95 | G19: =G10+SUM(G13:G18) -> 19723 | H19: =H10+SUM(H13:H18) -> 26025 | I19: =I10+SUM(I13:I18) -> 38736 | J19: =J10+SUM(J13:J18) -> 2774 | M19: =M10+SUM(M13:M17) -> 2320.449 | N19: =N10+SUM(N13:N17) -> 5044.075 | O19: =O10+SUM(O13:O17) -> 4383.349 | P19: =P10+SUM(P13:P17) -> 594.947 | Q19: =Q10+SUM(Q13:Q18) -> 1659.744 | R19: =R10+SUM(R13:R18) -> 300.756 | S19: =S10+SUM(S13:S18) -> 2572.437 | T19: =T10+SUM(T13:T18) -> -391.987 | U19: =U10+SUM(U13:U18) -> 2409 | V19: =V10+SUM(V13:V18) -> 3758 | W19: =W10+SUM(W13:W18) -> 8728 | X19: =X10+SUM(X13:X18) -> 4828 | ... AK19: =AK10+SUM(AK13:AK18) -> 3807
B20: Share of results of equity investees | C20: -1113.105 | D20: -1738.219 | E20: 4291.453 | F20: -4918.023 | G20: -2195 | H20: 1010 | I20: 2327 | J20: 8025 | M20: -1120.22 | N20: 4004.164 | O20: -272.313 | P20: =E20-SUM(M20:O20) -> 1679.822 | Q20: 682.329 | R20: 522.781 | S20: -1850.787 | T20: =F20-SUM(Q20:S20) -> -4272.346 | U20: -1081 | V20: -1604 | W20: 377 | X20: =G20-SUM(U20:W20) -> 113 | Y20: -821 | Z20: 907 | AA20: 427 | AB20: =H20-SUM(Y20:AA20) -> 497 | AC20: -730 | AD20: 1142 | AE20: 1359 | AF20: =I20-SUM(AC20:AE20) -> 556 | AG20: 1330 | AH20: 2072 | AI20: 2740 | AJ20: =J20-SUM(AG20:AI20) -> 1883 | AK20: 1636
B21: Interest expense | C21: -854.538 | D21: -725.01 | E21: -1125.181 | F21: -1213.455 | G21: -2106 | H21: -2881 | I21: -2896 | J21: -2803 | M21: -207.1 | N21: -324.218 | O21: -297.802 | P21: =E21-SUM(M21:O21) -> -296.061 | Q21: -257.821 | R21: -232.325 | S21: -276.139 | T21: =F21-SUM(Q21:S21) -> -447.17 | U21: -345 | V21: -484 | W21: -579 | X21: =G21-SUM(U21:W21) -> -698 | Y21: -590 | Z21: -654 | AA21: -710 | AB21: =H21-SUM(Y21:AA21) -> -927 | AC21: -601 | AD21: -688 | AE21: -681 | AF21: =I21-SUM(AC21:AE21) -> -926 | AG21: -600 | AH21: -643 | AI21: -730 | AJ21: =J21-SUM(AG21:AI21) -> -830 | AK21: -686
B22: Finance income | C22: 2117.921 | D22: 1785.572 | E22: 2753.36 | F22: 0 | G22: 0 | H22: 0 | I22: 0 | J22: 0 | M22: 0 | N22: 0 | O22: 0 | P22: =E22-SUM(M22:O22) -> 2753.36 | Q22: 0 | R22: 0 | S22: 0 | T22: =F22-SUM(Q22:S22) -> 0 | U22: 0 | V22: 0 | W22: 0 | X22: =G22-SUM(U22:W22) -> 0 | Y22: 0 | Z22: 0 | AA22: 0 | AB22: =H22-SUM(Y22:AA22) -> 0 | AC22: 0 | AD22: 0 | AE22: 0 | AF22: =I22-SUM(AC22:AE22) -> 0 | AG22: 0 | AH22: 0 | AI22: 0 | AJ22: =J22-SUM(AG22:AI22) -> 0 | AK22: 0
B23: Others, net | C23: 95.175 | D23: 5375.309 | E23: 32556.439 | F23: -590.222 | G23: -1555 | H23: =7496 -> 7496 | I23: 13371 | J23: 17327 | M23: 390.498 | N23: 8485.552 | O23: 4462.624 | P23: =E23-SUM(M23:O23) -> 19217.765 | Q23: 2037.735 | R23: 455.936 | S23: -3061.899 | T23: =F23-SUM(Q23:S23) -> -21.994 | U23: -3898 | V23: 3586 | W23: -816 | X23: =G23-SUM(U23:W23) -> -427 | Y23: 2792 | Z23: 1211 | AA23: 1782 | AB23: =H23-SUM(Y23:AA23) -> 1711 | AC23: 2696 | AD23: 4661 | AE23: 2521 | AF23: =I23-SUM(AC23:AE23) -> 3493 | AG23: 2079 | AH23: 6129 | AI23: 5674 | AJ23: =J23-SUM(AG23:AI23) -> 3445 | AK23: 2333
B24: Profit before tax | C24: =C19+SUM(C20:C23) -> -2373.678 | D24: =D19+SUM(D20:D23) -> 13692.532 | E24: =E19+SUM(E20:E23) -> 50818.891 | F24: =F19+SUM(F20:F23) -> -2580.75 | G24: =G19+SUM(G20:G23) -> 13867 | H24: =H19+SUM(H20:H23) -> 31650 | I24: =I19+SUM(I20:I23) -> 51538 | J24: =J19+SUM(J20:J23) -> 25323 | M24: =M19+SUM(M20:M23) -> 1383.627 | N24: =N19+SUM(N20:N23) -> 17209.573 | O24: =O19+SUM(O20:O23) -> 8275.858 | P24: =P19+SUM(P20:P23) -> 23949.833 | Q24: =Q19+SUM(Q20:Q23) -> 4121.987 | R24: =R19+SUM(R20:R23) -> 1047.148 | S24: =S19+SUM(S20:S23) -> -2616.388 | T24: =T19+SUM(T20:T23) -> -5133.497 | ... AK24: =AK19+SUM(AK20:AK23) -> 7090
B25: Income tax expenses | C25: -426.872 | D25: -1802.44 | E25: -1481.645 | F25: -1886.535 | G25: -4176 | H25: -8393 | I25: -6878 | J25: -2181 | M25: -326.444 | N25: -796.55 | O25: -690.373 | P25: =E25-SUM(M25:O25) -> 331.722 | Q25: -479.489 | R25: -569.624 | S25: -652.199 | T25: =F25-SUM(Q25:S25) -> -185.223 | U25: -603 | V25: -1227 | W25: -1751 | X25: =G25-SUM(U25:W25) -> -595 | Y25: -1609 | Z25: -2811 | AA25: -2579 | AB25: =H25-SUM(Y25:AA25) -> -1394 | AC25: -1700 | AD25: -2022 | AE25: -2406 | AF25: =I25-SUM(AC25:AE25) -> -750 | AG25: -2063 | AH25: 10 | AI25: -252 | AJ25: =J25-SUM(AG25:AI25) -> 124 | AK25: -1260
B26: Net profit/loss | C26: =+C24+C25 -> -2800.55 | D26: =+D24+D25 -> 11890.092 | E26: =+E24+E25 -> 49337.246 | F26: =+F24+F25 -> -4467.285 | G26: =+G24+G25 -> 9691 | H26: =+H24+H25 -> 23257 | I26: =+I24+I25 -> 44660 | J26: =+J24+J25 -> 23142 | M26: =+M24+M25 -> 1057.183 | N26: =+N24+N25 -> 16413.023 | O26: =+O24+O25 -> 7585.485 | P26: =+P24+P25 -> 24281.555 | Q26: =+Q24+Q25 -> 3642.498 | R26: =+R24+R25 -> 477.524 | S26: =+S24+S25 -> -3268.587 | T26: =+T24+T25 -> -5318.72 | ... AK26: =+AK24+AK25 -> 5830
B27: % margin | C27: =+C26/C7 -> -0.0060615373 | D27: =+D26/D7 -> 0.020610729 | E27: =+E26/E7 -> 0.066153287 | F27: =+F26/F7 -> -0.0046945374 | G27: =+G26/G7 -> 0.0092627285 | H27: =+H26/H7 -> 0.021441703 | I27: =+I26/I7 -> 0.038539237 | J27: =+J26/J7 -> 0.017677996 | M27: =+M26/M7 -> 0.0072308162 | N27: =+N26/N7 -> 0.081634876 | O27: =+O26/O7 -> 0.043541075 | P27: =+P26/P7 -> 0.10824123 | Q27: =+Q26/Q7 -> 0.017927782 | R27: =+R26/R7 -> 0.0018814938 | S27: =+S26/S7 -> -0.014944957 | T27: =+T26/T7 -> -0.019277209 | ... AK27: =+AK26/AK7 -> 0.01846725
B28: Non-controlling interest | C28: =311.409-2.492 -> 308.917 | D28: =297.163-3.1 -> 294.063 | E28: =74.618-6.641 -> 67.977 | F28: =923.696-15.965 -> 907.731 | G28: =697-8 -> 689 | H28: 910 | I28: -3301 | J28: 3511 | M28: =16.42-0.782 -> 15.638 | N28: =34.384-0.794 -> 33.59 | O28: =-23.127-2.02 -> -25.147 | P28: =E28-SUM(M28:O28) -> 43.896 | Q28: =-22.248-2.965 -> -25.213 | R28: =320.368-3.625 -> 316.743 | S28: =466.736-4.687 -> 462.049 | T28: =F28-SUM(Q28:S28) -> 154.152 | U28: =532-5 -> 527 | V28: =350-3 -> 347 | W28: 4 | X28: =G28-SUM(U28:W28) -> -189 | Y28: 62 | Z28: -342 | AA28: -287 | AB28: =H28-SUM(Y28:AA28) -> 1477 | AC28: -235 | AD28: -950 | AE28: -1106 | AF28: =I28-SUM(AC28:AE28) -> -1010 | AG28: -389 | AH28: -531 | AI28: -1105 | AJ28: =J28-SUM(AG28:AI28) -> 5536 | AK28: -728
B29: Net profit/loss | C29: =+C26+C28 -> -2491.633 | D29: =+D26+D28 -> 12184.155 | E29: =+E26+E28 -> 49405.223 | F29: =+F26+F28 -> -3559.554 | G29: =+G26+G28 -> 10380 | H29: =+H26+H28 -> 24167 | I29: =+I26+I28 -> 41359 | J29: =+J26+J28 -> 26653 | M29: =+M26+M28 -> 1072.821 | N29: =+N26+N28 -> 16446.613 | O29: =+O26+O28 -> 7560.338 | P29: =+P26+P28 -> 24325.451 | Q29: =+Q26+Q28 -> 3617.285 | R29: =+R26+R28 -> 794.267 | S29: =+S26+S28 -> -2806.538 | T29: =+T26+T28 -> -5164.568 | ... AK29: =+AK26+AK28 -> 5102
B31: As % of sales unless stated otherwise
B32: =B13 -> Fulfillment | C32: =-C13/C7 -> 0.069282011 | D32: =-D13/D7 -> 0.06408178 | E32: =-E13/E7 -> 0.065299126 | F32: =-F13/F7 -> 0.062059367 | G32: =-G13/G7 -> 0.060226373 | H32: =-H13/H7 -> 0.059519002 | I32: =-I13/I7 -> 0.060773943 | J32: =-J13/J7 -> 0.067356971 | M32: =-M13/M7 -> 0.07113146 | N32: =-N13/N7 -> 0.059468345 | O32: =-O13/O7 -> 0.066539033 | P32: =-P13/P7 -> 0.065760836 | Q32: =-Q13/Q7 -> 0.067938091 | R32: =-R13/R7 -> 0.057719806 | S32: =-S13/S7 -> 0.065272544 | T32: =-T13/T7 -> 0.059175127 | ... AK32: =-AK13/AK7 -> 0.074100236
B33: =B14 -> Marketing | C33: =-C14/C7 -> 0.041636185 | D33: =-D14/D7 -> 0.038541322 | E33: =-E14/E7 -> 0.036411777 | F33: =-F14/F7 -> 0.040713913 | G33: =-G14/G7 -> 0.036102753 | H33: =-H14/H7 -> 0.037000467 | I33: =-I14/I7 -> 0.041380923 | J33: =-J14/J7 -> 0.064131053 | M33: =-M14/M7 -> 0.030561948 | N33: =-N14/N7 -> 0.033841242 | O33: =-O14/O7 -> 0.031343597 | P33: =-P14/P7 -> 0.046464203 | Q33: =-Q14/Q7 -> 0.034446742 | R33: =-R14/R7 -> 0.041814028 | S33: =-S14/S7 -> 0.03552295 | T33: =-T14/T7 -> 0.048431861 | ... AK33: =-AK14/AK7 -> 0.048692721
B34: =B15 -> Research and development | C34: =-C15/C7 -> 0.026285419 | D34: =-D15/D7 -> 0.02534056 | E34: =-E15/E7 -> 0.021653134 | F34: =-F15/F7 -> 0.017162853 | G34: =-G15/G7 -> 0.016146453 | H34: =-H15/H7 -> 0.015113464 | I34: =-I15/I7 -> 0.014696859 | J34: =-J15/J7 -> 0.016980563 | M34: =-M15/M7 -> 0.026915313 | N34: =-N15/N7 -> 0.017923538 | O34: =-O15/O7 -> 0.023572893 | P34: =-P15/P7 -> 0.020075278 | Q34: =-Q15/Q7 -> 0.022293491 | R34: =-R15/R7 -> 0.014552416 | S34: =-S15/S7 -> 0.01830749 | T34: =-T15/T7 -> 0.014878625 | ... AK34: =-AK15/AK7 -> 0.021748909
B35: =B16 -> General and administrative | C35: =-C16/C7 -> 0.011215934 | D35: =-D16/D7 -> 0.0095168462 | E35: =-E16/E7 -> 0.0085936106 | F35: =-F16/F7 -> 0.012150637 | G35: =-G16/G7 -> 0.010564538 | H35: =-H16/H7 -> 0.0089520975 | I35: =-I16/I7 -> 0.0076698777 | J35: =-J16/J7 -> 0.0091514302 | M35: =-M16/M7 -> 0.0096562633 | N35: =-N16/N7 -> 0.0070783301 | O35: =-O16/O7 -> 0.0091630853 | P35: =-P16/P7 -> 0.0088168425 | Q35: =-Q16/Q7 -> 0.010893861 | R35: =-R16/R7 -> 0.010090726 | S35: =-S16/S7 -> 0.013946349 | T35: =-T16/T7 -> 0.013547543 | ... AK35: =-AK16/AK7 -> 0.011368604
B36: =B17 -> Gain on sale of development properties | C36: =-C17/C7 -> 0 | D36: =-D17/D7 -> -0.0067338994 | E36: =-E17/E7 -> -0.0022107037 | F36: =-F17/F7 -> -0.00080600917 | G36: =-G17/G7 -> -0.0013180583 | H36: =-H17/H7 -> -0.0021048032 | I36: =-I17/I7 -> -0.0013177209 | J36: =-J17/J7 -> -0.00029562633 | M36: =-M17/M7 -> 0 | N36: =-N17/N7 -> -0.00097280305 | O36: =-O17/O7 -> -0.0019744744 | P36: =-P17/P7 -> -0.0049444485 | Q36: =-Q17/Q7 -> -0.00040734108 | R36: =-R17/R7 -> -0.00034411678 | S36: =-S17/S7 -> -0.002645994 | T36: =-T17/T7 -> -6.5935223e-05 | ... AG36: =-AG17/AG7 -> 0 | AH36: =-AH16/AH7 -> 0.0091571805 | AI36: =-AI17/AI7 -> -0.00054504295 | AJ36: =-AJ17/AJ7 -> 0 | AK36: =-AK17/AK7 -> 0
B37: =B20 -> Share of results of equity investees | C37: =-C20/C7 -> 0.0024092151 | D37: =-D20/D7 -> 0.0030130936 | E37: =-E20/E7 -> -0.0057541461 | F37: =-F20/F7 -> 0.0051682047 | G37: =-G20/G7 -> 0.002097997 | H37: =-H20/H7 -> -0.00093116565 | I37: =-I20/I7 -> -0.0020080789 | J37: =-J20/J7 -> -0.006130236 | M37: =-M20/M7 -> 0.0076619705 | N37: =-N20/N7 -> -0.019915858 | O37: =-O20/O7 -> 0.0015630907 | P37: =-P20/P7 -> -0.0074882353 | Q37: =-Q20/Q7 -> -0.0033583122 | R37: =-R20/R7 -> -0.002059811 | S37: =-S20/S7 -> 0.0084623515 | T37: =-T20/T7 -> 0.015484723 | ... AK37: =-AK20/AK7 -> -0.0051822334
B38: Interest expense as % of debt | C38: =-C21/C119 -> 0.085267516 | D38: =-D21/D119 -> 0.038629238 | E38: =-E21/E119 -> 0.035658751 | F38: =-F21/F119 -> 0.035544257 | G38: =-G21/G119 -> 0.032377585 | H38: =-H21/H119 -> 0.042100802 | I38: =-I21/I119 -> 0.032260939 | J38: =-J21/J119 -> 0.02617058 | P38: =-SUM(M21:P21)/P119 -> 0.035658751 | Q38: =-SUM(N21:Q21)/Q119 -> 0.035797466 | R38: =-SUM(O21:R21)/R119 -> 0.035533356 | S38: =-SUM(P21:S21)/S119 -> 0.028248142 | T38: =-SUM(Q21:T21)/T119 -> 0.035544257 | U38: =-SUM(R21:U21)/U119 -> 0.024469625 | V38: =-SUM(S21:V21)/V119 -> 0.026274695 | W38: =-SUM(T21:W21)/W119 -> 0.026874837 | ... AK38: =-SUM(AH21:AK21)/AK119 -> 0.026745047
B39: Finance income as % of cash and cash equivalents | C39: =-C22/C120 -> -0.058348114 | D39: =-D22/D120 -> -0.028998705 | E39: =-E22/E120 -> -0.018773511 | F39: =-F22/F120 -> 0 | G39: =-G22/G120 -> 0 | H39: =-H22/H120 -> 0 | I39: =-I22/I120 -> 0 | J39: =-J22/J120 -> 0 | P39: =-SUM(M22:P22)/P120 -> -0.013285911 | Q39: =-SUM(N22:Q22)/Q120 -> -0.020413607 | R39: =-SUM(O22:R22)/R120 -> -0.015933832 | S39: =-SUM(P22:S22)/S120 -> -0.014465135 | T39: =-SUM(Q22:T22)/T120 -> 0 | U39: =-SUM(R22:U22)/U120 -> 0 | V39: =-SUM(S22:V22)/V120 -> 0 | W39: =-SUM(T22:W22)/W120 -> 0 | ... AK39: =-SUM(AH22:AK22)/AK120 -> 0
B40: =B23 -> Others, net | C40: =-C23/C7 -> -0.00020599768 | D40: =-D23/D7 -> -0.009317761 | E40: =-E23/E7 -> -0.043652932 | F40: =-F23/F7 -> 0.00062024681 | G40: =-G23/G7 -> 0.0014862803 | H40: =-H23/H7 -> -0.0069109087 | I40: =-I23/I7 -> -0.011538471 | J40: =-J23/J7 -> -0.013235963 | M40: =-M23/M7 -> -0.0026708898 | N40: =-N23/N7 -> -0.042205326 | O40: =-O23/O7 -> -0.025615692 | P40: =-P23/P7 -> -0.085668092 | Q40: =-Q23/Q7 -> -0.0100294 | R40: =-R23/R7 -> -0.0017964348 | S40: =-S23/S7 -> 0.013999918 | T40: =-T23/T7 -> 7.9715221e-05 | ... AK40: =-AK23/AK7 -> -0.0073900676
B41: Tax % of PBT | C41: =-C25/C24 -> -0.17983568 | D41: =-D25/D24 -> 0.13163672 | E41: =-E25/E24 -> 0.029155398 | F41: =-F25/F24 -> -0.73100262 | G41: =-G25/G24 -> 0.30114661 | H41: =-H25/H24 -> 0.26518167 | I41: =-I25/I24 -> 0.13345493 | J41: =-J25/J24 -> 0.086127236 | M41: =-M25/M24 -> 0.23593353 | N41: =-N25/N24 -> 0.046285286 | O41: =-O25/O24 -> 0.083420112 | P41: =-P25/P24 -> -0.013850702 | Q41: =-Q25/Q24 -> 0.11632472 | R41: =-R25/R24 -> 0.54397659 | S41: =-S25/S24 -> -0.24927457 | T41: =-T25/T24 -> -0.036081252 | ... AK41: =-AK25/AK24 -> 0.17771509
B44: EBITDA | C44: =C3 -> 43465 | D44: =D3 -> 43830 | E44: =E3 -> 44196 | F44: =F3 -> 44561 | G44: =G3 -> 44926 | H44: =H3 -> 45291 | I44: =I3 -> 45657 | J44: =J3 -> 46022 | M44: =M3 -> 43921 | N44: =N3 -> 44012 | O44: =O3 -> 44104 | P44: =P3 -> 44196 | Q44: =Q3 -> 44286 | R44: =R3 -> 44377 | S44: =S3 -> 44469 | T44: =T3 -> 44561 | ... AK44: =AK3 -> 46112
B45: Operating profit | C45: =C19 -> -2619.131 | D45: =D19 -> 8994.88 | E45: =E19 -> 12342.82 | F45: =F19 -> 4140.95 | G45: =G19 -> 19723 | H45: =H19 -> 26025 | I45: =I19 -> 38736 | J45: =J19 -> 2774 | M45: =M19 -> 2320.449 | N45: =N19 -> 5044.075 | O45: =O19 -> 4383.349 | P45: =P19 -> 594.947 | Q45: =Q19 -> 1659.744 | R45: =R19 -> 300.756 | S45: =S19 -> 2572.437 | T45: =T19 -> -391.987 | ... AK45: =AK19 -> 3807
B46: Depreciation, depletion & amortization | C46: 5560.034 | D46: 5828.055 | E46: 6067.654 | F46: 5292.127 | G46: 6018 | H46: 7011 | I46: 7894 | J46: 8701 | M46: 1258.464 | N46: 1306.835 | O46: 1327.856 | P46: =E46-SUM(M46:O46) -> 2174.499 | Q46: 1437.53 | R46: 1224.321 | S46: 1299.599 | T46: =F46-SUM(Q46:S46) -> 1330.677 | U46: 1414 | V46: 1422 | W46: 1537 | X46: =G46-SUM(U46:W46) -> 1645 | Y46: 1624 | Z46: 1727 | AA46: 1792 | AB46: =H46-SUM(Y46:AA46) -> 1868 | AC46: 1908 | AD46: 1934 | AE46: 1998 | AF46: =I46-SUM(AC46:AE46) -> 2054 | AG46: 2038 | AH46: 2103 | AI46: 2255 | AJ46: =J46-SUM(AG46:AI46) -> 2305 | AK46: 2390
B47: EBITDA | C47: =SUM(C45:C46) -> 2940.903 | D47: =SUM(D45:D46) -> 14822.935 | E47: =SUM(E45:E46) -> 18410.474 | F47: =SUM(F45:F46) -> 9433.077 | G47: =SUM(G45:G46) -> 25741 | H47: =SUM(H45:H46) -> 33036 | I47: =SUM(I45:I46) -> 46630 | J47: =SUM(J45:J46) -> 11475 | M47: =SUM(M45:M46) -> 3578.913 | N47: =SUM(N45:N46) -> 6350.91 | O47: =SUM(O45:O46) -> 5711.205 | P47: =SUM(P45:P46) -> 2769.446 | Q47: =SUM(Q45:Q46) -> 3097.274 | R47: =SUM(R45:R46) -> 1525.077 | S47: =SUM(S45:S46) -> 3872.036 | T47: =SUM(T45:T46) -> 938.69 | ... AK47: =SUM(AK45:AK46) -> 6197
B48: % growth | D48: =+D47/C47-1 -> 4.0402665 | E48: =+E47/D47-1 -> 0.24202622 | F48: =+F47/E47-1 -> -0.48762444 | G48: =+G47/F47-1 -> 1.7288021 | H48: =+H47/G47-1 -> 0.28340002 | I48: =+I47/H47-1 -> 0.4114905 | J48: =+J47/I47-1 -> -0.75391379 | Q48: =Q47/M47-1 -> -0.1345769 | R48: =R47/N47-1 -> -0.75986481 | S48: =S47/O47-1 -> -0.32202819 | T48: =T47/P47-1 -> -0.66105495 | U48: =U47/Q47-1 -> 0.2343112 | V48: =V47/R47-1 -> 2.3965498 | W48: =W47/S47-1 -> 1.6510601 | X48: =X47/T47-1 -> 5.8957803 | ... AK48: =AK47/AG47-1 -> -0.50704001
B49: % margin | C49: =+C47/C7 -> 0.0063653187 | D49: =+D47/D7 -> 0.025694628 | E49: =+E47/E7 -> 0.024685475 | F49: =+F47/F7 -> 0.0099129411 | G49: =+G47/G7 -> 0.024603436 | H49: =+H47/H7 -> 0.030457414 | I49: =+I47/I7 -> 0.040239244 | J49: =+J47/J7 -> 0.0087656646 | M49: =+M47/M7 -> 0.024478697 | N49: =+N47/N7 -> 0.031588072 | O49: =+O47/O7 -> 0.032782611 | P49: =+P47/P7 -> 0.012345512 | Q49: =+Q47/Q7 -> 0.015244278 | R49: =+R47/R7 -> 0.0060089605 | S49: =+S47/S7 -> 0.017704106 | T49: =+T47/T7 -> 0.0034021952 | ... AK49: =+AK47/AK7 -> 0.019629768
B51: Adjustment | C51: =C52-C47 -> 2726.058 | D51: =D52-D47 -> -1011.914 | E51: =E52-E47 -> 2270.647 | F51: =F52-F47 -> 9278.521 | G51: =G52-G47 -> 7861 | H51: =H52-H47 -> 9416 | I51: =I52-I47 -> 5293 | J51: =J52-J47 -> 6869 | M51: =M52-M47 -> 935.434 | N51: =N52-N47 -> 549.515 | O51: =O52-O47 -> 890.537 | P51: =P52-P47 -> -104.839 | Q51: =Q52-Q47 -> 1842.529 | R51: =R52-R47 -> 2221.732 | S51: =S52-S47 -> 1991.042 | T51: =T52-T47 -> 3223.218 | ... AK51: =AK52-AK47 -> 1821
B52: Adj. EBITDA | C52: 5666.961 | D52: 13811.021 | E52: 20681.121 | F52: 18711.598 | G52: 33602 | H52: 42452 | I52: 51923 | J52: 18344 | M52: 4514.347 | N52: 6900.425 | O52: 6601.742 | P52: =E52-SUM(M52:O52) -> 2664.607 | Q52: 4939.803 | R52: 3746.809 | S52: 5863.078 | T52: =F52-SUM(Q52:S52) -> 4161.908 | U52: 6066 | V52: 7175 | W52: 11463 | X52: =G52-SUM(U52:W52) -> 8898 | Y52: 9499 | Z52: 10403 | AA52: 12889 | AB52: =H52-SUM(Y52:AA52) -> 9661 | AC52: 10787 | AD52: 13530 | AE52: 15077 | AF52: =I52-SUM(AC52:AE52) -> 12529 | AG52: 13702 | AH52: 2999 | AI52: 2466 | AJ52: =J52-SUM(AG52:AI52) -> -823 | AK52: 8018
B53: % growth | D53: =+D52/C52-1 -> 1.4371124 | E53: =+E52/D52-1 -> 0.49743607 | F53: =+F52/E52-1 -> -0.095232894 | G53: =+G52/F52-1 -> 0.79578463 | H53: =+H52/G52-1 -> 0.26337718 | I53: =+I52/H52-1 -> 0.22309903 | J53: =+J52/I52-1 -> -0.64670762 | Q53: =Q52/M52-1 -> 0.094245303 | R53: =R52/N52-1 -> -0.45701765 | S53: =S52/O52-1 -> -0.11188926 | T53: =T52/P52-1 -> 0.56192189 | U53: =U52/Q52-1 -> 0.22798419 | V53: =V52/R52-1 -> 0.91496284 | W53: =W52/S52-1 -> 0.95511641 | X53: =X52/T52-1 -> 1.1379617 | ... AK53: =AK52/AG52-1 -> -0.41482995
B54: % margin | C54: =+C52/C7 -> 0.012265625 | D54: =+D52/D7 -> 0.023940539 | E54: =+E52/E7 -> 0.027730047 | F54: =+F52/F7 -> 0.019663464 | G54: =+G52/G7 -> 0.032117037 | H54: =+H52/H7 -> 0.03913846 | I54: =+I52/I7 -> 0.044806825 | J54: =+J52/J7 -> 0.014012841 | M54: =+M52/M7 -> 0.030876786 | N54: =+N52/N7 -> 0.034321242 | O54: =+O52/O7 -> 0.037894339 | P54: =+P52/P7 -> 0.011878166 | Q54: =+Q52/Q7 -> 0.024312906 | R54: =+R52/R7 -> 0.014762813 | S54: =+S52/S7 -> 0.026807746 | T54: =+T52/T7 -> 0.015084451 | ... AK54: =+AK52/AK7 -> 0.025398012
B56: Capex sales | C56: =-C65/C7 -> 0.030041481 | D56: =-D65/D7 -> 0.0063030813 | E56: =-E65/E7 -> 0.0065545879 | F56: =-F65/F7 -> 0.014068002 | G56: =-G65/G7 -> 0.010256768 | H56: =-H65/H7 -> 0.0083030474 | I56: =-I65/I7 -> 0.0051526597 | J56: =-J65/J7 -> 0.006279195 | M56: =-M65/M7 -> 0 | N56: =-N65/N7 -> 0 | O56: =-O65/O7 -> 0 | P56: =-P65/P7 -> 0 | Q56: =-Q65/Q7 -> 0 | R56: =-R65/R7 -> 0 | S56: =-S65/S7 -> 0 | T56: =-T65/T7 -> 0.019865378 | ... AK56: =-AK65/AK7 -> 0.027118032
B57: WC SALES | C57: =C61/C7 -> 0.0090095541 | D57: =D61/D7 -> 0.00034517763 | E57: =E61/E7 -> 0.015395518 | F57: =F61/F7 -> 0.045870492 | G57: =G61/G7 -> 0.0078223269 | H57: =H61/H7 -> 0.013087026 | I57: =I61/I7 -> 0.0027131071 | J57: =J61/J7 -> -0.010094837
B59: CASH FLOW | C59: =C3 -> 43465 | D59: =D3 -> 43830 | E59: =E3 -> 44196 | F59: =F3 -> 44561 | G59: =G3 -> 44926 | H59: =H3 -> 45291 | I59: =I3 -> 45657 | J59: =J3 -> 46022 | M59: =M3 -> 43921 | N59: =N3 -> 44012 | O59: =O3 -> 44104 | P59: =P3 -> 44196 | Q59: =Q3 -> 44286 | R59: =R3 -> 44377 | S59: =S3 -> 44469 | T59: =T3 -> 44561 | ... AK59: =AK3 -> 46112
B60: Adj. EBITDA | C60: =C52 -> 5666.961 | D60: =D52 -> 13811.021 | E60: =E52 -> 20681.121 | F60: =F52 -> 18711.598 | G60: =G52 -> 33602 | H60: =H52 -> 42452 | I60: =I52 -> 51923 | J60: =J52 -> 18344
B61: Working Capital | C61: =4162.592 -> 4162.592 | D61: =3723.398-13915.61+10391.341 -> 199.129 | E61: =-412.132+799.356+11094.782 -> 11482.006 | F61: =-5632+16697+32585 -> 43650 | G61: =-7196+17658-2278 -> 8184 | H61: =-310+4614+9891 -> 14195 | I61: =-4546-20154+27844 -> 3144 | J61: =-2526-5780-4909 -> -13215
B62: Taxes | C62: =-666.305-2342.058+5466.698 -> 2458.335 | D62: -807.622 | E62: -1190.062 | F62: -2538 | G62: -2555 | H62: -5462 | I62: -8807 | J62: -8697
B63: Cash interest paid | C63: -421.035 | D63: -679.12 | E63: -1019.932 | F63: -1221 | G63: -2393 | H63: -2808 | I63: -2774 | J63: -2684
B64: Net cash from operations | C64: =SUM(C60:C63) -> 11866.853 | D64: =SUM(D60:D63) -> 12523.408 | E64: =SUM(E60:E63) -> 29953.133 | F64: =SUM(F60:F63) -> 58602.598 | G64: =SUM(G60:G63) -> 36838 | H64: =SUM(H60:H63) -> 48377 | I64: =SUM(I60:I63) -> 43486 | J64: =SUM(J60:J63) -> -6252 | T64: 6472 | U64: -3485 | V64: 33667 | W64: 9151 | X64: 18486 | Y64: -21607 | Z64: 46511 | AA64: 15004 | AB64: 19613 | AC64: -11315 | AD64: 46511 | AE64: -6219 | AF64: 24891 | AG64: -18262 | AH64: 24409 | AI64: -8035 | AJ64: 20879 | AK64: 555
B65: Net Capex | C65: =-9743.453-4136.305 -> -13879.758 | D65: =-2597.069-1039.106 -> -3636.175 | E65: =-3370.165-1518.259 -> -4888.424 | F65: =-5562-7825 -> -13387 | G65: =-5495-5236 -> -10731 | H65: =-4025-4981 -> -9006 | I65: =-5353-618 -> -5971 | J65: =-7823-397 -> -8220 | T65: =-3867-1614 -> -5481 | U65: =-902-2676 -> -3578 | V65: =-4947-513 -> -5460 | W65: =-3784-1522 -> -5306 | X65: =-6097-1539 -> -7636 | Y65: =-2145-1068 -> -3213 | Z65: =-2363-1244 -> -3607 | AA65: =-3013-1980 -> -4993 | AB65: =-4596-1969 -> -6565 | AC65: =-1360-1520 -> -2880 | AD65: =-2363-1244 -> -3607 | AE65: =-3461-1897 -> -5358 | AF65: =-875-1789 -> -2664 | AG65: =-915-1408 -> -2323 | AH65: =-1076-1956 -> -3032 | AI65: =-78-2518 -> -2596 | AJ65: =-2029-2755 -> -4784 | AK65: =-5063-3498 -> -8561
B66: Purchase of intangible assets | C66: -130.797 | D66: -41.449 | E66: -19.361 | F66: -23 | G66: -10 | H66: -3 | I66: -132 | J66: 0 | T66: 1031 | U66: -1734 | V66: -1802 | W66: -1506 | X66: 1194 | Y66: -582 | Z66: -1586 | AA66: -1747 | AB66: 251 | AC66: -1281 | AD66: -1586 | AE66: -2232 | AF66: 1243 | AG66: -1018 | AH66: 641 | AI66: -618 | AJ66: 1215 | AK66: -1973
B67: Disposals/ Acquistion, of subsidiaries, businesses | C67: -19.578 | D67: -41.38 | E67: 671.356 | F67: -321 | G67: -15684 | H67: 0 | I67: -2776 | J67: -1105
B68: Free cash flow | C68: =SUM(C64:C67) -> -2163.28 | D68: =SUM(D64:D67) -> 8804.404 | E68: =SUM(E64:E67) -> 25716.704 | F68: =SUM(F64:F67) -> 44871.598 | G68: =SUM(G64:G67) -> 10413 | H68: =SUM(H64:H67) -> 39368 | I68: =SUM(I64:I67) -> 34607 | J68: =SUM(J64:J67) -> -15577 | T68: 2292 | U68: -8797 | V68: 33009 | W68: 2339 | X68: 12044 | Y68: -25402 | Z68: 44490 | AA68: 8264 | AB68: 13299 | AC68: =SUM(AC64:AC66) -> -15476 | AD68: =SUM(AD64:AD66) -> 41318 | AE68: =SUM(AE64:AE66) -> -13809 | AF68: =SUM(AF64:AF66) -> 23470 | AG68: =SUM(AG64:AG66) -> -21603 | AH68: =SUM(AH64:AH66) -> 22018 | AI68: =SUM(AI64:AI66) -> -11249 | AJ68: =SUM(AJ64:AJ66) -> 17310 | AK68: =SUM(AK64:AK66) -> -9979
B69: Other Investing | C69: =-26078.992-SUM(C65:C67) -> -12048.859 | D69: =-25349.357-SUM(D65:D67) -> -21630.353 | E69: =-57810.588-SUM(E65:E67) -> -53574.159 | F69: =-74248-SUM(F65:F67) -> -60517 | G69: =-54026-SUM(G65:G67) -> -27601 | H69: =-59543-SUM(H65:H67) -> -50534 | I69: =-871-SUM(I65:I67) -> 8008 | J69: =-80193+133308-60+3213-935+2881-83617+82915+169-3607-5964+4887-680-1160 -> 51157
B70: Equity Issuance | C70: =3531.87+48.555+15958.792 -> 19539.217 | D70: 112.153 | E70: =31341.555+235.889+443.039 -> 32020.483 | F70: =0+62+0 -> 62 | G70: 1043 | H70: 33 | I70: 27 | J70: 33
B71: Dividends | C71: 0 | D71: 0 | E71: 0 | F71: 0 | G71: -13087 | H71: -6741 | I71: -8263 | J71: -10379
B72: Net Change in debt | C72: =-1200+2890.575-11960.194 -> -10269.619 | D72: =-5969.768-3886.227 -> -9855.995 | E72: =14765.536-16581.632-123.296+6803.716-72.326 -> 4791.998 | F72: =7133-5982-29+0-3246 -> -2124 | G72: =33208-31804+14101-3635-31 -> 11839 | H72: =17343-16192+13157-11195-0 -> 3113 | I72: =13628-13253+13999 -> 14374 | J72: =34271-24003 -> 10268
B73: Other financing activities | C73: =11219.928-SUM(C70:C72) -> 1950.33 | D73: =2572.467-SUM(D70:D72) -> 12316.309 | E73: =71071.595-SUM(E70:E72) -> 34259.114 | F73: =19503-SUM(F70:F72) -> 21565 | G73: =1180-SUM(G70:G72) -> 1385 | H73: =-5808-SUM(H70:H72) -> -2213 | I73: =-25912+31-829-432 -> -27142 | J73: =-21430+2650-7175-695 -> -26650
B74: Cash flow after financing activities | C74: =SUM(C68:C73) -> -2992.211 | D74: =SUM(D68:D73) -> -10253.482 | E74: =SUM(E68:E73) -> 43214.14 | F74: =SUM(F68:F73) -> 3857.598 | G74: =SUM(G68:G73) -> -16008 | H74: =SUM(H68:H73) -> -16974 | I74: =SUM(I68:I73) -> 21611 | J74: =SUM(J68:J73) -> 8852
B75: Balancing figure | C75: =7703.521-C74-C76 -> 9014.569 | D75: =2410.221-D74-D76 -> 12257.812 | E75: =50722.944-E74-E76 -> 12591.184 | F75: =-13942-F74-F76 -> -16301.598 | G75: =8463-G74-G76 -> 20981 | H75: =-5705-H74-H76 -> 11144 | I75: =36318-I74-I76 -> 14609 | J75: =33909-J74-J76 -> 25243
B76: FX | C76: 1681.163 | D76: 405.891 | E76: -5082.38 | F76: -1498 | G76: 3490 | H76: 125 | I76: 98 | J76: -186
B77: Net change in cash | C77: =SUM(C74:C76) -> 7703.521 | D77: =SUM(D74:D76) -> 2410.221 | E77: =SUM(E74:E76)-115.918 -> 50607.026 | F77: =SUM(F74:F76) -> -13942 | G77: =SUM(G74:G76) -> 8463 | H77: =SUM(H74:H76)+41 -> -5664 | I77: =SUM(I74:I76)+53 -> 36371 | J77: =SUM(J74:J76) -> 33909
B78: Cash and cash equivalents | C78: =29798.537+C77 -> 37502.058 | D78: =C78+D77 -> 39912.279 | E78: =D78+E77 -> 90519.305 | F78: =E78+F77+115.918 -> 76693.223 | G78: =F78+G77-41.2 -> 85115.023 | H78: =G78+H77-53 -> 79398.023 | I78: =H78+I77-53 -> 115716.02 | J78: =I78+J77 -> 149625.02
B80: check 1 | C80: =+C78-C120-3239.613+2035.575 -> 0 | D80: =+D78-D120-2940.859+24603 -> 0.223 | E80: =+E78-E120-4434.448+60577 -> -0.11 | F80: =+F78-F120-5926.692+114564 -> -0.218 | G80: =+G78-G120-6254+141095 -> 0.023 | H80: =+H78-H120-7506+118254 -> 0.023 | I80: =+I78-I120-7366+125645 -> 0.023 | J80: =+J78-J120-12137+75744 -> 0.023
B81: check 2 | C81: =20881.422-(C64+C75) -> 0 | D81: =24781.22-(D64+D75) -> 0 | E81: =42544.317-(E64+E75) -> 0 | F81: =42301-(F64+F75) -> 0 | G81: =57819-(G64+G75) -> 0 | H81: =59521-(H64+H75) -> 0 | I81: =58095-(I64+I75) -> 0 | J81: =18991-(J64+J75) -> 0
B83: LTM | C83: =C3 -> 43465 | D83: =D3 -> 43830 | E83: =E3 -> 44196 | F83: =F3 -> 44561 | G83: =G3 -> 44926 | H83: =H3 -> 45291 | I83: =I3 -> 45657 | J83: =J3 -> 46022 | M83: =M3 -> 43921 | N83: =N3 -> 44012 | O83: =O3 -> 44104 | P83: =P3 -> 44196 | Q83: =Q3 -> 44286 | R83: =R3 -> 44377 | S83: =S3 -> 44469 | T83: =T3 -> 44561 | ... AK83: =AK3 -> 46112
B84: =B7 -> Revenue | C84: =C7 -> 462019.76 | D84: =D7 -> 576888.48 | E84: =E7 -> 745801.89 | F84: =F7 -> 951592.15 | G84: =G7 -> 1046236 | H84: =H7 -> 1084662 | I84: =I7 -> 1158819 | J84: =J7 -> 1309085 | P84: =SUM(M7:P7) -> 745801.89 | Q84: =SUM(N7:Q7) -> 802772.85 | R84: =SUM(O7:R7) -> 855519.26 | S84: =SUM(P7:S7) -> 900013.15 | T84: =SUM(Q7:T7) -> 951592.15 | U84: =SUM(R7:U7) -> 988070.98 | V84: =SUM(S7:V7) -> 1001870.5 | W84: =SUM(T7:W7) -> 1026697.2 | ... AK84: =SUM(AH7:AK7) -> 1323697
B85: Operating profit | C85: =C19 -> -2619.131 | D85: =D19 -> 8994.88 | E85: =E19 -> 12342.82 | F85: =F19 -> 4140.95 | G85: =G19 -> 19723 | H85: =H19 -> 26025 | I85: =I19 -> 38736 | J85: =J19 -> 2774 | P85: =SUM(M19:P19) -> 12342.82 | Q85: =SUM(N19:Q19) -> 11682.115 | R85: =SUM(O19:R19) -> 6938.796 | S85: =SUM(P19:S19) -> 5127.884 | T85: =SUM(Q19:T19) -> 4140.95 | U85: =SUM(R19:U19) -> 4890.206 | V85: =SUM(S19:V19) -> 8347.45 | W85: =SUM(T19:W19) -> 14503.013 | ... AK85: =SUM(AH19:AK19) -> -3952
B86: EBITDA | C86: =+C47 -> 2940.903 | D86: =+D47 -> 14822.935 | E86: =+E47 -> 18410.474 | F86: =+F47 -> 9433.077 | G86: =+G47 -> 25741 | H86: =+H47 -> 33036 | I86: =+I47 -> 46630 | J86: =+J47 -> 11475 | P86: =SUM(M47:P47) -> 18410.474 | Q86: =SUM(N47:Q47) -> 17928.835 | R86: =SUM(O47:R47) -> 13103.002 | S86: =SUM(P47:S47) -> 11263.833 | T86: =SUM(Q47:T47) -> 9433.077 | U86: =SUM(R47:U47) -> 10158.803 | V86: =SUM(S47:V47) -> 13813.726 | W86: =SUM(T47:W47) -> 20206.69 | ... AK86: =SUM(AH47:AK47) -> 5101
B87: Adjusted EBITDA | C87: =+C52 -> 5666.961 | D87: =+D52 -> 13811.021 | E87: =+E52 -> 20681.121 | F87: =+F52 -> 18711.598 | G87: =+G52 -> 33602 | H87: =+H52 -> 42452 | I87: =+I52 -> 51923 | J87: =+J52 -> 18344 | P87: =SUM(M52:P52) -> 20681.121 | Q87: =SUM(N52:Q52) -> 21106.577 | R87: =SUM(O52:R52) -> 17952.961 | S87: =SUM(P52:S52) -> 17214.297 | T87: =SUM(Q52:T52) -> 18711.598 | U87: =SUM(R52:U52) -> 19837.795 | V87: =SUM(S52:V52) -> 23265.986 | W87: =SUM(T52:W52) -> 28865.908 | ... AK87: =SUM(AH52:AK52) -> 12660
B88: Cash interest paid | C88: =-C63 -> 421.035 | D88: =-D63 -> 679.12 | E88: =-E63 -> 1019.932 | F88: =-F63 -> 1221 | G88: =-G63 -> 2393 | H88: =-H63 -> 2808 | I88: =-I63 -> 2774 | J88: =-J63 -> 2684
B89: Net Income | C89: =+C26 -> -2800.55 | D89: =+D26 -> 11890.092 | E89: =+E26 -> 49337.246 | F89: =+F26 -> -4467.285 | G89: =+G26 -> 9691 | H89: =+H26 -> 23257 | I89: =+I26 -> 44660 | J89: =+J26 -> 23142 | P89: =SUM(M26:P26) -> 49337.246 | Q89: =SUM(N26:Q26) -> 51922.561 | R89: =SUM(O26:R26) -> 35987.062 | S89: =SUM(P26:S26) -> 25132.99 | T89: =SUM(Q26:T26) -> -4467.285 | U89: =SUM(R26:U26) -> -11627.783 | V89: =SUM(S26:V26) -> -8076.307 | W89: =SUM(T26:W26) -> 1151.28 | ... AK89: =SUM(AH26:AK26) -> 17693
B90: Capex | C90: =-C65 -> 13879.758 | D90: =-D65 -> 3636.175 | E90: =-E65 -> 4888.424 | F90: =-F65 -> 13387 | G90: =-G65 -> 10731 | H90: =-H65 -> 9006 | I90: =-I65 -> 5971 | J90: =-J65 -> 8220 | T90: =-13510-5055 -> -18565 | U90: =-14563-4122 -> -18685 | V90: =-16637-4849 -> -21486 | W90: =-15274-4551 -> -19825 | X90: =-17504-4476 -> -21980 | Y90: =-16974-4641 -> -21615 | Z90: =-14390-5372 -> -19762 | AA90: =-13618-5831 -> -19449 | AB90: =-12117-6261 -> -18378 | AC90: =-11332-6713 -> -18045 | AD90: =-10559-7200 -> -17759 | AE90: =-11007-7117 -> -18124 | AF90: =-7286-6937 -> -14223 | AG90: =-6841-6825 -> -13666 | AH90: =-6327-7050 -> -13377 | AI90: =-2944-7671 -> -10615 | AJ90: =-4098-8637 -> -12735 | AK90: =-6681-8794 -> -15475
B91: Free cash flow | C91: =+C68 -> -2163.28 | D91: =+D68 -> 8804.404 | E91: =+E68 -> 25716.704 | F91: =+F68 -> 44871.598 | G91: =+G68 -> 10413 | H91: =+H68 -> 39368 | I91: =+I68 -> 34607 | J91: =+J68 -> -15577 | T91: 26228 | U91: 27173 | V91: 27660 | W91: =25843 -> 25843 | X91: 35595 | Y91: 18990 | Z91: 33471 | AA91: 39396 | AB91: 40651 | AC91: 50577 | AD91: 55642 | AE91: 33569 | AF91: 43740 | AG91: 37613 | AH91: 10076 | AI91: 33569 | AJ91: 6476 | AK91: 21598
B93: BALANCE SHEET | C93: =C3 -> 43465 | D93: =D3 -> 43830 | E93: =E3 -> 44196 | F93: =F3 -> 44561 | G93: =G3 -> 44926 | H93: =H3 -> 45291 | I93: =I3 -> 45657 | J93: =J3 -> 46022 | M93: =M3 -> 43921 | N93: =N3 -> 44012 | O93: =O3 -> 44104 | P93: =P3 -> 44196 | Q93: =Q3 -> 44286 | R93: =R3 -> 44377 | S93: =S3 -> 44469 | T93: =T3 -> 44561 | ... AK93: =AK3 -> 46112
B95: Tangible fixed assets | C95: =21082.838+10475.658 -> 31558.496 | D95: =20654.071+10891.742 -> 31545.813 | E95: =22596.57+11124.913 -> 33721.483 | F95: =32944.163 +14327.797 -> 47271.96 | G95: =55080+33848 -> 88928 | H95: =70035+39563 -> 109598 | I95: =82737+36833 -> 119570 | J95: =91349+36878 -> 128227 | M95: =17487.942+10432.47 -> 27920.412 | N95: =17909.536+10902.645 -> 28812.181 | O95: =21579.057+11032.402 -> 32611.459 | P95: =E95 -> 33721.483 | Q95: =22463.058+11787.709 -> 34250.767 | R95: =25135.571+12480.251 -> 37615.822 | S95: =27884.937+13321.66 -> 41206.597 | T95: =F95 -> 47271.96 | U95: =42255+27392 -> 69647 | V95: =44569+27884 -> 72453 | W95: =51686+33487 -> 85173 | X95: =G95 -> 88928 | Y95: =57296+33939 -> 91235 | Z95: =59862+37752 -> 97614 | AA95: =66649+37975 -> 104624 | AB95: =H95 -> 109598 | AC95: =71255+38646 -> 109901 | AD95: =78178+38436 -> 116614 | AE95: =84203+38154 -> 122357 | AF95: =I95 -> 119570 | AG95: =83054+36820 -> 119874 | AH95: =87160+37173 -> 124333 | AI95: =88559+36877 -> 125436 | AJ95: =J95 -> 128227 | AK95: =93920+36817 -> 130737
B96: Inventory | C96: 44030.084 | D96: 57932.156 | E96: 58932.519 | F96: 75601.327 | G96: 77949 | H96: 68058 | I96: 89326 | J96: 95428 | M96: 50584.695 | N96: 54476.745 | O96: 55345.624 | P96: =E96 -> 58932.519 | Q96: 59524.389 | R96: 65768.288 | S96: 60043.995 | T96: =F96 -> 75601.327 | U96: 68790 | V96: 76029 | W96: 71757 | X96: =G96 -> 77949 | Y96: 63299 | Z96: 63562 | AA96: 64638 | AB96: =H96 -> 68058 | AC96: 67994 | AD96: 70644 | AE96: 72883 | AF96: =I96 -> 89326 | AG96: 95434 | AH96: 103537 | AI96: 100999 | AJ96: =J96 -> 95428 | AK96: 96166
B97: Trade accounts receivable | C97: 11109.988 | D97: 6190.588 | E97: 7111.947 | F97: 11899.851 | G97: 20576 | H97: 20302 | I97: 25596 | J97: 27333 | M97: 8264.122 | N97: 9674.251 | O97: 6691.873 | P97: =E97 -> 7111.947 | Q97: 7751.204 | R97: 13948.093 | S97: 10951.303 | T97: =F97 -> 11899.851 | U97: 12729 | V97: 15841 | W97: 16419 | X97: =G97 -> 20576 | Y97: 15583 | Z97: 20003 | AA97: 20705 | AB97: =H97 -> 20302 | AC97: 17540 | AD97: 21643 | AE97: 19714 | AF97: =I97 -> 25596 | AG97: 31380 | AH97: 41983 | AI97: 39735 | AJ97: =J97 -> 27333 | AK97: 25430
B98: Trade accounts payable | C98: 79985.018 | D98: 90428.382 | E98: 106818.43 | F98: 140484.11 | G98: 160607 | H98: 166167 | I98: 192860 | J98: 188379 | M98: 76485.078 | N98: 100209.9 | O98: 105302.64 | P98: =E98 -> 106818.43 | Q98: 97098.678 | R98: 127966.5 | S98: 126442.31 | T98: =F98 -> 140484.11 | U98: 125253 | V98: 159932 | W98: 150624 | X98: =G98 -> 160607 | Y98: 121432 | Z98: 152011 | AA98: 153563 | AB98: =H98 -> 166167 | AC98: 146831 | AD98: 182247 | AE98: 162500 | AF98: =I98 -> 192860 | AG98: 176736 | AH98: 211711 | AI98: 189804 | AJ98: =J98 -> 188379 | AK98: 187215
B99: Net working capital | C99: =+C96+C97-C98 -> -24844.946 | D99: =+D96+D97-D98 -> -26305.638 | E99: =+E96+E97-E98 -> -40773.959 | F99: =+F96+F97-F98 -> -52982.927 | G99: =+G96+G97-G98 -> -62082 | H99: =+H96+H97-H98 -> -77807 | I99: =+I96+I97-I98 -> -77938 | J99: =+J96+J97-J98 -> -65618 | M99: =+M96+M97-M98 -> -17636.261 | N99: =+N96+N97-N98 -> -36058.909 | O99: =+O96+O97-O98 -> -43265.147 | P99: =+P96+P97-P98 -> -40773.959 | Q99: =+Q96+Q97-Q98 -> -29823.085 | R99: =+R96+R97-R98 -> -48250.12 | S99: =+S96+S97-S98 -> -55447.01 | T99: =+T96+T97-T98 -> -52982.927 | ... AK99: =+AK96+AK97-AK98 -> -65619
B100: % of revenues | C100: =+C99/C84 -> -0.05377464 | D100: =+D99/D84 -> -0.045599173 | E100: =+E99/E84 -> -0.0546713 | F100: =+F99/F84 -> -0.055678188 | G100: =+G99/G84 -> -0.059338428 | H100: =+H99/H84 -> -0.071733867 | I100: =+I99/I84 -> -0.067256405 | J100: =+J99/J84 -> -0.050125087 | P100: =+P99/P84 -> -0.0546713 | Q100: =+Q99/Q84 -> -0.037150092 | R100: =+R99/R84 -> -0.056398637 | S100: =+S99/S84 -> -0.061606889 | T100: =+T99/T84 -> -0.055678188 | U100: =+U99/U84 -> -0.044262002 | V100: =+V99/V84 -> -0.067934927 | W100: =+W99/W84 -> -0.060824168 | ... AK100: =+AK99/AK84 -> -0.049572523
B102: Inventory Days | C102: =IFERROR((C96/-C9)*365,"-") -> 40.576509 | D102: =IFERROR((D96/-D9)*365,"-") -> 42.937334 | E102: =IFERROR((E96/-E9)*365,"-") -> 33.784494 | F102: =IFERROR((F96/-F9)*365,"-") -> 33.548486 | G102: =IFERROR((G96/-G9)*365,"-") -> 31.642077 | H102: =IFERROR((H96/-H9)*365,"-") -> 26.856538 | I102: =IFERROR((I96/-I9)*365,"-") -> 33.44167 | J102: =IFERROR((J96/-J9)*365,"-") -> 31.691914 | M102: =IFERROR((M96/-M9)*(365/4),"-") -> 37.324045 | N102: =IFERROR((N96/-N9)*(365/4),"-") -> 28.831018 | O102: =IFERROR((O96/-O9)*(365/4),"-") -> 34.257951 | P102: =IFERROR((P96/-P9)*(365/4),"-") -> 27.83637 | Q102: =IFERROR((Q96/-Q9)*(365/4),"-") -> 31.206383 | R102: =IFERROR((R96/-R9)*(365/4),"-") -> 27.024509 | S102: =IFERROR((S96/-S9)*(365/4),"-") -> 29.203403 | T102: =IFERROR((T96/-T9)*(365/4),"-") -> 28.890535 | ... AK102: =IFERROR((AK96/-AK9)*(365/4),"-") -> 33.40788
B103: Receivable Days | C103: =IFERROR((C97/C7)*365,"-") -> 8.7769961 | D103: =IFERROR((D97/D7)*365,"-") -> 3.9168135 | E103: =IFERROR((E97/E7)*365,"-") -> 3.4806303 | F103: =IFERROR((F97/F7)*365,"-") -> 4.5643983 | G103: =IFERROR((G97/G7)*365,"-") -> 7.1783422 | H103: =IFERROR((H97/H7)*365,"-") -> 6.8318333 | I103: =IFERROR((I97/I7)*365,"-") -> 8.0621219 | J103: =IFERROR((J97/J7)*365,"-") -> 7.6210063 | M103: =IFERROR((M97/M7)*(365/4),"-") -> 5.1578267 | N103: =IFERROR((N97/N7)*(365/4),"-") -> 4.3907366 | O103: =IFERROR((O97/O7)*(365/4),"-") -> 3.5050672 | P103: =IFERROR((P97/P7)*(365/4),"-") -> 2.8929278 | Q103: =IFERROR((Q97/Q7)*(365/4),"-") -> 3.4812024 | R103: =IFERROR((R97/R7)*(365/4),"-") -> 5.0148193 | S103: =IFERROR((S97/S7)*(365/4),"-") -> 4.5691276 | T103: =IFERROR((T97/T7)*(365/4),"-") -> 3.9356043 | ... AK103: =IFERROR((AK97/AK7)*(365/4),"-") -> 7.3504327
B104: Payable Days | C104: =IFERROR((C98/-C9)*365,"-") -> 73.711256 | D104: =IFERROR((D98/-D9)*365,"-") -> 67.022426 | E104: =IFERROR((E98/-E9)*365,"-") -> 61.236249 | F104: =IFERROR((F98/-F9)*365,"-") -> 62.34056 | G104: =IFERROR((G98/-G9)*365,"-") -> 65.195693 | H104: =IFERROR((H98/-H9)*365,"-") -> 65.571577 | I104: =IFERROR((I98/-I9)*365,"-") -> 72.2025 | J104: =IFERROR((J98/-J9)*365,"-") -> 62.561209 | M104: =IFERROR((M98/-M9)*(365/4),"-") -> 56.434708 | N104: =IFERROR((N98/-N9)*(365/4),"-") -> 53.034623 | O104: =IFERROR((O98/-O9)*(365/4),"-") -> 65.180453 | P104: =IFERROR((P98/-P9)*(365/4),"-") -> 50.454948 | Q104: =IFERROR((Q98/-Q9)*(365/4),"-") -> 50.90516 | R104: =IFERROR((R98/-R9)*(365/4),"-") -> 52.582056 | S104: =IFERROR((S98/-S9)*(365/4),"-") -> 61.497335 | T104: =IFERROR((T98/-T9)*(365/4),"-") -> 53.685049 | ... AK104: =IFERROR((AK98/-AK9)*(365/4),"-") -> 65.038123
B106: Debt Breakdown
B107: Short-term debt | C107: 147.264 | D107: 0 | E107: 3259.882 | F107: 4367.675 | G107: 12146 | H107: 5034 | I107: 7581 | J107: =8014+3511 -> 11525 | M107: 8601.811 | N107: =3532.83+8788.184 -> 12321.014 | O107: =3400.371+2941.671 -> 6342.042 | P107: =E107 -> 3259.882 | Q107: =3285.003+1017.699 -> 4302.702 | R107: 562.398 | S107: 7027.897 | T107: =F107 -> 4367.675 | U107: 17151 | V107: 13754 | W107: 17996 | X107: =G107 -> 12146 | Y107: 14280 | Z107: 17951 | AA107: 13740 | AB107: =H107 -> 5034 | AC107: 5267 | AD107: 5601 | AE107: 9684 | AF107: =I107 -> 7581 | AG107: 4230 | AH107: =11661+3571 -> 15232 | AI107: =17062+3547 -> 20609 | AJ107: =J107 -> 11525 | AK107: =8274+3459 -> 11733
B108: Long-term debt | C108: =6786.143+3088.44 -> 9874.583 | D108: =6912.492+3139.29 -> 10051.782 | E108: =9594.556+2936.205 -> 12530.761 | F108: =9385.959 -> 9385.959 | G108: =10224+20009 -> 30233 | H108: =10411+31555 -> 41966 | I108: =24770+31705 -> 56475 | J108: =20798+41675 -> 62473 | M108: =13943.189+3188.295 -> 17131.484 | N108: =10404.25+3185.775 -> 13590.025 | O108: =10011.115+3176.15 -> 13187.265 | P108: =E108 -> 12530.761 | Q108: =9665.524+2957.085 -> 12622.609 | R108: =9504.686+2907.045 -> 12411.731 | S108: =2947.91+9544.666 -> 12492.576 | T108: =F108 -> 9385.959 | U108: =9311+6298 -> 15609 | V108: =9847+14812 -> 24659 | W108: =10420+18193 -> 28613 | X108: =G108 -> 30233 | Y108: =19245+10091 -> 29336 | Z108: =10614+21450 -> 32064 | AA108: =10550+22191 -> 32741 | AB108: =H108 -> 41966 | AC108: =10432+32157 -> 42589 | AD108: =24514+32267 -> 56781 | AE108: =24126+29721 -> 53847 | AF108: =I108 -> 56475 | AG108: =24758+31492 -> 56250 | AH108: =35454+21141 -> 56595 | AI108: =38957+21005 -> 59962 | AJ108: =J108 -> 62473 | AK108: =20494+42162 -> 62656
B109: Total Debt | C109: =SUM(C107:C108) -> 10021.847 | D109: =SUM(D107:D108) -> 10051.782 | E109: =SUM(E107:E108) -> 15790.643 | F109: =SUM(F107:F108) -> 13753.634 | G109: =SUM(G107:G108) -> 42379 | H109: =SUM(H107:H108) -> 47000 | I109: =SUM(I107:I108) -> 64056 | J109: =SUM(J107:J108) -> 73998 | M109: =SUM(M107:M108) -> 25733.295 | N109: =SUM(N107:N108) -> 25911.039 | O109: =SUM(O107:O108) -> 19529.307 | P109: =SUM(P107:P108) -> 15790.643 | Q109: =SUM(Q107:Q108) -> 16925.311 | R109: =SUM(R107:R108) -> 12974.129 | S109: =SUM(S107:S108) -> 19520.473 | T109: =SUM(T107:T108) -> 13753.634 | ... AK109: =SUM(AK107:AK108) -> 74389
B111: Lease Obligations
B112: Short-term | C112: 0 | D112: 3193.48 | E112: 5513.534 | F112: 6664.839 | G112: 7688 | H112: 7755 | I112: 7606 | J112: 9399 | M112: 3406.984 | N112: 4109.88 | O112: 4962.214 | P112: =E112 -> 5513.534 | Q112: 5667.129 | R112: 6061.668 | S112: 6404.137 | T112: =F112 -> 6664.839 | U112: 6686 | V112: 6861 | W112: 7640 | X112: =G112 -> 7688 | Y112: 7964 | Z112: 7945 | AA112: 8097 | AB112: =H112 -> 7755 | AC112: 7859 | AD112: 7843 | AE112: 7675 | AF112: =I112 -> 7606 | AG112: 7801 | AH112: 8285 | AI112: 8897 | AJ112: =J112 -> 9399 | AK112: 9486
B113: Long-term | C113: 0 | D113: 5523.164 | E113: 10249.957 | F113: 13720.797 | G113: 14978 | H113: 13676 | I113: 18106 | J113: 23708 | M113: 5325.542 | N113: 7492.961 | O113: 9476.701 | P113: =E113 -> 10249.957 | Q113: 10256.31 | R113: 11471.003 | S113: 11683.031 | T113: =F113 -> 13720.797 | U113: 13707 | V113: 13806 | W113: 14781 | X113: =G113 -> 14978 | Y113: 14493 | Z113: 14981 | AA113: 15280 | AB113: =H113 -> 13676 | AC113: 14264 | AD113: 15965 | AE113: 16792 | AF113: =I113 -> 18106 | AG113: 19151 | AH113: 20680 | AI113: 22621 | AJ113: =J113 -> 23708 | AK113: 24145
B114: Total Lease | C114: =SUM(C112:C113) -> 0 | D114: =SUM(D112:D113) -> 8716.644 | E114: =SUM(E112:E113) -> 15763.491 | F114: =SUM(F112:F113) -> 20385.636 | G114: =SUM(G112:G113) -> 22666 | H114: =SUM(H112:H113) -> 21431 | I114: =SUM(I112:I113) -> 25712 | J114: =SUM(J112:J113) -> 33107 | M114: =SUM(M112:M113) -> 8732.526 | N114: =SUM(N112:N113) -> 11602.841 | O114: =SUM(O112:O113) -> 14438.915 | P114: =SUM(P112:P113) -> 15763.491 | Q114: =SUM(Q112:Q113) -> 15923.439 | R114: =SUM(R112:R113) -> 17532.671 | S114: =SUM(S112:S113) -> 18087.168 | T114: =SUM(T112:T113) -> 20385.636 | ... AK114: =SUM(AK112:AK113) -> 33631
...

Sheet KPIs
B2: JD.com, Inc. | C2: Annual | D2: Annual | E2: Annual | F2: Annual | G2: Annual | H2: Annual | I2: Annual | J2: Annual | M2: Quarters | N2: Quarters | O2: Quarters | P2: Quarters | Q2: Quarters | R2: Quarters | S2: Quarters | T2: Quarters | U2: Quarters | V2: Quarters | W2: Quarters | X2: Quarters | Y2: Quarters | Z2: Quarters | AA2: Quarters | AB2: Quarters | AC2: Quarters | AD2: Quarters | AE2: Quarters | AF2: Quarters | AG2: Quarters | AH2: Quarters | AI2: Quarters | AJ2: Quarters | AK2: Quarters
B3: (RMB million) | C3: 43465 | D3: 43830 | E3: 44196 | F3: 44561 | G3: 44926 | H3: 45291 | I3: 45657 | J3: 46022 | M3: 43921 | N3: 44012 | O3: 44104 | P3: 44196 | Q3: 44286 | R3: 44377 | S3: 44469 | T3: 44561 | U3: 44651 | V3: 44742 | W3: 44834 | X3: 44926 | Y3: 45016 | Z3: 45107 | AA3: 45199 | AB3: 45291 | AC3: 45382 | AD3: 45473 | AE3: 45565 | AF3: 45657 | AG3: 45747 | AH3: 45838 | AI3: 45930 | AJ3: 46022 | AK3: 46112
C4: Act | D4: Act | E4: Act | F4: Act | G4: Act | H4: Act | I4: Act | J4: Act | M4: Act | N4: Act | O4: Act | P4: Act | Q4: Act | R4: Act | S4: Act | T4: Act | U4: Act | V4: Act | W4: Act | X4: Act | Y4: Act | Z4: Act | AA4: Act | AB4: Act | AC4: Act | AD4: Act | AE4: Act | AF4: Act | AG4: Act | AH4: Act | AI4: Act | AJ4: Act | AK4: Act
C5: FY | D5: FY | E5: FY | F5: FY | G5: FY | H5: FY | I5: FY | J5: FY | M5: 1Q | N5: 2Q | O5: 3Q | P5: 4Q | Q5: 1Q | R5: 2Q | S5: 3Q | T5: 4Q | U5: 1Q | V5: 2Q | W5: 3Q | X5: 4Q | Y5: 1Q | Z5: 2Q | AA5: 3Q | AB5: 4Q | AC5: 1Q | AD5: 2Q | AE5: 3Q | AF5: 4Q | AG5: 1Q | AH5: 2Q | AI5: 3Q | AJ5: 4Q | AK5: 1Q
B7: Net revenues
B8: JD Retail | C8: 447502.17 | D8: 552245.14 | E8: 702929.62 | F8: 866302.54 | G8: 929929 | H8: 945343 | I8: 1015948 | J8: 1126399 | M8: 137356.07 | N8: 189482.78 | O8: 161081.24 | P8: =E8-SUM(M8:O8) -> 215009.52 | Q8: 185796.24 | R8: 232556.81 | S8: 198080.24 | T8: =F8-SUM(Q8:S8) -> 249869.24 | U8: 217524 | V8: 241557 | W8: 211923 | X8: =G8-SUM(U8:W8) -> 258925 | Y8: 212358 | Z8: 253280 | AA8: 212059 | AB8: =H8-SUM(Y8:AA8) -> 267646 | AC8: 226835 | AD8: 257072 | AE8: 224986 | AF8: =I8-SUM(AC8:AE8) -> 307055 | AG8: 263845 | AH8: 310075 | AI8: 250577 | AJ8: =J8-SUM(AG8:AI8) -> 301902 | AK8: 268588
B9: JD Logistics | F9: 104693.4 | G9: 137402 | H9: 166625 | I9: 182837 | J9: 217146 | M9: 13656.913 | N9: 17885.953 | O9: 17964.35 | P9: =E9-SUM(M9:O9) -> -49507.216 | Q9: 22411.019 | R9: 26061.431 | S9: 25749.276 | T9: =F9-SUM(Q9:S9) -> 30471.676 | U9: 27351 | V9: 31272 | W9: 35771 | X9: =G9-SUM(U9:W9) -> 43008 | Y9: 36728 | Z9: 41033 | AA9: 41663 | AB9: =H9-SUM(Y9:AA9) -> 47201 | AC9: 42137 | AD9: 44207 | AE9: 44396 | AF9: =I9-SUM(AC9:AE9) -> 52097 | AG9: 46967 | AH9: 51564 | AI9: 55084 | AJ9: =J9-SUM(AG9:AI9) -> 63531 | AK9: 60581
B10: Dada | G10: 8030 | U10: 688 | V10: 2281 | W10: 2380 | X10: =G10-SUM(U10:W10) -> 2681 | Y10: 2576 | Z10: 2811 | AA10: 2867 | AB10: =H10-SUM(Y10:AA10) -> -8254
B11: New businesses | C11: 14665.281 | D11: 23932.278 | E11: 42790.954 | F11: 26063.231 | G11: 21779 | H11: 26617 | I11: 19157 | J11: 49282 | M11: 3309.375 | N11: 4345.183 | O11: 4302.067 | P11: =E11-SUM(M11:O11) -> 30834.329 | Q11: 5154.277 | R11: 6963.307 | S11: 5732.81 | T11: =F11-SUM(Q11:S11) -> 8212.837 | U11: 5756 | V11: 6265 | W11: 4997 | X11: =G11-SUM(U11:W11) -> 4761 | Y11: 3450 | Z11: 4316 | AA11: 3818 | AB11: =H11-SUM(Y11:AA11) -> 15033 | AC11: 4870 | AD11: 4636 | AE11: 4970 | AF11: =I11-SUM(AC11:AE11) -> 4681 | AG11: 5753 | AH11: 13852 | AI11: 15592 | AJ11: =J11-SUM(AG11:AI11) -> 14085 | AK11: 6279
B12: Inter-segment | C12: -1103.943 | D12: -435.364 | E12: -724.639 | F12: -46042.537 | G12: -50904 | H12: -53923 | I12: -59123 | J12: -83742 | M12: -8440.135 | N12: -10844.903 | O12: -9291.697 | P12: =E12-SUM(M12:O12) -> 27852.096 | Q12: -10321.12 | R12: -11920.408 | S12: -11003.427 | T12: =F12-SUM(Q12:S12) -> -12797.582 | U12: -11664 | V12: -13775 | W12: -11536 | X12: =G12-SUM(U12:W12) -> -13929 | Y12: -12156 | Z12: -13509 | AA12: -12709 | AB12: =H12-SUM(Y12:AA12) -> -15549 | AC12: -13793 | AD12: -14518 | AE12: -13965 | AF12: =I12-SUM(AC12:AE12) -> -16847 | AG12: -15483 | AH12: -18831 | AI12: -22194 | AJ12: =J12-SUM(AG12:AI12) -> -27234 | AK12: -19754
B13: Total segment net revenues | C13: =SUM(C8:C12) -> 461063.51 | D13: =SUM(D8:D12) -> 575742.06 | E13: =SUM(E8:E12) -> 744995.93 | F13: =SUM(F8:F12) -> 951016.64 | G13: =SUM(G8:G12) -> 1046236 | H13: =SUM(H8:H12) -> 1084662 | I13: =SUM(I8:I12) -> 1158819 | J13: =SUM(J8:J12) -> 1309085 | M13: =SUM(M8:M12) -> 145882.23 | N13: =SUM(N8:N12) -> 200869.01 | O13: =SUM(O8:O12) -> 174055.97 | P13: =SUM(P8:P12) -> 224188.73 | Q13: =SUM(Q8:Q12) -> 203040.42 | R13: =SUM(R8:R12) -> 253661.14 | S13: =SUM(S8:S12) -> 218558.9 | T13: =SUM(T8:T12) -> 275756.18 | ... AK13: =SUM(AK8:AK12) -> 315694
B14: Unallocated items | C14: 956.248 | D14: 1146.429 | E14: 805.952 | F14: 575.519 | G14: 0 | H14: 0 | I14: 0 | J14: 0 | M14: 322.982 | N14: 185.045 | O14: 158.499 | P14: =E14-SUM(M14:O14) -> 139.426 | Q14: 135.754 | R14: 139.33 | S14: 149.454 | T14: =F14-SUM(Q14:S14) -> 150.981 | U14: 0 | V14: 0 | W14: 0 | X14: =G14-SUM(U14:W14) -> 0 | Z14: 0 | AA14: 0 | AB14: =H14-SUM(Y14:AA14) -> 0 | AD14: 0 | AE14: 0 | AF14: =I14-SUM(AC14:AE14) -> 0 | AH14: 0 | AI14: 0 | AJ14: =J14-SUM(AG14:AI14) -> 0
B15: Total consolidated net revenues | C15: =SUM(C13:C14) -> 462019.76 | D15: =SUM(D13:D14) -> 576888.48 | E15: =SUM(E13:E14) -> 745801.89 | F15: =SUM(F13:F14) -> 951592.15 | G15: =SUM(G13:G14) -> 1046236 | H15: =SUM(H13:H14) -> 1084662 | I15: =SUM(I13:I14) -> 1158819 | J15: =SUM(J13:J14) -> 1309085 | M15: =SUM(M13:M14) -> 146205.21 | N15: =SUM(N13:N14) -> 201054.06 | O15: =SUM(O13:O14) -> 174214.46 | P15: =SUM(P13:P14) -> 224328.15 | Q15: =SUM(Q13:Q14) -> 203176.17 | R15: =SUM(R13:R14) -> 253800.47 | S15: =SUM(S13:S14) -> 218708.36 | T15: =SUM(T13:T14) -> 275907.16 | ... AK15: =SUM(AK13:AK14) -> 315694
B16: check | C16: =C15-Model!C7 -> 0 | D16: =D15-Model!D7 -> 0 | E16: =E15-Model!E7 -> 0 | F16: =F15-Model!F7 -> 0 | G16: =G15-Model!G7 -> 0 | H16: =H15-Model!H7 -> 0 | I16: =I15-Model!I7 -> 0 | J16: =J15-Model!J7 -> 0 | M16: =M15-Model!M7 -> 0 | N16: =N15-Model!N7 -> 0 | O16: =O15-Model!O7 -> 0 | P16: =P15-Model!P7 -> 0 | Q16: =Q15-Model!Q7 -> 0 | R16: =R15-Model!R7 -> 0 | S16: =S15-Model!S7 -> 0 | T16: =T15-Model!T7 -> 0 | ... AK16: =AK15-Model!AK7 -> 0
B18: Net revenues (Share %)
B19: JD Retail | C19: =C8/C$15 -> 0.968578 | D19: =D8/D$15 -> 0.95728231 | E19: =E8/E$15 -> 0.94251521 | F19: =F8/F$15 -> 0.91037167 | G19: =G8/G$15 -> 0.88883292 | H19: =H8/H$15 -> 0.87155538 | I19: =I8/I$15 -> 0.87670982 | J19: =J8/J$15 -> 0.86044756 | M19: =M8/M$15 -> 0.93947456 | N19: =N8/N$15 -> 0.94244693 | O19: =O8/O$15 -> 0.92461465 | P19: =P8/P$15 -> 0.95845981 | Q19: =Q8/Q$15 -> 0.91445882 | R19: =R8/R$15 -> 0.91629779 | S19: =S8/S$15 -> 0.9056821 | T19: =T8/T$15 -> 0.90562799 | ... AK19: =AK8/AK$15 -> 0.85078589
B20: JD Logistics | C20: =C9/C$15 -> 0 | D20: =D9/D$15 -> 0 | E20: =E9/E$15 -> 0 | F20: =F9/F$15 -> 0.11001919 | G20: =G9/G$15 -> 0.13132983 | H20: =H9/H$15 -> 0.15361928 | I20: =I9/I$15 -> 0.15777874 | J20: =J9/J$15 -> 0.16587617 | M20: =M9/M$15 -> 0.09340921 | N20: =N9/N$15 -> 0.088960915 | O20: =O9/O$15 -> 0.10311629 | P20: =P9/P$15 -> -0.22069105 | Q20: =Q9/Q$15 -> 0.11030338 | R20: =R9/R$15 -> 0.10268472 | S20: =S9/S$15 -> 0.11773339 | T20: =T9/T$15 -> 0.11044177 | ... AK20: =AK9/AK$15 -> 0.19189785
B21: Dada | C21: =C10/C$15 -> 0 | D21: =D10/D$15 -> 0 | E21: =E10/E$15 -> 0 | F21: =F10/F$15 -> 0 | G21: =G10/G$15 -> 0.0076751326 | H21: =H10/H$15 -> 0 | I21: =I10/I$15 -> 0 | J21: =J10/J$15 -> 0 | M21: =M10/M$15 -> 0 | N21: =N10/N$15 -> 0 | O21: =O10/O$15 -> 0 | P21: =P10/P$15 -> 0 | Q21: =Q10/Q$15 -> 0 | R21: =R10/R$15 -> 0 | S21: =S10/S$15 -> 0 | T21: =T10/T$15 -> 0 | ... AK21: =AK10/AK$15 -> 0
B22: New businesses | C22: =C11/C$15 -> 0.031741675 | D22: =D11/D$15 -> 0.041485103 | E22: =E11/E$15 -> 0.057375765 | F22: =F11/F$15 -> 0.027389077 | G22: =G11/G$15 -> 0.020816527 | H22: =H11/H$15 -> 0.024539442 | I22: =I11/I$15 -> 0.016531486 | J22: =J11/J$15 -> 0.037646142 | M22: =M11/M$15 -> 0.022635137 | N22: =N11/N$15 -> 0.021612013 | O22: =O11/O$15 -> 0.024694086 | P22: =P11/P$15 -> 0.13745189 | Q22: =Q11/Q$15 -> 0.025368512 | R22: =R11/R$15 -> 0.027436147 | S22: =S11/S$15 -> 0.026212121 | T22: =T11/T$15 -> 0.029766669 | ... AK22: =AK11/AK$15 -> 0.019889513
B23: Inter-segment | C23: =C12/C$15 -> -0.0023893848 | D23: =D12/D$15 -> -0.00075467618 | E23: =E12/E$15 -> -0.00097162398 | F23: =F12/F$15 -> -0.048384738 | G23: =G12/G$15 -> -0.048654414 | H23: =H12/H$15 -> -0.049714104 | I23: =I12/I$15 -> -0.051020047 | J23: =J12/J$15 -> -0.063969872 | M23: =M12/M$15 -> -0.057728005 | N23: =N12/N$15 -> -0.053940234 | O23: =O12/O$15 -> -0.05333482 | P23: =P12/P$15 -> 0.12415783 | Q23: =Q12/Q$15 -> -0.050798871 | R23: =R12/R$15 -> -0.046967636 | S23: =S12/S$15 -> -0.050310958 | T23: =T12/T$15 -> -0.046383654 | ... AK23: =AK12/AK$15 -> -0.062573251
B24: Total segment net revenues | C24: =C13/C$15 -> 0.99793029 | D24: =D13/D$15 -> 0.99801274 | E24: =E13/E$15 -> 0.99891935 | F24: =F13/F$15 -> 0.9993952 | G24: =G13/G$15 -> 1 | H24: =H13/H$15 -> 1 | I24: =I13/I$15 -> 1 | J24: =J13/J$15 -> 1 | M24: =M13/M$15 -> 0.9977909 | N24: =N13/N$15 -> 0.99907963 | O24: =O13/O$15 -> 0.99909021 | P24: =P13/P$15 -> 0.99937847 | Q24: =Q13/Q$15 -> 0.99933184 | R24: =R13/R$15 -> 0.99945103 | S24: =S13/S$15 -> 0.99931665 | T24: =T13/T$15 -> 0.99945278 | ... AK24: =AK13/AK$15 -> 1
B25: Unallocated items | C25: =C14/C$15 -> 0.0020697123 | D25: =D14/D$15 -> 0.0019872628 | E25: =E14/E$15 -> 0.0010806516 | F25: =F14/F$15 -> 0.00060479587 | G25: =G14/G$15 -> 0 | H25: =H14/H$15 -> 0 | I25: =I14/I$15 -> 0 | J25: =J14/J$15 -> 0 | M25: =M14/M$15 -> 0.0022091005 | N25: =N14/N$15 -> 0.00092037436 | O25: =O14/O$15 -> 0.00090979243 | P25: =P14/P$15 -> 0.00062152698 | Q25: =Q14/Q$15 -> 0.00066815907 | R25: =R14/R$15 -> 0.00054897455 | S25: =S14/S$15 -> 0.00068334837 | T25: =T14/T$15 -> 0.00054721669 | ... AK25: =AK14/AK$15 -> 0
B26: Total consolidated net revenues | C26: =SUM(C24:C25) -> 1 | D26: =SUM(D24:D25) -> 1 | E26: =SUM(E24:E25) -> 1 | F26: =SUM(F24:F25) -> 1 | G26: =SUM(G24:G25) -> 1 | H26: =SUM(H24:H25) -> 1 | I26: =SUM(I24:I25) -> 1 | J26: =SUM(J24:J25) -> 1 | M26: =SUM(M24:M25) -> 1 | N26: =SUM(N24:N25) -> 1 | O26: =SUM(O24:O25) -> 1 | P26: =SUM(P24:P25) -> 1 | Q26: =SUM(Q24:Q25) -> 1 | R26: =SUM(R24:R25) -> 1 | S26: =SUM(S24:S25) -> 1 | T26: =SUM(T24:T25) -> 1 | ... AK26: =SUM(AK24:AK25) -> 1
B28: Net revenues (YoY % Growth)
B29: JD Retail | D29: =D8/C8-1 -> 0.23406136 | E29: =E8/D8-1 -> 0.27285795 | F29: =F8/E8-1 -> 0.23241718 | G29: =G8/F8-1 -> 0.073446005 | H29: =H8/G8-1 -> 0.016575459 | I29: =I8/H8-1 -> 0.074687177 | J29: =J8/I8-1 -> 0.10871718 | Q29: =Q8/M8-1 -> 0.35266125 | R29: =R8/N8-1 -> 0.22732425 | S29: =S8/O8-1 -> 0.22969154 | T29: =T8/P8-1 -> 0.16213108 | U29: =U8/Q8-1 -> 0.17076643 | V29: =V8/R8-1 -> 0.038701038 | W29: =W8/S8-1 -> 0.069884581 | X29: =X8/T8-1 -> 0.036241975 | ... AK29: =AK8/AG8-1 -> 0.017976463
B30: JD Logistics | D30: =D9/C9-1 -> #DIV/0! | E30: =E9/D9-1 -> #DIV/0! | F30: =F9/E9-1 -> #DIV/0! | G30: =G9/F9-1 -> 0.31242273 | H30: =H9/G9-1 -> 0.21268249 | I30: =I9/H9-1 -> 0.097296324 | J30: =J9/I9-1 -> 0.18764801 | Q30: =Q9/M9-1 -> 0.64100181 | R30: =R9/N9-1 -> 0.45708931 | S30: =S9/O9-1 -> 0.43335417 | T30: =T9/P9-1 -> -1.6154997 | U30: =U9/Q9-1 -> 0.22042643 | V30: =V9/R9-1 -> 0.19993411 | W30: =W9/S9-1 -> 0.38920411 | X30: =X9/T9-1 -> 0.41140907 | ... AK30: =AK9/AG9-1 -> 0.2898631
B31: Dada | D31: =D10/C10-1 -> #DIV/0! | E31: =E10/D10-1 -> #DIV/0! | F31: =F10/E10-1 -> #DIV/0! | G31: =G10/F10-1 -> #DIV/0! | H31: =H10/G10-1 -> -1 | I31: =I10/H10-1 -> #DIV/0! | J31: =J10/I10-1 -> #DIV/0! | Q31: =Q10/M10-1 -> #DIV/0! | R31: =R10/N10-1 -> #DIV/0! | S31: =S10/O10-1 -> #DIV/0! | T31: =T10/P10-1 -> #DIV/0! | U31: =U10/Q10-1 -> #DIV/0! | V31: =V10/R10-1 -> #DIV/0! | W31: =W10/S10-1 -> #DIV/0! | X31: =X10/T10-1 -> #DIV/0! | ... AK31: =AK10/AG10-1 -> #DIV/0!
B32: New businesses | D32: =D11/C11-1 -> 0.6319004 | E32: =E11/D11-1 -> 0.78800171 | F32: =F11/E11-1 -> -0.39091727 | G32: =G11/F11-1 -> -0.16437835 | H32: =H11/G11-1 -> 0.22214059 | I32: =I11/H11-1 -> -0.28027201 | J32: =J11/I11-1 -> 1.5725322 | Q32: =Q11/M11-1 -> 0.55747747 | R32: =R11/N11-1 -> 0.60253481 | S32: =S11/O11-1 -> 0.33257106 | T32: =T11/P11-1 -> -0.73364632 | U32: =U11/Q11-1 -> 0.11674246 | V32: =V11/R11-1 -> -0.10028382 | W32: =W11/S11-1 -> -0.12835067 | X32: =X11/T11-1 -> -0.42029776 | ... AK32: =AK11/AG11-1 -> 0.091430558
B33: Inter-segment | D33: =D12/C12-1 -> -0.60562819 | E33: =E12/D12-1 -> 0.66444401 | F33: =F12/E12-1 -> 62.538585 | G33: =G12/F12-1 -> 0.10558634 | H33: =H12/G12-1 -> 0.059307716 | I33: =I12/H12-1 -> 0.096433804 | J33: =J12/I12-1 -> 0.41640309 | Q33: =Q12/M12-1 -> 0.22286196 | R33: =R12/N12-1 -> 0.099171473 | S33: =S12/O12-1 -> 0.18422146 | T33: =T12/P12-1 -> -1.4594836 | U33: =U12/Q12-1 -> 0.13010991 | V33: =V12/R12-1 -> 0.15558125 | W33: =W12/S12-1 -> 0.048400648 | X33: =X12/T12-1 -> 0.088408732 | ... AK33: =AK12/AG12-1 -> 0.27585093
B34: Total segment net revenues | D34: =D13/C13-1 -> 0.24872613 | E34: =E13/D13-1 -> 0.29397519 | F34: =F13/E13-1 -> 0.27653936 | G34: =G13/F13-1 -> 0.10012376 | H34: =H13/G13-1 -> 0.036727851 | I34: =I13/H13-1 -> 0.068368764 | J34: =J13/I13-1 -> 0.12967167 | Q34: =Q13/M13-1 -> 0.3918105 | R34: =R13/N13-1 -> 0.26281867 | S34: =S13/O13-1 -> 0.25568178 | T34: =T13/P13-1 -> 0.23001802 | U34: =U13/Q13-1 -> 0.18033151 | V34: =V13/R13-1 -> 0.054950711 | W34: =W13/S13-1 -> 0.11427627 | X34: =X13/T13-1 -> 0.071403021 | ... AK34: =AK13/AG13-1 -> 0.048531629
B35: Unallocated items | D35: =D14/C14-1 -> 0.19888251 | E35: =E14/D14-1 -> -0.29698917 | F35: =F14/E14-1 -> -0.28591405 | G35: =G14/F14-1 -> -1 | H35: =H14/G14-1 -> #DIV/0! | I35: =I14/H14-1 -> #DIV/0! | J35: =J14/I14-1 -> #DIV/0! | Q35: =Q14/M14-1 -> -0.57968556 | R35: =R14/N14-1 -> -0.24704802 | S35: =S14/O14-1 -> -0.057066606 | T35: =T14/P14-1 -> 0.082875504 | U35: =U14/Q14-1 -> -1 | V35: =V14/R14-1 -> -1 | W35: =W14/S14-1 -> -1 | X35: =X14/T14-1 -> -1 | ... AK35: =AK14/AG14-1 -> #DIV/0!
B36: Total consolidated net revenues | D36: =D15/C15-1 -> 0.24862297 | E36: =E15/D15-1 -> 0.29280079 | F36: =F15/E15-1 -> 0.27593155 | G36: =G15/F15-1 -> 0.099458414 | H36: =H15/G15-1 -> 0.036727851 | I36: =I15/H15-1 -> 0.068368764 | J36: =J15/I15-1 -> 0.12967167 | Q36: =Q15/M15-1 -> 0.38966437 | R36: =R15/N15-1 -> 0.2623494 | S36: =S15/O15-1 -> 0.25539724 | T36: =T15/P15-1 -> 0.22992656 | U36: =U15/Q15-1 -> 0.17954286 | V36: =V15/R15-1 -> 0.05437157 | W36: =W15/S15-1 -> 0.11351483 | X36: =X15/T15-1 -> 0.070816731 | ... AK36: =AK15/AG15-1 -> 0.048531629
B39: Operating income/(loss)
B40: JD Retail | C40: 7049.222 | D40: 13775.339 | E40: 19484.484 | F40: 26612.604 | G40: 34852 | H40: 35925 | I40: 41077 | J40: 51402 | M40: 5061.433 | N40: 4859.411 | O40: 6734.811 | P40: =E40-SUM(M40:O40) -> 2828.829 | Q40: 7340.103 | R40: 5986.538 | S40: 7942.242 | T40: =F40-SUM(Q40:S40) -> 5343.721 | U40: 7891 | V40: 8173 | W40: 10926 | X40: =G40-SUM(U40:W40) -> 7862 | Y40: 9844 | Z40: 8143 | AA40: 11001 | AB40: =H40-SUM(Y40:AA40) -> 6937 | AC40: 9325 | AD40: 10108 | AE40: 11608 | AF40: =I40-SUM(AC40:AE40) -> 10036 | AG40: 12846 | AH40: 13939 | AI40: 14828 | AJ40: =J40-SUM(AG40:AI40) -> 9789 | AK40: 14960
B41: JD Logistics | F41: -1827.056 | G41: 528 | H41: 1005 | I41: 6317 | J41: 5269 | M41: -421.385 | N41: 2101.478 | O41: 83.549 | P41: =E41-SUM(M41:O41) -> -1763.642 | Q41: -1473.582 | R41: -356.599 | S41: -726.612 | T41: =F41-SUM(Q41:S41) -> 729.737 | U41: -661 | V41: 36 | W41: 253 | X41: =G41-SUM(U41:W41) -> 900 | Y41: -1123 | Z41: 510 | AA41: 288 | AB41: =H41-SUM(Y41:AA41) -> 1330 | AC41: 224 | AD41: 2183 | AE41: 2086 | AF41: =I41-SUM(AC41:AE41) -> 1824 | AG41: 145 | AH41: 1958 | AI41: 1282 | AJ41: =J41-SUM(AG41:AI41) -> 1884 | AK41: 1020
B42: Dada | G42: -1122 | U42: -191 | V42: -424 | W42: -300 | X42: =G42-SUM(U42:W42) -> -207 | Y42: -217 | Z42: -29 | AA42: -52 | AB42: =H42-SUM(Y42:AA42) -> 298
B43: New businesses | C43: -5136.657 | D43: -1022.281 | E43: -2498.85 | F43: -10599.085 | G43: -5295 | H43: -329 | I43: -2865 | J43: -46641 | M43: -1384.165 | N43: -1171.713 | O43: -1200.492 | P43: =E43-SUM(M43:O43) -> 1257.52 | Q43: -2281.486 | R43: -3020.114 | S43: -2073.45 | T43: =F43-SUM(Q43:S43) -> -3224.035 | U43: -2386 | V43: -2032 | W43: 276 | X43: =G43-SUM(U43:W43) -> -1153 | Y43: -157 | Z43: 1061 | AA43: -140 | AB43: =H43-SUM(Y43:AA43) -> -1093 | AC43: -670 | AD43: -695 | AE43: -615 | AF43: =I43-SUM(AC43:AE43) -> -885 | AG43: -1327 | AH43: -14777 | AI43: -15736 | AJ43: =J43-SUM(AG43:AI43) -> -14801 | AK43: -10352
B44: Total segment operating income | C44: =SUM(C40:C43) -> 1912.565 | D44: =SUM(D40:D43) -> 12753.058 | E44: =SUM(E40:E43) -> 16985.634 | F44: =SUM(F40:F43) -> 14186.463 | G44: =SUM(G40:G43) -> 28963 | H44: =SUM(H40:H43) -> 36601 | I44: =SUM(I40:I43) -> 44529 | J44: =SUM(J40:J43) -> 10030 | M44: =SUM(M40:M43) -> 3255.883 | N44: =SUM(N40:N43) -> 5789.176 | O44: =SUM(O40:O43) -> 5617.868 | P44: =SUM(P40:P43) -> 2322.707 | Q44: =SUM(Q40:Q43) -> 3585.035 | R44: =SUM(R40:R43) -> 2609.825 | S44: =SUM(S40:S43) -> 5142.18 | T44: =SUM(T40:T43) -> 2849.423 | ... AK44: =SUM(AK40:AK43) -> 5628
B45: Unallocated items | C45: -4531.696 | D45: -3758.178 | E45: -4642.814 | F45: -10045.513 | G45: -9240 | H45: -10576 | I45: -5793 | J45: -7256 | M45: -935.434 | N45: -745.101 | O45: -1234.519 | P45: =E45-SUM(M45:O45) -> -1727.76 | Q45: -1925.291 | R45: -2309.069 | S45: -2569.743 | T45: =F45-SUM(Q45:S45) -> -3241.41 | U45: -2244 | V45: -1995 | W45: -2427 | X45: =G45-SUM(U45:W45) -> -2574 | Y45: -1920 | Z45: -1415 | AA45: -1794 | AB45: =H45-SUM(Y45:AA45) -> -5447 | AC45: -1179 | AD45: -1095 | AE45: -1035 | AF45: =I45-SUM(AC45:AE45) -> -2484 | AG45: -1131 | AH45: -1979 | AI45: -1425 | AJ45: =J45-SUM(AG45:AI45) -> -2721 | AK45: -1821
B46: Total consolidated operating income | C46: =SUM(C44:C45) -> -2619.131 | D46: =SUM(D44:D45) -> 8994.88 | E46: =SUM(E44:E45) -> 12342.82 | F46: =SUM(F44:F45) -> 4140.95 | G46: =SUM(G44:G45) -> 19723 | H46: =SUM(H44:H45) -> 26025 | I46: =SUM(I44:I45) -> 38736 | J46: =SUM(J44:J45) -> 2774 | M46: =SUM(M44:M45) -> 2320.449 | N46: =SUM(N44:N45) -> 5044.075 | O46: =SUM(O44:O45) -> 4383.349 | P46: =SUM(P44:P45) -> 594.947 | Q46: =SUM(Q44:Q45) -> 1659.744 | R46: =SUM(R44:R45) -> 300.756 | S46: =SUM(S44:S45) -> 2572.437 | T46: =SUM(T44:T45) -> -391.987 | ... AK46: =SUM(AK44:AK45) -> 3807
B47: check | C47: =C46-Model!C19 -> -3.5470293e-11 | D47: =D46-Model!D19 -> -6.184564e-11 | E47: =E46-Model!E19 -> -7.8216544e-11 | F47: =F46-Model!F19 -> 7.4578566e-11 | G47: =G46-Model!G19 -> 0 | H47: =H46-Model!H19 -> 0 | I47: =I46-Model!I19 -> 0 | J47: =J46-Model!J19 -> 0 | M47: =M46-Model!M19 -> -1.1823431e-11 | N47: =N46-Model!N19 -> 7.2759576e-12 | O47: =O46-Model!O19 -> -1.0004442e-11 | P47: =P46-Model!P19 -> -5.7298166e-11 | Q47: =Q46-Model!Q19 -> 0 | R47: =R46-Model!R19 -> -1.2732926e-11 | S47: =S46-Model!S19 -> 5.9117156e-12 | T47: =T46-Model!T19 -> 4.9112714e-11 | ... AK47: =AK46-Model!AK19 -> 0
B49: Revenues by product
B50: Electronics and home appliances revenues | C50: 280059 | D50: 328703 | E50: 400927 | F50: 492592.26 | G50: 515945 | H50: 538799 | I50: 564982 | J50: 605131 | M50: 77630.952 | N50: 114147.36 | O50: 93329.728 | P50: =E50-SUM(M50:O50) -> 115818.96 | Q50: 104005.73 | R50: 136773.76 | S50: 110881.05 | T50: =F50-SUM(Q50:S50) -> 140931.72 | U50: 118368 | V50: 136618 | W50: 119284 | X50: =G50-SUM(U50:W50) -> 141675 | Y50: 116999 | Z50: 152131 | AA50: 119316 | AB50: =H50-SUM(Y50:AA50) -> 150353 | AC50: 123212 | AD50: 145061 | AE50: 122560 | AF50: =I50-SUM(AC50:AE50) -> 174149 | AG50: 144295 | AH50: 178982 | AI50: 128587 | AJ50: =J50-SUM(AG50:AI50) -> 153267 | AK50: 132171
B51: General merchandise revenues | C51: 136050 | D51: 182031 | E51: 250952 | F51: 323062.62 | G51: 349117 | H51: 332425 | I51: 363025 | J51: 418671 | M51: 52462.186 | N51: 64039.523 | O51: 58069.531 | P51: =E51-SUM(M51:O51) -> 76380.76 | Q51: 71276.078 | R51: 82916.122 | S51: 75127.319 | T51: =F51-SUM(Q51:S51) -> 93743.101 | U51: 86048 | V51: 89402 | W51: 77743 | X51: =G51-SUM(U51:W51) -> 95924 | Y51: 78565 | Z51: 81724 | AA51: 75988 | AB51: =H51-SUM(Y51:AA51) -> 96148 | AC51: 85296 | AD51: 88847 | AE51: 82053 | AF51: =I51-SUM(AC51:AE51) -> 106829 | AG51: 98014 | AH51: 103432 | AI51: 97505 | AJ51: =J51-SUM(AG51:AI51) -> 119720 | AK51: 112648
B52: Net product revenues | C52: =SUM(C50:C51) -> 416109 | D52: =SUM(D50:D51) -> 510734 | E52: =SUM(E50:E51) -> 651879 | F52: =SUM(F50:F51) -> 815654.88 | G52: =SUM(G50:G51) -> 865062 | H52: =SUM(H50:H51) -> 871224 | I52: =SUM(I50:I51) -> 928007 | J52: =SUM(J50:J51) -> 1023802 | M52: =SUM(M50:M51) -> 130093.14 | N52: =SUM(N50:N51) -> 178186.88 | O52: =SUM(O50:O51) -> 151399.26 | P52: =SUM(P50:P51) -> 192199.72 | Q52: =SUM(Q50:Q51) -> 175281.8 | R52: =SUM(R50:R51) -> 219689.88 | S52: =SUM(S50:S51) -> 186008.36 | T52: =SUM(T50:T51) -> 234674.82 | ... AK52: =SUM(AK50:AK51) -> 244819
B53: Marketplace and marketing revenues | C53: 33532 | D53: 42680 | E53: 53473 | F53: 72118.163 | G53: 81970 | H53: 84726 | I53: 90111 | J53: 107131 | M53: 9526.815 | N53: 14052.871 | O53: 12412.342 | P53: =E53-SUM(M53:O53) -> 17480.972 | Q53: 14119.827 | R53: 18984.788 | S53: 16774.786 | T53: =F53-SUM(Q53:S53) -> 22238.762 | U53: 17676 | V53: 20742 | W53: 18954 | X53: =G53-SUM(U53:W53) -> 24598 | Y53: 19062 | Z53: 22509 | AA53: 19529 | AB53: =H53-SUM(Y53:AA53) -> 23626 | AC53: 19289 | AD53: 23425 | AE53: 20763 | AF53: =I53-SUM(AC53:AE53) -> 26634 | AG53: 22320 | AH53: 28507 | AI53: 25688 | AJ53: =J53-SUM(AG53:AI53) -> 30616 | AK53: 26517
B54: Logistics and other service revenues | C54: 12379 | D54: 23474 | E54: 40450 | F54: 63819.114 | G54: 99204 | H54: 128712 | I54: 140701 | J54: 178152 | M54: 6585.256 | N54: 8814.306 | O54: 10402.863 | P54: =E54-SUM(M54:O54) -> 14647.575 | Q54: 13774.538 | R54: 15125.798 | S54: 15925.207 | T54: =F54-SUM(Q54:S54) -> 18993.571 | U54: 17563 | V54: 20838 | W54: 27554 | X54: =G54-SUM(U54:W54) -> 33249 | Y54: 28330 | Z54: 31567 | AA54: 32865 | AB54: =H54-SUM(Y54:AA54) -> 35950 | AC54: 32252 | AD54: 34064 | AE54: 35011 | AF54: =I54-SUM(AC54:AE54) -> 39374 | AG54: 36453 | AH54: 45739 | AI54: 47279 | AJ54: =J54-SUM(AG54:AI54) -> 48681 | AK54: 44358
B55: Net service revenues | C55: =SUM(C53:C54) -> 45911 | D55: =SUM(D53:D54) -> 66154 | E55: =SUM(E53:E54) -> 93923 | F55: =SUM(F53:F54) -> 135937.28 | G55: =SUM(G53:G54) -> 181174 | H55: =SUM(H53:H54) -> 213438 | I55: =SUM(I53:I54) -> 230812 | J55: =SUM(J53:J54) -> 285283 | M55: =SUM(M53:M54) -> 16112.071 | N55: =SUM(N53:N54) -> 22867.177 | O55: =SUM(O53:O54) -> 22815.205 | P55: =SUM(P53:P54) -> 32128.547 | Q55: =SUM(Q53:Q54) -> 27894.365 | R55: =SUM(R53:R54) -> 34110.586 | S55: =SUM(S53:S54) -> 32699.993 | T55: =SUM(T53:T54) -> 41232.333 | ... AK55: =SUM(AK53:AK54) -> 70875
B56: Total net revenues | C56: =C55+C52 -> 462020 | D56: =D55+D52 -> 576888 | E56: =E55+E52 -> 745802 | F56: =F55+F52 -> 951592.15 | G56: =G55+G52 -> 1046236 | H56: =H55+H52 -> 1084662 | I56: =I55+I52 -> 1158819 | J56: =J55+J52 -> 1309085 | M56: =M55+M52 -> 146205.21 | N56: =N55+N52 -> 201054.06 | O56: =O55+O52 -> 174214.46 | P56: =P55+P52 -> 224328.27 | Q56: =Q55+Q52 -> 203176.17 | R56: =R55+R52 -> 253800.47 | S56: =S55+S52 -> 218708.36 | T56: =T55+T52 -> 275907.16 | ... AK56: =AK55+AK52 -> 315694
B57: check | C57: =C56-Model!C7 -> 0.241 | D57: =D56-Model!D7 -> -0.484 | E57: =E56-Model!E7 -> 0.114 | F57: =F56-Model!F7 -> 0 | G57: =G56-Model!G7 -> 0 | H57: =H56-Model!H7 -> 0 | I57: =I56-Model!I7 -> 0 | J57: =J56-Model!J7 -> 0 | M57: =M56-Model!M7 -> 0 | N57: =N56-Model!N7 -> 0 | O57: =O56-Model!O7 -> 0 | P57: =P56-Model!P7 -> 0.114 | Q57: =Q56-Model!Q7 -> 0 | R57: =R56-Model!R7 -> 0 | S57: =S56-Model!S7 -> 0 | T57: =T56-Model!T7 -> 0 | ... AK57: =AK56-Model!AK7 -> 0
B59: Revenues by product (Share %)
B60: Electronics and home appliances revenues | C60: =C50/C$56 -> 0.60616207 | D60: =D50/D$56 -> 0.56978651 | E60: =E50/E$56 -> 0.53757834 | F60: =F50/F$56 -> 0.51765061 | G60: =G50/G$56 -> 0.49314399 | H60: =H50/H$56 -> 0.49674369 | I60: =I50/I$56 -> 0.48754982 | J60: =J50/J$56 -> 0.46225493 | M60: =M50/M$56 -> 0.53097255 | N60: =N50/N$56 -> 0.56774461 | O60: =O50/O$56 -> 0.53571745 | P60: =P50/P$56 -> 0.51629232 | Q60: =Q50/Q$56 -> 0.51189924 | R60: =R50/R$56 -> 0.53890271 | S60: =S50/S$56 -> 0.50698129 | T60: =T50/T$56 -> 0.51079401 | ... AK60: =AK50/AK$56 -> 0.41866808
B61: General merchandise revenues | C61: =C51/C$56 -> 0.29446777 | D61: =D51/D$56 -> 0.31553958 | E61: =E51/E$56 -> 0.33648609 | F61: =F51/F$56 -> 0.33949694 | G61: =G51/G$56 -> 0.33368858 | H61: =H51/H$56 -> 0.30647796 | I61: =I51/I$56 -> 0.31327153 | J61: =J51/J$56 -> 0.31981957 | M61: =M51/M$56 -> 0.3588257 | N61: =N51/N$56 -> 0.31851893 | O61: =O51/O$56 -> 0.3333221 | P61: =P51/P$56 -> 0.34048656 | Q61: =Q51/Q$56 -> 0.35080924 | R61: =R51/R$56 -> 0.32669806 | S61: =S51/S$56 -> 0.34350456 | T61: =T51/T$56 -> 0.33976321 | ... AK61: =AK51/AK$56 -> 0.35682655
B62: Net product revenues | C62: =C52/C$56 -> 0.90062984 | D62: =D52/D$56 -> 0.88532609 | E62: =E52/E$56 -> 0.87406443 | F62: =F52/F$56 -> 0.85714754 | G62: =G52/G$56 -> 0.82683257 | H62: =H52/H$56 -> 0.80322165 | I62: =I52/I$56 -> 0.80082135 | J62: =J52/J$56 -> 0.7820745 | M62: =M52/M$56 -> 0.88979824 | N62: =N52/N$56 -> 0.88626354 | O62: =O52/O$56 -> 0.86903955 | P62: =P52/P$56 -> 0.85677888 | Q62: =Q52/Q$56 -> 0.86270848 | R62: =R52/R$56 -> 0.86560078 | S62: =S52/S$56 -> 0.85048586 | T62: =T52/T$56 -> 0.85055722 | ... AK62: =AK52/AK$56 -> 0.77549462
B63: Marketplace and marketing revenues | C63: =C53/C$56 -> 0.072576945 | D63: =D53/D$56 -> 0.073983165 | E63: =E53/E$56 -> 0.071698655 | F63: =F53/F$56 -> 0.075786841 | G63: =G53/G$56 -> 0.078347524 | H63: =H53/H$56 -> 0.078112813 | I63: =I53/I$56 -> 0.077761065 | J63: =J53/J$56 -> 0.08183655 | M63: =M53/M$56 -> 0.065160572 | N63: =N53/N$56 -> 0.069895983 | O63: =O53/O$56 -> 0.071247483 | P63: =P53/P$56 -> 0.077925854 | Q63: =Q53/Q$56 -> 0.069495488 | R63: =R53/R$56 -> 0.074802021 | S63: =S53/S$56 -> 0.076699337 | T63: =T53/T$56 -> 0.080602338 | ... AK63: =AK53/AK$56 -> 0.083995895
B64: Logistics and other service revenues | C64: =C54/C$56 -> 0.026793212 | D64: =D54/D$56 -> 0.040690741 | E64: =E54/E$56 -> 0.054236915 | F64: =F54/F$56 -> 0.067065616 | G64: =G54/G$56 -> 0.094819907 | H64: =H54/H$56 -> 0.11866554 | I64: =I54/I$56 -> 0.12141758 | J64: =J54/J$56 -> 0.13608895 | M64: =M54/M$56 -> 0.045041186 | N64: =N54/N$56 -> 0.043840478 | O64: =O54/O$56 -> 0.05971297 | P64: =P54/P$56 -> 0.06529527 | Q64: =Q54/Q$56 -> 0.067796032 | R64: =R54/R$56 -> 0.059597202 | S64: =S54/S$56 -> 0.072814808 | T64: =T54/T$56 -> 0.068840443 | ... AK64: =AK54/AK$56 -> 0.14050948
B65: Net service revenues | C65: =C55/C$56 -> 0.099370157 | D65: =D55/D$56 -> 0.11467391 | E65: =E55/E$56 -> 0.12593557 | F65: =F55/F$56 -> 0.14285246 | G65: =G55/G$56 -> 0.17316743 | H65: =H55/H$56 -> 0.19677835 | I65: =I55/I$56 -> 0.19917865 | J65: =J55/J$56 -> 0.2179255 | M65: =M55/M$56 -> 0.11020176 | N65: =N55/N$56 -> 0.11373646 | O65: =O55/O$56 -> 0.13096045 | P65: =P55/P$56 -> 0.14322112 | Q65: =Q55/Q$56 -> 0.13729152 | R65: =R55/R$56 -> 0.13439922 | S65: =S55/S$56 -> 0.14951414 | T65: =T55/T$56 -> 0.14944278 | ... AK65: =AK55/AK$56 -> 0.22450538
B66: Total net revenues | C66: =SUM(C62,C65) -> 1 | D66: =SUM(D62,D65) -> 1 | E66: =SUM(E62,E65) -> 1 | F66: =SUM(F62,F65) -> 1 | G66: =SUM(G62,G65) -> 1 | H66: =SUM(H62,H65) -> 1 | I66: =SUM(I62,I65) -> 1 | J66: =SUM(J62,J65) -> 1 | M66: =SUM(M62,M65) -> 1 | N66: =SUM(N62,N65) -> 1 | O66: =SUM(O62,O65) -> 1 | P66: =SUM(P62,P65) -> 1 | Q66: =SUM(Q62,Q65) -> 1 | R66: =SUM(R62,R65) -> 1 | S66: =SUM(S62,S65) -> 1 | T66: =SUM(T62,T65) -> 1 | ... AK66: =SUM(AK62,AK65) -> 1
B68: Revenues by product (YoY % Growth)
B69: Electronics and home appliances revenues | D69: =D50/C50-1 -> 0.17369197 | E69: =E50/D50-1 -> 0.21972419 | F69: =F50/E50-1 -> 0.22863328 | G69: =G50/F50-1 -> 0.047407856 | H69: =H50/G50-1 -> 0.044295419 | I69: =I50/H50-1 -> 0.048595116 | J69: =J50/I50-1 -> 0.071062441 | Q69: =Q50/M50-1 -> 0.3397456 | R69: =R50/N50-1 -> 0.198221 | S69: =S50/O50-1 -> 0.1880571 | T69: =T50/P50-1 -> 0.21682772 | U69: =U50/Q50-1 -> 0.13809119 | V69: =V50/R50-1 -> -0.0011388295 | W69: =W50/S50-1 -> 0.075783502 | X69: =X50/T50-1 -> 0.0052740219 | ... AK69: =AK50/AG50-1 -> -0.084022315
B70: General merchandise revenues | D70: =D51/C51-1 -> 0.33797133 | E70: =E51/D51-1 -> 0.37862232 | F70: =F51/E51-1 -> 0.28734826 | G70: =G51/F51-1 -> 0.08064808 | H70: =H51/G51-1 -> -0.047812052 | I70: =I51/H51-1 -> 0.092050839 | J70: =J51/I51-1 -> 0.15328421 | Q70: =Q51/M51-1 -> 0.35861815 | R70: =R51/N51-1 -> 0.29476483 | S70: =S51/O51-1 -> 0.29374765 | T70: =T51/P51-1 -> 0.22731302 | U70: =U51/Q51-1 -> 0.20724937 | V70: =V51/R51-1 -> 0.078222158 | W70: =W51/S51-1 -> 0.034816642 | X70: =X51/T51-1 -> 0.023264635 | ... AK70: =AK51/AG51-1 -> 0.1493052
B71: Net product revenues | D71: =D52/C52-1 -> 0.22740436 | E71: =E52/D52-1 -> 0.27635716 | F71: =F52/E52-1 -> 0.25123662 | G71: =G52/F52-1 -> 0.060573564 | H71: =H52/G52-1 -> 0.0071231889 | I71: =I52/H52-1 -> 0.06517612 | J71: =J52/I52-1 -> 0.10322659 | Q71: =Q52/M52-1 -> 0.34735626 | R71: =R52/N52-1 -> 0.2329184 | S71: =S52/O52-1 -> 0.22859495 | T71: =T52/P52-1 -> 0.22099461 | U71: =U52/Q52-1 -> 0.16621347 | V71: =V52/R52-1 -> 0.028813871 | W71: =W52/S52-1 -> 0.059237309 | X71: =X52/T52-1 -> 0.012460544 | ... AK71: =AK52/AG52-1 -> 0.010358674
B72: Marketplace and marketing revenues | D72: =D53/C53-1 -> 0.27281403 | E72: =E53/D53-1 -> 0.25288191 | F72: =F53/E53-1 -> 0.34868369 | G72: =G53/F53-1 -> 0.13660688 | H72: =H53/G53-1 -> 0.033622057 | I72: =I53/H53-1 -> 0.063557822 | J72: =J53/I53-1 -> 0.18887816 | Q72: =Q53/M53-1 -> 0.48211412 | R72: =R53/N53-1 -> 0.35095441 | S72: =S53/O53-1 -> 0.35146018 | T72: =T53/P53-1 -> 0.27216965 | U72: =U53/Q53-1 -> 0.2518567 | V72: =V53/R53-1 -> 0.092558948 | W72: =W53/S53-1 -> 0.12991009 | X72: =X53/T53-1 -> 0.10608675 | ... AK72: =AK53/AG53-1 -> 0.18803763
B73: Logistics and other service revenues | D73: =D54/C54-1 -> 0.89627595 | E73: =E54/D54-1 -> 0.7231831 | F73: =F54/E54-1 -> 0.57772841 | G73: =G54/F54-1 -> 0.55445593 | H73: =H54/G54-1 -> 0.29744768 | I73: =I54/H54-1 -> 0.093145938 | J73: =J54/I54-1 -> 0.26617437 | Q73: =Q54/M54-1 -> 1.091724 | R73: =R54/N54-1 -> 0.71605093 | S73: =S54/O54-1 -> 0.53084848 | T73: =T54/P54-1 -> 0.29670413 | U73: =U54/Q54-1 -> 0.27503369 | V73: =V54/R54-1 -> 0.37764632 | W73: =W54/S54-1 -> 0.73021299 | X73: =X54/T54-1 -> 0.7505397 | ... AK73: =AK54/AG54-1 -> 0.21685458
B74: Net service revenues | D74: =D55/C55-1 -> 0.4409183 | E74: =E55/D55-1 -> 0.41976298 | F74: =F55/E55-1 -> 0.44732682 | G74: =G55/F55-1 -> 0.33277644 | H74: =H55/G55-1 -> 0.17808295 | I74: =I55/H55-1 -> 0.081400688 | J74: =J55/I55-1 -> 0.23599726 | Q74: =Q55/M55-1 -> 0.73127123 | R74: =R55/N55-1 -> 0.4916833 | S74: =S55/O55-1 -> 0.4332544 | T74: =T55/P55-1 -> 0.28335505 | U74: =U55/Q55-1 -> 0.26330175 | V74: =V55/R55-1 -> 0.21897642 | W74: =W55/S55-1 -> 0.4222633 | X74: =X55/T55-1 -> 0.40295239 | ... AK74: =AK55/AG55-1 -> 0.20591088
B75: Total net revenues | D75: =D56/C56-1 -> 0.24862127 | E75: =E56/D56-1 -> 0.29280207 | F75: =F56/E56-1 -> 0.27593135 | G75: =G56/F56-1 -> 0.099458414 | H75: =H56/G56-1 -> 0.036727851 | I75: =I56/H56-1 -> 0.068368764 | J75: =J56/I56-1 -> 0.12967167 | Q75: =Q56/M56-1 -> 0.38966437 | R75: =R56/N56-1 -> 0.2623494 | S75: =S56/O56-1 -> 0.25539724 | T75: =T56/P56-1 -> 0.22992594 | U75: =U56/Q56-1 -> 0.17954286 | V75: =V56/R56-1 -> 0.05437157 | W75: =W56/S56-1 -> 0.11351483 | X75: =X56/T56-1 -> 0.070816731 | ... AK75: =AK56/AG56-1 -> 0.048531629
B77: Headcount (Employees) | C77: 178000 | D77: 220000 | E77: 310000 | M77: 220000 | N77: 240000 | O77: 284000 | P77: 310000 | Q77: 310000 | R77: 320000 | U77: 390000
B79: Key Metrics
B80: Free cash flow (in RMB billions) – trailing twelve months | H80: 40.7 | I80: 43.7 | J80: 6.5 | M80: 15.2 | N80: 22.7 | O80: 30.2 | P80: 34.9 | Q80: 28.2 | R80: 31.9 | S80: 28.5 | T80: 26.2 | U80: 27.2 | V80: 27.7 | W80: 25.8 | X80: 35.6 | Y80: 19 | Z80: 33.5 | AA80: 39.4 | AB80: 40.7 | AC80: 50.6 | AD80: 55.6 | AE80: 33.6 | AF80: 43.7 | AG80: 37.6 | AH80: 10.1 | AI80: 12.6 | AJ80: 6.5 | AK80: 21.6
B81: Inventory turnover days | C81: 38.7 | D81: 35.8 | E81: 33.3 | F81: 30.3 | G81: 33.2 | H81: 30.3 | I81: 31.5 | J81: 37.8 | M81: 35.4 | N81: 34.8 | O81: 34.3 | P81: 33.3 | Q81: 31.2 | R81: 31 | S81: 30.1 | T81: 30.3 | U81: 30.2 | V81: 31.5 | W81: 31.7 | X81: 33.2 | Y81: 32.4 | Z81: 31.7 | AA81: 30.8 | AB81: 30.3 | AC81: 29 | AD81: 29.8 | AE81: 30.4 | AF81: 31.5 | AG81: 32.8 | AH81: 34.1 | AI81: 35.8 | AJ81: 37.8 | AK81: 38.3
B82: Accounts payable turnover days | C82: 60.2 | D82: 54.5 | E82: 47.1 | F82: 45.3 | G82: 52.5 | H82: 53.2 | I82: 58.6 | J82: 60 | M82: 51.7 | N82: 50.8 | O82: 49.2 | P82: 47.1 | Q82: 44.2 | R82: 45.8 | S82: 45.5 | T82: 45.3 | U82: 45 | V82: 49.4 | W82: 50.4 | X82: 52.5 | Y82: 51.3 | Z82: 52.8 | AA82: 52.6 | AB82: 53.2 | AC82: 51.8 | AD82: 57 | AE82: 57.5 | AF82: 58.6 | AG82: 57.6 | AH82: 59 | AI82: 58 | AJ82: 60 | AK82: 59.7
B83: Accounts receivable turnover days | C83: 2.7 | D83: 3.2 | E83: 2.7 | F83: 2.9 | G83: 4.5 | H83: 5.6 | I83: 5.9 | J83: 8.7 | M83: 3.1 | N83: 2.9 | O83: 2.8 | P83: 2.7 | Q83: 2.6 | R83: 2.7 | S83: 2.8 | T83: 2.9 | U83: 3.2 | V83: 3.6 | W83: 4 | X83: 4.5 | Y83: 4.8 | Z83: 5 | AA83: 5.4 | AB83: 5.6 | AC83: 5.4 | AD83: 5.7 | AE83: 5.8 | AF83: 5.9 | AG83: 6.4 | AH83: 7.4 | AI83: 8.3 | AJ83: 8.7 | AK83: 8.7
B84: Annual active customer accounts (in millions) | C84: 305.3 | D84: 362 | E84: 471.9 | F84: 569.7 | M84: 387.4 | N84: 417.4 | O84: 441.6 | P84: 471.9 | Q84: 499.8 | R84: 531.9 | S84: 552.2 | T84: 569.7 | U84: 580.5 | V84: 580.8 | W84: 588.3
