Workbook
Name IQ_CH: 110000
Name IQ_CQ: 5000
Name IQ_CY: 10000
Name IQ_DAILY: 500000
Name IQ_FH: 100000
Name IQ_FQ: 500
Name IQ_FY: 1000
Name IQ_LTM: 2000
Name IQ_MONTH: 15000
Name IQ_NTM: 6000
Name IQ_WEEK: 50000
Name IQ_YTD: 3000

Sheet Capitalisation
A3: 1Q26 | I3: Exchange rate as at end | J3: =Model!O$204 -> 0.86557604
I4: LTM Average exchange rate | J4: =Model!O$205 -> 0.87061569
B7: Debt Breakdown as on 31-Mar-2026 | C7: EUR (mn) | D7: USD (mn) | E7: Leverage | F7: Leverage (USD) | I7: Company reported
B8: Long term | I8: Gross debt | J8: =4347.2+5030 -> 9377.2
B9: Interest-bearing loans and borrowings from financial institutions | C9: 4276.9 | D9: =C9/$J3 -> 4941.1026 | I9: Cash and cash equivalents | J9: =C17 -> 633
B10: Bonds issued | C10: 4218 | D10: =C10/$J3 -> 4873.0554 | I10: Net Debt | J10: =J8-J9 -> 8744.2
B12: Short term | I12: NORMALISED NET DEBT TO EBITDA | J12: 9.4x
B13: Interest-bearing loans and borrowings from financial institutions | C13: 70.4 | D13: =C13/$J3 -> 81.33312
B14: Bonds issued | C14: 812.1 | D14: =C14/$J3 -> 938.21913
B16: Total Debt | C16: =SUM(C9:C14) -> 9377.4 | D16: =SUM(D9:D14) -> 10833.71 | E16: =C16/C21 -> 13.053174 | F16: =D16/D21 -> 13.129173
B17: Cash and Short-Term Investments | C17: =Model!BF$130 -> 633 | D17: =C17/$J3 -> 731.3049
B18: Net debt | C18: =C16-C17 -> 8744.4 | D18: =D16-D17 -> 10102.405 | E18: =C18/C21 -> 12.172049 | F18: =D18/D21 -> 12.242918
B19: Equity | C19: =Model!BF$134 -> 8679.8 | D19: =C19/$J3 -> 10027.773
B20: Total Capitalisation | C20: =C18+C19 -> 17424.2 | D20: =C20/$J3 -> 20130.178
B21: LTM Adjusted EBITDA | C21: =Model!BF$110 -> 718.4 | D21: =C21/$J4 -> 825.16316
B22: check | C22: =+C16-Model!BF$128 -> 0
B25: Debt Maturity for 1Q26 | C25: EUR mn | D25: USD mn
B26: 2026 | C26: 327 | D26: =+C26/$J3 -> 377.7831
B27: =B26+1 -> 2027 | C27: 583 | D27: =+C27/$J3 -> 673.5399
B28: =B27+1 -> 2028 | C28: 478 | D28: =+C28/$J3 -> 552.2334
B29: =B28+1 -> 2029 | C29: 1338 | D29: =+C29/$J3 -> 1545.7914
B30: =B29+1 -> 2030 | C30: 2094 | D30: =+C30/$J3 -> 2419.1982
B31: =B30+1 -> 2031 | C31: 2438 | D31: =+C31/$J3 -> 2816.6214
B32: =B31+1 -> 2032 | C32: 1199 | D32: =+C32/$J3 -> 1385.2047
B33: =B32+1 -> 2033 | C33: 35 | D33: =+C33/$J3 -> 40.4355
B34: =B33+1 -> 2034 | C34: 397 | D34: =+C34/$J3 -> 458.6541
B35: 2035+ | C35: 513 | D35: =+C35/$J3 -> 592.6689
B36: Total Debt | C36: =+SUM(C26:C35) -> 9402 | D36: =+SUM(D26:D35) -> 10862.131
A39: FY25 | I39: Exchange rate as at end | J39: =Model!O$204 -> 0.86557604
I40: LTM Average exchange rate | J40: =Model!O$205 -> 0.87061569
B43: Debt Breakdown as on31-Dec-2025 | C43: EUR (mn) | D43: USD (mn) | E43: Leverage | F43: Leverage (USD) | I43: Company reported
B44: Long term | I44: Gross debt | J44: =5142.6+4085.9 -> 9228.5
B45: Interest-bearing loans and borrowings from financial institutions | C45: 4013.5 | D45: =C45/$J39 -> 4636.7966 | I45: Cash and cash equivalents | J45: =C53 -> 708.4
B46: Bonds issued | C46: 4434.3 | D46: =C46/$J39 -> 5122.9468 | I46: Net Debt | J46: =J44-J45 -> 8520.1
B48: Short term | I48: NORMALISED NET DEBT TO EBITDA | J48: 9.3x
B49: Interest-bearing loans and borrowings from financial institutions | C49: 72.4 | D49: =C49/$J39 -> 83.64372
B50: Bonds issued | C50: 708.4 | D50: =C50/$J39 -> 818.41452
B52: Total Debt | C52: =SUM(C45:C50) -> 9228.6 | D52: =SUM(D45:D50) -> 10661.802 | E52: =C52/C57 -> 13.161152 | F52: =D52/D57 -> 13.237781
B53: Cash and Short-Term Investments | C53: =Model!BE$130 -> 708.4 | D53: =C53/$J39 -> 818.41452
B54: Net debt | C54: =C52-C53 -> 8520.2 | D54: =D52-D53 -> 9843.3871 | E54: =C54/C57 -> 12.150884 | F54: =D54/D57 -> 12.22163
B55: Equity | C55: =Model!BE$134 -> 8462.2 | D55: =C55/$J39 -> 9776.3797
B56: Total Capitalisation | C56: =C54+C55 -> 16982.4 | D56: =C56/$J39 -> 19619.767
B57: LTM Adjusted EBITDA | C57: =Model!BE$110 -> 701.2 | D57: =C57/$J40 -> 805.40703
B58: check | C58: =+C52-Model!BE$128 -> 0
B61: Debt Maturity for FY25 | C61: EUR mn | D61: USD mn
B62: 2026 | C62: 696 | D62: =+C62/$J39 -> 804.0888
B63: =B62+1 -> 2027 | C63: 583 | D63: =+C63/$J39 -> 673.5399
B64: =B63+1 -> 2028 | C64: 478 | D64: =+C64/$J39 -> 552.2334
B65: =B64+1 -> 2029 | C65: 1338 | D65: =+C65/$J39 -> 1545.7914
B66: =B65+1 -> 2030 | C66: 1810 | D66: =+C66/$J39 -> 2091.093
B67: =B66+1 -> 2031 | C67: 2158 | D67: =+C67/$J39 -> 2493.1374
B68: =B67+1 -> 2032 | C68: 1199 | D68: =+C68/$J39 -> 1385.2047
B69: =B68+1 -> 2033 | C69: 35 | D69: =+C69/$J39 -> 40.4355
B70: =B69+1 -> 2034 | C70: 397 | D70: =+C70/$J39 -> 458.6541
B71: 2035+ | C71: 513 | D71: =+C71/$J39 -> 592.6689
B72: Total Debt | C72: =+SUM(C62:C71) -> 9207 | D72: =+SUM(D62:D71) -> 10636.847
A108: 3Q25 | I108: Exchange rate as at end 3Q25 | J108: =Model!BD$204 -> 0.8523
I109: Average exchange rate for LTM 3Q25 | J109: =Model!BD$205 -> 0.9132625
B112: Debt Breakdown as on 30-Sep-2025 | C112: EUR (mn) | D112: USD (mn) | E112: Leverage | F112: Leverage (USD) | I112: Company reported
B113: Long term | I113: Gross debt | J113: =4790.5+4246.5 -> 9037
B114: Interest-bearing loans and borrowings from financial institutions | C114: 4128.4 | D114: =C114/$J108 -> 4843.8343 | I114: Cash and cash equivalents | J114: =C122 -> 1052.2
B115: Bonds issued | C115: 3905.8 | D115: =C115/$J108 -> 4582.6587 | I115: Net Debt | J115: =J113-J114 -> 7984.8
B117: Short term | I117: NORMALISED NET DEBT TO EBITDA | J117: 9.2x
B118: Interest-bearing loans and borrowings from financial institutions | C118: 118.1 | D118: =C118/$J108 -> 138.56623
B119: Bonds issued | C119: 884.7 | D119: =C119/$J108 -> 1038.0148
B121: Total Debt | C121: =SUM(C114:C119) -> 9037 | D121: =SUM(D114:D119) -> 10603.074 | E121: =C121/C126 -> 13.305359 | F121: =D121/D126 -> 14.257052
B122: Cash and Short-Term Investments | C122: =Model!BD$130 -> 1052.2 | D122: =C122/$J108 -> 1234.5418
B123: Net debt | C123: =C121-C122 -> 7984.8 | D123: =D121-D122 -> 9368.5322 | E123: =C123/C126 -> 11.756184 | F123: =D123/D126 -> 12.597069
B124: Equity | C124: =Model!BD$134 -> 8243.9 | D124: =C124/$J108 -> 9672.5331
B125: Total Capitalisation | C125: =C123+C124 -> 16228.7 | D125: =C125/$J108 -> 19041.065
B126: LTM Adjusted EBITDA | C126: =Model!BD$110 -> 679.2 | D126: =C126/$J109 -> 743.70731
B127: check | C127: =+C121-Model!BD$128 -> 0
B129: Debt Maturity for 3Q25 | C129: EUR mn | D129: USD mn
B130: 2025 | C130: 248 | D130: =+C130/$J108 -> 290.97736
B131: 2026 | C131: 686 | D131: =+C131/$J108 -> 804.88091
B132: 2027 | C132: 588 | D132: =+C132/$J108 -> 689.89792
B133: 2028 | C133: 476 | D133: =+C133/$J108 -> 558.4888
B134: 2029 | C134: 1496 | D134: =+C134/$J108 -> 1755.2505
B135: 2030 | C135: 1885 | D135: =+C135/$J108 -> 2211.6626
B136: 2031 | C136: 2158 | D136: =+C136/$J108 -> 2531.9723
B137: 2032 | C137: 534 | D137: =+C137/$J108 -> 626.53995
B138: 2033 | C138: 35 | D138: =+C138/$J108 -> 41.065353
B139: 2034 | C139: 397 | D139: =+C139/$J108 -> 465.79843
B140: 2035+ | C140: 513 | D140: =+C140/$J108 -> 601.90074
B141: Total Debt | C141: =+SUM(C130:C140) -> 9016 | D141: =+SUM(D130:D140) -> 10578.435
A147: 2Q25 | I147: Exchange rate as at end 2Q25 | J147: =Model!BC$204 -> 0.8682
I148: Average exchange rate for LTM 2Q25 | J148: =Model!BC$205 -> 0.9268625
B151: Debt Breakdown as on 30-Jun-2025 | C151: EUR (mn) | D151: USD (mn) | E151: Leverage | F151: Leverage (USD) | I151: Company reported
B152: Long term | D152: =C152/$J147 -> 0 | I152: Gross debt | J152: =4766.3+3768.6 -> 8534.9
B153: Interest-bearing loans and borrowings from financial institutions | C153: 3663.4 | D153: =C153/$J147 -> 4219.5347 | I153: Cash and cash equivalents | J153: =C161 -> 848.4
B154: Bonds issued | C154: 4178.4 | D154: =C154/$J147 -> 4812.716 | I154: Net Debt | J154: =J152-J153 -> 7686.5
B156: Short term | I156: NORMALISED NET DEBT TO EBITDA | J156: 9.2x
B157: Interest-bearing loans and borrowings from financial institutions | C157: 105.3 | D157: =C157/$J147 -> 121.28542
B158: Bonds issued | C158: 587.9 | D158: =C158/$J147 -> 677.14812
B160: Total Debt | C160: =SUM(C153:C158) -> 8535 | D160: =SUM(D153:D158) -> 9830.6842 | E160: =C160/C165 -> 13.13279 | F160: =D160/D165 -> 14.020145
B161: Cash and Short-Term Investments | C161: =Model!BC$130 -> 848.4 | D161: =C161/$J147 -> 977.19419
B162: Net debt | C162: =C160-C161 -> 7686.6 | D162: =D160-D161 -> 8853.49 | E162: =C162/C165 -> 11.827358 | F162: =D162/D165 -> 12.626508
B163: Equity | C163: =Model!BC$134 -> 7989 | D163: =C163/$J147 -> 9201.7968
B164: Total Capitalisation | C164: =C162+C163 -> 15675.6 | D164: =C164/$J147 -> 18055.287
B165: LTM Adjusted EBITDA | C165: =Model!BC$110 -> 649.9 | D165: =C165/$J148 -> 701.18275
...

Sheet Model
B2: CTP Group | C2: Annual | D2: Annual | E2: Annual | F2: Annual | G2: Annual | H2: Annual | I2: Annual | J2: Annual | K2: Annual | L2: Annual | M2: Annual | N2: Annual | O2: LTM | Q2: Half-yearly | R2: Half-yearly | S2: Half-yearly | T2: Half-yearly | U2: Half-yearly | V2: Half-yearly | W2: Half-yearly | X2: Half-yearly | Y2: Half-yearly | Z2: Half-yearly | AA2: Half-yearly | AB2: Half-yearly | AC2: Half-yearly | AD2: Half-yearly | AF2: Quarterly | AG2: Quarterly | AH2: Quarterly | AI2: Quarterly | AJ2: Quarterly | AK2: Quarterly | AL2: Quarterly | AM2: Quarterly | AN2: Quarterly | AO2: Quarterly | AP2: Quarterly | AQ2: Quarterly | AR2: Quarterly | AS2: Quarterly | AT2: Quarterly | AU2: Quarterly | AV2: Quarterly | AW2: Quarterly | AX2: Quarterly | AY2: Quarterly | AZ2: Quarterly | BA2: Quarterly | BB2: Quarterly | BC2: Quarterly | BD2: Quarterly | BE2: Quarterly | BF2: Quarterly
B3: (EUR millions) | C3: 42735 | D3: 43100 | E3: 43465 | F3: 43830 | G3: 44196 | H3: 44561 | I3: 44926 | J3: 44926 | K3: 45291 | L3: 45291 | M3: 45657 | N3: 46022 | O3: =BF3 -> 46112 | Q3: 43646 | R3: 43830 | S3: 44012 | T3: 44196 | U3: 44377 | V3: 44561 | W3: 44742 | X3: 44926 | Y3: 45107 | Z3: 45291 | AA3: 45473 | AB3: 45657 | AC3: 45838 | AD3: 46022 | AF3: 43738 | AG3: 43830 | AH3: 43920 | AI3: 44012 | AJ3: 44104 | AK3: 44196 | AL3: 44285 | AM3: 44377 | AN3: 44469 | AO3: 44561 | AP3: 44651 | AQ3: 44742 | AR3: 44834 | AS3: 44926 | AT3: 45016 | AU3: 45107 | AV3: 45199 | AW3: 45291 | AX3: 45382 | AY3: 45473 | AZ3: 45565 | BA3: 45657 | BB3: 45747 | BC3: 45838 | BD3: 45930 | BE3: 46022 | BF3: 46112
C4: Act | D4: Act | E4: Act | F4: Act | G4: Act | H4: Act | I4: Act | J4: Restated | K4: Act | L4: Restated | M4: Act | N4: Act | O4: Act | Q4: Act | R4: Act | S4: Act | T4: Act | U4: Act | V4: Act | W4: Act | X4: Act | Y4: Act | Z4: Act | AA4: Act | AB4: Act | AC4: Act | AD4: Act | AF4: Act | AG4: Act | AH4: Act | AI4: Act | AJ4: Act | AK4: Act | AL4: Act | AM4: Act | AN4: Act | AO4: Act | AP4: Act | AQ4: Act | AR4: Act | AS4: Act | AT4: Act | AU4: Act | AV4: Act | AW4: Act | AX4: Act | AY4: Act | AZ4: Act | BA4: Act | BB4: Act | BC4: Act | BD4: Act | BE4: Act | BF4: Act
C5: FY 16 | D5: FY 17 | E5: FY 18 | F5: FY 19 | G5: FY 20 | H5: FY 21 | I5: FY 22 | J5: FY 22 | K5: FY 23 | L5: FY 23 | M5: FY 24 | N5: FY 25 | O5: LTM | Q5: 1H 19 | R5: 2H 19 | S5: 1H 20 | T5: 2H 20 | U5: 1H 21 | V5: 2H 21 | W5: 1H22 | X5: 2H 22 | Y5: 1H23 | Z5: 2H 22 | AA5: 1H24 | AB5: 2H 24 | AC5: 1H 25 | AD5: 2H 25 | AF5: 3Q19 | AG5: 4Q19 | AH5: 1Q20 | AI5: 2Q20 | AJ5: 3Q20 | AK5: 4Q20 | AL5: 1Q21 | AM5: 2Q21 | AN5: 3Q21 | AO5: 4Q21 | AP5: 1Q22 | AQ5: 2Q22 | AR5: 3Q22 | AS5: 4Q22 | AT5: 1Q23 | AU5: 2Q23 | AV5: 3Q23 | AW5: 4Q23 | AX5: 1Q24 | AY5: 2Q24 | AZ5: 3Q24 | BA5: 4Q24 | BB5: 1Q25 | BC5: 2Q25 | BD5: 3Q25 | BE5: 4Q25 | BF5: 1Q25
B6: INCOME STATEMENT
B7: Rental income | C7: 182.705 | D7: 208.26 | E7: 241.96 | F7: 257.986 | G7: 291.935 | H7: 334.651 | I7: 485.017 | J7: 485.017 | K7: 571.9 | L7: 571.9 | M7: 664.1 | N7: 759.8 | O7: =SUM(BC7:BF7) -> 782.4 | Q7: 122.901 | R7: =F7-Q7 -> 135.085 | S7: 140.587 | T7: =G7-S7 -> 151.348 | U7: 159.808 | V7: =H7-U7 -> 174.843 | W7: 230.5 | X7: =I7-W7 -> 254.517 | Y7: 280.4 | Z7: =K7-Y7 -> 291.5 | AA7: 320.9 | AB7: =M7-AA7 -> 343.2 | AC7: 367.2 | AD7: =N7-AC7 -> 392.6 | AF7: =181.313-Q7 -> 58.412 | AG7: =F7-AF7-Q7 -> 76.673 | AH7: 68.382 | AI7: =S7-AH7 -> 72.205 | AJ7: =209.693-S7 -> 69.106 | AK7: =G7-AJ7-S7 -> 82.242 | AL7: 77.772 | AM7: =U7-AL7 -> 82.036 | AN7: =245.712-U7 -> 85.904 | AO7: =H7-AN7-U7 -> 88.939 | AP7: 109.593 | AQ7: =W7-AP7 -> 120.907 | AR7: =354.226-W7 -> 123.726 | AS7: =I7-AR7-W7 -> 130.791 | AT7: 136.031 | AU7: =Y7-AT7 -> 144.369 | AV7: =421.5-Y7 -> 141.1 | AW7: =K7-AV7-Y7 -> 150.4 | AX7: 157.5 | AY7: =AA7-AX7 -> 163.4 | AZ7: =488.4-AA7 -> 167.5 | BA7: =M7-AZ7-AA7 -> 175.7 | BB7: 182.5 | BC7: =AC7-BB7 -> 184.7 | BD7: =562-AC7 -> 194.8 | BE7: =N7-AC7-BD7 -> 197.8 | BF7: 205.1
B8: Service charge income | C8: 12.325 | D8: 14.049 | E8: 19.99 | F8: 22.379 | G8: 25.882 | H8: 31.112 | I8: 51.875 | J8: 51.875 | K8: 60.7 | L8: 60.7 | M8: 75.9 | N8: 92.3 | O8: =SUM(BC8:BF8) -> 96 | Q8: 10.916 | R8: =F8-Q8 -> 11.463 | S8: 12.159 | T8: =G8-S8 -> 13.723 | U8: 14.704 | V8: =H8-U8 -> 16.408 | W8: 23.866 | X8: =I8-W8 -> 28.009 | Y8: 29.1 | Z8: =K8-Y8 -> 31.6 | AA8: 35.4 | AB8: =M8-AA8 -> 40.5 | AC8: 44.8 | AD8: =N8-AC8 -> 47.5 | AF8: =16.176-Q8 -> 5.26 | AG8: =F8-AF8-Q8 -> 6.203 | AH8: 6.046 | AI8: =S8-AH8 -> 6.113 | AJ8: =18.093-S8 -> 5.934 | AK8: =G8-AJ8-S8 -> 7.789 | AL8: 7.402 | AM8: =U8-AL8 -> 7.302 | AN8: =22.597-U8 -> 7.893 | AO8: =H8-AN8-U8 -> 8.515 | AP8: 11.106 | AQ8: =W8-AP8 -> 12.76 | AR8: =37.755-W8 -> 13.889 | AS8: =I8-AR8-W8 -> 14.12 | AT8: 14.434 | AU8: =Y8-AT8 -> 14.666 | AV8: =43.4-Y8 -> 14.3 | AW8: =K8-AV8-Y8 -> 17.3 | AX8: 17.5 | AY8: =AA8-AX8 -> 17.9 | AZ8: =54.9-AA8 -> 19.5 | BA8: =M8-AZ8-AA8 -> 21 | BB8: 21.8 | BC8: =AC8-BB8 -> 23 | BD8: =68.8-AC8 -> 24 | BE8: =N8-AC8-BD8 -> 23.5 | BF8: 25.5
B9: Property operating expenses | C9: -13.371 | D9: -15.221 | E9: -29.799 | F9: -40.575 | G9: -37.148 | H9: -38.91 | I9: -84.758 | J9: -84.758 | K9: -89.4 | L9: -89.2 | M9: -93.2 | N9: -114.1 | O9: =SUM(BC9:BF9) -> -120.1 | Q9: -21.254 | R9: =F9-Q9 -> -19.321 | S9: -16.256 | T9: =G9-S9 -> -20.892 | U9: -14.205 | V9: =H9-U9 -> -24.705 | W9: -42.861 | X9: =I9-W9 -> -41.897 | Y9: =-41.2+1.5 -> -39.7 | Z9: =K9-Y9 -> -49.7 | AA9: =-42.4+1.8 -> -40.6 | AB9: =M9-AA9 -> -52.6 | AC9: =-51.6 -> -51.6 | AD9: =N9-AC9 -> -62.5 | AF9: =-31.938-Q9 -> -10.684 | AG9: =F9-AF9-Q9 -> -8.637 | AH9: -7.613 | AI9: =S9-AH9 -> -8.643 | AJ9: =-24.509-S9 -> -8.253 | AK9: =G9-AJ9-S9 -> -12.639 | AL9: -7.086 | AM9: =U9-AL9 -> -7.119 | AN9: =-28.44-U9 -> -14.235 | AO9: =H9-AN9-U9 -> -10.47 | AP9: -13.5 | AQ9: =W9-AP9 -> -29.361 | AR9: =-(63.745)-W9 -> -20.884 | AS9: =I9-AR9-W9 -> -21.013 | AT9: -19.814 | AU9: =Y9-AT9 -> -19.886 | AV9: =-62.4-Y9+3.2 -> -19.5 | AW9: =K9-AV9-Y9 -> -30.2 | AX9: =-21.5+0.3 -> -21.2 | AY9: =AA9-AX9 -> -19.4 | AZ9: =-67.4-AA9+3.1 -> -23.7 | BA9: =M9-AZ9-AA9 -> -28.9 | BB9: -25 | BC9: =AC9-BB9 -> -26.6 | BD9: =-81.9-AC9 -> -30.3 | BE9: =N9-AC9-BD9 -> -32.2 | BF9: -31
B10: Net rental income | C10: =SUM(C7:C9) -> 181.659 | D10: =SUM(D7:D9) -> 207.088 | E10: =SUM(E7:E9) -> 232.151 | F10: =SUM(F7:F9) -> 239.79 | G10: =SUM(G7:G9) -> 280.669 | H10: =SUM(H7:H9) -> 326.853 | I10: =SUM(I7:I9) -> 452.134 | J10: =SUM(J7:J9) -> 452.134 | ... O10: =SUM(O7:O9) -> 758.3 | Q10: =SUM(Q7:Q9) -> 112.563 | R10: =SUM(R7:R9) -> 127.227 | S10: =SUM(S7:S9) -> 136.49 | T10: =SUM(T7:T9) -> 144.179 | U10: =SUM(U7:U9) -> 160.307 | V10: =SUM(V7:V9) -> 166.546 | W10: =SUM(W7:W9) -> 211.505 | X10: =SUM(X7:X9) -> 240.629 | ... AD10: =SUM(AD7:AD9) -> 377.6 | AF10: =SUM(AF7:AF9) -> 52.988 | AG10: =SUM(AG7:AG9) -> 74.239 | AH10: =SUM(AH7:AH9) -> 66.815 | AI10: =SUM(AI7:AI9) -> 69.675 | AJ10: =SUM(AJ7:AJ9) -> 66.787 | AK10: =SUM(AK7:AK9) -> 77.392 | AL10: =SUM(AL7:AL9) -> 78.088 | AM10: =SUM(AM7:AM9) -> 82.219 | ... BF10: =SUM(BF7:BF9) -> 199.6
B11: Income from renewable energy | L11: 6.3 | M11: 7.6 | N11: 14.7 | O11: =SUM(BC11:BF11) -> 16.1 | AB11: =M11-AA11 -> 7.6 | AC11: 8 | AD11: =N11-AC11 -> 6.7 | AX11: 1 | BA11: =M11-AZ11-AA11 -> 7.6 | BB11: 1.9 | BC11: =AC11-BB11 -> 6.1 | BD11: =12.4-AC11 -> 4.4 | BE11: =N11-AC11-BD11 -> 2.3 | BF11: 3.3
B12: Expenses from renewable energy | L12: -2.8 | M12: -4.2 | N12: -9.5 | O12: =SUM(BC12:BF12) -> -12.8 | AB12: =M12-AA12 -> -4.2 | AC12: -4.1 | AD12: =N12-AC12 -> -5.4 | AX12: -0.7 | BA12: =M12-AZ12-AA12 -> -4.2 | BB12: -1.8 | BC12: =AC12-BB12 -> -2.3 | BD12: =-6.6-AC12 -> -2.5 | BE12: =N12-AC12-BD12 -> -2.9 | BF12: -5.1
B13: Net income from renewable energy | L13: =SUM(L11:L12) -> 3.5 | M13: =SUM(M11:M12) -> 3.4 | N13: =SUM(N11:N12) -> 5.2 | O13: =SUM(O11:O12) -> 3.3 | AB13: =SUM(AB11:AB12) -> 3.4 | AC13: =SUM(AC11:AC12) -> 3.9 | AD13: =SUM(AD11:AD12) -> 1.3 | AX13: =SUM(AX11:AX12) -> 0.3 | BA13: =SUM(BA11:BA12) -> 3.4 | BB13: =SUM(BB11:BB12) -> 0.1 | BC13: =SUM(BC11:BC12) -> 3.8 | BD13: =SUM(BD11:BD12) -> 1.9 | BE13: =SUM(BE11:BE12) -> -0.6 | BF13: =SUM(BF11:BF12) -> -1.8
B14: Hotel operating revenue | C14: 9.772 | D14: 14.978 | E14: 16.805 | F14: 17.312 | G14: 5.752 | H14: 8.779 | I14: 16.021 | J14: 16.021 | K14: 21.1 | L14: 21.1 | M14: 22.4 | N14: 22.8 | O14: =SUM(BC14:BF14) -> 22.7 | Q14: 8.679 | R14: =F14-Q14 -> 8.633 | S14: 3.274 | T14: =G14-S14 -> 2.478 | U14: 2.664 | V14: =H14-U14 -> 6.115 | W14: 7.181 | X14: =I14-W14 -> 8.84 | Y14: 10 | Z14: =K14-Y14 -> 11.1 | AA14: 10.5 | AB14: =M14-AA14 -> 11.9 | AC14: 10.9 | AD14: =N14-AC14 -> 11.9 | AF14: =13.437-Q14 -> 4.758 | AG14: =F14-AF14-Q14 -> 3.875 | AH14: 2.542 | AI14: =S14-AH14 -> 0.732 | AJ14: =4.846-S14 -> 1.572 | AK14: =G14-AJ14-S14 -> 0.906 | AL14: 0.83 | AM14: =U14-AL14 -> 1.834 | AN14: =5.838-U14 -> 3.174 | AO14: =H14-AN14-U14 -> 2.941 | AP14: 2.249 | AQ14: =W14-AP14 -> 4.932 | AR14: =11.074-W14 -> 3.893 | AS14: =I14-AR14-W14 -> 4.947 | AT14: 4.039 | AU14: =Y14-AT14 -> 5.961 | AV14: =15.3-Y14 -> 5.3 | AW14: =K14-AV14-Y14 -> 5.8 | AX14: 4.5 | AY14: =AA14-AX14 -> 6 | AZ14: =16.1-AA14 -> 5.6 | BA14: =M14-AZ14-AA14 -> 6.3 | BB14: 4.6 | BC14: =AC14-BB14 -> 6.3 | BD14: =16.6-AC14 -> 5.7 | BE14: =N14-AC14-BD14 -> 6.2 | BF14: 4.5
B15: Hotel operating expenses | C15: -6.961 | D15: -10.564 | E15: -10.681 | F15: -11.545 | G15: -5.897 | H15: -11.334 | I15: -12.28 | J15: -12.28 | K15: -15.7 | L15: -15.7 | M15: -16.3 | N15: -13.7 | O15: =SUM(BC15:BF15) -> -13.8 | Q15: -5.605 | R15: =F15-Q15 -> -5.94 | S15: -3.24 | T15: =G15-S15 -> -2.657 | U15: -2.538 | V15: =H15-U15 -> -8.796 | W15: -6.048 | X15: =I15-W15 -> -6.232 | Y15: -7.4 | Z15: =K15-Y15 -> -8.3 | AA15: -5.4 | AB15: =M15-AA15 -> -10.9 | AC15: -5 | AD15: =N15-AC15 -> -8.7 | AF15: =-7.9-Q15 -> -2.295 | AG15: =F15-AF15-Q15 -> -3.645 | AH15: -2.298 | AI15: =S15-AH15 -> -0.942 | AJ15: =-4.508-S15 -> -1.268 | AK15: =G15-AJ15-S15 -> -1.389 | AL15: -1.166 | AM15: =U15-AL15 -> -1.372 | AN15: =-5.693-U15 -> -3.155 | AO15: =H15-AN15-U15 -> -5.641 | AP15: -2.649 | AQ15: =W15-AP15 -> -3.399 | AR15: =-9.324-W15 -> -3.276 | AS15: =I15-AR15-W15 -> -2.956 | AT15: -3.356 | AU15: =Y15-AT15 -> -4.044 | AV15: =-11.6-Y15 -> -4.2 | AW15: =K15-AV15-Y15 -> -4.1 | AX15: -3.2 | AY15: =AA15-AX15 -> -2.2 | AZ15: =-10-AA15 -> -4.6 | BA15: =M15-AZ15-AA15 -> -6.3 | BB15: -3.6 | BC15: =AC15-BB15 -> -1.4 | BD15: =-9-AC15 -> -4 | BE15: =N15-AC15-BD15 -> -4.7 | BF15: -3.7
B16: Net operating income from hotel operations | C16: =SUM(C14:C15) -> 2.811 | D16: =SUM(D14:D15) -> 4.414 | E16: =SUM(E14:E15) -> 6.124 | F16: =SUM(F14:F15) -> 5.767 | G16: =SUM(G14:G15) -> -0.145 | H16: =SUM(H14:H15) -> -2.555 | I16: =SUM(I14:I15) -> 3.741 | J16: =SUM(J14:J15) -> 3.741 | ... O16: =SUM(O14:O15) -> 8.9 | Q16: =SUM(Q14:Q15) -> 3.074 | R16: =SUM(R14:R15) -> 2.693 | S16: =SUM(S14:S15) -> 0.034 | T16: =SUM(T14:T15) -> -0.179 | U16: =SUM(U14:U15) -> 0.126 | V16: =SUM(V14:V15) -> -2.681 | W16: =SUM(W14:W15) -> 1.133 | X16: =SUM(X14:X15) -> 2.608 | ... AD16: =SUM(AD14:AD15) -> 3.2 | AF16: =SUM(AF14:AF15) -> 2.463 | AG16: =SUM(AG14:AG15) -> 0.23 | AH16: =SUM(AH14:AH15) -> 0.244 | AI16: =SUM(AI14:AI15) -> -0.21 | AJ16: =SUM(AJ14:AJ15) -> 0.304 | AK16: =SUM(AK14:AK15) -> -0.483 | AL16: =SUM(AL14:AL15) -> -0.336 | AM16: =SUM(AM14:AM15) -> 0.462 | ... BF16: =SUM(BF14:BF15) -> 0.8
B17: Income from development activities | C17: 5.194 | D17: 16.55 | E17: 9.358 | F17: 4.483 | G17: 49.411 | H17: 32.824 | I17: 36.2 | J17: 36.2 | K17: 20.1 | L17: 20.1 | M17: 100.7 | N17: 82.9 | O17: =SUM(BC17:BF17) -> 86 | Q17: 6.059 | R17: =F17-Q17 -> -1.576 | S17: 43.576 | T17: =G17-S17 -> 5.835 | U17: 23.399 | V17: =H17-U17 -> 9.425 | W17: 23.251 | X17: =I17-W17 -> 12.949 | Y17: 7.1 | Z17: =K17-Y17 -> 13 | AA17: 32.3 | AB17: =M17-AA17 -> 68.4 | AC17: 21.4 | AD17: =N17-AC17 -> 61.5 | AF17: =10.269-Q17 -> 4.21 | AG17: =F17-AF17-Q17 -> -5.786 | AH17: 21.629 | AI17: =S17-AH17 -> 21.947 | AJ17: =45.956-S17 -> 2.38 | AK17: =G17-AJ17-S17 -> 3.455 | AL17: 17.519 | AM17: =U17-AL17 -> 5.88 | AN17: =24.866-U17 -> 1.467 | AO17: =H17-AN17-U17 -> 7.958 | AP17: 11.869 | AQ17: =W17-AP17 -> 11.382 | AR17: =31.187-W17 -> 7.936 | AS17: =I17-AR17-W17 -> 5.013 | AT17: 3.446 | AU17: =Y17-AT17 -> 3.654 | AV17: =12.1-Y17 -> 5 | AW17: =K17-AV17-Y17 -> 8 | AX17: 10.4 | AY17: =AA17-AX17 -> 21.9 | AZ17: =41.5-AA17 -> 9.2 | BA17: =M17-AZ17-AA17 -> 59.2 | BB17: 10.4 | BC17: =AC17-BB17 -> 11 | BD17: =33.7-AC17 -> 12.3 | BE17: =N17-AC17-BD17 -> 49.2 | BF17: 13.5
B18: Expenses from development activities | C18: -4.108 | D18: -12.55 | E18: -7.891 | F18: -3.927 | G18: -26.984 | H18: -23.459 | I18: -27.158 | J18: -27.1 | K18: -14.7 | L18: -14.7 | M18: -75.2 | N18: -55.9 | O18: =SUM(BC18:BF18) -> -55.4 | Q18: -4.838 | R18: =F18-Q18 -> 0.911 | S18: -20.019 | T18: =G18-S18 -> -6.965 | U18: -17.141 | V18: =H18-U18 -> -6.318 | W18: -17.427 | X18: =I18-W18 -> -9.731 | Y18: -5.1 | Z18: =K18-Y18 -> -9.6 | AA18: -23.7 | AB18: =M18-AA18 -> -51.5 | AC18: -15 | AD18: =N18-AC18 -> -40.9 | AF18: =-8.565-Q18 -> -3.727 | AG18: =F18-AF18-Q18 -> 4.638 | AH18: -11.556 | AI18: =S18-AH18 -> -8.463 | AJ18: =-21.621-S18 -> -1.602 | AK18: =G18-AJ18-S18 -> -5.363 | AL18: -12.826 | AM18: =U18-AL18 -> -4.315 | AN18: =-17.991-U18 -> -0.85 | AO18: =H18-AN18-U18 -> -5.468 | AP18: -8.827 | AQ18: =W18-AP18 -> -8.6 | AR18: =-(23.623)-W18 -> -6.196 | AS18: =I18-AR18-W18 -> -3.535 | AT18: -2.608 | AU18: =Y18-AT18 -> -2.492 | AV18: =-9.2-Y18 -> -4.1 | AW18: =K18-AV18-Y18 -> -5.5 | AX18: -7.4 | AY18: =AA18-AX18 -> -16.3 | AZ18: =-31-AA18 -> -7.3 | BA18: =M18-AZ18-AA18 -> -44.2 | BB18: -7.9 | BC18: =AC18-BB18 -> -7.1 | BD18: =-23.4-AC18 -> -8.4 | BE18: =N18-AC18-BD18 -> -32.5 | BF18: -7.4
B19: Net income from development activities | C19: =SUM(C17:C18) -> 1.086 | D19: =SUM(D17:D18) -> 4 | E19: =SUM(E17:E18) -> 1.467 | F19: =SUM(F17:F18) -> 0.556 | G19: =SUM(G17:G18) -> 22.427 | H19: =SUM(H17:H18) -> 9.365 | I19: =SUM(I17:I18) -> 9.042 | J19: =SUM(J17:J18) -> 9.1 | ... O19: =SUM(O17:O18) -> 30.6 | Q19: =SUM(Q17:Q18) -> 1.221 | R19: =SUM(R17:R18) -> -0.665 | S19: =SUM(S17:S18) -> 23.557 | T19: =SUM(T17:T18) -> -1.13 | U19: =SUM(U17:U18) -> 6.258 | V19: =SUM(V17:V18) -> 3.107 | W19: =SUM(W17:W18) -> 5.824 | X19: =SUM(X17:X18) -> 3.218 | ... AD19: =SUM(AD17:AD18) -> 20.6 | AF19: =SUM(AF17:AF18) -> 0.483 | AG19: =SUM(AG17:AG18) -> -1.148 | AH19: =SUM(AH17:AH18) -> 10.073 | AI19: =SUM(AI17:AI18) -> 13.484 | AJ19: =SUM(AJ17:AJ18) -> 0.778 | AK19: =SUM(AK17:AK18) -> -1.908 | AL19: =SUM(AL17:AL18) -> 4.693 | AM19: =SUM(AM17:AM18) -> 1.565 | ... BB19: =SUM(BB17:BB18) -> 2.5 | BC19: =AC19-BB19 -> 3.9 | BD19: =SUM(BD17:BD18) -> 3.9 | BE19: =SUM(BE17:BE18) -> 16.7 | BF19: =SUM(BF17:BF18) -> 6.1
B20: Revenue | C20: =C10+C16+C19 -> 185.556 | D20: =D10+D16+D19 -> 215.502 | E20: =E10+E16+E19 -> 239.742 | F20: =F10+F16+F19 -> 246.113 | G20: =G10+G16+G19 -> 302.951 | H20: =H10+H16+H19 -> 333.663 | I20: =I10+I16+I19 -> 464.917 | J20: =J10+J16+J19 -> 464.975 | K20: =K10+K16+K19 -> 554 | L20: =L10+L16+L19+L13 -> 557.7 | M20: =M10+M16+M19+M13 -> 681.8 | N20: =N10+N16+N19+N13 -> 779.3 | O20: =O10+O16+O19+O13 -> 801.1 | Q20: =Q10+Q16+Q19+Q13 -> 116.858 | R20: =R10+R16+R19+R13 -> 129.255 | S20: =S10+S16+S19+S13 -> 160.081 | T20: =T10+T16+T19+T13 -> 142.87 | U20: =U10+U16+U19+U13 -> 166.691 | V20: =V10+V16+V19+V13 -> 166.972 | W20: =W10+W16+W19+W13 -> 218.462 | X20: =X10+X16+X19+X13 -> 246.455 | ... AD20: =AD10+AD16+AD19+AD13 -> 402.7 | AF20: =AF10+AF16+AF19+AF13 -> 55.934 | AG20: =AG10+AG16+AG19+AG13 -> 73.321 | AH20: =AH10+AH16+AH19+AH13 -> 77.132 | AI20: =AI10+AI16+AI19+AI13 -> 82.949 | AJ20: =AJ10+AJ16+AJ19+AJ13 -> 67.869 | AK20: =AK10+AK16+AK19+AK13 -> 75.001 | AL20: =AL10+AL16+AL19+AL13 -> 82.445 | AM20: =AM10+AM16+AM19+AM13 -> 84.246 | ... BF20: =BF10+BF16+BF19+BF13 -> 204.7
B21: % growth | D21: =D20/C20-1 -> 0.16138524 | E21: =E20/D20-1 -> 0.11248155 | F21: =F20/E20-1 -> 0.026574401 | G21: =G20/F20-1 -> 0.2309427 | H21: =H20/G20-1 -> 0.10137613 | I21: =I20/H20-1 -> 0.39337295 | J21: =J20/I20-1 -> 0.00012475345 | K21: =K20/I20-1 -> 0.19161055 | L21: =L20/J20-1 -> 0.19941932 | M21: =M20/L20-1 -> 0.22252107 | N21: =N20/M20-1 -> 0.14300381 | S21: =S20/Q20-1 -> 0.36987626 | U21: =U20/S20-1 -> 0.041291596 | W21: =W20/U20-1 -> 0.31058066 | Y21: =Y20/W20-1 -> 0.25605368 | AA21: =AA20/X20-1 -> 0.33655231 | AC21: =AC20/Z20-1 -> 0.34692418 | AJ21: =AJ20/AF20-1 -> 0.21337648 | AK21: =AK20/AG20-1 -> 0.022912944 | AL21: =AL20/AH20-1 -> 0.068881917 | AM21: =AM20/AI20-1 -> 0.015636114 | AN21: =AN20/AJ20-1 -> 0.18165878 | AO21: =AO20/AK20-1 -> 0.15697124 | AP21: =+AP20/AL20-1 -> 0.33229426 | AQ21: =+AQ20/AM20-1 -> 0.28933124 | AR21: =AR20/AN20-1 -> 0.48492481 | AS21: =AS20/AO20-1 -> 0.46780142 | AT21: =+AT20/AP20-1 -> 0.20330296 | AU21: =+AU20/AQ20-1 -> 0.30939689 | AV21: =AV20/AR20-1 -> 0.15796722 | AW21: =AW20/AS20-1 -> 0.11253307 | AX21: =+AX20/AT20-1 -> 0.1984384 | AY21: =+AY20/AU20-1 -> 0.2044042 | AZ21: =+AZ20/AV20-1 -> 0.20522117 | BA21: =BA20/AW20-1 -> 0.31404375 | BB21: =+BB20/AX20-1 -> 0.15467172 | BC21: =+BC20/AY20-1 -> 0.13076474 | BD21: =+BD20/AZ20-1 -> 0.17930205 | BE21: =BE20/BA20-1 -> 0.11009667 | BF21: =+BF20/BB20-1 -> 0.11919081
B22: Net valuation result on investment property | C22: =296.326-35.491 -> 260.835 | D22: =407.417-78.889 -> 328.528 | E22: 238.017 | F22: 406.775 | G22: 152.162 | H22: 1100.571 | I22: 723.58 | J22: 697.3 | K22: 878.7 | L22: 878.7 | M22: 941.5 | N22: 1139.9 | O22: =SUM(BC22:BF22) -> 1147.8 | Q22: 145.243 | R22: =F22-Q22 -> 261.532 | S22: 29.96 | T22: =G22-S22 -> 122.202 | U22: 145.743 | V22: =H22-U22 -> 954.828 | W22: 499.016 | X22: =I22-W22 -> 224.564 | Y22: 417.2 | Z22: =K22-Y22 -> 461.5 | AA22: 436.7 | AB22: =M22-AA22 -> 504.8 | AC22: 597.9 | AD22: =N22-AC22 -> 542 | AF22: =179.608-Q22 -> 34.365 | AG22: =F22-AF22-Q22 -> 227.167 | AH22: 28.68 | AI22: =S22-AH22 -> 1.28 | AJ22: =76.627-S22 -> 46.667 | AK22: =G22-AJ22-S22 -> 75.535 | AL22: 67.101 | AM22: =U22-AL22 -> 78.642 | AN22: =265.232-U22 -> 119.489 | AO22: =H22-AN22-U22 -> 835.339 | AP22: 27.521 | AQ22: =W22-AP22 -> 471.495 | AR22: =558.138 -W22 -> 59.122 | AS22: =I22-AR22-W22 -> 165.442 | AT22: 208.282 | AU22: =Y22-AT22 -> 208.918 | AV22: =656.3 -Y22 -> 239.1 | AW22: =K22-AV22-Y22 -> 222.4 | AX22: 165.6 | AY22: =AA22-AX22 -> 271.1 | AZ22: =604.1-AA22 -> 167.4 | BA22: =M22-AZ22-AA22 -> 337.4 | BB22: 156.2 | BC22: =AC22-BB22 -> 441.7 | BD22: =801.6-AC22 -> 203.7 | BE22: =N22-AC22-BD22 -> 338.3 | BF22: 164.1
B24: Net business income | C24: =+C20+C22 -> 446.391 | D24: =+D20+D22 -> 544.03 | E24: =+E20+E22 -> 477.759 | F24: =+F20+F22 -> 652.888 | G24: =+G20+G22 -> 455.113 | H24: =+H20+H22 -> 1434.234 | I24: =+I20+I22 -> 1188.497 | J24: =+J20+J22 -> 1162.275 | ... O24: =+O20+O22 -> 1948.9 | Q24: =+Q20+Q22 -> 262.101 | R24: =+R20+R22 -> 390.787 | S24: =+S20+S22 -> 190.041 | T24: =+T20+T22 -> 265.072 | U24: =+U20+U22 -> 312.434 | V24: =+V20+V22 -> 1121.8 | W24: =+W20+W22 -> 717.478 | X24: =+X20+X22 -> 471.019 | ... AD24: =+AD20+AD22 -> 944.7 | AF24: =+AF20+AF22 -> 90.299 | AG24: =+AG20+AG22 -> 300.488 | AH24: =+AH20+AH22 -> 105.812 | AI24: =+AI20+AI22 -> 84.229 | AJ24: =+AJ20+AJ22 -> 114.536 | AK24: =+AK20+AK22 -> 150.536 | AL24: =+AL20+AL22 -> 149.546 | AM24: =+AM20+AM22 -> 162.888 | ... BF24: =+BF20+BF22 -> 368.8
B25: % growth | D25: =D24/C24-1 -> 0.21872977 | E25: =E24/D24-1 -> -0.12181497 | F25: =F24/E24-1 -> 0.36656348 | G25: =G24/F24-1 -> -0.30292332 | H25: =H24/G24-1 -> 2.15138 | I25: =I24/H24-1 -> -0.17133676 | J25: =J24/I24-1 -> -0.02206316 | K25: =K24/I24-1 -> 0.20547212 | L25: =L24/J24-1 -> 0.2358521 | M25: =M24/J24-1 -> 0.39665742 | N25: =N24/K24-1 -> 0.33956865 | S25: =S24/Q24-1 -> -0.27493218 | U25: =U24/S24-1 -> 0.64403471 | W25: =W24/U24-1 -> 1.2964146 | Y25: =Y24/W24-1 -> -0.036068005 | AA25: =AA24/X24-1 -> 0.62647367 | AC25: =AC24/Z24-1 -> 0.31493726
B26: Other income | C26: 9.17 | D26: 3.794 | E26: 49.693 | F26: 9.094 | G26: 4.01 | H26: 10.445 | I26: 8.182 | J26: 8.182 | K26: 14.1 | L26: 7.8 | M26: 10.7 | N26: 12.4 | O26: =SUM(BC26:BF26) -> 14.2 | Q26: 14.528 | R26: =F26-Q26 -> -5.434 | S26: 3.871 | T26: =G26-S26 -> 0.139 | U26: 4.047 | V26: =H26-U26 -> 6.398 | W26: 4.369 | X26: =I26-W26 -> 3.813 | Y26: 8.6 | Z26: =K26-Y26 -> 5.5 | AA26: 8.1 | AB26: =M26-AA26 -> 2.6 | AC26: 6.5 | AD26: =N26-AC26 -> 5.9 | AF26: =15.17-Q26 -> 0.642 | AG26: =F26-AF26-Q26 -> -6.076 | AH26: 0.951 | AI26: =S26-AH26 -> 2.92 | AJ26: =7.296-S26 -> 3.425 | AK26: =G26-AJ26-S26 -> -3.286 | AL26: 1.769 | AM26: =U26-AL26 -> 2.278 | AN26: =7.338-U26 -> 3.291 | AO26: =H26-AN26-U26 -> 3.107 | AP26: 2.53 | AQ26: =W26-AP26 -> 1.839 | AR26: =6.597-W26 -> 2.228 | AS26: =I26-AR26-W26 -> 1.585 | AT26: 0.6 | AU26: =Y26-AT26 -> 8 | AV26: =6.6-Y26 -> -2 | AW26: =K26-AV26-Y26 -> 7.5 | AX26: 4.6 | AY26: =AA26-AX26 -> 3.5 | AZ26: =10-AA26 -> 1.9 | BA26: =M26-AZ26-AA26 -> 0.7 | BB26: 2.7 | BC26: =AC26-BB26 -> 3.8 | BD26: =7.6-AC26 -> 1.1 | BE26: =N26-AC26-BD26 -> 4.8 | BF26: 4.5
B27: Amortization and depreciation | C27: -3.996 | D27: -5.418 | E27: -3.868 | F27: -9.753 | G27: -10.462 | H27: -8.447 | I27: -10.729 | J27: -10.729 | K27: -12.7 | L27: -11.3 | M27: -11 | N27: -12.2 | O27: =SUM(BC27:BF27) -> -13 | Q27: -3.456 | R27: =F27-Q27 -> -6.297 | S27: -4.317 | T27: =G27-S27 -> -6.145 | U27: -5.102 | V27: =H27-U27 -> -3.345 | W27: -5.015 | X27: =I27-W27 -> -5.714 | Y27: -6.1 | Z27: =K27-Y27 -> -6.6 | AA27: -5.7 | AB27: =M27-AA27 -> -5.3 | AC27: -5.7 | AD27: =N27-AC27 -> -6.5 | AF27: =-4.487-Q27 -> -1.031 | AG27: =F27-AF27-Q27 -> -5.266 | AH27: -2.635 | AI27: =S27-AH27 -> -1.682 | AJ27: =-6.424-S27 -> -2.107 | AK27: =G27-AJ27-S27 -> -4.038 | AL27: -2.564 | AM27: =U27-AL27 -> -2.538 | AN27: =-6.371-U27 -> -1.269 | AO27: =H27-AN27-U27 -> -2.076 | AP27: -2.225 | AQ27: =W27-AP27 -> -2.79 | AR27: =-(7.906)-W27 -> -2.891 | AS27: =I27-AR27-W27 -> -2.823 | AT27: -2.8 | AU27: =Y27-AT27 -> -3.3 | AV27: =-8.2-Y27 -> -2.1 | AW27: =K27-AV27-Y27 -> -4.5 | AX27: -3.2 | AY27: =AA27-AX27 -> -2.5 | AZ27: =-8.4-AA27 -> -2.7 | BA27: =M27-AZ27-AA27 -> -2.6 | BB27: -2.8 | BC27: =AC27-BB27 -> -2.9 | BD27: =-8.5-AC27 -> -2.8 | BE27: =N27-AC27-BD27 -> -3.7 | BF27: -3.6
B28: Employee benefits | C28: 0 | D28: 0 | E28: -11.335 | F28: -17.172 | G28: -22.969 | H28: -31.883 | I28: -43.706 | J28: -43.706 | K28: -50.4 | L28: -50.4 | M28: -52.8 | N28: -51.4 | O28: =SUM(BC28:BF28) -> -53.5 | Q28: -8.221 | R28: =F28-Q28 -> -8.951 | S28: -9.321 | T28: =G28-S28 -> -13.648 | U28: -12.321 | V28: =H28-U28 -> -19.562 | W28: -21.588 | X28: =I28-W28 -> -22.118 | Y28: -25.5 | Z28: =K28-Y28 -> -24.9 | AA28: -24.9 | AB28: =M28-AA28 -> -27.9 | AC28: -26.5 | AD28: =N28-AC28 -> -24.9 | AF28: =-12.236-Q28 -> -4.015 | AG28: =F28-AF28-Q28 -> -4.936 | AH28: -4.293 | AI28: =S28-AH28 -> -5.028 | AJ28: =-13.486-S28 -> -4.165 | AK28: =G28-AJ28-S28 -> -9.483 | AL28: -5.693 | AM28: =U28-AL28 -> -6.628 | AN28: =-22.616-U28 -> -10.295 | AO28: =H28-AN28-U28 -> -9.267 | AP28: -9.704 | AQ28: =W28-AP28 -> -11.884 | AR28: =-(33.563)-W28 -> -11.975 | AS28: =I28-AR28-W28 -> -10.143 | AT28: -13.026 | AU28: =Y28-AT28 -> -12.474 | AV28: =-35.4-Y28 -> -9.9 | AW28: =K28-AV28-Y28 -> -15 | AX28: -13.4 | AY28: =AA28-AX28 -> -11.5 | AZ28: =-39.9-AA28 -> -15 | BA28: =M28-AZ28-AA28 -> -12.9 | BB28: -13.1 | BC28: =AC28-BB28 -> -13.4 | BD28: =-38.6-AC28 -> -12.1 | BE28: =N28-AC28-BD28 -> -12.8 | BF28: -15.2
B29: Impairment of goodwill | N29: -113.6 | O29: =SUM(BC29:BF29) -> -113.6 | AD29: =N29-AC29 -> -113.6 | BE29: =N29-AC29-BD29 -> -113.6
B30: Impairment of financial assets | C30: 0 | D30: 0 | E30: 0 | F30: -0.009 | G30: -0.685 | H30: -1.078 | I30: 1.225 | J30: 1.225 | K30: -1.4 | L30: -1.4 | M30: -3.7 | N30: -0.2 | O30: =SUM(BC30:BF30) -> -0.1 | Q30: 0 | R30: =F30-Q30 -> -0.009 | S30: 0 | T30: =G30-S30 -> -0.685 | U30: 0.248 | V30: =H30-U30 -> -1.326 | W30: 0.463 | X30: =I30-W30 -> 0.762 | Y30: -0.5 | Z30: =K30-Y30 -> -0.9 | AA30: -1.1 | AB30: =M30-AA30 -> -2.6 | AC30: 0 | AD30: =N30-AC30 -> -0.2 | AF30: =0-Q30 -> 0 | AG30: =F30-AF30-Q30 -> -0.009 | AH30: -0.039 | AI30: =S30-AH30 -> 0.039 | AJ30: =-S30 -> 0 | AK30: =G30-AJ30-S30 -> -0.685 | AL30: 0.24 | AM30: =U30-AL30 -> 0.008 | AN30: =-0.254-U30 -> -0.502 | AO30: =H30-AN30-U30 -> -0.824 | AP30: 0.337 | AQ30: =W30-AP30 -> 0.126 | AR30: =1.723-W30 -> 1.26 | AS30: =I30-AR30-W30 -> -0.498 | AT30: -0.124 | AU30: =Y30-AT30 -> -0.376 | AV30: =-0.8-Y30 -> -0.3 | AW30: =K30-AV30-Y30 -> -0.6 | AX30: -0.7 | AY30: =AA30-AX30 -> -0.4 | AZ30: =-1.4-AA30 -> -0.3 | BA30: =M30-AZ30-AA30 -> -2.3 | BB30: 0 | BC30: =AC30-BB30 -> 0 | BD30: =0-AC30 -> 0 | BE30: =N30-AC30-BD30 -> -0.2 | BF30: 0.1
B31: Other expenses | C31: -29.766 | D31: -33.309 | E31: -28.356 | F31: -17.149 | G31: -33.121 | H31: -26.463 | I31: -59.584 | J31: -69.7 | K31: -58.5 | L31: -57.3 | M31: -55.3 | N31: -65.5 | O31: =SUM(BC31:BF31) -> -69.9 | Q31: -17.315 | R31: =F31-Q31 -> 0.166 | S31: -12.225 | T31: =G31-S31 -> -20.896 | U31: -9.589 | V31: =H31-U31 -> -16.874 | W31: -35.198 | X31: =I31-W31 -> -24.386 | Y31: -29.6 | Z31: =K31-Y31 -> -28.9 | AA31: -26.3 | AB31: =M31-AA31 -> -29 | AC31: -25.5 | AD31: =N31-AC31 -> -40 | AF31: =-15.365-Q31 -> 1.95 | AG31: =F31-AF31-Q31 -> -1.784 | AH31: -6.785 | AI31: =S31-AH31 -> -5.44 | AJ31: =-16.723-S31 -> -4.498 | AK31: =G31-AJ31-S31 -> -16.398 | AL31: -5.081 | AM31: =U31-AL31 -> -4.508 | AN31: =-14.291-U31 -> -4.702 | AO31: =H31-AN31-U31 -> -12.172 | AP31: -20.59 | AQ31: =W31-AP31 -> -14.608 | AR31: =-48.127-W31 -> -12.929 | AS31: =I31-AR31-W31 -> -11.457 | AT31: -17.107 | AU31: =Y31-AT31 -> -12.493 | AV31: =-41-Y31 -> -11.4 | AW31: =K31-AV31-Y31 -> -17.5 | AX31: -10.9 | AY31: =AA31-AX31 -> -15.4 | AZ31: =-35.6-AA31 -> -9.3 | BA31: =M31-AZ31-AA31 -> -19.7 | BB31: -12.4 | BC31: =AC31-BB31 -> -13.1 | BD31: =-37.7-AC31 -> -12.2 | BE31: =N31-AC31-BD31 -> -27.8 | BF31: -16.8
B32: Net other income/expenses | C32: =SUM(C26:C31) -> -24.592 | D32: =SUM(D26:D31) -> -34.933 | E32: =SUM(E26:E31) -> 6.134 | F32: =SUM(F26:F31) -> -34.989 | G32: =SUM(G26:G31) -> -63.227 | H32: =SUM(H26:H31) -> -57.426 | I32: =SUM(I26:I31) -> -104.612 | J32: =SUM(J26:J31) -> -114.728 | ... O32: =SUM(O26:O31) -> -235.9 | Q32: =SUM(Q26:Q31) -> -14.464 | R32: =SUM(R26:R31) -> -20.525 | S32: =SUM(S26:S31) -> -21.992 | T32: =SUM(T26:T31) -> -41.235 | U32: =SUM(U26:U31) -> -22.717 | V32: =SUM(V26:V31) -> -34.709 | W32: =SUM(W26:W31) -> -56.969 | X32: =SUM(X26:X31) -> -47.643 | ... AD32: =SUM(AD26:AD31) -> -179.3 | AF32: =SUM(AF26:AF31) -> -2.454 | AG32: =SUM(AG26:AG31) -> -18.071 | AH32: =SUM(AH26:AH31) -> -12.801 | AI32: =SUM(AI26:AI31) -> -9.191 | AJ32: =SUM(AJ26:AJ31) -> -7.345 | AK32: =SUM(AK26:AK31) -> -33.89 | AL32: =SUM(AL26:AL31) -> -11.329 | AM32: =SUM(AM26:AM31) -> -11.388 | ... BF32: =SUM(BF26:BF31) -> -31
B34: Profit before net financing cost | C34: =C24+C32 -> 421.799 | D34: =D24+D32 -> 509.097 | E34: =E24+E32 -> 483.893 | F34: =F24+F32 -> 617.899 | G34: =G24+G32 -> 391.886 | H34: =H24+H32 -> 1376.808 | I34: =I24+I32 -> 1083.885 | J34: =J24+J32 -> 1047.547 | ... O34: =O24+O32 -> 1713 | Q34: =Q24+Q32 -> 247.637 | R34: =R24+R32 -> 370.262 | S34: =S24+S32 -> 168.049 | T34: =T24+T32 -> 223.837 | U34: =U24+U32 -> 289.717 | V34: =V24+V32 -> 1087.091 | W34: =W24+W32 -> 660.509 | X34: =X24+X32 -> 423.376 | ... AD34: =AD24+AD32 -> 765.4 | AF34: =AF24+AF32 -> 87.845 | AG34: =AG24+AG32 -> 282.417 | AH34: =AH24+AH32 -> 93.011 | AI34: =AI24+AI32 -> 75.038 | AJ34: =AJ24+AJ32 -> 107.191 | AK34: =AK24+AK32 -> 116.646 | AL34: =AL24+AL32 -> 138.217 | AM34: =AM24+AM32 -> 151.5 | ... BF34: =BF24+BF32 -> 337.8
B35: % margin | C35: =C34/C20 -> 2.2731628 | D35: =D34/D20 -> 2.3623771 | E35: =E34/E20 -> 2.0183906 | F35: =F34/F20 -> 2.5106313 | G35: =G34/G20 -> 1.2935623 | H35: =H34/H20 -> 4.126343 | I35: =I34/I20 -> 2.3313516 | J35: =J34/J20 -> 2.2529104 | ... O35: =O34/O20 -> 2.1383098 | Q35: =Q34/Q20 -> 2.1191275 | R35: =R34/R20 -> 2.8645855 | S35: =S34/S20 -> 1.0497748 | T35: =T34/T20 -> 1.566718 | U35: =U34/U20 -> 1.7380482 | V35: =V34/V20 -> 6.5106185 | W35: =W34/W20 -> 3.0234503 | X35: =X34/X20 -> 1.7178633 | ... AD35: =AD34/AD20 -> 1.9006705 | AF35: =AF34/AF20 -> 1.5705117 | AG35: =AG34/AG20 -> 3.8517887 | AH35: =AH34/AH20 -> 1.2058679 | AI35: =AI34/AI20 -> 0.90462815 | AJ35: =AJ34/AJ20 -> 1.5793809 | AK35: =AK34/AK20 -> 1.5552593 | AL35: =AL34/AL20 -> 1.6764752 | AM35: =AM34/AM20 -> 1.798305 | ... BF35: =BF34/BF20 -> 1.6502198
B36: Interest income | C36: 0.89 | D36: 1.323 | E36: 1.953 | F36: 0.582 | G36: 0.953 | H36: 1.993 | I36: 4.235 | J36: 4.235 | K36: 17.2 | L36: 17.2 | M36: 36.7 | N36: 26.9 | O36: =SUM(BC36:BF36) -> 24.2 | Q36: 0.298 | R36: =F36-Q36 -> 0.284 | S36: 0.411 | T36: =G36-S36 -> 0.542 | U36: 0.977 | V36: =H36-U36 -> 1.016 | W36: 2.27 | X36: =I36-W36 -> 1.965 | Y36: 7 | Z36: =K36-Y36 -> 10.2 | AA36: 18.6 | AB36: =M36-AA36 -> 18.1 | AC36: 15.5 | AD36: =N36-AC36 -> 11.4 | AF36: =0.392-Q36 -> 0.094 | AG36: =F36-AF36-Q36 -> 0.19 | AH36: 0.278 | AI36: =S36-AH36 -> 0.133 | AJ36: =0.538-S36 -> 0.127 | AK36: =G36-AJ36-S36 -> 0.415 | AL36: 0.475 | AM36: =U36-AL36 -> 0.502 | AN36: =1.468-U36 -> 0.491 | AO36: =H36-AN36-U36 -> 0.525 | AP36: 1.005 | AQ36: =W36-AP36 -> 1.265 | AR36: =3.213-W36 -> 0.943 | AS36: =I36-AR36-W36 -> 1.022 | AT36: 3.062 | AU36: =Y36-AT36 -> 3.938 | AV36: =11.7-Y36 -> 4.7 | AW36: =K36-AV36-Y36 -> 5.5 | AX36: 8 | AY36: =AA36-AX36 -> 10.6 | AZ36: =27.7-AA36 -> 9.1 | BA36: =M36-AZ36-AA36 -> 9 | BB36: 5.5 | BC36: =AC36-BB36 -> 10 | BD36: =19.7-AC36 -> 4.2 | BE36: =N36-AC36-BD36 -> 7.2 | BF36: 2.8
B37: Interest expense | C37: -38.556 | D37: -44.426 | E37: -54.927 | F37: -57.019 | G37: -68.534 | H37: -70.883 | I37: -84.944 | J37: -84.944 | K37: -129 | L37: -129 | M37: -241.7 | N37: -293.7 | O37: =SUM(BC37:BF37) -> -290.6 | Q37: -25.962 | R37: =F37-Q37 -> -31.057 | S37: -30.877 | T37: =G37-S37 -> -37.657 | U37: -43.721 | V37: =H37-U37 -> -27.162 | W37: -40.423 | X37: =I37-W37 -> -44.521 | Y37: -59.8 | Z37: =K37-Y37 -> -69.2 | AA37: -107 | AB37: =M37-AA37 -> -134.7 | AC37: -143.1 | AD37: =N37-AC37 -> -150.6 | AF37: =-40.697-Q37 -> -14.735 | AG37: =F37-AF37-Q37 -> -16.322 | AH37: -16.468 | AI37: =S37-AH37 -> -14.409 | AJ37: =-54.531-S37 -> -23.654 | AK37: =G37-AJ37-S37 -> -14.003 | AL37: -18.875 | AM37: =U37-AL37 -> -24.846 | AN37: =-55.89-U37 -> -12.169 | AO37: =H37-AN37-U37 -> -14.993 | AP37: -21.822 | AQ37: =W37-AP37 -> -18.601 | AR37: =-(60.087) -W37 -> -19.664 | AS37: =I37-AR37-W37 -> -24.857 | AT37: -28.052 | AU37: =Y37-AT37 -> -31.748 | AV37: =-(90.2) -Y37 -> -30.4 | AW37: =K37-AV37-Y37 -> -38.8 | AX37: -50.7 | AY37: =AA37-AX37 -> -56.3 | AZ37: =-171.9-AA37 -> -64.9 | BA37: =M37-AZ37-AA37 -> -69.8 | BB37: -67 | BC37: =AC37-BB37 -> -76.1 | BD37: =-215.9-AC37 -> -72.8 | BE37: =N37-AC37-BD37 -> -77.8 | BF37: -63.9
B38: Other financial expenses | C38: -6.441 | D38: -6.587 | E38: -8.405 | F38: -15.944 | G38: -11.501 | H38: -38.12 | I38: -17.939 | J38: -17.939 | K38: -8.5 | L38: -8.5 | M38: -17.3 | N38: -33.2 | O38: =SUM(BC38:BF38) -> -43.8 | Q38: -15.79 | R38: =F38-Q38 -> -0.154 | S38: -2.495 | T38: =G38-S38 -> -9.006 | U38: -20.29 | V38: =H38-U38 -> -17.83 | W38: -14.914 | X38: =I38-W38 -> -3.025 | Y38: -3.1 | Z38: =K38-Y38 -> -5.4 | AA38: -3 | AB38: =M38-AA38 -> -14.3 | AC38: -18.4 | AD38: =N38-AC38 -> -14.8 | AF38: =-20.56-Q38 -> -4.77 | AG38: =F38-AF38-Q38 -> 4.616 | AH38: -0.973 | AI38: =S38-AH38 -> -1.522 | AJ38: =-9.105-S38 -> -6.61 | AK38: =G38-AJ38-S38 -> -2.396 | AL38: -8.02 | AM38: =U38-AL38 -> -12.27 | AN38: =-33.39-U38 -> -13.1 | AO38: =H38-AN38-U38 -> -4.73 | AP38: -12.04 | AQ38: =W38-AP38 -> -2.874 | AR38: =-(16.367)-W38 -> -1.453 | AS38: =I38-AR38-W38 -> -1.572 | AT38: -1.393 | AU38: =Y38-AT38 -> -1.707 | AV38: =-(6.5)-Y38 -> -3.4 | AW38: =K38-AV38-Y38 -> -2 | AX38: -1.393 | AY38: =AA38-AX38 -> -1.607 | AZ38: =-5.1-AA38 -> -2.1 | BA38: =M38-AZ38-AA38 -> -12.2 | BB38: -5.3 | BC38: =AC38-BB38 -> -13.1 | BD38: =-21.6-AC38 -> -3.2 | BE38: =N38-AC38-BD38 -> -11.6 | BF38: -15.9
B39: Other financial gains/losses | C39: 6.474 | D39: -0.178 | E39: 1.361 | F39: -44.809 | G39: -22.379 | H39: 6.892 | I39: 2.031 | J39: 2.031 | K39: 8.6 | L39: 8.6 | M39: 41.2 | N39: -23.2 | O39: =SUM(BC39:BF39) -> -15.4 | Q39: -32.136 | R39: =F39-Q39 -> -12.673 | S39: -8.146 | T39: =G39-S39 -> -14.233 | U39: 6.531 | V39: =H39-U39 -> 0.361 | W39: 2.6 | X39: =I39-W39 -> -0.569 | Y39: 1 | Z39: =K39-Y39 -> 7.6 | AA39: 37.7 | AB39: =M39-AA39 -> 3.5 | AC39: -7.7 | AD39: =N39-AC39 -> -15.5 | AF39: =-66.055-Q39 -> -33.919 | AG39: =F39-AF39-Q39 -> 21.246 | AH39: -1.928 | AI39: =S39-AH39 -> -6.218 | AJ39: =-6.563-S39 -> 1.583 | AK39: =G39-AJ39-S39 -> -15.816 | AL39: 9.325 | AM39: =U39-AL39 -> -2.794 | AN39: =5.961-U39 -> -0.57 | AO39: =H39-AN39-U39 -> 0.931 | AP39: 0.153 | AQ39: =W39-AP39 -> 2.447 | AR39: =0.397-W39 -> -2.203 | AS39: =I39-AR39-W39 -> 1.634 | AT39: -2.136 | AU39: =Y39-AT39 -> 3.136 | AV39: =3.2-Y39 -> 2.2 | AW39: =K39-AV39-Y39 -> 5.4 | AX39: 25.6 | AY39: =AA39-AX39 -> 12.1 | AZ39: =39.7-AA39 -> 2 | BA39: =M39-AZ39-AA39 -> 1.5 | BB39: -5.6 | BC39: =AC39-BB39 -> -2.1 | BD39: =-17.9-AC39 -> -10.2 | BE39: =N39-AC39-BD39 -> -5.3 | BF39: 2.2
B40: Profit before tax | C40: =C34+C37+C36+C38+C39 -> 384.166 | D40: =D34+D37+D36+D38+D39 -> 459.229 | E40: =E34+E37+E36+E38+E39 -> 423.875 | F40: =F34+F37+F36+F38+F39 -> 500.709 | G40: =G34+G37+G36+G38+G39 -> 290.425 | H40: =H34+H37+H36+H38+H39 -> 1276.69 | I40: =I34+I37+I36+I38+I39 -> 987.268 | J40: =J34+J37+J36+J38+J39 -> 950.93 | ... O40: =O34+O37+O36+O38+O39 -> 1387.4 | Q40: =Q34+Q37+Q36+Q38+Q39 -> 174.047 | R40: =R34+R37+R36+R38+R39 -> 326.662 | S40: =S34+S37+S36+S38+S39 -> 126.942 | T40: =T34+T37+T36+T38+T39 -> 163.483 | U40: =U34+U37+U36+U38+U39 -> 233.214 | V40: =V34+V37+V36+V38+V39 -> 1043.476 | W40: =W34+W37+W36+W38+W39 -> 610.042 | X40: =X34+X37+X36+X38+X39 -> 377.226 | ... AD40: =AD34+AD37+AD36+AD38+AD39 -> 595.9 | AF40: =AF34+AF37+AF36+AF38+AF39 -> 34.515 | AG40: =AG34+AG37+AG36+AG38+AG39 -> 292.147 | AH40: =AH34+AH37+AH36+AH38+AH39 -> 73.92 | AI40: =AI34+AI37+AI36+AI38+AI39 -> 53.022 | AJ40: =AJ34+AJ37+AJ36+AJ38+AJ39 -> 78.637 | AK40: =AK34+AK37+AK36+AK38+AK39 -> 84.846 | AL40: =AL34+AL37+AL36+AL38+AL39 -> 121.122 | AM40: =AM34+AM37+AM36+AM38+AM39 -> 112.092 | ... BF40: =BF34+BF37+BF36+BF38+BF39 -> 263
BC41: =AC41-BB41 -> 0
B42: Income tax expense | C42: -73.369 | D42: -109.41 | E42: -60.992 | F42: -108.548 | G42: -37.901 | H42: -250.754 | I42: -190.743 | J42: -186.6 | K42: -289.5 | L42: -289.5 | M42: -248.7 | N42: -283.7 | O42: =SUM(BC42:BF42) -> -289 | Q42: -33.794 | R42: =F42-Q42 -> -74.754 | S42: -27.659 | T42: =G42-S42 -> -10.242 | U42: -44.935 | V42: =H42-U42 -> -205.819 | W42: -119.82 | X42: =I42-W42 -> -70.923 | Y42: =-112.5 -> -112.5 | Z42: =K42-Y42 -> -177 | AA42: -128.7 | AB42: =M42-AA42 -> -120 | AC42: -143.9 | AD42: =N42-AC42 -> -139.8 | AF42: =-45.585-Q42 -> -11.791 | AG42: =F42-AF42-Q42 -> -62.963 | AH42: -16.153 | AI42: =S42-AH42 -> -11.506 | AJ42: =-44.513-S42 -> -16.854 | AK42: =G42-AJ42-S42 -> 6.612 | AL42: -22.636 | AM42: =U42-AL42 -> -22.299 | AN42: =-76.296-U42 -> -31.361 | AO42: =H42-AN42-U42 -> -174.458 | AP42: -14.793 | AQ42: =W42-AP42 -> -105.027 | AR42: =-145.669-W42 -> -25.849 | AS42: =I42-AR42-W42 -> -45.074 | AT42: -53.992 | AU42: =Y42-AT42 -> -58.508 | AV42: =-175.5-Y42 -> -63 | AW42: =K42-AV42-Y42 -> -114 | AX42: -54.7 | AY42: =AA42-AX42 -> -74 | AZ42: =-177.8-AA42 -> -49.1 | BA42: =M42-AZ42-AA42 -> -70.9 | BB42: -45.1 | BC42: =AC42-BB42 -> -98.8 | BD42: =-198.4-AC42 -> -54.5 | BE42: =N42-AC42-BD42 -> -85.3 | BF42: -50.4
B43: Net profit/loss | C43: =C40+C42 -> 310.797 | D43: =D40+D42 -> 349.819 | E43: =E40+E42 -> 362.883 | F43: =F40+F42 -> 392.161 | G43: =G40+G42 -> 252.524 | H43: =H40+H42 -> 1025.936 | I43: =I40+I42 -> 796.525 | J43: =J40+J42 -> 764.33 | ... O43: =O40+O42 -> 1098.4 | Q43: =Q40+Q42 -> 140.253 | R43: =R40+R42 -> 251.908 | S43: =S40+S42 -> 99.283 | T43: =T40+T42 -> 153.241 | U43: =U40+U42 -> 188.279 | V43: =V40+V42 -> 837.657 | W43: =W40+W42 -> 490.222 | X43: =X40+X42 -> 306.303 | ... AD43: =AD40+AD42 -> 456.1 | AF43: =AF40+AF42 -> 22.724 | AG43: =AG40+AG42 -> 229.184 | AH43: =AH40+AH42 -> 57.767 | AI43: =AI40+AI42 -> 41.516 | AJ43: =AJ40+AJ42 -> 61.783 | AK43: =AK40+AK42 -> 91.458 | AL43: =AL40+AL42 -> 98.486 | AM43: =AM40+AM42 -> 89.793 | ... BF43: =BF40+BF42 -> 212.6
B44: % margin | C44: =C43/C20 -> 1.6749499 | D44: =D43/D20 -> 1.623275 | E44: =E43/E20 -> 1.5136397 | F44: =F43/F20 -> 1.5934185 | G44: =G43/G20 -> 0.83354734 | H44: =H43/H20 -> 3.0747671 | I44: =I43/I20 -> 1.7132628 | J44: =J43/J20 -> 1.6438088 | ... O44: =O43/O20 -> 1.3711147 | Q44: =Q43/Q20 -> 1.2002002 | R44: =R43/R20 -> 1.9489227 | S44: =S43/S20 -> 0.62020477 | T44: =T43/T20 -> 1.0725905 | U44: =U43/U20 -> 1.1295091 | V44: =V43/V20 -> 5.0167513 | W44: =W43/W20 -> 2.2439692 | X44: =X43/X20 -> 1.2428354 | ... AD44: =AD43/AD20 -> 1.1326049 | AF44: =AF43/AF20 -> 0.40626453 | AG44: =AG43/AG20 -> 3.1257621 | AH44: =AH43/AH20 -> 0.74893689 | AI44: =AI43/AI20 -> 0.50050031 | AJ44: =AJ43/AJ20 -> 0.91032725 | AK44: =AK43/AK20 -> 1.2194237 | AL44: =AL43/AL20 -> 1.1945661 | AM44: =AM43/AM20 -> 1.0658429 | ... BF44: =BF43/BF20 -> 1.0385931
B46: Profit attributable to:
B47: – Equity holders of the Company | C47: =C43-C48 -> 310.797 | D47: =D43-D48 -> 349.819 | E47: =E43-E48 -> 366.275 | F47: =F43-F48 -> 392.175 | G47: =G43-G48 -> 252.118 | H47: =H43-H48 -> 1025.936 | I47: =I43-I48 -> 794.649 | J47: =J43-J48 -> 766.73 | ... N47: =N43-N48 -> 1081.8 | O47: =SUM(BC47:BF47) -> 1098.4 | Q47: =Q43-Q48 -> 138.703 | R47: =R43-R48 -> 253.472 | S47: =S43-S48 -> 99.323 | T47: =T43-T48 -> 152.795 | U47: =U43-U48 -> 188.279 | V47: =V43-V48 -> 837.657 | W47: =W43-W48 -> 490.222 | X47: =X43-X48 -> 304.427 | ... AD47: =AD43-AD48 -> 456.1 | AF47: =AF43-AF48 -> 22.96 | AG47: =AG43-AG48 -> 230.512 | AH47: =AH43-AH48 -> 56.823 | AI47: =AI43-AI48 -> 42.5 | AJ47: =AJ43-AJ48 -> 61.635 | AK47: =AK43-AK48 -> 91.16 | AL47: =AL43-AL48 -> 98.486 | AM47: =AM43-AM48 -> 89.793 | ... BB47: =BB43-BB48 -> 196 | BC47: =AC47-BB47 -> 429.7 | BD47: =BD43-BD48 -> 237.2 | BE47: =BE43-BE48 -> 218.9 | BF47: =BF43-BF48 -> 212.6
B48: – Non-controlling interests | C48: 0 | D48: 0 | E48: -3.392 | F48: -0.014 | G48: 0.406 | H48: 0 | I48: 1.876 | J48: -2.4 | K48: 0 | L48: 0 | M48: 0 | N48: 0 | O48: =SUM(BC48:BF48) -> 0 | Q48: 1.55 | R48: =F48-Q48 -> -1.564 | S48: -0.04 | T48: =G48-S48 -> 0.446 | U48: 0 | V48: =H48-U48 -> 0 | W48: 0 | X48: =I48-W48 -> 1.876 | Y48: 0 | Z48: =K48-Y48 -> 0 | AA48: 0 | AB48: =M48-AA48 -> 0 | AC48: 0 | AD48: =N48-AC48 -> 0 | AF48: =1.314-Q48 -> -0.236 | AG48: =F48-AF48-Q48 -> -1.328 | AH48: 0.944 | AI48: =S48-AH48 -> -0.984 | AJ48: =0.108-S48 -> 0.148 | AK48: =G48-AJ48-S48 -> 0.298 | AL48: 0 | AM48: =U48-AL48 -> 0 | AN48: =0-U48 -> 0 | AO48: =H48-AN48-U48 -> 0 | AP48: 0 | AQ48: =W48-AP48 -> 0 | AR48: =0-W48 -> 0 | AS48: =I48-AR48-W48 -> 1.876 | AT48: 0 | AU48: =Y48-AT48 -> 0 | AV48: =0-Y48 -> 0 | AW48: =K48-AV48-Y48 -> 0 | AX48: 0 | AY48: =AA48-AX48 -> 0 | AZ48: =AE48-AY48 -> 0 | BA48: =M48-AZ48-AA48 -> 0 | BB48: 0 | BC48: =AC48-BB48 -> 0 | BD48: =0-AC48 -> 0 | BE48: =N48-AC48-BD48 -> 0 | BF48: 0
B50: check | C50: =+C43-C47-C48 -> 0 | D50: =+D43-D47-D48 -> 0 | E50: =+E43-E47-E48 -> 3.9968029e-15 | F50: =+F43-F47-F48 -> -1.000415e-14 | G50: =+G43-G47-G48 -> 5.884182e-15 | H50: =+H43-H47-H48 -> 0 | I50: =+I43-I47-I48 -> -2.3536728e-14 | J50: =+J43-J47-J48 -> 2.264855e-14 | ... O50: =+O43-O47-O48 -> 2.2737368e-13 | Q50: =+Q43-Q47-Q48 -> 1.1324275e-14 | R50: =+R43-R47-R48 -> 7.1054274e-15 | S50: =+S43-S47-S48 -> -6.2519434e-15 | T50: =+T43-T47-T48 -> -2.0539126e-15 | U50: =+U43-U47-U48 -> 0 | V50: =+V43-V47-V48 -> 0 | W50: =+W43-W47-W48 -> 0 | X50: =+X43-X47-X48 -> -2.3536728e-14 | ... AD50: =+AD43-AD47-AD48 -> 0 | AF50: =+AF43-AF47-AF48 -> -6.6613381e-16 | AG50: =+AG43-AG47-AG48 -> -2.8865799e-15 | AH50: =+AH43-AH47-AH48 -> 2.6645353e-15 | AI50: =+AI43-AI47-AI48 -> -1.7763568e-15 | AJ50: =+AJ43-AJ47-AJ48 -> 3.2474023e-15 | AK50: =+AK43-AK47-AK48 -> 1.831868e-15 | AL50: =+AL43-AL47-AL48 -> 0 | AM50: =+AM43-AM47-AM48 -> 0 | ... BF50: =+BF43-BF47-BF48 -> 0
B52: As a % of Sales
B53: Net rental income | C53: =C10/C$20 -> 0.97899825 | D53: =D10/D$20 -> 0.96095628 | E53: =E10/E$20 -> 0.9683368 | F53: =F10/F$20 -> 0.97430855 | G53: =G10/G$20 -> 0.92645015 | H53: =H10/H$20 -> 0.97959019 | I53: =I10/I$20 -> 0.97250477 | J53: =J10/J$20 -> 0.97238346 | ... O53: =O10/O$20 -> 0.94657346 | Q53: =Q10/Q$20 -> 0.96324599 | R53: =R10/R$20 -> 0.98431008 | S53: =S10/S$20 -> 0.85263086 | T53: =T10/T$20 -> 1.0091622 | U53: =U10/U$20 -> 0.96170159 | V53: =V10/V$20 -> 0.99744867 | W53: =W10/W$20 -> 0.96815464 | X53: =X10/X$20 -> 0.9763608 | ... AD53: =AD10/AD$20 -> 0.93767072 | AF53: =AF10/AF$20 -> 0.94733078 | AG53: =AG10/AG$20 -> 1.0125203 | AH53: =AH10/AH$20 -> 0.86624229 | AI53: =AI10/AI$20 -> 0.83997396 | AJ53: =AJ10/AJ$20 -> 0.98405752 | AK53: =AK10/AK$20 -> 1.0318796 | AL53: =AL10/AL$20 -> 0.94715265 | AM53: =AM10/AM$20 -> 0.97593951 | ... BF53: =BF10/BF$20 -> 0.97508549
B54: Net operating income from hotel operations | C54: =C16/C$20 -> 0.015149066 | D54: =D16/D$20 -> 0.020482409 | E54: =E16/E$20 -> 0.025544127 | F54: =F16/F$20 -> 0.023432326 | G54: =G16/G$20 -> -0.00047862526 | H54: =H16/H$20 -> -0.0076574268 | I54: =I16/I$20 -> 0.0080465976 | J54: =J16/J$20 -> 0.0080455938 | ... O54: =O16/O$20 -> 0.011109724 | Q54: =Q16/Q$20 -> 0.026305431 | R54: =R16/R$20 -> 0.020834784 | S54: =S16/S$20 -> 0.00021239248 | T54: =T16/T$20 -> -0.0012528872 | U54: =U16/U$20 -> 0.00075588964 | V54: =V16/V$20 -> -0.016056584 | W54: =W16/W$20 -> 0.0051862566 | X54: =X16/X$20 -> 0.010582054 | ... AD54: =AD16/AD$20 -> 0.0079463621 | AF54: =AF16/AF$20 -> 0.04403404 | AG54: =AG16/AG$20 -> 0.0031368912 | AH54: =AH16/AH$20 -> 0.0031634082 | AI54: =AI16/AI$20 -> -0.0025316761 | AJ54: =AJ16/AJ$20 -> 0.0044792173 | AK54: =AK16/AK$20 -> -0.0064399141 | AL54: =AL16/AL$20 -> -0.0040754442 | AM54: =AM16/AM$20 -> 0.0054839399 | ... BF54: =BF16/BF$20 -> 0.0039081583
B55: Net income from development activities | C55: =C19/C$20 -> 0.0058526806 | D55: =D19/D$20 -> 0.018561313 | E55: =E19/E$20 -> 0.006119078 | F55: =F19/F$20 -> 0.0022591249 | G55: =G19/G$20 -> 0.074028473 | H55: =H19/H$20 -> 0.028067241 | I55: =I19/I$20 -> 0.019448633 | J55: =J19/J$20 -> 0.019570945 | ... O55: =O19/O$20 -> 0.038197478 | Q55: =Q19/Q$20 -> 0.010448579 | R55: =R19/R$20 -> -0.0051448687 | S55: =S19/S$20 -> 0.14715675 | T55: =T19/T$20 -> -0.0079092882 | U55: =U19/U$20 -> 0.037542519 | V55: =V19/V$20 -> 0.01860791 | W55: =W19/W$20 -> 0.026659099 | X55: =X19/X$20 -> 0.01305715 | ... AD55: =AD19/AD$20 -> 0.051154706 | AF55: =AF19/AF$20 -> 0.0086351772 | AG55: =AG19/AG$20 -> -0.015657179 | AH55: =AH19/AH$20 -> 0.13059431 | AI55: =AI19/AI$20 -> 0.16255772 | AJ55: =AJ19/AJ$20 -> 0.01146326 | AK55: =AK19/AK$20 -> -0.025439661 | AL55: =AL19/AL$20 -> 0.056922797 | AM55: =AM19/AM$20 -> 0.01857655 | ... BF55: =BF19/BF$20 -> 0.029799707
B56: Other income | C56: =C26/C$20 -> 0.049419043 | D56: =D26/D$20 -> 0.017605405 | E56: =E26/E$20 -> 0.20727699 | F56: =F26/F$20 -> 0.036950506 | G56: =G26/G$20 -> 0.013236464 | H56: =H26/H$20 -> 0.03130404 | I56: =I26/I$20 -> 0.01759884 | J56: =J26/J$20 -> 0.017596645 | ... O56: =O26/O$20 -> 0.017725627 | Q56: =Q26/Q$20 -> 0.12432183 | R56: =R26/R$20 -> -0.042040927 | S56: =S26/S$20 -> 0.024181508 | T56: =T26/T$20 -> 0.00097291244 | U56: =U26/U$20 -> 0.024278455 | V56: =V26/V$20 -> 0.038317802 | W56: =W26/W$20 -> 0.019998901 | X56: =X26/X$20 -> 0.015471384 | ... AD56: =AD26/AD$20 -> 0.014651105 | AF56: =AF26/AF$20 -> 0.011477813 | AG56: =AG26/AG$20 -> -0.082868482 | AH56: =AH26/AH$20 -> 0.012329513 | AI56: =AI26/AI$20 -> 0.035202353 | AJ56: =AJ26/AJ$20 -> 0.050464866 | AK56: =AK26/AK$20 -> -0.043812749 | AL56: =AL26/AL$20 -> 0.021456729 | AM56: =AM26/AM$20 -> 0.027039859 | ... BF56: =BF26/BF$20 -> 0.02198339
B57: Amortization and depreciation | C57: =-C27/C$20 -> 0.021535278 | D57: =-D27/D$20 -> 0.025141298 | E57: =-E27/E$20 -> 0.016134011 | F57: =-F27/F$20 -> 0.039628138 | G57: =-G27/G$20 -> 0.034533637 | H57: =-H27/H$20 -> 0.025315963 | I57: =-I27/I$20 -> 0.023077237 | J57: =-J27/J$20 -> 0.023074359 | ... O57: =-O27/O$20 -> 0.016227687 | Q57: =-Q27/Q$20 -> 0.029574355 | R57: =-R27/R$20 -> 0.048717651 | S57: =-S27/S$20 -> 0.026967598 | T57: =-T27/T$20 -> 0.043011129 | U57: =-U27/U$20 -> 0.030607531 | V57: =-V27/V$20 -> 0.020033299 | W57: =-W27/W$20 -> 0.022955937 | X57: =-X27/X$20 -> 0.02318476 | ... AD57: =-AD27/AD$20 -> 0.016141048 | AF57: =-AF27/AF$20 -> 0.018432438 | AG57: =-AG27/AG$20 -> 0.07182117 | AH57: =-AH27/AH$20 -> 0.034162215 | AI57: =-AI27/AI$20 -> 0.02027752 | AJ57: =-AJ27/AJ$20 -> 0.031045102 | AK57: =-AK27/AK$20 -> 0.053839282 | AL57: =-AL27/AL$20 -> 0.031099521 | AM57: =-AM27/AM$20 -> 0.030126059 | ... BF57: =-BF27/BF$20 -> 0.017586712
B58: Employee benefits | C58: =-C28/C$20 -> 0 | D58: =-D28/D$20 -> 0 | E58: =-E28/E$20 -> 0.047279993 | F58: =-F28/F$20 -> 0.069772828 | G58: =-G28/G$20 -> 0.075817541 | H58: =-H28/H$20 -> 0.095554497 | I58: =-I28/I$20 -> 0.094008178 | J58: =-J28/J$20 -> 0.093996451 | ... O58: =-O28/O$20 -> 0.066783173 | Q58: =-Q28/Q$20 -> 0.07035034 | R58: =-R28/R$20 -> 0.069250706 | S58: =-S28/S$20 -> 0.058226773 | T58: =-T28/T$20 -> 0.095527403 | U58: =-U28/U$20 -> 0.073915208 | V58: =-V28/V$20 -> 0.11715737 | W58: =-W28/W$20 -> 0.098818101 | X58: =-X28/X$20 -> 0.089744578 | ... AD58: =-AD28/AD$20 -> 0.06183263 | AF58: =-AF28/AF$20 -> 0.071781028 | AG58: =-AG28/AG$20 -> 0.067320413 | AH58: =-AH28/AH$20 -> 0.055657833 | AI58: =-AI28/AI$20 -> 0.060615559 | AJ58: =-AJ28/AJ$20 -> 0.061368224 | AK58: =-AK28/AK$20 -> 0.12643831 | AL58: =-AL28/AL$20 -> 0.069052095 | AM58: =-AM28/AM$20 -> 0.078674358 | ... BF58: =-BF28/BF$20 -> 0.074255007
B59: Other expenses | C59: =-C31/C$20 -> 0.16041518 | D59: =-D31/D$20 -> 0.15456469 | E59: =-E31/E$20 -> 0.11827715 | F59: =-F31/F$20 -> 0.069679375 | G59: =-G31/G$20 -> 0.10932791 | H59: =-H31/H$20 -> 0.079310562 | I59: =-I31/I$20 -> 0.12816051 | J59: =-J31/J$20 -> 0.14990053 | ... O59: =-O31/O$20 -> 0.087255024 | Q59: =-Q31/Q$20 -> 0.14817128 | R59: =-R31/R$20 -> -0.001284283 | S59: =-S31/S$20 -> 0.076367589 | T59: =-T31/T$20 -> 0.14625884 | U59: =-U31/U$20 -> 0.057525601 | V59: =-V31/V$20 -> 0.10105886 | W59: =-W31/W$20 -> 0.16111727 | X59: =-X31/X$20 -> 0.098947069 | ... AD59: =-AD31/AD$20 -> 0.099329526 | AF59: =-AF31/AF$20 -> -0.034862517 | AG59: =-AG31/AG$20 -> 0.024331365 | AH59: =-AH31/AH$20 -> 0.087966084 | AI59: =-AI31/AI$20 -> 0.065582466 | AJ59: =-AJ31/AJ$20 -> 0.066274735 | AK59: =-AK31/AK$20 -> 0.21863708 | AL59: =-AL31/AL$20 -> 0.061628965 | AM59: =-AM31/AM$20 -> 0.053509959 | ... BF59: =-BF31/BF$20 -> 0.082071324
B60: EBITDA | C60: =C78/C$20 -> 0.88900386 | D60: =D78/D$20 -> 0.86304071 | E60: =E78/E$20 -> 0.84757781 | F60: =F78/F$20 -> 0.87155087 | G60: =G78/G$20 -> 0.78593568 | H60: =H78/H$20 -> 0.85320818 | I60: =I78/I$20 -> 0.79806503 | J60: =J78/J$20 -> 0.77633421 | ... O60: =O78/O$20 -> 0.89676695 | Q60: =Q78/Q$20 -> 0.79583768 | R60: =R78/R$20 -> 0.94000232 | S60: =S78/S$20 -> 0.74524772 | T60: =T78/T$20 -> 0.83152516 | U60: =U78/U$20 -> 0.89432543 | V60: =V78/V$20 -> 0.81216012 | W60: =W78/W$20 -> 0.7621829 | X60: =X78/X$20 -> 0.82987158 | ... AD60: =AD78/AD$20 -> 0.91904644 | AF60: =AF78/AF$20 -> 0.9745593 | AG60: =AG78/AG$20 -> 0.91364002 | AH60: =AH78/AH$20 -> 0.86819997 | AI60: =AI78/AI$20 -> 0.63091779 | AJ60: =AJ78/AJ$20 -> 0.82511898 | AK60: =AK78/AK$20 -> 0.83732217 | AL60: =AL78/AL$20 -> 0.8936867 | AM60: =AM78/AM$20 -> 0.8949505 | ... BF60: =BF78/BF$20 -> 0.86614558
B61: Finance income as a % of total cash | C61: =C36/C130 -> 0.013816229 | D61: =D36/D130 -> 0.05191289 | E61: =E36/E130 -> 0.042196007 | F61: =F36/F130 -> 0.0091192554 | G61: =G36/G130 -> 0.0022736979 | H61: =H36/H130 -> 0.0022322629 | I61: =I36/I130 -> 0.0064105378 | J61: =J36/J130 -> 0.0064105378 | ... O61: =O36/O130 -> 0.038230648 | R61: =R36/R130 -> 0.0044499459 | S61: =S36/S130 -> 0.0052228943 | T61: =T36/T130 -> 0.0012931209 | U61: =U36/U130 -> 0.0020040573 | V61: =V36/V130 -> 0.0011379724 | W61: =W36/W130 -> 0.0035454236 | X61: =X36/X130 -> 0.002974429 | Y61: =Y36/Y130 -> 0.010180337 | ... AD61: =AD36/AD130 -> 0.016092603 | AG61: =AG36/AG130 -> 0.0029770765 | AI61: =AI36/AI130 -> 0.0016901337 | AJ61: =AJ36/AJ130 -> 0.0019557718 | AK61: =AK36/AK130 -> 0.00099012027 | AL61: =AL36/AL130 -> 0.00041376235 | AM61: =AM36/AM130 -> 0.0010297204 | AN61: =AN36/AN130 -> 0.00035332282 | AO61: =AO36/AO130 -> 0.0005880271 | AP61: =AP36/AP130 -> 0.00087759283 | ... BF61: =BF36/BF130 -> 0.0044233807
B62: Finance costs as a % of total debt | C62: =-(C37)/C128 -> 0.022266807 | D62: =-(D37)/D128 -> 0.021942623 | E62: =-(E37)/E128 -> 0.025771087 | F62: =-(F37)/F128 -> 0.021293122 | G62: =-(G37)/G128 -> 0.020191158 | H62: =-(H37)/H128 -> 0.015707051 | I62: =-(I37)/I128 -> 0.0144605 | J62: =-(J37)/J128 -> 0.0144605 | ... O62: =-(O37)/O128 -> 0.0309894 | R62: =-(R37)/R128 -> 0.011597897 | S62: =-(S37)/S128 -> 0.010984957 | T62: =-(T37)/T128 -> 0.011094325 | U62: =-(U37)/U128 -> 0.014262474 | V62: =-(V37)/V128 -> 0.006018861 | W62: =-(W37)/W128 -> 0.0076507388 | X62: =-(X37)/X128 -> 0.007579063 | Y62: =-(Y37)/Y128 -> 0.0093488627 | ... AD62: =-(AD37)/AD128 -> 0.016318835 | AG62: =-(AG37)/AG128 -> 0.0060952725 | AI62: =-(AI37)/AI128 -> 0.0051262183 | AJ62: =-(AJ37)/AJ128 -> 0.0081681364 | AK62: =-(AK37)/AK128 -> 0.0041254966 | AL62: =-(AL37)/AL128 -> 0.0054434909 | AM62: =-(AM37)/AM128 -> 0.0081051537 | AN62: =-(AN37)/AN128 -> 0.0027015759 | AO62: =-(AO37)/AO128 -> 0.0033223173 | AP62: =-(AP37)/AP128 -> 0.0040437628 | ... BF62: =-(BF37)/BF128 -> 0.0068142556
B63: Income Tax Expense as a % PBT | C63: =(-C42)/C40 -> 0.19098254 | D63: =(-D42)/D40 -> 0.23824715 | E63: =(-E42)/E40 -> 0.14389148 | F63: =(-F42)/F40 -> 0.21678859 | G63: =(-G42)/G40 -> 0.13050185 | H63: =(-H42)/H40 -> 0.19640947 | I63: =(-I42)/I40 -> 0.19320286 | J63: =(-J42)/J40 -> 0.19622895 | ... O63: =(-O42)/O40 -> 0.2083033 | Q63: =(-Q42)/Q40 -> 0.19416594 | R63: =(-R42)/R40 -> 0.22884204 | S63: =(-S42)/S40 -> 0.21788691 | T63: =(-T42)/T40 -> 0.062648716 | U63: =(-U42)/U40 -> 0.19267711 | V63: =(-V42)/V40 -> 0.19724364 | W63: =(-W42)/W40 -> 0.19641271 | X63: =(-X42)/X40 -> 0.18801196 | ... AD63: =(-AD42)/AD40 -> 0.23460312 | AF63: =(-AF42)/AF40 -> 0.34161959 | AG63: =(-AG42)/AG40 -> 0.21551822 | AH63: =(-AH42)/AH40 -> 0.21852002 | AI63: =(-AI42)/AI40 -> 0.21700426 | AJ63: =(-AJ42)/AJ40 -> 0.21432659 | AK63: =(-AK42)/AK40 -> -0.077929425 | AL63: =(-AL42)/AL40 -> 0.18688595 | AM63: =(-AM42)/AM40 -> 0.1989348 | ... BF63: =(-BF42)/BF40 -> 0.19163498
B65: LTM Cash interest paid: % of debt | C65: =C111/C128 -> 0.02423499 | D65: =D111/D128 -> 0.02354735 | E65: =E111/E128 -> 0.025671619 | F65: =F111/F128 -> 0.020383425 | G65: =G111/G128 -> 0.018346278 | H65: =H111/H128 -> 0.010008168 | I65: =I111/I128 -> 0.011013738 | J65: =J111/J128 -> 0.011013738 | ... O65: =O111/O128 -> 0.029805703 | R65: =R111/R128 -> 0.020383425 | S65: =S111/S128 -> 0.021401401 | T65: =T111/T128 -> 0.018346278 | U65: =U111/U128 -> 0.017078693 | V65: =V111/V128 -> 0.010008168 | W65: =W111/W128 -> 0.0097421389 | X65: =X111/X128 -> 0.011013738 | Y65: =Y111/Y128 -> 0.013487376 | ... AD65: =AD111/AD128 -> 0.026244501 | AG65: =AG111/AG128 -> 0.020383425 | AK65: =AK111/AK128 -> 0.018346278 | AO65: =AO111/AO128 -> 0.010008168 | AS65: =AS111/AS128 -> 0.011013738 | AW65: =AW111/AW128 -> 0.016718808 | BA65: =BA111/BA128 -> 0.025557133 | BE65: =BE111/BE128 -> 0.026244501
B66: Working capital/sales | C66: =C122/C107 -> -0.08008903 | D66: =D122/D107 -> -0.38671103 | E66: =E122/E107 -> -0.27995929 | F66: =F122/F107 -> -0.28276442 | G66: =G122/G107 -> -0.29109328 | H66: =H122/H107 -> -0.25782601 | I66: =I122/I107 -> -0.17622285 | J66: =J122/J107 -> -0.17620087 | ... O66: =O122/O107 -> 0.062289352 | R66: =R122/R107 -> -0.28276442 | S66: =S122/S107 -> -0.39224638 | T66: =T122/T107 -> -0.29109328 | U66: =U122/U107 -> -0.18396051 | V66: =V122/V107 -> -0.25782601 | W66: =W122/W107 -> -0.15900258 | X66: =X122/X107 -> -0.17622285 | Y66: =Y122/Y107 -> -0.072956965 | ... AD66: =AD122/AD107 -> -0.063390222 | AG66: =AG122/AG107 -> -0.28276442 | AI66: =AI122/AI107 -> -0.39224638 | AJ66: =AJ122/AJ107 -> -0.26275679 | AK66: =AK122/AK107 -> -0.29109328 | AL66: =AL122/AL107 -> -0.23216464 | AM66: =AM122/AM107 -> -0.18396051 | AN66: =AN122/AN107 -> -0.28816677 | AO66: =AO122/AO107 -> -0.25782601 | AP66: =AP122/AP107 -> -0.029914778 | ... BF66: =BF122/BF107 -> 0.062289352
B68: EBITDA
B70: Operating profit | C70: =+C34 -> 421.799 | D70: =+D34 -> 509.097 | E70: =+E34 -> 483.893 | F70: =+F34 -> 617.899 | G70: =+G34 -> 391.886 | H70: =+H34 -> 1376.808 | I70: =+I34 -> 1083.885 | J70: =+J34 -> 1047.547 | ... O70: =+O34 -> 1713 | Q70: =+Q34 -> 247.637 | R70: =+R34 -> 370.262 | S70: =+S34 -> 168.049 | T70: =+T34 -> 223.837 | U70: =+U34 -> 289.717 | V70: =+V34 -> 1087.091 | W70: =+W34 -> 660.509 | X70: =+X34 -> 423.376 | ... AD70: =+AD34 -> 765.4 | AF70: =+AF34 -> 87.845 | AG70: =+AG34 -> 282.417 | AH70: =+AH34 -> 93.011 | AI70: =+AI34 -> 75.038 | AJ70: =+AJ34 -> 107.191 | AK70: =+AK34 -> 116.646 | AL70: =+AL34 -> 138.217 | AM70: =+AM34 -> 151.5 | ... BF70: =+BF34 -> 337.8
B71: Net valuation result on investment | C71: =-C22 -> -260.835 | D71: =-D22 -> -328.528 | E71: =-E22 -> -238.017 | F71: =-F22 -> -406.775 | G71: =-G22 -> -152.162 | H71: =-H22 -> -1100.571 | I71: =-I22 -> -723.58 | J71: =-J22 -> -697.3 | ... O71: =-O22 -> -1147.8 | Q71: =-Q22 -> -145.243 | R71: =-R22 -> -261.532 | S71: =-S22 -> -29.96 | T71: =-T22 -> -122.202 | U71: =-U22 -> -145.743 | V71: =-V22 -> -954.828 | W71: =-W22 -> -499.016 | X71: =-X22 -> -224.564 | ... AD71: =-AD22 -> -542 | AF71: =-AF22 -> -34.365 | AG71: =-AG22 -> -227.167 | AH71: =-AH22 -> -28.68 | AI71: =-AI22 -> -1.28 | AJ71: =-AJ22 -> -46.667 | AK71: =-AK22 -> -75.535 | AL71: =-AL22 -> -67.101 | AM71: =-AM22 -> -78.642 | ... BF71: =-BF22 -> -164.1
B72: Depreciation and amortisation | C72: =-C27 -> 3.996 | D72: =-D27 -> 5.418 | E72: =-E27 -> 3.868 | F72: =-F27 -> 9.753 | G72: =-G27 -> 10.462 | H72: =-H27 -> 8.447 | I72: =-I27 -> 10.729 | J72: =-J27 -> 10.729 | ... O72: =-O27 -> 13 | Q72: =-Q27 -> 3.456 | R72: =-R27 -> 6.297 | S72: =-S27 -> 4.317 | T72: =-T27 -> 6.145 | U72: =-U27 -> 5.102 | V72: =-V27 -> 3.345 | W72: =-W27 -> 5.015 | X72: =-X27 -> 5.714 | ... AD72: =-AD27 -> 6.5 | AF72: =-AF27 -> 1.031 | AG72: =-AG27 -> 5.266 | AH72: =-AH27 -> 2.635 | AI72: =-AI27 -> 1.682 | AJ72: =-AJ27 -> 2.107 | AK72: =-AK27 -> 4.038 | AL72: =-AL27 -> 2.564 | AM72: =-AM27 -> 2.538 | ... BF72: =-BF27 -> 3.6
B73: EBITDA | C73: =C70+C72+C71 -> 164.96 | D73: =D70+D72+D71 -> 185.987 | E73: =E70+E72+E71 -> 249.744 | F73: =F70+F72+F71 -> 220.877 | G73: =G70+G72+G71 -> 250.186 | H73: =H70+H72+H71 -> 284.684 | I73: =I70+I72+I71 -> 371.034 | J73: =J70+J72+J71 -> 360.976 | ... O73: =O70+O72+O71 -> 578.2 | Q73: =Q70+Q72+Q71 -> 105.85 | R73: =R70+R72+R71 -> 115.027 | S73: =S70+S72+S71 -> 142.406 | T73: =T70+T72+T71 -> 107.78 | U73: =U70+U72+U71 -> 149.076 | V73: =V70+V72+V71 -> 135.608 | W73: =W70+W72+W71 -> 166.508 | X73: =X70+X72+X71 -> 204.526 | ... AD73: =AD70+AD72+AD71 -> 229.9 | AF73: =AF70+AF72+AF71 -> 54.511 | AG73: =AG70+AG72+AG71 -> 60.516 | AH73: =AH70+AH72+AH71 -> 66.966 | AI73: =AI70+AI72+AI71 -> 75.44 | AJ73: =AJ70+AJ72+AJ71 -> 62.631 | AK73: =AK70+AK72+AK71 -> 45.149 | AL73: =AL70+AL72+AL71 -> 73.68 | AM73: =AM70+AM72+AM71 -> 75.396 | ... BF73: =BF70+BF72+BF71 -> 177.3
B74: % growth | D74: =D73/C73-1 -> 0.12746726 | E74: =E73/D73-1 -> 0.34280353 | F74: =F73/E73-1 -> -0.11558636 | G74: =G73/F73-1 -> 0.13269376 | H74: =H73/G73-1 -> 0.13788941 | I74: =I73/H73-1 -> 0.30331877 | J74: =J73/I73-1 -> -0.027108028 | K74: =K73/J73-1 -> 0.26822836 | L74: =L73/J73-1 -> 0.26434998 | M74: =M73/L73-1 -> 0.27234882 | N74: =N73/M73-1 -> -0.033924574 | S74: =S73/Q73-1 -> 0.34535664 | T74: =T73/R73-1 -> -0.063002599 | U74: =U73/S73-1 -> 0.046837914 | V74: =V73/T73-1 -> 0.25819261 | W74: =W73/U73-1 -> 0.11693364 | X74: =X73/V73-1 -> 0.50821485 | Y74: =Y73/W73-1 -> 0.36570015 | Z74: =Z73/X73-1 -> 0.12650714 | AA74: =AA73/X73-1 -> 0.39444374 | AB74: =AB73/Z73-1 -> 0.28255208 | AC74: =AC73/Z73-1 -> 0.43706597 | AD74: =AD73/AB73-1 -> -0.22199662 | AJ74: =AJ73/AF73-1 -> 0.14896076 | AK74: =AK73/AG73-1 -> -0.25393284 | AL74: =AL73/AH73-1 -> 0.10025983 | AM74: =AM73/AI73-1 -> -0.00058324496 | AN74: =AN73/AJ73-1 -> 0.085564656 | AO74: =AO73/AK73-1 -> 0.49766329 | AP74: =+AP73/AL73-1 -> 0.11853963 | AQ74: =+AQ73/AM73-1 -> 0.11536421 | AR74: =AR73/AN73-1 -> 0.4365642 | AS74: =AS73/AO73-1 -> 0.58025969 | AT74: =+AT73/AP73-1 -> 0.24390273 | AU74: =+AU73/AQ73-1 -> 0.48506433 | AV74: =AV73/AR73-1 -> 0.17024326 | AW74: =AW73/AS73-1 -> 0.086529283 | AX74: =+AX73/AT73-1 -> 0.34614447 | AY74: =+AY73/AU73-1 -> 0.1810866 | AZ74: =+AZ73/AV73-1 -> 0.25546807 | BA74: =BA73/AW73-1 -> 0.30921619 | BB74: =+BB73/AX73-1 -> 0.16014493 | BC74: =+BC73/AY73-1 -> 0.15932203 | BD74: =+BD73/AZ73-1 -> 0.20418118 | BE74: =BE73/BA73-1 -> -0.62434211 | BF74: =+BF73/BB73-1 -> 0.10743285
B75: % margin | D75: =D73/D20 -> 0.86304071 | E75: =E73/E20 -> 1.0417198 | F75: =F73/F20 -> 0.89746174 | G75: =G73/G20 -> 0.82582992 | H75: =H73/H20 -> 0.85320818 | I75: =I73/I20 -> 0.79806503 | J75: =J73/J20 -> 0.77633421 | K75: =K73/K20 -> 0.82635379 | ... O75: =O73/O20 -> 0.72175758 | Q75: =Q73/Q20 -> 0.9058002 | R75: =R73/R20 -> 0.88992302 | S75: =S73/S20 -> 0.88958715 | T75: =T73/T20 -> 0.7543921 | U75: =U73/U20 -> 0.89432543 | V75: =V73/V20 -> 0.81216012 | W75: =W73/W20 -> 0.7621829 | X75: =X73/X20 -> 0.82987158 | ... AD75: =AD73/AD20 -> 0.57089645 | AF75: =AF73/AF20 -> 0.9745593 | AG75: =AG73/AG20 -> 0.82535699 | AH75: =AH73/AH20 -> 0.86819997 | AI75: =AI73/AI20 -> 0.9094745 | AJ75: =AJ73/AJ20 -> 0.92282191 | AK75: =AK73/AK20 -> 0.60197864 | AL75: =AL73/AL20 -> 0.8936867 | AM75: =AM73/AM20 -> 0.8949505 | ... BF75: =BF73/BF20 -> 0.86614558
B77: Adjustment | C77: =C78-C73 -> 0 | D77: =D78-D73 -> 0 | E77: =E78-E73 -> -46.544 | F77: =F78-F73 -> -6.377 | G77: =G78-G73 -> -12.086 | H77: =H78-H73 -> 0 | I77: =I78-I73 -> 0 | J77: =J78-J73 -> 0 | ... O77: =O78-O73 -> 140.2 | Q77: =Q78-Q73 -> -12.85 | R77: =R78-R73 -> 6.473 | S77: =S78-S73 -> -23.106 | T77: =T78-T73 -> 11.02 | U77: =U78-U73 -> 0 | V77: =V78-V73 -> 0 | W77: =W78-W73 -> 0 | X77: =X78-X73 -> 0 | ... AD77: =AD78-AD73 -> 140.2 | AF77: =AF78-AF73 -> 0 | AG77: =AG78-AG73 -> 6.473 | AH77: =AH78-AH73 -> 0 | AI77: =AI78-AI73 -> -23.106 | AJ77: =AJ78-AJ73 -> -6.631 | AK77: =AK78-AK73 -> 17.651 | AL77: =AL78-AL73 -> 0 | AM77: =AM78-AM73 -> 0 | ... BF77: =BF78-BF73 -> 0
B78: Adjusted Normalised EBITDA | C78: =C73 -> 164.96 | D78: =D73 -> 185.987 | E78: 203.2 | F78: 214.5 | G78: 238.1 | H78: =H73 -> 284.684 | I78: =I73 -> 371.034 | J78: =J73 -> 360.976 | K78: =K73 -> 457.8 | L78: 472.7 | M78: 604 | N78: 701.2 | O78: =SUM(BC78:BF78) -> 718.4 | Q78: 93 | R78: =F78-Q78 -> 121.5 | S78: 119.3 | T78: =G78-S78 -> 118.8 | U78: =U73 -> 149.076 | V78: =H78-U78 -> 135.608 | W78: =W73 -> 166.508 | X78: =I78-W78 -> 204.526 | Y78: =Y73 -> 227.4 | Z78: =K78-Y78 -> 230.4 | AA78: =AA73 -> 285.2 | AB78: =M78-AA78 -> 318.8 | AC78: =AC73 -> 331.1 | AD78: =N78-AC78 -> 370.1 | AF78: =AF73 -> 54.511 | AG78: =F78-Q78-AF78 -> 66.989 | AH78: =AH73 -> 66.966 | AI78: =S78-AH78 -> 52.334 | AJ78: =175.3-S78 -> 56 | AK78: =G78-AJ78-S78 -> 62.8 | AL78: =AL73 -> 73.68 | AM78: =AM73 -> 75.396 | AN78: =AN73 -> 67.99 | AO78: =H78-AN78-U78 -> 67.618 | AP78: =AP73 -> 82.414 | AQ78: =AQ73 -> 84.094 | AR78: =AR73 -> 97.672 | AS78: =I78-AR78-W78 -> 106.854 | AT78: =AT73 -> 102.515 | AU78: =AU73 -> 124.885 | AV78: =AV73 -> 114.3 | AW78: =K78-AV78-Y78 -> 116.1 | AX78: =AX73 -> 138 | AY78: =AY73 -> 147.5 | AZ78: =AZ73 -> 143.5 | BA78: =M78-AZ78-AA78 -> 175.3 | BB78: =BB73 -> 160.1 | BC78: =BC73 -> 171 | BD78: =BD73 -> 172.8 | BE78: =N78-AC78-BD78 -> 197.3 | BF78: =BF73 -> 177.3
B79: % growth | D79: =D78/C78-1 -> 0.12746726 | E79: =E78/D78-1 -> 0.092549479 | F79: =F78/E78-1 -> 0.055610236 | G79: =G78/F78-1 -> 0.11002331 | H79: =H78/G78-1 -> 0.19564889 | I79: =I78/H78-1 -> 0.30331877 | J79: =J78/I78-1 -> -0.027108028 | K79: =K78/J78-1 -> 0.26822836 | L79: =L78/J78-1 -> 0.30950534 | M79: =M78/L78-1 -> 0.27776602 | N79: =N78/M78-1 -> 0.16092715 | S79: =S78/Q78-1 -> 0.2827957 | U79: =U78/R78-1 -> 0.22696296 | W79: =W78/T78-1 -> 0.40158249 | X79: =X78/U78-1 -> 0.37195793 | Y79: =Y78/V78-1 -> 0.67689222 | Z79: =Z78/W78-1 -> 0.3837173 | AA79: =AA78/W78-1 -> 0.71283061 | AB79: =AB78/Y78-1 -> 0.40193492 | AC79: =AC78/Y78-1 -> 0.45602463 | AD79: =AD78/AA78-1 -> 0.29768583 | AJ79: =AJ78/AF78-1 -> 0.027315588 | AK79: =AK78/AG78-1 -> -0.062532655 | AL79: =AL78/AH78-1 -> 0.10025983 | AM79: =AM78/AI78-1 -> 0.44066955 | AN79: =AN78/AJ78-1 -> 0.21410714 | AO79: =AO78/AK78-1 -> 0.076719745 | AP79: =AP78/AL78-1 -> 0.11853963 | AQ79: =AQ78/AM78-1 -> 0.11536421 | ... BF79: =BF78/BB78-1 -> 0.10743285
B80: % margin | C80: =C78/C20 -> 0.88900386 | D80: =D78/D20 -> 0.86304071 | E80: =E78/E20 -> 0.84757781 | F80: =F78/F20 -> 0.87155087 | G80: =G78/G20 -> 0.78593568 | H80: =H78/H20 -> 0.85320818 | I80: =I78/I20 -> 0.79806503 | J80: =J78/J20 -> 0.77633421 | ... O80: =O78/O20 -> 0.89676695 | Q80: =Q78/Q20 -> 0.79583768 | R80: =R78/R20 -> 0.94000232 | S80: =S78/S20 -> 0.74524772 | T80: =T78/T20 -> 0.83152516 | U80: =U78/U20 -> 0.89432543 | V80: =V78/V20 -> 0.81216012 | W80: =W78/W20 -> 0.7621829 | X80: =X78/X20 -> 0.82987158 | ... AD80: =AD78/AD20 -> 0.91904644 | AF80: =AF78/AF20 -> 0.9745593 | AG80: =AG78/AG20 -> 0.91364002 | AH80: =AH78/AH20 -> 0.86819997 | AI80: =AI78/AI20 -> 0.63091779 | AJ80: =AJ78/AJ20 -> 0.82511898 | AK80: =AK78/AK20 -> 0.83732217 | AL80: =AL78/AL20 -> 0.8936867 | AM80: =AM78/AM20 -> 0.8949505 | ... BF80: =BF78/BF20 -> 0.86614558
B82: CASH FLOW
B83: Adj EBITDA | C83: =C78 -> 164.96 | D83: =D78 -> 185.987 | E83: =E78 -> 203.2 | F83: =F78 -> 214.5 | G83: =G78 -> 238.1 | H83: =H78 -> 284.684 | I83: =I78 -> 371.034 | J83: =J78 -> 360.976 | ... N83: =N78 -> 701.2 | O83: =SUM(BC83:BF83) -> 718.4 | Q83: =Q78 -> 93 | R83: =R78 -> 121.5 | S83: =S78 -> 119.3 | T83: =T78 -> 118.8 | U83: =U78 -> 149.076 | V83: =V78 -> 135.608 | W83: =W78 -> 166.508 | X83: =X78 -> 204.526 | ... AD83: =AD78 -> 370.1 | AT83: =AT78 -> 102.515 | AU83: =AU78 -> 124.885 | AV83: =AV78 -> 114.3 | AW83: =AW78 -> 116.1 | AX83: =AX78 -> 138 | AY83: =AY78 -> 147.5 | AZ83: =AZ78 -> 143.5 | BA83: =BA78 -> 175.3 | ... BF83: =BF78 -> 177.3
B84: Working Capital | C84: -74.723 | D84: 44.216 | E84: 33.066 | F84: -5.393 | G84: 17.893 | H84: -47.254 | I84: 34.206 | J84: 34.206 | K84: 10.4 | L84: 10.4 | M84: -33 | N84: 35 | O84: =SUM(BC84:BF84) -> -32.2 | Q84: -30.764 | R84: =F84-Q84 -> 25.371 | S84: 13.16 | T84: =G84-S84 -> 4.733 | U84: -60.152 | V84: =H84-U84 -> 12.898 | W84: 20.638 | X84: =I84-W84 -> 13.568 | Y84: -54.1 | Z84: =K84-Y84 -> 64.5 | AA84: 8.9 | AB84: =M84-AA84 -> -41.9 | AC84: 8.2 | AD84: =N84-AC84 -> 26.8 | AT84: -73.192 | AU84: =Y84-AT84 -> 19.092 | AV84: =7.2-Y84 -> 61.3 | AW84: =K84-SUM(AT84:AV84) -> 3.2 | AX84: -29.3 | AY84: =AA84-AX84 -> 38.2 | AZ84: =32.5-35.6-19.6-AA84 -> -31.6 | BA84: =M84-AZ84-AA84 -> -10.3 | BB84: -27.8 | BC84: =AC84-BB84 -> 36 | BD84: =-12.6+60.7-3.8-AC84 -> 36.1 | BE84: =N84-AC84-BD84 -> -9.3 | BF84: -95
B85: Taxes | C85: -8.676 | D85: -11.124 | E85: -36.766 | F85: -12.077 | G85: -8.685 | H85: -33.066 | I85: -30.819 | J85: -30.819 | K85: -45 | L85: -45 | M85: -44.9 | N85: -74 | O85: =SUM(BC85:BF85) -> -72.1 | Q85: -10.375 | R85: =F85-Q85 -> -1.702 | S85: -3.827 | T85: =G85-S85 -> -4.858 | U85: 14.695 | V85: =H85-U85 -> -47.761 | W85: -25.885 | X85: =I85-W85 -> -4.934 | Y85: -25.2 | Z85: =K85-Y85 -> -19.8 | AA85: -31.1 | AB85: =M85-AA85 -> -13.8 | AC85: -40.1 | AD85: =N85-AC85 -> -33.9 | AT85: -8.711 | AU85: =Y85-AT85 -> -16.489 | AV85: =-38.9-Y85 -> -13.7 | AW85: =K85-SUM(AT85:AV85) -> -6.1 | AX85: -10.4 | AY85: =AA85-AX85 -> -20.7 | AZ85: =-34.3-AA85 -> -3.2 | BA85: =M85-AZ85-AA85 -> -10.6 | BB85: -16.2 | BC85: =AC85-BB85 -> -23.9 | BD85: =-54.5-AC85 -> -14.4 | BE85: =N85-AC85-BD85 -> -19.5 | BF85: -14.3
B86: Cash interest paid | C86: -41.964 | D86: -47.675 | E86: -54.715 | F86: -54.583 | G86: -62.272 | H86: -45.165 | I86: -64.697 | J86: -64.697 | K86: -116.5 | L86: -116.5 | M86: -207 | N86: -242.2 | O86: =SUM(BC86:BF86) -> -279.5 | Q86: -25.962 | R86: =F86-Q86 -> -28.621 | S86: -31.535 | T86: =G86-S86 -> -30.737 | U86: -21.617 | V86: =H86-U86 -> -23.548 | W86: -27.925 | X86: =I86-W86 -> -36.772 | Y86: -49.5 | Z86: =K86-Y86 -> -67 | AA86: -91 | AB86: =M86-AA86 -> -116 | AC86: -128.3 | AD86: =N86-AC86 -> -113.9 | AT86: -24.128 | AU86: =Y86-AT86 -> -25.372 | AV86: =-76.6-Y86 -> -27.1 | AW86: =K86-SUM(AT86:AV86) -> -39.9 | AX86: -35.9 | AY86: =AA86-AX86 -> -55.1 | AZ86: =-150.1-AA86 -> -59.1 | BA86: =M86-AZ86-AA86 -> -56.9 | BB86: -76.6 | BC86: =AC86-BB86 -> -51.7 | BD86: =-175.2-AC86 -> -46.9 | BE86: =N86-AC86-BD86 -> -67 | BF86: -113.9
B87: Interest received | C87: 2.978 | D87: 2.677 | E87: 1.953 | F87: 0.582 | G87: 0.371 | H87: 0.223 | I87: 3.785 | J87: 3.785 | K87: 20.4 | L87: 20.4 | M87: 50.7 | N87: 25.4 | O87: =SUM(BC87:BF87) -> 20.4 | Q87: 0.298 | R87: =F87-Q87 -> 0.284 | S87: 0.382 | T87: =G87-S87 -> -0.011 | U87: 0.223 | V87: =H87-U87 -> 0 | W87: -0.302 | X87: =I87-W87 -> 4.087 | Y87: 6.2 | Z87: =K87-Y87 -> 14.2 | AA87: 26.8 | AB87: =M87-AA87 -> 23.9 | AC87: 19.9 | AD87: =N87-AC87 -> 5.5 | AT87: 2.599 | AU87: =Y87-AT87 -> 3.601 | AV87: =4.6-Y87 -> -1.6 | AW87: =K87-SUM(AT87:AV87) -> 15.8 | AX87: 12.2 | AY87: =AA87-AX87 -> 14.6 | AZ87: =37.7-AA87 -> 10.9 | BA87: =M87-AZ87-AA87 -> 13 | BB87: 7.3 | BC87: =AC87-BB87 -> 12.6 | BD87: =18.2-AC87 -> -1.7 | BE87: =N87-AC87-BD87 -> 7.2 | BF87: 2.3
B88: Net cash from operations | C88: =SUM(C83:C87) -> 42.575 | D88: =SUM(D83:D87) -> 174.081 | E88: =SUM(E83:E87) -> 146.738 | F88: =SUM(F83:F87) -> 143.029 | G88: =SUM(G83:G87) -> 185.407 | H88: =SUM(H83:H87) -> 159.422 | I88: =SUM(I83:I87) -> 313.509 | J88: =SUM(J83:J87) -> 303.451 | ... O88: =SUM(O83:O87) -> 355 | Q88: =SUM(Q83:Q87) -> 26.197 | R88: =SUM(R83:R87) -> 116.832 | S88: =SUM(S83:S87) -> 97.48 | T88: =SUM(T83:T87) -> 87.927 | U88: =SUM(U83:U87) -> 82.225 | V88: =SUM(V83:V87) -> 77.197 | W88: =SUM(W83:W87) -> 133.034 | X88: =SUM(X83:X87) -> 180.475 | ... AD88: =SUM(AD83:AD87) -> 254.6 | AT88: =SUM(AT83:AT87) -> -0.917 | AU88: =SUM(AU83:AU87) -> 105.717 | AV88: =SUM(AV83:AV87) -> 133.2 | AW88: =SUM(AW83:AW87) -> 89.1 | AX88: =SUM(AX83:AX87) -> 74.6 | AY88: =SUM(AY83:AY87) -> 124.5 | AZ88: =SUM(AZ83:AZ87) -> 60.5 | BA88: =SUM(BA83:BA87) -> 110.5 | ... BF88: =SUM(BF83:BF87) -> -43.6
B89: Net Capex | C89: =-16.905-173.865 -> -190.77 | D89: =-14.7-62.278+14.68-387.812 -> -450.11 | E89: =-46.603-20.879+37.09-348.922 -> -379.314 | F89: =-48.699-3.228+12.11-322.055 -> -361.872 | G89: =-64.105-2.232+8.95-359.227 -> -416.614 | H89: =-174.392-13.969-96.526+4.312-599.566 -> -880.141 | I89: =-228.433-43.909-6.353+11.146-870.674 -> -1138.223 | J89: =-228.433-43.909-6.353+11.146-870.674 -> -1138.223 | K89: =-246.8-61.9-8.8-812.8 -> -1130.3 | L89: =-246.8-61.9-8.8-812.8 -> -1130.3 | M89: =-326.2-33.4-1-793.1 -> -1153.7 | N89: =-134.5-44.5-50.5-965.5 -> -1195 | O89: =SUM(BC89:BF89) -> -1200.7 | Q89: =-0.761-145.597+14.49 -> -131.868 | R89: =F89-Q89 -> -230.004 | S89: =-0.489-166.927 -> -167.416 | T89: =G89-S89 -> -249.198 | U89: =-48.18-22.884-275.205 -> -346.269 | V89: =H89-U89 -> -533.872 | W89: =-37.576-5.769-2.538+12.719-450.991 -> -484.155 | X89: =I89-W89 -> -654.068 | Y89: =-55.6-19-11.6-344.9 -> -431.1 | Z89: =K89-Y89 -> -699.2 | AA89: =-48-18.1-0.8-396.9 -> -463.8 | AB89: =M89-AA89 -> -689.9 | AC89: =-58.6-12.3-1.5-400 -> -472.4 | AD89: =N89-AC89 -> -722.6 | AT89: =-36.655-11.685-154.704 -> -203.044 | AU89: =Y89-AT89 -> -228.056 | AV89: =-127.2-33.2-8.5-554-Y89 -> -291.8 | AW89: =K89-SUM(AT89:AV89) -> -407.4 | AX89: =-15.6-10.5-187.2 -> -213.3 | AY89: =AA89-AX89 -> -250.5 | AZ89: =-120.6-24.9-1.7-604-AA89 -> -287.4 | BA89: =M89-AZ89-AA89 -> -402.5 | BB89: =-40.9-5.7-149.8 -> -196.4 | BC89: =AC89-BB89 -> -276 | BD89: =-93.7-22.8-72.9-699.2-AC89 -> -416.2 | BE89: =N89-AC89-BD89 -> -306.4 | BF89: =-32.8-8.5-160.8 -> -202.1
B90: Investment in subsidiaries, JVs | C90: -38.063 | D90: -14.723 | E90: -39.689 | F90: -20.378 | G90: =-27.116+1.06 -> -26.056 | H90: =-552.568+8.95 -> -543.618 | I90: =-112.522-194.843 -> -307.365 | J90: =-102.522-194.843 -> -297.365 | K90: =-58.5-39.5 -> -98 | L90: =-58.5-39.5 -> -98 | M90: =-147.4-26.6 -> -174 | N90: =-168.8-162.3 -> -331.1 | O90: =SUM(BC90:BF90) -> -323.9 | Q90: -13.22 | R90: =F90-Q90 -> -7.158 | S90: -5.207 | T90: =G90-S90 -> -20.849 | U90: -60.735 | V90: =H90-U90 -> -482.883 | W90: -138.325 | X90: =I90-W90 -> -169.04 | Y90: =-40.1-29.5+3.7 -> -65.9 | Z90: =K90-Y90 -> -32.1 | AA90: =-131.1-26.6 -> -157.7 | AB90: =M90-AA90 -> -16.3 | AC90: =-45.2-36.3 -> -81.5 | AD90: =N90-AC90 -> -249.6 | AT90: =-40.146-29.519 -> -69.665 | AU90: =Y90-AT90 -> 3.765 | AV90: =-40.1-29.5+3.7-Y90 -> 0 | AW90: =K90-SUM(AT90:AV90) -> -32.1 | AX90: 0 | AY90: =AA90-AX90 -> -157.7 | AZ90: =-131.1-26.6-AA90 -> 0 | BA90: =M90-AZ90-AA90 -> -16.3 | BB90: -7.2 | BC90: =AC90-BB90 -> -74.3 | BD90: =-45.2-36.3-AC90 -> 0 | BE90: =N90-AC90-BD90 -> -249.6 | BF90: 0
B91: Free cash flow | C91: =SUM(C88:C90) -> -186.258 | D91: =SUM(D88:D90) -> -290.752 | E91: =SUM(E88:E90) -> -272.265 | F91: =SUM(F88:F90) -> -239.221 | G91: =SUM(G88:G90) -> -257.263 | H91: =SUM(H88:H90) -> -1264.337 | I91: =SUM(I88:I90) -> -1132.079 | J91: =SUM(J88:J90) -> -1132.137 | ... N91: =SUM(N88:N90) -> -1080.7 | O91: =SUM(BC91:BF91) -> -1169.6 | Q91: =SUM(Q88:Q90) -> -118.891 | R91: =SUM(R88:R90) -> -120.33 | S91: =SUM(S88:S90) -> -75.143 | T91: =SUM(T88:T90) -> -182.12 | U91: =SUM(U88:U90) -> -324.779 | V91: =SUM(V88:V90) -> -939.558 | W91: =SUM(W88:W90) -> -489.446 | X91: =SUM(X88:X90) -> -642.633 | ... AD91: =SUM(AD88:AD90) -> -717.6 | AT91: =SUM(AT88:AT90) -> -273.626 | AU91: =SUM(AU88:AU90) -> -118.574 | AV91: =SUM(AV88:AV90) -> -158.6 | AW91: =SUM(AW88:AW90) -> -350.4 | AX91: =SUM(AX88:AX90) -> -138.7 | AY91: =SUM(AY88:AY90) -> -283.7 | AZ91: =SUM(AZ88:AZ90) -> -226.9 | BA91: =SUM(BA88:BA90) -> -308.3 | ... BF91: =SUM(BF88:BF90) -> -245.7
B92: Other investing activities | C92: 0 | D92: 23.481 | E92: 398.159 | F92: 0 | G92: =-27.08+0.629 -> -26.451 | H92: =-15+3.512 -> -11.488 | I92: =-1.79+2.398+80.184 -> 80.792 | J92: =-1.79+2.398+80.184 -> 80.792 | K92: =-0.2+44+4.1+3.7 -> 51.6 | L92: =-0.2+44+4.1+3.7 -> 51.6 | M92: =0.6 -> 0.6 | N92: 0 | O92: =SUM(BC92:BF92) -> 0.8 | Q92: 0 | R92: =F92-Q92 -> 0 | S92: 0 | T92: =G92-S92 -> -26.451 | U92: 0 | V92: =H92-U92 -> -11.488 | W92: 0 | X92: =I92-W92 -> 80.792 | Y92: =-0.1+4+4.1 -> 8 | Z92: =K92-Y92 -> 43.6 | AA92: 0.6 | AB92: =M92-AA92 -> 0 | AC92: 0 | AD92: =N92-AC92 -> 0 | AT92: =-0.05+4.08 -> 4.03 | AU92: =Y92-AT92 -> 3.97 | AV92: =-0.2+44+4.1-Y92 -> 39.9 | AW92: =K92-SUM(AT92:AV92) -> 3.7 | AX92: =-0.4+0.6 -> 0.2 | AY92: =AA92-AX92 -> 0.4 | AZ92: =0.6-0-0-AA92 -> 0 | BA92: =M92-AZ92-AA92 -> 0 | BB92: =-1.6-0.7 -> -2.3 | BC92: =AC92-BB92 -> 2.3 | BD92: =0-AC92 -> 0 | BE92: =N92-AC92-BD92 -> 0 | BF92: -1.5
B93: Dividends / Equity movements | C93: 0 | D93: 0 | E93: -195.606 | F93: 0 | G93: =0.2-12.5 -> -12.3 | H93: =854.238-34.904-5.513 -> 813.821 | I93: =-123.96-2.247 -> -126.207 | J93: =-123.96-2.247 -> -126.207 | K93: -164 | L93: -164 | M93: =-151.4+294.6 -> 143.2 | N93: -83.7 | O93: =SUM(BC93:BF93) -> -83.7 | Q93: 0 | R93: =F93-Q93 -> 0 | S93: -12.5 | T93: =G93-S93 -> 0.2 | U93: 0 | V93: =H93-U93 -> 813.821 | W93: 0 | X93: =I93-W93 -> -126.207 | Y93: 0 | Z93: =K93-Y93 -> -164 | AA93: 0 | AB93: =M93-AA93 -> 143.2 | AC93: 0 | AD93: =N93-AC93 -> -83.7 | AT93: 0 | AU93: =Y93-AT93 -> 0 | AV93: =0-Y93 -> 0 | AW93: =K93-SUM(AT93:AV93) -> -164 | AX93: 0 | AY93: =AA93-AX93 -> 0 | AZ93: =222.8-AA93 -> 222.8 | BA93: =M93-AZ93-AA93 -> -79.6 | BB93: 0 | BC93: =AC93-BB93 -> 0 | BD93: =-44.9-AC93 -> -44.9 | BE93: =N93-AC93-BD93 -> -38.8 | BF93: 0
B94: Change in debt | C94: =-846.437+1019.269 -> 172.832 | D94: =-528.446-21.657+828.944 -> 278.841 | E94: =-273.782+357.466-13.428+11.518 -> 81.774 | F94: =-1508.8+2042.082-225 -> 308.282 | G94: =1041.395-1088.814+743.657-20.625 -> 675.613 | H94: =2479.615-2119.968+677.468-35.968 -> 1001.147 | I94: =733.368-391.201+628.987-0 -> 971.154 | J94: =733.368-391.201+628.987-0 -> 971.154 | K94: =-427.9+1492.8 -> 1064.9 | L94: =-427.9+1492.8 -> 1064.9 | M94: =1369.3-1350.3+1035.4-4.2 -> 1050.2 | N94: =1596.2-1248.3+764.8-4.6 -> 1108.1 | O94: =SUM(BC94:BF94) -> 123.7 | Q94: =-1443.246+1824.639-225 -> 156.393 | R94: =F94-Q94 -> 151.889 | S94: =-105.387+201.539+0.629-15.981 -> 80.8 | T94: =G94-S94 -> 594.813 | U94: =-1910.975+75.468+3.542-35.969+1487.52-15 -> -395.414 | V94: =H94-U94 -> 1396.561 | W94: =-434.517+53.987+4.626+695.226-1.5 -> 317.822 | X94: =I94-W94 -> 653.332 | Y94: =-13.2+508.3-1.8 -> 493.3 | Z94: =K94-Y94 -> 571.6 | AA94: =823.2-748.5+823.8-2.1 -> 896.4 | AB94: =M94-AA94 -> 153.8 | AC94: =996.2-743.3+185.6-2.3 -> 436.2 | AD94: =N94-AC94 -> 671.9 | AT94: =-6.122+228.4 -> 222.278 | AU94: =Y94-AT94 -> 271.022 | AV94: =-19.3+905.3-2.8-Y94 -> 389.9 | AW94: =K94-SUM(AT94:AV94) -> 181.7 | AX94: =-247.6+192+747.9 -> 692.3 | AY94: =AA94-AX94 -> 204.1 | AZ94: =823.2-763.8+1035.5-3.2-AA94 -> 195.3 | BA94: =M94-AZ94-AA94 -> -41.5 | BB94: =-15+185.6+996.2 -> 1166.8 | BC94: =AC94-BB94 -> -730.6 | BD94: =996.2-757.1+684.8-3.4-AC94 -> 484.3 | BE94: =N94-AC94-BD94 -> 187.6 | BF94: =-597.2+280+499.6 -> 182.4
B95: Other financing activities | C95: 0 | D95: -10.999 | E95: =-2.385-0.59 -> -2.975 | F95: =-31.705-0.5 -> -32.205 | G95: =-21.649-0.541 -> -22.19 | H95: =-45.344-0.974 -> -46.318 | I95: =-4.754-3.01 -> -7.764 | J95: =-4.754-3.01 -> -7.764 | K95: =-3.6-11.2 -> -14.8 | L95: =-3.6-11.2 -> -14.8 | M95: =-39.6 -> -39.6 | N95: -32.4 | O95: =SUM(BC95:BF95) -> -29.8 | Q95: =-59.621-0.2 -> -59.821 | R95: =F95-Q95 -> 27.616 | S95: =-1.376+0.2-0.123 -> -1.299 | T95: =G95-S95 -> -20.891 | U95: =-23.844-0.5+854.238-13.208 -> 816.686 | V95: =H95-U95 -> -863.004 | W95: =0.832-67.942-0.555 -> -67.665 | X95: =I95-W95 -> 59.901 | Y95: =-6.8-75.9 -> -82.7 | Z95: =K95-Y95 -> 67.9 | AA95: =-15.7-41.4 -> -57.1 | AB95: =M95-AA95 -> 17.5 | AC95: =-44.9-12.3 -> -57.2 | AD95: =N95-AC95 -> 24.8 | AT95: =-2.374-0.955 -> -3.329 | AU95: =Y95-AT95 -> -79.371 | AV95: =-9.2-164-Y95 -> -90.5 | AW95: =K95-SUM(AT95:AV95) -> 158.4 | AX95: =-8.8-1.2 -> -10 | AY95: =AA95-AX95 -> -47.1 | AZ95: =-19.3-41.4-AA95 -> -3.6 | BA95: =M95-AZ95-AA95 -> 21.1 | BB95: =-9.7-1.2 -> -10.9 | BC95: =AC95-BB95 -> -46.3 | BD95: =-27.1-AC95 -> 30.1 | BE95: =N95-AC95-BD95 -> -5.3 | BF95: =-6.9-1.4 -> -8.3
B96: Cash flow after financing activities | C96: =SUM(C91:C95) -> -13.426 | D96: =SUM(D91:D95) -> 0.571 | E96: =SUM(E91:E95) -> 9.087 | F96: =SUM(F91:F95) -> 36.856 | G96: =SUM(G91:G95) -> 357.409 | H96: =SUM(H91:H95) -> 492.825 | I96: =SUM(I91:I95) -> -214.104 | J96: =SUM(J91:J95) -> -214.162 | ... O96: =SUM(O91:O95) -> -1158.6 | Q96: =SUM(Q91:Q95) -> -22.319 | R96: =SUM(R91:R95) -> 59.175 | S96: =SUM(S91:S95) -> -8.142 | T96: =SUM(T91:T95) -> 365.551 | U96: =SUM(U91:U95) -> 96.493 | V96: =SUM(V91:V95) -> 396.332 | W96: =SUM(W91:W95) -> -239.289 | X96: =SUM(X91:X95) -> 25.185 | ... AD96: =SUM(AD91:AD95) -> -104.6 | AT96: =SUM(AT91:AT95) -> -50.647 | AU96: =Y96-AT96 -> 77.047 | AV96: =SUM(AV91:AV95) -> 180.7 | AW96: =SUM(AW91:AW95) -> -170.6 | AX96: =SUM(AX91:AX95) -> 543.8 | AY96: =AA96-AX96 -> -126.6 | AZ96: =SUM(AZ91:AZ95) -> 187.6 | BA96: =SUM(BA91:BA95) -> -408.3 | BB96: =SUM(BB91:BB95) -> 996.8 | BC96: =SUM(BC91:BC95) -> -980.9 | BD96: =SUM(BD91:BD95) -> 199.2 | BE96: =SUM(BE91:BE95) -> -303.8 | BF96: =SUM(BF91:BF95) -> -73.1
B97: Balancing figure | C97: =21.11-C96 -> 34.536 | D97: =-0.09-D96 -> -0.661 | E97: =16.258-E96 -> 7.171 | F97: =17.785-F96 -> -19.071 | G97: =357.432-G96 -> 0.023 | H97: =472.461-H96 -> -20.364 | I97: =-227.298-I96 -> -13.194 | J97: =-227.298-J96 -> -13.136 | K97: =27.8-K96 -> -8.7 | L97: =27.8-L96 -> -23.6 | M97: =166.7-M96 -> -29.8 | N97: =-151.4-N96 -> -62.7 | O97: =SUM(BC97:BF97) -> -56.8 | Q97: =-9.498-Q96 -> 12.821 | R97: =F97-Q97 -> -31.892 | S97: =14.871-S96 -> 23.013 | T97: =G97-S97 -> -22.99 | U97: =66.811-U96 -> -29.682 | V97: =H97-U97 -> 9.318 | W97: =-247.141-W96 -> -7.852 | X97: =I97-W97 -> -5.342 | Y97: =22.9-Y96 -> -3.5 | Z97: =K97-Y97 -> -5.2 | AA97: =412.1-AA96 -> -5.1 | AB97: =M97-AA97 -> -24.7 | AC97: =-9-AC96 -> -24.9 | AD97: =N97-AC97 -> -37.8 | AT97: =-52.188-AT96 -> -1.541 | AU97: =22.9-AU96-AT96-AT97 -> -1.959 | AV97: =207.7-AV96-AU96-AT96-AT97-AU97 -> 4.1 | AW97: =K97-SUM(AT97:AV97) -> -9.3 | AX97: =543.9-AX96 -> 0.1 | AY97: =412.1-AY96-AX96-AX97 -> -5.2 | AZ97: =596.6-AZ96-AY96-AX96-AX97-AY97 -> -3.1 | BA97: =M97-AZ97-AA97 -> -21.6 | BB97: =989.4-BB96 -> -7.4 | BC97: =-9-BC96-BB96-BB97 -> -17.5 | BD97: =193.1-BD96-BC96-BB96-BB97-BC97 -> 2.9 | BE97: =N97-AC97-BD97 -> -40.7 | BF97: =-74.6-BF96 -> -1.5
B98: FX | C98: 0 | D98: 0 | E98: 4.541 | F98: -0.248 | G98: -2.112 | H98: 1.214 | I98: -4.887 | J98: -4.887 | K98: 2.2 | L98: 2.2 | M98: -1.9 | N98: 4.4 | O98: =SUM(BC98:BF98) -> 2.1 | Q98: 0 | R98: =F98-Q98 -> -0.248 | S98: 0 | T98: =G98-S98 -> -2.112 | U98: 1.559 | V98: =H98-U98 -> -0.345 | W98: -5.413 | X98: =I98-W98 -> 0.526 | Y98: 4.1 | Z98: =K98-Y98 -> -1.9 | AA98: -1.3 | AB98: =M98-AA98 -> -0.6 | AC98: 2 | AD98: =N98-AC98 -> 2.4 | AT98: 3.567 | AU98: =Y98-AT98 -> 0.533 | AV98: =0.2-Y98 -> -3.9 | AW98: =K98-SUM(AT98:AV98) -> 2 | AX98: -2.3 | AY98: =AA98-AX98 -> 1 | AZ98: =-1.8-AA98 -> -0.5 | BA98: =M98-AZ98-AA98 -> -0.1 | BB98: 1.7 | BC98: =AC98-BB98 -> 0.3 | BD98: =3.7-AC98 -> 1.7 | BE98: =N98-AC98-BD98 -> 0.7 | BF98: -0.6
B99: Net change in cash | C99: =SUM(C96:C98) -> 21.11 | D99: =SUM(D96:D98) -> -0.09 | E99: =SUM(E96:E98) -> 20.799 | F99: =SUM(F96:F98) -> 17.537 | G99: =SUM(G96:G98) -> 355.32 | H99: =SUM(H96:H98) -> 473.675 | I99: =SUM(I96:I98) -> -232.185 | J99: =SUM(J96:J98) -> -232.185 | ... O99: =SUM(O96:O98) -> -1213.3 | Q99: =SUM(Q96:Q98) -> -9.498 | R99: =SUM(R96:R98) -> 27.035 | S99: =SUM(S96:S98) -> 14.871 | T99: =SUM(T96:T98) -> 340.449 | U99: =SUM(U96:U98) -> 68.37 | V99: =SUM(V96:V98) -> 405.305 | W99: =SUM(W96:W98) -> -252.554 | X99: =SUM(X96:X98) -> 20.369 | ... AD99: =SUM(AD96:AD98) -> -140 | AT99: =SUM(AT96:AT98) -> -48.621 | AU99: =SUM(AU96:AU98) -> 75.621 | AV99: =SUM(AV96:AV98) -> 180.9 | AW99: =SUM(AW96:AW98) -> -177.9 | AX99: =SUM(AX96:AX98) -> 541.6 | AY99: =SUM(AY96:AY98) -> -130.8 | AZ99: =SUM(AZ96:AZ98) -> 184 | BA99: =SUM(BA96:BA98) -> -430 | ... BF99: =SUM(BF96:BF98) -> -75.2
B100: Cash and cash equivalents | C100: =C130 -> 64.417 | D100: =D130 -> 25.485 | E100: =D100+E99 -> 46.284 | F100: =+E100+F99 -> 63.821 | G100: =+F100+G99 -> 419.141 | H100: =+G100+H99 -> 892.816 | I100: =+H100+I99 -> 660.631 | J100: =+H100+J99 -> 660.631 | K100: =+J100+K99 -> 690.631 | L100: =+J100+L99 -> 690.631 | M100: =+K100+M99 -> 855.431 | N100: =+M100+N99 -> 708.431 | O100: =BF100 -> 633.2 | Q100: =+E100+Q99 -> 36.786 | R100: =+Q100+R99 -> 63.821 | S100: =+R100+S99 -> 78.692 | T100: =+S100+T99 -> 419.141 | U100: =+T100+U99 -> 487.511 | V100: =+U100+V99 -> 892.816 | W100: =+V100+W99 -> 640.262 | X100: =+W100+X99 -> 660.631 | Y100: =+X100+Y99 -> 687.631 | ... AD100: =+AC100+AD99 -> 708.431 | AT100: =AT130 -> 612.01 | AU100: =AT100+AU99 -> 687.631 | AV100: =AU100+AV99 -> 868.531 | AW100: =AV100+AW99 -> 690.631 | AX100: =AX130 -> 1232.2 | AY100: =AX100+AY99 -> 1101.4 | AZ100: =AY100+AZ99 -> 1285.4 | BA100: =AZ100+BA99 -> 855.4 | BB100: =BA100+BB99 -> 1846.5 | BC100: =BB100+BC99 -> 848.4 | BD100: =BC100+BD99 -> 1052.2 | BE100: =BD100+BE99 -> 708.4 | BF100: =BE100+BF99 -> 633.2
B102: Check 1 | C102: =C100-C130 -> 0 | D102: =D100-D130 -> 0 | E102: =E100-E130 -> 0 | F102: =F100-F130 -> 0 | G102: =G100-G130 -> 0 | H102: =H100-H130 -> 0 | I102: =I100-I130 -> 0 | J102: =J100-J130 -> 0 | ... O102: =O100-O130 -> 0.2 | R102: =R100-R130 -> 0 | S102: =S100-S130 -> 0 | T102: =T100-T130 -> 0 | U102: =U100-U130 -> 0 | V102: =V100-V130 -> 0 | W102: =W100-W130 -> 0 | X102: =X100-X130 -> 0 | Y102: =Y100-Y130 -> 0.031 | ... AD102: =AD100-AD130 -> 0.031 | AT102: =AT100-AT130 -> 0 | AU102: =AU100-AU130 -> 0.031 | AV102: =AV100-AV130 -> 0.031 | AW102: =AW100-AW130 -> 0.031 | AX102: =AX100-AX130 -> 0 | AY102: =AY100-AY130 -> 0 | AZ102: =AZ100-AZ130 -> 0 | BA102: =BA100-BA130 -> 0 | ... BF102: =BF100-BF130 -> 0.2
B103: Check 2 | C103: =77.111-(C88+C97) -> 0 | D103: =173.42-(D88+D97) -> 0 | E103: =153.909-(E88+E97) -> 0 | F103: =123.958-(F88+F97) -> 1.563194e-13 | G103: =185.43-(G88+G97) -> 0 | H103: =139.058-(H88+H97) -> 0 | I103: =300.315-(I88+I97) -> 0 | J103: =290.2-(J88+J97) -> -0.115 | K103: =318.4-(K88+K97) -> 0 | L103: =318.4-(L88+L97) -> 0 | M103: =340-(M88+M97) -> 0 | N103: =382.7-(N88+N97) -> 0 | Q103: =39.018-(Q88+Q97) -> -1.9895197e-13 | S103: =120.493-(S88+S97) -> 0 | U103: =52.543-(U88+U97) -> 7.8159701e-14 | W103: =125.182-(W88+W97) -> 0 | Y103: =101.3-(Y88+Y97) -> 0 | AA103: =191.4-(AA88+AA97) -> -2.3 | AT103: =-2.458-(AT88+AT97) -> -5.3290705e-15 | AV103: =238.6-(SUM(AT97:AV97)+SUM(AT88:AV88)) -> 2.2737368e-13 | AX103: =74.7-(AX88+AX97) -> 0 | BB103: =39.4-(BB88+BB97) -> 0 | BF103: =-45.1-(BF88+BF97) -> 0
B105: LTM METRICS | AF105: =AF3 -> 43738 | AG105: =AG3 -> 43830 | AH105: =AH3 -> 43920 | AI105: =AI3 -> 44012 | AJ105: =AJ3 -> 44104 | AK105: =AK3 -> 44196 | AL105: =AL3 -> 44285 | AM105: =AM3 -> 44377 | ... BF105: =BF3 -> 46112
B107: Revenue | C107: =+C20 -> 185.556 | D107: =+D20 -> 215.502 | E107: =+E20 -> 239.742 | F107: =+F20 -> 246.113 | G107: =+G20 -> 302.951 | H107: =+H20 -> 333.663 | I107: =+I20 -> 464.917 | J107: =+J20 -> 464.975 | ... O107: =+O20 -> 801.1 | R107: =SUM(Q20,R20) -> 246.113 | S107: =SUM(R20,S20) -> 289.336 | T107: =SUM(S20,T20) -> 302.951 | U107: =SUM(T20,U20) -> 309.561 | V107: =SUM(U20,V20) -> 333.663 | W107: =SUM(V20,W20) -> 385.434 | X107: =SUM(W20,X20) -> 464.917 | Y107: =SUM(X20,Y20) -> 520.855 | Z107: =SUM(Y20,Z20) -> 554 | AA107: =SUM(Y20,AA20) -> 603.8 | AB107: =SUM(AA20,AB20) -> 681.8 | AC107: =SUM(AB20,AC20) -> 729 | AD107: =SUM(AC20,AD20) -> 779.3 | AG107: =F107 -> 246.113 | AI107: =SUM(AF20:AI20) -> 289.336 | AJ107: =SUM(AG20:AJ20) -> 301.271 | AK107: =G107 -> 302.951 | AL107: =SUM(AI20:AL20) -> 308.264 | AM107: =SUM(AJ20:AM20) -> 309.561 | AN107: =SUM(AK20:AN20) -> 321.89 | AO107: =H107 -> 333.663 | AP107: =SUM(AM20:AP20) -> 361.059 | AQ107: =SUM(AN20:AQ20) -> 385.434 | AR107: =SUM(AO20:AR20) -> 424.324 | AS107: =I107 -> 464.917 | AT107: =SUM(AQ20:AT20) -> 487.248 | AU107: =SUM(AR20:AU20) -> 520.855 | AV107: =SUM(AS20:AV20) -> 539.667 | AW107: =K107 -> 554 | AX107: =SUM(AU20:AX20) -> 580.228 | AY107: =SUM(AV20:AY20) -> 609.3 | AZ107: =SUM(AW20:AZ20) -> 637.6 | BA107: =SUM(AX20:BA20) -> 682.1 | BB107: =SUM(AY20:BB20) -> 706.6 | BC107: =SUM(AZ20:BC20) -> 729 | BD107: =SUM(BA20:BD20) -> 758.8 | BE107: =SUM(BB20:BE20) -> 779.3 | BF107: =SUM(BC20:BF20) -> 801.1
B108: Operating profit | C108: =+C70 -> 421.799 | D108: =+D70 -> 509.097 | E108: =+E70 -> 483.893 | F108: =+F70 -> 617.899 | G108: =+G70 -> 391.886 | H108: =+H70 -> 1376.808 | I108: =+I70 -> 1083.885 | J108: =+J70 -> 1047.547 | ... O108: =+O70 -> 1713 | R108: =SUM(Q70,R70) -> 617.899 | S108: =SUM(R70,S70) -> 538.311 | T108: =SUM(S70,T70) -> 391.886 | U108: =SUM(T70,U70) -> 513.554 | V108: =SUM(U70,V70) -> 1376.808 | W108: =SUM(V70,W70) -> 1747.6 | X108: =SUM(W70,X70) -> 1083.885 | Y108: =SUM(X70,Y70) -> 1061.876 | Z108: =SUM(Y70,Z70) -> 1323.8 | AA108: =SUM(Y70,AA70) -> 1354.7 | AB108: =SUM(AA70,AB70) -> 1511.2 | AC108: =SUM(AB70,AC70) -> 1718.3 | AD108: =SUM(AC70,AD70) -> 1688.7 | AG108: =F108 -> 617.899 | AI108: =SUM(AF70:AI70) -> 538.311 | AJ108: =SUM(AG70:AJ70) -> 557.657 | AK108: =G108 -> 391.886 | AL108: =SUM(AI70:AL70) -> 437.092 | AM108: =SUM(AJ70:AM70) -> 513.554 | AN108: =SUM(AK70:AN70) -> 592.573 | AO108: =H108 -> 1376.808 | AP108: =SUM(AM70:AP70) -> 1346.301 | AQ108: =SUM(AN70:AQ70) -> 1747.6 | AR108: =SUM(AO70:AR70) -> 1715.293 | AS108: =I108 -> 1083.885 | AT108: =SUM(AQ70:AT70) -> 1284.172 | AU108: =SUM(AR70:AU70) -> 1061.876 | AV108: =SUM(AS70:AV70) -> 1259.273 | AW108: =K108 -> 1323.8 | AX108: =SUM(AU70:AX70) -> 1316.203 | AY108: =SUM(AV70:AY70) -> 1401.8 | AZ108: =SUM(AW70:AZ70) -> 1358.7 | BA108: =SUM(AX70:BA70) -> 1511.5 | BB108: =SUM(AY70:BB70) -> 1524.6 | BC108: =SUM(AZ70:BC70) -> 1718.3 | BD108: =SUM(BA70:BD70) -> 1783.8 | BE108: =SUM(BB70:BE70) -> 1688.7 | BF108: =SUM(BC70:BF70) -> 1713
B109: EBITDA | C109: =+C73 -> 164.96 | D109: =+D73 -> 185.987 | E109: =+E73 -> 249.744 | F109: =+F73 -> 220.877 | G109: =+G73 -> 250.186 | H109: =+H73 -> 284.684 | I109: =+I73 -> 371.034 | J109: =+J73 -> 360.976 | ... O109: =+O73 -> 578.2 | R109: =SUM(Q73,R73) -> 220.877 | S109: =SUM(R73,S73) -> 257.433 | T109: =SUM(S73,T73) -> 250.186 | U109: =SUM(T73,U73) -> 256.856 | V109: =SUM(U73,V73) -> 284.684 | W109: =SUM(V73,W73) -> 302.116 | X109: =SUM(W73,X73) -> 371.034 | Y109: =SUM(X73,Y73) -> 431.926 | Z109: =SUM(Y73,Z73) -> 457.8 | AA109: =SUM(Y73,AA73) -> 512.6 | AB109: =SUM(AA73,AB73) -> 580.7 | AC109: =SUM(AB73,AC73) -> 626.6 | AD109: =SUM(AC73,AD73) -> 561 | AG109: =F109 -> 220.877 | AI109: =SUM(AF73:AI73) -> 257.433 | AJ109: =SUM(AG73:AJ73) -> 265.553 | AK109: =G109 -> 250.186 | AL109: =SUM(AI73:AL73) -> 256.9 | AM109: =SUM(AJ73:AM73) -> 256.856 | AN109: =SUM(AK73:AN73) -> 262.215 | AO109: =H109 -> 284.684 | AP109: =SUM(AM73:AP73) -> 293.418 | AQ109: =SUM(AN73:AQ73) -> 302.116 | AR109: =SUM(AO73:AR73) -> 331.798 | AS109: =I109 -> 371.034 | AT109: =SUM(AQ73:AT73) -> 391.135 | AU109: =SUM(AR73:AU73) -> 431.926 | AV109: =SUM(AS73:AV73) -> 448.554 | AW109: =K109 -> 457.8 | AX109: =SUM(AU73:AX73) -> 493.285 | AY109: =SUM(AV73:AY73) -> 515.9 | AZ109: =SUM(AW73:AZ73) -> 545.1 | BA109: =SUM(AX73:BA73) -> 581 | BB109: =SUM(AY73:BB73) -> 603.1 | BC109: =SUM(AZ73:BC73) -> 626.6 | BD109: =SUM(BA73:BD73) -> 655.9 | BE109: =SUM(BB73:BE73) -> 561 | BF109: =SUM(BC73:BF73) -> 578.2
B110: Adjusted EBITDA | C110: =+C78 -> 164.96 | D110: =+D78 -> 185.987 | E110: =+E78 -> 203.2 | F110: =+F78 -> 214.5 | G110: =+G78 -> 238.1 | H110: =+H78 -> 284.684 | I110: =+I78 -> 371.034 | J110: =+J78 -> 360.976 | ... O110: =+O78 -> 718.4 | R110: =SUM(Q78,R78) -> 214.5 | S110: =SUM(R78,S78) -> 240.8 | T110: =SUM(S78,T78) -> 238.1 | U110: =SUM(T78,U78) -> 267.876 | V110: =SUM(U78,V78) -> 284.684 | W110: =SUM(V78,W78) -> 302.116 | X110: =SUM(W78,X78) -> 371.034 | Y110: =SUM(X78,Y78) -> 431.926 | Z110: =SUM(Y78,Z78) -> 457.8 | AA110: =SUM(Y78,AA78) -> 512.6 | AB110: =SUM(AA78,AB78) -> 604 | AC110: =SUM(AB78,AC78) -> 649.9 | AD110: =SUM(AC78,AD78) -> 701.2 | AG110: =F110 -> 214.5 | AI110: =SUM(AF78:AI78) -> 240.8 | AJ110: =SUM(AG78:AJ78) -> 242.289 | AK110: =G110 -> 238.1 | AL110: =SUM(AI78:AL78) -> 244.814 | AM110: =SUM(AJ78:AM78) -> 267.876 | AN110: =SUM(AK78:AN78) -> 279.866 | AO110: =H110 -> 284.684 | AP110: =SUM(AM78:AP78) -> 293.418 | AQ110: =SUM(AN78:AQ78) -> 302.116 | AR110: =SUM(AO78:AR78) -> 331.798 | AS110: =I110 -> 371.034 | AT110: =SUM(AQ78:AT78) -> 391.135 | AU110: =SUM(AR78:AU78) -> 431.926 | AV110: =SUM(AS78:AV78) -> 448.554 | AW110: =K110 -> 457.8 | AX110: =SUM(AU78:AX78) -> 493.285 | AY110: =SUM(AV78:AY78) -> 515.9 | AZ110: =SUM(AW78:AZ78) -> 545.1 | BA110: =SUM(AX78:BA78) -> 604.3 | BB110: =SUM(AY78:BB78) -> 626.4 | BC110: =SUM(AZ78:BC78) -> 649.9 | BD110: =SUM(BA78:BD78) -> 679.2 | BE110: =SUM(BB78:BE78) -> 701.2 | BF110: =SUM(BC78:BF78) -> 718.4
B111: Cash interest paid | C111: =-C86 -> 41.964 | D111: =-D86 -> 47.675 | E111: =-E86 -> 54.715 | F111: =-F86 -> 54.583 | G111: =-G86 -> 62.272 | H111: =-H86 -> 45.165 | I111: =-I86 -> 64.697 | J111: =-J86 -> 64.697 | ... O111: =-O86 -> 279.5 | R111: =-SUM(Q86,R86) -> 54.583 | S111: =-SUM(R86,S86) -> 60.156 | T111: =-SUM(S86,T86) -> 62.272 | U111: =-SUM(T86,U86) -> 52.354 | V111: =-SUM(U86,V86) -> 45.165 | W111: =-SUM(V86,W86) -> 51.473 | X111: =-SUM(W86,X86) -> 64.697 | Y111: =-SUM(X86,Y86) -> 86.272 | Z111: =-SUM(Y86,Z86) -> 116.5 | AA111: =-SUM(Y86,AA86) -> 140.5 | AB111: =-SUM(AA86,AB86) -> 207 | AC111: =-SUM(AB86,AC86) -> 244.3 | AD111: =-SUM(AC86,AD86) -> 242.2 | AG111: =F111 -> 54.583 | AK111: =G111 -> 62.272 | AO111: =H111 -> 45.165 | AS111: =I111 -> 64.697 | AW111: =K111 -> 116.5 | AX111: =J111 -> 64.697 | AY111: =K111 -> 116.5 | AZ111: =L111 -> 116.5 | BA111: =M111 -> 207 | BB111: =-SUM(AY86:BB86) -> 247.7 | BC111: =-SUM(AZ86:BC86) -> 244.3 | BD111: =-SUM(BA86:BD86) -> 232.1 | BE111: =-SUM(BB86:BE86) -> 242.2 | BF111: =-SUM(BC86:BF86) -> 279.5
B112: Net Income | C112: =+C43 -> 310.797 | D112: =+D43 -> 349.819 | E112: =+E43 -> 362.883 | F112: =+F43 -> 392.161 | G112: =+G43 -> 252.524 | H112: =+H43 -> 1025.936 | I112: =+I43 -> 796.525 | J112: =+J43 -> 764.33 | ... O112: =+O43 -> 1098.4 | R112: =SUM(Q43,R43) -> 392.161 | S112: =SUM(R43,S43) -> 351.191 | T112: =SUM(S43,T43) -> 252.524 | U112: =SUM(T43,U43) -> 341.52 | V112: =SUM(U43,V43) -> 1025.936 | W112: =SUM(V43,W43) -> 1327.879 | X112: =SUM(W43,X43) -> 796.525 | Y112: =SUM(X43,Y43) -> 777.403 | Z112: =SUM(Y43,Z43) -> 922.6 | AA112: =SUM(Y43,AA43) -> 1004.9 | AB112: =SUM(AA43,AB43) -> 1081.4 | AC112: =SUM(AB43,AC43) -> 1173.3 | AD112: =SUM(AC43,AD43) -> 1081.8 | AG112: =F112 -> 392.161 | AI112: =SUM(AF43:AI43) -> 351.191 | AJ112: =SUM(AG43:AJ43) -> 390.25 | AK112: =G112 -> 252.524 | AL112: =SUM(AI43:AL43) -> 293.243 | AM112: =SUM(AJ43:AM43) -> 341.52 | AN112: =SUM(AK43:AN43) -> 409.238 | AO112: =H112 -> 1025.936 | AP112: =SUM(AM43:AP43) -> 987.663 | AQ112: =SUM(AN43:AQ43) -> 1327.879 | AR112: =SUM(AO43:AR43) -> 1304.055 | AS112: =I112 -> 796.525 | AT112: =SUM(AQ43:AT43) -> 961.798 | AU112: =SUM(AR43:AU43) -> 777.403 | AV112: =SUM(AS43:AV43) -> 933.126 | AW112: =K112 -> 922.6 | AX112: =SUM(AU43:AX43) -> 924.321 | AY112: =SUM(AV43:AY43) -> 985.6 | AZ112: =SUM(AW43:AZ43) -> 927.4 | BA112: =M112 -> 1081.4 | BB112: =SUM(AY43:BB43) -> 1050.493 | BC112: =SUM(AZ43:BC43) -> 1173.3 | BD112: =SUM(BA43:BD43) -> 1207.3 | BE112: =SUM(BB43:BE43) -> 1081.8 | BF112: =SUM(BC43:BF43) -> 1098.4
B113: Capex | C113: =-C89 -> 190.77 | D113: =-D89 -> 450.11 | E113: =-E89 -> 379.314 | F113: =-F89 -> 361.872 | G113: =-G89 -> 416.614 | H113: =-H89 -> 880.141 | I113: =-I89 -> 1138.223 | J113: =-J89 -> 1138.223 | ... O113: =-O89 -> 1200.7 | R113: =-SUM(Q89,R89) -> 361.872 | S113: =-SUM(R89,S89) -> 397.42 | T113: =-SUM(S89,T89) -> 416.614 | U113: =-SUM(T89,U89) -> 595.467 | V113: =-SUM(U89,V89) -> 880.141 | W113: =-SUM(V89,W89) -> 1018.027 | X113: =-SUM(W89,X89) -> 1138.223 | Y113: =-SUM(X89,Y89) -> 1085.168 | Z113: =-SUM(Y89,Z89) -> 1130.3 | AA113: =-SUM(Y89,AA89) -> 894.9 | AB113: =-SUM(AA89,AB89) -> 1153.7 | AC113: =-SUM(AB89,AC89) -> 1162.3 | AD113: =-SUM(AC89,AD89) -> 1195 | AG113: =F113 -> 361.872 | AK113: =G113 -> 416.614 | AO113: =H113 -> 880.141 | AS113: =I113 -> 1138.223 | AW113: =K113 -> 1130.3 | AX113: =J113 -> 1138.223 | AY113: =K113 -> 1130.3 | AZ113: =L113 -> 1130.3 | BA113: =M113 -> 1153.7 | BB113: =-SUM(AY89:BB89) -> 1136.8 | BC113: =-SUM(AZ89:BC89) -> 1162.3 | BD113: =-SUM(BA89:BD89) -> 1291.1 | BE113: =-SUM(BB89:BE89) -> 1195 | BF113: =-SUM(BC89:BF89) -> 1200.7
B114: Free cash flow | C114: =+C91 -> -186.258 | D114: =+D91 -> -290.752 | E114: =+E91 -> -272.265 | F114: =+F91 -> -239.221 | G114: =+G91 -> -257.263 | H114: =+H91 -> -1264.337 | I114: =+I91 -> -1132.079 | J114: =+J91 -> -1132.137 | ... O114: =+O91 -> -1169.6 | R114: =SUM(Q91,R91) -> -239.221 | S114: =SUM(R91,S91) -> -195.473 | T114: =SUM(S91,T91) -> -257.263 | U114: =SUM(T91,U91) -> -506.899 | V114: =SUM(U91,V91) -> -1264.337 | W114: =SUM(V91,W91) -> -1429.004 | X114: =SUM(W91,X91) -> -1132.079 | Y114: =SUM(X91,Y91) -> -1034.833 | Z114: =SUM(Y91,Z91) -> -901.2 | AA114: =SUM(Y91,AA91) -> -814.9 | AB114: =SUM(AA91,AB91) -> -957.9 | AC114: =SUM(AB91,AC91) -> -898.3 | AD114: =SUM(AC91,AD91) -> -1080.7 | AG114: =F114 -> -239.221 | AK114: =G114 -> -257.263 | AO114: =H114 -> -1264.337 | AS114: =I114 -> -1132.079 | AW114: =K114 -> -901.2 | AX114: =J114 -> -1132.137 | AY114: =K114 -> -901.2 | AZ114: =L114 -> -886.3 | BA114: =M114 -> -957.9 | BB114: =SUM(AY91:BB91) -> -975.7 | BC114: =SUM(AZ91:BC91) -> -898.3 | BD114: =SUM(BA91:BD91) -> -941.7 | BE114: =SUM(BB91:BE91) -> -1080.7 | BF114: =SUM(BC91:BF91) -> -1169.6
...

Sheet KPIs
B2: CTP Group | C2: Annual | D2: Annual | E2: Annual | F2: Annual | G2: Annual | H2: Annual | I2: Annual | J2: Annual | K2: Annual | L2: Annual | M2: LTM | O2: Half Yearly | P2: Half Yearly | Q2: Half Yearly | R2: Half Yearly | S2: Half Yearly | T2: Half Yearly | U2: Half Yearly | V2: Half Yearly | W2: Half Yearly | X2: Half Yearly | Y2: Half Yearly | Z2: Half Yearly | AA2: Half Yearly | AB2: Half Yearly | AD2: Quaterly | AE2: Quaterly | AF2: Quaterly | AG2: Quaterly | AH2: Quaterly | AI2: Quaterly | AJ2: Quaterly | AK2: Quaterly | AL2: Quaterly | AM2: Quaterly | AN2: Quaterly | AO2: Quaterly | AP2: Quaterly | AQ2: Quaterly | AR2: Quaterly | AS2: Quaterly | AT2: Quaterly | AU2: Quaterly | AV2: Quaterly | AW2: Quaterly | AX2: Quaterly | AY2: Quaterly | AZ2: Quaterly | BA2: Quaterly | BB2: Quaterly | BC2: Quaterly | BD2: Quaterly
B3: (EUR millions) | C3: 42735 | D3: 43100 | E3: 43465 | F3: 43830 | G3: 44196 | H3: 44561 | I3: 44926 | J3: 45291 | K3: 45657 | L3: 46022 | M3: =BD3 -> 46111 | O3: 43646 | P3: 43829 | Q3: 44012 | R3: 44195 | S3: 44377 | T3: 44560 | U3: 44742 | V3: 44925 | W3: 45107 | X3: 45290 | Y3: 45473 | Z3: 45656 | AA3: 45838 | AB3: 46021 | AD3: 43738 | AE3: 43830 | AF3: 43920 | AG3: 44012 | AH3: 44104 | AI3: 44196 | AJ3: 44285 | AK3: 44377 | AL3: 44469 | AM3: 44561 | AN3: 44650 | AO3: 44742 | AP3: 44834 | AQ3: 44926 | AR3: 45015 | AS3: 45107 | AT3: 45199 | AU3: 45291 | AV3: 45381 | AW3: 45473 | AX3: 45565 | AY3: 45657 | AZ3: 45746 | BA3: 45838 | BB3: 45930 | BC3: 46022 | BD3: 46111
C4: Act | D4: Act | E4: Act | F4: Act | G4: Act | H4: Act | I4: Act | J4: Act | K4: Act | L4: Act | M4: Act | O4: Act | P4: Act | Q4: Act | R4: Act | S4: Act | T4: Act | U4: Act | V4: Act | W4: Act | X4: Act | Y4: Act | Z4: Act | AA4: Act | AB4: Act | AD4: Act | AE4: Act | AF4: Act | AG4: Act | AH4: Act | AI4: Act | AJ4: Act | AK4: Act | AL4: Act | AM4: Act | AN4: Act | AO4: Act | AP4: Act | AQ4: Act | AR4: Act | AS4: Act | AT4: Act | AU4: Act | AV4: Act | AW4: Act | AX4: Act | AY4: Act | AZ4: Act | BA4: Act | BB4: Act | BC4: Act | BD4: Act
C5: FY | D5: FY | E5: FY | F5: FY | G5: FY | H5: FY | I5: FY | J5: FY | K5: FY | L5: FY | M5: LTM | O5: 1H19 | P5: 2H19 | Q5: 1H20 | R5: 2H20 | S5: 1H21 | T5: 2H21 | U5: 1H22 | V5: 2H22 | W5: 1H23 | X5: 2H23 | Y5: 1H24 | Z5: 2H24 | AA5: 1H25 | AB5: 2H25 | AD5: 3Q19 | AE5: 4Q19 | AF5: 1Q20 | AG5: 2Q20 | AH5: 3Q20 | AI5: 4Q20 | AJ5: 1Q21 | AK5: 2Q21 | AL5: 3Q21 | AM5: 4Q21 | AN5: 1Q22 | AO5: 2Q22 | AP5: 3Q22 | AQ5: 4Q22 | AR5: 1Q23 | AS5: 2Q23 | AT5: 3Q23 | AU5: 4Q23 | AV5: 1Q24 | AW5: 2Q23 | AX5: 3Q24 | AY5: 4Q24 | AZ5: 1Q25 | BA5: 2Q24 | BB5: 3Q25 | BC5: 4Q25 | BD5: 1Q26
B8: Net rental Income by segment
B9: Czech Republic | E9: 170.029 | F9: 164.654 | G9: 183.356 | H9: 199.473 | I9: 215.536 | J9: 247.1 | K9: 273.3 | L9: 288.5 | O9: 78.898 | P9: =+F9-O9 -> 85.756 | Q9: 89.906 | R9: =+G9-Q9 -> 93.45 | S9: 100.465 | T9: =+H9-S9 -> 99.008 | U9: 102.726 | V9: =+I9-U9 -> 112.81 | W9: 133.9 | X9: =+J9-W9 -> 113.2 | Y9: 136.2 | Z9: =+K9-Y9 -> 137.1 | AA9: 142.5 | AB9: =+L9-AA9 -> 146 | AF9: =0.68*66.814 -> 45.43352 | AG9: =Q9-AF9 -> 44.47248 | AJ9: =0.64*78.087 -> 49.97568 | AK9: =S9-AJ9 -> 50.48932 | AL9: =(0.61*239.869)-S9 -> 45.85509 | AM9: =H9-AL9-AK9-AJ9 -> 53.15291
B10: Romania | E10: 33.31 | F10: 36.416 | G10: 47.338 | H10: 61.769 | I10: 85.73 | J10: 101.1 | K10: 121.7 | L10: 142.7 | O10: 16.231 | P10: =+F10-O10 -> 20.185 | Q10: 23.512 | R10: =+G10-Q10 -> 23.826 | S10: 30.482 | T10: =+H10-S10 -> 31.287 | U10: 40.488 | V10: =+I10-U10 -> 45.242 | W10: 48.5 | X10: =+J10-W10 -> 52.6 | Y10: 58.1 | Z10: =+K10-Y10 -> 63.6 | AA10: 69.3 | AB10: =+L10-AA10 -> 73.4 | AF10: =0.16*66.814 -> 10.69024 | AG10: =Q10-AF10 -> 12.82176 | AJ10: =0.19*78.087 -> 14.83653 | AK10: =S10-AJ10 -> 15.64547 | AL10: =(0.19*239.869)-S10 -> 15.09311 | AM10: =H10-AL10-AK10-AJ10 -> 16.19389
B11: Hungary | E11: 7.307 | F11: 17.93 | G11: 22.292 | H11: 29.043 | I11: 48.228 | J11: 56.7 | K11: 61.8 | L11: 78.1 | O11: 7.402 | P11: =+F11-O11 -> 10.528 | Q11: 9.766 | R11: =+G11-Q11 -> 12.526 | S11: 11.782 | T11: =+H11-S11 -> 17.261 | U11: 22.825 | V11: =+I11-U11 -> 25.403 | W11: 29 | X11: =+J11-W11 -> 27.7 | Y11: 30.8 | Z11: =+K11-Y11 -> 31 | AA11: 39 | AB11: =+L11-AA11 -> 39.1 | AF11: =0.06*66.814 -> 4.00884 | AG11: =Q11-AF11 -> 5.75716 | AJ11: =0.07*78.087 -> 5.46609 | AK11: =S11-AJ11 -> 6.31591 | AL11: =(0.09*239.869)-S11 -> 9.80621 | AM11: =H11-AL11-AK11-AJ11 -> 7.45479
B12: Slovakia | H12: 24.383 | I12: 36.351 | J12: 42.5 | K12: 53.5 | L12: 66.4 | S12: 12.764 | T12: =+H12-S12 -> 11.619 | U12: 17.216 | V12: =+I12-U12 -> 19.135 | W12: 20.4 | X12: =+J12-W12 -> 22.1 | Y12: 25.7 | Z12: =+K12-Y12 -> 27.8 | AA12: 32.5 | AB12: =+L12-AA12 -> 33.9 | AK12: =S12-AJ12 -> 12.764 | AL12: =(0.08*239.869)-S12 -> 6.42552 | AM12: =H12-AL12-AK12-AJ12 -> 5.19348
B13: Netherland, Germany and Poland | E13: 21.505 | F13: 20.79 | G13: =21.376+6.644-0.337 -> 27.683 | H13: =11.84+0.659-0.115 -> 12.384 | I13: =22.041+41.919+2.761 -> 66.721 | J13: =32.2+6.5+57.9 -> 96.6 | K13: =7.7+70.7+11.6 -> 90 | L13: =8.8+60.3+31.7 -> 100.8 | O13: 10.032 | P13: =+F13-O13 -> 10.758 | Q13: 13.306 | R13: =+G13-Q13 -> 14.377 | S13: 4.91 | T13: =+H13-S13 -> 7.474 | U13: =7.307+1.035+20.102 -> 28.444 | V13: =+I13-U13 -> 38.277 | W13: =3.7+28.1+14.2-9.5 -> 36.5 | X13: =+J13-W13 -> 60.1 | Y13: =4+34.2+3.5+21.4 -> 63.1 | Z13: =+K13-Y13 -> 26.9 | AA13: =4.2+29.7+13.1+30 -> 77 | AB13: =+L13-AA13 -> 23.8 | AF13: =0.1*66.814 -> 6.6814 | AG13: =Q13-AF13 -> 6.6246 | AJ13: =0.1*78.087 -> 7.8087 | AK13: =S13-AJ13 -> -2.8987 | AL13: =(0.03*239.869)-S13 -> 2.28607 | AM13: =H13-AL13-AK13-AJ13 -> 5.18793
B14: Others | H14: -0.199 | I14: -0.432 | J14: -0.8 | K14: 46.6 | L14: 61.4 | S14: -0.096 | T14: =+H14-S14 -> -0.103 | U14: -0.194 | V14: =+I14-U14 -> -0.238 | W14: 2.6 | X14: =+J14-W14 -> -3.4 | Y14: 5.2 | Z14: =+K14-Y14 -> 41.4 | AA14: 0 | AB14: =+L14-AA14 -> 61.4 | AK14: =S14-AJ14 -> -0.096 | AM14: =H14-AL14-AK14-AJ14 -> -0.103
B15: Total | C15: =+SUM(C9:C13) -> 0 | D15: =+SUM(D9:D13) -> 0 | E15: =+SUM(E9:E13) -> 232.151 | F15: =+SUM(F9:F13) -> 239.79 | G15: =+SUM(G9:G13) -> 280.669 | H15: =+SUM(H9:H14) -> 326.853 | I15: =+SUM(I9:I14) -> 452.134 | J15: =+SUM(J9:J14) -> 543.2 | K15: =+SUM(K9:K14) -> 646.9 | L15: =+SUM(L9:L14) -> 737.9 | O15: =+SUM(O9:O13) -> 112.563 | P15: =+SUM(P9:P13) -> 127.227 | Q15: =+SUM(Q9:Q13) -> 136.49 | R15: =+SUM(R9:R13) -> 144.179 | S15: =+SUM(S9:S14) -> 160.307 | T15: =+SUM(T9:T14) -> 166.546 | U15: =+SUM(U9:U14) -> 211.505 | V15: =+SUM(V9:V14) -> 240.629 | W15: =+SUM(W9:W14) -> 270.9 | X15: =+SUM(X9:X14) -> 272.3 | Y15: =+SUM(Y9:Y14) -> 319.1 | Z15: =+SUM(Z9:Z14) -> 327.8 | ... AB15: =+SUM(AB9:AB14) -> 377.6 | AF15: =+SUM(AF9:AF13) -> 66.814 | AG15: =+SUM(AG9:AG13) -> 69.676 | AJ15: =+SUM(AJ9:AJ13) -> 78.087 | AK15: =+SUM(AK9:AK13) -> 82.316 | AL15: =+SUM(AL9:AL13) -> 79.466 | AM15: =SUM(AM9:AM14) -> 87.08
B16: check | E16: =+E15-Model!E10 -> 0 | F16: =+F15-Model!F10 -> 0 | G16: =+G15-Model!G10 -> 0 | H16: =+H15-Model!H10 -> 0 | I16: =+I15-Model!J10 -> 0 | J16: =+J15-Model!K10 -> 0 | K16: =+K15-Model!M10 -> 0.1 | L16: =+L15-Model!N10 -> -0.1 | M16: =+M15-Model!O10 -> -758.3 | O16: =+O15-Model!Q10 -> 0 | P16: =+P15-Model!R10 -> 0 | Q16: =+Q15-Model!S10 -> 0 | R16: =+R15-Model!T10 -> 0 | S16: =+S15-Model!U10 -> 0 | T16: =+T15-Model!V10 -> 0 | U16: =+U15-Model!W10 -> 0 | V16: =+V15-Model!X10 -> 0 | W16: =+W15-Model!Y10 -> 1.1 | Y16: =+Y15-Model!AA10 -> 3.4 | Z16: =+Z15-Model!AB10 -> -3.3 | AA16: =+AA15-Model!AC10 -> -0.1 | AB16: =+AB15-Model!AD10 -> 0 | AF16: =+AF15-Model!AH10 -> -0.001 | AG16: =+AG15-Model!AI10 -> 0.001 | AJ16: =+AJ15-Model!AL10 -> -0.001 | AK16: =+AK15-Model!AM10 -> 0.097 | AL16: =+AL15-Model!AN10 -> -0.096 | AM16: =+AM15-Model!AO10 -> 0.096
B18: Revenue (% Share)
B19: Czech Republic | E19: =+E9/E$15 -> 0.73240692 | F19: =+F9/F$15 -> 0.68665916 | G19: =+G9/G$15 -> 0.65328198 | H19: =+H9/H$15 -> 0.61028352 | I19: =+I9/I$15 -> 0.47670823 | J19: =+J9/J$15 -> 0.45489691 | K19: =+K9/K$15 -> 0.42247643 | L19: =+L9/L$15 -> 0.39097439 | M19: =+M9/M$15 -> #DIV/0! | O19: =+O9/O$15 -> 0.70092304 | P19: =+P9/P$15 -> 0.67403932 | Q19: =+Q9/Q$15 -> 0.65870027 | R19: =+R9/R$15 -> 0.64815264 | S19: =+S9/S$15 -> 0.62670376 | T19: =+T9/T$15 -> 0.5944784 | U19: =+U9/U$15 -> 0.48569065 | V19: =+V9/V$15 -> 0.46881299 | ... AB19: =+AB9/AB$15 -> 0.38665254 | AF19: =+AF9/AF$15 -> 0.68 | AG19: =+AG9/AG$15 -> 0.63827545 | AJ19: =+AJ9/AJ$15 -> 0.64 | AK19: =+AK9/AK$15 -> 0.61335974 | AL19: =+AL9/AL$15 -> 0.57704037 | AM19: =+AM9/AM$15 -> 0.61039171
B20: Romania | E20: =+E10/E$15 -> 0.1434842 | F20: =+F10/F$15 -> 0.15186622 | G20: =+G10/G$15 -> 0.16866131 | H20: =+H10/H$15 -> 0.18898098 | I20: =+I10/I$15 -> 0.18961193 | J20: =+J10/J$15 -> 0.18611929 | K20: =+K10/K$15 -> 0.188128 | L20: =+L10/L$15 -> 0.19338664 | M20: =+M10/M$15 -> #DIV/0! | O20: =+O10/O$15 -> 0.14419481 | P20: =+P10/P$15 -> 0.15865343 | Q20: =+Q10/Q$15 -> 0.1722617 | R20: =+R10/R$15 -> 0.16525291 | S20: =+S10/S$15 -> 0.19014765 | T20: =+T10/T$15 -> 0.18785801 | U20: =+U10/U$15 -> 0.1914281 | V20: =+V10/V$15 -> 0.18801558 | ... AB20: =+AB10/AB$15 -> 0.19438559 | AF20: =+AF10/AF$15 -> 0.16 | AG20: =+AG10/AG$15 -> 0.18401975 | AJ20: =+AJ10/AJ$15 -> 0.19 | AK20: =+AK10/AK$15 -> 0.19006597 | AL20: =+AL10/AL$15 -> 0.18993167 | AM20: =+AM10/AM$15 -> 0.18596566
B21: Hungary | E21: =+E11/E$15 -> 0.031475204 | F21: =+F11/F$15 -> 0.07477376 | G21: =+G11/G$15 -> 0.079424518 | H21: =+H11/H$15 -> 0.088856458 | I21: =+I11/I$15 -> 0.10666749 | J21: =+J11/J$15 -> 0.10438144 | K21: =+K11/K$15 -> 0.09553254 | L21: =+L11/L$15 -> 0.1058409 | M21: =+M11/M$15 -> #DIV/0! | O21: =+O11/O$15 -> 0.065758731 | P21: =+P11/P$15 -> 0.082749731 | Q21: =+Q11/Q$15 -> 0.071551029 | R21: =+R11/R$15 -> 0.086878117 | S21: =+S11/S$15 -> 0.073496479 | T21: =+T11/T$15 -> 0.10364104 | U21: =+U11/U$15 -> 0.10791707 | V21: =+V11/V$15 -> 0.10556915 | ... AB21: =+AB11/AB$15 -> 0.10354873 | AF21: =+AF11/AF$15 -> 0.06 | AG21: =+AG11/AG$15 -> 0.082627591 | AJ21: =+AJ11/AJ$15 -> 0.07 | AK21: =+AK11/AK$15 -> 0.076727611 | AL21: =+AL11/AL$15 -> 0.12340133 | AM21: =+AM11/AM$15 -> 0.085608521
B22: Slovakia | H22: =+H12/H$15 -> 0.074599285 | I22: =+I12/I$15 -> 0.080398731 | J22: =+J12/J$15 -> 0.078240059 | K22: =+K12/K$15 -> 0.082702118 | L22: =+L12/L$15 -> 0.089985093 | M22: =+M12/M$15 -> #DIV/0! | S22: =+S12/S$15 -> 0.079622225 | T22: =+T12/T$15 -> 0.06976451 | U22: =+U12/U$15 -> 0.081397603 | V22: =+V12/V$15 -> 0.079520756 | W22: =+W12/W$15 -> 0.07530454 | X22: =+X12/X$15 -> 0.081160485 | Y22: =+Y12/Y$15 -> 0.080539016 | Z22: =+Z12/Z$15 -> 0.08480781 | ... AB22: =+AB12/AB$15 -> 0.089777542 | AK22: =+AK12/AK$15 -> 0.15506098 | AL22: =+AL12/AL$15 -> 0.080858732 | AM22: =+AM12/AM$15 -> 0.059640331
B23: Netherland, Germany and Poland | E23: =+E13/E$15 -> 0.092633674 | F23: =+F13/F$15 -> 0.086700863 | G23: =+G13/G$15 -> 0.098632197 | H23: =+H13/H$15 -> 0.037888592 | I23: =+I13/I$15 -> 0.14756908 | J23: =+J13/J$15 -> 0.17783505 | K23: =+K13/K$15 -> 0.13912506 | L23: =+L13/L$15 -> 0.13660388 | M23: =+M13/M$15 -> #DIV/0! | O23: =+O13/O$15 -> 0.089123424 | P23: =+P13/P$15 -> 0.084557523 | Q23: =+Q13/Q$15 -> 0.097486995 | R23: =+R13/R$15 -> 0.099716325 | S23: =+S13/S$15 -> 0.030628731 | T23: =+T13/T$15 -> 0.044876491 | U23: =+U13/U$15 -> 0.13448382 | V23: =+V13/V$15 -> 0.1590706 | ... AB23: =+AB13/AB$15 -> 0.063029661 | AF23: =+AF13/AF$15 -> 0.1 | AG23: =+AG13/AG$15 -> 0.095077215 | AJ23: =+AJ13/AJ$15 -> 0.1 | AK23: =+AK13/AK$15 -> -0.035214296 | AL23: =+AL13/AL$15 -> 0.028767901 | AM23: =+AM13/AM$15 -> 0.059576596
B24: Others | H24: =+H14/H$15 -> -0.00060883639 | I24: =+I14/I$15 -> -0.00095546895 | J24: =+J14/J$15 -> -0.0014727541 | K24: =+K14/K$15 -> 0.072035863 | L24: =+L14/L$15 -> 0.083209107 | M24: =+M14/M$15 -> #DIV/0! | S24: =+S14/S$15 -> -0.00059885095 | T24: =+T14/T$15 -> -0.00061844776 | U24: =+U14/U$15 -> -0.000917236 | V24: =+V14/V$15 -> -0.00098907447 | W24: =+W14/W$15 -> 0.0095976375 | X24: =+X14/X$15 -> -0.012486228 | Y24: =+Y14/Y$15 -> 0.016295832 | Z24: =+Z14/Z$15 -> 0.12629652 | ... AB24: =+AB14/AB$15 -> 0.16260593 | AK24: =+AK14/AK$15 -> -0.0011662374 | AL24: =+AL14/AL$15 -> 0 | AM24: =+AM14/AM$15 -> -0.0011828204
B25: Total | E25: =+SUM(E19:E23) -> 1 | F25: =+SUM(F19:F23) -> 1 | G25: =+SUM(G19:G23) -> 1 | H25: =+SUM(H19:H24) -> 1 | I25: =+SUM(I19:I24) -> 1 | J25: =+SUM(J19:J24) -> 1 | K25: =+SUM(K19:K24) -> 1 | L25: =+SUM(L19:L24) -> 1 | M25: =+SUM(M19:M24) -> #DIV/0! | O25: =+SUM(O19:O23) -> 1 | P25: =+SUM(P19:P23) -> 1 | Q25: =+SUM(Q19:Q23) -> 1 | R25: =+SUM(R19:R23) -> 1 | S25: =+SUM(S19:S24) -> 1 | T25: =+SUM(T19:T24) -> 1 | U25: =+SUM(U19:U24) -> 1 | V25: =+SUM(V19:V24) -> 1 | W25: =+SUM(W19:W24) -> 1 | X25: =+SUM(X19:X24) -> 1 | Y25: =+SUM(Y19:Y24) -> 1 | Z25: =+SUM(Z19:Z24) -> 1 | ... AB25: =+SUM(AB19:AB24) -> 1 | AF25: =+SUM(AF19:AF23) -> 1 | AG25: =+SUM(AG19:AG23) -> 1 | AJ25: =+SUM(AJ19:AJ23) -> 1 | AK25: =+SUM(AK19:AK24) -> 0.99883376 | AL25: =+SUM(AL19:AL24) -> 1 | AM25: =+SUM(AM19:AM24) -> 1
B27: Revenue (YoY % Growth)
B28: Czech Republic | F28: =F9/E9-1 -> -0.031612254 | G28: =G9/F9-1 -> 0.11358364 | H28: =H9/G9-1 -> 0.087900041 | I28: =I9/H9-1 -> 0.080527189 | J28: =J9/I9-1 -> 0.14644421 | K28: =K9/J9-1 -> 0.10602995 | L28: =L9/K9-1 -> 0.055616539 | Q28: =Q9/O9-1 -> 0.13952191 | R28: =R9/P9-1 -> 0.08971967 | S28: =S9/Q9-1 -> 0.11744489 | T28: =T9/R9-1 -> 0.059475655 | U28: =U9/S9-1 -> 0.02250535 | V28: =V9/T9-1 -> 0.13940288 | W28: =W9/U9-1 -> 0.30346748 | X28: =X9/V9-1 -> 0.0034571403 | ... AB28: =AB9/Z9-1 -> 0.06491612
B29: Romania | F29: =F10/E10-1 -> 0.093245272 | G29: =G10/F10-1 -> 0.29992311 | H29: =H10/G10-1 -> 0.30485023 | I29: =I10/H10-1 -> 0.38791303 | J29: =J10/I10-1 -> 0.1792838 | K29: =K10/J10-1 -> 0.20375865 | L29: =L10/K10-1 -> 0.17255546 | Q29: =Q10/O10-1 -> 0.44858604 | R29: =R10/P10-1 -> 0.18038147 | S29: =S10/Q10-1 -> 0.29644437 | T29: =T10/R10-1 -> 0.3131453 | U29: =U10/S10-1 -> 0.3282593 | V29: =V10/T10-1 -> 0.4460319 | W29: =W10/U10-1 -> 0.19788579 | X29: =X10/V10-1 -> 0.16263649 | ... AB29: =AB10/Z10-1 -> 0.15408805
B30: Hungary | F30: =F11/E11-1 -> 1.4538114 | G30: =G11/F11-1 -> 0.24327942 | H30: =H11/G11-1 -> 0.30284407 | I30: =I11/H11-1 -> 0.66057225 | J30: =J11/I11-1 -> 0.17566559 | K30: =K11/J11-1 -> 0.08994709 | L30: =L11/K11-1 -> 0.26375405 | Q30: =Q11/O11-1 -> 0.31937314 | R30: =R11/P11-1 -> 0.18977964 | S30: =S11/Q11-1 -> 0.20643047 | T30: =T11/R11-1 -> 0.37801373 | U30: =U11/S11-1 -> 0.9372772 | V30: =V11/T11-1 -> 0.47169921 | W30: =W11/U11-1 -> 0.27053669 | X30: =X11/V11-1 -> 0.090422391 | ... AB30: =AB11/Z11-1 -> 0.26129032
B31: Slovakia | F31: =F12/E12-1 -> #DIV/0! | G31: =G12/F12-1 -> #DIV/0! | H31: =H12/G12-1 -> #DIV/0! | I31: =I12/H12-1 -> 0.49083378 | J31: =J12/I12-1 -> 0.16915628 | K31: =K12/J12-1 -> 0.25882353 | L31: =L12/K12-1 -> 0.2411215 | Q31: =Q12/O12-1 -> #DIV/0! | R31: =R12/P12-1 -> #DIV/0! | S31: =S12/Q12-1 -> #DIV/0! | T31: =T12/R12-1 -> #DIV/0! | U31: =U12/S12-1 -> 0.34879348 | V31: =V12/T12-1 -> 0.6468715 | W31: =W12/U12-1 -> 0.18494424 | X31: =X12/V12-1 -> 0.15495166 | ... AB31: =AB12/Z12-1 -> 0.21942446
B32: Netherland, Germany and Poland | F32: =F13/E13-1 -> -0.033248082 | G32: =G13/F13-1 -> 0.33155363 | H32: =H13/G13-1 -> -0.55264964 | I32: =I13/H13-1 -> 4.3876776 | J32: =J13/I13-1 -> 0.44782003 | K32: =K13/J13-1 -> -0.068322981 | L32: =L13/K13-1 -> 0.12 | Q32: =Q13/O13-1 -> 0.32635566 | R32: =R13/P13-1 -> 0.33640082 | S32: =S13/Q13-1 -> -0.63099354 | T32: =T13/R13-1 -> -0.48014189 | U32: =U13/S13-1 -> 4.7930754 | V32: =V13/T13-1 -> 4.121354 | W32: =W13/U13-1 -> 0.28322318 | X32: =X13/V13-1 -> 0.5701335 | ... AB32: =AB13/Z13-1 -> -0.11524164
B33: Others | F33: =F14/E14-1 -> #DIV/0! | G33: =G14/F14-1 -> #DIV/0! | H33: =H14/G14-1 -> #DIV/0! | I33: =I14/H14-1 -> 1.1708543 | J33: =J14/I14-1 -> 0.85185185 | K33: =K14/J14-1 -> -59.25 | L33: =L14/K14-1 -> 0.31759657 | Q33: =Q14/O14-1 -> #DIV/0! | R33: =R14/P14-1 -> #DIV/0! | S33: =S14/Q14-1 -> #DIV/0! | T33: =T14/R14-1 -> #DIV/0! | U33: =U14/S14-1 -> 1.0208333 | V33: =V14/T14-1 -> 1.3106796 | W33: =W14/U14-1 -> -14.402062 | X33: =X14/V14-1 -> 13.285714 | ... AB33: =AB14/Z14-1 -> 0.48309179
B34: Total | F34: =F15/E15-1 -> 0.032905307 | G34: =G15/F15-1 -> 0.17047834 | H34: =H15/G15-1 -> 0.1645497 | I34: =I15/H15-1 -> 0.38329463 | J34: =J15/I15-1 -> 0.20141374 | K34: =K15/J15-1 -> 0.19090574 | L34: =L15/K15-1 -> 0.14067089 | Q34: =Q15/O15-1 -> 0.21256541 | R34: =R15/P15-1 -> 0.13324216 | S34: =S15/Q15-1 -> 0.1744963 | T34: =T15/R15-1 -> 0.15513355 | U34: =U15/S15-1 -> 0.3193747 | V34: =V15/T15-1 -> 0.44482005 | W34: =W15/U15-1 -> 0.28082078 | X34: =X15/V15-1 -> 0.13161755 | ... AB34: =AB15/Z15-1 -> 0.1519219
B37: Net valuation result on IP
B38: Czech Republic | E38: 153.382 | F38: 257.983 | G38: 62.577 | H38: 733.943 | I38: 394.372 | J38: 260.2 | K38: 340.7 | L38: 297.6 | O38: 69.839 | P38: =+F38-O38 -> 188.144 | Q38: -6.35 | R38: =+G38-Q38 -> 68.927 | S38: 74.964 | T38: =+H38-S38 -> 658.979 | U38: 341.868 | V38: =+I38-U38 -> 52.504 | W38: 120.5 | X38: =+J38-W38 -> 139.7 | Y38: 224.8 | Z38: =+K38-Y38 -> 115.9 | AA38: 166.8 | AB38: =+L38-AA38 -> 130.8
B39: Romania | E39: 40.41 | F39: 67.064 | G39: 22.681 | H39: 110.458 | I39: 67.238 | J39: 149.6 | K39: 207.8 | L39: 226.3 | O39: 46.687 | P39: =+F39-O39 -> 20.377 | Q39: 20.721 | R39: =+G39-Q39 -> 1.96 | S39: 13.324 | T39: =+H39-S39 -> 97.134 | U39: 44.768 | V39: =+I39-U39 -> 22.47 | W39: 106.5 | X39: =+J39-W39 -> 43.1 | Y39: 99.8 | Z39: =+K39-Y39 -> 108 | AA39: 68.9 | AB39: =+L39-AA39 -> 157.4
B40: Hungary | E40: 20.498 | F40: 48.525 | G40: 53.092 | H40: 123.31 | I40: 46.434 | J40: 3.4 | K40: 69.9 | L40: 53.6 | O40: 22.415 | P40: =+F40-O40 -> 26.11 | Q40: 19.417 | R40: =+G40-Q40 -> 33.675 | S40: 41.654 | T40: =+H40-S40 -> 81.656 | U40: 33.285 | V40: =+I40-U40 -> 13.149 | W40: 18.6 | X40: =+J40-W40 -> -15.2 | Y40: 4.7 | Z40: =+K40-Y40 -> 65.2 | AA40: 30.5 | AB40: =+L40-AA40 -> 23.1
B41: Slovakia | H41: 100.271 | I41: 18.412 | J41: 105.3 | K41: 116.8 | L41: 124.6 | S41: 11.622 | T41: =+H41-S41 -> 88.649 | U41: 43.336 | V41: =+I41-U41 -> -24.924 | W41: 44.9 | X41: =+J41-W41 -> 60.4 | Y41: 13.5 | Z41: =+K41-Y41 -> 103.3 | AA41: 54.3 | AB41: =+L41-AA41 -> 70.3
B42: Netherland, Germany and Poland | E42: 23.728 | F42: =27.106+6.097 -> 33.203 | G42: =5.037+8.775 -> 13.812 | H42: =43.835-8.36-2.886 -> 32.589 | I42: =186.05+14.761-29.97 -> 170.841 | J42: =17.8+123.4+219 -> 360.2 | K42: =-4+121.8+57.3+31.2 -> 206.3 | L42: =-0.9+242.8+92.8+103.1 -> 437.8 | O42: 6.302 | P42: =+F42-O42 -> 26.901 | Q42: -3.828 | R42: =+G42-Q42 -> 17.64 | S42: 4.179 | T42: =+H42-S42 -> 28.41 | U42: =22.09-39.269+52.938 -> 35.759 | V42: =+I42-U42 -> 135.082 | W42: =9.7+22.2+94.8 -> 126.7 | X42: =+J42-W42 -> 233.5 | Y42: =-6.6+37.1+55.4+7.9 -> 93.8 | Z42: =+K42-Y42 -> 112.5 | AA42: =-3.2+182+42.1+56.6 -> 277.5 | AB42: =+L42-AA42 -> 160.3
B43: Others | H43: 0 | I43: 0 | J43: 0 | K43: 0 | L43: 0 | S43: 0 | T43: =+H43-S43 -> 0 | U43: 0 | V43: =+I43-U43 -> 0 | X43: =+J43-W43 -> 0 | Z43: =+K43-Y43 -> 0 | AB43: =+L43-AA43 -> 0
B44: Total | C44: =+SUM(C38:C42) -> 0 | D44: =+SUM(D38:D42) -> 0 | E44: =+SUM(E38:E42) -> 238.018 | F44: =+SUM(F38:F42) -> 406.775 | G44: =+SUM(G38:G42) -> 152.162 | H44: =+SUM(H38:H43) -> 1100.571 | I44: =+SUM(I38:I43) -> 697.297 | J44: =+SUM(J38:J43) -> 878.7 | K44: =+SUM(K38:K43) -> 941.5 | L44: =+SUM(L38:L43) -> 1139.9 | M44: =+SUM(M38:M43) -> 0 | O44: =+SUM(O38:O42) -> 145.243 | P44: =+SUM(P38:P42) -> 261.532 | Q44: =+SUM(Q38:Q42) -> 29.96 | R44: =+SUM(R38:R42) -> 122.202 | S44: =+SUM(S38:S43) -> 145.743 | T44: =+SUM(T38:T43) -> 954.828 | U44: =+SUM(U38:U43) -> 499.016 | V44: =+SUM(V38:V43) -> 198.281 | W44: =+SUM(W38:W43) -> 417.2 | X44: =+SUM(X38:X43) -> 461.5 | Y44: =+SUM(Y38:Y43) -> 436.6 | Z44: =+SUM(Z38:Z43) -> 504.9 | ... AB44: =+SUM(AB38:AB43) -> 541.9
B45: check | E45: =+E44-Model!E22 -> 0.001 | F45: =+F44-Model!F22 -> 0 | G45: =+G44-Model!G22 -> 0 | H45: =+H44-Model!H22 -> 0 | I45: =+I44-Model!J22 -> -0.003 | J45: =+J44-Model!K22 -> 0 | K45: =+K44-Model!M22 -> 0 | L45: =+L44-Model!N22 -> 0 | M45: =+M44-Model!O22 -> -1147.8 | O45: =+O44-Model!Q22 -> 0 | P45: =+P44-Model!R22 -> 0 | Q45: =+Q44-Model!S22 -> 0 | R45: =+R44-Model!T22 -> 0 | S45: =+S44-Model!U22 -> 0 | T45: =+T44-Model!V22 -> 0 | U45: =+U44-Model!W22 -> 0 | V45: =+V44-Model!X22 -> -26.283 | ... AB45: =+AB44-Model!AD22 -> -0.1
B47: Net valuation result on IP (% Share)
B48: Czech Republic | E48: =+E38/E$44 -> 0.64441345 | F48: =+F38/F$44 -> 0.63421548 | G48: =+G38/G$44 -> 0.41125248 | H48: =+H38/H$44 -> 0.66687474 | I48: =+I38/I$44 -> 0.56557249 | J48: =+J38/J$44 -> 0.29611927 | K48: =+K38/K$44 -> 0.36186936 | L48: =+L38/L$44 -> 0.26107553 | M48: =+M38/M$44 -> #DIV/0! | O48: =+O38/O$44 -> 0.48084245 | P48: =+P38/P$44 -> 0.71939189 | Q48: =+Q38/Q$44 -> -0.21194927 | R48: =+R38/R$44 -> 0.56404151 | S48: =+S38/S$44 -> 0.51435746 | T48: =+T38/T$44 -> 0.69015467 | U48: =+U38/U$44 -> 0.68508425 | V48: =+V38/V$44 -> 0.26479592 | ... AB48: =+AB38/AB$44 -> 0.24137295
B49: Romania | E49: =+E39/E$44 -> 0.16977708 | F49: =+F39/F$44 -> 0.16486756 | G49: =+G39/G$44 -> 0.14905824 | H49: =+H39/H$44 -> 0.10036427 | I49: =+I39/I$44 -> 0.09642663 | J49: =+J39/J$44 -> 0.17025151 | K49: =+K39/K$44 -> 0.22071163 | L49: =+L39/L$44 -> 0.19852619 | M49: =+M39/M$44 -> #DIV/0! | O49: =+O39/O$44 -> 0.32144062 | P49: =+P39/P$44 -> 0.077913984 | Q49: =+Q39/Q$44 -> 0.69162216 | R49: =+R39/R$44 -> 0.016039017 | S49: =+S39/S$44 -> 0.0914212 | T49: =+T39/T$44 -> 0.10172932 | U49: =+U39/U$44 -> 0.089712554 | V49: =+V39/V$44 -> 0.11332402 | ... AB49: =+AB39/AB$44 -> 0.29045949
B50: Hungary | E50: =+E40/E$44 -> 0.086119537 | F50: =+F40/F$44 -> 0.11929199 | G50: =+G40/G$44 -> 0.3489176 | H50: =+H40/H$44 -> 0.11204184 | I50: =+I40/I$44 -> 0.066591424 | J50: =+J40/J$44 -> 0.0038693525 | K50: =+K40/K$44 -> 0.074243229 | L50: =+L40/L$44 -> 0.047021669 | M50: =+M40/M$44 -> #DIV/0! | O50: =+O40/O$44 -> 0.15432758 | P50: =+P40/P$44 -> 0.099834819 | Q50: =+Q40/Q$44 -> 0.64809746 | R50: =+R40/R$44 -> 0.27556832 | S50: =+S40/S$44 -> 0.28580446 | T50: =+T40/T$44 -> 0.085519067 | U50: =+U40/U$44 -> 0.066701268 | V50: =+V40/V$44 -> 0.066314977 | ... AB50: =+AB40/AB$44 -> 0.042627791
B51: Slovakia | H51: =+H41/H$44 -> 0.091108161 | I51: =+I41/I$44 -> 0.026404817 | J51: =+J41/J$44 -> 0.11983612 | K51: =+K41/K$44 -> 0.12405736 | L51: =+L41/L$44 -> 0.10930783 | M51: =+M41/M$44 -> #DIV/0! | S51: =+S41/S$44 -> 0.079743109 | T51: =+T41/T$44 -> 0.092842899 | U51: =+U41/U$44 -> 0.086842907 | V51: =+V41/V$44 -> -0.12570039 | W51: =+W41/W$44 -> 0.10762224 | X51: =+X41/X$44 -> 0.13087757 | Y51: =+Y41/Y$44 -> 0.030920751 | Z51: =+Z41/Z$44 -> 0.20459497 | ... AB51: =+AB41/AB$44 -> 0.12972873
B52: Netherland, Germany and Poland | E52: =+E42/E$44 -> 0.099689939 | F52: =+F42/F$44 -> 0.081624977 | G52: =+G42/G$44 -> 0.090771678 | H52: =+H42/H$44 -> 0.029610993 | I52: =+I42/I$44 -> 0.24500464 | J52: =+J42/J$44 -> 0.40992375 | K52: =+K42/K$44 -> 0.21911843 | L52: =+L42/L$44 -> 0.38406878 | M52: =+M42/M$44 -> #DIV/0! | O52: =+O42/O$44 -> 0.043389354 | P52: =+P42/P$44 -> 0.10285931 | Q52: =+Q42/Q$44 -> -0.12777036 | R52: =+R42/R$44 -> 0.14435116 | S52: =+S42/S$44 -> 0.028673761 | T52: =+T42/T$44 -> 0.02975405 | U52: =+U42/U$44 -> 0.071659025 | V52: =+V42/V$44 -> 0.68126548 | ... AB52: =+AB42/AB$44 -> 0.29581104
B53: Others | H53: =+H43/H$44 -> 0 | I53: =+I43/I$44 -> 0 | J53: =+J43/J$44 -> 0 | K53: =+K43/K$44 -> 0 | L53: =+L43/L$44 -> 0 | M53: =+M43/M$44 -> #DIV/0! | S53: =+S43/S$44 -> 0 | T53: =+T43/T$44 -> 0 | U53: =+U43/U$44 -> 0 | V53: =+V43/V$44 -> 0 | W53: =+W43/W$44 -> 0 | X53: =+X43/X$44 -> 0 | Y53: =+Y43/Y$44 -> 0 | Z53: =+Z43/Z$44 -> 0 | ... AB53: =+AB43/AB$44 -> 0
B54: Total | E54: =+SUM(E48:E52) -> 1 | F54: =+SUM(F48:F52) -> 1 | G54: =+SUM(G48:G52) -> 1 | H54: =+SUM(H48:H53) -> 1 | I54: =+SUM(I48:I53) -> 1 | J54: =+SUM(J48:J53) -> 1 | K54: =+SUM(K48:K53) -> 1 | L54: =+SUM(L48:L53) -> 1 | M54: =+SUM(M48:M53) -> #DIV/0! | O54: =+SUM(O48:O52) -> 1 | P54: =+SUM(P48:P52) -> 1 | Q54: =+SUM(Q48:Q52) -> 1 | R54: =+SUM(R48:R52) -> 1 | S54: =+SUM(S48:S53) -> 1 | T54: =+SUM(T48:T53) -> 1 | U54: =+SUM(U48:U53) -> 1 | V54: =+SUM(V48:V53) -> 1 | W54: =+SUM(W48:W53) -> 1 | X54: =+SUM(X48:X53) -> 1 | Y54: =+SUM(Y48:Y53) -> 1 | Z54: =+SUM(Z48:Z53) -> 1 | ... AB54: =+SUM(AB48:AB53) -> 1
B56: Net valuation result on IP (YoY % Growth)
B57: Czech Republic | F57: =F38/E38-1 -> 0.68196399 | G57: =G38/F38-1 -> -0.75743751 | H57: =H38/G38-1 -> 10.728638 | I57: =I38/H38-1 -> -0.46266672 | J57: =J38/I38-1 -> -0.34021685 | K57: =K38/J38-1 -> 0.3093774 | L57: =L38/K38-1 -> -0.12650426 | Q57: =Q38/O38-1 -> -1.0909234 | R57: =R38/P38-1 -> -0.63364763 | S57: =S38/Q38-1 -> -12.805354 | T57: =T38/R38-1 -> 8.5605351 | U57: =U38/S38-1 -> 3.560429 | V57: =V38/T38-1 -> -0.92032523 | W57: =W38/U38-1 -> -0.64752478 | X57: =X38/V38-1 -> 1.6607497 | ... AB57: =AB38/Z38-1 -> 0.1285591
B58: Romania | F58: =F39/E39-1 -> 0.65958921 | G58: =G39/F39-1 -> -0.66180067 | H58: =H39/G39-1 -> 3.8700675 | I58: =I39/H39-1 -> -0.39127994 | J58: =J39/I39-1 -> 1.2249323 | K58: =K39/J39-1 -> 0.38903743 | L58: =L39/K39-1 -> 0.089027911 | Q58: =Q39/O39-1 -> -0.55617195 | R58: =R39/P39-1 -> -0.90381312 | S58: =S39/Q39-1 -> -0.35698084 | T58: =T39/R39-1 -> 48.558163 | U58: =U39/S39-1 -> 2.359952 | V58: =V39/T39-1 -> -0.76867008 | W58: =W39/U39-1 -> 1.3789314 | X58: =X39/V39-1 -> 0.91811304 | ... AB58: =AB39/Z39-1 -> 0.45740741
B59: Hungary | F59: =F40/E40-1 -> 1.3673041 | G59: =G40/F40-1 -> 0.094116435 | H59: =H40/G40-1 -> 1.3225721 | I59: =I40/H40-1 -> -0.62343687 | J59: =J40/I40-1 -> -0.92677779 | K59: =K40/J40-1 -> 19.558824 | L59: =L40/K40-1 -> -0.23319027 | Q59: =Q40/O40-1 -> -0.13374972 | R59: =R40/P40-1 -> 0.28973573 | S59: =S40/Q40-1 -> 1.1452336 | T59: =T40/R40-1 -> 1.4248255 | U59: =U40/S40-1 -> -0.20091708 | V59: =V40/T40-1 -> -0.8389708 | W59: =W40/U40-1 -> -0.44118973 | X59: =X40/V40-1 -> -2.1559814 | ... AB59: =AB40/Z40-1 -> -0.64570552
B60: Slovakia | F60: =F41/E41-1 -> #DIV/0! | G60: =G41/F41-1 -> #DIV/0! | H60: =H41/G41-1 -> #DIV/0! | I60: =I41/H41-1 -> -0.81637762 | J60: =J41/I41-1 -> 4.7190962 | K60: =K41/J41-1 -> 0.10921178 | L60: =L41/K41-1 -> 0.066780822 | Q60: =Q41/O41-1 -> #DIV/0! | R60: =R41/P41-1 -> #DIV/0! | S60: =S41/Q41-1 -> #DIV/0! | T60: =T41/R41-1 -> #DIV/0! | U60: =U41/S41-1 -> 2.7287902 | V60: =V41/T41-1 -> -1.2811538 | W60: =W41/U41-1 -> 0.036090087 | X60: =X41/V41-1 -> -3.423367 | ... AB60: =AB41/Z41-1 -> -0.31945789
B61: Slovakia | F61: =F42/E42-1 -> 0.39931726 | G61: =G42/F42-1 -> -0.58401349 | H61: =H42/G42-1 -> 1.35947 | I61: =I42/H42-1 -> 4.2422903 | J61: =J42/I42-1 -> 1.1083932 | K61: =K42/J42-1 -> -0.42726263 | L61: =L42/K42-1 -> 1.1221522 | Q61: =Q42/O42-1 -> -1.6074262 | R61: =R42/P42-1 -> -0.3442623 | S61: =S42/Q42-1 -> -2.0916928 | T61: =T42/R42-1 -> 0.61054422 | U61: =U42/S42-1 -> 7.5568318 | V61: =V42/T42-1 -> 3.7547342 | W61: =W42/U42-1 -> 2.543164 | X61: =X42/V42-1 -> 0.72857968 | ... AB61: =AB42/Z42-1 -> 0.42488889
B62: Others | F62: =F43/E43-1 -> #DIV/0! | G62: =G43/F43-1 -> #DIV/0! | H62: =H43/G43-1 -> #DIV/0! | I62: =I43/H43-1 -> #DIV/0! | J62: =J43/I43-1 -> #DIV/0! | K62: =K43/J43-1 -> #DIV/0! | L62: =L43/K43-1 -> #DIV/0! | Q62: =Q43/O43-1 -> #DIV/0! | R62: =R43/P43-1 -> #DIV/0! | S62: =S43/Q43-1 -> #DIV/0! | T62: =T43/R43-1 -> #DIV/0! | U62: =U43/S43-1 -> #DIV/0! | V62: =V43/T43-1 -> #DIV/0! | W62: =W43/U43-1 -> #DIV/0! | X62: =X43/V43-1 -> #DIV/0! | ... AB62: =AB43/Z43-1 -> #DIV/0!
B63: Total | F63: =F44/E44-1 -> 0.7090094 | G63: =G44/F44-1 -> -0.6259308 | H63: =H44/G44-1 -> 6.2328899 | I63: =I44/H44-1 -> -0.36642252 | J63: =J44/I44-1 -> 0.2601517 | K63: =K44/J44-1 -> 0.071469216 | L63: =L44/K44-1 -> 0.21072756 | Q63: =Q44/O44-1 -> -0.793725 | R63: =R44/P44-1 -> -0.53274551 | S63: =S44/Q44-1 -> 3.8645861 | T63: =T44/R44-1 -> 6.8135219 | U63: =U44/S44-1 -> 2.4239449 | V63: =V44/T44-1 -> -0.79233852 | W63: =W44/U44-1 -> -0.16395466 | X63: =X44/V44-1 -> 1.3275049 | ... AB63: =AB44/Z44-1 -> 0.073281838
B66: Profit/loss before tax
B67: Czech Republic | E67: 280.466 | F67: 318.455 | G67: 171.407 | H67: 858.818 | I67: 574.857 | O67: 82.532 | P67: =+F67-O67 -> 235.923 | Q67: 56.837 | R67: =+G67-Q67 -> 114.57 | S67: 129.167 | T67: =+H67-S67 -> 729.651 | U67: 413.409 | V67: =+I67-U67 -> 161.448 | W67: 203.8
B68: Romania | E68: 61.537 | F68: 80.152 | G68: 42.907 | H68: 132.955 | I68: 109.504 | O68: 53.935 | P68: =+F68-O68 -> 26.217 | Q68: 42.733 | R68: =+G68-Q68 -> 0.174 | S68: 24.431 | T68: =+H68-S68 -> 108.524 | U68: 65.076 | V68: =+I68-U68 -> 44.428 | W68: 129.8
B69: Hungary | E69: 22.537 | F69: 52.264 | G69: 60.763 | H69: 147.048 | I69: 112.365 | O69: 24.956 | P69: =+F69-O69 -> 27.308 | Q69: 21.088 | R69: =+G69-Q69 -> 39.675 | S69: 42.171 | T69: =+H69-S69 -> 104.877 | U69: 81.838 | V69: =+I69-U69 -> 30.527 | W69: -4.8
B70: Slovakia | H70: 115.419 | I70: 42.295 | S70: 20.171 | T70: =+H70-S70 -> 95.248 | U70: 54.179 | V70: =+I70-U70 -> -11.884 | W70: 58.6
B71: Other | E71: 59.335 | F71: =37.268+10.352+2.218 -> 49.838 | G71: =18.537+4.874-8.063 -> 15.348 | H71: =-12.847+38.646 -> 25.799 | I71: =176.979+15.174-13.315 -> 178.838 | O71: 12.624 | P71: =+F71-O71 -> 37.214 | Q71: 6.284 | R71: =+G71-Q71 -> 9.064 | S71: 18.277 | T71: =+H71-S71 -> 7.522 | U71: =-18.958-36.008+50.467 -> -4.499 | V71: =+I71-U71 -> 183.337 | W71: =68.1+40.5+86.1 -> 194.7
B72: Hotel segment | H72: -3.349 | I72: 2.351 | S72: -1.003 | T72: =+H72-S72 -> -2.346 | U72: 0.039 | V72: =+I72-U72 -> 2.312
B73: Intersegment Eliminations | I73: -32.942 | V73: =+I73-U73 -> -32.942
B74: Total | C74: =+SUM(C67:C71) -> 0 | D74: =+SUM(D67:D71) -> 0 | E74: =+SUM(E67:E71) -> 423.875 | F74: =+SUM(F67:F71) -> 500.709 | G74: =+SUM(G67:G71) -> 290.425 | H74: =+SUM(H67:H72) -> 1276.69 | I74: =+SUM(I67:I73) -> 987.268 | O74: =+SUM(O67:O71) -> 174.047 | P74: =+SUM(P67:P71) -> 326.662 | Q74: =+SUM(Q67:Q71) -> 126.942 | R74: =+SUM(R67:R71) -> 163.483 | S74: =+SUM(S67:S72) -> 233.214 | T74: =+SUM(T67:T72) -> 1043.476 | U74: =+SUM(U67:U72) -> 610.042 | V74: =+SUM(V67:V73) -> 377.226 | W74: =+SUM(W67:W72) -> 582.1
B76: check | E76: =ROUND(E74-Model!E40,-1) -> 0 | F76: =ROUND(F74-Model!F40,-1) -> 0 | G76: =ROUND(G74-Model!G40,-1) -> 0 | H76: =ROUND(H74-Model!H40,-1) -> 0 | I76: =ROUND(I74-Model!J40,-1) -> 40 | O76: =ROUND(O74-Model!Q40,-1) -> 0 | P76: =ROUND(P74-Model!R40,-1) -> 0 | Q76: =ROUND(Q74-Model!S40,-1) -> 0 | R76: =ROUND(R74-Model!T40,-1) -> 0 | S76: =ROUND(S74-Model!U40,-1) -> 0 | T76: =ROUND(T74-Model!V40,-1) -> 0 | U76: =ROUND(U74-Model!W40,-1) -> 0 | V76: =ROUND(V74-Model!X40,-1) -> 0 | W76: =ROUND(W74-Model!Y40,-1) -> 0
B78: % of revenue
B79: Czech Republic | E79: =+E67/E$74 -> 0.66167148 | F79: =+F67/F$74 -> 0.63600814 | G79: =+G67/G$74 -> 0.59019368 | H79: =+H67/H$74 -> 0.6726911 | I79: =+I67/I$74 -> 0.58227047 | O79: =+O67/O$74 -> 0.47419375 | P79: =+P67/P$74 -> 0.72222358 | Q79: =+Q67/Q$74 -> 0.44773991 | R79: =+R67/R$74 -> 0.70080681 | S79: =+S67/S$74 -> 0.55385611 | T79: =+T67/T$74 -> 0.69925039 | U79: =+U67/U$74 -> 0.67767301 | V79: =+V67/V$74 -> 0.42798747 | W79: =+W67/W$74 -> 0.35011166
B80: Romania | E80: =+E68/E$74 -> 0.14517723 | F80: =+F68/F$74 -> 0.16007701 | G80: =+G68/G$74 -> 0.14773866 | H80: =+H68/H$74 -> 0.10414039 | I80: =+I68/I$74 -> 0.11091618 | O80: =+O68/O$74 -> 0.30988756 | P80: =+P68/P$74 -> 0.080257269 | Q80: =+Q68/Q$74 -> 0.33663405 | R80: =+R68/R$74 -> 0.0010643308 | S80: =+S68/S$74 -> 0.10475786 | T80: =+T68/T$74 -> 0.10400239 | U80: =+U68/U$74 -> 0.10667462 | V80: =+V68/V$74 -> 0.11777555 | W80: =+W68/W$74 -> 0.22298574
B81: Hungary | E81: =+E69/E$74 -> 0.053168977 | F81: =+F69/F$74 -> 0.10437999 | G81: =+G69/G$74 -> 0.20922097 | H81: =+H69/H$74 -> 0.1151791 | I81: =+I69/I$74 -> 0.11381408 | O81: =+O69/O$74 -> 0.14338656 | P81: =+P69/P$74 -> 0.083597113 | Q81: =+Q69/Q$74 -> 0.16612311 | R81: =+R69/R$74 -> 0.24268578 | S81: =+S69/S$74 -> 0.18082534 | T81: =+T69/T$74 -> 0.10050734 | U81: =+U69/U$74 -> 0.13415142 | V81: =+V69/V$74 -> 0.080924963 | W81: =+W69/W$74 -> -0.0082460058
B82: Slovakia | H82: =+H70/H$74 -> 0.090404875 | I82: =+I70/I$74 -> 0.042840445 | S82: =+S70/S$74 -> 0.086491377 | T82: =+T70/T$74 -> 0.091279531 | U82: =+U70/U$74 -> 0.088811918 | V82: =+V70/V$74 -> -0.031503661 | W82: =+W70/W$74 -> 0.10066999
B83: Other | E83: =+E71/E$74 -> 0.13998231 | F83: =+F71/F$74 -> 0.09953486 | G83: =+G71/G$74 -> 0.05284669 | H83: =+H71/H$74 -> 0.020207725 | I83: =+I71/I$74 -> 0.18114433 | O83: =+O71/O$74 -> 0.072532132 | P83: =+P71/P$74 -> 0.11392204 | Q83: =+Q71/Q$74 -> 0.049502923 | R83: =+R71/R$74 -> 0.055443074 | S83: =+S71/S$74 -> 0.078370081 | T83: =+T71/T$74 -> 0.007208599 | U83: =+U71/U$74 -> -0.0073749021 | V83: =+V71/V$74 -> 0.48601369 | W83: =+W71/W$74 -> 0.33447861
B84: Hotel segment | H84: =+H72/H$74 -> -0.0026231897 | I84: =+I72/I$74 -> 0.002381319 | S84: =+S72/S$74 -> -0.004300771 | T84: =+T72/T$74 -> -0.0022482549 | U84: =+U72/U$74 -> 6.3930024e-05 | V84: =+V72/V$74 -> 0.0061289519 | W84: =+W72/W$74 -> 0
B85: Total | E85: =+SUM(E79:E83) -> 1 | F85: =+SUM(F79:F83) -> 1 | G85: =+SUM(G79:G83) -> 1 | H85: =+SUM(H79:H84) -> 1 | I85: =+SUM(I79:I84) -> 1.0333668 | O85: =+SUM(O79:O83) -> 1 | P85: =+SUM(P79:P83) -> 1 | Q85: =+SUM(Q79:Q83) -> 1 | R85: =+SUM(R79:R83) -> 1 | S85: =+SUM(S79:S84) -> 1 | T85: =+SUM(T79:T84) -> 1 | U85: =+SUM(U79:U84) -> 1 | V85: =+SUM(V79:V84) -> 1.087327 | W85: =+SUM(W79:W84) -> 1
B87: Rental income by sector
B88: Industrial | C88: =83.203+72.767 -> 155.97 | D88: =95.97+85.114 -> 181.084 | E88: 203.441 | F88: 216.404 | G88: 240.905 | H88: 287.328 | I88: 424.727 | J88: 504.6 | K88: 590.3 | O88: 102.843 | P88: =+F88-O88 -> 113.561 | Q88: 118.218 | R88: =+G88-Q88 -> 122.687 | S88: 135.596 | T88: =+H88-S88 -> 151.732 | U88: 204.119 | V88: =+I88-U88 -> 220.608 | W88: 245.1 | X88: =+J88-W88 -> 259.5 | Y88: 285.4 | Z88: =+K88-Y88 -> 304.9 | AA88: 333.5
B89: Office | C89: 23.305 | D89: 24.879 | E89: 26.674 | F89: 26.202 | G89: 31.061 | H89: 32.531 | I89: 32.923 | J89: 30.7 | O89: 12.977 | P89: =+F89-O89 -> 13.225 | Q89: 15.604 | R89: =+G89-Q89 -> 15.457 | S89: 16.147 | T89: =+H89-S89 -> 16.384 | U89: 16.119 | V89: =+I89-U89 -> 16.804 | W89: 15.9 | X89: =+J89-W89 -> 14.8 | Z89: =+K89-Y89 -> 0
B90: Retail | C90: 3.131 | D90: 2.219 | E90: 0.786 | F90: 1.017 | G90: 0.825 | H90: 0.568 | I90: 1.062 | J90: 1.2 | O90: 0.504 | P90: =+F90-O90 -> 0.513 | Q90: 0.432 | R90: =+G90-Q90 -> 0.393 | S90: 0.399 | T90: =+H90-S90 -> 0.169 | U90: 0.447 | V90: =+I90-U90 -> 0.615 | W90: 0.6 | X90: =+J90-W90 -> 0.6 | Z90: =+K90-Y90 -> 0
B91: Other | C91: 0.299 | D91: 0.078 | E91: 11.059 | F91: 14.363 | G91: 19.144 | H91: 14.224 | I91: 26.305 | J91: 35.4 | K91: 43.5 | O91: 6.577 | P91: =+F91-O91 -> 7.786 | Q91: 6.333 | R91: =+G91-Q91 -> 12.811 | S91: 7.666 | T91: =+H91-S91 -> 6.558 | U91: 9.815 | V91: =+I91-U91 -> 16.49 | W91: 18.8 | X91: =+J91-W91 -> 16.6 | Y91: 20.1 | Z91: =+K91-Y91 -> 23.4 | AA91: 19.1
B92: Office and Retail | K92: 30.3 | X92: =+J92-W92 -> 0 | Y92: 15.4 | Z92: =+K92-Y92 -> 14.9 | AA92: 14.6
B93: Total | C93: =+SUM(C88:C92) -> 182.705 | D93: =+SUM(D88:D92) -> 208.26 | E93: =+SUM(E88:E92) -> 241.96 | F93: =+SUM(F88:F92) -> 257.986 | G93: =+SUM(G88:G92) -> 291.935 | H93: =+SUM(H88:H92) -> 334.651 | I93: =+SUM(I88:I92) -> 485.017 | J93: =+SUM(J88:J92) -> 571.9 | K93: =+SUM(K88:K92) -> 664.1 | L93: 759.8 | M93: =SUM(AA93:AB93) -> 759.8 | O93: =+SUM(O88:O91) -> 122.901 | P93: =+SUM(P88:P91) -> 135.085 | Q93: =+SUM(Q88:Q91) -> 140.587 | R93: =+SUM(R88:R91) -> 151.348 | S93: =+SUM(S88:S91) -> 159.808 | T93: =+SUM(T88:T91) -> 174.843 | U93: =+SUM(U88:U91) -> 230.5 | V93: =+SUM(V88:V91) -> 254.517 | ... X93: =+SUM(X88:X91) -> 291.5 | Y93: =+SUM(Y88:Y92) -> 320.9 | Z93: =+SUM(Z88:Z92) -> 343.2 | AA93: =+SUM(AA88:AA92) -> 367.2 | AB93: =L93-AA93 -> 392.6
B94: check | D94: =+D93-Model!D7 -> 0 | E94: =+E93-Model!E7 -> 0 | F94: =+F93-Model!F7 -> 0 | G94: =+G93-Model!G7 -> 0 | H94: =+H93-Model!H7 -> 0 | I94: =+I93-Model!J7 -> 0 | J94: =+J93-Model!K7 -> 0 | K94: =+K93-Model!M7 -> 0 | L94: =+L93-Model!N7 -> 0 | M94: =+M93-Model!O7 -> -22.6 | O94: =+O93-Model!Q7 -> 0 | P94: =+P93-Model!R7 -> 0 | Q94: =+Q93-Model!S7 -> 0 | R94: =+R93-Model!T7 -> 0 | S94: =+S93-Model!U7 -> 0 | T94: =+T93-Model!V7 -> 0 | V94: =+V93-Model!X7 -> 0 | W94: =+W93-Model!Y7 -> 0 | Y94: =+Y93-Model!AA7 -> 0 | Z94: =+Z93-Model!AB7 -> 0 | AA94: =+AA93-Model!AC7 -> 0
B96: Rental income by sector (% Share)
B97: Industrial | C97: =+C88/C$93 -> 0.85367122 | D97: =+D88/D$93 -> 0.86950927 | E97: =+E88/E$93 -> 0.84080427 | F97: =+F88/F$93 -> 0.83882071 | G97: =+G88/G$93 -> 0.82520082 | H97: =+H88/H$93 -> 0.85858999 | I97: =+I88/I$93 -> 0.87569508 | J97: =+J88/J$93 -> 0.88232208 | K97: =+K88/K$93 -> 0.88887216 | O97: =+O88/O$93 -> 0.83679547 | P97: =+P88/P$93 -> 0.84066329 | Q97: =+Q88/Q$93 -> 0.84088856 | R97: =+R88/R$93 -> 0.81062849 | S97: =+S88/S$93 -> 0.84849319 | T97: =+T88/T$93 -> 0.86781856 | U97: =+U88/U$93 -> 0.88554881 | V97: =+V88/V$93 -> 0.86677118 | ... AA97: =+AA88/AA$93 -> 0.9082244
B98: Office | C98: =+C89/C$93 -> 0.12755535 | D98: =+D89/D$93 -> 0.11946125 | E98: =+E89/E$93 -> 0.11024136 | F98: =+F89/F$93 -> 0.10156365 | G98: =+G89/G$93 -> 0.10639697 | H98: =+H89/H$93 -> 0.097208734 | I98: =+I89/I$93 -> 0.067880095 | J98: =+J89/J$93 -> 0.053680713 | O98: =+O89/O$93 -> 0.10558905 | P98: =+P89/P$93 -> 0.097901321 | Q98: =+Q89/Q$93 -> 0.11099177 | R98: =+R89/R$93 -> 0.10212887 | S98: =+S89/S$93 -> 0.10104 | T98: =+T89/T$93 -> 0.093706926 | U98: =+U89/U$93 -> 0.069930586 | V98: =+V89/V$93 -> 0.066023095 | ... AA98: =+AA89/AA$93 -> 0
B99: Retail | C99: =+C90/C$93 -> 0.017136915 | D99: =+D90/D$93 -> 0.010654951 | E99: =+E90/E$93 -> 0.0032484708 | F99: =+F90/F$93 -> 0.0039420744 | G99: =+G90/G$93 -> 0.0028259715 | H99: =+H90/H$93 -> 0.0016972906 | I99: =+I90/I$93 -> 0.002189614 | J99: =+J90/J$93 -> 0.0020982689 | O99: =+O90/O$93 -> 0.0041008617 | P99: =+P90/P$93 -> 0.0037976089 | Q99: =+Q90/Q$93 -> 0.0030728303 | R99: =+R90/R$93 -> 0.0025966646 | S99: =+S90/S$93 -> 0.0024967461 | T99: =+T90/T$93 -> 0.00096658145 | U99: =+U90/U$93 -> 0.0019392625 | V99: =+V90/V$93 -> 0.0024163415 | ... AA99: =+AA90/AA$93 -> 0
B100: Other | C100: =+C91/C$93 -> 0.0016365179 | D100: =+D91/D$93 -> 0.00037453184 | E100: =+E91/E$93 -> 0.045705902 | F100: =+F91/F$93 -> 0.055673564 | G100: =+G91/G$93 -> 0.065576241 | H100: =+H91/H$93 -> 0.042503982 | I100: =+I91/I$93 -> 0.054235212 | J100: =+J91/J$93 -> 0.061898933 | K100: =+K91/K$93 -> 0.065502183 | O100: =+O91/O$93 -> 0.053514617 | P100: =+P91/P$93 -> 0.057637784 | Q100: =+Q91/Q$93 -> 0.045046839 | R100: =+R91/R$93 -> 0.084645981 | S100: =+S91/S$93 -> 0.047970064 | T100: =+T91/T$93 -> 0.037507936 | U100: =+U91/U$93 -> 0.042581345 | V100: =+V91/V$93 -> 0.064789385 | ... AA100: =+AA91/AA$93 -> 0.052015251
B101: Office and Retail | K101: =K92/$K$93 -> 0.045625659
B102: Total | C102: =+SUM(C97:C101) -> 1 | D102: =+SUM(D97:D101) -> 1 | E102: =+SUM(E97:E101) -> 1 | F102: =+SUM(F97:F101) -> 1 | G102: =+SUM(G97:G101) -> 1 | H102: =+SUM(H97:H101) -> 1 | I102: =+SUM(I97:I101) -> 1 | J102: =+SUM(J97:J101) -> 1 | K102: =+SUM(K97:K101) -> 1 | O102: =+SUM(O97:O100) -> 1 | P102: =+SUM(P97:P100) -> 1 | Q102: =+SUM(Q97:Q100) -> 1 | R102: =+SUM(R97:R100) -> 1 | S102: =+SUM(S97:S100) -> 1 | T102: =+SUM(T97:T100) -> 1 | U102: =+SUM(U97:U100) -> 1 | V102: =+SUM(V97:V100) -> 1 | ... AA102: =+SUM(AA97:AA100) -> 0.96023965
B104: Rental income by geography
B105: Czech Republic | C105: 159.323 | D105: 165.901 | E105: 188.259 | F105: 185.891 | G105: 201.201 | H105: 220.036 | I105: 248.117 | J105: 276 | K105: 297.8 | L105: 315.6 | O105: 88.815 | P105: =+F105-O105 -> 97.076 | Q105: 97.496 | R105: =+G105-Q105 -> 103.705 | S105: 108 | T105: =+H105-S105 -> 112.036 | U105: 121.211 | V105: =+I105-U105 -> 126.906 | W105: 136.4 | X105: =+J105-W105 -> 139.6 | Y105: 144.6 | Z105: =+K105-Y105 -> 153.2 | AA105: 153.1 | AB105: =+L105-AA105 -> 162.5
B106: Romania | C106: 17.434 | D106: 25.678 | E106: 38.618 | F106: 45.703 | G106: 55.281 | H106: 68.448 | I106: 94.76 | J106: 113.7 | K106: 136.5 | L106: 160.2 | O106: 22.483 | P106: =+F106-O106 -> 23.22 | Q106: 26.814 | R106: =+G106-Q106 -> 28.467 | S106: 33.169 | T106: =+H106-S106 -> 35.279 | U106: 44.86 | V106: =+I106-U106 -> 49.9 | W106: 54.5 | X106: =+J106-W106 -> 59.2 | Y106: 64.4 | Z106: =+K106-Y106 -> 72.1 | AA106: 77.6 | AB106: =+L106-AA106 -> 82.6
B107: Hungary | C107: 3.514 | D107: 11.719 | E107: 12.224 | F107: 24.307 | G107: 28.849 | H107: 34.998 | I107: 55.378 | J107: 65.3 | K107: 60.3 | L107: 89.1 | O107: 10.928 | P107: =+F107-O107 -> 13.379 | Q107: 12.686 | R107: =+G107-Q107 -> 16.163 | S107: 14.068 | T107: =+H107-S107 -> 20.93 | U107: 26.632 | V107: =+I107-U107 -> 28.746 | W107: 32.8 | X107: =+J107-W107 -> 32.5 | Y107: 34.9 | Z107: =+K107-Y107 -> 25.4 | AA107: 43.9 | AB107: =+L107-AA107 -> 45.2
B108: Slovakia | C108: 10.921 | D108: 15.112 | E108: 18.614 | F108: 20.237 | G108: 25.361 | H108: 28.623 | I108: 41.525 | J108: 48.8 | K108: 71 | L108: 73.3 | O108: 9.529 | P108: =+F108-O108 -> 10.708 | Q108: 12.427 | R108: =+G108-Q108 -> 12.934 | S108: 13.947 | T108: =+H108-S108 -> 14.676 | U108: 20.049 | V108: =+I108-U108 -> 21.476 | W108: 22.9 | X108: =+J108-W108 -> 25.9 | Y108: 28.2 | Z108: =+K108-Y108 -> 42.8 | AA108: 36 | AB108: =+L108-AA108 -> 37.3
B109: Germany | C109: 2.402 | D109: 2.186 | E109: 2.497 | F109: 1.786 | G109: 1.918 | H109: 0.708 | I109: 69.633 | J109: 81.5 | K109: 91.5 | L109: 90 | O109: 0.679 | P109: =+F109-O109 -> 1.107 | Q109: 0.757 | R109: =+G109-Q109 -> 1.161 | S109: 0.333 | T109: =+H109-S109 -> 0.375 | U109: 31.63 | V109: =+I109-U109 -> 38.003 | W109: 40.9 | X109: =+J109-W109 -> 40.6 | Y109: 45.2 | Z109: =+K109-Y109 -> 46.3 | AA109: 43.4 | AB109: =+L109-AA109 -> 46.6
B110: Poland | C110: 1.256 | D110: 1.545 | E110: 1.542 | F110: 1.476 | G110: 1.506 | H110: 2.51 | I110: 4.122 | J110: 8.4 | K110: 23.8 | L110: 48.2 | O110: 0.957 | P110: =+F110-O110 -> 0.519 | Q110: 1.019 | R110: =+G110-Q110 -> 0.487 | S110: 0.921 | T110: =+H110-S110 -> 1.589 | U110: 1.493 | V110: =+I110-U110 -> 2.629 | W110: 4.2 | X110: =+J110-W110 -> 4.2 | Y110: 9.4 | Z110: =+K110-Y110 -> 14.4 | AA110: 21.2 | AB110: =+L110-AA110 -> 27
B111: Serbia | C111: 0 | D111: 0 | E111: 0.026 | F111: 0.793 | G111: 3.539 | H111: 8.56 | I111: 13.064 | J111: 18.5 | K111: 31.6 | L111: 39.8 | O111: 0.342 | P111: =+F111-O111 -> 0.451 | Q111: 1.461 | R111: =+G111-Q111 -> 2.078 | S111: 3.642 | T111: =+H111-S111 -> 4.918 | U111: 5.628 | V111: =+I111-U111 -> 7.436 | W111: 8.6 | X111: =+J111-W111 -> 9.9 | Y111: 14.6 | Z111: =+K111-Y111 -> 17 | AA111: 19 | AB111: =+L111-AA111 -> 20.8
B112: Austria | C112: 0.18 | D112: 0.168 | E112: 0.17 | F112: 0.172 | G112: 0.135 | H112: 0.151 | I112: 0.152 | J112: 1 | K112: 2.7 | L112: 7.3 | O112: 0.084 | P112: =+F112-O112 -> 0.088 | Q112: 0.086 | R112: =+G112-Q112 -> 0.049 | S112: 0.092 | T112: =+H112-S112 -> 0.059 | U112: 0.065 | V112: =+I112-U112 -> 0.087 | W112: 0.3 | X112: =+J112-W112 -> 0.7 | Y112: 1.1 | Z112: =+K112-Y112 -> 1.6 | AA112: 4.1 | AB112: =+L112-AA112 -> 3.2
B113: Slovenia | I113: 0.034 | J113: 0 | O113: 0 | P113: 0 | Q113: 0 | R113: 0 | S113: 0 | T113: 0 | U113: 1.064 | V113: =+I113-U113 -> -1.03 | W113: 0 | X113: =+J113-W113 -> 0 | AB113: =+L113-AA113 -> 0
B114: Netherlands | I114: 2.99 | J114: 7.2 | K114: 9.4 | L114: 10.9 | O114: 0 | P114: 0 | Q114: 0 | R114: 0 | S114: 0 | T114: 0 | U114: 0.019 | V114: =+I114-U114 -> 2.971 | W114: 3.2 | X114: =+J114-W114 -> 4 | Y114: 4.6 | Z114: =+K114-Y114 -> 4.8 | AA114: 5.1 | AB114: =+L114-AA114 -> 5.8
B115: Bulgaria | G115: 0.027 | H115: 1.729 | I115: 7.117 | J115: 12.2 | K115: 15.4 | L115: 17.6 | R115: =+G115-Q115 -> 0.027 | S115: 0.34 | T115: =+H115-S115 -> 1.389 | U115: 1.715 | V115: =+I115-U115 -> 5.402 | W115: 5.7 | X115: =+J115-W115 -> 6.5 | Y115: 7.1 | Z115: =+K115-Y115 -> 8.3 | AA115: 8.5 | AB115: =+L115-AA115 -> 9.1
B116: Italy | L116: 0.2
...
