Workbook
Name IQ_CH: 110000
Name IQ_CQ: 5000
Name IQ_CY: 10000
Name IQ_DAILY: 500000
Name IQ_FH: 100000
Name IQ_FQ: 500
Name IQ_FY: 1000
Name IQ_LTM: 2000
Name IQ_MONTH: 15000
Name IQ_NTM: 6000
Name IQ_WEEK: 50000
Name IQ_YTD: 3000

Sheet Capitalization
A2: 2Q26
J3: Exchange rate as at end | K3: =[1]Sheet1!$A$201 -> 60.295
J4: LTM Average exchange rate | K4: =AVERAGE(Model!$AS$200:$AU$200) -> 58.079667
B6: Debt Breakdown as on 30-Jun-2026 | C6: Php (in million) | D6: USD (mn) | E6: Leverage (PHP) | F6: Leverage (USD) | J6: =B6 -> Debt Breakdown as on 30-Jun-2026 | K6: =C6 -> Php (in million) | L6: =D6 -> USD (mn) | M6: =E6 -> Leverage (PHP) | N6: =F6 -> Leverage (USD)
A7: =SUM(C8:C10)/C17 -> 0.56260655 | B7: Term Loans: | J7: Total debt (company reported) | K7: 261670 | L7: =K7/K3 -> 4339.8292
B8: Peso | C8: 202864.66 | D8: =C8/$K3 -> 3364.5354 | J8: Perpetuals | K8: =C18 -> 35702.8 | L8: =K8/K3 -> 592.13533
B9: Dollar | C9: 14854.689 | D9: =C9/$K3 -> 246.36685 | J9: Total Debt (including perpetuals) | K9: =K7+K8 -> 297372.8 | L9: =L7+L8 -> 4931.9645 | M9: =K9/K12 -> 13.099351 | N9: =L9/L12 -> 13.099351
B10: Yen | C10: 7434.15 | D10: =C10/$K3 -> 123.29629 | J10: Cash and Short-Term Investments | K10: =C20 -> 19700.518 | L10: =K10/K3 -> 326.73552
A11: =SUM(C12:C13)/C17 -> 0.091246512 | B11: Retail bonds | J11: Net debt | K11: =K9-K10 -> 277672.28 | L11: =L9-L10 -> 4605.229 | M11: =K11/K12 -> 12.231538 | N11: =L11/L12 -> 12.231538
B12: Peso | C12: 0 | D12: =C12/$K3 -> 0 | J12: LTM Adjusted EBITDA | K12: =C24 -> 22701.339 | L12: =K12/K3 -> 376.5045
B13: Dollar | C13: 36516.588 | D13: =C13/$K3 -> 605.63211
B14: Total Debt (excluding lease liabilities) | C14: =+C8+C9+C12+C13+C10 -> 261670.09 | D14: =+D8+D9+D12+D13 -> 4216.5344
A15: =SUM(C15:C16)/C17 -> 0.34614693 | B15: Current portion of lease liabilities | C15: 8335.832 | D15: =C15/$K3 -> 138.2508 | J15: Company reported
B16: Non-current portion of lease liabilities | C16: 130191.16 | D16: =C16/$K3 -> 2159.2364 | J16: Gross debt to EBITDA | K16: 2.68
B17: Total Debt (including lease liabilities) | C17: =C14+C15+C16 -> 400197.08 | D17: =D14+D15+D16 -> 6514.0216 | J17: Net debt to EBITDA | K17: 2.48
B18: Perpetuals | C18: =[1]Sheet1!A$119 -> 35702.8 | D18: =C18/$K3 -> 592.13533
B19: Total debt (including perpetuals & lease liabilities) | C19: =C17+C18 -> 435899.88 | D19: =D17+D18 -> 7106.1569 | E19: =C19/C24 -> 19.201505 | F19: =D19/D24 -> 18.180567
B20: Cash and Short-Term Investments | C20: =[1]Sheet1!A$122 -> 19700.518 | D20: =C20/$K3 -> 326.73552
B21: Net debt | C21: =C19-C20 -> 416199.36 | D21: =D19-D20 -> 6779.4214 | E21: =C21/C24 -> 18.333692 | F21: =D21/D24 -> 17.344639
B22: Equity | C22: =[1]Sheet1!A$127 -> 177784.86 | D22: =C22/$K3 -> 2948.5839
B23: Total Capitalisation | C23: =C21+C22 -> 593984.23 | D23: =C23/$K3 -> 9851.3016
B24: LTM Adjusted EBITDA | C24: =[1]Sheet1!A$87 -> 22701.339 | D24: =C24/$K4 -> 390.86552
B25: check | C25: =C19-[1]Sheet1!A$120 -> 0
B28: Liquidity Table at end-2Q26 | C28: =C6 -> Php (in million) | D28: =D6 -> USD (mn)
B29: Cash on hand and in banks | C29: 5014.411 | D29: =C29/$K$3 -> 83.164624
B30: Short-term money market placements | C30: 14686.107 | D30: =C30/$K$3 -> 243.57089
B31: Total | C31: =SUM(C29:C30) -> 19700.518 | D31: =SUM(D29:D30) -> 326.73552
B32: check | C32: =C31-C20 -> 0
B35: Globe’s short term credit facilities at end-2Q26 | C35: =C6 -> Php (in million) | D35: =D6 -> USD (mn)
B36: Uncommitted credit facilty
B37: Peso | C37: 85249 | D37: =C37/$K3 -> 1413.8652
B38: Dollar | C38: =+D38*$K3 -> 1205.9 | D38: 20
B39: Committed
B40: Peso | C40: 3000 | D40: =C40/$K3 -> 49.755369
B41: Dollar | C41: =+D41*$K3 -> 3014.75 | D41: 50
B42: Cash and Short-Term Investments | C42: =C31 -> 19700.518 | D42: =C42/$K3 -> 326.73552
B43: Total Liquidity | C43: =+C37+C38+C41+C42 -> 109170.17 | D43: =+D37+D38+D41+D42 -> 1810.6007
B46: Debt maturity 2Q26 | C46: =C6 -> Php (in million) | D46: =D6 -> USD (mn)
B47: 2026 | C47: 20238.5 | D47: =C47/$K3 -> 335.65801
B48: 2027 | C48: 24226.6 | D48: =C48/$K3 -> 401.80114
B49: 2028 | C49: 23652.736 | D49: =C49/$K3 -> 392.28354
B50: 2029 | C50: 24211.471 | D50: =C50/$K3 -> 401.55023
B51: 2030 and thereafter | C51: 170615.99 | D51: =C51/$K3 -> 2829.6872
B52: Total Debt | C52: =+SUM(C47:C51) -> 262945.29 | D52: =+SUM(D47:D50) -> 1531.2929
B53: Less: Unamortized debt issuance costs | C53: =C54-C52 -> -1275.205 | D53: =C53/$K3 -> -21.149432
B54: Total debt after unamortized debt issuance costs | C54: =C14 -> 261670.09 | D54: =+D52+D53 -> 1510.1435
B55: Check | C55: =+C54-C14 -> 0
A59: 1Q26
J60: Exchange rate as at end | K60: =Model!$M$201 -> 0
J61: LTM Average exchange rate | K61: =Model!$M$200 -> 0
B63: Debt Breakdown as on 31-Mar-2026 | C63: Php (in million) | D63: USD (mn) | E63: Leverage (PHP) | F63: Leverage (USD) | J63: =B63 -> Debt Breakdown as on 31-Mar-2026 | K63: =C63 -> Php (in million) | L63: =D63 -> USD (mn) | M63: =E63 -> Leverage (PHP) | N63: =F63 -> Leverage (USD)
A64: =SUM(C65:C67)/C74 -> 0.55686816 | B64: Term Loans: | J64: Total debt (company reported) | K64: 251237 | L64: =K64/K60 -> #DIV/0!
B65: Peso | C65: 192961.23 | D65: =C65/$K60 -> #DIV/0! | J65: Perpetuals | K65: =C75 -> 46283.78 | L65: =K65/K60 -> #DIV/0!
B66: Dollar | C66: 14700.696 | D66: =C66/$K60 -> #DIV/0! | J66: Total Debt (including perpetuals) | K66: =K64+K65 -> 297520.78 | L66: =L64+L65 -> #DIV/0! | M66: =K66/K69 -> 3.3415984 | N66: =L66/L69 -> #DIV/0!
B67: Yen | C67: 7438.242 | D67: =C67/$K60 -> #DIV/0! | J67: Cash and Short-Term Investments | K67: =C77 -> 42352.876 | L67: =K67/K60 -> #DIV/0!
A68: =SUM(C69:C70)/C74 -> 0.09355459 | B68: Retail bonds | J68: Net debt | K68: =K66-K67 -> 255167.9 | L68: =L66-L67 -> #DIV/0! | M68: =K68/K69 -> 2.865913 | N68: =L68/L69 -> #DIV/0!
B69: Peso | C69: 0 | D69: =C69/$K60 -> #DIV/0! | J69: LTM Adjusted EBITDA | K69: =C81 -> 89035.468 | L69: =K69/K60 -> #DIV/0!
B70: Dollar | C70: 36137.114 | D70: =C70/$K60 -> #DIV/0!
B71: Total Debt (excluding lease liabilities) | C71: =+C65+C66+C69+C70+C67 -> 251237.28 | D71: =+D65+D66+D69+D70 -> #DIV/0!
A72: =SUM(C72:C73)/C74 -> 0.34957725 | B72: Current portion of lease liabilities | C72: 8668.237 | D72: =C72/$K60 -> #DIV/0! | J72: Company reported
B73: Noncurrent portion of lease liabilities | C73: 126362.16 | D73: =C73/$K60 -> #DIV/0! | J73: Gross debt to EBITDA | K73: 2.61
B74: Total Debt (including lease liabilities) | C74: =C71+C72+C73 -> 386267.67 | D74: =D71+D72+D73 -> #DIV/0! | J74: Net debt to EBITDA | K74: 2.17
B75: Perpetuals | C75: =Model!AU$119 -> 46283.78 | D75: =C75/$K60 -> #DIV/0!
B76: Total debt (including perpetuals & lease liabilities) | C76: =C74+C75 -> 432551.45 | D76: =D74+D75 -> #DIV/0! | E76: =C76/C81 -> 4.8581926 | F76: =D76/D81 -> #DIV/0!
B77: Cash and Short-Term Investments | C77: =Model!AU$122 -> 42352.876 | D77: =C77/$K60 -> #DIV/0!
B78: Net debt | C78: =C76-C77 -> 390198.58 | D78: =D76-D77 -> #DIV/0! | E78: =C78/C81 -> 4.3825072 | F78: =D78/D81 -> #DIV/0!
B79: Equity | C79: =Model!AU$127 -> 202371.77 | D79: =C79/$K60 -> #DIV/0!
B80: Total Capitalisation | C80: =C78+C79 -> 592570.35 | D80: =C80/$K60 -> #DIV/0!
B81: LTM Adjusted EBITDA | C81: =Model!AU$87 -> 89035.468 | D81: =C81/$K61 -> #DIV/0!
B82: check | C82: =C76-Model!AU$120 -> 0
B85: Liquidity Table at end-1Q26 | C85: =C63 -> Php (in million) | D85: =D63 -> USD (mn)
B86: Cash on hand and in banks | C86: 10191.931 | D86: =C86/$K$60 -> #DIV/0!
B87: Short-term money market placements | C87: 32160.945 | D87: =C87/$K$60 -> #DIV/0!
B88: Total | C88: =SUM(C86:C87) -> 42352.876 | D88: =SUM(D86:D87) -> #DIV/0!
B89: check | C89: =C88-C77 -> 0
B92: Globe’s short term credit facilities at end-1Q26 | C92: =C63 -> Php (in million) | D92: =D63 -> USD (mn)
B93: Uncommitted credit facilty
B94: Peso | C94: 84318 | D94: =C94/$K60 -> #DIV/0!
B95: Dollar | C95: =+D95*$K60 -> 0 | D95: 20
B96: Committed
B97: Peso | C97: 3000 | D97: =C97/$K60 -> #DIV/0!
B98: Dollar | C98: =+D98*$K60 -> 0 | D98: 50
B99: Cash and Short-Term Investments | C99: =C88 -> 42352.876 | D99: =C99/$K60 -> #DIV/0!
B100: Total Liquidity | C100: =+C94+C95+C98+C99 -> 126670.88 | D100: =+D94+D95+D98+D99 -> #DIV/0!
B103: Debt maturity 1Q26 | C103: =C63 -> Php (in million) | D103: =D63 -> USD (mn)
B104: 2026 | C104: 15483.525 | D104: =C104/$K60 -> #DIV/0!
B105: 2027 | C105: 24018.771 | D105: =C105/$K60 -> #DIV/0!
B106: 2028 | C106: 23593.502 | D106: =C106/$K60 -> #DIV/0!
B107: 2029 | C107: 24183.005 | D107: =C107/$K60 -> #DIV/0!
B108: 2030 and thereafter | C108: 165253.39 | D108: =C108/$K60 -> #DIV/0!
B109: Total Debt | C109: =+SUM(C104:C108) -> 252532.2 | D109: =+SUM(D104:D107) -> #DIV/0!
B110: Less: Unamortized debt issuance costs | C110: =C111-C109 -> -1294.916 | D110: =C110/$K60 -> #DIV/0!
B111: Total debt after unamortized debt issuance costs | C111: =C71 -> 251237.28 | D111: =+D109+D110 -> #DIV/0!
B112: Check | C112: =+C111-C71 -> 0
A117: FY25
J118: Exchange rate as at end | K118: =Model!$M$201 -> 0
J119: LTM Average exchange rate | K119: =Model!$M$200 -> 0
B121: Debt Breakdown as on 31-Dec-2025 | C121: Php (in million) | D121: USD (mn) | E121: Leverage (PHP) | F121: Leverage (USD) | J121: =B121 -> Debt Breakdown as on 31-Dec-2025 | K121: =C121 -> Php (in million) | L121: =D121 -> USD (mn) | M121: =E121 -> Leverage (PHP) | N121: =F121 -> Leverage (USD)
A122: =SUM(C123:C125)/C132 -> 0.5740256 | B122: Term Loans: | J122: Total debt (company reported) | K122: 256313 | L122: =K122/K118 -> #DIV/0!
B123: Peso | C123: 199627.53 | D123: =C123/$K118 -> #DIV/0! | J123: Perpetuals | K123: =C133 -> 45412.62 | L123: =K123/K118 -> #DIV/0!
...

Sheet Model
B2: Globe Telecom Philippines | C2: Annual | D2: Annual | E2: Annual | F2: Annual | G2: Annual | H2: Annual | I2: Annual | J2: Annual | K2: Annual | L2: Annual | O2: Quarter | P2: Quarter | Q2: Quarter | R2: Quarter | S2: Quarter | T2: Quarter | U2: Quarter | V2: Quarter | W2: Quarter | X2: Quarter | Y2: Quarter | Z2: Quarter | AA2: Quarter | AB2: Quarter | AC2: Quarter | AD2: Quarter | AE2: Quarter | AF2: Quarter | AG2: Quarter | AH2: Quarter | AI2: Quarter | AJ2: Quarter | AK2: Quarter | AL2: Quarter | AM2: Quarter | AN2: Quarter | AO2: Quarter | AP2: Quarter | AQ2: Quarter | AR2: Quarter | AS2: Quarter | AT2: Quarter | AU2: Quarter
B3: (PHP millions) | C3: 42735 | D3: 43100 | E3: 43465 | F3: 43830 | G3: 44196 | H3: 44561 | I3: 44926 | J3: 45291 | K3: 45657 | L3: 46022 | O3: 43190 | P3: 43281 | Q3: 43373 | R3: 43465 | S3: 43555 | T3: 43646 | U3: 43738 | V3: 43830 | W3: 43921 | X3: 44012 | Y3: 44104 | Z3: 44196 | AA3: 44286 | AB3: 44377 | AC3: 44469 | AD3: 44561 | AE3: 44651 | AF3: 44742 | AG3: 44834 | AH3: 44926 | AI3: 45016 | AJ3: 45107 | AK3: 45199 | AL3: 45291 | AM3: 45382 | AN3: 45473 | AO3: 45565 | AP3: 45657 | AQ3: 45747 | AR3: 45838 | AS3: 45930 | AT3: 46022 | AU3: 46112
C4: Act | D4: Act | E4: Act | F4: Act | G4: Act | H4: Act | I4: Act | J4: Act | K4: Act | L4: Act | O4: Act | P4: Act | Q4: Act | R4: Act | S4: Act | T4: Act | U4: Act | V4: Act | W4: Act | X4: Act | Y4: Act | Z4: Act | AA4: Act | AB4: Act | AC4: Act | AD4: Act | AE4: Act | AF4: Act | AG4: Act | AH4: Act | AI4: Act | AJ4: Act | AK4: Act | AL4: Act | AM4: Act | AN4: Act | AO4: Act | AP4: Act | AQ4: Act | AR4: Act | AS4: Act | AT4: Act | AU4: Act
C5: FY 16 | D5: FY 17 | E5: FY 18 | F5: FY 19 | G5: FY 20 | H5: FY 21 | I5: FY 22 | J5: FY 23 | K5: FY 24 | L5: FY 25 | O5: Q1 18 | P5: Q2 18 | Q5: Q3 18 | R5: Q4 18 | S5: Q1 19 | T5: Q2 19 | U5: Q3 19 | V5: Q4 19 | W5: Q1 20 | X5: Q2 20 | Y5: Q3 20 | Z5: Q4 20 | AA5: Q1 21 | AB5: Q2 21 | AC5: Q3 21 | AD5: Q4 21 | AE5: Q1 22 | AF5: Q2 22 | AG5: Q3 22 | AH5: Q4 22 | AI5: Q1 23 | AJ5: Q2 23 | AK5: Q3 23 | AL5: Q4 23 | AM5: Q1 24 | AN5: Q2 24 | AO5: Q3 24 | AP5: Q4 24 | AQ5: Q1 25 | AR5: Q2 24 | AS5: Q3 24 | AT5: Q4 25 | AU5: Q1 26
B6: INCOME STATEMENT
B7: Service revenues | C7: 120588 | D7: 127905.85 | E7: 132875.31 | F7: 149009.96 | G7: 146388.13 | H7: 152262.83 | I7: 157979.33 | J7: =162333.484 -> 162333.48 | K7: 165016.29 | L7: 165077.66 | O7: 31942.191 | P7: 32803.989 | Q7: 33197.531 | R7: =E7-Q7-P7-O7 -> 34931.599 | S7: 36003.039 | T7: 36875.674 | U7: 37736.247 | V7: =F7-U7-T7-S7 -> 38395.003 | W7: 36881.974 | X7: 35540.807 | Y7: 36681.453 | Z7: =G7-Y7-X7-W7 -> 37283.9 | AA7: 37813.235 | AB7: 37849.072 | AC7: 38433.322 | AD7: =H7-AC7-AB7-AA7 -> 38167.204 | AE7: 39155.08 | AF7: 39725.035 | AG7: 39075.122 | AH7: =I7-AG7-AF7-AE7 -> 40024.098 | AI7: 39981.702 | AJ7: 40419.291 | AK7: 40661.107 | AL7: =J7-AK7-AJ7-AI7 -> 41271.384 | AM7: 41148.386 | AN7: 41077.304 | AO7: 41783.727 | AP7: =K7-AO7-AN7-AM7 -> 41006.872 | AQ7: 39853.267 | AR7: =80188.239-AQ7 -> 40334.972 | AS7: 41488.212 | AT7: =L7-AS7-AR7-AQ7 -> 43401.207 | AU7: 41964.725
B8: % growth | D8: =D7/C7-1 -> 0.060684727 | E8: =E7/D7-1 -> 0.03885246 | F8: =F7/E7-1 -> 0.12142702 | G8: =G7/F7-1 -> -0.017594991 | H8: =H7/G7-1 -> 0.040130978 | I8: =I7/H7-1 -> 0.037543647 | J8: =J7/I7-1 -> 0.02756151 | K8: =K7/J7-1 -> 0.016526504 | L8: =L7/K7-1 -> 0.00037189662 | S8: =S7/O7-1 -> 0.12713117 | T8: =T7/P7-1 -> 0.12412164 | U8: =U7/Q7-1 -> 0.13671848 | V8: =V7/R7-1 -> 0.099148167 | W8: =W7/S7-1 -> 0.0244128 | X8: =X7/T7-1 -> -0.036199121 | Y8: =Y7/U7-1 -> -0.027951746 | Z8: =Z7/V7-1 -> -0.02893874 | ... AU8: =AU7/AQ7-1 -> 0.052980801
B9: Non-service revenues | C9: 6193.657 | D9: 7374.878 | E9: 18297.496 | F9: 17650.374 | G9: 14131.408 | H9: 16233.625 | I9: 17061.388 | J9: 17830.971 | K9: 15569.771 | L9: 13162.186 | O9: 4995.435 | P9: 4704.35 | Q9: 3959.257 | R9: =E9-Q9-P9-O9 -> 4638.454 | S9: 4633.028 | T9: 4009.277 | U9: 4160.65 | V9: =F9-U9-T9-S9 -> 4847.419 | W9: 4309.378 | X9: 2081.971 | Y9: 4097.424 | Z9: =G9-Y9-X9-W9 -> 3642.635 | AA9: 5033.852 | AB9: 3713.592 | AC9: 3310.988 | AD9: =H9-AC9-AB9-AA9 -> 4175.193 | AE9: 4401.796 | AF9: 4039.956 | AG9: 3800.15 | AH9: =I9-AG9-AF9-AE9 -> 4819.486 | AI9: 5048.606 | AJ9: 4074.679 | AK9: 3607.018 | AL9: =J9-AK9-AJ9-AI9 -> 5100.668 | AM9: 4159.236 | AN9: 3240.327 | AO9: 3335.212 | AP9: =K9-AO9-AN9-AM9 -> 4834.996 | AQ9: 3902.414 | AR9: =7037.464-AQ9 -> 3135.05 | AS9: 2876.52 | AT9: =L9-AS9-AR9-AQ9 -> 3248.202 | AU9: 3741.727
B10: Total revenue | C10: =C7+C9 -> 126781.66 | D10: =D7+D9 -> 135280.73 | E10: =E7+E9 -> 151172.81 | F10: =F7+F9 -> 166660.34 | G10: =G7+G9 -> 160519.54 | H10: =H7+H9 -> 168496.46 | I10: =I7+I9 -> 175040.72 | J10: =J7+J9 -> 180164.45 | ... L10: =L7+L9 -> 178239.84 | O10: =O7+O9 -> 36937.626 | P10: =P7+P9 -> 37508.339 | Q10: =Q7+Q9 -> 37156.788 | R10: =R7+R9 -> 39570.053 | S10: =S7+S9 -> 40636.067 | T10: =T7+T9 -> 40884.951 | U10: =U7+U9 -> 41896.897 | V10: =V7+V9 -> 43242.422 | ... AU10: =AU7+AU9 -> 45706.452
B11: % growth | D11: =D10/C10-1 -> 0.06703707 | E11: =E10/D10-1 -> 0.11747479 | F11: =F10/E10-1 -> 0.10244919 | G11: =G10/F10-1 -> -0.036846169 | H11: =H10/G10-1 -> 0.049694361 | I11: =I10/H10-1 -> 0.038839184 | J11: =J10/I10-1 -> 0.029271657 | K11: =K10/J10-1 -> 0.002340112 | L11: =L10/K10-1 -> -0.012992232 | S11: =S10/O10-1 -> 0.10012666 | T11: =T10/P10-1 -> 0.090022968 | U11: =U10/Q10-1 -> 0.12757047 | V11: =V10/R10-1 -> 0.092806775 | W11: =W10/S10-1 -> 0.013664831 | X11: =X10/T10-1 -> -0.079789089 | Y11: =Y10/U10-1 -> -0.026685031 | Z11: =Z10/V10-1 -> -0.053555904 | ... AU11: =AU10/AQ10-1 -> 0.044583262
B12: Equity in net losses of associates and joint ventures | C12: -855.198 | D12: -846.177 | E12: -1249.603 | F12: -2554.782 | G12: -2367.44 | H12: 881.535 | I12: 1083.202 | J12: 2214.761 | K12: 3897.012 | L12: 6392.043 | O12: -263.842 | P12: -259.013 | Q12: -383.395 | R12: =E12-Q12-P12-O12 -> -343.353 | S12: -516.798 | T12: -730.719 | U12: -622.099 | V12: =F12-U12-T12-S12 -> -685.166 | W12: -708.21 | X12: -514.086 | Y12: -425.918 | Z12: =G12-Y12-X12-W12 -> -719.226 | AA12: 660.512 | AB12: -6.75 | AC12: 135.618 | AD12: =H12-AC12-AB12-AA12 -> 92.155 | AE12: 377.394 | AF12: 315.962 | AG12: 190.047 | AH12: =I12-AG12-AF12-AE12 -> 199.799 | AI12: 303.596 | AJ12: 573.703 | AK12: 636.607 | AL12: =J12-AK12-AJ12-AI12 -> 700.855 | AM12: 1215.928 | AN12: 1226.21 | AO12: 1221.621 | AP12: =K12-AO12-AN12-AM12 -> 233.253 | AQ12: 1816.376 | AR12: =3851.558-AQ12 -> 2035.182 | AS12: 1530.854 | AT12: =L12-AS12-AR12-AQ12 -> 1009.631 | AU12: 1950.344
B13: Gain on sale of controlling interest on data center business | F13: 0 | G13: 0 | H13: 0 | I13: 10511.945 | J13: 0 | K13: 0 | L13: 0 | AA13: 0 | AB13: 0 | AC13: 0 | AD13: =H13-AC13-AB13-AA13 -> 0 | AE13: 10511.945 | AF13: 0 | AG13: 0 | AH13: =I13-AG13-AF13-AE13 -> 0 | AI13: 0 | AJ13: 0 | AK13: 0 | AL13: =J13-AK13-AJ13-AI13 -> 0 | AM13: 0 | AN13: 0 | AO13: 0 | AP13: =K13-AO13-AN13-AM13 -> 0 | AQ13: 0 | AR13: =0-AQ13 -> 0 | AS13: 0 | AT13: =L13-AS13-AR13-AQ13 -> 0 | AU13: 0
B14: Gain on sale and leaseback of telecom towers - net | F14: 0 | G14: 0 | H14: 0 | I14: 8260.927 | J14: 7258.378 | K14: 3482.083 | L14: 380.717 | AA14: 0 | AB14: 0 | AC14: 0 | AD14: =H14-AC14-AB14-AA14 -> 0 | AE14: 0 | AF14: 0 | AG14: 1868.707 | AH14: =I14-AG14-AF14-AE14 -> 6392.22 | AI14: 2852.897 | AJ14: 2979.72 | AK14: 188.858 | AL14: =J14-AK14-AJ14-AI14 -> 1236.903 | AM14: 1315.171 | AN14: 2172.044 | AO14: 140.596 | AP14: =K14-AO14-AN14-AM14 -> -145.728 | AQ14: 300.166 | AR14: =300.583-AQ14 -> 0.417 | AS14: 80.134 | AT14: =L14-AS14-AR14-AQ14 -> 0 | AU14: 0
B15: Interest income | C15: 151.589 | D15: 139.581 | E15: 391.03 | F15: 500.437 | G15: 194.938 | H15: 149.508 | I15: 340.109 | J15: 677.57 | K15: 918.338 | L15: 821.815 | O15: 56.262 | P15: 84.428 | Q15: 82.239 | R15: =E15-Q15-P15-O15 -> 168.101 | S15: 195.676 | T15: 143.895 | U15: 96.995 | V15: =F15-U15-T15-S15 -> 63.871 | W15: 73.329 | X15: 89.663 | Y15: 10.036 | Z15: =G15-Y15-X15-W15 -> 21.91 | AA15: 15.448 | AB15: 33.381 | AC15: 46.848 | AD15: =H15-AC15-AB15-AA15 -> 53.831 | AE15: 49.42 | AF15: 46.478 | AG15: 71.375 | AH15: =I15-AG15-AF15-AE15 -> 172.836 | AI15: 112.774 | AJ15: 171.778 | AK15: 182.324 | AL15: =J15-AK15-AJ15-AI15 -> 210.694 | AM15: 202.125 | AN15: 167.351 | AO15: 256.258 | AP15: =K15-AO15-AN15-AM15 -> 292.604 | AQ15: 166.624 | AR15: =325.205-AQ15 -> 158.581 | AS15: 217.16 | AT15: =L15-AS15-AR15-AQ15 -> 279.45 | AU15: 208.695
B16: Gain on disposal of property and equipment – net | C16: 101.232 | D16: 38.455 | E16: 73.088 | F16: 43.012 | G16: 33.244 | H16: 152.565 | I16: 321.354 | J16: 371.655 | K16: 206.5 | L16: 283.559 | O16: 9.806 | P16: 10.502 | Q16: 47.774 | R16: =E16-Q16-P16-O16 -> 5.006 | S16: 17.351 | T16: 5.92 | U16: 16.62 | V16: =F16-U16-T16-S16 -> 3.121 | W16: 42.064 | X16: 8.427 | Y16: -0.08 | Z16: =G16-Y16-X16-W16 -> -17.167 | AA16: 53.19 | AB16: 32.934 | AC16: 23.922 | AD16: =H16-AC16-AB16-AA16 -> 42.519 | AE16: 10.751 | AF16: 101.382 | AG16: 73.562 | AH16: =I16-AG16-AF16-AE16 -> 135.659 | AI16: 34.901 | AJ16: 167.707 | AK16: 88.755 | AL16: =J16-AK16-AJ16-AI16 -> 80.292 | AM16: 141.217 | AN16: 264.084 | AO16: -163.993 | AP16: =K16-AO16-AN16-AM16 -> -34.808 | AQ16: 32.769 | AR16: =33.773-AQ16 -> 1.004 | AS16: 96.911 | AT16: =L16-AS16-AR16-AQ16 -> 152.875 | AU16: 15.329
B17: Other income – net | C17: 983.186 | D17: =1889.901+701.653 -> 2591.554 | E17: 695.405 | F17: 1047.007 | G17: 3817.211 | H17: 4656.647 | I17: 2474.814 | J17: 959.898 | K17: 1734.944 | L17: 3870.814 | O17: 947.901 | P17: 223.995 | Q17: 230.162 | R17: =E17-Q17-P17-O17 -> -706.653 | S17: 124.404 | T17: 172.925 | U17: 369.572 | V17: =F17-U17-T17-S17 -> 380.106 | W17: 396.263 | X17: 1105.173 | Y17: -29.766 | Z17: =G17-Y17-X17-W17 -> 2345.541 | AA17: 15.273 | AB17: 47.586 | AC17: -54.266 | AD17: =H17-AC17-AB17-AA17 -> 4648.054 | AE17: =10731.97-AE13 -> 220.025 | AF17: 481.528 | AG17: 1116.062 | AH17: =I17-AG17-AF17-AE17 -> 657.199 | AI17: 79.701 | AJ17: 221.229 | AK17: -16.262 | AL17: =J17-AK17-AJ17-AI17 -> 675.23 | AM17: 194.023 | AN17: 530.68 | AO17: 501.046 | AP17: =K17-AO17-AN17-AM17 -> 509.195 | AQ17: 2727.091 | AR17: =2850.649-AQ17 -> 123.558 | AS17: 365.146 | AT17: =L17-AS17-AR17-AQ17 -> 655.019 | AU17: 1079.458
B18: Cost of inventories sold | C18: -11914.114 | D18: -13013.437 | E18: -18645.314 | F18: -18554.814 | G18: -16406.196 | H18: =-17307.774 -> -17307.774 | I18: -17691.677 | J18: -18217.044 | K18: -16428.713 | L18: =-13487.058 -> -13487.058 | O18: -4745.987 | P18: -4665.072 | Q18: -4222.212 | R18: =E18-Q18-P18-O18 -> -5012.043 | S18: -4615.626 | T18: -4497.012 | U18: -4142.913 | V18: =F18-U18-T18-S18 -> -5299.263 | W18: -4530.397 | X18: -2449.531 | Y18: -5167.546 | Z18: =G18-Y18-X18-W18 -> -4258.722 | AA18: -5457.519 | AB18: -4100.946 | AC18: -3661.397 | AD18: =H18-AC18-AB18-AA18 -> -4087.912 | AE18: -4735.168 | AF18: -4164.008 | AG18: -3973.387 | AH18: =I18-AG18-AF18-AE18 -> -4819.114 | AI18: -5353.226 | AJ18: -4199.18 | AK18: -3778.17 | AL18: =J18-AK18-AJ18-AI18 -> -4886.468 | AM18: -4166.309 | AN18: -3486.354 | AO18: -3856.457 | AP18: =K18-AO18-AN18-AM18 -> -4919.593 | AQ18: -3921.606 | AR18: =-7118.954-AQ18 -> -3197.348 | AS18: -2973.152 | AT18: =L18-AS18-AR18-AQ18 -> -3394.952 | AU18: -3858.726
B19: General, selling and administrative expenses | C19: -52471.053 | D19: -56608.922 | E19: -57742.131 | F19: -64471.409 | G19: -64913.355 | H19: -71366.092 | I19: -74227.306 | J19: -74681.05 | K19: -72836.753 | L19: -72207.939 | O19: -13429.954 | P19: -13056.455 | Q19: -13988.066 | R19: =E19-Q19-P19-O19 -> -17267.656 | S19: -14295.58 | T19: -15568.88 | U19: -16742.046 | V19: =F19-U19-T19-S19 -> -17864.903 | W19: -15178.125 | X19: -14771.669 | Y19: -16515.615 | Z19: =G19-Y19-X19-W19 -> -18447.946 | AA19: -17377.103 | AB19: -17392.453 | AC19: -17301.232 | AD19: =H19-AC19-AB19-AA19 -> -19295.304 | AE19: -17787.777 | AF19: -17557.402 | AG19: -18064.688 | AH19: =I19-AG19-AF19-AE19 -> -20817.439 | AI19: -17605.23 | AJ19: -19001.16 | AK19: -18859.526 | AL19: =J19-AK19-AJ19-AI19 -> -19215.134 | AM19: -18407.255 | AN19: -18104.775 | AO19: -18743.558 | AP19: =K19-AO19-AN19-AM19 -> -17581.165 | AQ19: -17579.632 | AR19: =-35262.304-AQ19 -> -17682.672 | AS19: -18130.298 | AT19: =L19-AS19-AR19-AQ19 -> -18815.337 | AU19: -18532.047
B20: Interconnect costs | C20: -9623.127 | D20: -7852.336 | E20: -5677.375 | F20: -3982.873 | G20: -1007.234 | H20: -1182.381 | I20: -1362.309 | J20: -1367.052 | K20: -1619.788 | L20: -1911.763 | O20: -1800.006 | P20: -1711.156 | Q20: -1435.963 | R20: =E20-Q20-P20-O20 -> -730.25 | S20: -806.821 | T20: -944.464 | U20: -1064.175 | V20: =F20-U20-T20-S20 -> -1167.413 | W20: -303.573 | X20: -241.851 | Y20: -274.817 | Z20: =G20-Y20-X20-W20 -> -186.993 | AA20: -284.058 | AB20: -290.496 | AC20: -271.367 | AD20: =H20-AC20-AB20-AA20 -> -336.46 | AE20: -323.916 | AF20: -320.193 | AG20: -308.656 | AH20: =I20-AG20-AF20-AE20 -> -409.544 | AI20: -360.992 | AJ20: -343.597 | AK20: -308.478 | AL20: =J20-AK20-AJ20-AI20 -> -353.985 | AM20: -363.299 | AN20: -407.952 | AO20: -415.507 | AP20: =K20-AO20-AN20-AM20 -> -433.03 | AQ20: -441.894 | AR20: =-850.558-AQ20 -> -408.664 | AS20: -522.68 | AT20: =L20-AS20-AR20-AQ20 -> -538.525 | AU20: -508.791
B21: Depreciation and amortisation | C21: -23848.646 | D21: -27512.689 | E21: -30421.721 | F21: -34143.541 | G21: -35412.038 | H21: -41132.992 | I21: -45653.296 | J21: -47356.043 | K21: -50473.04 | L21: -53871.127 | O21: -7285.383 | P21: -7287.645 | Q21: -7741.981 | R21: =E21-Q21-P21-O21 -> -8106.712 | S21: -7995.932 | T21: -8457.483 | U21: -8545.086 | V21: =F21-U21-T21-S21 -> -9145.04 | W21: -8639.488 | X21: -8881.131 | Y21: -9057.167 | Z21: =G21-Y21-X21-W21 -> -8834.252 | AA21: -9173.234 | AB21: -9375.231 | AC21: -10652.961 | AD21: =H21-AC21-AB21-AA21 -> -11931.566 | AE21: -11049.426 | AF21: -11253.333 | AG21: -10991.014 | AH21: =I21-AG21-AF21-AE21 -> -12359.523 | AI21: -11154.876 | AJ21: -11735.062 | AK21: -11604.508 | AL21: =J21-AK21-AJ21-AI21 -> -12861.597 | AM21: -12299.948 | AN21: -12460.789 | AO21: -12540.699 | AP21: =K21-AO21-AN21-AM21 -> -13171.604 | AQ21: -13441.415 | AR21: =-26429.849-AQ21 -> -12988.434 | AS21: -13551.984 | AT21: =L21-AS21-AR21-AQ21 -> -13889.294 | AU21: -14360.804
B22: Impairment and other losses | C22: -3271.301 | D22: -5423.366 | E22: -4787.644 | F22: -4913.137 | G22: -10207.599 | H22: -5566.939 | I22: -4906.747 | J22: -5463.979 | K22: -4691.29 | L22: -3827.345 | O22: -1011.67 | P22: -1655.97 | Q22: -1160.599 | R22: =E22-Q22-P22-O22 -> -959.405 | S22: -1149.529 | T22: -1346.856 | U22: -1292.858 | V22: =F22-U22-T22-S22 -> -1123.894 | W22: -1051.101 | X22: -2844.799 | Y22: -1126.858 | Z22: =G22-Y22-X22-W22 -> -5184.841 | AA22: -1605.51 | AB22: -851.574 | AC22: -1100.286 | AD22: =H22-AC22-AB22-AA22 -> -2009.569 | AE22: -1480.383 | AF22: -1456.959 | AG22: -1423.111 | AH22: =I22-AG22-AF22-AE22 -> -546.294 | AI22: -1330.008 | AJ22: -1200.515 | AK22: -1160.954 | AL22: =J22-AK22-AJ22-AI22 -> -1772.502 | AM22: -1198.969 | AN22: -1035.493 | AO22: -730.566 | AP22: =K22-AO22-AN22-AM22 -> -1726.262 | AQ22: -1199.368 | AR22: =-2235.924-AQ22 -> -1036.556 | AS22: -901.66 | AT22: =L22-AS22-AR22-AQ22 -> -689.761 | AU22: -791.38
B23: Operating profit | C23: =C10+SUM(C12:C22) -> 26034.228 | D23: =D10+SUM(D12:D22) -> 26793.394 | E23: =E10+SUM(E12:E22) -> 33808.541 | F23: =F10+SUM(F12:F22) -> 39630.237 | G23: =G10+SUM(G12:G22) -> 34251.073 | H23: =H10+SUM(H12:H22) -> 37780.535 | I23: =I10+SUM(I12:I22) -> 54191.739 | J23: =J10+SUM(J12:J22) -> 44561.549 | ... L23: =L10+SUM(L12:L22) -> 44683.56 | O23: =O10+SUM(O12:O22) -> 9414.753 | P23: =P10+SUM(P12:P22) -> 9191.953 | Q23: =Q10+SUM(Q12:Q22) -> 8584.747 | R23: =R10+SUM(R12:R22) -> 6617.088 | S23: =S10+SUM(S12:S22) -> 11593.212 | T23: =T10+SUM(T12:T22) -> 9662.277 | U23: =U10+SUM(U12:U22) -> 9970.907 | V23: =V10+SUM(V12:V22) -> 8403.841 | ... AU23: =AU10+SUM(AU12:AU22) -> 10908.53
B24: % margin | C24: =C23/C10 -> 0.20534696 | D24: =D23/D10 -> 0.19805773 | E24: =E23/E10 -> 0.22364168 | F24: =F23/F10 -> 0.23779045 | G24: =G23/G10 -> 0.21337634 | H24: =H23/H10 -> 0.22422154 | I24: =I23/I10 -> 0.30959504 | J24: =J23/J10 -> 0.24733818 | ... L24: =L23/L10 -> 0.25069344 | O24: =O23/O10 -> 0.25488246 | P24: =P23/P10 -> 0.24506425 | Q24: =Q23/Q10 -> 0.23104115 | R24: =R23/R10 -> 0.16722464 | S24: =S23/S10 -> 0.28529365 | T24: =T23/T10 -> 0.23632845 | U24: =U23/U10 -> 0.23798677 | V24: =V23/V10 -> 0.19434251 | ... AU24: =AU23/AU10 -> 0.23866499
B25: Finance costs | C25: -4096.826 | D25: -5251.692 | E25: -6195.225 | F25: -6802.861 | G25: -7111.41 | H25: -8740.763 | I25: -10091.289 | J25: -12145.879 | K25: -14444.27 | L25: -16456.49 | O25: -2373.005 | P25: -1533.206 | Q25: -1550.943 | R25: =E25-Q25-P25-O25 -> -738.071 | S25: -1797.252 | T25: -1725.179 | U25: -1670.25 | V25: =F25-U25-T25-S25 -> -1610.18 | W25: -1655.9 | X25: -1690.463 | Y25: -1830.308 | Z25: =G25-Y25-X25-W25 -> -1934.739 | AA25: -1873.403 | AB25: -2026.395 | AC25: -2357.964 | AD25: =H25-AC25-AB25-AA25 -> -2483.001 | AE25: -2422.935 | AF25: -2161.804 | AG25: -2542.719 | AH25: =I25-AG25-AF25-AE25 -> -2963.831 | AI25: -2841.469 | AJ25: -2862.297 | AK25: -3156.529 | AL25: =J25-AK25-AJ25-AI25 -> -3285.584 | AM25: -3279.731 | AN25: -3437.259 | AO25: -3794.046 | AP25: =K25-AO25-AN25-AM25 -> -3933.234 | AQ25: -3956.892 | AR25: =-7959.65-AQ25 -> -4002.758 | AS25: -4145.716 | AT25: =L25-AS25-AR25-AQ25 -> -4351.124 | AU25: -4381.943
B26: Profit before tax | C26: =C23+C25 -> 21937.402 | D26: =D23+D25 -> 21541.702 | E26: =E23+E25 -> 27613.316 | F26: =F23+F25 -> 32827.376 | G26: =G23+G25 -> 27139.663 | H26: =H23+H25 -> 29039.772 | I26: =I23+I25 -> 44100.45 | J26: =J23+J25 -> 32415.67 | ... L26: =L23+L25 -> 28227.07 | O26: =O23+O25 -> 7041.748 | P26: =P23+P25 -> 7658.747 | Q26: =Q23+Q25 -> 7033.804 | R26: =R23+R25 -> 5879.017 | S26: =S23+S25 -> 9795.96 | T26: =T23+T25 -> 7937.098 | U26: =U23+U25 -> 8300.657 | V26: =V23+V25 -> 6793.661 | ... AU26: =AU23+AU25 -> 6526.587
B27: Current tax | C27: -5556.965 | D27: -6005.42 | E27: -7259.985 | F27: -8488.595 | G27: -8139.602 | H27: -4903.568 | I27: -9696.533 | J27: -7853.664 | K27: -6919.731 | L27: -5593.063 | O27: -1850.957 | P27: -1705.047 | Q27: -2054.897 | R27: =E27-Q27-P27-O27 -> -1649.084 | S27: -2062.55 | T27: -2100.331 | U27: -2486.62 | V27: =F27-U27-T27-S27 -> -1839.094 | W27: -2162.421 | X27: -2687.981 | Y27: -1807.762 | Z27: =G27-Y27-X27-W27 -> -1481.438 | AA27: -1036.841 | AB27: -1438.294 | AC27: -1606.394 | AD27: =H27-AC27-AB27-AA27 -> -822.039 | AE27: -2155.144 | AF27: -650.376 | AG27: -2121.041 | AH27: =I27-AG27-AF27-AE27 -> -4769.972 | AI27: -2393.583 | AJ27: -2897.977 | AK27: -1095.112 | AL27: =J27-AK27-AJ27-AI27 -> -1466.992 | AM27: -1804.15 | AN27: -2089.572 | AO27: -1002.599 | AP27: =K27-AO27-AN27-AM27 -> -2023.41 | AQ27: -857.727 | AR27: =-1873.471-AQ27 -> -1015.744 | AS27: -831.584 | AT27: =L27-AS27-AR27-AQ27 -> -2888.008 | AU27: -936.854
B28: Deferred tax | C28: -491.938 | D28: -452.069 | E28: -1727.388 | F28: -2055.024 | G28: -377.016 | H28: -412.347 | I28: 200.132 | J28: =16.004 -> 16.004 | K28: 874.417 | L28: 628.053 | O28: -511.025 | P28: -668.439 | Q28: -161.029 | R28: =E28-Q28-P28-O28 -> -386.895 | S28: -1003.628 | T28: -520.038 | U28: -176.775 | V28: =F28-U28-T28-S28 -> -354.583 | W28: -879.212 | X28: 155.644 | Y28: -159.719 | Z28: =G28-Y28-X28-W28 -> 506.271 | AA28: 552.668 | AB28: -492.631 | AC28: -24.115 | AD28: =H28-AC28-AB28-AA28 -> -448.269 | AE28: -1109.61 | AF28: -1126.932 | AG28: 47.736 | AH28: =I28-AG28-AF28-AE28 -> 2388.938 | AI28: -102.465 | AJ28: 734.58 | AK28: -396.358 | AL28: =J28-AK28-AJ28-AI28 -> -219.753 | AM28: -60.491 | AN28: 85.144 | AO28: 28.429 | AP28: =K28-AO28-AN28-AM28 -> 821.335 | AQ28: -424.809 | AR28: =-419.935-AQ28 -> 4.874 | AS28: -343.86 | AT28: =L28-AS28-AR28-AQ28 -> 1391.848 | AU28: -35.99
B29: Net profit/loss | C29: =C26+C28+C27 -> 15888.499 | D29: =D26+D28+D27 -> 15084.213 | E29: =E26+E28+E27 -> 18625.943 | F29: =F26+F28+F27 -> 22283.757 | G29: =G26+G28+G27 -> 18623.045 | H29: =H26+H28+H27 -> 23723.857 | I29: =I26+I28+I27 -> 34604.049 | J29: =J26+J28+J27 -> 24578.01 | ... L29: =L26+L28+L27 -> 23262.06 | O29: =O26+O28+O27 -> 4679.766 | P29: =P26+P28+P27 -> 5285.261 | Q29: =Q26+Q28+Q27 -> 4817.878 | R29: =R26+R28+R27 -> 3843.038 | S29: =S26+S28+S27 -> 6729.782 | T29: =T26+T28+T27 -> 5316.729 | U29: =U26+U28+U27 -> 5637.262 | V29: =V26+V28+V27 -> 4599.984 | ... AU29: =AU26+AU28+AU27 -> 5553.743
B30: % margin | C30: =C29/C10 -> 0.12532175 | D30: =D29/D10 -> 0.11150304 | E30: =E29/E10 -> 0.12320961 | F30: =F29/F10 -> 0.13370762 | G30: =G29/G10 -> 0.11601731 | H30: =H29/H10 -> 0.14079736 | I30: =I29/I10 -> 0.19769142 | J30: =J29/J10 -> 0.13641986 | ... L30: =L29/L10 -> 0.13050988 | O30: =O29/O10 -> 0.12669374 | P30: =P29/P10 -> 0.14090896 | Q30: =Q29/Q10 -> 0.12966347 | R30: =R29/R10 -> 0.09711986 | S30: =S29/S10 -> 0.16561106 | T30: =T29/T10 -> 0.13004122 | U30: =U29/U10 -> 0.13455082 | V30: =V29/V10 -> 0.10637665 | ... AU30: =AU29/AU10 -> 0.12150895
B32: Marginal tax rate | C32: =C27/C26 -> -0.25331008 | D32: =D27/D26 -> -0.27878113 | E32: =E27/E26 -> -0.26291609 | F32: =F27/F26 -> -0.25858281 | G32: =G27/G26 -> -0.29991537 | H32: =H27/H26 -> -0.16885697 | I32: =I27/I26 -> -0.21987379 | J32: =J27/J26 -> -0.24227986 | ... L32: =L27/L26 -> -0.19814536 | O32: =O27/O26 -> -0.26285476 | P32: =P27/P26 -> -0.22262741 | Q32: =Q27/Q26 -> -0.2921459 | R32: =R27/R26 -> -0.28050336 | S32: =S27/S26 -> -0.21055108 | T32: =T27/T26 -> -0.26462203 | U32: =U27/U26 -> -0.29956906 | V32: =V27/V26 -> -0.27070735 | ... AU32: =AU27/AU26 -> -0.14354424
B33: Defered tax rate | C33: =C28/C26 -> -0.022424624 | D33: =D28/D26 -> -0.020985761 | E33: =E28/E26 -> -0.062556341 | F33: =F28/F26 -> -0.062600922 | G33: =G28/G26 -> -0.013891698 | H33: =H28/H26 -> -0.014199388 | I33: =I28/I26 -> 0.0045380943 | J33: =J28/J26 -> 0.00049371184 | ... L33: =L28/L26 -> 0.022250025 | O33: =O28/O26 -> -0.072570759 | P33: =P28/P26 -> -0.087277854 | Q33: =Q28/Q26 -> -0.022893586 | R33: =R28/R26 -> -0.065809471 | S33: =S28/S26 -> -0.10245326 | T33: =T28/T26 -> -0.065519917 | U33: =U28/U26 -> -0.021296507 | V33: =V28/V26 -> -0.052193214 | ... AU33: =AU28/AU26 -> -0.0055143676
B35: As % of Net sales unless stated otherwise
B36: =B18 -> Cost of inventories sold | C36: =-C18/C7 -> 0.09880016 | D36: =-D18/D7 -> 0.10174231 | E36: =-E18/E7 -> 0.14032189 | F36: =-F18/F7 -> 0.12452063 | G36: =-G18/G7 -> 0.11207326 | H36: =-H18/H7 -> 0.11367038 | I36: =-I18/I7 -> 0.11198729 | J36: =-J18/J7 -> 0.11221988 | ... L36: =-L18/L7 -> 0.081701292 | O36: =-O18/O7 -> 0.14858051 | P36: =-P18/P7 -> 0.14221051 | Q36: =-Q18/Q7 -> 0.12718452 | R36: =-R18/R7 -> 0.14348164 | S36: =-S18/S7 -> 0.12820101 | T36: =-T18/T7 -> 0.12195064 | U36: =-U18/U7 -> 0.10978604 | V36: =-V18/V7 -> 0.1380196 | ... AU36: =-AU18/AU7 -> 0.091951657
B37: =B19 -> General, selling and administrative expenses | C37: =-C19/C7 -> 0.43512664 | D37: =-D19/D7 -> 0.44258273 | E37: =-E19/E7 -> 0.43455877 | F37: =-F19/F7 -> 0.43266509 | G37: =-G19/G7 -> 0.44343317 | H37: =-H19/H7 -> 0.4687033 | I37: =-I19/I7 -> 0.46985453 | J37: =-J19/J7 -> 0.46004711 | ... L37: =-L19/L7 -> 0.437418 | O37: =-O19/O7 -> 0.42044561 | P37: =-P19/P7 -> 0.39801425 | Q37: =-Q19/Q7 -> 0.42135862 | R37: =-R19/R7 -> 0.49432767 | S37: =-S19/S7 -> 0.39706593 | T37: =-T19/T7 -> 0.4221992 | U37: =-U19/U7 -> 0.44365954 | V37: =-V19/V7 -> 0.4652924 | ... AU37: =-AU19/AU7 -> 0.44161011
B38: =B20 -> Interconnect costs | C38: =-C20/C7 -> 0.079801695 | D38: =-D20/D7 -> 0.06139153 | E38: =-E20/E7 -> 0.042727088 | F38: =-F20/F7 -> 0.026728904 | G38: =-G20/G7 -> 0.0068805713 | H38: =-H20/H7 -> 0.0077653947 | I38: =-I20/I7 -> 0.0086233367 | J38: =-J20/J7 -> 0.0084212571 | ... L38: =-L20/L7 -> 0.011580992 | O38: =-O20/O7 -> 0.056351989 | P38: =-P20/P7 -> 0.052163046 | Q38: =-Q20/Q7 -> 0.043255114 | R38: =-R20/R7 -> 0.020905141 | S38: =-S20/S7 -> 0.022409803 | T38: =-T20/T7 -> 0.025612115 | U38: =-U20/U7 -> 0.02820034 | V38: =-V20/V7 -> 0.030405337 | ... AU38: =-AU20/AU7 -> 0.012124254
B39: =B23 -> Operating profit | C39: =C23/C7 -> 0.21589401 | D39: =D23/D7 -> 0.20947747 | E39: =E23/E7 -> 0.2544381 | F39: =F23/F7 -> 0.26595696 | G39: =G23/G7 -> 0.23397438 | H39: =H23/H7 -> 0.2481271 | I39: =I23/I7 -> 0.34303056 | J39: =J23/J7 -> 0.27450621 | ... L39: =L23/L7 -> 0.27068206 | O39: =O23/O7 -> 0.29474349 | P39: =P23/P7 -> 0.28020839 | Q39: =Q23/Q7 -> 0.25859595 | R39: =R23/R7 -> 0.18942986 | S39: =S23/S7 -> 0.32200648 | T39: =T23/T7 -> 0.26202306 | U39: =U23/U7 -> 0.26422625 | V39: =V23/V7 -> 0.21887851 | ... AU39: =AU23/AU7 -> 0.25994523
B40: PBT | C40: =C26/C7 -> 0.18192027 | D40: =D26/D7 -> 0.16841842 | E40: =E26/E7 -> 0.20781375 | F40: =F26/F7 -> 0.22030323 | G40: =G26/G7 -> 0.18539524 | H40: =H26/H7 -> 0.19072134 | I40: =I26/I7 -> 0.27915328 | J40: =J26/J7 -> 0.19968567 | ... L40: =L26/L7 -> 0.17099267 | O40: =O26/O7 -> 0.22045288 | P40: =P26/P7 -> 0.23346999 | Q40: =Q26/Q7 -> 0.21187732 | R40: =R26/R7 -> 0.16830083 | S40: =S26/S7 -> 0.27208703 | T40: =T26/T7 -> 0.2152394 | U40: =U26/U7 -> 0.21996509 | V40: =V26/V7 -> 0.17694128 | ... AU40: =AU26/AU7 -> 0.15552555
B41: Income Tax Expense as a % PBT | C41: =-(C28+C27)/C26 -> 0.2757347 | D41: =-(D28+D27)/D26 -> 0.29976689 | E41: =-(E28+E27)/E26 -> 0.32547243 | F41: =-(F28+F27)/F26 -> 0.32118373 | G41: =-(G28+G27)/G26 -> 0.31380707 | H41: =-(H28+H27)/H26 -> 0.18305636 | I41: =-(I28+I27)/I26 -> 0.21533569 | J41: =-(J28+J27)/J26 -> 0.24178615 | ... L41: =-(L28+L27)/L26 -> 0.17589534 | O41: =-(O28+O27)/O26 -> 0.33542552 | P41: =-(P28+P27)/P26 -> 0.30990526 | Q41: =-(Q28+Q27)/Q26 -> 0.31503949 | R41: =-(R28+R27)/R26 -> 0.34631283 | S41: =-(S28+S27)/S26 -> 0.31300434 | T41: =-(T28+T27)/T26 -> 0.33014195 | U41: =-(U28+U27)/U26 -> 0.32086557 | V41: =-(V28+V27)/V26 -> 0.32290057 | ... AU41: =-(AU28+AU27)/AU26 -> 0.14905861
B42: Finance costs as % of debt | C42: =-C25/C120 -> 0.040471036 | D42: =-D25/D120 -> 0.039928105 | E42: =-E25/E120 -> 0.04178005 | F42: =-F25/F120 -> 0.048756818 | G42: =-G25/G120 -> 0.042000611 | H42: =-H25/H120 -> 0.038014405 | I42: =-I25/I120 -> 0.03043887 | J42: =-J25/J120 -> 0.031714412 | ... L42: =-L25/L120 -> 0.038184639 | R42: =-SUM(O25:R25)/R120 -> 0.04178005 | S42: =-SUM(P25:S25)/S120 -> 0.039649674 | T42: =-SUM(Q25:T25)/T120 -> 0.042916506 | U42: =-SUM(R25:U25)/U120 -> 0.043841899 | V42: =-SUM(S25:V25)/V120 -> 0.048756818 | W42: =-SUM(T25:W25)/W120 -> 0.044854294 | X42: =-SUM(U25:X25)/X120 -> 0.042992165 | Y42: =-SUM(V25:Y25)/Y120 -> 0.040411863 | ... AU42: =-SUM(AR25:AU25)/AU120 -> 0.039027822
B43: Working capital/sales | C43: =C62/C10 -> -0.091285222 | D43: =D62/D10 -> -0.022931862 | E43: =E62/E10 -> -0.05209814 | F43: =F62/F10 -> -0.010603663 | G43: =G62/G10 -> -0.058039052 | H43: =H62/H10 -> -0.059711837 | I43: =I62/I10 -> -0.08333819 | J43: =J62/J10 -> -0.025916028 | ... L43: =L62/L10 -> -0.045282703 | R43: =R99/R84 -> -0.20315754 | S43: =S99/S84 -> -0.19512668 | T43: =T99/T84 -> -0.20456439 | U43: =U99/U84 -> -0.23055836 | V43: =V99/V84 -> -0.18676785 | W43: =W99/W84 -> -0.17499025 | X43: =X99/X84 -> -0.16964495 | Y43: =Y99/Y84 -> -0.20600656 | ... AU43: =AU99/AU84 -> -0.2951051
B45: depreciation/capex | C45: =C21/SUM(C66:C67) -> 0.41116757 | D45: =D21/SUM(D66:D67) -> 0.50726414 | E45: =E21/SUM(E66:E67) -> 0.7123231 | F45: =F21/SUM(F66:F67) -> 0.61252359 | G45: =G21/SUM(G66:G67) -> 0.5703022 | H45: =H21/SUM(H66:H67) -> 0.43682969 | I45: =I21/SUM(I66:I67) -> 0.46671743 | J45: =J21/SUM(J66:J67) -> 0.64876373 | ... L45: =L21/SUM(L66:L67) -> 1.2233353 | O45: =O21/SUM(O66:O67) -> 1.1017263 | P45: =P21/SUM(P66:P67) -> 0.4469809 | Q45: =Q21/SUM(Q66:Q67) -> 0.8145585 | R45: =R21/SUM(R66:R67) -> 0.78810055 | S45: =S21/SUM(S66:S67) -> 0.81332439 | T45: =T21/SUM(T66:T67) -> 0.78870843 | U45: =U21/SUM(U66:U67) -> 0.59578461 | V45: =V21/SUM(V66:V67) -> 0.43870664 | ... AU45: =AU21/SUM(AU66:AU67) -> 1.0924997
B46: impairment/capex | C46: =C22/SUM(C66:C67) -> 0.05639955 | D46: =D22/SUM(D66:D67) -> 0.099993101 | E46: =E22/SUM(E66:E67) -> 0.11210245 | F46: =F22/SUM(F66:F67) -> 0.088140018 | G46: =G22/SUM(G66:G67) -> 0.16439088 | H46: =H22/SUM(H66:H67) -> 0.059120529 | I46: =I22/SUM(I66:I67) -> 0.050162082 | J46: =J22/SUM(J66:J67) -> 0.074854891 | ... L46: =L22/SUM(L66:L67) -> 0.086913465 | O46: =O22/SUM(O66:O67) -> 0.15298899 | P46: =P22/SUM(P66:P67) -> 0.10156737 | Q46: =Q22/SUM(Q66:Q67) -> 0.12211032 | R46: =R22/SUM(R66:R67) -> 0.093269332 | S46: =S22/SUM(S66:S67) -> 0.11692695 | T46: =T22/SUM(T66:T67) -> 0.12560199 | U46: =U22/SUM(U66:U67) -> 0.090141269 | V46: =V22/SUM(V66:V67) -> 0.053915539 | ... AU46: =AU22/SUM(AU66:AU67) -> 0.060204319
B48: EBITDA | C48: =C3 -> 42735 | D48: =D3 -> 43100 | E48: =E3 -> 43465 | F48: =F3 -> 43830 | G48: =G3 -> 44196 | H48: =H3 -> 44561 | I48: =I3 -> 44926 | J48: =J3 -> 45291 | ... L48: =L3 -> 46022 | O48: =O3 -> 43190 | P48: =P3 -> 43281 | Q48: =Q3 -> 43373 | R48: =R3 -> 43465 | S48: =S3 -> 43555 | T48: =T3 -> 43646 | U48: =U3 -> 43738 | V48: =V3 -> 43830 | ... AU48: =AU3 -> 46112
B49: =B23 -> Operating profit | C49: =C23 -> 26034.228 | D49: =D23 -> 26793.394 | E49: =E23 -> 33808.541 | F49: =F23 -> 39630.237 | G49: =G23 -> 34251.073 | H49: =H23 -> 37780.535 | I49: =I23 -> 54191.739 | ... L49: =L23 -> 44683.56 | O49: =O23 -> 9414.753 | P49: =P23 -> 9191.953 | Q49: =Q23 -> 8584.747 | R49: =R23 -> 6617.088 | S49: =S23 -> 11593.212 | T49: =T23 -> 9662.277 | U49: =U23 -> 9970.907 | V49: =V23 -> 8403.841 | ... AU49: =AU23 -> 10908.53
B50: Depreciation & amortisation | C50: 23848.646 | D50: 27512.689 | E50: 30421.721 | F50: 34143.541 | G50: 35412.038 | H50: 41132.992 | I50: 45653.296 | J50: 47356.043 | K50: 50473.04 | L50: 53871.127 | O50: 7285.383 | P50: 7287.645 | Q50: 7741.981 | R50: =E50-Q50-P50-O50 -> 8106.712 | S50: 7995.932 | T50: 8457.483 | U50: 8545.086 | V50: =F50-U50-T50-S50 -> 9145.04 | W50: 8639.488 | X50: 8881.131 | Y50: 9057.167 | Z50: =G50-Y50-X50-W50 -> 8834.252 | AA50: 9173.234 | AB50: 9375.231 | AC50: 10652.961 | AD50: =H50-AC50-AB50-AA50 -> 11931.566 | AE50: 11049.426 | AF50: 11253.333 | AG50: 10991.014 | AH50: =I50-AG50-AF50-AE50 -> 12359.523 | AI50: 11154.876 | AJ50: 11735.062 | AK50: 11604.508 | AL50: =J50-AK50-AJ50-AI50 -> 12861.597 | AM50: 12299.948 | AN50: 12460.789 | AO50: 12540.699 | AP50: =K50-AO50-AN50-AM50 -> 13171.604 | AQ50: 13441.415 | AR50: =26429.849-AQ50 -> 12988.434 | AS50: =39981.833-AR50-AQ50 -> 13551.984 | AT50: =L50-AS50-AR50-AQ50 -> 13889.294 | AU50: 14360.804
B51: EBITDA | C51: =C49+C50 -> 49882.874 | D51: =D49+D50 -> 54306.083 | E51: =E49+E50 -> 64230.262 | F51: =F49+F50 -> 73773.778 | G51: =G49+G50 -> 69663.111 | H51: =H49+H50 -> 78913.527 | I51: =I49+I50 -> 99845.035 | J51: =J49+J50 -> 91917.592 | ... L51: =L49+L50 -> 98554.687 | O51: =O49+O50 -> 16700.136 | P51: =P49+P50 -> 16479.598 | Q51: =Q49+Q50 -> 16326.728 | R51: =R49+R50 -> 14723.8 | S51: =S49+S50 -> 19589.144 | T51: =T49+T50 -> 18119.76 | U51: =U49+U50 -> 18515.993 | V51: =V49+V50 -> 17548.881 | ... AU51: =AU49+AU50 -> 25269.334
B52: % growth | D52: =(D51-C51)/C51 -> 0.088671896 | E52: =(E51-D51)/D51 -> 0.18274526 | F52: =(F51-E51)/E51 -> 0.14858286 | G52: =(G51-F51)/F51 -> -0.055719893 | H52: =(H51-G51)/G51 -> 0.13278787 | I52: =(I51-H51)/H51 -> 0.26524613 | J52: =(J51-I51)/I51 -> -0.079397468 | K52: =(K51-J51)/J51 -> 0.036236817 | L52: =(L51-K51)/K51 -> 0.034712334 | S52: =S51/O51-1 -> 0.17299308 | T52: =T51/P51-1 -> 0.099526821 | U52: =U51/Q51-1 -> 0.13409086 | V52: =V51/R51-1 -> 0.19187173 | W52: =W51/S51-1 -> 0.01748203 | X52: =X51/T51-1 -> -0.0063828108 | Y52: =Y51/U51-1 -> -0.068464057 | Z52: =Z51/V51-1 -> -0.17492796 | ... AU52: =AU51/AQ51-1 -> -0.015079119
B53: % margin | C53: =C51/C10 -> 0.39345497 | D53: =D51/D10 -> 0.40143251 | E53: =E51/E10 -> 0.42487974 | F53: =F51/F10 -> 0.44265948 | G53: =G51/G10 -> 0.43398523 | H53: =H51/H10 -> 0.46833938 | I53: =I51/I10 -> 0.57041032 | J53: =J51/J10 -> 0.51018716 | ... L53: =L51/L10 -> 0.55293297 | O53: =O51/O10 -> 0.4521172 | P53: =P51/P10 -> 0.43935825 | Q53: =Q51/Q10 -> 0.43940095 | R53: =R51/R10 -> 0.37209452 | S53: =S51/S10 -> 0.48206299 | T53: =T51/T10 -> 0.44318899 | U53: =U51/U10 -> 0.44194187 | V53: =V51/V10 -> 0.40582558 | ... AU53: =AU51/AU10 -> 0.55286142
B55: Adjustment | C55: =C56-C51 -> 95.522 | D55: =D56-D51 -> -980.412 | E55: =E56-E51 -> 896.853 | F55: =F56-F51 -> 2257.655 | G55: =G56-G51 -> 3849.244 | H55: =H56-H51 -> -3991.646 | I55: =I56-I51 -> -20753.016 | J55: =J56-J51 -> -10490.846 | ... L55: =L56-L51 -> -10930.371 | O55: =O56-O51 -> -620.457 | P55: =P56-P51 -> 259.818 | Q55: =Q56-Q51 -> 149.11 | R55: =R56-R51 -> 1108.382 | S55: =S56-S51 -> 330.209 | T55: =T56-T51 -> 542.591 | U55: =U56-U51 -> 759.021 | V55: =V56-V51 -> 625.834 | ... AU55: =AU56-AU51 -> -3095.468
B56: Adj. EBITDA | C56: 49978.396 | D56: 53325.671 | E56: 65127.115 | F56: 76031.433 | G56: 73512.355 | H56: 74921.881 | I56: 79092.019 | J56: 81426.746 | K56: 86813.676 | L56: 87624.316 | O56: 16079.679 | P56: =32819.095-O56 -> 16739.416 | Q56: =49294.933-P56-O56 -> 16475.838 | R56: =E56-Q56-P56-O56 -> 15832.182 | S56: 19919.353 | T56: =38581.704-S56 -> 18662.351 | U56: =57856.718-T56-S56 -> 19275.014 | V56: =F56-U56-T56-S56 -> 18174.715 | W56: 20475.678 | X56: =38387.553-W56 -> 17911.875 | Y56: =56254.518-X56-W56 -> 17866.965 | Z56: =G56-Y56-X56-W56 -> 17257.837 | AA56: 18287.93 | AB56: =37372.404-AA56 -> 19084.474 | AC56: =56915.1-AB56-AA56 -> 19542.696 | AD56: =H56-AC56-AB56-AA56 -> 18006.781 | AE56: 19680.34 | AF56: =40545.7229999999-AE56 -> 20865.383 | AG56: =60317.538-AF56-AE56 -> 19771.815 | AH56: =I56-AG56-AF56-AE56 -> 18774.481 | AI56: 20528.1 | AJ56: 19965 | AK56: =60696.439-AJ56-AI56 -> 20203.339 | AL56: =J56-AK56-AJ56-AI56 -> 20730.307 | AM56: 21350.792 | AN56: 21613 | AO56: =64864.658-AN56-AM56 -> 21900.866 | AP56: =K56-AO56-AN56-AM56 -> 21949.018 | AQ56: 20762.714 | AR56: =42139.757-AQ56 -> 21377.043 | AS56: =64185.452-AR56-AQ56 -> 22045.695 | AT56: =L56-AS56-AR56-AQ56 -> 23438.864 | AU56: 22173.866
B57: % growth | D57: =(D56-C56)/C56 -> 0.066974438 | E57: =(E56-D56)/D56 -> 0.22130887 | F57: =(F56-E56)/E56 -> 0.16743131 | G57: =(G56-F56)/F56 -> -0.03313206 | H57: =(H56-G56)/G56 -> 0.019174001 | I57: =(I56-H56)/H56 -> 0.055659815 | J57: =(J56-I56)/I56 -> 0.029519123 | K57: =(K56-J56)/J56 -> 0.066156764 | L57: =(L56-K56)/K56 -> 0.0093376993 | S57: =S56/O56-1 -> 0.23879046 | T57: =T56/P56-1 -> 0.11487468 | U57: =U56/Q56-1 -> 0.16989582 | V57: =V56/R56-1 -> 0.14796021 | W57: =W56/S56-1 -> 0.027928869 | X57: =X56/T56-1 -> -0.040213369 | Y57: =Y56/U56-1 -> -0.073050479 | Z57: =Z56/V56-1 -> -0.050447999 | ... AU57: =AU56/AQ56-1 -> 0.067965681
B58: % margin | C58: =C56/C10 -> 0.39420841 | D58: =D56/D10 -> 0.39418527 | E58: =E56/E10 -> 0.43081237 | F58: =F56/F10 -> 0.45620592 | G58: =G56/G10 -> 0.45796514 | H58: =H56/H10 -> 0.44464959 | I58: =I56/I10 -> 0.45184925 | J58: =J56/J10 -> 0.45195788 | ... L58: =L56/L10 -> 0.49160903 | O58: =O56/O10 -> 0.43531977 | P58: =P56/P10 -> 0.44628518 | Q58: =Q56/Q10 -> 0.44341395 | R58: =R56/R10 -> 0.40010515 | S58: =S56/S10 -> 0.490189 | T58: =T56/T10 -> 0.45646015 | U58: =U56/U10 -> 0.46005827 | V58: =V56/V10 -> 0.42029827 | ... AU58: =AU56/AU10 -> 0.48513645
B60: CASH FLOW | C60: =C48 -> 42735 | D60: =D48 -> 43100 | E60: =E48 -> 43465 | F60: =F48 -> 43830 | G60: =G48 -> 44196 | H60: =H48 -> 44561 | I60: =I48 -> 44926 | J60: =J48 -> 45291 | ... L60: =L48 -> 46022 | O60: =O48 -> 43190 | P60: =P48 -> 43281 | Q60: =Q48 -> 43373 | R60: =R48 -> 43465 | S60: =S48 -> 43555 | T60: =T48 -> 43646 | U60: =U48 -> 43738 | V60: =V48 -> 43830 | ... AU60: =AU48 -> 46112
B61: Adj EBITDA | C61: =C56 -> 49978.396 | D61: =D56 -> 53325.671 | E61: =E56 -> 65127.115 | F61: =F56 -> 76031.433 | G61: =G56 -> 73512.355 | H61: =H56 -> 74921.881 | I61: =I56 -> 79092.019 | J61: =J56 -> 81426.746 | ... L61: =L56 -> 87624.316 | O61: =O56 -> 16079.679 | P61: =P56 -> 16739.416 | Q61: =Q56 -> 16475.838 | R61: =R56 -> 15832.182 | S61: =S56 -> 19919.353 | T61: =T56 -> 18662.351 | U61: =U56 -> 19275.014 | V61: =V56 -> 18174.715 | ... Y61: =Y56 -> 17866.965 | Z61: =G61-Y61-X61-W61 -> 17257.837 | AA61: =AA56 -> 18287.93 | AB61: =AB56 -> 19084.474 | AC61: =AC56 -> 19542.696 | AD61: =H61-AC61-AB61-AA61 -> 18006.781 | AE61: =AE56 -> 19680.34 | AF61: =AF56 -> 20865.383 | AG61: =AG56 -> 19771.815 | AH61: =I61-AG61-AF61-AE61 -> 18774.481 | AI61: =AI56 -> 20528.1 | AJ61: =AJ56 -> 19965 | AK61: =AK56 -> 20203.339 | AL61: =J61-AK61-AJ61-AI61 -> 20730.307 | AM61: =AM56 -> 21350.792 | AN61: =AN56 -> 21613 | AO61: =AO56 -> 21900.866 | AP61: =AP56 -> 21949.018 | AQ61: =AQ56 -> 20762.714 | AR61: =AR56 -> 21377.043 | AS61: =AS56 -> 22045.695 | AT61: =AT56 -> 23438.864 | AU61: =AU56 -> 22173.866
B62: Working Capital | C62: =-8210.048-410.495+0-4786.592+754.355+478.914+448.385+152.189 -> -11573.292 | D62: =-4865.124+914.923+0-3386.918-1177.991+6711.102-1717.582+419.351 -> -3102.239 | E62: =-5791.841-1990.025-784.314-2327.349-147.569+2092.554-1127.092+2199.814 -> -7875.822 | F62: =-2424.629-572.35+158.341-5301.967-258.528+6715.399-780.892+697.416 -> -1767.21 | G62: =71455.331-80771.733 -> -9316.402 | H62: =70871.034-80932.267 -> -10061.233 | I62: =70618.22-85205.797 -> -14587.577 | J62: =82940.152-87609.299 -> -4669.147 | K62: =88687.001-92217.493 -> -3530.492 | L62: =84920.35-92991.532 -> -8071.182 | O62: =-2148.334-968.789-247.625-3472.483+22.809+65.75-19.816-156.293 -> -6924.781 | P62: =-1853.98-409.203-482.374-836.282-77.395+352.079+9.784+173.311-O62 -> 3800.721 | Q62: =-2621.689+329.805-610.209-2376.947-234.869-25.218+4.625+1076.467-P62-O62 -> -1333.975 | R62: =E62-Q62-P62-O62 -> -3417.787 | S62: =239.331+422.563+72.718-2524.429-241.037-461.624-17.641-379.324 -> -2889.443 | T62: =-1359.651+889.863+676.893-4888.889-427.627+1192.099+198.256+238.848-S62 -> -590.765 | U62: =52.136+1578.902+127.922-7554.799-193.98+3199.082-407.391+818.435-T62-S62 -> 1100.515 | V62: =F62-U62-T62-S62 -> 612.483 | W62: =-2816.69+917.745+455.148-4216.278-26.26-2178.084+53.541+804.809 -> -7006.069 | X62: =-5454.823-471.231+1911.391-8850.862-220.508-2801.619+267.084-79.704-W62 -> -8694.203 | Y62: =-3879.085-452.265+1709.442-9110.502-874.22+1132.762+189.131-216.476-X62-W62 -> 4199.059 | Z62: =G62-Y62-X62-W62 -> 2184.811 | AA62: =16827.516-20275.575 -> -3448.059 | AB62: =34996.451-40591.308-AA62 -> -2146.798 | AC62: =51975.393-61603.333-AB62-AA62 -> -4033.083 | AD62: =H62-AC62-AB62-AA62 -> -433.293 | AE62: =13135.463-21299.949 -> -8164.486 | AF62: =34035.727-43950.959-AE62 -> -1750.746 | AG62: =51224.421-65497.527-AF62-AE62 -> -4357.874 | AH62: =I62-AG62-AF62-AE62 -> -314.471 | AI62: =13868.639-22152.046 -> -8283.407 | AJ62: =36052.458-43577.131-AI62 -> 758.734 | AK62: =59305.216-65292.147-AJ62-AI62 -> 1537.742 | AL62: =J62-AK62-AJ62-AI62 -> 1317.784 | AM62: =24599.768-22882.338 -> 1717.43 | AN62: =45334.325-45745.477-AM62 -> -2128.582 | AO62: =68605.072-68856.173-AN62-AM62 -> 160.051 | AP62: =K62-AO62-AN62-AM62 -> -3279.391 | AQ62: =23553.519-22253.789 -> 1299.73 | AR62: =38559.505-45038.471-AQ62 -> -7778.696 | AS62: =64426.332-68300.395-AR62-AQ62 -> 2604.903 | AT62: =L62-AS62-AR62-AQ62 -> -4197.119 | AU62: =24297.34-23266.71 -> 1030.63
B63: Taxes | C63: -5577.281 | D63: -5599.215 | E63: -4775.445 | F63: -6090.569 | G63: -6295.333 | H63: -5730.531 | I63: -5463.218 | J63: -2493.272 | K63: -3905.16 | L63: -5378.583 | O63: -27.932 | P63: =-2527.878-O63 -> -2499.946 | Q63: =-3176.198-P63-O63 -> -648.32 | R63: =E63-Q63-P63-O63 -> -1599.247 | S63: -52.008 | T63: =-2631.007-S63 -> -2578.999 | U63: =-4092.817-T63-S63 -> -1461.81 | V63: =F63-U63-T63-S63 -> -1997.752 | W63: -1053.181 | X63: =-2876.356-W63 -> -1823.175 | Y63: =-4725.654-X63-W63 -> -1849.298 | Z63: =G63-Y63-X63-W63 -> -1569.679 | AA63: -70.29 | AB63: =-1125.179-AA63 -> -1054.889 | AC63: =-2017.6-AB63-AA63 -> -892.421 | AD63: =H63-AC63-AB63-AA63 -> -3712.931 | AE63: -942.485 | AF63: =-2320.865-AE63 -> -1378.38 | AG63: =-2906.983-AF63-AE63 -> -586.118 | AH63: =I63-AG63-AF63-AE63 -> -2556.235 | AI63: -272.328 | AJ63: =-1960.266-AI63 -> -1687.938 | AK63: =-1897.058-AJ63-AI63 -> 63.208 | AL63: =J63-AK63-AJ63-AI63 -> -596.214 | AM63: -976.375 | AN63: =-2507.32-AM63 -> -1530.945 | AO63: =-3041.523-AN63-AM63 -> -534.203 | AP63: =K63-AO63-AN63-AM63 -> -863.637 | AQ63: -818.143 | AR63: =-2472.206-356.324-AQ63 -> -2010.387 | AS63: =-3715.028-307.724-AR63-AQ63 -> -1194.222 | AT63: =L63-AS63-AR63-AQ63 -> -1355.831 | AU63: -737.766
B64: Cash interest paid | C64: -3812.532 | D64: -5525.049 | E64: -6607.604 | F64: -7232.591 | G64: -6770.877 | H64: -7692.594 | I64: -9834.409 | J64: -13048.218 | K64: -13901.534 | L64: -13667.616 | O64: -1305.538 | P64: =-3200.745-O64 -> -1895.207 | Q64: =-4715.475-P64-O64 -> -1514.73 | R64: =E64-Q64-P64-O64 -> -1892.129 | S64: -1954.564 | T64: =-3883.74-S64 -> -1929.176 | U64: =-5642.768-T64-S64 -> -1759.028 | V64: =F64-U64-T64-S64 -> -1589.823 | W64: -1749.925 | X64: =-3532.28-W64 -> -1782.355 | Y64: =-5282.79-X64-W64 -> -1750.51 | Z64: =G64-Y64-X64-W64 -> -1488.087 | AA64: -1951.234 | AB64: =-3533.543-AA64 -> -1582.309 | AC64: =-5788.876-AB64-AA64 -> -2255.333 | AD64: =H64-AC64-AB64-AA64 -> -1903.718 | AE64: -2421.955 | AF64: =-4526.176-AE64 -> -2104.221 | AG64: =-7362.025-AF64-AE64 -> -2835.849 | AH64: =I64-AG64-AF64-AE64 -> -2472.384 | AI64: -3069.499 | AJ64: =-5938.572-AI64 -> -2869.073 | AK64: =-9631.626-AJ64-AI64 -> -3693.054 | AL64: =J64-AK64-AJ64-AI64 -> -3416.592 | AM64: -3676.295 | AN64: =-7055.156-AM64 -> -3378.861 | AO64: =-10809.592-AN64-AM64 -> -3754.436 | AP64: =K64-AO64-AN64-AM64 -> -3091.942 | AQ64: -3758.477 | AR64: =-6777.706-AQ64 -> -3019.229 | AS64: =-10520.728-AR64-AQ64 -> -3743.022 | AT64: =L64-AS64-AR64-AQ64 -> -3146.888 | AU64: -3679.125
B65: Net cash from operations | C65: =SUM(C61:C64) -> 29015.291 | D65: =SUM(D61:D64) -> 39099.168 | E65: =SUM(E61:E64) -> 45868.244 | F65: =SUM(F61:F64) -> 60941.063 | G65: =SUM(G61:G64) -> 51129.743 | H65: =SUM(H61:H64) -> 51437.523 | I65: =SUM(I61:I64) -> 49206.815 | J65: =SUM(J61:J64) -> 61216.109 | ... L65: =SUM(L61:L64) -> 60506.935 | O65: =SUM(O61:O64) -> 7821.428 | P65: =SUM(P61:P64) -> 16144.984 | Q65: =SUM(Q61:Q64) -> 12978.813 | R65: =SUM(R61:R64) -> 8923.019 | S65: =SUM(S61:S64) -> 15023.338 | T65: =SUM(T61:T64) -> 13563.411 | U65: =SUM(U61:U64) -> 17154.691 | V65: =SUM(V61:V64) -> 15199.623 | ... AU65: =SUM(AU61:AU64) -> 18787.605
B66: Net Capex | C66: =-36609.815+170.116 -> -36439.699 | D66: =-42121.307+118.117 -> -42003.19 | E66: =-42768.194+171.638 -> -42596.556 | F66: =-50975.224+101.463 -> -50873.761 | G66: =-60268.935+93.154 -> -60175.781 | H66: =-92750.679+179.998 -> -92570.681 | I66: =-97983.036+750.716 -> -97232.32 | J66: =-70534.793+747.121 -> -69787.672 | K66: =-55960.088+1068.74 -> -54891.348 | L66: =-46067.462+1068.69 -> -44998.772 | O66: =-6571.389+9.891 -> -6561.498 | P66: =-22834.957+29.306-O66 -> -16244.153 | Q66: =-32419.417+109.254-P66-O66 -> -9504.512 | R66: =E66-Q66-P66-O66 -> -10286.393 | S66: =-8730.934+28.762 -> -8702.172 | T66: =-18980.306+98.178-S66 -> -10179.956 | U66: =-31899.7+123.504-T66-S66 -> -12894.068 | V66: =F66-U66-T66-S66 -> -19097.565 | W66: =-10653.084+48.85 -> -10604.234 | X66: =-20860.479+83.296-W66 -> -10172.949 | Y66: =-33349.83+102.622-X66-W66 -> -12470.025 | Z66: =G66-Y66-X66-W66 -> -26928.573 | AA66: =-19106.421+65.367 -> -19041.054 | AB66: =-43245.625+107.228-AA66 -> -24097.343 | AC66: =-65391.078+124.371-AB66-AA66 -> -22128.31 | AD66: =H66-AC66-AB66-AA66 -> -27303.974 | AE66: =-20983.147+37.713 -> -20945.434 | AF66: =-47243.078+205.608-AE66 -> -26092.036 | AG66: =-71052.217+308.082-AF66-AE66 -> -23706.665 | AH66: =I66-AG66-AF66-AE66 -> -26488.185 | AI66: =-17570.97+82.83 -> -17488.14 | AJ66: =-37652.958+307.361-AI66 -> -19857.457 | AK66: =-53979.177+455.546-AJ66-AI66 -> -16178.034 | AL66: =J66-AK66-AJ66-AI66 -> -16264.041 | AM66: =-13739.065+194.158 -> -13544.907 | AN66: =-28236.319+1040.723-AM66 -> -13650.689 | AO66: =-40850.414+1098.163-AN66-AM66 -> -12556.655 | AP66: =K66-AO66-AN66-AM66 -> -15139.097 | AQ66: =-8437.141+115.227 -> -8321.914 | AR66: =-18855.245+151.589-AQ66 -> -10381.742 | AS66: =-31421.641+344.898-AR66-AQ66 -> -12373.087 | AT66: =L66-AS66-AR66-AQ66 -> -13922.029 | AU66: =-12714.884+84.742 -> -12630.142
B67: Acquisitions / sales of subsidiaries, JVs | C67: -21562.555 | D67: -12234.212 | E67: =-111.2 -> -111.2 | F67: =-3305-1563.649 -> -4868.649 | G67: =-1532.5-385.181 -> -1917.681 | H67: -1591.856 | I67: -585.53 | J67: =-749.39-2457.22 -> -3206.61 | K67: -270.15 | L67: =962.5 -> 962.5 | O67: =-51.2 -> -51.2 | P67: =-111.2-O67 -> -60 | Q67: =-111.2-P67-O67 -> 0 | R67: =E67-Q67-P67-O67 -> 0 | S67: -1129 | T67: =-1672.25-S67 -> -543.25 | U67: =-386.758-2734-T67-S67 -> -1448.508 | V67: =F67-U67-T67-S67 -> -1747.891 | W67: =-26.829-10 -> -36.829 | X67: =-771.25-26.829-W67 -> -761.25 | Y67: =-161.271-771.25-X67-W67 -> -134.442 | Z67: =G67-Y67-X67-W67 -> -985.16 | AA67: 0 | AB67: =0-AA67 -> 0 | AC67: =0-AB67-AA67 -> 0 | AD67: =H67-AC67-AB67-AA67 -> -1591.856 | AE67: -147.192 | AF67: =-336.966-AE67 -> -189.774 | AG67: =-646.669-AF67-AE67 -> -309.703 | AH67: =I67-AG67-AF67-AE67 -> 61.139 | AI67: -220.1 | AJ67: =-300.988-AI67 -> -80.888 | AK67: =-749.39-AJ67-AI67 -> -448.402 | AL67: =J67-AK67-AJ67-AI67 -> -2457.22 | AM67: -135.65 | AN67: =-135.649-AM67 -> 0.001 | AO67: =-253.649-AN67-AM67 -> -118 | AP67: =K67-AO67-AN67-AM67 -> -16.501 | AQ67: 0 | AR67: =-29.349-AQ67 -> -29.349 | AS67: =962.5-29.519-AR67-AQ67 -> 962.33 | AT67: =L67-AS67-AR67-AQ67 -> 29.519 | AU67: -514.762
B68: Free cash flow | C68: =SUM(C65:C67) -> -28986.963 | D68: =SUM(D65:D67) -> -15138.234 | E68: =SUM(E65:E67) -> 3160.488 | F68: =SUM(F65:F67) -> 5198.653 | G68: =SUM(G65:G67) -> -10963.719 | H68: =SUM(H65:H67) -> -42725.014 | I68: =SUM(I65:I67) -> -48611.035 | J68: =SUM(J65:J67) -> -11778.173 | ... L68: =SUM(L65:L67) -> 16470.663 | O68: =SUM(O65:O67) -> 1208.73 | P68: =SUM(P65:P67) -> -159.169 | Q68: =SUM(Q65:Q67) -> 3474.301 | R68: =SUM(R65:R67) -> -1363.374 | S68: =SUM(S65:S67) -> 5192.166 | T68: =SUM(T65:T67) -> 2840.205 | U68: =SUM(U65:U67) -> 2812.115 | V68: =SUM(V65:V67) -> -5645.833 | ... AU68: =SUM(AU65:AU67) -> 5642.701
B69: Other investing activities | C69: =-135.273+180+155.672+115.257+16.12+13.671-4.78 -> 340.667 | D69: =-419.92+243.78+145.234+93.258+0-1246.965 -> -1184.613 | E69: =-490.569+180+352.302+13.852+0.418 -> 56.003 | F69: =-48.532+70+544.739+21.368+124.056 -> 711.631 | G69: =-32.586+358.62+193.249 -> 519.283 | H69: =-57.661+70+136.152-2547.935 -> -2399.444 | I69: =-5622.764-3383.869-681+29940.218+408+311.379+5030+175.725 -> 26177.689 | J69: =-92.878-636+24858.693+660.328 -> 24790.143 | K69: =-233.565+101+857.47+598.5+27821.162 -> 29144.567 | L69: =-97.942+3222.201+3023.935+747.897+654.5+600+200.595 -> 8351.186 | O69: =-17.876+120+68.85+13.852+0.418 -> 185.244 | P69: =-80.786+120+140.377+13.852+0.418-O69 -> 8.617 | Q69: =-113.443+150+228.822+13.852+0.418-P69-O69 -> 85.788 | R69: =E69-Q69-P69-O69 -> -223.646 | S69: =-24.746+70+230.368+10.684+124.056 -> 410.362 | T69: =-58.484+70+381.122+21.368+124.056-S69 -> 127.7 | U69: =-62.909+70+483.682+21.368+124.056-T69-S69 -> 98.135 | V69: =F69-U69-T69-S69 -> 75.434 | W69: =-5.447+250+74.356 -> 318.909 | X69: =-24.987+250+158.185-W69 -> 64.289 | Y69: =-26.69+250+173.451-X69-W69 -> 13.563 | Z69: =G69-Y69-X69-W69 -> 122.522 | AA69: =-14.29+23.256 -> 8.966 | AB69: =-18.337-2547.935+70+33.001-AA69 -> -2472.237 | AC69: =-83.696-2547.935+70+50.514-AB69-AA69 -> -47.846 | AD69: =H69-AC69-AB69-AA69 -> 111.673 | AE69: =-10.093+21.771 -> 11.678 | AF69: =-3250.797-0+408+101.364+5030-AE69 -> 2276.889 | AG69: =-5622.764-3308.392-580-10160+408+131.356+5030+175.725--853.837-AF69-AE69 -> -15360.805 | AH69: =I69-AG69-AF69-AE69 -> 39249.927 | AI69: =-15.998+84.16 -> 68.162 | AJ69: =-40.332-160+17437.457+265.962-4145.656-AI69 -> 13289.269 | AK69: =-55.41-431+20667.675+436.195-5668.33-AJ69-AI69 -> 1591.699 | AL69: =J69-AK69-AJ69-AI69 -> 9841.013 | AM69: =-7.791+4804.565+169.2 -> 4965.974 | AN69: =-111.765+14239.41+360.015-1376.732-AM69 -> 8144.954 | AO69: =-164.018+500.5+27313.807+566.957-2727.494-AN69-AM69 -> 12378.824 | AP69: =K69-AO69-AN69-AM69 -> 3654.815 | AQ69: =-24.366+2087.384+122.881 -> 2185.899 | AR69: =-10.966+2002.147+200.595+306.44+308-AQ69 -> 620.317 | AS69: =-18.496+3177.259+200.595+457.705+654.5+600+476-AR69-AQ69 -> 2741.347 | AT69: =L69-AS69-AR69-AQ69 -> 2803.623 | AU69: =-101.88-22.937+158.971 -> 34.154
B70: Dividends / Equity movements | C70: =-11682.483-552.087 -> -12234.57 | D70: =-12091.736-553.791 -> -12645.527 | E70: =-12104.579-561.812 -> -12666.391 | F70: =-12118.071-570.087 -> -12688.158 | G70: =-14403.344-570.087 -> -14973.431 | H70: =-14425.839-570.087-10000+29977.845-20.582 -> 4961.337 | I70: =-14442.073-50.027-1306.734+16804.482 -> 1005.648 | J70: =-14418.658-50.027-1330.619 -> -15799.304 | K70: =-14434.24-61.297-1369.672 -> -15865.209 | L70: =-14444.648-61.297-1361.45 -> -15867.395 | O70: =-3023.852-260.03 -> -3283.882 | P70: =-6050.656-260.03-O70 -> -3026.804 | Q70: =-9077.618-520.06-P70-O70 -> -3286.992 | R70: =E70-Q70-P70-O70 -> -3068.713 | S70: =-3026.961-260.03 -> -3286.991 | T70: =-6057.264-260.03-S70 -> -3030.303 | U70: =-9087.58-520.06-T70-S70 -> -3290.346 | V70: =F70-U70-T70-S70 -> -3080.518 | W70: =-3596.627-260.03 -> -3856.657 | X70: =-6909.762-260.03-W70 -> -3313.135 | Y70: =-10222.896-520.06-X70-W70 -> -3573.164 | Z70: =G70-Y70-X70-W70 -> -4230.475 | AA70: =-3602.684-260.03-10.291 -> -3873.005 | AB70: =-7210.402-260.03-20.582-AA70 -> -3618.009 | AC70: =-10818.121-520.06-20.582-AB70-AA70 -> -3867.749 | AD70: =H70-AC70-AB70-AA70 -> 16320.1 | AE70: -3607.719 | AF70: =-7224.139-0-0-AE70 -> -3616.42 | AG70: =-10840.559-618.207-AF70-AE70 -> -4234.627 | AH70: =I70-AG70-AF70-AE70 -> 12464.414 | AI70: -3601.514 | AJ70: =-7207.227-0-0-AI70 -> -3605.713 | AK70: =-10812.941-658.452-AJ70-AI70 -> -4264.166 | AL70: =J70-AK70-AJ70-AI70 -> -4327.911 | AM70: -3605.716 | AN70: =-7215.224-0-0-AM70 -> -3609.508 | AO70: =-10824.732-681.546-AN70-AM70 -> -4291.054 | AP70: =K70-AO70-AN70-AM70 -> -4358.931 | AQ70: -3609.508 | AR70: =-7221.221-664.477-AQ70 -> -4276.19 | AS70: =-10832.934-664.477-AR70-AQ70 -> -3611.713 | AT70: =L70-AS70-AR70-AQ70 -> -4369.984 | AU70: =-3611.712+24837.406 -> 21225.694
B71: Principal Repayments | C71: =36500+21600-7993.304-17100 -> 33006.696 | D71: =36430.73+4600-5953.717-9100 -> 25977.013 | E71: =24156-8319.604 -> 15836.396 | F71: =5000-16745.816-300-1298.341 -> -13344.157 | G71: =43998.82+18440-12928.496-17740-1536.853 -> 30233.471 | H71: =50733.809+41894.04-8009.757-42258.8-3566.395 -> 38792.897 | I71: =8000+82020.167-15934.168-56175-6878.96 -> 11032.039 | J71: =45000+63250-20214.691-70905.167-15841.394 -> 1288.748 | K71: =27000+23310-18396.869-34572.5-17035.519 -> -19694.888 | L71: =32500.303+1036-19102.08-8298.5-15731.076 -> -9595.353 | O71: =2500-7030.874 -> -4530.874 | P71: =8500-7273.571-O71 -> 5757.303 | Q71: =8500-7536.071-P71-O71 -> -262.5 | R71: =E71-Q71-P71-O71 -> 14872.467 | S71: =-9877.5-265.265 -> -10142.765 | T71: =-15620.753-563.012-S71 -> -6041 | U71: =16069.379-917.982-T71-S71 -> 31335.162 | V71: =F71-U71-T71-S71 -> -28495.554 | W71: =9852.22+700-1647.028-367.974 -> 8537.218 | X71: =-7791.426-3050-755.052+12852.22+13050-W71 -> 5768.524 | Y71: =42498.82+17440-12236.475-17440.5-1138.682-X71-W71 -> 14817.421 | Z71: =G71-Y71-X71-W71 -> 1110.308 | AA71: =10000+1100-6551.657-1100-397.096 -> 3051.247 | AB71: =-16900+25692+16805-6818.139-847.122-AA71 -> 14880.492 | AC71: =43732.584+32789-7281.457-29390-1754.213-AB71-AA71 -> 20164.175 | AD71: =H71-AC71-AB71-AA71 -> 696.983 | AE71: =8000+1820-1048.992-2125-1341.65 -> 5304.358 | AF71: =-2125+8000+32090-12180.012-2769.437-AE71 -> 17711.193 | AG71: =8000+59110-15149.869-21625-4267.077-AF71-AE71 -> 3052.503 | AH71: =I71-AG71-AF71-AE71 -> -15036.015 | AI71: =17615-1064.679-13850.167-2191.295 -> 508.859 | AJ71: =-20750.167-8744.655+46570-5804.16-AI71 -> 10762.159 | AK71: =53220-12609.261-29405.167-10463.588-AJ71-AI71 -> -10529.034 | AL71: =J71-AK71-AJ71-AI71 -> 546.764 | AM71: =3030-1083.897-6000-3268.118 -> -7322.015 | AN71: =-21270-1337.967+16285-7333.513-AM71 -> -6334.465 | AO71: =15000+16305-6393.87-34563-13331.5-AN71-AM71 -> -9326.89 | AP71: =K71-AO71-AN71-AM71 -> 3288.482 | AQ71: =10000-9768.699-7000-4564.902 -> -11333.601 | AR71: =20000-13011.699-7062.5-6504.965-AQ71 -> 4754.437 | AS71: =25000+217-13929.08-7479.5-10921.101-AR71-AQ71 -> -533.517 | AT71: =L71-AS71-AR71-AQ71 -> -2482.672 | AU71: =-6760.248-4611.827 -> -11372.075
B72: Other financing activities | C72: 5.036 | D72: =7.913 -> 7.913 | E72: 2.553 | F72: 7.553 | G72: 0 | H72: 0 | I72: 0 | J72: 0 | K72: 0 | L72: =-29.519 -> -29.519 | O72: 0 | P72: =0.532-O72 -> 0.532 | Q72: =2.554-P72-O72 -> 2.022 | R72: =E72-Q72-P72-O72 -> -0.001 | S72: 0.895 | T72: =1.69-S72 -> 0.795 | U72: =7.553-T72-S72 -> 5.863 | V72: =F72-U72-T72-S72 -> 0 | W72: 0 | X72: =0-W72 -> 0 | Y72: =0-X72-W72 -> 0 | Z72: =G72-Y72-X72-W72 -> 0 | AA72: 0 | AB72: =0-AA72 -> 0 | AC72: =0-AB72-AA72 -> 0 | AD72: =H72-AC72-AB72-AA72 -> 0 | AE72: 0 | AF72: =-824.276-AE72 -> -824.276 | AG72: =0-AF72-AE72 -> 824.276 | AH72: =I72-AG72-AF72-AE72 -> 0 | AI72: 0 | AJ72: =-658.452-AI72 -> -658.452 | AK72: =0-AJ72-AI72 -> 658.452 | AL72: =J72-AK72-AJ72-AI72 -> 0 | AM72: 0 | AN72: =-681.546-AM72 -> -681.546 | AO72: =0-AN72-AM72 -> 681.546 | AP72: =K72-AO72-AN72-AM72 -> 0 | AQ72: 0 | AR72: =0-AQ72 -> 0 | AS72: =0-AR72-AQ72 -> 0 | AT72: =L72-AS72-AR72-AQ72 -> -29.519 | AU72: 0
B73: Cash flow after financing activities | C73: =SUM(C68:C72) -> -7869.134 | D73: =SUM(D68:D72) -> -2983.448 | E73: =SUM(E68:E72) -> 6389.049 | F73: =SUM(F68:F72) -> -20114.478 | G73: =SUM(G68:G72) -> 4815.604 | H73: =SUM(H68:H72) -> -1370.224 | I73: =SUM(I68:I72) -> -10395.659 | J73: =SUM(J68:J72) -> -1498.586 | ... L73: =SUM(L68:L72) -> -670.418 | O73: =SUM(O68:O72) -> -6420.782 | P73: =SUM(P68:P72) -> 2580.479 | Q73: =SUM(Q68:Q72) -> 12.619 | R73: =SUM(R68:R72) -> 10216.733 | S73: =SUM(S68:S72) -> -7826.333 | T73: =SUM(T68:T72) -> -6102.603 | U73: =SUM(U68:U72) -> 30960.929 | V73: =SUM(V68:V72) -> -37146.471 | ... AU73: =SUM(AU68:AU72) -> 15530.474
B74: Balancing figure | C74: =-3234.36-C73 -> 4634.774 | D74: =2696.597-D73 -> 5680.045 | E74: =11763.73-E73 -> 5374.681 | F74: =-14245.913-F73 -> 5868.565 | G74: =12074.982-G73 -> 7259.378 | H74: =4640.162-H73 -> 6010.386 | I74: =-6492.979-I73 -> 3902.68 | J74: =-1590.496-J73 -> -91.91 | K74: =4574.798-K73 -> 675.336 | L74: =4060.432-L73 -> 4730.85 | O74: =-5198.816-O73 -> 1221.966 | P74: =-965.845-P73-O74-O73 -> 1652.492 | Q74: =443.048-Q73-P74-P73-O74-O73 -> 1396.274 | R74: =E74-Q74-P74-O74 -> 1103.949 | S74: =-6687.7-S73 -> 1138.633 | T74: =-11032.549-T73-S74-S73 -> 1757.754 | U74: =-11189-U73-T74-T73-S74-S73 -> -31117.38 | V74: =F74-U74-T74-S74 -> 34089.558 | W74: =6360.293-W73 -> 1335.383 | X74: =6689.671-X73-W74-W73 -> 3131.757 | Y74: =25109.517-Y73-X74-X73-W74-W73 -> 1300.277 | Z74: =G74-Y74-X74-W74 -> 1491.961 | AA74: =-5047.854-AA73 -> 1987.645 | AB74: =-4823.214-AB73-AA74-AA73 -> 1231.259 | AC74: =-6912.335-AC73-AB74-AB73-AA74-AA73 -> -8571.25 | AD74: =H74-AC74-AB74-AA74 -> 11362.732 | AE74: =-9613.286-AE73 -> 1619.609 | AF74: =-8519.871-AF73-AE74-AE73 -> -3804.197 | AG74: =-10302.742-AG73-AF74-AF73-AE74-AE73 -> 25960.176 | AH74: =I74-AG74-AF74-AE74 -> -19872.908 | AI74: =-1854.068-AI73 -> 9975.799 | AJ74: =7269.806-AJ73-AI74-AI73 -> -6891.767 | AK74: =-2276.768-AK73-AJ74-AJ73-AI74-AI73 -> 1511.676 | AL74: =J74-AK74-AJ74-AI74 -> -4687.618 | AM74: =304.784-AM73 -> 1531.546 | AN74: =1998.282-AN73-AM74-AM73 -> 3250.139 | AO74: =5748.161-AO73-AN74-AN73-AM74-AM73 -> -790.17 | AP74: =K74-AO74-AN74-AM74 -> -3316.179 | AQ74: =-2102.225-483.245-AQ73 -> 1007.83 | AR74: =-1438.382-AR73-AQ74-AQ73-461.9 -> 1428.984 | AS74: =6676.561-AS73-AR74-AR73-AQ74-AQ73-349.059 -> 1329.07 | AT74: =L74-AS74-AR74-AQ74 -> 964.966 | AU74: =16623.318-AU73 -> 1092.844
B75: FX | C75: 52.833 | D75: -107.229 | E75: 240.436 | F75: -682.381 | G75: -864.96 | H75: 90.919 | I75: 287.569 | J75: 201.788 | K75: 133.784 | L75: 145.528 | O75: 280.536 | P75: =382.394-O75 -> 101.858 | Q75: =468.025-P75-O75 -> 85.631 | R75: =E75-Q75-P75-O75 -> -227.589 | S75: 20.424 | T75: =-407.556-S75 -> -427.98 | U75: =-407.476-T75-S75 -> 0.08 | V75: =F75-U75-T75-S75 -> -274.905 | W75: -139.284 | X75: =-202.528-W75 -> -63.244 | Y75: =-780.489-X75-W75 -> -577.961 | Z75: =G75-Y75-X75-W75 -> -84.471 | AA75: 24.114 | AB75: =-55.944-AA75 -> -80.058 | AC75: =108.934-AB75-AA75 -> 164.878 | AD75: =H75-AC75-AB75-AA75 -> -18.015 | AE75: 228.636 | AF75: =356.103-AE75 -> 127.467 | AG75: =454.041-AF75-AE75 -> 97.938 | AH75: =I75-AG75-AF75-AE75 -> -166.472 | AI75: 64.123 | AJ75: =54.068-AI75 -> -10.055 | AK75: =219.818-AJ75-AI75 -> 165.75 | AL75: =J75-AK75-AJ75-AI75 -> -18.03 | AM75: 29.474 | AN75: =-9.321-AM75 -> -38.795 | AO75: =-137.214-AN75-AM75 -> -127.893 | AP75: =K75-AO75-AN75-AM75 -> 270.998 | AQ75: -41.342 | AR75: =-137.891-AQ75 -> -96.549 | AS75: =47.218-AR75-AQ75 -> 185.109 | AT75: =L75-AS75-AR75-AQ75 -> 98.31 | AU75: 169.939
B76: Net change in cash | C76: =SUM(C73:C75) -> -3181.527 | D76: =SUM(D73:D75) -> 2589.368 | E76: =SUM(E73:E75) -> 12004.166 | F76: =SUM(F73:F75) -> -14928.294 | G76: =SUM(G73:G75) -> 11210.022 | H76: =SUM(H73:H75) -> 4731.081 | I76: =SUM(I73:I75) -> -6205.41 | J76: =SUM(J73:J75) -> -1388.708 | ... L76: =SUM(L73:L75) -> 4205.96 | O76: =SUM(O73:O75) -> -4918.28 | P76: =SUM(P73:P75) -> 4334.829 | Q76: =SUM(Q73:Q75) -> 1494.524 | R76: =SUM(R73:R75) -> 11093.093 | S76: =SUM(S73:S75) -> -6667.276 | T76: =SUM(T73:T75) -> -4772.829 | U76: =SUM(U73:U75) -> -156.371 | V76: =SUM(V73:V75) -> -3331.818 | ... AU76: =SUM(AU73:AU75) -> 16793.257
B77: Cash and cash equivalents | C77: =11814.379+C76 -> 8632.852 | D77: =C77+D76 -> 11222.22 | E77: =11222.22+E76 -> 23226.386 | F77: =23226.386+F76 -> 8298.092 | G77: =F77+G76 -> 19508.114 | H77: =G77+H76 -> 24239.195 | I77: =H77+I76 -> 18033.785 | J77: =I77+J76 -> 16645.077 | K77: =J77+K76 -> 21353.659 | L77: =K77+L76-529.762 -> 25029.857 | O77: =11222.22+O76 -> 6303.94 | P77: =+O77+P76 -> 10638.769 | Q77: =+P77+Q76 -> 12133.293 | R77: =Q77+R76 -> 23226.386 | S77: =23226.386+S76 -> 16559.11 | T77: =S77+T76 -> 11786.281 | U77: =T77+U76 -> 11629.91 | V77: =U77+V76 -> 8298.092 | W77: =8298.092+W76 -> 14519.101 | X77: =W77+X76 -> 14785.235 | Y77: =X77+Y76 -> 32627.12 | Z77: =Y77+Z76 -> 19508.114 | AA77: =Z77+AA76 -> 14484.374 | AB77: =AA77+AB76 -> 14628.956 | AC77: =AB77+AC76 -> 12704.713 | AD77: =AC77+AD76 -> 24239.195 | AE77: =AD77+AE76 -> 14854.545 | ... AS77: =AR77+AS76 -> 27728.379 | AT77: =AS77+AT76-529.762 -> 25029.857 | AU77: =25559.619+AU76 -> 42352.876
B79: Check | C79: =C77-C122 -> 0 | D79: =D77-D122 -> 0 | E79: =E77-E122 -> 0 | F79: =F77-F122 -> 0 | G79: =G77-G122 -> 0 | H79: =H77-H122 -> 0 | I79: =I77-I122 -> 0 | J79: =J77-J122 -> 0 | ... L79: =L77-L122 -> 0 | O79: =O77-O122 -> 0 | P79: =P77-P122 -> 0 | Q79: =Q77-Q122 -> 0 | R79: =R77-R122 -> 0 | S79: =S77-S122 -> 0 | T79: =T77-T122 -> 0 | U79: =U77-U122 -> 0 | V79: =V77-V122 -> 0 | ... AU79: =AU77-AU122 -> 0
B80: cost of debt | C80: =C64/C109 -> -0.037662601 | D80: =D64/D109 -> -0.042006412 | E80: =E64/E109 -> -0.044561097 | F80: =F64/F109 -> -0.053234546 | G80: =G64/G109 -> -0.041087376 | H80: =H64/H109 -> -0.036622058 | I80: =I64/I109 -> -0.042170723 | J80: =J64/J109 -> -0.05220215 | ... L80: =L64/L109 -> -0.053323846 | R80: =SUM(O64:R64)/R109 -> -0.044561097 | S80: =SUM(P64:S64)/S109 -> -0.052418341 | T80: =SUM(Q64:T64)/T109 -> -0.055187495 | U80: =SUM(R64:U64)/U109 -> -0.05710637 | V80: =SUM(S64:V64)/V109 -> -0.053234546 | W80: =SUM(T64:W64)/W109 -> -0.048572533 | X80: =SUM(U64:X64)/X109 -> -0.045877407 | Y80: =SUM(V64:Y64)/Y109 -> -0.041997925 | ... AU80: =SUM(AR64:AU64)/AU109 -> -0.054085381
B82: LTM METRICS | C82: =C60 -> 42735 | D82: =D60 -> 43100 | E82: =E60 -> 43465 | F82: =F60 -> 43830 | G82: =G60 -> 44196 | H82: =H60 -> 44561 | I82: =I60 -> 44926 | J82: =J60 -> 45291 | ... L82: =L60 -> 46022 | O82: =O60 -> 43190 | P82: =P60 -> 43281 | Q82: =Q60 -> 43373 | R82: =R60 -> 43465 | S82: =S60 -> 43555 | T82: =T60 -> 43646 | U82: =U60 -> 43738 | V82: =V60 -> 43830 | ... AU82: =AU60 -> 46112
B84: Revenue | C84: =C10 -> 126781.66 | D84: =D10 -> 135280.73 | E84: =E10 -> 151172.81 | F84: =F10 -> 166660.34 | G84: =G10 -> 160519.54 | H84: =H10 -> 168496.46 | I84: =I10 -> 175040.72 | J84: =J10 -> 180164.45 | ... L84: =L10 -> 178239.84 | R84: =SUM(O10:R10) -> 151172.81 | S84: =SUM(P10:S10) -> 154871.25 | T84: =SUM(Q10:T10) -> 158247.86 | U84: =SUM(R10:U10) -> 162987.97 | V84: =SUM(S10:V10) -> 166660.34 | W84: =SUM(T10:W10) -> 167215.62 | X84: =SUM(U10:X10) -> 163953.45 | Y84: =SUM(V10:Y10) -> 162835.43 | ... AU84: =SUM(AR10:AU10) -> 180190.61
B85: Operating profit | C85: =+C23 -> 26034.228 | D85: =+D23 -> 26793.394 | E85: =+E23 -> 33808.541 | F85: =+F23 -> 39630.237 | G85: =+G23 -> 34251.073 | H85: =+H23 -> 37780.535 | I85: =+I23 -> 54191.739 | J85: =+J23 -> 44561.549 | ... L85: =+L23 -> 44683.56 | R85: =SUM(O23:R23) -> 33808.541 | S85: =SUM(P23:S23) -> 35987 | T85: =SUM(Q23:T23) -> 36457.324 | U85: =SUM(R23:U23) -> 37843.484 | V85: =SUM(S23:V23) -> 39630.237 | W85: =SUM(T23:W23) -> 39329.139 | X85: =SUM(U23:X23) -> 38789.836 | Y85: =SUM(V23:Y23) -> 37010.075 | ... AU85: =SUM(AR23:AU23) -> 43377.298
B86: EBITDA | C86: =+C51 -> 49882.874 | D86: =+D51 -> 54306.083 | E86: =+E51 -> 64230.262 | F86: =+F51 -> 73773.778 | G86: =+G51 -> 69663.111 | H86: =+H51 -> 78913.527 | I86: =+I51 -> 99845.035 | J86: =+J51 -> 91917.592 | ... L86: =+L51 -> 98554.687 | R86: =SUM(O51:R51) -> 64230.262 | S86: =SUM(P51:S51) -> 67119.27 | T86: =SUM(Q51:T51) -> 68759.432 | U86: =SUM(R51:U51) -> 70948.697 | V86: =SUM(S51:V51) -> 73773.778 | W86: =SUM(T51:W51) -> 74116.236 | X86: =SUM(U51:X51) -> 74000.581 | Y86: =SUM(V51:Y51) -> 72732.901 | ... AU86: =SUM(AR51:AU51) -> 98167.814
B87: Adjusted EBITDA | C87: =+C56 -> 49978.396 | D87: =+D56 -> 53325.671 | E87: =+E56 -> 65127.115 | F87: =+F56 -> 76031.433 | G87: =+G56 -> 73512.355 | H87: =+H56 -> 74921.881 | I87: =+I56 -> 79092.019 | J87: =+J56 -> 81426.746 | ... L87: =+L56 -> 87624.316 | R87: =SUM(O56:R56) -> 65127.115 | S87: =SUM(P56:S56) -> 68966.789 | T87: =SUM(Q56:T56) -> 70889.724 | U87: =SUM(R56:U56) -> 73688.9 | V87: =SUM(S56:V56) -> 76031.433 | W87: =SUM(T56:W56) -> 76587.758 | X87: =SUM(U56:X56) -> 75837.282 | Y87: =SUM(V56:Y56) -> 74429.233 | ... AU87: =SUM(AR56:AU56) -> 89035.468
B88: Cash interest paid | C88: =-C64 -> 3812.532 | D88: =-D64 -> 5525.049 | E88: =-E64 -> 6607.604 | F88: =-F64 -> 7232.591 | G88: =-G64 -> 6770.877 | H88: =-H64 -> 7692.594 | I88: =-I64 -> 9834.409 | J88: =-J64 -> 13048.218 | ... L88: =-L64 -> 13667.616 | R88: =-SUM(O64:R64) -> 6607.604 | S88: =-SUM(P64:S64) -> 7256.63 | T88: =-SUM(Q64:T64) -> 7290.599 | U88: =-SUM(R64:U64) -> 7534.897 | V88: =-SUM(S64:V64) -> 7232.591 | W88: =-SUM(T64:W64) -> 7027.952 | X88: =-SUM(U64:X64) -> 6881.131 | Y88: =-SUM(V64:Y64) -> 6872.613 | ... AU88: =-SUM(AR64:AU64) -> 13588.264
B89: Net Income | C89: =+C29 -> 15888.499 | D89: =+D29 -> 15084.213 | E89: =+E29 -> 18625.943 | F89: =+F29 -> 22283.757 | G89: =+G29 -> 18623.045 | H89: =+H29 -> 23723.857 | I89: =+I29 -> 34604.049 | J89: =+J29 -> 24578.01 | ... L89: =+L29 -> 23262.06 | R89: =SUM(O29:R29) -> 18625.943 | S89: =SUM(P29:S29) -> 20675.959 | T89: =SUM(Q29:T29) -> 20707.427 | U89: =SUM(R29:U29) -> 21526.811 | V89: =SUM(S29:V29) -> 22283.757 | W89: =SUM(T29:W29) -> 22148.556 | X89: =SUM(U29:X29) -> 21732.001 | Y89: =SUM(V29:Y29) -> 20488.096 | ... AU89: =SUM(AR29:AU29) -> 21840.439
B90: Capex | C90: =-C66 -> 36439.699 | D90: =-D66 -> 42003.19 | E90: =-E66 -> 42596.556 | F90: =-F66 -> 50873.761 | G90: =-G66 -> 60175.781 | H90: =-H66 -> 92570.681 | I90: =-I66 -> 97232.32 | J90: =-J66 -> 69787.672 | ... L90: =-L66 -> 44998.772 | R90: =-SUM(O66:R66) -> 42596.556 | S90: =-SUM(P66:S66) -> 44737.23 | T90: =-SUM(Q66:T66) -> 38673.033 | U90: =-SUM(R66:U66) -> 42062.589 | V90: =-SUM(S66:V66) -> 50873.761 | W90: =-SUM(T66:W66) -> 52775.823 | X90: =-SUM(U66:X66) -> 52768.816 | Y90: =-SUM(V66:Y66) -> 52344.773 | ... AU90: =-SUM(AR66:AU66) -> 49307
B91: Free cash flow | C91: =+C68 -> -28986.963 | D91: =+D68 -> -15138.234 | E91: =+E68 -> 3160.488 | F91: =+F68 -> 5198.653 | G91: =+G68 -> -10963.719 | H91: =+H68 -> -42725.014 | I91: =+I68 -> -48611.035 | J91: =+J68 -> -11778.173 | ... L91: =+L68 -> 16470.663 | R91: =SUM(O68:R68) -> 3160.488 | S91: =SUM(P68:S68) -> 7143.924 | T91: =SUM(Q68:T68) -> 10143.298 | U91: =SUM(R68:U68) -> 9481.112 | V91: =SUM(S68:V68) -> 5198.653 | W91: =SUM(T68:W68) -> 31.927 | X91: =SUM(U68:X68) -> -8130.335 | Y91: =SUM(V68:Y68) -> -5080.701 | ... AU91: =SUM(AR68:AU68) -> 12949.454
B93: BALANCE SHEET | C93: =C82 -> 42735 | D93: =D82 -> 43100 | E93: =E82 -> 43465 | F93: =F82 -> 43830 | G93: =G82 -> 44196 | H93: =H82 -> 44561 | I93: =I82 -> 44926 | J93: =J82 -> 45291 | ... L93: =L82 -> 46022 | O93: =O82 -> 43190 | P93: =P82 -> 43281 | Q93: =Q82 -> 43373 | R93: =R82 -> 43465 | S93: =S82 -> 43555 | T93: =T82 -> 43646 | U93: =U82 -> 43738 | V93: =V82 -> 43830 | ... AU93: =AU82 -> 46112
B95: Tangible fixed assets | C95: 142251.98 | D95: 16602.646 | E95: =169393.768 -> 169393.77 | F95: =182662.528+3566.28 -> 186228.81 | G95: =190292.393+4300.835 -> 194593.23 | H95: =270747.147+19687.012 -> 290434.16 | I95: =281899.06+37108.116 -> 319007.18 | J95: =334408.653+69538.796 -> 403947.45 | K95: =352115.098+90464.458 -> 442579.56 | L95: =356127.191+99418.585 -> 455545.78 | O95: 162273.93 | P95: 169068.02 | Q95: =168803.619 -> 168803.62 | R95: =E95 -> 169393.77 | S95: =170051.265 +3284.863 -> 173336.13 | T95: =172051.712+3265.876 -> 175317.59 | U95: =178453.614+3253.858 -> 181707.47 | V95: =F95 -> 186228.81 | W95: =186498.895+3687.482 -> 190186.38 | X95: =189017.153+3982.301 -> 192999.45 | Y95: =190915.573+4104.177 -> 195019.75 | Z95: =G95 -> 194593.23 | AA95: =202475.692+4449.201 -> 206924.89 | AB95: =219498.126+4936.397 -> 224434.52 | AC95: =250673.176+13765.624 -> 264438.8 | AD95: =H95 -> 290434.16 | AE95: =276761.829+22613.181 -> 299375.01 | AF95: =287630.222+23931.821 -> 311562.04 | AG95: =270851.261+20616.275 -> 291467.54 | AH95: =I95 -> 319007.18 | AI95: =300086.803+44055.99 -> 344142.79 | AJ95: =318227.998+55859.739 -> 374087.74 | AK95: =331555.439+63662.565 -> 395218 | AL95: =J95 -> 403947.45 | AM95: =340897.379+74928.596 -> 415825.98 | AN95: =345957.666+78919.589 -> 424877.26 | AO95: =348663.699+87887.778 -> 436551.48 | AP95: =K95 -> 442579.56 | AQ95: =353736.867+91919.233 -> 445656.1 | AR95: =353827.094+93664.003 -> 447491.1 | AS95: =359923.032+96442.381 -> 456365.41 | AT95: =L95 -> 455545.78 | AU95: =359923.763+104443.855 -> 464367.62
B96: Inventory | C96: 4579.954 | D96: 3242.689 | E96: 4854.939 | F96: 4713.572 | G96: 5988.899 | H96: 4045.049 | I96: 3881.682 | J96: =3388.42 -> 3388.42 | K96: 2964.814 | L96: 2318.95 | O96: 4138.665 | P96: 3527.62 | Q96: 2722.888 | R96: =E96 -> 4854.939 | S96: 4348.191 | T96: 3579.641 | U96: 2806.577 | V96: =F96 -> 4713.572 | W96: 3742.685 | X96: 5099.153 | Y96: 5022.653 | Z96: =G96 -> 5988.899 | AA96: 5538.852 | AB96: 4907.584 | AC96: 4268.216 | AD96: =H96 -> 4045.049 | AE96: 4607.026 | AF96: 4741.969 | AG96: 4434.409 | AH96: =I96 -> 3881.682 | AI96: 5301.781 | AJ96: 3664.534 | AK96: 2559.75 | AL96: =J96 -> 3388.42 | AM96: 2681.387 | AN96: =2262.792 -> 2262.792 | AO96: 1723.045 | AP96: =K96 -> 2964.814 | AQ96: 2713.034 | AR96: 2084.826 | AS96: 1873.047 | AT96: =L96 -> 2318.95 | AU96: 2242.372
B97: Trade debtors | C97: 26944.645 | D97: 27304.288 | E97: 20652.532 | F97: 21138.95 | G97: 20145.484 | H97: 16696.542 | I97: 23563.414 | J97: =18097.898 -> 18097.898 | K97: 19660.468 | L97: 17892.54 | O97: 20166.278 | P97: 19009.113 | Q97: 19592.18 | R97: =E97 -> 20652.532 | S97: 19838.092 | T97: 20360.555 | U97: 18772.662 | V97: =F97 -> 21138.95 | W97: 22903.121 | X97: 22851.701 | Y97: 20112.43 | Z97: =G97 -> 20145.484 | AA97: 18749.756 | AB97: 17113.365 | AC97: 16482.969 | AD97: =H97 -> 16696.542 | AE97: 18077.122 | AF97: 19453.526 | AG97: 20267.404 | AH97: =I97 -> 23563.414 | AI97: 22127.393 | AJ97: 21554.51 | AK97: 23453.299 | AL97: =J97 -> 18097.898 | AM97: 17391.927 | AN97: =17806.91 -> 17806.91 | AO97: 17707.198 | AP97: =K97 -> 19660.468 | AQ97: 17456.792 | AR97: 18354.685 | AS97: 17548.974 | AT97: =L97 -> 17892.54 | AU97: 17598.742
B98: Trade creditors | C98: 59137.686 | D98: 62232.862 | E98: 56219.366 | F98: 56979.315 | G98: 56377.186 | H98: 84576.156 | I98: 88380.797 | J98: =87664.258 -> 87664.258 | K98: 78107.332 | L98: 72188.252 | O98: 62333.147 | P98: 59065.571 | Q98: 56737.981 | R98: =E98 -> 56219.366 | S98: 54405.796 | T98: 56312.072 | U98: 59157.477 | V98: =F98 -> 56979.315 | W98: 55906.909 | X98: 55764.729 | Y98: 58680.249 | Z98: =G98 -> 56377.186 | AA98: 60817.162 | AB98: 67632.13 | AC98: 84488.914 | AD98: =H98 -> 84576.156 | AE98: 84852.759 | AF98: 83066.001 | AG98: 82964.97 | AH98: =I98 -> 88380.797 | AI98: 96523.261 | AJ98: 102448.85 | AK98: 23453.299 | AL98: =J98 -> 87664.258 | AM98: 89094.656 | AN98: =87210.623 -> 87210.623 | AO98: 81171.247 | AP98: =K98 -> 78107.332 | AQ98: 80067.963 | AR98: 76064.07 | AS98: 77605.785 | AT98: =L98 -> 72188.252 | AU98: 73016.283
B99: Net working capital | C99: =C96+C97-C98 -> -27613.087 | D99: =D96+D97-D98 -> -31685.885 | E99: =E96+E97-E98 -> -30711.895 | F99: =F96+F97-F98 -> -31126.793 | G99: =G96+G97-G98 -> -30242.803 | H99: =H96+H97-H98 -> -63834.565 | I99: =I96+I97-I98 -> -60935.701 | J99: =J96+J97-J98 -> -66177.94 | ... L99: =L96+L97-L98 -> -51976.762 | O99: =O96+O97-O98 -> -38028.204 | P99: =P96+P97-P98 -> -36528.838 | Q99: =Q96+Q97-Q98 -> -34422.913 | R99: =R96+R97-R98 -> -30711.895 | S99: =S96+S97-S98 -> -30219.513 | T99: =T96+T97-T98 -> -32371.876 | U99: =U96+U97-U98 -> -37578.238 | V99: =V96+V97-V98 -> -31126.793 | ... AU99: =AU96+AU97-AU98 -> -53175.169
B100: % of revenues | C100: =C99/C84 -> -0.21780033 | D100: =D99/D84 -> -0.23422319 | E100: =E99/E84 -> -0.20315754 | F100: =F99/F84 -> -0.18676785 | G100: =G99/G84 -> -0.18840574 | H100: =H99/H84 -> -0.37884811 | I100: =I99/I84 -> -0.348123 | J100: =J99/J84 -> -0.36731962 | ... L100: =L99/L84 -> -0.29161135 | R100: =R99/R84 -> -0.20315754 | S100: =S99/S84 -> -0.19512668 | T100: =T99/T84 -> -0.20456439 | U100: =U99/U84 -> -0.23055836 | V100: =V99/V84 -> -0.18676785 | W100: =W99/W84 -> -0.17499025 | X100: =X99/X84 -> -0.16964495 | Y100: =Y99/Y84 -> -0.20600656 | ... AU100: =AU99/AU84 -> -0.2951051
B102: Inventory Days | C102: =C96/-C18*365 -> 140.31116 | D102: =D96/-D18*365 -> 90.950722 | E102: =E96/-E18*365 -> 95.040112 | F102: =F96/-F18*365 -> 92.722772 | G102: =G96/-G18*365 -> 133.23918 | H102: =H96/-H18*365 -> 85.305186 | I102: =I96/-I18*365 -> 80.083642 | J102: =J96/-J18*365 -> 67.890998 | ... L102: =L96/-L18*365 -> 62.757701 | O102: =O96/-O18*365/4 -> 79.57316 | P102: =P96/-P18*365/4 -> 69.001148 | Q102: =Q96/-Q18*365/4 -> 58.846768 | R102: =R96/-R18*365/4 -> 88.389741 | S102: =S96/-S18*365/4 -> 85.962864 | T102: =T96/-T18*365/4 -> 72.635395 | U102: =U96/-U18*365/4 -> 61.816444 | V102: =V96/-V18*365/4 -> 81.164767 | ... AU102: =AU96/-AU18*365/4 -> 53.026943
B103: Receivable Days | C103: =C97/C10*365 -> 77.572698 | D103: =D97/D10*365 -> 73.66951 | E103: =E97/E10*365 -> 49.864618 | F103: =F97/F10*365 -> 46.296059 | G103: =G97/G10*365 -> 45.80814 | H103: =H97/H10*365 -> 36.168344 | I103: =I97/I10*365 -> 49.135115 | J103: =J97/J10*365 -> 36.665017 | ... L103: =L97/L10*365 -> 36.640388 | O103: =O97/O10*365/4 -> 49.818385 | P103: =P97/P10*365/4 -> 46.245225 | Q103: =Q97/Q10*365/4 -> 48.114665 | R103: =R97/R10*365/4 -> 47.6255 | S103: =S97/S10*365/4 -> 44.547271 | T103: =T97/T10*365/4 -> 45.442164 | U103: =U97/U10*365/4 -> 40.886212 | V103: =V97/V10*365/4 -> 44.607335 | ... AU103: =AU97/AU10*365/4 -> 35.13476
B104: Payable Days
B106: Debt Breakdown
B107: Short-term debt | C107: 5830.319 | D107: 8278.222 | E107: 16758.196 | F107: 12919.898 | G107: 8521.424 | H107: 16018.505 | I107: 46172.043 | J107: =36792.956 -> 36792.956 | K107: 26349.796 | L107: 22218.988 | O107: 11085.88 | P107: 16588.399 | Q107: 16851.331 | R107: =E107 -> 16758.196 | S107: 8503.288 | T107: 8939.558 | U107: 13007.917 | V107: =F107 -> 12919.898 | W107: 18531.427 | X107: 21927.244 | Y107: 7868.313 | Z107: =G107 -> 8521.424 | AA107: 2949.138 | AB107: 13566.904 | AC107: 19769.604 | AD107: =H107 -> 16018.505 | AE107: 15819.545 | AF107: 42649.517 | AG107: 51177.525 | AH107: =I107 -> 46172.043 | AI107: 49895.268 | AJ107: 64639.247 | AK107: 63963.507 | AL107: =J107 -> 36792.956 | AM107: 42563.395 | AN107: 43759.445 | AO107: 26159.527 | AP107: =K107 -> 26349.796 | AQ107: 16124.396 | AR107: 13108.553 | AS107: 22202.462 | AT107: =L107 -> 22218.988 | AU107: 21273.744
B108: Long-term debt | C108: 95398.272 | D108: 123250.48 | E108: 131523.7 | F108: 122942.84 | G108: 156270.73 | H108: 194035.06 | I108: 187032.62 | J108: =213162.613 -> 213162.61 | K108: 223110.11 | L108: 234094.41 | O108: 116763.77 | P108: 117448.41 | Q108: 117235.42 | R108: =E108 -> 131523.7 | S108: 129933.56 | T108: 123166.44 | U108: 118937.03 | V108: =F108 -> 122942.84 | W108: 126158.41 | X108: 128062.29 | Y108: 155773.42 | Z108: =G108 -> 156270.73 | AA108: 165811.35 | AB108: 170620.41 | AC108: 187643.67 | AD108: =H108 -> 194035.06 | AE108: 201921.22 | AF108: 197395.63 | AG108: 197185.6 | AH108: =I108 -> 187032.62 | AI108: 184605.08 | AJ108: 185369.21 | AK108: 181515.36 | AL108: =J108 -> 213162.61 | AM108: 204174.93 | AN108: 204975.15 | AO108: 214777.89 | AP108: =K108 -> 223110.11 | AQ108: 225851.34 | AR108: 234790 | AS108: 231288.99 | AT108: =L108 -> 234094.41 | AU108: 229963.54
B109: Total Debt | C109: =C107+C108 -> 101228.59 | D109: =D107+D108 -> 131528.7 | E109: =E107+E108 -> 148281.9 | F109: =F107+F108 -> 135862.73 | G109: =G107+G108 -> 164792.15 | H109: =H107+H108 -> 210053.57 | I109: =I107+I108 -> 233204.66 | J109: =J107+J108 -> 249955.57 | ... L109: =L107+L108 -> 256313.4 | O109: =O107+O108 -> 127849.65 | P109: =P107+P108 -> 134036.81 | Q109: =Q107+Q108 -> 134086.75 | R109: =E109 -> 148281.9 | S109: =S107+S108 -> 138436.85 | T109: =T107+T108 -> 132106 | U109: =U107+U108 -> 131944.95 | V109: =F109 -> 135862.73 | W109: =W107+W108 -> 144689.84 | X109: =X107+X108 -> 149989.54 | Y109: =Y107+Y108 -> 163641.73 | Z109: =Z107+Z108 -> 164792.15 | AA109: =AA107+AA108 -> 168760.49 | AB109: =AB107+AB108 -> 184187.32 | AC109: =AC107+AC108 -> 207413.27 | AD109: =AD107+AD108 -> 210053.57 | ... AU109: =AU107+AU108 -> 251237.28
B111: Lease Obligations
B112: Short-term debt | C112: 0 | D112: 0 | E112: 0 | F112: 981.817 | G112: 999.2 | H112: 3664.344 | I112: 4522.438 | J112: =5899.426 -> 5899.426 | K112: 8175.643 | L112: 9067.593 | O112: 0 | P112: 0 | Q112: 0 | R112: =E112 -> 0 | S112: 865.42 | T112: 914.018 | U112: 985.61 | V112: =F112 -> 981.817 | W112: 1059.34 | X112: 1001.988 | Y112: 1037.98 | Z112: =G112 -> 999.2 | AA112: 944.537 | AB112: 965.309 | AC112: 959.507 | AD112: =H112 -> 3664.344 | AE112: 3796.89 | AF112: 7712.459 | AG112: 3976.141 | AH112: =I112 -> 4522.438 | AI112: 4756.867 | AJ112: 4517.986 | AK112: 2707.468 | AL112: =J112 -> 5899.426 | AM112: 6244.409 | AN112: 6422.161 | AO112: 7201.679 | AP112: =K112 -> 8175.643 | AQ112: 8971.21 | AR112: 8721.936 | AS112: 8575.791 | AT112: =L112 -> 9067.593 | AU112: 8668.237
B113: Long-term debt | C113: 0 | D113: 0 | E113: 0 | F113: 2681.8 | G113: 3525.472 | H113: 16215.004 | I113: 49709.159 | J113: 82825.056 | K113: 107932.23 | L113: 120177.86 | O113: 0 | P113: 0 | Q113: 0 | R113: =E113 -> 0 | S113: 2425.805 | T113: 2392.802 | U113: 2345.335 | V113: =F113 -> 2681.8 | W113: 2765.232 | X113: 3148.027 | Y113: 3262.341 | Z113: =G113 -> 3525.472 | AA113: 3728.179 | AB113: 4199.581 | AC113: 13102.115 | AD113: =H113 -> 16215.004 | AE113: 19066.155 | AF113: 16600.816 | AG113: 31280.66 | AH113: =I113 -> 49709.159 | AI113: 58310.467 | AJ113: 72151.263 | AK113: 80747.203 | AL113: =J113 -> 82825.056 | AM113: 89042.221 | AN113: 94023.902 | AO113: 106415.66 | AP113: =K113 -> 107932.23 | AQ113: 109463.99 | AR113: 114429.3 | AS113: 118448.2 | AT113: =L113 -> 120177.86 | AU113: 126362.16
B114: Total Lease | C114: =C112+C113 -> 0 | D114: =D112+D113 -> 0 | E114: =E112+E113 -> 0 | F114: =F112+F113 -> 3663.617 | G114: =G112+G113 -> 4524.672 | H114: =H112+H113 -> 19879.348 | I114: =I112+I113 -> 54231.597 | J114: =J112+J113 -> 88724.482 | ... L114: =L112+L113 -> 129245.46 | O114: =SUM(O112:O113) -> 0 | P114: =SUM(P112:P113) -> 0 | Q114: =SUM(Q112:Q113) -> 0 | R114: =SUM(R112:R113) -> 0 | S114: =SUM(S112:S113) -> 3291.225 | T114: =SUM(T112:T113) -> 3306.82 | U114: =SUM(U112:U113) -> 3330.945 | V114: =SUM(V112:V113) -> 3663.617 | ... AP114: =SUM(AP112:AP113) -> 116107.87 | AQ114: =AQ112+AQ113 -> 118435.2 | AR114: =SUM(AR112:AR113) -> 123151.24 | AS114: =SUM(AS112:AS113) -> 127023.99 | AT114: =SUM(AT112:AT113) -> 129245.46 | AU114: =AU112+AU113 -> 135030.39
B116: Debt Including Lease and perpetuals
...

Sheet KPI
B2: Globe Telecom Philippines | C2: Annual | D2: Annual | E2: Annual | F2: Annual | G2: Annual | H2: Annual | I2: Annual | J2: Annual | K2: Annual | L2: Annual | M2: LTM | O2: Quarterly | P2: Quarterly | Q2: Quarterly | R2: Quarterly | S2: Quarterly | T2: Quarterly | U2: Quarterly | V2: Quarterly | W2: Quarterly | X2: Quarterly | Y2: Quarterly | Z2: Quarterly | AA2: Quarterly | AB2: Quarterly | AC2: Quarterly | AD2: Quarterly | AE2: Quarterly | AF2: Quarterly | AG2: Quarterly | AH2: Quarterly | AI2: Quarterly | AJ2: Quarterly | AK2: Quarterly | AL2: Quarterly | AM2: Quarterly | AN2: Quarterly | AO2: Quarterly | AP2: Quarterly | AQ2: Quarterly | AR2: Quarterly | AS2: Quarterly | AT2: Quarterly | AU2: Quarterly
B3: (PHP millions) | C3: 42735 | D3: =EDATE(C3,12) -> 43100 | E3: =EDATE(D3,12) -> 43465 | F3: =EDATE(E3,12) -> 43830 | G3: =EDATE(F3,12) -> 44196 | H3: =EDATE(G3,12) -> 44561 | I3: =EDATE(H3,12) -> 44926 | J3: =EDATE(I3,12) -> 45291 | K3: =EDATE(J3,12) -> 45657 | L3: =EDATE(K3,12) -> 46022 | M3: =AV3 -> 0 | O3: 43160 | P3: 43252 | Q3: 43344 | R3: 43435 | S3: 43525 | T3: 43617 | U3: 43709 | V3: 43800 | W3: 43891 | X3: 43983 | Y3: 44075 | Z3: 44166 | AA3: 44256 | AB3: 44348 | AC3: 44440 | AD3: 44531 | AE3: 44621 | AF3: 44713 | AG3: 44805 | AH3: 44896 | AI3: 44986 | AJ3: 45078 | AK3: 45170 | AL3: 45261 | AM3: 45352 | AN3: 45444 | AO3: 45536 | AP3: 45627 | AQ3: 45717 | AR3: 45809 | AS3: 45901 | AT3: 45992 | AU3: 46082
C4: Act | D4: Act | E4: Act | F4: Act | G4: Act | H4: Act | I4: Act | J4: Act | K4: Act | L4: Act | M4: Act | O4: Act | P4: Act | Q4: Act | R4: Act | S4: Act | T4: Act | U4: Act | V4: Act | W4: Act | X4: Act | Y4: Act | Z4: Act | AA4: Act | AB4: Act | AC4: Act | AD4: Act | AE4: Act | AF4: Act | AG4: Act | AH4: Act | AI4: Act | AJ4: Act | AK4: Act | AL4: Act | AM4: Act | AN4: Act | AO4: Act | AP4: Act | AQ4: Act | AR4: Act | AS4: Act | AT4: Act | AU4: Act
C5: FY | D5: FY | E5: FY | F5: FY | G5: FY | H5: FY | I5: FY | J5: FY | K5: FY | L5: FY | M5: LTM | O5: Q1 | P5: Q2 | Q5: Q3 | R5: Q4 | S5: Q1 | T5: Q2 | U5: Q3 | V5: Q4 | W5: Q1 | X5: Q2 | Y5: Q3 | Z5: Q4 | AA5: Q1 | AB5: Q2 | AC5: Q3 | AD5: Q4 | AE5: Q1 | AF5: Q2 | AG5: Q3 | AH5: Q4 | AI5: Q1 | AJ5: Q2 | AK5: Q3 | AL5: Q4 | AM5: Q1 | AN5: Q2 | AO5: Q3 | AP5: Q4 | AQ5: Q1 | AR5: Q2 | AS5: Q3 | AT5: Q4 | AU5: Q1
B8: Revenue by business segment
B9: Mobile Communications | C9: =+C11+C12+C13+C14+C15+C16 -> 97925.564 | D9: =+D11+D12+D13+D14+D15+D16 -> 105586.15 | E9: =+E11+E12+E13+E14+E15+E16 -> 117436.27 | F9: =+F11+F12+F13+F14+F15+F16 -> 129024.24 | G9: =+G11+G12+G13+G14+G15+G16 -> 115082.19 | H9: =+H11+H12+H13+H14+H15+H16 -> 119592.24 | I9: =+I11+I12+I13+I14+I15+I16 -> 124084.84 | J9: =+J11+J12+J13+J14+J15+J16 -> 129833.26 | ... M9: =+M11+M12+M13+M14+M15+M16 -> 99557.581 | O9: =+O11+O12+O13+O14+O15+O16 -> 29108.214 | P9: =+P11+P12+P13+P14+P15+P16 -> 29416.691 | Q9: =+Q11+Q12+Q13+Q14+Q15+Q16 -> 28523.406 | R9: =+R11+R12+R13+R14+R15+R16 -> 30387.962 | S9: =+S11+S12+S13+S14+S15+S16 -> 31417.808 | T9: =+T11+T12+T13+T14+T15+T16 -> 31660.231 | U9: =+U11+U12+U13+U14+U15+U16 -> 32415.748 | V9: =+V11+V12+V13+V14+V15+V16 -> 33530.45 | ... AU9: =+AU11+AU12+AU13+AU14+AU15+AU16 -> 33705.482
B10: Service revenues: | R10: =+E10-SUM(O10:Q10) -> 0
B11: Data | C11: 34991.091 | D11: 43058.894 | E11: 50960.555 | F11: 71801.472 | G11: 71953.848 | H11: 77812.713 | I11: 83758.035 | J11: 90894.707 | K11: 97368.837 | L11: 101166.06 | M11: =SUM(AS11:AV11) -> 79118.406 | O11: 11481.915 | P11: =23416.783-O11 -> 11934.868 | Q11: =36166.39-P11-O11 -> 12749.607 | R11: =+E11-SUM(O11:Q11) -> 14794.165 | S11: 16487.975 | T11: =34036.778-S11 -> 17548.803 | U11: =52218.535-T11-S11 -> 18181.757 | V11: =+F11-SUM(S11:U11) -> 19582.937 | W11: 18470.828 | X11: =35847.804-W11 -> 17376.976 | Y11: =53401.309-X11-W11 -> 17553.505 | Z11: =+G11-SUM(W11:Y11) -> 18552.539 | AA11: 19204.087 | AB11: =38632.568-AA11 -> 19428.481 | AC11: =57915.33-AB11-AA11 -> 19282.762 | AD11: =+H11-SUM(AA11:AC11) -> 19897.383 | AE11: 20841.338 | AF11: =41836.71-AE11 -> 20995.372 | AG11: =62546.552-AF11-AE11 -> 20709.842 | AH11: =+I11-SUM(AE11:AG11) -> 21211.483 | AI11: 21657.313 | AJ11: =44036.306-AI11 -> 22378.993 | AK11: =67046.878-AJ11-AI11 -> 23010.572 | AL11: =+J11-SUM(AI11:AK11) -> 23847.829 | AM11: 23831.211 | AN11: =48010.98-AM11 -> 24179.769 | AO11: =72859.051-AN11-AM11 -> 24848.071 | AP11: =+K11-SUM(AM11:AO11) -> 24509.786 | AQ11: 24124.789 | AR11: =48831.557-AQ11 -> 24706.768 | AS11: =73996.839-AR11-AQ11 -> 25165.282 | AT11: =+L11-SUM(AQ11:AS11) -> 27169.222 | AU11: 26783.902
B12: Voice | C12: 34065.3 | D12: 32274.474 | E12: 28407.83 | F12: 24275.585 | G12: 20129.875 | H12: 17228.714 | I12: 14916.566 | J12: 13505.925 | K12: 12652.83 | L12: 10882.048 | M12: =SUM(AS12:AV12) -> 7784.986 | O12: 7324.831 | P12: =14760.032-O12 -> 7435.201 | Q12: =21753.542-P12-O12 -> 6993.51 | R12: =+E12-SUM(O12:Q12) -> 6654.288 | S12: 6197.795 | T12: =12316.334-S12 -> 6118.539 | U12: =18495.762-T12-S12 -> 6179.428 | V12: =+F12-SUM(S12:U12) -> 5779.823 | W12: 5288.667 | X12: =10206.875-W12 -> 4918.208 | Y12: =15306.266-X12-W12 -> 5099.391 | Z12: =+G12-SUM(W12:Y12) -> 4823.609 | AA12: 4711.361 | AB12: =9112.982-AA12 -> 4401.621 | AC12: =13281.404-AB12-AA12 -> 4168.422 | AD12: =+H12-SUM(AA12:AC12) -> 3947.31 | AE12: 3899.23 | AF12: =7769.43-AE12 -> 3870.2 | AG12: =11389.308-AF12-AE12 -> 3619.878 | AH12: =+I12-SUM(AE12:AG12) -> 3527.258 | AI12: 3427.074 | AJ12: =6793.917-AI12 -> 3366.843 | AK12: =10168.49-AJ12-AI12 -> 3374.573 | AL12: =+J12-SUM(AI12:AK12) -> 3337.435 | AM12: 3355.937 | AN12: =6635.061-AM12 -> 3279.124 | AO12: =9642.449-AN12-AM12 -> 3007.388 | AP12: =+K12-SUM(AM12:AO12) -> 3010.381 | AQ12: 2776.253 | AR12: =5534.864-AQ12 -> 2758.611 | AS12: =8283.253-AR12-AQ12 -> 2748.389 | AT12: =+L12-SUM(AQ12:AS12) -> 2598.795 | AU12: 2437.802
B13: SMS | C13: 23198.924 | D13: 23149.293 | E13: 20162.343 | F13: 15690.309 | G13: 11029.64 | H13: 9350.815 | I13: 8845.422 | J13: 7975.319 | K13: 6691.721 | L13: 4801.389 | M13: =SUM(AS13:AV13) -> 2838.023 | O13: 5402.15 | P13: =10837.592-O13 -> 5435.442 | Q13: =15772.38-P13-O13 -> 4934.788 | R13: =+E13-SUM(O13:Q13) -> 4389.963 | S13: 4196.915 | T13: =8283.258-S13 -> 4086.343 | U13: =12285.502-T13-S13 -> 4002.244 | V13: =+F13-SUM(S13:U13) -> 3404.807 | W13: 3033.833 | X13: =5777.977-W13 -> 2744.144 | Y13: =8602.79-X13-W13 -> 2824.813 | Z13: =+G13-SUM(W13:Y13) -> 2426.85 | AA13: 2400.977 | AB13: =4826.972-AA13 -> 2425.995 | AC13: =7167.415-AB13-AA13 -> 2340.443 | AD13: =+H13-SUM(AA13:AC13) -> 2183.4 | AE13: 2148.86 | AF13: =4440.455-AE13 -> 2291.595 | AG13: =6650.753-AF13-AE13 -> 2210.298 | AH13: =+I13-SUM(AE13:AG13) -> 2194.669 | AI13: 2007.807 | AJ13: =3992.439-AI13 -> 1984.632 | AK13: =5964.287-AJ13-AI13 -> 1971.848 | AL13: =+J13-SUM(AI13:AK13) -> 2011.032 | AM13: 1939.027 | AN13: =3745.909-AM13 -> 1806.882 | AO13: =5204.629-AN13-AM13 -> 1458.72 | AP13: =+K13-SUM(AM13:AO13) -> 1487.092 | AQ13: 1393.051 | AR13: =2706.677-AQ13 -> 1313.626 | AS13: =3892.904-AR13-AQ13 -> 1186.227 | AT13: =+L13-SUM(AQ13:AS13) -> 908.485 | AU13: 743.311
B14: Broadband | C14: 0 | D14: 0 | E14: 0 | F14: 0 | G14: 0 | H14: 0 | I14: 0 | J14: 0 | K14: 0 | L14: 0 | M14: =SUM(AS14:AV14) -> 0 | O14: 0 | P14: =0-O14 -> 0 | Q14: =0-P14-O14 -> 0 | R14: =+E14-SUM(O14:Q14) -> 0 | S14: 0 | T14: =0-S14 -> 0 | U14: =0-T14-S14 -> 0 | V14: =+F14-SUM(S14:U14) -> 0 | W14: 0 | X14: =0-W14 -> 0 | Y14: =0-X14-W14 -> 0 | Z14: =+G14-SUM(W14:Y14) -> 0 | AA14: 0 | AB14: =0-AA14 -> 0 | AC14: =0-AB14-AA14 -> 0 | AD14: =+H14-SUM(AA14:AC14) -> 0 | AE14: 0 | AF14: =0-AE14 -> 0 | AG14: =0-AF14-AE14 -> 0 | AH14: =+I14-SUM(AE14:AG14) -> 0 | AI14: 0 | AJ14: =0-AI14 -> 0 | AK14: =0-AJ14-AI14 -> 0 | AL14: =+J14-SUM(AI14:AK14) -> 0 | AM14: 0 | AN14: =0-AM14 -> 0 | AO14: =0-AN14-AM14 -> 0 | AP14: =+K14-SUM(AM14:AO14) -> 0 | AQ14: 0 | AR14: =0-AQ14 -> 0 | AS14: =0-AR14-AQ14 -> 0 | AT14: =+L14-SUM(AQ14:AS14) -> 0 | AU14: 0
B15: Other | C15: 0 | D15: 0 | E15: 0 | F15: 0 | G15: 0 | H15: 0 | I15: 0 | J15: 0 | K15: 0 | L15: 0 | M15: =SUM(AS15:AV15) -> 0 | O15: 0 | P15: =0-O15 -> 0 | Q15: =0-P15-O15 -> 0 | R15: =+E15-SUM(O15:Q15) -> 0 | S15: 0 | T15: =0-S15 -> 0 | U15: =0-T15-S15 -> 0 | V15: =+F15-SUM(S15:U15) -> 0 | W15: 0 | X15: =0-W15 -> 0 | Y15: =0-X15-W15 -> 0 | Z15: =+G15-SUM(W15:Y15) -> 0 | AA15: 0 | AB15: =0-AA15 -> 0 | AC15: =0-AB15-AA15 -> 0 | AD15: =+H15-SUM(AA15:AC15) -> 0 | AE15: 0 | AF15: =0-AE15 -> 0 | AG15: =0-AF15-AE15 -> 0 | AH15: =+I15-SUM(AE15:AG15) -> 0 | AI15: 0 | AJ15: =0-AI15 -> 0 | AK15: =0-AJ15-AI15 -> 0 | AL15: =+J15-SUM(AI15:AK15) -> 0 | AM15: 0 | AN15: =0-AM15 -> 0 | AO15: =0-AN15-AM15 -> 0 | AP15: =+K15-SUM(AM15:AO15) -> 0 | AQ15: 0 | AR15: =0-AQ15 -> 0 | AS15: =0-AR15-AQ15 -> 0 | AT15: =+L15-SUM(AQ15:AS15) -> 0 | AU15: 0
B16: Nonservice revenues | C16: 5670.249 | D16: 7103.49 | E16: 17905.545 | F16: 17256.871 | G16: 11968.825 | H16: 15199.998 | I16: 16564.819 | J16: 17457.309 | K16: 15201.455 | L16: 13050.019 | M16: =SUM(AS16:AV16) -> 9816.166 | O16: 4899.318 | P16: =9510.498-O16 -> 4611.18 | Q16: =13355.999-P16-O16 -> 3845.501 | R16: =+E16-SUM(O16:Q16) -> 4549.546 | S16: 4535.123 | T16: =8441.669-S16 -> 3906.546 | U16: =12493.988-T16-S16 -> 4052.319 | V16: =+F16-SUM(S16:U16) -> 4762.883 | W16: 3962.999 | X16: =5475.12-W16 -> 1512.121 | Y16: =8768.036-X16-W16 -> 3292.916 | Z16: =+G16-SUM(W16:Y16) -> 3200.789 | AA16: 4736.78 | AB16: =8212.069-AA16 -> 3475.289 | AC16: =11252.254-AB16-AA16 -> 3040.185 | AD16: =+H16-SUM(AA16:AC16) -> 3947.744 | AE16: 4257.865 | AF16: =8161.795-AE16 -> 3903.93 | AG16: =11842.183-AF16-AE16 -> 3680.388 | AH16: =+I16-SUM(AE16:AG16) -> 4722.636 | AI16: 4945.223 | AJ16: =8907.502-AI16 -> 3962.279 | AK16: =12417.537-AJ16-AI16 -> 3510.035 | AL16: =+J16-SUM(AI16:AK16) -> 5039.772 | AM16: 4058.38 | AN16: =7221.077-AM16 -> 3162.697 | AO16: =10457.109-AN16-AM16 -> 3236.032 | AP16: =+K16-SUM(AM16:AO16) -> 4744.346 | AQ16: 3867.523 | AR16: =6974.32-AQ16 -> 3106.797 | AS16: =9818.645-AR16-AQ16 -> 2844.325 | AT16: =+L16-SUM(AQ16:AS16) -> 3231.374 | AU16: 3740.467
B17: Wireline Communications | C17: =+C19+C20+C21+C22+C23+C24 -> 28856.096 | D17: =+D19+D20+D21+D22+D23+D24 -> 29694.58 | E17: =+E19+E20+E21+E22+E23+E24 -> 33736.533 | F17: =+F19+F20+F21+F22+F23+F24 -> 37636.1 | G17: =+G19+G20+G21+G22+G23+G24 -> 44029.614 | H17: =+H19+H20+H22+H21+H23+H24 -> 46806.11 | I17: =+I19+I20+I22+I21+I23+I24 -> 46670.826 | J17: =+J19+J20+J22+J21+J23+J24 -> 45289.363 | K17: =+K19+K20+K22+K21+K23+K24 -> 45940.536 | L17: =+L19+L20+L22+L21+L23+L24 -> 45931.731 | M17: =+M19+M20+M21+M22+M23+M24 -> 35590.46 | O17: =+O19+O20+O21+O22+O23+O24 -> 7829.412 | P17: =+P19+P20+P21+P22+P23+P24 -> 8091.648 | Q17: =+Q19+Q20+Q21+Q22+Q23+Q24 -> 8633.382 | R17: =+R19+R20+R21+R22+R23+R24 -> 9182.091 | S17: =+S19+S20+S21+S22+S23+S24 -> 9151.808 | T17: =+T19+T20+T21+T22+T23+T24 -> 9291.171 | U17: =+U19+U20+U21+U22+U23+U24 -> 9481.149 | V17: =+V19+V20+V21+V22+V23+V24 -> 9711.972 | ... AU17: =+AU19+AU20+AU21+AU22+AU23+AU24 -> 11635.923
B18: Service revenues:
B19: Data | C19: 9873.417 | D19: 10287.868 | E19: 11761.929 | F19: 12827.652 | G19: 12539.234 | H19: 14170.1 | I19: 17198.099 | J19: 18319.203 | K19: 20379.506 | L19: 20670.497 | M19: =SUM(AS19:AV19) -> 16179.258 | O19: 2666.57 | P19: =5492.761-O19 -> 2826.191 | Q19: =8437.238-P19-O19 -> 2944.477 | R19: =+E19-SUM(O19:Q19) -> 3324.691 | S19: 3136.219 | T19: =6294.489-S19 -> 3158.27 | U19: =9481.169-T19-S19 -> 3186.68 | V19: =+F19-SUM(S19:U19) -> 3346.483 | W19: 3250.423 | X19: =6199.21-W19 -> 2948.787 | Y19: =9276.673-X19-W19 -> 3077.463 | Z19: =+G19-SUM(W19:Y19) -> 3262.561 | AA19: 3322.683 | AB19: =6729.309-AA19 -> 3406.626 | AC19: =10388.197-AB19-AA19 -> 3658.888 | AD19: =+H19-SUM(AA19:AC19) -> 3781.903 | AE19: 3921.731 | AF19: =8151.542-AE19 -> 4229.811 | AG19: =12534.178-AF19-AE19 -> 4382.636 | AH19: =+I19-SUM(AE19:AG19) -> 4663.921 | AI19: 4504.629 | AJ19: =9071.921-AI19 -> 4567.292 | AK19: =13559.353-AJ19-AI19 -> 4487.432 | AL19: =+J19-SUM(AI19:AK19) -> 4759.85 | AM19: 4955.858 | AN19: =9789.005-AM19 -> 4833.147 | AO19: =15480.071-AN19-AM19 -> 5691.066 | AP19: =+K19-SUM(AM19:AO19) -> 4899.435 | AQ19: 4857.516 | AR19: =9626.663-AQ19 -> 4769.147 | AS19: =14995.089-AR19-AQ19 -> 5368.426 | AT19: =+L19-SUM(AQ19:AS19) -> 5675.408 | AU19: 5135.424
B20: Voice | C20: 3779.82 | D20: 3490.35 | E20: 2977.017 | F20: 2668.413 | G20: 2620.106 | H20: 2280.357 | I20: 1989.174 | J20: 1595.674 | K20: 1500.199 | L20: 1251.135 | M20: =SUM(AS20:AV20) -> 946.79 | O20: 768.976 | P20: =1511.88-O20 -> 742.904 | Q20: =2261.083-P20-O20 -> 749.203 | R20: =+E20-SUM(O20:Q20) -> 715.934 | S20: 710.33 | T20: =1393.641-S20 -> 683.311 | U20: =2062.378-T20-S20 -> 668.737 | V20: =+F20-SUM(S20:U20) -> 606.035 | W20: 696.624 | X20: =1301.319-W20 -> 604.695 | Y20: =2032.9-X20-W20 -> 731.581 | Z20: =+G20-SUM(W20:Y20) -> 587.206 | AA20: 599.086 | AB20: =1176.849-AA20 -> 577.763 | AC20: =1741.904-AB20-AA20 -> 565.055 | AD20: =+H20-SUM(AA20:AC20) -> 538.453 | AE20: 527.423 | AF20: =1012.515-AE20 -> 485.092 | AG20: =1516.42-AF20-AE20 -> 503.905 | AH20: =+I20-SUM(AE20:AG20) -> 472.754 | AI20: 426.474 | AJ20: =856.725-AI20 -> 430.251 | AK20: =1248.665-AJ20-AI20 -> 391.94 | AL20: =+J20-SUM(AI20:AK20) -> 347.009 | AM20: 382.954 | AN20: =762.961-AM20 -> 380.007 | AO20: =1129.99-AN20-AM20 -> 367.029 | AP20: =+K20-SUM(AM20:AO20) -> 370.209 | AQ20: 320.534 | AR20: =626.115-AQ20 -> 305.581 | AS20: =942.868-AR20-AQ20 -> 316.753 | AT20: =+L20-SUM(AQ20:AS20) -> 308.267 | AU20: 321.77
B21: SMS | C21: 0 | D21: 0 | E21: 0 | F21: 0 | G21: 0 | M21: =SUM(AS21:AV21) -> 0 | O21: 0 | P21: =0-O21 -> 0 | Q21: =0-P21-O21 -> 0 | R21: =+E21-SUM(O21:Q21) -> 0 | S21: 0 | T21: =0-S21 -> 0 | U21: =0-T21-S21 -> 0 | V21: =+F21-SUM(S21:U21) -> 0 | W21: 0 | X21: =0-W21 -> 0 | Y21: =0-X21-W21 -> 0 | Z21: =+G21-SUM(W21:Y21) -> 0 | AA21: 0 | AB21: =0-AA21 -> 0 | AC21: =0-AB21-AA21 -> 0 | AD21: =+H21-SUM(AA21:AC21) -> 0 | AE21: 0 | AF21: =0-AE21 -> 0 | AG21: =0-AF21-AE21 -> 0 | AH21: =+I21-SUM(AE21:AG21) -> 0 | AI21: 0 | AJ21: =0-AI21 -> 0 | AK21: =0-AJ21-AI21 -> 0 | AL21: =+J21-SUM(AI21:AK21) -> 0 | AM21: 0 | AN21: =0-AM21 -> 0 | AO21: =0-AN21-AM21 -> 0 | AP21: =+K21-SUM(AM21:AO21) -> 0 | AQ21: 0 | AR21: =0-AQ21 -> 0 | AS21: =0-AR21-AQ21 -> 0 | AT21: =+L21-SUM(AQ21:AS21) -> 0 | AU21: 0
B22: Broadband | C22: 14679.451 | D22: 15644.974 | E22: 18605.636 | F22: 21746.532 | G22: 26798.31 | H22: 29391.454 | I22: 27093.52 | J22: 25111.748 | K22: 23785.396 | L22: 23980.12 | M22: =SUM(AS22:AV22) -> 18449.65 | O22: 4297.749 | P22: =8727.132-O22 -> 4429.383 | Q22: =13553.078-P22-O22 -> 4825.946 | R22: =+E22-SUM(O22:Q22) -> 5052.558 | S22: 5207.354 | T22: =10554.213-S22 -> 5346.859 | U22: =16071.614-T22-S22 -> 5517.401 | V22: =+F22-SUM(S22:U22) -> 5674.918 | W22: 5779.956 | X22: =12512.794-W22 -> 6732.838 | Y22: =19548.475-X22-W22 -> 7035.681 | Z22: =+G22-SUM(W22:Y22) -> 7249.835 | AA22: 7350.644 | AB22: =14531.856-AA22 -> 7181.212 | AC22: =22397.312-AB22-AA22 -> 7865.456 | AD22: =+H22-SUM(AA22:AC22) -> 6994.142 | AE22: 7025.776 | AF22: =13794.756-AE22 -> 6768.98 | AG22: =20475.986-AF22-AE22 -> 6681.23 | AH22: =+I22-SUM(AE22:AG22) -> 6617.534 | AI22: 6531.853 | AJ22: =12809.116-AI22 -> 6277.263 | AK22: =18993.848-AJ22-AI22 -> 6184.732 | AL22: =+J22-SUM(AI22:AK22) -> 6117.9 | AM22: 6116.796 | AN22: =12100.164-AM22 -> 5983.368 | AO22: =17886.868-AN22-AM22 -> 5786.704 | AP22: =+K22-SUM(AM22:AO22) -> 5898.528 | AQ22: 5813.032 | AR22: =11708.118-AQ22 -> 5895.086 | AS22: =17840.249-AR22-AQ22 -> 6132.131 | AT22: =+L22-SUM(AQ22:AS22) -> 6139.871 | AU22: 6177.648
B23: Other | C23: 0 | D23: 0 | E23: 0 | F23: 0 | G23: 0 | H23: 0 | I23: 0 | J23: 0 | K23: 0 | L23: 0 | M23: =SUM(AS23:AV23) -> 0 | O23: 0 | P23: =0-O23 -> 0 | Q23: =0-P23-O23 -> 0 | R23: =+E23-SUM(O23:Q23) -> 0 | S23: 0 | T23: =0-S23 -> 0 | U23: =0-T23-S23 -> 0 | V23: =+F23-SUM(S23:U23) -> 0 | W23: 0 | X23: =0-W23 -> 0 | Y23: =0-X23-W23 -> 0 | Z23: =+G23-SUM(W23:Y23) -> 0 | AA23: 0 | AB23: =0-AA23 -> 0 | AC23: =0-AB23-AA23 -> 0 | AD23: =+H23-SUM(AA23:AC23) -> 0 | AE23: 0 | AF23: =0-AE23 -> 0 | AG23: =0-AF23-AE23 -> 0 | AH23: =+I23-SUM(AE23:AG23) -> 0 | AI23: 0 | AJ23: =0-AI23 -> 0 | AK23: =0-AJ23-AI23 -> 0 | AL23: =+J23-SUM(AI23:AK23) -> 0 | AM23: 0 | AN23: =0-AM23 -> 0 | AO23: =0-AN23-AM23 -> 0 | AP23: =+K23-SUM(AM23:AO23) -> 0 | AQ23: 0 | AR23: =0-AQ23 -> 0 | AS23: =0-AR23-AQ23 -> 0 | AT23: =+L23-SUM(AQ23:AS23) -> 0 | AU23: 0
B24: Nonservice revenues | C24: 523.408 | D24: 271.388 | E24: 391.951 | F24: 393.503 | G24: 2071.964 | H24: 964.199 | I24: 390.033 | J24: 262.738 | K24: 275.435 | L24: 29.979 | M24: =SUM(AS24:AV24) -> 14.762 | O24: 96.117 | P24: =189.287-O24 -> 93.17 | Q24: =303.043-P24-O24 -> 113.756 | R24: =+E24-SUM(O24:Q24) -> 88.908 | S24: 97.905 | T24: =200.636-S24 -> 102.731 | U24: =308.967-T24-S24 -> 108.331 | V24: =+F24-SUM(S24:U24) -> 84.536 | W24: 343.044 | X24: =912.351-W24 -> 569.307 | Y24: =1716.859-X24-W24 -> 804.508 | Z24: =+G24-SUM(W24:Y24) -> 355.105 | AA24: 273.236 | AB24: =494.409-AA24 -> 221.173 | AC24: =736.749-AB24-AA24 -> 242.34 | AD24: =+H24-SUM(AA24:AC24) -> 227.45 | AE24: 116.913 | AF24: =232.579-AE24 -> 115.666 | AG24: =323.618-AF24-AE24 -> 91.039 | AH24: =+I24-SUM(AE24:AG24) -> 66.415 | AI24: 65.408 | AJ24: =152.147-AI24 -> 86.739 | AK24: =226.762-AJ24-AI24 -> 74.615 | AL24: =+J24-SUM(AI24:AK24) -> 35.976 | AM24: 66.759 | AN24: =128.222-AM24 -> 61.463 | AO24: =195.765-AN24-AM24 -> 67.543 | AP24: =+K24-SUM(AM24:AO24) -> 79.67 | AQ24: 8.889 | AR24: =16.298-AQ24 -> 7.409 | AS24: =28.422-AR24-AQ24 -> 12.124 | AT24: =+L24-SUM(AQ24:AS24) -> 1.557 | AU24: 1.081
B25: Other | C25: =+C26+C27 -> 0 | D25: =+D26+D27 -> 0 | E25: =+E26+E27 -> 0 | F25: =+F26+F27 -> 0 | G25: =+G26+G27 -> 1407.74 | H25: =+H26+H27 -> 2098.108 | I25: =+I26+I27 -> 4285.055 | J25: =+J26+J27 -> 5041.832 | ... M25: =+M26+M27 -> 1572.552 | O25: =+O26+O27 -> 0 | P25: =+P26+P27 -> 0 | Q25: =+Q26+Q27 -> 0 | R25: =+R26+R27 -> 0 | S25: =+S26+S27 -> 66.451 | T25: =+T26+T27 -> -66.451 | U25: =+U26+U27 -> 0 | V25: =+V26+V27 -> 0 | ... AU25: =+AU26+AU27 -> 365.047
B26: Service revenues: | C26: 0 | D26: 0 | E26: 0 | F26: 0 | G26: 1317.121 | H26: 2028.68 | I26: 4178.519 | J26: 4930.908 | K26: 2637.8 | L26: 2326.408 | M26: =SUM(AS26:AV26) -> 1537.031 | O26: 0 | P26: =0-O26 -> 0 | Q26: =0-P26-O26 -> 0 | R26: =+E26-SUM(O26:Q26) -> 0 | S26: 66.451 | T26: =0-S26 -> -66.451 | U26: =0-T26-S26 -> 0 | V26: =+F26-SUM(S26:U26) -> 0 | W26: 361.643 | X26: =576.802-W26 -> 215.159 | Y26: =935.821-X26-W26 -> 359.019 | Z26: =+G26-SUM(W26:Y26) -> 381.3 | AA26: 224.397 | AB26: =858.523-AA26 -> 634.126 | AC26: =1410.819-AB26-AA26 -> 552.296 | AD26: =+H26-SUM(AA26:AC26) -> 617.861 | AE26: 790.722 | AF26: =1874.707-AE26 -> 1083.985 | AG26: =2842.04-AF26-AE26 -> 967.333 | AH26: =+I26-SUM(AE26:AG26) -> 1336.479 | AI26: 1426.552 | AJ26: =2840.569-AI26 -> 1414.017 | AK26: =4080.579-AJ26-AI26 -> 1240.01 | AL26: =+J26-SUM(AI26:AK26) -> 850.329 | AM26: 566.603 | AN26: =1181.61-AM26 -> 615.007 | AO26: =1806.359-AN26-AM26 -> 624.749 | AP26: =+K26-SUM(AM26:AO26) -> 831.441 | AQ26: 568.092 | AR26: =1154.245-AQ26 -> 586.153 | AS26: =1725.249-AR26-AQ26 -> 571.004 | AT26: =+L26-SUM(AQ26:AS26) -> 601.159 | AU26: 364.868
B27: Nonservice revenues | C27: 0 | D27: 0 | E27: 0 | F27: 0 | G27: 90.619 | H27: 69.428 | I27: 106.536 | J27: 110.924 | K27: 92.881 | L27: 82.188 | M27: =SUM(AS27:AV27) -> 35.521 | O27: 0 | P27: =0-O27 -> 0 | Q27: =0-P27-O27 -> 0 | R27: =+E27-SUM(O27:Q27) -> 0 | S27: 0 | T27: =0-S27 -> 0 | U27: =0-T27-S27 -> 0 | V27: =+F27-SUM(S27:U27) -> 0 | W27: 3.335 | X27: =3.878-W27 -> 0.543 | Y27: =3.878-X27-W27 -> 0 | Z27: =+G27-SUM(W27:Y27) -> 86.741 | AA27: 23.836 | AB27: =40.966-AA27 -> 17.13 | AC27: =69.429-AB27-AA27 -> 28.463 | AD27: =+H27-SUM(AA27:AC27) -> -0.001 | AE27: 27.018 | AF27: =47.378-AE27 -> 20.36 | AG27: =76.101-AF27-AE27 -> 28.723 | AH27: =+I27-SUM(AE27:AG27) -> 30.435 | AI27: 37.975 | AJ27: =63.636-AI27 -> 25.661 | AK27: =86.004-AJ27-AI27 -> 22.368 | AL27: =+J27-SUM(AI27:AK27) -> 24.92 | AM27: 34.097 | AN27: =50.264-AM27 -> 16.167 | AO27: =81.901-AN27-AM27 -> 31.637 | AP27: =+K27-SUM(AM27:AO27) -> 10.98 | AQ27: 26.002 | AR27: =46.846-AQ27 -> 20.844 | AS27: =66.917-AR27-AQ27 -> 20.071 | AT27: =+L27-SUM(AQ27:AS27) -> 15.271 | AU27: 0.179
B28: Total | C28: =+C9+C17+C25 -> 126781.66 | D28: =+D9+D17+D25 -> 135280.73 | E28: =+E9+E17+E25 -> 151172.81 | F28: =+F9+F17+F25 -> 166660.34 | G28: =+G9+G17+G25 -> 160519.54 | H28: =+H9+H17+H25 -> 168496.46 | I28: =+I9+I17+I25 -> 175040.72 | J28: =+J9+J17+J25 -> 180164.46 | ... M28: =+M9+M17+M25 -> 136720.59 | O28: =+O9+O17+O25 -> 36937.626 | P28: =+P9+P17+P25 -> 37508.339 | Q28: =+Q9+Q17+Q25 -> 37156.788 | R28: =+R9+R17+R25 -> 39570.053 | S28: =+S9+S17+S25 -> 40636.067 | T28: =+T9+T17+T25 -> 40884.951 | U28: =+U9+U17+U25 -> 41896.897 | V28: =+V9+V17+V25 -> 43242.422 | ... AU28: =+AU9+AU17+AU25 -> 45706.452
B29: Check | C29: =+C28-Model!C10 -> 0 | D29: =+D28-Model!D10 -> 0 | E29: =+E28-Model!E10 -> 0 | F29: =+F28-Model!F10 -> 0 | G29: =+G28-Model!G10 -> 0 | H29: =+H28-Model!H10 -> 0 | I29: =+I28-Model!I10 -> 0 | J29: =+J28-Model!J10 -> 0 | ... M29: =+M28-Model!M10 -> 136720.59 | O29: =+O28-Model!O10 -> 0 | P29: =+P28-Model!P10 -> 0 | Q29: =+Q28-Model!Q10 -> 0 | R29: =+R28-Model!R10 -> 0 | S29: =+S28-Model!S10 -> 0 | T29: =+T28-Model!T10 -> 0 | U29: =+U28-Model!U10 -> 0 | V29: =+V28-Model!V10 -> 0 | ... AU29: =+AU28-Model!AU10 -> 0
B31: % of Revenue by business segment
B32: =+B9 -> Mobile Communications | C32: =+C9/C$28 -> 0.77239534 | D32: =+D9/D$28 -> 0.7804966 | E32: =+E9/E$28 -> 0.77683464 | F32: =+F9/F$28 -> 0.77417482 | G32: =+G9/G$28 -> 0.71693569 | H32: =+H9/H$28 -> 0.70976115 | I32: =+I9/I$28 -> 0.70889128 | J32: =+J9/J$28 -> 0.72063749 | ... M32: =+M9/M$28 -> 0.72818278 | O32: =+O9/O$28 -> 0.78803695 | P32: =+P9/P$28 -> 0.78427069 | Q32: =+Q9/Q$28 -> 0.76764994 | R32: =+R9/R$28 -> 0.76795353 | S32: =+S9/S$28 -> 0.77315081 | T32: =+T9/T$28 -> 0.77437371 | U32: =+U9/U$28 -> 0.77370284 | V32: =+V9/V$28 -> 0.77540638 | ... AU32: =+AU9/AU$28 -> 0.73743379
B33: =+B17 -> Wireline Communications | C33: =+C17/C$28 -> 0.22760466 | D33: =+D17/D$28 -> 0.2195034 | E33: =+E17/E$28 -> 0.22316536 | F33: =+F17/F$28 -> 0.22582518 | G33: =+G17/G$28 -> 0.27429442 | H33: =+H17/H$28 -> 0.27778691 | I33: =+I17/I$28 -> 0.26662839 | J33: =+J17/J$28 -> 0.2513779 | ... M33: =+M17/M$28 -> 0.26031528 | O33: =+O17/O$28 -> 0.21196305 | P33: =+P17/P$28 -> 0.21572931 | Q33: =+Q17/Q$28 -> 0.23235006 | R33: =+R17/R$28 -> 0.23204647 | S33: =+S17/S$28 -> 0.22521392 | T33: =+T17/T$28 -> 0.22725161 | U33: =+U17/U$28 -> 0.22629716 | V33: =+V17/V$28 -> 0.22459362 | ... AU33: =+AU17/AU$28 -> 0.25457944
B34: =+B25 -> Other | C34: =+C25/C$28 -> 0 | D34: =+D25/D$28 -> 0 | E34: =+E25/E$28 -> 0 | F34: =+F25/F$28 -> 0 | G34: =+G25/G$28 -> 0.0087698979 | H34: =+H25/H$28 -> 0.012451941 | I34: =+I25/I$28 -> 0.024480332 | J34: =+J25/J$28 -> 0.02798461 | ... M34: =+M25/M$28 -> 0.01150194 | O34: =+O25/O$28 -> 0 | P34: =+P25/P$28 -> 0 | Q34: =+Q25/Q$28 -> 0 | R34: =+R25/R$28 -> 0 | S34: =+S25/S$28 -> 0.0016352714 | T34: =+T25/T$28 -> -0.0016253169 | U34: =+U25/U$28 -> 0 | V34: =+V25/V$28 -> 0 | ... AU34: =+AU25/AU$28 -> 0.0079867718
B35: Total | C35: =+C32+C33+C34 -> 1 | D35: =+D32+D33+D34 -> 1 | E35: =+E32+E33+E34 -> 1 | F35: =+F32+F33+F34 -> 1 | G35: =+G32+G33+G34 -> 1 | H35: =+H32+H33+H34 -> 1 | I35: =+I32+I33+I34 -> 1 | J35: =+J32+J33+J34 -> 1 | ... M35: =+M32+M33+M34 -> 1 | O35: =+O32+O33+O34 -> 1 | P35: =+P32+P33+P34 -> 1 | Q35: =+Q32+Q33+Q34 -> 1 | R35: =+R32+R33+R34 -> 1 | S35: =+S32+S33+S34 -> 1 | T35: =+T32+T33+T34 -> 1 | U35: =+U32+U33+U34 -> 1 | V35: =+V32+V33+V34 -> 1 | ... AU35: =+AU32+AU33+AU34 -> 1
B37: EBITDA by business segment
B38: =+B9 -> Mobile Communications | C38: 41260.57 | D38: 46412.954 | E38: 54813.431 | F38: 63935.268 | G38: 60240.7 | H38: 59309.36 | I38: 61719.758 | J38: 65524.818 | K38: 69890.996 | L38: 70461.477 | M38: =SUM(AS38:AV38) -> 53941.614 | O38: 13579.419 | P38: =27789.635-O38 -> 14210.216 | Q38: =41332.447-P38-O38 -> 13542.812 | R38: =+E38-SUM(O38:Q38) -> 13480.984 | S38: 16660.983 | T38: =32159.321-S38 -> 15498.338 | U38: =48552.366-T38-S38 -> 16393.045 | V38: =+F38-SUM(S38:U38) -> 15382.902 | W38: 16589.83 | X38: =31252.085-W38 -> 14662.255 | Y38: =45350.726-X38-W38 -> 14098.641 | Z38: =+G38-SUM(W38:Y38) -> 14889.974 | AA38: 14522.764 | AB38: =29535.182-AA38 -> 15012.418 | AC38: =44459.084-AB38-AA38 -> 14923.902 | AD38: =+H38-SUM(AA38:AC38) -> 14850.276 | AE38: 15862.442 | AF38: =32215.336-AE38 -> 16352.894 | AG38: =47440.573-AF38-AE38 -> 15225.237 | AH38: =+I38-SUM(AE38:AG38) -> 14279.185 | AI38: 16292.543 | AJ38: =31923.786-AI38 -> 15631.243 | AK38: =48253.42-AJ38-AI38 -> 16329.634 | AL38: =+J38-SUM(AI38:AK38) -> 17271.398 | AM38: 17299.439 | AN38: =34366.037-AM38 -> 17066.598 | AO38: =52118.708-AN38-AM38 -> 17752.671 | AP38: =+K38-SUM(AM38:AO38) -> 17772.288 | AQ38: 17017.295 | AR38: =34333.017-AQ38 -> 17315.722 | AS38: =51992.777-AR38-AQ38 -> 17659.76 | AT38: =+L38-SUM(AQ38:AS38) -> 18468.7 | AU38: 17813.154
B39: =+B17 -> Wireline Communications | C39: 8717.826 | D39: 6912.717 | E39: 10313.684 | F39: 12096.165 | G39: 12656.74 | H39: 15186.191 | I39: 14899.935 | J39: 14476.633 | K39: 16917.109 | L39: 17243.441 | M39: =SUM(AS39:AV39) -> 13883.33 | O39: 2500.26 | P39: =5029.46-O39 -> 2529.2 | Q39: =7962.486-P39-O39 -> 2933.026 | R39: =+E39-SUM(O39:Q39) -> 2351.198 | S39: 3249.885 | T39: =6422.383-S39 -> 3172.498 | U39: =9304.352-T39-S39 -> 2881.969 | V39: =+F39-SUM(S39:U39) -> 2791.813 | W39: 3700.407 | X39: =6815.261-W39 -> 3114.854 | Y39: =10384.365-X39-W39 -> 3569.104 | Z39: =+G39-SUM(W39:Y39) -> 2272.375 | AA39: 3723.78 | AB39: =7708.406-AA39 -> 3984.626 | AC39: =12157.581-AB39-AA39 -> 4449.175 | AD39: =+H39-SUM(AA39:AC39) -> 3028.61 | AE39: 3161.736 | AF39: =7231.738-AE39 -> 4070.002 | AG39: =10773.869-AF39-AE39 -> 3542.131 | AH39: =+I39-SUM(AE39:AG39) -> 4126.066 | AI39: 3975.913 | AJ39: =7696.001-AI39 -> 3720.088 | AK39: =11202.875-AJ39-AI39 -> 3506.874 | AL39: =+J39-SUM(AI39:AK39) -> 3273.758 | AM39: 4017.31 | AN39: =8419.744-AM39 -> 4402.434 | AO39: =12223.931-AN39-AM39 -> 3804.187 | AP39: =+K39-SUM(AM39:AO39) -> 4693.178 | AQ39: 3747.474 | AR39: =7871.053-AQ39 -> 4123.579 | AS39: =12286.115-AR39-AQ39 -> 4415.062 | AT39: =+L39-SUM(AQ39:AS39) -> 4957.326 | AU39: 4510.942
B40: =+B25 -> Other | C40: 0 | D40: 0 | E40: 0 | F40: 0 | G40: 614.915 | H40: 426.33 | I40: 2472.326 | J40: 1425.295 | K40: 5.571 | L40: -80.602 | M40: =SUM(AS40:AV40) -> -166.519 | O40: 0 | P40: 0 | Q40: 0 | R40: =+E40-SUM(O40:Q40) -> 0 | S40: 8.485 | T40: =0-S40 -> -8.485 | U40: 0 | V40: =+F40-SUM(S40:U40) -> 0 | W40: 185.441 | X40: =320.207-W40 -> 134.766 | Y40: =519.427-X40-W40 -> 199.22 | Z40: =+G40-SUM(W40:Y40) -> 95.488 | AA40: 41.386 | AB40: =128.816-AA40 -> 87.43 | AC40: =298.435-AB40-AA40 -> 169.619 | AD40: =+H40-SUM(AA40:AC40) -> 127.895 | AE40: 656.162 | AF40: =1098.649-AE40 -> 442.487 | AG40: =2103.096-AF40-AE40 -> 1004.447 | AH40: =+I40-SUM(AE40:AG40) -> 369.23 | AI40: 259.644 | AJ40: =873.288-AI40 -> 613.644 | AK40: =1240.144-AJ40-AI40 -> 366.856 | AL40: =+J40-SUM(AI40:AK40) -> 185.151 | AM40: 34.043 | AN40: =177.779-AM40 -> 143.736 | AO40: =522.019-AN40-AM40 -> 344.24 | AP40: =+K40-SUM(AM40:AO40) -> -516.448 | AQ40: -2.055 | AR40: =-64.313-AQ40 -> -62.258 | AS40: =-93.44-AR40-AQ40 -> -29.127 | AT40: =+L40-SUM(AQ40:AS40) -> 12.838 | AU40: -150.23
B41: Total | C41: =+C38+C39+C40 -> 49978.396 | D41: =+D38+D39+D40 -> 53325.671 | E41: =+E38+E39+E40 -> 65127.115 | F41: =+F38+F39+F40 -> 76031.433 | G41: =+G38+G39+G40 -> 73512.355 | H41: =+H38+H39+H40 -> 74921.881 | I41: =+I38+I39+I40 -> 79092.019 | J41: =+J38+J39+J40 -> 81426.746 | ... M41: =+M38+M39+M40 -> 67658.425 | O41: =+O38+O39+O40 -> 16079.679 | P41: =+P38+P39+P40 -> 16739.416 | Q41: =+Q38+Q39+Q40 -> 16475.838 | R41: =+R38+R39+R40 -> 15832.182 | S41: =+S38+S39+S40 -> 19919.353 | T41: =+T38+T39+T40 -> 18662.351 | U41: =+U38+U39+U40 -> 19275.014 | V41: =+V38+V39+V40 -> 18174.715 | ... AU41: =+AU38+AU39+AU40 -> 22173.866
B42: Check | C42: =+C41-Model!C56 -> 0 | D42: =+D41-Model!D56 -> 0 | E42: =+E41-Model!E56 -> 0 | F42: =+F41-Model!F56 -> 0 | G42: =+G41-Model!G56 -> 0 | H42: =+H41-Model!H56 -> 0 | I42: =+I41-Model!I56 -> 0 | J42: =+J41-Model!J56 -> 0 | ... M42: =+M41-Model!M56 -> 67658.425 | O42: =+O41-Model!O56 -> 0 | P42: =+P41-Model!P56 -> 0 | Q42: =+Q41-Model!Q56 -> 0 | R42: =+R41-Model!R56 -> 0 | S42: =+S41-Model!S56 -> 0 | T42: =+T41-Model!T56 -> 0 | U42: =+U41-Model!U56 -> 0 | V42: =+V41-Model!V56 -> 0 | ... AU42: =+AU41-Model!AU56 -> 0
B44: % margin
B45: =+B38 -> Mobile Communications | C45: =+C38/C9 -> 0.42134626 | D45: =+D38/D9 -> 0.43957426 | E45: =+E38/E9 -> 0.46675043 | F45: =+F38/F9 -> 0.49552913 | G45: =+G38/G9 -> 0.52345807 | H45: =+H38/H9 -> 0.49592984 | I45: =+I38/I9 -> 0.49739966 | J45: =+J38/J9 -> 0.50468438 | ... M45: =+M38/M9 -> 0.54181322 | O45: =+O38/O9 -> 0.46651502 | P45: =+P38/P9 -> 0.48306643 | Q45: =+Q38/Q9 -> 0.47479645 | R45: =+R38/R9 -> 0.44362909 | S45: =+S38/S9 -> 0.5303038 | T45: =+T38/T9 -> 0.48952069 | U45: =+U38/U9 -> 0.50571238 | V45: =+V38/V9 -> 0.4587741 | ... AU45: =+AU38/AU9 -> 0.52849427
B46: =+B39 -> Wireline Communications | C46: =+C39/C17 -> 0.30211384 | D46: =+D39/D17 -> 0.2327939 | E46: =+E39/E17 -> 0.30571262 | F46: =+F39/F17 -> 0.32139794 | G46: =+G39/G17 -> 0.28745971 | H46: =+H39/H17 -> 0.3244489 | I46: =+I39/I17 -> 0.31925587 | J46: =+J39/J17 -> 0.31964753 | ... M46: =+M39/M17 -> 0.39008571 | O46: =+O39/O17 -> 0.31934199 | P46: =+P39/P17 -> 0.31256921 | Q46: =+Q39/Q17 -> 0.33973083 | R46: =+R39/R17 -> 0.25606346 | S46: =+S39/S17 -> 0.35510852 | T46: =+T39/T17 -> 0.34145298 | U46: =+U39/U17 -> 0.30396833 | V46: =+V39/V17 -> 0.28746098 | ... AU46: =+AU39/AU17 -> 0.38767376
B47: =+B40 -> Other | G47: =+G40/G25 -> 0.43681006 | H47: =+H40/H25 -> 0.20319736 | I47: =+I40/I25 -> 0.57696482 | J47: =+J40/J25 -> 0.28269387 | K47: =+K40/K25 -> 0.0020401504 | L47: =+L40/L25 -> -0.033464309 | M47: =+M40/M25 -> -0.10589093 | S47: =+S40/S25 -> 0.12768807 | T47: =+T40/T25 -> 0.12768807 | W47: =+W40/W25 -> 0.50808816 | X47: =+X40/X25 -> 0.62477863 | Y47: =+Y40/Y25 -> 0.55490099 | Z47: =+Z40/Z25 -> 0.20401631 | AA47: =+AA40/AA25 -> 0.16672239 | AB47: =+AB40/AB25 -> 0.13424828 | AC47: =+AC40/AC25 -> 0.29206435 | AD47: =+AD40/AD25 -> 0.20699673 | ... AU47: =+AU40/AU25 -> -0.41153605
B48: Total | C48: =+C41/C28 -> 0.39420841 | D48: =+D41/D28 -> 0.39418527 | E48: =+E41/E28 -> 0.43081237 | F48: =+F41/F28 -> 0.45620592 | G48: =+G41/G28 -> 0.45796514 | H48: =+H41/H28 -> 0.44464959 | I48: =+I41/I28 -> 0.45184925 | J48: =+J41/J28 -> 0.45195788 | ... M48: =+M41/M28 -> 0.49486638 | O48: =+O41/O28 -> 0.43531977 | P48: =+P41/P28 -> 0.44628518 | Q48: =+Q41/Q28 -> 0.44341395 | R48: =+R41/R28 -> 0.40010515 | S48: =+S41/S28 -> 0.490189 | T48: =+T41/T28 -> 0.45646015 | U48: =+U41/U28 -> 0.46005827 | V48: =+V41/V28 -> 0.42029827 | ... AU48: =+AU41/AU28 -> 0.48513645
B50: Mobile Service Revenue
B51: Mobile Voice | C51: 34065 | D51: 32275 | E51: 28408 | F51: 24276 | G51: 20130 | H51: 17229 | I51: 14917 | J51: 13506 | K51: 12653 | L51: 10883 | M51: =SUM(AS51:AV51) -> 7785.549 | O51: 7325 | P51: =14760-O51 -> 7435 | Q51: =21754-P51-O51 -> 6994 | R51: =+E51-SUM(O51:Q51) -> 6654 | S51: 6198 | T51: 6056 | U51: 6180 | V51: =+F51-SUM(S51:U51) -> 5842 | W51: 5288 | X51: 4918 | Y51: 5099 | Z51: =+G51-SUM(W51:Y51) -> 4825 | AA51: 4711 | AB51: 4402 | AC51: 4168 | AD51: =+H51-SUM(AA51:AC51) -> 3948 | AE51: 3899 | AF51: 3870 | AG51: 3620 | AH51: =+I51-SUM(AE51:AG51) -> 3528 | AI51: 3427.074 | AJ51: 3366.843 | AK51: 3375 | AL51: =+J51-SUM(AI51:AK51) -> 3337.083 | AM51: 3355.937 | AN51: 3279 | AO51: 3007 | AP51: =+K51-SUM(AM51:AO51) -> 3011.063 | AQ51: 2776.253 | AR51: 2759 | AS51: 2748 | AT51: =+L51-SUM(AQ51:AS51) -> 2599.747 | AU51: 2437.802
B52: Mobile SMS | C52: 23199 | D52: 23149 | E52: 20162 | F52: 15690 | G52: 11029 | H52: 9350 | I52: 8845 | J52: 7975 | K52: 6691 | L52: 4801 | M52: =SUM(AS52:AV52) -> 2838.26 | O52: 5402 | P52: =10838-O52 -> 5436 | Q52: =15772-P52-O52 -> 4934 | R52: =+E52-SUM(O52:Q52) -> 4390 | S52: 4197 | T52: 4049 | U52: 4002 | V52: =+F52-SUM(S52:U52) -> 3442 | W52: 3034 | X52: 2744 | Y52: 2825 | Z52: =+G52-SUM(W52:Y52) -> 2426 | AA52: 2401 | AB52: 2426 | AC52: 2340 | AD52: =+H52-SUM(AA52:AC52) -> 2183 | AE52: 2149 | AF52: 2291 | AG52: 2210 | AH52: =+I52-SUM(AE52:AG52) -> 2195 | AI52: 2007.807 | AJ52: 1984.632 | AK52: 1971 | AL52: =+J52-SUM(AI52:AK52) -> 2011.561 | AM52: 1939.027 | AN52: 1807 | AO52: 1459 | AP52: =+K52-SUM(AM52:AO52) -> 1485.973 | AQ52: 1393.051 | AR52: 1313 | AS52: 1186 | AT52: =+L52-SUM(AQ52:AS52) -> 908.949 | AU52: 743.311
B53: Mobile Data | C53: 34991 | D53: 43059 | E53: 50961 | F53: 71801 | G53: 71954 | H53: 77813 | I53: 83758 | J53: 90895 | K53: 97369 | L53: 101166 | M53: =SUM(AS53:AV53) -> 79118.113 | O53: 11482 | P53: =23417-O53 -> 11935 | Q53: =36166-P53-O53 -> 12749 | R53: =+E53-SUM(O53:Q53) -> 14795 | S53: 16488 | T53: 17549 | U53: 18182 | V53: =+F53-SUM(S53:U53) -> 19582 | W53: 18471 | X53: 17377 | Y53: 17554 | Z53: =+G53-SUM(W53:Y53) -> 18552 | AA53: 19204 | AB53: 19428 | AC53: 19283 | AD53: =+H53-SUM(AA53:AC53) -> 19898 | AE53: 20841 | AF53: 20996 | AG53: 20710 | AH53: =+I53-SUM(AE53:AG53) -> 21211 | AI53: 21657.313 | AJ53: 22378.993 | AK53: 23011 | AL53: =+J53-SUM(AI53:AK53) -> 23847.694 | AM53: 23831.211 | AN53: 24180 | AO53: 24848 | AP53: =+K53-SUM(AM53:AO53) -> 24509.789 | AQ53: 24124.789 | AR53: 24707 | AS53: 25166 | AT53: =+L53-SUM(AQ53:AS53) -> 27168.211 | AU53: 26783.902
B54: Total | C54: =+C51+C52+C53 -> 92255 | D54: =+D51+D52+D53 -> 98483 | E54: =+E51+E52+E53 -> 99531 | F54: =+F51+F52+F53 -> 111767 | G54: =+G51+G52+G53 -> 103113 | H54: =+H51+H52+H53 -> 104392 | I54: =+I51+I52+I53 -> 107520 | J54: =+J51+J52+J53 -> 112376 | ... M54: =+M51+M52+M53 -> 89741.922 | O54: =+O51+O52+O53 -> 24209 | P54: =+P51+P52+P53 -> 24806 | Q54: =+Q51+Q52+Q53 -> 24677 | R54: =+R51+R52+R53 -> 25839 | S54: =+S51+S52+S53 -> 26883 | T54: =+T51+T52+T53 -> 27654 | U54: =+U51+U52+U53 -> 28364 | V54: =+V51+V52+V53 -> 28866 | ... AU54: =+AU51+AU52+AU53 -> 29965.015
B56: Fixed Line and home broadband Business
B57: Home Broadband | C57: 14680 | D57: 15645 | E57: 18606 | F57: 21747 | G57: 26798 | H57: 29392 | I57: 27094 | J57: 25112 | K57: 23785 | L57: 23980 | M57: =SUM(AS57:AV57) -> 18449.616 | O57: 4298 | P57: =8727-O57 -> 4429 | Q57: =13553-P57-O57 -> 4826 | R57: =+E57-SUM(O57:Q57) -> 5053 | S57: 5208 | T57: 5347 | U57: 5518 | V57: =+F57-SUM(S57:U57) -> 5674 | W57: 5780 | X57: 6733 | Y57: 7036 | Z57: =+G57-SUM(W57:Y57) -> 7249 | AA57: 7351 | AB57: 7181 | AC57: 7865 | AD57: =+H57-SUM(AA57:AC57) -> 6995 | AE57: 7026 | AF57: 6769 | AG57: 6681 | AH57: =+I57-SUM(AE57:AG57) -> 6618 | AI57: 6531.853 | AJ57: 6277.263 | AK57: 6185 | AL57: =+J57-SUM(AI57:AK57) -> 6117.884 | AM57: 6116.796 | AN57: 5983 | AO57: 5787 | AP57: =+K57-SUM(AM57:AO57) -> 5898.204 | AQ57: 5813.032 | AR57: 5895 | AS57: 6132 | AT57: =+L57-SUM(AQ57:AS57) -> 6139.968 | AU57: 6177.648
B58: Corporate Data | C58: 9873 | D58: 10288 | E58: 11762 | F58: 12828 | G58: 12539 | H58: 14170 | I58: 17198 | J58: 18319 | K58: 20380 | L58: 20671 | M58: =SUM(AS58:AV58) -> 16179.908 | O58: 2666 | P58: =5493-O58 -> 2827 | Q58: =8437-P58-O58 -> 2944 | R58: =+E58-SUM(O58:Q58) -> 3325 | S58: 3136 | T58: 3191 | U58: 3186 | V58: =+F58-SUM(S58:U58) -> 3315 | W58: 3250 | X58: 2949 | Y58: 3077 | Z58: =+G58-SUM(W58:Y58) -> 3263 | AA58: 3323 | AB58: 3407 | AC58: 3659 | AD58: =+H58-SUM(AA58:AC58) -> 3781 | AE58: 3922 | AF58: 4230 | AG58: 4383 | AH58: =+I58-SUM(AE58:AG58) -> 4663 | AI58: 4504.629 | AJ58: 4567.292 | AK58: 4487 | AL58: =+J58-SUM(AI58:AK58) -> 4760.079 | AM58: 4955.858 | AN58: 4833 | AO58: 5691 | AP58: =+K58-SUM(AM58:AO58) -> 4900.142 | AQ58: 4857.516 | AR58: 4769 | AS58: 4769 | AT58: =+L58-SUM(AQ58:AS58) -> 6275.484 | AU58: 5135.424
B59: Fixed line Voice | C59: 3780 | D59: 3490 | E59: 2977 | F59: 2668 | G59: 2620 | H59: 2280 | I59: 1989 | J59: 1595 | K59: 1500 | L59: 1251 | M59: =SUM(AS59:AV59) -> 946.236 | O59: 769 | P59: =1512-O59 -> 743 | Q59: =2261-P59-O59 -> 749 | R59: =+E59-SUM(O59:Q59) -> 716 | S59: 710 | T59: 684 | U59: 668 | V59: =+F59-SUM(S59:U59) -> 606 | W59: 697 | X59: 605 | Y59: 732 | Z59: =+G59-SUM(W59:Y59) -> 586 | AA59: 599 | AB59: 578 | AC59: 565 | AD59: =+H59-SUM(AA59:AC59) -> 538 | AE59: 527 | AF59: 485 | AG59: 504 | AH59: =+I59-SUM(AE59:AG59) -> 473 | AI59: 426.474 | AJ59: 430.251 | AK59: 392 | AL59: =+J59-SUM(AI59:AK59) -> 346.275 | AM59: 382.954 | AN59: 380 | AO59: 367 | AP59: =+K59-SUM(AM59:AO59) -> 370.046 | AQ59: 320.534 | AR59: 306 | AS59: 306 | AT59: =+L59-SUM(AQ59:AS59) -> 318.466 | AU59: 321.77
B60: Total | C60: =+C57+C58+C59 -> 28333 | D60: =+D57+D58+D59 -> 29423 | E60: =+E57+E58+E59 -> 33345 | F60: =+F57+F58+F59 -> 37243 | G60: =+G57+G58+G59 -> 41957 | H60: =+H57+H58+H59 -> 45842 | I60: =+I57+I58+I59 -> 46281 | J60: =+J57+J58+J59 -> 45026 | ... M60: =+M57+M58+M59 -> 35575.76 | O60: =+O57+O58+O59 -> 7733 | P60: =+P57+P58+P59 -> 7999 | Q60: =+Q57+Q58+Q59 -> 8519 | R60: =+R57+R58+R59 -> 9094 | S60: =+S57+S58+S59 -> 9054 | T60: =+T57+T58+T59 -> 9222 | U60: =+U57+U58+U59 -> 9372 | V60: =+V57+V58+V59 -> 9595 | ... AU60: =+AU57+AU58+AU59 -> 11634.842
B62: Cumulative Broadband Subscribers
B63: Fixed Wireless | C63: 520117 | D63: 655441 | E63: 984238 | F63: 1375260 | G63: 3057933 | H63: 2721130 | I63: 1427868 | J63: 618972 | K63: 462788 | L63: 344486 | M63: =AV63 -> 0 | O63: 741659 | P63: 839555 | Q63: 909861 | R63: =+E63 -> 984238 | S63: 1071451 | T63: 1177113 | U63: 1270029 | V63: =+F63 -> 1375260 | W63: 1613305 | X63: 2188734 | Y63: 2784625 | Z63: =+G63 -> 3057933 | AA63: 3303207 | AB63: 3380537 | AC63: 2819492 | AD63: =+H63 -> 2721130 | AE63: 2432398 | AF63: 2050422 | AG63: 1578376 | AH63: =+I63 -> 1427868 | AI63: 1200301 | AJ63: 1055222 | AK63: 622257 | AL63: =+J63 -> 618972 | AM63: 574505 | AN63: 541256 | AO63: 494733 | AP63: =+K63 -> 462788 | AQ63: 420830 | AR63: 386745 | AS63: 365886 | AT63: =L63 -> 344486 | AU63: 327897
B64: Wired | C64: 610633 | D64: 645720 | E64: 631439 | F64: 642078 | G64: 739112 | H64: 964784 | I64: 1134669 | J64: 1131525 | K64: 1280693 | L64: 1795313 | M64: =AV64 -> 0 | O64: 654345 | P64: 661834 | Q64: 630391 | R64: =+E64 -> 631439 | S64: 636782 | T64: 637131 | U64: 641304 | V64: =+F64 -> 642078 | W64: 645225 | X64: 677903 | Y64: 686584 | Z64: =+G64 -> 739112 | AA64: 784883 | AB64: 830162 | AC64: 907087 | AD64: =+H64 -> 964784 | AE64: 1030243 | AF64: 1059184 | AG64: 1130038 | AH64: =+I64 -> 1134669 | AI64: 1116399 | AJ64: 1103766 | AK64: 1126814 | AL64: =+J64 -> 1131525 | AM64: 1150072 | AN64: 1173410 | AO64: 1202019 | AP64: =+K64 -> 1280693 | AQ64: 1412296 | AR64: 1553488 | AS64: 1688713 | AT64: =L64 -> 1795313 | AU64: 1915299
B65: Total (end of period) | C65: =+C63+C64 -> 1130750 | D65: =+D63+D64 -> 1301161 | E65: =+E63+E64 -> 1615677 | F65: =+F63+F64 -> 2017338 | G65: =+G63+G64 -> 3797045 | H65: =+H63+H64 -> 3685914 | I65: =+I63+I64 -> 2562537 | J65: =+J63+J64 -> 1750497 | ... M65: =+M63+M64 -> 0 | O65: =+O63+O64 -> 1396004 | P65: =+P63+P64 -> 1501389 | Q65: =+Q63+Q64 -> 1540252 | R65: =+R63+R64 -> 1615677 | S65: =+S63+S64 -> 1708233 | T65: =+T63+T64 -> 1814244 | U65: =+U63+U64 -> 1911333 | V65: =+V63+V64 -> 2017338 | ... AU65: =+AU63+AU64 -> 2243196
B68: Cumulative Subscribers (or SIMs) - Net | C68: =+C69+C70 -> 62798858 | D68: =+D69+D70 -> 60686155 | E68: =+E69+E70 -> 74093591 | F68: =+F69+F70 -> 94204277 | G68: =+G69+G70 -> 76645567 | H68: =+H69+H70 -> 86784662 | I68: =+I69+I70 -> 86746672 | J68: =+J69+J70 -> 57047237 | ... M68: =+M69+M70 -> 0 | O68: =+O69+O70 -> 63262677 | P68: =+P69+P70 -> 65142263 | Q68: =+Q69+Q70 -> 65359749 | R68: =+R69+R70 -> 74093591 | S68: =+S69+S70 -> 89320045 | T68: =+T69+T70 -> 92941794 | U68: =+U69+U70 -> 97358374 | V68: =+V69+V70 -> 94204277 | ... AU68: =+AU69+AU70 -> 66555897
B69: Globe Postpaid | C69: 2489719 | D69: 2484788 | E69: 2598171 | F69: 2690577 | G69: 2513547 | H69: 2496867 | I69: 2529694 | J69: 2545462 | K69: 2429816 | L69: 2429477 | M69: =AV69 -> 0 | O69: 2467767 | P69: 2487740 | Q69: 2517886 | R69: =+E69 -> 2598171 | S69: 2721086 | T69: 2631452 | U69: 2663434 | V69: =+F69 -> 2690577 | W69: 2721086 | X69: 2671048 | Y69: 2563621 | Z69: =+G69 -> 2513547 | AA69: 2507779 | AB69: 2499882 | AC69: 2505898 | AD69: =+H69 -> 2496867 | AE69: 2508180 | AF69: 2548538 | AG69: 2514403 | AH69: =+I69 -> 2529694 | AI69: 2542019 | AJ69: 2552330 | AK69: 2559167 | AL69: =+O69 -> 2467767 | AM69: 2527237 | AN69: 2512464 | AO69: 2452186 | AP69: =+K69 -> 2429816 | AQ69: 2404426 | AR69: 2397759 | AS69: 2416067 | AT69: =+L69 -> 2429477 | AU69: 2443888
B70: Prepaid | C70: =+C71+C72 -> 60309139 | D70: =+D71+D72 -> 58201367 | E70: =+E71+E72 -> 71495420 | F70: =+F71+F72 -> 91513700 | G70: =+G71+G72 -> 74132020 | H70: =+H71+H72 -> 84287795 | I70: =+I71+I72 -> 84216978 | J70: =+J71+J72 -> 54501775 | ... M70: =+M71+M72 -> 0 | O70: =+O71+O72 -> 60794910 | P70: =+P71+P72 -> 62654523 | Q70: =+Q71+Q72 -> 62841863 | R70: =+R71+R72 -> 71495420 | S70: =+S71+S72 -> 86598959 | T70: =+T71+T72 -> 90310342 | U70: =+U71+U72 -> 94694940 | V70: =+V71+V72 -> 91513700 | ... AU70: =+AU71+AU72 -> 64112009
B71: Globe Prepaid | C71: 28433793 | D71: 27909102 | E71: 34587598 | F71: 44815390 | G71: 38109102 | H71: 42525667 | I71: 44536976 | J71: 29884300 | K71: 32078927 | L71: 35040448 | M71: =AV71 -> 0 | O71: 28927355 | P71: 29805847 | Q71: 30453286 | R71: =+E71 -> 34587598 | S71: 42337123 | T71: 43923932 | U71: 45936354 | V71: =+F71 -> 44815390 | W71: 42337123 | X71: 38699982 | Y71: 38570956 | Z71: =+G71 -> 38109102 | AA71: 38861833 | AB71: 39641444 | AC71: 40839543 | AD71: =+H71 -> 42525667 | AE71: 43286370 | AF71: 43670567 | AG71: 44504131 | AH71: =+I71 -> 44536976 | AI71: 43962293 | AJ71: 43738135 | AK71: 28665429 | AL71: =+O71 -> 28927355 | AM71: 30827302 | AN71: 31262784 | AO71: 31640837 | AP71: =+K71 -> 32078927 | AQ71: 32601781 | AR71: 33126680 | AS71: 33295741 | AT71: =+L71 -> 35040448 | AU71: 35432871
B72: TM | C72: 31875346 | D72: 30292265 | E72: 36907822 | F72: 46698310 | G72: 36022918 | H72: 41762128 | I72: 39680002 | J72: 24617475 | K72: 26397753 | L72: 28302832 | M72: =AV72 -> 0 | O72: 31867555 | P72: 32848676 | Q72: 32388577 | R72: =+E72 -> 36907822 | S72: 44261836 | T72: 46386410 | U72: 48758586 | V72: =+F72 -> 46698310 | W72: 44261836 | X72: 38801236 | Y72: 37032065 | Z72: =+G72 -> 36022918 | AA72: 38396120 | AB72: 39607985 | AC72: 40645133 | AD72: =+H72 -> 41762128 | AE72: 41633308 | AF72: 41191434 | AG72: 40855402 | AH72: =+I72 -> 39680002 | AI72: 37710961 | AJ72: 36599114 | AK72: 23506772 | AL72: =+O72 -> 31867555 | AM72: 25419471 | AN72: 25711995 | AO72: 26073756 | AP72: =+K72 -> 26397753 | AQ72: 26586310 | AR72: 26970746 | AS72: 27436182 | AT72: =+L72 -> 28302832 | AU72: 28679138
B74: Net Subscriber (or SIM) Additions | C74: =+C75+C76 -> 6616180 | D74: =+D75+D76 -> -2112703 | E74: =+E75+E76 -> 13407436 | F74: =+F75+F76 -> 20110686 | G74: =+G75+G76 -> -17558710 | H74: =+H75+H76 -> 10139095 | I74: =+I75+I76 -> -37990 | J74: =+J75+J76 -> -29699435 | ... M74: =+M75+M76 -> 0 | O74: =+O75+O76 -> 2576522 | P74: =+P75+P76 -> 4456108 | Q74: =+Q75+Q76 -> 4673594 | R74: =+R75+R76 -> 13407436 | S74: =+S75+S76 -> 9396109 | T74: =+T75+T76 -> 9452094 | U74: =+U75+U76 -> 4416580 | V74: =+V75+V76 -> 20110686 | ... AU74: =+AU75+AU76 -> 783140
B75: Globe Postpaid | C75: -107308 | D75: -4931 | E75: 113383 | F75: 92406 | G75: -177030 | H75: -16680 | I75: 32827 | J75: 15768 | K75: -115646 | L75: -339 | M75: =AV75 -> 0 | O75: -17021 | P75: 2952 | Q75: 33098 | R75: =+E75 -> 113383 | S75: 44563 | T75: -11282 | U75: 31982 | V75: =+F75 -> 92406 | W75: 30509 | X75: -50038 | Y75: -107427 | Z75: =+G75 -> -177030 | AA75: -5768 | AB75: -7897 | AC75: 6016 | AD75: =+H75 -> -16680 | AE75: 11313 | AF75: 40358 | AG75: -34135 | AH75: =+I75 -> 32827 | AI75: 12325 | AJ75: 10311 | AK75: 6837 | AL75: =+J75 -> 15768 | AM75: -18225 | AN75: -14773 | AO75: -60278 | AP75: =+K75 -> -115646 | AQ75: -25390 | AR75: -6667 | AS75: 18308 | AT75: =+L75 -> -339 | AU75: 14411
B76: Prepaid | C76: =+C77+C78 -> 6723488 | D76: =+D77+D78 -> -2107772 | E76: =+E77+E78 -> 13294053 | F76: =+F77+F78 -> 20018280 | G76: =+G77+G78 -> -17381680 | H76: =+H77+H78 -> 10155775 | I76: =+I77+I78 -> -70817 | J76: =+J77+J78 -> -29715203 | ... M76: =+M77+M78 -> 0 | O76: =+O77+O78 -> 2593543 | P76: =+P77+P78 -> 4453156 | Q76: =+Q77+Q78 -> 4640496 | R76: =+R77+R78 -> 13294053 | S76: =+S77+S78 -> 9351546 | T76: =+T77+T78 -> 9463376 | U76: =+U77+U78 -> 4384598 | V76: =+V77+V78 -> 20018280 | ... AU76: =+AU77+AU78 -> 768729
B77: Globe Prepaid | C77: 2518697 | D77: -524691 | E77: 6678496 | F77: 10227792 | G77: -6706288 | H77: 4416565 | I77: 2011309 | J77: -14652676 | K77: 2194627 | L77: 2961521 | M77: =AV77 -> 0 | O77: 1018253 | P77: 1896745 | Q77: 2544184 | R77: =+E77 -> 6678496 | S77: 4741083 | T77: 4595251 | U77: 2012422 | V77: =+F77 -> 10227792 | W77: -2478267 | X77: -3637141 | Y77: -129026 | Z77: =+G77 -> -6706288 | AA77: 752731 | AB77: 779611 | AC77: 1198099 | AD77: =+H77 -> 4416565 | AE77: 760703 | AF77: 384197 | AG77: 833564 | AH77: =+I77 -> 2011309 | AI77: -574683 | AJ77: -224158 | AK77: -15072706 | AL77: =+J77 -> -14652676 | AM77: 943002 | AN77: 435482 | AO77: 378053 | AP77: =+K77 -> 2194627 | AQ77: 522854 | AR77: 524899 | AS77: 169061 | AT77: =+L77 -> 2961521 | AU77: 392423
B78: TM | C78: 4204791 | D78: -1583081 | E78: 6615557 | F78: 9790488 | G78: -10675392 | H78: 5739210 | I78: -2082126 | J78: -15062527 | K78: 1780278 | L78: 1905079 | M78: =AV78 -> 0 | O78: 1575290 | P78: 2556411 | Q78: 2096312 | R78: =+E78 -> 6615557 | S78: 4610463 | T78: 4868125 | U78: 2372176 | V78: =+F78 -> 9790488 | W78: -2436474 | X78: -5460600 | Y78: -1769171 | Z78: =+G78 -> -10675392 | AA78: 2373202 | AB78: 1211865 | AC78: 1037148 | AD78: =+H78 -> 5739210 | AE78: -128820 | AF78: -441874 | AG78: -336032 | AH78: =+I78 -> -2082126 | AI78: -1969041 | AJ78: -1111847 | AK78: -13092342 | AL78: =+J78 -> -15062527 | AM78: 801996 | AN78: 292524 | AO78: 361761 | AP78: =+K78 -> 1780278 | AQ78: 188557 | AR78: 384436 | AS78: 465436 | AT78: =+L78 -> 1905079 | AU78: 376306
B80: ARPU
B81: Globe Postpaid | C81: 1132 | D81: 1173 | E81: 919 | F81: 907 | G81: 850 | H81: 821 | I81: 839 | J81: 855 | K81: 914 | L81: 909 | M81: =AV81 -> 0 | O81: 957 | P81: 938 | Q81: 933 | R81: 914 | S81: 889 | T81: 882 | U81: 934 | V81: 921 | W81: 858 | X81: 815 | Y81: 845 | Z81: 832 | AA81: 882 | AB81: 822 | AC81: 802 | AD81: 776 | AE81: 888 | AF81: 823 | AG81: 811 | AH81: 822 | AI81: 850 | AJ81: 845 | AK81: 846 | AL81: 864 | AM81: 876 | AN81: 886 | AO81: 929 | AP81: 958 | AQ81: 910 | AR81: 907 | AS81: 908 | AT81: 935 | AU81: 909
B82: Prepaid
B83: Globe Prepaid | C83: 108 | D83: 115 | E83: 119 | F83: 108 | G83: 93 | H83: 99 | I83: 98 | J83: 121 | K83: 148 | L83: 136 | M83: =AV83 -> 0 | O83: 125 | P83: 126 | Q83: 124 | R83: 122 | S83: 114 | T83: 105 | U83: 97 | V83: 94 | W83: 91 | X83: 90 | Y83: 100 | Z83: 105 | AA83: 103 | AB83: 103 | AC83: 98 | AD83: 97 | AE83: 96 | AF83: 98 | AG83: 96 | AH83: 98 | AI83: 98 | AJ83: 101 | AK83: 126 | AL83: 160 | AM83: 152 | AN83: 149 | AO83: 146 | AP83: 140 | AQ83: 136 | AR83: 136 | AS83: 138 | AT83: 141 | AU83: 134
B84: TM | C84: 63 | D84: 66 | E84: 66 | F84: 61 | G84: 60 | H84: 66 | I84: 63 | J84: 84 | K84: 112 | L84: 108 | M84: =AV84 -> 0 | O84: 69 | P84: 69 | Q84: 70 | R84: 66 | S84: 62 | T84: 57 | U84: 55 | V84: 58 | W84: 57 | X84: 60 | Y84: 65 | Z84: 68 | AA84: 67 | AB84: 66 | AC84: 64 | AD84: 63 | AE84: 60 | AF84: 63 | AG84: 62 | AH84: 63 | AI84: 66 | AJ84: 71 | AK84: 91 | AL84: 118 | AM84: 115 | AN84: 113 | AO84: 111 | AP84: 110 | AQ84: 107 | AR84: 110 | AS84: 107 | AT84: 112 | AU84: 105
B86: Average Monthly Churn Rate (%)
B87: Globe Postpaid | C87: 0.033 | D87: 0.025 | E87: 0.018 | F87: 0.017 | G87: 0.018 | H87: 0.016 | I87: 0.016 | J87: 0.015 | K87: 0.016 | L87: 0.012 | M87: =AV87 -> 0 | O87: 0.023 | P87: 0.021 | Q87: 0.019 | R87: 0.015 | S87: 0.015 | T87: 0.02 | U87: 0.017 | V87: 0.015 | W87: 0.014 | X87: 0.011 | Y87: 0.025 | Z87: 0.021 | AA87: 0.016 | AB87: 0.017 | AC87: 0.016 | AD87: 0.016 | AE87: 0.017 | AF87: 0.011 | AG87: 0.022 | AH87: 0.014 | AI87: 0.015 | AJ87: 0.014 | AK87: 0.015 | AL87: 0.015 | AM87: 0.016 | AN87: 0.014 | AO87: 0.016 | AP87: 0.013 | AQ87: 0.013 | AR87: 0.012 | AS87: 0.013 | AT87: 0.011 | AU87: 0.011
B88: Prepaid
B89: Globe Prepaid | C89: 0.068 | D89: 0.077 | E89: 0.052 | F89: 0.031 | G89: 0.048 | H89: 0.029 | I89: 0.028 | J89: 0.058 | K89: 0.019 | L89: 0.015 | M89: =AV89 -> 0 | O89: 0.065 | P89: 0.066 | Q89: 0.065 | R89: 0.024 | S89: 0.017 | T89: 0.019 | U89: 0.028 | V89: 0.05 | W89: 0.054 | X89: 0.055 | Y89: 0.043 | Z89: 0.043 | AA89: 0.032 | AB89: 0.029 | AC89: 0.028 | AD89: 0.028 | AE89: 0.028 | AF89: 0.03 | AG89: 0.027 | AH89: 0.027 | AI89: 0.024 | AJ89: 0.022 | AK89: 0.168 | AL89: 0.015 | AM89: 0.018 | AN89: 0.019 | AO89: 0.019 | AP89: 0.017 | AQ89: 0.016 | AR89: 0.016 | AS89: 0.021 | AT89: 0.007 | AU89: 0.016
B90: TM | C90: 0.068 | D90: 0.08 | E90: 0.054 | F90: 0.035 | G90: 0.062 | H90: 0.035 | I90: 0.04 | J90: 0.064 | K90: 0.022 | L90: 0.02 | M90: =AV90 -> 0 | O90: 0.061 | P90: 0.065 | Q90: 0.068 | R90: 0.025 | S90: 0.02 | T90: 0.017 | U90: 0.029 | V90: 0.062 | W90: 0.065 | X90: 0.074 | Y90: 0.057 | Z90: 0.056 | AA90: 0.025 | AB90: 0.035 | AC90: 0.039 | AD90: 0.038 | AE90: 0.041 | AF90: 0.042 | AG90: 0.039 | AH90: 0.038 | AI90: 0.036 | AJ90: 0.029 | AK90: 0.176 | AL90: 0.018 | AM90: 0.02 | AN90: 0.022 | AO90: 0.023 | AP90: 0.022 | AQ90: 0.022 | AR90: 0.012 | AS90: 0.021 | AT90: 0.016 | AU90: 0.019

Sheet Adjusted EBITDA
B2: Globe Telecom Philippines | C2: Annual | D2: Annual | E2: Annual
B3: (PHP millions) | C3: 45291 | D3: 45657 | E3: 46022
C4: Act | D4: Act | E4: Act
C5: FY 23 | D5: FY 24 | E5: FY 25
B8: Adj. EBITDA | C8: 81426.746 | D8: 86813.676 | E8: 92991.532
B9: Depreciation and amortization | C9: -47356.043 | D9: -50473.04 | E9: -53871.127
B10: Financing costs | C10: -12145.879 | D10: -14444.27 | E10: =-16456.49 -> -16456.49
B11: Impairment of property and equipment | C11: -92.441 | D11: -410.563 | E11: 0
B12: Equity in net income (losses) of joint ventures | C12: 2214.761 | D12: 3897.012 | E12: 6392.043
B13: Foreign exchange gain (loss) - net | C13: 1042.052 | D13: -2431.889 | E13: -369.803
B14: Gain (loss) on derivative instruments | C14: -740.686 | D14: 2957.406 | E14: =772.855 -> 772.855
B15: Interest income | C15: 677.57 | D15: 918.338 | E15: 821.815
B16: Gain on disposal of property and equipment - net | C16: 371.655 | D16: 206.5 | E16: 283.559
B17: Gain on sale and leaseback of telecom towers - net | C17: 7258.378 | D17: 3482.083 | E17: 380.717
B18: Gain on sale of investments | C18: 76.669 | D18: 0 | E18: 21.093
B19: Impairment and other losses | C19: 0 | D19: 0 | E19: -3827.345
B20: Pension expense | C20: 0 | D20: 0 | E20: -947.838
B21: Share-based compensation | C21: 0 | D21: 0 | E21: -467.704
B22: Gain on deemed sale of Investment in Mynt | C22: 0 | D22: 0 | E22: 2560.357
B23: Loss on settlement and remeasurement of ARO | C23: 0 | D23: 0 | E23: -56.594
B24: Other items | C24: -317.112 | D24: -184.17 | E24: 0
B25: Income before income tax | C25: =SUM(C8:C24) -> 32415.67 | D25: =SUM(D8:D24) -> 30331.083 | E25: =SUM(E8:E24) -> 28227.07

Sheet Sheet1
I13: Globe Telecom (GLO) | J13: PLDT (TELPM)
H14: Market Cap | I14: 5.4bn | J14: 5.9bn
H15: LTM Revenues (USD) | I15: 3.25bn | J15: 3.3bn
H16: Data % of revenues | I16: 0.75 | J16: 0.65
H17: LTM EBITDA (USD) | I17: 1.46bn | J17: 1.69bn
H18: LTM EBITDA Margin | I18: =1.46/3.25 -> 0.44923077 | J18: =1.69/3.3 -> 0.51212121
H19: Total Debt | I19: 2.9bn | J19: 4.9bn
H20: 2020 (Est) Net Leverage | I20: 2.0x | J20: 2.7x
H21: 2020 (Est) Gross Leverage | I21: 2.6x | J21: 3.1x
H22: Ratings | I22: BBB- | J22: BBB+
H23: Capex/sales ratio | I23: 33% to 35% | J23: less than 40%
H24: Mobile % of total revenues | I24: 0.77 | J24: 0.53
H25: Fixed % of total revenues | I25: 0.23 | J25: 0.47
H26: Mobile Marketshare | I26: 0.54 | J26: 0.46
H27: Fixed Line Marketshare | I27: 0.32 | J27: 0.68
H28: Home Broadband marketshare | I28: 0.5 | J28: 0.5
H29: No of Mobile subscribers | I29: 89.3m | J29: 78.2m
H30: No of Fixed subscribers | I30: 2.3m | J30: 3.2m
H31: Fixed BB technology | I31: Predominnatly Fixed Wireless Technology (FWA- low end subcribers) | J31: Predominnatly Fixed Wireless Technology (Fibre high end subcribers)
H32: Dividend Policy
H33: Ownership | I33: Singtel (20.1%), Ayala(13.2%), Asiacom (50.9% JV Singtel+Ayala), Public 15.7% | J33: First Pacific 25.6%, NTT Docomo 20.3%, IG Summit Holdings 11.3%, Public 42.8%.
