Workbook
Name \A: #REF!
Name \A: #REF!
Name \B: #REF!
Name \B: #REF!
Name \C: #REF!
Name \C: #REF!
Name \L: #REF!
Name \M: #REF!
Name \P: #REF!
Name \Y: #REF!
Name _01_30_04: MonthlyOpStats
Name _01_30_04: MonthlyOpStats
Name _1_30_01: MonthlyOpStats
Name _1_30_01: MonthlyOpStats
Name _1_30_02: MonthlyOpStats
Name _1_30_02: MonthlyOpStats
Name _1_31_01: MonthlyOpStats
Name _1_31_01: MonthlyOpStats
Name _1_31_02: MonthlyOpStats
Name _1_31_02: MonthlyOpStats
Name _12_31_05: MonthlyOpStats
Name _12_31_05: MonthlyOpStats
Name _A: #REF!
Name _A: #REF!
Name _A___0: #REF!
Name _A___0: #REF!
Name _B: #REF!
Name _B: #REF!
Name _B___0: #REF!
Name _C: #REF!
Name _C___0: #REF!
Name _ent1: [1]Inputs!$J$17
Name _ent10: [1]Inputs!$J$476
Name _ent11: [1]Inputs!$J$527
Name _ent12: [1]Inputs!$J$578
Name _ent13: [1]Inputs!$J$629
Name _ent14: [1]Inputs!$J$680
Name _ent15: [1]Inputs!$J$731
Name _ent2: [1]Inputs!$J$68
Name _ent3: [1]Inputs!$J$119
Name _ent4: [1]Inputs!$J$170
Name _ent5: [1]Inputs!$J$221
Name _ent6: [1]Inputs!$J$272
Name _ent7: [1]Inputs!$J$323
Name _ent8: [1]Inputs!$J$374
Name _ent9: [1]Inputs!$J$425
Name _eps1: [1]Inputs!$P$42
Name _eps10: [1]Inputs!$P$501
Name _eps11: [1]Inputs!$P$552
Name _eps12: [1]Inputs!$P$603
Name _eps13: [1]Inputs!$P$654
Name _eps14: [1]Inputs!$P$705
Name _eps15: [1]Inputs!$P$756
Name _eps2: [1]Inputs!$P$93
Name _eps3: [1]Inputs!$P$144
Name _eps4: [1]Inputs!$P$195
Name _eps5: [1]Inputs!$P$246
Name _eps6: [1]Inputs!$P$297
Name _eps7: [1]Inputs!$P$348
Name _eps8: [1]Inputs!$P$399

Sheet Capitalisation
A2: 2Q26
B4: in billions
B5: Debt Maturity Profile at 30-Jun-2026 (from BBG) | C5: KRW bn
B6: 2026 | C6: 4061.3983
B7: 2027 | C7: 13694.293
B8: 2028 | C8: 12476.347
B9: 2029 | C9: 10764.291
B10: 2030 | C10: 4714.5643
B11: 2031 & thereafter | C11: =63085.00401-SUM(C6:C10) -> 17374.111
B12: Total | C12: =SUM(C6:C11) -> 63085.004
A20: 1Q26 | I20: Exchange rate as at end | J20: =Model!$K$203 -> 0.0006636713
I21: LTM Average exchange rate | J21: =Model!$K$204 -> 0.00070219616
B23: Debt Breakdown as on 31-Mar-2026 | C23: KRW mn | D23: Leverage | E23: USD mn | F23: Leverage | I23: Company reported | J23: =C23 -> KRW mn
I24: Total borrowings | J24: 19317665
B25: Current | C25: =SUM(C26:C29) -> 5890940 | E25: =SUM(E26:E28) -> 3909.6478 | I25: Cash and cash equivalents, and others | J25: -54329761
B26: Short-term borrowings | C26: 2522307 | E26: =C26*J20 -> 1673.9828 | I26: Net debt | J26: =SUM(J24:J25) -> -35012096
B27: Current portion of long-term borrowings | C27: 1716223 | E27: =C27*J20 -> 1139.0079 | I27: Net debt / EBITDA | J27: =J26/C46 -> -0.38196958
B28: Current portion of debentures | C28: 1652410 | E28: =C28*J20 -> 1096.6571
B31: Non-current | C31: =SUM(C32:C33) -> 13426725 | E31: =SUM(E32:E33) -> 8910.932
B32: Long-term borrowings | C32: 2675856 | E32: =C32*J20 -> 1775.8888
B33: Debentures | C33: 10750869 | E33: =C33*J20 -> 7135.0432
B35: Lease Obligations | C35: =SUM(C36:C37) -> 2514751 | E35: =SUM(E36:E37) -> 1668.9681
B36: Short-term | C36: =Model!$AG$107 -> 526303 | E36: =C36*J20 -> 349.29219
B37: Long-term | C37: =Model!$AG$108 -> 1988448 | E37: =C37*J20 -> 1319.6759
B39: Total Loans & Borrowings | C39: =C31+C25+C35 -> 21832416 | D39: =C39/C46 -> 0.23818394 | E39: =E31+E25+E35 -> 14489.548 | F39: =E39/E46 -> 0.22511636
B40: Cash and Cash Equivalents | C40: =Model!AG$115 -> 21166904 | E40: =C40*J20 -> 14047.867
B41: Short-term financial instruments | C41: =Model!AG$116 -> 18220075 | E41: =C41*J20 -> 12092.141
B42: Short-term investment assets | C42: =Model!AG$117 -> 14942782 | E42: =C42*J20 -> 9917.0955
B43: Net debt | C43: =C39-C40-C41-C42 -> -32497345 | D43: =C43/C46 -> -0.35453454 | E43: =E39-E40-E41-E42 -> -21567.555 | F43: =E43/E46 -> -0.33508357
B44: Equity | C44: =Model!AG$121 -> 164379799 | E44: =C44*J20 -> 109094.15
B45: Total Capitalisation | C45: =C43+C44 -> 131882454 | E45: =E43+E44 -> 87526.599
B46: LTM Adjusted EBITDA | C46: =Model!$AG$82 -> 91662000 | E46: =C46*J21 -> 64364.705
B47: check | C47: =+C39-Model!AG$114 -> 0
B50: Cash Breakdown as on 31-Mar-2026 | C50: =C23 -> KRW mn | D50: =E23 -> USD mn
B51: Cash and Cash Equivalents | C51: =C40 -> 21166904 | D51: =C51*J20 -> 14047.867
B52: Short-term financial instruments | C52: =C41 -> 18220075 | D52: =C52*J20 -> 12092.141
B53: Short-term investment assets | C53: =C42 -> 14942782 | D53: =C53*J20 -> 9917.0955
B54: Total | C54: =SUM(C51:C53) -> 54329761 | D54: =SUM(D51:D53) -> 36057.103
B57: Debt Maturity Profile at 31-Mar-2026 (from BBG) | C57: =C50 -> KRW mn | D57: =D50 -> USD mn
B58: 2026 | C58: 4303773.9 | D58: =C58*J20 -> 2856.2912
B59: 2027 | C59: 14024752 | D59: =C59*J20 -> 9307.8257
B60: 2028 | C60: 12553163 | D60: =C60*J20 -> 8331.1742
B61: 2029 | C61: 11032795 | D61: =C61*J20 -> 7322.1496
B62: 2030 | C62: 4730237.9 | D62: =C62*J20 -> 3139.3231
B63: 2031 & thereafter | C63: =64366534.2-SUM(C58:C62) -> 17721811 | D63: =C63*J20 -> 11761.457
C64: =SUM(C58:C63) -> 64366534 | D64: =SUM(D58:D63) -> 42718.221
A66: FY25 | I66: Exchange rate as at end | J66: =Model!$K$203 -> 0.0006636713
I67: LTM Average exchange rate | J67: =Model!$K$204 -> 0.00070219616
B69: Debt Breakdown as on 31-Dec-2025 | C69: KRW mn | D69: Leverage | E69: USD mn | F69: Leverage | I69: Company reported | J69: =C69 -> KRW mn
I70: Total borrowings | J70: 22248000
B71: Current | C71: =SUM(C72:C75) -> 8161757 | E71: =SUM(E72:E74) -> 5416.7239 | I71: Cash and cash equivalents, and others | J71: -34942000
B72: Short-term borrowings | C72: 2395797 | E72: =C72*J66 -> 1590.0217 | I72: Net debt | J72: =SUM(J70:J71) -> -12694000
B73: Current portion of long-term borrowings | C73: 1470301 | E73: =C73*J66 -> 975.79657 | I73: Net debt / EBITDA | J73: =J72/C92 -> -0.20777478
B74: Current portion of debentures | C74: 4295659 | E74: =C74*J66 -> 2850.9056
B77: Non-current | C77: =SUM(C78:C79) -> 14086148 | E77: =SUM(E78:E79) -> 9348.5721
B78: Long-term borrowings | C78: 2879750 | E78: =C78*J66 -> 1911.2074
B79: Debentures | C79: 11206398 | E79: =C79*J66 -> 7437.3647
B81: Lease Obligations | C81: =SUM(C82:C83) -> 2509943 | E81: =SUM(E82:E83) -> 1665.7771
B82: Short-term | C82: =Model!$AF$107 -> 547296 | E82: =C82*J66 -> 363.22465
B83: Long-term | C83: =Model!$AF$108 -> 1962647 | E83: =C83*J66 -> 1302.5525
B85: Total Loans & Borrowings | C85: =C77+C71+C81 -> 24757848 | D85: =C85/C92 -> 0.40523526 | E85: =E77+E71+E81 -> 16431.073 | F85: =E85/E92 -> 0.38300267
B86: Cash and Cash Equivalents | C86: =Model!AF$115 -> 14923766 | E86: =C86*J66 -> 9904.4751
B87: Short-term financial instruments | C87: =Model!AF$116 -> 14679719 | E87: =C87*J66 -> 9742.5081
B88: Short-term investment assets | C88: =Model!AF$117 -> 5338768 | E88: =C88*J66 -> 3543.1871
B89: Net debt | C89: =C85-C86-C87-C88 -> -10184405 | D89: =C89/C92 -> -0.16669785 | E89: =E85-E86-E87-E88 -> -6759.0973 | F89: =E89/E92 -> -0.15755224
B90: Equity | C90: =Model!AF$121 -> 120666751 | E90: =C90*J66 -> 80083.059
B91: Total Capitalisation | C91: =C89+C90 -> 110482346 | E91: =E89+E90 -> 73323.962
B92: LTM Adjusted EBITDA | C92: =Model!$AF$82 -> 61095000 | E92: =C92*J67 -> 42900.675
B93: check | C93: =+C85-Model!AF$114 -> 0
B96: Cash Breakdown as on 31-Dec-2025 | C96: =C69 -> KRW mn | D96: =E69 -> USD mn
B97: Cash and Cash Equivalents | C97: =C86 -> 14923766 | D97: =C97*J66 -> 9904.4751
B98: Short-term financial instruments | C98: =C87 -> 14679719 | D98: =C98*J66 -> 9742.5081
B99: Short-term investment assets | C99: =C88 -> 5338768 | D99: =C99*J66 -> 3543.1871
B100: Total | C100: =SUM(C97:C99) -> 34942253 | D100: =SUM(D97:D99) -> 23190.17
B104: Debt Maturity Profile at 31-Dec-2025 (contractual maturity) | C104: =C69 -> KRW mn | D104: =E69 -> USD mn
B105: Less than 1 year | C105: 7978826 | D105: =C105*J66 -> 5295.3178
B106: 1 - 2 years | C106: 4845560 | D106: =C106*J66 -> 3215.8591
B107: 2 - 5 years | C107: 8676290 | D107: =C107*J66 -> 5758.2046
B108: More than 5 years | C108: 3272460 | D108: =C108*J66 -> 2171.8378
C109: =SUM(C105:C108) -> 24773136 | D109: =SUM(D105:D108) -> 16441.219
B112: Lease liabilities Profile at 31-Dec-2025 (contractual maturity) | C112: =C104 -> KRW mn | D112: =D104 -> USD mn
B113: Less than 1 year | C113: 576548 | D113: =C113*J66 -> 382.63836
B114: 1 - 2 years | C114: 426197 | D114: =C114*J66 -> 282.85472
B115: 2 - 5 years | C115: 1068681 | D115: =C115*J66 -> 709.25291
B116: More than 5 years | C116: 944492 | D116: =C116*J66 -> 626.83223
C117: =SUM(C113:C116) -> 3015918 | D117: =SUM(D113:D116) -> 2001.5782
A121: 3Q25 | I121: Exchange rate as at end 3Q25 | J121: =Model!$K$203 -> 0.0006636713
I122: LTM Average exchange rate 3Q25 | J122: =Model!$K$204 -> 0.00070219616
B124: Debt Breakdown as on 30-Sep-2025 | C124: KRW mn | D124: Leverage | E124: USD mn | F124: Leverage | I124: Company reported | J124: =C124 -> KRW mn
I125: Total borrowings | J125: 24078734
B126: Current | C126: =SUM(C127:C130) -> 9249989 | E126: =SUM(E127:E129) -> 6138.9522 | I126: Cash and cash equivalents, and others | J126: -27854406
B127: Short-term borrowings | C127: 2180195 | E127: =C127*J121 -> 1446.9328 | I127: Net debt | J127: =SUM(J125:J126) -> -3775672
B128: Current portion of long-term borrowings | C128: 1380880 | E128: =C128*J121 -> 916.45042 | I128: Net debt / EBITDA | J128: =J127/C147 -> -0.076104007
B129: Current portion of debentures | C129: 5688914 | E129: =C129*J121 -> 3775.5689
B132: Non-current | C132: =SUM(C133:C134) -> 14828745 | E132: =SUM(E133:E134) -> 9841.4124
B133: Long-term borrowings | C133: 3803862 | E133: =C133*J121 -> 2524.514
B134: Debentures | C134: 11024883 | E134: =C134*J121 -> 7316.8984
B136: Lease Obligations | C136: =SUM(C137:C138) -> 2505190 | E136: =SUM(E137:E138) -> 1662.6227
B137: Short-term | C137: =Model!$AE$107 -> 539118 | E137: =C137*J121 -> 357.79714
B138: Long-term | C138: =Model!$AE$108 -> 1966072 | E138: =C138*J121 -> 1304.8256
...

Sheet Model
B2: SK Hynix Inc. | C2: Annual | D2: Annual | E2: Annual | F2: Annual | G2: Annual | H2: Annual | I2: Annual | J2: Annual | K2: LTM | M2: Quarters | N2: Quarters | O2: Quarters | P2: Quarters | Q2: Quarters | R2: Quarters | S2: Quarters | T2: Quarters | U2: Quarters | V2: Quarters | W2: Quarters | X2: Quarters | Y2: Quarters | Z2: Quarters | AA2: Quarters | AB2: Quarters | AC2: Quarters | AD2: Quarters | AE2: Quarters | AF2: Quarters | AG2: Quarters | AN2: s
B3: (KRW millions) | C3: 43465 | D3: 43830 | E3: 44196 | F3: 44561 | G3: 44926 | H3: 45291 | I3: 45657 | J3: 46022 | K3: =AG3 -> 46112 | M3: 44286 | N3: 44377 | O3: 44469 | P3: 44561 | Q3: 44651 | R3: 44742 | S3: 44834 | T3: 44926 | U3: 45016 | V3: 45107 | W3: 45199 | X3: 45291 | Y3: 45382 | Z3: 45473 | AA3: 45565 | AB3: 45657 | AC3: 45747 | AD3: 45838 | AE3: 45930 | AF3: 46022 | AG3: 46112
C4: Act | D4: Act | E4: Act | F4: Act | G4: Act | H4: Act | I4: Act | J4: Act | K4: Act | M4: Act | N4: Act | O4: Act | P4: Act | Q4: Act | R4: Act | S4: Act | T4: Act | U4: Act | V4: Act | W4: Act | X4: Act | Y4: Act | Z4: Act | AA4: Act | AB4: Act | AC4: Act | AD4: Act | AE4: Act | AF4: Act | AG4: Act
C5: FY | D5: FY | E5: FY | F5: FY | G5: FY | H5: FY | I5: FY | J5: FY | K5: LTM | M5: 1Q | N5: 2Q | O5: 3Q | P5: 4Q | Q5: 1Q | R5: 2Q | S5: 3Q | T5: 4Q | U5: 1Q | V5: 2Q | W5: 3Q | X5: 4Q | Y5: 1Q | Z5: 2Q | AA5: 3Q | AB5: 4Q | AC5: 1Q | AD5: 2Q | AE5: 3Q | AF5: 4Q | AG5: 1Q
B6: INCOME STATEMENT
B7: Revenue | C7: 40445066 | D7: 26990733 | E7: 31900418 | F7: 42997792 | G7: 44621568 | H7: 32765719 | I7: 66192960 | J7: 97146675 | K7: =SUM(AD7:AG7) -> 132083821 | M7: 8494188 | N7: 10321671 | O7: 11805324 | P7: =F7-SUM(M7:O7) -> 12376609 | Q7: 12155653 | R7: 13811001 | S7: 10982883 | T7: =G7-SUM(Q7:S7) -> 7672031 | U7: 5088111 | V7: 7305933 | W7: 9066171 | X7: =H7-SUM(U7:W7) -> 11305504 | Y7: 12429598 | Z7: 16423258 | AA7: 17573069 | AB7: =I7-SUM(Y7:AA7) -> 19767035 | AC7: 17639141 | AD7: 22231952 | AE7: 24448929 | AF7: =J7-SUM(AC7:AE7) -> 32826653 | AG7: 52576287
B8: % of growth | D8: =(D7/C7)-1 -> -0.33265697 | E8: =(E7/D7)-1 -> 0.18190262 | F8: =(F7/E7)-1 -> 0.3478755 | G8: =(G7/F7)-1 -> 0.037764172 | H8: =(H7/G7)-1 -> -0.26569772 | I8: =(I7/H7)-1 -> 1.0201895 | J8: =(J7/I7)-1 -> 0.46762851 | Q8: =(Q7/M7)-1 -> 0.43105533 | R8: =(R7/N7)-1 -> 0.33805863 | S8: =(S7/O7)-1 -> -0.069666957 | T8: =(T7/P7)-1 -> -0.3801185 | U8: =(U7/Q7)-1 -> -0.58142018 | V8: =(V7/R7)-1 -> -0.47100627 | W8: =(W7/S7)-1 -> -0.17451811 | X8: =(X7/T7)-1 -> 0.47359989 | ... AG8: =(AG7/AC7)-1 -> 1.9806603
B9: Cost of sales | C9: -15180838 | D9: -18818814 | E9: -21089789 | F9: -24045600 | G9: -28993713 | H9: -33299167 | I9: -34364814 | J9: -38455885 | K9: =SUM(AD9:AG9) -> -41815608 | M9: -5765640 | N9: -5982227 | O9: -5974270 | P9: =F9-SUM(M9:O9) -> -6323463 | Q9: -6754457 | R9: -7473340 | S9: -7117303 | T9: =G9-SUM(Q9:S9) -> -7648613 | U9: -6733410 | V9: -8483761 | W9: -9002045 | X9: =H9-SUM(U9:W9) -> -9079951 | Y9: -7634953 | Z9: -8926794 | AA9: -8401685 | AB9: =I9-SUM(Y9:AA9) -> -9401382 | AC9: -7537150 | AD9: -10248628 | AE9: =-10419829 -> -10419829 | AF9: =J9-SUM(AC9:AE9) -> -10250278 | AG9: -10896873
B10: Gross Profit | C10: =C7+C9 -> 25264228 | D10: =D7+D9 -> 8171919 | E10: =E7+E9 -> 10810629 | F10: =F7+F9 -> 18952192 | G10: =G7+G9 -> 15627855 | H10: =H7+H9 -> -533448 | I10: =I7+I9 -> 31828146 | J10: =J7+J9 -> 58690790 | K10: =K7+K9 -> 90268213 | M10: =M7+M9 -> 2728548 | N10: =N7+N9 -> 4339444 | O10: =O7+O9 -> 5831054 | P10: =P7+P9 -> 6053146 | Q10: =Q7+Q9 -> 5401196 | R10: =R7+R9 -> 6337661 | S10: =S7+S9 -> 3865580 | T10: =T7+T9 -> 23418 | ... AG10: =AG7+AG9 -> 41679414
B11: Gross Profit margin | C11: =C10/C7 -> 0.62465538 | D11: =D10/D7 -> 0.30276758 | E11: =E10/E7 -> 0.33888675 | F11: =F10/F7 -> 0.44077128 | G11: =G10/G7 -> 0.35023097 | H11: =H10/H7 -> -0.016280674 | I11: =I10/I7 -> 0.48083884 | J11: =J10/J7 -> 0.60414615 | K11: =K10/K7 -> 0.68341612 | M11: =M10/M7 -> 0.32122529 | N11: =N10/N7 -> 0.42042069 | O11: =O10/O7 -> 0.49393426 | P11: =P10/P7 -> 0.48907952 | Q11: =Q10/Q7 -> 0.44433615 | R11: =R10/R7 -> 0.45888499 | S11: =S10/S7 -> 0.35196405 | T11: =T10/T7 -> 0.003052386 | ... AG11: =AG10/AG7 -> 0.79274168
B12: Operating expenses:
B13: Selling and administrative expenses | C13: -4420478 | D13: -5452740 | E13: -5798005 | F13: -6541852 | G13: -8818438 | H13: -7196865 | I13: -8360827 | J13: -11484471 | K13: =SUM(AD13:AG13) -> -12892115 | M13: -1404127 | N13: -1644870 | O13: -1659233 | P13: =F13-SUM(M13:O13) -> -1833622 | Q13: -2537299 | R13: -2140435 | S13: -2205057 | T13: =G13-SUM(Q13:S13) -> -1935647 | U13: -1757003 | V13: -1704256 | W13: -1856087 | X13: =H13-SUM(U13:W13) -> -1879519 | Y13: -1908616 | Z13: -2027928 | AA13: -2141426 | AB13: =I13-SUM(Y13:AA13) -> -2282857 | AC13: -2661487 | AD13: -2770473 | AE13: -2645710 | AF13: =J13-SUM(AC13:AE13) -> -3406801 | AG13: -4069131
B14: Operating profit | C14: =C10+SUM(C13:C13) -> 20843750 | D14: =D10+SUM(D13:D13) -> 2719179 | E14: =E10+SUM(E13:E13) -> 5012624 | F14: =F10+SUM(F13:F13) -> 12410340 | G14: =G10+SUM(G13:G13) -> 6809417 | H14: =H10+SUM(H13:H13) -> -7730313 | I14: =I10+SUM(I13:I13) -> 23467319 | J14: =J10+SUM(J13:J13) -> 47206319 | K14: =K10+SUM(K13:K13) -> 77376098 | M14: =M10+SUM(M13:M13) -> 1324421 | N14: =N10+SUM(N13:N13) -> 2694574 | O14: =O10+SUM(O13:O13) -> 4171821 | P14: =P10+SUM(P13:P13) -> 4219524 | Q14: =Q10+SUM(Q13:Q13) -> 2863897 | R14: =R10+SUM(R13:R13) -> 4197226 | S14: =S10+SUM(S13:S13) -> 1660523 | T14: =T10+SUM(T13:T13) -> -1912229 | ... AG14: =AG10+SUM(AG13:AG13) -> 37610283
B15: Finance income | C15: 1691955 | D15: 1247640 | E15: 3327905 | F15: 2377516 | G15: 3714278 | H15: 2261801 | I15: 4855082 | J15: 16373480 | K15: =SUM(AD15:AG15) -> 30742471 | M15: 597565 | N15: 216373 | O15: 649820 | P15: =F15-SUM(M15:O15) -> 913758 | Q15: 657956 | R15: 1425304 | S15: 2095629 | T15: =G15-SUM(Q15:S15) -> -464611 | U15: 1073308 | V15: =447027 -> 447027 | W15: 668230 | X15: =H15-SUM(U15:W15) -> 73236 | Y15: 1117553 | Z15: 915411 | AA15: 1594457 | AB15: =I15-SUM(Y15:AA15) -> 1227661 | AC15: 2687359 | AD15: 1719380 | AE15: =4490315 -> 4490315 | AF15: =J15-SUM(AC15:AE15) -> 7476426 | AG15: 17056350
B16: Finance expenses | C16: -1142134 | D16: -1531417 | E16: -1980411 | F16: -1469860 | G16: -5091553 | H16: -6093167 | I16: -5707997 | J16: -12504998 | K16: =SUM(AD16:AG16) -> -14763877 | M16: -589521 | N16: -216686 | O16: -274108 | P16: =F16-SUM(M16:O16) -> -389545 | Q16: -737321 | R16: -1814401 | S16: -2064165 | T16: =G16-SUM(Q16:S16) -> -475666 | U16: -1202394 | V16: -1312018 | W16: -1141653 | X16: =H16-SUM(U16:W16) -> -2437102 | Y16: -1625139 | Z16: -1312751 | AA16: -1778636 | AB16: =I16-SUM(Y16:AA16) -> -991471 | AC16: -764604 | AD16: -2172268 | AE16: -1092286 | AF16: =J16-SUM(AC16:AE16) -> -8475840 | AG16: -3023483
B17: Share of profit of equity-accounted investees | C17: 13007 | D17: 22633 | E17: -36279 | F17: 162280 | G17: 131186 | H17: 15061 | I17: -38245 | J17: -564553 | K17: =SUM(AD17:AG17) -> -550222 | M17: 17479 | N17: 125458 | O17: 41493 | P17: =F17-SUM(M17:O17) -> -22150 | Q17: 31967 | R17: 60752 | S17: 26526 | T17: =G17-SUM(Q17:S17) -> 11941 | U17: 2745 | V17: 10102 | W17: 6011 | X17: =H17-SUM(U17:W17) -> -3797 | Y17: 6161 | Z17: 782 | AA17: 6798 | AB17: =I17-SUM(Y17:AA17) -> -51986 | AC17: -41109 | AD17: 17312 | AE17: -23221 | AF17: =J17-SUM(AC17:AE17) -> -517535 | AG17: -26778
B18: Other income | C18: 112810 | D18: 88179 | E18: 84773 | F18: 116135 | G18: 241371 | H18: 623867 | I18: 1476579 | J18: 333277 | K18: =SUM(AD18:AG18) -> 269357 | M18: 16927 | N18: 31826 | O18: 29869 | P18: =F18-SUM(M18:O18) -> 37513 | Q18: 26111 | R18: 158041 | S18: 30097 | T18: =G18-SUM(Q18:S18) -> 27122 | U18: 18891 | V18: 7210 | W18: 234157 | X18: =H18-SUM(U18:W18) -> 363609 | Y18: 27478 | Z18: 16781 | AA18: 57239 | AB18: =I18-SUM(Y18:AA18) -> 1375081 | AC18: 78943 | AD18: 29879 | AE18: =54827 -> 54827 | AF18: =J18-SUM(AC18:AE18) -> 169628 | AG18: 15023
B19: Other expenses | C19: -178358 | D19: -113575 | E19: -171575 | F19: -180424 | G19: -1801919 | H19: -735065 | I19: -167388 | J19: -377973 | K19: =SUM(AD19:AG19) -> -290646 | M19: -16279 | N19: -50437 | O19: -20260 | P19: =F19-SUM(M19:O19) -> -93448 | Q19: -64078 | R19: -55586 | S19: -60401 | T19: =G19-SUM(Q19:S19) -> -1621854 | U19: -15431 | V19: -58444 | W19: -444441 | X19: =H19-SUM(U19:W19) -> -216749 | Y19: -39507 | Z19: -36572 | AA19: -30643 | AB19: =I19-SUM(Y19:AA19) -> -60666 | AC19: -101864 | AD19: -84571 | AE19: -22597 | AF19: =J19-SUM(AC19:AE19) -> -168941 | AG19: -14537
B20: Profit before tax | C20: =C14+SUM(C15:C19) -> 21341030 | D20: =D14+SUM(D15:D19) -> 2432639 | E20: =E14+SUM(E15:E19) -> 6237037 | F20: =F14+SUM(F15:F19) -> 13415987 | G20: =G14+SUM(G15:G19) -> 4002780 | H20: =H14+SUM(H15:H19) -> -11657816 | I20: =I14+SUM(I15:I19) -> 23885350 | J20: =J14+SUM(J15:J19) -> 50465552 | K20: =K14+SUM(K15:K19) -> 92783181 | M20: =M14+SUM(M15:M19) -> 1350592 | N20: =N14+SUM(N15:N19) -> 2801108 | O20: =O14+SUM(O15:O19) -> 4598635 | P20: =P14+SUM(P15:P19) -> 4665652 | Q20: =Q14+SUM(Q15:Q19) -> 2778532 | R20: =R14+SUM(R15:R19) -> 3971336 | S20: =S14+SUM(S15:S19) -> 1688209 | T20: =T14+SUM(T15:T19) -> -4435297 | ... AG20: =AG14+SUM(AG15:AG19) -> 51616858
B21: Income tax expense (benefit) | C21: -5801046 | D21: -423561 | E21: -1478123 | F21: -3799799 | G21: -1761111 | H21: 2520269 | I21: -4088448 | J21: -7517650 | K21: =SUM(AD21:AG21) -> -17597565 | M21: -357952 | N21: -812684 | O21: -1283383 | P21: =F21-SUM(M21:O21) -> -1345780 | Q21: -791322 | R21: -1089906 | S21: -580592 | T21: =G21-SUM(Q21:S21) -> 700709 | U21: 939692 | V21: 800300 | W21: 284958 | X21: =H21-SUM(U21:W21) -> 495319 | Y21: -455536 | Z21: -932184 | AA21: -1125800 | AB21: =I21-SUM(Y21:AA21) -> -1574928 | AC21: -1191034 | AD21: -1726367 | AE21: -2192890 | AF21: =J21-SUM(AC21:AE21) -> -2407359 | AG21: -11270949
B22: Net profit/loss | C22: =+C20+C21 -> 15539984 | D22: =+D20+D21 -> 2009078 | E22: =+E20+E21 -> 4758914 | F22: =+F20+F21 -> 9616188 | G22: =+G20+G21 -> 2241669 | H22: =+H20+H21 -> -9137547 | I22: =+I20+I21 -> 19796902 | J22: =+J20+J21 -> 42947902 | K22: =+K20+K21 -> 75185616 | M22: =+M20+M21 -> 992640 | N22: =+N20+N21 -> 1988424 | O22: =+O20+O21 -> 3315252 | P22: =+P20+P21 -> 3319872 | Q22: =+Q20+Q21 -> 1987210 | R22: =+R20+R21 -> 2881430 | S22: =+S20+S21 -> 1107617 | T22: =+T20+T21 -> -3734588 | ... AG22: =+AG20+AG21 -> 40345909
B23: % margin | C23: =+C22/C7 -> 0.38422447 | D23: =+D22/D7 -> 0.074435844 | E23: =+E22/E7 -> 0.1491803 | F23: =+F22/F7 -> 0.22364376 | G23: =+G22/G7 -> 0.050237343 | H23: =+H22/H7 -> -0.27887522 | I23: =+I22/I7 -> 0.29907866 | J23: =+J22/J7 -> 0.44209338 | K23: =+K22/K7 -> 0.56922654 | M23: =+M22/M7 -> 0.11686108 | N23: =+N22/N7 -> 0.19264555 | O23: =+O22/O7 -> 0.28082685 | P23: =+P22/P7 -> 0.26823761 | Q23: =+Q22/Q7 -> 0.16348032 | R23: =+R22/R7 -> 0.20863296 | S23: =+S22/S7 -> 0.10084939 | T23: =+T22/T7 -> -0.48677958 | ... AG23: =+AG22/AG7 -> 0.76737844
B24: Non-controlling interest | C24: 127 | D24: -3103 | E24: -3812 | F24: -13872 | G24: -12109 | H24: 25119 | I24: -8221 | J24: -28615 | K24: =SUM(AD24:AG24) -> -43234 | M24: -2194 | N24: -3909 | O24: -4429 | P24: =F24-SUM(M24:O24) -> -3340 | Q24: -4084 | R24: -5282 | S24: 4088 | T24: =G24-SUM(Q24:S24) -> -6831 | U24: 5082 | V24: -3274 | W24: 966 | X24: =H24-SUM(U24:W24) -> 22345 | Y24: 2212 | Z24: 276 | AA24: -4697 | AB24: =I24-SUM(Y24:AA24) -> -6012 | AC24: -1114 | AD24: 1012 | AE24: -2343 | AF24: =J24-SUM(AC24:AE24) -> -26170 | AG24: -15733
B25: Net profit/loss | C25: =+C22+C24 -> 15540111 | D25: =+D22+D24 -> 2005975 | E25: =+E22+E24 -> 4755102 | F25: =+F22+F24 -> 9602316 | G25: =+G22+G24 -> 2229560 | H25: =+H22+H24 -> -9112428 | I25: =+I22+I24 -> 19788681 | J25: =+J22+J24 -> 42919287 | K25: =+K22+K24 -> 75142382 | M25: =+M22+M24 -> 990446 | N25: =+N22+N24 -> 1984515 | O25: =+O22+O24 -> 3310823 | P25: =+P22+P24 -> 3316532 | Q25: =+Q22+Q24 -> 1983126 | R25: =+R22+R24 -> 2876148 | S25: =+S22+S24 -> 1111705 | T25: =+T22+T24 -> -3741419 | ... AG25: =+AG22+AG24 -> 40330176
B27: As % of sales unless stated otherwise
B28: =B13 -> Selling and administrative expenses | C28: =-C13/C7 -> 0.10929585 | D28: =-D13/D7 -> 0.20202267 | E28: =-E13/E7 -> 0.18175326 | F28: =-F13/F7 -> 0.15214391 | G28: =-G13/G7 -> 0.19762726 | H28: =-H13/H7 -> 0.21964618 | I28: =-I13/I7 -> 0.12630991 | J28: =-J13/J7 -> 0.11821785 | K28: =-K13/K7 -> 0.097605558 | M28: =-M13/M7 -> 0.16530444 | N28: =-N13/N7 -> 0.15936082 | O28: =-O13/O7 -> 0.14054955 | P28: =-P13/P7 -> 0.14815221 | Q28: =-Q13/Q7 -> 0.20873408 | R28: =-R13/R7 -> 0.15498044 | S28: =-S13/S7 -> 0.20077215 | T28: =-T13/T7 -> 0.25229916 | ... AG28: =-AG13/AG7 -> 0.077394796
B29: Finance expenses as % of debt | C29: =-C16/C104 -> 0.21623393 | D29: =-D16/D104 -> 0.14552346 | E29: =-E16/E104 -> 0.17601075 | F29: =-F16/F104 -> 0.083401948 | G29: =-G16/G104 -> 0.22142382 | H29: =-H16/H104 -> 0.20676789 | I29: =-I16/I104 -> 0.25163394 | J29: =-J16/J104 -> 0.56207531 | K29: =-K16/K104 -> 0.7642682 | P29: {=-SUM(M16:P16/P104)} -> 0.083401948 | Q29: {=-SUM(N16:Q16/Q104)} -> 0.089306215 | R29: {=-SUM(O16:R16/R104)} -> 0.16589404 | S29: {=-SUM(P16:S16/S104)} -> 0.22729778 | T29: {=-SUM(Q16:T16/T104)} -> 0.22142382 | U29: {=-SUM(R16:U16/U104)} -> 0.19322171 | V29: {=-SUM(S16:V16/V104)} -> 0.16406412 | W29: {=-SUM(T16:W16/W104)} -> 0.13092244 | ... AG29: {=-SUM(AD16:AG16/AG104)} -> 0.7642682
B30: Finance income as % of cash and cash equivalents | C30: =C15/C115 -> 0.72018955 | D30: =D15/D115 -> 0.54102434 | E30: =E15/E115 -> 1.1182518 | F30: =F15/F115 -> 0.47005229 | G30: =G15/G115 -> 0.74628748 | H30: =H15/H115 -> 0.2981024 | I30: =I15/I115 -> 0.4332915 | J30: =J15/J115 -> 1.0971413 | K30: =K15/K115 -> 1.4523839 | P30: =SUM(M15:P15)/P115 -> 0.47005229 | Q30: =SUM(N15:Q15)/Q115 -> 0.489268 | R30: =SUM(O15:R15)/R115 -> 0.80215304 | S30: =SUM(P15:S15)/S115 -> 1.0791297 | T30: =SUM(Q15:T15)/T115 -> 0.74628748 | U30: =SUM(R15:U15)/U115 -> 0.84368007 | V30: =SUM(S15:V15)/V115 -> 0.52167723 | W30: =SUM(T15:W15)/W115 -> 0.24204998 | ... AG30: =SUM(AD15:AG15)/AG115 -> 1.4523839
B31: Other income | C31: =C18/C7 -> 0.0027892154 | D31: =D18/D7 -> 0.0032670102 | E31: =E18/E7 -> 0.002657426 | F31: =F18/F7 -> 0.0027009526 | G31: =G18/G7 -> 0.00540929 | H31: =H18/H7 -> 0.019040235 | I31: =I18/I7 -> 0.022307191 | J31: =J18/J7 -> 0.0034306578 | K31: =K18/K7 -> 0.0020392884 | M31: =M18/M7 -> 0.0019927744 | N31: =N18/N7 -> 0.0030834155 | O31: =O18/O7 -> 0.0025301296 | P31: =P18/P7 -> 0.0030309594 | Q31: =Q18/Q7 -> 0.0021480541 | R31: =R18/R7 -> 0.011443124 | S31: =S18/S7 -> 0.0027403552 | T31: =T18/T7 -> 0.0035351786 | ... AG31: =AG18/AG7 -> 0.00028573718
B32: Other expenses | C32: =-C19/C7 -> 0.0044098828 | D32: =-D19/D7 -> 0.0042079257 | E32: =-E19/E7 -> 0.0053784562 | F32: =-F19/F7 -> 0.0041961224 | G32: =-G19/G7 -> 0.040382243 | H32: =-H19/H7 -> 0.022433965 | I32: =-I19/I7 -> 0.0025287886 | J32: =-J19/J7 -> 0.0038907456 | K32: =-K19/K7 -> 0.0022004663 | M32: =-M19/M7 -> 0.0019164869 | N32: =-N19/N7 -> 0.004886515 | O32: =-O19/O7 -> 0.0017161748 | P32: =-P19/P7 -> 0.0075503718 | Q32: =-Q19/Q7 -> 0.0052714568 | R32: =-R19/R7 -> 0.0040247626 | S32: =-S19/S7 -> 0.0054995578 | T32: =-T19/T7 -> 0.21139826 | ... AG32: =-AG19/AG7 -> 0.00027649347
B33: Tax % of PBT | C33: =-C21/C20 -> 0.27182596 | D33: =-D21/D20 -> 0.17411585 | E33: =-E21/E20 -> 0.23699122 | F33: =-F21/F20 -> 0.28322918 | G33: =-G21/G20 -> 0.43997197 | H33: =-H21/H20 -> 0.21618706 | I33: =-I21/I20 -> 0.17116969 | J33: =-J21/J20 -> 0.14896597 | K33: =-K21/K20 -> 0.18966331 | M33: =-M21/M20 -> 0.26503341 | N33: =-N21/N20 -> 0.29012948 | O33: =-O21/O20 -> 0.27907912 | P33: =-P21/P20 -> 0.28844414 | Q33: =-Q21/Q20 -> 0.28479859 | R33: =-R21/R20 -> 0.27444316 | S33: =-S21/S20 -> 0.34391003 | T33: =-T21/T20 -> 0.15798469 | ... AG33: =-AG21/AG20 -> 0.21835791
B35: Working capital /sales | C35: =C55/C7 -> -0.056146923 | D35: =D55/D7 -> 0.040180902 | E35: =E55/E7 -> -0.048812903 | F35: =F55/F7 -> -0.079545038 | G35: =G55/G7 -> -0.060713398 | H35: =H55/H7 -> 0.021783041 | I35: =I55/I7 -> -0.070344384 | J35: =J55/J7 -> -0.059494707 | K35: =K55/K7 -> -0.17292883 | M35: =M55/M7 -> -0.014361231 | N35: =N55/N7 -> -0.12383247 | O35: =O55/O7 -> -0.087092993 | P35: =P55/P7 -> -0.080147559 | Q35: =Q55/Q7 -> -0.02581153 | R35: =R55/R7 -> -0.12330707 | S35: =S55/S7 -> -0.14631914 | T35: =T55/T7 -> 0.11921602 | ... AG35: =AG55/AG7 -> -0.3089093
B36: Capex/sales | C36: =-C59/C7 -> 0.39323442 | D36: =-D59/D7 -> 0.51374685 | E36: =-E59/E7 -> 0.31377561 | F36: =-F59/F7 -> 0.28854261 | G36: =-G59/G7 -> 0.41877827 | H36: =-H59/H7 -> 0.20708573 | I36: =-I59/I7 -> 0.24018276 | J36: =-J59/J7 -> 0.28178109 | K36: =-K59/K7 -> 0.2178813 | M36: =-M59/M7 -> 0.46905767 | N36: =-N59/N7 -> 0.28091614 | O36: =-O59/O7 -> 0.23609356 | P36: =-P59/P7 -> 0.22104164 | Q36: =-Q59/Q7 -> 0.42881588 | R36: =-R59/R7 -> 0.33045534 | S36: =-S59/S7 -> 0.43538969 | T36: =-T59/T7 -> 0.53809128 | ... AG36: =-AG59/AG7 -> 0.1453642
B38: EBITDA | C38: =C3 -> 43465 | D38: =D3 -> 43830 | E38: =E3 -> 44196 | F38: =F3 -> 44561 | G38: =G3 -> 44926 | H38: =H3 -> 45291 | I38: =I3 -> 45657 | J38: =J3 -> 46022 | K38: =K2 -> LTM | M38: =M3 -> 44286 | N38: =N3 -> 44377 | O38: =O3 -> 44469 | P38: =P3 -> 44561 | Q38: =Q3 -> 44651 | R38: =R3 -> 44742 | S38: =S3 -> 44834 | T38: =T3 -> 44926 | ... AG38: =AG3 -> 46112
B39: Operating profit | C39: =C14 -> 20843750 | D39: =D14 -> 2719179 | E39: =E14 -> 5012624 | F39: =F14 -> 12410340 | G39: =G14 -> 6809417 | H39: =H14 -> -7730313 | I39: =I14 -> 23467319 | J39: =J14 -> 47206319 | K39: =K14 -> 77376098 | M39: =M14 -> 1324421 | N39: =N14 -> 2694574 | O39: =O14 -> 4171821 | P39: =P14 -> 4219524 | Q39: =Q14 -> 2863897 | R39: =R14 -> 4197226 | S39: =S14 -> 1660523 | T39: =T14 -> -1912229 | ... AG39: =AG14 -> 37610283
B40: Depreciation, depletion & amortization | C40: 6309070 | D40: 8605492 | E40: 9764776 | F40: 10646887 | G40: 14135292 | H40: 13619161 | I40: 12544767 | J40: 13889639 | K40: =SUM(AD40:AG40) -> 14281476 | M40: 2532934 | N40: 2614665 | O40: 2708159 | P40: =F40-SUM(M40:O40) -> 2791129 | Q40: 3391643 | R40: 3478314 | S40: 3552718 | T40: =G40-SUM(Q40:S40) -> 3712617 | U40: 3556847 | V40: 3493623 | W40: 3332583 | X40: =H40-SUM(U40:W40) -> 3236108 | Y40: 3186882 | Z40: 3122193 | AA40: 3070447 | AB40: =I40-SUM(Y40:AA40) -> 3165245 | AC40: 3333928 | AD40: 3442889 | AE40: 3549343 | AF40: =J40-SUM(AC40:AE40) -> 3563479 | AG40: 3725765
B41: EBITDA | C41: =SUM(C39:C40) -> 27152820 | D41: =SUM(D39:D40) -> 11324671 | E41: =SUM(E39:E40) -> 14777400 | F41: =SUM(F39:F40) -> 23057227 | G41: =SUM(G39:G40) -> 20944709 | H41: =SUM(H39:H40) -> 5888848 | I41: =SUM(I39:I40) -> 36012086 | J41: =SUM(J39:J40) -> 61095958 | K41: =SUM(K39:K40) -> 91657574 | M41: =SUM(M39:M40) -> 3857355 | N41: =SUM(N39:N40) -> 5309239 | O41: =SUM(O39:O40) -> 6879980 | P41: =SUM(P39:P40) -> 7010653 | Q41: =SUM(Q39:Q40) -> 6255540 | R41: =SUM(R39:R40) -> 7675540 | S41: =SUM(S39:S40) -> 5213241 | T41: =SUM(T39:T40) -> 1800388 | ... AG41: =SUM(AG39:AG40) -> 41336048
B42: % growth | D42: =+D41/C41-1 -> -0.58292837 | E42: =+E41/D41-1 -> 0.30488559 | F42: =+F41/E41-1 -> 0.56030337 | G42: =+G41/F41-1 -> -0.091620645 | H42: =+H41/G41-1 -> -0.71883839 | I42: =+I41/H41-1 -> 5.1153023 | J42: =+J41/I41-1 -> 0.69654038 | Q42: =Q41/M41-1 -> 0.62171747 | R42: =R41/N41-1 -> 0.44569495 | S42: =S41/O41-1 -> -0.24225928 | T42: =T41/P41-1 -> -0.74319254 | U42: =U41/Q41-1 -> -0.9752947 | V42: =V41/R41-1 -> -0.92032626 | W42: =W41/S41-1 -> -0.70447904 | X42: =X41/T41-1 -> 0.98965001 | ... AG42: =AG41/AC41-1 -> 2.8364944
B43: % margin | C43: =+C41/C7 -> 0.67135062 | D43: =+D41/D7 -> 0.41957627 | E43: =+E41/E7 -> 0.46323531 | F43: =+F41/F7 -> 0.53624212 | G43: =+G41/G7 -> 0.46938532 | H43: =+H41/H7 -> 0.17972589 | I43: =+I41/I7 -> 0.54404707 | J43: =+J41/J7 -> 0.62890426 | K43: =+K41/K7 -> 0.69393491 | M43: =+M41/M7 -> 0.45411698 | N43: =+N41/N7 -> 0.51437786 | O43: =+O41/O7 -> 0.58278621 | P43: =+P41/P7 -> 0.56644377 | Q43: =+Q41/Q7 -> 0.51461982 | R43: =+R41/R7 -> 0.55575552 | S43: =+S41/S7 -> 0.47466963 | T43: =+T41/T7 -> 0.23466902 | ... AG43: =+AG41/AG7 -> 0.78621086
B45: Adjustment | C45: =C46-C41 -> 107180 | D45: =D46-D41 -> -73671 | E45: =E46-E41 -> 25600 | F45: =F46-F41 -> -227 | G45: =G46-G41 -> 3291 | H45: =H46-H41 -> 152 | I45: =I46-I41 -> 914 | J45: =J46-J41 -> -958 | K45: =K46-K41 -> 4426 | M45: =M46-M41 -> -355 | N45: =N46-N41 -> -239 | O45: =O46-O41 -> 20 | P45: =P46-P41 -> 347 | Q45: =Q46-Q41 -> 460 | R45: =R46-R41 -> -3540 | S45: =S46-S41 -> 6759 | T45: =T46-T41 -> -388 | ... AG45: =AG46-AG41 -> -48
B46: Adj. EBITDA | C46: =6181000+8120000+7146000+5813000 -> 27260000 | D46: =2478000+2631000+2745000+3397000 -> 11251000 | E46: =3557000+3764000+4375000+3107000 -> 14803000 | F46: =SUM(M46:P46) -> 23057000 | G46: =SUM(Q46:T46) -> 20948000 | H46: =SUM(U46:X46) -> 5889000 | I46: =SUM(Y46:AB46) -> 36013000 | J46: =SUM(AC46:AF46) -> 61095000 | K46: =SUM(AD46:AG46) -> 91662000 | M46: 3857000 | N46: 5309000 | O46: 6880000 | P46: 7011000 | Q46: 6256000 | R46: 7672000 | S46: 5220000 | T46: 1800000 | U46: 154000 | V46: 612000 | W46: 1541000 | X46: 3582000 | Y46: 6073000 | Z46: 8591000 | AA46: 10100000 | AB46: 11249000 | AC46: 10769000 | AD46: 12645000 | AE46: 14949000 | AF46: 22732000 | AG46: 41336000
B47: % growth | D47: =+D46/C46-1 -> -0.58727073 | E47: =+E46/D46-1 -> 0.31570527 | F47: =+F46/E46-1 -> 0.55758968 | G47: =+G46/F46-1 -> -0.091468968 | H47: =+H46/G46-1 -> -0.71887531 | I47: =+I46/H46-1 -> 5.1152997 | J47: =+J46/I46-1 -> 0.69647072 | Q47: =Q46/M46-1 -> 0.621986 | R47: =R46/N46-1 -> 0.44509324 | S47: =S46/O46-1 -> -0.24127907 | T47: =T46/P46-1 -> -0.74326059 | U47: =U46/Q46-1 -> -0.97538363 | V47: =V46/R46-1 -> -0.92022941 | W47: =W46/S46-1 -> -0.70478927 | X47: =X46/T46-1 -> 0.99 | ... AG47: =AG46/AC46-1 -> 2.8384251
B48: % margin | C48: =+C46/C7 -> 0.67400063 | D48: =+D46/D7 -> 0.41684677 | E48: =+E46/E7 -> 0.46403781 | F48: =+F46/F7 -> 0.53623684 | G48: =+G46/G7 -> 0.46945907 | H48: =+H46/H7 -> 0.17973053 | I48: =+I46/I7 -> 0.54406088 | J48: =+J46/J7 -> 0.6288944 | K48: =+K46/K7 -> 0.69396842 | M48: =+M46/M7 -> 0.45407519 | N48: =+N46/N7 -> 0.5143547 | O48: =+O46/O7 -> 0.5827879 | P48: =+P46/P7 -> 0.5664718 | Q48: =+Q46/Q7 -> 0.51465767 | R48: =+R46/R7 -> 0.5554992 | S48: =+S46/S7 -> 0.47528504 | T48: =+T46/T7 -> 0.23461845 | ... AG48: =+AG46/AG7 -> 0.78620995
B50: Capex sales | C50: =-C59/C7 -> 0.39323442 | D50: =-D59/D7 -> 0.51374685 | E50: =-E59/E7 -> 0.31377561 | F50: =-F59/F7 -> 0.28854261 | G50: =-G59/G7 -> 0.41877827 | H50: =-H59/H7 -> 0.20708573 | I50: =-I59/I7 -> 0.24018276 | J50: =-J59/J7 -> 0.28178109 | K50: =-K59/K7 -> 0.2178813 | M50: =-M59/M7 -> 0.46905767 | N50: =-N59/N7 -> 0.28091614 | O50: =-O59/O7 -> 0.23609356 | P50: =-P59/P7 -> 0.22104164 | Q50: =-Q59/Q7 -> 0.42881588 | R50: =-R59/R7 -> 0.33045534 | S50: =-S59/S7 -> 0.43538969 | T50: =-T59/T7 -> 0.53809128 | ... AG50: =-AG59/AG7 -> 0.1453642
B51: WC SALES | C51: =C55/C7 -> -0.056146923 | D51: =D55/D7 -> 0.040180902 | E51: =E55/E7 -> -0.048812903 | F51: =F55/F7 -> -0.079545038 | G51: =G55/G7 -> -0.060713398 | H51: =H55/H7 -> 0.021783041 | I51: =I55/I7 -> -0.070344384 | J51: =J55/J7 -> -0.059494707 | K51: =K55/K7 -> -0.17292883 | M51: =M55/M7 -> -0.014361231 | N51: =N55/N7 -> -0.12383247 | O51: =O55/O7 -> -0.087092993 | P51: =P55/P7 -> -0.080147559 | Q51: =Q55/Q7 -> -0.02581153 | R51: =R55/R7 -> -0.12330707 | S51: =S55/S7 -> -0.14631914 | T51: =T55/T7 -> 0.11921602 | ... AG51: =AG55/AG7 -> -0.3089093
B53: CASH FLOW | C53: =C3 -> 43465 | D53: =D3 -> 43830 | E53: =E3 -> 44196 | F53: =F3 -> 44561 | G53: =G3 -> 44926 | H53: =H3 -> 45291 | I53: =I3 -> 45657 | J53: =J3 -> 46022 | K53: =K2 -> LTM | M53: =M3 -> 44286 | N53: =N3 -> 44377 | O53: =O3 -> 44469 | P53: =P3 -> 44561 | Q53: =Q3 -> 44651 | R53: =R3 -> 44742 | S53: =S3 -> 44834 | T53: =T3 -> 44926 | ... AG53: =AG3 -> 46112
B54: Adj. EBITDA | C54: =C46 -> 27260000 | D54: =D46 -> 11251000 | E54: =E46 -> 14803000 | F54: =F46 -> 23057000 | G54: =G46 -> 20948000 | H54: =H46 -> 5889000 | I54: =I46 -> 36013000 | J54: =J46 -> 61095000 | K54: =K46 -> 91662000 | M54: =M46 -> 3857000 | N54: =N46 -> 5309000 | O54: =O46 -> 6880000 | P54: =F54-SUM(M54:O54) -> 7011000 | Q54: =Q46 -> 6256000 | R54: =R46 -> 7672000 | S54: =S46 -> 5220000 | T54: =G54-SUM(Q54:S54) -> 1800000 | U54: =U46 -> 154000 | V54: =V46 -> 612000 | W54: =W46 -> 1541000 | X54: =H54-SUM(U54:W54) -> 3582000 | Y54: =Y46 -> 6073000 | Z54: =Z46 -> 8591000 | AA54: =AA46 -> 10100000 | AB54: =AB46 -> 11249000 | AC54: =AC46 -> 10769000 | AD54: =AD46 -> 12645000 | AE54: =AE46 -> 14949000 | AF54: =AF46 -> 22732000 | AG54: =AG46 -> 41336000
B55: Working Capital | C55: =-547255-1782384+58773 -> -2270866 | D55: =2214776-851735-278529 -> 1084512 | E55: =-935346-843842+222036 -> -1557152 | F55: =-2525722-696559-197980 -> -3420261 | G55: =3341986-6572069+520956 -> -2709127 | H55: =-1406188+2288020-168095 -> 713737 | I55: =-5098005+166722+274980 -> -4656303 | J55: =-5584225-1059484+863996 -> -5779713 | K55: =SUM(AD55:AG55) -> -22841101 | M55: =-129043-11858+18914 -> -121987 | N55: =-1268426-40514-91205-M55 -> -1278158 | O55: =-1774620-355758-297928-M55-N55 -> -1028161 | P55: =F55-SUM(M55:O55) -> -991955 | Q55: =300388-1397850+783706 -> -313756 | R55: =-705759-2682503+1371512-Q55 -> -1702994 | S55: =203143-4970105+1143206-Q55-R55 -> -1607006 | T55: =G55-SUM(Q55:S55) -> 914629 | U55: =1202610-1341656-595231 -> -734277 | V55: =847083-628154-262533-U55 -> 690673 | W55: =-15552+939085-227937-U55-V55 -> 739200 | X55: =H55-SUM(U55:W55) -> 18141 | Y55: =-210897-192079-256934 -> -659910 | Z55: =-3023590+196212+179435-Y55 -> -1988033 | AA55: =-3735567+178175+33141-Y55-Z55 -> -876308 | AB55: =I55-SUM(Y55:AA55) -> -1132052 | AC55: =2426173-1235634-370455 -> 820084 | AD55: =-1049365-311353-62653-AC55 -> -2243455 | AE55: =-1876556+213537+200659-AC55-AD55 -> -38989 | AF55: =J55-SUM(AC55:AE55) -> -4317353 | AG55: =-13177522-1435500-1628282 -> -16241304
B56: Taxes | C56: -3568370 | D56: -5153218 | E56: -370635 | F56: -1014908 | G56: -3979355 | H56: -1383942 | I56: -552088 | J56: -5891155 | K56: =SUM(AD56:AG56) -> -7757943 | M56: -251222 | N56: =-635646-M56 -> -384424 | O56: =-893776-M56-N56 -> -258130 | P56: =F56-SUM(M56:O56) -> -121132 | Q56: -274957 | R56: =-2402414-Q56 -> -2127457 | S56: =-2910028-Q56-R56 -> -507614 | T56: =G56-SUM(Q56:S56) -> -1069327 | U56: -502283 | V56: =-1095145-U56 -> -592862 | W56: =-1214229-U56-V56 -> -119084 | X56: =H56-SUM(U56:W56) -> -169713 | Y56: -55025 | Z56: =-141107-Y56 -> -86082 | AA56: =-266689-Y56-Z56 -> -125582 | AB56: =I56-SUM(Y56:AA56) -> -285399 | AC56: -1421386 | AD56: =-3250301-AC56 -> -1828915 | AE56: =-4567175-AC56-AD56 -> -1316874 | AF56: =J56-SUM(AC56:AE56) -> -1323980 | AG56: -3288174
B57: Cash interest paid | C57: -126029 | D57: -238314 | E57: -288565 | F57: -240942 | G57: -494513 | H57: -1261540 | I57: -1276564 | J57: -938849 | K57: =SUM(AD57:AG57) -> -974782 | M57: -56133 | N57: =-105068-M57 -> -48935 | O57: =-187335-M57-N57 -> -82267 | P57: =F57-SUM(M57:O57) -> -53607 | Q57: -95412 | R57: =-182167-Q57 -> -86755 | S57: =-312697-Q57-R57 -> -130530 | T57: =G57-SUM(Q57:S57) -> -181816 | U57: -214216 | V57: =-512759-U57 -> -298543 | W57: =-90531-U57-V57 -> 422228 | X57: =H57-SUM(U57:W57) -> -1171009 | Y57: -416279 | Z57: =-710309-Y57 -> -294030 | AA57: =-1070846-Y57-Z57 -> -360537 | AB57: =I57-SUM(Y57:AA57) -> -205718 | AC57: -319264 | AD57: =-494127-AC57 -> -174863 | AE57: =-808963-AC57-AD57 -> -314836 | AF57: =J57-SUM(AC57:AE57) -> -129886 | AG57: -355197
B58: Net cash from operations | C58: =SUM(C54:C57) -> 21294735 | D58: =SUM(D54:D57) -> 6943980 | E58: =SUM(E54:E57) -> 12586648 | F58: =SUM(F54:F57) -> 18380889 | G58: =SUM(G54:G57) -> 13765005 | H58: =SUM(H54:H57) -> 3957255 | I58: =SUM(I54:I57) -> 29528045 | J58: =SUM(J54:J57) -> 48485283 | K58: =SUM(K54:K57) -> 60088174 | M58: =SUM(M54:M57) -> 3427658 | N58: =SUM(N54:N57) -> 3597483 | O58: =SUM(O54:O57) -> 5511442 | P58: =SUM(P54:P57) -> 5844306 | Q58: =SUM(Q54:Q57) -> 5571875 | R58: =SUM(R54:R57) -> 3754794 | S58: =SUM(S54:S57) -> 2974850 | T58: =SUM(T54:T57) -> 1463486 | ... AG58: =SUM(AG54:AG57) -> 21451325
B59: Net Capex | C59: =-16036146+131754 -> -15904392 | D59: =-13920244+53840 -> -13866404 | E59: =-10068662+59089 -> -10009573 | F59: =-12486635+79940 -> -12406695 | G59: =-19010261+323718 -> -18686543 | H59: =1539825-8325138 -> -6785313 | I59: =47126-15945534 -> -15898408 | J59: =144828-27518924 -> -27374096 | K59: =SUM(AD59:AG59) -> -28778594 | M59: =-4105305+121041 -> -3984264 | N59: =-6919550+35762-M59 -> -2899524 | O59: =-9732259+61310-M59-N59 -> -2787161 | P59: =F59-SUM(M59:O59) -> -2735746 | Q59: =-5236776+24239 -> -5212537 | R59: =-10069382+292926-Q59 -> -4563919 | S59: =-14873038+314748-Q59-R59 -> -4781834 | T59: =G59-SUM(Q59:S59) -> -4128253 | U59: =-3152150+5501 -> -3146649 | V59: =-5085936+9583-U59 -> -1929704 | W59: =-6599521+1388014-U59-V59 -> -135154 | X59: =H59-SUM(U59:W59) -> -1573806 | Y59: =-3102847+8597 -> -3094250 | Z59: =-5166120-Y59 -> -2071870 | AA59: =-8672460+20734-Y59-Z59 -> -3485606 | AB59: =I59-SUM(Y59:AA59) -> -7246682 | AC59: =-6284222+46010 -> -6238212 | AD59: =-10615739+75170-AC59 -> -4302357 | AE59: =-15648350+106445-AC59-AD59 -> -5001336 | AF59: =J59-SUM(AC59:AE59) -> -11832191 | AG59: =-7657403+14693 -> -7642710
B60: Purchase of intangible assets | C60: =-933139+2532 -> -930607 | D60: =-673356+183 -> -673173 | E60: =-800729+695 -> -800034 | F60: =-973893+2073 -> -971820 | G60: =-738621+1018 -> -737603 | H60: =-454710+484 -> -454226 | I60: =19703-717106 -> -697403 | J60: =2142-1060419 -> -1058277 | K60: =SUM(AD60:AG60) -> -1095775 | M60: =-249601+2029 -> -247572 | N60: =-557684-M60 -> -310112 | O60: =-731064+2073-M60-N60 -> -171307 | P60: =F60-SUM(M60:O60) -> -242829 | Q60: =-198150+3 -> -198147 | R60: =-344591+1016-Q60 -> -145428 | S60: =-521587+1016-Q60-R60 -> -176996 | T60: =G60-SUM(Q60:S60) -> -217032 | U60: =-164783+272 -> -164511 | V60: =-261813+286-U60 -> -97016 | W60: =-352682+1016-U60-V60 -> -90139 | X60: =H60-SUM(U60:W60) -> -102560 | Y60: =-105895+214 -> -105681 | Z60: =-257639-Y60 -> -151958 | AA60: =-525650+19532-Y60-Z60 -> -248479 | AB60: =I60-SUM(Y60:AA60) -> -191285 | AC60: -170465 | AD60: =-460437-AC60 -> -289972 | AE60: =-685237+2137-AC60-AD60 -> -222663 | AF60: =J60-SUM(AC60:AE60) -> -375177 | AG60: -207963
B61: Disposals/ Acquistion, of subsidiaries, businesses | C61: 0 | D61: -2462 | E61: 0 | F61: -7250087 | G61: -1027663 | H61: 0 | I61: 0 | J61: -3079783 | K61: =SUM(AD61:AG61) -> -3079783 | M61: 0 | N61: =0-M61 -> 0 | O61: =0-M61-N61 -> 0 | P61: =F61-SUM(M61:O61) -> -7250087 | Q61: -602475 | R61: =-602475-Q61 -> 0 | S61: =-1027663-Q61-R61 -> -425188 | T61: =G61-SUM(Q61:S61) -> 0 | U61: 0 | V61: =0-U61 -> 0 | W61: =0-U61-V61 -> 0 | X61: =H61-SUM(U61:W61) -> 0 | Y61: 0 | Z61: =0-Y61 -> 0 | AA61: =0-Y61-Z61 -> 0 | AB61: =I61-SUM(Y61:AA61) -> 0 | AC61: 0 | AD61: =0-AC61 -> 0 | AE61: =-3079783-AC61-AD61 -> -3079783 | AF61: =J61-SUM(AC61:AE61) -> 0 | AG61: 0
B62: Free cash flow | C62: =SUM(C58:C61) -> 4459736 | D62: =SUM(D58:D61) -> -7598059 | E62: =SUM(E58:E61) -> 1777041 | F62: =SUM(F58:F61) -> -2247713 | G62: =SUM(G58:G61) -> -6686804 | H62: =SUM(H58:H61) -> -3282284 | I62: =SUM(I58:I61) -> 12932234 | J62: =SUM(J58:J61) -> 16973127 | K62: =SUM(K58:K61) -> 27134022 | M62: =SUM(M58:M61) -> -804178 | N62: =SUM(N58:N61) -> 387847 | O62: =SUM(O58:O61) -> 2552974 | P62: =SUM(P58:P61) -> -4384356 | Q62: =SUM(Q58:Q61) -> -441284 | R62: =SUM(R58:R61) -> -954553 | S62: =SUM(S58:S61) -> -2409168 | T62: =SUM(T58:T61) -> -2881799 | ... AG62: =SUM(AG58:AG61) -> 13600652
B63: Other Investing | C63: =-21428749-C59-C60-C61 -> -4593750 | D63: =-10450936-D59-D60-D61 -> 4091103 | E63: =-11840393-E59-E60-E61 -> -1030786 | F63: =-22392277-F59-F60-F61 -> -1763675 | G63: =-17883746-G59-G60-G61 -> 2568063 | H63: =-7334727-H59-H60-H61 -> -95188 | I63: =-18004637-I59-I60-I61 -> -1408826 | J63: =6513772-18804330-4552604+32880-178331+1233030-33956+115091-1105649+16875-9000+85216+144911 -> -16542095 | K63: =SUM(AD63:AG63) -> -24516510 | M63: =-5885210-M59-M60-M61 -> -1653374 | N63: =-9369519-N59-N60-N61-M63-M59-M60-M61 -> -274673 | O63: =-15720484-O59-O60-O61-N63-M63-M59-N59-M60-N60-M61-N61 -> -3392497 | P63: =F63-SUM(M63:O63) -> 3556869 | Q63: =-5455618-Q59-Q60-Q61 -> 557541 | R63: =-9928894-R59-R60-R61-Q63-Q59-Q60-Q61 -> 236071 | S63: =-14575625-S59-S60-S61-R63-Q63-Q59-R59-Q60-R60-Q61-R61 -> 737287 | T63: =G63-SUM(Q63:S63) -> 1037164 | U63: =-3127223-U59-U60-U61 -> 183937 | V63: =-5350919-V59-V60-V61-U63-U59-U60-U61 -> -196976 | W63: =-5694904-W59-W60-W61-V63-U63-U59-V59-U60-V60-U61-V61 -> -118692 | X63: =H63-SUM(U63:W63) -> 36543 | Y63: =-3797325-Y59-Y60-Y61 -> -597394 | Z63: =-5774579-Z59-Z60-Z61-Y63-Y59-Y60-Y61 -> 246574 | AA63: =-9391319-AA59-AA60-AA61-Z63-Y63-Y59-Z59-Y60-Z60-Y61-Z61 -> 117345 | AB63: =I63-SUM(Y63:AA63) -> -1175351 | AC63: =-8218488-AC59-AC60-AC61 -> -1809811 | AD63: =-18669943-AD59-AD60-AD61-AC63-AC59-AC60-AC61 -> -5859126 | AE63: =-32914535-AE59-AE60-AE61-AD63-AC63-AC59-AD59-AC60-AD60-AC61-AD61 -> -5940810 | AF63: =J63-SUM(AC63:AE63) -> -2932348 | AG63: =-17634899-AG59-AG60-AG61 -> -9784226
B64: Equity Issuance | C64: -1736514 | D64: 0 | E64: 0 | F64: 0 | G64: 0 | H64: 0 | I64: 0 | J64: 0 | K64: =SUM(AD64:AG64) -> 0 | M64: 0 | N64: =0-M64 -> 0 | O64: =0-M64-N64 -> 0 | P64: =F64-SUM(M64:O64) -> 0 | Q64: 0 | R64: =0-Q64 -> 0 | S64: =0-Q64-R64 -> 0 | T64: =G64-SUM(Q64:S64) -> 0 | U64: 0 | V64: =0-U64 -> 0 | W64: =0-U64-V64 -> 0 | X64: =H64-SUM(U64:W64) -> 0 | Y64: 0 | Z64: =0-Y64 -> 0 | AA64: =0-Y64-Z64 -> 0 | AB64: =I64-SUM(Y64:AA64) -> 0 | AC64: 0 | AD64: =0-AC64 -> 0 | AE64: =0-AC64-AD64 -> 0 | AF64: =J64-SUM(AC64:AE64) -> 0 | AG64: 0
B65: Dividends | C65: -706002 | D65: -1026003 | E65: -684002 | F65: -805024 | G65: -1680905 | H65: -825575 | I65: -826323 | J65: -1681166 | K65: =SUM(AD65:AG65) -> -1681166 | M65: 0 | N65: =-800282-M65 -> -800282 | O65: =-800282-M65-N65 -> 0 | P65: =F65-SUM(M65:O65) -> -4742 | Q65: 0 | R65: =-1268314-Q65 -> -1268314 | S65: =-1474610-Q65-R65 -> -206296 | T65: =G65-SUM(Q65:S65) -> -206295 | U65: 0 | V65: =-412712-U65 -> -412712 | W65: =-619140-U65-V65 -> -206428 | X65: =H65-SUM(U65:W65) -> -206435 | Y65: 0 | Z65: =-413026-Y65 -> -413026 | AA65: =-619611-Y65-Z65 -> -206585 | AB65: =I65-SUM(Y65:AA65) -> -206712 | AC65: 0 | AD65: =-1159114-AC65 -> -1159114 | AE65: =-1418035-AC65-AD65 -> -258921 | AF65: =J65-SUM(AC65:AE65) -> -263131 | AG65: 0
B66: Net Change in debt | C66: =3125721-2078522 -> 1047199 | D66: =9833882-4585425-390501 -> 4857956 | E66: =5173016-3921310-319740 -> 931966 | F66: =8933737-3320911-323975 -> 5288851 | G66: =11917454-7124565-301858 -> 4491031 | H66: =20657967-13689433-461466 -> 6507068 | I66: =8717964-16093621-601821 -> -7977478 | J66: =8183735-7416131-596465 -> 171139 | K66: =SUM(AD66:AG66) -> -3223707 | M66: =2906972-923048 -> 1983924 | N66: =4890763-2660327-M66 -> 246512 | O66: =5428149-3073321-M66-N66 -> 124392 | P66: =F66-SUM(M66:O66) -> 2934023 | Q66: =922151-677449-69386 -> 175316 | R66: =3828515-3170775-139869-Q66 -> 342555 | S66: =6392515-4611893-212727-Q66-R66 -> 1050024 | T66: =G66-SUM(Q66:S66) -> 2923136 | U66: =8346550-3288195-80020 -> 4978335 | V66: =13677699-6035603-164903-U66 -> 2498858 | W66: =17747887-9446375-283185-U66-V66 -> 541134 | X66: =H66-SUM(U66:W66) -> -1511259 | Y66: =4068545-4849086-160769 -> -941310 | Z66: =6076256-10460595-309886-Y66 -> -3752915 | AA66: =7640162-14425050-458392-Y66-Z66 -> -2549055 | AB66: =I66-SUM(Y66:AA66) -> -734198 | AC66: =2111363-1466432-151657 -> 493274 | AD66: =3175749-3014365-301734-AC66 -> -633624 | AE66: =6018271-4099968-446955-AC66-AD66 -> 1611698 | AF66: =J66-SUM(AC66:AE66) -> -1300209 | AG66: =1006250-3760030-147792 -> -2901572
B67: Other financing activities | C67: 0 | D67: 4715 | E67: 4090 | F67: =8484+2 -> 8486 | G67: =11653+17 -> 11670 | H67: =24519+53-9220 -> 15352 | I67: =93829+6032 -> 99861 | J67: 65035 | K67: =SUM(AD67:AG67) -> -492 | M67: -83452 | N67: =-164451+3567-M67 -> -77432 | O67: =-243808+7574-M67-N67 -> -75350 | P67: =F67-SUM(M67:O67) -> 244720 | Q67: 0 | R67: =6516+3-Q67 -> 6519 | S67: =3+9518-Q67-R67 -> 3002 | T67: =G67-SUM(Q67:S67) -> 2149 | U67: =3041 -> 3041 | V67: =7040-13575-U67 -> -9576 | W67: =53+12737-13575-U67-V67 -> 5750 | X67: =H67-SUM(U67:W67) -> 16137 | Y67: 31640 | Z67: =73032+1315-Y67 -> 42707 | AA67: =1315+87836-Y67-Z67 -> 14804 | AB67: =I67-SUM(Y67:AA67) -> 10710 | AC67: 15620 | AD67: =28560+8-AC67 -> 12948 | AE67: =50666+8-AC67-AD67 -> 22106 | AF67: =J67-SUM(AC67:AE67) -> 14361 | AG67: =7775-57682 -> -49907
B68: Cash flow after financing activities | C68: =SUM(C62:C67) -> -1529331 | D68: =SUM(D62:D67) -> 329712 | E68: =SUM(E62:E67) -> 998309 | F68: =SUM(F62:F67) -> 480925 | G68: =SUM(G62:G67) -> -1296945 | H68: =SUM(H62:H67) -> 2319373 | I68: =SUM(I62:I67) -> 2819468 | J68: =SUM(J62:J67) -> -1013960 | K68: =SUM(K62:K67) -> -2287853 | M68: =SUM(M62:M67) -> -557080 | N68: =SUM(N62:N67) -> -518028 | O68: =SUM(O62:O67) -> -790481 | P68: =SUM(P62:P67) -> 2346514 | Q68: =SUM(Q62:Q67) -> 291573 | R68: =SUM(R62:R67) -> -1637722 | S68: =SUM(S62:S67) -> -825151 | T68: =SUM(T62:T67) -> 874355 | ... AG68: =SUM(AG62:AG67) -> 864947
B69: Balancing figure | C69: =-600672-C68 -> 928659 | D69: =-43249-D68 -> -372961 | E69: =669919-E68 -> -328390 | F69: =2081993-F68 -> 1601068 | G69: =-80975-G68 -> 1215970 | H69: =2610322-H68 -> 290949 | I69: =3617788-I68 -> 798320 | J69: =3718649-J68 -> 4732609 | K69: =SUM(AD69:AG69) -> 10896688 | M69: =-749845-M68 -> -192765 | N69: =-309638-N68-M68-M69 -> 958235 | O69: =-214012-O68-M68-N68-M69-N69 -> 886107 | P69: =F69-SUM(M69:O69) -> -50509 | Q69: =-75218-Q68 -> -366791 | R69: =-511670-R68-Q68-Q69 -> 1201270 | S69: =-338765-S68-Q68-R68-Q69-R69 -> 998056 | T69: =G69-SUM(Q69:S69) -> -616565 | U69: =-82225-U68 -> -639602 | V69: =1063803-V68-U68-U69 -> 881886 | W69: =2145299-W68-U68-V68-U69-V69 -> -1498319 | X69: =H69-SUM(U69:W69) -> 1546984 | Y69: =794066-Y68 -> 559275 | Z69: =346500-Z68-Y68-Y69 -> -569933 | AA69: =1548359-AA68-Y68-Z68-Y69-Z69 -> -1178138 | AB69: =I69-SUM(Y69:AA69) -> 1987116 | AC69: =1352952-AC68 -> -785888 | AD69: =-2129806-AD68-AC68-AC69 -> 350720 | AE69: =-390602-AE68-AC68-AD68-AC69-AD69 -> 1330612 | AF69: =J69-SUM(AC69:AE69) -> 3837165 | AG69: =6243138-AG68 -> 5378191
B70: FX | C70: -3805 | D70: 21283 | E70: -56313 | F70: 184309 | G70: 200458 | H70: -29987 | I70: 530480 | J70: -155234 | K70: =SUM(AD70:AG70) -> 305288 | M70: 28131 | N70: =33876-M70 -> 5745 | O70: =164736-M70-N70 -> 130860 | P70: =F70-SUM(M70:O70) -> 19573 | Q70: 63856 | R70: =446255-Q70 -> 382399 | S70: =538334-Q70-R70 -> 92079 | T70: =G70-SUM(Q70:S70) -> -337876 | U70: 69110 | V70: =50825-U70 -> -18285 | W70: =116518-U70-V70 -> 65693 | X70: =H70-SUM(U70:W70) -> -146505 | Y70: 144583 | Z70: =221381-Y70 -> 76798 | AA70: =43502-Y70-Z70 -> -177879 | AB70: =I70-SUM(Y70:AA70) -> 486978 | AC70: 38875 | AD70: =-332862-AC70 -> -371737 | AE70: =-91444-AC70-AD70 -> 241418 | AF70: =J70-SUM(AC70:AE70) -> -63790 | AG70: 499397
B71: Classification as held for sale | F71: 0 | G71: 0 | H71: 0 | I71: 0 | J71: 0 | K71: =SUM(AD71:AG71) -> 0 | U71: 0 | V71: 0 | W71: 0 | X71: =H71-SUM(U71:W71) -> 0 | Y71: 0 | Z71: =-82899-Y71 -> -82899 | AA71: =-104847-Z71-Y71 -> -21948 | AB71: =I71-SUM(Y71:AA71) -> 104847 | AC71: 0 | AD71: =-45946-AC71 -> -45946 | AE71: =0-AD71-AC71 -> 45946 | AF71: =J71-SUM(AC71:AE71) -> 0 | AG71: 0
B72: Net change in cash | C72: =C68+C69 -> -600672 | D72: =D68+D69 -> -43249 | E72: =E68+E69 -> 669919 | F72: =F68+F69 -> 2081993 | G72: =G68+G69 -> -80975 | H72: =H68+H69 -> 2610322 | I72: =I68+I69 -> 3617788 | J72: =J68+J69 -> 3718649 | K72: =K68+K69 -> 8608835 | M72: =M68+M69 -> -749845 | N72: =N68+N69 -> 440207 | O72: =O68+O69 -> 95626 | P72: =P68+P69 -> 2296005 | Q72: =Q68+Q69 -> -75218 | R72: =R68+R69 -> -436452 | S72: =S68+S69 -> 172905 | T72: =T68+T69 -> 257790 | ... AG72: =AG68+AG69 -> 6243138
B73: Cash and cash equivalents | C73: =2949991+C72 -> 2349319 | D73: =C73+D72 -> 2306070 | E73: =D73+E72 -> 2975989 | F73: =E73+F72 -> 5057982 | G73: =F73+G72 -> 4977007 | H73: =G73+H72 -> 7587329 | I73: =H73+I72 -> 11205117 | J73: =I73+J72 -> 14923766 | K73: =AC73+K72 -> 21166904 | M73: =2975989+M72 -> 2226144 | N73: =M73+N72 -> 2666351 | O73: =N73+O72 -> 2761977 | P73: =O73+P72 -> 5057982 | Q73: =P73+Q72 -> 4982764 | R73: =Q73+R72 -> 4546312 | S73: =R73+S72 -> 4719217 | T73: =S73+T72 -> 4977007 | U73: =T73+U72 -> 4894782 | ... AG73: =AF73+AG72 -> 21166904
B75: check 1 | C75: =+C73-C115 -> 0 | D75: =+D73-D115 -> 0 | E75: =+E73-E115 -> 0 | F75: =+F73-F115 -> 0 | G75: =+G73-G115 -> 0 | H75: =+H73-H115 -> 0 | I75: =+I73-I115 -> 0 | J75: =+J73-J115 -> 0 | K75: =+K73-K115 -> 0 | M75: =+M73-M115 -> 0 | N75: =+N73-N115 -> 0 | O75: =+O73-O115 -> 0 | P75: =+P73-P115 -> 0 | Q75: =+Q73-Q115 -> 0 | R75: =+R73-R115 -> 0 | S75: =+S73-S115 -> 0 | T75: =+T73-T115 -> 0 | ... AG75: =+AG73-AG115 -> 0
B76: check 2 | C76: =22227199-C69-C58+C70 -> 0 | D76: =6549736-D69-D58+D70 -> 0 | E76: =12314571-E69-E58+E70 -> 0 | F76: =19797648-F69-F58+F70 -> 0 | G76: =14780517-G69-G58+G70 -> 0 | H76: =4278191-H69-H58+H70 -> 0 | I76: =29795885-I69-I58+I70 -> 0 | J76: =53373126-J69-J58+J70 -> 0 | M76: =3206762-M69-M58+M70 -> 0 | N76: =7756735-N69-N58+N70-M58-M69+M70 -> 0 | O76: =14023424-O69-O58+O70-N58-N69+N70-M58-M69+M70 -> 0 | Q76: =5141228-Q69-Q58+Q70 -> 0 | R76: =9714893-R69-R58+R70-Q58-Q69+Q70 -> 0 | S76: =13595720-S69-S58+S70-R58-R69+R70-Q58-Q69+Q70 -> 0 | U76: =-2005488-U69-U58+U70 -> 0 | V76: =-694049-V69-U69-V58-U58+V70+U70 -> 0 | W76: =325283-W69-W58+W70-V58-V69+V70-U58-U69+U70 -> 0 | Y76: =5356478-Y69-Y58+Y70 -> 0 | Z76: =11015501-Z69-Y69-Z58-Y58+Z70+Y70+Z71+Y71 -> 0 | AA76: =18774763-AA69-AA58+AA70-Z58-Z69+Z70-Y58-Y69+Y70+AA71+Z71+Y71 -> 0 | AC76: =9023671-AC69-AC58+AC70 -> 0 | AD76: =18189841-AD69-AC69-AD58-AC58+AD70+AC70+AD71+AC71 -> 0 | AE76: =32511390-AE69-AE58+AE70-AD58-AD69+AD70-AC58-AC69+AC70+AE71+AD71+AC71 -> 0 | AG76: =26330119-AG69-AG58+AG70 -> 0
B78: LTM | C78: =C3 -> 43465 | D78: =D3 -> 43830 | E78: =E3 -> 44196 | F78: =F3 -> 44561 | G78: =G3 -> 44926 | H78: =H3 -> 45291 | I78: =I3 -> 45657 | J78: =J3 -> 46022 | K78: =K2 -> LTM | M78: =M3 -> 44286 | N78: =N3 -> 44377 | O78: =O3 -> 44469 | P78: =P3 -> 44561 | Q78: =Q3 -> 44651 | R78: =R3 -> 44742 | S78: =S3 -> 44834 | T78: =T3 -> 44926 | ... AG78: =AG3 -> 46112
B79: =B7 -> Revenue | C79: =C7 -> 40445066 | D79: =D7 -> 26990733 | E79: =E7 -> 31900418 | F79: =F7 -> 42997792 | G79: =G7 -> 44621568 | H79: =H7 -> 32765719 | I79: =I7 -> 66192960 | ... K79: =K7 -> 132083821 | P79: =SUM(M7:P7) -> 42997792 | Q79: =SUM(N7:Q7) -> 46659257 | R79: =SUM(O7:R7) -> 50148587 | S79: =SUM(P7:S7) -> 49326146 | T79: =SUM(Q7:T7) -> 44621568 | U79: =SUM(R7:U7) -> 37554026 | V79: =SUM(S7:V7) -> 31048958 | W79: =SUM(T7:W7) -> 29132246 | ... AG79: =SUM(AD7:AG7) -> 132083821
B80: Operating profit | C80: =C14 -> 20843750 | D80: =D14 -> 2719179 | E80: =E14 -> 5012624 | F80: =F14 -> 12410340 | G80: =G14 -> 6809417 | H80: =H14 -> -7730313 | I80: =I14 -> 23467319 | J80: =J14 -> 47206319 | K80: =K14 -> 77376098 | P80: =SUM(M14:P14) -> 12410340 | Q80: =SUM(N14:Q14) -> 13949816 | R80: =SUM(O14:R14) -> 15452468 | S80: =SUM(P14:S14) -> 12941170 | T80: =SUM(Q14:T14) -> 6809417 | U80: =SUM(R14:U14) -> 543218 | V80: =SUM(S14:V14) -> -6536092 | W80: =SUM(T14:W14) -> -9988576 | ... AG80: =SUM(AD14:AG14) -> 77376098
B81: EBITDA | C81: =+C41 -> 27152820 | D81: =+D41 -> 11324671 | E81: =+E41 -> 14777400 | F81: =+F41 -> 23057227 | G81: =+G41 -> 20944709 | H81: =+H41 -> 5888848 | I81: =+I41 -> 36012086 | J81: =+J41 -> 61095958 | K81: =+K41 -> 91657574 | P81: =SUM(M41:P41) -> 23057227 | Q81: =SUM(N41:Q41) -> 25455412 | R81: =SUM(O41:R41) -> 27821713 | S81: =SUM(P41:S41) -> 26154974 | T81: =SUM(Q41:T41) -> 20944709 | U81: =SUM(R41:U41) -> 14843714 | V81: =SUM(S41:V41) -> 7779713 | W81: =SUM(T41:W41) -> 4107094 | ... AG81: =SUM(AD41:AG41) -> 91657574
B82: Adjusted EBITDA | C82: =+C46 -> 27260000 | D82: =+D46 -> 11251000 | E82: =+E46 -> 14803000 | F82: =+F46 -> 23057000 | G82: =+G46 -> 20948000 | H82: =+H46 -> 5889000 | I82: =+I46 -> 36013000 | J82: =+J46 -> 61095000 | K82: =+K46 -> 91662000 | P82: =SUM(M46:P46) -> 23057000 | Q82: =SUM(N46:Q46) -> 25456000 | R82: =SUM(O46:R46) -> 27819000 | S82: =SUM(P46:S46) -> 26159000 | T82: =SUM(Q46:T46) -> 20948000 | U82: =SUM(R46:U46) -> 14846000 | V82: =SUM(S46:V46) -> 7786000 | W82: =SUM(T46:W46) -> 4107000 | ... AG82: =SUM(AD46:AG46) -> 91662000
B83: Cash interest paid | C83: =-C57 -> 126029 | D83: =-D57 -> 238314 | E83: =-E57 -> 288565 | F83: =-F57 -> 240942 | G83: =-G57 -> 494513 | H83: =-H57 -> 1261540 | I83: =-I57 -> 1276564 | J83: =-J57 -> 938849 | K83: =-K57 -> 974782 | P83: =-SUM(M57:P57) -> 240942 | Q83: =-SUM(N57:Q57) -> 280221 | R83: =-SUM(O57:R57) -> 318041 | S83: =-SUM(P57:S57) -> 366304 | T83: =-SUM(Q57:T57) -> 494513 | U83: =-SUM(R57:U57) -> 613317 | V83: =-SUM(S57:V57) -> 825105 | W83: =-SUM(T57:W57) -> 272347 | ... AG83: =-SUM(AD57:AG57) -> 974782
B84: Net Income | C84: =+C22 -> 15539984 | D84: =+D22 -> 2009078 | E84: =+E22 -> 4758914 | F84: =+F22 -> 9616188 | G84: =+G22 -> 2241669 | H84: =+H22 -> -9137547 | I84: =+I22 -> 19796902 | J84: =+J22 -> 42947902 | K84: =+K22 -> 75185616 | P84: =SUM(M22:P22) -> 9616188 | Q84: =SUM(N22:Q22) -> 10610758 | R84: =SUM(O22:R22) -> 11503764 | S84: =SUM(P22:S22) -> 9296129 | T84: =SUM(Q22:T22) -> 2241669 | U84: =SUM(R22:U22) -> -2331032 | V84: =SUM(S22:V22) -> -8200369 | W84: =SUM(T22:W22) -> -11492685 | ... AG84: =SUM(AD22:AG22) -> 75185616
B85: Capex | C85: =-C59 -> 15904392 | D85: =-D59 -> 13866404 | E85: =-E59 -> 10009573 | F85: =-F59 -> 12406695 | G85: =-G59 -> 18686543 | H85: =-H59 -> 6785313 | I85: =-I59 -> 15898408 | J85: =-J59 -> 27374096 | K85: =-K59 -> 28778594 | P85: =-SUM(M59:P59) -> 12406695 | Q85: =-SUM(N59:Q59) -> 13634968 | R85: =-SUM(O59:R59) -> 15299363 | S85: =-SUM(P59:S59) -> 17294036 | T85: =-SUM(Q59:T59) -> 18686543 | U85: =-SUM(R59:U59) -> 16620655 | V85: =-SUM(S59:V59) -> 13986440 | W85: =-SUM(T59:W59) -> 9339760 | ... AG85: =-SUM(AD59:AG59) -> 28778594
B86: Free cash flow | C86: =+C62 -> 4459736 | D86: =+D62 -> -7598059 | E86: =+E62 -> 1777041 | F86: =+F62 -> -2247713 | G86: =+G62 -> -6686804 | H86: =+H62 -> -3282284 | I86: =+I62 -> 12932234 | J86: =+J62 -> 16973127 | K86: =+K62 -> 27134022 | P86: =SUM(M62:P62) -> -2247713 | Q86: =SUM(N62:Q62) -> -1884819 | R86: =SUM(O62:R62) -> -3227219 | S86: =SUM(P62:S62) -> -8189361 | T86: =SUM(Q62:T62) -> -6686804 | U86: =SUM(R62:U62) -> -10853456 | V86: =SUM(S62:V62) -> -11514355 | W86: =SUM(T62:W62) -> -6747136 | ... AG86: =SUM(AD62:AG62) -> 27134022
B88: BALANCE SHEET | C88: =C3 -> 43465 | D88: =D3 -> 43830 | E88: =E3 -> 44196 | F88: =F3 -> 44561 | G88: =G3 -> 44926 | H88: =H3 -> 45291 | I88: =I3 -> 45657 | J88: =J3 -> 46022 | K88: =K2 -> LTM | M88: =M3 -> 44286 | N88: =N3 -> 44377 | O88: =O3 -> 44469 | P88: =P3 -> 44561 | Q88: =Q3 -> 44651 | R88: =R3 -> 44742 | S88: =S3 -> 44834 | T88: =T3 -> 44926 | ... AG88: =AG3 -> 46112
B90: Tangible fixed assets | C90: =34952617 -> 34952617 | D90: =39949940+1706658 -> 41656598 | E90: =41230562+1707645 -> 42938207 | F90: =53225667+1597344 -> 54823011 | G90: =60228528+1779985 -> 62008513 | H90: =52704853+2694844 -> 55399697 | I90: =60157474+2486871 -> 62644345 | J90: =77502704+2336457 -> 79839161 | K90: =AG90 -> 84405600 | M90: =43328696+1779739 -> 45108435 | N90: =43866891+1644749 -> 45511640 | O90: =44307734+1581465 -> 45889199 | P90: =F90 -> 54823011 | Q90: =55320713+1655699 -> 56976412 | R90: =58113861+1747218 -> 59861079 | S90: =60404219+1758255 -> 62162474 | T90: =G90 -> 62008513 | U90: =59225641+1937844 -> 61163485 | V90: =56597820+1946663 -> 58544483 | W90: =54016964+2683902 -> 56700866 | X90: =H90 -> 55399697 | Y90: =53163891+2715955 -> 55879846 | Z90: =53231992+2509383 -> 55741375 | AA90: =54633704+2474330 -> 57108034 | AB90: =I90 -> 62644345 | AC90: =63015300+2400441 -> 65415741 | AD90: =64472933+2349614 -> 66822547 | AE90: =68145161+2312210 -> 70457371 | AF90: =J90 -> 79839161 | AG90: =82051924+2353676 -> 84405600
B91: Inventory | C91: 4422733 | D91: 5295835 | E91: 6136318 | F91: 8950087 | G91: 15664707 | H91: 13480659 | I91: 13313937 | J91: 14289390 | K91: =AG91 -> 15974133 | M91: 6182597 | N91: 6226651 | O91: 6600336 | P91: =F91 -> 8950087 | Q91: 10392670 | R91: 11878738 | S91: 14664974 | T91: =G91 -> 15664707 | U91: 17182269 | V91: 16420200 | W91: 14947895 | X91: =H91 -> 13480659 | Y91: 13844639 | Z91: 13354938 | AA91: 13353865 | AB91: =I91 -> 13313937 | AC91: 14551350 | AD91: 13408333 | AE91: 13156389 | AF91: =J91 -> 14289390 | AG91: 15974133
B92: Trade accounts receivable | C92: 6319994 | D92: 4261674 | E92: 4931322 | F92: 8267111 | G92: 5186054 | H92: 6600273 | I92: 13019006 | J92: 18199078 | K92: =AG92 -> 33807843 | M92: 5336152 | N92: 6500214 | O92: 7517462 | P92: =F92 -> 8267111 | Q92: 8146418 | R92: 9040032 | S92: 8519642 | T92: =G92 -> 5186054 | U92: 4227451 | V92: 4487069 | W92: 5515297 | X92: =H92 -> 6600273 | Y92: 7178507 | Z92: 10223675 | AA92: 10471229 | AB92: =I92 -> 13019006 | AC92: 10628589 | AD92: 13125210 | AE92: 14312462 | AF92: =J92 -> 18199078 | AG92: 33807843
B93: Trade accounts payable | C93: 1096380 | D93: 1042542 | E93: 1046159 | F93: 1359247 | G93: 2186230 | H93: 1845537 | I93: 2277347 | J93: 2848455 | K93: =AG93 -> 2797840 | M93: 1260162 | N93: 1168771 | O93: 1275837 | P93: =F93 -> 1359247 | Q93: 2292070 | R93: 2926222 | S93: 2476315 | T93: =G93 -> 2186230 | U93: 1745905 | V93: 1882106 | W93: 1916761 | X93: =H93 -> 1845537 | Y93: 1747205 | Z93: 2093222 | AA93: 1889926 | AB93: =I93 -> 2277347 | AC93: 1875167 | AD93: 1862417 | AE93: 2270386 | AF93: =J93 -> 2848455 | AG93: 2797840
B94: Net working capital | C94: =+C91+C92-C93 -> 9646347 | D94: =+D91+D92-D93 -> 8514967 | E94: =+E91+E92-E93 -> 10021481 | F94: =+F91+F92-F93 -> 15857951 | G94: =+G91+G92-G93 -> 18664531 | H94: =+H91+H92-H93 -> 18235395 | I94: =+I91+I92-I93 -> 24055596 | J94: =+J91+J92-J93 -> 29640013 | K94: =+K91+K92-K93 -> 46984136 | M94: =+M91+M92-M93 -> 10258587 | N94: =+N91+N92-N93 -> 11558094 | O94: =+O91+O92-O93 -> 12841961 | P94: =+P91+P92-P93 -> 15857951 | Q94: =+Q91+Q92-Q93 -> 16247018 | R94: =+R91+R92-R93 -> 17992548 | S94: =+S91+S92-S93 -> 20708301 | T94: =+T91+T92-T93 -> 18664531 | ... AG94: =+AG91+AG92-AG93 -> 46984136
B95: % of revenues | C95: =+C94/C79 -> 0.23850491 | D95: =+D94/D79 -> 0.31547743 | E95: =+E94/E79 -> 0.31414889 | F95: =+F94/F79 -> 0.3688085 | G95: =+G94/G79 -> 0.41828496 | H95: =+H94/H79 -> 0.55653883 | I95: =+I94/I79 -> 0.36341623 | J95: =+J94/J79 -> 0.30510579 | K95: =+K94/K79 -> 0.35571454 | P95: =+P94/P79 -> 0.3688085 | Q95: =+Q94/Q79 -> 0.34820567 | R95: =+R94/R79 -> 0.35878475 | S95: =+S94/S79 -> 0.41982402 | T95: =+T94/T79 -> 0.41828496 | U95: =+U94/U79 -> 0.52361403 | V95: =+V94/V79 -> 0.61274723 | W95: =+W94/W79 -> 0.63662894 | ... AG95: =+AG94/AG79 -> 0.35571454
B97: Inventory Days | C97: =IFERROR((C91/-C9)*365,"-") -> 106.33784 | D97: =IFERROR((D91/-D9)*365,"-") -> 102.71528 | E97: =IFERROR((E91/-E9)*365,"-") -> 106.20097 | F97: =IFERROR((F91/-F9)*365,"-") -> 135.85778 | G97: =IFERROR((G91/-G9)*365,"-") -> 197.202 | H97: =IFERROR((H91/-H9)*365,"-") -> 147.76467 | I97: =IFERROR((I91/-I9)*365,"-") -> 141.41171 | J97: =IFERROR((J91/-J9)*365,"-") -> 135.62625 | K97: =IFERROR((K91/-K9)*365,"-") -> 139.43498 | M97: =IFERROR((M91/-M9)*(365/4),"-") -> 97.848977 | N97: =IFERROR((N91/-N9)*(365/4),"-") -> 94.978326 | O97: =IFERROR((O91/-O9)*(365/4),"-") -> 100.81243 | P97: =IFERROR((P91/-P9)*(365/4),"-") -> 129.15319 | Q97: =IFERROR((Q91/-Q9)*(365/4),"-") -> 140.4008 | R97: =IFERROR((R91/-R9)*(365/4),"-") -> 145.04022 | S97: =IFERROR((S91/-S9)*(365/4),"-") -> 188.01769 | T97: =IFERROR((T91/-T9)*(365/4),"-") -> 186.88415 | ... AG97: =IFERROR((AG91/-AG9)*(365/4),"-") -> 133.76678
B98: Receivable Days | C98: =IFERROR((C92/C7)*365,"-") -> 57.035333 | D98: =IFERROR((D92/D7)*365,"-") -> 57.631299 | E98: =IFERROR((E92/E7)*365,"-") -> 56.423478 | F98: =IFERROR((F92/F7)*365,"-") -> 70.177918 | G98: =IFERROR((G92/G7)*365,"-") -> 42.421407 | H98: =IFERROR((H92/H7)*365,"-") -> 73.525005 | I98: =IFERROR((I92/I7)*365,"-") -> 71.789163 | J98: =IFERROR((J92/J7)*365,"-") -> 68.377672 | K98: =IFERROR((K92/K7)*365,"-") -> 93.424483 | M98: =IFERROR((M92/M7)*(365/4),"-") -> 57.324358 | N98: =IFERROR((N92/N7)*(365/4),"-") -> 57.46594 | O98: =IFERROR((O92/O7)*(365/4),"-") -> 58.106699 | P98: =IFERROR((P92/P7)*(365/4),"-") -> 60.95158 | Q98: =IFERROR((Q92/Q7)*(365/4),"-") -> 61.153493 | R98: =IFERROR((R92/R7)*(365/4),"-") -> 59.72796 | S98: =IFERROR((S92/S7)*(365/4),"-") -> 70.78445 | T98: =IFERROR((T92/T7)*(365/4),"-") -> 61.682158 | ... AG98: =IFERROR((AG92/AG7)*(365/4),"-") -> 58.67599
B99: Payable Days | C99: =IFERROR((C93/-C9)*365,"-") -> 26.360778 | D99: =IFERROR((D93/-D9)*365,"-") -> 20.220606 | E99: =IFERROR((E93/-E9)*365,"-") -> 18.105825 | F99: =IFERROR((F93/-F9)*365,"-") -> 20.632679 | G99: =IFERROR((G93/-G9)*365,"-") -> 27.52231 | H99: =IFERROR((H93/-H9)*365,"-") -> 20.229365 | I99: =IFERROR((I93/-I9)*365,"-") -> 24.188452 | J99: =IFERROR((J93/-J9)*365,"-") -> 27.035812 | K99: =IFERROR((K93/-K9)*365,"-") -> 24.42178 | M99: =IFERROR((M93/-M9)*(365/4),"-") -> 19.943975 | N99: =IFERROR((N93/-N9)*(365/4),"-") -> 17.827868 | O99: =IFERROR((O93/-O9)*(365/4),"-") -> 19.486921 | P99: =IFERROR((P93/-P9)*(365/4),"-") -> 19.614456 | Q99: =IFERROR((Q93/-Q9)*(365/4),"-") -> 30.964945 | R99: =IFERROR((R93/-R9)*(365/4),"-") -> 35.729374 | S99: =IFERROR((S93/-S9)*(365/4),"-") -> 31.748507 | T99: =IFERROR((T93/-T9)*(365/4),"-") -> 26.082309 | ... AG99: =IFERROR((AG93/-AG9)*(365/4),"-") -> 23.429006
B101: Debt Breakdown
B102: Short-term debt | C102: 1614303 | D102: 2737770 | E102: 3114250 | F102: 2880763 | G102: 7423247 | H102: 9857189 | I102: 5252238 | J102: 8161757 | K102: =AG102 -> 5890940 | M102: 2807051 | N102: 2314554 | O102: =2523633 -> 2523633 | P102: =F102 -> 2880763 | Q102: 3709094 | R102: 4017441 | S102: 5429825 | T102: =G102 -> 7423247 | U102: 7942755 | V102: 10521348 | W102: 11229878 | X102: =H102 -> 9857189 | Y102: 8845236 | Z102: 6274350 | AA102: 5140835 | AB102: =I102 -> 5252238 | AC102: 9079608 | AD102: 8521462 | AE102: 9249989 | AF102: =J102 -> 8161757 | AG102: 5890940
B103: Long-term debt | C103: 3667634 | D103: 7785736 | E103: 8137398 | F103: 14743046 | G103: 15571357 | H103: 19611443 | I103: 17431495 | J103: 14086148 | K103: =AG103 -> 13426725 | M103: 10785739 | N103: 11531414 | O103: 11767803 | P103: =F103 -> 14743046 | Q103: 14404539 | R103: 15364660 | S103: 16591648 | T103: =G103 -> 15571357 | U103: 20815018 | V103: 20285163 | W103: 20328737 | X103: =H103 -> 19611443 | Y103: 20660671 | Z103: 18953617 | AA103: 16703945 | AB103: =I103 -> 17431495 | AC103: 14254063 | AD103: 13319576 | AE103: 14828745 | AF103: =J103 -> 14086148 | AG103: 13426725
B104: Total Debt | C104: =SUM(C102:C103) -> 5281937 | D104: =SUM(D102:D103) -> 10523506 | E104: =SUM(E102:E103) -> 11251648 | F104: =SUM(F102:F103) -> 17623809 | G104: =SUM(G102:G103) -> 22994604 | H104: =SUM(H102:H103) -> 29468632 | I104: =SUM(I102:I103) -> 22683733 | J104: =SUM(J102:J103) -> 22247905 | K104: =SUM(K102:K103) -> 19317665 | M104: =SUM(M102:M103) -> 13592790 | N104: =SUM(N102:N103) -> 13845968 | O104: =SUM(O102:O103) -> 14291436 | P104: =SUM(P102:P103) -> 17623809 | Q104: =SUM(Q102:Q103) -> 18113633 | R104: =SUM(R102:R103) -> 19382101 | S104: =SUM(S102:S103) -> 22021473 | T104: =SUM(T102:T103) -> 22994604 | ... AG104: =SUM(AG102:AG103) -> 19317665
B106: Lease Obligations
B107: Short-term | C107: 0 | D107: 293171 | E107: 347464 | F107: 302059 | G107: 280873 | H107: 631497 | I107: 588355 | J107: 547296 | K107: =AG107 -> 526303 | M107: 368708 | N107: 325511 | O107: 305087 | P107: =F107 -> 302059 | Q107: 311566 | R107: 333993 | S107: 5429825 | T107: =G107 -> 280873 | U107: 323891 | V107: 339508 | W107: 600461 | X107: =H107 -> 631497 | Y107: 638344 | Z107: 592561 | AA107: 561346 | AB107: =I107 -> 588355 | AC107: 563533 | AD107: 535839 | AE107: 539118 | AF107: =J107 -> 547296 | AG107: 526303
B108: Long-term | C108: 0 | D108: 1373828 | E108: 1296252 | F108: 1223703 | G108: 1516208 | H108: 2398377 | I108: 2180021 | J108: 1962647 | K108: =AG108 -> 1988448 | M108: 1373221 | N108: 1287517 | O108: 1265752 | P108: =F108 -> 1223703 | Q108: 1285763 | R108: 1443321 | S108: 1492477 | T108: =G108 -> 1516208 | U108: 1646030 | V108: 1640479 | W108: 2423357 | X108: =H108 -> 2398377 | Y108: 2431065 | Z108: 2259454 | AA108: 2142200 | AB108: =I108 -> 2180021 | AC108: 2086562 | AD108: 1992294 | AE108: 1966072 | AF108: =J108 -> 1962647 | AG108: 1988448
B109: Total Lease | C109: =SUM(C107:C108) -> 0 | D109: =SUM(D107:D108) -> 1666999 | E109: =SUM(E107:E108) -> 1643716 | F109: =SUM(F107:F108) -> 1525762 | G109: =SUM(G107:G108) -> 1797081 | H109: =SUM(H107:H108) -> 3029874 | I109: =SUM(I107:I108) -> 2768376 | J109: =SUM(J107:J108) -> 2509943 | K109: =SUM(K107:K108) -> 2514751 | M109: =SUM(M107:M108) -> 1741929 | N109: =SUM(N107:N108) -> 1613028 | O109: =SUM(O107:O108) -> 1570839 | P109: =SUM(P107:P108) -> 1525762 | Q109: =SUM(Q107:Q108) -> 1597329 | R109: =SUM(R107:R108) -> 1777314 | S109: =SUM(S107:S108) -> 6922302 | T109: =SUM(T107:T108) -> 1797081 | ... AG109: =SUM(AG107:AG108) -> 2514751
B111: Debt Including Lease obligations
B112: Short-term debt | C112: =C102+C107 -> 1614303 | D112: =D102+D107 -> 3030941 | E112: =E102+E107 -> 3461714 | F112: =F102+F107 -> 3182822 | G112: =G102+G107 -> 7704120 | H112: =H102+H107 -> 10488686 | I112: =I102+I107 -> 5840593 | J112: =J102+J107 -> 8709053 | K112: =K102+K107 -> 6417243 | M112: =M102+M107 -> 3175759 | N112: =N102+N107 -> 2640065 | O112: =O102+O107 -> 2828720 | P112: =F112 -> 3182822 | Q112: =Q102+Q107 -> 4020660 | R112: =R102+R107 -> 4351434 | S112: =S102+S107 -> 10859650 | T112: =G112 -> 7704120 | U112: =U102+U107 -> 8266646 | V112: =V102+V107 -> 10860856 | W112: =W102+W107 -> 11830339 | X112: =H112 -> 10488686 | Y112: =Y102+Y107 -> 9483580 | Z112: =Z102+Z107 -> 6866911 | AA112: =AA102+AA107 -> 5702181 | AB112: =AB102+AB107 -> 5840593 | AC112: =AC102+AC107 -> 9643141 | AD112: =AD102+AD107 -> 9057301 | AE112: =AE102+AE107 -> 9789107 | AF112: =AF102+AF107 -> 8709053 | AG112: =AG102+AG107 -> 6417243
B113: Long-term debt | C113: =C103+C108 -> 3667634 | D113: =D103+D108 -> 9159564 | E113: =E103+E108 -> 9433650 | F113: =F103+F108 -> 15966749 | G113: =G103+G108 -> 17087565 | H113: =H103+H108 -> 22009820 | I113: =I103+I108 -> 19611516 | J113: =J103+J108 -> 16048795 | K113: =K103+K108 -> 15415173 | M113: =M103+M108 -> 12158960 | N113: =N103+N108 -> 12818931 | O113: =O103+O108 -> 13033555 | P113: =F113 -> 15966749 | Q113: =Q103+Q108 -> 15690302 | R113: =R103+R108 -> 16807981 | S113: =S103+S108 -> 18084125 | T113: =G113 -> 17087565 | U113: =U103+U108 -> 22461048 | V113: =V103+V108 -> 21925642 | W113: =W103+W108 -> 22752094 | X113: =H113 -> 22009820 | Y113: =Y103+Y108 -> 23091736 | Z113: =Z103+Z108 -> 21213071 | AA113: =AA103+AA108 -> 18846145 | AB113: =AB103+AB108 -> 19611516 | AC113: =AC103+AC108 -> 16340625 | AD113: =AD103+AD108 -> 15311870 | AE113: =AE103+AE108 -> 16794817 | AF113: =AF103+AF108 -> 16048795 | AG113: =AG103+AG108 -> 15415173
B114: Total debt | C114: =SUM(C112:C113) -> 5281937 | D114: =SUM(D112:D113) -> 12190505 | E114: =SUM(E112:E113) -> 12895364 | F114: =SUM(F112:F113) -> 19149571 | G114: =SUM(G112:G113) -> 24791685 | H114: =SUM(H112:H113) -> 32498506 | I114: =SUM(I112:I113) -> 25452109 | J114: =SUM(J112:J113) -> 24757848 | K114: =SUM(K112:K113) -> 21832416 | M114: =SUM(M112:M113) -> 15334719 | N114: =SUM(N112:N113) -> 15458996 | O114: =SUM(O112:O113) -> 15862275 | P114: =SUM(P112:P113) -> 19149571 | Q114: =SUM(Q112:Q113) -> 19710962 | R114: =SUM(R112:R113) -> 21159415 | S114: =SUM(S112:S113) -> 28943775 | T114: =SUM(T112:T113) -> 24791685 | ... AG114: =SUM(AG112:AG113) -> 21832416
B115: Cash and cash equivalents | C115: 2349319 | D115: 2306070 | E115: 2975989 | F115: 5057982 | G115: =4977007 -> 4977007 | H115: 7587329 | I115: 11205117 | J115: 14923766 | K115: =AG115 -> 21166904 | M115: 2226144 | N115: 2666351 | O115: 2761977 | P115: =F115 -> 5057982 | Q115: 4982764 | R115: 4546312 | S115: 4719217 | T115: =G115 -> 4977007 | U115: 4894782 | V115: 6040810 | W115: 7122306 | X115: =H115 -> 7587329 | Y115: 8381395 | Z115: 7933829 | AA115: 9135688 | AB115: =I115 -> 11205117 | AC115: 12558069 | AD115: 9075311 | AE115: 10814515 | AF115: =J115 -> 14923766 | AG115: 21166904
...

Sheet KPIs
B2: SK Hynix Inc. | C2: Annual | D2: Annual | E2: Annual | F2: Annual | G2: Annual | H2: Annual | I2: Annual | J2: Annual | K2: LTM | M2: Quarters | N2: Quarters | O2: Quarters | P2: Quarters | Q2: Quarters | R2: Quarters | S2: Quarters | T2: Quarters | U2: Quarters | V2: Quarters | W2: Quarters | X2: Quarters | Y2: Quarters | Z2: Quarters | AA2: Quarters | AB2: Quarters | AC2: Quarters | AD2: Quarters | AE2: Quarters | AF2: Quarters | AG2: Quarters
B3: (KRW millions) | C3: 43465 | D3: 43830 | E3: 44196 | F3: 44561 | G3: 44926 | H3: 45291 | I3: 45657 | J3: 46022 | K3: =AG3 -> 46112 | M3: 44286 | N3: 44377 | O3: 44469 | P3: 44561 | Q3: 44651 | R3: 44742 | S3: 44834 | T3: 44926 | U3: 45016 | V3: 45107 | W3: 45199 | X3: 45291 | Y3: 45382 | Z3: 45473 | AA3: 45565 | AB3: 45657 | AC3: 45747 | AD3: 45838 | AE3: 45930 | AF3: 46022 | AG3: 46112
C4: Act | D4: Act | E4: Act | F4: Act | G4: Act | H4: Act | I4: Act | J4: Act | K4: Act | M4: Act | N4: Act | O4: Act | P4: Act | Q4: Act | R4: Act | S4: Act | T4: Act | U4: Act | V4: Act | W4: Act | X4: Act | Y4: Act | Z4: Act | AA4: Act | AB4: Act | AC4: Act | AD4: Act | AE4: Act | AF4: Act | AG4: Act
C5: FY | D5: FY | E5: FY | F5: FY | G5: FY | H5: FY | I5: FY | J5: FY | K5: FY | M5: 1Q | N5: 2Q | O5: 3Q | P5: 4Q | Q5: 1Q | R5: 2Q | S5: 3Q | T5: 4Q | U5: 1Q | V5: 2Q | W5: 3Q | X5: 4Q | Y5: 1Q | Z5: 2Q | AA5: 3Q | AB5: 4Q | AC5: 1Q | AD5: 2Q | AE5: 3Q | AF5: 4Q | AG5: 1Q
B7: Revenue by type
B8: Sale of goods | C8: 40388846 | D8: 26922416 | E8: 31837538 | F8: 42932963 | G8: 44540140 | H8: 32680033 | I8: 66100890 | J8: 97024278 | K8: =SUM(AD8:AG8) -> 131961631 | M8: 8479145 | N8: 10303146 | O8: 11789903 | P8: =F8-SUM(M8:O8) -> 12360769 | Q8: 12139578 | R8: 13789311 | S8: 10962408 | T8: =G8-SUM(Q8:S8) -> 7648843 | U8: 5073063 | V8: 7255332 | W8: 9047470 | X8: =H8-SUM(U8:W8) -> 11304168 | Y8: 12408716 | Z8: 16402538 | AA8: 17552396 | AB8: =I8-SUM(Y8:AA8) -> 19737240 | AC8: 17608044 | AD8: 22201681 | AE8: 24417726 | AF8: =J8-SUM(AC8:AE8) -> 32796827 | AG8: 52545397
B9: Providing services | C9: 56220 | D9: 68317 | E9: 62880 | F9: 64829 | G9: 81428 | H9: 85686 | I9: 92070 | J9: 122397 | K9: =SUM(AD9:AG9) -> 122190 | M9: 15043 | N9: 18525 | O9: 15421 | P9: =F9-SUM(M9:O9) -> 15840 | Q9: 16075 | R9: 21690 | S9: 20475 | T9: =G9-SUM(Q9:S9) -> 23188 | U9: 15048 | V9: 50601 | W9: 18701 | X9: =H9-SUM(U9:W9) -> 1336 | Y9: 20882 | Z9: 20720 | AA9: 20673 | AB9: =I9-SUM(Y9:AA9) -> 29795 | AC9: 31097 | AD9: 30271 | AE9: 31203 | AF9: =J9-SUM(AC9:AE9) -> 29826 | AG9: 30890
B10: Net Revenue | C10: =SUM(C8:C9) -> 40445066 | D10: =SUM(D8:D9) -> 26990733 | E10: =SUM(E8:E9) -> 31900418 | F10: =SUM(F8:F9) -> 42997792 | G10: =SUM(G8:G9) -> 44621568 | H10: =SUM(H8:H9) -> 32765719 | I10: =SUM(I8:I9) -> 66192960 | J10: =SUM(J8:J9) -> 97146675 | K10: =SUM(K8:K9) -> 132083821 | M10: =SUM(M8:M9) -> 8494188 | N10: =SUM(N8:N9) -> 10321671 | O10: =SUM(O8:O9) -> 11805324 | P10: =SUM(P8:P9) -> 12376609 | Q10: =SUM(Q8:Q9) -> 12155653 | R10: =SUM(R8:R9) -> 13811001 | S10: =SUM(S8:S9) -> 10982883 | T10: =SUM(T8:T9) -> 7672031 | ... AG10: =SUM(AG8:AG9) -> 52576287
B11: check | C11: =C10-Model!C7 -> 0 | D11: =D10-Model!D7 -> 0 | E11: =E10-Model!E7 -> 0 | F11: =F10-Model!F7 -> 0 | G11: =G10-Model!G7 -> 0 | H11: =H10-Model!H7 -> 0 | I11: =I10-Model!I7 -> 0 | J11: =J10-Model!J7 -> 0 | K11: =K10-Model!K7 -> 0 | M11: =M10-Model!M7 -> 0 | N11: =N10-Model!N7 -> 0 | O11: =O10-Model!O7 -> 0 | P11: =P10-Model!P7 -> 0 | Q11: =Q10-Model!Q7 -> 0 | R11: =R10-Model!R7 -> 0 | S11: =S10-Model!S7 -> 0 | T11: =T10-Model!T7 -> 0 | ... AG11: =AG10-Model!AG7 -> 0
B13: Revenue by type (% Share)
B14: Sale of goods | C14: =C8/C$10 -> 0.99860997 | D14: =D8/D$10 -> 0.99746887 | E14: =E8/E$10 -> 0.99802887 | F14: =F8/F$10 -> 0.99849227 | G14: =G8/G$10 -> 0.99817514 | H14: =H8/H$10 -> 0.99738489 | I14: =I8/I$10 -> 0.99860907 | J14: =J8/J$10 -> 0.99874008 | K14: =K8/K$10 -> 0.99907491 | M14: =M8/M$10 -> 0.99822902 | N14: =N8/N$10 -> 0.99820523 | O14: =O8/O$10 -> 0.99869372 | P14: =P8/P$10 -> 0.99872017 | Q14: =Q8/Q$10 -> 0.99867757 | R14: =R8/R$10 -> 0.99842951 | S14: =S8/S$10 -> 0.99813574 | T14: =T8/T$10 -> 0.99697759 | ... AG14: =AG8/AG$10 -> 0.99941247
B15: Providing services | C15: =C9/C$10 -> 0.0013900336 | D15: =D9/D$10 -> 0.002531128 | E15: =E9/E$10 -> 0.001971134 | F15: =F9/F$10 -> 0.0015077286 | G15: =G9/G$10 -> 0.0018248574 | H15: =H9/H$10 -> 0.0026151112 | I15: =I9/I$10 -> 0.0013909334 | J15: =J9/J$10 -> 0.0012599196 | K15: =K9/K$10 -> 0.00092509438 | M15: =M9/M$10 -> 0.0017709756 | N15: =N9/N$10 -> 0.0017947675 | O15: =O9/O$10 -> 0.001306275 | P15: =P9/P$10 -> 0.0012798336 | Q15: =Q9/Q$10 -> 0.00132243 | R15: =R9/R$10 -> 0.0015704872 | S15: =S9/S$10 -> 0.0018642646 | T15: =T9/T$10 -> 0.003022407 | ... AG15: =AG9/AG$10 -> 0.00058752722
B16: Net Revenue | C16: =SUM(C14:C15) -> 1 | D16: =SUM(D14:D15) -> 1 | E16: =SUM(E14:E15) -> 1 | F16: =SUM(F14:F15) -> 1 | G16: =SUM(G14:G15) -> 1 | H16: =SUM(H14:H15) -> 1 | I16: =SUM(I14:I15) -> 1 | J16: =SUM(J14:J15) -> 1 | K16: =SUM(K14:K15) -> 1 | M16: =SUM(M14:M15) -> 1 | N16: =SUM(N14:N15) -> 1 | O16: =SUM(O14:O15) -> 1 | P16: =SUM(P14:P15) -> 1 | Q16: =SUM(Q14:Q15) -> 1 | R16: =SUM(R14:R15) -> 1 | S16: =SUM(S14:S15) -> 1 | T16: =SUM(T14:T15) -> 1 | ... AG16: =SUM(AG14:AG15) -> 1
B18: Revenue by type (% YoY Growth)
B19: Sale of goods | D19: =D8/C8-1 -> -0.33341953 | E19: =E8/D8-1 -> 0.18256616 | F19: =F8/E8-1 -> 0.34850135 | G19: =G8/F8-1 -> 0.03743457 | H19: =H8/G8-1 -> -0.26627907 | I19: =I8/H8-1 -> 1.022669 | J19: =J8/I8-1 -> 0.46782105 | Q19: =Q8/M8-1 -> 0.43169836 | R19: =R8/N8-1 -> 0.33835927 | S19: =S8/O8-1 -> -0.070186752 | T19: =T8/P8-1 -> -0.38120007 | U19: =U8/Q8-1 -> -0.58210549 | V19: =V8/R8-1 -> -0.47384376 | W19: =W8/S8-1 -> -0.17468224 | X19: =X8/T8-1 -> 0.47789254 | ... AG19: =AG8/AC8-1 -> 1.98417
B20: Providing services | D20: =D9/C9-1 -> 0.21517254 | E20: =E9/D9-1 -> -0.079584876 | F20: =F9/E9-1 -> 0.030995547 | G20: =G9/F9-1 -> 0.25604282 | H20: =H9/G9-1 -> 0.052291595 | I20: =I9/H9-1 -> 0.074504587 | J20: =J9/I9-1 -> 0.32939068 | Q20: =Q9/M9-1 -> 0.068603337 | R20: =R9/N9-1 -> 0.1708502 | S20: =S9/O9-1 -> 0.32773491 | T20: =T9/P9-1 -> 0.46388889 | U20: =U9/Q9-1 -> -0.063888025 | V20: =V9/R9-1 -> 1.3329184 | W20: =W9/S9-1 -> -0.086642247 | X20: =X9/T9-1 -> -0.94238399 | ... AG20: =AG9/AC9-1 -> -0.0066565907
B21: Net Revenue | D21: =D10/C10-1 -> -0.33265697 | E21: =E10/D10-1 -> 0.18190262 | F21: =F10/E10-1 -> 0.3478755 | G21: =G10/F10-1 -> 0.037764172 | H21: =H10/G10-1 -> -0.26569772 | I21: =I10/H10-1 -> 1.0201895 | J21: =J10/I10-1 -> 0.46762851 | Q21: =Q10/M10-1 -> 0.43105533 | R21: =R10/N10-1 -> 0.33805863 | S21: =S10/O10-1 -> -0.069666957 | T21: =T10/P10-1 -> -0.3801185 | U21: =U10/Q10-1 -> -0.58142018 | V21: =V10/R10-1 -> -0.47100627 | W21: =W10/S10-1 -> -0.17451811 | X21: =X10/T10-1 -> 0.47359989 | ... AG21: =AG10/AC10-1 -> 1.9806603
B25: Revenue by Products
B26: DRAM | C26: 32370936 | D26: 20292687 | E26: 22536404 | F26: 30599711 | G26: 28168802 | H26: 20768662 | I26: 44731664 | J26: 74904134 | K26: =SUM(AD26:AG26) -> 101525900 | M26: 6062469 | N26: 7505783 | O26: 8312960 | P26: =F26-SUM(M26:O26) -> 8718499 | Q26: 7857576 | R26: 8781735 | S26: 6954326 | T26: =G26-SUM(Q26:S26) -> 4575165 | U26: 2918692 | V26: 4414132 | W26: 6085615 | X26: =H26-SUM(U26:W26) -> 7350223 | Y26: 7493448 | Z26: 10700356 | AA26: 12048412 | AB26: =I26-SUM(Y26:AA26) -> 14489448 | AC26: 14036870 | AD26: 17123990 | AE26: 19083916 | AF26: =J26-SUM(AC26:AE26) -> 24659358 | AG26: 40658636
B27: NAND Flash | C27: 7420857 | D27: 5139563 | E27: 7471242 | F27: 10529447 | G27: 14183923 | H27: 9653061 | I27: 19274112 | J27: 20690084 | K27: =SUM(AD27:AG27) -> 29035484 | M27: 2007523 | N27: 2305681 | O27: 3044004 | P27: =F27-SUM(M27:O27) -> 3172239 | Q27: 3913395 | R27: 4517859 | S27: 3388185 | T27: =G27-SUM(Q27:S27) -> 2364484 | U27: 1688034 | V27: 2240211 | W27: 2426210 | X27: =H27-SUM(U27:W27) -> 3298606 | Y27: 4407213 | Z27: 5184707 | AA27: 4980518 | AB27: =I27-SUM(Y27:AA27) -> 4701674 | AC27: 3228835 | AD27: 4727806 | AE27: 4989186 | AF27: =J27-SUM(AC27:AE27) -> 7744257 | AG27: 11574235
B28: Others | C28: 653273 | D28: 1558483 | E28: 1892772 | F28: 1868634 | G28: 2268843 | H28: 2343996 | I28: 2187184 | J28: 1552457 | K28: =SUM(AD28:AG28) -> 1522437 | M28: 424196 | N28: 510207 | O28: 448360 | P28: =F28-SUM(M28:O28) -> 485871 | Q28: 384682 | R28: 511407 | S28: 640372 | T28: =G28-SUM(Q28:S28) -> 732382 | U28: 481385 | V28: 651590 | W28: 554346 | X28: =H28-SUM(U28:W28) -> 656675 | Y28: 528937 | Z28: 538195 | AA28: 544139 | AB28: =I28-SUM(Y28:AA28) -> 575913 | AC28: 373436 | AD28: 380156 | AE28: 375827 | AF28: =J28-SUM(AC28:AE28) -> 423038 | AG28: 343416
B29: Net Revenue | C29: =SUM(C26:C28) -> 40445066 | D29: =SUM(D26:D28) -> 26990733 | E29: =SUM(E26:E28) -> 31900418 | F29: =SUM(F26:F28) -> 42997792 | G29: =SUM(G26:G28) -> 44621568 | H29: =SUM(H26:H28) -> 32765719 | I29: =SUM(I26:I28) -> 66192960 | J29: =SUM(J26:J28) -> 97146675 | K29: =SUM(K26:K28) -> 132083821 | M29: =SUM(M26:M28) -> 8494188 | N29: =SUM(N26:N28) -> 10321671 | O29: =SUM(O26:O28) -> 11805324 | P29: =SUM(P26:P28) -> 12376609 | Q29: =SUM(Q26:Q28) -> 12155653 | R29: =SUM(R26:R28) -> 13811001 | S29: =SUM(S26:S28) -> 10982883 | T29: =SUM(T26:T28) -> 7672031 | ... AG29: =SUM(AG26:AG28) -> 52576287
B30: check | C30: =C29-Model!C7 -> 0 | D30: =D29-Model!D7 -> 0 | E30: =E29-Model!E7 -> 0 | F30: =F29-Model!F7 -> 0 | G30: =G29-Model!G7 -> 0 | H30: =H29-Model!H7 -> 0 | I30: =I29-Model!I7 -> 0 | J30: =J29-Model!J7 -> 0 | K30: =K29-Model!K7 -> 0 | M30: =M29-Model!M7 -> 0 | N30: =N29-Model!N7 -> 0 | O30: =O29-Model!O7 -> 0 | P30: =P29-Model!P7 -> 0 | Q30: =Q29-Model!Q7 -> 0 | R30: =R29-Model!R7 -> 0 | S30: =S29-Model!S7 -> 0 | T30: =T29-Model!T7 -> 0 | ... AG30: =AG29-Model!AG7 -> 0
B32: Revenue by Products (% Share)
B33: DRAM | C33: =C26/C$29 -> 0.80036799 | D33: =D26/D$29 -> 0.75183905 | E33: =E26/E$29 -> 0.70646109 | F33: =F26/F$29 -> 0.71165773 | G33: =G26/G$29 -> 0.63128221 | H33: =H26/H$29 -> 0.63385339 | I33: =I26/I$29 -> 0.67577676 | J33: =J26/J$29 -> 0.77104166 | K33: =K26/K$29 -> 0.76864751 | M33: =M26/M$29 -> 0.71371966 | N33: =N26/N$29 -> 0.72718681 | O33: =O26/O$29 -> 0.70417042 | P33: =P26/P$29 -> 0.70443358 | Q33: =Q26/Q$29 -> 0.64641332 | R33: =R26/R$29 -> 0.63585073 | S33: =S26/S$29 -> 0.63319677 | T33: =T26/T$29 -> 0.59634339 | ... AG33: =AG26/AG$29 -> 0.7733265
B34: NAND Flash | C34: =C27/C$29 -> 0.18347991 | D34: =D27/D$29 -> 0.19041954 | E34: =E27/E$29 -> 0.23420514 | F34: =F27/F$29 -> 0.24488343 | G34: =G27/G$29 -> 0.31787146 | H34: =H27/H$29 -> 0.29460855 | I34: =I27/I$29 -> 0.29118069 | J34: =J27/J$29 -> 0.21297779 | K34: =K27/K$29 -> 0.2198262 | M34: =M27/M$29 -> 0.23634078 | N34: =N27/N$29 -> 0.22338253 | O34: =O27/O$29 -> 0.2578501 | P34: =P27/P$29 -> 0.25630922 | Q34: =Q27/Q$29 -> 0.32194034 | R34: =R27/R$29 -> 0.32712032 | S34: =S27/S$29 -> 0.30849687 | T34: =T27/T$29 -> 0.30819531 | ... AG34: =AG27/AG$29 -> 0.22014173
B35: Others | C35: =C28/C$29 -> 0.016152106 | D35: =D28/D$29 -> 0.057741411 | E35: =E28/E$29 -> 0.059333768 | F35: =F28/F$29 -> 0.043458836 | G35: =G28/G$29 -> 0.050846331 | H35: =H28/H$29 -> 0.071538061 | I35: =I28/I$29 -> 0.033042547 | J35: =J28/J$29 -> 0.015980547 | K35: =K28/K$29 -> 0.011526294 | M35: =M28/M$29 -> 0.049939559 | N35: =N28/N$29 -> 0.049430659 | O35: =O28/O$29 -> 0.037979474 | P35: =P28/P$29 -> 0.039257199 | Q35: =Q28/Q$29 -> 0.031646346 | R35: =R28/R$29 -> 0.03702896 | S35: =S28/S$29 -> 0.058306366 | T35: =T28/T$29 -> 0.095461293 | ... AG35: =AG28/AG$29 -> 0.0065317659
B36: Net Revenue | C36: =SUM(C33:C35) -> 1 | D36: =SUM(D33:D35) -> 1 | E36: =SUM(E33:E35) -> 1 | F36: =SUM(F33:F35) -> 1 | G36: =SUM(G33:G35) -> 1 | H36: =SUM(H33:H35) -> 1 | I36: =SUM(I33:I35) -> 1 | J36: =SUM(J33:J35) -> 1 | K36: =SUM(K33:K35) -> 1 | M36: =SUM(M33:M35) -> 1 | N36: =SUM(N33:N35) -> 1 | O36: =SUM(O33:O35) -> 1 | P36: =SUM(P33:P35) -> 1 | Q36: =SUM(Q33:Q35) -> 1 | R36: =SUM(R33:R35) -> 1 | S36: =SUM(S33:S35) -> 1 | T36: =SUM(T33:T35) -> 1 | ... AG36: =SUM(AG33:AG35) -> 1
B38: Revenue by Products (% YoY Growth)
B39: DRAM | D39: =D26/C26-1 -> -0.37312017 | E39: =E26/D26-1 -> 0.11056776 | F39: =F26/E26-1 -> 0.35779031 | G39: =G26/F26-1 -> -0.079442221 | H39: =H26/G26-1 -> -0.26270695 | I39: =I26/H26-1 -> 1.1538058 | J39: =J26/I26-1 -> 0.67452152 | Q39: =Q26/M26-1 -> 0.29610164 | R39: =R26/N26-1 -> 0.16999586 | S39: =S26/O26-1 -> -0.16343565 | T39: =T26/P26-1 -> -0.47523479 | U39: =U26/Q26-1 -> -0.62855059 | V39: =V26/R26-1 -> -0.49735081 | W39: =W26/S26-1 -> -0.12491663 | X39: =X26/T26-1 -> 0.60654818 | ... AG39: =AG26/AC26-1 -> 1.89656
B40: NAND Flash | D40: =D27/C27-1 -> -0.30741652 | E40: =E27/D27-1 -> 0.45367262 | F40: =F27/E27-1 -> 0.4093302 | G40: =G27/F27-1 -> 0.34707198 | H40: =H27/G27-1 -> -0.31943645 | I40: =I27/H27-1 -> 0.99668395 | J40: =J27/I27-1 -> 0.073464967 | Q40: =Q27/M27-1 -> 0.94936496 | R40: =R27/N27-1 -> 0.95944669 | S40: =S27/O27-1 -> 0.11306851 | T40: =T27/P27-1 -> -0.25463245 | U40: =U27/Q27-1 -> -0.56865228 | V40: =V27/R27-1 -> -0.50414322 | W40: =W27/S27-1 -> -0.28392045 | X40: =X27/T27-1 -> 0.39506379 | ... AG40: =AG27/AC27-1 -> 2.5846474
B41: Others | D41: =D28/C28-1 -> 1.3856535 | E41: =E28/D28-1 -> 0.2144964 | F41: =F28/E28-1 -> -0.012752725 | G41: =G28/F28-1 -> 0.21417196 | H41: =H28/G28-1 -> 0.033123931 | I41: =I28/H28-1 -> -0.066899432 | J41: =J28/I28-1 -> -0.29020284 | Q41: =Q28/M28-1 -> -0.093150336 | R41: =R28/N28-1 -> 0.0023519865 | S41: =S28/O28-1 -> 0.42825408 | T41: =T28/P28-1 -> 0.50735895 | U41: =U28/Q28-1 -> 0.25138426 | V41: =V28/R28-1 -> 0.2741124 | W41: =W28/S28-1 -> -0.13433754 | X41: =X28/T28-1 -> -0.10337092 | ... AG41: =AG28/AC28-1 -> -0.080388607
B42: Net Revenue | D42: =D29/C29-1 -> -0.33265697 | E42: =E29/D29-1 -> 0.18190262 | F42: =F29/E29-1 -> 0.3478755 | G42: =G29/F29-1 -> 0.037764172 | H42: =H29/G29-1 -> -0.26569772 | I42: =I29/H29-1 -> 1.0201895 | J42: =J29/I29-1 -> 0.46762851 | Q42: =Q29/M29-1 -> 0.43105533 | R42: =R29/N29-1 -> 0.33805863 | S42: =S29/O29-1 -> -0.069666957 | T42: =T29/P29-1 -> -0.3801185 | U42: =U29/Q29-1 -> -0.58142018 | V42: =V29/R29-1 -> -0.47100627 | W42: =W29/S29-1 -> -0.17451811 | X42: =X29/T29-1 -> 0.47359989 | ... AG42: =AG29/AC29-1 -> 1.9806603
B46: Revenue by Geography
B47: Korea | C47: 840491 | D47: 1446997 | E47: 1452006 | F47: 1461982 | G47: 1225765 | H47: 2033857 | I47: 1904112 | J47: 1932342 | K47: =SUM(AD47:AG47) -> 1668489 | M47: 321150 | N47: 398880 | O47: 344933 | P47: =F47-SUM(M47:O47) -> 397019 | Q47: 253540 | R47: 292987 | S47: 397823 | T47: =G47-SUM(Q47:S47) -> 281415 | U47: 394307 | V47: 467047 | W47: 600930 | X47: =H47-SUM(U47:W47) -> 571573 | Y47: 485931 | Z47: 481626 | AA47: 375675 | AB47: =I47-SUM(Y47:AA47) -> 560880 | AC47: 442620 | AD47: 408005 | AE47: 472452 | AF47: =J47-SUM(AC47:AE47) -> 609265 | AG47: 178767
B48: U.S.A. | C48: 14278161 | D48: 8141151 | E48: 12686108 | F48: 17144323 | G48: 23960980 | H48: 15390229 | I48: 41961072 | J48: 66885115 | K48: =SUM(AD48:AG48) -> 88089740 | M48: 3197159 | N48: 3888759 | O48: 4601148 | P48: =F48-SUM(M48:O48) -> 5457257 | Q48: 5992764 | R48: 7087906 | S48: 6167748 | T48: =G48-SUM(Q48:S48) -> 4712562 | U48: 2290112 | V48: 3150488 | W48: 4268604 | X48: =H48-SUM(U48:W48) -> 5681025 | Y48: 6312614 | Z48: 9666130 | AA48: 11327116 | AB48: =I48-SUM(Y48:AA48) -> 14655212 | AC48: 12794533 | AD48: 15039907 | AE48: 17345742 | AF48: =J48-SUM(AC48:AE48) -> 21704933 | AG48: 33999158
B49: China | C49: 15785993 | D49: 12570278 | E49: 12217634 | F49: 15730223 | G49: 12210470 | H49: 10110084 | I49: 15533563 | J49: 19136237 | K49: =SUM(AD49:AG49) -> 29238463 | M49: 3234700 | N49: 3891709 | O49: 4456709 | P49: =F49-SUM(M49:O49) -> 4147105 | Q49: 3818525 | R49: 4206358 | S49: 2753335 | T49: =G49-SUM(Q49:S49) -> 1432252 | U49: 1546079 | V49: 2362645 | W49: 2738825 | X49: =H49-SUM(U49:W49) -> 3462535 | Y49: 4091101 | Z49: 4515011 | AA49: 4156213 | AB49: =I49-SUM(Y49:AA49) -> 2771238 | AC49: 2694352 | AD49: 4670650 | AE49: 4383924 | AF49: =J49-SUM(AC49:AE49) -> 7387311 | AG49: 12796578
B50: Asia ( Excl Korea and China) | C50: =4609601+2950067 -> 7559668 | D50: =2301314+1444188 -> 3745502 | E50: =2416321+1905650 -> 4321971 | F50: =4033614+2989315 -> 7022929 | G50: =5615384 -> 5615384 | H50: 4296937 | I50: 5381439 | J50: 7215598 | K50: =SUM(AD50:AG50) -> 10430593 | M50: 1410774 | N50: 1744920 | O50: 1992788 | P50: =F50-SUM(M50:O50) -> 1874447 | Q50: 1647717 | R50: 1822087 | S50: 1219391 | T50: =G50-SUM(Q50:S50) -> 926189 | U50: 711623 | V50: 1119770 | W50: 1228031 | X50: =H50-SUM(U50:W50) -> 1237513 | Y50: 1170251 | Z50: 1378600 | AA50: 1374216 | AB50: =I50-SUM(Y50:AA50) -> 1458372 | AC50: 1258292 | AD50: 1739197 | AE50: 1777843 | AF50: =J50-SUM(AC50:AE50) -> 2440266 | AG50: 4473287
B51: Europe | C51: 1980753 | D51: 1086805 | E51: 1222699 | F51: 1638335 | G51: 1608969 | H51: 934612 | I51: 1412774 | J51: 1977383 | K51: =SUM(AD51:AG51) -> 2656536 | M51: 330405 | N51: 397403 | O51: 409746 | P51: =F51-SUM(M51:O51) -> 500781 | Q51: 443107 | R51: 401663 | S51: 444586 | T51: =G51-SUM(Q51:S51) -> 319613 | U51: 145990 | V51: 205983 | W51: 229781 | X51: =H51-SUM(U51:W51) -> 352858 | Y51: 369701 | Z51: 381891 | AA51: 339849 | AB51: =I51-SUM(Y51:AA51) -> 321333 | AC51: 449344 | AD51: 374193 | AE51: 468968 | AF51: =J51-SUM(AC51:AE51) -> 684878 | AG51: 1128497
B52: Net cost of revenues | C52: =SUM(C47:C51) -> 40445066 | D52: =SUM(D47:D51) -> 26990733 | E52: =SUM(E47:E51) -> 31900418 | F52: =SUM(F47:F51) -> 42997792 | G52: =SUM(G47:G51) -> 44621568 | H52: =SUM(H47:H51) -> 32765719 | I52: =SUM(I47:I51) -> 66192960 | J52: =SUM(J47:J51) -> 97146675 | K52: =SUM(K47:K51) -> 132083821 | M52: =SUM(M47:M51) -> 8494188 | N52: =SUM(N47:N51) -> 10321671 | O52: =SUM(O47:O51) -> 11805324 | P52: =SUM(P47:P51) -> 12376609 | Q52: =SUM(Q47:Q51) -> 12155653 | R52: =SUM(R47:R51) -> 13811001 | S52: =SUM(S47:S51) -> 10982883 | T52: =SUM(T47:T51) -> 7672031 | ... AG52: =SUM(AG47:AG51) -> 52576287
B53: check | C53: =C52-Model!C7 -> 0 | D53: =D52-Model!D7 -> 0 | E53: =E52-Model!E7 -> 0 | F53: =F52-Model!F7 -> 0 | G53: =G52-Model!G7 -> 0 | H53: =H52-Model!H7 -> 0 | I53: =I52-Model!I7 -> 0 | J53: =J52-Model!J7 -> 0 | K53: =K52-Model!K7 -> 0 | M53: =M52-Model!M7 -> 0 | N53: =N52-Model!N7 -> 0 | O53: =O52-Model!O7 -> 0 | P53: =P52-Model!P7 -> 0 | Q53: =Q52-Model!Q7 -> 0 | R53: =R52-Model!R7 -> 0 | S53: =S52-Model!S7 -> 0 | T53: =T52-Model!T7 -> 0 | ... AG53: =AG52-Model!AG7 -> 0
B55: Revenue by Geography (% Share)
B56: Korea | C56: =C47/C$52 -> 0.020781052 | D56: =D47/D$52 -> 0.053610882 | E56: =E47/E$52 -> 0.045516833 | F56: =F47/F$52 -> 0.034001327 | G56: =G47/G$52 -> 0.027470236 | H56: =H47/H$52 -> 0.062072711 | I56: =I47/I$52 -> 0.02876608 | J56: =J47/J$52 -> 0.019890974 | K56: =K47/K$52 -> 0.012632047 | M56: =M47/M$52 -> 0.037808205 | N56: =N47/N$52 -> 0.038644905 | O56: =O47/O$52 -> 0.029218427 | P56: =P47/P$52 -> 0.032078173 | Q56: =Q47/Q$52 -> 0.020857785 | R56: =R47/R$52 -> 0.021214031 | S56: =S47/S$52 -> 0.036222092 | T56: =T47/T$52 -> 0.036680639 | ... AG56: =AG47/AG$52 -> 0.003400145
B57: U.S.A. | C57: =C48/C$52 -> 0.35302603 | D57: =D48/D$52 -> 0.30162764 | E57: =E48/E$52 -> 0.39767843 | F57: =F48/F$52 -> 0.39872566 | G57: =G48/G$52 -> 0.53698203 | H57: =H48/H$52 -> 0.46970521 | I57: =I48/I$52 -> 0.63392047 | J57: =J48/J$52 -> 0.68849618 | K57: =K48/K$52 -> 0.66692301 | M57: =M48/M$52 -> 0.37639372 | N57: =N48/N$52 -> 0.37675673 | O57: =O48/O$52 -> 0.38975195 | P57: =P48/P$52 -> 0.44093313 | Q57: =Q48/Q$52 -> 0.49300223 | R57: =R48/R$52 -> 0.51320726 | S57: =S48/S$52 -> 0.56157823 | T57: =T48/T$52 -> 0.61425221 | ... AG57: =AG48/AG$52 -> 0.64666335
B58: China | C58: =C49/C$52 -> 0.39030702 | D58: =D49/D$52 -> 0.4657257 | E58: =E49/E$52 -> 0.38299291 | F58: =F49/F$52 -> 0.36583792 | G58: =G49/G$52 -> 0.27364502 | H58: =H49/H$52 -> 0.30855676 | I58: =I49/I$52 -> 0.23467092 | J58: =J49/J$52 -> 0.19698293 | K58: =K49/K$52 -> 0.22136294 | M58: =M49/M$52 -> 0.38081333 | N58: =N49/N$52 -> 0.37704254 | O58: =O49/O$52 -> 0.37751687 | P58: =P49/P$52 -> 0.33507603 | Q58: =Q49/Q$52 -> 0.31413574 | R58: =R49/R$52 -> 0.30456576 | S58: =S49/S$52 -> 0.25069328 | T58: =T49/T$52 -> 0.18668486 | ... AG58: =AG49/AG$52 -> 0.24339068
B59: Asia ( Excl Korea and China) | C59: =C50/C$52 -> 0.186912 | D59: =D50/D$52 -> 0.13876993 | E59: =E50/E$52 -> 0.13548321 | F59: =F50/F$52 -> 0.16333232 | G59: =G50/G$52 -> 0.12584461 | H59: =H50/H$52 -> 0.13114124 | I59: =I50/I$52 -> 0.081299265 | J59: =J50/J$52 -> 0.074275296 | K59: =K50/K$52 -> 0.078969498 | M59: =M50/M$52 -> 0.16608698 | N59: =N50/N$52 -> 0.16905402 | O59: =O50/O$52 -> 0.16880418 | P59: =P50/P$52 -> 0.15145077 | Q59: =Q50/Q$52 -> 0.1355515 | R59: =R50/R$52 -> 0.13193012 | S59: =S50/S$52 -> 0.11102649 | T59: =T50/T$52 -> 0.12072279 | ... AG59: =AG50/AG$52 -> 0.085081835
B60: Europe | C60: =C51/C$52 -> 0.048973909 | D60: =D51/D$52 -> 0.040265857 | E60: =E51/E$52 -> 0.03832862 | F60: =F51/F$52 -> 0.03810277 | G60: =G51/G$52 -> 0.036058101 | H60: =H51/H$52 -> 0.02852408 | I60: =I51/I$52 -> 0.021343267 | J60: =J51/J$52 -> 0.020354613 | K60: =K51/K$52 -> 0.020112501 | M60: =M51/M$52 -> 0.038897773 | N60: =N51/N$52 -> 0.038501808 | O60: =O51/O$52 -> 0.034708577 | P60: =P51/P$52 -> 0.040461891 | Q60: =Q51/Q$52 -> 0.036452752 | R60: =R51/R$52 -> 0.02908283 | S60: =S51/S$52 -> 0.040479899 | T60: =T51/T$52 -> 0.041659503 | ... AG60: =AG51/AG$52 -> 0.021463992
B61: Net cost of revenues | C61: =SUM(C56:C60) -> 1 | D61: =SUM(D56:D60) -> 1 | E61: =SUM(E56:E60) -> 1 | F61: =SUM(F56:F60) -> 1 | G61: =SUM(G56:G60) -> 1 | H61: =SUM(H56:H60) -> 1 | I61: =SUM(I56:I60) -> 1 | J61: =SUM(J56:J60) -> 1 | K61: =SUM(K56:K60) -> 1 | M61: =SUM(M56:M60) -> 1 | N61: =SUM(N56:N60) -> 1 | O61: =SUM(O56:O60) -> 1 | P61: =SUM(P56:P60) -> 1 | Q61: =SUM(Q56:Q60) -> 1 | R61: =SUM(R56:R60) -> 1 | S61: =SUM(S56:S60) -> 1 | T61: =SUM(T56:T60) -> 1 | ... AG61: =SUM(AG56:AG60) -> 1
B63: Revenue by Geography (% YoY Growth)
B64: Korea | D64: =D47/C47-1 -> 0.72160915 | E64: =E47/D47-1 -> 0.003461652 | F64: =F47/E47-1 -> 0.006870495 | G64: =G47/F47-1 -> -0.16157312 | H64: =H47/G47-1 -> 0.65925524 | I64: =I47/H47-1 -> -0.063792587 | J64: =J47/I47-1 -> 0.014825809 | Q64: =Q47/M47-1 -> -0.21052468 | R64: =R47/N47-1 -> -0.26547583 | S64: =S47/O47-1 -> 0.15333413 | T64: =T47/P47-1 -> -0.29118002 | U64: =U47/Q47-1 -> 0.55520628 | V64: =V47/R47-1 -> 0.59408779 | W64: =W47/S47-1 -> 0.51054615 | X64: =X47/T47-1 -> 1.031068 | ... AG64: =AG47/AC47-1 -> -0.59611631
B65: U.S.A. | D65: =D48/C48-1 -> -0.42981796 | E65: =E48/D48-1 -> 0.55826959 | F65: =F48/E48-1 -> 0.35142496 | G65: =G48/F48-1 -> 0.39760433 | H65: =H48/G48-1 -> -0.35769618 | I65: =I48/H48-1 -> 1.7264748 | J65: =J48/I48-1 -> 0.59398013 | Q65: =Q48/M48-1 -> 0.87440287 | R65: =R48/N48-1 -> 0.82266528 | S65: =S48/O48-1 -> 0.34048025 | T65: =T48/P48-1 -> -0.13645958 | U65: =U48/Q48-1 -> -0.6178538 | V65: =V48/R48-1 -> -0.55551216 | W65: =W48/S48-1 -> -0.3079153 | X65: =X48/T48-1 -> 0.20550669 | ... AG65: =AG48/AC48-1 -> 1.6573192
B66: China | D66: =D49/C49-1 -> -0.20370686 | E66: =E49/D49-1 -> -0.028053795 | F66: =F49/E49-1 -> 0.28750157 | G66: =G49/F49-1 -> -0.22375735 | H66: =H49/G49-1 -> -0.17201516 | I66: =I49/H49-1 -> 0.53644253 | J66: =J49/I49-1 -> 0.23192837 | Q66: =Q49/M49-1 -> 0.18048814 | R66: =R49/N49-1 -> 0.080851112 | S66: =S49/O49-1 -> -0.38220445 | T66: =T49/P49-1 -> -0.65463812 | U66: =U49/Q49-1 -> -0.59511094 | V66: =V49/R49-1 -> -0.43831576 | W66: =W49/S49-1 -> -0.0052699726 | X66: =X49/T49-1 -> 1.4175459 | ... AG66: =AG49/AC49-1 -> 3.7494084
B67: Asia ( Excl Korea and China) | D67: =D50/C50-1 -> -0.50454147 | E67: =E50/D50-1 -> 0.15390968 | F67: =F50/E50-1 -> 0.62493663 | G67: =G50/F50-1 -> -0.20042136 | H67: =H50/G50-1 -> -0.23479196 | I67: =I50/H50-1 -> 0.25238955 | J67: =J50/I50-1 -> 0.34083058 | Q67: =Q50/M50-1 -> 0.16795249 | R67: =R50/N50-1 -> 0.044223804 | S67: =S50/O50-1 -> -0.38809798 | T67: =T50/P50-1 -> -0.5058868 | U67: =U50/Q50-1 -> -0.56811576 | V67: =V50/R50-1 -> -0.38544647 | W67: =W50/S50-1 -> 0.0070855042 | X67: =X50/T50-1 -> 0.33613442 | ... AG67: =AG50/AC50-1 -> 2.5550468
B68: Europe | D68: =D51/C51-1 -> -0.45131725 | E68: =E51/D51-1 -> 0.12503991 | F68: =F51/E51-1 -> 0.33993321 | G68: =G51/F51-1 -> -0.017924295 | H68: =H51/G51-1 -> -0.41912367 | I68: =I51/H51-1 -> 0.51161552 | J68: =J51/I51-1 -> 0.39964566 | Q68: =Q51/M51-1 -> 0.34110259 | R68: =R51/N51-1 -> 0.010719597 | S68: =S51/O51-1 -> 0.085028286 | T68: =T51/P51-1 -> -0.36177091 | U68: =U51/Q51-1 -> -0.67053105 | V68: =V51/R51-1 -> -0.48717457 | W68: =W51/S51-1 -> -0.48315736 | X68: =X51/T51-1 -> 0.10401642 | ... AG68: =AG51/AC51-1 -> 1.5114322
B69: Net cost of revenues | D69: =D52/C52-1 -> -0.33265697 | E69: =E52/D52-1 -> 0.18190262 | F69: =F52/E52-1 -> 0.3478755 | G69: =G52/F52-1 -> 0.037764172 | H69: =H52/G52-1 -> -0.26569772 | I69: =I52/H52-1 -> 1.0201895 | J69: =J52/I52-1 -> 0.46762851 | Q69: =Q52/M52-1 -> 0.43105533 | R69: =R52/N52-1 -> 0.33805863 | S69: =S52/O52-1 -> -0.069666957 | T69: =T52/P52-1 -> -0.3801185 | U69: =U52/Q52-1 -> -0.58142018 | V69: =V52/R52-1 -> -0.47100627 | W69: =W52/S52-1 -> -0.17451811 | X69: =X52/T52-1 -> 0.47359989 | ... AG69: =AG52/AC52-1 -> 1.9806603

Sheet Earnings Release
B2: SK Hynix Inc. | C2: Quarters | D2: Quarters | E2: Quarters | F2: Quarters | G2: Quarters | H2: Quarters | I2: Quarters | J2: Quarters | K2: Quarters | L2: Quarters
B3: (KRW billions) | C3: 45382 | D3: 45473 | E3: 45565 | F3: 45657 | G3: 45747 | H3: 45838 | I3: 45930 | J3: 46022 | K3: 46112 | L3: 46203
C4: Act | D4: Act | E4: Act | F4: Act | G4: Act | H4: Act | I4: Act | J4: Act | K4: Act | L4: Act
C5: 1Q | D5: 2Q | E5: 3Q | F5: 4Q | G5: 1Q | H5: 2Q | I5: 3Q | J5: 4Q | K5: 1Q | L5: 2Q
B6: INCOME STATEMENT
B8: Revenue | C8: 12430 | D8: 16423 | E8: 17573 | F8: 19767 | G8: 17639 | H8: 22232 | I8: 24449 | J8: 32827 | K8: 52576 | L8: 79319
B9: Cost of goods sold | C9: -7635 | D9: -8927 | E9: -8402 | F9: -9401 | G9: -7537 | H9: -10249 | I9: -10420 | J9: -10250 | K9: -10897 | L9: -13327
B10: Gross Profit | C10: 4795 | D10: 7496 | E10: 9171 | F10: 10366 | G10: 10102 | H10: 11983 | I10: 14029 | J10: 22576 | K10: 41679 | L10: 65991
B11: SG&A Expense | C11: -1909 | D11: -2028 | E11: -2141 | F11: -2283 | G11: -2661 | H11: -2770 | I11: -2646 | J11: -3407 | K11: -4069 | L11: -5449
B12: Operating Profit | C12: 2886 | D12: 5469 | E12: 7030 | F12: 8083 | G12: 7441 | H12: 9213 | I12: 11383 | J12: 19170 | K12: 37610 | L12: 60543
B13: Net Financial Profit/Loss | C13: -322 | D13: -275 | E13: -233 | F13: -170 | G13: -152 | H13: -129 | I13: -103 | J13: -46 | K13: 22 | L13: 150
B14: Net F/X Transaction & Translation P/L | C14: -215 | D14: -159 | E14: 18 | F14: 625 | G14: 122 | H14: -613 | I14: 209 | J14: -166 | K14: 1573 | L14: 1147
B15: Net Income(Expense) From Jointly Controlled Entities & Associates | C15: 6 | D15: 1 | E15: 7 | F15: -27 | G15: -41 | H15: 17 | I15: -23 | J15: -47 | K15: -27 | L15: -20
B16: Others | C16: 17 | D16: 17 | E16: 57 | F16: 1071 | G16: 1930 | H16: 234 | I16: 3324 | J16: -1258 | K16: 12438 | L16: 60889
B18: EBITDA | C18: 6073 | D18: 8591 | E18: 10100 | F18: 11249 | G18: 10769 | H18: 12645 | I18: 14949 | J18: 22732 | K18: 41336 | L18: 64563
B20: Income Before Tax | C20: 2373 | D20: 5052 | E20: 6879 | F20: 9581 | G20: 9299 | H20: 8723 | I20: 14790 | J20: 17653 | K20: 51617 | L20: 122708
B21: Tax Expense/Benefit | C21: -456 | D21: -932 | E21: -1126 | F21: -1575 | G21: -1191 | H21: -1726 | I21: -2193 | J21: -2407 | K21: -11271 | L21: -28786
B22: Net Profit | C22: 1917 | D22: 4120 | E22: 5753 | F22: 8006 | G22: 8108 | H22: 6996 | I22: 12598 | J22: 15246 | K22: 40346 | L22: 93923
B24: CASH FLOW STATEMENT
B26: Beginning Cash Balance | C26: 8921 | D26: 10319 | E26: 9688 | F26: 10858 | G26: 14156 | H26: 14311 | I26: 16962 | J26: 27854 | K26: 34942 | L26: 54330
B28: CF from Operating Activities | C28: 5385 | D28: 5697 | E28: 7804 | F28: 11081 | G28: 9075 | H28: 9208 | I28: 14368 | J28: 20939 | K28: 26430 | L28: 65710
B29: Net Profit (Loss) | C29: 1917 | D29: 4120 | E29: 5753 | F29: 8006 | G29: 8108 | H29: 6996 | I29: 12598 | J29: 15246 | K29: 40346 | L29: 93923
B30: D&A | C30: 3194 | D30: 3132 | E30: 3082 | F30: 3173 | G30: 3346 | H30: 3454 | I30: 3560 | J30: 3571 | K30: 3729 | L30: 4030
B31: Changes in Working Capital, etc. | C31: 274 | D31: -1554 | E31: -1032 | F31: -99 | G31: -2378 | H31: -1243 | I31: -1789 | J31: 2122 | K31: -17645 | L31: -32243
B33: CF from Investing Activities | C33: -3226 | D33: -2207 | E33: -3688 | F33: -7469 | G33: -9470 | H33: -4329 | I33: -5154 | J33: -12258 | K33: -7228 | L33: -28747
B34: Acquisition of PP&E | C34: -3103 | D34: -2079 | E34: -3516 | F34: -7248 | G34: -6284 | H34: -4332 | I34: -5033 | J34: -11871 | K34: -7657 | L34: -10671
B36: CF from Financing Activities | C36: -913 | D36: -4120 | E36: -2741 | F36: -930 | G36: 509 | H36: -1780 | I36: 1375 | J36: -1549 | K36: -2951 | L36: -4666
B37: Changes in Debt | C37: -783 | D37: -3601 | E37: -2401 | F37: -591 | G37: 645 | H37: -484 | I37: 1757 | J37: -1151 | K37: -2754 | L37: -3032
B38: Repayment of Lease Liability | C38: -161 | D38: -149 | E38: -149 | F38: -143 | G38: -152 | H38: -150 | I38: -145 | J38: -150 | K38: -148 | L38: -139
B39: Dividend Payout | C39: 0 | D39: -413 | E39: -207 | F39: -207 | G39: 0 | H39: -1159 | I39: -259 | J39: -263 | K39: 0 | L39: -1594
B40: Effect of F/X rate changes on Cash & Equivalents | C40: 151 | D40: -1 | E40: -205 | F40: 617 | G40: 41 | H40: -447 | I40: 303 | J40: -45 | K40: 3138 | L40: 1332
B42: Net Changes in Cash | C42: 1398 | D42: -631 | E42: 1170 | F42: 3298 | G42: 155 | H42: 2651 | I42: 10892 | J42: 7088 | K42: 19388 | L42: 33628
B43: Ending Cash Balance | C43: =C26+C42 -> 10319 | D43: =D26+D42 -> 9688 | E43: 10858 | F43: =F26+F42 -> 14156 | G43: =G26+G42 -> 14311 | H43: =H26+H42 -> 16962 | I43: 27854 | J43: =J26+J42 -> 34942 | K43: =K26+K42 -> 54330 | L43: =L26+L42 -> 87958
B45: BALANCE SHEET STATEMENT
B47: Current Assets | C47: 33026 | D47: 35684 | E47: 37078 | F47: 42279 | G47: 41228 | H47: 45203 | I47: 57140 | J47: 69458 | K47: 106506 | L47: 156156
B48: Cash & Cash Equivalents | C48: 10319 | D48: 9688 | E48: 10858 | F48: 14156 | G48: 14311 | H48: 16962 | I48: 27854 | J48: 34942 | K48: 54330 | L48: 87958
B49: Accounts Receivables | C49: 7179 | D49: 10224 | E49: 10471 | F49: 13019 | G49: 10629 | H49: 13125 | I49: 14312 | J49: 18199 | K49: 33808 | L49: 47821
B50: Inventories | C50: 13845 | D50: 13355 | E50: 13354 | F50: 13314 | G50: 14551 | H50: 13408 | I50: 13156 | J50: 14289 | K50: 15974 | L50: 17986
B52: Non-Current Assets | C52: 70171 | D52: 69941 | E52: 71289 | F52: 77576 | G52: 82757 | H52: 83885 | I52: 91295 | J52: 106650 | K52: 116323 | L52: 192706
B53: Property, Plant & Equipment | C53: 53164 | D53: 53232 | E53: 54634 | F53: 60157 | G53: 63015 | H53: 64473 | I53: 68145 | J53: 77503 | K53: 82052 | L53: 88889
B54: Intangible Assets | C54: 3830 | D54: 3840 | E54: 3926 | F54: 4019 | G54: 3963 | H54: 3945 | I54: 3954 | J54: 4049 | K54: 4051 | L54: 4283
B55: Total Assets | C55: 103198 | D55: 105624 | E55: 108367 | F55: 119855 | G55: 123985 | H55: 129088 | I55: 148435 | J55: 176108 | K55: 222829 | L55: 348862
B58: Liabilites
B59: Interest-bearing Debts | C59: 29506 | D59: 25228 | E59: 21845 | F59: 22684 | G59: 23334 | H59: 21841 | I59: 24079 | J59: 22248 | K59: 19318 | L59: 18587
B60: S-T Borrowings | C60: 3139 | D60: 1548 | E60: 1742 | F60: 1283 | G60: 2018 | H60: 1573 | I60: 2180 | J60: 2396 | K60: 2522 | L60: 2664
B61: Current Portion of L-T Borrowings | C61: 5707 | D61: 4727 | E61: 3399 | F61: 3969 | G61: 7061 | H61: 6949 | I61: 7070 | J61: 5766 | K61: 3369 | L61: 3194
B62: Bonds | C62: 11407 | D62: 12424 | E62: 11905 | F62: 12409 | G62: 10100 | H62: 9161 | I62: 11025 | J62: 11206 | K62: 10751 | L62: 10544
B63: L-T Borrowings | C63: 9254 | D63: 6530 | E63: 4799 | F63: 5022 | G63: 4154 | H63: 4158 | I63: 3804 | J63: 2880 | K63: 2676 | L63: 2184
B64: Accounts Payables | C64: 1747 | D64: 2093 | E64: 1890 | F64: 2277 | G64: 1875 | H64: 1806 | I64: 2270 | J64: 2848 | K64: 2798 | L64: 3043
B65: Total Liabilities | C65: 47690 | D65: 45794 | E65: 43066 | F65: 45940 | G65: 42547 | H65: 41945 | I65: 48429 | J65: 55441 | K65: 58449 | L65: 86169
B67: Shareholders' Equity
B68: Capital Stock | C68: 3658 | D68: 3658 | E68: 3658 | F68: 3658 | G68: 3658 | H68: 3658 | I68: 3658 | J68: 3658 | K68: 3658 | L68: 3658
B69: Capital Surplus | C69: 4406 | D69: 4420 | E69: 4479 | F69: 4487 | G69: 4715 | H69: 4726 | I69: 4757 | J69: 8954 | K69: 8510 | L69: 11876
B70: Retained Earnings | C70: 48392 | D70: 52302 | E70: 57842 | F70: 65418 | G70: 72622 | H70: 79358 | I70: 91691 | J70: 106577 | K70: 148746 | L70: 242270
B71: Total Shareholders' Equity | C71: 55507 | D71: 59830 | E71: 65302 | F71: 73916 | G71: 81439 | H71: 87142 | I71: 100006 | J71: 120667 | K71: 164380 | L71: 262693
B75: Gross Debt | C75: =C59 -> 29506 | D75: =D59 -> 25228 | E75: =E59 -> 21845 | F75: =F59 -> 22684 | G75: =G59 -> 23334 | H75: =H59 -> 21841 | I75: =I59 -> 24079 | J75: =J59 -> 22248 | ... L75: =L59 -> 18587
B76: Net debt | C76: =IF((C75-C48)<0,"net cash", (C75-C48)) -> 19187 | D76: =IF((D75-D48)<0,"net cash", (D75-D48)) -> 15540 | E76: =IF((E75-E48)<0,"net cash", (E75-E48)) -> 10987 | F76: =IF((F75-F48)<0,"net cash", (F75-F48)) -> 8528 | G76: =IF((G75-G48)<0,"net cash", (G75-G48)) -> 9023 | H76: =IF((H75-H48)<0,"net cash", (H75-H48)) -> 4879 | I76: =IF((I75-I48)<0,"net cash", (I75-I48)) -> net cash | J76: =IF((J75-J48)<0,"net cash", (J75-J48)) -> net cash | ... L76: =IF((L75-L48)<0,"net cash", (L75-L48)) -> net cash
B78: Annualized EBITDA | C78: =C18*4 -> 24292 | D78: =D18*4 -> 34364 | E78: =E18*4 -> 40400 | F78: =F18*4 -> 44996 | G78: =G18*4 -> 43076 | H78: =H18*4 -> 50580 | I78: =I18*4 -> 59796 | J78: =J18*4 -> 90928 | ... L78: =L18*4 -> 258252
B79: LTM EBITDA | F79: =SUM(C18:F18) -> 36013 | G79: =SUM(D18:G18) -> 40709 | H79: =SUM(E18:H18) -> 44763 | I79: =SUM(F18:I18) -> 49612 | J79: =SUM(G18:J18) -> 61095 | K79: =SUM(H18:K18) -> 91662 | L79: =SUM(I18:L18) -> 143580
B81: Gross Leverage (EBITDA Annualized) | C81: =C59/(C18*4) -> 1.2146386 | D81: =D59/(D18*4) -> 0.73414038 | E81: =E59/(E18*4) -> 0.54071782 | F81: =F59/(F18*4) -> 0.5041337 | G81: =G59/(G18*4) -> 0.54169375 | H81: =H59/(H18*4) -> 0.43181099 | I81: =I59/(I18*4) -> 0.4026858 | J81: =J59/(J18*4) -> 0.24467711 | ... L81: =L59/(L18*4) -> 0.071972337
B82: Net Leverage (EBITDA Annualized) | C82: =C76/C78 -> 0.78984851 | D82: =D76/D78 -> 0.45221744 | E82: =E76/E78 -> 0.27195545 | F82: =F76/F78 -> 0.18952796 | G82: =G76/G78 -> 0.20946699 | H82: =H76/H78 -> 0.096461052 | I82: =I76 -> net cash | J82: =J76 -> net cash | K82: =K76 -> net cash | L82: =L76 -> net cash
B84: Gross leverage (LTM EBITDA) | F84: =F59/F79 -> 0.62988365 | G84: =G59/G79 -> 0.5731902 | H84: =H59/H79 -> 0.4879253 | I84: =I59/I79 -> 0.48534629 | J84: =J59/J79 -> 0.36415419 | K84: =K59/K79 -> 0.21075255 | L84: =L59/L79 -> 0.12945396
B85: Net leverage (LTM EBITDA) | F85: =F76/F79 -> 0.23680338 | G85: =G76/G79 -> 0.22164632 | H85: =H76/H79 -> 0.10899627 | I85: =I76 -> net cash | J85: =J76 -> net cash | K85: =K76 -> net cash | L85: =L76 -> net cash
