Workbook
Name \A: #REF!
Name \B: #REF!
Name \C: #REF!
Name \L: #REF!
Name \M: #REF!
Name \P: #REF!
Name \Y: #REF!
Name _01_30_04: MonthlyOpStats
Name _01_30_04: MonthlyOpStats
Name _1_30_01: MonthlyOpStats
Name _1_30_01: MonthlyOpStats
Name _1_30_02: MonthlyOpStats
Name _1_30_02: MonthlyOpStats
Name _1_31_01: MonthlyOpStats
Name _1_31_01: MonthlyOpStats
Name _1_31_02: MonthlyOpStats
Name _1_31_02: MonthlyOpStats
Name _12_31_05: MonthlyOpStats
Name _12_31_05: MonthlyOpStats
Name _A: #REF!
Name _A___0: #REF!
Name _B: #REF!
Name _B___0: #REF!
Name _C: #REF!
Name _C___0: #REF!
Name _ent1: [1]Inputs!$J$17
Name _ent10: [1]Inputs!$J$476
Name _ent11: [1]Inputs!$J$527
Name _ent12: [1]Inputs!$J$578
Name _ent13: [1]Inputs!$J$629
Name _ent14: [1]Inputs!$J$680
Name _ent15: [1]Inputs!$J$731
Name _ent2: [1]Inputs!$J$68
Name _ent3: [1]Inputs!$J$119
Name _ent4: [1]Inputs!$J$170
Name _ent5: [1]Inputs!$J$221
Name _ent6: [1]Inputs!$J$272
Name _ent7: [1]Inputs!$J$323
Name _ent8: [1]Inputs!$J$374
Name _ent9: [1]Inputs!$J$425
Name _eps1: [1]Inputs!$P$42
Name _eps10: [1]Inputs!$P$501
Name _eps11: [1]Inputs!$P$552
Name _eps12: [1]Inputs!$P$603
Name _eps13: [1]Inputs!$P$654
Name _eps14: [1]Inputs!$P$705
Name _eps15: [1]Inputs!$P$756
Name _eps2: [1]Inputs!$P$93
Name _eps3: [1]Inputs!$P$144
Name _eps4: [1]Inputs!$P$195
Name _eps5: [1]Inputs!$P$246
Name _eps6: [1]Inputs!$P$297
Name _eps7: [1]Inputs!$P$348
Name _eps8: [1]Inputs!$P$399
Name _eps9: [1]Inputs!$P$450
Name _fye1: [1]Inputs!$E$12
Name _fye10: [1]Inputs!$E$471
Name _fye11: [1]Inputs!$E$522
Name _fye12: [1]Inputs!$E$573
Name _fye13: [1]Inputs!$E$624

Sheet Capitalisation
A2: 4Q26 | J2: Exchange rate as at end 4Q26 | K2: =Model!$AE$207 -> 0.010696903
J3: Average Exchange rate of 4Q26 | K3: =Model!$AE$208 -> 0.011317886
B5: Debt Breakdown as on 31-Mar-2026 | C5: INR mn | D5: Leverage | E5: USD mn | F5: Leverage | J5: Company Reported | K5: INR mn
B6: Loans | C6: =SUM(C7:C10) -> 322770 | E6: =SUM(E7:E10) -> 3452.6395 | J6: Gross Debt | K6: 220450
B7: Current | C7: =Model!$AE$107 -> 65110 | E7: =C7*$K2 -> 696.47537 | J7: Cash and cash equivalent | K7: 67200
B8: Non current | C8: =Model!$AE$108 -> 155350 | E8: =C8*$K2 -> 1661.7639 | J8: Net debt | K8: 153250
B9: Receivable factoring | C9: =Model!$AE$119 -> 102310 | E9: =C9*$K2 -> 1094.4002 | J9: Net debt / EBITDA | K9: 1.6x
B10: 50% of Hybrid | C10: =Model!$AE$126/2 -> 0 | E10: =C10*$K2 -> 0
B12: Operating lease liabilities | C12: =SUM(C13:C14) -> 15300 | E12: =SUM(E13:E14) -> 163.66262
B13: Current | C13: =Model!AE112 -> 5090 | E13: =C13*$K2 -> 54.447238
B14: Non current | C14: =Model!AE113 -> 10210 | E14: =C14*$K2 -> 109.21538
B15: Total Loans & Borrowings | C15: =C12+C6 -> 338070 | D15: =C15/C21 -> 3.52597 | E15: =E12+E6 -> 3616.3021 | F15: =E15/E21 -> 3.3325093
B16: Cash and Cash Equivalents | C16: =Model!$AE$121 -> 60860 | E16: =C16*$K2 -> 651.01353
B17: Investments | C17: =Model!$AE$122 -> 6340 | E17: =C17*$K2 -> 67.818367
B18: Net debt | C18: =C15-C16-C17 -> 270870 | D18: =C18/C21 -> 2.8250939 | E18: =E15-E16-E17 -> 2897.4702 | F18: =E18/E21 -> 2.6700884
B19: Equity | C19: =Model!$AE$127 -> 346960 | E19: =C19*$K2 -> 3711.3976
B20: Total Capitalisation | C20: =C18+C19 -> 617830 | E20: =C20*$K2 -> 6608.8677
B21: LTM Adjusted EBITDA | C21: =Model!$AE$85 -> 95880 | E21: =C21*$K3 -> 1085.1589
B22: check | C22: =+C15-Model!$AE$120 -> 0
B25: LT Debt Maturity Breakdown at 4Q26 (from BBG) | C25: INR mn | D25: USD mn
B26: 2026 | C26: 47138.68 | D26: =C26*$K$2 -> 504.2379
B27: 2027 | C27: 52138.68 | D27: =C27*$K$2 -> 557.72242
B28: 2028 | C28: 28358.21 | D28: =C28*$K$2 -> 303.34503
B29: 2029 | C29: 66094.15 | D29: =C29*$K$2 -> 707.00273
B30: 2030 | C30: 48338.68 | D30: =C30*$K$2 -> 517.07418
B31: 2031 | C31: 145 | D31: =C31*$K$2 -> 1.551051
B32: 2032 | C32: 1690 | D32: =C32*$K$2 -> 18.077766
B33: Total | C33: =SUM(C26:C32) -> 243903.4 | D33: =SUM(D26:D32) -> 2609.0111
A40: 3Q26 | J40: Exchange rate as at end 3Q26 | K40: =Model!$J$207 -> 0.010696903
J41: Average Exchange rate of 3Q26 | K41: =Model!$J$208 -> 0.011317886
B43: Debt Breakdown as on 31-Dec-2025 | C43: INR mn | D43: Leverage | E43: USD mn | F43: Leverage | J43: Company Reported | K43: INR mn
B44: Loans | C44: =SUM(C45:C48) -> 339650 | E44: =SUM(E45:E48) -> 3633.2032 | J44: Gross Debt | K44: 284640
B45: Current | C45: =Model!$AD$107 -> 175070 | E45: =C45*$K40 -> 1872.7069 | J45: Cash and cash equivalent | K45: 51470
B46: Non current | C46: =Model!$AD$108 -> 109570 | E46: =C46*$K40 -> 1172.0597 | J46: Net debt | K46: 233170
B47: Receivable factoring | C47: =Model!$AD$119 -> 55010 | E47: =C47*$K40 -> 588.43665 | J47: Net debt / EBITDA | K47: 2.5x
B48: 50% of Hybrid | C48: =Model!$AD$126/2 -> 0 | E48: =C48*$K40 -> 0
B49: Operating lease liabilities | C49: =SUM(C50:C51) -> 0 | E49: =SUM(E50:E51) -> 0
B50: Current
B51: Non current
B52: Total Loans & Borrowings | C52: =C49+C44 -> 339650 | D52: =C52/C58 -> 3.7006973 | E52: =E49+E44 -> 3633.2032 | F52: =E52/E58 -> 3.4976499
B53: Cash and Cash Equivalents | C53: =Model!$AD$121 -> 45950 | E53: =C53*$K40 -> 491.5227
B54: Investments | C54: =Model!$AD$122 -> 5520 | E54: =C54*$K40 -> 59.046906
B55: Net debt | C55: =C52-C53-C54 -> 288180 | D55: =C55/C58 -> 3.1398998 | E55: =E52-E53-E54 -> 3082.6336 | F55: =E55/E58 -> 2.9676218
B56: Equity | C56: =Model!$AD$127 -> 326110 | E56: =C56*$K40 -> 3488.3671
B57: Total Capitalisation | C57: =C55+C56 -> 614290 | E57: =C57*$K40 -> 6571.0007
B58: LTM Adjusted EBITDA | C58: =Model!$AD$85 -> 91780 | E58: =C58*$K41 -> 1038.7555
B59: check | C59: =+C52-Model!$AD$120 -> 55010
B62: LT Debt Maturity Breakdown at 3Q26 (from BBG) | C62: INR mn | D62: USD mn
B63: 2026 | C63: 98587.67 | D63: =C63*$K$40 -> 1054.5828
B64: 2027 | C64: 50854.73 | D64: =C64*$K$40 -> 543.98813
B65: 2028 | C65: 27587.84 | D65: =C65*$K$40 -> 295.10446
B66: 2029 | C66: 100 | D66: =C66*$K$40 -> 1.0696903
B67: 2030 | C67: 47054.73 | D67: =C67*$K$40 -> 503.33989
B68: 2031 | C68: 145 | D68: =C68*$K$40 -> 1.551051
B69: 2032 | C69: 1690 | D69: =C69*$K$40 -> 18.077766
B70: Total | C70: =SUM(C63:C69) -> 226019.97 | D70: =SUM(D63:D69) -> 2417.7138
A76: 2Q26 | J76: Exchange rate as at end 2Q26 | K76: =Model!$AC$207 -> 0.011256064
J77: Average Exchange rate of 2Q26 | K77: =Model!$AC$208 -> 0.01163062
B79: Debt Breakdown as on 30-Sep-2025 | C79: INR mn | D79: Leverage | E79: USD mn | F79: Leverage | J79: Company Reported | K79: INR mn
B80: Loans | C80: =SUM(C81:C84) -> 334730 | E80: =SUM(E81:E84) -> 3767.7424 | J80: Gross Debt | K80: 285620
B81: Current | C81: 113530 | E81: =C81*$K76 -> 1277.901 | J81: Cash and cash equivalent | K81: 47600
B82: Non current | C82: 172090 | E82: =C82*$K76 -> 1937.0561 | J82: Net debt | K82: 238020
B83: Receivable factoring | C83: =Model!$AC$119 -> 49110 | E83: =C83*$K76 -> 552.78531 | J83: Net debt / EBITDA | K83: 2.7x
B84: 50% of Hybrid | C84: =Model!$AC$126/2 -> 0 | E84: =C84*$K76 -> 0
B85: Operating lease liabilities | C85: =SUM(C86:C87) -> 14600 | E85: =SUM(E86:E87) -> 164.33854
B86: Current | C86: 4320 | E86: =C86*$K76 -> 48.626197
B87: Non current | C87: 10280 | E87: =C87*$K76 -> 115.71234
B88: Total Loans & Borrowings | C88: =C85+C80 -> 349330 | D88: =C88/C94 -> 3.9219715 | E88: =E85+E80 -> 3932.0809 | F88: =E88/E94 -> 3.7956672
B89: Cash and Cash Equivalents | C89: =Model!$AC$121 -> 41520 | E89: =C89*$K76 -> 467.35179
B90: Investments | C90: =Model!$AC$122 -> 6080 | E90: =C90*$K76 -> 68.43687
B91: Net debt | C91: =C88-C89-C90 -> 301730 | D91: =C91/C94 -> 3.3875603 | E91: =E88-E89-E90 -> 3396.2923 | F91: =E91/E94 -> 3.2784664
B92: Equity | C92: =Model!$AC$127 -> 318940 | E92: =C92*$K76 -> 3590.0091
B93: Total Capitalisation | C93: =C91+C92 -> 620670 | E93: =C93*$K76 -> 6986.3014
B94: LTM Adjusted EBITDA | C94: =Model!$AC$85 -> 89070 | E94: =C94*$K77 -> 1035.9393
B95: check | C95: =+C88-Model!$AC$120 -> 49110
B98: LT Debt Maturity Breakdown at 2Q26 (from BBG) | C98: INR mn | D98: USD mn
B99: 2026 | C99: 96629.21 | D99: =C99*$K$76 -> 1087.6646
B100: 2027 | C100: 49943.82 | D100: =C100*$K$76 -> 562.17084
B101: 2028 | C101: 27041.29 | D101: =C101*$K$76 -> 304.3785
B102: 2029 | C102: 100 | D102: =C102*$K$76 -> 1.1256064
B103: 2030 | C103: 46143.82 | D103: =C103*$K$76 -> 519.3978
B104: 2031 | C104: 145 | D104: =C104*$K$76 -> 1.6321293
B105: 2032 | C105: 1690 | D105: =C105*$K$76 -> 19.022749
B106: Total | C106: =SUM(C99:C105) -> 221693.14 | D106: =SUM(D99:D105) -> 2495.3922
A111: 1Q26 | J111: Exchange rate as at end 1Q26 | K111: =Model!$AB$207 -> 0.011660448
J112: Average Exchange rate of 1Q26 | K112: =Model!$AB$208 -> 0.011758492
B114: Debt Breakdown as on 30-Jun-2025 | C114: INR mn | D114: Leverage | E114: USD mn | F114: Leverage | J114: Company Reported | K114: INR mn
B115: Loans | E115: =SUM(E116:E119) -> 0 | J115: Gross Debt | K115: 268350
B116: Current | E116: =C116*$K111 -> 0 | J116: Cash and cash equivalent | K116: 54640
B117: Non current | E117: =C117*$K111 -> 0 | J117: Net debt | K117: 213710
B118: Receivable factoring | E118: =C118*$K111 -> 0 | J118: Net debt / EBITDA | K118: 2.6x
B119: 50% of Hybrid | E119: =C119*$K111 -> 0
B120: Operating lease liabilities | E120: =SUM(E121:E122) -> 0
B121: Current | E121: =C121*$K111 -> 0
B122: Non current | E122: =C122*$K111 -> 0
B123: Total Loans & Borrowings | C123: =Model!AB120 -> 268350 | D123: =C123/C129 -> 3.2417251 | E123: =C123*K111 -> 3129.0812 | F123: =E123/E129 -> 3.2417251
B124: Cash and Cash Equivalents | C124: =Model!$AB$121 -> 49980 | E124: =C124*$K111 -> 582.78918
B125: Investments | C125: =Model!$AB$122 -> 4660 | E125: =C125*$K111 -> 54.337687
B126: Net debt | C126: =C123-C124-C125 -> 213710 | D126: =C126/C129 -> 2.5816622 | E126: =E123-E124-E125 -> 2491.9543 | F126: =E126/E129 -> 2.5816622
B127: Equity | C127: =Model!$AB$127 -> 0 | E127: =C127*$K111 -> 0
...

Sheet Model
B2: UPL Ltd | C2: Annual | D2: Annual | E2: Annual | F2: Annual | G2: Annual | H2: Annual | I2: Annual | J2: LTM | L2: Quarters | M2: Quarters | N2: Quarters | O2: Quarters | P2: Quarters | Q2: Quarters | R2: Quarters | S2: Quarters | T2: Quarters | U2: Quarters | V2: Quarters | W2: Quarters | X2: Quarters | Y2: Quarters | Z2: Quarters | AA2: Quarters | AB2: Quarters | AC2: Quarters | AD2: Quarters | AE2: Quarters
B3: (INR million) | C3: 43921 | D3: 44286 | E3: 44651 | F3: 45016 | G3: 45382 | H3: 45747 | I3: 46112 | J3: =AE3 -> 46112 | L3: 44377 | M3: 44469 | N3: 44561 | O3: 44651 | P3: 44742 | Q3: 44834 | R3: 44926 | S3: 45016 | T3: 45107 | U3: 45199 | V3: 45291 | W3: 45382 | X3: 45473 | Y3: 45565 | Z3: 45657 | AA3: 45747 | AB3: 45838 | AC3: 45930 | AD3: 46022 | AE3: 46112
C4: Act | D4: Act | E4: Act | F4: Act | G4: Act | H4: Act | I4: Act | J4: Act | L4: Act | M4: Act | N4: Act | O4: Act | P4: Act | Q4: Act | R4: Act | S4: Act | T4: Act | U4: Act | V4: Act | W4: Act | X4: Act | Y4: Act | Z4: Act | AA4: Act | AB4: Act | AC4: Act | AD4: Act | AE4: Act
C5: FY | D5: FY | E5: FY | F5: FY | G5: FY | H5: FY | I5: FY | J5: LTM | L5: 1Q | M5: 2Q | N5: 3Q | O5: 4Q | P5: 1Q | Q5: 2Q | R5: 3Q | S5: 4Q | T5: 1Q | U5: 2Q | V5: 3Q | W5: 4Q | X5: 1Q | Y5: 2Q | Z5: 3Q | AA5: 4Q | AB5: 1Q | AC5: 2Q | AD5: 3Q | AE5: 4Q
B6: INCOME STATEMENT
B7: Revenue from Operations | C7: 357560 | D7: 386940 | E7: 462400 | F7: 535760 | G7: 430980 | H7: 466370 | I7: 518390 | J7: =SUM(AB7:AE7) -> 518390 | L7: 85150 | M7: 105670 | N7: 112970 | O7: =E7-SUM(L7:N7) -> 158610 | P7: 108210 | Q7: 125070 | R7: 136790 | S7: =F7-SUM(P7:R7) -> 165690 | T7: 89630 | U7: 101700 | V7: 98870 | W7: =G7-SUM(T7:V7) -> 140780 | X7: 90670 | Y7: 110900 | Z7: 109070 | AA7: =H7-SUM(X7:Z7) -> 155730 | AB7: 92160 | AC7: 120190 | AD7: 122690 | AE7: =I7-SUM(AB7:AD7) -> 183350
B8: Other income | C8: 1040 | D8: 2580 | E8: 2810 | F8: 4770 | G8: 4830 | H8: 4860 | I8: 6630 | J8: =SUM(AB8:AE8) -> 6630 | L8: 480 | M8: 470 | N8: 700 | O8: =E8-SUM(L8:N8) -> 1160 | P8: 730 | Q8: 780 | R8: 1150 | S8: =F8-SUM(P8:R8) -> 2110 | T8: 1010 | U8: 1050 | V8: 1510 | W8: =G8-SUM(T8:V8) -> 1260 | X8: 980 | Y8: 1110 | Z8: 1700 | AA8: =H8-SUM(X8:Z8) -> 1070 | AB8: 1430 | AC8: 2500 | AD8: 920 | AE8: =I8-SUM(AB8:AD8) -> 1780
B9: % of growth | D9: =(D7/C7)-1 -> 0.082168028 | E9: =(E7/D7)-1 -> 0.19501732 | F9: =(F7/E7)-1 -> 0.15865052 | G9: =(G7/F7)-1 -> -0.19557264 | H9: =(H7/G7)-1 -> 0.082115179 | I9: =(I7/H7)-1 -> 0.11154234
B10: Cost of revenue | C10: -187430 | D10: -190960 | E10: -220720 | F10: -272810 | G10: -244940 | H10: -242230 | I10: =-239280-38080+18450 -> -258910 | J10: =SUM(AB10:AE10) -> -258910 | L10: -37030 | M10: -52210 | N10: -51540 | O10: =E10-SUM(L10:N10) -> -79940 | P10: -49190 | Q10: -57810 | R10: -66220 | S10: =F10-SUM(P10:R10) -> -99590 | T10: -39300 | U10: -52320 | V10: -63230 | W10: =G10-SUM(T10:V10) -> -90090 | X10: -45200 | Y10: -58230 | Z10: -53290 | AA10: =H10-SUM(X10:Z10) -> -85510 | AB10: -41690 | AC10: -57530 | AD10: -58460 | AE10: =I10-SUM(AB10:AD10) -> -101230
B11: Gross Profit | C11: =C7+C8+C10 -> 171170 | D11: =D7+D8+D10 -> 198560 | E11: =E7+E8+E10 -> 244490 | F11: =F7+F8+F10 -> 267720 | G11: =G7+G8+G10 -> 190870 | H11: =H7+H8+H10 -> 229000 | I11: =I7+I8+I10 -> 266110 | J11: =J7+J8+J10 -> 266110 | L11: =L7+L8+L10 -> 48600 | M11: =M7+M8+M10 -> 53930 | N11: =N7+N8+N10 -> 62130 | O11: =O7+O8+O10 -> 79830 | P11: =P7+P8+P10 -> 59750 | Q11: =Q7+Q8+Q10 -> 68040 | R11: =R7+R8+R10 -> 71720 | S11: =S7+S8+S10 -> 68210 | ... AE11: =AE7+AE8+AE10 -> 83900
B12: Gross Profit margin | C12: =C11/C7 -> 0.47871686 | D12: =D11/D7 -> 0.51315449 | E12: =E11/E7 -> 0.52874135 | F12: =F11/F7 -> 0.49970136 | G12: =G11/G7 -> 0.44287438 | H12: =H11/H7 -> 0.49102644 | I12: =I11/I7 -> 0.51333938 | J12: =J11/J7 -> 0.51333938 | L12: =L11/L7 -> 0.57075749 | M12: =M11/M7 -> 0.51036245 | N12: =N11/N7 -> 0.54996902 | O12: =O11/O7 -> 0.50331001 | P12: =P11/P7 -> 0.55216708 | Q12: =Q11/Q7 -> 0.54401535 | R12: =R11/R7 -> 0.52430733 | S12: =S11/S7 -> 0.4116724 | ... AE12: =AE11/AE7 -> 0.45759476
B13: Operating expenses:
B14: Employee benefit expense | C14: -33910 | D14: -37120 | E14: -46220 | F14: -50560 | G14: -46820 | H14: -53090 | I14: -58070 | J14: =SUM(AB14:AE14) -> -58070 | L14: -10300 | M14: -10790 | N14: -11660 | O14: =E14-SUM(L14:N14) -> -13470 | P14: -12440 | Q14: -12330 | R14: -13210 | S14: =F14-SUM(P14:R14) -> -12580 | T14: -12400 | U14: -12510 | V14: -11550 | W14: =G14-SUM(T14:V14) -> -10360 | X14: -13370 | Y14: -13370 | Z14: -11840 | AA14: =H14-SUM(X14:Z14) -> -14510 | AB14: -13220 | AC14: -14660 | AD14: -13790 | AE14: =I14-SUM(AB14:AD14) -> -16400
B15: Impairment loss/(writeback) on trade receivables | C15: -490 | D15: -800 | E15: 150 | F15: -1230 | G15: -910 | H15: -2400 | I15: -7500 | J15: =SUM(AB15:AE15) -> -7500 | L15: 370 | M15: -580 | N15: 250 | O15: =E15-SUM(L15:N15) -> 110 | P15: -330 | Q15: -500 | R15: -80 | S15: =F15-SUM(P15:R15) -> -320 | T15: -630 | U15: -380 | V15: -140 | W15: =G15-SUM(T15:V15) -> 240 | X15: -870 | Y15: -1520 | Z15: 190 | AA15: =H15-SUM(X15:Z15) -> -200 | AB15: -1920 | AC15: -1140 | AD15: -650 | AE15: =I15-SUM(AB15:AD15) -> -3790
B16: Depreciation and Amortisation expense | C16: -20120 | D16: -21730 | E16: -23590 | F16: -25470 | G16: -27630 | H16: -27500 | I16: -32440 | J16: =SUM(AB16:AE16) -> -32440 | L16: -5510 | M16: -5660 | N16: -6000 | O16: =E16-SUM(L16:N16) -> -6420 | P16: -5880 | Q16: -6080 | R16: -6240 | S16: =F16-SUM(P16:R16) -> -7270 | T16: -6360 | U16: -6570 | V16: -6760 | W16: =G16-SUM(T16:V16) -> -7940 | X16: -6600 | Y16: -6970 | Z16: -6880 | AA16: =H16-SUM(X16:Z16) -> -7050 | AB16: -7310 | AC16: -7710 | AD16: -8270 | AE16: =I16-SUM(AB16:AD16) -> -9150
B17: Exchange difference on trade receivables and trade payables | C17: -3310 | D17: -2070 | E17: -6360 | F17: -9640 | G17: -9760 | H17: -5200 | I17: -3160 | J17: =SUM(AB17:AE17) -> -3160 | L17: -890 | M17: -1140 | N17: -2210 | O17: =E17-SUM(L17:N17) -> -2120 | P17: -1970 | Q17: -3240 | R17: -1500 | S17: =F17-SUM(P17:R17) -> -2930 | T17: -3190 | U17: -2500 | V17: -3230 | W17: =G17-SUM(T17:V17) -> -840 | X17: -450 | Y17: -2230 | Z17: -2060 | AA17: =H17-SUM(X17:Z17) -> -460 | AB17: 930 | AC17: -2040 | AD17: -1160 | AE17: =I17-SUM(AB17:AD17) -> -890
B18: Operating profit | C18: =C11+SUM(C14:C17) -> 113340 | D18: =D11+SUM(D14:D17) -> 136840 | E18: =E11+SUM(E14:E17) -> 168470 | F18: =F11+SUM(F14:F17) -> 180820 | G18: =G11+SUM(G14:G17) -> 105750 | H18: =H11+SUM(H14:H17) -> 140810 | I18: =I11+SUM(I14:I17) -> 164940 | J18: =J11+SUM(J14:J17) -> 164940 | L18: =L11+SUM(L14:L17) -> 32270 | M18: =M11+SUM(M14:M17) -> 35760 | N18: =N11+SUM(N14:N17) -> 42510 | O18: =O11+SUM(O14:O17) -> 57930 | P18: =P11+SUM(P14:P17) -> 39130 | Q18: =Q11+SUM(Q14:Q17) -> 45890 | R18: =R11+SUM(R14:R17) -> 50690 | S18: =S11+SUM(S14:S17) -> 45110 | ... AE18: =AE11+SUM(AE14:AE17) -> 53670
B19: Finance cost | C19: -14810 | D19: -20600 | E19: -22950 | F19: -29630 | G19: -38520 | H19: -36270 | I19: -34010 | J19: =SUM(AB19:AE19) -> -34010 | L19: -6070 | M19: -3590 | N19: -5290 | O19: =E19-SUM(L19:N19) -> -8000 | P19: -5190 | Q19: -6440 | R19: -8940 | S19: =F19-SUM(P19:R19) -> -9060 | T19: -7000 | U19: -8710 | V19: -11910 | W19: =G19-SUM(T19:V19) -> -10900 | X19: -9130 | Y19: -10700 | Z19: -7300 | AA19: =H19-SUM(X19:Z19) -> -9140 | AB19: -10070 | AC19: -7840 | AD19: -7740 | AE19: =I19-SUM(AB19:AD19) -> -8360
B20: Other Expenses | C20: -64690 | D20: -72470 | E20: -93960 | F20: -99560 | G20: -83160 | H20: -87450 | I20: -98030 | J20: =SUM(AB20:AE20) -> -98030 | L20: -19560 | M20: -21640 | N20: -23370 | O20: =E20-SUM(L20:N20) -> -29390 | P20: -22820 | Q20: -26750 | R20: -26940 | S20: =F20-SUM(P20:R20) -> -23050 | T20: -21380 | U20: -20740 | V20: -19790 | W20: =G20-SUM(T20:V20) -> -21250 | X20: -19770 | Y20: -22030 | Z20: -22510 | AA20: =H20-SUM(X20:Z20) -> -23140 | AB20: -22300 | AC20: -24810 | AD20: -25460 | AE20: =I20-SUM(AB20:AD20) -> -25460
B21: Share of profit/loss from Associates/ JV | C21: 30 | D21: 420 | E21: 1340 | F21: 1570 | G21: -2420 | H21: -4720 | I21: -1940 | J21: =SUM(AB21:AE21) -> -1940 | L21: -40 | M21: 100 | N21: 140 | O21: =E21-SUM(L21:N21) -> 1140 | P21: 300 | Q21: -270 | R21: 340 | S21: =F21-SUM(P21:R21) -> 1200 | T21: -570 | U21: -2040 | V21: -260 | W21: =G21-SUM(T21:V21) -> 450 | X21: -320 | Y21: -1350 | Z21: -2780 | AA21: =H21-SUM(X21:Z21) -> -270 | AB21: 180 | AC21: -540 | AD21: -810 | AE21: =I21-SUM(AB21:AD21) -> -770
B22: Exceptional items | C22: -6230 | D22: -2380 | E22: -3240 | F22: -1700 | G22: -2520 | H22: -4080 | I22: 610 | J22: =SUM(AB22:AE22) -> 610 | L22: -630 | M22: -400 | N22: -530 | O22: =E22-SUM(L22:N22) -> -1680 | P22: -780 | Q22: -430 | R22: -200 | S22: =F22-SUM(P22:R22) -> -290 | T22: -430 | U22: -870 | V22: -170 | W22: =G22-SUM(T22:V22) -> -1050 | X22: -490 | Y22: -80 | Z22: -760 | AA22: =H22-SUM(X22:Z22) -> -2750 | AB22: -90 | AC22: =(((142)/10)*10)*10 -> 1420 | AD22: -560 | AE22: =I22-SUM(AB22:AD22) -> -160
B23: Profit / (Loss) before tax | C23: =C18+SUM(C19:C22) -> 27640 | D23: =D18+SUM(D19:D22) -> 41810 | E23: =E18+SUM(E19:E22) -> 49660 | F23: =F18+SUM(F19:F22) -> 51500 | G23: =G18+SUM(G19:G22) -> -20870 | H23: =H18+SUM(H19:H22) -> 8290 | I23: =I18+SUM(I19:I22) -> 31570 | J23: =J18+SUM(J19:J22) -> 31570 | L23: =L18+SUM(L19:L22) -> 5970 | M23: =M18+SUM(M19:M22) -> 10230 | N23: =N18+SUM(N19:N22) -> 13460 | O23: =O18+SUM(O19:O22) -> 20000 | P23: =P18+SUM(P19:P22) -> 10640 | Q23: =Q18+SUM(Q19:Q22) -> 12000 | R23: =R18+SUM(R19:R22) -> 14950 | S23: =S18+SUM(S19:S22) -> 13910 | ... AE23: =AE18+SUM(AE19:AE22) -> 18920
B24: Tax expenses | C24: -5860 | D24: -6860 | E24: -5290 | F24: -7360 | G24: 2090 | H24: =(-295+286)*10 -> -90 | I24: =-(1243-306)*10 -> -9370 | J24: =SUM(AB24:AE24) -> -9370 | L24: 1520 | M24: -2490 | N24: -1670 | O24: =E24-SUM(L24:N24) -> -2650 | P24: -590 | Q24: -2310 | R24: -1350 | S24: =F24-SUM(P24:R24) -> -3110 | T24: 1640 | U24: 960 | V24: 590 | W24: =G24-SUM(T24:V24) -> -1100 | X24: -720 | Y24: -1380 | Z24: 4990 | AA24: =H24-SUM(X24:Z24) -> -2980 | AB24: 140 | AC24: -1720 | AD24: -1810 | AE24: =I24-SUM(AB24:AD24) -> -5980
B25: Net profit/ (Loss) | C25: =+C23+C24 -> 21780 | D25: =+D23+D24 -> 34950 | E25: =+E23+E24 -> 44370 | F25: =+F23+F24 -> 44140 | G25: =+G23+G24 -> -18780 | H25: =+H23+H24 -> 8200 | I25: =+I23+I24 -> 22200 | J25: =+J23+J24 -> 22200 | L25: =+L23+L24 -> 7490 | M25: =+M23+M24 -> 7740 | N25: =+N23+N24 -> 11790 | O25: =+O23+O24 -> 17350 | P25: =+P23+P24 -> 10050 | Q25: =+Q23+Q24 -> 9690 | R25: =+R23+R24 -> 13600 | S25: =+S23+S24 -> 10800 | ... AE25: =+AE23+AE24 -> 12940
B26: % margin | C26: =+C25/C7 -> 0.060912854 | D26: =+D25/D7 -> 0.090324081 | E26: =+E25/E7 -> 0.095955882 | F26: =+F25/F7 -> 0.082387636 | G26: =+G25/G7 -> -0.043575108 | H26: =+H25/H7 -> 0.017582606 | I26: =+I25/I7 -> 0.0428249 | J26: =+J25/J7 -> 0.0428249 | L26: =+L25/L7 -> 0.087962419 | M26: =+M25/M7 -> 0.073246901 | N26: =+N25/N7 -> 0.10436399 | O26: =+O25/O7 -> 0.10938781 | P26: =+P25/P7 -> 0.092874965 | Q26: =+Q25/Q7 -> 0.077476613 | R26: =+R25/R7 -> 0.099422472 | S26: =+S25/S7 -> 0.065181966 | ... AE26: =+AE25/AE7 -> 0.070575402
B27: Non-controlling interest | C27: 0 | D27: 0 | E27: -8110 | F27: -8440 | G27: 6780 | H27: 770 | I27: -2980 | J27: =SUM(AB27:AE27) -> -2980 | L27: 0 | M27: 0 | N27: -2430 | O27: =E27-SUM(L27:N27) -> -5680 | P27: 0 | Q27: -1550 | R27: -2730 | S27: =F27-SUM(P27:R27) -> -4160 | T27: 640 | U27: 1040 | V27: 3900 | W27: 1200 | X27: 1430 | Y27: 1420 | Z27: -250 | AA27: =H27-SUM(X27:Z27) -> -1830 | AB27: 880 | AC27: -590 | AD27: -940 | AE27: =I27-SUM(AB27:AD27) -> -2330
B28: Net profit/loss | C28: =+C25+SUM(C27:C27) -> 21780 | D28: =+D25+SUM(D27:D27) -> 34950 | E28: =+E25+SUM(E27:E27) -> 36260 | F28: =+F25+SUM(F27:F27) -> 35700 | G28: =+G25+SUM(G27:G27) -> -12000 | H28: =+H25+SUM(H27:H27) -> 8970 | I28: =+I25+SUM(I27:I27) -> 19220 | J28: =+J25+SUM(J27:J27) -> 19220 | L28: =+L25+SUM(L27:L27) -> 7490 | M28: =+M25+SUM(M27:M27) -> 7740 | N28: =+N25+SUM(N27:N27) -> 9360 | O28: =+O25+SUM(O27:O27) -> 11670 | P28: =+P25+SUM(P27:P27) -> 10050 | Q28: =+Q25+SUM(Q27:Q27) -> 8140 | R28: =+R25+SUM(R27:R27) -> 10870 | S28: =+S25+SUM(S27:S27) -> 6640 | ... AE28: =+AE25+SUM(AE27:AE27) -> 10610
B30: As % of Revenues unless stated otherwise
B31: =B14 -> Employee benefit expense | C31: =-C14/C7 -> 0.09483723 | D31: =-D14/D7 -> 0.095932186 | E31: =-E14/E7 -> 0.099956747 | F31: =-F14/F7 -> 0.094370614 | G31: =-G14/G7 -> 0.10863613 | H31: =-H14/H7 -> 0.11383665 | I31: =-I14/I7 -> 0.11201991 | J31: =-J14/J7 -> 0.11201991 | L31: =-L14/L7 -> 0.12096301 | M31: =-M14/M7 -> 0.10211034 | N31: =-N14/N7 -> 0.10321324 | O31: =-O14/O7 -> 0.084925288 | P31: =-P14/P7 -> 0.11496165 | Q31: =-Q14/Q7 -> 0.098584793 | R31: =-R14/R7 -> 0.096571387 | S31: =-S14/S7 -> 0.07592492 | ... AE31: =-AE14/AE7 -> 0.089446414
B32: =B15 -> Impairment loss/(writeback) on trade receivables | C32: =-C15/C7 -> 0.0013703994 | D32: =-D15/D7 -> 0.002067504 | E32: =-E15/E7 -> -0.00032439446 | F32: =-F15/F7 -> 0.0022958041 | G32: =-G15/G7 -> 0.0021114669 | H32: =-H15/H7 -> 0.0051461286 | I32: =-I15/I7 -> 0.014467872 | J32: =-J15/J7 -> 0.014467872 | L32: =-L15/L7 -> -0.004345273 | M32: =-M15/M7 -> 0.0054887858 | N32: =-N15/N7 -> -0.0022129769 | O32: =-O15/O7 -> -0.000693525 | P32: =-P15/P7 -> 0.0030496257 | Q32: =-Q15/Q7 -> 0.0039977613 | R32: =-R15/R7 -> 0.00058483807 | S32: =-S15/S7 -> 0.0019313175 | ... AE32: =-AE15/AE7 -> 0.020670848
B33: =B16 -> Depreciation and Amortisation expense | C33: =-C16/C7 -> 0.056270276 | D33: =-D16/D7 -> 0.056158578 | E33: =-E16/E7 -> 0.051016436 | F33: =-F16/F7 -> 0.047539943 | G33: =-G16/G7 -> 0.064109703 | H33: =-H16/H7 -> 0.058966057 | I33: =-I16/I7 -> 0.062578368 | J33: =-J16/J7 -> 0.062578368 | L33: =-L16/L7 -> 0.064709336 | M33: =-M16/M7 -> 0.053562979 | N33: =-N16/N7 -> 0.053111446 | O33: =-O16/O7 -> 0.040476641 | P33: =-P16/P7 -> 0.054338786 | Q33: =-Q16/Q7 -> 0.048612777 | R33: =-R16/R7 -> 0.04561737 | S33: =-S16/S7 -> 0.04387712 | ... AE33: =-AE16/AE7 -> 0.049904554
B34: =B17 -> Exchange difference on trade receivables and trade payables | C34: =-C17/C7 -> 0.0092571876 | D34: =-D17/D7 -> 0.0053496666 | E34: =-E17/E7 -> 0.013754325 | F34: =-F17/F7 -> 0.017993131 | G34: =-G17/G7 -> 0.022646062 | H34: =-H17/H7 -> 0.011149945 | I34: =-I17/I7 -> 0.0060957966 | J34: =-J17/J7 -> 0.0060957966 | L34: =-L17/L7 -> 0.010452143 | M34: =-M17/M7 -> 0.010788303 | N34: =-N17/N7 -> 0.019562716 | O34: =-O17/O7 -> 0.013366118 | P34: =-P17/P7 -> 0.018205341 | Q34: =-Q17/Q7 -> 0.025905493 | R34: =-R17/R7 -> 0.010965714 | S34: =-S17/S7 -> 0.017683626 | ... AE34: =-AE17/AE7 -> 0.0048541042
B35: Finance cost as % of debt | C35: =-C19/C109 -> 0.051658586 | D35: =-D19/D109 -> 0.086667508 | E35: =-E19/E109 -> 0.088726514 | F35: =-F19/F109 -> 0.12883169 | G35: =-G19/G109 -> 0.13545256 | H35: =-H19/H109 -> 0.15294763 | I35: =-I19/I109 -> 0.15426835 | J35: =-J19/J109 -> 0.15426835 | O35: =-SUM(L19:O19)/O109 -> 0.088726514 | Q35: =-SUM(N19:Q19)/Q109 -> 0.076561492 | S35: =-SUM(P19:S19)/S109 -> 0.12883169 | U35: =-SUM(R19:U19)/U109 -> 0.099339895 | W35: =-SUM(T19:W19)/W109 -> 0.13545256 | Y35: =-SUM(V19:Y19)/Y109 -> 0.13390698 | AA35: =-SUM(X19:AA19)/AA109 -> 0.15294763 | AC35: =-SUM(Z19:AC19)/AC109 -> 0.12026469 | AD35: =-SUM(AA19:AD19)/AD109 -> 0.12222456 | AE35: =-SUM(AB19:AE19)/AE109 -> 0.15426835
B36: Tax % of PBT | C36: =-C24/C23 -> 0.21201158 | D36: =-D24/D23 -> 0.16407558 | E36: =-E24/E23 -> 0.10652437 | F36: =-F24/F23 -> 0.14291262 | G36: =-G24/G23 -> 0.10014375 | H36: =-H24/H23 -> 0.010856454 | I36: =-I24/I23 -> 0.29680076 | J36: =-J24/J23 -> 0.29680076 | L36: =L24/L23 -> 0.25460637 | M36: =-M24/M23 -> 0.24340176 | N36: =-N24/N23 -> 0.12407132 | O36: =-O24/O23 -> 0.1325 | P36: =-P24/P23 -> 0.055451128 | Q36: =-Q24/Q23 -> 0.1925 | R36: =-R24/R23 -> 0.090301003 | S36: =-S24/S23 -> 0.22358016 | T36: =-T24/T23 -> 2.6451613 | ... AE36: =-AE24/AE23 -> 0.31606765
B38: Working capital /sales | C38: =C59/C7 -> 0.085300369 | D38: =-D59/D7 -> 0.0055305732 | E38: =-E59/E7 -> 0.038213668 | F38: =-F59/F7 -> 0.025552486 | G38: =-G59/G7 -> 0.029490928 | H38: =-H59/H7 -> -0.077620773 | I38: =-I59/I7 -> 0.022627751 | J38: =-J59/J7 -> 0.022627751 | L38: =L59/L7 -> 0 | M38: =M59/M7 -> -0.53279076 | N38: =N59/N7 -> 0 | O38: =O59/O7 -> 0.24355337 | P38: =P59/P7 -> 0 | Q38: =Q59/Q7 -> -0.68761494 | R38: =R59/R7 -> 0 | S38: =S59/S7 -> 0.43641741 | ... AE38: =AE59/AE7 -> 0.38821925
B39: Capex/sales | C39: =-C63/C7 -> 0.039993288 | D39: =-D63/D7 -> 0.040368016 | E39: =-E63/E7 -> 0.041068339 | F39: =-F63/F7 -> 0.029882783 | G39: =-G63/G7 -> 0.025940879 | H39: =-H63/H7 -> 0.0079979415 | I39: =-I63/I7 -> 0.031115569 | J39: =-J63/J7 -> 0.031115569 | L39: =-L63/L7 -> 0 | M39: =-M63/M7 -> 0.071354216 | N39: =-N63/N7 -> 0 | O39: =-O63/O7 -> 0.072189648 | P39: =-P63/P7 -> 0 | Q39: =-Q63/Q7 -> 0.077956344 | R39: =-R63/R7 -> 0 | S39: =-S63/S7 -> 0.037781399 | ... AE39: =-AE63/AE7 -> 0.044668666
B41: EBITDA | C41: =C3 -> 43921 | D41: =D3 -> 44286 | E41: =E3 -> 44651 | F41: =F3 -> 45016 | G41: =G3 -> 45382 | H41: =H3 -> 45747 | I41: =I3 -> 46112 | J41: =J2 -> LTM | L41: =L3 -> 44377 | M41: =M3 -> 44469 | N41: =N3 -> 44561 | O41: =O3 -> 44651 | P41: =P3 -> 44742 | Q41: =Q3 -> 44834 | R41: =R3 -> 44926 | S41: =S3 -> 45016 | ... AE41: =AE3 -> 46112
B42: Operating profit | C42: =C18 -> 113340 | D42: =D18 -> 136840 | E42: =E18 -> 168470 | F42: =F18 -> 180820 | G42: =G18 -> 105750 | H42: =H18 -> 140810 | I42: =I18 -> 164940 | J42: =J18 -> 164940 | L42: =L18 -> 32270 | M42: =M18 -> 35760 | N42: =N18 -> 42510 | O42: =O18 -> 57930 | P42: =P18 -> 39130 | Q42: =Q18 -> 45890 | R42: =R18 -> 50690 | S42: =S18 -> 45110 | ... AE42: =AE18 -> 53670
B43: Depreciation & amortization | C43: =-C16 -> 20120 | D43: =-D16 -> 21730 | E43: =-E16 -> 23590 | F43: =-F16 -> 25470 | G43: =-G16 -> 27630 | H43: =-H16 -> 27500 | I43: =-I16 -> 32440 | J43: =SUM(AB43:AE43) -> 32440 | L43: =-L16 -> 5510 | M43: =-M16 -> 5660 | N43: =-N16 -> 6000 | O43: =E43-SUM(L43:N43) -> 6420 | P43: =-P16 -> 5880 | Q43: =-Q16 -> 6080 | R43: =-R16 -> 6240 | S43: =F43-SUM(P43:R43) -> 7270 | T43: =-T16 -> 6360 | U43: =-U16 -> 6570 | V43: =-V16 -> 6760 | W43: =G43-SUM(T43:V43) -> 7940 | X43: =-X16 -> 6600 | Y43: =-Y16 -> 6970 | Z43: =-Z16 -> 6880 | AA43: =H43-SUM(X43:Z43) -> 7050 | AB43: =-AB16 -> 7310 | AC43: =-AC16 -> 7710 | AD43: =-AD16 -> 8270 | AE43: =-AE16 -> 9150
B44: EBITDA | C44: =SUM(C42:C43) -> 133460 | D44: =SUM(D42:D43) -> 158570 | E44: =SUM(E42:E43) -> 192060 | F44: =SUM(F42:F43) -> 206290 | G44: =SUM(G42:G43) -> 133380 | H44: =SUM(H42:H43) -> 168310 | I44: =SUM(I42:I43) -> 197380 | J44: =SUM(J42:J43) -> 197380 | L44: =SUM(L42:L43) -> 37780 | M44: =SUM(M42:M43) -> 41420 | N44: =SUM(N42:N43) -> 48510 | O44: =SUM(O42:O43) -> 64350 | P44: =SUM(P42:P43) -> 45010 | Q44: =SUM(Q42:Q43) -> 51970 | R44: =SUM(R42:R43) -> 56930 | S44: =SUM(S42:S43) -> 52380 | ... AE44: =SUM(AE42:AE43) -> 62820
B45: % growth | D45: =+D44/C44-1 -> 0.18814626 | E45: =+E44/D44-1 -> 0.2112001 | F45: =+F44/E44-1 -> 0.07409143 | G45: =+G44/F44-1 -> -0.35343449 | H45: =+H44/G44-1 -> 0.26188334 | I45: =+I44/H44-1 -> 0.17271701
B46: % margin | C46: =+C44/C7 -> 0.37325204 | D46: =+D44/D7 -> 0.40980514 | E46: =+E44/E7 -> 0.41535467 | F46: =+F44/F7 -> 0.38504181 | G46: =+G44/G7 -> 0.30948072 | H46: =+H44/H7 -> 0.36089371 | I46: =+I44/I7 -> 0.3807558 | J46: =+J44/J7 -> 0.3807558 | L46: =+L44/L7 -> 0.44368761 | M46: =+M44/M7 -> 0.39197502 | N46: =+N44/N7 -> 0.42940604 | O46: =+O44/O7 -> 0.40571212 | P46: =+P44/P7 -> 0.41595047 | Q46: =+Q44/Q7 -> 0.4155273 | R46: =+R44/R7 -> 0.41618539 | S46: =+S44/S7 -> 0.31613254 | ... AE46: =+AE44/AE7 -> 0.3426234
B48: Adjustment | C48: =C49-C44 -> -62430 | D48: =D49-D44 -> -72980 | E48: =E49-E44 -> -90410 | F48: =F49-F44 -> -94510 | G48: =G49-G44 -> -78230 | H48: =H49-H44 -> -87110 | I48: =I49-I44 -> -101500 | J48: =J49-J44 -> -101500 | L48: =L49-L44 -> -19160 | M48: =M49-M44 -> -20970 | N48: =N49-N44 -> -21850 | O48: =E48-SUM(L48:N48) -> -28430 | P48: =P49-P44 -> -21590 | Q48: =Q49-Q44 -> -24290 | R48: =R49-R44 -> -26580 | S48: =F48-SUM(P48:R48) -> -22050 | T48: =T49-T44 -> -19190 | U48: =U49-U44 -> -19310 | V48: =V49-V44 -> -18070 | W48: =G48-SUM(T48:V48) -> -21660 | X48: =X49-X44 -> -20310 | Y48: =Y49-Y44 -> -20900 | Z48: =Z49-Z44 -> -22140 | AA48: =M48-SUM(X48:Z48) -> 42380 | AB48: =AB49-AB44 -> -24660 | AC48: =AC49-AC44 -> -25270 | AD48: =AD49-AD44 -> -25210 | AE48: =I48-SUM(AB48:AD48) -> -26360
B49: Adj. EBITDA | C49: 71030 | D49: 85590 | E49: 101650 | F49: 111780 | G49: 55150 | H49: =81.2*1000 -> 81200 | I49: 95880 | J49: =SUM(AB49:AE49) -> 95880 | L49: 18620 | M49: 20450 | N49: 26660 | O49: =O44+O48 -> 35920 | P49: 23420 | Q49: 27680 | R49: 30350 | S49: =S44+S48 -> 30330 | T49: 15930 | U49: 15730 | V49: 4160 | W49: =W44+W48 -> 19330 | X49: 11450 | Y49: 15760 | Z49: 21630 | AA49: =H49-SUM(X49:Z49) -> 32360 | AB49: 13030 | AC49: 22050 | AD49: 24340 | AE49: =I49-SUM(AB49:AD49) -> 36460
B50: % growth | D50: =+D49/C49-1 -> 0.20498381 | E50: =+E49/D49-1 -> 0.18763874 | F50: =+F49/E49-1 -> 0.099655681 | G50: =+G49/F49-1 -> -0.50662015 | H50: =+H49/G49-1 -> 0.47234814 | I50: =+I49/H49-1 -> 0.18078818 | P50: =P49/L49-1 -> 0.25778733 | Q50: =Q49/M49-1 -> 0.35354523 | R50: =R49/N49-1 -> 0.1384096 | S50: =S49/O49-1 -> -0.15562361 | T50: =T49/P49-1 -> -0.31981213 | U50: =U49/Q49-1 -> -0.43171965 | V50: =V49/R49-1 -> -0.86293245 | W50: =W49/S49-1 -> -0.36267722 | ... AE50: =AE49/AA49-1 -> 0.12669963
B51: % margin | C51: =+C49/C7 -> 0.19865197 | D51: =+D49/D7 -> 0.22119708 | E51: =+E49/E7 -> 0.21983131 | F51: =+F49/F7 -> 0.2086382 | G51: =+G49/G7 -> 0.12796417 | H51: =+H49/H7 -> 0.17411068 | I51: =+I49/I7 -> 0.18495727 | J51: =+J49/J7 -> 0.18495727 | L51: =+L49/L7 -> 0.21867293 | M51: =+M49/M7 -> 0.19352702 | N51: =+N49/N7 -> 0.23599186 | O51: =+O49/O7 -> 0.22646744 | P51: =+P49/P7 -> 0.21643101 | Q51: =+Q49/Q7 -> 0.22131606 | R51: =+R49/R7 -> 0.22187294 | S51: =+S49/S7 -> 0.18305269 | ... AE51: =+AE49/AE7 -> 0.19885465
B53: Capex sales | C53: =-C63/C7 -> 0.039993288 | D53: =-D63/D7 -> 0.040368016 | E53: =-E63/E7 -> 0.041068339 | F53: =-F63/F7 -> 0.029882783 | G53: =-G63/G7 -> 0.025940879 | H53: =-H63/H7 -> 0.0079979415 | I53: =-I63/I7 -> 0.031115569 | J53: =-J63/J7 -> 0.031115569 | L53: =-L63/L7 -> 0 | M53: =-M63/M7 -> 0.071354216 | N53: =-N63/N7 -> 0 | O53: =-O63/O7 -> 0.072189648 | P53: =-P63/P7 -> 0 | Q53: =-Q63/Q7 -> 0.077956344 | R53: =-R63/R7 -> 0 | S53: =-S63/S7 -> 0.037781399 | ... AE53: =-AE63/AE7 -> 0.044668666
B54: WC SALES | C54: =C59/C7 -> 0.085300369 | D54: =-D59/D7 -> 0.0055305732 | E54: =-E59/E7 -> 0.038213668 | F54: =-F59/F7 -> 0.025552486 | G54: =-G59/G7 -> 0.029490928 | H54: =-H59/H7 -> -0.077620773 | I54: =-I59/I7 -> 0.022627751 | J54: =-J59/J7 -> 0.022627751 | L54: =L59/L7 -> 0 | M54: =M59/M7 -> -0.53279076 | N54: =N59/N7 -> 0 | O54: =O59/O7 -> 0.24355337 | P54: =P59/P7 -> 0 | Q54: =Q59/Q7 -> -0.68761494 | R54: =R59/R7 -> 0 | S54: =S59/S7 -> 0.43641741 | ... AE54: =AE59/AE7 -> 0.38821925
B56: CASH FLOW | C56: =C3 -> 43921 | D56: =D3 -> 44286 | E56: =E3 -> 44651 | F56: =F3 -> 45016 | G56: =G3 -> 45382 | H56: =H3 -> 45747 | I56: =I3 -> 46112 | J56: =J2 -> LTM | L56: =L3 -> 44377 | M56: =M3 -> 44469 | N56: =N3 -> 44561 | O56: =O3 -> 44651 | P56: =P3 -> 44742 | Q56: =Q3 -> 44834 | R56: =R3 -> 44926 | S56: =S3 -> 45016 | ... AE56: =AE3 -> 46112
M57: 1H | O57: 2H | Q57: 1H | S57: 2H | U57: 1H | W57: 2H | Y57: 1H | AA57: 2H | AC57: 1H | AE57: 2H
B58: Adj. EBITDA | C58: =C49 -> 71030 | D58: =D49 -> 85590 | E58: =E49 -> 101650 | F58: =F49 -> 111780 | G58: =G49 -> 55150 | H58: =H49 -> 81200 | I58: =I49 -> 95880 | J58: =J49 -> 95880 | M58: =M49+L49 -> 39070 | O58: =O49+N49 -> 62580 | Q58: =Q49+P49 -> 51100 | S58: =S49+R49 -> 60680 | U58: =U49+T49 -> 31660 | W58: =W49+V49 -> 23490 | Y58: =Y49+X49 -> 27210 | AA58: =AA49+Z49 -> 53990 | AC58: =AC49+AB49 -> 35080 | AE58: =AE49+AD49 -> 60800
B59: Working Capital | C59: 30500 | D59: -2140 | E59: -17670 | F59: -13690 | G59: =29650-42360 -> -12710 | H59: =(11057-7437)*10 -> 36200 | I59: =(8426-9599)*10 -> -11730 | J59: =SUM(AB59:AE59) -> -11730 | M59: -56300 | O59: =E59-SUM(L59:N59) -> 38630 | Q59: -86000 | S59: =F59-SUM(P59:R59) -> 72310 | U59: -114210 | W59: =G59-SUM(T59:V59) -> 101500 | Y59: -48940 | AA59: =H59-SUM(X59:Z59) -> 85140 | AC59: =(-4844-3447)*10 -> -82910 | AE59: =I59-SUM(AB59:AD59) -> 71180
B60: Taxes | C60: -8190 | D60: -7250 | E60: -10040 | F60: -12620 | G60: -11430 | H60: -9830 | I60: -5710 | J60: =SUM(AB60:AE60) -> -5710 | M60: -4380 | O60: =E60-SUM(L60:N60) -> -5660 | Q60: -5690 | S60: =F60-SUM(P60:R60) -> -6930 | U60: -8400 | W60: =G60-SUM(T60:V60) -> -3030 | Y60: -5470 | AA60: =H60-SUM(X60:Z60) -> -4360 | AC60: 330 | AE60: =I60-SUM(AB60:AD60) -> -6040
B61: Cash interest paid | C61: -16460 | D61: -16550 | E61: -19410 | F61: -23450 | G61: -34050 | H61: -33280 | I61: -28790 | J61: =SUM(AB61:AE61) -> -28790 | M61: -9490 | O61: =E61-SUM(L61:N61) -> -9920 | Q61: -8360 | S61: =F61-SUM(P61:R61) -> -15090 | U61: -13750 | W61: =G61-SUM(T61:V61) -> -20300 | Y61: -17440 | AA61: =H61-SUM(X61:Z61) -> -15840 | AC61: -15610 | AE61: =I61-SUM(AB61:AD61) -> -13180
B62: Net cash from operations | C62: =SUM(C58:C61) -> 76880 | D62: =SUM(D58:D61) -> 59650 | E62: =SUM(E58:E61) -> 54530 | F62: =SUM(F58:F61) -> 62020 | G62: =SUM(G58:G61) -> -3040 | H62: =SUM(H58:H61) -> 74290 | I62: =SUM(I58:I61) -> 49650 | J62: =SUM(J58:J61) -> 49650 | M62: =SUM(M58:M61) -> -31100 | O62: =SUM(O58:O61) -> 85630 | Q62: =SUM(Q58:Q61) -> -48950 | S62: =SUM(S58:S61) -> 110970 | U62: =SUM(U58:U61) -> -104700 | W62: =SUM(W58:W61) -> 101660 | Y62: =SUM(Y58:Y61) -> -44640 | AA62: =SUM(AA58:AA61) -> 118930 | AC62: =SUM(AC58:AC61) -> -63110 | AE62: =SUM(AE58:AE61) -> 112760
B63: Net Capex | C63: =-14750+450 -> -14300 | D63: =-16190+570 -> -15620 | E63: =-20220+1230 -> -18990 | F63: =-16720+710 -> -16010 | G63: =-11590+410 -> -11180 | H63: =(-813+440)*10 -> -3730 | I63: =(-1666+53)*10 -> -16130 | J63: =SUM(AB63:AE63) -> -16130 | M63: =-7790+250 -> -7540 | O63: =E63-SUM(L63:N63) -> -11450 | Q63: =-9900+150 -> -9750 | S63: =F63-SUM(P63:R63) -> -6260 | U63: =-7230+250 -> -6980 | W63: =G63-SUM(T63:V63) -> -4200 | Y63: =-4940+4210 -> -730 | AA63: =H63-SUM(X63:Z63) -> -3000 | AC63: =(-800+6)*10 -> -7940 | AE63: =I63-SUM(AB63:AD63) -> -8190
B64: Purchase of intangible assets | C64: -5050 | D64: -5030 | E64: -6660 | F64: -6880 | G64: -8360 | H64: =(-882)*10 -> -8820 | I64: =(-740)*10 -> -7400 | J64: =SUM(AB64:AE64) -> -7400 | M64: -2550 | O64: =E64-SUM(L64:N64) -> -4110 | Q64: -1810 | S64: =F64-SUM(P64:R64) -> -5070 | U64: -3540 | W64: =G64-SUM(T64:V64) -> -4820 | Y64: -4530 | AA64: =H64-SUM(X64:Z64) -> -4290 | AC64: -1890 | AE64: =I64-SUM(AB64:AD64) -> -5510
B65: Disposals/ Acquistion, of subsidiaries, businesses | C65: -7610 | D65: -1790 | E65: -1300 | F65: -560 | G65: -1360 | H65: -1850 | I65: 0 | J65: =SUM(AB65:AE65) -> 0 | M65: -150 | O65: =E65-SUM(L65:N65) -> -1150 | Q65: -560 | S65: =F65-SUM(P65:R65) -> 0 | U65: -850 | W65: =G65-SUM(T65:V65) -> -510 | Y65: -1850 | AA65: =H65-SUM(X65:Z65) -> 0 | AC65: -470 | AE65: =I65-SUM(AB65:AD65) -> 470
B66: Free cash flow | C66: =SUM(C62:C65) -> 49920 | D66: =SUM(D62:D65) -> 37210 | E66: =SUM(E62:E65) -> 27580 | F66: =SUM(F62:F65) -> 38570 | G66: =SUM(G62:G65) -> -23940 | H66: =SUM(H62:H65) -> 59890 | I66: =SUM(I62:I65) -> 26120 | J66: =SUM(J62:J65) -> 26120 | M66: =SUM(M62:M65) -> -41340 | O66: =SUM(O62:O65) -> 68920 | Q66: =SUM(Q62:Q65) -> -61070 | S66: =SUM(S62:S65) -> 99640 | U66: =SUM(U62:U65) -> -116070 | W66: =SUM(W62:W65) -> 92130 | Y66: =SUM(Y62:Y65) -> -51750 | AA66: =SUM(AA62:AA65) -> 111640 | AC66: =SUM(AC62:AC65) -> -73410 | AE66: =SUM(AE62:AE65) -> 99530
B67: Other Investing | C67: =-940-90+630-120+170-30+60+850 -> 530 | D67: =250-280-230-20+1710 -> 1430 | E67: =1320-8400-3190+160-170-2670+160+1550 -> -11240 | F67: =210-6190+11070-610+1930+300+1840 -> 8550 | G67: =-8810+470+610+370+260+3220 -> -3880 | H67: =(-680-9-48-17+34+21+299)*10 -> -4000 | I67: =(-22-65-313-162-52+275+512+25-207)*10 -> -90 | J67: =SUM(AB67:AE67) -> -90 | M67: =320-130+150-80+20+740 -> 1020 | O67: =E67-SUM(L67:N67) -> -12260 | Q67: =-6900+9110-40+2770+220+1080 -> 6240 | S67: =F67-SUM(P67:R67) -> 2310 | U67: =-3910-820+250+600+260+1420 -> -2200 | W67: =G67-SUM(T67:V67) -> -1680 | Y67: =-130-140-1650+80+570+210+1240 -> 180 | AA67: =H67-SUM(X67:Z67) -> -4180 | AC67: =(-9-2+26-278+39-35+151+345)*10 -> 2370 | AE67: =I67-SUM(AB67:AD67) -> -2460
B68: Equity Issuance | C68: 0 | D68: 0 | E68: 0 | F68: -13550 | G68: 0 | H68: 16330 | I68: 17000 | J68: =SUM(AB68:AE68) -> 17000 | M68: 0 | O68: =E68-SUM(L68:N68) -> 0 | Q68: 0 | S68: =F68-SUM(P68:R68) -> -13550 | U68: 0 | W68: =G68-SUM(T68:V68) -> 0 | Y68: 0 | AA68: =H68-SUM(X68:Z68) -> 16330 | AC68: =(1685)*10 -> 16850 | AE68: =I68-SUM(AB68:AD68) -> 150
B69: Dividends | C69: =-500-4070 -> -4570 | D69: -4580 | E69: =-1580-7640 -> -9220 | F69: -7500 | G69: -7490 | H69: -770 | I69: =-4780-90 -> -4870 | J69: =SUM(AB69:AE69) -> -4870 | M69: =-7630 -> -7630 | O69: =E69-SUM(L69:N69) -> -1590 | Q69: -7520 | S69: =F69-SUM(P69:R69) -> 20 | U69: -7520 | W69: =G69-SUM(T69:V69) -> 30 | Y69: -760 | AA69: =H69-SUM(X69:Z69) -> -10 | AC69: -4780 | AE69: =I69-SUM(AB69:AD69) -> -90
B70: Net Change in debt | C70: =-16670-12030+30270 -> 1570 | D70: =73110-116750+1450 -> -42190 | E70: =71930-84640+25770 -> 13060 | F70: =61630-78640-28940 -> -45950 | G70: =33130-16610+31530 -> 48050 | H70: =(-2137-3217-530)*10 -> -58840 | I70: =(-4742+575-641-3409)*10 -> -82170 | J70: =SUM(AB70:AE70) -> -82170 | M70: =18560-21060+33180 -> 30680 | O70: =E70-SUM(L70:N70) -> -17620 | Q70: =54990-54990+50060 -> 50060 | S70: =F70-SUM(P70:R70) -> -96010 | U70: =16330+90760 -> 107090 | W70: =G70-SUM(T70:V70) -> -59040 | Y70: =31850 -> 31850 | AA70: =H70-SUM(X70:Z70) -> -90690 | AC70: =(3902-3409-294)*10 -> 1990 | AE70: =I70-SUM(AB70:AD70) -> -84160
B71: Other financing activities | C71: =-400-1890 -> -2290 | D71: =-990-2820 -> -3810 | E71: =-860-2780 -> -3640 | F71: =13840-480-3700-2080+40540-19940 -> 28180 | G71: =-530-4340-0+0-0 -> -4870 | H71: 28630 | I71: 0 | J71: =SUM(AB71:AE71) -> 0 | M71: =-440-1380 -> -1820 | O71: =E71-SUM(L71:N71) -> -1820 | Q71: =13840-480-1720-13550 -> -1910 | S71: =F71-SUM(P71:R71) -> 30090 | U71: =-1860 -> -1860 | W71: =G71-SUM(T71:V71) -> -3010 | Y71: =-2520 -> -2520 | AA71: =H71-SUM(X71:Z71) -> 31150 | AC71: 0 | AE71: =I71-SUM(AB71:AD71) -> 0
B72: Cash flow after financing activities | C72: =SUM(C66:C71) -> 45160 | D72: =SUM(D66:D71) -> -11940 | E72: =SUM(E66:E71) -> 16540 | F72: =SUM(F66:F71) -> 8300 | G72: =SUM(G66:G71) -> 7870 | H72: =SUM(H66:H71) -> 41240 | I72: =SUM(I66:I71) -> -44010 | J72: =SUM(J66:J71) -> -44010 | M72: =SUM(M66:M71) -> -19090 | O72: =SUM(O66:O71) -> 35630 | Q72: =SUM(Q66:Q71) -> -14200 | S72: =SUM(S66:S71) -> 22500 | U72: =SUM(U66:U71) -> -20560 | W72: =SUM(W66:W71) -> 28430 | Y72: =SUM(Y66:Y71) -> -23000 | AA72: =SUM(AA66:AA71) -> 64240 | AC72: =SUM(AC66:AC71) -> -56980 | AE72: =SUM(AE66:AE71) -> 12970
B73: Balancing figure | C73: =38980-C72-C74 -> -5950 | D73: =-19270-D72-D74 -> -4080 | E73: =10000-E72-E74 -> -8980 | F73: =1700-F72-F74 -> -7960 | G73: =-240-G72-G74 -> -12790 | H73: =35350-H72-H74 -> -6830 | I73: =-35030-I72-I74 -> 110 | J73: =-35030-J72-J74 -> 110 | M73: =-19860-M72-M74 -> -2540 | O73: =10000-M73-O72-M72-O74-M74 -> -6440 | Q73: =-22090-Q72-Q74 -> -5350 | S73: =1700-Q73-S72-Q72-S74-Q74 -> -2610 | U73: =-28670-U72-U74 -> -5960 | W73: =-240-U73-W72-U72-W74-U74 -> -6830 | Y73: =-20690-Y72-Y74 -> 4570 | AA73: =35350-Y73-AA72-Y72-AA74-Y74 -> -11400 | AC73: =-54200-AC72-AC74 -> -610 | AE73: =-35030-AC73-AE72-AC72-AE74-AC74 -> 720
B74: FX | C74: -230 | D74: -3250 | E74: 2440 | F74: 1360 | G74: 4680 | H74: =170+770 -> 940 | I74: 8870 | J74: =SUM(AB74:AE74) -> 8870 | M74: 1770 | O74: =E74-SUM(L74:N74) -> 670 | Q74: -2540 | S74: =F74-SUM(P74:R74) -> 3900 | U74: -2150 | W74: =G74-SUM(T74:V74) -> 6830 | Y74: -2260 | AA74: =H74-SUM(X74:Z74) -> 3200 | AC74: 3390 | AE74: =I74-SUM(AB74:AD74) -> 5480
B75: Net change in cash | C75: =SUM(C72:C74) -> 38980 | D75: =SUM(D72:D74) -> -19270 | E75: =SUM(E72:E74) -> 10000 | F75: =SUM(F72:F74) -> 1700 | G75: =SUM(G72:G74) -> -240 | H75: =SUM(H72:H74) -> 35350 | I75: =SUM(I72:I74) -> -35030 | J75: =SUM(AB75:AE75) -> -35030 | M75: =SUM(M72:M74) -> -19860 | O75: =SUM(O72:O74) -> 29860 | Q75: =SUM(Q72:Q74) -> -22090 | S75: =SUM(S72:S74) -> 23790 | U75: =SUM(U72:U74) -> -28670 | W75: =SUM(W72:W74) -> 28430 | Y75: =SUM(Y72:Y74) -> -20690 | AA75: =SUM(AA72:AA74) -> 56040 | AC75: =SUM(AC72:AC74) -> -54200 | AE75: =SUM(AE72:AE74) -> 19170
B76: Cash and cash equivalents | C76: =28260+C75 -> 67240 | D76: =C76+D75 -> 47970 | E76: =D76+E75 -> 57970 | F76: =E76+F75 -> 59670 | G76: =F76+G75 -> 59430 | H76: =G76+H75 -> 94780 | I76: =H76+I75 -> 59750 | J76: =AA76+J75 -> 59750 | M76: =48530+M75 -> 28670 | O76: =D76+O75+M75 -> 57970 | Q76: =O76+Q75 -> 35880 | S76: =E76+S75+Q75 -> 59670 | U76: =S76+U75 -> 31000 | W76: =F76+W75+U75 -> 59430 | Y76: =W76+Y75 -> 38740 | AA76: =Y76+AA75 -> 94780 | AC76: =AA76+AC75 -> 40580 | AE76: =AC76+AE75 -> 59750
B78: check 1 | C78: =+C76-C121+280 -> 0 | D78: =+D76-D121+560 -> 0 | E78: =+E76-E121+3230 -> 0 | F78: =+F76-F121+1300 -> 0 | G78: =+G76-G121+930 -> 0 | H78: =+H76-H121+590 -> 0 | I78: =+I76-I121+1110 -> 0 | M78: =+M76-M121 -> 0 | O78: =+O76-O121+3230 -> 0 | Q78: =+Q76-Q121 -> 0 | S78: =+S76-S121+1300 -> 0 | U78: =+U76-U121+700 -> 0 | W78: =+W76-W121+930 -> 0 | Y78: =+Y76-Y121+360 -> 0 | AA78: =+AA76-AA121+590 -> 0 | AC78: =+AC76-AC121+940 -> 0 | AE78: =+AE76-AE121+1110 -> 0
B79: check 2 | C79: =87390-(C62+C73)+C61 -> 0 | D79: =72120-(D62+D73)+D61 -> 0 | E79: =64960-(E62+E73)+E61 -> 0 | F79: =77510-(F62+F73)+F61 -> 0 | G79: =18220-(G62+G73)+G61 -> 0 | H79: =100740-(H62+H73)+H61 -> 0 | I79: =78550-(I62+I73)+I61 -> 0 | M79: =-24150-(M62+M73)+M61 -> 0 | Q79: =-45940-(Q62+Q73)+Q61 -> 0 | U79: =-96910-(U62+U73)+U61 -> 0
B81: LTM | C81: =C3 -> 43921 | D81: =D3 -> 44286 | E81: =E3 -> 44651 | F81: =F3 -> 45016 | G81: =G3 -> 45382 | H81: =H3 -> 45747 | I81: =I3 -> 46112 | J81: =J2 -> LTM | L81: =L3 -> 44377 | M81: =M3 -> 44469 | N81: =N3 -> 44561 | O81: =O3 -> 44651 | P81: =P3 -> 44742 | Q81: =Q3 -> 44834 | R81: =R3 -> 44926 | S81: =S3 -> 45016 | ... AE81: =AE3 -> 46112
B82: =B7 -> Revenue from Operations | C82: =C7 -> 357560 | D82: =D7 -> 386940 | E82: =E7 -> 462400 | F82: =F7 -> 535760 | G82: =G7 -> 430980 | H82: =H7 -> 466370 | I82: =I7 -> 518390 | J82: =J7 -> 518390 | O82: =SUM(L7:O7) -> 462400 | P82: =SUM(M7:P7) -> 485460 | Q82: =SUM(N7:Q7) -> 504860 | R82: =SUM(O7:R7) -> 528680 | S82: =SUM(P7:S7) -> 535760 | T82: =SUM(Q7:T7) -> 517180 | U82: =SUM(R7:U7) -> 493810 | V82: =SUM(S7:V7) -> 455890 | ... AE82: =SUM(AB7:AE7) -> 518390
B83: Operating profit | C83: =C18 -> 113340 | D83: =D18 -> 136840 | E83: =E18 -> 168470 | F83: =F18 -> 180820 | G83: =G18 -> 105750 | H83: =H18 -> 140810 | I83: =I18 -> 164940 | J83: =J18 -> 164940 | O83: =SUM(L18:O18) -> 168470 | P83: =SUM(M18:P18) -> 175330 | Q83: =SUM(N18:Q18) -> 185460 | R83: =SUM(O18:R18) -> 193640 | S83: =SUM(P18:S18) -> 180820 | T83: =SUM(Q18:T18) -> 170450 | U83: =SUM(R18:U18) -> 153030 | V83: =SUM(S18:V18) -> 117810 | ... AE83: =SUM(AB18:AE18) -> 164940
B84: EBITDA | C84: =+C44 -> 133460 | D84: =+D44 -> 158570 | E84: =+E44 -> 192060 | F84: =+F44 -> 206290 | G84: =+G44 -> 133380 | H84: =+H44 -> 168310 | I84: =+I44 -> 197380 | J84: =+J44 -> 197380 | O84: =SUM(L44:O44) -> 192060 | P84: =SUM(M44:P44) -> 199290 | Q84: =SUM(N44:Q44) -> 209840 | R84: =SUM(O44:R44) -> 218260 | S84: =SUM(P44:S44) -> 206290 | T84: =SUM(Q44:T44) -> 196400 | U84: =SUM(R44:U44) -> 179470 | V84: =SUM(S44:V44) -> 144770 | ... AE84: =SUM(AB44:AE44) -> 197380
B85: Adjusted EBITDA | C85: =+C49 -> 71030 | D85: =+D49 -> 85590 | E85: =+E49 -> 101650 | F85: =+F49 -> 111780 | G85: =+G49 -> 55150 | H85: =+H49 -> 81200 | I85: =+I49 -> 95880 | J85: =+J49 -> 95880 | O85: =SUM(L49:O49) -> 101650 | P85: =SUM(M49:P49) -> 106450 | Q85: =SUM(N49:Q49) -> 113680 | R85: =SUM(O49:R49) -> 117370 | S85: =SUM(P49:S49) -> 111780 | T85: =SUM(Q49:T49) -> 104290 | U85: =SUM(R49:U49) -> 92340 | V85: =SUM(S49:V49) -> 66150 | ... AE85: =SUM(AB49:AE49) -> 95880
B86: Cash interest paid | C86: =-C61 -> 16460 | D86: =-D61 -> 16550 | E86: =-E61 -> 19410 | F86: =-F61 -> 23450 | G86: =-G61 -> 34050 | H86: =-H61 -> 33280 | I86: =-I61 -> 28790 | J86: =-J61 -> 28790 | O86: =-SUM(L61:O61) -> 19410 | Q86: =-SUM(N61:Q61) -> 18280 | S86: =-SUM(P61:S61) -> 23450 | U86: =-SUM(R61:U61) -> 28840 | W86: =-SUM(T61:W61) -> 34050 | Y86: =-SUM(V61:Y61) -> 37740 | AA86: =-SUM(X61:AA61) -> 33280 | AC86: =-SUM(Z61:AC61) -> 31450 | AE86: =-SUM(AB61:AE61) -> 28790
B87: Net Income | C87: =+C25 -> 21780 | D87: =+D25 -> 34950 | E87: =+E25 -> 44370 | F87: =+F25 -> 44140 | G87: =+G25 -> -18780 | H87: =+H25 -> 8200 | I87: =+I25 -> 22200 | J87: =+J25 -> 22200 | O87: =SUM(L25:O25) -> 44370 | P87: =SUM(M25:P25) -> 46930 | Q87: =SUM(N25:Q25) -> 48880 | R87: =SUM(O25:R25) -> 50690 | S87: =SUM(P25:S25) -> 44140 | T87: =SUM(Q25:T25) -> 35110 | U87: =SUM(R25:U25) -> 22490 | V87: =SUM(S25:V25) -> -7180 | ... AE87: =SUM(AB25:AE25) -> 22200
B88: Capex | C88: =-C63 -> 14300 | D88: =-D63 -> 15620 | E88: =-E63 -> 18990 | F88: =-F63 -> 16010 | G88: =-G63 -> 11180 | H88: =-H63 -> 3730 | I88: =-I63 -> 16130 | J88: =-J63 -> 16130 | O88: =-SUM(L63:O63) -> 18990 | Q88: =-SUM(N63:Q63) -> 21200 | S88: =-SUM(P63:S63) -> 16010 | U88: =-SUM(R63:U63) -> 13240 | W88: =-SUM(T63:W63) -> 11180 | Y88: =-SUM(V63:Y63) -> 4930 | AA88: =-SUM(X63:AA63) -> 3730 | AC88: =-SUM(Z63:AC63) -> 10940 | AE88: =-SUM(AB63:AE63) -> 16130
B89: Free cash flow | C89: =+C66 -> 49920 | D89: =+D66 -> 37210 | E89: =+E66 -> 27580 | F89: =+F66 -> 38570 | G89: =+G66 -> -23940 | H89: =+H66 -> 59890 | I89: =+I66 -> 26120 | J89: =+J66 -> 26120 | O89: =SUM(L66:O66) -> 27580 | Q89: =SUM(N66:Q66) -> 7850 | S89: =SUM(P66:S66) -> 38570 | U89: =SUM(R66:U66) -> -16430 | W89: =SUM(T66:W66) -> -23940 | Y89: =SUM(V66:Y66) -> 40380 | AA89: =SUM(X66:AA66) -> 59890 | AC89: =SUM(Z66:AC66) -> 38230 | AE89: =SUM(AB66:AE66) -> 26120
B91: BALANCE SHEET | C91: =C3 -> 43921 | D91: =D3 -> 44286 | E91: =E3 -> 44651 | F91: =F3 -> 45016 | G91: =G3 -> 45382 | H91: =H3 -> 45747 | I91: =I3 -> 46112 | J91: =J2 -> LTM | L91: =L3 -> 44377 | M91: =M3 -> 44469 | N91: =N3 -> 44561 | O91: =O3 -> 44651 | P91: =P3 -> 44742 | Q91: =Q3 -> 44834 | R91: =R3 -> 44926 | S91: =S3 -> 45016 | ... AE91: =AE3 -> 46112
B93: Tangible fixed assets | C93: =55960+10590+6420 -> 72970 | D93: =64520+8990+6950 -> 80460 | E93: =72860+11840+7920 -> 92620 | F93: =81640+11970+9060 -> 102670 | G93: =84430+11060+12650 -> 108140 | H93: =(8107+615+1324)*10 -> 100460 | I93: =(8474+999+1440)*10 -> 109130 | J93: =AE93 -> 109130 | M93: =65960+10090+6940 -> 82990 | O93: =E93 -> 92620 | Q93: =75580+15430+8680 -> 99690 | S93: =F93 -> 102670 | U93: =81670+13140+9590 -> 104400 | W93: =G93 -> 108140 | Y93: =79070+10980+13100 -> 103150 | AA93: =H93 -> 100460 | AC93: =(8351+794+1385)*10 -> 105300 | AE93: =I93 -> 109130
B94: Inventory | C94: 78500 | D94: 94220 | E94: 130780 | F94: 139850 | G94: 127760 | H94: 103160 | I94: 126760 | J94: =AE94 -> 126760 | M94: 130770 | O94: =E94 -> 130780 | Q94: 194570 | S94: =F94 -> 139850 | U94: 182460 | W94: =G94 -> 127760 | Y94: 141060 | Z94: 135310 | AA94: =H94 -> 103160 | AC94: 161930 | AD94: 170660 | AE94: =I94 -> 126760
B95: Trade accounts receivable | C95: 118670 | D95: 121450 | E95: 153280 | F95: 182240 | G95: 163540 | H95: 155050 | I95: 178740 | J95: =AE95 -> 178740 | M95: 140800 | O95: =E95 -> 153280 | Q95: 165490 | S95: =F95 -> 182240 | U95: 182290 | W95: =G95 -> 163540 | Y95: 157190 | Z95: 135300 | AA95: =H95 -> 155050 | AC95: 164090 | AD95: 167270 | AE95: =I95 -> 178740
B96: Trade accounts payable | C96: =64+101690 -> 101754 | D96: =870+126720 -> 127590 | E96: =1440+164080 -> 165520 | F96: =820+175320 -> 176140 | G96: =840+156000 -> 156840 | H96: =(38+10829)*10 -> 108670 | I96: =(34+11984)*10 -> 120180 | J96: =AE96 -> 120180 | M96: =1770+142640 -> 144410 | O96: =E96 -> 165520 | Q96: =510+194750 -> 195260 | S96: =F96 -> 176140 | U96: =500+154800 -> 155300 | W96: =G96 -> 156840 | Y96: =350+141900 -> 142250 | Z96: 137820 | AA96: =H96 -> 108670 | AC96: =(12854+43)*10 -> 128970 | AD96: 181690 | AE96: =I96 -> 120180
B97: Net working capital | C97: =+C94+C95-C96 -> 95416 | D97: =+D94+D95-D96 -> 88080 | E97: =+E94+E95-E96 -> 118540 | F97: =+F94+F95-F96 -> 145950 | G97: =+G94+G95-G96 -> 134460 | H97: =+H94+H95-H96 -> 149540 | I97: =+I94+I95-I96 -> 185320 | J97: =+J94+J95-J96 -> 185320 | M97: =+M94+M95-M96 -> 127160 | O97: =+O94+O95-O96 -> 118540 | Q97: =+Q94+Q95-Q96 -> 164800 | S97: =+S94+S95-S96 -> 145950 | U97: =+U94+U95-U96 -> 209450 | W97: =+W94+W95-W96 -> 134460 | Y97: =+Y94+Y95-Y96 -> 156000 | Z97: =+Z94+Z95-Z96 -> 132790 | AA97: =+AA94+AA95-AA96 -> 149540 | AC97: =+AC94+AC95-AC96 -> 197050 | AD97: =+AD94+AD95-AD96 -> 156240 | AE97: =+AE94+AE95-AE96 -> 185320
B98: % of revenues | C98: =+C97/C82 -> 0.26685312 | D98: =+D97/D82 -> 0.22763219 | E98: =+E97/E82 -> 0.25635813 | F98: =+F97/F82 -> 0.27241675 | G98: =+G97/G82 -> 0.31198664 | H98: =+H97/H82 -> 0.3206467 | I98: =+I97/I82 -> 0.35749146 | J98: =+J97/J82 -> 0.35749146 | O98: =+O97/O82 -> 0.25635813 | Q98: =+Q97/Q82 -> 0.32642713 | S98: =+S97/S82 -> 0.27241675 | U98: =+U97/U82 -> 0.42415099 | W98: =+W97/W82 -> 0.31198664 | Y98: =+Y97/Y82 -> 0.35356511 | Z98: =+Z97/Z82 -> 0.29416065 | AA98: =+AA97/AA82 -> 0.3206467 | AC98: =+AC97/AC82 -> 0.41297286 | AD98: =+AD97/AD82 -> 0.31835687 | AE98: =+AE97/AE82 -> 0.35749146
B100: Inventory days | C100: 81 | D100: 90 | E100: 104 | F100: 95 | G100: 108 | H100: 81 | I100: 89 | J100: =AE100 -> 89 | L100: 118 | M100: 117 | N100: 122 | O100: =E100 -> 104 | P100: 128 | Q100: 141 | R100: 138 | S100: =F100 -> 95 | T100: 125 | U100: 135 | V100: 140 | W100: =G100 -> 108 | X100: 117 | Y100: 117 | Z100: 109 | AA100: =H100 -> 81 | AB100: 110 | AC100: 124 | AD100: 127 | AE100: =I100 -> 89
B101: Receivable days | C101: 118 | D101: 113 | E101: 114 | F101: 102 | G101: 124 | H101: 102 | I101: 116 | J101: =AE101 -> 116 | L101: 118 | M101: 134 | N101: 113 | O101: =E101 -> 114 | P101: 125 | Q101: 130 | R101: 117 | S101: =F101 -> 102 | T101: 124 | U101: 135 | V101: 133 | W101: =G101 -> 124 | X101: 135 | Y101: 133 | Z101: 109 | AA101: =H101 -> 102 | AB101: 129 | AC101: 146 | AD101: 124 | AE101: =I101 -> 116
B102: Payable days | C102: 119 | D102: 131 | E102: 149 | F102: 133 | G102: 146 | H102: 130 | I102: 148 | J102: =AE102 -> 148 | L102: 145 | M102: 137 | N102: 127 | O102: =E102 -> 149 | P102: 145 | Q102: 147 | R102: 134 | S102: =F102 -> 133 | T102: 127 | U102: 121 | V102: 118 | W102: =G102 -> 146 | X102: 131 | Y102: 127 | Z102: 111 | AA102: =H102 -> 130 | AB102: 152 | AC102: 151 | AD102: 135 | AE102: =I102 -> 148
B103: Net working capital days | C103: 80 | D103: 71 | E103: 69 | F103: 64 | G103: 86 | H103: 53 | I103: 57 | J103: =AE103 -> 57 | L103: 91 | M103: 114 | N103: 108 | O103: =E103 -> 69 | P103: 108 | Q103: 124 | R103: 121 | S103: =F103 -> 64 | T103: 122 | U103: 149 | V103: 155 | W103: =G103 -> 86 | X103: 121 | Y103: 123 | Z103: 107 | AA103: =H103 -> 53 | AB103: 86 | AC103: 118 | AD103: 116 | AE103: =I103 -> 57
B106: Debt Breakdown
B107: Short-term debt | C107: 12980 | D107: 16280 | E107: 42610 | F107: 28550 | G107: 44280 | H107: 54510 | I107: 65110 | J107: =AE107 -> 65110 | M107: 49130 | O107: =E107 -> 42610 | Q107: 92880 | S107: =F107 -> 28550 | U107: 119010 | W107: =G107 -> 44280 | Y107: 97890 | Z107: 175070 | AA107: =H107 -> 54510 | AC107: 113530 | AD107: 175070 | AE107: =I107 -> 65110
B108: Long-term debt | C108: 273710 | D108: 221410 | E108: 216050 | F108: 201440 | G108: 240100 | H108: 182630 | I108: 155350 | J108: =AE108 -> 155350 | M108: 222330 | O108: =E108 -> 216050 | Q108: 232610 | S108: =F108 -> 201440 | U108: 220330 | W108: =G108 -> 240100 | Y108: 220540 | Z108: 109570 | AA108: =H108 -> 182630 | AC108: 172090 | AD108: 109570 | AE108: =I108 -> 155350
B109: Total Debt (this is company reported) | C109: =SUM(C107:C108) -> 286690 | D109: =SUM(D107:D108) -> 237690 | E109: =SUM(E107:E108) -> 258660 | F109: =SUM(F107:F108) -> 229990 | G109: =SUM(G107:G108) -> 284380 | H109: =SUM(H107:H108) -> 237140 | I109: =SUM(I107:I108) -> 220460 | J109: =SUM(J107:J108) -> 220460 | M109: =SUM(M107:M108) -> 271460 | O109: =SUM(O107:O108) -> 258660 | Q109: =SUM(Q107:Q108) -> 325490 | S109: =SUM(S107:S108) -> 229990 | U109: =SUM(U107:U108) -> 339340 | W109: =SUM(W107:W108) -> 284380 | Y109: =SUM(Y107:Y108) -> 318430 | Z109: =SUM(Z107:Z108) -> 284640 | AA109: =SUM(AA107:AA108) -> 237140 | AC109: =SUM(AC107:AC108) -> 285620 | AD109: =SUM(AD107:AD108) -> 284640 | AE109: =SUM(AE107:AE108) -> 220460
B111: Lease Obligations
B112: Short-term | C112: 960 | D112: 1560 | E112: 2170 | F112: 2650 | G112: 3580 | H112: 3920 | I112: 5090 | J112: =AE112 -> 5090 | M112: 1550 | O112: =E112 -> 2170 | Q112: 2090 | S112: =F112 -> 2650 | U112: 2670 | W112: =G112 -> 3580 | Y112: 3920 | AA112: =H112 -> 3920 | AC112: 4320 | AE112: =I112 -> 5090
B113: Long-term | C113: 5860 | D113: 5850 | E113: 6260 | F113: 6750 | G113: 9580 | H113: 9930 | I113: 10210 | J113: =AE113 -> 10210 | M113: 5780 | O113: =E113 -> 6260 | Q113: 6800 | S113: =F113 -> 6750 | U113: 7350 | W113: =G113 -> 9580 | Y113: 9820 | AA113: =H113 -> 9930 | AC113: 10280 | AE113: =I113 -> 10210
B114: Total Lease | C114: =SUM(C112:C113) -> 6820 | D114: =SUM(D112:D113) -> 7410 | E114: =SUM(E112:E113) -> 8430 | F114: =SUM(F112:F113) -> 9400 | G114: =SUM(G112:G113) -> 13160 | H114: =SUM(H112:H113) -> 13850 | I114: =SUM(I112:I113) -> 15300 | J114: =SUM(J112:J113) -> 15300 | M114: =SUM(M112:M113) -> 7330 | O114: =SUM(O112:O113) -> 8430 | Q114: =SUM(Q112:Q113) -> 8890 | S114: =SUM(S112:S113) -> 9400 | U114: =SUM(U112:U113) -> 10020 | W114: =SUM(W112:W113) -> 13160 | Y114: =SUM(Y112:Y113) -> 13740 | AA114: =SUM(AA112:AA113) -> 13850 | AC114: =SUM(AC112:AC113) -> 14600 | AE114: =SUM(AE112:AE113) -> 15300
B116: Debt Including Lease obligations
...

Sheet KPIs
B2: UPL Ltd | C2: Annual | D2: Annual | E2: Annual | F2: Annual | G2: Annual | H2: Annual | I2: Annual | J2: LTM | L2: Quarters | M2: Quarters | N2: Quarters | O2: Quarters | P2: Quarters | Q2: Quarters | R2: Quarters | S2: Quarters | T2: Quarters | U2: Quarters | V2: Quarters | W2: Quarters | X2: Quarters | Y2: Quarters | Z2: Quarters | AA2: Quarters | AB2: Quarters | AC2: Quarters | AD2: Quarters | AE2: Quarters
B3: (INR million) | C3: 43921 | D3: 44286 | E3: 44651 | F3: 45016 | G3: 45382 | H3: 45747 | I3: 46112 | J3: =AE3 -> 46112 | L3: 44377 | M3: 44469 | N3: 44561 | O3: 44651 | P3: 44742 | Q3: 44834 | R3: 44926 | S3: 45016 | T3: 45107 | U3: 45199 | V3: 45291 | W3: 45382 | X3: 45473 | Y3: 45565 | Z3: 45657 | AA3: 45747 | AB3: 45838 | AC3: 45930 | AD3: 46022 | AE3: 46112
C4: Act | D4: Act | E4: Act | F4: Act | G4: Act | H4: Act | I4: Act | J4: Act | L4: Act | M4: Act | N4: Act | O4: Act | P4: Act | Q4: Act | R4: Act | S4: Act | T4: Act | U4: Act | V4: Act | W4: Act | X4: Act | Y4: Act | Z4: Act | AA4: Act | AB4: Act | AC4: Act | AD4: Act | AE4: Act
C5: FY | D5: FY | E5: FY | F5: FY | G5: FY | H5: FY | I5: FY | J5: LTM | L5: 1Q | M5: 2Q | N5: 3Q | O5: 4Q | P5: 1Q | Q5: 2Q | R5: 3Q | S5: 4Q | T5: 1Q | U5: 2Q | V5: 3Q | W5: 4Q | X5: 1Q | Y5: 2Q | Z5: 3Q | AA5: 4Q | AB5: 1Q | AC5: 2Q | AD5: 3Q | AE5: 4Q
B7: Revenue breakup by region
B8: Latin America | C8: 137640 | D8: 148630 | E8: 180400 | F8: 219750 | G8: 172540 | H8: 176000 | I8: 193580 | J8: =SUM(AB8:AE8) -> 193580 | L8: 25070 | M8: 50880 | N8: 46830 | O8: =E8-SUM(L8:N8) -> 57620 | P8: 34640 | Q8: 60920 | R8: 59740 | S8: =F8-SUM(P8:R8) -> 64450 | T8: 29650 | U8: 50330 | V8: 42870 | W8: =G8-SUM(T8:V8) -> 49690 | X8: 26590 | Y8: 50430 | Z8: 48150 | AA8: =H8-SUM(X8:Z8) -> 50830 | AB8: 24010 | AC8: 56930 | AD8: 51370 | AE8: =I8-SUM(AB8:AD8) -> 61270
B9: North America | C9: 56350 | D9: 56910 | E9: 78100 | F9: 87350 | G9: 38930 | H9: 60700 | I9: 71820 | J9: =SUM(AB9:AE9) -> 71820 | L9: 12210 | M9: 9580 | N9: 21170 | O9: =E9-SUM(L9:N9) -> 35140 | P9: 17960 | Q9: 11850 | R9: 27450 | S9: =F9-SUM(P9:R9) -> 30090 | T9: 8700 | U9: 12630 | V9: 9900 | W9: =G9-SUM(T9:V9) -> 7700 | X9: 12350 | Y9: 5580 | Z9: 15710 | AA9: =H9-SUM(X9:Z9) -> 27060 | AB9: 13370 | AC9: 9070 | AD9: 16170 | AE9: =I9-SUM(AB9:AD9) -> 33210
B10: Europe | C10: 57140 | D10: 64220 | E10: 68900 | F10: 73240 | G10: 66090 | H10: 71900 | I10: 81670 | J10: =SUM(AB10:AE10) -> 81670 | L10: 15220 | M10: 13360 | N10: 14060 | O10: =E10-SUM(L10:N10) -> 26260 | P10: 17280 | Q10: 13540 | R10: 14440 | S10: =F10-SUM(P10:R10) -> 27980 | T10: 12590 | U10: 5070 | V10: 10060 | W10: =G10-SUM(T10:V10) -> 38370 | X10: 14250 | Y10: 13680 | Z10: 12850 | AA10: =H10-SUM(X10:Z10) -> 31120 | AB10: 15350 | AC10: 13710 | AD10: 15540 | AE10: =I10-SUM(AB10:AD10) -> 37070
B11: India | C11: 38280 | D11: 46770 | E11: 56900 | F11: 65390 | G11: 55030 | H11: 59500 | I11: 63430 | J11: =SUM(AB11:AE11) -> 63430 | L11: 19140 | M11: 14830 | N11: 9070 | O11: =E11-SUM(L11:N11) -> 13860 | P11: 20670 | Q11: 18080 | R11: 10750 | S11: =F11-SUM(P11:R11) -> 15890 | T11: 20540 | U11: 13870 | V11: 8600 | W11: =G11-SUM(T11:V11) -> 12020 | X11: 18720 | Y11: 15710 | Z11: 11050 | AA11: =H11-SUM(X11:Z11) -> 14020 | AB11: 22620 | AC11: 16600 | AD11: 11480 | AE11: =I11-SUM(AB11:AD11) -> 12730
B12: Rest of World | C12: 68150 | D12: 70440 | E12: 78100 | F12: 90020 | G12: 98400 | H12: 98300 | I12: 107890 | J12: =SUM(AB12:AE12) -> 107890 | L12: 13500 | M12: 17020 | N12: 21850 | O12: =E12-SUM(L12:N12) -> 25730 | P12: 17650 | Q12: 20670 | R12: 24410 | S12: =F12-SUM(P12:R12) -> 27290 | T12: 18140 | U12: 19800 | V12: 27440 | W12: =G12-SUM(T12:V12) -> 33020 | X12: 18760 | Y12: 25500 | Z12: 21310 | AA12: =H12-SUM(X12:Z12) -> 32730 | AB12: 16810 | AC12: 23880 | AD12: 28140 | AE12: =I12-SUM(AB12:AD12) -> 39060
B13: Total | C13: =SUM(C7:C12) -> 357560 | D13: =SUM(D7:D12) -> 386970 | E13: =SUM(E7:E12) -> 462400 | F13: =SUM(F7:F12) -> 535750 | G13: =SUM(G7:G12) -> 430990 | H13: =SUM(H7:H12) -> 466400 | I13: =SUM(I7:I12) -> 518390 | J13: =SUM(J8:J12) -> 518390 | L13: =SUM(L7:L12) -> 85140 | M13: =SUM(M7:M12) -> 105670 | N13: =SUM(N7:N12) -> 112980 | O13: =SUM(O7:O12) -> 158610 | P13: =SUM(P7:P12) -> 108200 | Q13: =SUM(Q7:Q12) -> 125060 | R13: =SUM(R7:R12) -> 136790 | S13: =SUM(S7:S12) -> 165700 | ... AE13: =SUM(AE7:AE12) -> 183340
B14: Check | C14: =C13-Model!C7 -> 0 | D14: =D13-Model!D7 -> 30 | E14: =E13-Model!E7 -> 0 | F14: =F13-Model!F7 -> -10 | G14: =G13-Model!G7 -> 10 | H14: =H13-Model!H7 -> 30 | I14: =I13-Model!I7 -> 0 | L14: =L13-Model!L7 -> -10 | M14: =M13-Model!M7 -> 0 | N14: =N13-Model!N7 -> 10 | O14: =O13-Model!O7 -> 0 | P14: =P13-Model!P7 -> -10 | Q14: =Q13-Model!Q7 -> -10 | R14: =R13-Model!R7 -> 0 | S14: =S13-Model!S7 -> 10 | ... AE14: =AE13-Model!AE7 -> -10
B16: Revenue contribution by region (%)
B17: Latin America | C17: =C8/C$13 -> 0.38494239 | D17: =D8/D$13 -> 0.38408662 | E17: =E8/E$13 -> 0.39013841 | F17: =F8/F$13 -> 0.41017266 | G17: =G8/G$13 -> 0.40033411 | H17: =H8/H$13 -> 0.37735849 | I17: =I8/I$13 -> 0.37342541 | J17: =J8/J$13 -> 0.37342541 | L17: =L8/L$13 -> 0.29445619 | M17: =M8/M$13 -> 0.48149901 | N17: =N8/N$13 -> 0.41449814 | O17: =O8/O$13 -> 0.363281 | P17: =P8/P$13 -> 0.32014787 | Q17: =Q8/Q$13 -> 0.48712618 | R17: =R8/R$13 -> 0.43672783 | S17: =S8/S$13 -> 0.38895594 | ... AE17: =AE8/AE$13 -> 0.33418785
B18: North America | C18: =C9/C$13 -> 0.15759593 | D18: =D9/D$13 -> 0.14706566 | E18: =E9/E$13 -> 0.16890138 | F18: =F9/F$13 -> 0.16304246 | G18: =G9/G$13 -> 0.090326922 | H18: =H9/H$13 -> 0.1301458 | I18: =I9/I$13 -> 0.13854434 | J18: =J9/J$13 -> 0.13854434 | L18: =L9/L$13 -> 0.14341085 | M18: =M9/M$13 -> 0.090659601 | N18: =N9/N$13 -> 0.1873783 | O18: =O9/O$13 -> 0.22154971 | P18: =P9/P$13 -> 0.16598891 | Q18: =Q9/Q$13 -> 0.094754518 | R18: =R9/R$13 -> 0.20067256 | S18: =S9/S$13 -> 0.18159324 | ... AE18: =AE9/AE$13 -> 0.18113887
B19: Europe | C19: =C10/C$13 -> 0.15980535 | D19: =D10/D$13 -> 0.16595602 | E19: =E10/E$13 -> 0.14900519 | F19: =F10/F$13 -> 0.13670555 | G19: =G10/G$13 -> 0.15334463 | H19: =H10/H$13 -> 0.15415952 | I19: =I10/I$13 -> 0.15754548 | J19: =J10/J$13 -> 0.15754548 | L19: =L10/L$13 -> 0.17876439 | M19: =M10/M$13 -> 0.12643134 | N19: =N10/N$13 -> 0.1244468 | O19: =O10/O$13 -> 0.16556333 | P19: =P10/P$13 -> 0.15970425 | Q19: =Q10/Q$13 -> 0.10826803 | R19: =R10/R$13 -> 0.10556327 | S19: =S10/S$13 -> 0.16885938 | ... AE19: =AE10/AE$13 -> 0.20219265
B20: India | C20: =C11/C$13 -> 0.10705896 | D20: =D11/D$13 -> 0.12086208 | E20: =E11/E$13 -> 0.12305363 | F20: =F11/F$13 -> 0.1220532 | G20: =G11/G$13 -> 0.12768278 | H20: =H11/H$13 -> 0.1275729 | I20: =I11/I$13 -> 0.12235961 | J20: =J11/J$13 -> 0.12235961 | L20: =L11/L$13 -> 0.2248062 | M20: =M11/M$13 -> 0.14034258 | N20: =N11/N$13 -> 0.080279696 | O20: =O11/O$13 -> 0.08738415 | P20: =P11/P$13 -> 0.19103512 | Q20: =Q11/Q$13 -> 0.14457061 | R20: =R11/R$13 -> 0.078587616 | S20: =S11/S$13 -> 0.095896198 | ... AE20: =AE11/AE$13 -> 0.069433839
B21: Rest of World | C21: =C12/C$13 -> 0.19059738 | D21: =D12/D$13 -> 0.18202961 | E21: =E12/E$13 -> 0.16890138 | F21: =F12/F$13 -> 0.16802613 | G21: =G12/G$13 -> 0.22831156 | H21: =H12/H$13 -> 0.21076329 | I21: =I12/I$13 -> 0.20812516 | J21: =J12/J$13 -> 0.20812516 | L21: =L12/L$13 -> 0.15856237 | M21: =M12/M$13 -> 0.16106747 | N21: =N12/N$13 -> 0.19339706 | O21: =O12/O$13 -> 0.1622218 | P21: =P12/P$13 -> 0.16312384 | Q21: =Q12/Q$13 -> 0.16528067 | R21: =R12/R$13 -> 0.17844872 | S21: =S12/S$13 -> 0.16469523 | ... AE21: =AE12/AE$13 -> 0.2130468
B23: Revenue growth by region (%)
B24: Latin America | C24: 0.24 | D24: 0.08 | E24: 0.21 | F24: 0.22 | G24: -0.21 | H24: 0.02 | I24: 0.1 | L24: 0.24 | M24: 0.2 | N24: 0.22 | O24: 0.21 | P24: 0.38 | Q24: 0.2 | R24: 0.28 | S24: 0.12 | T24: -0.14 | U24: -0.17 | V24: -0.28 | W24: -0.23 | X24: -0.1 | Y24: 0 | Z24: 0.12 | AA24: 0.02 | AB24: -0.1 | AC24: 0.13 | AD24: 0.07 | AE24: 0.21
B25: North America | C25: 0.13 | D25: 0.01 | E25: 0.37 | F25: 0.12 | G25: -0.55 | H25: 0.56 | I25: 0.18 | L25: 0.19 | M25: 0.24 | N25: 0.57 | O25: 0.38 | P25: 0.47 | Q25: 0.24 | R25: 0.3 | S25: -0.14 | T25: -0.52 | U25: -0.07 | V25: -0.64 | W25: -0.49 | X25: 0.42 | Y25: 0.1 | Z25: 0.59 | AA25: 0.77 | AB25: 0.08 | AC25: 0.63 | AD25: 0.03 | AE25: 0.23
B26: Europe | C26: -0.07 | D26: 0.12 | E26: 0.07 | F26: 0.07 | G26: -0.1 | H26: 0.09 | I26: 0.14 | L26: -0.11 | M26: 0.31 | N26: 0.26 | O26: 0.02 | P26: 0.13 | Q26: 0.01 | R26: 0.03 | S26: 0.07 | T26: -0.27 | U26: -0.57 | V26: -0.3 | W26: 0.1 | X26: 0.13 | Y26: 0.08 | Z26: 0.28 | AA26: 0.09 | AB26: 0.08 | AC26: 0 | AD26: 0.21 | AE26: 0.19
B27: India | C27: 0.11 | D27: 0.22 | E27: 0.11 | F27: 0.13 | G27: -0.16 | H27: 0.08 | I27: 0.07 | L27: 0.27 | M27: 0.05 | N27: 0 | O27: 0.63 | P27: 0.08 | Q27: 0.22 | R27: 0.19 | S27: 0.15 | T27: -0.01 | U27: -0.23 | V27: -0.2 | W27: -0.24 | X27: -0.09 | Y27: 0.13 | Z27: 0.28 | AA27: 0.17 | AB27: 0.21 | AC27: 0.06 | AD27: 0.04 | AE27: -0.09
B28: Rest of World | C28: 0.12 | D28: 0.03 | E28: 0.22 | F28: 0.1 | G28: 0.09 | H28: 0 | I28: 0.1 | L28: -0.14 | M28: 0.13 | N28: 0.15 | O28: 0.25 | P28: 0.31 | Q28: 0.21 | R28: 0.12 | S28: 0.06 | T28: 0.03 | U28: -0.04 | V28: 0.12 | W28: 0.21 | X28: 0.03 | Y28: 0.29 | Z28: -0.22 | AA28: -0.01 | AB28: -0.1 | AC28: -0.06 | AD28: 0.32 | AE28: 0.19
C30: Annual | D30: Annual | E30: Annual | F30: Annual | G30: Annual | H30: Annual | I30: Annual | J30: LTM | L30: Quarters | M30: Quarters | N30: Quarters | O30: Quarters | P30: Quarters | Q30: Quarters | R30: Quarters | S30: Quarters | T30: Quarters | U30: Quarters | V30: Quarters | W30: Quarters | X30: Quarters | Y30: Quarters | Z30: Quarters | AA30: Quarters | AB30: Quarters | AC30: Quarters | AD30: Quarters | AE30: Quarters
B31: =Model!B30 -> As % of Revenues unless stated otherwise | C31: 43921 | D31: 44286 | E31: 44651 | F31: 45016 | G31: 45382 | H31: =H3 -> 45747 | I31: =I3 -> 46112 | J31: =AE31 -> 46112 | L31: 44377 | M31: 44469 | N31: 44561 | O31: 44651 | P31: 44742 | Q31: 44834 | R31: 44926 | S31: 45016 | T31: 45107 | U31: 45199 | V31: 45291 | W31: 45382 | X31: 45473 | Y31: =Y3 -> 45565 | Z31: =Z3 -> 45657 | AA31: =AA3 -> 45747 | AB31: 45838 | AC31: =AC3 -> 45930 | AD31: =AD3 -> 46022 | AE31: =AE3 -> 46112
B32: Volume yoy | E32: 0.08 | F32: 0.002 | G32: -0.06 | H32: 0.13 | I32: 0.08 | L32: 0.06 | M32: 0.15 | N32: 0.11 | O32: 0.03 | P32: 0.06 | Q32: -0.07 | R32: 0.01 | S32: 0.01 | T32: -0.09 | U32: -0.07 | V32: -0.05 | W32: -0.02 | X32: -0.09 | Y32: 0.16 | Z32: 0.09 | AA32: 0.11 | AB32: -0.01 | AC32: 0.07 | AD32: 0.08
B33: Price yoy | E33: 0.1 | F33: 0.1 | G33: -0.17 | H33: -0.03 | I33: -0.03 | L33: 0.02 | M33: 0.03 | N33: 0.13 | O33: 0.19 | P33: 0.18 | Q33: 0.21 | R33: 0.13 | S33: -0.03 | T33: -0.1 | U33: -0.15 | V33: -0.24 | W33: -0.15 | X33: -0.1 | Y33: -0.07 | Z33: 0.05 | AA33: 0.01 | AB33: 0.01 | AC33: -0.02 | AD33: 0.03
B34: Revenue | E34: =E13 -> 462400 | F34: =F13 -> 535750 | G34: =G13 -> 430990 | H34: =H13 -> 466400 | I34: =I13 -> 518390 | J34: =SUM(AB34:AE34) -> 518390 | L34: =L13 -> 85140 | M34: =M13 -> 105670 | N34: =N13 -> 112980 | O34: =O13 -> 158610 | P34: =P13 -> 108200 | Q34: =Q13 -> 125060 | R34: =R13 -> 136790 | S34: =S13 -> 165700 | ... AE34: =AE13 -> 183340
B35: Revenue yoy | E35: =Model!E9 -> 0.19501732 | F35: =Model!F9 -> 0.15865052 | G35: =Model!G9 -> -0.19557264 | H35: =Model!H9 -> 0.082115179 | I35: =Model!I9 -> 0.11154234 | J35: =I35 -> 0.11154234 | L35: 0.09 | M35: 0.18 | N35: 0.24 | O35: 0.24 | P35: =P13/L13-1 -> 0.27084802 | Q35: =Q13/M13-1 -> 0.18349579 | R35: =R13/N13-1 -> 0.21074526 | S35: =S13/O13-1 -> 0.044700839 | T35: =T13/P13-1 -> -0.17171904 | U35: =U13/Q13-1 -> -0.18679034 | V35: =V13/R13-1 -> -0.27721325 | W35: =W13/S13-1 -> -0.15027158 | ... AE35: =AE13/AA13-1 -> 0.17706728
B37: EBITDA | E37: =Model!E49 -> 101650 | F37: =Model!F49 -> 111780 | G37: =Model!G49 -> 55150 | H37: =Model!H49 -> 81200 | I37: =Model!I49 -> 95880 | J37: =SUM(AB37:AE37) -> 95880 | L37: =Model!L49 -> 18620 | M37: =Model!M49 -> 20450 | N37: =Model!N49 -> 26660 | O37: =Model!O49 -> 35920 | P37: =Model!P49 -> 23420 | Q37: =Model!Q49 -> 27680 | R37: =Model!R49 -> 30350 | S37: =Model!S49 -> 30330 | ... AE37: =Model!AE49 -> 36460
B38: EBITDA yoy | E38: =Model!E50 -> 0.18763874 | F38: =Model!F50 -> 0.099655681 | G38: =Model!G50 -> -0.50662015 | H38: =Model!H50 -> 0.47234814 | I38: =Model!I50 -> 0.18078818 | J38: =I38 -> 0.18078818 | L38: 0.09 | M38: 0.13 | N38: 0.21 | O38: 0.26 | P38: =P37/L37-1 -> 0.25778733 | Q38: =Q37/M37-1 -> 0.35354523 | R38: =R37/N37-1 -> 0.1384096 | S38: =S37/O37-1 -> -0.15562361 | T38: =T37/P37-1 -> -0.31981213 | U38: =U37/Q37-1 -> -0.43171965 | V38: =V37/R37-1 -> -0.86293245 | W38: =W37/S37-1 -> -0.36267722 | ... AE38: =AE37/AA37-1 -> 0.12669963
B39: EBITDA margin | E39: =Model!E51 -> 0.21983131 | F39: =Model!F51 -> 0.2086382 | G39: =Model!G51 -> 0.12796417 | H39: =Model!H51 -> 0.17411068 | I39: =Model!I51 -> 0.18495727 | J39: =I39 -> 0.18495727 | L39: =Model!L51 -> 0.21867293 | M39: =Model!M51 -> 0.19352702 | N39: =Model!N51 -> 0.23599186 | O39: =Model!O51 -> 0.22646744 | P39: =Model!P51 -> 0.21643101 | Q39: =Model!Q51 -> 0.22131606 | R39: =Model!R51 -> 0.22187294 | S39: =Model!S51 -> 0.18305269 | ... AE39: =Model!AE51 -> 0.19885465
C81: 43921 | D81: 44286 | E81: 44651 | F81: 45016 | G81: 45382 | H81: 45747 | I81: 46112 | J81: =J3 -> 46112 | L81: 44377 | M81: 44469 | N81: 44561 | O81: 44651 | P81: 44742 | Q81: 44834 | R81: 44926 | S81: 45016 | T81: 45107 | U81: 45199 | V81: 45291 | W81: 45382 | X81: 45473 | Y81: =Y3 -> 45565 | Z81: =Z3 -> 45657 | AA81: =AA3 -> 45747 | AB81: 45838 | AC81: =AC3 -> 45930 | AD81: =AD3 -> 46022 | AE81: =AE3 -> 46112
B82: EBITDA | E82: =E37 -> 101650 | F82: =F37 -> 111780 | G82: =G37 -> 55150 | H82: =H37 -> 81200 | I82: =I37 -> 95880 | J82: =J37 -> 95880 | L82: =L37 -> 18620 | M82: =M37 -> 20450 | N82: =N37 -> 26660 | O82: =O37 -> 35920 | P82: =P37 -> 23420 | Q82: =Q37 -> 27680 | R82: =R37 -> 30350 | S82: =S37 -> 30330 | ... AE82: =AE37 -> 36460
B83: EBITDA margin | E83: =E39 -> 0.21983131 | F83: =F39 -> 0.2086382 | G83: =G39 -> 0.12796417 | H83: =H39 -> 0.17411068 | I83: =I39 -> 0.18495727 | J83: =J39 -> 0.18495727 | L83: =L39 -> 0.21867293 | M83: =M39 -> 0.19352702 | N83: =N39 -> 0.23599186 | O83: =O39 -> 0.22646744 | P83: =P39 -> 0.21643101 | Q83: =Q39 -> 0.22131606 | R83: =R39 -> 0.22187294 | S83: =S39 -> 0.18305269 | ... AE83: =AE39 -> 0.19885465

Sheet Detailed Debt information
A3: FY25 | B3: Below details published only on Annual basis by company
B6: All values in INR Millions, recorded at amortised cost
B7: Particulars | C7: Effective Interest Date | D7: Maturity | E7: FY23 | F7: FY24 | G7: FY25
E8: 45016 | F8: 45382 | G8: 45747
B9: A) Non-current borrowings
B10: 1) Debentures
B11: i) Unsecured Redeemable non-convertible debentures (NCDs) | C11: 10.40% to 10.470% | D11: 2021-2023 | E11: 0 | F11: 0 | G11: 0
B13: 2) Bonds (Unsecured)
B14: i) 4.50% Senior Notes (Note 1) | C14: 0.045 | D14: 8th March 2028 | E14: 22540 | F14: 22910 | G14: 23510
B15: ii) 4.625% Senior Notes (Note 2) | C15: 0.04625 | D15: 16th June 2030 | E15: 36370 | F15: 36980 | G15: 37970
B16: Total Bonds | E16: =SUM(E14:E15) -> 58910 | F16: =SUM(F14:F15) -> 59890 | G16: =SUM(G14:G15) -> 61480
B18: 3) Term Loans
B19: i) From Bank
B20: a) Foreign currency loan (Unsecured) | C20: SOFR + 1.25% and 1.40% | D20: Sep 2025 and Sep 2027 | E20: 61170 | F20: 95200 | G20: 76620
B21: b) Sustainability linked Foreign currency loan (Unsecured) | C21: SOFR + 1.27%, 1.46%, 1.65% | D21: January 2024/March 2026/Dec 2026 | E21: 97720 | F21: 82780 | G21: 85120
B22: ii) From others (Unsecured) | C22: 0.02 | D22: 1st January 2023 | E22: 0 | F22: 2230 | G22: 1980
B23: Total Term Loans | E23: =SUM(E20:E22) -> 158890 | F23: =SUM(F20:F22) -> 180210 | G23: =SUM(G20:G22) -> 163720
B25: Total Non-Current Borrowings | E25: =E23+E16+E11 -> 217800 | F25: =F23+F16+F11 -> 240100 | G25: =G23+G16+G11 -> 225200
B28: B) Current borrowings
B29: 1) Loan from banks
B30: i) Secured | C30: Euribor +1.30% to 8.0% | D30: On demand | E30: 830 | F30: 1950 | G30: 0
B31: ii) Unsecured | G31: 530
B32: a) Working capital loan repayable on demand from banks: | C32: 3.45% to 13% | D32: On demand | E32: 6730 | F32: 37380 | G32: 9130
B33: b) Interest accrued and not due on borrowings | C33: NA | D33: NA | E33: 1130 | F33: 1950 | G33: 1780
B34: c) Commercial paper | C34: 0.084 | D34: Within 90 days | E34: 3500 | F34: 3000 | G34: 500
B35: Total Loans from banks | E35: =SUM(E30:E34) -> 12190 | F35: =SUM(F30:F34) -> 44280 | G35: =SUM(G30:G34) -> 11940
B37: 2) Discounted trade receivables (Unsecured) | C37: 5.00% - 9.90% | D37: 2021-22 | E37: 0 | F37: 0 | G37: 0
B39: 3) Current maturities of non current borrowings | C39: NA | D39: NA | E39: 16360 | F39: 0 | G39: 42570
B41: Total Current Borrowings | E41: =E35+E37+E39 -> 28550 | F41: =F35+F37+F39 -> 44280 | G41: =G35+G37+G39 -> 54510
B44: Total Non current borrowings | E44: =E25 -> 217800 | F44: =F25 -> 240100 | G44: =G25 -> 225200
B45: Less current portion | E45: =E39 -> 16360 | F45: =F39 -> 0 | G45: =G39 -> 42570
B46: Net Non Current Borrowings | E46: =E44-E45 -> 201440 | F46: =F44-F45 -> 240100 | G46: =G44-G45 -> 182630
B47: Secured Portion | E47: 0 | F47: 2230 | G47: 1980
B48: Unsecured Portion | E48: 201440 | F48: 237870 | G48: 223220
B49: Net Current Borrowings | E49: =E41 -> 28550 | F49: =F41 -> 44280 | G49: =G41 -> 54510
B50: Secured Portion | E50: 830 | F50: 1950 | G50: =G35 -> 11940
B51: Unsecured Portion | E51: 27720 | F51: 42330 | G51: =G39 -> 42570
B52: Total Borrowings | E52: =E46+E49 -> 229990 | F52: =F46+F49 -> 284380 | G52: =G46+G49 -> 237140
B53: Check | E53: =E52-Model!F109 -> 0 | F53: =F52-Model!G109 -> 0 | G53: =G52-Model!H109 -> 0
B57: Note 1
B58: Bonds of USD 443 million 4.625% Senior Notes due 2030 with carrying value of INR36,980 million (March 31, 2023: INR36,370 million) are recorded at net of amortised cost bearing an interest rate of 4.625%, repayable on 16 June 2030
B61: Note 2
B62: Bonds of USD 274 million 4.50% Senior Notes due 2028 with carrying value of INR22,910 million (March 31, 2023: INR22,540 million) are recorded at net of amortised cost bearing an interest rate of 4.50%, repayable on 8 March 2028.
