Workbook
Name \A: #REF!
Name \B: #REF!
Name \C: #REF!
Name \L: #REF!
Name \M: #REF!
Name \P: #REF!
Name \Y: #REF!
Name _01_30_04: MonthlyOpStats
Name _1_30_01: MonthlyOpStats
Name _1_30_02: MonthlyOpStats
Name _1_31_01: MonthlyOpStats
Name _1_31_02: MonthlyOpStats
Name _12_31_05: MonthlyOpStats
Name _A: #REF!
Name _A___0: #REF!
Name _B: #REF!
Name _B___0: #REF!
Name _C: #REF!
Name _C___0: #REF!
Name _ent1: [1]Inputs!$J$17
Name _ent10: [1]Inputs!$J$476
Name _ent11: [1]Inputs!$J$527
Name _ent12: [1]Inputs!$J$578
Name _ent13: [1]Inputs!$J$629
Name _ent14: [1]Inputs!$J$680
Name _ent15: [1]Inputs!$J$731
Name _ent2: [1]Inputs!$J$68
Name _ent3: [1]Inputs!$J$119
Name _ent4: [1]Inputs!$J$170
Name _ent5: [1]Inputs!$J$221
Name _ent6: [1]Inputs!$J$272
Name _ent7: [1]Inputs!$J$323
Name _ent8: [1]Inputs!$J$374
Name _ent9: [1]Inputs!$J$425
Name _eps1: [1]Inputs!$P$42
Name _eps10: [1]Inputs!$P$501
Name _eps11: [1]Inputs!$P$552
Name _eps12: [1]Inputs!$P$603
Name _eps13: [1]Inputs!$P$654
Name _eps14: [1]Inputs!$P$705
Name _eps15: [1]Inputs!$P$756
Name _eps2: [1]Inputs!$P$93
Name _eps3: [1]Inputs!$P$144
Name _eps4: [1]Inputs!$P$195
Name _eps5: [1]Inputs!$P$246
Name _eps6: [1]Inputs!$P$297
Name _eps7: [1]Inputs!$P$348
Name _eps8: [1]Inputs!$P$399
Name _eps9: [1]Inputs!$P$450
Name _fye1: [1]Inputs!$E$12
Name _fye10: [1]Inputs!$E$471
Name _fye11: [1]Inputs!$E$522
Name _fye12: [1]Inputs!$E$573
Name _fye13: [1]Inputs!$E$624
Name _fye14: [1]Inputs!$E$675
Name _fye15: [1]Inputs!$E$726
Name _fye2: [1]Inputs!$E$63
Name _fye3: [1]Inputs!$E$114
Name _fye4: [1]Inputs!$E$165
Name _fye5: [1]Inputs!$E$216

Sheet Capitalisation
A3: 1Q26
B5: Debt Breakdown as on 31-Mar-2026 | C5: USD mn | D5: Leverage | H5: Company Reported | I5: USD mn | J5: Leverage
B6: Long-term debt - Including current portion | C6: =SUM(C7:C16) -> 1175.6845
B7: Series B Senior Note 60,000,000 5.31% (2) September 2027 | C7: 60
B8: Series B Senior Note 45,000,000 5.85% (2) May 2028 | C8: 45
B9: MetLife 10-year 118,000,000 4.75% (1) December 2027 | C9: 0
B10: Series RC Senior Note 70,000,000 5.18% (3) June 2029 | C10: 70
B11: Series RD Senior Note 15,000,000 5.28% (4) June 2031 | C11: 15
B12: Vesta ESG Global bond 35/8 05/31 350,000,000 3.63% (5) May 2031 | C12: 350
B13: Facility – Tranche I 75,000,000 SOFR + 130 bp (6) December 2027 | C13: 75
B14: Facility – Tranche II 75,000,000 SOFR + 150 bp (6) December 2029 | C14: 75
B15: Senior Notes 2033 500,000,000 5.50% (7) January 2033 | C15: 500
B16: (Less) Direct Issuance Costs | C16: -14.315517
B18: Operating lease liabilities | C18: =Model!$AP$121 -> 1.383273
B20: Total Loans & Borrowings | C20: =C6+C18 -> 1177.0678 | D20: =C20/C25 -> 4.9470288
B21: Cash and Cash Equivalents | C21: =Model!$AP$127 -> 206.14451
B22: Net debt exc Short term inv | C22: =C20-C21 -> 970.92324 | D22: =C22/C25 -> 4.0806361
B23: Equity | C23: =Model!$AP$131 -> 2858.6722
B24: Total Capitalisation | C24: =C22+C23 -> 3829.5954
B25: LTM Adjusted EBITDA | C25: =Model!$AP$98 -> 237.93429
B26: check | C26: =C20-Model!$AP$126 -> 0
B29: Liquidity at 1Q26 | C29: USD mn
B30: Cash and cash equivalents | C30: 206.12475
B31: Restricted cash - Current | C31: 0.019765
B32: Restricted cash - Non Current | C32: 0
B33: Total Liquidity | C33: =+C30+C31+C32 -> 206.14451
B34: check | C34: =C33-C21 -> 0
B37: Debt maturity at 1Q26 | C37: USD mn
B38: 2027 | C38: =60+75 -> 135
B39: 2028 | C39: =45 -> 45
B40: 2029 | C40: =70+75 -> 145
B41: 2030 and later | C41: =15+350+500 -> 865
B42: (Less) Direct Issuance Costs | C42: =C16 -> -14.315517
B43: Total long-term debt | C43: =SUM(C38:C42) -> 1175.6845
B44: check | C44: =C43-C6 -> 0
B47: Lease maturity at 1Q26 | C47: USD mn
B48: Not later than 1 year | C48: 0.719902
B49: Later than 1 year and not later than 5 years | C49: 0.77466
B50: (Less) future finance cost | C50: -0.111289
B51: Total long-term debt | C51: =SUM(C48:C50) -> 1.383273
B52: check | C52: =C51-C18 -> 0
A58: FY25
B60: Debt Breakdown as on 31-Dec-2025 | C60: USD mn | D60: Leverage | H60: Company Reported | I60: USD mn | J60: Leverage
B61: Long-term debt - Including current portion | C61: =SUM(C62:C75) -> 1275.2014 | H61: Debt | I61: 1275.2014 | J61: =I61/$C$82 -> 5.5179636
B62: MetLife - 10 Year - 4.55% | C62: 0 | H62: Cash, cash equivalents and restricted cash | I62: -336.90128
B63: Series A Senior Note - 5.03% | C63: 0 | H63: Net Debt | I63: =SUM(I61:I62) -> 938.30011 | J63: =I63/$C$82 -> 4.0601476
B64: Series B Senior Note - 5.31% | C64: 60
B65: Series A Senior Note - 5.50% | C65: 0
B66: Series B Senior Note - 5.85% | C66: 45
B67: MetLife - 10 Year - 4.75% | C67: 100.63484
B68: MetLife - 8 Year - 4.75% | C68: 0
B69: Series RC Senior Notes - 5.18% | C69: 70
B70: Series RD Senior Notes - 5.28% | C70: 15
B71: Vesta ESG Global Bond 3.63% | C71: 350
B72: Facility - Tranche I SOFR + 130 bp | C72: 75
B73: Facility - Tranche II SOFR + 150 bp | C73: 75
B74: Senior Notes 2033 5.50% | C74: 500
B75: (Less) Direct Issuance Costs | C75: -15.433448
B76: Operating lease liabilities | C76: =Model!$AO$121 -> 1.456046
B77: Total Loans & Borrowings | C77: =C61+C76 -> 1276.6574 | D77: =C77/C82 -> 5.5242641
B78: Cash and Cash Equivalents | C78: =Model!$AO$127 -> 336.90128
B79: Net debt exc Short term inv | C79: =C77-C78 -> 939.75616 | D79: =C79/C82 -> 4.0664481
B80: Equity | C80: =Model!$AO$131 -> 2747.7567
B81: Total Capitalisation | C81: =C79+C80 -> 3687.5129
B82: LTM Adjusted EBITDA | C82: =Model!$AO$98 -> 231.1
B83: check | C83: =C77-Model!$AO$126 -> 0
B85: Liquidity at FY25 | C85: USD mn
B86: Cash and cash equivalents | C86: 336.88147
B87: Restricted cash - Current | C87: 0.019813
B88: Restricted cash - Non Current | C88: 0.735312
B89: Total Liquidity | C89: =+C86+C87+C88 -> 337.63659
B92: Debt maturity at FY25 | C92: USD mn
B93: 2027 | C93: =60+100.634841+75 -> 235.63484
B94: 2028 | C94: =45 -> 45
B95: 2029 | C95: =70+75 -> 145
B96: 2030 and later | C96: =15+350+500 -> 865
B97: (Less) Direct Issuance Costs | C97: =C75 -> -15.433448
B98: Total long-term debt | C98: =SUM(C93:C97) -> 1275.2014
B99: check | C99: =C98-C61 -> 0
B101: Lease maturity at 3FY25 | C101: USD mn
B102: Not later than 1 year | C102: =0.717288 -> 0.717288
B103: Later than 1 year and not later than 5 years | C103: 0.86408
B104: (Less) future finance cost | C104: -0.125322
B105: Total long-term debt | C105: =SUM(C102:C104) -> 1.456046
B106: check | C106: =C105-C76 -> 0
A112: 3Q25
B114: Debt Breakdown as on 30-Sep-2025 | C114: USD mn | D114: Leverage
B115: Long-term debt - Including current portion | C115: =SUM(C116:C128) -> 1445.2304
B116: MetLife - 10 Year - 4.55% | C116: 139.68957
B117: Series B Senior Note - 5.31% | C117: 60
B118: Series A Senior Note - 5.50% | C118: 0
B119: Series B Senior Note - 5.85% | C119: 45
B120: MetLife - 10 Year - 4.75% | C120: 101.06733
B121: MetLife - 8 Year - 4.75% | C121: 24.836172
B122: Series RC Senior Notes - 5.18% | C122: 70
B123: Series RD Senior Notes - 5.28% | C123: 15
B124: Vesta ESG Global Bond 3.625% | C124: 350
B125: Facility - Tranche I SOFR + 130 bp | C125: 75
B126: Facility - Tranche I SOFR + 150 bp | C126: 75
B127: Senior Notes 2033 5.50% | C127: 500
...

Sheet Model
B2: Corporación Inmobiliaria Vesta | C2: Annual | D2: Annual | E2: Annual | F2: Annual | G2: Annual | H2: Annual | I2: Annual | J2: Annual | K2: Annual | L2: LTM | N2: Quarters | O2: Quarters | P2: Quarters | Q2: Quarters | R2: Quarters | S2: Quarters | T2: Quarters | U2: Quarters | V2: Quarters | W2: Quarters | X2: Quarters | Y2: Quarters | Z2: Quarters | AA2: Quarters | AB2: Quarters | AC2: Quarters | AD2: Quarters | AE2: Quarters | AF2: Quarters | AG2: Quarters | AH2: Quarters | AI2: Quarters | AJ2: Quarters | AK2: Quarters | AL2: Quarters | AM2: Quarters | AN2: Quarters | AO2: Quarters | AP2: Quarters
B3: (USD million) | C3: 43100 | D3: 43465 | E3: 43830 | F3: 44196 | G3: 44561 | H3: 44926 | I3: 45291 | J3: 45657 | K3: 46022 | L3: =AP3 -> 46112 | N3: 43555 | O3: 43646 | P3: 43738 | Q3: 43830 | R3: 43921 | S3: 44012 | T3: 44104 | U3: 44196 | V3: 44286 | W3: 44377 | X3: 44469 | Y3: 44561 | Z3: 44651 | AA3: 44742 | AB3: 44834 | AC3: 44926 | AD3: 45016 | AE3: 45107 | AF3: 45199 | AG3: 45291 | AH3: 45382 | AI3: 45473 | AJ3: 45565 | AK3: 45657 | AL3: 45747 | AM3: 45838 | AN3: 45930 | AO3: 46022 | AP3: 46112
C4: Act | D4: Act | E4: Act | F4: Act | G4: Act | H4: Act | I4: Act | J4: Act | K4: Act | L4: Act | N4: Act | O4: Act | P4: Act | Q4: Act | R4: Act | S4: Act | T4: Act | U4: Act | V4: Act | W4: Act | X4: Act | Y4: Act | Z4: Act | AA4: Act | AB4: Act | AC4: Act | AD4: Act | AE4: Act | AF4: Act | AG4: Act | AH4: Act | AI4: Act | AJ4: Act | AK4: Act | AL4: Act | AM4: Act | AN4: Act | AO4: Act | AP4: Act
C5: FY | D5: FY | E5: FY | F5: FY | G5: FY | H5: FY | I5: FY | J5: FY | K5: FY | L5: LTM | N5: 1Q | O5: 2Q | P5: 3Q | Q5: 4Q | R5: 1Q | S5: 2Q | T5: 3Q | U5: 4Q | V5: 1Q | W5: 2Q | X5: 3Q | Y5: 4Q | Z5: 1Q | AA5: 2Q | AB5: 3Q | AC5: 4Q | AD5: 1Q | AE5: 2Q | AF5: 3Q | AG5: 4Q | AH5: 1Q | AI5: 2Q | AJ5: 3Q | AK5: 4Q | AL5: 1Q | AM5: 2Q | AN5: 3Q | AO5: 4Q | AP5: 1Q
B6: INCOME STATEMENT | AF6: Restated
B7: Rental Income | C7: =109.427282 -> 109.42728 | D7: 132.66927 | E7: 144.2924 | F7: 149.53589 | G7: 160.69839 | H7: 178.02546 | I7: 213.4483 | J7: 251.9505 | K7: 283.19337 | L7: =SUM(AM7:AP7) -> 292.90351 | N7: 36.290385 | O7: 35.928051 | P7: 35.825569 | Q7: =E7-SUM(N7:P7) -> 36.248397 | R7: 37.695133 | S7: 36.538805 | T7: 37.457861 | U7: =F7-SUM(R7:T7) -> 37.844088 | V7: 38.352404 | W7: 39.756847 | X7: 41.00213 | Y7: =G7-SUM(V7:X7) -> 41.587004 | Z7: 41.988045 | AA7: 41.340864 | AB7: 45.508043 | AC7: =H7-SUM(Z7:AB7) -> 49.188509 | AD7: 49.610889 | AE7: 48.693742 | AF7: 51.613071 | AG7: =I7-SUM(AD7:AF7) -> 63.530594 | AH7: 60.176393 | AI7: 57.668018 | AJ7: 58.377122 | AK7: =J7-SUM(AH7:AJ7) -> 75.728971 | AL7: 67.03901 | AM7: 62.2 | AN7: 72.420925 | AO7: =K7-SUM(AL7:AN7) -> 81.533435 | AP7: 76.749154
B8: Management Fees | C8: 0 | D8: 0 | E8: 0.072677 | F8: 0.319446 | G8: 0.087973 | H8: 0 | I8: 1.019316 | J8: 0.376618 | K8: 0.031437 | L8: =SUM(AM8:AP8) -> 0.006789 | N8: 0 | O8: 0.010681 | P8: 0 | Q8: =E8-SUM(N8:P8) -> 0.061996 | R8: 0.017667 | S8: 0.112015 | T8: 0.019768 | U8: =F8-SUM(R8:T8) -> 0.169996 | V8: 0.041387 | W8: 0.039083 | X8: 0.007502 | Y8: =G8-SUM(V8:X8) -> 1e-06 | Z8: 0 | AA8: 1.756358 | AB8: 0 | AC8: =H8-SUM(Z8:AB8) -> -1.756358 | AD8: 0.327618 | AE8: 3.23069 | AF8: =3.073078+0.330703+0.639933 -> 4.043714 | AG8: =I8-SUM(AD8:AF8) -> -6.582706 | AH8: 0.413263 | AI8: =3.309085+2.037764 -> 5.346849 | AJ8: =2.701432+2.611647 -> 5.313079 | AK8: =J8-SUM(AH8:AJ8) -> -10.696573 | AL8: 0.024648 | AM8: =3.2+1.9 -> 5.1 | AN8: =6789/10^6 -> 0.006789 | AO8: =K8-SUM(AL8:AN8) -> -5.1 | AP8: 0
B9: Total Revenue | C9: =SUM(C7:C8) -> 109.42728 | D9: =SUM(D7:D8) -> 132.66927 | E9: =SUM(E7:E8) -> 144.36508 | F9: =SUM(F7:F8) -> 149.85533 | G9: =SUM(G7:G8) -> 160.78636 | H9: =SUM(H7:H8) -> 178.02546 | I9: =SUM(I7:I8) -> 214.46761 | J9: =SUM(J7:J8) -> 252.32712 | ... L9: =SUM(L7:L8) -> 292.9103 | N9: =SUM(N7:N8) -> 36.290385 | O9: =SUM(O7:O8) -> 35.938732 | P9: =SUM(P7:P8) -> 35.825569 | Q9: =SUM(Q7:Q8) -> 36.310393 | R9: =SUM(R7:R8) -> 37.7128 | S9: =SUM(S7:S8) -> 36.65082 | T9: =SUM(T7:T8) -> 37.477629 | U9: =SUM(U7:U8) -> 38.014084 | ... AP9: =SUM(AP7:AP8) -> 76.749154
B10: % of growth | D10: =(D7/C7)-1 -> 0.21239661 | E10: =(E7/D7)-1 -> 0.087609861 | F10: =(F7/E7)-1 -> 0.036339301 | G10: =(G7/F7)-1 -> 0.07464762 | H10: =(H7/G7)-1 -> 0.10782359 | I10: =(I7/H7)-1 -> 0.19897623 | J10: =(J7/I7)-1 -> 0.18038189 | K10: =(K7/J7)-1 -> 0.12400398 | R10: =(R7/N7)-1 -> 0.038708545 | S10: =(S7/O7)-1 -> 0.016999364 | T10: =(T7/P7)-1 -> 0.045562207 | U10: =(U7/Q7)-1 -> 0.044021009 | V10: =(V7/R7)-1 -> 0.017436495 | W10: =(W7/S7)-1 -> 0.088071901 | X10: =(X7/T7)-1 -> 0.094620165 | Y10: =(Y7/U7)-1 -> 0.098903586 | ... AP10: =(AP7/AL7)-1 -> 0.14484319
B11: COR - Related to Properties that generated rental income | C11: -4.106403 | D11: -4.848618 | E11: -7.26649 | F11: -8.925518 | G11: =-8543961/10^6 -> -8.543961 | H11: =-8940789/10^6 -> -8.940789 | I11: =-13476324/10^6 -> -13.476324 | J11: -21.24416 | K11: -24.104475 | L11: =SUM(AM11:AP11) -> -25.829283 | N11: -1.338009 | O11: -1.689009 | P11: -1.708186 | Q11: =E11-SUM(N11:P11) -> -2.531286 | R11: -2.275524 | S11: -2.589607 | T11: -2.004441 | U11: =F11-SUM(R11:T11) -> -2.055946 | V11: -1.173883 | W11: -2.252464 | X11: -2.473727 | Y11: =G11-SUM(V11:X11) -> -2.643887 | Z11: -1.603949 | AA11: -2.444505 | AB11: -2.342554 | AC11: =H11-SUM(Z11:AB11) -> -2.549781 | AD11: -2.238569 | AE11: -3.390747 | AF11: -3.924533 | AG11: =I11-SUM(AD11:AF11) -> -3.922475 | AH11: -3.786225 | AI11: -5.014314 | AJ11: -5.412651 | AK11: =J11-SUM(AH11:AJ11) -> -7.03097 | AL11: -4.445843 | AM11: -5.6 | AN11: -7.226843 | AO11: =K11-SUM(AL11:AN11) -> -6.831789 | AP11: -6.170651
B12: COR - Related to Properties that did not generate rental income | C12: -0.886688 | D12: -0.828082 | E12: -0.874128 | F12: -1.229137 | G12: =-2182796/10^6 -> -2.182796 | H12: =-2482605/10^6 -> -2.482605 | I12: =-4763398/10^6 -> -4.763398 | J12: -3.348273 | K12: -4.171323 | L12: =SUM(AM12:AP12) -> -4.670426 | N12: -0.222134 | O12: -0.09285 | P12: -0.105084 | Q12: =E12-SUM(N12:P12) -> -0.45406 | R12: -0.242162 | S12: -0.285434 | T12: -0.287292 | U12: =F12-SUM(R12:T12) -> -0.414249 | V12: -0.27204 | W12: -0.358192 | X12: -0.353652 | Y12: =G12-SUM(V12:X12) -> -1.198912 | Z12: -0.514839 | AA12: -0.169774 | AB12: -0.591547 | AC12: =H12-SUM(Z12:AB12) -> -1.206445 | AD12: -0.666089 | AE12: -0.977976 | AF12: -1.400458 | AG12: =I12-SUM(AD12:AF12) -> -1.718875 | AH12: -0.71703 | AI12: -1.178181 | AJ12: -1.067008 | AK12: =J12-SUM(AH12:AJ12) -> -0.386054 | AL12: -0.758698 | AM12: -0.92 | AN12: -1.008863 | AO12: =K12-SUM(AL12:AN12) -> -1.483762 | AP12: -1.257801
B13: Gross Profit | C13: =C9+C11+C12 -> 104.43419 | D13: =D9+D11+D12 -> 126.99257 | E13: =E9+E11+E12 -> 136.22446 | F13: =F9+F11+F12 -> 139.70068 | G13: =G9+G11+G12 -> 150.0596 | H13: =H9+H11+H12 -> 166.60207 | I13: =I9+I11+I12 -> 196.22789 | J13: =J9+J11+J12 -> 227.73469 | ... L13: =L9+L11+L12 -> 262.41059 | N13: =N9+N11+N12 -> 34.730242 | O13: =O9+O11+O12 -> 34.156873 | P13: =P9+P11+P12 -> 34.012299 | Q13: =Q9+Q11+Q12 -> 33.325047 | R13: =R9+R11+R12 -> 35.195114 | S13: =S9+S11+S12 -> 33.775779 | T13: =T9+T11+T12 -> 35.185896 | U13: =U9+U11+U12 -> 35.543889 | ... AP13: =AP9+AP11+AP12 -> 69.320702
B14: Gross Profit margin | C14: =C13/C7 -> 0.95437069 | D14: =D13/D7 -> 0.95721164 | E14: =E13/E7 -> 0.94408617 | F14: =F13/F7 -> 0.93422844 | G14: =G13/G7 -> 0.93379657 | H14: =H13/H7 -> 0.93583281 | I14: =I13/I7 -> 0.91932282 | J14: =J13/J7 -> 0.90388662 | ... L14: =L13/L7 -> 0.89589432 | N14: =N13/N7 -> 0.95700947 | O14: =O13/O7 -> 0.95070209 | P14: =P13/P7 -> 0.94938615 | Q14: =Q13/Q7 -> 0.9193523 | R14: =R13/R7 -> 0.93367794 | S14: =S13/S7 -> 0.92438105 | T14: =T13/T7 -> 0.93934611 | U14: =U13/U7 -> 0.93921907 | ... AP14: =AP13/AP7 -> 0.90321128
B15: Operating expenses:
B16: Administration Expenses | C16: -13.911938 | D16: -16.094364 | E16: -17.630342 | F16: -17.184479 | G16: =-19799701/10^6 -> -19.799701 | H16: =-(16300021+6650487)/10^6 -> -22.950508 | I16: =-(22139991+8001831)/10^6 -> -30.141822 | J16: =-23.779729-8.982488 -> -32.762217 | K16: =(-24137274-9630465)/1000000 -> -33.767739 | L16: =SUM(AM16:AP16) -> -34.783625 | N16: -4.313463 | O16: -4.597505 | P16: -4.462334 | Q16: =E16-SUM(N16:P16) -> -4.25704 | R16: -4.67189 | S16: -3.962524 | T16: -4.004564 | U16: =F16-SUM(R16:T16) -> -4.545501 | V16: -4.933187 | W16: -4.928192 | X16: -5.144429 | Y16: =G16-SUM(V16:X16) -> -4.793893 | Z16: -6.113201 | AA16: -5.738825 | AB16: -5.529993 | AC16: =H16-SUM(Z16:AB16) -> -5.568489 | AD16: =-5.04415-2.792918 -> -7.837068 | AE16: -6.437817 | AF16: -7.054483 | AG16: =I16-SUM(AD16:AF16) -> -8.812454 | AH16: =-6.082243-2.146913 -> -8.229156 | AI16: -9.047505 | AJ16: -7.00599 | AK16: =J16-SUM(AH16:AJ16) -> -8.479566 | AL16: =(-8924602+636653)/1000000 -> -8.287949 | AM16: -8.3 | AN16: -8.326405 | AO16: =K16-SUM(AL16:AN16) -> -8.853385 | AP16: =(-9775131+471296)/1000000 -> -9.303835
B17: Depreciation | C17: -0.356727 | D17: -0.573177 | E17: -1.494778 | F17: -1.477413 | G17: =-1601216/10^6 -> -1.601216 | H17: =-1463920/10^6 -> -1.46392 | I17: =-1578073/10^6 -> -1.578073 | J17: -1.416026 | K17: -1.724637 | L17: =SUM(AM17:AP17) -> -1.55928 | N17: -0.337236 | O17: -0.337236 | P17: -0.403047 | Q17: =E17-SUM(N17:P17) -> -0.417259 | R17: -0.492342 | S17: -0.299754 | T17: -0.323789 | U17: =F17-SUM(R17:T17) -> -0.361528 | V17: -0.388299 | W17: -0.396139 | X17: -0.390724 | Y17: =G17-SUM(V17:X17) -> -0.426054 | Z17: -0.349123 | AA17: -0.330449 | AB17: -0.405601 | AC17: =H17-SUM(Z17:AB17) -> -0.378747 | AD17: -0.368875 | AE17: -0.376117 | AF17: -0.265962 | AG17: =I17-SUM(AD17:AF17) -> -0.567119 | AH17: -0.327639 | AI17: -0.146099 | AJ17: -0.425616 | AK17: =J17-SUM(AH17:AJ17) -> -0.516672 | AL17: -0.636653 | AM17: -0.1 | AN17: 0 | AO17: =K17-SUM(AL17:AN17) -> -0.987984 | AP17: -0.471296
B18: Total operating expenses | C18: =C16+C17 -> -14.268665 | D18: =D16+D17 -> -16.667541 | E18: =E16+E17 -> -19.12512 | F18: =F16+F17 -> -18.661892 | G18: =G16+G17 -> -21.400917 | H18: =H16+H17 -> -24.414428 | I18: =I16+I17 -> -31.719895 | J18: =J16+J17 -> -34.178243 | ... L18: =L16+L17 -> -36.342905 | N18: =N16+N17 -> -4.650699 | O18: =O16+O17 -> -4.934741 | P18: =P16+P17 -> -4.865381 | Q18: =Q16+Q17 -> -4.674299 | R18: =R16+R17 -> -5.164232 | S18: =S16+S17 -> -4.262278 | T18: =T16+T17 -> -4.328353 | U18: =U16+U17 -> -4.907029 | ... AP18: =AP16+AP17 -> -9.775131
B19: Operating profit | C19: =C13+C18 -> 90.165526 | D19: =D13+D18 -> 110.32502 | E19: =E13+E18 -> 117.09934 | F19: =F13+F18 -> 121.03879 | G19: =G13+G18 -> 128.65868 | H19: =H13+H18 -> 142.18764 | I19: =I13+I18 -> 164.50799 | J19: =J13+J18 -> 193.55645 | ... L19: =L13+L18 -> 226.06769 | N19: =N13+N18 -> 30.079543 | O19: =O13+O18 -> 29.222132 | P19: =P13+P18 -> 29.146918 | Q19: =Q13+Q18 -> 28.650748 | R19: =R13+R18 -> 30.030882 | S19: =S13+S18 -> 29.513501 | T19: =T13+T18 -> 30.857543 | U19: =U13+U18 -> 30.63686 | ... AP19: =AP13+AP18 -> 59.545571
B20: % margin | C20: =+C19/C7 -> 0.82397666 | D20: =+D19/D7 -> 0.83157937 | E20: =+E19/E7 -> 0.81154198 | F20: =+F19/F7 -> 0.80942969 | G20: =+G19/G7 -> 0.80062213 | H20: =+H19/H7 -> 0.79869272 | I20: =+I19/I7 -> 0.7707159 | J20: =+J19/J7 -> 0.76823203 | ... L20: =+L19/L7 -> 0.77181624 | N20: =+N19/N7 -> 0.82885709 | O20: =+O19/O7 -> 0.81335144 | P20: =+P19/P7 -> 0.81357865 | Q20: =+Q19/Q7 -> 0.79040041 | R20: =+R19/R7 -> 0.79667797 | S20: =+S19/S7 -> 0.80773033 | T20: =+T19/T7 -> 0.82379352 | U20: =+U19/U7 -> 0.80955472 | ... AP20: =+AP19/AP7 -> 0.77584661
B21: Other income (expenses):
B22: Interest income | C22: 0.055171 | D22: 0.434427 | E22: 0.070394 | F22: 0.311959 | G22: =76871/10^6 -> 0.076871 | H22: =2640687/10^6 -> 2.640687 | I22: =9414027/10^6 -> 9.414027 | J22: 15.185565 | K22: 5.27266 | L22: =SUM(AM22:AP22) -> 6.336389 | N22: 0.014307 | O22: 0.016533 | P22: 0.022073 | Q22: =E22-SUM(N22:P22) -> 0.017481 | R22: 0.009967 | S22: 0.204945 | T22: 0.081746 | U22: =F22-SUM(R22:T22) -> 0.015301 | V22: 0.016572 | W22: 0.012215 | X22: 0.024167 | Y22: =G22-SUM(V22:X22) -> 0.023917 | Z22: 0.037774 | AA22: 0.132774 | AB22: 1.375039 | AC22: =H22-SUM(Z22:AB22) -> 1.0951 | AD22: 0.566836 | AE22: 0.5378 | AF22: 4.423263 | AG22: =I22-SUM(AD22:AF22) -> 3.886128 | AH22: 5.068364 | AI22: 4.06199 | AJ22: 4.010121 | AK22: =J22-SUM(AH22:AJ22) -> 2.04509 | AL22: 1.025445 | AM22: 0.4 | AN22: 0.651746 | AO22: =K22-SUM(AL22:AN22) -> 3.195469 | AP22: 2.089174
B23: Other income - net | C23: 0.449193 | D23: 0.47624 | E23: 1.051904 | F23: 0.007852 | G23: =27795/10^6 -> 0.027795 | H23: =956862/10^6 -> 0.956862 | I23: =(5138158-3037113)/10^6 -> 2.101045 | J23: =4.307956-5.152385 -> -0.844429 | K23: =(6818185-3523537)/1000000 -> 3.294648 | L23: =SUM(AM23:AP23) -> 4.296107 | N23: -0.207438 | O23: 0 | P23: 0.445761 | Q23: =E23-SUM(N23:P23) -> 0.813581 | R23: 0.079917 | S23: 0.098649 | T23: -0.202364 | U23: =F23-SUM(R23:T23) -> 0.03165 | V23: 0.093629 | W23: -0.014122 | X23: 0.116322 | Y23: =G23-SUM(V23:X23) -> -0.168034 | Z23: 0.025695 | AA23: 0.354909 | AB23: 0.257563 | AC23: =H23-SUM(Z23:AB23) -> 0.318695 | AD23: =0.256351-0.330286 -> -0.073935 | AE23: 0.808513 | AF23: =1.707806+0.222955 -> 1.930761 | AG23: =I23-SUM(AD23:AF23) -> -0.564294 | AH23: =0.895669-1.110553 -> -0.214884 | AI23: =1.140107-2.305118 -> -1.165011 | AJ23: =0.358488+0.114849 -> 0.473337 | AK23: =J23-SUM(AH23:AJ23) -> 0.062129 | AL23: =(1563173-518562)/1000000 -> 1.044611 | AM23: 0 | AN23: =(1196412-623458)/1000000 -> 0.572954 | AO23: =K23-SUM(AL23:AN23) -> 1.677083 | AP23: =3.636548-1.590478 -> 2.04607
B24: Transaction costs on debt issuance | C24: -0.395559 | D24: -0.139062 | E24: 0 | F24: 0 | G24: 0 | H24: 0 | I24: 0 | J24: 0 | K24: 0 | L24: =SUM(AM24:AP24) -> 0 | N24: 0 | O24: 0 | P24: 0 | Q24: =E24-SUM(N24:P24) -> 0 | R24: 0 | S24: 0 | T24: 0 | U24: =F24-SUM(R24:T24) -> 0 | V24: 0 | W24: 0 | X24: 0 | Y24: =G24-SUM(V24:X24) -> 0 | Z24: -10.40765 | AA24: 0 | AB24: 0 | AC24: =H24-SUM(Z24:AB24) -> 10.40765 | AD24: 0 | AE24: 0 | AF24: 0 | AG24: =I24-SUM(AD24:AF24) -> 0 | AH24: 0 | AI24: 0 | AJ24: 0 | AK24: =J24-SUM(AH24:AJ24) -> 0 | AL24: 0 | AM24: 0 | AN24: 0 | AO24: =K24-SUM(AL24:AN24) -> 0 | AP24: 0
B25: Interest expense | C25: -19.668274 | D25: -35.156825 | E25: -39.161931 | F25: -39.052739 | G25: =-50263493/10^6 -> -50.263493 | H25: =-46396156/10^6 -> -46.396156 | I25: =-46306975/10^6 -> -46.306975 | J25: -44.26139 | K25: -56.226952 | L25: =SUM(AM25:AP25) -> -64.896665 | N25: -9.181172 | O25: -11.210785 | P25: -9.102284 | Q25: =E25-SUM(N25:P25) -> -9.66769 | R25: -9.295627 | S25: -10.191399 | T25: -9.933891 | U25: =F25-SUM(R25:T25) -> -9.631822 | V25: -11.045969 | W25: -16.440226 | X25: -11.651279 | Y25: =G25-SUM(V25:X25) -> -11.126019 | Z25: 0 | AA25: -11.927469 | AB25: -11.783272 | AC25: =H25-SUM(Z25:AB25) -> -22.685415 | AD25: -11.580977 | AE25: -11.771653 | AF25: -11.395892 | AG25: =I25-SUM(AD25:AF25) -> -11.558453 | AH25: -10.212525 | AI25: -12.251664 | AJ25: -11.22982 | AK25: =J25-SUM(AH25:AJ25) -> -10.567381 | AL25: -10.285252 | AM25: -11.9 | AN25: -12.289994 | AO25: =K25-SUM(AL25:AN25) -> -21.751706 | AP25: -18.954965
B26: Exchange gain (loss)- net | C26: 2.897256 | D26: -0.719007 | E26: 2.15693 | F26: -0.171566 | G26: =-1109567/10^6 -> -1.109567 | H26: =1939848/10^6 -> 1.939848 | I26: =8906782/10^6 -> 8.906782 | J26: -10.837867 | K26: 10.097353 | L26: =SUM(AM26:AP26) -> 9.94163 | N26: 1.240277 | O26: 0.690787 | P26: -1.468717 | Q26: =E26-SUM(N26:P26) -> 1.694583 | R26: -9.104508 | S26: 1.73479 | T26: 7.666205 | U26: =F26-SUM(R26:T26) -> -0.468053 | V26: 0.500146 | W26: -0.254524 | X26: -0.476894 | Y26: =G26-SUM(V26:X26) -> -0.878295 | Z26: -0.800455 | AA26: 1.252495 | AB26: -0.754543 | AC26: =H26-SUM(Z26:AB26) -> 2.242351 | AD26: 4.602489 | AE26: 3.74076 | AF26: -2.149238 | AG26: =I26-SUM(AD26:AF26) -> 2.712771 | AH26: 0.854082 | AI26: -6.523491 | AJ26: -4.305296 | AK26: =J26-SUM(AH26:AJ26) -> -0.863162 | AL26: -0.096271 | AM26: 6.3 | AN26: 2.429486 | AO26: =K26-SUM(AL26:AN26) -> 1.464138 | AP26: -0.251994
B27: Gain on sale of investment property | C27: 0 | D27: 0 | E27: 17.920717 | F27: 0 | G27: =13992675/10^6 -> 13.992675 | H27: =5027826/10^6 -> 5.027826 | I27: =-461600/10^6 -> -0.4616 | J27: 2.617233 | K27: -0.009945 | L27: =SUM(AM27:AP27) -> -0.009945 | N27: 0 | O27: 16.017448 | P27: 0 | Q27: =E27-SUM(N27:P27) -> 1.903269 | R27: 0 | S27: 0 | T27: 0 | U27: =F27-SUM(R27:T27) -> 0 | V27: 4.299598 | W27: 4.25929 | X27: 0 | Y27: =G27-SUM(V27:X27) -> 5.433787 | Z27: 0.567754 | AA27: 4.460072 | AB27: 0 | AC27: =H27-SUM(Z27:AB27) -> 0 | AD27: 0 | AE27: 0 | AF27: 0 | AG27: =I27-SUM(AD27:AF27) -> -0.4616 | AH27: 0.25 | AI27: 0 | AJ27: 0 | AK27: =J27-SUM(AH27:AJ27) -> 2.367233 | AL27: 0 | AM27: -0.4 | AN27: 0.4 | AO27: =K27-SUM(AL27:AN27) -> -0.009945 | AP27: 0
B28: Share of results of associates | K28: 0.011538 | L28: =SUM(AM28:AP28) -> 0.04923 | AN28: -0.008711 | AO28: =K28-SUM(AL28:AN28) -> 0.020249 | AP28: 0.037692
B29: Gain on revaluation of investment property | C29: 84.058105 | D29: 52.822802 | E29: 86.062112 | F29: 45.370264 | G29: =164649959/10^6 -> 164.64996 | H29: =185491518/10^6 -> 185.49152 | I29: =243459821/10^6 -> 243.45982 | J29: 270.74766 | K29: 52.075064 | L29: =SUM(AM29:AP29) -> 121.54895 | N29: 11.954926 | O29: 32.442363 | P29: 13.944263 | Q29: =E29-SUM(N29:P29) -> 27.72056 | R29: 13.899686 | S29: 14.282625 | T29: 4.215727 | U29: =F29-SUM(R29:T29) -> 12.972226 | V29: -3.716929 | W29: 90.996712 | X29: 26.610777 | Y29: =G29-SUM(V29:X29) -> 50.759399 | Z29: 38.195915 | AA29: 38.599306 | AB29: 62.985726 | AC29: =H29-SUM(Z29:AB29) -> 45.710571 | AD29: 10.759462 | AE29: 73.628123 | AF29: 95.162184 | AG29: =I29-SUM(AD29:AF29) -> 63.910052 | AH29: 107.32603 | AI29: 100.0795 | AJ29: 23.969004 | AK29: =J29-SUM(AH29:AJ29) -> 39.373132 | AL29: -16.038206 | AM29: 7.8 | AN29: 4.792273 | AO29: =K29-SUM(AL29:AN29) -> 55.520997 | AP29: 53.435678
B30: Profit before tax | C30: =C19+SUM(C22:C29) -> 157.56142 | D30: =D19+SUM(D22:D29) -> 128.0436 | E30: =E19+SUM(E22:E29) -> 185.19947 | F30: =F19+SUM(F22:F29) -> 127.50456 | G30: =G19+SUM(G22:G29) -> 256.03292 | H30: =H19+SUM(H22:H29) -> 291.84822 | I30: =I19+SUM(I22:I29) -> 381.62109 | J30: =J19+SUM(J22:J29) -> 426.16322 | ... L30: =L19+SUM(L22:L29) -> 303.33338 | N30: =N19+SUM(N22:N29) -> 33.900443 | O30: =O19+SUM(O22:O29) -> 67.178478 | P30: =P19+SUM(P22:P29) -> 32.988014 | Q30: =Q19+SUM(Q22:Q29) -> 51.132532 | R30: =R19+SUM(R22:R29) -> 25.620317 | S30: =S19+SUM(S22:S29) -> 35.643111 | T30: =T19+SUM(T22:T29) -> 32.684966 | U30: =U19+SUM(U22:U29) -> 33.556162 | ... AP30: =AP19+SUM(AP22:AP29) -> 97.947226
B31: Current income tax expense | C31: -31.531237 | D31: -21.892031 | E31: -37.670744 | F31: -26.15048 | G31: =-50262466/10^6 -> -50.262466 | H31: =-41981391/10^6 -> -41.981391 | I31: =-91953099/10^6 -> -91.953099 | J31: -31.892785 | K31: -56.138103 | L31: =SUM(AM31:AP31) -> -39.439241 | N31: -11.167037 | O31: -12.273515 | P31: -6.39751 | Q31: =E31-SUM(N31:P31) -> -7.832682 | R31: -1.851778 | S31: -3.21361 | T31: -6.63117 | U31: =F31-SUM(R31:T31) -> -14.453922 | V31: -5.521844 | W31: -13.492846 | X31: -6.671784 | Y31: =G31-SUM(V31:X31) -> -24.575992 | Z31: -9.13698 | AA31: -12.346817 | AB31: -6.534278 | AC31: =H31-SUM(Z31:AB31) -> -13.963316 | AD31: -20.749621 | AE31: -21.475691 | AF31: -31.57051 | AG31: =I31-SUM(AD31:AF31) -> -18.157277 | AH31: -25.733091 | AI31: -22.526023 | AJ31: -10.712706 | AK31: =J31-SUM(AH31:AJ31) -> 27.079035 | AL31: -13.663554 | AM31: -26.8 | AN31: -27.446316 | AO31: =K31-SUM(AL31:AN31) -> 11.771767 | AP31: 3.035308
B32: Deferred income tax | C32: 0 | D32: -13.091239 | E32: -12.918014 | F32: -34.397994 | G32: =-31828085/10^6 -> -31.828085 | H32: =-6242079/10^6 -> -6.242079 | I32: =26969516/10^6 -> 26.969516 | J32: -170.92409 | K32: 64.069427 | L32: =SUM(AM32:AP32) -> 64.069427 | N32: -0.797586 | O32: -5.571251 | P32: -14.178535 | Q32: =E32-SUM(N32:P32) -> 7.629358 | R32: -48.187278 | S32: -13.36146 | T32: 10.588101 | U32: =F32-SUM(R32:T32) -> 16.562643 | V32: -1.939495 | W32: 11.477473 | X32: -35.832671 | Y32: =G32-SUM(V32:X32) -> -5.533392 | Z32: -2.502225 | AA32: -1.340663 | AB32: -20.210106 | AC32: =H32-SUM(Z32:AB32) -> 17.810915 | AD32: 32.974505 | AE32: 9.4986 | AF32: -23.193789 | AG32: =I32-SUM(AD32:AF32) -> 7.6902 | AH32: 0 | AI32: 0 | AJ32: 0 | AK32: =J32-SUM(AH32:AJ32) -> -170.92409 | AL32: 0 | AM32: 0 | AN32: 0 | AO32: =K32-SUM(AL32:AN32) -> 64.069427 | AP32: 0
B33: Net profit/loss | C33: =+C30+C31+C32 -> 126.03018 | D33: =+D30+D31+D32 -> 93.06033 | E33: =+E30+E31+E32 -> 134.61071 | F33: =+F30+F31+F32 -> 66.956082 | G33: =+G30+G31+G32 -> 173.94237 | H33: =+H30+H31+H32 -> 243.62475 | I33: =+I30+I31+I32 -> 316.63751 | J33: =+J30+J31+J32 -> 223.34635 | ... L33: =+L30+L31+L32 -> 327.96357 | N33: =+N30+N31+N32 -> 21.93582 | O33: =+O30+O31+O32 -> 49.333712 | P33: =+P30+P31+P32 -> 12.411969 | Q33: =+Q30+Q31+Q32 -> 50.929208 | R33: =+R30+R31+R32 -> -24.418739 | S33: =+S30+S31+S32 -> 19.068041 | T33: =+T30+T31+T32 -> 36.641897 | U33: =+U30+U31+U32 -> 35.664883 | ... AP33: =+AP30+AP31+AP32 -> 100.98253
B34: % margin | C34: =+C33/C7 -> 1.1517254 | D34: =+D33/D7 -> 0.70144603 | E34: =+E33/E7 -> 0.93290227 | F34: =+F33/F7 -> 0.44775929 | G34: =+G33/G7 -> 1.0824152 | H34: =+H33/H7 -> 1.3684826 | I34: =+I33/I7 -> 1.4834389 | J34: =+J33/J7 -> 0.88646914 | ... L34: =+L33/L7 -> 1.1196983 | N34: =+N33/N7 -> 0.60445267 | O34: =+O33/O7 -> 1.3731252 | P34: =+P33/P7 -> 0.3464556 | Q34: =+Q33/Q7 -> 1.4050058 | R34: =+R33/R7 -> -0.64779554 | S34: =+S33/S7 -> 0.52185727 | T34: =+T33/T7 -> 0.97821648 | U34: =+U33/U7 -> 0.94241624 | ... AP34: =+AP33/AP7 -> 1.3157478
B36: As % of sales unless stated otherwise
B37: =B11 -> COR - Related to Properties that generated rental income | C37: =-C11/C9 -> 0.037526318 | D37: =-D11/D9 -> 0.036546656 | E37: =-E11/E9 -> 0.050334125 | F37: =-F11/F9 -> 0.059560897 | G37: =-G11/G9 -> 0.053138594 | H37: =-H11/H9 -> 0.050221968 | I37: =-I11/I9 -> 0.062836173 | J37: =-J11/J9 -> 0.084192931 | ... L37: =-L11/L9 -> 0.088181545 | N37: =-N11/N9 -> 0.036869518 | O37: =-O11/O9 -> 0.0469969 | P37: =-P11/P9 -> 0.047680638 | Q37: =-Q11/Q9 -> 0.069712437 | R37: =-R11/R9 -> 0.060338241 | S37: =-S11/S9 -> 0.070656182 | T37: =-T11/T9 -> 0.053483666 | U37: =-U11/U9 -> 0.054083797 | ... AP37: =-AP11/AP9 -> 0.080400248
B38: =B12 -> COR - Related to Properties that did not generate rental income | C38: =-C12/C9 -> 0.0081029884 | D38: =-D12/D9 -> 0.0062417018 | E38: =-E12/E9 -> 0.0060549823 | F38: =-F12/F9 -> 0.0082021572 | G38: =-G12/G9 -> 0.013575754 | H38: =-H12/H9 -> 0.013945224 | I38: =-I12/I9 -> 0.022210337 | J38: =-J12/J9 -> 0.013269572 | ... L38: =-L12/L9 -> 0.015944902 | N38: =-N12/N9 -> 0.0061210152 | O38: =-O12/O9 -> 0.0025835636 | P38: =-P12/P9 -> 0.0029332123 | Q38: =-Q12/Q9 -> 0.01250496 | R38: =-R12/R9 -> 0.0064212151 | S38: =-S12/S9 -> 0.0077879294 | T38: =-T12/T9 -> 0.007665693 | U38: =-U12/U9 -> 0.010897251 | ... AP38: =-AP12/AP9 -> 0.016388467
B39: =B16 -> Administration Expenses | C39: =-C16/C9 -> 0.12713409 | D39: =-D16/D9 -> 0.12131192 | E39: =-E16/E9 -> 0.12212331 | F39: =-F16/F9 -> 0.11467379 | G39: =-G16/G9 -> 0.12314292 | H39: =-H16/H9 -> 0.128917 | I39: =-I16/I9 -> 0.14054254 | J39: =-J16/J9 -> 0.12984025 | ... L39: =-L16/L9 -> 0.1187518 | N39: =-N16/N9 -> 0.11885966 | O39: =-O16/O9 -> 0.12792619 | P39: =-P16/P9 -> 0.12455724 | Q39: =-Q16/Q9 -> 0.11724026 | R39: =-R16/R9 -> 0.12388075 | S39: =-S16/S9 -> 0.10811556 | T39: =-T16/T9 -> 0.10685212 | U39: =-U16/U9 -> 0.11957413 | ... AP39: =-AP16/AP9 -> 0.12122394
B40: =B17 -> Depreciation | C40: =-C17/C9 -> 0.0032599457 | D40: =-D17/D9 -> 0.004320345 | E40: =-E17/E9 -> 0.010354152 | F40: =-F17/F9 -> 0.0098589284 | G40: =-G17/G9 -> 0.0099586558 | H40: =-H17/H9 -> 0.0082230934 | I40: =-I17/I9 -> 0.0073580947 | J40: =-J17/J9 -> 0.005611866 | ... L40: =-L17/L9 -> 0.0053234044 | N40: =-N17/N9 -> 0.0092927093 | O40: =-O17/O9 -> 0.0093836366 | P40: =-P17/P9 -> 0.011250261 | Q40: =-Q17/Q9 -> 0.011491448 | R40: =-R17/R9 -> 0.013055037 | S40: =-S17/S9 -> 0.0081786438 | T40: =-T17/T9 -> 0.0086395273 | U40: =-U17/U9 -> 0.0095103699 | ... AP40: =-AP17/AP9 -> 0.0061407322
B41: =B22 -> Interest income | C41: =C22/C9 -> 0.00050417957 | D41: =D22/D9 -> 0.0032745112 | E41: =E22/E9 -> 0.000487611 | F41: =F22/F9 -> 0.0020817344 | G41: =G22/G9 -> 0.00047809404 | H41: =H22/H9 -> 0.014833198 | I41: =I22/I9 -> 0.043894866 | J41: =J22/J9 -> 0.060182056 | ... L41: =L22/L9 -> 0.021632523 | N41: =N22/N9 -> 0.00039423666 | O41: =O22/O9 -> 0.00046003292 | P41: =P22/P9 -> 0.0006161242 | Q41: =Q22/Q9 -> 0.00048143241 | R41: =R22/R9 -> 0.00026428693 | S41: =S22/S9 -> 0.0055918258 | T41: =T22/T9 -> 0.0021811945 | U41: =U22/U9 -> 0.00040250871 | ... AP41: =AP22/AP9 -> 0.027220808
B42: =B23 -> Other income - net | C42: =C23/C9 -> 0.0041049452 | D42: =D23/D9 -> 0.0035896784 | E42: =E23/E9 -> 0.0072864159 | F42: =F23/F9 -> 5.2397201e-05 | G42: =G23/G9 -> 0.00017286914 | H42: =H23/H9 -> 0.0053748604 | I42: =I23/I9 -> 0.0097965608 | J42: =J23/J9 -> -0.0033465645 | ... L42: =L23/L9 -> 0.014666971 | N42: =N23/N9 -> -0.0057160595 | O42: =O23/O9 -> 0 | P42: =P23/P9 -> 0.012442538 | Q42: =Q23/Q9 -> 0.022406285 | R42: =R23/R9 -> 0.0021190948 | S42: =S23/S9 -> 0.0026915905 | T42: =T23/T9 -> -0.0053995945 | U42: =U23/U9 -> 0.00083258615 | ... AP42: =AP23/AP9 -> 0.026659186
B43: =B24 -> Transaction costs on debt issuance | C43: =-C24/C9 -> 0.0036148115 | D43: =-D24/D9 -> 0.0010481855 | E43: =-E24/E9 -> 0 | F43: =-F24/F9 -> 0 | G43: =-G24/G9 -> 0 | H43: =-H24/H9 -> 0 | I43: =-I24/I9 -> 0 | J43: =-J24/J9 -> 0 | ... L43: =-L24/L9 -> 0 | N43: =-N24/N9 -> 0 | O43: =-O24/O9 -> 0 | P43: =-P24/P9 -> 0 | Q43: =-Q24/Q9 -> 0 | R43: =-R24/R9 -> 0 | S43: =-S24/S9 -> 0 | T43: =-T24/T9 -> 0 | U43: =-U24/U9 -> 0 | ... AP43: =-AP24/AP9 -> 0
B44: Interest expense as % of debt | C44: =-C25/C116 -> 0.033794583 | D44: =-D25/D116 -> 0.050238575 | E44: =-E25/E116 -> 0.054815816 | F44: =-F25/F116 -> 0.046504585 | G44: =-G25/G116 -> 0.053842212 | H44: =-H25/H116 -> 0.049861555 | I44: =-I25/I116 -> 0.050598389 | J44: =-J25/J116 -> 0.052253533 | ... L44: =-L25/L116 -> 0.055199049 | Q44: =-SUM(N25:Q25)/Q116 -> 0.054815816 | R44: =-SUM(O25:R25)/R116 -> 0.049125064 | S44: =-SUM(P25:S25)/S116 -> 0.045565115 | T44: =-SUM(Q25:T25)/T116 -> 0.046551764 | U44: =-SUM(R25:U25)/U116 -> 0.046504585 | V44: =-SUM(S25:V25)/V116 -> 0.048586516 | W44: =-SUM(T25:W25)/W116 -> 0.050353481 | X44: =-SUM(U25:X25)/X116 -> 0.052199537 | ... AP44: =-SUM(AM25:AP25)/AP116 -> 0.055199049
B45: =B26 -> Exchange gain (loss)- net | C45: =C26/C9 -> 0.026476542 | D45: =D26/D9 -> -0.0054195446 | E45: =E26/E9 -> 0.014940802 | F45: =F26/F9 -> -0.0011448775 | G45: =G26/G9 -> -0.0069008777 | H45: =H26/H9 -> 0.010896464 | I45: =I26/I9 -> 0.04152973 | J45: =J26/J9 -> -0.042951653 | ... L45: =L26/L9 -> 0.033940868 | N45: =N26/N9 -> 0.034176463 | O45: =O26/O9 -> 0.01922124 | P45: =P26/P9 -> -0.040996334 | Q45: =Q26/Q9 -> 0.046669365 | R45: =R26/R9 -> -0.24141692 | S45: =S26/S9 -> 0.047332911 | T45: =T26/T9 -> 0.20455416 | U45: =U26/U9 -> -0.012312621 | ... AP45: =AP26/AP9 -> -0.0032833456
B46: =B27 -> Gain on sale of investment property | C46: =C27/C9 -> 0 | D46: =D27/D9 -> 0 | E46: =E27/E9 -> 0.12413471 | F46: =F27/F9 -> 0 | G46: =G27/G9 -> 0.087026506 | H46: =H27/H9 -> 0.028242174 | I46: =I27/I9 -> -0.0021523063 | J46: =J27/J9 -> 0.010372381 | ... L46: =L27/L9 -> -3.3952373e-05 | N46: =N27/N9 -> 0 | O46: =O27/O9 -> 0.44568762 | P46: =P27/P9 -> 0 | Q46: =Q27/Q9 -> 0.052416646 | R46: =R27/R9 -> 0 | S46: =S27/S9 -> 0 | T46: =T27/T9 -> 0 | U46: =U27/U9 -> 0 | ... AP46: =AP27/AP9 -> 0
B47: =B29 -> Gain on revaluation of investment property | C47: =C29/C9 -> 0.76816406 | D47: =D29/D9 -> 0.39815402 | E47: =E29/E9 -> 0.59614217 | F47: =F29/F9 -> 0.30276042 | G47: =G29/G9 -> 1.0240294 | H47: =H29/H9 -> 1.0419381 | I47: =I29/I9 -> 1.1351822 | J47: =J29/J9 -> 1.0730026 | ... L47: =L29/L9 -> 0.41496986 | N47: =N29/N9 -> 0.32942406 | O47: =O29/O9 -> 0.90271307 | P47: =P29/P9 -> 0.38922656 | Q47: =Q29/Q9 -> 0.76343321 | R47: =R29/R9 -> 0.3685668 | S47: =S29/S9 -> 0.38969456 | T47: =T29/T9 -> 0.11248649 | U47: =U29/U9 -> 0.34124789 | ... AP47: =AP29/AP9 -> 0.69623801
B48: =B31 -> Current income tax expense | C48: =-C31/C9 -> 0.28814786 | D48: =-D31/D9 -> 0.16501208 | E48: =-E31/E9 -> 0.26094083 | F48: =-F31/F9 -> 0.17450483 | G48: =-G31/G9 -> 0.31260405 | H48: =-H31/H9 -> 0.23581678 | I48: =-I31/I9 -> 0.42875051 | J48: =-J31/J9 -> 0.1263946 | ... L48: =-L31/L9 -> 0.13464614 | N48: =-N31/N9 -> 0.30771338 | O48: =-O31/O9 -> 0.34151219 | P48: =-P31/P9 -> 0.17857386 | Q48: =-Q31/Q9 -> 0.2157146 | R48: =-R31/R9 -> 0.049102109 | S48: =-S31/S9 -> 0.087681804 | T48: =-T31/T9 -> 0.17693675 | U48: =-U31/U9 -> 0.38022544 | ... AP48: =-AP31/AP9 -> -0.039548423
B49: =B32 -> Deferred income tax | C49: =-C32/C9 -> 0 | D49: =-D32/D9 -> 0.098675748 | E49: =-E32/E9 -> 0.089481571 | F49: =-F32/F9 -> 0.22954134 | G49: =-G32/G9 -> 0.19795265 | H49: =-H32/H9 -> 0.035062844 | I49: =-I32/I9 -> -0.125751 | J49: =-J32/J9 -> 0.67739087 | ... L49: =-L32/L9 -> -0.21873395 | N49: =-N32/N9 -> 0.021977888 | O49: =-O32/O9 -> 0.1550208 | P49: =-P32/P9 -> 0.3957658 | Q49: =-Q32/Q9 -> -0.21011499 | R49: =-R32/R9 -> 1.2777433 | S49: =-S32/S9 -> 0.36456101 | T49: =-T32/T9 -> -0.2825179 | U49: =-U32/U9 -> -0.43569754 | ... AP49: =-AP32/AP9 -> 0
B50: Tax % of PBT | C50: =(-C31-C32)/C30 -> 0.20012029 | D50: =(-D31-D32)/D30 -> 0.27321373 | E50: =(-E31-E32)/E30 -> 0.27315823 | F50: =(-F31-F32)/F30 -> 0.47487302 | G50: =(-G31-G32)/G30 -> 0.32062498 | H50: =(-H31-H32)/H30 -> 0.16523476 | I50: =(-I31-I32)/I30 -> 0.17028299 | J50: =(-J31-J32)/J30 -> 0.4759136 | ... L50: =(-L31-L32)/L30 -> -0.081198402 | N50: =(-N31-N32)/N30 -> 0.35293412 | O50: =(-O31-O32)/O30 -> 0.26563219 | P50: =(-P31-P32)/P30 -> 0.62374307 | Q50: =(-Q31-Q32)/Q30 -> 0.0039764117 | R50: =(-R31-R32)/R30 -> 1.9531006 | S50: =(-S31-S32)/S30 -> 0.46502871 | T50: =(-T31-T32)/T30 -> -0.12106272 | U50: =(-U31-U32)/U30 -> -0.062841543 | ... AP50: =(-AP31-AP32)/AP30 -> -0.030989219
B52: Working capital /sales | C52: =C72/C9 -> -0.069877227 | D52: =D72/D9 -> -0.10072795 | E52: =E72/E9 -> -0.021570348 | F52: =F72/F9 -> -0.017305444 | G52: =G72/G9 -> 0.021445333 | H52: =H72/H9 -> -0.21576365 | I52: =I72/I9 -> -0.0011675702 | J52: =J72/J9 -> -0.013165041 | ... L52: =L72/L9 -> -0.019518839 | N52: =N72/N9 -> -0.12238991 | O52: =O72/O9 -> 0.2407416 | P52: =P72/P9 -> 0.12108994 | Q52: =Q72/Q9 -> -0.32118881 | R52: =R72/R9 -> -0.036179838 | S52: =S72/S9 -> -0.35781412 | T52: =T72/T9 -> 0.051503258 | U52: =U72/U9 -> 0.26187902 | ... AP52: =AP72/AP9 -> -0.36452866
B53: Capex/sales | C53: =-C76/C9 -> 1.7954423 | D53: =-D76/D9 -> 1.0484193 | E53: =-E76/E9 -> -0.0088339092 | F53: =-F76/F9 -> 0.48944237 | G53: =-G76/G9 -> -0.099213181 | H53: =-H76/H9 -> 1.4725849 | I53: =-I76/I9 -> 1.0401219 | J53: =-J76/J9 -> 0.89829894 | ... L53: =-L76/L9 -> 0.98683072 | N53: =-N76/N9 -> 0.56483146 | O53: =-O76/O9 -> -2.5494122 | P53: =-P76/P9 -> 1.0352078 | Q53: =-Q76/Q9 -> 0.90228913 | R53: =-R76/R9 -> 0.31877689 | S53: =-S76/S9 -> 0.59048755 | T53: =-T76/T9 -> 0.39592216 | U53: =-U76/U9 -> 0.65353417 | ... AP53: =-AP76/AP9 -> 0.20505786
B55: EBITDA | C55: =C3 -> 43100 | D55: =D3 -> 43465 | E55: =E3 -> 43830 | F55: =F3 -> 44196 | G55: =G3 -> 44561 | H55: =H3 -> 44926 | I55: =I3 -> 45291 | J55: =J3 -> 45657 | K55: =K3 -> 46022 | L55: =L2 -> LTM | N55: =N3 -> 43555 | O55: =O3 -> 43646 | P55: =P3 -> 43738 | Q55: =Q3 -> 43830 | R55: =R3 -> 43921 | S55: =S3 -> 44012 | T55: =T3 -> 44104 | U55: =U3 -> 44196 | ... AP55: =AP3 -> 46112
B56: Operating profit | C56: =+C19 -> 90.165526 | D56: =+D19 -> 110.32502 | E56: =+E19 -> 117.09934 | F56: =+F19 -> 121.03879 | G56: =+G19 -> 128.65868 | H56: =+H19 -> 142.18764 | I56: =+I19 -> 164.50799 | J56: =+J19 -> 193.55645 | ... L56: =+L19 -> 226.06769 | N56: =+N19 -> 30.079543 | O56: =+O19 -> 29.222132 | P56: =+P19 -> 29.146918 | Q56: =+Q19 -> 28.650748 | R56: =+R19 -> 30.030882 | S56: =+S19 -> 29.513501 | T56: =+T19 -> 30.857543 | U56: =+U19 -> 30.63686 | ... AP56: =+AP19 -> 59.545571
B57: Depreciation, depletion & amortization | C57: =-C17+1.43 -> 1.786727 | D57: =-D17+1.93 -> 2.503177 | E57: =-E17+2.79 -> 4.284778 | F57: =-F17+3.68 -> 5.157413 | G57: =-G17+5.55 -> 7.151216 | H57: =-H17+6.65 -> 8.11392 | I57: =-I17+8.001831 -> 9.579904 | J57: =-J17+8.982488 -> 10.398514 | K57: =-K17+9.630465 -> 11.355102 | L57: =SUM(AM57:AP57) -> 12.282045 | N57: =-N17+0.69 -> 1.027236 | O57: =-O17+0.7 -> 1.037236 | P57: =-P17+0.67 -> 1.073047 | Q57: =-Q17+0.7 -> 1.117259 | R57: =-R17+0.94 -> 1.432342 | S57: =-S17+0.87 -> 1.169754 | T57: =-T17+0.91 -> 1.233789 | U57: =-U17+0.96 -> 1.321528 | V57: =-V17+1.42 -> 1.808299 | W57: =-W17+1.43 -> 1.826139 | X57: =-X17+1.345609 -> 1.736333 | Y57: =-Y17+1.35 -> 1.776054 | Z57: =-Z17+1.65 -> 1.999123 | AA57: =-AA17+1.650944 -> 1.981393 | AB57: =-AB17+1.635247 -> 2.040848 | AC57: =-AC17+1.68 -> 2.058747 | AD57: =-AD17+2.79 -> 3.158875 | AE57: =-AE17+1.650944 -> 2.027061 | AF57: =-AF17+1.786611 -> 2.052573 | AG57: =-AG17+(8.001831-1.786611-1.650944-2.79) -> 2.341395 | AH57: =-AH17+2.146913 -> 2.474552 | AI57: =-AI17+2.6577 -> 2.803799 | AJ57: =-AJ17+2.147902 -> 2.573518 | AK57: =J57-SUM(AH57:AJ57) -> 2.546645 | AL57: =-AL17+2.196456 -> 2.833109 | AM57: =-AM17+2.4 -> 2.5 | AN57: =0.494869+2.336235 -> 2.831104 | AO57: =K57-SUM(AL57:AN57) -> 3.190889 | AP57: =-AP17+3.288756 -> 3.760052
B58: EBITDA | C58: =SUM(C56:C57) -> 91.952253 | D58: =SUM(D56:D57) -> 112.8282 | E58: =SUM(E56:E57) -> 121.38412 | F58: =SUM(F56:F57) -> 126.1962 | G58: =SUM(G56:G57) -> 135.8099 | H58: =SUM(H56:H57) -> 150.30156 | I58: =SUM(I56:I57) -> 174.0879 | J58: =SUM(J56:J57) -> 203.95496 | ... L58: =SUM(L56:L57) -> 238.34973 | N58: =SUM(N56:N57) -> 31.106779 | O58: =SUM(O56:O57) -> 30.259368 | P58: =SUM(P56:P57) -> 30.219965 | Q58: =SUM(Q56:Q57) -> 29.768007 | R58: =SUM(R56:R57) -> 31.463224 | S58: =SUM(S56:S57) -> 30.683255 | T58: =SUM(T56:T57) -> 32.091332 | U58: =SUM(U56:U57) -> 31.958388 | ... AP58: =SUM(AP56:AP57) -> 63.305623
B59: % growth | D59: =+D58/C58-1 -> 0.22703032 | E59: =+E58/D58-1 -> 0.075831369 | F59: =+F58/E58-1 -> 0.039643407 | G59: =+G58/F58-1 -> 0.076180591 | H59: =+H58/G58-1 -> 0.10670547 | I59: =+I58/H58-1 -> 0.15825744 | J59: =+J58/I58-1 -> 0.17156311 | K59: =+K58/J58-1 -> 0.13167993 | R59: =R58/N58-1 -> 0.011458756 | S59: =S58/O58-1 -> 0.014008455 | T59: =T58/P58-1 -> 0.061924857 | U59: =U58/Q58-1 -> 0.073581715 | V59: =V58/R58-1 -> 0.06265909 | W59: =W58/S58-1 -> 0.097897925 | X59: =X58/T58-1 -> 0.071424302 | Y59: =Y58/U58-1 -> 0.073280448 | ... AP59: =AP58/AL58-1 -> 0.13516801
B60: % margin | C60: =+C58/C7 -> 0.84030464 | D60: =+D58/D7 -> 0.85044717 | E60: =+E58/E7 -> 0.84123708 | F60: =+F58/F7 -> 0.84391915 | G60: =+G58/G7 -> 0.84512299 | H60: =+H58/H7 -> 0.84427002 | I60: =+I58/I7 -> 0.81559751 | J60: =+J58/J7 -> 0.80950408 | ... L60: =+L58/L7 -> 0.81374829 | N60: =+N58/N7 -> 0.8571631 | O60: =+O58/O7 -> 0.84222125 | P60: =+P58/P7 -> 0.84353064 | Q60: =+Q58/Q7 -> 0.82122272 | R60: =+R58/R7 -> 0.83467603 | S60: =+S58/S7 -> 0.83974435 | T60: =+T58/T7 -> 0.85673157 | U60: =+U58/U7 -> 0.84447505 | ... AP60: =+AP58/AP7 -> 0.82483806
B62: Adjustment | C62: =C63-C58 -> 0 | D62: =D63-D58 -> 0 | E62: =E63-E58 -> 0 | F62: =F63-F58 -> 0 | G62: =G63-G58 -> 0 | H62: =H63-H58 -> 0 | I62: =I63-I58 -> 0 | J62: =J63-J58 -> 0.44504 | ... L62: =L63-L58 -> -0.415449 | N62: =N63-N58 -> 0 | O62: =O63-O58 -> 0 | P62: =P63-P58 -> 0 | Q62: =Q63-Q58 -> 0 | R62: =R63-R58 -> 0 | S62: =S63-S58 -> 0 | T62: =T63-T58 -> 0 | U62: =U63-U58 -> 0 | ... AP62: =AP63-AP58 -> -1.212966
B63: Adj. EBITDA | C63: =C58 -> 91.952253 | D63: =D58 -> 112.8282 | E63: =E58 -> 121.38412 | F63: =F58 -> 126.1962 | G63: =G58 -> 135.8099 | H63: =H58 -> 150.30156 | I63: =I58 -> 174.0879 | J63: 204.4 | K63: 231.1 | L63: =SUM(AM63:AP63) -> 237.93429 | N63: =N58 -> 31.106779 | O63: =O58 -> 30.259368 | P63: =P58 -> 30.219965 | Q63: =Q58 -> 29.768007 | R63: =R58 -> 31.463224 | S63: =S58 -> 30.683255 | T63: =T58 -> 32.091332 | U63: =U58 -> 31.958388 | ... AG63: =AG58 -> 44.26836 | AH63: 50.578089 | AI63: =AI58 -> 50.432567 | AJ63: =AJ58 -> 52.352454 | AK63: =AK58 -> 51.165781 | AL63: 55.258372 | AM63: =AM58 -> 54.88 | AN63: 59.7 | AO63: =K63-SUM(AL63:AN63) -> 61.261628 | AP63: 62.092657
B64: % growth | D64: =+D63/C63-1 -> 0.22703032 | E64: =+E63/D63-1 -> 0.075831369 | F64: =+F63/E63-1 -> 0.039643407 | G64: =+G63/F63-1 -> 0.076180591 | H64: =+H63/G63-1 -> 0.10670547 | I64: =+I63/H63-1 -> 0.15825744 | J64: =+J63/I63-1 -> 0.17411952 | K64: =+K63/J63-1 -> 0.13062622 | R64: =R63/N63-1 -> 0.011458756 | S64: =S63/O63-1 -> 0.014008455 | T64: =T63/P63-1 -> 0.061924857 | U64: =U63/Q63-1 -> 0.073581715 | V64: =V63/R63-1 -> 0.06265909 | W64: =W63/S63-1 -> 0.097897925 | X64: =X63/T63-1 -> 0.071424302 | Y64: =Y63/U63-1 -> 0.073280448 | ... AP64: =AP63/AL63-1 -> 0.12367873
B65: % margin | C65: =+C63/C7 -> 0.84030464 | D65: =+D63/D7 -> 0.85044717 | E65: =+E63/E7 -> 0.84123708 | F65: =+F63/F7 -> 0.84391915 | G65: =+G63/G7 -> 0.84512299 | H65: =+H63/H7 -> 0.84427002 | I65: =+I63/I7 -> 0.81559751 | J65: =+J63/J7 -> 0.81127045 | ... L65: =+L63/L7 -> 0.81232991 | N65: =+N63/N7 -> 0.8571631 | O65: =+O63/O7 -> 0.84222125 | P65: =+P63/P7 -> 0.84353064 | Q65: =+Q63/Q7 -> 0.82122272 | R65: =+R63/R7 -> 0.83467603 | S65: =+S63/S7 -> 0.83974435 | T65: =+T63/T7 -> 0.85673157 | U65: =+U63/U7 -> 0.84447505 | ... AP65: =+AP63/AP7 -> 0.80903376
B67: Capex sales | C67: =-C76/C7 -> 1.7954423 | D67: =-D76/D7 -> 1.0484193 | E67: =-E76/E7 -> -0.0088383587 | F67: =-F76/F7 -> 0.49048794 | G67: =-G76/G7 -> -0.099267494 | H67: =-H76/H7 -> 1.4725849 | I67: =-I76/I7 -> 1.045089 | J67: =-J76/J7 -> 0.89964172 | ... L67: =-L76/L7 -> 0.98685359 | N67: =-N76/N7 -> 0.56483146 | O67: =-O76/O7 -> -2.5501701 | P67: =-P76/P7 -> 1.0352078 | Q67: =-Q76/Q7 -> 0.90383233 | R67: =-R76/R7 -> 0.31892629 | S67: =-S76/S7 -> 0.59229778 | T67: =-T76/T7 -> 0.39613111 | U67: =-U76/U7 -> 0.65646986 | ... AP67: =-AP76/AP7 -> 0.20505786
B68: WC SALES | C68: =C72/C7 -> -0.069877227 | D68: =D72/D7 -> -0.10072795 | E68: =E72/E7 -> -0.021581213 | F68: =F72/F7 -> -0.017342412 | G68: =G72/G7 -> 0.021457073 | H68: =H72/H7 -> -0.21576365 | I68: =I72/I7 -> -0.0011731459 | J68: =J72/J7 -> -0.013184721 | ... L68: =L72/L7 -> -0.019519291 | N68: =N72/N7 -> -0.12238991 | O68: =O72/O7 -> 0.24081317 | P68: =P72/P7 -> 0.12108994 | Q68: =Q72/Q7 -> -0.32173814 | R68: =R72/R7 -> -0.036196795 | S68: =S72/S7 -> -0.35891105 | T68: =T72/T7 -> 0.051530438 | U68: =U72/U7 -> 0.26305538 | ... AP68: =AP72/AP7 -> -0.36452866
B70: CASH FLOW | C70: =C3 -> 43100 | D70: =D3 -> 43465 | E70: =E3 -> 43830 | F70: =F3 -> 44196 | G70: =G3 -> 44561 | H70: =H3 -> 44926 | I70: =I3 -> 45291 | J70: =J3 -> 45657 | K70: =K3 -> 46022 | L70: =L2 -> LTM | N70: =N3 -> 43555 | O70: =O3 -> 43646 | P70: =P3 -> 43738 | Q70: =Q3 -> 43830 | R70: =R3 -> 43921 | S70: =S3 -> 44012 | T70: =T3 -> 44104 | U70: =U3 -> 44196 | ... AP70: =AP3 -> 46112
B71: Adj. EBITDA | C71: =C63 -> 91.952253 | D71: =D63 -> 112.8282 | E71: =E63 -> 121.38412 | F71: =F63 -> 126.1962 | G71: =G63 -> 135.8099 | H71: =H63 -> 150.30156 | I71: =I63 -> 174.0879 | J71: =J63 -> 204.4 | ... L71: =L63 -> 237.93429 | N71: =N63 -> 31.106779 | O71: =O63 -> 30.259368 | P71: =P63 -> 30.219965 | Q71: =E71-SUM(N71:P71) -> 29.798007 | R71: =R63 -> 31.463224 | S71: =S63 -> 30.683255 | T71: =T63 -> 32.091332 | U71: =U63 -> 31.958388 | V71: =V63 -> 33.434681 | W71: =W63 -> 33.687082 | X71: =X63 -> 34.383433 | Y71: =Y63 -> 34.300313 | ... AP71: =AP63 -> 62.092657
B72: Working Capital | C72: =1.807458-14.32504-0.332484+3.363652+1.839939 -> -7.646475 | D72: =-2.909036-8.943674-0.167753-2.22735+0.88431 -> -13.363503 | E72: =-0.14154-4.558054-0.730465+0.684301+1.631753 -> -3.114005 | F72: =1.911192-4.495989+0.847836-0.713267-0.143085 -> -2.593313 | G72: =-2.678246-4.516452-0.063524-0.230177+10.936516 -> 3.448117 | H72: =1.348952-10.710911-17.338623-1.619312-10.09153 -> -38.411424 | I72: =-2.410637-3.776348+4.008959+0.003258+1.924362 -> -0.250406 | J72: =5.419812-18.967824+19.179847-8.512107-0.441625 -> -3.321897 | K72: =-4.088859+5.29353-0.787488+0.642912 -> 1.060095 | L72: =SUM(AM72:AP72) -> -5.717269 | N72: =-0.318506+0.135087-1.811799-0.785956-1.660403 -> -4.441577 | O72: =-1.349164+5.768707-1.54518+2.119884-0.783876-N72 -> 8.651948 | P72: =0.000467+7.246339-1.963011+3.359281-0.094589-O72-N72 -> 4.338116 | Q72: =E72-SUM(N72:P72) -> -11.662492 | R72: =0.755103+0.774618-0.001741-1.553253+0.742237-2.122855+0.041448 -> -1.364443 | S72: =-0.526648-12.690928-1.302163+1.621094-1.579979-R72 -> -13.114181 | T72: =-0.804995-11.528694-0.391051+1.190815-1.014479-S72-R72 -> 1.93022 | U72: =F72-SUM(R72:T72) -> 9.955091 | V72: =-0.31377-3.638806-0.006211-2.080312+0.99142-1.440011+0.71671 -> -5.77098 | W72: =-0.184846+9.826746-3.127775+1.641523-0.839274-V72 -> 13.087354 | X72: =-1.069285+8.721256-1.518898+1.87901-0.37727-W72-V72 -> 0.318439 | Y72: =G72-SUM(V72:X72) -> -4.186696 | Z72: =2.519167+6.421346+0.26388-3.815885+3.146679-12.192544-0.254668 -> -3.912025 | AA72: =1.900471+9.500516-30.258341+3.962526-11.397359-Z72 -> -22.380162 | AB72: =1.736636+4.879666-18.241521+33.723994-10.660994-AA72-Z72 -> 37.729968 | AC72: =H72-SUM(Z72:AB72) -> -49.849205 | AD72: =-3.391723+4.339883+1.512522+2.05657+9.012106-1.613735-0.186324 -> 11.729299 | AE72: =-2.542551+6.931195-6.039568+1.009398-0.506668-AD72 -> -12.877493 | AF72: =-1.216366-1.176506+3.874754+15.933767+0.570711-AE72-AD72 -> 19.134554 | AG72: =I72-SUM(AD72:AF72) -> -18.236766 | AH72: =-4.737407+1.10638-0.479854-14.466736+7.228516-2.429474-0.085015 -> -13.86359 | AI72: =-1.79968-1.928855-5.194844+3.786041-1.763319-AH72 -> 6.962933 | AJ72: =2.008957+1.119415+14.344979-19.768972-1.129748-AI72-AH72 -> 3.475288 | AK72: =J72-SUM(AH72:AJ72) -> 0.103472 | AL72: =(-1881555-3206073-470183-7034683-7451494-1843846+687932)/1000000 -> -21.199902 | AM72: =-1.5-6.8-5.6-0.2-1-AL72 -> 6.099902 | AN72: =-4.310805-7.310117+0.330524-0.177477-AM72-AL72 -> 3.632125 | AO72: =K72-SUM(AL72:AN72) -> 12.52797 | AP72: =(-153332+862104+1254003-6098901-22602432-2549205+1310497)/1000000 -> -27.977266
B73: Taxes | C73: -2.242043 | D73: -12.542218 | E73: -16.091645 | F73: -24.092663 | G73: -27.06222 | H73: -54.995605 | I73: -64.103701 | J73: -75.01159 | K73: -40.11939 | L73: =SUM(AM73:AP73) -> -50.081178 | N73: -0.517446 | O73: =-14.050758-N73 -> -13.533312 | P73: =-15.443461-O73-N73 -> -1.392703 | Q73: =E73-SUM(N73:P73) -> -0.648184 | R73: -16.558044 | S73: =-8.979423-R73 -> 7.578621 | T73: =-17.789095-S73-R73 -> -8.809672 | U73: =F73-SUM(R73:T73) -> -6.303568 | V73: -5.166124 | W73: =-24.712872-V73 -> -19.546748 | X73: =-28.624984-W73-V73 -> -3.912112 | Y73: =G73-SUM(V73:X73) -> 1.562764 | Z73: -36.277915 | AA73: =-(48.901178)-Z73 -> -12.623263 | AB73: =-55.871027-AA73-Z73 -> -6.969849 | AC73: =H73-SUM(Z73:AB73) -> 0.875422 | AD73: -22.492445 | AE73: =-35.753958-AD73 -> -13.261513 | AF73: =-41.421299-AE73-AD73 -> -5.667341 | AG73: =I73-SUM(AD73:AF73) -> -22.682402 | AH73: -40.40214 | AI73: =-62.996814-AH73 -> -22.594674 | AJ73: =-79.680953-AH73-AI73 -> -16.684139 | AK73: =J73-SUM(AH73:AJ73) -> 4.669363 | AL73: -8.373559 | AM73: =-14.2-AL73 -> -5.826441 | AN73: =-20.308588-AL73-AM73 -> -6.108588 | AO73: =K73-SUM(AL73:AN73) -> -19.810802 | AP73: -18.335347
B74: Cash interest paid | C74: -15.907052 | D74: -32.288118 | E74: -38.606429 | F74: -37.986844 | G74: -44.474123 | H74: -44.84437 | I74: -45.034414 | J74: -42.08771 | K74: -45.88417 | L74: =SUM(AM74:AP74) -> -55.233535 | N74: -9.164014 | O74: =-19.78855-N74 -> -10.624536 | P74: =-32.918864-O74-N74 -> -13.130314 | Q74: =E74-SUM(N74:P74) -> -5.687565 | R74: -8.457043 | S74: =-18.774019-R74 -> -10.316976 | T74: =-28.402511-S74-R74 -> -9.628492 | U74: =F74-SUM(R74:T74) -> -9.584333 | V74: -10.415163 | W74: =-22.539258-V74 -> -12.124095 | X74: =-29.714415-W74-V74 -> -7.175157 | Y74: =G74-SUM(V74:X74) -> -14.759708 | Z74: -7.467529 | AA74: =-(22.164919)-Z74 -> -14.69739 | AB74: =-29.168137-AA74-Z74 -> -7.003218 | AC74: =H74-SUM(Z74:AB74) -> -15.676233 | AD74: -7.09824 | AE74: =-23.00014-AD74 -> -15.9019 | AF74: =-29.6771-AE74-AD74 -> -6.67696 | AG74: =I74-SUM(AD74:AF74) -> -15.357314 | AH74: -6.427036 | AI74: =-20.549596-AH74 -> -14.12256 | AJ74: =-27.416097-AH74-AI74 -> -6.866501 | AK74: =J74-SUM(AH74:AJ74) -> -14.671613 | AL74: -6.66977 | AM74: =-20.8-AL74 -> -14.13023 | AN74: =-27.584857-AL74-AM74 -> -6.784857 | AO74: =K74-SUM(AL74:AN74) -> -18.299313 | AP74: -16.019135
B75: Net cash from operations | C75: =SUM(C71:C74) -> 66.156683 | D75: =SUM(D71:D74) -> 54.634363 | E75: =SUM(E71:E74) -> 63.57204 | F75: =SUM(F71:F74) -> 61.523379 | G75: =SUM(G71:G74) -> 67.721674 | H75: =SUM(H71:H74) -> 12.05016 | I75: =SUM(I71:I74) -> 64.699378 | J75: =SUM(J71:J74) -> 83.978803 | ... L75: =SUM(L71:L74) -> 126.9023 | N75: =SUM(N71:N74) -> 16.983742 | O75: =SUM(O71:O74) -> 14.753468 | P75: =SUM(P71:P74) -> 20.035064 | Q75: =SUM(Q71:Q74) -> 11.799766 | R75: =SUM(R71:R74) -> 5.083694 | S75: =SUM(S71:S74) -> 14.830719 | T75: =SUM(T71:T74) -> 15.583388 | U75: =SUM(U71:U74) -> 26.025578 | ... AP75: =SUM(AP71:AP74) -> -0.239091
B76: Net Capex | C76: =-196.210053-0.260314 -> -196.47037 | D76: =-137.897718-1.1953 -> -139.09302 | E76: =-106.376406+109.26-1.608286 -> 1.275308 | F76: =-72.523331-0.822218 -> -73.345549 | G76: =-108.39427+124.565539-0.219143 -> 15.952126 | H76: =-269.222961+7.285242-0.219884 -> -262.1576 | I76: =-263.051665+42.0575-2.0783 -> -223.07247 | J76: =-231.137856+5.07-0.597329 -> -226.66519 | K76: =-336.934128+5.5-0.837371 -> -332.2715 | L76: =SUM(AM76:AP76) -> -289.05288 | N76: =-20.385168-0.112783 -> -20.497951 | O76: =-38.135309+109.26-N76 -> 91.622642 | P76: =-74.000185+109.26-1.222034-O76-N76 -> -37.08691 | Q76: =E76-SUM(N76:P76) -> -32.762473 | R76: -12.021969 | S76: =-33.663822-R76 -> -21.641853 | T76: =-48.269708-0.232338-S76-R76 -> -14.838224 | U76: =F76-SUM(R76:T76) -> -24.843503 | V76: =-25.607747+7.489115 -> -18.118632 | W76: =-48.094693-0.211272+15.954315-V76 -> -14.233018 | X76: =-78.553838-0.211273+15.954315-W76-V76 -> -30.459146 | Y76: =G76-SUM(V76:X76) -> 78.762922 | Z76: =-81.549633+0.909005 -> -80.640628 | AA76: =-(109.006462)+14.771388-Z76 -> -13.594446 | AB76: =-182.641651+14.771388-0.4425-AA76-Z76 -> -74.077689 | AC76: =H76-SUM(Z76:AB76) -> -93.84484 | AD76: =-54.236948-0.08566 -> -54.322608 | AE76: =-89.185947-0.195815-AD76 -> -35.059154 | AF76: =-195.666429-0.109674-AE76-AD76 -> -106.39434 | AG76: =I76-SUM(AD76:AF76) -> -27.296362 | AH76: =-47.625125-0.010441 -> -47.635566 | AI76: =-127.269831+25.217393+0.78-0.01044-AH76 -> -53.647312 | AJ76: =-172.493271-0.010444+0.78-AH76-AI76 -> -70.440837 | AK76: =J76-SUM(AH76:AJ76) -> -54.94147 | AL76: =(-58219038-737594)/1000000 -> -58.956632 | AM76: =-169.4-0.4-0.7-AL76 -> -111.54337 | AN76: =-226.50818+5.5-0.473938-AL76-AM76 -> -50.982118 | AO76: =K76-SUM(AL76:AN76) -> -110.78938 | AP76: =(-15482581-255436)/1000000 -> -15.738017
B77: Purchase of intangible assets | C77: 0 | D77: 0 | E77: 0 | F77: 0 | G77: 0 | H77: 0 | I77: 0 | J77: 0 | K77: 0 | L77: =SUM(AM77:AP77) -> 0 | N77: 0 | O77: 0 | P77: 0 | Q77: =E77-SUM(N77:P77) -> 0 | R77: 0 | S77: 0 | T77: 0 | U77: =F77-SUM(R77:T77) -> 0 | V77: 0 | W77: 0 | X77: 0 | Y77: =G77-SUM(V77:X77) -> 0 | Z77: 0 | AA77: 0 | AB77: 0 | AC77: =H77-SUM(Z77:AB77) -> 0 | AD77: 0 | AE77: 0 | AF77: =0-AE77-AD77 -> 0 | AG77: =I77-SUM(AD77:AF77) -> 0 | AH77: 0 | AI77: 0 | AJ77: =0-AH77-AI77 -> 0 | AK77: =J77-SUM(AH77:AJ77) -> 0 | AL77: 0 | AM77: 0 | AN77: =0-AL77-AM77 -> 0 | AO77: =K77-SUM(AL77:AN77) -> 0 | AP77: 0
B78: Disposals/ Acquistion, of subsidiaries, businesses | C78: 0 | D78: 0 | E78: 0 | F78: 0 | G78: 0 | H78: 0 | I78: 0 | J78: 0 | K78: 0 | L78: =SUM(AM78:AP78) -> 0 | N78: 0 | O78: 0 | P78: 0 | Q78: =E78-SUM(N78:P78) -> 0 | R78: 0 | S78: 0 | T78: 0 | U78: =F78-SUM(R78:T78) -> 0 | V78: 0 | W78: 0 | X78: 0 | Y78: =G78-SUM(V78:X78) -> 0 | Z78: 0 | AA78: 0 | AB78: 0 | AC78: =H78-SUM(Z78:AB78) -> 0 | AD78: 0 | AE78: 0 | AF78: =0-AE78-AD78 -> 0 | AG78: =I78-SUM(AD78:AF78) -> 0 | AH78: 0 | AI78: 0 | AJ78: =0-AH78-AI78 -> 0 | AK78: =J78-SUM(AH78:AJ78) -> 0 | AL78: 0 | AM78: 0 | AN78: =0-AL78-AM78 -> 0 | AO78: =K78-SUM(AL78:AN78) -> 0 | AP78: 0
B79: Free cash flow | C79: =SUM(C75:C78) -> -130.31368 | D79: =SUM(D75:D78) -> -84.458655 | E79: =SUM(E75:E78) -> 64.847348 | F79: =SUM(F75:F78) -> -11.82217 | G79: =SUM(G75:G78) -> 83.6738 | H79: =SUM(H75:H78) -> -250.10744 | I79: =SUM(I75:I78) -> -158.37309 | J79: =SUM(J75:J78) -> -142.68638 | ... L79: =SUM(L75:L78) -> -162.15058 | N79: =SUM(N75:N78) -> -3.514209 | O79: =SUM(O75:O78) -> 106.37611 | P79: =SUM(P75:P78) -> -17.051846 | Q79: =SUM(Q75:Q78) -> -20.962707 | R79: =SUM(R75:R78) -> -6.938275 | S79: =SUM(S75:S78) -> -6.811134 | T79: =SUM(T75:T78) -> 0.745164 | U79: =SUM(U75:U78) -> 1.182075 | ... AP79: =SUM(AP75:AP78) -> -15.977108
B80: Other Investing | C80: =-0.064813+0.055171 -> -0.009642 | D80: =-0.046571+0.434427 -> 0.387856 | E80: =-0.080568+0.070394 -> -0.010174 | F80: =0.120031+0.311959 -> 0.43199 | G80: =0.684936+0.076871 -> 0.761807 | H80: 0 | I80: 0 | J80: 0 | K80: -3.521881 | L80: =SUM(AM80:AP80) -> -3.521881 | N80: =-0.02258+0.014307 -> -0.008273 | O80: =0.035943-N80 -> 0.044216 | P80: =0.058017-O80-N80 -> 0.022074 | Q80: =E80-SUM(N80:P80) -> -0.068191 | R80: =0.240075+0.009967 -> 0.250042 | S80: =0.222496+0.214912-R80 -> 0.187366 | T80: =0.209159+0.296659-S80-R80 -> 0.06841 | U80: =F80-SUM(R80:T80) -> -0.073828 | V80: =0.021806+0.016572 -> 0.038378 | W80: =-0.00505+0.028787-V80 -> -0.014641 | X80: =0.684936+0.052954-W80-V80 -> 0.714153 | Y80: =G80-SUM(V80:X80) -> 0.023917 | Z80: 0.037774 | AA80: =0.170548-Z80 -> 0.132774 | AB80: =0-AA80-Z80 -> -0.170548 | AC80: =H80-SUM(Z80:AB80) -> 0 | AD80: 0 | AE80: 0 | AF80: =0-AE80-AD80 -> 0 | AG80: =I80-SUM(AD80:AF80) -> 0 | AH80: =14.367041+0.78 -> 15.147041 | AI80: =0-AH80 -> -15.147041 | AJ80: =28.444283-AH80-AI80 -> 28.444283 | AK80: =J80-SUM(AH80:AJ80) -> -28.444283 | AL80: 0 | AM80: =-0.5-AL80 -> -0.5 | AN80: =-3.442268-AL80-AM80 -> -2.942268 | AO80: =K80-SUM(AL80:AN80) -> -0.079613 | AP80: 0
B81: Equity Issuance / Repurchase of treasury shares | C81: 0 | D81: 0 | E81: 0 | F81: 0 | G81: =229.215419 -> 229.21542 | H81: =-15.603308 -> -15.603308 | I81: 594.375 | J81: -44.16579 | K81: -36.415845 | L81: =SUM(AM81:AP81) -> -0.508061 | N81: 0 | O81: 0 | P81: 0 | Q81: =E81-SUM(N81:P81) -> 0 | R81: 0 | S81: 0 | T81: 0 | U81: =F81-SUM(R81:T81) -> 0 | V81: 0 | W81: =229.215429-6.01998-V81 -> 223.19545 | X81: =229.215429-6.01998-W81-V81 -> 0 | Y81: =G81-SUM(V81:X81) -> 6.01997 | Z81: 0 | AA81: =-(15.489262)-Z81 -> -15.489262 | AB81: =-15.603308-AA81-Z81 -> -0.114046 | AC81: =H81-SUM(Z81:AB81) -> 0 | AD81: 0 | AE81: 0 | AF81: =444.018137-AE81-AD81 -> 444.01814 | AG81: =I81-SUM(AD81:AF81) -> 150.35686 | AH81: 0 | AI81: 0 | AJ81: =-14.336806-AH81-AI81 -> -14.336806 | AK81: =J81-SUM(AH81:AJ81) -> -29.828984 | AL81: -35.907784 | AM81: =-36.4-AL81 -> -0.492216 | AN81: =-36.415845-AL81-AM81 -> -0.015845 | AO81: =K81-SUM(AL81:AN81) -> 0 | AP81: 0
B82: Dividends | C82: -39.110027 | D82: -47.897981 | E82: -39.444748 | F82: -53.975583 | G82: =-55.367252 -> -55.367252 | H82: =-57.018815 -> -57.018815 | I82: -59.509926 | J82: -63.670176 | K82: =-68.325102 -> -68.325102 | L82: =SUM(AM82:AP82) -> -69.537973 | N82: 0 | O82: =-13.19698-N82 -> -13.19698 | P82: =-26.567376-O82-N82 -> -13.370396 | Q82: =E82-SUM(N82:P82) -> -12.877372 | R82: -13.37192 | S82: =-26.906475-R82 -> -13.534555 | T82: =-40.441028-S82-R82 -> -13.534553 | U82: =F82-SUM(R82:T82) -> -13.534555 | V82: -13.534555 | W82: =-27.669473-V82 -> -14.134918 | X82: =-41.42302-W82-V82 -> -13.753547 | Y82: =G82-SUM(V82:X82) -> -13.944232 | Z82: -13.944232 | AA82: =-(28.302427)-Z82 -> -14.358195 | AB82: =-42.660621-AA82-Z82 -> -14.358194 | AC82: =H82-SUM(Z82:AB82) -> -14.358194 | AD82: -14.358194 | AE82: =-29.356405-AD82 -> -14.998211 | AF82: =-44.433165-AE82-AD82 -> -15.07676 | AG82: =I82-SUM(AD82:AF82) -> -15.076761 | AH82: -15.155312 | AI82: =-31.326933-AH82 -> -16.171621 | AJ82: =-47.498555-AH82-AI82 -> -16.171622 | AK82: =J82-SUM(AH82:AJ82) -> -16.171621 | AL82: -16.171622 | AM82: =-33.6-AL82 -> -17.428378 | AN82: =-50.940609-AL82-AM82 -> -17.340609 | AO82: =K82-SUM(AL82:AN82) -> -17.384493 | AP82: -17.384493
B83: Net Change in debt | C83: 243 | D83: =116.6-0.123019 -> 116.47698 | E83: =225-210-0.545048 -> 14.454952 | F83: =125-0.794904-0.53492 -> 123.67018 | G83: =350-252.5-0.564677 -> 96.935323 | H83: =0-0-0.647971 -> -0.647971 | I83: =0-0-0.606279 -> -0.606279 | J83: =-69.613005-0.790811 -> -70.403816 | K83: =650-213.594745-0.834281 -> 435.57097 | L83: =SUM(AM83:AP83) -> 380.42044 | N83: =-0.317797-0.134967 -> -0.452764 | O83: =145+3.260647-150.503356-0.271154-N83 -> -2.061099 | P83: =225+0.331729-210.757793-0.407951-O83-N83 -> 16.679848 | Q83: =E83-SUM(N83:P83) -> 0.288967 | R83: =85-0.137223 -> 84.862777 | S83: =125-0.198232-0.270908-R83 -> 39.668083 | T83: =125-0.402824-S83-R83 -> 0.066316 | U83: =F83-SUM(R83:T83) -> -0.927 | V83: -0.126117 | W83: =350-0.252216-252.5-7.746222-V83 -> 89.627679 | X83: =350-252.5-7.746222-0.37833-W83-V83 -> -0.126114 | Y83: =G83-SUM(V83:X83) -> 7.559875 | Z83: =-0.142887-0.36845 -> -0.511337 | AA83: =-(0.285774)-(0.722674)-Z83 -> -0.497111 | AB83: =-2.072334-1.092916-0.413761-AA83-Z83 -> -2.570563 | AC83: =H83-SUM(Z83:AB83) -> 2.93104 | AD83: =-0.181707-1.183062 -> -1.364769 | AE83: =-2.342427-0.360022-AD83 -> -1.33768 | AF83: =-3.477928-0.53688-AE83-AD83 -> -1.312359 | AG83: =I83-SUM(AD83:AF83) -> 3.408529 | AH83: =-0.151748-1.143784 -> -1.295532 | AI83: =-2.300976-0.151748-AH83 -> -1.157192 | AJ83: =-68.450145-0.50229-AH83-AI83 -> -66.499711 | AK83: =J83-SUM(AH83:AJ83) -> -1.451381 | AL83: =(-45480698-192800)/1000000 -> -45.673498 | AM83: =100-47.4-0.4-AL83 -> 97.873498 | AN83: =650-48.636514-0.628206-AL83-AM83 -> 548.53528 | AO83: =K83-SUM(AL83:AN83) -> -165.16431 | AP83: =(-100634841-189194)/1000000 -> -100.82403
B84: Other financing activities | C84: =-1.519688+2.670811-26.953702-3.474806 -> -29.277385 | D84: =1.513911+0.064058-11.256567 -> -9.678598 | E84: =0.20208-0.08576-27.90295-3.098044 -> -30.884674 | F84: =0.668786-0.044661-14.795892 -> -14.171767 | G84: =-7.746222-6.01997 -> -13.766192 | H84: =-1.667278-0 -> -1.667278 | I84: =-16.789756-27.693021 -> -44.482777 | J84: -5.563162 | K84: =-5.350706 -> -5.350706 | L84: =SUM(AM84:AP84) -> -5.350706 | N84: =-0.030571+0.30244-2.03445 -> -1.762581 | O84: =-0.053306+0.283078-20.677113-N84 -> -18.68476 | P84: =-0.07384+0.0864-27.90295-O84-N84 -> -7.443049 | Q84: =E84-SUM(N84:P84) -> -2.994284 | R84: -14.242138 | S84: =-14.795892-R84 -> -0.553754 | T84: =0.033075+0.33522-14.795892-S84-R84 -> 0.368295 | U84: =F84-SUM(R84:T84) -> 0.25583 | V84: 0 | W84: =-V84 -> 0 | X84: 0 | Y84: =G84-SUM(V84:X84) -> -13.766192 | Z84: -6.042121 | AA84: =-Z84 -> 6.042121 | AB84: =0-AA84-Z84 -> 0 | AC84: =H84-SUM(Z84:AB84) -> -1.667278 | AD84: 0 | AE84: =-AD84 -> 0 | AF84: =-21.3403-AE84-AD84 -> -21.3403 | AG84: =I84-SUM(AD84:AF84) -> -23.142477 | AH84: 0 | AI84: =0-AH84 -> 0 | AJ84: =0-AH84-AI84 -> 0 | AK84: =J84-SUM(AH84:AJ84) -> -5.563162 | AL84: 0 | AM84: =0-AL84 -> 0 | AN84: =-4.291445-AL84-AM84 -> -4.291445 | AO84: =K84-SUM(AL84:AN84) -> -1.059261 | AP84: 0
B85: Cash flow after financing activities | C85: =SUM(C79:C84) -> 44.289262 | D85: =SUM(D79:D84) -> -25.170397 | E85: =SUM(E79:E84) -> 8.962704 | F85: =SUM(F79:F84) -> 44.132646 | G85: =SUM(G79:G84) -> 341.4529 | H85: =SUM(H79:H84) -> -325.04482 | I85: =SUM(I79:I84) -> 331.40293 | J85: =SUM(J79:J84) -> -326.48933 | ... L85: =SUM(L79:L84) -> 139.35124 | N85: =SUM(N79:N84) -> -5.737827 | O85: =SUM(O79:O84) -> 72.477487 | P85: =SUM(P79:P84) -> -21.163369 | Q85: =SUM(Q79:Q84) -> -36.613587 | R85: =SUM(R79:R84) -> 50.560486 | S85: =SUM(S79:S84) -> 18.956006 | T85: =SUM(T79:T84) -> -12.286368 | U85: =SUM(U79:U84) -> -13.097478 | ... AP85: =SUM(AP79:AP84) -> -134.18564
B86: Balancing figure | C86: =40.280958-C85-C87 -> 0.100792 | D86: =-26.518314-D85-D87 -> 0.349988 | E86: =10.580198-E85-E87 -> 1.050843 | F86: =45.478549-F85-F87 -> 0.005949 | G86: =332.27899-G85-G87 -> -5.027572 | H86: =-313.674047-H85-H87 -> 8.320338 | I86: =362.019051-I85-I87 -> 35.062443 | J86: =-317.045242-J85-J87 -> 3.642315 | K86: =152.780389-K85-K87 -> 15.211095 | L86: =SUM(AM86:AP86) -> 26.260598 | N86: =-4.959946-N85-N87 -> 0.41322 | O86: =66.570805-O85-N85-N86-N87-O87 -> -0.224793 | P86: =45.612238-P85-O85-N85-N86-O86-N87-O87-P87 -> -0.247046 | Q86: =E86-SUM(N86:P86) -> 1.109462 | R86: =47.209982-R85-R87 -> 0.185049 | S86: =68.919713-S85-R85-R86-R87-S87 -> 0.355817 | T86: =61.529996-T85-S85-R85-R86-S86-R87-S87-T87 -> -0.538344 | U86: =F86-SUM(R86:T86) -> 0.003427 | V86: =-21.422705-V85-V87 -> 0.070549 | W86: =272.894036-W85-V85-V86-V87-W87 -> -5.651057 | X86: =253.179557-X85-W85-V85-V86-W86-V87-W87-X87 -> 0.631682 | Y86: =G86-SUM(V86:X86) -> -0.078746 | Z86: =-110.316595-Z85-Z87 -> 0.026639 | AA86: =-(154.436106)-AA85-Z85-Z86-Z87-AA87 -> 8.827577 | AB86: =-182.125996-AB85-AA85-Z85-Z86-AA86-Z87-AA87-AB87 -> 0.604179 | AC86: =H86-SUM(Z86:AB86) -> -1.138057 | AD86: =-40.934346-AD85-AD87 -> 0.495818 | AE86: =-88.422409-AE85-AD85-AD86-AD87-AE87 -> 4.055834 | AF86: =269.035572-AF85-AE85-AD85-AD86-AE86-AD87-AE87-AF87 -> 18.011486 | AG86: =I86-SUM(AD86:AF86) -> 12.499305 | AH86: =-56.104787-AH85-AH87 -> 3.735017 | AI86: =-124.224661-AI85-AH85-AH86-AH87-AI87 -> 2.874585 | AJ86: =-219.968529-AJ85-AI85-AH85-AH86-AI86-AH87-AI87-AJ87 -> 2.379789 | AK86: =J86-SUM(AH86:AJ86) -> -5.347076 | AL86: =-135.435686-AL85-AL87 -> 0.207701 | AM86: =-118.9-AM85-AL85-AL86-AL87-AM87 -> 8.753927 | AN86: =402.927475-AN85-AM85-AL85-AL86-AM86-AL87-AM87-AN87 -> -0.780028 | AO86: =K86-SUM(AL86:AN86) -> 7.029495 | AP86: =-131.492081-AP85-AP87 -> 11.257204
B87: FX | C87: -4.109096 | D87: -1.697905 | E87: 0.566651 | F87: 1.339954 | G87: =-4.146343 -> -4.146343 | H87: =3.05043 -> 3.05043 | I87: -4.446323 | J87: 5.801769 | K87: 1.726818 | L87: =SUM(AM87:AP87) -> -8.887839 | N87: 0.364661 | O87: =-0.357282-N87 -> -0.721943 | P87: =0.094566-O87-N87 -> 0.451848 | Q87: =E87-SUM(N87:P87) -> 0.472085 | R87: -3.535553 | S87: =-1.137645-R87 -> 2.397908 | T87: =4.29735-S87-R87 -> 5.434995 | U87: =F87-SUM(R87:T87) -> -2.957396 | V87: -1.834742 | W87: =-1.411088-V87 -> 0.423654 | X87: =-1.747198-W87-V87 -> -0.33611 | Y87: =G87-SUM(V87:X87) -> -2.399145 | Z87: 3.008723 | AA87: =1.131507-Z87 -> -1.877216 | AB87: =1.692381-AA87-Z87 -> 0.560874 | AC87: =H87-SUM(Z87:AB87) -> 1.358049 | AD87: 4.490012 | AE87: =3.61323-AD87 -> -0.876782 | AF87: =-8.688827-AE87-AD87 -> -12.302057 | AG87: =I87-SUM(AD87:AF87) -> 4.242504 | AH87: -0.785758 | AI87: =-6.335317-AH87 -> -5.549559 | AJ87: =2.268617-AI87-AH87 -> 8.603934 | AK87: =J87-SUM(AH87:AJ87) -> 3.533152 | AL87: 2.051008 | AM87: =0.9-AL87 -> -1.151008 | AN87: =0.105828-AM87-AL87 -> -0.794172 | AO87: =K87-SUM(AL87:AN87) -> 1.62099 | AP87: -8.563649
B88: Net change in cash | C88: =SUM(C85:C87) -> 40.280958 | D88: =SUM(D85:D87) -> -26.518314 | E88: =SUM(E85:E87) -> 10.580198 | F88: =SUM(F85:F87) -> 45.478549 | G88: =SUM(G85:G87) -> 332.27899 | H88: =SUM(H85:H87) -> -313.67405 | I88: =SUM(I85:I87) -> 362.01905 | J88: =SUM(J85:J87) -> -317.04524 | ... L88: =SUM(L85:L87) -> 156.72399 | N88: =SUM(N85:N87) -> -4.959946 | O88: =SUM(O85:O87) -> 71.530751 | P88: =SUM(P85:P87) -> -20.958567 | Q88: =SUM(Q85:Q87) -> -35.03204 | R88: =SUM(R85:R87) -> 47.209982 | S88: =SUM(S85:S87) -> 21.709731 | T88: =SUM(T85:T87) -> -7.389717 | U88: =SUM(U85:U87) -> -16.051447 | ... AP88: =SUM(AP85:AP87) -> -131.49208
B89: Cash and cash equivalents | C89: =51.456063+C88 -> 91.737021 | D89: =C89+D88 -> 65.218707 | E89: =D89+E88 -> 75.798905 | F89: =E89+F88 -> 121.27745 | G89: =F89+G88 -> 453.55644 | H89: =G89+H88 -> 139.8824 | I89: =H89+I88 -> 501.90145 | J89: =I89+J88 -> 184.85621 | K89: =J89+K88 -> 337.6366 | L89: =AL89+L88-0.128890999999953 -> 206.14451 | N89: =65.218707+N88 -> 60.258761 | O89: =N89+O88 -> 131.78951 | P89: =O89+P88 -> 110.83095 | Q89: =P89+Q88 -> 75.798905 | R89: =Q89+R88 -> 123.00889 | S89: =R89+S88 -> 144.71862 | T89: =S89+T88 -> 137.3289 | U89: =T89+U88 -> 121.27745 | V89: =U89+V88 -> 99.854749 | ... AG89: =AF89+AG88 -> 501.86325 | AH89: =I89+AH88 -> 445.79666 | AI89: =AH89+AI88 -> 377.67679 | AJ89: =AI89+AJ88 -> 281.93292 | AK89: =AJ89+AK88 -> 184.9851 | AL89: =AK89+AL88 -> 49.549411 | AM89: =AL89+AM88-0.5 -> 65.585097 | AN89: =AM89+AN88-0.0739310000001296 -> 587.33864 | AO89: =AN89+AO88+0.445040000000063 -> 337.6366 | AP89: =AO89+AP88 -> 206.14451
B91: check | C91: =+C89-C127 -> 0.735312 | D91: =+D89-D127 -> 0.735312 | E91: =+E89-E127 -> 0.735312 | F91: =+F89-F127 -> 0.735312 | G91: =+G89-G127 -> 0.735312 | H91: =+H89-H127 -> 0.735312 | I91: =+I89-I127 -> 0.735312 | J91: =+J89-J127 -> 0.735312 | ... L91: =+L89-L127 -> 0 | N91: =+N89-N127 -> 0.735312 | O91: =+O89-O127 -> 0.735312 | P91: =+P89-P127 -> 0.735312 | Q91: =+Q89-Q127 -> 0.735312 | R91: =+R89-R127 -> 0.735312 | S91: =+S89-S127 -> 0.735312 | T91: =+T89-T127 -> 0.735312 | U91: =+U89-U127 -> 0.735312 | ... AP91: =+AP89-AP127 -> 0
C92: =82.164527-(C75+C86)+C74 -> 0 | D92: =82.272469-(D75+D86)+D74 -> -5 | E92: =103.229312-(E75+E86)+E74 -> 0 | F92: =99.516172-(F75+F86)+F74 -> 0 | G92: =107.168225-(G75+G86)+G74 -> -6.3948846e-14 | H92: =65.214868-(H75+H86)+H74 -> -6.3948846e-14 | I92: =144.796235-(I75+I86)+I74 -> 0 | J92: =129.708828-(J75+J86)+J74 -> 0 | K92: =207.2518-(K75+K86)+K74 -> 0 | N92: =26.560976-(N75+N86)+N74 -> 0 | O92: =51.714187-(O75+O86+N75+N86)+O74+N74 -> 4.6185278e-14 | P92: =84.632519-(P75+P86+O75+O86+N75+N86)+P74+O74+N74 -> 1.4210855e-14 | R92: =13.725786-(R75+R86)+R74 -> 0 | S92: =39.229298-(S75+S86+R75+R86)+S74+R74 -> -1.7763568e-14 | T92: =63.902834-(T75+T86+S75+S86+R75+R86)+T74+S74+R74 -> 0 | V92: =22.568126-(V75+V86)+V74 -> 0 | W92: =44.144757-(W75+W86+V75+V86)+W74+V74 -> 0 | X92: =75.566199 -(X75+X86+W75+W86+V75+V86)+X74+W74+V74 -> 0 | Z92: =-4.757245-(Z75+Z86)+Z74 -> 1.4210855e-14 | AA92: =5.461969-(AA75+AA86+Z75+Z86)+AA74+Z74 -> 2.3980817e-14 | AB92: =75.505463 -(AB75+AB86+AA75+AA86+Z75+Z86)+AB74+AA74+Z74 -> 1.3322676e-14 | AD92: =31.719453-(AD75+AD86)+AD74 -> 0 | AE92: =52.405117-(AE75+AE86+AD75+AD86)+AE74+AD74 -> 1.1546319e-14 | AF92: =128.947738 -(AF75+AF86+AE75+AE86+AD75+AD86)+AF74+AE74+AD74 -> 2.5757174e-14 | AI92: =37.722787-(AI75+AI86+AH75+AH86)+AI74+AH74 -> -1.3322676e-14 | AJ92: =79.246179 -(AJ75+AJ86+AI75+AI86+AH75+AH86)+AJ74+AI74+AH74 -> -3.4638958e-14 | AL92: =25.892612-(AL75+AL86)+AL74 -> -1.0658141e-14 | AM92: =89.73-(AM75+AM86+AL75+AL86)+AM74+AL74 -> -0.07 | AN92: =146.243509-(AN75+AN86+AM75+AM86+AL75+AL86)+AN74+AM74+AL74 -> -7.1054274e-14 | AP92: =27.037248-(AP75+AP86)+AP74 -> 0
B94: LTM | C94: =C3 -> 43100 | D94: =D3 -> 43465 | E94: =E3 -> 43830 | F94: =F3 -> 44196 | G94: =G3 -> 44561 | H94: =H3 -> 44926 | I94: =I3 -> 45291 | J94: =J3 -> 45657 | K94: =K3 -> 46022 | L94: =L2 -> LTM | N94: =N3 -> 43555 | O94: =O3 -> 43646 | P94: =P3 -> 43738 | Q94: =Q3 -> 43830 | R94: =R3 -> 43921 | S94: =S3 -> 44012 | T94: =T3 -> 44104 | U94: =U3 -> 44196 | ... AP94: =AP3 -> 46112
B95: =B7 -> Rental Income | C95: =C7 -> 109.42728 | D95: =D7 -> 132.66927 | E95: =E7 -> 144.2924 | F95: =F7 -> 149.53589 | G95: =G7 -> 160.69839 | H95: =H7 -> 178.02546 | I95: =I7 -> 213.4483 | ... L95: =L7 -> 292.90351 | N95: =SUM(F7:N7) -> 1566.0458 | O95: =SUM(L7:O7) -> 365.12195 | P95: =SUM(L7:P7) -> 400.94752 | Q95: =SUM(N7:Q7) -> 144.2924 | R95: =SUM(O7:R7) -> 145.69715 | S95: =SUM(P7:S7) -> 146.3079 | T95: =SUM(Q7:T7) -> 147.9402 | U95: =SUM(R7:U7) -> 149.53589 | V95: =SUM(S7:V7) -> 150.19316 | W95: =SUM(T7:W7) -> 153.4112 | X95: =SUM(U7:X7) -> 156.95547 | ... AP95: =SUM(AM7:AP7) -> 292.90351
B96: Operating profit | C96: =+C19 -> 90.165526 | D96: =+D19 -> 110.32502 | E96: =+E19 -> 117.09934 | F96: =+F19 -> 121.03879 | G96: =+G19 -> 128.65868 | H96: =+H19 -> 142.18764 | I96: =+I19 -> 164.50799 | J96: =+J19 -> 193.55645 | ... L96: =+L19 -> 226.06769 | N96: =SUM(F19:N19) -> 1225.5534 | O96: =SUM(L19:O19) -> 285.36936 | P96: =SUM(L19:P19) -> 314.51628 | Q96: =SUM(N19:Q19) -> 117.09934 | R96: =SUM(O19:R19) -> 117.05068 | S96: =SUM(P19:S19) -> 117.34205 | T96: =SUM(Q19:T19) -> 119.05267 | U96: =SUM(R19:U19) -> 121.03879 | V96: =SUM(S19:V19) -> 122.63429 | W96: =SUM(T19:W19) -> 124.98173 | X96: =SUM(U19:X19) -> 126.77129 | ... AP96: =SUM(AM19:AP19) -> 226.06769
B97: EBITDA | C97: =+C58 -> 91.952253 | D97: =+D58 -> 112.8282 | E97: =+E58 -> 121.38412 | F97: =+F58 -> 126.1962 | G97: =+G58 -> 135.8099 | H97: =+H58 -> 150.30156 | I97: =+I58 -> 174.0879 | J97: =+J58 -> 203.95496 | ... L97: =+L58 -> 238.34973 | N97: =SUM(F58:N58) -> 1290.6188 | O97: =SUM(L58:O58) -> 299.71588 | P97: =SUM(L58:P58) -> 329.93585 | Q97: =SUM(N58:Q58) -> 121.35412 | R97: =SUM(O58:R58) -> 121.71056 | S97: =SUM(P58:S58) -> 122.13445 | T97: =SUM(Q58:T58) -> 124.00582 | U97: =SUM(R58:U58) -> 126.1962 | V97: =SUM(S58:V58) -> 128.16766 | W97: =SUM(T58:W58) -> 131.17148 | X97: =SUM(U58:X58) -> 133.46358 | ... AP97: =SUM(AM58:AP58) -> 238.34973
B98: Adjusted EBITDA | C98: =+C63 -> 91.952253 | D98: =+D63 -> 112.8282 | E98: =+E63 -> 121.38412 | F98: =+F63 -> 126.1962 | G98: =+G63 -> 135.8099 | H98: =+H63 -> 150.30156 | I98: =+I63 -> 174.0879 | J98: =+J63 -> 204.4 | ... L98: =+L63 -> 237.93429 | N98: =SUM(F63:N63) -> 1290.9366 | O98: =SUM(L63:O63) -> 299.30043 | P98: =SUM(L63:P63) -> 329.5204 | Q98: =SUM(N63:Q63) -> 121.35412 | R98: =SUM(O63:R63) -> 121.71056 | S98: =SUM(P63:S63) -> 122.13445 | T98: =SUM(Q63:T63) -> 124.00582 | U98: =SUM(R63:U63) -> 126.1962 | V98: =SUM(S63:V63) -> 128.16766 | W98: =SUM(T63:W63) -> 131.17148 | X98: =SUM(U63:X63) -> 133.46358 | ... AP98: =SUM(AM63:AP63) -> 237.93429
B99: Cash interest paid | C99: =-C74 -> 15.907052 | D99: =-D74 -> 32.288118 | E99: =-E74 -> 38.606429 | F99: =-F74 -> 37.986844 | G99: =-G74 -> 44.474123 | H99: =-H74 -> 44.84437 | I99: =-I74 -> 45.034414 | J99: =-J74 -> 42.08771 | ... L99: =-L74 -> 55.233535 | N99: =-SUM(F74:N74) -> 324.70918 | O99: =-SUM(L74:O74) -> 75.022085 | P99: =-SUM(L74:P74) -> 88.152399 | Q99: =-SUM(N74:Q74) -> 38.606429 | R99: =-SUM(O74:R74) -> 37.899458 | S99: =-SUM(P74:S74) -> 37.591898 | T99: =-SUM(Q74:T74) -> 34.090076 | U99: =-SUM(R74:U74) -> 37.986844 | V99: =-SUM(S74:V74) -> 39.944964 | W99: =-SUM(T74:W74) -> 41.752083 | X99: =-SUM(U74:X74) -> 39.298748 | ... AP99: =-SUM(AM74:AP74) -> 55.233535
B100: Net Income | C100: =+C33 -> 126.03018 | D100: =+D33 -> 93.06033 | E100: =+E33 -> 134.61071 | F100: =+F33 -> 66.956082 | G100: =+G33 -> 173.94237 | H100: =+H33 -> 243.62475 | I100: =+I33 -> 316.63751 | J100: =+J33 -> 223.34635 | ... L100: =+L33 -> 327.96357 | N100: =SUM(F33:N33) -> 1616.3088 | O100: =SUM(L33:O33) -> 399.2331 | P100: =SUM(L33:P33) -> 411.64507 | Q100: =SUM(N33:Q33) -> 134.61071 | R100: =SUM(O33:R33) -> 88.25615 | S100: =SUM(P33:S33) -> 57.990479 | T100: =SUM(Q33:T33) -> 82.220407 | U100: =SUM(R33:U33) -> 66.956082 | V100: =SUM(S33:V33) -> 105.68691 | W100: =SUM(T33:W33) -> 195.02378 | X100: =SUM(U33:X33) -> 163.14763 | ... AP100: =SUM(AM33:AP33) -> 327.96357
B101: Capex | C101: =-C76 -> 196.47037 | D101: =-D76 -> 139.09302 | E101: =-E76 -> -1.275308 | F101: =-F76 -> 73.345549 | G101: =-G76 -> -15.952126 | H101: =-H76 -> 262.1576 | I101: =-I76 -> 223.07247 | J101: =-J76 -> 226.66519 | ... L101: =-L76 -> 289.05288 | N101: =-SUM(F76:N76) -> 1411.111 | O101: =-SUM(L76:O76) -> 217.92819 | P101: =-SUM(L76:P76) -> 255.0151 | Q101: =-SUM(N76:Q76) -> -1.275308 | R101: =-SUM(O76:R76) -> -9.75129 | S101: =-SUM(P76:S76) -> 103.51321 | T101: =-SUM(Q76:T76) -> 81.264519 | U101: =-SUM(R76:U76) -> 73.345549 | V101: =-SUM(S76:V76) -> 79.442212 | W101: =-SUM(T76:W76) -> 72.033377 | X101: =-SUM(U76:X76) -> 87.654299 | ... AP101: =-SUM(AM76:AP76) -> 289.05288
B102: Free cash flow | C102: =+C79 -> -130.31368 | D102: =+D79 -> -84.458655 | E102: =+E79 -> 64.847348 | F102: =+F79 -> -11.82217 | G102: =+G79 -> 83.6738 | H102: =+H79 -> -250.10744 | I102: =+I79 -> -158.37309 | J102: =+J79 -> -142.68638 | ... L102: =+L79 -> -162.15058 | N102: =SUM(F79:N79) -> -831.09504 | O102: =SUM(L79:O79) -> -59.28868 | P102: =SUM(L79:P79) -> -76.340526 | Q102: =SUM(N79:Q79) -> 64.847348 | R102: =SUM(O79:R79) -> 61.423282 | S102: =SUM(P79:S79) -> -51.763962 | T102: =SUM(Q79:T79) -> -33.966952 | U102: =SUM(R79:U79) -> -11.82217 | V102: =SUM(S79:V79) -> -10.920113 | W102: =SUM(T79:W79) -> -3.238404 | X102: =SUM(U79:X79) -> -10.828111 | ... AP102: =SUM(AM79:AP79) -> -162.15058
B104: BALANCE SHEET | C104: =C3 -> 43100 | D104: =D3 -> 43465 | E104: =E3 -> 43830 | F104: =F3 -> 44196 | G104: =G3 -> 44561 | H104: =H3 -> 44926 | I104: =I3 -> 45291 | J104: =J3 -> 45657 | K104: =K3 -> 46022 | L104: =L2 -> LTM | N104: =N3 -> 43555 | O104: =O3 -> 43646 | P104: =P3 -> 43738 | Q104: =Q3 -> 43830 | R104: =R3 -> 43921 | S104: =S3 -> 44012 | T104: =T3 -> 44104 | U104: =U3 -> 44196 | ... AP104: =AP3 -> 46112
B106: Tangible fixed assets | C106: =1701.006371+1.868778 -> 1702.8751 | D106: =1884.62143+2.490902 -> 1887.1123 | E106: =1989.131091+3.06365+1.104036 -> 1993.2988 | F106: =2103.214762+2.854654+0.657837 -> 2106.7273 | G106: =2263.170941+2.119589+1.344417 -> 2266.6349 | H106: =2738.465276+1.437981+1.417945 -> 2741.3212 | I106: =3212.164164+2.54199+0.834199 -> 3215.5404 | J106: =3696.768269+2.386285+0.533792 -> 3699.6883 | K106: =4129.443925+2.256393+1.419215 -> 4133.1195 | L106: =AP106 -> 4231.7966 | N106: =1918.279788+2.266449+1.448466 -> 1921.9947 | O106: =1878.337468+2.069412+1.333656 -> 1881.7405 | P106: =1928.134121+2.981397 +1.218846 -> 1932.3344 | Q106: =E106 -> 1993.2988 | R106: =2015.152264+2.686056+0.989226 -> 2018.8275 | S106: =2035.134222+2.497852+0.877677 -> 2038.5098 | T106: =2058.525638+2.61503+0.767757 -> 2061.9084 | U106: =F106 -> 2106.7273 | V106: =2121.222884+2.595827+0.553334 -> 2124.372 | W106: =2231.219664+2.495728+0.448829 -> 2234.1642 | X106: =2288.855026+2.21874+0.344324 -> 2291.4181 | Y106: =G106 -> 2266.6349 | Z106: =2384.901697+1.671391+1.220877 -> 2387.794 | AA106: =2440.634036+1.464482+1.097337 -> 2443.1959 | AB106: =2577.25495+1.612859+0.985857 -> 2579.8537 | AC106: =H106 -> 2741.3212 | AD106: =2792.27347+1.30164+1.271071 -> 2794.8462 | AE106: =2921.90093+1.182552+1.124197 -> 2924.2077 | AF106: =3112.803904+1.063465+0.977323 -> 3114.8447 | AG106: =I106 -> 3215.5404 | AH106: =3353.858113+2.365408+0.693583 -> 3356.9171 | AI106: =3521.758035+2.219307+0.693583 -> 3524.6709 | AJ106: =3589.613509+2.073209+0.41407 -> 3592.1008 | AK106: =J106 -> 3699.6883 | AL106: =(3749180886+2652907+368111)/1000000 -> 3752.2019 | AM106: =3859+2.4+0.4 -> 3861.8 | AN106: =3915.071845+2.167032+1.496991 -> 3918.7359 | AO106: =K106 -> 4133.1195 | AP106: =(4228244698+2209903+1342007)/1000000 -> 4231.7966
B107: Prepaid expenses | C107: 0.369675 | D107: 0.537428 | E107: 1.267893 | F107: 0.420057 | G107: 0.483581 | H107: 25.308351 | I107: 21.299392 | J107: 2.119545 | K107: 4.141257 | L107: =AP107 -> 10.240158 | N107: 2.349227 | O107: 2.082608 | P107: 2.500439 | Q107: =E107 -> 1.267893 | R107: 2.821146 | S107: 2.570056 | T107: 1.658944 | U107: =F107 -> 0.420057 | V107: 2.500369 | W107: 3.547832 | X107: 1.938955 | Y107: =G107 -> 0.483581 | Z107: 4.299466 | AA107: 30.741922 | AB107: 18.725102 | AC107: =H107 -> 25.308351 | AD107: 23.251781 | AE107: 31.347919 | AF107: 21.433597 | AG107: =I107 -> 21.299392 | AH107: 35.766128 | AI107: 26.494236 | AJ107: 6.954413 | AK107: =J107 -> 2.119545 | AL107: 9.154228 | AM107: 7.7 | AN107: 8.140683 | AO107: =K107 -> 4.141257 | AP107: 10.240158
B108: Accounts payable and client advances | C108: 4.082166 | D108: 2.788387 | E108: 2.539117 | F108: 1.82585 | G108: =3.011415 -> 3.011415 | H108: 16.628788 | I108: 13.188966 | J108: 14.1943 | K108: 30.798915 | L108: =AP108 -> 29.747785 | N108: 2.33155 | O108: 4.908271 | P108: 6.147668 | Q108: =E108 -> 2.539117 | R108: 9.344231 | S108: 4.16021 | T108: 3.729932 | U108: =F108 -> 1.82585 | V108: 2.81727 | W108: 3.467373 | X108: 3.70486 | Y108: =G108 -> 3.011415 | Z108: 6.158094 | AA108: 6.973941 | AB108: 36.735409 | AC108: =H108 -> 16.628788 | AD108: 18.078142 | AE108: 12.062229 | AF108: 16.985635 | AG108: =I108 -> 13.188966 | AH108: 20.233994 | AI108: 16.975007 | AJ108: 15.925594 | AK108: =J108 -> 14.1943 | AL108: 19.12187 | AM108: 9.8 | AN108: 6.701751 | AO108: =K108 -> 30.798915 | AP108: 29.747785
B109: Accrued expenses | C109: 3.821201 | D109: 3.663962 | E109: 4.452725 | F109: 4.30964 | G109: =15.246156 -> 15.246156 | H109: =5.154626 -> 5.154626 | I109: 7.078988 | J109: 6.637354 | K109: 7.280266 | L109: =AP109 -> 4.731061 | N109: 2.003559 | O109: 2.880086 | P109: 3.569373 | Q109: =E109 -> 4.452725 | R109: 2.32987 | S109: 2.872746 | T109: 3.438246 | U109: =F109 -> 4.30964 | V109: 2.869629 | W109: 3.470366 | X109: 3.93237 | Y109: =G109 -> 15.246156 | Z109: 3.053612 | AA109: 3.848797 | AB109: 4.585162 | AC109: =H109 -> 5.154626 | AD109: 3.540891 | AE109: 4.647958 | AF109: 5.729315 | AG109: =I109 -> 7.078988 | AH109: 4.649514 | AI109: 5.315669 | AJ109: 5.949231 | AK109: =J109 -> 6.637354 | AL109: 4.793508 | AM109: 5.7 | AN109: 6.459877 | AO109: =K109 -> 7.280266 | AP109: 4.731061
B110: Net working capital | C110: =C107-C108-C109 -> -7.533692 | D110: =D107-D108-D109 -> -5.914921 | E110: =E107-E108-E109 -> -5.723949 | F110: =F107-F108-F109 -> -5.715433 | G110: =G107-G108-G109 -> -17.77399 | H110: =H107-H108-H109 -> 3.524937 | I110: =I107-I108-I109 -> 1.031438 | J110: =J107-J108-J109 -> -18.712109 | ... L110: =L107-L108-L109 -> -24.238688 | N110: =N107-N108-N109 -> -1.985882 | O110: =O107-O108-O109 -> -5.705749 | P110: =P107-P108-P109 -> -7.216602 | Q110: =Q107-Q108-Q109 -> -5.723949 | R110: =R107-R108-R109 -> -8.852955 | S110: =S107-S108-S109 -> -4.4629 | T110: =T107-T108-T109 -> -5.509234 | U110: =U107-U108-U109 -> -5.715433 | ... AP110: =AP107-AP108-AP109 -> -24.238688
B111: % of revenues | C111: =+C110/C95 -> -0.068846561 | D111: =+D110/D95 -> -0.044583958 | E111: =+E110/E95 -> -0.039669095 | F111: =+F110/F95 -> -0.038221146 | G111: =+G110/G95 -> -0.11060466 | H111: =+H110/H95 -> 0.019800185 | I111: =+I110/I95 -> 0.0048322616 | J111: =+J110/J95 -> -0.074268988 | ... L111: =+L110/L95 -> -0.082753149 | N111: =+N110/N95 -> -0.0012680868 | O111: =+O110/O95 -> -0.015626968 | P111: =+P110/P95 -> -0.017998869 | Q111: =+Q110/Q95 -> -0.039669095 | R111: =+R110/R95 -> -0.060762719 | S111: =+S110/S95 -> -0.030503478 | T111: =+T110/T95 -> -0.037239602 | U111: =+U110/U95 -> -0.038221146 | ... AP111: =+AP110/AP95 -> -0.082753149
...

Sheet EBITDA
B2: Corporación Inmobiliaria Vesta | C2: Annual | D2: Annual | F2: Quarters | G2: Quarters | H2: Quarters | I2: Quarters | J2: Quarters | K2: Quarters | L2: Quarters | M2: Quarters | N2: Quarters
B3: (USD million) | C3: 45657 | D3: 46022 | F3: 45382 | G3: 45473 | H3: 45565 | I3: 45657 | J3: 45747 | K3: 45838 | L3: 45930 | M3: 46022 | N3: 46112
C4: Act | D4: Act | F4: Act | G4: Act | H4: Act | I4: Act | J4: Act | K4: Act | L4: Act | M4: Act | N4: Act
F5: 1Q | G5: 2Q | H5: 3Q | I5: 4Q | J5: 1Q | K5: 2Q | L5: 3Q | M5: 4Q | N5: 1Q
B8: Total revenues | C8: 252.3 | D8: 283.2 | F8: 60.589657 | G8: 63 | H8: 63.7 | I8: 65.2 | J8: 67.063658 | K8: 67.3 | L8: 72.4 | M8: 76.4 | N8: 76.749154
B10: Property operating costs:
B11: Related to properties that generate rental income | C11: =SUM(C12:C13) -> -21.2 | D11: =SUM(D12:D13) -> -24.1 | F11: =SUM(F12:F13) -> -3.786225 | G11: =SUM(G12:G13) -> -5.3 | H11: =SUM(H12:H13) -> -5.7 | I11: =SUM(I12:I13) -> -6.3 | J11: =SUM(J12:J13) -> -4.445843 | K11: =SUM(K12:K13) -> -5.6 | L11: =SUM(L12:L13) -> -7.2 | M11: =SUM(M12:M13) -> -6.8 | N11: =SUM(N12:N13) -> -6.170651
B12: Costs related to properties | C12: -13.2 | D12: -14.2 | F12: -2.365872 | G12: -3.3 | H12: -3.5 | I12: -4 | J12: -2.779184 | K12: -3.6 | L12: -3.9 | M12: -4 | N12: -3.633335
B13: Costs related to energy | C13: -8 | D13: -9.9 | F13: -1.420353 | G13: -2 | H13: -2.2 | I13: -2.3 | J13: -1.666659 | K13: -2 | L13: -3.3 | M13: -2.8 | N13: -2.537316
B14: Related to properties that did not generate rental income | C14: -3.3 | D14: -4.2 | F14: -0.71703 | G14: -0.85 | H14: -0.81 | I14: -1.11 | J14: -0.758699 | K14: -0.92 | L14: -1.01 | M14: -1.48 | N14: -1.257801
B16: Adjusted NOI | C16: 231.5 | D16: =(SUM(D8,D11,D14)) -> 254.9 | F16: =(SUM(F8,F11,F14)) -> 56.086402 | G16: =(SUM(G8,G11,G14)) -> 56.85 | H16: 57.6 | I16: 59.3 | J16: =(SUM(J8,J11,J14)) -> 61.859116 | K16: =(SUM(K8,K11,K14)) -> 60.78 | L16: 66.1 | M16: 69.4 | N16: 70.406117
B18: General and administrative expenses | C18: -32.8 | D18: -33.8 | F18: -8.229156 | G18: -9 | H18: -7 | I18: -8.5 | J18: -8.287949 | K18: -8.287949 | L18: -7.8 | M18: -9.3 | N18: -9.303835
B19: Stock-based compensation expenses | C19: 9 | D19: 9.6 | F19: 2.146913 | G19: 2.7 | H19: 2.1 | I19: 2 | J19: 2.196456 | K19: 2.4 | L19: 2.5 | M19: 2.5 | N19: 2.248176
B20: Depreciation | C20: -1.4 | D20: -1.7 | F20: -0.327639 | G20: -0.1 | H20: -0.4 | I20: -0.5 | J20: -0.636653 | K20: -0.1 | L20: -0.5 | M20: -0.5 | N20: -0.471296
B21: EBITDA | C21: 204.4 | D21: 231.1 | F21: 50.578089 | G21: =SUM(G18:G20)+G16-0.1 -> 50.35 | H21: 51.9 | I21: 51.7 | J21: 55.258372 | K21: =SUM(K18:K20)+K16+0.2 -> 54.992051 | L21: 59.7 | M21: 61.1 | N21: 62.092657

Sheet KPIs
B2: Corporación Inmobiliaria Vesta | C2: Annual | D2: Annual | E2: Annual | F2: Annual | G2: Annual | H2: Annual | I2: Annual | J2: Annual | K2: Annual | L2: LTM | N2: Quarters | O2: Quarters | P2: Quarters | Q2: Quarters | R2: Quarters | S2: Quarters | T2: Quarters | U2: Quarters | V2: Quarters | W2: Quarters | X2: Quarters | Y2: Quarters | Z2: Quarters | AA2: Quarters | AB2: Quarters | AC2: Quarters | AD2: Quarters | AE2: Quarters | AF2: Quarters | AG2: Quarters | AH2: Quarters | AI2: Quarters | AJ2: Quarters | AK2: Quarters | AL2: Quarters | AM2: Quarters | AN2: Quarters | AO2: Quarters | AP2: Quarters
B3: (USD million) | C3: 43100 | D3: 43465 | E3: 43830 | F3: 44196 | G3: 44561 | H3: 44926 | I3: 45291 | J3: 45657 | K3: 46022 | L3: =AP3 -> 46112 | N3: 43555 | O3: 43646 | P3: 43738 | Q3: 43830 | R3: 43921 | S3: 44012 | T3: 44104 | U3: 44196 | V3: 44286 | W3: 44377 | X3: 44469 | Y3: 44561 | Z3: 44651 | AA3: 44742 | AB3: 44834 | AC3: 44926 | AD3: 45016 | AE3: 45107 | AF3: 45199 | AG3: 45291 | AH3: 45382 | AI3: 45473 | AJ3: 45565 | AK3: 45657 | AL3: 45747 | AM3: 45838 | AN3: 45930 | AO3: 46022 | AP3: 46112
C4: Act | D4: Act | E4: Act | F4: Act | G4: Act | H4: Act | I4: Act | J4: Act | K4: Act | L4: Act | N4: Act | O4: Act | P4: Act | Q4: Act | R4: Act | S4: Act | T4: Act | U4: Act | V4: Act | W4: Act | X4: Act | Y4: Act | Z4: Act | AA4: Act | AB4: Act | AC4: Act | AD4: Act | AE4: Act | AF4: Act | AG4: Act | AH4: Act | AI4: Act | AJ4: Act | AK4: Act | AL4: Act | AM4: Act | AN4: Act | AO4: Act | AP4: Act
C5: FY | D5: FY | E5: FY | F5: FY | G5: FY | H5: FY | I5: FY | J5: FY | K5: FY | L5: FY | N5: 1Q | O5: 2Q | P5: 3Q | Q5: 4Q | R5: 1Q | S5: 2Q | T5: 3Q | U5: 4Q | V5: 1Q | W5: 2Q | X5: 3Q | Y5: 4Q | Z5: 1Q | AA5: 2Q | AB5: 3Q | AC5: 4Q | AD5: 1Q | AE5: 2Q | AF5: 3Q | AG5: 4Q | AH5: 1Q | AI5: 2Q | AJ5: 3Q | AK5: 4Q | AL5: 1Q | AM5: 2Q | AN5: 3Q | AO5: 4Q | AP5: 1Q
B7: North Region
B8: Number of operating buildings | C8: 63 | D8: 66 | E8: 69 | F8: 70 | G8: 72 | H8: 78 | I8: 85 | J8: 88 | K8: 91 | L8: =AP8 -> 89 | N8: 66 | O8: 68 | P8: 68 | Q8: =E8 -> 69 | R8: 69 | S8: 70 | T8: 70 | U8: =F8 -> 70 | V8: 71 | W8: 71 | X8: 71 | Y8: =G8 -> 72 | Z8: 73 | AA8: 74 | AB8: 74 | AC8: =H8 -> 78 | AD8: 78 | AE8: 79 | AF8: 86 | AG8: =I8 -> 85 | AH8: 85 | AI8: 86 | AJ8: 88 | AK8: =J8 -> 88 | AL8: 89 | AM8: 91 | AN8: 92 | AO8: =K8 -> 91 | AP8: 89
B9: Number of buildings under development | C9: 0 | D9: 2 | E9: 2 | F9: 1 | G9: 5 | H9: 8 | I9: 3 | J9: 4 | K9: 0 | L9: =AP9 -> 1 | N9: 5 | O9: 2 | P9: 4 | Q9: =E9 -> 2 | R9: 2 | S9: 0 | T9: 1 | U9: =F9 -> 1 | V9: 3 | W9: 4 | X9: 4 | Y9: =G9 -> 5 | Z9: 7 | AA9: 6 | AB9: 8 | AC9: =H9 -> 8 | AD9: 8 | AE9: 7 | AF9: 3 | AG9: =I9 -> 3 | AH9: 6 | AI9: 6 | AJ9: 4 | AK9: =J9 -> 4 | AL9: 3 | AM9: 1 | AN9: 0 | AO9: =K9 -> 0 | AP9: 1
B10: Total Buildings | C10: =SUM(C8:C9) -> 63 | D10: =SUM(D8:D9) -> 68 | E10: =SUM(E8:E9) -> 71 | F10: =SUM(F8:F9) -> 71 | G10: =SUM(G8:G9) -> 77 | H10: =SUM(H8:H9) -> 86 | I10: =SUM(I8:I9) -> 88 | J10: =SUM(J8:J9) -> 92 | ... L10: =SUM(L8:L9) -> 90 | N10: =SUM(N8:N9) -> 71 | O10: =SUM(O8:O9) -> 70 | P10: =SUM(P8:P9) -> 72 | Q10: =SUM(Q8:Q9) -> 71 | R10: =SUM(R8:R9) -> 71 | S10: =SUM(S8:S9) -> 70 | T10: =SUM(T8:T9) -> 71 | U10: =SUM(U8:U9) -> 71 | ... AP10: =SUM(AP8:AP9) -> 90
B12: Operating portfolio (sf) | C12: 6875440 | D12: 7996798 | E12: 8852290 | F12: 9078485 | G12: 9303139 | H12: 10352575 | I12: 12070580 | J12: 12786657 | K12: 14283183 | L12: =AP12 -> 14283187 | N12: 8212054 | O12: 8631873 | P12: 8631873 | Q12: =E12 -> 8852290 | R12: 8852385 | S12: 9074369 | T12: 9074369 | U12: =F12 -> 9078485 | V12: 9361517 | W12: 9360915 | X12: 9303139 | Y12: =G12 -> 9303139 | Z12: 9509958 | AA12: 9628555 | AB12: 9628555 | AC12: =H12 -> 10352575 | AD12: 10352575 | AE12: 10657963 | AF12: 12384129 | AG12: =I12 -> 12070580 | AH12: 12070580 | AI12: 12281380 | AJ12: 12786659 | AK12: =J12 -> 12786657 | AL12: 13263621 | AM12: 13628161 | AN12: 14282993 | AO12: =K12 -> 14283183 | AP12: 14283187
B13: Development portfolio (sf) | C13: 1121413 | D13: 419673 | E13: 221984 | F13: 603239 | G13: 957623 | H13: 2026077 | I13: 716079 | J13: 1619288 | K13: 0 | L13: =AP13 -> 375625 | N13: 639874 | O13: 220201 | P13: 442185 | Q13: =E13 -> 221984 | R13: 221984 | S13: 0 | T13: 283032 | U13: =F13 -> 603239 | V13: 625891 | W13: 735112 | X13: 892299 | Y13: =G13 -> 957623 | Z13: 1410492 | AA13: 1291895 | AB13: 1821284 | AC13: =H13 -> 2026077 | AD13: 2026077 | AE13: 1728660 | AF13: 791879 | AG13: =I13 -> 716079 | AH13: 1666458 | AI13: 2105824 | AJ13: 1600545 | AK13: =J13 -> 1619288 | AL13: 1142324 | AM13: 730762 | AN13: 0 | AO13: =K13 -> 0 | AP13: 375625
B14: Total GLA (sf) | C14: =SUM(C12:C13) -> 7996853 | D14: =SUM(D12:D13) -> 8416471 | E14: =SUM(E12:E13) -> 9074274 | F14: =SUM(F12:F13) -> 9681724 | G14: =SUM(G12:G13) -> 10260762 | H14: =SUM(H12:H13) -> 12378652 | I14: =SUM(I12:I13) -> 12786659 | J14: =SUM(J12:J13) -> 14405945 | ... L14: =SUM(L12:L13) -> 14658812 | N14: =SUM(N12:N13) -> 8851928 | O14: =SUM(O12:O13) -> 8852074 | P14: =SUM(P12:P13) -> 9074058 | Q14: =SUM(Q12:Q13) -> 9074274 | R14: =SUM(R12:R13) -> 9074369 | S14: =SUM(S12:S13) -> 9074369 | T14: =SUM(T12:T13) -> 9357401 | U14: =SUM(U12:U13) -> 9681724 | ... AP14: =SUM(AP12:AP13) -> 14658812
B16: Development portfolio Total Expected Investment ($ 000's) | C16: 62861 | D16: 20778 | E16: 11050 | F16: 30778 | G16: 51234 | H16: 127072 | I16: 57715 | J16: 134868 | K16: 0 | L16: =AP16 -> 32379 | N16: 32773 | O16: 11995 | P16: 23044 | Q16: =E16 -> 11050 | R16: 11049 | S16: 0 | T16: 12934 | U16: =F16 -> 30778 | V16: 35760 | W16: 41441 | X16: 48065 | Y16: =G16 -> 51234 | Z16: 79303 | AA16: 73622 | AB16: 108199 | AC16: =H16 -> 127072 | AD16: 127072 | AE16: 112376 | AF16: 60105 | AG16: =I16 -> 57715 | AH16: 130701 | AI16: 175779 | AJ16: 134714 | AK16: =J16 -> 134868 | AL16: 90135 | AM16: 57180 | AN16: 0 | AO16: =K16 -> 0 | AP16: 32379
B17: Land (acres) | C17: 72 | D17: 53.63 | E17: 118.63 | F17: 107.17 | G17: 108.24 | H17: 153.64 | I17: 100.83 | J17: 88.32 | K17: 539.48 | L17: =AP17 -> 523.61 | N17: 53.63 | O17: 43.33 | P17: 31.18 | Q17: =E17 -> 118.63 | R17: 118.63 | S17: 118.63 | T17: 107.17 | U17: =F17 -> 107.17 | V17: 178.73 | W17: 152.67 | X17: 141.99 | Y17: =G17 -> 108.24 | Z17: 257.1 | AA17: 216.59 | AB17: 194.3 | AC17: =H17 -> 153.64 | AD17: 141.24 | AE17: 141.24 | AF17: 100.83 | AG17: =I17 -> 100.83 | AH17: 56.24 | AI17: 0 | AJ17: 88.32 | AK17: =J17 -> 88.32 | AL17: 185.6 | AM17: 209.57 | AN17: 209.57 | AO17: =K17 -> 539.48 | AP17: 523.61
B18: Land Book Value ($ 000's) | C18: 23909 | D18: 17208 | E18: 30107 | F18: 26275 | G18: 20050 | H18: 44258 | I18: 33.22 | J18: 10272 | K18: 163880 | L18: =AP18 -> 160243 | N18: 17208 | O18: 13966 | P18: 11503 | Q18: =E18 -> 30107 | R18: 30107 | S18: 30107 | T18: 26275 | U18: =F18 -> 26275 | V18: 42328 | W18: 30552 | X18: 26984 | Y18: =G18 -> 20050 | Z18: 70452 | AA18: 58645 | AB18: 51610 | AC18: =H18 -> 44258 | AD18: 45415 | AE18: 45420 | AF18: 32660 | AG18: =I18 -> 33.22 | AH18: 18203 | AI18: 0 | AJ18: 10298 | AK18: =J18 -> 10272 | AL18: 36754 | AM18: 48358 | AN18: 48358 | AO18: =K18 -> 163880 | AP18: 160243
B20: Bajio Region
B21: Number of operating buildings | C21: 76 | D21: 84 | E21: 83 | F21: 84 | G21: 83 | H21: 88 | I21: 92 | J21: 98 | K21: 102 | L21: =AP21 -> 101 | N21: 87 | O21: 82 | P21: 82 | Q21: =E21 -> 83 | R21: 83 | S21: 83 | T21: 83 | U21: =F21 -> 84 | V21: 84 | W21: 84 | X21: 84 | Y21: =G21 -> 83 | Z21: 83 | AA21: 85 | AB21: 86 | AC21: =H21 -> 88 | AD21: 88 | AE21: 89 | AF21: 91 | AG21: =I21 -> 92 | AH21: 92 | AI21: 93 | AJ21: 96 | AK21: =J21 -> 98 | AL21: 99 | AM21: 99 | AN21: 102 | AO21: =K21 -> 102 | AP21: 101
B22: Number of buildings under development | C22: 0 | D22: 3 | E22: 1 | F22: 2 | G22: 3 | H22: 6 | I22: 6 | J22: 5 | K22: 3 | L22: =AP22 -> 3 | N22: 2 | O22: 2 | P22: 1 | Q22: =E22 -> 1 | R22: 3 | S22: 4 | T22: 5 | U22: =F22 -> 2 | V22: 2 | W22: 2 | X22: 3 | Y22: =G22 -> 3 | Z22: 5 | AA22: 3 | AB22: 5 | AC22: =H22 -> 6 | AD22: 6 | AE22: 4 | AF22: 6 | AG22: =I22 -> 6 | AH22: 5 | AI22: 7 | AJ22: 3 | AK22: =J22 -> 5 | AL22: 3 | AM22: 3 | AN22: 1 | AO22: =K22 -> 3 | AP22: 3
B23: Total Buildings | C23: =SUM(C21:C22) -> 76 | D23: =SUM(D21:D22) -> 87 | E23: =SUM(E21:E22) -> 84 | F23: =SUM(F21:F22) -> 86 | G23: =SUM(G21:G22) -> 86 | H23: =SUM(H21:H22) -> 94 | I23: =SUM(I21:I22) -> 98 | J23: =SUM(J21:J22) -> 103 | ... L23: =SUM(L21:L22) -> 104 | N23: =SUM(N21:N22) -> 89 | O23: =SUM(O21:O22) -> 84 | P23: =SUM(P21:P22) -> 83 | Q23: =SUM(Q21:Q22) -> 84 | R23: =SUM(R21:R22) -> 86 | S23: =SUM(S21:S22) -> 87 | T23: =SUM(T21:T22) -> 88 | U23: =SUM(U21:U22) -> 86 | ... AP23: =SUM(AP21:AP22) -> 104
B25: Operating portfolio (sf) | C25: 12722893 | D25: 14748046 | E25: 14445698 | F25: 15182807 | G25: 14771316 | H25: 16183191 | I25: 18027608 | J25: 19193885 | K25: 20093889 | L25: =AP25 -> 20093885 | N25: 15081603 | O25: 14136412 | P25: 14210107 | Q25: =E25 -> 14445698 | R25: 14447822 | S25: 14447822 | T25: 14447822 | U25: =F25 -> 15182807 | V25: 15227219 | W25: 15231132 | X25: 15231131 | Y25: =G25 -> 14771316 | Z25: 14849602 | AA25: 15451284 | AB25: 15630160 | AC25: =H25 -> 16183191 | AD25: 16183191 | AE25: 16769047 | AF25: 17341893 | AG25: =I25 -> 18027608 | AH25: 17963025 | AI25: 18255502 | AJ25: 19033534 | AK25: =J25 -> 19193885 | AL25: 19533041 | AM25: 19533041 | AN25: 20093889 | AO25: =K25 -> 20093889 | AP25: 20093885
B26: Development portfolio (sf) | C26: 1209136 | D26: 622080 | E26: 405509 | F26: 449921 | G26: 678842 | H26: 1839413 | I26: 1155265 | J26: 900007 | K26: 771844 | L26: =AP26 -> 777226 | N26: 309285 | O26: 309285 | P26: 235591 | Q26: =E26 -> 405509 | R26: 1065584 | S26: 1157593 | T26: 1202005 | U26: =F26 -> 449921 | V26: 631475 | W26: 631475 | X26: 904808 | Y26: =G26 -> 678842 | Z26: 1287347 | AA26: 686791 | AB26: 1333873 | AC26: =H26 -> 1839413 | AD26: 1839413 | AE26: 1520283 | AF26: 1489514 | AG26: =I26 -> 1155265 | AH26: 1236423 | AI26: 1248766 | AJ26: 470727 | AK26: =J26 -> 900007 | AL26: 560851 | AM26: 560851 | AN26: 376016 | AO26: =K26 -> 771844 | AP26: 777226
B27: Total GLA (sf) | C27: =SUM(C25:C26) -> 13932029 | D27: =SUM(D25:D26) -> 15370126 | E27: =SUM(E25:E26) -> 14851207 | F27: =SUM(F25:F26) -> 15632728 | G27: =SUM(G25:G26) -> 15450158 | H27: =SUM(H25:H26) -> 18022604 | I27: =SUM(I25:I26) -> 19182873 | J27: =SUM(J25:J26) -> 20093892 | ... L27: =SUM(L25:L26) -> 20871111 | N27: =SUM(N25:N26) -> 15390888 | O27: =SUM(O25:O26) -> 14445697 | P27: =SUM(P25:P26) -> 14445698 | Q27: =SUM(Q25:Q26) -> 14851207 | R27: =SUM(R25:R26) -> 15513406 | S27: =SUM(S25:S26) -> 15605415 | T27: =SUM(T25:T26) -> 15649827 | U27: =SUM(U25:U26) -> 15632728 | ... AP27: =SUM(AP25:AP26) -> 20871111
B29: Development portfolio Total Expected Investment ($ 000's) | C29: 48006 | D29: 25458 | E29: 19397 | F29: 21540 | G29: 37038 | H29: 114612 | I29: 70.141 | J29: 54435 | K29: 59042 | L29: =AP29 -> 62613 | N29: 12193 | O29: 12193 | P29: 9319 | Q29: =E29 -> 19397 | R29: 58207 | S29: 61233 | T29: 63375 | U29: =F29 -> 21540 | V29: 33082 | W29: 33082 | X29: 50723 | Y29: =G29 -> 37038 | Z29: 71352 | AA29: 37861 | AB29: 80693 | AC29: =H29 -> 114612 | AD29: 114612 | AE29: 93237 | AF29: 91855 | AG29: =I29 -> 70.141 | AH29: 74588 | AI29: 76130 | AJ29: 28981 | AK29: =J29 -> 54435 | AL29: 33776 | AM29: 33776 | AN29: 29188 | AO29: =K29 -> 59042 | AP29: 62613
B30: Land (acres) | C30: 684 | D30: 778.17 | E30: 861.46 | F30: 791.38 | G30: 785.29 | H30: 693.65 | I30: 605.97 | J30: 569.56 | K30: 672.09 | L30: =AP30 -> 672.09 | N30: 786.7 | O30: 786.7 | P30: 861.46 | Q30: =E30 -> 861.46 | R30: 833.41 | S30: 833.41 | T30: 833.41 | U30: =F30 -> 791.38 | V30: 769.76 | W30: 705 | X30: 793.88 | Y30: =G30 -> 785.29 | Z30: 751.94 | AA30: 751.94 | AB30: 731.54 | AC30: =H30 -> 693.65 | AD30: 669.42 | AE30: 660.06 | AF30: 632.19 | AG30: =I30 -> 605.97 | AH30: 594.31 | AI30: 579.45 | AJ30: 579.45 | AK30: =J30 -> 569.56 | AL30: 569.56 | AM30: 697.96 | AN30: 682.11 | AO30: =K30 -> 672.09 | AP30: 672.09
B31: Land Book Value | C31: 62216 | D31: 73807 | E31: 106160 | F31: 95999 | G31: 113305 | H31: 96895 | I31: 104370 | J31: 104050 | K31: 133160 | L31: =AP31 -> 133160 | N31: 75233 | O31: 75386 | P31: 96264 | Q31: =E31 -> 106160 | R31: 98327 | S31: 98327 | T31: 98327 | U31: =F31 -> 95999 | V31: 94801 | W31: 100075 | X31: 115704 | Y31: =G31 -> 113305 | Z31: 107331 | AA31: 107330 | AB31: 104550 | AC31: =H31 -> 96895 | AD31: 112740 | AE31: 110410 | AF31: 106650 | AG31: =I31 -> 104370 | AH31: 101423 | AI31: 99798 | AJ31: 99798 | AK31: =J31 -> 104050 | AL31: 104050 | AM31: 137266 | AN31: 131530 | AO31: =K31 -> 133160 | AP31: 133160
B33: Central Region
B34: Number of operating buildings | C34: 34 | D34: 34 | E34: 32 | F34: 34 | G34: 34 | H34: 36 | I34: 36 | J34: 39 | K34: 41 | L34: =AP34 -> 41 | N34: 34 | O34: 32 | P34: 32 | Q34: =E34 -> 32 | R34: 32 | S34: 33 | T34: 33 | U34: =F34 -> 34 | V34: 34 | W34: 34 | X34: 34 | Y34: =G34 -> 34 | Z34: 34 | AA34: 34 | AB34: 34 | AC34: =H34 -> 36 | AD34: 36 | AE34: 36 | AF34: 37 | AG34: =I34 -> 36 | AH34: 37 | AI34: 37 | AJ34: 37 | AK34: =J34 -> 39 | AL34: 40 | AM34: 41 | AN34: 41 | AO34: =K34 -> 41 | AP34: 41
B35: Number of buildings under development | C35: 0 | D35: 0 | E35: 1 | F35: 1 | G35: 0 | H35: 0 | I35: 3 | J35: 2 | K35: 0 | L35: =AP35 -> 2 | N35: 0 | O35: 0 | P35: 1 | Q35: =E35 -> 1 | R35: 2 | S35: 2 | T35: 2 | U35: =F35 -> 1 | V35: 0 | W35: 0 | X35: 0 | Y35: =G35 -> 0 | Z35: 0 | AA35: 0 | AB35: 0 | AC35: =H35 -> 0 | AD35: 0 | AE35: 0 | AF35: 3 | AG35: =I35 -> 3 | AH35: 3 | AI35: 4 | AJ35: 4 | AK35: =J35 -> 2 | AL35: 1 | AM35: 0 | AN35: 0 | AO35: =K35 -> 0 | AP35: 2
B36: Total Buildings | C36: =SUM(C34:C35) -> 34 | D36: =SUM(D34:D35) -> 34 | E36: =SUM(E34:E35) -> 33 | F36: =SUM(F34:F35) -> 35 | G36: =SUM(G34:G35) -> 34 | H36: =SUM(H34:H35) -> 36 | I36: =SUM(I34:I35) -> 39 | J36: =SUM(J34:J35) -> 41 | ... L36: =SUM(L34:L35) -> 43 | N36: =SUM(N34:N35) -> 34 | O36: =SUM(O34:O35) -> 32 | P36: =SUM(P34:P35) -> 33 | Q36: =SUM(Q34:Q35) -> 33 | R36: =SUM(R34:R35) -> 34 | S36: =SUM(S34:S35) -> 35 | T36: =SUM(T34:T35) -> 35 | U36: =SUM(U34:U35) -> 35 | ... AP36: =SUM(AP34:AP35) -> 43
B38: Operating portfolio (sf) | C38: 7122837 | D38: 7122733 | E38: 6494060 | F38: 6959744 | G38: 7007291 | H38: 7178604 | I38: 7179938 | J38: 8319422 | K38: 8576950 | L38: =AP38 -> 8576950 | N38: 7122733 | O38: 6494060 | P38: 6494060 | Q38: =E38 -> 6494060 | R38: 6494214 | S38: 6629396 | T38: 6629396 | U38: =F38 -> 6959744 | V38: 7003125 | W38: 7003125 | X38: 7007291 | Y38: =G38 -> 7007291 | Z38: 7007291 | AA38: 7008211 | AB38: 7008211 | AC38: =H38 -> 7178604 | AD38: 7178604 | AE38: 7179701 | AF38: 7179938 | AG38: =I38 -> 7179938 | AH38: 7256310 | AI38: 7256310 | AJ38: 7256310 | AK38: =J38 -> 8319422 | AL38: 8405555 | AM38: 8756841 | AN38: 8576840 | AO38: =K38 -> 8576950 | AP38: 8576950
B39: Development portfolio (sf) | C39: 0 | D39: 0 | E39: 135182 | F39: 43381 | G39: 0 | H39: 0 | I39: 1230308 | J39: 257419 | K39: 0 | L39: =AP39 -> 400458 | N39: 0 | O39: 0 | P39: 135182 | Q39: =E39 -> 135182 | R39: 474675 | S39: 382874 | T39: 382874 | U39: =F39 -> 43381 | V39: 0 | W39: 0 | X39: 0 | Y39: =G39 -> 0 | Z39: 0 | AA39: 0 | AB39: 0 | AC39: =H39 -> 0 | AD39: 0 | AE39: 0 | AF39: 1230308 | AG39: =I39 -> 1230308 | AH39: 1230308 | AI39: 1320532 | AJ39: 1320532 | AK39: =J39 -> 257419 | AL39: 171286 | AM39: 0 | AN39: 0 | AO39: =K39 -> 0 | AP39: 400458
B40: Total GLA (sf) | C40: =SUM(C38:C39) -> 7122837 | D40: =SUM(D38:D39) -> 7122733 | E40: =SUM(E38:E39) -> 6629242 | F40: =SUM(F38:F39) -> 7003125 | G40: =SUM(G38:G39) -> 7007291 | H40: =SUM(H38:H39) -> 7178604 | I40: =SUM(I38:I39) -> 8410246 | J40: =SUM(J38:J39) -> 8576841 | ... L40: =SUM(L38:L39) -> 8977408 | N40: =SUM(N38:N39) -> 7122733 | O40: =SUM(O38:O39) -> 6494060 | P40: =SUM(P38:P39) -> 6629242 | Q40: =SUM(Q38:Q39) -> 6629242 | R40: =SUM(R38:R39) -> 6968889 | S40: =SUM(S38:S39) -> 7012270 | T40: =SUM(T38:T39) -> 7012270 | U40: =SUM(U38:U39) -> 7003125 | ... AP40: =SUM(AP38:AP39) -> 8977408
B42: Development portfolio Total Expected Investment ($ 000's) | C42: 0 | D42: 0 | E42: 6358 | F42: 2550 | G42: 0 | H42: 0 | I42: 82.909 | J42: 24755 | K42: 0 | L42: =AP42 -> 51736 | N42: 0 | O42: 0 | P42: 6358 | Q42: =E42 -> 6358 | R42: 24314 | S42: 20506 | T42: 20506 | U42: =F42 -> 2550 | V42: 0 | W42: 0 | X42: 0 | Y42: =G42 -> 0 | Z42: 0 | AA42: 0 | AB42: 0 | AC42: =H42 -> 0 | AD42: 0 | AE42: 0 | AF42: 82909 | AG42: =I42 -> 82.909 | AH42: 82909 | AI42: 87071 | AJ42: 165249 | AK42: =J42 -> 24755 | AL42: 18650 | AM42: 0 | AN42: 0 | AO42: =K42 -> 0 | AP42: 51736
B43: Land (acres) | C43: 28 | D43: 28.08 | E43: 28.08 | F43: 7.63 | G43: 2.12 | H43: 62.47 | I43: 2.12 | J43: 0 | K43: 18.73 | L43: =AP43 -> 0 | N43: 28.08 | O43: 28.08 | P43: 28.08 | Q43: =E43 -> 28.08 | R43: 7.63 | S43: 7.63 | T43: 7.63 | U43: =F43 -> 7.63 | V43: 7.63 | W43: 2.12 | X43: 2.12 | Y43: =G43 -> 2.12 | Z43: 2.12 | AA43: 2.12 | AB43: 10.78 | AC43: =H43 -> 62.47 | AD43: 62.47 | AE43: 62.47 | AF43: 2.12 | AG43: =I43 -> 2.12 | AH43: 2.12 | AI43: 0 | AJ43: 0 | AK43: =J43 -> 0 | AL43: 18.73 | AM43: 18.73 | AN43: 18.73 | AO43: =K43 -> 18.73 | AP43: 0
B44: Land Book Value | C44: 1508 | D44: 1508 | E44: 6712 | F44: 1824 | G44: 508 | H44: 50129 | I44: 790 | J44: 0 | K44: 18610 | L44: =AP44 -> 0 | N44: 1508 | O44: 1508 | P44: 1508 | Q44: =E44 -> 6712 | R44: 1824 | S44: 1824 | T44: 1824 | U44: =F44 -> 1824 | V44: 1824 | W44: 508 | X44: 508 | Y44: =G44 -> 508 | Z44: 508 | AA44: 508 | AB44: 17919 | AC44: =H44 -> 50129 | AD44: 50750 | AE44: 50750 | AF44: 790 | AG44: =I44 -> 790 | AH44: 790 | AI44: 0 | AJ44: 0 | AK44: =J44 -> 0 | AL44: 18887 | AM44: 18887 | AN44: 18887 | AO44: =K44 -> 18610 | AP44: 0
B46: Total
B47: Number of operating buildings | C47: =SUM(C8,C21,C34) -> 173 | D47: =SUM(D8,D21,D34) -> 184 | E47: =SUM(E8,E21,E34) -> 184 | F47: =SUM(F8,F21,F34) -> 188 | G47: =SUM(G8,G21,G34) -> 189 | H47: =SUM(H8,H21,H34) -> 202 | I47: =SUM(I8,I21,I34) -> 213 | J47: =SUM(J8,J21,J34) -> 225 | ... L47: =SUM(L8,L21,L34) -> 231 | N47: =SUM(N8,N21,N34) -> 187 | O47: =SUM(O8,O21,O34) -> 182 | P47: =SUM(P8,P21,P34) -> 182 | Q47: =SUM(Q8,Q21,Q34) -> 184 | R47: =SUM(R8,R21,R34) -> 184 | S47: =SUM(S8,S21,S34) -> 186 | T47: =SUM(T8,T21,T34) -> 186 | U47: =SUM(U8,U21,U34) -> 188 | ... AP47: =SUM(AP8,AP21,AP34) -> 231
B48: Number of buildings under development | C48: =SUM(C9,C22,C35) -> 0 | D48: =SUM(D9,D22,D35) -> 5 | E48: =SUM(E9,E22,E35) -> 4 | F48: =SUM(F9,F22,F35) -> 4 | G48: =SUM(G9,G22,G35) -> 8 | H48: =SUM(H9,H22,H35) -> 14 | I48: =SUM(I9,I22,I35) -> 12 | J48: =SUM(J9,J22,J35) -> 11 | ... L48: =SUM(L9,L22,L35) -> 6 | N48: =SUM(N9,N22,N35) -> 7 | O48: =SUM(O9,O22,O35) -> 4 | P48: =SUM(P9,P22,P35) -> 6 | Q48: =SUM(Q9,Q22,Q35) -> 4 | R48: =SUM(R9,R22,R35) -> 7 | S48: =SUM(S9,S22,S35) -> 6 | T48: =SUM(T9,T22,T35) -> 8 | U48: =SUM(U9,U22,U35) -> 4 | ... AP48: =SUM(AP9,AP22,AP35) -> 6
B49: Total Buildings | C49: =SUM(C47:C48) -> 173 | D49: =SUM(D47:D48) -> 189 | E49: =SUM(E47:E48) -> 188 | F49: =SUM(F47:F48) -> 192 | G49: =SUM(G47:G48) -> 197 | H49: =SUM(H47:H48) -> 216 | I49: =SUM(I47:I48) -> 225 | J49: =SUM(J47:J48) -> 236 | ... L49: =SUM(L47:L48) -> 237 | N49: =SUM(N47:N48) -> 194 | O49: =SUM(O47:O48) -> 186 | P49: =SUM(P47:P48) -> 188 | Q49: =SUM(Q47:Q48) -> 188 | R49: =SUM(R47:R48) -> 191 | S49: =SUM(S47:S48) -> 192 | T49: =SUM(T47:T48) -> 194 | U49: =SUM(U47:U48) -> 192 | ... AP49: =SUM(AP47:AP48) -> 237
B51: Operating portfolio (sf) | C51: =SUM(C12,C25,C38) -> 26721170 | D51: =SUM(D12,D25,D38) -> 29867577 | E51: =SUM(E12,E25,E38) -> 29792048 | F51: =SUM(F12,F25,F38) -> 31221036 | G51: =SUM(G12,G25,G38) -> 31081746 | H51: =SUM(H12,H25,H38) -> 33714370 | I51: =SUM(I12,I25,I38) -> 37278126 | J51: =SUM(J12,J25,J38) -> 40299964 | K51: =SUM(K12,K25,K38) -> 42954022 | L51: =AN51 -> 42953722 | N51: =SUM(N12,N25,N38) -> 30416390 | O51: =SUM(O12,O25,O38) -> 29262345 | P51: =SUM(P12,P25,P38) -> 29336040 | Q51: =SUM(Q12,Q25,Q38) -> 29792048 | R51: =SUM(R12,R25,R38) -> 29794421 | S51: =SUM(S12,S25,S38) -> 30151587 | T51: =SUM(T12,T25,T38) -> 30151587 | U51: =SUM(U12,U25,U38) -> 31221036 | ... AP51: =SUM(AP12,AP25,AP38) -> 42954022
B52: Development portfolio (sf) | C52: =SUM(C13,C26,C39) -> 2330549 | D52: =SUM(D13,D26,D39) -> 1041753 | E52: =SUM(E13,E26,E39) -> 762675 | F52: =SUM(F13,F26,F39) -> 1096541 | G52: =SUM(G13,G26,G39) -> 1636465 | H52: =SUM(H13,H26,H39) -> 3865490 | I52: =SUM(I13,I26,I39) -> 3101652 | J52: =SUM(J13,J26,J39) -> 2776714 | K52: =SUM(K13,K26,K39) -> 771844 | L52: =AN52 -> 376016 | N52: =SUM(N13,N26,N39) -> 949159 | O52: =SUM(O13,O26,O39) -> 529486 | P52: =SUM(P13,P26,P39) -> 812958 | Q52: =SUM(Q13,Q26,Q39) -> 762675 | R52: =SUM(R13,R26,R39) -> 1762243 | S52: =SUM(S13,S26,S39) -> 1540467 | T52: =SUM(T13,T26,T39) -> 1867911 | U52: =SUM(U13,U26,U39) -> 1096541 | ... AP52: =SUM(AP13,AP26,AP39) -> 1553309
B53: Total GLA (sf) | C53: =SUM(C51:C52) -> 29051719 | D53: =SUM(D51:D52) -> 30909330 | E53: =SUM(E51:E52) -> 30554723 | F53: =SUM(F51:F52) -> 32317577 | G53: =SUM(G51:G52) -> 32718211 | H53: =SUM(H51:H52) -> 37579860 | I53: =SUM(I51:I52) -> 40379778 | J53: =SUM(J51:J52) -> 43076678 | ... L53: =SUM(L51:L52) -> 43329738 | N53: =SUM(N51:N52) -> 31365549 | O53: =SUM(O51:O52) -> 29791831 | P53: =SUM(P51:P52) -> 30148998 | Q53: =SUM(Q51:Q52) -> 30554723 | R53: =SUM(R51:R52) -> 31556664 | S53: =SUM(S51:S52) -> 31692054 | T53: =SUM(T51:T52) -> 32019498 | U53: =SUM(U51:U52) -> 32317577 | ... AP53: =SUM(AP51:AP52) -> 44507331
B55: Development portfolio Total Expected Investment ($ 000's) | C55: =SUM(C16,C29,C42) -> 110867 | D55: =SUM(D16,D29,D42) -> 46236 | E55: =SUM(E16,E29,E42) -> 36805 | F55: =SUM(F16,F29,F42) -> 54868 | G55: =SUM(G16,G29,G42) -> 88272 | H55: =SUM(H16,H29,H42) -> 241684 | I55: =SUM(I16,I29,I42) -> 57868.05 | J55: =SUM(J16,J29,J42) -> 214058 | K55: =SUM(K16,K29,K42) -> 59042 | L55: =AN55 -> 29188 | N55: =SUM(N16,N29,N42) -> 44966 | O55: =SUM(O16,O29,O42) -> 24188 | P55: =SUM(P16,P29,P42) -> 38721 | Q55: =SUM(Q16,Q29,Q42) -> 36805 | R55: =SUM(R16,R29,R42) -> 93570 | S55: =SUM(S16,S29,S42) -> 81739 | T55: =SUM(T16,T29,T42) -> 96815 | U55: =SUM(U16,U29,U42) -> 54868 | ... AP55: =SUM(AP16,AP29,AP42) -> 146728
B56: Land (acres) | C56: =SUM(C17,C30,C43) -> 784 | D56: =SUM(D17,D30,D43) -> 859.88 | E56: =SUM(E17,E30,E43) -> 1008.17 | F56: =SUM(F17,F30,F43) -> 906.18 | G56: =SUM(G17,G30,G43) -> 895.65 | H56: =SUM(H17,H30,H43) -> 909.76 | I56: =SUM(I17,I30,I43) -> 708.92 | J56: =SUM(J17,J30,J43) -> 657.88 | K56: =SUM(K17,K30,K43) -> 1230.3 | L56: =AN56 -> 910.41 | N56: =SUM(N17,N30,N43) -> 868.41 | O56: =SUM(O17,O30,O43) -> 858.11 | P56: =SUM(P17,P30,P43) -> 920.72 | Q56: =SUM(Q17,Q30,Q43) -> 1008.17 | R56: =SUM(R17,R30,R43) -> 959.67 | S56: =SUM(S17,S30,S43) -> 959.67 | T56: =SUM(T17,T30,T43) -> 948.21 | U56: =SUM(U17,U30,U43) -> 906.18 | ... AP56: =SUM(AP17,AP30,AP43) -> 1195.7
B57: Land Book Value | C57: =SUM(C18,C31,C44) -> 87633 | D57: =SUM(D18,D31,D44) -> 92523 | E57: =SUM(E18,E31,E44) -> 142979 | F57: =SUM(F18,F31,F44) -> 124098 | G57: =SUM(G18,G31,G44) -> 133863 | H57: =SUM(H18,H31,H44) -> 191282 | I57: =SUM(I18,I31,I44) -> 105193.22 | J57: =SUM(J18,J31,J44) -> 114322 | ... L57: =SUM(L18,L31,L44) -> 293403 | N57: =SUM(N18,N31,N44) -> 93949 | O57: =SUM(O18,O31,O44) -> 90860 | P57: =SUM(P18,P31,P44) -> 109275 | Q57: =SUM(Q18,Q31,Q44) -> 142979 | R57: =SUM(R18,R31,R44) -> 130258 | S57: =SUM(S18,S31,S44) -> 130258 | T57: =SUM(T18,T31,T44) -> 126426 | U57: =SUM(U18,U31,U44) -> 124098 | ... AP57: =SUM(AP18,AP31,AP44) -> 293403
B59: Portfolio (sf)
B60: Same store portfolio | C60: 21283813 | D60: 25512153 | E60: 26320325 | F60: 28769289 | G60: 29759799 | H60: 31063694 | I60: 32542808 | J60: 36150182 | K60: 39137968 | L60: =AP60 -> 39832024 | N60: 25850750 | O60: 25458170 | P60: 25458170 | Q60: =E60 -> 26320325 | R60: 26527562 | S60: 27529558 | T60: 28234554 | U60: =F60 -> 28769289 | V60: 29545962 | W60: 29618454 | X60: 29622619 | Y60: =G60 -> 29759799 | Z60: 29803180 | AA60: 29939714 | AB60: 29948606 | AC60: =H60 -> 31063694 | AD60: 31141980 | AE60: 31910575 | AF60: 32121834 | AG60: =I60 -> 32542808 | AH60: 33004534 | AI60: 33447743 | AJ60: 34746633 | AK60: =J60 -> 36150182 | AL60: 36587884 | AM60: 36763804 | AN60: 37992894 | AO60: =K60 -> 39137968 | AP60: 39832024
B61: Portfolio Occupancy | C61: 0.955 | D61: 0.982 | E61: 0.979 | F61: 0.927 | G61: 0.94 | H61: 0.972 | I61: 0.97 | J61: 0.976 | K61: 0.95 | L61: =AP61 -> 0.95 | N61: 0.98 | O61: 0.981 | P61: 0.981 | Q61: =E61 -> 0.979 | R61: 0.972 | S61: 0.967 | T61: 0.945 | U61: =F61 -> 0.927 | V61: 0.911 | W61: 0.93 | X61: 0.935 | Y61: =G61 -> 0.94 | Z61: 0.941 | AA61: 0.957 | AB61: 0.964 | AC61: =H61 -> 0.972 | AD61: 0.965 | AE61: 0.967 | AF61: 0.976 | AG61: =I61 -> 0.97 | AH61: 0.974 | AI61: 0.978 | AJ61: 0.983 | AK61: =J61 -> 0.976 | AL61: 0.974 | AM61: 0.97 | AN61: 0.948 | AO61: =K61 -> 0.95 | AP61: 0.95
B63: Stabilized Portfolio | C63: 25536265 | D63: 27914997 | E63: 28779464 | F63: 31085421 | G63: 31032114 | H63: 32850684 | I63: 35923860 | J63: 39265296 | K63: 41164714 | L63: =AP63 -> 41250846 | N63: 28165300 | O63: 27527064 | P63: 28232060 | Q63: =E63 -> 28779464 | R63: 29558829 | S63: 29637211 | T63: 29637211 | U63: =F63 -> 31085421 | V63: 31173214 | W63: 31304077 | X63: 31308242 | Y63: =G63 -> 31032114 | Z63: 31110400 | AA63: 31881231 | AB63: 32096942 | AC63: =H63 -> 32850684 | AD63: 33073658 | AE63: 33715097 | AF63: 34805657 | AG63: =I63 -> 35923860 | AH63: 36082218 | AI63: 36808437 | AJ63: 38118104 | AK63: =J63 -> 39265296 | AL63: 39959353 | AM63: 40205680 | AN63: 40819778 | AO63: =K63 -> 41164714 | AP63: 41250846
B64: Portfolio Occupancy | C64: 0.953 | D64: 0.972 | E64: 0.947 | F64: 0.911 | G64: 0.943 | H64: 0.973 | I64: 0.967 | J64: 0.955 | K64: 0.936 | L64: =AP64 -> 0.934 | N64: 0.968 | O64: 0.954 | P64: 0.956 | Q64: =E64 -> 0.947 | R64: 0.936 | S64: 0.939 | T64: 0.919 | U64: =F64 -> 0.911 | V64: 0.906 | W64: 0.927 | X64: 0.931 | Y64: =G64 -> 0.943 | Z64: 0.943 | AA64: 0.959 | AB64: 0.966 | AC64: =H64 -> 0.973 | AD64: 0.967 | AE64: 0.969 | AF64: 0.973 | AG64: =I64 -> 0.967 | AH64: 0.971 | AI64: 0.975 | AJ64: 0.958 | AK64: =J64 -> 0.955 | AL64: 0.953 | AM64: 0.955 | AN64: 0.943 | AO64: =K64 -> 0.936 | AP64: 0.934
B66: Total Portfolio | C66: 26721171 | D66: 29867577 | E66: 29792047 | F66: 31221035 | G66: 31081746 | H66: 33714370 | I66: 37354498 | J66: 40299964 | K66: 42954022 | L66: =AP66 -> 42954021 | N66: 30416390 | O66: 29262345 | P66: 29336039 | Q66: =E66 -> 29792047 | R66: 29794420 | S66: 30151586 | T66: 30151586 | U66: =F66 -> 31221035 | V66: 31591860 | W66: 31595172 | X66: 31648969 | Y66: =G66 -> 31081746 | Z66: 31366851 | AA66: 32088050 | AB66: 32266926 | AC66: =H66 -> 33714370 | AD66: 33714370 | AE66: 34606711 | AF66: 36905960 | AG66: =I66 -> 37354498 | AH66: 37289914 | AI66: 37793191 | AJ66: 39076503 | AK66: =J66 -> 40299964 | AL66: 41202217 | AM66: 41738043 | AN66: 42953722 | AO66: =K66 -> 42954022 | AP66: 42954021
B67: Portfolio Occupancy | C67: 0.923 | D67: 0.918 | E67: 0.917 | F67: 0.907 | G67: 0.941 | H67: 0.951 | I67: 0.934 | J67: 0.934 | K67: 0.897 | L67: =AO67 -> 0.897 | N67: 0.908 | O67: 0.912 | P67: 0.926 | Q67: =E67 -> 0.917 | R67: 0.929 | S67: 0.923 | T67: 0.905 | U67: =F67 -> 0.907 | V67: 0.9 | W67: 0.925 | X67: 0.928 | Y67: =G67 -> 0.941 | Z67: 0.938 | AA67: 0.958 | AB67: 0.961 | AC67: =H67 -> 0.951 | AD67: 0.951 | AE67: 0.947 | AF67: 0.925 | AG67: =I67 -> 0.934 | AH67: 0.94 | AI67: 0.95 | AJ67: 0.939 | AK67: =J67 -> 0.934 | AL67: 0.928 | AM67: 0.923 | AN67: 0.897 | AO67: =K67 -> 0.897 | AP67: 0.897
B68: Total Portfolio average rent per sf | C68: 0.383 | D68: 0.415 | E68: 0.416 | F68: 0.439 | G68: 0.454 | H68: 0.465 | I68: 0.48 | J68: 0.0512 | K68: 0.56 | L68: =AO68 -> 0.56 | N68: 0.419 | O68: 0.433 | P68: 0.426 | Q68: =E68 -> 0.416 | R68: 0.43 | S68: 0.423 | T68: 0.442 | U68: =F68 -> 0.439 | V68: 0.433 | W68: 0.449 | X68: 0.449 | Y68: =G68 -> 0.454 | Z68: 0.451 | AA68: 0.448 | AB68: 0.46 | AC68: =H68 -> 0.465 | AD68: 0.488 | AE68: 0.495 | AF68: 0.504 | AG68: =I68 -> 0.48 | AH68: 0.531 | AI68: 0.268 | AJ68: 0.531 | AK68: =J68 -> 0.0512 | AL68: 0.528 | AM68: 0.538 | AN68: 0.572 | AO68: =K68 -> 0.56 | AP68: 0.591
B70: Same Stores Portfolio
B71: Square Footage
B72: North Region | C72: 4324743 | D72: 6659361 | E72: 7660230 | F72: 8548146 | G72: 8386153 | H72: 9255796 | I72: 9520026 | J72: 11081992 | K72: 11081992 | L72: =AP72 -> 12909934 | N72: 6701361 | O72: 7228950 | P72: 7228950 | Q72: =E72 -> 7660230 | R72: 7660230 | S72: 8016067 | T72: 8524190 | U72: =F72 -> 8548146 | V72: 8856503 | W72: 8925082 | X72: 8925082 | Y72: =G72 -> 8386153 | Z72: 8386153 | AA72: 8386153 | AB72: 8386153 | AC72: =H72 -> 9255796 | AD72: 9255796 | AE72: 9421603 | AF72: 9633004 | AG72: =I72 -> 9520026 | AH72: 10046335 | AI72: 10297622 | AJ72: 11032620 | AK72: =J72 -> 11081992 | AL72: 11304934 | AM72: 11480854 | AN72: 12432776 | AO72: =K72 -> 11081992 | AP72: 12909934
B73: Bajio Region | C73: 10621342 | D73: 12121907 | E73: 12166035 | F73: 13735537 | G73: 14545350 | H73: 14816411 | I73: 15842844 | J73: 17811881 | K73: 18598536 | L73: =AP73 -> 18815625 | N73: 12236862 | O73: 11945367 | P73: 11945368 | Q73: =E73 -> 12166035 | R73: 12373118 | S73: 13019277 | T73: 13216151 | U73: =F73 -> 13735537 | V73: 14203853 | W73: 14207767 | X73: 14207766 | Y73: =G73 -> 14545350 | Z73: 14545350 | AA73: 14545350 | AB73: 14554242 | AC73: =H73 -> 14816411 | AD73: 14894697 | AE73: 15496388 | AF73: 15496009 | AG73: =I73 -> 15842844 | AH73: 15778261 | AI73: 15970183 | AJ73: 16534075 | AK73: =J73 -> 17811881 | AL73: 18026641 | AM73: 18026641 | AN73: 18303810 | AO73: =K73 -> 18598536 | AP73: 18815625
B74: Central Region | C74: 6337728 | D74: 6730884 | E74: 6494060 | F74: 6485605 | G74: 6828296 | H74: 6991487 | I74: 7179938 | J74: 7256309 | K74: 8106466 | L74: =AP74 -> 8106466 | N74: 6912526 | O74: 6283853 | P74: 6283853 | Q74: =E74 -> 6494060 | R74: 6494214 | S74: 6494214 | T74: 6494213 | U74: =F74 -> 6485605 | V74: 6485605 | W74: 6485605 | X74: 6489771 | Y74: =G74 -> 6828296 | Z74: 6871677 | AA74: 7008211 | AB74: 7008211 | AC74: =H74 -> 6991487 | AD74: 6991487 | AE74: 6992584 | AF74: 6992821 | AG74: =I74 -> 7179938 | AH74: 7179938 | AI74: 7179938 | AJ74: 7179938 | AK74: =J74 -> 7256309 | AL74: 7256309 | AM74: 7256309 | AN74: 7256308 | AO74: =K74 -> 8106466 | AP74: 8106466
B76: Occupancy
B77: North Region | C77: 0.934 | D77: 0.991 | E77: 0.999 | F77: 0.954 | G77: 0.993 | H77: 1 | I77: 0.981 | J77: 0.981 | K77: 0.914 | L77: =AO77 -> 0.914 | N77: 0.992 | O77: 0.992 | P77: 0.999 | Q77: =E77 -> 0.999 | R77: 0.986 | S77: 0.991 | T77: 0.955 | U77: =F77 -> 0.954 | V77: 0.972 | W77: 0.99 | X77: 0.989 | Y77: =G77 -> 0.993 | Z77: 0.993 | AA77: 1 | AB77: 1 | AC77: =H77 -> 1 | AD77: 1 | AE77: 1 | AF77: 1 | AG77: =I77 -> 0.981 | AH77: 0.99 | AI77: 0.993 | AJ77: 0.994 | AK77: =J77 -> 0.981 | AL77: 0.972 | AM77: 0.971 | AN77: 0.913 | AO77: =K77 -> 0.914 | AP77: 0.93
B78: Bajio Region | C78: 0.96 | D78: 0.993 | E78: 0.99 | F78: 0.922 | G78: 0.906 | H78: 0.945 | I78: 0.963 | J78: 0.964 | K78: 0.952 | L78: =AO78 -> 0.952 | N78: 0.988 | O78: 0.988 | P78: 0.989 | Q78: =E78 -> 0.99 | R78: 0.978 | S78: 0.97 | T78: 0.961 | U78: =F78 -> 0.922 | V78: 0.894 | W78: 0.918 | X78: 0.918 | Y78: =G78 -> 0.906 | Z78: 0.901 | AA78: 0.918 | AB78: 0.93 | AC78: =H78 -> 0.945 | AD78: 0.937 | AE78: 0.953 | AF78: 0.963 | AG78: =I78 -> 0.963 | AH78: 0.955 | AI78: 0.958 | AJ78: 0.967 | AK78: =J78 -> 0.964 | AL78: 0.964 | AM78: 0.958 | AN78: 0.95 | AO78: =K78 -> 0.952 | AP78: 0.942
B79: Central Region | C79: 0.96 | D79: 0.953 | E79: 0.943 | F79: 0.901 | G79: 0.949 | H79: 0.99 | I79: 0.972 | J79: 1 | K79: 1 | L79: =AO79 -> 1 | N79: 0.954 | O79: 0.952 | P79: 0.946 | Q79: =E79 -> 0.943 | R79: 0.943 | S79: 0.931 | T79: 0.899 | U79: =F79 -> 0.901 | V79: 0.867 | W79: 0.875 | X79: 0.897 | Y79: =G79 -> 0.949 | Z79: 0.961 | AA79: 0.985 | AB79: 0.99 | AC79: =H79 -> 0.99 | AD79: 0.977 | AE79: 0.953 | AF79: 0.972 | AG79: =I79 -> 0.972 | AH79: 0.991 | AI79: 1 | AJ79: 1 | AK79: =J79 -> 1 | AL79: 1 | AM79: 1 | AN79: 1 | AO79: =K79 -> 1 | AP79: 1
B81: Stabilized Portfolio
B82: Square Footage
B83: North Region | C83: 6659416 | D83: 7444828 | E83: 8544028 | F83: 9078485 | G83: 9253507 | H83: 10352575 | I83: 10871194 | J83: 12560400 | K83: 13140859 | L83: =AP83 -> 13140863 | N83: 7660084 | O83: 8015851 | P83: 8523974 | Q83: =E83 -> 8544028 | R83: 8852385 | S83: 8930767 | T83: 8930767 | U83: =F83 -> 9078485 | V83: 9078485 | W83: 9069820 | X83: 9069820 | Y83: =G83 -> 9253507 | Z83: 9253507 | AA83: 9421736 | AB83: 9628555 | AC83: =H83 -> 10352575 | AD83: 10051831 | AE83: 10500250 | AF83: 11027030 | AG83: =I83 -> 10871194 | AH83: 11094136 | AI83: 11527878 | AJ83: 12560402 | AK83: =J83 -> 12560400 | AL83: 13037364 | AM83: 12990342 | AN83: 13140669 | AO83: =K83 -> 13140859 | AP83: 13140863
B84: Bajio Region | C84: 12145861 | D84: 13347436 | E84: 13741377 | F84: 15182807 | G84: 14771316 | H84: 16183191 | I84: 17796356 | J84: 18598539 | K84: 19533038 | L84: =AP84 -> 19533034 | N84: 13382483 | O84: 13017153 | P84: 13214027 | Q84: =E84 -> 13741377 | R84: 14212231 | S84: 14212231 | T84: 14212231 | U84: =F84 -> 15182807 | V84: 15227219 | W84: 15231132 | X84: 15231131 | Y84: =G84 -> 14771316 | Z84: 14849602 | AA84: 15451284 | AB84: 15460176 | AC84: =H84 -> 16183191 | AD84: 15843223 | AE84: 16035145 | AF84: 16598688 | AG84: =I84 -> 17796356 | AH84: 17731773 | AI84: 18024250 | AJ84: 18301392 | AK84: =J84 -> 18598539 | AL84: 18815632 | AM84: 18937695 | AN84: 19401467 | AO84: =K84 -> 19533038 | AP84: 19533034
B85: Central Region | C85: 6730988 | D85: 7122733 | E85: 6494060 | F85: 6824130 | G85: 7007291 | H85: 7178604 | I85: 7256310 | J85: 8106357 | K85: 8490817 | L85: =AP85 -> 8576950 | N85: 7122733 | O85: 6494060 | P85: 6494060 | Q85: =E85 -> 6494060 | R85: 6494214 | S85: 6494214 | T85: 6494214 | U85: =F85 -> 6824130 | V85: 6867511 | W85: 70003125 | X85: 7007291 | Y85: =G85 -> 7007291 | Z85: 7007291 | AA85: 7008211 | AB85: 7008211 | AC85: =H85 -> 7178604 | AD85: 7178604 | AE85: 7179701 | AF85: 7179938 | AG85: =I85 -> 7256310 | AH85: 7256310 | AI85: 7256310 | AJ85: 7256310 | AK85: =J85 -> 8106357 | AL85: 8106357 | AM85: 8277643 | AN85: 8277642 | AO85: =K85 -> 8490817 | AP85: 8576950
B87: Occupancy
B88: North Region | C88: 0.957 | D88: 0.981 | E88: 0.983 | F88: 0.956 | G88: 0.994 | H88: 0.958 | I88: 0.983 | J88: 0.923 | K88: 0.918 | L88: =AO88 -> 0.918 | N88: 0.993 | O88: 0.992 | P88: 0.983 | Q88: =E88 -> 0.983 | R88: 0.988 | S88: 0.992 | T88: 0.957 | U88: =F88 -> 0.956 | V88: 0.966 | W88: 0.99 | X88: 0.989 | Y88: =G88 -> 0.994 | Z88: 0.994 | AA88: 1 | AB88: 1 | AC88: =H88 -> 0.958 | AD88: 1 | AE88: 1 | AF88: 1 | AG88: =I88 -> 0.983 | AH88: 0.991 | AI88: 0.994 | AJ88: 0.935 | AK88: =J88 -> 0.923 | AL88: 0.918 | AM88: 0.918 | AN88: 0.918 | AO88: =K88 -> 0.918 | AP88: 0.931
B89: Bajio Region | C89: 0.952 | D89: 0.988 | E89: 0.948 | F89: 0.886 | G89: 0.907 | H89: 0.929 | I89: 0.954 | J89: 0.956 | K89: 0.932 | L89: =AO89 -> 0.932 | N89: 0.972 | O89: 0.972 | P89: 0.947 | Q89: =E89 -> 0.948 | R89: 0.901 | S89: 0.909 | T89: 0.905 | U89: =F89 -> 0.886 | V89: 0.885 | W89: 0.908 | X89: 0.908 | Y89: =G89 -> 0.907 | Z89: 0.903 | AA89: 0.923 | AB89: 0.934 | AC89: =H89 -> 0.929 | AD89: 0.941 | AE89: 0.955 | AF89: 0.955 | AG89: =I89 -> 0.954 | AH89: 0.951 | AI89: 0.954 | AJ89: 0.958 | AK89: =J89 -> 0.956 | AL89: 0.957 | AM89: 0.96 | AN89: 0.937 | AO89: =K89 -> 0.932 | AP89: 0.922
B90: Central Region | C90: 0.951 | D90: 0.934 | E90: 0.94 | F90: 0.906 | G90: 0.951 | H90: 0.991 | I90: 0.972 | J90: 1 | K90: 0.975 | L90: =AO90 -> 0.975 | N90: 0.934 | O90: 0.929 | P90: 0.94 | Q90: =E90 -> 0.94 | R90: 0.943 | S90: 0.931 | T90: 0.899 | U90: =F90 -> 0.906 | V90: 0.874 | W90: 0.884 | X90: 0.905 | Y90: =G90 -> 0.951 | Z90: 0.962 | AA90: 0.985 | AB90: 0.99 | AC90: =H90 -> 0.991 | AD90: 0.978 | AE90: 0.954 | AF90: 0.972 | AG90: =I90 -> 0.972 | AH90: 0.991 | AI90: 1 | AJ90: 1 | AK90: =J90 -> 1 | AL90: 1 | AM90: 1 | AN90: 1 | AO90: =K90 -> 0.975 | AP90: 0.965
B92: Total Portfolio
B93: Square Footage
B94: North Region | C94: 6875440 | D94: 7996798 | E94: 8852290 | F94: 9078485 | G94: 9303139 | H94: 9628555 | I94: 12070580 | J94: 12786657 | K94: 14283183 | L94: =AP94 -> 14283187 | N94: 8212054 | O94: 8631873 | P94: 8631873 | Q94: =E94 -> 8852290 | R94: 8852385 | S94: 9074369 | T94: 9074369 | U94: =F94 -> 9078485 | V94: 9361517 | W94: 9360915 | X94: 9410547 | Y94: =G94 -> 9303139 | Z94: 9509958 | AA94: 9628555 | AB94: 9628555 | AC94: =H94 -> 9628555 | AD94: 10352575 | AE94: 10657963 | AF94: 12384129 | AG94: =I94 -> 12070580 | AH94: 12070580 | AI94: 12281380 | AJ94: 12786659 | AK94: =J94 -> 12786657 | AL94: 13263621 | AM94: 13628161 | AN94: 14282993 | AO94: =K94 -> 14283183 | AP94: 14283187
B95: Bajio Region | C95: 12722893 | D95: 14748046 | E95: 14445698 | F95: 15182807 | G95: 14771316 | H95: 15630160 | I95: 18027608 | J95: 19193885 | K95: 20093889 | L95: =AP95 -> 20093885 | N95: 15081603 | O95: 14136412 | P95: 14210107 | Q95: =E95 -> 14445698 | R95: 14447822 | S95: 14447822 | T95: 14447822 | U95: =F95 -> 15182807 | V95: 15227219 | W95: 15231132 | X95: 15231131 | Y95: =G95 -> 14771316 | Z95: 14849602 | AA95: 15451284 | AB95: 15630160 | AC95: =H95 -> 15630160 | AD95: 16183191 | AE95: 16769047 | AF95: 17341893 | AG95: =I95 -> 18027608 | AH95: 17963025 | AI95: 18255502 | AJ95: 19033534 | AK95: =J95 -> 19193885 | AL95: 19533041 | AM95: 19533041 | AN95: 20093889 | AO95: =K95 -> 20093889 | AP95: 20093885
B96: Central Region | C96: 7122837 | D96: 7122733 | E96: 6494060 | F96: 6959744 | G96: 7007291 | H96: 7008211 | I96: 7256310 | J96: 8319422 | K96: 8576950 | L96: =AP96 -> 8576950 | N96: 7122733 | O96: 6494060 | P96: 6494060 | Q96: =E96 -> 6494060 | R96: 6494214 | S96: 6629396 | T96: 6629396 | U96: =F96 -> 6959744 | V96: 7003125 | W96: 7003125 | X96: 7007291 | Y96: =G96 -> 7007291 | Z96: 7007291 | AA96: 7008211 | AB96: 7008211 | AC96: =H96 -> 7008211 | AD96: 7178604 | AE96: 7179701 | AF96: 7179938 | AG96: =I96 -> 7256310 | AH96: 7256310 | AI96: 7256310 | AJ96: 7256310 | AK96: =J96 -> 8319422 | AL96: 8405555 | AM96: 8576841 | AN96: 8576840 | AO96: =K96 -> 8576950 | AP96: 8576950
B98: Occupancy
B99: North Region | C99: 0.927 | D99: 0.949 | E99: 0.978 | F99: 0.956 | G99: 0.989 | H99: 1 | I99: 0.898 | J99: 0.907 | K99: 0.845 | L99: =AO99 -> 0.845 | N99: 0.961 | O99: 0.962 | P99: 0.978 | Q99: =E99 -> 0.978 | R99: 0.988 | S99: 0.977 | T99: 0.947 | U99: =F99 -> 0.956 | V99: 0.955 | W99: 0.984 | X99: 0.977 | Y99: =G99 -> 0.989 | Z99: 0.974 | AA99: 0.995 | AB99: 1 | AC99: =H99 -> 1 | AD99: 0.979 | AE99: 0.995 | AF99: 0.899 | AG99: =I99 -> 0.898 | AH99: 0.911 | AI99: 0.933 | AJ99: 0.918 | AK99: =J99 -> 0.907 | AL99: 0.902 | AM99: 0.875 | AN99: 0.844 | AO99: =K99 -> 0.845 | AP99: 0.856
B100: Bajio Region | C100: 0.921 | D100: 0.894 | E100: 0.889 | F100: 0.886 | G100: 0.907 | H100: 0.924 | I100: 0.942 | J100: 0.935 | K100: 0.906 | L100: =AO100 -> 0.906 | N100: 0.868 | O100: 0.865 | P100: 0.889 | Q100: =E100 -> 0.889 | R100: 0.886 | S100: 0.894 | T100: 0.89 | U100: =F100 -> 0.886 | V100: 0.885 | W100: 0.908 | X100: 0.908 | Y100: =G100 -> 0.907 | Z100: 0.903 | AA100: 0.923 | AB100: 0.924 | AC100: =H100 -> 0.924 | AD100: 0.921 | AE100: 0.913 | AF100: 0.923 | AG100: =I100 -> 0.942 | AH100: 0.939 | AI100: 0.942 | AJ100: 0.929 | AK100: =J100 -> 0.935 | AL100: 0.929 | AM100: 0.939 | AN100: 0.905 | AO100: =K100 -> 0.906 | AP100: 0.896
B101: Central Region | C101: 0.92 | D101: 0.934 | E101: 0.94 | F101: 0.888 | G101: 0.951 | H101: 0.991 | I101: 0.972 | J101: 0.974 | K101: 0.965 | L101: =AO101 -> 0.965 | N101: 0.934 | O101: 0.929 | P101: 0.94 | Q101: =E101 -> 0.94 | R101: 0.943 | S101: 0.912 | T101: 0.881 | U101: =F101 -> 0.888 | V101: 0.857 | W101: 0.884 | X101: 0.905 | Y101: =G101 -> 0.951 | Z101: 0.962 | AA101: 0.985 | AB101: 0.99 | AC101: =H101 -> 0.991 | AD101: 0.978 | AE101: 0.954 | AF101: 0.972 | AG101: =I101 -> 0.972 | AH101: 0.991 | AI101: 1 | AJ101: 1 | AK101: =J101 -> 0.974 | AL101: 0.964 | AM101: 0.965 | AN101: 0.965 | AO101: =K101 -> 0.965 | AP101: 0.965
B103: Total Rental Revenue
B104: North Region | C104: 6265774 | D104: 10014292 | E104: 11196135 | F104: 12212514 | G104: 12920126 | H104: 14406347 | I104: 17347807 | J104: 20239465 | K104: 24327900 | L104: =AP104 -> 22073278 | N104: 10324459 | O104: 10654755 | P104: 10935012 | Q104: =(E104) -> 11196135 | R104: 11658887 | S104: 11863274 | T104: 12111955 | U104: =(F104) -> 12212514 | V104: 12254811 | W104: 12567569 | X104: 12989936 | Y104: =(G104) -> 12920126 | Z104: 12974761 | AA104: 13385902 | AB104: 13942665 | AC104: =(H104) -> 14406347 | AD104: 15025100 | AE104: 15678228 | AF104: 16833472 | AG104: =(I104) -> 17347807 | AH104: 18093366 | AI104: 19067082 | AJ104: 19761866 | AK104: =(J104) -> 20239465 | AL104: 20283722 | AM104: 20370308 | AN104: 22068097 | AO104: =K104 -> 24327900 | AP104: 22073278
B105: Bajio Region | C105: 13979459 | D105: 15889657 | E105: 16156352 | F105: 16968220 | G105: 18404280 | H105: 20231832 | I105: 24610156 | J105: 27664786 | K105: 30276148 | L105: =AP105 -> 30022656 | N105: 16045884 | O105: 16059984 | P105: 16173797 | Q105: =(E105) -> 16156352 | R105: 16465329 | S105: 16074286 | T105: 16655276 | U105: =(F105) -> 16968220 | V105: 17035685 | W105: 17802015 | X105: 18324729 | Y105: =(G105) -> 18404280 | Z105: 18099701 | AA105: 18589077 | AB105: 19587749 | AC105: =(H105) -> 20231832 | AD105: 21358648 | AE105: 22172650 | AF105: 23887704 | AG105: =(I105) -> 24610156 | AH105: 26237209 | AI105: 26538972 | AJ105: 26814216 | AK105: =(J105) -> 27664786 | AL105: 28352615 | AM105: 28895076 | AN105: 28959340 | AO105: =K105 -> 30276148 | AP105: 30022656
B106: Central Region | C106: 8071027 | D106: 8212355 | E106: 7663446 | F106: 7418320 | G106: 8528368 | H106: 10079241 | I106: 11019595 | J106: 11988047 | K106: 15695860 | L106: =AP106 -> 16135326 | N106: 8357627 | O106: 7921241 | P106: 7620910 | Q106: =(E106) -> 7663446 | R106: 7805125 | S106: 7415582 | T106: 7418033 | U106: =(F106) -> 7418320 | V106: 7179250 | W106: 7869896 | X106: 8210607 | Y106: =(G106) -> 8528368 | Z106: 8765076 | AA106: 9365885 | AB106: 9279052 | AC106: =(H106) -> 10079241 | AD106: 10592384 | AE106: 10842863 | AF106: 10891895 | AG106: =(I106) -> 11019595 | AH106: 11478135 | AI106: 12061964 | AJ106: 11801040 | AK106: =(J106) -> 11988047 | AL106: 11936378 | AM106: 12974059 | AN106: 15016486 | AO106: =K106 -> 15695860 | AP106: 16135326
